{
  "type": "Feature",
  "properties": {
    "gn:admin1_code":"02",
    "gn:asciiname":"Samari",
    "gn:country_code":"BA",
    "gn:dem":278,
    "gn:feature_class":"P",
    "gn:feature_code":"PPL",
    "gn:name":"Samari",
    "gn:population":0,
    "gn:timezone":"Europe/Sarajevo",
    "iso:country":"BA",
    "name:ceb_x_preferred":[
        "Samari"
    ],
    "name:deu_x_preferred":[
        "Samari"
    ],
    "name:fra_x_preferred":[
        "Samari"
    ],
    "name:swe_x_preferred":[
        "Samari"
    ],
    "wof:name":"Samari",
    "wof:placetype":"locality"
},
  "geometry": {"coordinates":[19.20683,44.27406],"type":"Point"}
}