{
  "type": "Feature",
  "properties": {
    "gn:admin1_code":"01",
    "gn:asciiname":"Gornji Megdan",
    "gn:country_code":"BA",
    "gn:dem":871,
    "gn:feature_class":"P",
    "gn:feature_code":"PPL",
    "gn:name":"Gornji Megdan",
    "gn:population":0,
    "gn:timezone":"Europe/Sarajevo",
    "iso:country":"BA",
    "wof:name":"Gornji Megdan",
    "wof:placetype":"locality"
},
  "geometry": {"coordinates":[17.05778,43.75861],"type":"Point"}
}