{
  "type": "Feature",
  "properties": {
    "gn:admin1_code":"02",
    "gn:asciiname":"Mrakodol",
    "gn:country_code":"BA",
    "gn:dem":183,
    "gn:feature_class":"P",
    "gn:feature_code":"PPLL",
    "gn:name":"Mrakodol",
    "gn:population":0,
    "gn:timezone":"Europe/Sarajevo",
    "iso:country":"BA",
    "name:bos_x_preferred":[
        "Mrakodol"
    ],
    "name:ceb_x_preferred":[
        "Mrakodol"
    ],
    "name:fra_x_preferred":[
        "Mrakodol"
    ],
    "name:hrv_x_preferred":[
        "Mrakodol"
    ],
    "name:srp_x_preferred":[
        "\u041c\u0440\u0430\u043a\u043e\u0434\u043e\u043b"
    ],
    "name:swe_x_preferred":[
        "Mrakodol"
    ],
    "wof:name":"Mrakodol",
    "wof:placetype":"locality"
},
  "geometry": {"coordinates":[16.52547,45.20643],"type":"Point"}
}