{
  "type": "Feature",
  "properties": {
    "gn:admin1_code":"01",
    "gn:asciiname":"Rasadine",
    "gn:country_code":"BA",
    "gn:dem":923,
    "gn:feature_class":"P",
    "gn:feature_code":"PPL",
    "gn:name":"Rasadine",
    "gn:population":0,
    "gn:timezone":"Europe/Sarajevo",
    "iso:country":"BA",
    "wof:name":"Rasadine",
    "wof:placetype":"locality"
},
  "geometry": {"coordinates":[17.4146,43.52917],"type":"Point"}
}