{
  "type": "Feature",
  "properties": {
    "gn:admin1_code":"02",
    "gn:asciiname":"Knezevici",
    "gn:country_code":"BA",
    "gn:dem":198,
    "gn:feature_class":"P",
    "gn:feature_code":"PPL",
    "gn:name":"Kne\u017eevi\u0107i",
    "gn:population":0,
    "gn:timezone":"Europe/Sarajevo",
    "iso:country":"BA",
    "wof:name":"Knezevici",
    "wof:placetype":"locality"
},
  "geometry": {"coordinates":[16.94746,44.81748],"type":"Point"}
}