{
  "type": "Feature",
  "properties": {
    "gn:admin1_code":"01",
    "gn:asciiname":"Avdici",
    "gn:country_code":"BA",
    "gn:dem":346,
    "gn:feature_class":"P",
    "gn:feature_code":"PPL",
    "gn:name":"Avdi\u0107i",
    "gn:population":0,
    "gn:timezone":"Europe/Sarajevo",
    "iso:country":"BA",
    "wof:name":"Avdici",
    "wof:placetype":"locality"
},
  "geometry": {"coordinates":[18.30829,44.74137],"type":"Point"}
}