{
  "type": "Feature",
  "properties": {
    "gn:admin1_code":"02",
    "gn:asciiname":"Stojisici",
    "gn:country_code":"BA",
    "gn:dem":573,
    "gn:feature_class":"P",
    "gn:feature_code":"PPL",
    "gn:name":"Stoji\u0161i\u0107i",
    "gn:population":0,
    "gn:timezone":"Europe/Sarajevo",
    "iso:country":"BA",
    "wof:name":"Stojisici",
    "wof:placetype":"locality"
},
  "geometry": {"coordinates":[18.87517,44.21954],"type":"Point"}
}