{
  "type": "Feature",
  "properties": {
    "gn:admin1_code":"02",
    "gn:asciiname":"Potoci",
    "gn:country_code":"BA",
    "gn:dem":1041,
    "gn:feature_class":"P",
    "gn:feature_code":"PPLA2",
    "gn:name":"Potoci",
    "gn:population":0,
    "gn:timezone":"Europe/Sarajevo",
    "iso:country":"BA",
    "wof:name":"Potoci",
    "wof:placetype":"locality"
},
  "geometry": {"coordinates":[16.62001,44.39261],"type":"Point"}
}