{
  "type": "Feature",
  "properties": {
    "gn:admin1_code":"01",
    "gn:asciiname":"Debelo Brdo",
    "gn:country_code":"BA",
    "gn:dem":358,
    "gn:feature_class":"P",
    "gn:feature_code":"PPL",
    "gn:name":"Debelo Brdo",
    "gn:population":0,
    "gn:timezone":"Europe/Sarajevo",
    "iso:country":"BA",
    "name:srp_x_preferred":[
        "\u0414\u0435\u0431\u0435\u043b\u043e \u0431\u0440\u0434\u043e"
    ],
    "wof:name":"Debelo Brdo",
    "wof:placetype":"locality"
},
  "geometry": {"coordinates":[18.13206,44.46351],"type":"Point"}
}