{
  "type": "Feature",
  "properties": {
    "gn:admin1_code":"02",
    "gn:asciiname":"Sodolovici",
    "gn:country_code":"BA",
    "gn:dem":1114,
    "gn:feature_class":"P",
    "gn:feature_code":"PPL",
    "gn:name":"Sodolovi\u0107i",
    "gn:population":0,
    "gn:timezone":"Europe/Sarajevo",
    "iso:country":"BA",
    "wof:name":"Sodolovici",
    "wof:placetype":"locality"
},
  "geometry": {"coordinates":[17.4905,44.38742],"type":"Point"}
}