{
  "type": "Feature",
  "properties": {
    "gn:admin1_code":"01",
    "gn:asciiname":"Maljski Kraj",
    "gn:country_code":"BA",
    "gn:dem":723,
    "gn:feature_class":"P",
    "gn:feature_code":"PPL",
    "gn:name":"Maljski Kraj",
    "gn:population":0,
    "gn:timezone":"Europe/Sarajevo",
    "iso:country":"BA",
    "wof:name":"Maljski Kraj",
    "wof:placetype":"locality"
},
  "geometry": {"coordinates":[16.73568,43.88699],"type":"Point"}
}