{
  "type": "Feature",
  "properties": {
    "gn:admin1_code":"02",
    "gn:asciiname":"Mrakovica",
    "gn:country_code":"BA",
    "gn:dem":796,
    "gn:feature_class":"P",
    "gn:feature_code":"PPL",
    "gn:name":"Mrakovica",
    "gn:population":0,
    "gn:timezone":"Europe/Sarajevo",
    "iso:country":"BA",
    "wof:name":"Mrakovica",
    "wof:placetype":"locality"
},
  "geometry": {"coordinates":[16.9075,45.01278],"type":"Point"}
}