{
  "type": "Feature",
  "properties": {
    "gn:admin1_code":"02",
    "gn:asciiname":"Prlin",
    "gn:country_code":"BA",
    "gn:dem":279,
    "gn:feature_class":"P",
    "gn:feature_code":"PPL",
    "gn:name":"Prlin",
    "gn:population":0,
    "gn:timezone":"Europe/Sarajevo",
    "iso:country":"BA",
    "wof:name":"Prlin",
    "wof:placetype":"locality"
},
  "geometry": {"coordinates":[16.34024,44.91402],"type":"Point"}
}