{
  "type": "Feature",
  "properties": {
    "gn:admin1_code":"00",
    "gn:asciiname":"Berici",
    "gn:country_code":"BA",
    "gn:dem":359,
    "gn:feature_class":"P",
    "gn:feature_code":"PPL",
    "gn:name":"Beri\u0107i",
    "gn:population":0,
    "gn:timezone":"Europe/Sarajevo",
    "iso:country":"BA",
    "wof:name":"Berici",
    "wof:placetype":"locality"
},
  "geometry": {"coordinates":[18.63171,44.38997],"type":"Point"}
}