{
  "type": "Feature",
  "properties": {
    "gn:admin1_code":"01",
    "gn:asciiname":"Brezje",
    "gn:country_code":"BA",
    "gn:dem":385,
    "gn:feature_class":"P",
    "gn:feature_code":"PPL",
    "gn:name":"Brezje",
    "gn:population":0,
    "gn:timezone":"Europe/Sarajevo",
    "iso:country":"BA",
    "wof:name":"Brezje",
    "wof:placetype":"locality"
},
  "geometry": {"coordinates":[18.14718,44.50316],"type":"Point"}
}