{
  "type": "Feature",
  "properties": {
    "gn:admin1_code":"01",
    "gn:asciiname":"Zioke",
    "gn:country_code":"BA",
    "gn:dem":476,
    "gn:feature_class":"P",
    "gn:feature_code":"PPL",
    "gn:name":"\u017dioke",
    "gn:population":0,
    "gn:timezone":"Europe/Sarajevo",
    "iso:country":"BA",
    "wof:name":"Zioke",
    "wof:placetype":"locality"
},
  "geometry": {"coordinates":[18.22618,44.41256],"type":"Point"}
}