{
  "type": "Feature",
  "properties": {
    "gn:admin1_code":"02",
    "gn:asciiname":"Bijelici",
    "gn:country_code":"BA",
    "gn:dem":237,
    "gn:feature_class":"P",
    "gn:feature_code":"PPL",
    "gn:name":"Bijeli\u0107i",
    "gn:population":0,
    "gn:timezone":"Europe/Sarajevo",
    "iso:country":"BA",
    "wof:name":"Bijelici",
    "wof:placetype":"locality"
},
  "geometry": {"coordinates":[17.34003,44.66365],"type":"Point"}
}