{
  "type": "Feature",
  "properties": {
    "gn:admin1_code":"01",
    "gn:asciiname":"Grabovica",
    "gn:country_code":"BA",
    "gn:dem":643,
    "gn:feature_class":"P",
    "gn:feature_code":"PPL",
    "gn:name":"Grabovica",
    "gn:population":0,
    "gn:timezone":"Europe/Sarajevo",
    "iso:country":"BA",
    "wof:name":"Grabovica",
    "wof:placetype":"locality"
},
  "geometry": {"coordinates":[18.04639,43.52417],"type":"Point"}
}