{
  "type": "Feature",
  "properties": {
    "gn:admin1_code":"02",
    "gn:asciiname":"Prodo",
    "gn:country_code":"BA",
    "gn:dem":957,
    "gn:feature_class":"P",
    "gn:feature_code":"PPL",
    "gn:name":"Prodo",
    "gn:population":0,
    "gn:timezone":"Europe/Sarajevo",
    "iso:country":"BA",
    "wof:name":"Prodo",
    "wof:placetype":"locality"
},
  "geometry": {"coordinates":[18.47458,42.98059],"type":"Point"}
}