{
  "type": "Feature",
  "properties": {
    "gn:admin1_code":"02",
    "gn:asciiname":"Krndici",
    "gn:country_code":"BA",
    "gn:dem":409,
    "gn:feature_class":"P",
    "gn:feature_code":"PPL",
    "gn:name":"Krndi\u0107i",
    "gn:population":0,
    "gn:timezone":"Europe/Sarajevo",
    "iso:country":"BA",
    "wof:name":"Krndici",
    "wof:placetype":"locality"
},
  "geometry": {"coordinates":[16.82108,44.44845],"type":"Point"}
}