{
  "type": "Feature",
  "properties": {
    "gn:country":"BA",
    "gn:fcode":"PPL",
    "gn:pop":4206,
    "iso:country":"BA",
    "name:ben_x_preferred":[
        "\u09b9\u09be\u09a8 \u09aa\u09c7\u099c\u09be\u09b8\u09be\u0995"
    ],
    "name:bos_x_preferred":[
        "Han-Pijesak"
    ],
    "name:deu_x_preferred":[
        "Han Pijesak"
    ],
    "name:eng_x_preferred":[
        "Han Pijesak"
    ],
    "name:fas_x_preferred":[
        "\u0647\u0627\u0646 \u067e\u06cc\u06cc\u0633\u0627\u06a9"
    ],
    "name:fra_x_preferred":[
        "Han Pijesak"
    ],
    "name:hrv_x_preferred":[
        "Han Pijesak"
    ],
    "name:hsb_x_preferred":[
        "Han Pijesak"
    ],
    "name:ita_x_preferred":[
        "Han Pijesak"
    ],
    "name:jpn_x_preferred":[
        "\u30cf\u30f3\u30fb\u30d4\u30a4\u30a7\u30b5\u30af"
    ],
    "name:nld_x_preferred":[
        "Han Pijesak"
    ],
    "name:pol_x_preferred":[
        "Han Pijesak"
    ],
    "name:rus_x_preferred":[
        "\u0425\u0430\u043d-\u041f\u0435\u0441\u0430\u043a"
    ],
    "name:spa_x_preferred":[
        "Han Pijesak"
    ],
    "name:srp_x_preferred":[
        "\u0425\u0430\u043d \u041f\u0438\u0458\u0435\u0441\u0430\u043a"
    ],
    "name:tur_x_preferred":[
        "Pisakhan"
    ],
    "name:unk_x_variant":[
        "Han Pijesak"
    ],
    "name:urd_x_preferred":[
        "\u062d\u0627\u0646 \u067e\u06cc\u0626\u0633\u0627\u06a9"
    ],
    "name:zho_x_preferred":[
        "\u6c49\u76ae\u8036\u8428\u514b"
    ],
    "qs:name":"Han-Pijesak",
    "qs:name_adm0":"Bosna i Hercegovina",
    "qs:name_adm1":"Republika Srpska",
    "qs:photos_9k":1,
    "qs:photos_9r":1,
    "qs:photos_all":1,
    "qs:photos_sr":0,
    "qs:placetype":"Town",
    "qs:pop_sr":"4",
    "wd:wordcount":125,
    "wof:name":"Han-Pijesak",
    "wof:placetype":"locality",
    "wof:population":4206
},
  "geometry": {"coordinates":[18.95258,44.08161],"type":"Point"}
}