{
  "type": "Feature",
  "properties": {
    "gn:admin1_code":"02",
    "gn:asciiname":"Gobeljice",
    "gn:country_code":"BA",
    "gn:dem":653,
    "gn:feature_class":"P",
    "gn:feature_code":"PPL",
    "gn:name":"Gobeljice",
    "gn:population":0,
    "gn:timezone":"Europe/Sarajevo",
    "iso:country":"BA",
    "wof:name":"Gobeljice",
    "wof:placetype":"locality"
},
  "geometry": {"coordinates":[19.0168,43.60232],"type":"Point"}
}