{
  "type": "Feature",
  "properties": {
    "gn:admin1_code":"01",
    "gn:asciiname":"Krsmanici",
    "gn:country_code":"BA",
    "gn:dem":1175,
    "gn:feature_class":"P",
    "gn:feature_code":"PPL",
    "gn:name":"Krsmani\u0107i",
    "gn:population":0,
    "gn:timezone":"Europe/Sarajevo",
    "iso:country":"BA",
    "name:bos_x_preferred":[
        "Krsmani\u0107i"
    ],
    "name:fra_x_preferred":[
        "Krsmani\u0107i"
    ],
    "name:und_x_variant":[
        "Krsmani\u0107"
    ],
    "wof:name":"Krsmanici",
    "wof:placetype":"locality"
},
  "geometry": {"coordinates":[18.57577,43.65847],"type":"Point"}
}