{
  "type": "Feature",
  "properties": {
    "gn:admin1_code":"01",
    "gn:asciiname":"Karahodze",
    "gn:country_code":"BA",
    "gn:dem":544,
    "gn:feature_class":"P",
    "gn:feature_code":"PPL",
    "gn:name":"Karahod\u017ee",
    "gn:population":0,
    "gn:timezone":"Europe/Sarajevo",
    "iso:country":"BA",
    "wof:name":"Karahodze",
    "wof:placetype":"locality"
},
  "geometry": {"coordinates":[17.75766,44.2157],"type":"Point"}
}