{
  "type": "Feature",
  "properties": {
    "gn:admin1_code":"01",
    "gn:asciiname":"Polje",
    "gn:country_code":"BA",
    "gn:dem":801,
    "gn:feature_class":"P",
    "gn:feature_code":"PPL",
    "gn:name":"Polje",
    "gn:population":0,
    "gn:timezone":"Europe/Sarajevo",
    "iso:country":"BA",
    "wof:name":"Polje",
    "wof:placetype":"locality"
},
  "geometry": {"coordinates":[17.59752000000001,43.80111],"type":"Point"}
}