{
  "type": "Feature",
  "properties": {
    "gn:admin1_code":"01",
    "gn:asciiname":"Polje",
    "gn:country_code":"BA",
    "gn:dem":801,
    "gn:feature_class":"P",
    "gn:feature_code":"PPL",
    "gn:name":"Polje",
    "gn:population":0,
    "gn:timezone":"Europe/Sarajevo",
    "iso:country":"BA",
    "name:arg_x_preferred":[
        "Polje"
    ],
    "name:ast_x_preferred":[
        "Polj\u00e9"
    ],
    "name:bos_x_preferred":[
        "Kra\u0161ko polje"
    ],
    "name:cat_x_preferred":[
        "P\u00f2lie"
    ],
    "name:ces_x_preferred":[
        "Polje"
    ],
    "name:deu_x_preferred":[
        "Polje"
    ],
    "name:eus_x_preferred":[
        "Polje"
    ],
    "name:fas_x_preferred":[
        "\u062f\u0634\u062a \u06a9\u0627\u0631\u0633\u062a\u06cc"
    ],
    "name:fin_x_preferred":[
        "Polje"
    ],
    "name:fra_x_preferred":[
        "Polj\u00e9"
    ],
    "name:hun_x_preferred":[
        "Polje"
    ],
    "name:ita_x_preferred":[
        "Polje"
    ],
    "name:jpn_x_preferred":[
        "\u30dd\u30ea\u30a8"
    ],
    "name:kor_x_preferred":[
        "\ud3f4\ub9ac\uc5d0"
    ],
    "name:nld_x_preferred":[
        "Polje"
    ],
    "name:nno_x_preferred":[
        "Polje"
    ],
    "name:nor_x_preferred":[
        "Polje"
    ],
    "name:pol_x_preferred":[
        "Polje"
    ],
    "name:por_x_preferred":[
        "Polje"
    ],
    "name:ron_x_preferred":[
        "Polie"
    ],
    "name:rus_x_preferred":[
        "\u041f\u043e\u043b\u044c\u0435"
    ],
    "name:slk_x_preferred":[
        "Polje"
    ],
    "name:slv_x_preferred":[
        "Kra\u0161ko polje"
    ],
    "name:spa_x_preferred":[
        "Polj\u00e9"
    ],
    "name:srp_x_preferred":[
        "\u041a\u0440\u0430\u0448\u043a\u043e \u043f\u043e\u0459\u0435"
    ],
    "name:swe_x_preferred":[
        "Polje"
    ],
    "name:tur_x_preferred":[
        "Polye"
    ],
    "wof:name":"Polje",
    "wof:placetype":"locality"
},
  "geometry": {"coordinates":[17.59752000000001,43.80111],"type":"Point"}
}