{
  "type": "Feature",
  "properties": {
    "gn:admin1_code":"02",
    "gn:asciiname":"Micista",
    "gn:country_code":"BA",
    "gn:dem":1133,
    "gn:feature_class":"P",
    "gn:feature_code":"PPL",
    "gn:name":"Mi\u0107i\u0161ta",
    "gn:population":0,
    "gn:timezone":"Europe/Sarajevo",
    "iso:country":"BA",
    "wof:name":"Micista",
    "wof:placetype":"locality"
},
  "geometry": {"coordinates":[18.63361,43.83361],"type":"Point"}
}