{
  "type": "Feature",
  "properties": {
    "gn:admin1_code":"02",
    "gn:asciiname":"Stublici",
    "gn:country_code":"BA",
    "gn:dem":680,
    "gn:feature_class":"P",
    "gn:feature_code":"PPL",
    "gn:name":"Stubli\u0107i",
    "gn:population":0,
    "gn:timezone":"Europe/Sarajevo",
    "iso:country":"BA",
    "wof:name":"Stublici",
    "wof:placetype":"locality"
},
  "geometry": {"coordinates":[19.32326,43.67294],"type":"Point"}
}