{
  "type": "Feature",
  "properties": {
    "gn:admin1_code":"02",
    "gn:asciiname":"Kladari",
    "gn:country_code":"BA",
    "gn:dem":128,
    "gn:feature_class":"P",
    "gn:feature_code":"PPL",
    "gn:name":"Kladari",
    "gn:population":0,
    "gn:timezone":"Europe/Sarajevo",
    "iso:country":"BA",
    "wof:name":"Kladari",
    "wof:placetype":"locality"
},
  "geometry": {"coordinates":[19.1281,44.74585],"type":"Point"}
}