{
  "type": "Feature",
  "properties": {
    "gn:admin1_code":"02",
    "gn:asciiname":"Jajino Brdo",
    "gn:country_code":"BA",
    "gn:dem":981,
    "gn:feature_class":"P",
    "gn:feature_code":"PPL",
    "gn:name":"Jajino Brdo",
    "gn:population":0,
    "gn:timezone":"Europe/Sarajevo",
    "iso:country":"BA",
    "wof:name":"Jajino Brdo",
    "wof:placetype":"locality"
},
  "geometry": {"coordinates":[18.61517000000001,43.87016],"type":"Point"}
}