{
  "type": "Feature",
  "properties": {
    "gn:admin1_code":"01",
    "gn:asciiname":"Donje Dragajice",
    "gn:country_code":"BA",
    "gn:dem":1274,
    "gn:feature_class":"P",
    "gn:feature_code":"PPL",
    "gn:name":"Donje Dragajice",
    "gn:population":0,
    "gn:timezone":"Europe/Sarajevo",
    "iso:country":"BA",
    "wof:name":"Donje Dragajice",
    "wof:placetype":"locality"
},
  "geometry": {"coordinates":[17.54839,43.6867],"type":"Point"}
}