{
  "type": "Feature",
  "properties": {
    "gn:admin1_code":"01",
    "gn:asciiname":"Mravljaca",
    "gn:country_code":"BA",
    "gn:dem":795,
    "gn:feature_class":"P",
    "gn:feature_code":"PPLL",
    "gn:name":"Mravlja\u010da",
    "gn:population":0,
    "gn:timezone":"Europe/Sarajevo",
    "iso:country":"BA",
    "name:und_x_variant":[
        "Mravlja\u010da"
    ],
    "wof:name":"Mravljaca",
    "wof:placetype":"locality"
},
  "geometry": {"coordinates":[18.75528,43.61],"type":"Point"}
}