{
  "type": "Feature",
  "properties": {
    "gn:admin1_code":"02",
    "gn:asciiname":"Zmirici",
    "gn:country_code":"BA",
    "gn:dem":238,
    "gn:feature_class":"P",
    "gn:feature_code":"PPL",
    "gn:name":"\u017dmiri\u0107i",
    "gn:population":0,
    "gn:timezone":"Europe/Sarajevo",
    "iso:country":"BA",
    "wof:name":"Zmirici",
    "wof:placetype":"locality"
},
  "geometry": {"coordinates":[16.45222,45.0475],"type":"Point"}
}