{
  "type": "Feature",
  "properties": {
    "gn:admin1_code":"01",
    "gn:asciiname":"Kamen",
    "gn:country_code":"BA",
    "gn:dem":1048,
    "gn:feature_class":"P",
    "gn:feature_code":"PPL",
    "gn:name":"Kamen",
    "gn:population":0,
    "gn:timezone":"Europe/Sarajevo",
    "iso:country":"BA",
    "wof:name":"Kamen",
    "wof:placetype":"locality"
},
  "geometry": {"coordinates":[18.50832,43.67236],"type":"Point"}
}