{
  "type": "Feature",
  "properties": {
    "gn:admin1_code":"01",
    "gn:asciiname":"Hegica Selo",
    "gn:country_code":"BA",
    "gn:dem":218,
    "gn:feature_class":"P",
    "gn:feature_code":"PPL",
    "gn:name":"Hegi\u0107a Selo",
    "gn:population":0,
    "gn:timezone":"Europe/Sarajevo",
    "iso:country":"BA",
    "wof:name":"Hegica Selo",
    "wof:placetype":"locality"
},
  "geometry": {"coordinates":[15.90999,45.1833],"type":"Point"}
}