{
  "type": "Feature",
  "properties": {
    "gn:admin1_code":"02",
    "gn:asciiname":"Porjecje",
    "gn:country_code":"BA",
    "gn:dem":227,
    "gn:feature_class":"P",
    "gn:feature_code":"PPL",
    "gn:name":"Porje\u010dje",
    "gn:population":0,
    "gn:timezone":"Europe/Sarajevo",
    "iso:country":"BA",
    "name:bos_x_preferred":[
        "Porje\u010dje"
    ],
    "name:ceb_x_preferred":[
        "Porje\u010dje"
    ],
    "name:fra_x_preferred":[
        "Porje\u010dje"
    ],
    "name:hrv_x_preferred":[
        "Porje\u010dje"
    ],
    "name:srp_x_preferred":[
        "\u041f\u043e\u0440\u0458\u0435\u0447\u0458\u0435"
    ],
    "name:swe_x_preferred":[
        "Porje\u010dje"
    ],
    "name:und_x_variant":[
        "Porje\u010dje"
    ],
    "wof:name":"Porjecje",
    "wof:placetype":"locality"
},
  "geometry": {"coordinates":[18.12188,44.7985],"type":"Point"}
}