{
  "type": "Feature",
  "properties": {
    "gn:admin1_code":"01",
    "gn:asciiname":"Uzricje",
    "gn:country_code":"BA",
    "gn:dem":685,
    "gn:feature_class":"P",
    "gn:feature_code":"PPL",
    "gn:name":"Uzri\u010dje",
    "gn:population":0,
    "gn:timezone":"Europe/Sarajevo",
    "iso:country":"BA",
    "name:bos_x_preferred":[
        "Uzri\u010dje"
    ],
    "name:fra_x_preferred":[
        "Uzri\u010dje"
    ],
    "name:hrv_x_preferred":[
        "Uzri\u010dje"
    ],
    "name:srp_x_preferred":[
        "\u0423\u0437\u0440\u0438\u0447\u0458\u0435"
    ],
    "name:und_x_variant":[
        "Uzri\u010dje"
    ],
    "wof:name":"Uzricje",
    "wof:placetype":"locality"
},
  "geometry": {"coordinates":[17.57593,43.9248],"type":"Point"}
}