{
  "type": "Feature",
  "properties": {
    "gn:admin1_code":"01",
    "gn:asciiname":"Sesnaesti-Kilometar",
    "gn:country_code":"BA",
    "gn:dem":1228,
    "gn:feature_class":"P",
    "gn:feature_code":"PPL",
    "gn:name":"\u0160esnaesti-Kilometar",
    "gn:population":0,
    "gn:timezone":"Europe/Sarajevo",
    "iso:country":"BA",
    "wof:name":"Sesnaesti-Kilometar",
    "wof:placetype":"locality"
},
  "geometry": {"coordinates":[16.27822,44.50861],"type":"Point"}
}