{
  "type": "Feature",
  "properties": {
    "gn:admin1_code":"02",
    "gn:asciiname":"Donja Pecka",
    "gn:country_code":"BA",
    "gn:dem":194,
    "gn:feature_class":"P",
    "gn:feature_code":"PPL",
    "gn:name":"Donja Pecka",
    "gn:population":0,
    "gn:timezone":"Europe/Sarajevo",
    "iso:country":"BA",
    "wof:name":"Donja Pecka",
    "wof:placetype":"locality"
},
  "geometry": {"coordinates":[19.14562,44.54523],"type":"Point"}
}