{
  "type": "Feature",
  "properties": {
    "gn:admin1_code":"02",
    "gn:asciiname":"Kalat",
    "gn:country_code":"BA",
    "gn:dem":131,
    "gn:feature_class":"P",
    "gn:feature_code":"PPL",
    "gn:name":"Kalat",
    "gn:population":0,
    "gn:timezone":"Europe/Sarajevo",
    "iso:country":"BA",
    "wof:name":"Kalat",
    "wof:placetype":"locality"
},
  "geometry": {"coordinates":[18.91265,44.72695],"type":"Point"}
}