{
  "type": "Feature",
  "properties": {
    "gn:admin1_code":"02",
    "gn:asciiname":"Zabica",
    "gn:country_code":"BA",
    "gn:dem":553,
    "gn:feature_class":"P",
    "gn:feature_code":"PPLL",
    "gn:name":"\u017dabica",
    "gn:population":0,
    "gn:timezone":"Europe/Sarajevo",
    "iso:country":"BA",
    "name:und_x_variant":[
        "\u017dabice",
        "\u017dabica"
    ],
    "wof:name":"Zabica",
    "wof:placetype":"locality"
},
  "geometry": {"coordinates":[18.17,42.87762],"type":"Point"}
}