{
  "type": "Feature",
  "properties": {
    "gn:admin1_code":"02",
    "gn:asciiname":"Balina Njiva",
    "gn:country_code":"BA",
    "gn:dem":1035,
    "gn:feature_class":"P",
    "gn:feature_code":"PPL",
    "gn:name":"Balina Njiva",
    "gn:population":0,
    "gn:timezone":"Europe/Sarajevo",
    "iso:country":"BA",
    "wof:name":"Balina Njiva",
    "wof:placetype":"locality"
},
  "geometry": {"coordinates":[18.6624,43.81966],"type":"Point"}
}