{
  "type": "Feature",
  "properties": {
    "gn:admin1_code":"01",
    "gn:asciiname":"Mahmutovici",
    "gn:country_code":"BA",
    "gn:dem":373,
    "gn:feature_class":"P",
    "gn:feature_code":"PPL",
    "gn:name":"Mahmutovi\u0107i",
    "gn:population":0,
    "gn:timezone":"Europe/Sarajevo",
    "iso:country":"BA",
    "wof:name":"Mahmutovici",
    "wof:placetype":"locality"
},
  "geometry": {"coordinates":[15.90924,45.00448],"type":"Point"}
}