{
  "type": "Feature",
  "properties": {
    "gn:admin1_code":"02",
    "gn:asciiname":"Bobari",
    "gn:country_code":"BA",
    "gn:dem":300,
    "gn:feature_class":"P",
    "gn:feature_code":"PPL",
    "gn:name":"Bobari",
    "gn:population":0,
    "gn:timezone":"Europe/Sarajevo",
    "iso:country":"BA",
    "wof:name":"Bobari",
    "wof:placetype":"locality"
},
  "geometry": {"coordinates":[16.96047,44.76134],"type":"Point"}
}