{
  "type": "Feature",
  "properties": {
    "gn:admin1_code":"01",
    "gn:asciiname":"Vukovo",
    "gn:country_code":"BA",
    "gn:dem":935,
    "gn:feature_class":"P",
    "gn:feature_code":"PPL",
    "gn:name":"Vukovo",
    "gn:population":0,
    "gn:timezone":"Europe/Sarajevo",
    "iso:country":"BA",
    "name:bul_x_preferred":[
        "\u0412\u0443\u043a\u043e\u0432\u043e"
    ],
    "name:fas_x_preferred":[
        "\u0648\u0648\u06a9\u0648\u0641\u0648"
    ],
    "name:kat_x_preferred":[
        "\u10d5\u10e3\u10d9\u10dd\u10d5\u10dd"
    ],
    "name:kaz_x_preferred":[
        "\u0412\u0443\u043a\u043e\u0432\u043e"
    ],
    "name:msa_x_preferred":[
        "Vukovo"
    ],
    "name:ron_x_preferred":[
        "Vukovo"
    ],
    "name:rus_x_preferred":[
        "\u0412\u0443\u043a\u043e\u0432\u043e"
    ],
    "name:ukr_x_preferred":[
        "\u0412\u0443\u043a\u043e\u0432\u043e"
    ],
    "wof:name":"Vukovo",
    "wof:placetype":"locality"
},
  "geometry": {"coordinates":[17.31742,44.19982],"type":"Point"}
}