{
  "type": "Feature",
  "properties": {
    "gn:admin1_code":"01",
    "gn:asciiname":"Vukovo",
    "gn:country_code":"BA",
    "gn:dem":935,
    "gn:feature_class":"P",
    "gn:feature_code":"PPL",
    "gn:name":"Vukovo",
    "gn:population":0,
    "gn:timezone":"Europe/Sarajevo",
    "iso:country":"BA",
    "wof:name":"Vukovo",
    "wof:placetype":"locality"
},
  "geometry": {"coordinates":[17.31742,44.19982],"type":"Point"}
}