{
  "type": "Feature",
  "properties": {
    "gn:admin1_code":"01",
    "gn:asciiname":"Puhovac",
    "gn:country_code":"BA",
    "gn:dem":725,
    "gn:feature_class":"P",
    "gn:feature_code":"PPL",
    "gn:name":"Puhovac",
    "gn:population":0,
    "gn:timezone":"Europe/Sarajevo",
    "iso:country":"BA",
    "wof:name":"Puhovac",
    "wof:placetype":"locality"
},
  "geometry": {"coordinates":[18.0503,44.21515],"type":"Point"}
}