{
  "type": "Feature",
  "properties": {
    "gn:admin1_code":"01",
    "gn:asciiname":"Puhovac",
    "gn:country_code":"BA",
    "gn:dem":725,
    "gn:feature_class":"P",
    "gn:feature_code":"PPL",
    "gn:name":"Puhovac",
    "gn:population":0,
    "gn:timezone":"Europe/Sarajevo",
    "iso:country":"BA",
    "name:fra_x_preferred":[
        "Puhovac"
    ],
    "name:hye_x_preferred":[
        "\u054a\u0578\u0582\u0570\u0578\u057e\u0561\u0581"
    ],
    "name:msa_x_preferred":[
        "Puhovac"
    ],
    "name:nld_x_preferred":[
        "Puhovac"
    ],
    "name:por_x_preferred":[
        "Puhovac"
    ],
    "name:slv_x_preferred":[
        "Puhovac"
    ],
    "name:spa_x_preferred":[
        "Puhovac"
    ],
    "name:srp_x_preferred":[
        "\u041f\u0443\u0445\u043e\u0432\u0430\u0446"
    ],
    "wof:name":"Puhovac",
    "wof:placetype":"locality"
},
  "geometry": {"coordinates":[18.0503,44.21515],"type":"Point"}
}