{
  "type": "Feature",
  "properties": {
    "gn:admin1_code":"02",
    "gn:asciiname":"Todici",
    "gn:country_code":"BA",
    "gn:dem":851,
    "gn:feature_class":"P",
    "gn:feature_code":"PPL",
    "gn:name":"Todi\u0107i",
    "gn:population":0,
    "gn:timezone":"Europe/Sarajevo",
    "iso:country":"BA",
    "wof:name":"Todici",
    "wof:placetype":"locality"
},
  "geometry": {"coordinates":[16.93786,44.26636],"type":"Point"}
}