{
  "type": "Feature",
  "properties": {
    "gn:admin1_code":"01",
    "gn:asciiname":"Hodzici",
    "gn:country_code":"BA",
    "gn:dem":340,
    "gn:feature_class":"P",
    "gn:feature_code":"PPL",
    "gn:name":"Hod\u017ei\u0107i",
    "gn:population":0,
    "gn:timezone":"Europe/Sarajevo",
    "iso:country":"BA",
    "wof:name":"Hodzici",
    "wof:placetype":"locality"
},
  "geometry": {"coordinates":[18.40023,44.7233],"type":"Point"}
}