{
  "type": "Feature",
  "properties": {
    "gn:admin1_code":"02",
    "gn:asciiname":"Babajac",
    "gn:country_code":"BA",
    "gn:dem":638,
    "gn:feature_class":"P",
    "gn:feature_code":"PPL",
    "gn:name":"Babajac",
    "gn:population":0,
    "gn:timezone":"Europe/Sarajevo",
    "iso:country":"BA",
    "wof:name":"Babajac",
    "wof:placetype":"locality"
},
  "geometry": {"coordinates":[17.28178,44.60957],"type":"Point"}
}