{
  "type": "Feature",
  "properties": {
    "gn:admin1_code":"02",
    "gn:asciiname":"Zavozi",
    "gn:country_code":"BA",
    "gn:dem":944,
    "gn:feature_class":"P",
    "gn:feature_code":"PPL",
    "gn:name":"Zavozi",
    "gn:population":0,
    "gn:timezone":"Europe/Sarajevo",
    "iso:country":"BA",
    "wof:name":"Zavozi",
    "wof:placetype":"locality"
},
  "geometry": {"coordinates":[18.83787,43.98006],"type":"Point"}
}