{
  "type": "Feature",
  "properties": {
    "gn:admin1_code":"02",
    "gn:asciiname":"Klanci",
    "gn:country_code":"BA",
    "gn:dem":606,
    "gn:feature_class":"P",
    "gn:feature_code":"PPL",
    "gn:name":"Klanci",
    "gn:population":0,
    "gn:timezone":"Europe/Sarajevo",
    "iso:country":"BA",
    "wof:name":"Klanci",
    "wof:placetype":"locality"
},
  "geometry": {"coordinates":[19.02952,43.7648],"type":"Point"}
}