{
  "type": "Feature",
  "properties": {
    "gn:admin1_code":"02",
    "gn:asciiname":"Gajevi",
    "gn:country_code":"BA",
    "gn:dem":88,
    "gn:feature_class":"P",
    "gn:feature_code":"PPL",
    "gn:name":"Gajevi",
    "gn:population":0,
    "gn:timezone":"Europe/Sarajevo",
    "iso:country":"BA",
    "name:bos_x_preferred":[
        "Gajevi"
    ],
    "name:fra_x_preferred":[
        "Gajevi"
    ],
    "name:hrv_x_preferred":[
        "Gajevi"
    ],
    "name:slv_x_preferred":[
        "Gajevi"
    ],
    "name:srp_x_preferred":[
        "\u0413\u0430\u0458\u0435\u0432\u0438"
    ],
    "wof:name":"Gajevi",
    "wof:placetype":"locality"
},
  "geometry": {"coordinates":[19.26021,44.79738],"type":"Point"}
}