{
  "type": "Feature",
  "properties": {
    "gn:admin1_code":"02",
    "gn:asciiname":"Melecici",
    "gn:country_code":"BA",
    "gn:dem":939,
    "gn:feature_class":"P",
    "gn:feature_code":"PPL",
    "gn:name":"Mele\u010di\u0107i",
    "gn:population":0,
    "gn:timezone":"Europe/Sarajevo",
    "iso:country":"BA",
    "name:bos_x_preferred":[
        "Mele\u010di\u0107i"
    ],
    "name:fra_x_preferred":[
        "Mele\u010di\u0107i"
    ],
    "name:hrv_x_preferred":[
        "Mele\u010di\u0107i"
    ],
    "name:srp_x_preferred":[
        "\u041c\u0435\u043b\u0435\u0447\u0438\u045b\u0438"
    ],
    "name:und_x_variant":[
        "Mele\u010di\u0107i"
    ],
    "wof:name":"Melecici",
    "wof:placetype":"locality"
},
  "geometry": {"coordinates":[18.49742,43.3013],"type":"Point"}
}