{
  "type": "Feature",
  "properties": {
    "gn:admin1_code":"01",
    "gn:asciiname":"Mali Guber",
    "gn:country_code":"BA",
    "gn:dem":722,
    "gn:feature_class":"P",
    "gn:feature_code":"PPL",
    "gn:name":"Mali Guber",
    "gn:population":0,
    "gn:timezone":"Europe/Sarajevo",
    "iso:country":"BA",
    "wof:name":"Mali Guber",
    "wof:placetype":"locality"
},
  "geometry": {"coordinates":[16.95316,43.81004],"type":"Point"}
}