{
  "type": "Feature",
  "properties": {
    "gn:admin1_code":"01",
    "gn:asciiname":"Mali Guber",
    "gn:country_code":"BA",
    "gn:dem":722,
    "gn:feature_class":"P",
    "gn:feature_code":"PPL",
    "gn:name":"Mali Guber",
    "gn:population":0,
    "gn:timezone":"Europe/Sarajevo",
    "iso:country":"BA",
    "name:bos_x_preferred":[
        "Mali Guber"
    ],
    "name:ceb_x_preferred":[
        "Mali Guber"
    ],
    "name:fra_x_preferred":[
        "Mali Guber"
    ],
    "name:hrv_x_preferred":[
        "Mali Guber"
    ],
    "name:srp_x_preferred":[
        "\u041c\u0430\u043b\u0438 \u0413\u0443\u0431\u0435\u0440"
    ],
    "name:swe_x_preferred":[
        "Mali Guber"
    ],
    "wof:name":"Mali Guber",
    "wof:placetype":"locality"
},
  "geometry": {"coordinates":[16.95316,43.81004],"type":"Point"}
}