{
  "type": "Feature",
  "properties": {
    "gn:admin1_code":"02",
    "gn:asciiname":"Donje Godomilje",
    "gn:country_code":"BA",
    "gn:dem":1080,
    "gn:feature_class":"P",
    "gn:feature_code":"PPL",
    "gn:name":"Donje Godomilje",
    "gn:population":0,
    "gn:timezone":"Europe/Sarajevo",
    "iso:country":"BA",
    "wof:name":"Donje Godomilje",
    "wof:placetype":"locality"
},
  "geometry": {"coordinates":[19.09044,43.91968],"type":"Point"}
}