{
  "type": "Feature",
  "properties": {
    "gn:admin1_code":"02",
    "gn:asciiname":"Boskovici",
    "gn:country_code":"BA",
    "gn:dem":317,
    "gn:feature_class":"P",
    "gn:feature_code":"PPL",
    "gn:name":"Bo\u0161kovi\u0107i",
    "gn:population":0,
    "gn:timezone":"Europe/Sarajevo",
    "iso:country":"BA",
    "wof:name":"Boskovici",
    "wof:placetype":"locality"
},
  "geometry": {"coordinates":[19.02375,44.48637],"type":"Point"}
}