{
  "type": "Feature",
  "properties": {
    "gn:admin1_code":"01",
    "gn:asciiname":"Dragomiljici",
    "gn:country_code":"BA",
    "gn:dem":808,
    "gn:feature_class":"P",
    "gn:feature_code":"PPL",
    "gn:name":"Dragomilji\u0107i",
    "gn:population":0,
    "gn:timezone":"Europe/Sarajevo",
    "iso:country":"BA",
    "wof:name":"Dragomiljici",
    "wof:placetype":"locality"
},
  "geometry": {"coordinates":[18.63117,44.17247],"type":"Point"}
}