{
  "type": "Feature",
  "properties": {
    "gn:admin1_code":"02",
    "gn:asciiname":"Okruglo",
    "gn:country_code":"BA",
    "gn:dem":749,
    "gn:feature_class":"P",
    "gn:feature_code":"PPL",
    "gn:name":"Okruglo",
    "gn:population":0,
    "gn:timezone":"Europe/Sarajevo",
    "iso:country":"BA",
    "wof:name":"Okruglo",
    "wof:placetype":"locality"
},
  "geometry": {"coordinates":[19.05509,43.8372],"type":"Point"}
}