{
  "type": "Feature",
  "properties": {
    "gn:admin1_code":"02",
    "gn:asciiname":"Susteri",
    "gn:country_code":"BA",
    "gn:dem":811,
    "gn:feature_class":"P",
    "gn:feature_code":"PPL",
    "gn:name":"\u0160u\u0161teri",
    "gn:population":0,
    "gn:timezone":"Europe/Sarajevo",
    "iso:country":"BA",
    "wof:name":"Susteri",
    "wof:placetype":"locality"
},
  "geometry": {"coordinates":[18.92554,43.47305],"type":"Point"}
}