{
  "type": "Feature",
  "properties": {
    "gn:admin1_code":"02",
    "gn:asciiname":"Vlajici",
    "gn:country_code":"BA",
    "gn:dem":283,
    "gn:feature_class":"P",
    "gn:feature_code":"PPLL",
    "gn:name":"Vlaji\u0107i",
    "gn:population":0,
    "gn:timezone":"Europe/Sarajevo",
    "iso:country":"BA",
    "wof:name":"Vlajici",
    "wof:placetype":"locality"
},
  "geometry": {"coordinates":[17.81834,44.5673],"type":"Point"}
}