{
  "type": "Feature",
  "properties": {
    "gn:admin1_code":"02",
    "gn:asciiname":"Zivkovici",
    "gn:country_code":"BA",
    "gn:dem":261,
    "gn:feature_class":"P",
    "gn:feature_code":"PPL",
    "gn:name":"\u017divkovi\u0107i",
    "gn:population":0,
    "gn:timezone":"Europe/Sarajevo",
    "iso:country":"BA",
    "wof:name":"Zivkovici",
    "wof:placetype":"locality"
},
  "geometry": {"coordinates":[17.53019,44.79055],"type":"Point"}
}