{
  "type": "Feature",
  "properties": {
    "gn:admin1_code":"01",
    "gn:asciiname":"Rolje",
    "gn:country_code":"BA",
    "gn:dem":893,
    "gn:feature_class":"P",
    "gn:feature_code":"PPL",
    "gn:name":"Rolje",
    "gn:population":0,
    "gn:timezone":"Europe/Sarajevo",
    "iso:country":"BA",
    "wof:name":"Rolje",
    "wof:placetype":"locality"
},
  "geometry": {"coordinates":[17.75917,43.79639],"type":"Point"}
}