{
  "type": "Feature",
  "properties": {
    "gn:admin1_code":"01",
    "gn:asciiname":"Brijeg",
    "gn:country_code":"BA",
    "gn:dem":513,
    "gn:feature_class":"P",
    "gn:feature_code":"PPL",
    "gn:name":"Brijeg",
    "gn:population":0,
    "gn:timezone":"Europe/Sarajevo",
    "iso:country":"BA",
    "name:bos_x_preferred":[
        "Brijeg"
    ],
    "name:ceb_x_preferred":[
        "Brijeg"
    ],
    "name:fra_x_preferred":[
        "Brijeg"
    ],
    "name:swe_x_preferred":[
        "Brijeg"
    ],
    "wof:name":"Brijeg",
    "wof:placetype":"locality"
},
  "geometry": {"coordinates":[17.89415,42.86861],"type":"Point"}
}