{
  "type": "Feature",
  "properties": {
    "gn:admin1_code":"02",
    "gn:asciiname":"Uncani",
    "gn:country_code":"BA",
    "gn:dem":883,
    "gn:feature_class":"P",
    "gn:feature_code":"PPL",
    "gn:name":"Un\u010dani",
    "gn:population":0,
    "gn:timezone":"Europe/Sarajevo",
    "iso:country":"BA",
    "wof:name":"Uncani",
    "wof:placetype":"locality"
},
  "geometry": {"coordinates":[17.13875,44.18807],"type":"Point"}
}