{
  "type": "Feature",
  "properties": {
    "gn:admin1_code":"01",
    "gn:asciiname":"Varosiste",
    "gn:country_code":"BA",
    "gn:dem":250,
    "gn:feature_class":"P",
    "gn:feature_code":"PPL",
    "gn:name":"Varo\u0161i\u0161te",
    "gn:population":0,
    "gn:timezone":"Europe/Sarajevo",
    "iso:country":"BA",
    "wof:name":"Varosiste",
    "wof:placetype":"locality"
},
  "geometry": {"coordinates":[18.03228,44.42852],"type":"Point"}
}