{
  "type": "Feature",
  "properties": {
    "gn:admin1_code":"01",
    "gn:asciiname":"Sejarici",
    "gn:country_code":"BA",
    "gn:dem":489,
    "gn:feature_class":"P",
    "gn:feature_code":"PPL",
    "gn:name":"Sejari\u0107i",
    "gn:population":0,
    "gn:timezone":"Europe/Sarajevo",
    "iso:country":"BA",
    "wof:name":"Sejarici",
    "wof:placetype":"locality"
},
  "geometry": {"coordinates":[16.75809,44.59713],"type":"Point"}
}