{
  "type": "Feature",
  "properties": {
    "gn:admin1_code":"01",
    "gn:asciiname":"Donja Lucka",
    "gn:country_code":"BA",
    "gn:dem":204,
    "gn:feature_class":"P",
    "gn:feature_code":"PPL",
    "gn:name":"Donja Lu\u010dka",
    "gn:population":0,
    "gn:timezone":"Europe/Sarajevo",
    "iso:country":"BA",
    "name:und_x_variant":[
        "Donja Lu\u010dka"
    ],
    "wof:name":"Donja Lucka",
    "wof:placetype":"locality"
},
  "geometry": {"coordinates":[15.8993,45.07668],"type":"Point"}
}