{
  "type": "Feature",
  "properties": {
    "gn:admin1_code":"02",
    "gn:asciiname":"Velika Palanciste",
    "gn:country_code":"BA",
    "gn:dem":213,
    "gn:feature_class":"P",
    "gn:feature_code":"PPLL",
    "gn:name":"Velika Palan\u010di\u0161te",
    "gn:population":0,
    "gn:timezone":"Europe/Sarajevo",
    "iso:country":"BA",
    "wof:name":"Velika Palanciste",
    "wof:placetype":"locality"
},
  "geometry": {"coordinates":[16.75195,45.02437000000001],"type":"Point"}
}