{
  "type": "Feature",
  "properties": {
    "gn:admin1_code":"02",
    "gn:asciiname":"Patkovina",
    "gn:country_code":"BA",
    "gn:dem":757,
    "gn:feature_class":"P",
    "gn:feature_code":"PPLL",
    "gn:name":"Patkovina",
    "gn:population":0,
    "gn:timezone":"Europe/Sarajevo",
    "iso:country":"BA",
    "name:bos_x_preferred":[
        "Patkovina"
    ],
    "name:ceb_x_preferred":[
        "Patkovina"
    ],
    "name:fra_x_preferred":[
        "Patkovina"
    ],
    "name:hrv_x_preferred":[
        "Patkovina"
    ],
    "name:srp_x_preferred":[
        "\u041f\u0430\u0442\u043a\u043e\u0432\u0438\u043d\u0430"
    ],
    "name:swe_x_preferred":[
        "Patkovina"
    ],
    "wof:name":"Patkovina",
    "wof:placetype":"locality"
},
  "geometry": {"coordinates":[18.77342,43.53805],"type":"Point"}
}