{
  "type": "Feature",
  "properties": {
    "gn:admin1_code":"01",
    "gn:asciiname":"Radicke Uvale",
    "gn:country_code":"BA",
    "gn:dem":818,
    "gn:feature_class":"P",
    "gn:feature_code":"PPL",
    "gn:name":"Radi\u0107ke Uvale",
    "gn:population":0,
    "gn:timezone":"Europe/Sarajevo",
    "iso:country":"BA",
    "wof:name":"Radicke Uvale",
    "wof:placetype":"locality"
},
  "geometry": {"coordinates":[16.09381,44.80217],"type":"Point"}
}