{
  "type": "Feature",
  "properties": {
    "gn:admin1_code":"02",
    "gn:asciiname":"Civcije",
    "gn:country_code":"BA",
    "gn:dem":123,
    "gn:feature_class":"P",
    "gn:feature_code":"PPL",
    "gn:name":"\u010civ\u010dije",
    "gn:population":0,
    "gn:timezone":"Europe/Sarajevo",
    "iso:country":"BA",
    "wof:name":"Civcije",
    "wof:placetype":"locality"
},
  "geometry": {"coordinates":[18.08394,44.87502],"type":"Point"}
}