{
  "type": "Feature",
  "properties": {
    "gn:admin1_code":"01",
    "gn:asciiname":"Gornji Stanojevici",
    "gn:country_code":"BA",
    "gn:dem":294,
    "gn:feature_class":"P",
    "gn:feature_code":"PPL",
    "gn:name":"Gornji Stanojevi\u0107i",
    "gn:population":0,
    "gn:timezone":"Europe/Sarajevo",
    "iso:country":"BA",
    "name:bos_x_preferred":[
        "Stanojevi\u0107i"
    ],
    "name:ceb_x_preferred":[
        "Gornji Stanojevi\u0107i"
    ],
    "name:fra_x_preferred":[
        "Stanojevi\u0107i"
    ],
    "name:hrv_x_preferred":[
        "Stanojevi\u0107i"
    ],
    "name:srp_x_preferred":[
        "\u0421\u0442\u0430\u043d\u043e\u0458\u0435\u0432\u0438\u045b\u0438"
    ],
    "name:swe_x_preferred":[
        "Gornji Stanojevi\u0107i"
    ],
    "wof:name":"Gornji Stanojevici",
    "wof:placetype":"locality"
},
  "geometry": {"coordinates":[17.86243,43.17312],"type":"Point"}
}