{
  "type": "Feature",
  "properties": {
    "gn:admin1_code":"02",
    "gn:asciiname":"Durici",
    "gn:country_code":"BA",
    "gn:dem":187,
    "gn:feature_class":"P",
    "gn:feature_code":"PPL",
    "gn:name":"\u00d0uri\u0107i",
    "gn:population":0,
    "gn:timezone":"Europe/Sarajevo",
    "iso:country":"BA",
    "wof:name":"Durici",
    "wof:placetype":"locality"
},
  "geometry": {"coordinates":[17.87729,44.82792],"type":"Point"}
}