{
  "type": "Feature",
  "properties": {
    "gn:admin1_code":"01",
    "gn:asciiname":"Zelena Ravan",
    "gn:country_code":"BA",
    "gn:dem":1158,
    "gn:feature_class":"P",
    "gn:feature_code":"PPL",
    "gn:name":"Zelena Ravan",
    "gn:population":0,
    "gn:timezone":"Europe/Sarajevo",
    "iso:country":"BA",
    "name:und_x_variant":[
        "Brusovi",
        "Zelena Ravan"
    ],
    "wof:name":"Zelena Ravan",
    "wof:placetype":"locality"
},
  "geometry": {"coordinates":[18.74093,43.71594],"type":"Point"}
}