{
  "type": "Feature",
  "properties": {
    "gn:admin1_code":"02",
    "gn:asciiname":"Vardalici",
    "gn:country_code":"BA",
    "gn:dem":533,
    "gn:feature_class":"P",
    "gn:feature_code":"PPL",
    "gn:name":"Vardali\u0107i",
    "gn:population":0,
    "gn:timezone":"Europe/Sarajevo",
    "iso:country":"BA",
    "wof:name":"Vardalici",
    "wof:placetype":"locality"
},
  "geometry": {"coordinates":[17.18508,44.66621],"type":"Point"}
}