{
  "type": "Feature",
  "properties": {
    "gn:admin1_code":"01",
    "gn:asciiname":"Mirosevici",
    "gn:country_code":"BA",
    "gn:dem":730,
    "gn:feature_class":"P",
    "gn:feature_code":"PPL",
    "gn:name":"Miro\u0161evi\u0107i",
    "gn:population":0,
    "gn:timezone":"Europe/Sarajevo",
    "iso:country":"BA",
    "name:bos_x_preferred":[
        "Miro\u0161evi\u0107i"
    ],
    "name:fra_x_preferred":[
        "Miro\u0161evi\u0107i"
    ],
    "name:hrv_x_preferred":[
        "Miro\u0161evi\u0107i"
    ],
    "wof:name":"Mirosevici",
    "wof:placetype":"locality"
},
  "geometry": {"coordinates":[18.00293,44.04662],"type":"Point"}
}