{
  "type": "Feature",
  "properties": {
    "gn:admin1_code":"01",
    "gn:asciiname":"Pivnice",
    "gn:country_code":"BA",
    "gn:dem":71,
    "gn:feature_class":"P",
    "gn:feature_code":"PPL",
    "gn:name":"Pivnice",
    "gn:population":0,
    "gn:timezone":"Europe/Sarajevo",
    "iso:country":"BA",
    "name:ceb_x_preferred":[
        "Pivnice"
    ],
    "name:deu_x_preferred":[
        "Pivnice"
    ],
    "name:epo_x_preferred":[
        "Pivnice"
    ],
    "name:fra_x_preferred":[
        "Pivnice"
    ],
    "name:hrv_x_preferred":[
        "Pivnice"
    ],
    "name:hun_x_preferred":[
        "Pinc\u00e9d"
    ],
    "name:ita_x_preferred":[
        "Pivnice"
    ],
    "name:msa_x_preferred":[
        "Pivnice"
    ],
    "name:slv_x_preferred":[
        "Pivnice"
    ],
    "name:srp_x_preferred":[
        "\u041f\u0438\u0432\u043d\u0438\u0446\u0435"
    ],
    "name:ukr_x_preferred":[
        "\u041f\u0438\u0432\u043d\u0438\u0446\u0435"
    ],
    "wof:name":"Pivnice",
    "wof:placetype":"locality"
},
  "geometry": {"coordinates":[17.53917,43.17083],"type":"Point"}
}