{
  "type": "Feature",
  "properties": {
    "gn:admin1_code":"02",
    "gn:asciiname":"Avala",
    "gn:country_code":"BA",
    "gn:dem":765,
    "gn:feature_class":"P",
    "gn:feature_code":"PPL",
    "gn:name":"Avala",
    "gn:population":0,
    "gn:timezone":"Europe/Sarajevo",
    "iso:country":"BA",
    "name:bul_x_preferred":[
        "\u0410\u0432\u0430\u043b\u0430"
    ],
    "name:ces_x_preferred":[
        "Avala"
    ],
    "name:deu_x_preferred":[
        "Avala"
    ],
    "name:ell_x_preferred":[
        "\u0386\u03b2\u03b1\u03bb\u03b1"
    ],
    "name:fra_x_preferred":[
        "Avala"
    ],
    "name:hrv_x_preferred":[
        "Avala"
    ],
    "name:ind_x_preferred":[
        "Avala"
    ],
    "name:ita_x_preferred":[
        "Avala"
    ],
    "name:mkd_x_preferred":[
        "\u0410\u0432\u0430\u043b\u0430"
    ],
    "name:nld_x_preferred":[
        "Avala"
    ],
    "name:nno_x_preferred":[
        "Avala"
    ],
    "name:rus_x_preferred":[
        "\u0410\u0432\u0430\u043b\u0430"
    ],
    "name:slk_x_preferred":[
        "Avala"
    ],
    "name:slv_x_preferred":[
        "Avala"
    ],
    "name:spa_x_preferred":[
        "Avala"
    ],
    "name:srp_x_preferred":[
        "\u0410\u0432\u0430\u043b\u0430"
    ],
    "name:swe_x_preferred":[
        "Avala"
    ],
    "name:tur_x_preferred":[
        "Avala"
    ],
    "name:zho_x_preferred":[
        "\u963f\u74e6\u62c9\u5c71"
    ],
    "wof:name":"Avala",
    "wof:placetype":"locality"
},
  "geometry": {"coordinates":[16.44135,44.50701],"type":"Point"}
}