{
  "type": "Feature",
  "properties": {
    "gn:admin1_code":"02",
    "gn:asciiname":"Avala",
    "gn:country_code":"BA",
    "gn:dem":765,
    "gn:feature_class":"P",
    "gn:feature_code":"PPL",
    "gn:name":"Avala",
    "gn:population":0,
    "gn:timezone":"Europe/Sarajevo",
    "iso:country":"BA",
    "wof:name":"Avala",
    "wof:placetype":"locality"
},
  "geometry": {"coordinates":[16.44135,44.50701],"type":"Point"}
}