{
  "type": "Feature",
  "properties": {
    "gn:admin1_code":"02",
    "gn:asciiname":"Kremenovici",
    "gn:country_code":"BA",
    "gn:dem":334,
    "gn:feature_class":"P",
    "gn:feature_code":"PPL",
    "gn:name":"Kremenovi\u0107i",
    "gn:population":0,
    "gn:timezone":"Europe/Sarajevo",
    "iso:country":"BA",
    "wof:name":"Kremenovici",
    "wof:placetype":"locality"
},
  "geometry": {"coordinates":[17.04215,44.80324],"type":"Point"}
}