{
  "type": "Feature",
  "properties": {
    "gn:admin1_code":"02",
    "gn:asciiname":"Podgradina",
    "gn:country_code":"BA",
    "gn:dem":791,
    "gn:feature_class":"P",
    "gn:feature_code":"PPL",
    "gn:name":"Podgradina",
    "gn:population":0,
    "gn:timezone":"Europe/Sarajevo",
    "iso:country":"BA",
    "wof:name":"Podgradina",
    "wof:placetype":"locality"
},
  "geometry": {"coordinates":[18.86777,43.79365],"type":"Point"}
}