{
  "type": "Feature",
  "properties": {
    "gn:admin1_code":"01",
    "gn:asciiname":"Mali Ilici",
    "gn:country_code":"BA",
    "gn:dem":431,
    "gn:feature_class":"P",
    "gn:feature_code":"PPL",
    "gn:name":"Mali Ili\u0107i",
    "gn:population":0,
    "gn:timezone":"Europe/Sarajevo",
    "iso:country":"BA",
    "wof:name":"Mali Ilici",
    "wof:placetype":"locality"
},
  "geometry": {"coordinates":[16.59345,44.75583],"type":"Point"}
}