{
  "type": "Feature",
  "properties": {
    "gn:admin1_code":"01",
    "gn:asciiname":"Zabilje",
    "gn:country_code":"BA",
    "gn:dem":698,
    "gn:feature_class":"P",
    "gn:feature_code":"PPL",
    "gn:name":"Zabilje",
    "gn:population":0,
    "gn:timezone":"Europe/Sarajevo",
    "iso:country":"BA",
    "wof:name":"Zabilje",
    "wof:placetype":"locality"
},
  "geometry": {"coordinates":[17.77983,44.19692],"type":"Point"}
}