{
  "type": "Feature",
  "properties": {
    "gn:admin1_code":"01",
    "gn:asciiname":"Jelasinovci",
    "gn:country_code":"BA",
    "gn:dem":397,
    "gn:feature_class":"P",
    "gn:feature_code":"PPLL",
    "gn:name":"Jela\u0161inovci",
    "gn:population":0,
    "gn:timezone":"Europe/Sarajevo",
    "iso:country":"BA",
    "wof:name":"Jelasinovci",
    "wof:placetype":"locality"
},
  "geometry": {"coordinates":[16.52732,44.69662],"type":"Point"}
}