{
  "type": "Feature",
  "properties": {
    "gn:admin1_code":"02",
    "gn:asciiname":"Gornje Mladice",
    "gn:country_code":"BA",
    "gn:dem":630,
    "gn:feature_class":"P",
    "gn:feature_code":"PPL",
    "gn:name":"Gornje Mladice",
    "gn:population":0,
    "gn:timezone":"Europe/Sarajevo",
    "iso:country":"BA",
    "name:bos_x_preferred":[
        "Gornje Mladice"
    ],
    "name:ceb_x_preferred":[
        "Gornje Mladice"
    ],
    "name:fra_x_preferred":[
        "Gornje Mladice"
    ],
    "name:srp_x_preferred":[
        "\u0413\u043e\u0440\u045a\u0435 \u041c\u043b\u0430\u0434\u0438\u0446\u0435"
    ],
    "name:swe_x_preferred":[
        "Gornje Mladice"
    ],
    "wof:name":"Gornje Mladice",
    "wof:placetype":"locality"
},
  "geometry": {"coordinates":[18.37305,43.79904000000001],"type":"Point"}
}