{
  "type": "Feature",
  "properties": {
    "gn:admin1_code":"01",
    "gn:asciiname":"Loncaruse",
    "gn:country_code":"BA",
    "gn:dem":725,
    "gn:feature_class":"P",
    "gn:feature_code":"PPL",
    "gn:name":"Lon\u010daru\u0161e",
    "gn:population":0,
    "gn:timezone":"Europe/Sarajevo",
    "iso:country":"BA",
    "wof:name":"Loncaruse",
    "wof:placetype":"locality"
},
  "geometry": {"coordinates":[17.49514,43.42323],"type":"Point"}
}