{
  "type": "Feature",
  "properties": {
    "gn:admin1_code":"01",
    "gn:asciiname":"Sofici",
    "gn:country_code":"BA",
    "gn:dem":264,
    "gn:feature_class":"P",
    "gn:feature_code":"PPL",
    "gn:name":"Sofi\u0107i",
    "gn:population":0,
    "gn:timezone":"Europe/Sarajevo",
    "iso:country":"BA",
    "wof:name":"Sofici",
    "wof:placetype":"locality"
},
  "geometry": {"coordinates":[18.50578,44.70386],"type":"Point"}
}