{
  "type": "Feature",
  "properties": {
    "gn:admin1_code":"02",
    "gn:asciiname":"Skok",
    "gn:country_code":"BA",
    "gn:dem":681,
    "gn:feature_class":"P",
    "gn:feature_code":"PPL",
    "gn:name":"Skok",
    "gn:population":0,
    "gn:timezone":"Europe/Sarajevo",
    "iso:country":"BA",
    "wof:name":"Skok",
    "wof:placetype":"locality"
},
  "geometry": {"coordinates":[17.1587,44.34752],"type":"Point"}
}