{
  "type": "Feature",
  "properties": {
    "gn:admin1_code":"01",
    "gn:asciiname":"Halilovici",
    "gn:country_code":"BA",
    "gn:dem":485,
    "gn:feature_class":"P",
    "gn:feature_code":"PPL",
    "gn:name":"Halilovi\u0107i",
    "gn:population":0,
    "gn:timezone":"Europe/Sarajevo",
    "iso:country":"BA",
    "wof:name":"Halilovici",
    "wof:placetype":"locality"
},
  "geometry": {"coordinates":[18.25419,44.48251],"type":"Point"}
}