{
  "type": "Feature",
  "properties": {
    "gn:admin1_code":"02",
    "gn:asciiname":"Osojnica",
    "gn:country_code":"BA",
    "gn:dem":210,
    "gn:feature_class":"P",
    "gn:feature_code":"PPLL",
    "gn:name":"Osojnica",
    "gn:population":0,
    "gn:timezone":"Europe/Sarajevo",
    "iso:country":"BA",
    "wof:name":"Osojnica",
    "wof:placetype":"locality"
},
  "geometry": {"coordinates":[18.1177,44.64221],"type":"Point"}
}