{
  "type": "Feature",
  "properties": {
    "gn:admin1_code":"01",
    "gn:asciiname":"Relica Draga",
    "gn:country_code":"BA",
    "gn:dem":246,
    "gn:feature_class":"P",
    "gn:feature_code":"PPL",
    "gn:name":"Reli\u0107a Draga",
    "gn:population":0,
    "gn:timezone":"Europe/Sarajevo",
    "iso:country":"BA",
    "wof:name":"Relica Draga",
    "wof:placetype":"locality"
},
  "geometry": {"coordinates":[15.92417,44.74778],"type":"Point"}
}