{
  "type": "Feature",
  "properties": {
    "gn:admin1_code":"02",
    "gn:asciiname":"Banjci",
    "gn:country_code":"BA",
    "gn:dem":855,
    "gn:feature_class":"P",
    "gn:feature_code":"PPL",
    "gn:name":"Banjci",
    "gn:population":0,
    "gn:timezone":"Europe/Sarajevo",
    "iso:country":"BA",
    "wof:name":"Banjci",
    "wof:placetype":"locality"
},
  "geometry": {"coordinates":[16.76648,44.45481],"type":"Point"}
}