{
  "type": "Feature",
  "properties": {
    "gn:admin1_code":"02",
    "gn:asciiname":"Igrisnik",
    "gn:country_code":"BA",
    "gn:dem":1175,
    "gn:feature_class":"P",
    "gn:feature_code":"PPL",
    "gn:name":"Igri\u0161nik",
    "gn:population":0,
    "gn:timezone":"Europe/Sarajevo",
    "iso:country":"BA",
    "wof:name":"Igrisnik",
    "wof:placetype":"locality"
},
  "geometry": {"coordinates":[19.18444,44.00361],"type":"Point"}
}