{
  "type": "Feature",
  "properties": {
    "gn:admin1_code":"02",
    "gn:asciiname":"Surduk",
    "gn:country_code":"BA",
    "gn:dem":771,
    "gn:feature_class":"P",
    "gn:feature_code":"PPL",
    "gn:name":"Surduk",
    "gn:population":0,
    "gn:timezone":"Europe/Sarajevo",
    "iso:country":"BA",
    "name:ceb_x_preferred":[
        "Surduk"
    ],
    "name:ces_x_preferred":[
        "Surduk"
    ],
    "name:deu_x_preferred":[
        "Surduk"
    ],
    "name:epo_x_preferred":[
        "Surduk"
    ],
    "name:fra_x_preferred":[
        "Surduk"
    ],
    "name:hrv_x_preferred":[
        "Surduk"
    ],
    "name:hun_x_preferred":[
        "Szurdok"
    ],
    "name:msa_x_preferred":[
        "Surduk"
    ],
    "name:slv_x_preferred":[
        "Surduk"
    ],
    "name:srp_x_preferred":[
        "\u0421\u0443\u0440\u0434\u0443\u043a"
    ],
    "wof:name":"Surduk",
    "wof:placetype":"locality"
},
  "geometry": {"coordinates":[19.21139,43.96583],"type":"Point"}
}