{
  "type": "Feature",
  "properties": {
    "gn:admin1_code":"01",
    "gn:asciiname":"Ilidza",
    "gn:country_code":"BA",
    "gn:dem":277,
    "gn:feature_class":"P",
    "gn:feature_code":"PPLL",
    "gn:name":"Ilid\u017ea",
    "gn:population":0,
    "gn:timezone":"Europe/Sarajevo",
    "iso:country":"BA",
    "wof:name":"Ilidza",
    "wof:placetype":"locality"
},
  "geometry": {"coordinates":[16.76895,44.6851],"type":"Point"}
}