{
  "type": "Feature",
  "properties": {
    "gn:admin1_code":"02",
    "gn:asciiname":"Lisina",
    "gn:country_code":"BA",
    "gn:dem":1167,
    "gn:feature_class":"P",
    "gn:feature_code":"PPL",
    "gn:name":"Lisina",
    "gn:population":0,
    "gn:timezone":"Europe/Sarajevo",
    "iso:country":"BA",
    "name:msa_x_preferred":[
        "Lisina"
    ],
    "wof:name":"Lisina",
    "wof:placetype":"locality"
},
  "geometry": {"coordinates":[16.72715,44.34566],"type":"Point"}
}