{
  "type": "Feature",
  "properties": {
    "gn:admin1_code":"02",
    "gn:asciiname":"Panik",
    "gn:country_code":"BA",
    "gn:dem":383,
    "gn:feature_class":"P",
    "gn:feature_code":"PPLL",
    "gn:name":"Panik",
    "gn:population":0,
    "gn:timezone":"Europe/Sarajevo",
    "iso:country":"BA",
    "name:ceb_x_preferred":[
        "Panik"
    ],
    "name:dan_x_preferred":[
        "Panik"
    ],
    "name:deu_x_preferred":[
        "Panik"
    ],
    "name:fra_x_preferred":[
        "Panik"
    ],
    "name:ita_x_preferred":[
        "Panik"
    ],
    "name:rus_x_preferred":[
        "Panik"
    ],
    "name:swe_x_preferred":[
        "Panik"
    ],
    "wof:name":"Panik",
    "wof:placetype":"locality"
},
  "geometry": {"coordinates":[18.4425,42.80944],"type":"Point"}
}