{
  "type": "Feature",
  "properties": {
    "gn:admin1_code":"01",
    "gn:asciiname":"Glodina",
    "gn:country_code":"BA",
    "gn:dem":181,
    "gn:feature_class":"P",
    "gn:feature_code":"PPL",
    "gn:name":"Glodina",
    "gn:population":0,
    "gn:timezone":"Europe/Sarajevo",
    "iso:country":"BA",
    "wof:name":"Glodina",
    "wof:placetype":"locality"
},
  "geometry": {"coordinates":[16.18769,45.02408],"type":"Point"}
}