{
  "type": "Feature",
  "properties": {
    "gn:admin1_code":"01",
    "gn:asciiname":"Urduk",
    "gn:country_code":"BA",
    "gn:dem":711,
    "gn:feature_class":"P",
    "gn:feature_code":"PPL",
    "gn:name":"Urduk",
    "gn:population":0,
    "gn:timezone":"Europe/Sarajevo",
    "iso:country":"BA",
    "name:bos_x_preferred":[
        "Urduk"
    ],
    "name:fra_x_preferred":[
        "Urduk"
    ],
    "wof:name":"Urduk",
    "wof:placetype":"locality"
},
  "geometry": {"coordinates":[18.13223,43.80103],"type":"Point"}
}