{
  "type": "Feature",
  "properties": {
    "gn:admin1_code":"01",
    "gn:asciiname":"Klapici",
    "gn:country_code":"BA",
    "gn:dem":258,
    "gn:feature_class":"P",
    "gn:feature_code":"PPL",
    "gn:name":"Klapi\u0107i",
    "gn:population":0,
    "gn:timezone":"Europe/Sarajevo",
    "iso:country":"BA",
    "wof:name":"Klapici",
    "wof:placetype":"locality"
},
  "geometry": {"coordinates":[18.52305,44.46542],"type":"Point"}
}