{
  "type": "Feature",
  "properties": {
    "gn:admin1_code":"01",
    "gn:asciiname":"Benek",
    "gn:country_code":"BA",
    "gn:dem":611,
    "gn:feature_class":"P",
    "gn:feature_code":"PPL",
    "gn:name":"Benek",
    "gn:population":0,
    "gn:timezone":"Europe/Sarajevo",
    "iso:country":"BA",
    "wof:name":"Benek",
    "wof:placetype":"locality"
},
  "geometry": {"coordinates":[17.30606,44.40332],"type":"Point"}
}