{
  "type": "Feature",
  "properties": {
    "gn:admin1_code":"02",
    "gn:asciiname":"Klobucari",
    "gn:country_code":"BA",
    "gn:dem":541,
    "gn:feature_class":"P",
    "gn:feature_code":"PPL",
    "gn:name":"Klobu\u010dari",
    "gn:population":0,
    "gn:timezone":"Europe/Sarajevo",
    "iso:country":"BA",
    "wof:name":"Klobucari",
    "wof:placetype":"locality"
},
  "geometry": {"coordinates":[18.68219,43.55258],"type":"Point"}
}