{
  "type": "Feature",
  "properties": {
    "gn:admin1_code":"01",
    "gn:asciiname":"Strgonice",
    "gn:country_code":"BA",
    "gn:dem":987,
    "gn:feature_class":"P",
    "gn:feature_code":"PPL",
    "gn:name":"Strgonice",
    "gn:population":0,
    "gn:timezone":"Europe/Sarajevo",
    "iso:country":"BA",
    "wof:name":"Strgonice",
    "wof:placetype":"locality"
},
  "geometry": {"coordinates":[17.89852,43.72743],"type":"Point"}
}