{
  "type": "Feature",
  "properties": {
    "gn:admin1_code":"01",
    "gn:asciiname":"Strgonice",
    "gn:country_code":"BA",
    "gn:dem":987,
    "gn:feature_class":"P",
    "gn:feature_code":"PPL",
    "gn:name":"Strgonice",
    "gn:population":0,
    "gn:timezone":"Europe/Sarajevo",
    "iso:country":"BA",
    "name:ara_x_preferred":[
        "\u0633\u062a\u0631\u063a\u0648\u0646\u064a\u0633"
    ],
    "name:bos_x_preferred":[
        "Strgonice"
    ],
    "name:fra_x_preferred":[
        "Strgonice"
    ],
    "name:hrv_x_preferred":[
        "Strgonice"
    ],
    "name:srp_x_preferred":[
        "\u0421\u0442\u0440\u0433\u043e\u043d\u0438\u0446\u0435"
    ],
    "wof:name":"Strgonice",
    "wof:placetype":"locality"
},
  "geometry": {"coordinates":[17.89852,43.72743],"type":"Point"}
}