{
  "type": "Feature",
  "properties": {
    "gn:admin1_code":"01",
    "gn:asciiname":"Tihaljina",
    "gn:country_code":"BA",
    "gn:dem":162,
    "gn:feature_class":"P",
    "gn:feature_code":"PPLL",
    "gn:name":"Tihaljina",
    "gn:population":0,
    "gn:timezone":"Europe/Sarajevo",
    "iso:country":"BA",
    "name:bos_x_preferred":[
        "Tihaljina"
    ],
    "name:ceb_x_preferred":[
        "Tihaljina"
    ],
    "name:ell_x_preferred":[
        "\u03a4\u03b9\u03c7\u03ac\u03bb\u03b9\u03bd\u03b1"
    ],
    "name:fra_x_preferred":[
        "Tihaljina"
    ],
    "name:hrv_x_preferred":[
        "Tihaljina"
    ],
    "name:srp_x_preferred":[
        "\u0422\u0438\u0445\u0430\u0459\u0438\u043d\u0430"
    ],
    "name:swe_x_preferred":[
        "Tihaljina"
    ],
    "wof:name":"Tihaljina",
    "wof:placetype":"locality"
},
  "geometry": {"coordinates":[17.38667,43.31493],"type":"Point"}
}