{
  "type": "Feature",
  "properties": {
    "gn:admin1_code":"01",
    "gn:asciiname":"Tihaljina",
    "gn:country_code":"BA",
    "gn:dem":162,
    "gn:feature_class":"P",
    "gn:feature_code":"PPLL",
    "gn:name":"Tihaljina",
    "gn:population":0,
    "gn:timezone":"Europe/Sarajevo",
    "iso:country":"BA",
    "wof:name":"Tihaljina",
    "wof:placetype":"locality"
},
  "geometry": {"coordinates":[17.38667,43.31493],"type":"Point"}
}