{
  "type": "Feature",
  "properties": {
    "gn:admin1_code":"01",
    "gn:asciiname":"Buhaci",
    "gn:country_code":"BA",
    "gn:dem":297,
    "gn:feature_class":"P",
    "gn:feature_code":"PPL",
    "gn:name":"Buha\u010di",
    "gn:population":0,
    "gn:timezone":"Europe/Sarajevo",
    "iso:country":"BA",
    "wof:name":"Buhaci",
    "wof:placetype":"locality"
},
  "geometry": {"coordinates":[17.64685,43.32471],"type":"Point"}
}