{
  "type": "Feature",
  "properties": {
    "gn:admin1_code":"02",
    "gn:asciiname":"Smitrani",
    "gn:country_code":"BA",
    "gn:dem":339,
    "gn:feature_class":"P",
    "gn:feature_code":"PPLL",
    "gn:name":"\u0160mitrani",
    "gn:population":0,
    "gn:timezone":"Europe/Sarajevo",
    "iso:country":"BA",
    "wof:name":"Smitrani",
    "wof:placetype":"locality"
},
  "geometry": {"coordinates":[17.09143,45.00557],"type":"Point"}
}