{
  "type": "Feature",
  "properties": {
    "gn:admin1_code":"01",
    "gn:asciiname":"Milicevici",
    "gn:country_code":"BA",
    "gn:dem":958,
    "gn:feature_class":"P",
    "gn:feature_code":"PPL",
    "gn:name":"Mili\u0107evi\u0107i",
    "gn:population":0,
    "gn:timezone":"Europe/Sarajevo",
    "iso:country":"BA",
    "wof:name":"Milicevici",
    "wof:placetype":"locality"
},
  "geometry": {"coordinates":[17.4321,43.46618],"type":"Point"}
}