{
  "type": "Feature",
  "properties": {
    "gn:admin1_code":"01",
    "gn:asciiname":"Vasarevine",
    "gn:country_code":"BA",
    "gn:dem":731,
    "gn:feature_class":"P",
    "gn:feature_code":"PPL",
    "gn:name":"Va\u0161arevine",
    "gn:population":0,
    "gn:timezone":"Europe/Sarajevo",
    "iso:country":"BA",
    "wof:name":"Vasarevine",
    "wof:placetype":"locality"
},
  "geometry": {"coordinates":[16.90635,43.86725],"type":"Point"}
}