{
  "type": "Feature",
  "properties": {
    "gn:admin1_code":"02",
    "gn:asciiname":"Donji Rakani",
    "gn:country_code":"BA",
    "gn:dem":170,
    "gn:feature_class":"P",
    "gn:feature_code":"PPLL",
    "gn:name":"Donji Rakani",
    "gn:population":0,
    "gn:timezone":"Europe/Sarajevo",
    "iso:country":"BA",
    "name:bos_x_preferred":[
        "Donji Rakani"
    ],
    "name:ceb_x_preferred":[
        "Donji Rakani"
    ],
    "name:fra_x_preferred":[
        "Donji Rakani"
    ],
    "name:hrv_x_preferred":[
        "Donji Rakani"
    ],
    "name:srp_x_preferred":[
        "\u0414\u043e\u045a\u0438 \u0420\u0430\u043a\u0430\u043d\u0438"
    ],
    "name:swe_x_preferred":[
        "Donji Rakani"
    ],
    "wof:name":"Donji Rakani",
    "wof:placetype":"locality"
},
  "geometry": {"coordinates":[16.32413,44.99217],"type":"Point"}
}