{
  "type": "Feature",
  "properties": {
    "gn:admin1_code":"01",
    "gn:asciiname":"Ljaljevac",
    "gn:country_code":"BA",
    "gn:dem":495,
    "gn:feature_class":"P",
    "gn:feature_code":"PPL",
    "gn:name":"Ljaljevac",
    "gn:population":0,
    "gn:timezone":"Europe/Sarajevo",
    "iso:country":"BA",
    "wof:name":"Ljaljevac",
    "wof:placetype":"locality"
},
  "geometry": {"coordinates":[18.26722,44.54889],"type":"Point"}
}