{
  "type": "Feature",
  "properties": {
    "gn:admin1_code":"01",
    "gn:asciiname":"Crvljivac",
    "gn:country_code":"BA",
    "gn:dem":867,
    "gn:feature_class":"P",
    "gn:feature_code":"PPL",
    "gn:name":"Crvljivac",
    "gn:population":0,
    "gn:timezone":"Europe/Sarajevo",
    "iso:country":"BA",
    "wof:name":"Crvljivac",
    "wof:placetype":"locality"
},
  "geometry": {"coordinates":[18.95552,43.71605],"type":"Point"}
}