{
  "type": "Feature",
  "properties": {
    "gn:admin1_code":"01",
    "gn:asciiname":"Basici",
    "gn:country_code":"BA",
    "gn:dem":691,
    "gn:feature_class":"P",
    "gn:feature_code":"PPL",
    "gn:name":"Ba\u0161i\u0107i",
    "gn:population":0,
    "gn:timezone":"Europe/Sarajevo",
    "iso:country":"BA",
    "name:und_x_variant":[
        "Ba\u0161i\u0107a Mah",
        "Ba\u0161i\u0107i"
    ],
    "wof:name":"Basici",
    "wof:placetype":"locality"
},
  "geometry": {"coordinates":[17.4144,43.43806],"type":"Point"}
}