{
  "type": "Feature",
  "properties": {
    "gn:admin1_code":"02",
    "gn:asciiname":"Podovi",
    "gn:country_code":"BA",
    "gn:dem":1224,
    "gn:feature_class":"P",
    "gn:feature_code":"PPL",
    "gn:name":"Podovi",
    "gn:population":0,
    "gn:timezone":"Europe/Sarajevo",
    "iso:country":"BA",
    "wof:name":"Podovi",
    "wof:placetype":"locality"
},
  "geometry": {"coordinates":[17.12233,44.12829],"type":"Point"}
}