{
  "type": "Feature",
  "properties": {
    "gn:admin1_code":"02",
    "gn:asciiname":"Babici",
    "gn:country_code":"BA",
    "gn:dem":255,
    "gn:feature_class":"P",
    "gn:feature_code":"PPLL",
    "gn:name":"Babi\u0107i",
    "gn:population":0,
    "gn:timezone":"Europe/Sarajevo",
    "iso:country":"BA",
    "wof:name":"Babici",
    "wof:placetype":"locality"
},
  "geometry": {"coordinates":[16.90268,44.95086],"type":"Point"}
}