{
  "type": "Feature",
  "properties": {
    "gn:admin1_code":"02",
    "gn:asciiname":"Donje Brestice",
    "gn:country_code":"BA",
    "gn:dem":935,
    "gn:feature_class":"P",
    "gn:feature_code":"PPL",
    "gn:name":"Donje Brestice",
    "gn:population":0,
    "gn:timezone":"Europe/Sarajevo",
    "iso:country":"BA",
    "name:und_x_variant":[
        "Brestice",
        "Brestica",
        "Donje Brestice"
    ],
    "wof:name":"Donje Brestice",
    "wof:placetype":"locality"
},
  "geometry": {"coordinates":[18.45588,43.06656],"type":"Point"}
}