{
  "type": "Feature",
  "properties": {
    "gn:admin1_code":"01",
    "gn:asciiname":"Pecka",
    "gn:country_code":"BA",
    "gn:dem":158,
    "gn:feature_class":"P",
    "gn:feature_code":"PPL",
    "gn:name":"Pecka",
    "gn:population":0,
    "gn:timezone":"Europe/Sarajevo",
    "iso:country":"BA",
    "wof:name":"Pecka",
    "wof:placetype":"locality"
},
  "geometry": {"coordinates":[15.92287,45.20314000000001],"type":"Point"}
}