{
  "type": "Feature",
  "properties": {
    "gn:admin1_code":"01",
    "gn:asciiname":"Novi Put",
    "gn:country_code":"BA",
    "gn:dem":122,
    "gn:feature_class":"P",
    "gn:feature_code":"PPL",
    "gn:name":"Novi Put",
    "gn:population":0,
    "gn:timezone":"Europe/Sarajevo",
    "iso:country":"BA",
    "wof:name":"Novi Put",
    "wof:placetype":"locality"
},
  "geometry": {"coordinates":[17.67222000000001,42.9125],"type":"Point"}
}