{
  "type": "Feature",
  "properties": {
    "gn:admin1_code":"01",
    "gn:asciiname":"Tresnjica",
    "gn:country_code":"BA",
    "gn:dem":1174,
    "gn:feature_class":"P",
    "gn:feature_code":"PPL",
    "gn:name":"Tre\u0161njica",
    "gn:population":0,
    "gn:timezone":"Europe/Sarajevo",
    "iso:country":"BA",
    "wof:name":"Tresnjica",
    "wof:placetype":"locality"
},
  "geometry": {"coordinates":[18.82843,43.71897],"type":"Point"}
}