{
  "type": "Feature",
  "properties": {
    "gn:admin1_code":"02",
    "gn:asciiname":"Rogousici",
    "gn:country_code":"BA",
    "gn:dem":933,
    "gn:feature_class":"P",
    "gn:feature_code":"PPL",
    "gn:name":"Rogou\u0161i\u0107i",
    "gn:population":0,
    "gn:timezone":"Europe/Sarajevo",
    "iso:country":"BA",
    "name:und_x_variant":[
        "Rogou\u0161i\u0107i"
    ],
    "wof:name":"Rogousici",
    "wof:placetype":"locality"
},
  "geometry": {"coordinates":[18.55375,43.87588],"type":"Point"}
}