{
  "type": "Feature",
  "properties": {
    "gn:admin1_code":"02",
    "gn:asciiname":"Podcaus",
    "gn:country_code":"BA",
    "gn:dem":202,
    "gn:feature_class":"P",
    "gn:feature_code":"PPL",
    "gn:name":"Pod\u010dau\u0161",
    "gn:population":0,
    "gn:timezone":"Europe/Sarajevo",
    "iso:country":"BA",
    "name:und_x_variant":[
        "Pod\u010dau\u0161"
    ],
    "wof:name":"Podcaus",
    "wof:placetype":"locality"
},
  "geometry": {"coordinates":[19.33257,44.17382],"type":"Point"}
}