{
  "type": "Feature",
  "properties": {
    "gn:admin1_code":"02",
    "gn:asciiname":"Podcaus",
    "gn:country_code":"BA",
    "gn:dem":202,
    "gn:feature_class":"P",
    "gn:feature_code":"PPL",
    "gn:name":"Pod\u010dau\u0161",
    "gn:population":0,
    "gn:timezone":"Europe/Sarajevo",
    "iso:country":"BA",
    "name:bos_x_preferred":[
        "Pod\u010dau\u0161"
    ],
    "name:bul_x_preferred":[
        "\u041f\u043e\u0434\u0447\u0430\u0443\u0448"
    ],
    "name:ceb_x_preferred":[
        "Pod\u010dau\u0161"
    ],
    "name:fra_x_preferred":[
        "Pod\u010dau\u0161"
    ],
    "name:hrv_x_preferred":[
        "Pod\u010dau\u0161"
    ],
    "name:rus_x_preferred":[
        "\u041f\u043e\u0434\u0447\u0430\u0443\u0448"
    ],
    "name:srp_x_preferred":[
        "\u041f\u043e\u0434\u0447\u0430\u0443\u0448"
    ],
    "name:swe_x_preferred":[
        "Pod\u010dau\u0161"
    ],
    "wof:name":"Podcaus",
    "wof:placetype":"locality"
},
  "geometry": {"coordinates":[19.33257,44.17382],"type":"Point"}
}