{
  "type": "Feature",
  "properties": {
    "gn:admin1_code":"02",
    "gn:asciiname":"Likari",
    "gn:country_code":"BA",
    "gn:dem":269,
    "gn:feature_class":"P",
    "gn:feature_code":"PPLL",
    "gn:name":"Likari",
    "gn:population":0,
    "gn:timezone":"Europe/Sarajevo",
    "iso:country":"BA",
    "name:bos_x_preferred":[
        "Likari"
    ],
    "name:bul_x_preferred":[
        "\u041b\u0438\u043a\u0430\u0440\u0438"
    ],
    "name:ceb_x_preferred":[
        "Likari"
    ],
    "name:fra_x_preferred":[
        "Likari"
    ],
    "name:hrv_x_preferred":[
        "Likari"
    ],
    "name:srp_x_preferred":[
        "\u041b\u0438\u043a\u0430\u0440\u0438"
    ],
    "name:swe_x_preferred":[
        "Likari"
    ],
    "wof:name":"Likari",
    "wof:placetype":"locality"
},
  "geometry": {"coordinates":[19.30194,44.13914000000001],"type":"Point"}
}