{
  "type": "Feature",
  "properties": {
    "gn:admin1_code":"02",
    "gn:asciiname":"Oravci",
    "gn:country_code":"BA",
    "gn:dem":528,
    "gn:feature_class":"P",
    "gn:feature_code":"PPL",
    "gn:name":"Oravci",
    "gn:population":0,
    "gn:timezone":"Europe/Sarajevo",
    "iso:country":"BA",
    "wof:name":"Oravci",
    "wof:placetype":"locality"
},
  "geometry": {"coordinates":[17.15332,44.37606],"type":"Point"}
}