{
  "type": "Feature",
  "properties": {
    "gn:admin1_code":"01",
    "gn:asciiname":"Prevlje",
    "gn:country_code":"BA",
    "gn:dem":539,
    "gn:feature_class":"P",
    "gn:feature_code":"PPL",
    "gn:name":"Prevlje",
    "gn:population":0,
    "gn:timezone":"Europe/Sarajevo",
    "iso:country":"BA",
    "wof:name":"Prevlje",
    "wof:placetype":"locality"
},
  "geometry": {"coordinates":[17.96091000000001,43.62911],"type":"Point"}
}