{
  "type": "Feature",
  "properties": {
    "gn:admin1_code":"01",
    "gn:asciiname":"Prevlje",
    "gn:country_code":"BA",
    "gn:dem":539,
    "gn:feature_class":"P",
    "gn:feature_code":"PPL",
    "gn:name":"Prevlje",
    "gn:population":0,
    "gn:timezone":"Europe/Sarajevo",
    "iso:country":"BA",
    "name:ara_x_preferred":[
        "\u0628\u0631\u064a\u0641\u0644\u064a\u064a"
    ],
    "name:bos_x_preferred":[
        "Prevlje"
    ],
    "name:fra_x_preferred":[
        "Prevlje"
    ],
    "name:hrv_x_preferred":[
        "Prevlje"
    ],
    "name:srp_x_preferred":[
        "\u041f\u0440\u0435\u0432\u0459\u0435"
    ],
    "wof:name":"Prevlje",
    "wof:placetype":"locality"
},
  "geometry": {"coordinates":[17.96091000000001,43.62911],"type":"Point"}
}