{
  "type": "Feature",
  "properties": {
    "gn:admin1_code":"01",
    "gn:asciiname":"Zenica",
    "gn:country_code":"BA",
    "gn:dem":525,
    "gn:feature_class":"P",
    "gn:feature_code":"PPL",
    "gn:name":"Zenica",
    "gn:population":0,
    "gn:timezone":"Europe/Sarajevo",
    "iso:country":"BA",
    "wof:name":"Zenica",
    "wof:placetype":"locality"
},
  "geometry": {"coordinates":[18.30883,43.89243],"type":"Point"}
}