{
  "type": "Feature",
  "properties": {
    "gn:admin1_code":"01",
    "gn:asciiname":"Do",
    "gn:country_code":"BA",
    "gn:dem":110,
    "gn:feature_class":"P",
    "gn:feature_code":"PPL",
    "gn:name":"Do",
    "gn:population":0,
    "gn:timezone":"Europe/Sarajevo",
    "iso:country":"BA",
    "name:ara_x_preferred":[
        "\u062f\u0648"
    ],
    "name:fas_x_preferred":[
        "\u062f\u0648"
    ],
    "name:rus_x_preferred":[
        "\u0414\u043e"
    ],
    "name:swe_x_preferred":[
        "Do"
    ],
    "wof:name":"Do",
    "wof:placetype":"locality"
},
  "geometry": {"coordinates":[17.88902000000001,43.26521],"type":"Point"}
}