{
  "type": "Feature",
  "properties": {
    "gn:admin1_code":"01",
    "gn:asciiname":"Stog",
    "gn:country_code":"BA",
    "gn:dem":263,
    "gn:feature_class":"P",
    "gn:feature_code":"PPL",
    "gn:name":"Stog",
    "gn:population":0,
    "gn:timezone":"Europe/Sarajevo",
    "iso:country":"BA",
    "wof:name":"Stog",
    "wof:placetype":"locality"
},
  "geometry": {"coordinates":[18.29444,44.40977],"type":"Point"}
}