{
  "type": "Feature",
  "properties": {
    "gn:admin1_code":"02",
    "gn:asciiname":"Piragici",
    "gn:country_code":"BA",
    "gn:dem":874,
    "gn:feature_class":"P",
    "gn:feature_code":"PPL",
    "gn:name":"Piragi\u0107i",
    "gn:population":0,
    "gn:timezone":"Europe/Sarajevo",
    "iso:country":"BA",
    "wof:name":"Piragici",
    "wof:placetype":"locality"
},
  "geometry": {"coordinates":[18.19009,43.15582],"type":"Point"}
}