{
  "type": "Feature",
  "properties": {
    "gn:admin1_code":"01",
    "gn:asciiname":"Suljici",
    "gn:country_code":"BA",
    "gn:dem":288,
    "gn:feature_class":"P",
    "gn:feature_code":"PPL",
    "gn:name":"Sulji\u0107i",
    "gn:population":0,
    "gn:timezone":"Europe/Sarajevo",
    "iso:country":"BA",
    "wof:name":"Suljici",
    "wof:placetype":"locality"
},
  "geometry": {"coordinates":[15.818,44.99087],"type":"Point"}
}