{
  "type": "Feature",
  "properties": {
    "gn:admin1_code":"01",
    "gn:asciiname":"Svrake",
    "gn:country_code":"BA",
    "gn:dem":493,
    "gn:feature_class":"P",
    "gn:feature_code":"PPL",
    "gn:name":"Svrake",
    "gn:population":0,
    "gn:timezone":"Europe/Sarajevo",
    "iso:country":"BA",
    "wof:name":"Svrake",
    "wof:placetype":"locality"
},
  "geometry": {"coordinates":[18.30729,43.91936],"type":"Point"}
}