{
  "type": "Feature",
  "properties": {
    "gn:admin1_code":"01",
    "gn:asciiname":"Mali Mosunj",
    "gn:country_code":"BA",
    "gn:dem":433,
    "gn:feature_class":"P",
    "gn:feature_code":"PPL",
    "gn:name":"Mali Mo\u0161unj",
    "gn:population":0,
    "gn:timezone":"Europe/Sarajevo",
    "iso:country":"BA",
    "name:und_x_variant":[
        "Mo\u0161unj Mali",
        "Mali Mo\u0161unj"
    ],
    "wof:name":"Mali Mosunj",
    "wof:placetype":"locality"
},
  "geometry": {"coordinates":[17.74823,44.17433],"type":"Point"}
}