{
  "type": "Feature",
  "properties": {
    "gn:admin1_code":"02",
    "gn:asciiname":"Sumari",
    "gn:country_code":"BA",
    "gn:dem":220,
    "gn:feature_class":"P",
    "gn:feature_code":"PPL",
    "gn:name":"\u0160umari",
    "gn:population":0,
    "gn:timezone":"Europe/Sarajevo",
    "iso:country":"BA",
    "wof:name":"Sumari",
    "wof:placetype":"locality"
},
  "geometry": {"coordinates":[16.71867,45.17635],"type":"Point"}
}