{
  "type": "Feature",
  "properties": {
    "gn:admin1_code":"02",
    "gn:asciiname":"Hodzici",
    "gn:country_code":"BA",
    "gn:dem":893,
    "gn:feature_class":"P",
    "gn:feature_code":"PPLL",
    "gn:name":"Hod\u017ei\u0107i",
    "gn:population":0,
    "gn:timezone":"Europe/Sarajevo",
    "iso:country":"BA",
    "wof:name":"Hodzici",
    "wof:placetype":"locality"
},
  "geometry": {"coordinates":[18.45822,43.03966],"type":"Point"}
}