{
  "type": "Feature",
  "properties": {
    "gn:admin1_code":"BRC",
    "gn:asciiname":"Lucici",
    "gn:country_code":"BA",
    "gn:dem":98,
    "gn:feature_class":"P",
    "gn:feature_code":"PPL",
    "gn:name":"Lu\u0107i\u0107i",
    "gn:population":0,
    "gn:timezone":"Europe/Sarajevo",
    "iso:country":"BA",
    "wof:name":"Lucici",
    "wof:placetype":"locality"
},
  "geometry": {"coordinates":[18.74298,44.86716],"type":"Point"}
}