{
  "type": "Feature",
  "properties": {
    "gn:admin1_code":"00",
    "gn:asciiname":"Mackovac",
    "gn:country_code":"BA",
    "gn:dem":397,
    "gn:feature_class":"P",
    "gn:feature_code":"PPL",
    "gn:name":"Ma\u010dkovac",
    "gn:population":0,
    "gn:timezone":"Europe/Sarajevo",
    "iso:country":"BA",
    "wof:name":"Mackovac",
    "wof:placetype":"locality"
},
  "geometry": {"coordinates":[18.55994,44.35376],"type":"Point"}
}