{
  "type": "Feature",
  "properties": {
    "gn:admin1_code":"02",
    "gn:asciiname":"Riteni",
    "gn:country_code":"BA",
    "gn:dem":584,
    "gn:feature_class":"P",
    "gn:feature_code":"PPL",
    "gn:name":"Riteni",
    "gn:population":0,
    "gn:timezone":"Europe/Sarajevo",
    "iso:country":"BA",
    "wof:name":"Riteni",
    "wof:placetype":"locality"
},
  "geometry": {"coordinates":[16.81279,45.02694],"type":"Point"}
}