{
  "type": "Feature",
  "properties": {
    "gn:admin1_code":"01",
    "gn:asciiname":"Mostarska Vrata",
    "gn:country_code":"BA",
    "gn:dem":190,
    "gn:feature_class":"P",
    "gn:feature_code":"PPL",
    "gn:name":"Mostarska Vrata",
    "gn:population":0,
    "gn:timezone":"Europe/Sarajevo",
    "iso:country":"BA",
    "name:bos_x_preferred":[
        "Mostarska Vrata"
    ],
    "name:ceb_x_preferred":[
        "Mostarska Vrata"
    ],
    "name:fra_x_preferred":[
        "Mostarska Vrata"
    ],
    "name:hrv_x_preferred":[
        "Mostarska Vrata"
    ],
    "name:srp_x_preferred":[
        "\u041c\u043e\u0441\u0442\u0430\u0440\u0441\u043a\u0430 \u0412\u0440\u0430\u0442\u0430"
    ],
    "name:swe_x_preferred":[
        "Mostarska Vrata"
    ],
    "wof:name":"Mostarska Vrata",
    "wof:placetype":"locality"
},
  "geometry": {"coordinates":[17.56528,43.20167],"type":"Point"}
}