{
  "type": "Feature",
  "properties": {
    "gn:admin1_code":"01",
    "gn:asciiname":"Mostarska Vrata",
    "gn:country_code":"BA",
    "gn:dem":190,
    "gn:feature_class":"P",
    "gn:feature_code":"PPL",
    "gn:name":"Mostarska Vrata",
    "gn:population":0,
    "gn:timezone":"Europe/Sarajevo",
    "iso:country":"BA",
    "wof:name":"Mostarska Vrata",
    "wof:placetype":"locality"
},
  "geometry": {"coordinates":[17.56528,43.20167],"type":"Point"}
}