{
  "type": "Feature",
  "properties": {
    "gn:admin1_code":"02",
    "gn:asciiname":"Pavlovina",
    "gn:country_code":"BA",
    "gn:dem":565,
    "gn:feature_class":"P",
    "gn:feature_code":"PPL",
    "gn:name":"Pavlovina",
    "gn:population":0,
    "gn:timezone":"Europe/Sarajevo",
    "iso:country":"BA",
    "wof:name":"Pavlovina",
    "wof:placetype":"locality"
},
  "geometry": {"coordinates":[18.09127,43.11565],"type":"Point"}
}