{
  "type": "Feature",
  "properties": {
    "gn:admin1_code":"02",
    "gn:asciiname":"Srednji Busevic",
    "gn:country_code":"BA",
    "gn:dem":379,
    "gn:feature_class":"P",
    "gn:feature_code":"PPLL",
    "gn:name":"Srednji Bu\u0161evi\u0107",
    "gn:population":0,
    "gn:timezone":"Europe/Sarajevo",
    "iso:country":"BA",
    "name:ara_x_preferred":[
        "\u0633\u0631\u064a\u062f\u0646\u064a\u064a \u0628\u0648\u0634\u064a\u0641\u064a\u062a\u0634"
    ],
    "name:bos_x_preferred":[
        "Srednji Bu\u0161evi\u0107"
    ],
    "name:fra_x_preferred":[
        "Srednji Bu\u0161evi\u0107"
    ],
    "name:srp_x_preferred":[
        "\u0421\u0440\u0435\u0434\u045a\u0438 \u0411\u0443\u0448\u0435\u0432\u0438\u045b"
    ],
    "name:und_x_variant":[
        "Srednji Bu\u0161evi\u0107"
    ],
    "wof:name":"Srednji Busevic",
    "wof:placetype":"locality"
},
  "geometry": {"coordinates":[16.21799,44.95476],"type":"Point"}
}