{
  "type": "Feature",
  "properties": {
    "gn:admin1_code":"01",
    "gn:asciiname":"Muslimanska Jasenica",
    "gn:country_code":"BA",
    "gn:dem":388,
    "gn:feature_class":"P",
    "gn:feature_code":"PPL",
    "gn:name":"Muslimanska Jasenica",
    "gn:population":0,
    "gn:timezone":"Europe/Sarajevo",
    "iso:country":"BA",
    "wof:name":"Muslimanska Jasenica",
    "wof:placetype":"locality"
},
  "geometry": {"coordinates":[16.2586,44.835],"type":"Point"}
}