{
  "type": "Feature",
  "properties": {
    "gn:admin1_code":"02",
    "gn:asciiname":"Careve Vode",
    "gn:country_code":"BA",
    "gn:dem":1111,
    "gn:feature_class":"P",
    "gn:feature_code":"PPL",
    "gn:name":"Careve Vode",
    "gn:population":0,
    "gn:timezone":"Europe/Sarajevo",
    "iso:country":"BA",
    "wof:name":"Careve Vode",
    "wof:placetype":"locality"
},
  "geometry": {"coordinates":[18.62355,43.83289],"type":"Point"}
}