{
  "type": "Feature",
  "properties": {
    "gn:admin1_code":"02",
    "gn:asciiname":"Konjuhovci",
    "gn:country_code":"BA",
    "gn:dem":191,
    "gn:feature_class":"P",
    "gn:feature_code":"PPL",
    "gn:name":"Konjuhovci",
    "gn:population":0,
    "gn:timezone":"Europe/Sarajevo",
    "iso:country":"BA",
    "wof:name":"Konjuhovci",
    "wof:placetype":"locality"
},
  "geometry": {"coordinates":[17.65514,44.8808],"type":"Point"}
}