{
  "type": "Feature",
  "properties": {
    "gn:admin1_code":"02",
    "gn:asciiname":"Haluge",
    "gn:country_code":"BA",
    "gn:dem":818,
    "gn:feature_class":"P",
    "gn:feature_code":"PPL",
    "gn:name":"Haluge",
    "gn:population":0,
    "gn:timezone":"Europe/Sarajevo",
    "iso:country":"BA",
    "wof:name":"Haluge",
    "wof:placetype":"locality"
},
  "geometry": {"coordinates":[18.99575,43.89699],"type":"Point"}
}