{
  "type": "Feature",
  "properties": {
    "gn:admin1_code":"01",
    "gn:asciiname":"Parizevici",
    "gn:country_code":"BA",
    "gn:dem":551,
    "gn:feature_class":"P",
    "gn:feature_code":"PPL",
    "gn:name":"Pari\u017eevi\u0107i",
    "gn:population":0,
    "gn:timezone":"Europe/Sarajevo",
    "iso:country":"BA",
    "name:und_x_variant":[
        "Pari\u017eevi\u0107i"
    ],
    "wof:name":"Parizevici",
    "wof:placetype":"locality"
},
  "geometry": {"coordinates":[18.05843,43.94297],"type":"Point"}
}