{
  "type": "Feature",
  "properties": {
    "gn:admin1_code":"02",
    "gn:asciiname":"Begici",
    "gn:country_code":"BA",
    "gn:dem":412,
    "gn:feature_class":"P",
    "gn:feature_code":"PPL",
    "gn:name":"Begi\u0107i",
    "gn:population":0,
    "gn:timezone":"Europe/Sarajevo",
    "iso:country":"BA",
    "wof:name":"Begici",
    "wof:placetype":"locality"
},
  "geometry": {"coordinates":[16.61435,44.85827000000001],"type":"Point"}
}