{
  "type": "Feature",
  "properties": {
    "gn:admin1_code":"01",
    "gn:asciiname":"Arapcici",
    "gn:country_code":"BA",
    "gn:dem":191,
    "gn:feature_class":"P",
    "gn:feature_code":"PPL",
    "gn:name":"Arap\u010di\u0107i",
    "gn:population":0,
    "gn:timezone":"Europe/Sarajevo",
    "iso:country":"BA",
    "wof:name":"Arapcici",
    "wof:placetype":"locality"
},
  "geometry": {"coordinates":[18.5268,44.51196],"type":"Point"}
}