{
  "type": "Feature",
  "properties": {
    "gn:admin1_code":"02",
    "gn:asciiname":"Budinje",
    "gn:country_code":"BA",
    "gn:dem":952,
    "gn:feature_class":"P",
    "gn:feature_code":"PPL",
    "gn:name":"Budinje",
    "gn:population":0,
    "gn:timezone":"Europe/Sarajevo",
    "iso:country":"BA",
    "wof:name":"Budinje",
    "wof:placetype":"locality"
},
  "geometry": {"coordinates":[18.53694,42.6625],"type":"Point"}
}