{
  "type": "Feature",
  "properties": {
    "gn:admin1_code":"02",
    "gn:asciiname":"Susici",
    "gn:country_code":"BA",
    "gn:dem":228,
    "gn:feature_class":"P",
    "gn:feature_code":"PPL",
    "gn:name":"Su\u0161i\u0107i",
    "gn:population":0,
    "gn:timezone":"Europe/Sarajevo",
    "iso:country":"BA",
    "wof:name":"Susici",
    "wof:placetype":"locality"
},
  "geometry": {"coordinates":[18.01415,44.91252],"type":"Point"}
}