{
  "type": "Feature",
  "properties": {
    "gn:admin1_code":"01",
    "gn:asciiname":"Hapstici",
    "gn:country_code":"BA",
    "gn:dem":777,
    "gn:feature_class":"P",
    "gn:feature_code":"PPL",
    "gn:name":"Hapsti\u0107i",
    "gn:population":0,
    "gn:timezone":"Europe/Sarajevo",
    "iso:country":"BA",
    "name:und_x_variant":[
        "Hapsti\u0107i"
    ],
    "wof:name":"Hapstici",
    "wof:placetype":"locality"
},
  "geometry": {"coordinates":[17.51114,44.03574],"type":"Point"}
}