{
  "type": "Feature",
  "properties": {
    "gn:admin1_code":"01",
    "gn:asciiname":"Skakici",
    "gn:country_code":"BA",
    "gn:dem":309,
    "gn:feature_class":"P",
    "gn:feature_code":"PPL",
    "gn:name":"Skaki\u0107i",
    "gn:population":0,
    "gn:timezone":"Europe/Sarajevo",
    "iso:country":"BA",
    "wof:name":"Skakici",
    "wof:placetype":"locality"
},
  "geometry": {"coordinates":[15.83592,45.00611],"type":"Point"}
}