{
  "type": "Feature",
  "properties": {
    "gn:admin1_code":"01",
    "gn:asciiname":"Petkovici",
    "gn:country_code":"BA",
    "gn:dem":1108,
    "gn:feature_class":"P",
    "gn:feature_code":"PPL",
    "gn:name":"Petkovi\u0107i",
    "gn:population":0,
    "gn:timezone":"Europe/Sarajevo",
    "iso:country":"BA",
    "wof:name":"Petkovici",
    "wof:placetype":"locality"
},
  "geometry": {"coordinates":[16.43361,44.43],"type":"Point"}
}