{
  "type": "Feature",
  "properties": {
    "gn:admin1_code":"02",
    "gn:asciiname":"Gornje Grancarevo",
    "gn:country_code":"BA",
    "gn:dem":433,
    "gn:feature_class":"P",
    "gn:feature_code":"PPL",
    "gn:name":"Gornje Gran\u010darevo",
    "gn:population":0,
    "gn:timezone":"Europe/Sarajevo",
    "iso:country":"BA",
    "name:bos_x_preferred":[
        "Gornje Gran\u010darevo"
    ],
    "name:fra_x_preferred":[
        "Gornje Gran\u010darevo"
    ],
    "name:srp_x_preferred":[
        "\u0413\u043e\u0440\u045a\u0435 \u0413\u0440\u0430\u043d\u0447\u0430\u0440\u0435\u0432\u043e"
    ],
    "wof:name":"Gornje Grancarevo",
    "wof:placetype":"locality"
},
  "geometry": {"coordinates":[18.48342,42.72213],"type":"Point"}
}