{
  "type": "Feature",
  "properties": {
    "gn:admin1_code":"02",
    "gn:asciiname":"Zmijanjci",
    "gn:country_code":"BA",
    "gn:dem":183,
    "gn:feature_class":"P",
    "gn:feature_code":"PPL",
    "gn:name":"Zmijanjci",
    "gn:population":0,
    "gn:timezone":"Europe/Sarajevo",
    "iso:country":"BA",
    "wof:name":"Zmijanjci",
    "wof:placetype":"locality"
},
  "geometry": {"coordinates":[16.87667,45.11861],"type":"Point"}
}