{
  "type": "Feature",
  "properties": {
    "gn:admin1_code":"01",
    "gn:asciiname":"Oplecani",
    "gn:cc2":"BA",
    "gn:country_code":"BA",
    "gn:dem":884,
    "gn:feature_class":"P",
    "gn:feature_code":"PPL",
    "gn:name":"Ople\u0107ani",
    "gn:population":0,
    "gn:timezone":"Europe/Sarajevo",
    "iso:country":"BA",
    "name:bos_x_preferred":[
        "Ople\u0107ani"
    ],
    "name:ceb_x_preferred":[
        "Ople\u0107ani"
    ],
    "name:deu_x_preferred":[
        "Ople\u0107ani"
    ],
    "name:fra_x_preferred":[
        "Ople\u0107ani"
    ],
    "name:hrv_x_preferred":[
        "Ople\u0107ani"
    ],
    "name:srp_x_preferred":[
        "\u041e\u043f\u043b\u0435\u045b\u0430\u043d\u0438"
    ],
    "name:swe_x_preferred":[
        "Ople\u0107ani"
    ],
    "name:und_x_variant":[
        "Ople\u0107an",
        "Ople\u0107ani"
    ],
    "wof:name":"Oplecani",
    "wof:placetype":"locality"
},
  "geometry": {"coordinates":[17.27833,43.71639],"type":"Point"}
}