{
  "type": "Feature",
  "properties": {
    "gn:admin1_code":"02",
    "gn:asciiname":"Laniste",
    "gn:country_code":"BA",
    "gn:dem":83,
    "gn:feature_class":"P",
    "gn:feature_code":"PPL",
    "gn:name":"Lani\u0161te",
    "gn:population":0,
    "gn:timezone":"Europe/Sarajevo",
    "iso:country":"BA",
    "wof:name":"Laniste",
    "wof:placetype":"locality"
},
  "geometry": {"coordinates":[19.27049,44.8096],"type":"Point"}
}