{
  "type": "Feature",
  "properties": {
    "gn:admin1_code":"02",
    "gn:asciiname":"Kamenjaca",
    "gn:country_code":"BA",
    "gn:dem":1137,
    "gn:feature_class":"P",
    "gn:feature_code":"PPL",
    "gn:name":"Kamenja\u010da",
    "gn:population":0,
    "gn:timezone":"Europe/Sarajevo",
    "iso:country":"BA",
    "wof:name":"Kamenjaca",
    "wof:placetype":"locality"
},
  "geometry": {"coordinates":[18.87145,43.39125],"type":"Point"}
}