{
  "type": "Feature",
  "properties": {
    "gn:admin1_code":"02",
    "gn:asciiname":"Podgreda",
    "gn:country_code":"BA",
    "gn:dem":598,
    "gn:feature_class":"P",
    "gn:feature_code":"PPL",
    "gn:name":"Podgreda",
    "gn:population":0,
    "gn:timezone":"Europe/Sarajevo",
    "iso:country":"BA",
    "wof:name":"Podgreda",
    "wof:placetype":"locality"
},
  "geometry": {"coordinates":[18.01008,42.97121],"type":"Point"}
}