{
  "type": "Feature",
  "properties": {
    "gn:admin1_code":"02",
    "gn:asciiname":"Turalici",
    "gn:country_code":"BA",
    "gn:dem":1147,
    "gn:feature_class":"P",
    "gn:feature_code":"PPL",
    "gn:name":"Turali\u0107i",
    "gn:population":0,
    "gn:timezone":"Europe/Sarajevo",
    "iso:country":"BA",
    "wof:name":"Turalici",
    "wof:placetype":"locality"
},
  "geometry": {"coordinates":[18.73005,43.85964],"type":"Point"}
}