{
  "type": "Feature",
  "properties": {
    "gn:admin1_code":"01",
    "gn:asciiname":"Busca",
    "gn:country_code":"BA",
    "gn:dem":675,
    "gn:feature_class":"P",
    "gn:feature_code":"PPL",
    "gn:name":"Bu\u0161\u0107a",
    "gn:population":0,
    "gn:timezone":"Europe/Sarajevo",
    "iso:country":"BA",
    "name:azb_x_preferred":[
        "\u0628\u0648\u0633\u06a9\u0627"
    ],
    "name:bel_x_preferred":[
        "\u0411\u0443\u0441\u043a\u0430"
    ],
    "name:bul_x_preferred":[
        "\u0411\u0443\u0441\u043a\u0430"
    ],
    "name:cat_x_preferred":[
        "Buscha"
    ],
    "name:ceb_x_preferred":[
        "Busca"
    ],
    "name:deu_x_preferred":[
        "Busca"
    ],
    "name:epo_x_preferred":[
        "Busca"
    ],
    "name:eus_x_preferred":[
        "Busca"
    ],
    "name:fas_x_preferred":[
        "\u0628\u0648\u0633\u06a9\u0627"
    ],
    "name:fra_x_preferred":[
        "Busca"
    ],
    "name:hun_x_preferred":[
        "Busca"
    ],
    "name:hye_x_preferred":[
        "\u0532\u0578\u0582\u057d\u056f\u0561"
    ],
    "name:ind_x_preferred":[
        "Busca"
    ],
    "name:ita_x_preferred":[
        "Busca"
    ],
    "name:jpn_x_preferred":[
        "\u30d6\u30b9\u30ab"
    ],
    "name:kaz_x_preferred":[
        "\u0411\u0443\u0441\u043a\u0430"
    ],
    "name:lat_x_preferred":[
        "Busca"
    ],
    "name:lmo_x_preferred":[
        "Busca"
    ],
    "name:msa_x_preferred":[
        "Busca"
    ],
    "name:nap_x_preferred":[
        "Busca"
    ],
    "name:nld_x_preferred":[
        "Busca"
    ],
    "name:oci_x_preferred":[
        "Buscha"
    ],
    "name:pms_x_preferred":[
        "Busca"
    ],
    "name:pol_x_preferred":[
        "Busca"
    ],
    "name:por_x_preferred":[
        "Busca"
    ],
    "name:ron_x_preferred":[
        "Busca"
    ],
    "name:rus_x_preferred":[
        "\u0411\u0443\u0441\u043a\u0430"
    ],
    "name:scn_x_preferred":[
        "Busca"
    ],
    "name:spa_x_preferred":[
        "Busca"
    ],
    "name:srp_x_preferred":[
        "\u0411\u0443\u0441\u043a\u0430"
    ],
    "name:tgl_x_preferred":[
        "Busca"
    ],
    "name:tur_x_preferred":[
        "Busca"
    ],
    "name:ukr_x_preferred":[
        "\u0411\u0443\u0441\u043a\u0430"
    ],
    "name:uzb_x_preferred":[
        "Busca"
    ],
    "name:vie_x_preferred":[
        "Busca"
    ],
    "name:vol_x_preferred":[
        "Busca"
    ],
    "name:war_x_preferred":[
        "Busca"
    ],
    "name:zho_x_preferred":[
        "\u5e03\u65af\u5361"
    ],
    "wof:name":"Busca",
    "wof:placetype":"locality"
},
  "geometry": {"coordinates":[18.38556,43.87889000000001],"type":"Point"}
}