{
  "type": "Feature",
  "properties": {
    "gn:admin1_code":"01",
    "gn:asciiname":"Busca",
    "gn:country_code":"BA",
    "gn:dem":675,
    "gn:feature_class":"P",
    "gn:feature_code":"PPL",
    "gn:name":"Bu\u0161\u0107a",
    "gn:population":0,
    "gn:timezone":"Europe/Sarajevo",
    "iso:country":"BA",
    "wof:name":"Busca",
    "wof:placetype":"locality"
},
  "geometry": {"coordinates":[18.38556,43.87889000000001],"type":"Point"}
}