{
  "type": "Feature",
  "properties": {
    "gn:admin1_code":"01",
    "gn:asciiname":"Beskeri",
    "gn:country_code":"BA",
    "gn:dem":1195,
    "gn:feature_class":"P",
    "gn:feature_code":"PPL",
    "gn:name":"Be\u0161keri",
    "gn:population":0,
    "gn:timezone":"Europe/Sarajevo",
    "iso:country":"BA",
    "wof:name":"Beskeri",
    "wof:placetype":"locality"
},
  "geometry": {"coordinates":[17.46845,43.82887],"type":"Point"}
}