{
  "type": "Feature",
  "properties": {
    "gn:admin1_code":"02",
    "gn:asciiname":"Budici",
    "gn:country_code":"BA",
    "gn:dem":785,
    "gn:feature_class":"P",
    "gn:feature_code":"PPL",
    "gn:name":"Budi\u0107i",
    "gn:population":0,
    "gn:timezone":"Europe/Sarajevo",
    "iso:country":"BA",
    "wof:name":"Budici",
    "wof:placetype":"locality"
},
  "geometry": {"coordinates":[17.33382000000001,44.47571],"type":"Point"}
}