{
  "type": "Feature",
  "properties": {
    "gn:admin1_code":"01",
    "gn:asciiname":"Zagorice",
    "gn:country_code":"BA",
    "gn:dem":555,
    "gn:feature_class":"P",
    "gn:feature_code":"PPLL",
    "gn:name":"Zagorice",
    "gn:population":0,
    "gn:timezone":"Europe/Sarajevo",
    "iso:country":"BA",
    "wof:name":"Zagorice",
    "wof:placetype":"locality"
},
  "geometry": {"coordinates":[18.13534,43.94711],"type":"Point"}
}