{
  "type": "Feature",
  "properties": {
    "gn:admin1_code":"02",
    "gn:asciiname":"Brijestovo",
    "gn:country_code":"BA",
    "gn:dem":108,
    "gn:feature_class":"P",
    "gn:feature_code":"PPLL",
    "gn:name":"Brijestovo",
    "gn:population":0,
    "gn:timezone":"Europe/Sarajevo",
    "iso:country":"BA",
    "name:und_x_variant":[
        "Brestovo",
        "Brijestovo"
    ],
    "wof:name":"Brijestovo",
    "wof:placetype":"locality"
},
  "geometry": {"coordinates":[18.22525,44.94559],"type":"Point"}
}