{
  "type": "Feature",
  "properties": {
    "gn:admin1_code":"02",
    "gn:asciiname":"Micici",
    "gn:country_code":"BA",
    "gn:dem":246,
    "gn:feature_class":"P",
    "gn:feature_code":"PPL",
    "gn:name":"Mi\u0107i\u0107i",
    "gn:population":0,
    "gn:timezone":"Europe/Sarajevo",
    "iso:country":"BA",
    "wof:name":"Micici",
    "wof:placetype":"locality"
},
  "geometry": {"coordinates":[18.18679,44.80064],"type":"Point"}
}