{
  "type": "Feature",
  "properties": {
    "gn:admin1_code":"01",
    "gn:asciiname":"Buncevac",
    "gn:country_code":"BA",
    "gn:dem":892,
    "gn:feature_class":"P",
    "gn:feature_code":"PPLL",
    "gn:name":"Bun\u010devac",
    "gn:population":0,
    "gn:timezone":"Europe/Sarajevo",
    "iso:country":"BA",
    "name:bos_x_preferred":[
        "Bun\u010devac"
    ],
    "name:fra_x_preferred":[
        "Bun\u010devac"
    ],
    "name:srp_x_preferred":[
        "\u0411\u0443\u043d\u0447\u0435\u0432\u0430\u0446"
    ],
    "wof:name":"Buncevac",
    "wof:placetype":"locality"
},
  "geometry": {"coordinates":[16.57443,44.31195],"type":"Point"}
}