{
  "type": "Feature",
  "properties": {
    "gn:admin1_code":"01",
    "gn:asciiname":"Sabljici",
    "gn:country_code":"BA",
    "gn:dem":733,
    "gn:feature_class":"P",
    "gn:feature_code":"PPL",
    "gn:name":"Sablji\u0107i",
    "gn:population":0,
    "gn:timezone":"Europe/Sarajevo",
    "iso:country":"BA",
    "wof:name":"Sabljici",
    "wof:placetype":"locality"
},
  "geometry": {"coordinates":[16.34336,44.35173],"type":"Point"}
}