{
  "type": "Feature",
  "properties": {
    "gn:admin1_code":"01",
    "gn:asciiname":"Borenovici",
    "gn:country_code":"BA",
    "gn:dem":512,
    "gn:feature_class":"P",
    "gn:feature_code":"PPL",
    "gn:name":"Borenovi\u0107i",
    "gn:population":0,
    "gn:timezone":"Europe/Sarajevo",
    "iso:country":"BA",
    "wof:name":"Borenovici",
    "wof:placetype":"locality"
},
  "geometry": {"coordinates":[16.78146,44.71896],"type":"Point"}
}