{
  "type": "Feature",
  "properties": {
    "gn:admin1_code":"01",
    "gn:asciiname":"Curkovici",
    "gn:country_code":"BA",
    "gn:dem":619,
    "gn:feature_class":"P",
    "gn:feature_code":"PPL",
    "gn:name":"\u0106urkovi\u0107i",
    "gn:population":0,
    "gn:timezone":"Europe/Sarajevo",
    "iso:country":"BA",
    "wof:name":"Curkovici",
    "wof:placetype":"locality"
},
  "geometry": {"coordinates":[17.0182,43.58161],"type":"Point"}
}