{
  "type": "Feature",
  "properties": {
    "gn:admin1_code":"02",
    "gn:asciiname":"Ljeskovac",
    "gn:country_code":"BA",
    "gn:dem":902,
    "gn:feature_class":"P",
    "gn:feature_code":"PPL",
    "gn:name":"Ljeskovac",
    "gn:population":0,
    "gn:timezone":"Europe/Sarajevo",
    "iso:country":"BA",
    "wof:name":"Ljeskovac",
    "wof:placetype":"locality"
},
  "geometry": {"coordinates":[18.46111,42.57933],"type":"Point"}
}