{
  "type": "Feature",
  "properties": {
    "gn:admin1_code":"01",
    "gn:asciiname":"Mlake",
    "gn:country_code":"BA",
    "gn:dem":699,
    "gn:feature_class":"P",
    "gn:feature_code":"PPL",
    "gn:name":"Mlake",
    "gn:population":0,
    "gn:timezone":"Europe/Sarajevo",
    "iso:country":"BA",
    "name:bos_x_preferred":[
        "Mlake"
    ],
    "name:ceb_x_preferred":[
        "Mlake"
    ],
    "name:nld_x_preferred":[
        "Mlake"
    ],
    "name:slv_x_preferred":[
        "Mlake"
    ],
    "name:srp_x_preferred":[
        "\u041c\u043b\u0430\u043a\u0435"
    ],
    "name:swe_x_preferred":[
        "Mlake"
    ],
    "wof:name":"Mlake",
    "wof:placetype":"locality"
},
  "geometry": {"coordinates":[17.96361,43.97972],"type":"Point"}
}