{
  "type": "Feature",
  "properties": {
    "gn:admin1_code":"02",
    "gn:asciiname":"Porjecina",
    "gn:country_code":"BA",
    "gn:dem":209,
    "gn:feature_class":"P",
    "gn:feature_code":"PPLL",
    "gn:name":"Porje\u010dina",
    "gn:population":0,
    "gn:timezone":"Europe/Sarajevo",
    "iso:country":"BA",
    "name:und_x_variant":[
        "Porje\u010dani",
        "Porje\u010dina"
    ],
    "wof:name":"Porjecina",
    "wof:placetype":"locality"
},
  "geometry": {"coordinates":[18.39131,44.59774],"type":"Point"}
}