{
  "type": "Feature",
  "properties": {
    "gn:admin1_code":"02",
    "gn:asciiname":"Porjecina",
    "gn:country_code":"BA",
    "gn:dem":209,
    "gn:feature_class":"P",
    "gn:feature_code":"PPLL",
    "gn:name":"Porje\u010dina",
    "gn:population":0,
    "gn:timezone":"Europe/Sarajevo",
    "iso:country":"BA",
    "name:bos_x_preferred":[
        "Porje\u010dina"
    ],
    "name:ceb_x_preferred":[
        "Porje\u010dina"
    ],
    "name:fra_x_preferred":[
        "Porje\u010dina"
    ],
    "name:hrv_x_preferred":[
        "Porje\u010dina"
    ],
    "name:srp_x_preferred":[
        "\u041f\u043e\u0440\u0458\u0435\u0447\u0438\u043d\u0430"
    ],
    "name:swe_x_preferred":[
        "Porje\u010dina"
    ],
    "name:und_x_variant":[
        "Porje\u010dani",
        "Porje\u010dina"
    ],
    "wof:name":"Porjecina",
    "wof:placetype":"locality"
},
  "geometry": {"coordinates":[18.39131,44.59774],"type":"Point"}
}