{
  "type": "Feature",
  "properties": {
    "gn:admin1_code":"01",
    "gn:asciiname":"Brezici",
    "gn:country_code":"BA",
    "gn:dem":512,
    "gn:feature_class":"P",
    "gn:feature_code":"PPL",
    "gn:name":"Brezi\u0107i",
    "gn:population":0,
    "gn:timezone":"Europe/Sarajevo",
    "iso:country":"BA",
    "wof:name":"Brezici",
    "wof:placetype":"locality"
},
  "geometry": {"coordinates":[18.27974,44.5026],"type":"Point"}
}