{
  "type": "Feature",
  "properties": {
    "gn:admin1_code":"01",
    "gn:asciiname":"Zapece",
    "gn:country_code":"BA",
    "gn:dem":738,
    "gn:feature_class":"P",
    "gn:feature_code":"PPL",
    "gn:name":"Zape\u0107e",
    "gn:population":0,
    "gn:timezone":"Europe/Sarajevo",
    "iso:country":"BA",
    "wof:name":"Zapece",
    "wof:placetype":"locality"
},
  "geometry": {"coordinates":[17.42697,44.40382],"type":"Point"}
}