{
  "type": "Feature",
  "properties": {
    "gn:admin1_code":"02",
    "gn:asciiname":"Lokvari",
    "gn:country_code":"BA",
    "gn:dem":95,
    "gn:feature_class":"P",
    "gn:feature_code":"PPL",
    "gn:name":"Lokvari",
    "gn:population":0,
    "gn:timezone":"Europe/Sarajevo",
    "iso:country":"BA",
    "name:bos_x_preferred":[
        "Lokvari"
    ],
    "name:ceb_x_preferred":[
        "Lokvari"
    ],
    "name:fra_x_preferred":[
        "Lokvari"
    ],
    "name:hrv_x_preferred":[
        "Lokvari"
    ],
    "name:rus_x_preferred":[
        "\u041b\u043e\u043a\u0432\u0430\u0440\u0438"
    ],
    "name:slv_x_preferred":[
        "Lokvari"
    ],
    "name:srp_x_preferred":[
        "\u041b\u043e\u043a\u0432\u0430\u0440\u0438"
    ],
    "name:swe_x_preferred":[
        "Lokvari"
    ],
    "wof:name":"Lokvari",
    "wof:placetype":"locality"
},
  "geometry": {"coordinates":[17.27877,45.05726],"type":"Point"}
}