{
  "type": "Feature",
  "properties": {
    "gn:admin1_code":"02",
    "gn:asciiname":"Kaliman",
    "gn:country_code":"BA",
    "gn:dem":869,
    "gn:feature_class":"P",
    "gn:feature_code":"PPL",
    "gn:name":"Kaliman",
    "gn:population":0,
    "gn:timezone":"Europe/Sarajevo",
    "iso:country":"BA",
    "name:deu_x_preferred":[
        "Kaliman"
    ],
    "name:fra_x_preferred":[
        "Kaliman"
    ],
    "name:jpn_x_preferred":[
        "\u30ab\u30ea\u30de\u30f3"
    ],
    "wof:name":"Kaliman",
    "wof:placetype":"locality"
},
  "geometry": {"coordinates":[18.74833,43.38472],"type":"Point"}
}