{
  "type": "Feature",
  "properties": {
    "gn:admin1_code":"01",
    "gn:asciiname":"Mrakov Potok",
    "gn:country_code":"BA",
    "gn:dem":526,
    "gn:feature_class":"P",
    "gn:feature_code":"PPL",
    "gn:name":"Mrakov Potok",
    "gn:population":0,
    "gn:timezone":"Europe/Sarajevo",
    "iso:country":"BA",
    "wof:name":"Mrakov Potok",
    "wof:placetype":"locality"
},
  "geometry": {"coordinates":[18.19882,44.07169],"type":"Point"}
}