{
  "type": "Feature",
  "properties": {
    "gn:admin1_code":"01",
    "gn:asciiname":"Cegari",
    "gn:country_code":"BA",
    "gn:dem":1068,
    "gn:feature_class":"P",
    "gn:feature_code":"PPL",
    "gn:name":"\u010cegari",
    "gn:population":0,
    "gn:timezone":"Europe/Sarajevo",
    "iso:country":"BA",
    "wof:name":"Cegari",
    "wof:placetype":"locality"
},
  "geometry": {"coordinates":[16.65598,44.24173],"type":"Point"}
}