{
  "type": "Feature",
  "properties": {
    "gn:admin1_code":"02",
    "gn:asciiname":"Klecak",
    "gn:country_code":"BA",
    "gn:dem":561,
    "gn:feature_class":"P",
    "gn:feature_code":"PPL",
    "gn:name":"Kle\u010dak",
    "gn:population":0,
    "gn:timezone":"Europe/Sarajevo",
    "iso:country":"BA",
    "wof:name":"Klecak",
    "wof:placetype":"locality"
},
  "geometry": {"coordinates":[18.1544,43.10153],"type":"Point"}
}