{
  "type": "Feature",
  "properties": {
    "gn:admin1_code":"02",
    "gn:asciiname":"Tipure",
    "gn:country_code":"BA",
    "gn:dem":168,
    "gn:feature_class":"P",
    "gn:feature_code":"PPL",
    "gn:name":"Tipure",
    "gn:population":0,
    "gn:timezone":"Europe/Sarajevo",
    "iso:country":"BA",
    "wof:name":"Tipure",
    "wof:placetype":"locality"
},
  "geometry": {"coordinates":[17.99833,44.83611],"type":"Point"}
}