{
  "type": "Feature",
  "properties": {
    "gn:admin1_code":"01",
    "gn:asciiname":"Tihomislje",
    "gn:country_code":"BA",
    "gn:dem":679,
    "gn:feature_class":"P",
    "gn:feature_code":"PPLL",
    "gn:name":"Tihomi\u0161lje",
    "gn:population":0,
    "gn:timezone":"Europe/Sarajevo",
    "iso:country":"BA",
    "wof:name":"Tihomislje",
    "wof:placetype":"locality"
},
  "geometry": {"coordinates":[17.52523,43.96001],"type":"Point"}
}