{
  "type": "Feature",
  "properties": {
    "gn:admin1_code":"BRC",
    "gn:asciiname":"Gluhakovac",
    "gn:country_code":"BA",
    "gn:dem":93,
    "gn:feature_class":"P",
    "gn:feature_code":"PPL",
    "gn:name":"Gluhakovac",
    "gn:population":0,
    "gn:timezone":"Europe/Sarajevo",
    "iso:country":"BA",
    "wof:name":"Gluhakovac",
    "wof:placetype":"locality"
},
  "geometry": {"coordinates":[18.77589,44.88499],"type":"Point"}
}