{
  "type": "Feature",
  "properties": {
    "gn:admin1_code":"02",
    "gn:asciiname":"Zemanica",
    "gn:country_code":"BA",
    "gn:dem":1071,
    "gn:feature_class":"P",
    "gn:feature_code":"PPL",
    "gn:name":"Zemanica",
    "gn:population":0,
    "gn:timezone":"Europe/Sarajevo",
    "iso:country":"BA",
    "wof:name":"Zemanica",
    "wof:placetype":"locality"
},
  "geometry": {"coordinates":[18.51924,43.87754],"type":"Point"}
}