{
  "type": "Feature",
  "properties": {
    "gn:admin1_code":"01",
    "gn:asciiname":"Core",
    "gn:country_code":"BA",
    "gn:dem":105,
    "gn:feature_class":"P",
    "gn:feature_code":"PPL",
    "gn:name":"\u010core",
    "gn:population":0,
    "gn:timezone":"Europe/Sarajevo",
    "iso:country":"BA",
    "name:ces_x_preferred":[
        "Core"
    ],
    "name:deu_x_preferred":[
        "Core"
    ],
    "name:fra_x_preferred":[
        "Core"
    ],
    "name:heb_x_preferred":[
        "\u05dc\u05d9\u05d1\u05d4"
    ],
    "name:ita_x_preferred":[
        "Core"
    ],
    "name:new_x_preferred":[
        "\u0928\u093f\u092f\u094b\u0921\u093e\u0907\u092e\u093f\u092f\u092e"
    ],
    "name:nld_x_preferred":[
        "Core"
    ],
    "name:nor_x_preferred":[
        "Core"
    ],
    "name:pol_x_preferred":[
        "Core"
    ],
    "name:por_x_preferred":[
        "Core"
    ],
    "name:slk_x_preferred":[
        "Core"
    ],
    "name:spa_x_preferred":[
        "Core"
    ],
    "name:tha_x_preferred":[
        "\u0e04\u0e2d\u0e23\u0e4c"
    ],
    "name:vie_x_preferred":[
        "L\u00f5i"
    ],
    "name:zho_x_preferred":[
        "Core"
    ],
    "wof:name":"Core",
    "wof:placetype":"locality"
},
  "geometry": {"coordinates":[17.83434,43.04316],"type":"Point"}
}