{
  "type": "Feature",
  "properties": {
    "gn:admin1_code":"01",
    "gn:asciiname":"Core",
    "gn:country_code":"BA",
    "gn:dem":105,
    "gn:feature_class":"P",
    "gn:feature_code":"PPL",
    "gn:name":"\u010core",
    "gn:population":0,
    "gn:timezone":"Europe/Sarajevo",
    "iso:country":"BA",
    "wof:name":"Core",
    "wof:placetype":"locality"
},
  "geometry": {"coordinates":[17.83434,43.04316],"type":"Point"}
}