{
  "type": "Feature",
  "properties": {
    "gn:admin1_code":"02",
    "gn:asciiname":"Romici",
    "gn:country_code":"BA",
    "gn:dem":276,
    "gn:feature_class":"P",
    "gn:feature_code":"PPL",
    "gn:name":"Romi\u0107i",
    "gn:population":0,
    "gn:timezone":"Europe/Sarajevo",
    "iso:country":"BA",
    "wof:name":"Romici",
    "wof:placetype":"locality"
},
  "geometry": {"coordinates":[16.71278,45.0347],"type":"Point"}
}