{
  "type": "Feature",
  "properties": {
    "gn:admin1_code":"01",
    "gn:asciiname":"Cive",
    "gn:country_code":"BA",
    "gn:dem":338,
    "gn:feature_class":"P",
    "gn:feature_code":"PPL",
    "gn:name":"\u0106ive",
    "gn:population":0,
    "gn:timezone":"Europe/Sarajevo",
    "iso:country":"BA",
    "wof:name":"Cive",
    "wof:placetype":"locality"
},
  "geometry": {"coordinates":[18.7697,44.48075],"type":"Point"}
}