{
  "type": "Feature",
  "properties": {
    "gn:admin1_code":"02",
    "gn:asciiname":"Milosevici",
    "gn:country_code":"BA",
    "gn:dem":242,
    "gn:feature_class":"P",
    "gn:feature_code":"PPL",
    "gn:name":"Milo\u0161evi\u0107i",
    "gn:population":0,
    "gn:timezone":"Europe/Sarajevo",
    "iso:country":"BA",
    "wof:name":"Milosevici",
    "wof:placetype":"locality"
},
  "geometry": {"coordinates":[16.68153,44.90061],"type":"Point"}
}