{
  "type": "Feature",
  "properties": {
    "gn:admin1_code":"02",
    "gn:asciiname":"Potocani",
    "gn:country_code":"BA",
    "gn:dem":219,
    "gn:feature_class":"P",
    "gn:feature_code":"PPL",
    "gn:name":"Poto\u010dani",
    "gn:population":0,
    "gn:timezone":"Europe/Sarajevo",
    "iso:country":"BA",
    "wof:name":"Potocani",
    "wof:placetype":"locality"
},
  "geometry": {"coordinates":[18.09289,44.66869000000001],"type":"Point"}
}