{
  "type": "Feature",
  "properties": {
    "gn:admin1_code":"01",
    "gn:asciiname":"Perici",
    "gn:country_code":"BA",
    "gn:dem":663,
    "gn:feature_class":"P",
    "gn:feature_code":"PPL",
    "gn:name":"Peri\u0107i",
    "gn:population":0,
    "gn:timezone":"Europe/Sarajevo",
    "iso:country":"BA",
    "wof:name":"Perici",
    "wof:placetype":"locality"
},
  "geometry": {"coordinates":[18.40699,43.93665],"type":"Point"}
}