{
  "type": "Feature",
  "properties": {
    "gn:admin1_code":"01",
    "gn:asciiname":"Gornja Rovna",
    "gn:country_code":"BA",
    "gn:dem":602,
    "gn:feature_class":"P",
    "gn:feature_code":"PPL",
    "gn:name":"Gornja Rovna",
    "gn:population":0,
    "gn:timezone":"Europe/Sarajevo",
    "iso:country":"BA",
    "name:bos_x_preferred":[
        "Gornja Rovna"
    ],
    "name:fra_x_preferred":[
        "Gornja Rovna"
    ],
    "name:und_x_variant":[
        "Rovna",
        "Gornja Rovna"
    ],
    "wof:name":"Gornja Rovna",
    "wof:placetype":"locality"
},
  "geometry": {"coordinates":[17.81946,44.11893],"type":"Point"}
}