{
  "type": "Feature",
  "properties": {
    "gn:admin1_code":"01",
    "gn:asciiname":"Donji Vranjevici",
    "gn:country_code":"BA",
    "gn:dem":291,
    "gn:feature_class":"P",
    "gn:feature_code":"PPL",
    "gn:name":"Donji Vranjevi\u0107i",
    "gn:population":0,
    "gn:timezone":"Europe/Sarajevo",
    "iso:country":"BA",
    "wof:name":"Donji Vranjevici",
    "wof:placetype":"locality"
},
  "geometry": {"coordinates":[17.91621,43.24307],"type":"Point"}
}