{
  "type": "Feature",
  "properties": {
    "gn:admin1_code":"02",
    "gn:asciiname":"Prosevica",
    "gn:country_code":"BA",
    "gn:dem":86,
    "gn:feature_class":"P",
    "gn:feature_code":"PPL",
    "gn:name":"Pro\u0161evica",
    "gn:population":0,
    "gn:timezone":"Europe/Sarajevo",
    "iso:country":"BA",
    "wof:name":"Prosevica",
    "wof:placetype":"locality"
},
  "geometry": {"coordinates":[17.40157,45.10836],"type":"Point"}
}