{
  "type": "Feature",
  "properties": {
    "gn:admin1_code":"02",
    "gn:asciiname":"Cukovici",
    "gn:country_code":"BA",
    "gn:dem":560,
    "gn:feature_class":"P",
    "gn:feature_code":"PPL",
    "gn:name":"\u010cukovi\u0107i",
    "gn:population":0,
    "gn:timezone":"Europe/Sarajevo",
    "iso:country":"BA",
    "wof:name":"Cukovici",
    "wof:placetype":"locality"
},
  "geometry": {"coordinates":[18.38472,42.90564000000001],"type":"Point"}
}