{
  "type": "Feature",
  "properties": {
    "gn:admin1_code":"01",
    "gn:asciiname":"Gromile",
    "gn:country_code":"BA",
    "gn:dem":421,
    "gn:feature_class":"P",
    "gn:feature_code":"PPL",
    "gn:name":"Gromile",
    "gn:population":0,
    "gn:timezone":"Europe/Sarajevo",
    "iso:country":"BA",
    "wof:name":"Gromile",
    "wof:placetype":"locality"
},
  "geometry": {"coordinates":[17.29598,44.24223],"type":"Point"}
}