{
  "type": "Feature",
  "properties": {
    "gn:admin1_code":"01",
    "gn:asciiname":"Curtovina",
    "gn:country_code":"BA",
    "gn:dem":990,
    "gn:feature_class":"P",
    "gn:feature_code":"PPL",
    "gn:name":"\u0106urtovina",
    "gn:population":0,
    "gn:timezone":"Europe/Sarajevo",
    "iso:country":"BA",
    "wof:name":"Curtovina",
    "wof:placetype":"locality"
},
  "geometry": {"coordinates":[17.31579,44.2664],"type":"Point"}
}