{
  "type": "Feature",
  "properties": {
    "gn:admin1_code":"02",
    "gn:asciiname":"Odzak",
    "gn:country_code":"BA",
    "gn:dem":1065,
    "gn:feature_class":"P",
    "gn:feature_code":"PPL",
    "gn:name":"Od\u017eak",
    "gn:population":0,
    "gn:timezone":"Europe/Sarajevo",
    "iso:country":"BA",
    "wof:name":"Odzak",
    "wof:placetype":"locality"
},
  "geometry": {"coordinates":[18.4825,43.50611],"type":"Point"}
}