{
  "type": "Feature",
  "properties": {
    "gn:admin1_code":"01",
    "gn:asciiname":"Gnusi",
    "gn:country_code":"BA",
    "gn:dem":419,
    "gn:feature_class":"P",
    "gn:feature_code":"PPL",
    "gn:name":"Gnusi",
    "gn:population":0,
    "gn:timezone":"Europe/Sarajevo",
    "iso:country":"BA",
    "wof:name":"Gnusi",
    "wof:placetype":"locality"
},
  "geometry": {"coordinates":[17.9461,44.18077],"type":"Point"}
}