{
  "type": "Feature",
  "properties": {
    "gn:admin1_code":"01",
    "gn:asciiname":"Trn",
    "gn:country_code":"BA",
    "gn:dem":272,
    "gn:feature_class":"P",
    "gn:feature_code":"PPLL",
    "gn:name":"Trn",
    "gn:population":0,
    "gn:timezone":"Europe/Sarajevo",
    "iso:country":"BA",
    "wof:name":"Trn",
    "wof:placetype":"locality"
},
  "geometry": {"coordinates":[17.56966,43.3795],"type":"Point"}
}