{
  "type": "Feature",
  "properties": {
    "gn:admin1_code":"01",
    "gn:asciiname":"Trn",
    "gn:country_code":"BA",
    "gn:dem":272,
    "gn:feature_class":"P",
    "gn:feature_code":"PPLL",
    "gn:name":"Trn",
    "gn:population":0,
    "gn:timezone":"Europe/Sarajevo",
    "iso:country":"BA",
    "name:bos_x_preferred":[
        "Trn"
    ],
    "name:ceb_x_preferred":[
        "Trn"
    ],
    "name:ces_x_preferred":[
        "Trn"
    ],
    "name:fra_x_preferred":[
        "Trn"
    ],
    "name:hrv_x_preferred":[
        "Trn"
    ],
    "name:hun_x_preferred":[
        "Trn"
    ],
    "name:pol_x_preferred":[
        "Trn"
    ],
    "name:rus_x_preferred":[
        "\u0422\u0440\u043d"
    ],
    "name:slv_x_preferred":[
        "Trn"
    ],
    "name:srp_x_preferred":[
        "\u0422\u0440\u043d"
    ],
    "name:swe_x_preferred":[
        "Trn"
    ],
    "wof:name":"Trn",
    "wof:placetype":"locality"
},
  "geometry": {"coordinates":[17.56966,43.3795],"type":"Point"}
}