{
  "type": "Feature",
  "properties": {
    "gn:admin1_code":"01",
    "gn:asciiname":"Gnjilica",
    "gn:country_code":"BA",
    "gn:dem":873,
    "gn:feature_class":"P",
    "gn:feature_code":"PPL",
    "gn:name":"Gnjilica",
    "gn:population":0,
    "gn:timezone":"Europe/Sarajevo",
    "iso:country":"BA",
    "name:ceb_x_preferred":[
        "Gnjilica"
    ],
    "name:fra_x_preferred":[
        "Gnjilica"
    ],
    "name:msa_x_preferred":[
        "Gnjilica"
    ],
    "name:nld_x_preferred":[
        "Gnjilica"
    ],
    "name:por_x_preferred":[
        "Gnjilica"
    ],
    "name:slv_x_preferred":[
        "Gnjilica"
    ],
    "name:srp_x_preferred":[
        "\u0413\u045a\u0438\u043b\u0438\u0446\u0430"
    ],
    "wof:name":"Gnjilica",
    "wof:placetype":"locality"
},
  "geometry": {"coordinates":[18.11806,43.56694],"type":"Point"}
}