{
  "type": "Feature",
  "properties": {
    "gn:admin1_code":"02",
    "gn:asciiname":"Krajcani",
    "gn:country_code":"BA",
    "gn:dem":264,
    "gn:feature_class":"P",
    "gn:feature_code":"PPL",
    "gn:name":"Kraj\u010dani",
    "gn:population":0,
    "gn:timezone":"Europe/Sarajevo",
    "iso:country":"BA",
    "wof:name":"Krajcani",
    "wof:placetype":"locality"
},
  "geometry": {"coordinates":[18.16297,44.79755],"type":"Point"}
}