{
  "type": "Feature",
  "properties": {
    "gn:admin1_code":"02",
    "gn:asciiname":"Meljan",
    "gn:country_code":"BA",
    "gn:dem":677,
    "gn:feature_class":"P",
    "gn:feature_code":"PPL",
    "gn:name":"Meljan",
    "gn:population":0,
    "gn:timezone":"Europe/Sarajevo",
    "iso:country":"BA",
    "wof:name":"Meljan",
    "wof:placetype":"locality"
},
  "geometry": {"coordinates":[19.33682,43.70748],"type":"Point"}
}