{
  "type": "Feature",
  "properties": {
    "gn:admin1_code":"02",
    "gn:asciiname":"Veselica",
    "gn:country_code":"BA",
    "gn:dem":753,
    "gn:feature_class":"P",
    "gn:feature_code":"PPL",
    "gn:name":"Veselica",
    "gn:population":0,
    "gn:timezone":"Europe/Sarajevo",
    "iso:country":"BA",
    "wof:name":"Veselica",
    "wof:placetype":"locality"
},
  "geometry": {"coordinates":[18.69661,43.3859],"type":"Point"}
}