{
  "type": "Feature",
  "properties": {
    "gn:admin1_code":"01",
    "gn:asciiname":"Malo Visnjevo",
    "gn:country_code":"BA",
    "gn:dem":857,
    "gn:feature_class":"P",
    "gn:feature_code":"PPL",
    "gn:name":"Malo Vi\u0161njevo",
    "gn:population":0,
    "gn:timezone":"Europe/Sarajevo",
    "iso:country":"BA",
    "wof:name":"Malo Visnjevo",
    "wof:placetype":"locality"
},
  "geometry": {"coordinates":[17.71561,44.30015],"type":"Point"}
}