{
  "type": "Feature",
  "properties": {
    "gn:admin1_code":"02",
    "gn:asciiname":"Bare",
    "gn:country_code":"BA",
    "gn:dem":87,
    "gn:feature_class":"P",
    "gn:feature_code":"PPL",
    "gn:name":"Bare",
    "gn:population":0,
    "gn:timezone":"Europe/Sarajevo",
    "iso:country":"BA",
    "wof:name":"Bare",
    "wof:placetype":"locality"
},
  "geometry": {"coordinates":[18.67878,44.92607],"type":"Point"}
}