{
  "type": "Feature",
  "properties": {
    "gn:admin1_code":"01",
    "gn:asciiname":"Krajnici",
    "gn:country_code":"BA",
    "gn:dem":305,
    "gn:feature_class":"P",
    "gn:feature_code":"PPL",
    "gn:name":"Krajni\u0107i",
    "gn:population":0,
    "gn:timezone":"Europe/Sarajevo",
    "iso:country":"BA",
    "wof:name":"Krajnici",
    "wof:placetype":"locality"
},
  "geometry": {"coordinates":[18.23801,44.43439],"type":"Point"}
}