{
  "type": "Feature",
  "properties": {
    "gn:admin1_code":"01",
    "gn:asciiname":"Bajramovici",
    "gn:country_code":"BA",
    "gn:dem":202,
    "gn:feature_class":"P",
    "gn:feature_code":"PPL",
    "gn:name":"Bajramovi\u0107i",
    "gn:population":0,
    "gn:timezone":"Europe/Sarajevo",
    "iso:country":"BA",
    "wof:name":"Bajramovici",
    "wof:placetype":"locality"
},
  "geometry": {"coordinates":[18.4101,44.84514],"type":"Point"}
}