{
  "type": "Feature",
  "properties": {
    "gn:admin1_code":"02",
    "gn:asciiname":"Paulje",
    "gn:country_code":"BA",
    "gn:dem":380,
    "gn:feature_class":"P",
    "gn:feature_code":"PPL",
    "gn:name":"Paulje",
    "gn:population":0,
    "gn:timezone":"Europe/Sarajevo",
    "iso:country":"BA",
    "wof:name":"Paulje",
    "wof:placetype":"locality"
},
  "geometry": {"coordinates":[18.76223,44.66192],"type":"Point"}
}