{
  "type": "Feature",
  "properties": {
    "gn:admin1_code":"01",
    "gn:asciiname":"Sormazi",
    "gn:country_code":"BA",
    "gn:dem":715,
    "gn:feature_class":"P",
    "gn:feature_code":"PPL",
    "gn:name":"\u0160ormazi",
    "gn:population":0,
    "gn:timezone":"Europe/Sarajevo",
    "iso:country":"BA",
    "wof:name":"Sormazi",
    "wof:placetype":"locality"
},
  "geometry": {"coordinates":[16.59778,44.03778],"type":"Point"}
}