{
  "type": "Feature",
  "properties": {
    "gn:admin1_code":"02",
    "gn:asciiname":"Vesici",
    "gn:country_code":"BA",
    "gn:dem":576,
    "gn:feature_class":"P",
    "gn:feature_code":"PPL",
    "gn:name":"Vesi\u0107i",
    "gn:population":0,
    "gn:timezone":"Europe/Sarajevo",
    "iso:country":"BA",
    "wof:name":"Vesici",
    "wof:placetype":"locality"
},
  "geometry": {"coordinates":[17.23165,44.60565],"type":"Point"}
}