{
  "type": "Feature",
  "properties": {
    "gn:admin1_code":"01",
    "gn:asciiname":"Donja Dobosnica",
    "gn:country_code":"BA",
    "gn:dem":182,
    "gn:feature_class":"P",
    "gn:feature_code":"PPL",
    "gn:name":"Donja Dobo\u0161nica",
    "gn:population":0,
    "gn:timezone":"Europe/Sarajevo",
    "iso:country":"BA",
    "wof:name":"Donja Dobosnica",
    "wof:placetype":"locality"
},
  "geometry": {"coordinates":[18.4485,44.58448],"type":"Point"}
}