{
  "type": "Feature",
  "properties": {
    "gn:admin1_code":"01",
    "gn:asciiname":"Donja Koprivnica",
    "gn:country_code":"BA",
    "gn:dem":507,
    "gn:feature_class":"P",
    "gn:feature_code":"PPL",
    "gn:name":"Donja Koprivnica",
    "gn:population":0,
    "gn:timezone":"Europe/Sarajevo",
    "iso:country":"BA",
    "wof:name":"Donja Koprivnica",
    "wof:placetype":"locality"
},
  "geometry": {"coordinates":[18.09837000000001,44.10848],"type":"Point"}
}