{
  "type": "Feature",
  "properties": {
    "gn:admin1_code":"02",
    "gn:asciiname":"Crnici",
    "gn:country_code":"BA",
    "gn:dem":248,
    "gn:feature_class":"P",
    "gn:feature_code":"PPL",
    "gn:name":"Crni\u0107i",
    "gn:population":0,
    "gn:timezone":"Europe/Sarajevo",
    "iso:country":"BA",
    "wof:name":"Crnici",
    "wof:placetype":"locality"
},
  "geometry": {"coordinates":[17.24445,44.88725],"type":"Point"}
}