{
  "type": "Feature",
  "properties": {
    "gn:admin1_code":"02",
    "gn:asciiname":"Malo Selo",
    "gn:country_code":"BA",
    "gn:dem":104,
    "gn:feature_class":"P",
    "gn:feature_code":"PPL",
    "gn:name":"Malo Selo",
    "gn:population":0,
    "gn:timezone":"Europe/Sarajevo",
    "iso:country":"BA",
    "wof:name":"Malo Selo",
    "wof:placetype":"locality"
},
  "geometry": {"coordinates":[19.22765,44.67992],"type":"Point"}
}