{
  "type": "Feature",
  "properties": {
    "gn:country":"BA",
    "gn:fcode":"PPL",
    "gn:pop":38479,
    "iso:country":"BA",
    "name:ara_x_preferred":[
        "\u0628\u0631\u062a\u0634\u0643\u0648"
    ],
    "name:bos_x_preferred":[
        "Br\u010dko"
    ],
    "name:bul_x_preferred":[
        "\u0411\u0440\u044a\u0447\u043a\u043e"
    ],
    "name:ces_x_preferred":[
        "Br\u010dko"
    ],
    "name:deu_x_preferred":[
        "Br\u010dko"
    ],
    "name:eng_x_preferred":[
        "Br\u010dko"
    ],
    "name:epo_x_preferred":[
        "Br\u010dko"
    ],
    "name:est_x_preferred":[
        "Br\u010dko"
    ],
    "name:fas_x_preferred":[
        "\u0628\u0631\u0686\u06a9\u0648"
    ],
    "name:fra_x_preferred":[
        "Br\u010dko"
    ],
    "name:glg_x_preferred":[
        "Br\u010dko"
    ],
    "name:heb_x_preferred":[
        "\u05d1\u05e8\u05e6\u05e7\u05d5"
    ],
    "name:hrv_x_preferred":[
        "Br\u010dko"
    ],
    "name:hun_x_preferred":[
        "Br\u010dko"
    ],
    "name:ile_x_preferred":[
        "Br\u010dko"
    ],
    "name:ita_x_preferred":[
        "Br\u010dko"
    ],
    "name:jav_x_preferred":[
        "Br\u010dko"
    ],
    "name:jpn_x_preferred":[
        "\u30d6\u30eb\u30c1\u30b3"
    ],
    "name:kor_x_preferred":[
        "\ube0c\ub974\uce58\ucf54"
    ],
    "name:lat_x_preferred":[
        "Breucus"
    ],
    "name:lit_x_preferred":[
        "Br\u010dkas"
    ],
    "name:mkd_x_preferred":[
        "\u0411\u0440\u0447\u043a\u043e"
    ],
    "name:nap_x_preferred":[
        "Br\u010dko"
    ],
    "name:nld_x_preferred":[
        "Br\u010dko"
    ],
    "name:nob_x_preferred":[
        "Br\u010dko"
    ],
    "name:pnb_x_preferred":[
        "\u0628\u0631\u06a9\u0648"
    ],
    "name:pol_x_preferred":[
        "Brczko"
    ],
    "name:por_x_preferred":[
        "Br\u010dko"
    ],
    "name:rus_x_preferred":[
        "\u0411\u0440\u0447\u043a\u043e"
    ],
    "name:sco_x_preferred":[
        "Br\u010dko"
    ],
    "name:slv_x_preferred":[
        "Br\u010dko"
    ],
    "name:spa_x_preferred":[
        "Br\u010dko"
    ],
    "name:sqi_x_preferred":[
        "B\u00ebr\u00e7ka"
    ],
    "name:srp_x_preferred":[
        "\u0411\u0440\u0447\u043a\u043e"
    ],
    "name:swe_x_preferred":[
        "Br\u010dko"
    ],
    "name:tat_x_preferred":[
        "\u0411\u0440\u0447\u043a\u043e"
    ],
    "name:tum_x_preferred":[
        "Br\u010dko"
    ],
    "name:tur_x_preferred":[
        "Br\u010dko"
    ],
    "name:ukr_x_preferred":[
        "\u0411\u0440\u0447\u043a\u043e"
    ],
    "name:urd_x_preferred":[
        "\u0628\u0631\u0686\u06a9\u0648"
    ],
    "name:vol_x_preferred":[
        "Br\u010dko"
    ],
    "name:zho_x_preferred":[
        "\u5e03\u5c14\u5947\u79d1"
    ],
    "name:zho_x_variant":[
        "\u5e03\u723e\u5947\u79d1"
    ],
    "qs:name":"Br\u010dko",
    "qs:name_adm0":"Bosna i Hercegovina",
    "qs:name_adm1":"Br\u010dko Distrikt",
    "qs:photos":138,
    "qs:photos_1k":28,
    "qs:photos_9k":1,
    "qs:photos_9r":3,
    "qs:photos_all":138,
    "qs:photos_sr":3,
    "qs:placetype":"Town",
    "qs:pop_sr":"7",
    "wd:wordcount":653,
    "wof:name":"Br\u010dko",
    "wof:placetype":"locality",
    "wof:population":38479
},
  "geometry": {"coordinates":[18.80833,44.87278],"type":"Point"}
}