{
  "type": "Feature",
  "properties": {
    "gn:admin1_code":"02",
    "gn:asciiname":"Pistali",
    "gn:country_code":"BA",
    "gn:dem":86,
    "gn:feature_class":"P",
    "gn:feature_code":"PPLL",
    "gn:name":"Pi\u0161tali",
    "gn:population":0,
    "gn:timezone":"Europe/Sarajevo",
    "iso:country":"BA",
    "wof:name":"Pistali",
    "wof:placetype":"locality"
},
  "geometry": {"coordinates":[18.61551,44.95342],"type":"Point"}
}