{
  "type": "Feature",
  "properties": {
    "gn:admin1_code":"00",
    "gn:asciiname":"Zivcici",
    "gn:country_code":"BA",
    "gn:dem":279,
    "gn:feature_class":"P",
    "gn:feature_code":"PPL",
    "gn:name":"\u017div\u010di\u0107i",
    "gn:population":0,
    "gn:timezone":"Europe/Sarajevo",
    "iso:country":"BA",
    "wof:name":"Zivcici",
    "wof:placetype":"locality"
},
  "geometry": {"coordinates":[18.65583,44.39971],"type":"Point"}
}