{
  "type": "Feature",
  "properties": {
    "gn:admin1_code":"02",
    "gn:asciiname":"Moravci",
    "gn:country_code":"BA",
    "gn:dem":204,
    "gn:feature_class":"P",
    "gn:feature_code":"PPL",
    "gn:name":"Moravci",
    "gn:population":0,
    "gn:timezone":"Europe/Sarajevo",
    "iso:country":"BA",
    "wof:name":"Moravci",
    "wof:placetype":"locality"
},
  "geometry": {"coordinates":[17.66297,44.84602],"type":"Point"}
}