{
  "type": "Feature",
  "properties": {
    "gn:admin1_code":"02",
    "gn:asciiname":"Zagorice",
    "gn:country_code":"BA",
    "gn:dem":769,
    "gn:feature_class":"P",
    "gn:feature_code":"PPL",
    "gn:name":"Zagorice",
    "gn:population":0,
    "gn:timezone":"Europe/Sarajevo",
    "iso:country":"BA",
    "wof:name":"Zagorice",
    "wof:placetype":"locality"
},
  "geometry": {"coordinates":[19.01539,43.83579],"type":"Point"}
}