{
  "type": "Feature",
  "properties": {
    "gn:admin1_code":"02",
    "gn:asciiname":"Baljci",
    "gn:country_code":"BA",
    "gn:dem":764,
    "gn:feature_class":"P",
    "gn:feature_code":"PPLL",
    "gn:name":"Baljci",
    "gn:population":0,
    "gn:timezone":"Europe/Sarajevo",
    "iso:country":"BA",
    "name:bos_x_preferred":[
        "Baljci"
    ],
    "name:cat_x_preferred":[
        "Baljci"
    ],
    "name:deu_x_preferred":[
        "Baljci"
    ],
    "name:fra_x_preferred":[
        "Baljci"
    ],
    "name:hrv_x_preferred":[
        "Baljci"
    ],
    "name:hun_x_preferred":[
        "Baljci"
    ],
    "name:rus_x_preferred":[
        "\u0411\u0430\u043b\u044c\u0446\u0438"
    ],
    "name:slv_x_preferred":[
        "Baljci"
    ],
    "name:srp_x_preferred":[
        "\u0411\u0430\u0459\u0446\u0438"
    ],
    "name:ukr_x_preferred":[
        "\u0411\u0430\u043b\u044c\u0446\u0456"
    ],
    "wof:name":"Baljci",
    "wof:placetype":"locality"
},
  "geometry": {"coordinates":[18.45614,42.89468],"type":"Point"}
}