{
  "type": "Feature",
  "properties": {
    "gn:admin1_code":"02",
    "gn:asciiname":"Baljci",
    "gn:country_code":"BA",
    "gn:dem":764,
    "gn:feature_class":"P",
    "gn:feature_code":"PPLL",
    "gn:name":"Baljci",
    "gn:population":0,
    "gn:timezone":"Europe/Sarajevo",
    "iso:country":"BA",
    "wof:name":"Baljci",
    "wof:placetype":"locality"
},
  "geometry": {"coordinates":[18.45614,42.89468],"type":"Point"}
}