{
  "type": "Feature",
  "properties": {
    "gn:admin1_code":"01",
    "gn:asciiname":"Meskovici",
    "gn:country_code":"BA",
    "gn:dem":457,
    "gn:feature_class":"P",
    "gn:feature_code":"PPL",
    "gn:name":"Me\u0161kovi\u0107i",
    "gn:population":0,
    "gn:timezone":"Europe/Sarajevo",
    "iso:country":"BA",
    "wof:name":"Meskovici",
    "wof:placetype":"locality"
},
  "geometry": {"coordinates":[18.83134,44.48816],"type":"Point"}
}