{
  "type": "Feature",
  "properties": {
    "gn:admin1_code":"02",
    "gn:asciiname":"Zlatac",
    "gn:country_code":"BA",
    "gn:dem":1103,
    "gn:feature_class":"P",
    "gn:feature_code":"PPL",
    "gn:name":"Zlatac",
    "gn:population":0,
    "gn:timezone":"Europe/Sarajevo",
    "iso:country":"BA",
    "wof:name":"Zlatac",
    "wof:placetype":"locality"
},
  "geometry": {"coordinates":[18.35348,43.16859],"type":"Point"}
}