{
  "type": "Feature",
  "properties": {
    "gn:admin1_code":"02",
    "gn:asciiname":"Gornja Bitunja",
    "gn:country_code":"BA",
    "gn:dem":512,
    "gn:feature_class":"P",
    "gn:feature_code":"PPL",
    "gn:name":"Gornja Bitunja",
    "gn:population":0,
    "gn:timezone":"Europe/Sarajevo",
    "iso:country":"BA",
    "wof:name":"Gornja Bitunja",
    "wof:placetype":"locality"
},
  "geometry": {"coordinates":[18.04486,43.04831],"type":"Point"}
}