{
  "type": "Feature",
  "properties": {
    "gn:admin1_code":"02",
    "gn:asciiname":"Pasajtovici",
    "gn:country_code":"BA",
    "gn:dem":700,
    "gn:feature_class":"P",
    "gn:feature_code":"PPL",
    "gn:name":"Pa\u0161ajtovi\u0107i",
    "gn:population":0,
    "gn:timezone":"Europe/Sarajevo",
    "iso:country":"BA",
    "wof:name":"Pasajtovici",
    "wof:placetype":"locality"
},
  "geometry": {"coordinates":[18.85028,43.50889],"type":"Point"}
}