{
  "type": "Feature",
  "properties": {
    "gn:admin1_code":"01",
    "gn:asciiname":"Dosenovici",
    "gn:country_code":"BA",
    "gn:dem":514,
    "gn:feature_class":"P",
    "gn:feature_code":"PPL",
    "gn:name":"Do\u0161enovi\u0107i",
    "gn:population":0,
    "gn:timezone":"Europe/Sarajevo",
    "iso:country":"BA",
    "wof:name":"Dosenovici",
    "wof:placetype":"locality"
},
  "geometry": {"coordinates":[16.54882000000001,44.76518],"type":"Point"}
}