{
  "type": "Feature",
  "properties": {
    "gn:admin1_code":"02",
    "gn:asciiname":"Aleksici",
    "gn:country_code":"BA",
    "gn:dem":217,
    "gn:feature_class":"P",
    "gn:feature_code":"PPLL",
    "gn:name":"Aleksi\u0107i",
    "gn:population":0,
    "gn:timezone":"Europe/Sarajevo",
    "iso:country":"BA",
    "wof:name":"Aleksici",
    "wof:placetype":"locality"
},
  "geometry": {"coordinates":[17.39522,44.84401],"type":"Point"}
}