{
  "type": "Feature",
  "properties": {
    "gn:admin1_code":"01",
    "gn:asciiname":"Stupe",
    "gn:country_code":"BA",
    "gn:dem":647,
    "gn:feature_class":"P",
    "gn:feature_code":"PPL",
    "gn:name":"Stupe",
    "gn:population":0,
    "gn:timezone":"Europe/Sarajevo",
    "iso:country":"BA",
    "wof:name":"Stupe",
    "wof:placetype":"locality"
},
  "geometry": {"coordinates":[18.42083,43.99111],"type":"Point"}
}