{
  "type": "Feature",
  "properties": {
    "gn:admin1_code":"01",
    "gn:asciiname":"Majdan",
    "gn:country_code":"BA",
    "gn:dem":544,
    "gn:feature_class":"P",
    "gn:feature_code":"PPL",
    "gn:name":"Majdan",
    "gn:population":0,
    "gn:timezone":"Europe/Sarajevo",
    "iso:country":"BA",
    "wof:name":"Majdan",
    "wof:placetype":"locality"
},
  "geometry": {"coordinates":[17.93694,43.96639],"type":"Point"}
}