{
  "type": "Feature",
  "properties": {
    "gn:admin1_code":"01",
    "gn:asciiname":"Solakovic",
    "gn:country_code":"BA",
    "gn:dem":564,
    "gn:feature_class":"P",
    "gn:feature_code":"PPL",
    "gn:name":"Solakovi\u0107",
    "gn:population":0,
    "gn:timezone":"Europe/Sarajevo",
    "iso:country":"BA",
    "name:bos_x_preferred":[
        "Solakovi\u0107i"
    ],
    "name:ceb_x_preferred":[
        "Solakovi\u0107"
    ],
    "name:fra_x_preferred":[
        "Solakovi\u0107i"
    ],
    "name:hrv_x_preferred":[
        "Solakovi\u0107i"
    ],
    "name:swe_x_preferred":[
        "Solakovi\u0107"
    ],
    "wof:name":"Solakovic",
    "wof:placetype":"locality"
},
  "geometry": {"coordinates":[18.12964,43.84934000000001],"type":"Point"}
}