{
  "type": "Feature",
  "properties": {
    "gn:admin1_code":"01",
    "gn:asciiname":"Maksica Dol",
    "gn:country_code":"BA",
    "gn:dem":655,
    "gn:feature_class":"P",
    "gn:feature_code":"PPL",
    "gn:name":"Maksi\u0107a Dol",
    "gn:population":0,
    "gn:timezone":"Europe/Sarajevo",
    "iso:country":"BA",
    "wof:name":"Maksica Dol",
    "wof:placetype":"locality"
},
  "geometry": {"coordinates":[16.48866,44.30548],"type":"Point"}
}