{
  "type": "Feature",
  "properties": {
    "gn:admin1_code":"02",
    "gn:asciiname":"Gatarici",
    "gn:country_code":"BA",
    "gn:dem":387,
    "gn:feature_class":"P",
    "gn:feature_code":"PPL",
    "gn:name":"Gatari\u0107i",
    "gn:population":0,
    "gn:timezone":"Europe/Sarajevo",
    "iso:country":"BA",
    "wof:name":"Gatarici",
    "wof:placetype":"locality"
},
  "geometry": {"coordinates":[17.05372,44.73893],"type":"Point"}
}