{
  "type": "Feature",
  "properties": {
    "gn:admin1_code":"02",
    "gn:asciiname":"Zaskog",
    "gn:country_code":"BA",
    "gn:dem":956,
    "gn:feature_class":"P",
    "gn:feature_code":"PPL",
    "gn:name":"Zaskog",
    "gn:population":0,
    "gn:timezone":"Europe/Sarajevo",
    "iso:country":"BA",
    "wof:name":"Zaskog",
    "wof:placetype":"locality"
},
  "geometry": {"coordinates":[17.60139,44.58028],"type":"Point"}
}