{
  "type": "Feature",
  "properties": {
    "gn:admin1_code":"01",
    "gn:asciiname":"Smarlovina",
    "gn:country_code":"BA",
    "gn:dem":299,
    "gn:feature_class":"P",
    "gn:feature_code":"PPL",
    "gn:name":"Smarlovina",
    "gn:population":0,
    "gn:timezone":"Europe/Sarajevo",
    "iso:country":"BA",
    "wof:name":"Smarlovina",
    "wof:placetype":"locality"
},
  "geometry": {"coordinates":[17.84637,43.15108],"type":"Point"}
}