{
  "type": "Feature",
  "properties": {
    "gn:admin1_code":"02",
    "gn:asciiname":"Zlatari",
    "gn:country_code":"BA",
    "gn:dem":550,
    "gn:feature_class":"P",
    "gn:feature_code":"PPLL",
    "gn:name":"Zlatari",
    "gn:population":0,
    "gn:timezone":"Europe/Sarajevo",
    "iso:country":"BA",
    "name:bos_x_preferred":[
        "Zlatari"
    ],
    "name:ceb_x_preferred":[
        "Zlatari"
    ],
    "name:fra_x_preferred":[
        "Zlatari"
    ],
    "name:hrv_x_preferred":[
        "Zlatari"
    ],
    "name:srp_x_preferred":[
        "\u0417\u043b\u0430\u0442\u0430\u0440\u0438"
    ],
    "name:swe_x_preferred":[
        "Zlatari"
    ],
    "wof:name":"Zlatari",
    "wof:placetype":"locality"
},
  "geometry": {"coordinates":[19.34493,43.6107],"type":"Point"}
}