{
  "type": "Feature",
  "properties": {
    "gn:admin1_code":"01",
    "gn:asciiname":"Prkosi",
    "gn:country_code":"BA",
    "gn:dem":746,
    "gn:feature_class":"P",
    "gn:feature_code":"PPLL",
    "gn:name":"Prkosi",
    "gn:population":0,
    "gn:timezone":"Europe/Sarajevo",
    "iso:country":"BA",
    "wof:name":"Prkosi",
    "wof:placetype":"locality"
},
  "geometry": {"coordinates":[16.12241,44.61621],"type":"Point"}
}