{
  "type": "Feature",
  "properties": {
    "gn:admin1_code":"02",
    "gn:asciiname":"Bjelajci",
    "gn:country_code":"BA",
    "gn:dem":377,
    "gn:feature_class":"P",
    "gn:feature_code":"PPLL",
    "gn:name":"Bjelajci",
    "gn:population":0,
    "gn:timezone":"Europe/Sarajevo",
    "iso:country":"BA",
    "name:bos_x_preferred":[
        "Bjelajci"
    ],
    "name:ceb_x_preferred":[
        "Bjelajci"
    ],
    "name:fra_x_preferred":[
        "Bjelajci"
    ],
    "name:hrv_x_preferred":[
        "Bjelajci"
    ],
    "name:slv_x_preferred":[
        "Bjelajci"
    ],
    "name:srp_x_preferred":[
        "\u0411\u0458\u0435\u043b\u0430\u0458\u0446\u0438"
    ],
    "name:swe_x_preferred":[
        "Bjelajci"
    ],
    "wof:name":"Bjelajci",
    "wof:placetype":"locality"
},
  "geometry": {"coordinates":[17.14274,44.4304],"type":"Point"}
}