{
  "type": "Feature",
  "properties": {
    "gn:admin1_code":"02",
    "gn:asciiname":"Kutace",
    "gn:country_code":"BA",
    "gn:dem":449,
    "gn:feature_class":"P",
    "gn:feature_code":"PPL",
    "gn:name":"Kuta\u010de",
    "gn:population":0,
    "gn:timezone":"Europe/Sarajevo",
    "iso:country":"BA",
    "wof:name":"Kutace",
    "wof:placetype":"locality"
},
  "geometry": {"coordinates":[18.7541,43.44305],"type":"Point"}
}