{
  "type": "Feature",
  "properties": {
    "gn:admin1_code":"01",
    "gn:asciiname":"Cojluk",
    "gn:country_code":"BA",
    "gn:dem":672,
    "gn:feature_class":"P",
    "gn:feature_code":"PPL",
    "gn:name":"\u010cojluk",
    "gn:population":0,
    "gn:timezone":"Europe/Sarajevo",
    "iso:country":"BA",
    "wof:name":"Cojluk",
    "wof:placetype":"locality"
},
  "geometry": {"coordinates":[16.1819,44.59393],"type":"Point"}
}