{
  "type": "Feature",
  "properties": {
    "gn:admin1_code":"01",
    "gn:asciiname":"Kulice",
    "gn:cc2":"BA",
    "gn:country_code":"BA",
    "gn:dem":463,
    "gn:feature_class":"P",
    "gn:feature_code":"PPL",
    "gn:name":"Kulice",
    "gn:population":0,
    "gn:timezone":"Europe/Sarajevo",
    "iso:country":"BA",
    "name:und_x_variant":[
        "Kolica",
        "Kulice"
    ],
    "wof:name":"Kulice",
    "wof:placetype":"locality"
},
  "geometry": {"coordinates":[18.68167,44.66861],"type":"Point"}
}