{
  "type": "Feature",
  "properties": {
    "gn:admin1_code":"02",
    "gn:asciiname":"Macute",
    "gn:country_code":"BA",
    "gn:dem":724,
    "gn:feature_class":"P",
    "gn:feature_code":"PPLL",
    "gn:name":"Macute",
    "gn:population":0,
    "gn:timezone":"Europe/Sarajevo",
    "iso:country":"BA",
    "name:bos_x_preferred":[
        "Macute"
    ],
    "name:fra_x_preferred":[
        "Macute"
    ],
    "name:hrv_x_preferred":[
        "Macute"
    ],
    "name:rus_x_preferred":[
        "\u041c\u0430\u0446\u0443\u0442\u0435"
    ],
    "name:srp_x_preferred":[
        "\u041c\u0430\u0446\u0443\u0442\u0435"
    ],
    "name:urd_x_preferred":[
        "\u0645\u06cc\u06a9\u0648\u0679\u06cc"
    ],
    "wof:name":"Macute",
    "wof:placetype":"locality"
},
  "geometry": {"coordinates":[19.43201,43.7375],"type":"Point"}
}