{
  "type": "Feature",
  "properties": {
    "gn:admin1_code":"02",
    "gn:asciiname":"Glozici",
    "gn:country_code":"BA",
    "gn:dem":170,
    "gn:feature_class":"P",
    "gn:feature_code":"PPL",
    "gn:name":"Glo\u017ei\u0107i",
    "gn:population":0,
    "gn:timezone":"Europe/Sarajevo",
    "iso:country":"BA",
    "wof:name":"Glozici",
    "wof:placetype":"locality"
},
  "geometry": {"coordinates":[17.67432,44.86189],"type":"Point"}
}