{
  "type": "Feature",
  "properties": {
    "gn:admin1_code":"01",
    "gn:asciiname":"Donje Dole",
    "gn:country_code":"BA",
    "gn:dem":319,
    "gn:feature_class":"P",
    "gn:feature_code":"PPL",
    "gn:name":"Donje Dole",
    "gn:population":0,
    "gn:timezone":"Europe/Sarajevo",
    "iso:country":"BA",
    "wof:name":"Donje Dole",
    "wof:placetype":"locality"
},
  "geometry": {"coordinates":[17.37574,43.27872],"type":"Point"}
}