{
  "type": "Feature",
  "properties": {
    "gn:admin1_code":"01",
    "gn:asciiname":"Ljutici",
    "gn:country_code":"BA",
    "gn:dem":691,
    "gn:feature_class":"P",
    "gn:feature_code":"PPL",
    "gn:name":"Ljuti\u0107i",
    "gn:population":0,
    "gn:timezone":"Europe/Sarajevo",
    "iso:country":"BA",
    "wof:name":"Ljutici",
    "wof:placetype":"locality"
},
  "geometry": {"coordinates":[16.2114,44.48304],"type":"Point"}
}