{
  "type": "Feature",
  "properties": {
    "gn:admin1_code":"02",
    "gn:asciiname":"Cukovina",
    "gn:country_code":"BA",
    "gn:dem":694,
    "gn:feature_class":"P",
    "gn:feature_code":"PPL",
    "gn:name":"\u0106ukovina",
    "gn:population":0,
    "gn:timezone":"Europe/Sarajevo",
    "iso:country":"BA",
    "wof:name":"Cukovina",
    "wof:placetype":"locality"
},
  "geometry": {"coordinates":[18.45944,42.95083],"type":"Point"}
}