{
  "type": "Feature",
  "properties": {
    "gn:admin1_code":"01",
    "gn:asciiname":"Oraslje",
    "gn:country_code":"BA",
    "gn:dem":410,
    "gn:feature_class":"P",
    "gn:feature_code":"PPL",
    "gn:name":"Ora\u0161lje",
    "gn:population":0,
    "gn:timezone":"Europe/Sarajevo",
    "iso:country":"BA",
    "wof:name":"Oraslje",
    "wof:placetype":"locality"
},
  "geometry": {"coordinates":[16.51567,44.79394],"type":"Point"}
}