{
  "type": "Feature",
  "properties": {
    "gn:admin1_code":"01",
    "gn:asciiname":"Pericini",
    "gn:country_code":"BA",
    "gn:dem":1085,
    "gn:feature_class":"P",
    "gn:feature_code":"PPL",
    "gn:name":"Peri\u010dini",
    "gn:population":0,
    "gn:timezone":"Europe/Sarajevo",
    "iso:country":"BA",
    "wof:name":"Pericini",
    "wof:placetype":"locality"
},
  "geometry": {"coordinates":[17.70391,44.04392],"type":"Point"}
}