{
  "type": "Feature",
  "properties": {
    "gn:admin1_code":"01",
    "gn:asciiname":"Cagare",
    "gn:country_code":"BA",
    "gn:dem":314,
    "gn:feature_class":"P",
    "gn:feature_code":"PPL",
    "gn:name":"Cagare",
    "gn:population":0,
    "gn:timezone":"Europe/Sarajevo",
    "iso:country":"BA",
    "wof:name":"Cagare",
    "wof:placetype":"locality"
},
  "geometry": {"coordinates":[17.96844,43.6337],"type":"Point"}
}