{
  "type": "Feature",
  "properties": {
    "gn:admin1_code":"02",
    "gn:asciiname":"Gornja Mededa",
    "gn:country_code":"BA",
    "gn:dem":92,
    "gn:feature_class":"P",
    "gn:feature_code":"PPL",
    "gn:name":"Gornja Me\u0111e\u0111a",
    "gn:population":0,
    "gn:timezone":"Europe/Sarajevo",
    "iso:country":"BA",
    "name:und_x_variant":[
        "Gornja Me\u0111i\u0111a",
        "Gornja Medjedja",
        "Gornja Me\u0111e\u0111a"
    ],
    "wof:name":"Gornja Mededa",
    "wof:placetype":"locality"
},
  "geometry": {"coordinates":[16.94984,45.21136],"type":"Point"}
}