{
  "type": "Feature",
  "properties": {
    "gn:admin1_code":"01",
    "gn:asciiname":"Podgredina",
    "gn:country_code":"BA",
    "gn:dem":404,
    "gn:feature_class":"P",
    "gn:feature_code":"PPLL",
    "gn:name":"Podgredina",
    "gn:population":0,
    "gn:timezone":"Europe/Sarajevo",
    "iso:country":"BA",
    "wof:name":"Podgredina",
    "wof:placetype":"locality"
},
  "geometry": {"coordinates":[16.04605,44.95823],"type":"Point"}
}