{
  "type": "Feature",
  "properties": {
    "gn:admin1_code":"02",
    "gn:asciiname":"Berek",
    "gn:country_code":"BA",
    "gn:dem":105,
    "gn:feature_class":"P",
    "gn:feature_code":"PPL",
    "gn:name":"Berek",
    "gn:population":0,
    "gn:timezone":"Europe/Sarajevo",
    "iso:country":"BA",
    "wof:name":"Berek",
    "wof:placetype":"locality"
},
  "geometry": {"coordinates":[17.34607,44.97999],"type":"Point"}
}