{
  "type": "Feature",
  "properties": {
    "gn:admin1_code":"02",
    "gn:asciiname":"Miljanovici",
    "gn:country_code":"BA",
    "gn:dem":818,
    "gn:feature_class":"P",
    "gn:feature_code":"PPL",
    "gn:name":"Miljanovi\u0107i",
    "gn:population":0,
    "gn:timezone":"Europe/Sarajevo",
    "iso:country":"BA",
    "wof:name":"Miljanovici",
    "wof:placetype":"locality"
},
  "geometry": {"coordinates":[17.99435,43.39939],"type":"Point"}
}