{
  "type": "Feature",
  "properties": {
    "gn:admin1_code":"01",
    "gn:asciiname":"Sabljari",
    "gn:country_code":"BA",
    "gn:dem":827,
    "gn:feature_class":"P",
    "gn:feature_code":"PPL",
    "gn:name":"Sabljari",
    "gn:population":0,
    "gn:timezone":"Europe/Sarajevo",
    "iso:country":"BA",
    "name:bos_x_preferred":[
        "Sabljari"
    ],
    "name:fra_x_preferred":[
        "Sabljari"
    ],
    "name:hrv_x_preferred":[
        "Sabljari"
    ],
    "name:srp_x_preferred":[
        "\u0421\u0430\u0431\u0459\u0430\u0440\u0438"
    ],
    "name:urd_x_preferred":[
        "\u0633\u0628\u0644\u062c\u0627\u0631\u06cc"
    ],
    "wof:name":"Sabljari",
    "wof:placetype":"locality"
},
  "geometry": {"coordinates":[17.49187,44.1373],"type":"Point"}
}