{
  "type": "Feature",
  "properties": {
    "gn:admin1_code":"01",
    "gn:asciiname":"Ostojici",
    "gn:country_code":"BA",
    "gn:dem":570,
    "gn:feature_class":"P",
    "gn:feature_code":"PPL",
    "gn:name":"Ostoji\u0107i",
    "gn:population":0,
    "gn:timezone":"Europe/Sarajevo",
    "iso:country":"BA",
    "wof:name":"Ostojici",
    "wof:placetype":"locality"
},
  "geometry": {"coordinates":[18.82261,44.559],"type":"Point"}
}