{
  "type": "Feature",
  "properties": {
    "gn:admin1_code":"02",
    "gn:asciiname":"Kostur",
    "gn:country_code":"BA",
    "gn:dem":188,
    "gn:feature_class":"P",
    "gn:feature_code":"PPL",
    "gn:name":"Kostur",
    "gn:population":0,
    "gn:timezone":"Europe/Sarajevo",
    "iso:country":"BA",
    "wof:name":"Kostur",
    "wof:placetype":"locality"
},
  "geometry": {"coordinates":[17.93344,44.96792],"type":"Point"}
}