{
  "type": "Feature",
  "properties": {
    "gn:admin1_code":"01",
    "gn:asciiname":"Pusista",
    "gn:country_code":"BA",
    "gn:dem":267,
    "gn:feature_class":"P",
    "gn:feature_code":"PPL",
    "gn:name":"Pusi\u0161ta",
    "gn:population":0,
    "gn:timezone":"Europe/Sarajevo",
    "iso:country":"BA",
    "wof:name":"Pusista",
    "wof:placetype":"locality"
},
  "geometry": {"coordinates":[17.92326,43.02078],"type":"Point"}
}