{
  "type": "Feature",
  "properties": {
    "gn:admin1_code":"02",
    "gn:asciiname":"Veliko Dvoriste",
    "gn:country_code":"BA",
    "gn:dem":229,
    "gn:feature_class":"P",
    "gn:feature_code":"PPLL",
    "gn:name":"Veliko Dvori\u0161te",
    "gn:population":0,
    "gn:timezone":"Europe/Sarajevo",
    "iso:country":"BA",
    "name:bos_x_preferred":[
        "Veliko Dvori\u0161te"
    ],
    "name:ceb_x_preferred":[
        "Veliko Dvori\u0161te"
    ],
    "name:fas_x_preferred":[
        "\u0648\u0644\u06cc\u06a9\u0648 \u062f\u0648\u0631\u06cc\u0634\u062a"
    ],
    "name:fra_x_preferred":[
        "Veliko Dvori\u0161te"
    ],
    "name:hrv_x_preferred":[
        "Veliko Dvori\u0161te"
    ],
    "name:slv_x_preferred":[
        "Veliko Dvori\u0161te"
    ],
    "name:srp_x_preferred":[
        "\u0412\u0435\u043b\u0438\u043a\u043e \u0414\u0432\u043e\u0440\u0438\u0448\u0442\u0435"
    ],
    "name:swe_x_preferred":[
        "Veliko Dvori\u0161te"
    ],
    "name:und_x_variant":[
        "Veliko Dvori\u0161te"
    ],
    "wof:name":"Veliko Dvoriste",
    "wof:placetype":"locality"
},
  "geometry": {"coordinates":[16.68737,45.13688],"type":"Point"}
}