{
  "type": "Feature",
  "properties": {
    "gn:admin1_code":"01",
    "gn:asciiname":"Karavlasi",
    "gn:country_code":"BA",
    "gn:dem":250,
    "gn:feature_class":"P",
    "gn:feature_code":"PPL",
    "gn:name":"Karavlasi",
    "gn:population":0,
    "gn:timezone":"Europe/Sarajevo",
    "iso:country":"BA",
    "wof:name":"Karavlasi",
    "wof:placetype":"locality"
},
  "geometry": {"coordinates":[18.82835,44.40752],"type":"Point"}
}