{
  "type": "Feature",
  "properties": {
    "gn:admin1_code":"02",
    "gn:asciiname":"Crni Vrh",
    "gn:country_code":"BA",
    "gn:dem":707,
    "gn:feature_class":"P",
    "gn:feature_code":"PPLL",
    "gn:name":"Crni Vrh",
    "gn:population":0,
    "gn:timezone":"Europe/Sarajevo",
    "iso:country":"BA",
    "name:bos_x_preferred":[
        "Crni Vrh"
    ],
    "name:fra_x_preferred":[
        "Crni Vrh"
    ],
    "name:hrv_x_preferred":[
        "Crni Vrh"
    ],
    "name:srp_x_preferred":[
        "\u0426\u0440\u043d\u0438 \u0412\u0440\u0445"
    ],
    "wof:name":"Crni Vrh",
    "wof:placetype":"locality"
},
  "geometry": {"coordinates":[19.2329,43.81282],"type":"Point"}
}