{
  "type": "Feature",
  "properties": {
    "gn:admin1_code":"01",
    "gn:asciiname":"Gvozdarevo",
    "gn:country_code":"BA",
    "gn:dem":1387,
    "gn:feature_class":"P",
    "gn:feature_code":"PPL",
    "gn:name":"Gvozdarevo",
    "gn:population":0,
    "gn:timezone":"Europe/Sarajevo",
    "iso:country":"BA",
    "wof:name":"Gvozdarevo",
    "wof:placetype":"locality"
},
  "geometry": {"coordinates":[18.46915,43.92217],"type":"Point"}
}