{
  "type": "Feature",
  "properties": {
    "gn:admin1_code":"01",
    "gn:asciiname":"Vardiste",
    "gn:country_code":"BA",
    "gn:dem":828,
    "gn:feature_class":"P",
    "gn:feature_code":"PPL",
    "gn:name":"Vardi\u0161te",
    "gn:population":0,
    "gn:timezone":"Europe/Sarajevo",
    "iso:country":"BA",
    "name:und_x_variant":[
        "Vardi\u0161te"
    ],
    "wof:name":"Vardiste",
    "wof:placetype":"locality"
},
  "geometry": {"coordinates":[18.28411,44.05243],"type":"Point"}
}