{
  "type": "Feature",
  "properties": {
    "gn:admin1_code":"01",
    "gn:asciiname":"Kosovaca",
    "gn:country_code":"BA",
    "gn:dem":534,
    "gn:feature_class":"P",
    "gn:feature_code":"PPL",
    "gn:name":"Kosova\u010da",
    "gn:population":0,
    "gn:timezone":"Europe/Sarajevo",
    "iso:country":"BA",
    "wof:name":"Kosovaca",
    "wof:placetype":"locality"
},
  "geometry": {"coordinates":[18.97377,43.62353],"type":"Point"}
}