{
  "type": "Feature",
  "properties": {
    "gn:admin1_code":"02",
    "gn:asciiname":"Rukaljevici",
    "gn:country_code":"BA",
    "gn:dem":182,
    "gn:feature_class":"P",
    "gn:feature_code":"PPL",
    "gn:name":"Rukaljevi\u0107i",
    "gn:population":0,
    "gn:timezone":"Europe/Sarajevo",
    "iso:country":"BA",
    "wof:name":"Rukaljevici",
    "wof:placetype":"locality"
},
  "geometry": {"coordinates":[16.75599,44.91304],"type":"Point"}
}