{
  "type": "Feature",
  "properties": {
    "gn:admin1_code":"02",
    "gn:asciiname":"Glavasi",
    "gn:country_code":"BA",
    "gn:dem":234,
    "gn:feature_class":"P",
    "gn:feature_code":"PPL",
    "gn:name":"Glava\u0161i",
    "gn:population":0,
    "gn:timezone":"Europe/Sarajevo",
    "iso:country":"BA",
    "wof:name":"Glavasi",
    "wof:placetype":"locality"
},
  "geometry": {"coordinates":[17.96585,44.91898],"type":"Point"}
}