{
  "type": "Feature",
  "properties": {
    "gn:admin1_code":"01",
    "gn:asciiname":"Mladeskovici",
    "gn:country_code":"BA",
    "gn:dem":402,
    "gn:feature_class":"P",
    "gn:feature_code":"PPL",
    "gn:name":"Mlade\u0161kovi\u0107i",
    "gn:population":0,
    "gn:timezone":"Europe/Sarajevo",
    "iso:country":"BA",
    "name:und_x_variant":[
        "Mlade\u0161kovi\u0107i"
    ],
    "wof:name":"Mladeskovici",
    "wof:placetype":"locality"
},
  "geometry": {"coordinates":[17.9653,43.61747],"type":"Point"}
}