{
  "type": "Feature",
  "properties": {
    "gn:admin1_code":"02",
    "gn:asciiname":"Rasevac",
    "gn:country_code":"BA",
    "gn:dem":140,
    "gn:feature_class":"P",
    "gn:feature_code":"PPL",
    "gn:name":"Ra\u0161evac",
    "gn:population":0,
    "gn:timezone":"Europe/Sarajevo",
    "iso:country":"BA",
    "wof:name":"Rasevac",
    "wof:placetype":"locality"
},
  "geometry": {"coordinates":[18.97281,44.77079000000001],"type":"Point"}
}