{
  "type": "Feature",
  "properties": {
    "gn:admin1_code":"02",
    "gn:asciiname":"Tepici",
    "gn:country_code":"BA",
    "gn:dem":521,
    "gn:feature_class":"P",
    "gn:feature_code":"PPL",
    "gn:name":"Tepi\u0107i",
    "gn:population":0,
    "gn:timezone":"Europe/Sarajevo",
    "iso:country":"BA",
    "wof:name":"Tepici",
    "wof:placetype":"locality"
},
  "geometry": {"coordinates":[17.46764,44.61165],"type":"Point"}
}