{
  "type": "Feature",
  "properties": {
    "gn:admin1_code":"02",
    "gn:asciiname":"Gaj",
    "gn:country_code":"BA",
    "gn:dem":111,
    "gn:feature_class":"P",
    "gn:feature_code":"PPL",
    "gn:name":"Gaj",
    "gn:population":0,
    "gn:timezone":"Europe/Sarajevo",
    "iso:country":"BA",
    "name:bos_x_preferred":[
        "Gaj"
    ],
    "name:ceb_x_preferred":[
        "Gaj"
    ],
    "name:fra_x_preferred":[
        "Gaj"
    ],
    "name:hrv_x_preferred":[
        "Gaj"
    ],
    "name:hun_x_preferred":[
        "Gaj"
    ],
    "name:hye_x_preferred":[
        "\u0533\u0561\u0575"
    ],
    "name:lit_x_preferred":[
        "Gajas"
    ],
    "name:nld_x_preferred":[
        "Gaj"
    ],
    "name:pol_x_preferred":[
        "Gaj"
    ],
    "name:slv_x_preferred":[
        "Gaj"
    ],
    "name:srp_x_preferred":[
        "\u0413\u0430\u0458"
    ],
    "name:swe_x_preferred":[
        "Gaj"
    ],
    "name:ukr_x_preferred":[
        "\u0490\u0430\u0439"
    ],
    "wof:name":"Gaj",
    "wof:placetype":"locality"
},
  "geometry": {"coordinates":[17.25371,45.01924],"type":"Point"}
}