{
  "type": "Feature",
  "properties": {
    "gn:admin1_code":"01",
    "gn:asciiname":"Raici",
    "gn:country_code":"BA",
    "gn:dem":712,
    "gn:feature_class":"P",
    "gn:feature_code":"PPL",
    "gn:name":"Rai\u0107i",
    "gn:population":0,
    "gn:timezone":"Europe/Sarajevo",
    "iso:country":"BA",
    "wof:name":"Raici",
    "wof:placetype":"locality"
},
  "geometry": {"coordinates":[17.72794,43.43839000000001],"type":"Point"}
}