{
  "type": "Feature",
  "properties": {
    "gn:admin1_code":"02",
    "gn:asciiname":"Kosovi",
    "gn:country_code":"BA",
    "gn:dem":162,
    "gn:feature_class":"P",
    "gn:feature_code":"PPL",
    "gn:name":"Kosovi",
    "gn:population":0,
    "gn:timezone":"Europe/Sarajevo",
    "iso:country":"BA",
    "wof:name":"Kosovi",
    "wof:placetype":"locality"
},
  "geometry": {"coordinates":[16.88609,44.8982],"type":"Point"}
}