{
  "type": "Feature",
  "properties": {
    "gn:admin1_code":"01",
    "gn:asciiname":"Ceranic",
    "gn:country_code":"BA",
    "gn:dem":362,
    "gn:feature_class":"P",
    "gn:feature_code":"PPL",
    "gn:name":"Cerani\u0107",
    "gn:population":0,
    "gn:timezone":"Europe/Sarajevo",
    "iso:country":"BA",
    "wof:name":"Ceranic",
    "wof:placetype":"locality"
},
  "geometry": {"coordinates":[18.35221,44.52564],"type":"Point"}
}