{
  "type": "Feature",
  "properties": {
    "gn:admin1_code":"02",
    "gn:asciiname":"Gornjani",
    "gn:country_code":"BA",
    "gn:dem":138,
    "gn:feature_class":"P",
    "gn:feature_code":"PPL",
    "gn:name":"Gornjani",
    "gn:population":0,
    "gn:timezone":"Europe/Sarajevo",
    "iso:country":"BA",
    "wof:name":"Gornjani",
    "wof:placetype":"locality"
},
  "geometry": {"coordinates":[17.24973,44.98853],"type":"Point"}
}