{
  "type": "Feature",
  "properties": {
    "gn:admin1_code":"01",
    "gn:asciiname":"Brdo",
    "gn:country_code":"BA",
    "gn:dem":418,
    "gn:feature_class":"P",
    "gn:feature_code":"PPL",
    "gn:name":"Brdo",
    "gn:population":0,
    "gn:timezone":"Europe/Sarajevo",
    "iso:country":"BA",
    "wof:name":"Brdo",
    "wof:placetype":"locality"
},
  "geometry": {"coordinates":[18.14944,44.03139],"type":"Point"}
}