{
  "type": "Feature",
  "properties": {
    "gn:admin1_code":"02",
    "gn:asciiname":"Vasadici",
    "gn:country_code":"BA",
    "gn:dem":643,
    "gn:feature_class":"P",
    "gn:feature_code":"PPL",
    "gn:name":"Va\u0161adi\u0107i",
    "gn:population":0,
    "gn:timezone":"Europe/Sarajevo",
    "iso:country":"BA",
    "wof:name":"Vasadici",
    "wof:placetype":"locality"
},
  "geometry": {"coordinates":[18.85169,43.54706],"type":"Point"}
}