{
  "type": "Feature",
  "properties": {
    "gn:admin1_code":"02",
    "gn:asciiname":"Sredelj",
    "gn:country_code":"BA",
    "gn:dem":1124,
    "gn:feature_class":"P",
    "gn:feature_code":"PPL",
    "gn:name":"Sredelj",
    "gn:population":0,
    "gn:timezone":"Europe/Sarajevo",
    "iso:country":"BA",
    "wof:name":"Sredelj",
    "wof:placetype":"locality"
},
  "geometry": {"coordinates":[18.9886,44.00132],"type":"Point"}
}