{
  "type": "Feature",
  "properties": {
    "gn:admin1_code":"02",
    "gn:asciiname":"Marcete",
    "gn:country_code":"BA",
    "gn:dem":225,
    "gn:feature_class":"P",
    "gn:feature_code":"PPL",
    "gn:name":"Mar\u010dete",
    "gn:population":0,
    "gn:timezone":"Europe/Sarajevo",
    "iso:country":"BA",
    "wof:name":"Marcete",
    "wof:placetype":"locality"
},
  "geometry": {"coordinates":[16.59961,44.9705],"type":"Point"}
}