{
  "type": "Feature",
  "properties": {
    "gn:admin1_code":"01",
    "gn:asciiname":"Uksici",
    "gn:country_code":"BA",
    "gn:dem":1002,
    "gn:feature_class":"P",
    "gn:feature_code":"PPL",
    "gn:name":"Uk\u0161i\u0107i",
    "gn:population":0,
    "gn:timezone":"Europe/Sarajevo",
    "iso:country":"BA",
    "wof:name":"Uksici",
    "wof:placetype":"locality"
},
  "geometry": {"coordinates":[18.70458,43.63874000000001],"type":"Point"}
}