{
  "type": "Feature",
  "properties": {
    "gn:admin1_code":"02",
    "gn:asciiname":"Zrvanj",
    "gn:country_code":"BA",
    "gn:dem":887,
    "gn:feature_class":"P",
    "gn:feature_code":"PPLL",
    "gn:name":"\u017drvanj",
    "gn:population":0,
    "gn:timezone":"Europe/Sarajevo",
    "iso:country":"BA",
    "wof:name":"Zrvanj",
    "wof:placetype":"locality"
},
  "geometry": {"coordinates":[18.18832,42.93418],"type":"Point"}
}