{
  "type": "Feature",
  "properties": {
    "gn:admin1_code":"02",
    "gn:asciiname":"Kupres",
    "gn:country_code":"BA",
    "gn:dem":354,
    "gn:feature_class":"P",
    "gn:feature_code":"PPL",
    "gn:name":"Kupres",
    "gn:population":0,
    "gn:timezone":"Europe/Sarajevo",
    "iso:country":"BA",
    "name:bos_x_preferred":[
        "Kupres"
    ],
    "name:ceb_x_preferred":[
        "Kupres"
    ],
    "name:deu_x_preferred":[
        "Kupres"
    ],
    "name:fra_x_preferred":[
        "Kupres"
    ],
    "name:hrv_x_preferred":[
        "Kupres"
    ],
    "name:ita_x_preferred":[
        "Kupres"
    ],
    "name:mkd_x_preferred":[
        "\u041a\u0443\u043f\u0440\u0435\u0441"
    ],
    "name:nld_x_preferred":[
        "Kupres"
    ],
    "name:pol_x_preferred":[
        "Kupres"
    ],
    "name:rus_x_preferred":[
        "\u041a\u0443\u043f\u0440\u0435\u0441"
    ],
    "name:sqi_x_preferred":[
        "Kupresi"
    ],
    "name:srp_x_preferred":[
        "\u041a\u0443\u043f\u0440\u0435\u0441"
    ],
    "name:swe_x_preferred":[
        "Kupres"
    ],
    "name:tur_x_preferred":[
        "Kupres"
    ],
    "name:ukr_x_preferred":[
        "\u041a\u0443\u043f\u0440\u0435\u0441"
    ],
    "name:urd_x_preferred":[
        "\u06a9\u0648\u067e\u0631\u06cc\u0633"
    ],
    "wof:name":"Kupres",
    "wof:placetype":"locality"
},
  "geometry": {"coordinates":[16.35431,44.87521],"type":"Point"}
}