{
  "type": "Feature",
  "properties": {
    "gn:asciiname":"Dolijani",
    "gn:country_code":"BA",
    "gn:dem":591,
    "gn:feature_class":"P",
    "gn:feature_code":"PPL",
    "gn:name":"Dolijani",
    "gn:population":0,
    "gn:timezone":"Europe/Sarajevo",
    "iso:country":"BA",
    "wof:name":"Dolijani",
    "wof:placetype":"locality"
},
  "geometry": {"coordinates":[17.657,43.69587],"type":"Point"}
}