{
  "type": "Feature",
  "properties": {
    "gn:admin1_code":"01",
    "gn:asciiname":"Husino",
    "gn:country_code":"BA",
    "gn:dem":253,
    "gn:feature_class":"P",
    "gn:feature_code":"PPL",
    "gn:name":"Husino",
    "gn:population":0,
    "gn:timezone":"Europe/Sarajevo",
    "iso:country":"BA",
    "name:und_x_variant":[
        "Husine",
        "Husina",
        "Husino"
    ],
    "wof:name":"Husino",
    "wof:placetype":"locality"
},
  "geometry": {"coordinates":[18.61214,44.5144],"type":"Point"}
}