{
  "type": "Feature",
  "properties": {
    "gn:admin1_code":"02",
    "gn:asciiname":"Duge Njive",
    "gn:country_code":"BA",
    "gn:dem":575,
    "gn:feature_class":"P",
    "gn:feature_code":"PPL",
    "gn:name":"Duge Njive",
    "gn:population":0,
    "gn:timezone":"Europe/Sarajevo",
    "iso:country":"BA",
    "wof:name":"Duge Njive",
    "wof:placetype":"locality"
},
  "geometry": {"coordinates":[19.02667000000001,43.78806],"type":"Point"}
}