{
  "type": "Feature",
  "properties": {
    "gn:admin1_code":"01",
    "gn:asciiname":"Varmasko Selo",
    "gn:country_code":"BA",
    "gn:dem":260,
    "gn:feature_class":"P",
    "gn:feature_code":"PPL",
    "gn:name":"Varmasko Selo",
    "gn:population":0,
    "gn:timezone":"Europe/Sarajevo",
    "iso:country":"BA",
    "wof:name":"Varmasko Selo",
    "wof:placetype":"locality"
},
  "geometry": {"coordinates":[15.91306,45.09472],"type":"Point"}
}