{
  "type": "Feature",
  "properties": {
    "gn:admin1_code":"02",
    "gn:asciiname":"Jeremici",
    "gn:country_code":"BA",
    "gn:dem":233,
    "gn:feature_class":"P",
    "gn:feature_code":"PPL",
    "gn:name":"Jeremi\u0107i",
    "gn:population":0,
    "gn:timezone":"Europe/Sarajevo",
    "iso:country":"BA",
    "wof:name":"Jeremici",
    "wof:placetype":"locality"
},
  "geometry": {"coordinates":[18.12421,44.80341],"type":"Point"}
}