{
  "type": "Feature",
  "properties": {
    "gn:admin1_code":"02",
    "gn:asciiname":"Rogoznik",
    "gn:country_code":"BA",
    "gn:dem":447,
    "gn:feature_class":"P",
    "gn:feature_code":"PPL",
    "gn:name":"Rogoznik",
    "gn:population":0,
    "gn:timezone":"Europe/Sarajevo",
    "iso:country":"BA",
    "wof:name":"Rogoznik",
    "wof:placetype":"locality"
},
  "geometry": {"coordinates":[17.16806,44.55833],"type":"Point"}
}