{
  "type": "Feature",
  "properties": {
    "gn:admin1_code":"02",
    "gn:asciiname":"Gornje Podnovlje",
    "gn:country_code":"BA",
    "gn:dem":240,
    "gn:feature_class":"P",
    "gn:feature_code":"PPLL",
    "gn:name":"Gornje Podnovlje",
    "gn:population":0,
    "gn:timezone":"Europe/Sarajevo",
    "iso:country":"BA",
    "wof:name":"Gornje Podnovlje",
    "wof:placetype":"locality"
},
  "geometry": {"coordinates":[18.11801,44.97568],"type":"Point"}
}