{
  "type": "Feature",
  "properties": {
    "gn:admin1_code":"01",
    "gn:asciiname":"Baljivac",
    "gn:country_code":"BA",
    "gn:dem":680,
    "gn:feature_class":"P",
    "gn:feature_code":"PPLL",
    "gn:name":"Baljivac",
    "gn:population":0,
    "gn:timezone":"Europe/Sarajevo",
    "iso:country":"BA",
    "name:bos_x_preferred":[
        "Baljivac"
    ],
    "name:fra_x_preferred":[
        "Baljivac"
    ],
    "name:hrv_x_preferred":[
        "Baljivac"
    ],
    "name:srp_x_preferred":[
        "\u0411\u0430\u0459\u0438\u0432\u0430\u0446"
    ],
    "name:und_x_variant":[
        "Baljevac"
    ],
    "wof:name":"Baljivac",
    "wof:placetype":"locality"
},
  "geometry": {"coordinates":[18.04763,42.79356],"type":"Point"}
}