{
  "type": "Feature",
  "properties": {
    "gn:admin1_code":"01",
    "gn:asciiname":"Mala Rijeka",
    "gn:country_code":"BA",
    "gn:dem":225,
    "gn:feature_class":"P",
    "gn:feature_code":"PPL",
    "gn:name":"Mala Rijeka",
    "gn:population":0,
    "gn:timezone":"Europe/Sarajevo",
    "iso:country":"BA",
    "wof:name":"Mala Rijeka",
    "wof:placetype":"locality"
},
  "geometry": {"coordinates":[18.37501,44.66131],"type":"Point"}
}