{
  "type": "Feature",
  "properties": {
    "gn:admin1_code":"02",
    "gn:asciiname":"Rakite",
    "gn:country_code":"BA",
    "gn:dem":811,
    "gn:feature_class":"P",
    "gn:feature_code":"PPLL",
    "gn:name":"Rakite",
    "gn:population":0,
    "gn:timezone":"Europe/Sarajevo",
    "iso:country":"BA",
    "wof:name":"Rakite",
    "wof:placetype":"locality"
},
  "geometry": {"coordinates":[18.66324,43.7765],"type":"Point"}
}