{
  "type": "Feature",
  "properties": {
    "gn:admin1_code":"02",
    "gn:asciiname":"Jasenica",
    "gn:country_code":"BA",
    "gn:dem":190,
    "gn:feature_class":"P",
    "gn:feature_code":"PPLL",
    "gn:name":"Jasenica",
    "gn:population":0,
    "gn:timezone":"Europe/Sarajevo",
    "iso:country":"BA",
    "name:bos_x_preferred":[
        "Jasenica"
    ],
    "name:ceb_x_preferred":[
        "Jasenica"
    ],
    "name:deu_x_preferred":[
        "Jasenica"
    ],
    "name:epo_x_preferred":[
        "Jasenica"
    ],
    "name:eus_x_preferred":[
        "Jasenica"
    ],
    "name:fra_x_preferred":[
        "Jasenica"
    ],
    "name:hrv_x_preferred":[
        "Jasenica"
    ],
    "name:hun_x_preferred":[
        "Jasenica"
    ],
    "name:nld_x_preferred":[
        "Jasenica"
    ],
    "name:slk_x_preferred":[
        "Jasenica"
    ],
    "name:slv_x_preferred":[
        "Jasenica"
    ],
    "name:srp_x_preferred":[
        "\u0408\u0430\u0441\u0435\u043d\u0438\u0446\u0430"
    ],
    "name:swe_x_preferred":[
        "Jasenica"
    ],
    "wof:name":"Jasenica",
    "wof:placetype":"locality"
},
  "geometry": {"coordinates":[19.07616,44.53339],"type":"Point"}
}