{
  "type": "Feature",
  "properties": {
    "gn:admin1_code":"02",
    "gn:asciiname":"Jasenica",
    "gn:country_code":"BA",
    "gn:dem":190,
    "gn:feature_class":"P",
    "gn:feature_code":"PPLL",
    "gn:name":"Jasenica",
    "gn:population":0,
    "gn:timezone":"Europe/Sarajevo",
    "iso:country":"BA",
    "wof:name":"Jasenica",
    "wof:placetype":"locality"
},
  "geometry": {"coordinates":[19.07616,44.53339],"type":"Point"}
}