{
  "type": "Feature",
  "properties": {
    "gn:admin1_code":"02",
    "gn:asciiname":"Brkici",
    "gn:country_code":"BA",
    "gn:dem":154,
    "gn:feature_class":"P",
    "gn:feature_code":"PPL",
    "gn:name":"Brki\u0107i",
    "gn:population":0,
    "gn:timezone":"Europe/Sarajevo",
    "iso:country":"BA",
    "wof:name":"Brkici",
    "wof:placetype":"locality"
},
  "geometry": {"coordinates":[16.6909,44.85025],"type":"Point"}
}