{
  "type": "Feature",
  "properties": {
    "gn:admin1_code":"01",
    "gn:asciiname":"Gvozd",
    "gn:country_code":"BA",
    "gn:dem":1266,
    "gn:feature_class":"P",
    "gn:feature_code":"PPL",
    "gn:name":"Gvozd",
    "gn:population":0,
    "gn:timezone":"Europe/Sarajevo",
    "iso:country":"BA",
    "wof:name":"Gvozd",
    "wof:placetype":"locality"
},
  "geometry": {"coordinates":[18.85857,43.70768],"type":"Point"}
}