{
  "type": "Feature",
  "properties": {
    "gn:admin1_code":"01",
    "gn:asciiname":"Gvozd",
    "gn:country_code":"BA",
    "gn:dem":1266,
    "gn:feature_class":"P",
    "gn:feature_code":"PPL",
    "gn:name":"Gvozd",
    "gn:population":0,
    "gn:timezone":"Europe/Sarajevo",
    "iso:country":"BA",
    "name:bos_x_preferred":[
        "Gvozd"
    ],
    "name:cat_x_preferred":[
        "Gvozd"
    ],
    "name:ceb_x_preferred":[
        "Gvozd"
    ],
    "name:deu_x_preferred":[
        "Gvozd"
    ],
    "name:fra_x_preferred":[
        "Gvozd"
    ],
    "name:hrv_x_preferred":[
        "Gvozd"
    ],
    "name:hun_x_preferred":[
        "Gvozd"
    ],
    "name:ita_x_preferred":[
        "Gvozd"
    ],
    "name:nld_x_preferred":[
        "Gvozd"
    ],
    "name:pol_x_preferred":[
        "Gmina Gvozd"
    ],
    "name:ron_x_preferred":[
        "Comuna Gvozd"
    ],
    "name:rus_x_preferred":[
        "\u0413\u0432\u043e\u0437\u0434"
    ],
    "name:slv_x_preferred":[
        "Vrginmost"
    ],
    "name:spa_x_preferred":[
        "Gvozd"
    ],
    "name:srp_x_preferred":[
        "\u0412\u0440\u0433\u0438\u043d\u043c\u043e\u0441\u0442"
    ],
    "name:swe_x_preferred":[
        "Gvozd"
    ],
    "name:ukr_x_preferred":[
        "\u0413\u0432\u043e\u0437\u0434"
    ],
    "name:war_x_preferred":[
        "Gvozd"
    ],
    "wof:name":"Gvozd",
    "wof:placetype":"locality"
},
  "geometry": {"coordinates":[18.85857,43.70768],"type":"Point"}
}