{
  "type": "Feature",
  "properties": {
    "gn:admin1_code":"01",
    "gn:asciiname":"Malo Cajno",
    "gn:country_code":"BA",
    "gn:dem":547,
    "gn:feature_class":"P",
    "gn:feature_code":"PPL",
    "gn:name":"Malo \u010cajno",
    "gn:population":0,
    "gn:timezone":"Europe/Sarajevo",
    "iso:country":"BA",
    "wof:name":"Malo Cajno",
    "wof:placetype":"locality"
},
  "geometry": {"coordinates":[18.20493,44.04263],"type":"Point"}
}