{
  "type": "Feature",
  "properties": {
    "gn:admin1_code":"02",
    "gn:asciiname":"Masali",
    "gn:country_code":"BA",
    "gn:dem":508,
    "gn:feature_class":"P",
    "gn:feature_code":"PPL",
    "gn:name":"Masali",
    "gn:population":0,
    "gn:timezone":"Europe/Sarajevo",
    "iso:country":"BA",
    "wof:name":"Masali",
    "wof:placetype":"locality"
},
  "geometry": {"coordinates":[19.45866,43.73151],"type":"Point"}
}