{
  "type": "Feature",
  "properties": {
    "gn:admin1_code":"01",
    "gn:asciiname":"Rosulje",
    "gn:country_code":"BA",
    "gn:dem":251,
    "gn:feature_class":"P",
    "gn:feature_code":"PPL",
    "gn:name":"Rosulje",
    "gn:population":0,
    "gn:timezone":"Europe/Sarajevo",
    "iso:country":"BA",
    "name:bos_x_preferred":[
        "Rosulje"
    ],
    "name:ceb_x_preferred":[
        "Rosulje"
    ],
    "name:fra_x_preferred":[
        "Rosulje"
    ],
    "name:hrv_x_preferred":[
        "Rosulje"
    ],
    "name:hun_x_preferred":[
        "Rosulje"
    ],
    "name:nld_x_preferred":[
        "Rosulje"
    ],
    "name:slv_x_preferred":[
        "Rosulje"
    ],
    "name:srp_x_preferred":[
        "\u0420\u043e\u0441\u0443\u0459\u0435"
    ],
    "name:swe_x_preferred":[
        "Rosulje"
    ],
    "wof:name":"Rosulje",
    "wof:placetype":"locality"
},
  "geometry": {"coordinates":[18.38668,44.52054],"type":"Point"}
}