{
  "type": "Feature",
  "properties": {
    "gn:admin1_code":"01",
    "gn:asciiname":"Rosulje",
    "gn:country_code":"BA",
    "gn:dem":251,
    "gn:feature_class":"P",
    "gn:feature_code":"PPL",
    "gn:name":"Rosulje",
    "gn:population":0,
    "gn:timezone":"Europe/Sarajevo",
    "iso:country":"BA",
    "wof:name":"Rosulje",
    "wof:placetype":"locality"
},
  "geometry": {"coordinates":[18.38668,44.52054],"type":"Point"}
}