{
  "type": "Feature",
  "properties": {
    "gn:admin1_code":"01",
    "gn:asciiname":"Krnja Ravan",
    "gn:country_code":"BA",
    "gn:dem":1099,
    "gn:feature_class":"P",
    "gn:feature_code":"PPL",
    "gn:name":"Krnja Ravan",
    "gn:population":0,
    "gn:timezone":"Europe/Sarajevo",
    "iso:country":"BA",
    "wof:name":"Krnja Ravan",
    "wof:placetype":"locality"
},
  "geometry": {"coordinates":[18.16589,43.47982],"type":"Point"}
}