{
  "type": "Feature",
  "properties": {
    "gn:admin1_code":"02",
    "gn:asciiname":"Stavanj",
    "gn:country_code":"BA",
    "gn:dem":925,
    "gn:feature_class":"P",
    "gn:feature_code":"PPL",
    "gn:name":"Stavanj",
    "gn:population":0,
    "gn:timezone":"Europe/Sarajevo",
    "iso:country":"BA",
    "wof:name":"Stavanj",
    "wof:placetype":"locality"
},
  "geometry": {"coordinates":[18.6442,43.49079],"type":"Point"}
}