{
  "type": "Feature",
  "properties": {
    "gn:admin1_code":"02",
    "gn:asciiname":"Donja Kapavica",
    "gn:country_code":"BA",
    "gn:dem":730,
    "gn:feature_class":"P",
    "gn:feature_code":"PPL",
    "gn:name":"Donja Kapavica",
    "gn:population":0,
    "gn:timezone":"Europe/Sarajevo",
    "iso:country":"BA",
    "wof:name":"Donja Kapavica",
    "wof:placetype":"locality"
},
  "geometry": {"coordinates":[18.13384,42.97001],"type":"Point"}
}