{
  "type": "Feature",
  "properties": {
    "gn:admin1_code":"01",
    "gn:asciiname":"Vranjace",
    "gn:country_code":"BA",
    "gn:dem":890,
    "gn:feature_class":"P",
    "gn:feature_code":"PPL",
    "gn:name":"Vranja\u010de",
    "gn:population":0,
    "gn:timezone":"Europe/Sarajevo",
    "iso:country":"BA",
    "name:bos_x_preferred":[
        "Vranja\u010de"
    ],
    "name:fra_x_preferred":[
        "Vranja\u010de"
    ],
    "name:hrv_x_preferred":[
        "Vranja\u010de"
    ],
    "name:srp_x_preferred":[
        "\u0412\u0440\u0430\u045a\u0430\u0447\u0435"
    ],
    "wof:name":"Vranjace",
    "wof:placetype":"locality"
},
  "geometry": {"coordinates":[17.11615,43.57976],"type":"Point"}
}