{
  "type": "Feature",
  "properties": {
    "gn:admin1_code":"01",
    "gn:asciiname":"Tokici",
    "gn:country_code":"BA",
    "gn:dem":945,
    "gn:feature_class":"P",
    "gn:feature_code":"PPL",
    "gn:name":"Toki\u0107i",
    "gn:population":0,
    "gn:timezone":"Europe/Sarajevo",
    "iso:country":"BA",
    "wof:name":"Tokici",
    "wof:placetype":"locality"
},
  "geometry": {"coordinates":[17.38839,43.54859],"type":"Point"}
}