{
  "type": "Feature",
  "properties": {
    "gn:admin1_code":"02",
    "gn:asciiname":"Kamenica",
    "gn:country_code":"BA",
    "gn:dem":416,
    "gn:feature_class":"P",
    "gn:feature_code":"PPL",
    "gn:name":"Kamenica",
    "gn:population":0,
    "gn:timezone":"Europe/Sarajevo",
    "iso:country":"BA",
    "name:bel_x_preferred":[
        "\u041a\u0430\u043c\u044f\u043d\u0456\u0446\u0430"
    ],
    "name:bos_x_preferred":[
        "Kamenica"
    ],
    "name:bul_x_preferred":[
        "\u041a\u0430\u043c\u0435\u043d\u0438\u0446\u0430"
    ],
    "name:ceb_x_preferred":[
        "Kamenica"
    ],
    "name:ces_x_preferred":[
        "Kamenica"
    ],
    "name:deu_x_preferred":[
        "Kamenica"
    ],
    "name:ell_x_preferred":[
        "\u039a\u03b1\u03bc\u03b5\u03bd\u03af\u03c4\u03c3\u03b1"
    ],
    "name:epo_x_preferred":[
        "Kamenica"
    ],
    "name:eus_x_preferred":[
        "Kamenica"
    ],
    "name:fra_x_preferred":[
        "Kamenica"
    ],
    "name:hrv_x_preferred":[
        "Kamenica"
    ],
    "name:hun_x_preferred":[
        "Kamenica"
    ],
    "name:jpn_x_preferred":[
        "\u30ab\u30e1\u30cb\u30c4\u30a1"
    ],
    "name:kor_x_preferred":[
        "\uce74\uba54\ub2c8\ucc28"
    ],
    "name:nld_x_preferred":[
        "Kamenica"
    ],
    "name:pol_x_preferred":[
        "Kamenica"
    ],
    "name:por_x_preferred":[
        "Kamenica"
    ],
    "name:ron_x_preferred":[
        "Kameni\u021ba"
    ],
    "name:rus_x_preferred":[
        "\u041a\u0430\u043c\u0435\u043d\u0438\u0446\u0430"
    ],
    "name:slk_x_preferred":[
        "Kamenica"
    ],
    "name:slv_x_preferred":[
        "Kamenica"
    ],
    "name:srp_x_preferred":[
        "\u041a\u0430\u043c\u0435\u043d\u0438\u0446\u0430"
    ],
    "name:swe_x_preferred":[
        "Kamenica"
    ],
    "name:ukr_x_preferred":[
        "\u041a\u0430\u043c\u0435\u043d\u0438\u0446\u044f"
    ],
    "wof:name":"Kamenica",
    "wof:placetype":"locality"
},
  "geometry": {"coordinates":[19.16654,44.20706],"type":"Point"}
}