{
  "type": "Feature",
  "properties": {
    "gn:admin1_code":"02",
    "gn:asciiname":"Vukosavljevici",
    "gn:country_code":"BA",
    "gn:dem":929,
    "gn:feature_class":"P",
    "gn:feature_code":"PPL",
    "gn:name":"Vukosavljevi\u0107i",
    "gn:population":0,
    "gn:timezone":"Europe/Sarajevo",
    "iso:country":"BA",
    "wof:name":"Vukosavljevici",
    "wof:placetype":"locality"
},
  "geometry": {"coordinates":[19.34639,44.09472],"type":"Point"}
}