{
  "type": "Feature",
  "properties": {
    "gn:admin1_code":"01",
    "gn:asciiname":"Vlahovici",
    "gn:country_code":"BA",
    "gn:dem":866,
    "gn:feature_class":"P",
    "gn:feature_code":"PPL",
    "gn:name":"Vlahovi\u0107i",
    "gn:population":0,
    "gn:timezone":"Europe/Sarajevo",
    "iso:country":"BA",
    "wof:name":"Vlahovici",
    "wof:placetype":"locality"
},
  "geometry": {"coordinates":[17.58656,44.22617],"type":"Point"}
}