{
  "type": "Feature",
  "properties": {
    "gn:admin1_code":"01",
    "gn:asciiname":"Miljusi",
    "gn:country_code":"BA",
    "gn:dem":566,
    "gn:feature_class":"P",
    "gn:feature_code":"PPL",
    "gn:name":"Milju\u0161i",
    "gn:population":0,
    "gn:timezone":"Europe/Sarajevo",
    "iso:country":"BA",
    "wof:name":"Miljusi",
    "wof:placetype":"locality"
},
  "geometry": {"coordinates":[16.15519,44.40409],"type":"Point"}
}