{
  "type": "Feature",
  "properties": {
    "gn:admin1_code":"01",
    "gn:asciiname":"Crkvina",
    "gn:country_code":"BA",
    "gn:dem":431,
    "gn:feature_class":"P",
    "gn:feature_code":"PPL",
    "gn:name":"Crkvina",
    "gn:population":0,
    "gn:timezone":"Europe/Sarajevo",
    "iso:country":"BA",
    "name:bos_x_preferred":[
        "Crkvina"
    ],
    "name:ceb_x_preferred":[
        "Crkvina"
    ],
    "name:fra_x_preferred":[
        "Crkvina"
    ],
    "name:hrv_x_preferred":[
        "Crkvina"
    ],
    "name:nld_x_preferred":[
        "Crkvina"
    ],
    "name:srp_x_preferred":[
        "\u0426\u0440\u043a\u0432\u0438\u043d\u0430"
    ],
    "name:swe_x_preferred":[
        "Crkvina"
    ],
    "wof:name":"Crkvina",
    "wof:placetype":"locality"
},
  "geometry": {"coordinates":[16.25029,44.794],"type":"Point"}
}