{
  "type": "Feature",
  "properties": {
    "gn:admin1_code":"01",
    "gn:asciiname":"Jarici",
    "gn:country_code":"BA",
    "gn:dem":435,
    "gn:feature_class":"P",
    "gn:feature_code":"PPL",
    "gn:name":"Jari\u0107i",
    "gn:population":0,
    "gn:timezone":"Europe/Sarajevo",
    "iso:country":"BA",
    "wof:name":"Jarici",
    "wof:placetype":"locality"
},
  "geometry": {"coordinates":[16.22532,44.21234000000001],"type":"Point"}
}