{
  "type": "Feature",
  "properties": {
    "gn:admin1_code":"01",
    "gn:asciiname":"Kamenica",
    "gn:country_code":"BA",
    "gn:dem":229,
    "gn:feature_class":"P",
    "gn:feature_code":"PPL",
    "gn:name":"Kamenica",
    "gn:population":0,
    "gn:timezone":"Europe/Sarajevo",
    "iso:country":"BA",
    "wof:name":"Kamenica",
    "wof:placetype":"locality"
},
  "geometry": {"coordinates":[15.82887,44.84467],"type":"Point"}
}