{
  "type": "Feature",
  "properties": {
    "gn:admin1_code":"01",
    "gn:asciiname":"Gavrici",
    "gn:country_code":"BA",
    "gn:dem":424,
    "gn:feature_class":"P",
    "gn:feature_code":"PPL",
    "gn:name":"Gavri\u0107i",
    "gn:population":0,
    "gn:timezone":"Europe/Sarajevo",
    "iso:country":"BA",
    "wof:name":"Gavrici",
    "wof:placetype":"locality"
},
  "geometry": {"coordinates":[19.02067000000001,44.53555],"type":"Point"}
}