{
  "type": "Feature",
  "properties": {
    "gn:admin1_code":"02",
    "gn:asciiname":"Dedovci",
    "gn:country_code":"BA",
    "gn:dem":957,
    "gn:feature_class":"P",
    "gn:feature_code":"PPL",
    "gn:name":"\u00d0edovci",
    "gn:population":0,
    "gn:timezone":"Europe/Sarajevo",
    "iso:country":"BA",
    "wof:name":"Dedovci",
    "wof:placetype":"locality"
},
  "geometry": {"coordinates":[18.83863,43.85268],"type":"Point"}
}