{
  "type": "Feature",
  "properties": {
    "gn:admin1_code":"02",
    "gn:asciiname":"Madzari",
    "gn:country_code":"BA",
    "gn:dem":627,
    "gn:feature_class":"P",
    "gn:feature_code":"PPL",
    "gn:name":"Mad\u017eari",
    "gn:population":0,
    "gn:timezone":"Europe/Sarajevo",
    "iso:country":"BA",
    "wof:name":"Madzari",
    "wof:placetype":"locality"
},
  "geometry": {"coordinates":[18.90014,43.51267],"type":"Point"}
}