{
  "type": "Feature",
  "properties": {
    "gn:admin1_code":"02",
    "gn:asciiname":"Citluci",
    "gn:country_code":"BA",
    "gn:dem":933,
    "gn:feature_class":"P",
    "gn:feature_code":"PPLL",
    "gn:name":"\u010citluci",
    "gn:population":0,
    "gn:timezone":"Europe/Sarajevo",
    "iso:country":"BA",
    "name:bos_x_preferred":[
        "\u010citluci"
    ],
    "name:fra_x_preferred":[
        "\u010citluci"
    ],
    "name:srp_x_preferred":[
        "\u0427\u0438\u0442\u043b\u0443\u0446\u0438"
    ],
    "wof:name":"Citluci",
    "wof:placetype":"locality"
},
  "geometry": {"coordinates":[18.84812,43.88809000000001],"type":"Point"}
}