{
  "type": "Feature",
  "properties": {
    "gn:admin1_code":"02",
    "gn:asciiname":"Citluci",
    "gn:country_code":"BA",
    "gn:dem":933,
    "gn:feature_class":"P",
    "gn:feature_code":"PPLL",
    "gn:name":"\u010citluci",
    "gn:population":0,
    "gn:timezone":"Europe/Sarajevo",
    "iso:country":"BA",
    "name:und_x_variant":[
        "\u010citluci"
    ],
    "wof:name":"Citluci",
    "wof:placetype":"locality"
},
  "geometry": {"coordinates":[18.84812,43.88809000000001],"type":"Point"}
}