{
  "type": "Feature",
  "properties": {
    "gn:admin1_code":"02",
    "gn:asciiname":"Lokvice",
    "gn:country_code":"BA",
    "gn:dem":265,
    "gn:feature_class":"P",
    "gn:feature_code":"PPL",
    "gn:name":"Lokvice",
    "gn:population":0,
    "gn:timezone":"Europe/Sarajevo",
    "iso:country":"BA",
    "name:bos_x_preferred":[
        "Lokvice"
    ],
    "name:fra_x_preferred":[
        "Lokvice"
    ],
    "name:srp_x_preferred":[
        "\u041b\u043e\u043a\u0432\u0438\u0446\u0435"
    ],
    "wof:name":"Lokvice",
    "wof:placetype":"locality"
},
  "geometry": {"coordinates":[18.21398,42.77372],"type":"Point"}
}