{
  "type": "Feature",
  "properties": {
    "gn:admin1_code":"02",
    "gn:asciiname":"Gornja Cagosta",
    "gn:country_code":"BA",
    "gn:dem":1094,
    "gn:feature_class":"P",
    "gn:feature_code":"PPL",
    "gn:name":"Gornja \u010cago\u0161ta",
    "gn:population":0,
    "gn:timezone":"Europe/Sarajevo",
    "iso:country":"BA",
    "wof:name":"Gornja Cagosta",
    "wof:placetype":"locality"
},
  "geometry": {"coordinates":[18.6966,43.42186],"type":"Point"}
}