{
  "type": "Feature",
  "properties": {
    "gn:admin1_code":"01",
    "gn:asciiname":"Trnjaci",
    "gn:country_code":"BA",
    "gn:dem":229,
    "gn:feature_class":"P",
    "gn:feature_code":"PPL",
    "gn:name":"Trnjaci",
    "gn:population":0,
    "gn:timezone":"Europe/Sarajevo",
    "iso:country":"BA",
    "name:bos_x_preferred":[
        "Trnjaci"
    ],
    "name:fra_x_preferred":[
        "Trnjaci"
    ],
    "name:hrv_x_preferred":[
        "Trnjaci"
    ],
    "name:msa_x_preferred":[
        "Trnjaci"
    ],
    "name:rus_x_preferred":[
        "\u0422\u0440\u043d\u044f\u0446\u0438"
    ],
    "name:slv_x_preferred":[
        "Trnjaci"
    ],
    "name:srp_x_preferred":[
        "\u0422\u0440\u045a\u0430\u0446\u0438"
    ],
    "name:swe_x_preferred":[
        "Trnjaci"
    ],
    "name:urd_x_preferred":[
        "\u062a\u0631\u0646\u06cc\u0627\u062a\u0633\u06cc"
    ],
    "wof:name":"Trnjaci",
    "wof:placetype":"locality"
},
  "geometry": {"coordinates":[18.29007,44.7126],"type":"Point"}
}