{
  "type": "Feature",
  "properties": {
    "gn:admin1_code":"02",
    "gn:asciiname":"Cokici",
    "gn:country_code":"BA",
    "gn:dem":330,
    "gn:feature_class":"P",
    "gn:feature_code":"PPL",
    "gn:name":"\u010coki\u0107i",
    "gn:population":0,
    "gn:timezone":"Europe/Sarajevo",
    "iso:country":"BA",
    "wof:name":"Cokici",
    "wof:placetype":"locality"
},
  "geometry": {"coordinates":[17.07064,44.80752],"type":"Point"}
}