{
  "type": "Feature",
  "properties": {
    "gn:admin1_code":"01",
    "gn:asciiname":"Putesic",
    "gn:country_code":"BA",
    "gn:dem":182,
    "gn:feature_class":"P",
    "gn:feature_code":"PPL",
    "gn:name":"Pute\u0161i\u0107",
    "gn:population":0,
    "gn:timezone":"Europe/Sarajevo",
    "iso:country":"BA",
    "wof:name":"Putesic",
    "wof:placetype":"locality"
},
  "geometry": {"coordinates":[17.90539,44.64482],"type":"Point"}
}