{
  "type": "Feature",
  "properties": {
    "gn:admin1_code":"01",
    "gn:asciiname":"Vrbanja",
    "gn:country_code":"BA",
    "gn:dem":580,
    "gn:feature_class":"P",
    "gn:feature_code":"PPL",
    "gn:name":"Vrbanja",
    "gn:population":0,
    "gn:timezone":"Europe/Sarajevo",
    "iso:country":"BA",
    "wof:name":"Vrbanja",
    "wof:placetype":"locality"
},
  "geometry": {"coordinates":[17.46528,44.0275],"type":"Point"}
}