{
  "type": "Feature",
  "properties": {
    "gn:admin1_code":"01",
    "gn:asciiname":"Kopljani",
    "gn:country_code":"BA",
    "gn:dem":934,
    "gn:feature_class":"P",
    "gn:feature_code":"PPL",
    "gn:name":"Kopljani",
    "gn:population":0,
    "gn:timezone":"Europe/Sarajevo",
    "iso:country":"BA",
    "wof:name":"Kopljani",
    "wof:placetype":"locality"
},
  "geometry": {"coordinates":[18.89537,43.71677],"type":"Point"}
}