{
  "type": "Feature",
  "properties": {
    "gn:admin1_code":"01",
    "gn:asciiname":"Kucetine",
    "gn:country_code":"BA",
    "gn:dem":663,
    "gn:feature_class":"P",
    "gn:feature_code":"PPL",
    "gn:name":"Ku\u010detine",
    "gn:population":0,
    "gn:timezone":"Europe/Sarajevo",
    "iso:country":"BA",
    "wof:name":"Kucetine",
    "wof:placetype":"locality"
},
  "geometry": {"coordinates":[17.20479,43.54659],"type":"Point"}
}