{
  "type": "Feature",
  "properties": {
    "gn:admin1_code":"02",
    "gn:asciiname":"Zovik",
    "gn:country_code":"BA",
    "gn:dem":678,
    "gn:feature_class":"P",
    "gn:feature_code":"PPL",
    "gn:name":"Zovik",
    "gn:population":0,
    "gn:timezone":"Europe/Sarajevo",
    "iso:country":"BA",
    "wof:name":"Zovik",
    "wof:placetype":"locality"
},
  "geometry": {"coordinates":[18.96734,43.78424],"type":"Point"}
}