{
  "type": "Feature",
  "properties": {
    "gn:admin1_code":"02",
    "gn:asciiname":"Gornja Mravica",
    "gn:country_code":"BA",
    "gn:dem":255,
    "gn:feature_class":"P",
    "gn:feature_code":"PPLL",
    "gn:name":"Gornja Mravica",
    "gn:population":0,
    "gn:timezone":"Europe/Sarajevo",
    "iso:country":"BA",
    "wof:name":"Gornja Mravica",
    "wof:placetype":"locality"
},
  "geometry": {"coordinates":[17.61417,44.84756],"type":"Point"}
}