{
  "type": "Feature",
  "properties": {
    "gn:admin1_code":"01",
    "gn:asciiname":"Prnjavor",
    "gn:country_code":"BA",
    "gn:dem":345,
    "gn:feature_class":"P",
    "gn:feature_code":"PPL",
    "gn:name":"Prnjavor",
    "gn:population":0,
    "gn:timezone":"Europe/Sarajevo",
    "iso:country":"BA",
    "wof:name":"Prnjavor",
    "wof:placetype":"locality"
},
  "geometry": {"coordinates":[18.20417,44.76472],"type":"Point"}
}