{
  "type": "Feature",
  "properties": {
    "gn:admin1_code":"02",
    "gn:asciiname":"Ridosici",
    "gn:country_code":"BA",
    "gn:dem":347,
    "gn:feature_class":"P",
    "gn:feature_code":"PPL",
    "gn:name":"Ri\u0111o\u0161i\u0107i",
    "gn:population":0,
    "gn:timezone":"Europe/Sarajevo",
    "iso:country":"BA",
    "wof:name":"Ridosici",
    "wof:placetype":"locality"
},
  "geometry": {"coordinates":[18.94965,44.37704],"type":"Point"}
}