{
  "type": "Feature",
  "properties": {
    "gn:admin1_code":"01",
    "gn:asciiname":"Donji Ljenobud",
    "gn:country_code":"BA",
    "gn:dem":312,
    "gn:feature_class":"P",
    "gn:feature_code":"PPL",
    "gn:name":"Donji Ljenobud",
    "gn:population":0,
    "gn:timezone":"Europe/Sarajevo",
    "iso:country":"BA",
    "wof:name":"Donji Ljenobud",
    "wof:placetype":"locality"
},
  "geometry": {"coordinates":[18.51017,44.68127],"type":"Point"}
}