{
  "type": "Feature",
  "properties": {
    "gn:admin1_code":"01",
    "gn:asciiname":"Kapulari",
    "gn:country_code":"BA",
    "gn:dem":145,
    "gn:feature_class":"P",
    "gn:feature_code":"PPL",
    "gn:name":"Kapulari",
    "gn:population":0,
    "gn:timezone":"Europe/Sarajevo",
    "iso:country":"BA",
    "wof:name":"Kapulari",
    "wof:placetype":"locality"
},
  "geometry": {"coordinates":[17.65306,43.16917],"type":"Point"}
}