{
  "type": "Feature",
  "properties": {
    "gn:country":"BA",
    "gn:fcode":"PPL",
    "gn:population":8026,
    "iso:country":"BA",
    "name:ara_x_preferred":[
        "\u0632\u0641\u0648\u0631\u0646\u064a\u0643"
    ],
    "name:aze_x_preferred":[
        "Zvornik"
    ],
    "name:bos_x_preferred":[
        "Zvornik"
    ],
    "name:bul_x_preferred":[
        "\u0417\u0432\u043e\u0440\u043d\u0438\u043a"
    ],
    "name:cat_x_preferred":[
        "Zvornik"
    ],
    "name:ces_x_preferred":[
        "Zvornik"
    ],
    "name:dan_x_preferred":[
        "Zvornik"
    ],
    "name:deu_x_preferred":[
        "Zvornik"
    ],
    "name:ell_x_preferred":[
        "\u0396\u03b2\u03cc\u03c1\u03bd\u03b9\u03ba"
    ],
    "name:eng_x_preferred":[
        "Zvornik"
    ],
    "name:epo_x_preferred":[
        "Zvornik"
    ],
    "name:fas_x_preferred":[
        "\u0632\u0648\u0648\u0631\u0646\u06cc\u06a9"
    ],
    "name:fin_x_preferred":[
        "Zvornik"
    ],
    "name:fra_x_preferred":[
        "Zvornik"
    ],
    "name:frr_x_preferred":[
        "Zvornik"
    ],
    "name:hbs_x_preferred":[
        "Zvornik"
    ],
    "name:heb_x_preferred":[
        "\u05d6\u05d1\u05d5\u05e8\u05e0\u05d9\u05e7"
    ],
    "name:hrv_x_preferred":[
        "Zvornik"
    ],
    "name:hsb_x_preferred":[
        "Zvornik"
    ],
    "name:hun_x_preferred":[
        "Zvornik"
    ],
    "name:hye_x_preferred":[
        "\u0536\u057e\u0578\u0580\u0576\u056b\u056f"
    ],
    "name:ile_x_preferred":[
        "Zvornik"
    ],
    "name:ita_x_preferred":[
        "Zvornik"
    ],
    "name:jpn_x_preferred":[
        "\u30ba\u30f4\u30a9\u30eb\u30cb\u30af"
    ],
    "name:kor_x_preferred":[
        "\uc988\ubcf4\ub974\ub2c8\ud06c"
    ],
    "name:lit_x_preferred":[
        "Zvornikas"
    ],
    "name:mkd_x_preferred":[
        "\u0417\u0432\u043e\u0440\u043d\u0438\u043a"
    ],
    "name:mlg_x_preferred":[
        "Zvornik"
    ],
    "name:nld_x_preferred":[
        "Zvornik"
    ],
    "name:nno_x_preferred":[
        "Zvornik"
    ],
    "name:nob_x_preferred":[
        "Zvornik"
    ],
    "name:pol_x_preferred":[
        "Zvornik"
    ],
    "name:ron_x_preferred":[
        "Zvornik"
    ],
    "name:rus_x_preferred":[
        "\u0417\u0432\u043e\u0440\u043d\u0438\u043a"
    ],
    "name:slk_x_preferred":[
        "Zvornik"
    ],
    "name:slv_x_preferred":[
        "Zvornik"
    ],
    "name:spa_x_preferred":[
        "Zvornik"
    ],
    "name:sqi_x_preferred":[
        "Zvorniku"
    ],
    "name:srp_x_preferred":[
        "\u0417\u0432\u043e\u0440\u043d\u0438\u043a"
    ],
    "name:swe_x_preferred":[
        "Zvornik"
    ],
    "name:tat_x_preferred":[
        "\u0417\u0432\u043e\u0440\u043d\u0438\u043a"
    ],
    "name:tur_x_preferred":[
        "Zvornik"
    ],
    "name:ukr_x_preferred":[
        "\u0417\u0432\u043e\u0440\u043d\u0438\u043a"
    ],
    "name:und_x_variant":[
        "Zvonik"
    ],
    "name:urd_x_preferred":[
        "\u0632\u0648\u0648\u0631\u0646\u06a9"
    ],
    "name:zho_x_preferred":[
        "\u8332\u6c83\u723e\u5c3c\u514b"
    ],
    "qs:name":"Zvornik",
    "qs:photos_9r":0,
    "qs:photos_sr":0,
    "qs:pop_sr":"5",
    "wd:wordcount":885,
    "wof:name":"Zvornik",
    "wof:placetype":"locality",
    "wof:population":8026
},
  "geometry": {"coordinates":[19.10247,44.38605],"type":"Point"}
}