{
  "type": "Feature",
  "properties": {
    "gn:admin1_code":"02",
    "gn:asciiname":"Zboriste",
    "gn:country_code":"BA",
    "gn:dem":91,
    "gn:feature_class":"P",
    "gn:feature_code":"PPL",
    "gn:name":"Zbori\u0161te",
    "gn:population":0,
    "gn:timezone":"Europe/Sarajevo",
    "iso:country":"BA",
    "name:und_x_variant":[
        "Zbori\u0161te"
    ],
    "wof:name":"Zboriste",
    "wof:placetype":"locality"
},
  "geometry": {"coordinates":[17.99335,45.04339],"type":"Point"}
}