{
  "type": "Feature",
  "properties": {
    "gn:admin1_code":"02",
    "gn:asciiname":"Podgorje",
    "gn:country_code":"BA",
    "gn:dem":497,
    "gn:feature_class":"P",
    "gn:feature_code":"PPLL",
    "gn:name":"Podgorje",
    "gn:population":0,
    "gn:timezone":"Europe/Sarajevo",
    "iso:country":"BA",
    "name:bos_x_preferred":[
        "Podgorje"
    ],
    "name:fra_x_preferred":[
        "Podgorje"
    ],
    "name:hrv_x_preferred":[
        "Podgorje"
    ],
    "name:rus_x_preferred":[
        "\u041f\u043e\u0434\u0433\u043e\u0440\u044c\u0435"
    ],
    "name:srp_x_preferred":[
        "\u041f\u043e\u0434\u0433\u043e\u0440\u0458\u0435"
    ],
    "wof:name":"Podgorje",
    "wof:placetype":"locality"
},
  "geometry": {"coordinates":[19.4457,43.7394],"type":"Point"}
}