{
  "type": "Feature",
  "properties": {
    "gn:admin1_code":"02",
    "gn:asciiname":"Veliki Banici",
    "gn:country_code":"BA",
    "gn:dem":797,
    "gn:feature_class":"P",
    "gn:feature_code":"PPLL",
    "gn:name":"Veliki Bani\u0107i",
    "gn:population":0,
    "gn:timezone":"Europe/Sarajevo",
    "iso:country":"BA",
    "wof:name":"Veliki Banici",
    "wof:placetype":"locality"
},
  "geometry": {"coordinates":[19.22447,43.55245],"type":"Point"}
}