{
  "type": "Feature",
  "properties": {
    "gn:admin1_code":"01",
    "gn:asciiname":"Brescica",
    "gn:country_code":"BA",
    "gn:dem":440,
    "gn:feature_class":"P",
    "gn:feature_code":"PPL",
    "gn:name":"Bre\u0161\u010dica",
    "gn:population":0,
    "gn:timezone":"Europe/Sarajevo",
    "iso:country":"BA",
    "wof:name":"Brescica",
    "wof:placetype":"locality"
},
  "geometry": {"coordinates":[16.77506,44.55742],"type":"Point"}
}