{
  "type": "Feature",
  "properties": {
    "gn:admin1_code":"01",
    "gn:asciiname":"Kazaginac",
    "gn:country_code":"BA",
    "gn:dem":763,
    "gn:feature_class":"P",
    "gn:feature_code":"PPLL",
    "gn:name":"Kazaginac",
    "gn:population":0,
    "gn:timezone":"Europe/Sarajevo",
    "iso:country":"BA",
    "name:und_x_variant":[
        "Kazaginec",
        "Kazaginac"
    ],
    "wof:name":"Kazaginac",
    "wof:placetype":"locality"
},
  "geometry": {"coordinates":[17.01371,43.61078],"type":"Point"}
}