{
  "type": "Feature",
  "properties": {
    "gn:admin1_code":"02",
    "gn:asciiname":"Tunjica",
    "gn:country_code":"BA",
    "gn:dem":187,
    "gn:feature_class":"P",
    "gn:feature_code":"PPL",
    "gn:name":"Tunjica",
    "gn:population":0,
    "gn:timezone":"Europe/Sarajevo",
    "iso:country":"BA",
    "wof:name":"Tunjica",
    "wof:placetype":"locality"
},
  "geometry": {"coordinates":[16.39583,45.05972],"type":"Point"}
}