{
  "type": "Feature",
  "properties": {
    "gn:admin1_code":"01",
    "gn:asciiname":"Krunici",
    "gn:country_code":"BA",
    "gn:dem":460,
    "gn:feature_class":"P",
    "gn:feature_code":"PPL",
    "gn:name":"Kruni\u0107i",
    "gn:population":0,
    "gn:timezone":"Europe/Sarajevo",
    "iso:country":"BA",
    "wof:name":"Krunici",
    "wof:placetype":"locality"
},
  "geometry": {"coordinates":[16.56586,44.7681],"type":"Point"}
}