{
  "type": "Feature",
  "properties": {
    "gn:admin1_code":"02",
    "gn:asciiname":"Vukelici",
    "gn:country_code":"BA",
    "gn:dem":406,
    "gn:feature_class":"P",
    "gn:feature_code":"PPL",
    "gn:name":"Vukeli\u0107i",
    "gn:population":0,
    "gn:timezone":"Europe/Sarajevo",
    "iso:country":"BA",
    "wof:name":"Vukelici",
    "wof:placetype":"locality"
},
  "geometry": {"coordinates":[17.00212,44.73773],"type":"Point"}
}