{
  "type": "Feature",
  "properties": {
    "gn:admin1_code":"01",
    "gn:asciiname":"Numanovici",
    "gn:country_code":"BA",
    "gn:dem":933,
    "gn:feature_class":"P",
    "gn:feature_code":"PPL",
    "gn:name":"Numanovi\u0107i",
    "gn:population":0,
    "gn:timezone":"Europe/Sarajevo",
    "iso:country":"BA",
    "wof:name":"Numanovici",
    "wof:placetype":"locality"
},
  "geometry": {"coordinates":[18.55994,44.06686],"type":"Point"}
}