{
  "type": "Feature",
  "properties": {
    "gn:admin1_code":"01",
    "gn:asciiname":"Jojici",
    "gn:country_code":"BA",
    "gn:dem":627,
    "gn:feature_class":"P",
    "gn:feature_code":"PPL",
    "gn:name":"Joji\u0107i",
    "gn:population":0,
    "gn:timezone":"Europe/Sarajevo",
    "iso:country":"BA",
    "wof:name":"Jojici",
    "wof:placetype":"locality"
},
  "geometry": {"coordinates":[16.52388,44.75123],"type":"Point"}
}