{
  "type": "Feature",
  "properties": {
    "gn:admin1_code":"01",
    "gn:asciiname":"Johovica",
    "gn:country_code":"BA",
    "gn:dem":377,
    "gn:feature_class":"P",
    "gn:feature_code":"PPLL",
    "gn:name":"Johovica",
    "gn:population":0,
    "gn:timezone":"Europe/Sarajevo",
    "iso:country":"BA",
    "wof:name":"Johovica",
    "wof:placetype":"locality"
},
  "geometry": {"coordinates":[15.79404,45.09594],"type":"Point"}
}