{
  "type": "Feature",
  "properties": {
    "gn:admin1_code":"01",
    "gn:asciiname":"Dosenovici",
    "gn:country_code":"BA",
    "gn:dem":176,
    "gn:feature_class":"P",
    "gn:feature_code":"PPL",
    "gn:name":"Dosenovi\u0107i",
    "gn:population":0,
    "gn:timezone":"Europe/Sarajevo",
    "iso:country":"BA",
    "wof:name":"Dosenovici",
    "wof:placetype":"locality"
},
  "geometry": {"coordinates":[16.62672,44.77229000000001],"type":"Point"}
}