{
  "type": "Feature",
  "properties": {
    "gn:admin1_code":"02",
    "gn:asciiname":"Dalmacija",
    "gn:country_code":"BA",
    "gn:dem":289,
    "gn:feature_class":"P",
    "gn:feature_code":"PPL",
    "gn:name":"Dalmacija",
    "gn:population":0,
    "gn:timezone":"Europe/Sarajevo",
    "iso:country":"BA",
    "wof:name":"Dalmacija",
    "wof:placetype":"locality"
},
  "geometry": {"coordinates":[16.42778,45.05611],"type":"Point"}
}