{
  "type": "Feature",
  "properties": {
    "gn:admin1_code":"01",
    "gn:asciiname":"Devor",
    "gn:country_code":"BA",
    "gn:dem":188,
    "gn:feature_class":"P",
    "gn:feature_code":"PPL",
    "gn:name":"\u00d0evor",
    "gn:population":0,
    "gn:timezone":"Europe/Sarajevo",
    "iso:country":"BA",
    "wof:name":"Devor",
    "wof:placetype":"locality"
},
  "geometry": {"coordinates":[17.7631,43.63467],"type":"Point"}
}