{
  "type": "Feature",
  "properties": {
    "gn:admin1_code":"01",
    "gn:asciiname":"Velja Sela",
    "gn:country_code":"BA",
    "gn:dem":263,
    "gn:feature_class":"P",
    "gn:feature_code":"PPL",
    "gn:name":"Velja Sela",
    "gn:population":0,
    "gn:timezone":"Europe/Sarajevo",
    "iso:country":"BA",
    "wof:name":"Velja Sela",
    "wof:placetype":"locality"
},
  "geometry": {"coordinates":[17.89594,42.91543],"type":"Point"}
}