{
  "type": "Feature",
  "properties": {
    "gn:admin1_code":"01",
    "gn:asciiname":"Glavica",
    "gn:country_code":"BA",
    "gn:dem":588,
    "gn:feature_class":"P",
    "gn:feature_code":"PPL",
    "gn:name":"Glavica",
    "gn:population":0,
    "gn:timezone":"Europe/Sarajevo",
    "iso:country":"BA",
    "wof:name":"Glavica",
    "wof:placetype":"locality"
},
  "geometry": {"coordinates":[17.1743,43.5241],"type":"Point"}
}