{
  "type": "Feature",
  "properties": {
    "gn:admin1_code":"01",
    "gn:asciiname":"Glavica",
    "gn:country_code":"BA",
    "gn:dem":588,
    "gn:feature_class":"P",
    "gn:feature_code":"PPL",
    "gn:name":"Glavica",
    "gn:population":0,
    "gn:timezone":"Europe/Sarajevo",
    "iso:country":"BA",
    "name:bos_x_preferred":[
        "Glavica"
    ],
    "name:ceb_x_preferred":[
        "Glavica"
    ],
    "name:fra_x_preferred":[
        "Glavica"
    ],
    "name:hrv_x_preferred":[
        "Glavica"
    ],
    "name:hun_x_preferred":[
        "Glavica"
    ],
    "name:nld_x_preferred":[
        "Glavica"
    ],
    "name:slv_x_preferred":[
        "Glavica"
    ],
    "name:srp_x_preferred":[
        "\u0413\u043b\u0430\u0432\u0438\u0446\u0430"
    ],
    "name:swe_x_preferred":[
        "Glavica"
    ],
    "wof:name":"Glavica",
    "wof:placetype":"locality"
},
  "geometry": {"coordinates":[17.1743,43.5241],"type":"Point"}
}