{
  "type": "Feature",
  "properties": {
    "gn:admin1_code":"01",
    "gn:asciiname":"Junuzovici",
    "gn:country_code":"BA",
    "gn:dem":436,
    "gn:feature_class":"P",
    "gn:feature_code":"PPL",
    "gn:name":"Junuzovi\u0107i",
    "gn:population":0,
    "gn:timezone":"Europe/Sarajevo",
    "iso:country":"BA",
    "wof:name":"Junuzovici",
    "wof:placetype":"locality"
},
  "geometry": {"coordinates":[18.53773,44.69668],"type":"Point"}
}