{
  "type": "Feature",
  "properties": {
    "gn:admin1_code":"02",
    "gn:asciiname":"Prvanj",
    "gn:country_code":"BA",
    "gn:dem":1056,
    "gn:feature_class":"P",
    "gn:feature_code":"PPLL",
    "gn:name":"Prvanj",
    "gn:population":0,
    "gn:timezone":"Europe/Sarajevo",
    "iso:country":"BA",
    "name:bos_x_preferred":[
        "Prvanj"
    ],
    "name:fra_x_preferred":[
        "Prvanj"
    ],
    "name:rus_x_preferred":[
        "\u041f\u0440\u0432\u0430\u043d\u044c"
    ],
    "name:srp_x_preferred":[
        "\u041f\u0440\u0432\u0430\u045a"
    ],
    "wof:name":"Prvanj",
    "wof:placetype":"locality"
},
  "geometry": {"coordinates":[18.98613,43.59665],"type":"Point"}
}