{
  "type": "Feature",
  "properties": {
    "gn:admin1_code":"01",
    "gn:asciiname":"Merce",
    "gn:country_code":"BA",
    "gn:dem":118,
    "gn:feature_class":"P",
    "gn:feature_code":"PPL",
    "gn:name":"Mer\u010de",
    "gn:population":0,
    "gn:timezone":"Europe/Sarajevo",
    "iso:country":"BA",
    "wof:name":"Merce",
    "wof:placetype":"locality"
},
  "geometry": {"coordinates":[17.8164,43.34628],"type":"Point"}
}