{
  "type": "Feature",
  "properties": {
    "gn:admin1_code":"02",
    "gn:asciiname":"Rakite",
    "gn:country_code":"BA",
    "gn:dem":972,
    "gn:feature_class":"P",
    "gn:feature_code":"PPL",
    "gn:name":"Rakite",
    "gn:population":0,
    "gn:timezone":"Europe/Sarajevo",
    "iso:country":"BA",
    "name:bos_x_preferred":[
        "Rakite"
    ],
    "name:fra_x_preferred":[
        "Rakite"
    ],
    "name:srp_x_preferred":[
        "\u0420\u0430\u043a\u0438\u0442\u0435"
    ],
    "wof:name":"Rakite",
    "wof:placetype":"locality"
},
  "geometry": {"coordinates":[18.70227,43.83002000000001],"type":"Point"}
}