{
  "type": "Feature",
  "properties": {
    "gn:admin1_code":"02",
    "gn:asciiname":"Ostruznja Donja",
    "gn:country_code":"BA",
    "gn:dem":216,
    "gn:feature_class":"P",
    "gn:feature_code":"PPL",
    "gn:name":"Ostru\u017enja Donja",
    "gn:population":0,
    "gn:timezone":"Europe/Sarajevo",
    "iso:country":"BA",
    "wof:name":"Ostruznja Donja",
    "wof:placetype":"locality"
},
  "geometry": {"coordinates":[17.86132000000001,44.75551],"type":"Point"}
}