{
  "type": "Feature",
  "properties": {
    "gn:admin1_code":"01",
    "gn:asciiname":"Dudici",
    "gn:country_code":"BA",
    "gn:dem":693,
    "gn:feature_class":"P",
    "gn:feature_code":"PPL",
    "gn:name":"Dudi\u0107i",
    "gn:population":0,
    "gn:timezone":"Europe/Sarajevo",
    "iso:country":"BA",
    "wof:name":"Dudici",
    "wof:placetype":"locality"
},
  "geometry": {"coordinates":[17.00522999999999,43.5934],"type":"Point"}
}