{
  "type": "Feature",
  "properties": {
    "gn:admin1_code":"02",
    "gn:asciiname":"Vukadinovici",
    "gn:country_code":"BA",
    "gn:dem":206,
    "gn:feature_class":"P",
    "gn:feature_code":"PPL",
    "gn:name":"Vukadinovi\u0107i",
    "gn:population":0,
    "gn:timezone":"Europe/Sarajevo",
    "iso:country":"BA",
    "wof:name":"Vukadinovici",
    "wof:placetype":"locality"
},
  "geometry": {"coordinates":[17.75649,44.793],"type":"Point"}
}