{
  "type": "Feature",
  "properties": {
    "gn:admin1_code":"02",
    "gn:asciiname":"Gornji Lukavac",
    "gn:country_code":"BA",
    "gn:dem":941,
    "gn:feature_class":"P",
    "gn:feature_code":"PPL",
    "gn:name":"Gornji Lukavac",
    "gn:population":0,
    "gn:timezone":"Europe/Sarajevo",
    "iso:country":"BA",
    "name:und_x_variant":[
        "Lukavac Gornji",
        "Gornji Lukavac"
    ],
    "wof:name":"Gornji Lukavac",
    "wof:placetype":"locality"
},
  "geometry": {"coordinates":[18.2837,43.12338],"type":"Point"}
}