{
  "type": "Feature",
  "properties": {
    "gn:admin1_code":"01",
    "gn:asciiname":"Ripici",
    "gn:country_code":"BA",
    "gn:dem":609,
    "gn:feature_class":"P",
    "gn:feature_code":"PPL",
    "gn:name":"Ripi\u0107i",
    "gn:population":0,
    "gn:timezone":"Europe/Sarajevo",
    "iso:country":"BA",
    "wof:name":"Ripici",
    "wof:placetype":"locality"
},
  "geometry": {"coordinates":[17.42556,44.07195],"type":"Point"}
}