{
  "type": "Feature",
  "properties": {
    "gn:admin1_code":"01",
    "gn:asciiname":"Berkusa",
    "gn:country_code":"BA",
    "gn:dem":805,
    "gn:feature_class":"P",
    "gn:feature_code":"PPL",
    "gn:name":"Berku\u0161a",
    "gn:population":0,
    "gn:timezone":"Europe/Sarajevo",
    "iso:country":"BA",
    "wof:name":"Berkusa",
    "wof:placetype":"locality"
},
  "geometry": {"coordinates":[18.42889,43.84694],"type":"Point"}
}