{
  "type": "Feature",
  "properties": {
    "gn:admin1_code":"02",
    "gn:asciiname":"Mihaljevici",
    "gn:country_code":"BA",
    "gn:dem":172,
    "gn:feature_class":"P",
    "gn:feature_code":"PPL",
    "gn:name":"Mihaljevi\u0107i",
    "gn:population":0,
    "gn:timezone":"Europe/Sarajevo",
    "iso:country":"BA",
    "name:bos_x_preferred":[
        "Mihaljevi\u0107i"
    ],
    "name:bul_x_preferred":[
        "\u041c\u0438\u0445\u0430\u043b\u0435\u0432\u0438\u0447\u0438"
    ],
    "name:ceb_x_preferred":[
        "Mihaljevi\u0107i"
    ],
    "name:fra_x_preferred":[
        "Mihaljevi\u0107i"
    ],
    "name:rus_x_preferred":[
        "\u041c\u0438\u0445\u0430\u043b\u0435\u0432\u0438\u0447\u0438"
    ],
    "name:srp_x_preferred":[
        "\u041c\u0438\u0445\u0430\u0459\u0435\u0432\u0438\u045b\u0438"
    ],
    "name:swe_x_preferred":[
        "Mihaljevi\u0107i"
    ],
    "name:und_x_variant":[
        "Mihaljevi\u0107i"
    ],
    "wof:name":"Mihaljevici",
    "wof:placetype":"locality"
},
  "geometry": {"coordinates":[19.34549,44.20006],"type":"Point"}
}