{
  "type": "Feature",
  "properties": {
    "gn:admin1_code":"01",
    "gn:asciiname":"Donja Ljubina",
    "gn:country_code":"BA",
    "gn:dem":543,
    "gn:feature_class":"P",
    "gn:feature_code":"PPL",
    "gn:name":"Donja Ljubina",
    "gn:population":0,
    "gn:timezone":"Europe/Sarajevo",
    "iso:country":"BA",
    "wof:name":"Donja Ljubina",
    "wof:placetype":"locality"
},
  "geometry": {"coordinates":[18.32416,43.92259],"type":"Point"}
}