{
  "type": "Feature",
  "properties": {
    "gn:admin1_code":"01",
    "gn:asciiname":"Otigosce",
    "gn:country_code":"BA",
    "gn:dem":817,
    "gn:feature_class":"P",
    "gn:feature_code":"PPL",
    "gn:name":"Otigo\u0161\u0107e",
    "gn:population":0,
    "gn:timezone":"Europe/Sarajevo",
    "iso:country":"BA",
    "name:und_x_variant":[
        "Otigo\u0161\u0107e"
    ],
    "wof:name":"Otigosce",
    "wof:placetype":"locality"
},
  "geometry": {"coordinates":[17.97437,43.9199],"type":"Point"}
}