{
  "type": "Feature",
  "properties": {
    "gn:admin1_code":"02",
    "gn:asciiname":"Jagodici",
    "gn:country_code":"BA",
    "gn:dem":343,
    "gn:feature_class":"P",
    "gn:feature_code":"PPL",
    "gn:name":"Jagodi\u0107i",
    "gn:population":0,
    "gn:timezone":"Europe/Sarajevo",
    "iso:country":"BA",
    "wof:name":"Jagodici",
    "wof:placetype":"locality"
},
  "geometry": {"coordinates":[17.47902,44.70514],"type":"Point"}
}