{
  "type": "Feature",
  "properties": {
    "gn:admin1_code":"02",
    "gn:asciiname":"Becarevici",
    "gn:country_code":"BA",
    "gn:dem":204,
    "gn:feature_class":"P",
    "gn:feature_code":"PPL",
    "gn:name":"Be\u0107arevi\u0107i",
    "gn:population":0,
    "gn:timezone":"Europe/Sarajevo",
    "iso:country":"BA",
    "wof:name":"Becarevici",
    "wof:placetype":"locality"
},
  "geometry": {"coordinates":[17.8334,44.85573],"type":"Point"}
}