{
  "type": "Feature",
  "properties": {
    "gn:admin1_code":"02",
    "gn:asciiname":"Stopici",
    "gn:country_code":"BA",
    "gn:dem":209,
    "gn:feature_class":"P",
    "gn:feature_code":"PPL",
    "gn:name":"Stopi\u0107i",
    "gn:population":0,
    "gn:timezone":"Europe/Sarajevo",
    "iso:country":"BA",
    "name:bos_x_preferred":[
        "Stopi\u0107i"
    ],
    "name:fra_x_preferred":[
        "Stopi\u0107i"
    ],
    "name:rus_x_preferred":[
        "\u0421\u0442\u043e\u043f\u0438\u0447\u0438"
    ],
    "name:srp_x_preferred":[
        "\u0421\u0442\u043e\u043f\u0438\u045b\u0438"
    ],
    "wof:name":"Stopici",
    "wof:placetype":"locality"
},
  "geometry": {"coordinates":[17.98931,44.858],"type":"Point"}
}