{
  "type": "Feature",
  "properties": {
    "gn:admin1_code":"02",
    "gn:asciiname":"Stopici",
    "gn:country_code":"BA",
    "gn:dem":209,
    "gn:feature_class":"P",
    "gn:feature_code":"PPL",
    "gn:name":"Stopi\u0107i",
    "gn:population":0,
    "gn:timezone":"Europe/Sarajevo",
    "iso:country":"BA",
    "name:und_x_variant":[
        "Stopi\u0107i"
    ],
    "wof:name":"Stopici",
    "wof:placetype":"locality"
},
  "geometry": {"coordinates":[17.98931,44.858],"type":"Point"}
}