{
  "type": "Feature",
  "properties": {
    "gn:admin1_code":"02",
    "gn:asciiname":"Boskovici",
    "gn:country_code":"BA",
    "gn:dem":152,
    "gn:feature_class":"P",
    "gn:feature_code":"PPL",
    "gn:name":"Bo\u0161kovi\u0107i",
    "gn:population":0,
    "gn:timezone":"Europe/Sarajevo",
    "iso:country":"BA",
    "wof:name":"Boskovici",
    "wof:placetype":"locality"
},
  "geometry": {"coordinates":[18.2057,44.94763],"type":"Point"}
}