{
  "type": "Feature",
  "properties": {
    "gn:admin1_code":"02",
    "gn:asciiname":"Gavrici",
    "gn:country_code":"BA",
    "gn:dem":789,
    "gn:feature_class":"P",
    "gn:feature_code":"PPL",
    "gn:name":"Gavri\u0107i",
    "gn:population":0,
    "gn:timezone":"Europe/Sarajevo",
    "iso:country":"BA",
    "wof:name":"Gavrici",
    "wof:placetype":"locality"
},
  "geometry": {"coordinates":[17.42696,44.43511],"type":"Point"}
}