{
  "type": "Feature",
  "properties": {
    "gn:admin1_code":"01",
    "gn:asciiname":"Smrcevice",
    "gn:country_code":"BA",
    "gn:dem":1307,
    "gn:feature_class":"P",
    "gn:feature_code":"PPL",
    "gn:name":"Smr\u010device",
    "gn:population":0,
    "gn:timezone":"Europe/Sarajevo",
    "iso:country":"BA",
    "name:bos_x_preferred":[
        "Smr\u010device"
    ],
    "name:fra_x_preferred":[
        "Smr\u010device"
    ],
    "name:hrv_x_preferred":[
        "Smr\u010device"
    ],
    "name:srp_x_preferred":[
        "\u0421\u043c\u0440\u0447\u0435\u0432\u0438\u0446\u0435"
    ],
    "name:und_x_variant":[
        "Smr\u010devica"
    ],
    "wof:name":"Smrcevice",
    "wof:placetype":"locality"
},
  "geometry": {"coordinates":[17.77732,43.87849],"type":"Point"}
}