{
  "type": "Feature",
  "properties": {
    "gn:admin1_code":"01",
    "gn:asciiname":"Smrcevice",
    "gn:country_code":"BA",
    "gn:dem":1307,
    "gn:feature_class":"P",
    "gn:feature_code":"PPL",
    "gn:name":"Smr\u010device",
    "gn:population":0,
    "gn:timezone":"Europe/Sarajevo",
    "iso:country":"BA",
    "name:und_x_variant":[
        "Smr\u010devica",
        "Smr\u010device"
    ],
    "wof:name":"Smrcevice",
    "wof:placetype":"locality"
},
  "geometry": {"coordinates":[17.77732,43.87849],"type":"Point"}
}