{
  "type": "Feature",
  "properties": {
    "gn:admin1_code":"01",
    "gn:asciiname":"Nadgaj",
    "gn:country_code":"BA",
    "gn:dem":945,
    "gn:feature_class":"P",
    "gn:feature_code":"PPL",
    "gn:name":"Nadgaj",
    "gn:population":0,
    "gn:timezone":"Europe/Sarajevo",
    "iso:country":"BA",
    "wof:name":"Nadgaj",
    "wof:placetype":"locality"
},
  "geometry": {"coordinates":[18.54966,44.0513],"type":"Point"}
}