{
  "type": "Feature",
  "properties": {
    "gn:admin1_code":"02",
    "gn:asciiname":"Kolun",
    "gn:country_code":"BA",
    "gn:dem":909,
    "gn:feature_class":"P",
    "gn:feature_code":"PPLL",
    "gn:name":"Kolun",
    "gn:population":0,
    "gn:timezone":"Europe/Sarajevo",
    "iso:country":"BA",
    "name:bos_x_preferred":[
        "Kolun"
    ],
    "name:fra_x_preferred":[
        "Kolun"
    ],
    "name:hrv_x_preferred":[
        "Kolun"
    ],
    "name:srp_x_preferred":[
        "\u041a\u043e\u043b\u0443\u043d"
    ],
    "wof:name":"Kolun",
    "wof:placetype":"locality"
},
  "geometry": {"coordinates":[18.65615,43.57883],"type":"Point"}
}