{
  "type": "Feature",
  "properties": {
    "gn:admin1_code":"02",
    "gn:asciiname":"Stanisevac",
    "gn:country_code":"BA",
    "gn:dem":966,
    "gn:feature_class":"P",
    "gn:feature_code":"PPL",
    "gn:name":"Stani\u0161evac",
    "gn:population":0,
    "gn:timezone":"Europe/Sarajevo",
    "iso:country":"BA",
    "name:und_x_variant":[
        "Stani\u0161evac"
    ],
    "wof:name":"Stanisevac",
    "wof:placetype":"locality"
},
  "geometry": {"coordinates":[19.42281,43.77258],"type":"Point"}
}