{
  "type": "Feature",
  "properties": {
    "gn:admin1_code":"02",
    "gn:asciiname":"Stanisevac",
    "gn:country_code":"BA",
    "gn:dem":966,
    "gn:feature_class":"P",
    "gn:feature_code":"PPL",
    "gn:name":"Stani\u0161evac",
    "gn:population":0,
    "gn:timezone":"Europe/Sarajevo",
    "iso:country":"BA",
    "name:bos_x_preferred":[
        "Stani\u0161evac"
    ],
    "name:fra_x_preferred":[
        "Stani\u0161evac"
    ],
    "name:hrv_x_preferred":[
        "Stani\u0161evac"
    ],
    "name:srp_x_preferred":[
        "\u0421\u0442\u0430\u043d\u0438\u0448\u0435\u0432\u0430\u0446"
    ],
    "wof:name":"Stanisevac",
    "wof:placetype":"locality"
},
  "geometry": {"coordinates":[19.42281,43.77258],"type":"Point"}
}