{
  "type": "Feature",
  "properties": {
    "gn:admin1_code":"02",
    "gn:asciiname":"Podcardak",
    "gn:country_code":"BA",
    "gn:dem":1069,
    "gn:feature_class":"P",
    "gn:feature_code":"PPL",
    "gn:name":"Pod\u010dardak",
    "gn:population":0,
    "gn:timezone":"Europe/Sarajevo",
    "iso:country":"BA",
    "wof:name":"Podcardak",
    "wof:placetype":"locality"
},
  "geometry": {"coordinates":[18.8768,44.10869],"type":"Point"}
}