{
  "type": "Feature",
  "properties": {
    "gn:admin1_code":"02",
    "gn:asciiname":"Glusci",
    "gn:country_code":"BA",
    "gn:dem":479,
    "gn:feature_class":"P",
    "gn:feature_code":"PPL",
    "gn:name":"Glu\u0161ci",
    "gn:population":0,
    "gn:timezone":"Europe/Sarajevo",
    "iso:country":"BA",
    "wof:name":"Glusci",
    "wof:placetype":"locality"
},
  "geometry": {"coordinates":[16.46422,44.8625],"type":"Point"}
}