{
  "type": "Feature",
  "properties": {
    "gn:admin1_code":"01",
    "gn:asciiname":"Dunderi",
    "gn:country_code":"BA",
    "gn:dem":662,
    "gn:feature_class":"P",
    "gn:feature_code":"PPL",
    "gn:name":"Dunderi",
    "gn:population":0,
    "gn:timezone":"Europe/Sarajevo",
    "iso:country":"BA",
    "wof:name":"Dunderi",
    "wof:placetype":"locality"
},
  "geometry": {"coordinates":[18.03149,44.03021],"type":"Point"}
}