{
  "type": "Feature",
  "properties": {
    "gn:admin1_code":"01",
    "gn:asciiname":"Kamenica",
    "gn:country_code":"BA",
    "gn:dem":1019,
    "gn:feature_class":"P",
    "gn:feature_code":"PPL",
    "gn:name":"Kamenica",
    "gn:population":0,
    "gn:timezone":"Europe/Sarajevo",
    "iso:country":"BA",
    "wof:name":"Kamenica",
    "wof:placetype":"locality"
},
  "geometry": {"coordinates":[18.47444,44.09389],"type":"Point"}
}