{
  "type": "Feature",
  "properties": {
    "gn:admin1_code":"02",
    "gn:asciiname":"Ilici",
    "gn:country_code":"BA",
    "gn:dem":1244,
    "gn:feature_class":"P",
    "gn:feature_code":"PPL",
    "gn:name":"Ili\u0107i",
    "gn:population":0,
    "gn:timezone":"Europe/Sarajevo",
    "iso:country":"BA",
    "name:ceb_x_preferred":[
        "Ilici"
    ],
    "name:swe_x_preferred":[
        "Ilici"
    ],
    "wof:name":"Ilici",
    "wof:placetype":"locality"
},
  "geometry": {"coordinates":[17.12324,44.10686],"type":"Point"}
}