{
  "type": "Feature",
  "properties": {
    "gn:admin1_code":"01",
    "gn:asciiname":"Zolje",
    "gn:country_code":"BA",
    "gn:dem":358,
    "gn:feature_class":"P",
    "gn:feature_code":"PPL",
    "gn:name":"Zolje",
    "gn:population":0,
    "gn:timezone":"Europe/Sarajevo",
    "iso:country":"BA",
    "name:bos_x_preferred":[
        "Zolje"
    ],
    "name:ceb_x_preferred":[
        "Zolje"
    ],
    "name:fra_x_preferred":[
        "Zolje"
    ],
    "name:hrv_x_preferred":[
        "Zolje"
    ],
    "name:srp_x_preferred":[
        "\u0417\u043e\u0459\u0435"
    ],
    "name:swe_x_preferred":[
        "Zolje"
    ],
    "wof:name":"Zolje",
    "wof:placetype":"locality"
},
  "geometry": {"coordinates":[18.21047,44.78026],"type":"Point"}
}