{
  "type": "Feature",
  "properties": {
    "gn:admin1_code":"01",
    "gn:asciiname":"Zolje",
    "gn:country_code":"BA",
    "gn:dem":358,
    "gn:feature_class":"P",
    "gn:feature_code":"PPL",
    "gn:name":"Zolje",
    "gn:population":0,
    "gn:timezone":"Europe/Sarajevo",
    "iso:country":"BA",
    "wof:name":"Zolje",
    "wof:placetype":"locality"
},
  "geometry": {"coordinates":[18.21047,44.78026],"type":"Point"}
}