{
  "type": "Feature",
  "properties": {
    "gn:admin1_code":"02",
    "gn:asciiname":"Spanici",
    "gn:country_code":"BA",
    "gn:dem":310,
    "gn:feature_class":"P",
    "gn:feature_code":"PPL",
    "gn:name":"Spani\u0107i",
    "gn:population":0,
    "gn:timezone":"Europe/Sarajevo",
    "iso:country":"BA",
    "wof:name":"Spanici",
    "wof:placetype":"locality"
},
  "geometry": {"coordinates":[17.69474,44.77078],"type":"Point"}
}