{
  "type": "Feature",
  "properties": {
    "gn:admin1_code":"02",
    "gn:asciiname":"Dobra Voda",
    "gn:country_code":"BA",
    "gn:dem":306,
    "gn:feature_class":"P",
    "gn:feature_code":"PPLL",
    "gn:name":"Dobra Voda",
    "gn:population":0,
    "gn:timezone":"Europe/Sarajevo",
    "iso:country":"BA",
    "wof:name":"Dobra Voda",
    "wof:placetype":"locality"
},
  "geometry": {"coordinates":[18.14383,45.00365],"type":"Point"}
}