{
  "type": "Feature",
  "properties": {
    "gn:admin1_code":"01",
    "gn:asciiname":"Cufurovici",
    "gn:country_code":"BA",
    "gn:dem":208,
    "gn:feature_class":"P",
    "gn:feature_code":"PPL",
    "gn:name":"\u0106ufurovi\u0107i",
    "gn:population":0,
    "gn:timezone":"Europe/Sarajevo",
    "iso:country":"BA",
    "wof:name":"Cufurovici",
    "wof:placetype":"locality"
},
  "geometry": {"coordinates":[15.91394,45.15206],"type":"Point"}
}