{
  "type": "Feature",
  "properties": {
    "gn:admin1_code":"02",
    "gn:asciiname":"Podgaj",
    "gn:country_code":"BA",
    "gn:dem":323,
    "gn:feature_class":"P",
    "gn:feature_code":"PPL",
    "gn:name":"Podgaj",
    "gn:population":0,
    "gn:timezone":"Europe/Sarajevo",
    "iso:country":"BA",
    "wof:name":"Podgaj",
    "wof:placetype":"locality"
},
  "geometry": {"coordinates":[19.11696,44.57425],"type":"Point"}
}