{
  "type": "Feature",
  "properties": {
    "gn:admin1_code":"02",
    "gn:asciiname":"Kotezi",
    "gn:country_code":"BA",
    "gn:dem":406,
    "gn:feature_class":"P",
    "gn:feature_code":"PPL",
    "gn:name":"Kotezi",
    "gn:population":0,
    "gn:timezone":"Europe/Sarajevo",
    "iso:country":"BA",
    "wof:name":"Kotezi",
    "wof:placetype":"locality"
},
  "geometry": {"coordinates":[18.00815,42.91093],"type":"Point"}
}