{
  "type": "Feature",
  "properties": {
    "gn:admin1_code":"01",
    "gn:asciiname":"Culjkova Njiva",
    "gn:country_code":"BA",
    "gn:dem":180,
    "gn:feature_class":"P",
    "gn:feature_code":"PPL",
    "gn:name":"\u010culjkova Njiva",
    "gn:population":0,
    "gn:timezone":"Europe/Sarajevo",
    "iso:country":"BA",
    "wof:name":"Culjkova Njiva",
    "wof:placetype":"locality"
},
  "geometry": {"coordinates":[17.45051,43.28316],"type":"Point"}
}