{
  "type": "Feature",
  "properties": {
    "gn:admin1_code":"01",
    "gn:asciiname":"Brezik",
    "gn:country_code":"BA",
    "gn:dem":374,
    "gn:feature_class":"P",
    "gn:feature_code":"PPL",
    "gn:name":"Brezik",
    "gn:population":0,
    "gn:timezone":"Europe/Sarajevo",
    "iso:country":"BA",
    "name:bos_x_preferred":[
        "Brezik"
    ],
    "name:ceb_x_preferred":[
        "Brezik"
    ],
    "name:fra_x_preferred":[
        "Brezik"
    ],
    "name:hrv_x_preferred":[
        "Brezik"
    ],
    "name:hun_x_preferred":[
        "Brezik"
    ],
    "name:nld_x_preferred":[
        "Brezik"
    ],
    "name:slv_x_preferred":[
        "Brezik"
    ],
    "name:spa_x_preferred":[
        "Brezik"
    ],
    "name:srp_x_preferred":[
        "\u0411\u0440\u0435\u0437\u0438\u043a"
    ],
    "name:swe_x_preferred":[
        "Brezik"
    ],
    "wof:name":"Brezik",
    "wof:placetype":"locality"
},
  "geometry": {"coordinates":[16.09507,44.92401],"type":"Point"}
}