{
  "type": "Feature",
  "properties": {
    "gn:admin1_code":"01",
    "gn:asciiname":"Lokve",
    "gn:country_code":"BA",
    "gn:dem":797,
    "gn:feature_class":"P",
    "gn:feature_code":"PPL",
    "gn:name":"Lokve",
    "gn:population":0,
    "gn:timezone":"Europe/Sarajevo",
    "iso:country":"BA",
    "name:bos_x_preferred":[
        "Lokve"
    ],
    "name:ceb_x_preferred":[
        "Lokve"
    ],
    "name:fra_x_preferred":[
        "Lokve"
    ],
    "name:hrv_x_preferred":[
        "Lokve"
    ],
    "wof:name":"Lokve",
    "wof:placetype":"locality"
},
  "geometry": {"coordinates":[18.20111,43.78222],"type":"Point"}
}