{
  "type": "Feature",
  "properties": {
    "gn:country":"BA",
    "gn:fcode":"PPL",
    "gn:population":5666,
    "iso:country":"BA",
    "qs:name":"Tesanjka",
    "qs:name_adm0":"Bosna i Hercegovina",
    "qs:name_adm1":"Federacija Bosne I Hercegovine",
    "qs:photos_9r":0,
    "qs:photos_sr":0,
    "qs:placetype":"Town",
    "qs:pop_sr":"5",
    "wof:name":"Tesanjka",
    "wof:placetype":"locality",
    "wof:population":5666
},
  "geometry": {"coordinates":[18.01109,44.67228],"type":"Point"}
}