{
  "type": "Feature",
  "properties": {
    "gn:admin1_code":"02",
    "gn:asciiname":"Brda",
    "gn:country_code":"BA",
    "gn:dem":494,
    "gn:feature_class":"P",
    "gn:feature_code":"PPL",
    "gn:name":"Brda",
    "gn:population":0,
    "gn:timezone":"Europe/Sarajevo",
    "iso:country":"BA",
    "name:bos_x_preferred":[
        "Brda"
    ],
    "name:ceb_x_preferred":[
        "Brda"
    ],
    "name:ces_x_preferred":[
        "Brda"
    ],
    "name:deu_x_preferred":[
        "Brda"
    ],
    "name:fra_x_preferred":[
        "Brda"
    ],
    "name:heb_x_preferred":[
        "\u05d1\u05e8\u05d3\u05d4"
    ],
    "name:hrv_x_preferred":[
        "Brda"
    ],
    "name:ita_x_preferred":[
        "Brda"
    ],
    "name:nld_x_preferred":[
        "Brda"
    ],
    "name:pol_x_preferred":[
        "Brda"
    ],
    "name:ron_x_preferred":[
        "Brda"
    ],
    "name:rus_x_preferred":[
        "\u0411\u0440\u0434\u0430"
    ],
    "name:slv_x_preferred":[
        "Brda"
    ],
    "name:srp_x_preferred":[
        "\u0411\u0440\u0434\u0430"
    ],
    "name:swe_x_preferred":[
        "Brda"
    ],
    "name:vie_x_preferred":[
        "Brda"
    ],
    "wof:name":"Brda",
    "wof:placetype":"locality"
},
  "geometry": {"coordinates":[16.47912,44.85878],"type":"Point"}
}