{
  "type": "Feature",
  "properties": {
    "gn:admin1_code":"01",
    "gn:asciiname":"Medojevici",
    "gn:country_code":"BA",
    "gn:dem":1112,
    "gn:feature_class":"P",
    "gn:feature_code":"PPL",
    "gn:name":"Medojevi\u0107i",
    "gn:population":0,
    "gn:timezone":"Europe/Sarajevo",
    "iso:country":"BA",
    "name:bos_x_preferred":[
        "Medojevi\u0107i"
    ],
    "name:fra_x_preferred":[
        "Medojevi\u0107i"
    ],
    "name:hrv_x_preferred":[
        "Medojevi\u0107i"
    ],
    "name:pol_x_preferred":[
        "Medojevi\u0107i"
    ],
    "name:und_x_variant":[
        "Medojevi\u0107i"
    ],
    "wof:name":"Medojevici",
    "wof:placetype":"locality"
},
  "geometry": {"coordinates":[18.4724,44.01467],"type":"Point"}
}