{
  "type": "Feature",
  "properties": {
    "gn:admin1_code":"01",
    "gn:asciiname":"Nikolici",
    "gn:country_code":"BA",
    "gn:dem":405,
    "gn:feature_class":"P",
    "gn:feature_code":"PPL",
    "gn:name":"Nikoli\u0107i",
    "gn:population":0,
    "gn:timezone":"Europe/Sarajevo",
    "iso:country":"BA",
    "wof:name":"Nikolici",
    "wof:placetype":"locality"
},
  "geometry": {"coordinates":[18.66674,44.61253],"type":"Point"}
}