{
  "type": "Feature",
  "properties": {
    "gn:admin1_code":"02",
    "gn:asciiname":"Ljeskov Dub",
    "gn:country_code":"BA",
    "gn:dem":1030,
    "gn:feature_class":"P",
    "gn:feature_code":"PPLL",
    "gn:name":"Ljeskov Dub",
    "gn:population":0,
    "gn:timezone":"Europe/Sarajevo",
    "iso:country":"BA",
    "name:bos_x_preferred":[
        "Ljeskov Dub"
    ],
    "name:fra_x_preferred":[
        "Ljeskov Dub"
    ],
    "name:hrv_x_preferred":[
        "Ljeskov Dub"
    ],
    "name:srp_x_preferred":[
        "\u0409\u0435\u0441\u043a\u043e\u0432 \u0414\u0443\u0431"
    ],
    "wof:name":"Ljeskov Dub",
    "wof:placetype":"locality"
},
  "geometry": {"coordinates":[18.36257,43.2253],"type":"Point"}
}