{
  "type": "Feature",
  "properties": {
    "gn:admin1_code":"02",
    "gn:asciiname":"Kostajnica",
    "gn:country_code":"BA",
    "gn:dem":146,
    "gn:feature_class":"P",
    "gn:feature_code":"PPL",
    "gn:name":"Kostajnica",
    "gn:population":0,
    "gn:timezone":"Europe/Sarajevo",
    "iso:country":"BA",
    "wof:name":"Kostajnica",
    "wof:placetype":"locality"
},
  "geometry": {"coordinates":[18.107,44.74691],"type":"Point"}
}