{
  "type": "Feature",
  "properties": {
    "gn:admin1_code":"01",
    "gn:asciiname":"Arnauti",
    "gn:country_code":"BA",
    "gn:dem":767,
    "gn:feature_class":"P",
    "gn:feature_code":"PPL",
    "gn:name":"Arnauti",
    "gn:population":0,
    "gn:timezone":"Europe/Sarajevo",
    "iso:country":"BA",
    "wof:name":"Arnauti",
    "wof:placetype":"locality"
},
  "geometry": {"coordinates":[17.50642,44.03862],"type":"Point"}
}