{
  "type": "Feature",
  "properties": {
    "gn:admin1_code":"01",
    "gn:asciiname":"Arnauti",
    "gn:country_code":"BA",
    "gn:dem":767,
    "gn:feature_class":"P",
    "gn:feature_code":"PPL",
    "gn:name":"Arnauti",
    "gn:population":0,
    "gn:timezone":"Europe/Sarajevo",
    "iso:country":"BA",
    "name:bos_x_preferred":[
        "Arnauti"
    ],
    "name:fra_x_preferred":[
        "Arnauti"
    ],
    "name:hrv_x_preferred":[
        "Arnauti"
    ],
    "name:srp_x_preferred":[
        "\u0410\u0440\u043d\u0430\u0443\u0442\u0438"
    ],
    "wof:name":"Arnauti",
    "wof:placetype":"locality"
},
  "geometry": {"coordinates":[17.50642,44.03862],"type":"Point"}
}