{
  "type": "Feature",
  "properties": {
    "gn:admin1_code":"01",
    "gn:asciiname":"Matkovici",
    "gn:country_code":"BA",
    "gn:dem":725,
    "gn:feature_class":"P",
    "gn:feature_code":"PPL",
    "gn:name":"Matkovi\u0107i",
    "gn:population":0,
    "gn:timezone":"Europe/Sarajevo",
    "iso:country":"BA",
    "wof:name":"Matkovici",
    "wof:placetype":"locality"
},
  "geometry": {"coordinates":[16.77667000000001,43.92742],"type":"Point"}
}