{
  "type": "Feature",
  "properties": {
    "gn:admin1_code":"02",
    "gn:asciiname":"Cairi",
    "gn:country_code":"BA",
    "gn:dem":86,
    "gn:feature_class":"P",
    "gn:feature_code":"PPL",
    "gn:name":"\u010cairi",
    "gn:population":0,
    "gn:timezone":"Europe/Sarajevo",
    "iso:country":"BA",
    "wof:name":"Cairi",
    "wof:placetype":"locality"
},
  "geometry": {"coordinates":[17.32614,45.1489],"type":"Point"}
}