{
  "type": "Feature",
  "properties": {
    "gn:admin1_code":"01",
    "gn:asciiname":"Bukve",
    "gn:country_code":"BA",
    "gn:dem":596,
    "gn:feature_class":"P",
    "gn:feature_code":"PPL",
    "gn:name":"Bukve",
    "gn:population":0,
    "gn:timezone":"Europe/Sarajevo",
    "iso:country":"BA",
    "wof:name":"Bukve",
    "wof:placetype":"locality"
},
  "geometry": {"coordinates":[18.17279,44.03516],"type":"Point"}
}