{
  "type": "Feature",
  "properties": {
    "gn:admin1_code":"02",
    "gn:asciiname":"Rudino Brdo",
    "gn:country_code":"BA",
    "gn:dem":803,
    "gn:feature_class":"P",
    "gn:feature_code":"PPL",
    "gn:name":"Rudino Brdo",
    "gn:population":0,
    "gn:timezone":"Europe/Sarajevo",
    "iso:country":"BA",
    "wof:name":"Rudino Brdo",
    "wof:placetype":"locality"
},
  "geometry": {"coordinates":[18.82486,43.4669],"type":"Point"}
}