{
  "type": "Feature",
  "properties": {
    "gn:admin1_code":"01",
    "gn:asciiname":"Solde",
    "gn:country_code":"BA",
    "gn:dem":823,
    "gn:feature_class":"P",
    "gn:feature_code":"PPL",
    "gn:name":"Solde",
    "gn:population":0,
    "gn:timezone":"Europe/Sarajevo",
    "iso:country":"BA",
    "wof:name":"Solde",
    "wof:placetype":"locality"
},
  "geometry": {"coordinates":[17.46897,43.44051],"type":"Point"}
}