{
  "type": "Feature",
  "properties": {
    "gn:admin1_code":"01",
    "gn:asciiname":"Potoci",
    "gn:country_code":"BA",
    "gn:dem":324,
    "gn:feature_class":"P",
    "gn:feature_code":"PPL",
    "gn:name":"Potoci",
    "gn:population":0,
    "gn:timezone":"Europe/Sarajevo",
    "iso:country":"BA",
    "name:bos_x_preferred":[
        "Potoci"
    ],
    "name:ceb_x_preferred":[
        "Potoci"
    ],
    "name:deu_x_preferred":[
        "Potoci"
    ],
    "name:fra_x_preferred":[
        "Potoci"
    ],
    "name:hrv_x_preferred":[
        "Potoci"
    ],
    "name:rus_x_preferred":[
        "\u041f\u043e\u0442\u043e\u0446\u0438"
    ],
    "name:slv_x_preferred":[
        "Potoci"
    ],
    "name:srp_x_preferred":[
        "\u041f\u043e\u0442\u043e\u0446\u0438"
    ],
    "name:swe_x_preferred":[
        "Potoci"
    ],
    "wof:name":"Potoci",
    "wof:placetype":"locality"
},
  "geometry": {"coordinates":[16.32731,44.81338],"type":"Point"}
}