{
  "type": "Feature",
  "properties": {
    "gn:admin1_code":"01",
    "gn:asciiname":"Ilikov Palez",
    "gn:country_code":"BA",
    "gn:dem":1120,
    "gn:feature_class":"P",
    "gn:feature_code":"PPL",
    "gn:name":"Ilikov Pale\u017e",
    "gn:population":0,
    "gn:timezone":"Europe/Sarajevo",
    "iso:country":"BA",
    "wof:name":"Ilikov Palez",
    "wof:placetype":"locality"
},
  "geometry": {"coordinates":[16.65081,44.34612],"type":"Point"}
}