{
  "type": "Feature",
  "properties": {
    "gn:admin1_code":"01",
    "gn:asciiname":"Skrti",
    "gn:country_code":"BA",
    "gn:dem":1011,
    "gn:feature_class":"P",
    "gn:feature_code":"PPL",
    "gn:name":"Skrti",
    "gn:population":0,
    "gn:timezone":"Europe/Sarajevo",
    "iso:country":"BA",
    "name:und_x_variant":[
        "Skrte",
        "Skrti"
    ],
    "wof:name":"Skrti",
    "wof:placetype":"locality"
},
  "geometry": {"coordinates":[17.43371,43.94711],"type":"Point"}
}