{
  "type": "Feature",
  "properties": {
    "gn:admin1_code":"02",
    "gn:asciiname":"Celici",
    "gn:country_code":"BA",
    "gn:dem":235,
    "gn:feature_class":"P",
    "gn:feature_code":"PPL",
    "gn:name":"\u010celi\u0107i",
    "gn:population":0,
    "gn:timezone":"Europe/Sarajevo",
    "iso:country":"BA",
    "wof:name":"Celici",
    "wof:placetype":"locality"
},
  "geometry": {"coordinates":[17.81365,44.80037],"type":"Point"}
}