{
  "type": "Feature",
  "properties": {
    "gn:admin1_code":"01",
    "gn:asciiname":"Brdani",
    "gn:country_code":"BA",
    "gn:dem":284,
    "gn:feature_class":"P",
    "gn:feature_code":"PPL",
    "gn:name":"Br\u0111ani",
    "gn:population":0,
    "gn:timezone":"Europe/Sarajevo",
    "iso:country":"BA",
    "wof:name":"Brdani",
    "wof:placetype":"locality"
},
  "geometry": {"coordinates":[18.01237,44.50506],"type":"Point"}
}