{
  "type": "Feature",
  "properties": {
    "gn:admin1_code":"02",
    "gn:asciiname":"Pervan Donji",
    "gn:country_code":"BA",
    "gn:dem":283,
    "gn:feature_class":"P",
    "gn:feature_code":"PPLL",
    "gn:name":"Pervan Donji",
    "gn:population":0,
    "gn:timezone":"Europe/Sarajevo",
    "iso:country":"BA",
    "name:bos_x_preferred":[
        "Pervan Donji"
    ],
    "name:ceb_x_preferred":[
        "Pervan Donji"
    ],
    "name:fra_x_preferred":[
        "Pervan Donji"
    ],
    "name:hrv_x_preferred":[
        "Pervan Donji"
    ],
    "name:rus_x_preferred":[
        "\u041f\u0435\u0440\u0432\u0430\u043d-\u0414\u043e\u043d\u0438"
    ],
    "name:slv_x_preferred":[
        "Pervan Donji"
    ],
    "name:srp_x_preferred":[
        "\u041f\u0435\u0440\u0432\u0430\u043d \u0414\u043e\u045a\u0438"
    ],
    "name:swe_x_preferred":[
        "Pervan Donji"
    ],
    "name:und_x_variant":[
        "Donji Pervan"
    ],
    "wof:name":"Pervan Donji",
    "wof:placetype":"locality"
},
  "geometry": {"coordinates":[16.98625,44.77349],"type":"Point"}
}