{
  "type": "Feature",
  "properties": {
    "gn:admin1_code":"01",
    "gn:asciiname":"Cavarov Stan",
    "gn:country_code":"BA",
    "gn:dem":868,
    "gn:feature_class":"P",
    "gn:feature_code":"PPL",
    "gn:name":"\u0106avarov Stan",
    "gn:population":0,
    "gn:timezone":"Europe/Sarajevo",
    "iso:country":"BA",
    "name:und_x_variant":[
        "\u0106avarov Stan"
    ],
    "wof:name":"Cavarov Stan",
    "wof:placetype":"locality"
},
  "geometry": {"coordinates":[17.24261,43.69527],"type":"Point"}
}