{
  "type": "Feature",
  "properties": {
    "gn:admin1_code":"01",
    "gn:asciiname":"Cavarov Stan",
    "gn:country_code":"BA",
    "gn:dem":868,
    "gn:feature_class":"P",
    "gn:feature_code":"PPL",
    "gn:name":"\u0106avarov Stan",
    "gn:population":0,
    "gn:timezone":"Europe/Sarajevo",
    "iso:country":"BA",
    "name:bos_x_preferred":[
        "\u0106avarov Stan"
    ],
    "name:ceb_x_preferred":[
        "\u0106avarov Stan"
    ],
    "name:fra_x_preferred":[
        "\u0106avarov Stan"
    ],
    "name:hrv_x_preferred":[
        "\u0106avarov Stan"
    ],
    "name:srp_x_preferred":[
        "\u040b\u0430\u0432\u0430\u0440\u043e\u0432 \u0421\u0442\u0430\u043d"
    ],
    "name:swe_x_preferred":[
        "\u0106avarov Stan"
    ],
    "wof:name":"Cavarov Stan",
    "wof:placetype":"locality"
},
  "geometry": {"coordinates":[17.24261,43.69527],"type":"Point"}
}