{
  "type": "Feature",
  "properties": {
    "gn:admin1_code":"01",
    "gn:asciiname":"Hasanovici",
    "gn:country_code":"BA",
    "gn:dem":386,
    "gn:feature_class":"P",
    "gn:feature_code":"PPL",
    "gn:name":"Hasanovi\u0107i",
    "gn:population":0,
    "gn:timezone":"Europe/Sarajevo",
    "iso:country":"BA",
    "wof:name":"Hasanovici",
    "wof:placetype":"locality"
},
  "geometry": {"coordinates":[18.25043,44.4652],"type":"Point"}
}