{
  "type": "Feature",
  "properties": {
    "gn:admin1_code":"02",
    "gn:asciiname":"Mirjanovici",
    "gn:country_code":"BA",
    "gn:dem":800,
    "gn:feature_class":"P",
    "gn:feature_code":"PPLL",
    "gn:name":"Mirjanovi\u0107i",
    "gn:population":0,
    "gn:timezone":"Europe/Sarajevo",
    "iso:country":"BA",
    "name:bos_x_preferred":[
        "Mirjanovi\u0107i"
    ],
    "name:fra_x_preferred":[
        "Mirjanovi\u0107i"
    ],
    "name:hrv_x_preferred":[
        "Mirjanovi\u0107i"
    ],
    "name:srp_x_preferred":[
        "\u041c\u0438\u0440\u0458\u0430\u043d\u043e\u0432\u0438\u045b\u0438"
    ],
    "name:und_x_variant":[
        "Mirjanovi\u0107i"
    ],
    "wof:name":"Mirjanovici",
    "wof:placetype":"locality"
},
  "geometry": {"coordinates":[18.74443,43.55707],"type":"Point"}
}