{
  "type": "Feature",
  "properties": {
    "gn:admin1_code":"01",
    "gn:asciiname":"Causlije",
    "gn:country_code":"BA",
    "gn:dem":550,
    "gn:feature_class":"P",
    "gn:feature_code":"PPL",
    "gn:name":"\u010cau\u0161lije",
    "gn:population":0,
    "gn:timezone":"Europe/Sarajevo",
    "iso:country":"BA",
    "wof:name":"Causlije",
    "wof:placetype":"locality"
},
  "geometry": {"coordinates":[17.45147,44.07783],"type":"Point"}
}