{
  "type": "Feature",
  "properties": {
    "gn:admin1_code":"02",
    "gn:asciiname":"Margetici",
    "gn:country_code":"BA",
    "gn:dem":907,
    "gn:feature_class":"P",
    "gn:feature_code":"PPLL",
    "gn:name":"Margeti\u0107i",
    "gn:population":0,
    "gn:timezone":"Europe/Sarajevo",
    "iso:country":"BA",
    "name:und_x_variant":[
        "Margeti\u0107i"
    ],
    "wof:name":"Margetici",
    "wof:placetype":"locality"
},
  "geometry": {"coordinates":[18.85702,43.96379],"type":"Point"}
}