{
  "type": "Feature",
  "properties": {
    "gn:admin1_code":"01",
    "gn:asciiname":"Zagorice",
    "gn:country_code":"BA",
    "gn:dem":810,
    "gn:feature_class":"P",
    "gn:feature_code":"PPLL",
    "gn:name":"Zagorice",
    "gn:population":0,
    "gn:timezone":"Europe/Sarajevo",
    "iso:country":"BA",
    "wof:name":"Zagorice",
    "wof:placetype":"locality"
},
  "geometry": {"coordinates":[18.00396,43.65737],"type":"Point"}
}