{
  "type": "Feature",
  "properties": {
    "gn:admin1_code":"02",
    "gn:asciiname":"Jupeci",
    "gn:country_code":"BA",
    "gn:dem":463,
    "gn:feature_class":"P",
    "gn:feature_code":"PPL",
    "gn:name":"Jupeci",
    "gn:population":0,
    "gn:timezone":"Europe/Sarajevo",
    "iso:country":"BA",
    "wof:name":"Jupeci",
    "wof:placetype":"locality"
},
  "geometry": {"coordinates":[17.17672,44.42912000000001],"type":"Point"}
}