{
  "type": "Feature",
  "properties": {
    "gn:admin1_code":"01",
    "gn:asciiname":"Alibabici",
    "gn:country_code":"BA",
    "gn:dem":347,
    "gn:feature_class":"P",
    "gn:feature_code":"PPL",
    "gn:name":"Alibabi\u0107i",
    "gn:population":0,
    "gn:timezone":"Europe/Sarajevo",
    "iso:country":"BA",
    "wof:name":"Alibabici",
    "wof:placetype":"locality"
},
  "geometry": {"coordinates":[15.95028,44.89444],"type":"Point"}
}