{
  "type": "Feature",
  "properties": {
    "gn:admin1_code":"01",
    "gn:asciiname":"Gornja Brda",
    "gn:country_code":"BA",
    "gn:dem":738,
    "gn:feature_class":"P",
    "gn:feature_code":"PPL",
    "gn:name":"Gornja Brda",
    "gn:population":0,
    "gn:timezone":"Europe/Sarajevo",
    "iso:country":"BA",
    "name:bos_x_preferred":[
        "Gornja Brda"
    ],
    "name:fra_x_preferred":[
        "Gornja Brda"
    ],
    "wof:name":"Gornja Brda",
    "wof:placetype":"locality"
},
  "geometry": {"coordinates":[18.94409,43.65584000000001],"type":"Point"}
}