{
  "type": "Feature",
  "properties": {
    "gn:admin1_code":"02",
    "gn:asciiname":"Rabadzici",
    "gn:country_code":"BA",
    "gn:dem":443,
    "gn:feature_class":"P",
    "gn:feature_code":"PPL",
    "gn:name":"Rabad\u017ei\u0107i",
    "gn:population":0,
    "gn:timezone":"Europe/Sarajevo",
    "iso:country":"BA",
    "wof:name":"Rabadzici",
    "wof:placetype":"locality"
},
  "geometry": {"coordinates":[19.38917,43.96806],"type":"Point"}
}