{
  "type": "Feature",
  "properties": {
    "gn:admin1_code":"01",
    "gn:asciiname":"Strasevici",
    "gn:country_code":"BA",
    "gn:dem":470,
    "gn:feature_class":"P",
    "gn:feature_code":"PPL",
    "gn:name":"Strasevi\u0107i",
    "gn:population":0,
    "gn:timezone":"Europe/Sarajevo",
    "iso:country":"BA",
    "wof:name":"Strasevici",
    "wof:placetype":"locality"
},
  "geometry": {"coordinates":[18.33144,44.7808],"type":"Point"}
}