{
  "type": "Feature",
  "properties": {
    "gn:admin1_code":"02",
    "gn:asciiname":"Grbavci",
    "gn:country_code":"BA",
    "gn:dem":134,
    "gn:feature_class":"P",
    "gn:feature_code":"PPL",
    "gn:name":"Grbavci",
    "gn:population":0,
    "gn:timezone":"Europe/Sarajevo",
    "iso:country":"BA",
    "wof:name":"Grbavci",
    "wof:placetype":"locality"
},
  "geometry": {"coordinates":[16.73795,45.11749],"type":"Point"}
}