{
  "type": "Feature",
  "properties": {
    "gn:admin1_code":"01",
    "gn:asciiname":"Odzak",
    "gn:country_code":"BA",
    "gn:dem":908,
    "gn:feature_class":"P",
    "gn:feature_code":"PPLL",
    "gn:name":"Od\u017eak",
    "gn:population":0,
    "gn:timezone":"Europe/Sarajevo",
    "iso:country":"BA",
    "name:bos_x_preferred":[
        "Od\u017eak"
    ],
    "name:fra_x_preferred":[
        "Od\u017eak"
    ],
    "name:srp_x_preferred":[
        "\u041e\u045f\u0430\u043a"
    ],
    "wof:name":"Odzak",
    "wof:placetype":"locality"
},
  "geometry": {"coordinates":[16.80508,44.15458],"type":"Point"}
}