{
  "type": "Feature",
  "properties": {
    "gn:admin1_code":"01",
    "gn:asciiname":"Hadje",
    "gn:country_code":"BA",
    "gn:dem":1049,
    "gn:feature_class":"P",
    "gn:feature_code":"PPL",
    "gn:name":"Hadje",
    "gn:population":0,
    "gn:timezone":"Europe/Sarajevo",
    "iso:country":"BA",
    "wof:name":"Hadje",
    "wof:placetype":"locality"
},
  "geometry": {"coordinates":[18.462,44.11966],"type":"Point"}
}