{
  "type": "Feature",
  "properties": {
    "gn:admin1_code":"01",
    "gn:asciiname":"Donji Bukovci",
    "gn:country_code":"BA",
    "gn:dem":630,
    "gn:feature_class":"P",
    "gn:feature_code":"PPL",
    "gn:name":"Donji Bukovci",
    "gn:population":0,
    "gn:timezone":"Europe/Sarajevo",
    "iso:country":"BA",
    "wof:name":"Donji Bukovci",
    "wof:placetype":"locality"
},
  "geometry": {"coordinates":[17.95851,44.04418],"type":"Point"}
}