{
  "type": "Feature",
  "properties": {
    "gn:admin1_code":"01",
    "gn:asciiname":"Vrhovine",
    "gn:country_code":"BA",
    "gn:dem":594,
    "gn:feature_class":"P",
    "gn:feature_code":"PPL",
    "gn:name":"Vrhovine",
    "gn:population":0,
    "gn:timezone":"Europe/Sarajevo",
    "iso:country":"BA",
    "name:bos_x_preferred":[
        "Vrhovine"
    ],
    "name:deu_x_preferred":[
        "Vrhovine"
    ],
    "name:fra_x_preferred":[
        "Vrhovine"
    ],
    "name:hrv_x_preferred":[
        "Vrhovine"
    ],
    "name:hun_x_preferred":[
        "Vrhovine"
    ],
    "name:ita_x_preferred":[
        "Vrhovine"
    ],
    "name:nld_x_preferred":[
        "Vrhovine"
    ],
    "name:pol_x_preferred":[
        "Gmina Vrhovine"
    ],
    "name:ron_x_preferred":[
        "Comuna Vrhovine"
    ],
    "name:slv_x_preferred":[
        "Vrhovine"
    ],
    "name:spa_x_preferred":[
        "Vrhovine"
    ],
    "name:srp_x_preferred":[
        "\u0412\u0440\u0445\u043e\u0432\u0438\u043d\u0435"
    ],
    "name:ukr_x_preferred":[
        "\u0412\u0440\u0445\u043e\u0432\u0438\u043d\u0435"
    ],
    "name:war_x_preferred":[
        "Vrhovine"
    ],
    "wof:name":"Vrhovine",
    "wof:placetype":"locality"
},
  "geometry": {"coordinates":[17.85122,44.16706],"type":"Point"}
}