{
  "type": "Feature",
  "properties": {
    "gn:admin1_code":"01",
    "gn:asciiname":"Vrhovine",
    "gn:country_code":"BA",
    "gn:dem":594,
    "gn:feature_class":"P",
    "gn:feature_code":"PPL",
    "gn:name":"Vrhovine",
    "gn:population":0,
    "gn:timezone":"Europe/Sarajevo",
    "iso:country":"BA",
    "wof:name":"Vrhovine",
    "wof:placetype":"locality"
},
  "geometry": {"coordinates":[17.85122,44.16706],"type":"Point"}
}