{
  "type": "Feature",
  "properties": {
    "gn:admin1_code":"02",
    "gn:asciiname":"Dragisici",
    "gn:country_code":"BA",
    "gn:dem":449,
    "gn:feature_class":"P",
    "gn:feature_code":"PPL",
    "gn:name":"Dragi\u0161i\u0107i",
    "gn:population":0,
    "gn:timezone":"Europe/Sarajevo",
    "iso:country":"BA",
    "wof:name":"Dragisici",
    "wof:placetype":"locality"
},
  "geometry": {"coordinates":[17.02807,44.71124],"type":"Point"}
}