{
  "type": "Feature",
  "properties": {
    "gn:admin1_code":"02",
    "gn:asciiname":"Pantic Mahala",
    "gn:country_code":"BA",
    "gn:dem":164,
    "gn:feature_class":"P",
    "gn:feature_code":"PPL",
    "gn:name":"Panti\u0107 Mahala",
    "gn:population":0,
    "gn:timezone":"Europe/Sarajevo",
    "iso:country":"BA",
    "wof:name":"Pantic Mahala",
    "wof:placetype":"locality"
},
  "geometry": {"coordinates":[19.00696,44.74945],"type":"Point"}
}