{
  "type": "Feature",
  "properties": {
    "gn:admin1_code":"02",
    "gn:asciiname":"Pejici",
    "gn:country_code":"BA",
    "gn:dem":1016,
    "gn:feature_class":"P",
    "gn:feature_code":"PPL",
    "gn:name":"Peji\u0107i",
    "gn:population":0,
    "gn:timezone":"Europe/Sarajevo",
    "iso:country":"BA",
    "wof:name":"Pejici",
    "wof:placetype":"locality"
},
  "geometry": {"coordinates":[17.54165,44.41957],"type":"Point"}
}