{
  "type": "Feature",
  "properties": {
    "gn:admin1_code":"01",
    "gn:asciiname":"Jezero",
    "gn:country_code":"BA",
    "gn:dem":347,
    "gn:feature_class":"P",
    "gn:feature_code":"PPL",
    "gn:name":"Jezero",
    "gn:population":0,
    "gn:timezone":"Europe/Sarajevo",
    "iso:country":"BA",
    "wof:name":"Jezero",
    "wof:placetype":"locality"
},
  "geometry": {"coordinates":[15.94241,44.88686],"type":"Point"}
}