{
  "type": "Feature",
  "properties": {
    "gn:admin1_code":"02",
    "gn:asciiname":"Pasalici",
    "gn:country_code":"BA",
    "gn:dem":192,
    "gn:feature_class":"P",
    "gn:feature_code":"PPL",
    "gn:name":"Pa\u0161ali\u0107i",
    "gn:population":0,
    "gn:timezone":"Europe/Sarajevo",
    "iso:country":"BA",
    "wof:name":"Pasalici",
    "wof:placetype":"locality"
},
  "geometry": {"coordinates":[17.96644,44.77051],"type":"Point"}
}