{
  "type": "Feature",
  "properties": {
    "gn:admin1_code":"01",
    "gn:asciiname":"Grab",
    "gn:country_code":"BA",
    "gn:dem":445,
    "gn:feature_class":"P",
    "gn:feature_code":"PPL",
    "gn:name":"Grab",
    "gn:population":0,
    "gn:timezone":"Europe/Sarajevo",
    "iso:country":"BA",
    "name:aze_x_preferred":[
        "Yaxalay\u0131c\u0131"
    ],
    "name:bos_x_preferred":[
        "Grab"
    ],
    "name:ceb_x_preferred":[
        "Grab"
    ],
    "name:deu_x_preferred":[
        "Grab"
    ],
    "name:fra_x_preferred":[
        "Grab"
    ],
    "name:heb_x_preferred":[
        "\u05d2\u05e8\u05d0\u05d1"
    ],
    "name:hrv_x_preferred":[
        "Grab"
    ],
    "name:hun_x_preferred":[
        "Grab"
    ],
    "name:nds_x_preferred":[
        "Grab"
    ],
    "name:nld_x_preferred":[
        "Grab"
    ],
    "name:pol_x_preferred":[
        "Grab"
    ],
    "name:slv_x_preferred":[
        "Grab"
    ],
    "name:srp_x_preferred":[
        "\u0413\u0440\u0430\u0431"
    ],
    "name:swe_x_preferred":[
        "Grab"
    ],
    "name:ukr_x_preferred":[
        "\u0490\u0440\u0430\u0431"
    ],
    "wof:name":"Grab",
    "wof:placetype":"locality"
},
  "geometry": {"coordinates":[18.10631,44.05992],"type":"Point"}
}