{
  "type": "Feature",
  "properties": {
    "gn:admin1_code":"01",
    "gn:asciiname":"Grab",
    "gn:country_code":"BA",
    "gn:dem":445,
    "gn:feature_class":"P",
    "gn:feature_code":"PPL",
    "gn:name":"Grab",
    "gn:population":0,
    "gn:timezone":"Europe/Sarajevo",
    "iso:country":"BA",
    "wof:name":"Grab",
    "wof:placetype":"locality"
},
  "geometry": {"coordinates":[18.10631,44.05992],"type":"Point"}
}