{
  "type": "Feature",
  "properties": {
    "iso:country":"BA",
    "qs:name":"Sejkovici",
    "qs:name_adm0":"Bosna i Hercegovina",
    "qs:name_adm1":"Republika Srpska",
    "qs:photos":3,
    "qs:photos_1k":1,
    "qs:photos_9k":1,
    "qs:photos_9r":1,
    "qs:photos_all":3,
    "qs:photos_sr":1,
    "qs:placetype":"Town",
    "qs:pop_sr":"0",
    "wof:name":"Sejkovici",
    "wof:placetype":"locality"
},
  "geometry": {"coordinates":[18.847732,44.300817],"type":"Point"}
}