{
  "type": "Feature",
  "properties": {
    "gn:admin1_code":"01",
    "gn:asciiname":"Kremenac",
    "gn:country_code":"BA",
    "gn:dem":495,
    "gn:feature_class":"P",
    "gn:feature_code":"PPL",
    "gn:name":"Kremenac",
    "gn:population":0,
    "gn:timezone":"Europe/Sarajevo",
    "iso:country":"BA",
    "wof:name":"Kremenac",
    "wof:placetype":"locality"
},
  "geometry": {"coordinates":[16.77478,44.69373],"type":"Point"}
}