{
  "type": "Feature",
  "properties": {
    "gn:admin1_code":"01",
    "gn:asciiname":"Kraboris",
    "gn:country_code":"BA",
    "gn:dem":1138,
    "gn:feature_class":"P",
    "gn:feature_code":"PPLL",
    "gn:name":"Krabori\u0161",
    "gn:population":0,
    "gn:timezone":"Europe/Sarajevo",
    "iso:country":"BA",
    "wof:name":"Kraboris",
    "wof:placetype":"locality"
},
  "geometry": {"coordinates":[18.83272,43.7023],"type":"Point"}
}