{
  "type": "Feature",
  "properties": {
    "gn:admin1_code":"01",
    "gn:asciiname":"Kukovina",
    "gn:country_code":"BA",
    "gn:dem":405,
    "gn:feature_class":"P",
    "gn:feature_code":"PPL",
    "gn:name":"Kukovina",
    "gn:population":0,
    "gn:timezone":"Europe/Sarajevo",
    "iso:country":"BA",
    "wof:name":"Kukovina",
    "wof:placetype":"locality"
},
  "geometry": {"coordinates":[18.80889,44.54556],"type":"Point"}
}