{
  "type": "Feature",
  "properties": {
    "gn:admin1_code":"02",
    "gn:asciiname":"Luzani Trstenacki",
    "gn:country_code":"BA",
    "gn:dem":91,
    "gn:feature_class":"P",
    "gn:feature_code":"PPLL",
    "gn:name":"Lu\u017eani Trstena\u010dki",
    "gn:population":0,
    "gn:timezone":"Europe/Sarajevo",
    "iso:country":"BA",
    "name:und_x_variant":[
        "Lu\u017eani-Trsteno\u010dki",
        "Lu\u017eani Trstena\u010dki"
    ],
    "wof:name":"Luzani Trstenacki",
    "wof:placetype":"locality"
},
  "geometry": {"coordinates":[17.80571,45.05575],"type":"Point"}
}