{
  "type": "Feature",
  "properties": {
    "gn:admin1_code":"01",
    "gn:asciiname":"Alibegovci",
    "gn:country_code":"BA",
    "gn:dem":220,
    "gn:feature_class":"P",
    "gn:feature_code":"PPLL",
    "gn:name":"Alibegov\u0107i",
    "gn:population":0,
    "gn:timezone":"Europe/Sarajevo",
    "iso:country":"BA",
    "name:bos_x_preferred":[
        "Alibegovci"
    ],
    "name:ceb_x_preferred":[
        "Alibegov\u0107i"
    ],
    "name:ell_x_preferred":[
        "\u0391\u03bb\u03b9\u03bc\u03c0\u03ad\u03b3\u03ba\u03bf\u03b2\u03c4\u03c3\u03b9"
    ],
    "name:fas_x_preferred":[
        "\u0639\u0644\u06cc\u0628\u06af\u0627\u0648\u0633\u06cc"
    ],
    "name:fra_x_preferred":[
        "Alibegovci"
    ],
    "name:hrv_x_preferred":[
        "Alibegovci"
    ],
    "name:srp_x_preferred":[
        "\u0410\u043b\u0438\u0431\u0435\u0433\u043e\u0432\u0446\u0438"
    ],
    "name:swe_x_preferred":[
        "Alibegov\u0107i"
    ],
    "name:und_x_variant":[
        "Alabegovci",
        "Alibegov\u0107i"
    ],
    "wof:name":"Alibegovci",
    "wof:placetype":"locality"
},
  "geometry": {"coordinates":[18.00645,44.69365],"type":"Point"}
}