{
  "type": "Feature",
  "properties": {
    "gn:admin1_code":"01",
    "gn:asciiname":"Alibegovci",
    "gn:country_code":"BA",
    "gn:dem":220,
    "gn:feature_class":"P",
    "gn:feature_code":"PPLL",
    "gn:name":"Alibegov\u0107i",
    "gn:population":0,
    "gn:timezone":"Europe/Sarajevo",
    "iso:country":"BA",
    "name:und_x_variant":[
        "Alabegovci",
        "Alibegov\u0107i"
    ],
    "wof:name":"Alibegovci",
    "wof:placetype":"locality"
},
  "geometry": {"coordinates":[18.00645,44.69365],"type":"Point"}
}