{
  "type": "Feature",
  "properties": {
    "gn:admin1_code":"02",
    "gn:asciiname":"Kolakovina",
    "gn:country_code":"BA",
    "gn:dem":891,
    "gn:feature_class":"P",
    "gn:feature_code":"PPL",
    "gn:name":"Kolakovina",
    "gn:population":0,
    "gn:timezone":"Europe/Sarajevo",
    "iso:country":"BA",
    "wof:name":"Kolakovina",
    "wof:placetype":"locality"
},
  "geometry": {"coordinates":[18.32523,43.04892],"type":"Point"}
}