{
  "type": "Feature",
  "properties": {
    "gn:admin1_code":"01",
    "gn:asciiname":"Ljaljica",
    "gn:country_code":"BA",
    "gn:dem":767,
    "gn:feature_class":"P",
    "gn:feature_code":"PPL",
    "gn:name":"Ljaljica",
    "gn:population":0,
    "gn:timezone":"Europe/Sarajevo",
    "iso:country":"BA",
    "wof:name":"Ljaljica",
    "wof:placetype":"locality"
},
  "geometry": {"coordinates":[18.70248,43.62749],"type":"Point"}
}