{
  "type": "Feature",
  "properties": {
    "gn:admin1_code":"01",
    "gn:asciiname":"Ostroc",
    "gn:country_code":"BA",
    "gn:dem":460,
    "gn:feature_class":"P",
    "gn:feature_code":"PPL",
    "gn:name":"O\u0161troc",
    "gn:population":0,
    "gn:timezone":"Europe/Sarajevo",
    "iso:country":"BA",
    "wof:name":"Ostroc",
    "wof:placetype":"locality"
},
  "geometry": {"coordinates":[18.18284,43.96805],"type":"Point"}
}