{
  "type": "Feature",
  "properties": {
    "gn:admin1_code":"01",
    "gn:asciiname":"Dubostica",
    "gn:country_code":"BA",
    "gn:dem":652,
    "gn:feature_class":"P",
    "gn:feature_code":"PPLL",
    "gn:name":"Dubo\u0161tica",
    "gn:population":0,
    "gn:timezone":"Europe/Sarajevo",
    "iso:country":"BA",
    "name:und_x_variant":[
        "Dubo\u0161ica",
        "Dubo\u0161\u010dica",
        "Dubo\u0161tica"
    ],
    "wof:name":"Dubostica",
    "wof:placetype":"locality"
},
  "geometry": {"coordinates":[18.32454,44.23826],"type":"Point"}
}