{
  "type": "Feature",
  "properties": {
    "gn:admin1_code":"01",
    "gn:asciiname":"Livade",
    "gn:country_code":"BA",
    "gn:dem":448,
    "gn:feature_class":"P",
    "gn:feature_code":"PPL",
    "gn:name":"Livade",
    "gn:population":0,
    "gn:timezone":"Europe/Sarajevo",
    "iso:country":"BA",
    "wof:name":"Livade",
    "wof:placetype":"locality"
},
  "geometry": {"coordinates":[18.2795,44.46368],"type":"Point"}
}