{
  "type": "Feature",
  "properties": {
    "gn:admin1_code":"02",
    "gn:asciiname":"Kudrici",
    "gn:country_code":"BA",
    "gn:dem":173,
    "gn:feature_class":"P",
    "gn:feature_code":"PPL",
    "gn:name":"Kudri\u0107i",
    "gn:population":0,
    "gn:timezone":"Europe/Sarajevo",
    "iso:country":"BA",
    "wof:name":"Kudrici",
    "wof:placetype":"locality"
},
  "geometry": {"coordinates":[17.71902,44.90653],"type":"Point"}
}