{
  "type": "Feature",
  "properties": {
    "gn:admin1_code":"01",
    "gn:asciiname":"Cigrije",
    "gn:country_code":"BA",
    "gn:dem":648,
    "gn:feature_class":"P",
    "gn:feature_code":"PPL",
    "gn:name":"\u010cigrije",
    "gn:population":0,
    "gn:timezone":"Europe/Sarajevo",
    "iso:country":"BA",
    "wof:name":"Cigrije",
    "wof:placetype":"locality"
},
  "geometry": {"coordinates":[16.18722,44.64528],"type":"Point"}
}