{
  "type": "Feature",
  "properties": {
    "gn:admin1_code":"01",
    "gn:asciiname":"Odzak",
    "gn:country_code":"BA",
    "gn:dem":985,
    "gn:feature_class":"P",
    "gn:feature_code":"PPL",
    "gn:name":"Od\u017eak",
    "gn:population":0,
    "gn:timezone":"Europe/Sarajevo",
    "iso:country":"BA",
    "name:bos_x_preferred":[
        "Od\u017eak"
    ],
    "name:fra_x_preferred":[
        "Od\u017eak"
    ],
    "name:pol_x_preferred":[
        "Od\u017eak"
    ],
    "name:und_x_variant":[
        "Od\u017eak"
    ],
    "wof:name":"Odzak",
    "wof:placetype":"locality"
},
  "geometry": {"coordinates":[18.47581,44.0864],"type":"Point"}
}