{
  "type": "Feature",
  "properties": {
    "gn:admin1_code":"01",
    "gn:asciiname":"Vojevac",
    "gn:country_code":"BA",
    "gn:dem":390,
    "gn:feature_class":"P",
    "gn:feature_code":"PPLL",
    "gn:name":"Vojevac",
    "gn:population":0,
    "gn:timezone":"Europe/Sarajevo",
    "iso:country":"BA",
    "name:ara_x_preferred":[
        "\u0641\u0648\u062c\u064a\u0641\u0627\u0643"
    ],
    "name:bos_x_preferred":[
        "Vojevac"
    ],
    "name:fra_x_preferred":[
        "Vojevac"
    ],
    "name:srp_x_preferred":[
        "\u0412\u043e\u0458\u0435\u0432\u0430\u0446"
    ],
    "wof:name":"Vojevac",
    "wof:placetype":"locality"
},
  "geometry": {"coordinates":[16.2168,44.80217],"type":"Point"}
}