{
  "type": "Feature",
  "properties": {
    "gn:admin1_code":"01",
    "gn:asciiname":"Marica Dolina",
    "gn:country_code":"BA",
    "gn:dem":1130,
    "gn:feature_class":"P",
    "gn:feature_code":"PPL",
    "gn:name":"Mari\u0107a Dolina",
    "gn:population":0,
    "gn:timezone":"Europe/Sarajevo",
    "iso:country":"BA",
    "wof:name":"Marica Dolina",
    "wof:placetype":"locality"
},
  "geometry": {"coordinates":[17.18306,43.89528],"type":"Point"}
}