{
  "type": "Feature",
  "properties": {
    "gn:admin1_code":"02",
    "gn:asciiname":"Sjenokosi",
    "gn:country_code":"BA",
    "gn:dem":107,
    "gn:feature_class":"P",
    "gn:feature_code":"PPL",
    "gn:name":"Sjenokosi",
    "gn:population":0,
    "gn:timezone":"Europe/Sarajevo",
    "iso:country":"BA",
    "wof:name":"Sjenokosi",
    "wof:placetype":"locality"
},
  "geometry": {"coordinates":[17.36258,44.98683],"type":"Point"}
}