{
  "type": "Feature",
  "properties": {
    "gn:admin1_code":"01",
    "gn:asciiname":"Janjicki Vrh",
    "gn:country_code":"BA",
    "gn:dem":578,
    "gn:feature_class":"P",
    "gn:feature_code":"PPL",
    "gn:name":"Janji\u0107ki Vrh",
    "gn:population":0,
    "gn:timezone":"Europe/Sarajevo",
    "iso:country":"BA",
    "name:und_x_variant":[
        "Vrh",
        "Janji\u0107ki Vrh"
    ],
    "wof:name":"Janjicki Vrh",
    "wof:placetype":"locality"
},
  "geometry": {"coordinates":[17.94,44.16027],"type":"Point"}
}