{
  "type": "Feature",
  "properties": {
    "gn:admin1_code":"02",
    "gn:asciiname":"Kecmanska Dolina",
    "gn:country_code":"BA",
    "gn:dem":743,
    "gn:feature_class":"P",
    "gn:feature_code":"PPL",
    "gn:name":"Kecmanska Dolina",
    "gn:population":0,
    "gn:timezone":"Europe/Sarajevo",
    "iso:country":"BA",
    "wof:name":"Kecmanska Dolina",
    "wof:placetype":"locality"
},
  "geometry": {"coordinates":[16.47583,44.50278],"type":"Point"}
}