{
  "type": "Feature",
  "properties": {
    "gn:admin1_code":"02",
    "gn:asciiname":"Cetkovac",
    "gn:country_code":"BA",
    "gn:dem":1146,
    "gn:feature_class":"P",
    "gn:feature_code":"PPL",
    "gn:name":"\u010cetkovac",
    "gn:population":0,
    "gn:timezone":"Europe/Sarajevo",
    "iso:country":"BA",
    "wof:name":"Cetkovac",
    "wof:placetype":"locality"
},
  "geometry": {"coordinates":[18.97384,43.99723],"type":"Point"}
}