{
  "type": "Feature",
  "properties": {
    "gn:admin1_code":"01",
    "gn:asciiname":"Hasicici",
    "gn:country_code":"BA",
    "gn:dem":269,
    "gn:feature_class":"P",
    "gn:feature_code":"PPL",
    "gn:name":"Hasi\u010di\u0107i",
    "gn:population":0,
    "gn:timezone":"Europe/Sarajevo",
    "iso:country":"BA",
    "wof:name":"Hasicici",
    "wof:placetype":"locality"
},
  "geometry": {"coordinates":[17.99796,44.64349],"type":"Point"}
}