{
  "type": "Feature",
  "properties": {
    "gn:admin1_code":"02",
    "gn:asciiname":"Bogdanovic-Mahala",
    "gn:country_code":"BA",
    "gn:dem":114,
    "gn:feature_class":"P",
    "gn:feature_code":"PPL",
    "gn:name":"Bogdanovi\u0107-Mahala",
    "gn:population":0,
    "gn:timezone":"Europe/Sarajevo",
    "iso:country":"BA",
    "wof:name":"Bogdanovic-Mahala",
    "wof:placetype":"locality"
},
  "geometry": {"coordinates":[19.01666,44.78817],"type":"Point"}
}