{
  "type": "Feature",
  "properties": {
    "gn:admin1_code":"02",
    "gn:asciiname":"Vaslici",
    "gn:country_code":"BA",
    "gn:dem":209,
    "gn:feature_class":"P",
    "gn:feature_code":"PPL",
    "gn:name":"Vasli\u0107i",
    "gn:population":0,
    "gn:timezone":"Europe/Sarajevo",
    "iso:country":"BA",
    "wof:name":"Vaslici",
    "wof:placetype":"locality"
},
  "geometry": {"coordinates":[17.83067999999999,44.86777],"type":"Point"}
}