{
  "type": "Feature",
  "properties": {
    "gn:admin1_code":"02",
    "gn:asciiname":"Knjeginja",
    "gn:country_code":"BA",
    "gn:dem":567,
    "gn:feature_class":"P",
    "gn:feature_code":"PPL",
    "gn:name":"Knjeginja",
    "gn:population":0,
    "gn:timezone":"Europe/Sarajevo",
    "iso:country":"BA",
    "name:und_x_variant":[
        "Kneginja",
        "Knjeginja"
    ],
    "wof:name":"Knjeginja",
    "wof:placetype":"locality"
},
  "geometry": {"coordinates":[19.48257000000001,43.6096],"type":"Point"}
}