{
  "type": "Feature",
  "properties": {
    "gn:country":"BA",
    "gn:fcode":"PPL",
    "gn:population":3614,
    "iso:country":"BA",
    "name:bos_x_preferred":[
        "Lopare"
    ],
    "name:ceb_x_preferred":[
        "Lopare"
    ],
    "name:ces_x_preferred":[
        "Lopare"
    ],
    "name:deu_x_preferred":[
        "Lopare"
    ],
    "name:eng_x_preferred":[
        "Lopare"
    ],
    "name:fra_x_preferred":[
        "Lopare"
    ],
    "name:hrv_x_preferred":[
        "Lopare"
    ],
    "name:hye_x_preferred":[
        "\u053c\u0578\u057a\u0561\u0580\u0565"
    ],
    "name:ita_x_preferred":[
        "Lopare"
    ],
    "name:jpn_x_preferred":[
        "\u30ed\u30d1\u30ec"
    ],
    "name:nld_x_preferred":[
        "Lopare"
    ],
    "name:pol_x_preferred":[
        "Lopare"
    ],
    "name:rus_x_preferred":[
        "\u041b\u043e\u043f\u0430\u0440\u0435"
    ],
    "name:slv_x_preferred":[
        "Lopare"
    ],
    "name:spa_x_preferred":[
        "Lopare"
    ],
    "name:srp_x_preferred":[
        "\u041b\u043e\u043f\u0430\u0440\u0435"
    ],
    "name:swe_x_preferred":[
        "Lopare"
    ],
    "name:tat_x_preferred":[
        "\u041b\u043e\u043f\u0430\u0440\u0435"
    ],
    "name:tur_x_preferred":[
        "Lopare"
    ],
    "name:urd_x_preferred":[
        "\u0644\u0648\u067e\u0627\u0631\u06d2"
    ],
    "name:zho_x_preferred":[
        "\u6d1b\u5e15\u96f7"
    ],
    "qs:name":"Lopare",
    "qs:name_adm0":"Bosna i Hercegovina",
    "qs:name_adm1":"Republika Srpska",
    "qs:photos":11,
    "qs:photos_1k":2,
    "qs:photos_9k":1,
    "qs:photos_9r":1,
    "qs:photos_all":11,
    "qs:photos_sr":1,
    "qs:placetype":"Town",
    "qs:pop_sr":"4",
    "wd:wordcount":448,
    "wof:name":"Lopare",
    "wof:placetype":"locality",
    "wof:population":3614
},
  "geometry": {"coordinates":[18.8434,44.63498],"type":"Point"}
}