{
  "type": "Feature",
  "properties": {
    "gn:country":"BA",
    "gn:fcode":"PPL",
    "gn:pop":3614,
    "iso:country":"BA",
    "name:rus_x_preferred":[
        "\u041b\u043e\u043f\u0430\u0440\u0435"
    ],
    "name:srp_x_preferred":[
        "\u041b\u043e\u043f\u0430\u0440\u0435"
    ],
    "name:zho_x_preferred":[
        "\u6d1b\u5e15\u96f7"
    ],
    "qs:name":"Lopare",
    "qs:name_adm0":"Bosna i Hercegovina",
    "qs:name_adm1":"Republika Srpska",
    "qs:photos":11,
    "qs:photos_1k":2,
    "qs:photos_9k":1,
    "qs:photos_9r":1,
    "qs:photos_all":11,
    "qs:photos_sr":1,
    "qs:placetype":"Town",
    "qs:pop_sr":"4",
    "wd:wordcount":448,
    "wof:name":"Lopare",
    "wof:placetype":"locality",
    "wof:population":3614
},
  "geometry": {"coordinates":[18.8434,44.63498],"type":"Point"}
}