{
  "type": "Feature",
  "properties": {
    "gn:admin1_code":"02",
    "gn:asciiname":"Cerska",
    "gn:country_code":"BA",
    "gn:dem":435,
    "gn:feature_class":"P",
    "gn:feature_code":"PPLL",
    "gn:name":"Cerska",
    "gn:population":0,
    "gn:timezone":"Europe/Sarajevo",
    "iso:country":"BA",
    "wof:name":"Cerska",
    "wof:placetype":"locality"
},
  "geometry": {"coordinates":[19.03874,44.25808],"type":"Point"}
}