{
  "type": "Feature",
  "properties": {
    "gn:admin1_code":"01",
    "gn:asciiname":"Radulovici",
    "gn:country_code":"BA",
    "gn:dem":356,
    "gn:feature_class":"P",
    "gn:feature_code":"PPL",
    "gn:name":"Radulovi\u0107i",
    "gn:population":0,
    "gn:timezone":"Europe/Sarajevo",
    "iso:country":"BA",
    "wof:name":"Radulovici",
    "wof:placetype":"locality"
},
  "geometry": {"coordinates":[18.5475,44.63222],"type":"Point"}
}