{
  "type": "Feature",
  "properties": {
    "gn:admin1_code":"02",
    "gn:asciiname":"Gigovici",
    "gn:country_code":"BA",
    "gn:dem":447,
    "gn:feature_class":"P",
    "gn:feature_code":"PPL",
    "gn:name":"Gigovi\u0107i",
    "gn:population":0,
    "gn:timezone":"Europe/Sarajevo",
    "iso:country":"BA",
    "wof:name":"Gigovici",
    "wof:placetype":"locality"
},
  "geometry": {"coordinates":[17.04579,45.01192],"type":"Point"}
}