{
  "type": "Feature",
  "properties": {
    "gn:admin1_code":"01",
    "gn:asciiname":"Ladice",
    "gn:country_code":"BA",
    "gn:dem":640,
    "gn:feature_class":"P",
    "gn:feature_code":"PPL",
    "gn:name":"La\u0111ice",
    "gn:population":0,
    "gn:timezone":"Europe/Sarajevo",
    "iso:country":"BA",
    "wof:name":"Ladice",
    "wof:placetype":"locality"
},
  "geometry": {"coordinates":[17.84502999999999,44.18353],"type":"Point"}
}