{
  "type": "Feature",
  "properties": {
    "gn:admin1_code":"01",
    "gn:asciiname":"Ladice",
    "gn:country_code":"BA",
    "gn:dem":640,
    "gn:feature_class":"P",
    "gn:feature_code":"PPL",
    "gn:name":"La\u0111ice",
    "gn:population":0,
    "gn:timezone":"Europe/Sarajevo",
    "iso:country":"BA",
    "name:cat_x_preferred":[
        "Ladice"
    ],
    "name:ces_x_preferred":[
        "Ladice"
    ],
    "name:epo_x_preferred":[
        "Ladice"
    ],
    "name:eus_x_preferred":[
        "Ladice"
    ],
    "name:fra_x_preferred":[
        "Ladice"
    ],
    "name:hun_x_preferred":[
        "Barsl\u00e9dec"
    ],
    "name:ita_x_preferred":[
        "Ladice"
    ],
    "name:msa_x_preferred":[
        "Ladice"
    ],
    "name:nld_x_preferred":[
        "Ladice"
    ],
    "name:ron_x_preferred":[
        "Ladice"
    ],
    "name:slk_x_preferred":[
        "Ladice"
    ],
    "name:spa_x_preferred":[
        "Ladice"
    ],
    "name:srp_x_preferred":[
        "\u041b\u0430\u0434\u0438\u0446\u0435"
    ],
    "name:ukr_x_preferred":[
        "\u041b\u0430\u0434\u0456\u0446\u0435"
    ],
    "name:war_x_preferred":[
        "Ladice"
    ],
    "wof:name":"Ladice",
    "wof:placetype":"locality"
},
  "geometry": {"coordinates":[17.84502999999999,44.18353],"type":"Point"}
}