{
  "type": "Feature",
  "properties": {
    "gn:admin1_code":"02",
    "gn:asciiname":"Sidranovina",
    "gn:country_code":"BA",
    "gn:dem":650,
    "gn:feature_class":"P",
    "gn:feature_code":"PPL",
    "gn:name":"Sidranovina",
    "gn:population":0,
    "gn:timezone":"Europe/Sarajevo",
    "iso:country":"BA",
    "wof:name":"Sidranovina",
    "wof:placetype":"locality"
},
  "geometry": {"coordinates":[18.10217,43.12242],"type":"Point"}
}