{
  "type": "Feature",
  "properties": {
    "gn:admin1_code":"01",
    "gn:asciiname":"Poljice",
    "gn:country_code":"BA",
    "gn:dem":466,
    "gn:feature_class":"P",
    "gn:feature_code":"PPL",
    "gn:name":"Poljice",
    "gn:population":0,
    "gn:timezone":"Europe/Sarajevo",
    "iso:country":"BA",
    "name:bos_x_preferred":[
        "Poljice"
    ],
    "name:ceb_x_preferred":[
        "Poljice"
    ],
    "name:fra_x_preferred":[
        "Poljice"
    ],
    "name:hrv_x_preferred":[
        "Poljice"
    ],
    "name:hun_x_preferred":[
        "Poljice"
    ],
    "name:nld_x_preferred":[
        "Poljice"
    ],
    "name:slv_x_preferred":[
        "Poljice"
    ],
    "name:srp_x_preferred":[
        "\u041f\u043e\u0459\u0438\u0446\u0435"
    ],
    "name:swe_x_preferred":[
        "Poljice"
    ],
    "name:ukr_x_preferred":[
        "\u041f\u043e\u043b\u0456\u0446\u0435"
    ],
    "wof:name":"Poljice",
    "wof:placetype":"locality"
},
  "geometry": {"coordinates":[16.04361,44.61028],"type":"Point"}
}