{
  "type": "Feature",
  "properties": {
    "gn:admin1_code":"01",
    "gn:asciiname":"Poljice",
    "gn:country_code":"BA",
    "gn:dem":466,
    "gn:feature_class":"P",
    "gn:feature_code":"PPL",
    "gn:name":"Poljice",
    "gn:population":0,
    "gn:timezone":"Europe/Sarajevo",
    "iso:country":"BA",
    "wof:name":"Poljice",
    "wof:placetype":"locality"
},
  "geometry": {"coordinates":[16.04361,44.61028],"type":"Point"}
}