{
  "type": "Feature",
  "properties": {
    "gn:admin1_code":"02",
    "gn:asciiname":"Kolundzije",
    "gn:country_code":"BA",
    "gn:dem":249,
    "gn:feature_class":"P",
    "gn:feature_code":"PPL",
    "gn:name":"Kolund\u017eije",
    "gn:population":0,
    "gn:timezone":"Europe/Sarajevo",
    "iso:country":"BA",
    "wof:name":"Kolundzije",
    "wof:placetype":"locality"
},
  "geometry": {"coordinates":[16.46139,45.08833],"type":"Point"}
}