{
  "type": "Feature",
  "properties": {
    "gn:admin1_code":"02",
    "gn:asciiname":"Turkovici",
    "gn:country_code":"BA",
    "gn:dem":801,
    "gn:feature_class":"P",
    "gn:feature_code":"PPLL",
    "gn:name":"Turkovi\u0107i",
    "gn:population":0,
    "gn:timezone":"Europe/Sarajevo",
    "iso:country":"BA",
    "name:und_x_variant":[
        "Turkovi\u0107i"
    ],
    "wof:name":"Turkovici",
    "wof:placetype":"locality"
},
  "geometry": {"coordinates":[18.7595,44.00859000000001],"type":"Point"}
}