{
  "type": "Feature",
  "properties": {
    "gn:admin1_code":"02",
    "gn:asciiname":"Turkovici",
    "gn:country_code":"BA",
    "gn:dem":801,
    "gn:feature_class":"P",
    "gn:feature_code":"PPLL",
    "gn:name":"Turkovi\u0107i",
    "gn:population":0,
    "gn:timezone":"Europe/Sarajevo",
    "iso:country":"BA",
    "name:bos_x_preferred":[
        "Turkovi\u0107i"
    ],
    "name:fas_x_preferred":[
        "\u062a\u0648\u0631\u06a9\u0648\u06cc\u0686\u06cc"
    ],
    "name:fra_x_preferred":[
        "Turkovi\u0107i"
    ],
    "name:srp_x_preferred":[
        "\u0422\u0443\u0440\u043a\u043e\u0432\u0438\u045b\u0438"
    ],
    "name:urd_x_preferred":[
        "\u062a\u0631\u06a9\u0648\u0648\u06cc\u0686\u06cc"
    ],
    "wof:name":"Turkovici",
    "wof:placetype":"locality"
},
  "geometry": {"coordinates":[18.7595,44.00859000000001],"type":"Point"}
}