{
  "type": "Feature",
  "properties": {
    "gn:admin1_code":"01",
    "gn:asciiname":"Orahovljani",
    "gn:country_code":"BA",
    "gn:dem":733,
    "gn:feature_class":"P",
    "gn:feature_code":"PPLL",
    "gn:name":"Orahovljani",
    "gn:population":0,
    "gn:timezone":"Europe/Sarajevo",
    "iso:country":"BA",
    "wof:name":"Orahovljani",
    "wof:placetype":"locality"
},
  "geometry": {"coordinates":[17.36729,44.16686],"type":"Point"}
}