{
  "type": "Feature",
  "properties": {
    "gn:admin1_code":"02",
    "gn:asciiname":"Mrsici",
    "gn:country_code":"BA",
    "gn:dem":585,
    "gn:feature_class":"P",
    "gn:feature_code":"PPL",
    "gn:name":"Mr\u0161i\u0107i",
    "gn:population":0,
    "gn:timezone":"Europe/Sarajevo",
    "iso:country":"BA",
    "name:und_x_variant":[
        "Mr\u0161i\u0107i"
    ],
    "wof:name":"Mrsici",
    "wof:placetype":"locality"
},
  "geometry": {"coordinates":[18.95275,44.23424],"type":"Point"}
}