{
  "type": "Feature",
  "properties": {
    "gn:admin1_code":"01",
    "gn:asciiname":"Bratis",
    "gn:country_code":"BA",
    "gn:dem":648,
    "gn:feature_class":"P",
    "gn:feature_code":"PPL",
    "gn:name":"Brati\u0161",
    "gn:population":0,
    "gn:timezone":"Europe/Sarajevo",
    "iso:country":"BA",
    "name:bos_x_preferred":[
        "Brati\u0161"
    ],
    "name:fra_x_preferred":[
        "Brati\u0161"
    ],
    "wof:name":"Bratis",
    "wof:placetype":"locality"
},
  "geometry": {"coordinates":[18.79602,43.63836],"type":"Point"}
}