{
  "type": "Feature",
  "properties": {
    "gn:admin1_code":"02",
    "gn:asciiname":"Dukatovici",
    "gn:country_code":"BA",
    "gn:dem":570,
    "gn:feature_class":"P",
    "gn:feature_code":"PPL",
    "gn:name":"Dukatovi\u0107i",
    "gn:population":0,
    "gn:timezone":"Europe/Sarajevo",
    "iso:country":"BA",
    "wof:name":"Dukatovici",
    "wof:placetype":"locality"
},
  "geometry": {"coordinates":[19.0388,43.63032000000001],"type":"Point"}
}