{
  "type": "Feature",
  "properties": {
    "gn:admin1_code":"02",
    "gn:asciiname":"Grabici",
    "gn:country_code":"BA",
    "gn:dem":164,
    "gn:feature_class":"P",
    "gn:feature_code":"PPL",
    "gn:name":"Grabi\u0107i",
    "gn:population":0,
    "gn:timezone":"Europe/Sarajevo",
    "iso:country":"BA",
    "wof:name":"Grabici",
    "wof:placetype":"locality"
},
  "geometry": {"coordinates":[16.7984,44.97563],"type":"Point"}
}