{
  "type": "Feature",
  "properties": {
    "gn:admin1_code":"01",
    "gn:asciiname":"Podgalevi",
    "gn:country_code":"BA",
    "gn:dem":283,
    "gn:feature_class":"P",
    "gn:feature_code":"PPLL",
    "gn:name":"Podgalevi",
    "gn:population":0,
    "gn:timezone":"Europe/Sarajevo",
    "iso:country":"BA",
    "wof:name":"Podgalevi",
    "wof:placetype":"locality"
},
  "geometry": {"coordinates":[18.66891,44.36967],"type":"Point"}
}