{
  "type": "Feature",
  "properties": {
    "gn:admin1_code":"02",
    "gn:asciiname":"Cetkovici",
    "gn:country_code":"BA",
    "gn:dem":1014,
    "gn:feature_class":"P",
    "gn:feature_code":"PPL",
    "gn:name":"\u0106etkovi\u0107i",
    "gn:population":0,
    "gn:timezone":"Europe/Sarajevo",
    "iso:country":"BA",
    "wof:name":"Cetkovici",
    "wof:placetype":"locality"
},
  "geometry": {"coordinates":[18.63007,43.88253],"type":"Point"}
}