{
  "type": "Feature",
  "properties": {
    "gn:admin1_code":"02",
    "gn:asciiname":"Kladari Donji",
    "gn:country_code":"BA",
    "gn:dem":97,
    "gn:feature_class":"P",
    "gn:feature_code":"PPLL",
    "gn:name":"Kladari Donji",
    "gn:population":0,
    "gn:timezone":"Europe/Sarajevo",
    "iso:country":"BA",
    "name:und_x_variant":[
        "Kladari",
        "Kladari Donji"
    ],
    "wof:name":"Kladari Donji",
    "wof:placetype":"locality"
},
  "geometry": {"coordinates":[18.38512,44.97015],"type":"Point"}
}