{
  "type": "Feature",
  "properties": {
    "gn:admin1_code":"01",
    "gn:asciiname":"Donji Poplat",
    "gn:country_code":"BA",
    "gn:dem":120,
    "gn:feature_class":"P",
    "gn:feature_code":"PPL",
    "gn:name":"Donji Poplat",
    "gn:population":0,
    "gn:timezone":"Europe/Sarajevo",
    "iso:country":"BA",
    "wof:name":"Donji Poplat",
    "wof:placetype":"locality"
},
  "geometry": {"coordinates":[17.94238,43.06405],"type":"Point"}
}