{
  "type": "Feature",
  "properties": {
    "gn:admin1_code":"02",
    "gn:asciiname":"Josavka Gornja",
    "gn:country_code":"BA",
    "gn:dem":326,
    "gn:feature_class":"P",
    "gn:feature_code":"PPL",
    "gn:name":"Jo\u0161avka Gornja",
    "gn:population":0,
    "gn:timezone":"Europe/Sarajevo",
    "iso:country":"BA",
    "name:und_x_variant":[
        "Jo\u0161avka Gornja"
    ],
    "wof:name":"Josavka Gornja",
    "wof:placetype":"locality"
},
  "geometry": {"coordinates":[17.46287,44.71989],"type":"Point"}
}