{
  "type": "Feature",
  "properties": {
    "gn:admin1_code":"02",
    "gn:asciiname":"Josavka Gornja",
    "gn:country_code":"BA",
    "gn:dem":326,
    "gn:feature_class":"P",
    "gn:feature_code":"PPL",
    "gn:name":"Jo\u0161avka Gornja",
    "gn:population":0,
    "gn:timezone":"Europe/Sarajevo",
    "iso:country":"BA",
    "name:bos_x_preferred":[
        "Jo\u0161avka Gornja"
    ],
    "name:ceb_x_preferred":[
        "Jo\u0161avka Gornja"
    ],
    "name:fra_x_preferred":[
        "Jo\u0161avka Gornja"
    ],
    "name:hrv_x_preferred":[
        "Jo\u0161avka Gornja"
    ],
    "name:srp_x_preferred":[
        "\u0408\u043e\u0448\u0430\u0432\u043a\u0430 \u0413\u043e\u0440\u045a\u0430"
    ],
    "name:swe_x_preferred":[
        "Jo\u0161avka Gornja"
    ],
    "name:und_x_variant":[
        "Jo\u0161avka Gornja"
    ],
    "wof:name":"Josavka Gornja",
    "wof:placetype":"locality"
},
  "geometry": {"coordinates":[17.46287,44.71989],"type":"Point"}
}