{
  "type": "Feature",
  "properties": {
    "gn:admin1_code":"01",
    "gn:asciiname":"Jagodici",
    "gn:country_code":"BA",
    "gn:dem":451,
    "gn:feature_class":"P",
    "gn:feature_code":"PPL",
    "gn:name":"Jagodi\u0107i",
    "gn:population":0,
    "gn:timezone":"Europe/Sarajevo",
    "iso:country":"BA",
    "name:bos_x_preferred":[
        "Jagodi\u0107i"
    ],
    "name:fra_x_preferred":[
        "Jagodi\u0107i"
    ],
    "name:urd_x_preferred":[
        "\u062c\u06af\u0648\u0688\u06cc\u0633\u0627"
    ],
    "wof:name":"Jagodici",
    "wof:placetype":"locality"
},
  "geometry": {"coordinates":[18.91883,43.64585],"type":"Point"}
}