{
  "type": "Feature",
  "properties": {
    "gn:admin1_code":"01",
    "gn:asciiname":"Vucelje",
    "gn:country_code":"BA",
    "gn:dem":628,
    "gn:feature_class":"P",
    "gn:feature_code":"PPL",
    "gn:name":"Vucelje",
    "gn:population":0,
    "gn:timezone":"Europe/Sarajevo",
    "iso:country":"BA",
    "wof:name":"Vucelje",
    "wof:placetype":"locality"
},
  "geometry": {"coordinates":[16.52161,44.3114],"type":"Point"}
}