{
  "type": "Feature",
  "properties": {
    "gn:admin1_code":"01",
    "gn:asciiname":"Osjecani",
    "gn:country_code":"BA",
    "gn:dem":923,
    "gn:feature_class":"P",
    "gn:feature_code":"PPL",
    "gn:name":"Osje\u010dani",
    "gn:population":0,
    "gn:timezone":"Europe/Sarajevo",
    "iso:country":"BA",
    "name:bos_x_preferred":[
        "Osje\u010dani"
    ],
    "name:fra_x_preferred":[
        "Osje\u010dani"
    ],
    "name:und_x_variant":[
        "Osije\u010dani",
        "Osje\u010dani"
    ],
    "wof:name":"Osjecani",
    "wof:placetype":"locality"
},
  "geometry": {"coordinates":[18.90255,43.71863],"type":"Point"}
}