{
  "type": "Feature",
  "properties": {
    "gn:admin1_code":"02",
    "gn:asciiname":"Seslaci",
    "gn:country_code":"BA",
    "gn:dem":218,
    "gn:feature_class":"P",
    "gn:feature_code":"PPL",
    "gn:name":"\u0160e\u0161laci",
    "gn:population":0,
    "gn:timezone":"Europe/Sarajevo",
    "iso:country":"BA",
    "wof:name":"Seslaci",
    "wof:placetype":"locality"
},
  "geometry": {"coordinates":[18.36148,44.6204],"type":"Point"}
}