{
  "type": "Feature",
  "properties": {
    "gn:admin1_code":"01",
    "gn:asciiname":"Radinja",
    "gn:country_code":"BA",
    "gn:dem":878,
    "gn:feature_class":"P",
    "gn:feature_code":"PPL",
    "gn:name":"Radinja",
    "gn:population":0,
    "gn:timezone":"Europe/Sarajevo",
    "iso:country":"BA",
    "wof:name":"Radinja",
    "wof:placetype":"locality"
},
  "geometry": {"coordinates":[18.36037,44.03545],"type":"Point"}
}