{
  "type": "Feature",
  "properties": {
    "gn:admin1_code":"02",
    "gn:asciiname":"Cericani",
    "gn:country_code":"BA",
    "gn:dem":241,
    "gn:feature_class":"P",
    "gn:feature_code":"PPLL",
    "gn:name":"Ceri\u010dani",
    "gn:population":0,
    "gn:timezone":"Europe/Sarajevo",
    "iso:country":"BA",
    "wof:name":"Cericani",
    "wof:placetype":"locality"
},
  "geometry": {"coordinates":[17.85787000000001,44.79014],"type":"Point"}
}