{
  "type": "Feature",
  "properties": {
    "gn:admin1_code":"02",
    "gn:asciiname":"Vracari",
    "gn:country_code":"BA",
    "gn:dem":781,
    "gn:feature_class":"P",
    "gn:feature_code":"PPL",
    "gn:name":"Vra\u010dari",
    "gn:population":0,
    "gn:timezone":"Europe/Sarajevo",
    "iso:country":"BA",
    "wof:name":"Vracari",
    "wof:placetype":"locality"
},
  "geometry": {"coordinates":[16.77262,44.4408],"type":"Point"}
}