{
  "type": "Feature",
  "properties": {
    "gn:admin1_code":"01",
    "gn:asciiname":"Subotinje",
    "gn:country_code":"BA",
    "gn:dem":580,
    "gn:feature_class":"P",
    "gn:feature_code":"PPLL",
    "gn:name":"Subotinje",
    "gn:population":0,
    "gn:timezone":"Europe/Sarajevo",
    "iso:country":"BA",
    "name:bos_x_preferred":[
        "Subotinje"
    ],
    "name:fra_x_preferred":[
        "Subotinje"
    ],
    "name:hrv_x_preferred":[
        "Subotinje"
    ],
    "name:srp_x_preferred":[
        "\u0421\u0443\u0431\u043e\u0442\u0438\u045a\u0435"
    ],
    "name:und_x_variant":[
        "Subotine"
    ],
    "wof:name":"Subotinje",
    "wof:placetype":"locality"
},
  "geometry": {"coordinates":[18.06332,44.16789],"type":"Point"}
}