{
  "type": "Feature",
  "properties": {
    "gn:admin1_code":"02",
    "gn:asciiname":"Zlovarici",
    "gn:country_code":"BA",
    "gn:dem":821,
    "gn:feature_class":"P",
    "gn:feature_code":"PPL",
    "gn:name":"Zlovari\u0107i",
    "gn:population":0,
    "gn:timezone":"Europe/Sarajevo",
    "iso:country":"BA",
    "wof:name":"Zlovarici",
    "wof:placetype":"locality"
},
  "geometry": {"coordinates":[17.42065,44.43605],"type":"Point"}
}