{
  "type": "Feature",
  "properties": {
    "gn:admin1_code":"02",
    "gn:asciiname":"Gradac",
    "gn:country_code":"BA",
    "gn:dem":1154,
    "gn:feature_class":"P",
    "gn:feature_code":"PPL",
    "gn:name":"Gradac",
    "gn:population":0,
    "gn:timezone":"Europe/Sarajevo",
    "iso:country":"BA",
    "name:bos_x_preferred":[
        "Gradac"
    ],
    "name:fra_x_preferred":[
        "Gradac"
    ],
    "name:srp_x_preferred":[
        "\u0413\u0440\u0430\u0434\u0430\u0446"
    ],
    "wof:name":"Gradac",
    "wof:placetype":"locality"
},
  "geometry": {"coordinates":[18.5984,43.90768],"type":"Point"}
}