{
  "type": "Feature",
  "properties": {
    "gn:admin1_code":"01",
    "gn:asciiname":"Dragunja Gornja",
    "gn:cc2":"BA",
    "gn:country_code":"BA",
    "gn:dem":425,
    "gn:feature_class":"P",
    "gn:feature_code":"PPL",
    "gn:name":"Dragunja Gornja",
    "gn:population":0,
    "gn:timezone":"Europe/Sarajevo",
    "iso:country":"BA",
    "name:und_x_variant":[
        "Gornja Dragunja",
        "Dragunja Gornja"
    ],
    "wof:name":"Dragunja Gornja",
    "wof:placetype":"locality"
},
  "geometry": {"coordinates":[18.61611,44.65056],"type":"Point"}
}