{
  "type": "Feature",
  "properties": {
    "gn:country":"BA",
    "gn:fcode":"PPL",
    "gn:pop":4371,
    "iso:country":"BA",
    "name:bos_x_preferred":[
        "Orguz"
    ],
    "name:bul_x_preferred":[
        "\u041e\u0440\u0433\u0443\u0437"
    ],
    "name:dut_x_preferred":[
        "Orguz"
    ],
    "name:eng_x_preferred":[
        "Orguz"
    ],
    "name:fre_x_preferred":[
        "Orguz"
    ],
    "name:hrv_x_preferred":[
        "Orguz"
    ],
    "name:swe_x_preferred":[
        "Orguz"
    ],
    "qs:name":"Orguz",
    "qs:name_adm0":"Bosna i Hercegovina",
    "qs:name_adm1":"Federacija Bosne I Hercegovine",
    "qs:photos_9k":1,
    "qs:photos_9r":4,
    "qs:photos_all":201,
    "qs:photos_sr":0,
    "qs:placetype":"Town",
    "qs:pop_sr":"4",
    "wd:wordcount":57,
    "wof:name":"Orguz",
    "wof:placetype":"locality",
    "wof:population":4371
},
  "geometry": {"coordinates":[16.86329,43.77414],"type":"Point"}
}