{
  "type": "Feature",
  "properties": {
    "gn:admin1_code":"02",
    "gn:asciiname":"Donji Visnjik",
    "gn:country_code":"BA",
    "gn:dem":193,
    "gn:feature_class":"P",
    "gn:feature_code":"PPLL",
    "gn:name":"Donji Vi\u0161njik",
    "gn:population":0,
    "gn:timezone":"Europe/Sarajevo",
    "iso:country":"BA",
    "wof:name":"Donji Visnjik",
    "wof:placetype":"locality"
},
  "geometry": {"coordinates":[18.04667,45.00833],"type":"Point"}
}