{
  "type": "Feature",
  "properties": {
    "gn:admin1_code":"01",
    "gn:asciiname":"Prsici",
    "gn:country_code":"BA",
    "gn:dem":241,
    "gn:feature_class":"P",
    "gn:feature_code":"PPL",
    "gn:name":"Pr\u0161i\u0107i",
    "gn:population":0,
    "gn:timezone":"Europe/Sarajevo",
    "iso:country":"BA",
    "wof:name":"Prsici",
    "wof:placetype":"locality"
},
  "geometry": {"coordinates":[16.74217,44.67554000000001],"type":"Point"}
}