{
  "type": "Feature",
  "properties": {
    "gn:admin1_code":"01",
    "gn:asciiname":"Kadijevici",
    "gn:country_code":"BA",
    "gn:dem":40,
    "gn:feature_class":"P",
    "gn:feature_code":"PPL",
    "gn:name":"Kadijevi\u0107i",
    "gn:population":0,
    "gn:timezone":"Europe/Sarajevo",
    "iso:country":"BA",
    "wof:name":"Kadijevici",
    "wof:placetype":"locality"
},
  "geometry": {"coordinates":[17.83278,43.28944],"type":"Point"}
}