{
  "type": "Feature",
  "properties": {
    "gn:admin1_code":"02",
    "gn:asciiname":"Crna Rijeka",
    "gn:country_code":"BA",
    "gn:dem":1198,
    "gn:feature_class":"P",
    "gn:feature_code":"PPL",
    "gn:name":"Crna Rijeka",
    "gn:population":0,
    "gn:timezone":"Europe/Sarajevo",
    "iso:country":"BA",
    "name:srp_x_preferred":[
        "\u0426\u0440\u043d\u0430 \u0440\u0438\u0458\u0435\u043a\u0430"
    ],
    "wof:name":"Crna Rijeka",
    "wof:placetype":"locality"
},
  "geometry": {"coordinates":[19.01417,44.08639],"type":"Point"}
}