{
  "type": "Feature",
  "properties": {
    "gn:admin1_code":"02",
    "gn:asciiname":"Vecici",
    "gn:country_code":"BA",
    "gn:dem":325,
    "gn:feature_class":"P",
    "gn:feature_code":"PPL",
    "gn:name":"Ve\u010di\u0107i",
    "gn:population":0,
    "gn:timezone":"Europe/Sarajevo",
    "iso:country":"BA",
    "name:und_x_variant":[
        "Ve\u010di\u0107i"
    ],
    "wof:name":"Vecici",
    "wof:placetype":"locality"
},
  "geometry": {"coordinates":[17.4328,44.57653],"type":"Point"}
}