{
  "type": "Feature",
  "properties": {
    "gn:admin1_code":"02",
    "gn:asciiname":"Vecici",
    "gn:country_code":"BA",
    "gn:dem":325,
    "gn:feature_class":"P",
    "gn:feature_code":"PPL",
    "gn:name":"Ve\u010di\u0107i",
    "gn:population":0,
    "gn:timezone":"Europe/Sarajevo",
    "iso:country":"BA",
    "name:bos_x_preferred":[
        "Ve\u010di\u0107i"
    ],
    "name:fra_x_preferred":[
        "Ve\u010di\u0107i"
    ],
    "name:hrv_x_preferred":[
        "Ve\u010di\u0107i"
    ],
    "name:spa_x_preferred":[
        "Ve\u010di\u0107i"
    ],
    "name:srp_x_preferred":[
        "\u0412\u0435\u0447\u0438\u045b\u0438"
    ],
    "wof:name":"Vecici",
    "wof:placetype":"locality"
},
  "geometry": {"coordinates":[17.4328,44.57653],"type":"Point"}
}