{
  "type": "Feature",
  "properties": {
    "gn:admin1_code":"02",
    "gn:asciiname":"Krajisnik",
    "gn:country_code":"BA",
    "gn:dem":95,
    "gn:feature_class":"P",
    "gn:feature_code":"PPL",
    "gn:name":"Kraji\u0161nik",
    "gn:population":0,
    "gn:timezone":"Europe/Sarajevo",
    "iso:country":"BA",
    "name:und_x_variant":[
        "Kraji\u0161nik"
    ],
    "wof:name":"Krajisnik",
    "wof:placetype":"locality"
},
  "geometry": {"coordinates":[17.32544,45.05731],"type":"Point"}
}