{
  "type": "Feature",
  "properties": {
    "gn:admin1_code":"01",
    "gn:asciiname":"Leke",
    "gn:country_code":"BA",
    "gn:dem":272,
    "gn:feature_class":"P",
    "gn:feature_code":"PPL",
    "gn:name":"Leke",
    "gn:population":0,
    "gn:timezone":"Europe/Sarajevo",
    "iso:country":"BA",
    "wof:name":"Leke",
    "wof:placetype":"locality"
},
  "geometry": {"coordinates":[17.46404,43.30791],"type":"Point"}
}