{
  "type": "Feature",
  "properties": {
    "gn:admin1_code":"01",
    "gn:asciiname":"Vrbice",
    "gn:country_code":"BA",
    "gn:dem":626,
    "gn:feature_class":"P",
    "gn:feature_code":"PPL",
    "gn:name":"Vrbice",
    "gn:population":0,
    "gn:timezone":"Europe/Sarajevo",
    "iso:country":"BA",
    "name:ceb_x_preferred":[
        "Vrbice"
    ],
    "name:ces_x_preferred":[
        "Vrbice"
    ],
    "name:deu_x_preferred":[
        "Vrbice"
    ],
    "name:epo_x_preferred":[
        "Vrbice"
    ],
    "name:fra_x_preferred":[
        "Vrbice"
    ],
    "name:ita_x_preferred":[
        "Vrbice"
    ],
    "name:nld_x_preferred":[
        "Vrbice"
    ],
    "name:pol_x_preferred":[
        "Vrbice"
    ],
    "name:slk_x_preferred":[
        "Vrbice"
    ],
    "name:srp_x_preferred":[
        "\u0412\u0440\u0431\u0438\u0446\u0435"
    ],
    "name:swe_x_preferred":[
        "Vrbice"
    ],
    "wof:name":"Vrbice",
    "wof:placetype":"locality"
},
  "geometry": {"coordinates":[17.77744,44.22837],"type":"Point"}
}