{
  "type": "Feature",
  "properties": {
    "gn:admin1_code":"02",
    "gn:asciiname":"Brloznik",
    "gn:country_code":"BA",
    "gn:dem":846,
    "gn:feature_class":"P",
    "gn:feature_code":"PPLL",
    "gn:name":"Brlo\u017enik",
    "gn:population":0,
    "gn:timezone":"Europe/Sarajevo",
    "iso:country":"BA",
    "name:und_x_variant":[
        "Brlo\u017enik"
    ],
    "wof:name":"Brloznik",
    "wof:placetype":"locality"
},
  "geometry": {"coordinates":[19.10388,44.01371],"type":"Point"}
}