{
  "type": "Feature",
  "properties": {
    "gn:admin1_code":"01",
    "gn:asciiname":"Gornja Ricica",
    "gn:country_code":"BA",
    "gn:dem":914,
    "gn:feature_class":"P",
    "gn:feature_code":"PPL",
    "gn:name":"Gornja Ri\u010dica",
    "gn:population":0,
    "gn:timezone":"Europe/Sarajevo",
    "iso:country":"BA",
    "name:bos_x_preferred":[
        "Gornja Ri\u010dica"
    ],
    "name:fra_x_preferred":[
        "Gornja Ri\u010dica"
    ],
    "name:hrv_x_preferred":[
        "Gornja Ri\u010dica"
    ],
    "name:srp_x_preferred":[
        "\u0413\u043e\u0440\u045a\u0430 \u0420\u0438\u0447\u0438\u0446\u0430"
    ],
    "name:und_x_variant":[
        "Gonja Ri\u010dica",
        "Gornja Ri\u010dica"
    ],
    "wof:name":"Gornja Ricica",
    "wof:placetype":"locality"
},
  "geometry": {"coordinates":[17.55569,43.98889000000001],"type":"Point"}
}