{
  "type": "Feature",
  "properties": {
    "gn:admin1_code":"01",
    "gn:asciiname":"Ravne Njive",
    "gn:country_code":"BA",
    "gn:dem":814,
    "gn:feature_class":"P",
    "gn:feature_code":"PPL",
    "gn:name":"Ravne Njive",
    "gn:population":0,
    "gn:timezone":"Europe/Sarajevo",
    "iso:country":"BA",
    "wof:name":"Ravne Njive",
    "wof:placetype":"locality"
},
  "geometry": {"coordinates":[18.85717,43.66238],"type":"Point"}
}