{
  "type": "Feature",
  "properties": {
    "gn:admin1_code":"01",
    "gn:asciiname":"Prekounje",
    "gn:country_code":"BA",
    "gn:dem":228,
    "gn:feature_class":"P",
    "gn:feature_code":"PPL",
    "gn:name":"Prekounje",
    "gn:population":0,
    "gn:timezone":"Europe/Sarajevo",
    "iso:country":"BA",
    "wof:name":"Prekounje",
    "wof:placetype":"locality"
},
  "geometry": {"coordinates":[15.95022,44.76262],"type":"Point"}
}