{
  "type": "Feature",
  "properties": {
    "gn:admin1_code":"02",
    "gn:asciiname":"Srdevici",
    "gn:country_code":"BA",
    "gn:dem":956,
    "gn:feature_class":"P",
    "gn:feature_code":"PPL",
    "gn:name":"Sr\u0111evi\u0107i",
    "gn:population":0,
    "gn:timezone":"Europe/Sarajevo",
    "iso:country":"BA",
    "name:und_x_variant":[
        "Srdjevi\u0107i",
        "Sr\u0111evi\u0107i"
    ],
    "wof:name":"Srdevici",
    "wof:placetype":"locality"
},
  "geometry": {"coordinates":[18.48515,43.16425],"type":"Point"}
}