{
  "type": "Feature",
  "properties": {
    "gn:admin1_code":"02",
    "gn:asciiname":"Avramovici",
    "gn:country_code":"BA",
    "gn:dem":422,
    "gn:feature_class":"P",
    "gn:feature_code":"PPL",
    "gn:name":"Avramovi\u0107i",
    "gn:population":0,
    "gn:timezone":"Europe/Sarajevo",
    "iso:country":"BA",
    "wof:name":"Avramovici",
    "wof:placetype":"locality"
},
  "geometry": {"coordinates":[19.05451,44.18429],"type":"Point"}
}