{
  "type": "Feature",
  "properties": {
    "gn:admin1_code":"02",
    "gn:asciiname":"Miljevici",
    "gn:country_code":"BA",
    "gn:dem":191,
    "gn:feature_class":"P",
    "gn:feature_code":"PPL",
    "gn:name":"Miljevi\u0107i",
    "gn:population":0,
    "gn:timezone":"Europe/Sarajevo",
    "iso:country":"BA",
    "wof:name":"Miljevici",
    "wof:placetype":"locality"
},
  "geometry": {"coordinates":[16.71805,44.92563],"type":"Point"}
}