{
  "type": "Feature",
  "properties": {
    "gn:admin1_code":"02",
    "gn:asciiname":"Garici",
    "gn:country_code":"BA",
    "gn:dem":515,
    "gn:feature_class":"P",
    "gn:feature_code":"PPL",
    "gn:name":"Gari\u0107i",
    "gn:population":0,
    "gn:timezone":"Europe/Sarajevo",
    "iso:country":"BA",
    "wof:name":"Garici",
    "wof:placetype":"locality"
},
  "geometry": {"coordinates":[18.86773,44.20734],"type":"Point"}
}