{
  "type": "Feature",
  "properties": {
    "gn:admin1_code":"01",
    "gn:asciiname":"Dimici",
    "gn:country_code":"BA",
    "gn:dem":532,
    "gn:feature_class":"P",
    "gn:feature_code":"PPL",
    "gn:name":"Dimi\u0107i",
    "gn:population":0,
    "gn:timezone":"Europe/Sarajevo",
    "iso:country":"BA",
    "wof:name":"Dimici",
    "wof:placetype":"locality"
},
  "geometry": {"coordinates":[16.53772,44.77821],"type":"Point"}
}