{
  "type": "Feature",
  "properties": {
    "gn:admin1_code":"01",
    "gn:asciiname":"Culumi",
    "gn:country_code":"BA",
    "gn:dem":1040,
    "gn:feature_class":"P",
    "gn:feature_code":"PPL",
    "gn:name":"\u0106ulumi",
    "gn:population":0,
    "gn:timezone":"Europe/Sarajevo",
    "iso:country":"BA",
    "wof:name":"Culumi",
    "wof:placetype":"locality"
},
  "geometry": {"coordinates":[16.67697,44.23712],"type":"Point"}
}