{
  "type": "Feature",
  "properties": {
    "gn:admin1_code":"02",
    "gn:asciiname":"Batovo",
    "gn:country_code":"BA",
    "gn:dem":757,
    "gn:feature_class":"P",
    "gn:feature_code":"PPL",
    "gn:name":"Batovo",
    "gn:population":0,
    "gn:timezone":"Europe/Sarajevo",
    "iso:country":"BA",
    "name:und_x_variant":[
        "Jehovci",
        "Batovo"
    ],
    "wof:name":"Batovo",
    "wof:placetype":"locality"
},
  "geometry": {"coordinates":[18.7499,44.02141],"type":"Point"}
}