{
  "type": "Feature",
  "properties": {
    "gn:admin1_code":"02",
    "gn:asciiname":"Batovo",
    "gn:country_code":"BA",
    "gn:dem":757,
    "gn:feature_class":"P",
    "gn:feature_code":"PPL",
    "gn:name":"Batovo",
    "gn:population":0,
    "gn:timezone":"Europe/Sarajevo",
    "iso:country":"BA",
    "name:ceb_x_preferred":[
        "Batovo"
    ],
    "name:fra_x_preferred":[
        "Batovo"
    ],
    "name:hrv_x_preferred":[
        "Batovo"
    ],
    "name:rus_x_preferred":[
        "\u0411\u0430\u0442\u043e\u0432\u043e"
    ],
    "name:srp_x_preferred":[
        "\u0411\u0430\u0442\u043e\u0432\u043e"
    ],
    "name:swe_x_preferred":[
        "Batovo"
    ],
    "name:und_x_variant":[
        "Jehovci"
    ],
    "wof:name":"Batovo",
    "wof:placetype":"locality"
},
  "geometry": {"coordinates":[18.7499,44.02141],"type":"Point"}
}