{
  "type": "Feature",
  "properties": {
    "gn:admin1_code":"02",
    "gn:asciiname":"Miljakovci",
    "gn:country_code":"BA",
    "gn:dem":210,
    "gn:feature_class":"P",
    "gn:feature_code":"PPLL",
    "gn:name":"Miljakovci",
    "gn:population":0,
    "gn:timezone":"Europe/Sarajevo",
    "iso:country":"BA",
    "wof:name":"Miljakovci",
    "wof:placetype":"locality"
},
  "geometry": {"coordinates":[16.72981,44.92015],"type":"Point"}
}