{
  "type": "Feature",
  "properties": {
    "gn:country":"BA",
    "gn:fcode":"PPL",
    "gn:population":4388,
    "iso:country":"BA",
    "name:bos_x_preferred":[
        "Svodna"
    ],
    "name:eng_x_preferred":[
        "Svodna"
    ],
    "name:fra_x_preferred":[
        "Svodna"
    ],
    "name:hrv_x_preferred":[
        "Svodna"
    ],
    "name:nld_x_preferred":[
        "Svodna"
    ],
    "name:srp_x_preferred":[
        "\u0421\u0432\u043e\u0434\u043d\u0430"
    ],
    "qs:name":"Svodna",
    "qs:name_adm0":"Bosna i Hercegovina",
    "qs:name_adm1":"Republika Srpska",
    "qs:photos_9r":0,
    "qs:photos_sr":0,
    "qs:placetype":"Town",
    "qs:pop_sr":"4",
    "wd:wordcount":62,
    "wof:name":"Svodna",
    "wof:placetype":"locality",
    "wof:population":4388
},
  "geometry": {"coordinates":[16.54019,45.0377],"type":"Point"}
}