{
  "type": "Feature",
  "properties": {
    "gn:admin1_code":"02",
    "gn:asciiname":"Milakovici",
    "gn:country_code":"BA",
    "gn:dem":896,
    "gn:feature_class":"P",
    "gn:feature_code":"PPL",
    "gn:name":"Milakovi\u0107i",
    "gn:population":0,
    "gn:timezone":"Europe/Sarajevo",
    "iso:country":"BA",
    "wof:name":"Milakovici",
    "wof:placetype":"locality"
},
  "geometry": {"coordinates":[18.23366,43.18566],"type":"Point"}
}