{
  "type": "Feature",
  "properties": {
    "gn:admin1_code":"02",
    "gn:asciiname":"Postolje",
    "gn:country_code":"BA",
    "gn:dem":851,
    "gn:feature_class":"P",
    "gn:feature_code":"PPL",
    "gn:name":"Postolje",
    "gn:population":0,
    "gn:timezone":"Europe/Sarajevo",
    "iso:country":"BA",
    "name:bos_x_preferred":[
        "Postolje"
    ],
    "name:bul_x_preferred":[
        "\u041f\u043e\u0441\u0442\u043e\u043b\u0435"
    ],
    "name:fra_x_preferred":[
        "Postolje"
    ],
    "name:hrv_x_preferred":[
        "Postolje"
    ],
    "name:srp_x_preferred":[
        "\u041f\u043e\u0441\u0442\u043e\u0459\u0435"
    ],
    "wof:name":"Postolje",
    "wof:placetype":"locality"
},
  "geometry": {"coordinates":[19.42514,44.02428],"type":"Point"}
}