{
  "type": "Feature",
  "properties": {
    "gn:admin1_code":"02",
    "gn:asciiname":"Vakufci",
    "gn:country_code":"BA",
    "gn:dem":494,
    "gn:feature_class":"P",
    "gn:feature_code":"PPL",
    "gn:name":"Vakufci",
    "gn:population":0,
    "gn:timezone":"Europe/Sarajevo",
    "iso:country":"BA",
    "wof:name":"Vakufci",
    "wof:placetype":"locality"
},
  "geometry": {"coordinates":[17.48414,44.59642],"type":"Point"}
}