{
  "type": "Feature",
  "properties": {
    "gn:admin1_code":"01",
    "gn:asciiname":"Jasikovaca",
    "gn:country_code":"BA",
    "gn:dem":1046,
    "gn:feature_class":"P",
    "gn:feature_code":"PPL",
    "gn:name":"Jasikova\u010da",
    "gn:population":0,
    "gn:timezone":"Europe/Sarajevo",
    "iso:country":"BA",
    "wof:name":"Jasikovaca",
    "wof:placetype":"locality"
},
  "geometry": {"coordinates":[16.43389,44.39611],"type":"Point"}
}