{
  "type": "Feature",
  "properties": {
    "gn:admin1_code":"01",
    "gn:asciiname":"Susljici",
    "gn:country_code":"BA",
    "gn:dem":1010,
    "gn:feature_class":"P",
    "gn:feature_code":"PPL",
    "gn:name":"\u0160u\u0161lji\u0107i",
    "gn:population":0,
    "gn:timezone":"Europe/Sarajevo",
    "iso:country":"BA",
    "name:und_x_variant":[
        "\u0160u\u0161lji\u0107i"
    ],
    "wof:name":"Susljici",
    "wof:placetype":"locality"
},
  "geometry": {"coordinates":[17.54957000000001,44.04165],"type":"Point"}
}