{
  "type": "Feature",
  "properties": {
    "gn:admin1_code":"02",
    "gn:asciiname":"Dimitrici",
    "gn:country_code":"BA",
    "gn:dem":170,
    "gn:feature_class":"P",
    "gn:feature_code":"PPL",
    "gn:name":"Dimitri\u0107i",
    "gn:population":0,
    "gn:timezone":"Europe/Sarajevo",
    "iso:country":"BA",
    "wof:name":"Dimitrici",
    "wof:placetype":"locality"
},
  "geometry": {"coordinates":[17.81573,44.85883],"type":"Point"}
}