{
  "type": "Feature",
  "properties": {
    "gn:admin1_code":"01",
    "gn:asciiname":"Lokve",
    "gn:country_code":"BA",
    "gn:dem":711,
    "gn:feature_class":"P",
    "gn:feature_code":"PPL",
    "gn:name":"Lokve",
    "gn:population":0,
    "gn:timezone":"Europe/Sarajevo",
    "iso:country":"BA",
    "name:bos_x_preferred":[
        "Lokve"
    ],
    "name:ceb_x_preferred":[
        "Lokve"
    ],
    "name:fra_x_preferred":[
        "Lokve"
    ],
    "name:hrv_x_preferred":[
        "Lokve"
    ],
    "name:hun_x_preferred":[
        "Lokve"
    ],
    "name:ita_x_preferred":[
        "Lokve"
    ],
    "name:nld_x_preferred":[
        "Lokve"
    ],
    "name:slv_x_preferred":[
        "Lokve"
    ],
    "name:srp_x_preferred":[
        "\u041b\u043e\u043a\u0432\u0435"
    ],
    "name:swe_x_preferred":[
        "Lokve"
    ],
    "wof:name":"Lokve",
    "wof:placetype":"locality"
},
  "geometry": {"coordinates":[18.7013,43.59848],"type":"Point"}
}