{
  "type": "Feature",
  "properties": {
    "gn:admin1_code":"01",
    "gn:asciiname":"Lokve",
    "gn:country_code":"BA",
    "gn:dem":711,
    "gn:feature_class":"P",
    "gn:feature_code":"PPL",
    "gn:name":"Lokve",
    "gn:population":0,
    "gn:timezone":"Europe/Sarajevo",
    "iso:country":"BA",
    "wof:name":"Lokve",
    "wof:placetype":"locality"
},
  "geometry": {"coordinates":[18.7013,43.59848],"type":"Point"}
}