{
  "type": "Feature",
  "properties": {
    "gn:admin1_code":"01",
    "gn:asciiname":"Sisarice",
    "gn:country_code":"BA",
    "gn:dem":389,
    "gn:feature_class":"P",
    "gn:feature_code":"PPL",
    "gn:name":"\u0160i\u0161arice",
    "gn:population":0,
    "gn:timezone":"Europe/Sarajevo",
    "iso:country":"BA",
    "wof:name":"Sisarice",
    "wof:placetype":"locality"
},
  "geometry": {"coordinates":[16.8498,44.60683],"type":"Point"}
}