{
  "type": "Feature",
  "properties": {
    "gn:admin1_code":"01",
    "gn:asciiname":"Kovacica",
    "gn:country_code":"BA",
    "gn:dem":402,
    "gn:feature_class":"P",
    "gn:feature_code":"PPLL",
    "gn:name":"Kova\u010dica",
    "gn:population":0,
    "gn:timezone":"Europe/Sarajevo",
    "iso:country":"BA",
    "wof:name":"Kovacica",
    "wof:placetype":"locality"
},
  "geometry": {"coordinates":[18.79215,44.56408],"type":"Point"}
}