{
  "type": "Feature",
  "properties": {
    "gn:admin1_code":"02",
    "gn:asciiname":"Gumnjani",
    "gn:country_code":"BA",
    "gn:dem":321,
    "gn:feature_class":"P",
    "gn:feature_code":"PPLL",
    "gn:name":"Gumnjani",
    "gn:population":0,
    "gn:timezone":"Europe/Sarajevo",
    "iso:country":"BA",
    "wof:name":"Gumnjani",
    "wof:placetype":"locality"
},
  "geometry": {"coordinates":[16.54959,45.1775],"type":"Point"}
}