{
  "type": "Feature",
  "properties": {
    "gn:admin1_code":"01",
    "gn:asciiname":"Jonjici",
    "gn:country_code":"BA",
    "gn:dem":524,
    "gn:feature_class":"P",
    "gn:feature_code":"PPL",
    "gn:name":"Jonji\u0107i",
    "gn:population":0,
    "gn:timezone":"Europe/Sarajevo",
    "iso:country":"BA",
    "wof:name":"Jonjici",
    "wof:placetype":"locality"
},
  "geometry": {"coordinates":[18.19284,44.07675],"type":"Point"}
}