{
  "type": "Feature",
  "properties": {
    "gn:admin1_code":"02",
    "gn:asciiname":"Bijelo Vrelo",
    "gn:country_code":"BA",
    "gn:dem":238,
    "gn:feature_class":"P",
    "gn:feature_code":"PPL",
    "gn:name":"Bijelo Vrelo",
    "gn:population":0,
    "gn:timezone":"Europe/Sarajevo",
    "iso:country":"BA",
    "wof:name":"Bijelo Vrelo",
    "wof:placetype":"locality"
},
  "geometry": {"coordinates":[16.53222,44.95806],"type":"Point"}
}