{
  "type": "Feature",
  "properties": {
    "gn:admin1_code":"01",
    "gn:asciiname":"Crnacka Ladina",
    "gn:country_code":"BA",
    "gn:dem":1002,
    "gn:feature_class":"P",
    "gn:feature_code":"PPL",
    "gn:name":"Crna\u010dka Ladina",
    "gn:population":0,
    "gn:timezone":"Europe/Sarajevo",
    "iso:country":"BA",
    "wof:name":"Crnacka Ladina",
    "wof:placetype":"locality"
},
  "geometry": {"coordinates":[17.60451,43.46873],"type":"Point"}
}