{
  "type": "Feature",
  "properties": {
    "gn:admin1_code":"01",
    "gn:asciiname":"Vaganj",
    "gn:country_code":"BA",
    "gn:dem":1166,
    "gn:feature_class":"P",
    "gn:feature_code":"PPL",
    "gn:name":"Vaganj",
    "gn:population":0,
    "gn:timezone":"Europe/Sarajevo",
    "iso:country":"BA",
    "wof:name":"Vaganj",
    "wof:placetype":"locality"
},
  "geometry": {"coordinates":[16.79526,43.78601],"type":"Point"}
}