{
  "type": "Feature",
  "properties": {
    "gn:admin1_code":"02",
    "gn:asciiname":"Dragasi",
    "gn:country_code":"BA",
    "gn:dem":124,
    "gn:feature_class":"P",
    "gn:feature_code":"PPL",
    "gn:name":"Draga\u0161i",
    "gn:population":0,
    "gn:timezone":"Europe/Sarajevo",
    "iso:country":"BA",
    "wof:name":"Dragasi",
    "wof:placetype":"locality"
},
  "geometry": {"coordinates":[16.8693,45.16262],"type":"Point"}
}