{
  "type": "Feature",
  "properties": {
    "gn:admin1_code":"01",
    "gn:asciiname":"Mjestova Ravan",
    "gn:country_code":"BA",
    "gn:dem":586,
    "gn:feature_class":"P",
    "gn:feature_code":"PPL",
    "gn:name":"Mjestova Ravan",
    "gn:population":0,
    "gn:timezone":"Europe/Sarajevo",
    "iso:country":"BA",
    "wof:name":"Mjestova Ravan",
    "wof:placetype":"locality"
},
  "geometry": {"coordinates":[17.93291,44.4059],"type":"Point"}
}