{
  "type": "Feature",
  "properties": {
    "gn:admin1_code":"01",
    "gn:asciiname":"Trestenica Gornja",
    "gn:country_code":"BA",
    "gn:dem":402,
    "gn:feature_class":"P",
    "gn:feature_code":"PPLL",
    "gn:name":"Tre\u0161tenica Gornja",
    "gn:population":0,
    "gn:timezone":"Europe/Sarajevo",
    "iso:country":"BA",
    "name:ara_x_preferred":[
        "\u062a\u0631\u0634\u062a\u064a\u0646\u064a\u0643\u0627 \u063a\u0648\u0631\u0646\u064a\u0627"
    ],
    "name:bos_x_preferred":[
        "Tre\u0161tenica Gornja"
    ],
    "name:ceb_x_preferred":[
        "Tre\u0161tenica Gornja"
    ],
    "name:deu_x_preferred":[
        "Tre\u0161tenica Gornja"
    ],
    "name:fra_x_preferred":[
        "Tre\u0161tenica Gornja"
    ],
    "name:hrv_x_preferred":[
        "Tre\u0161tenica Gornja"
    ],
    "name:slv_x_preferred":[
        "Tre\u0161tenica Gornja"
    ],
    "name:srp_x_preferred":[
        "\u0422\u0440\u0435\u0448\u0442\u0435\u043d\u0438\u0446\u0430 \u0413\u043e\u0440\u045a\u0430"
    ],
    "name:swe_x_preferred":[
        "Tre\u0161tenica Gornja"
    ],
    "wof:name":"Trestenica Gornja",
    "wof:placetype":"locality"
},
  "geometry": {"coordinates":[18.44165,44.44129],"type":"Point"}
}