{
  "type": "Feature",
  "properties": {
    "gn:country":"BA",
    "gn:fcode":"PPL",
    "gn:pop":6617,
    "iso:country":"BA",
    "name:bos_x_preferred":[
        "Tr\u017ea\u010dka Ra\u0161tela"
    ],
    "name:ceb_x_preferred":[
        "Tr\u017ea\u010dka Ra\u0161tela"
    ],
    "name:eng_x_preferred":[
        "Tr\u017ea\u010dka Ra\u0161tela"
    ],
    "name:fas_x_preferred":[
        "\u062a\u0631\u0698\u0627\u0698\u06a9\u0627 \u0631\u0627\u0634\u062a\u0644\u0627"
    ],
    "name:fra_x_preferred":[
        "Tr\u017ea\u010dka Ra\u0161tela"
    ],
    "name:nld_x_preferred":[
        "Tr\u017ea\u010dka Ra\u0161tela"
    ],
    "name:swe_x_preferred":[
        "Tr\u017ea\u010dka Ra\u0161tela"
    ],
    "name:zho_x_preferred":[
        "\u7279\u723e\u8cc8\u5947\u5361\u62c9\u5e0c\u7279\u96f7"
    ],
    "qs:name":"Tr\u017ea\u010dka Ra\u0161tela",
    "qs:name_adm0":"Bosna i Hercegovina",
    "qs:name_adm1":"Federacija Bosne I Hercegovine",
    "qs:photos_9r":0,
    "qs:photos_sr":0,
    "qs:placetype":"Town",
    "qs:pop_sr":"5",
    "wd:wordcount":58,
    "wof:name":"Tr\u017ea\u010dka Ra\u0161tela",
    "wof:placetype":"locality",
    "wof:population":6617
},
  "geometry": {"coordinates":[15.78489,44.97597],"type":"Point"}
}