{
  "type": "Feature",
  "properties": {
    "gn:admin1_code":"01",
    "gn:asciiname":"Toka",
    "gn:country_code":"BA",
    "gn:dem":653,
    "gn:feature_class":"P",
    "gn:feature_code":"PPL",
    "gn:name":"Toka",
    "gn:population":0,
    "gn:timezone":"Europe/Sarajevo",
    "iso:country":"BA",
    "name:ben_x_preferred":[
        "\u099f\u09cb\u0995\u09be"
    ],
    "name:ceb_x_preferred":[
        "Toka"
    ],
    "name:deu_x_preferred":[
        "Toka"
    ],
    "name:swe_x_preferred":[
        "Toka"
    ],
    "wof:name":"Toka",
    "wof:placetype":"locality"
},
  "geometry": {"coordinates":[17.31295,44.39518],"type":"Point"}
}