{
  "type": "Feature",
  "properties": {
    "gn:admin1_code":"01",
    "gn:asciiname":"Toka",
    "gn:country_code":"BA",
    "gn:dem":653,
    "gn:feature_class":"P",
    "gn:feature_code":"PPL",
    "gn:name":"Toka",
    "gn:population":0,
    "gn:timezone":"Europe/Sarajevo",
    "iso:country":"BA",
    "wof:name":"Toka",
    "wof:placetype":"locality"
},
  "geometry": {"coordinates":[17.31295,44.39518],"type":"Point"}
}