{
  "type": "Feature",
  "properties": {
    "gn:admin1_code":"02",
    "gn:asciiname":"Santraci",
    "gn:country_code":"BA",
    "gn:dem":822,
    "gn:feature_class":"P",
    "gn:feature_code":"PPL",
    "gn:name":"Santra\u010di",
    "gn:population":0,
    "gn:timezone":"Europe/Sarajevo",
    "iso:country":"BA",
    "wof:name":"Santraci",
    "wof:placetype":"locality"
},
  "geometry": {"coordinates":[18.47639,43.83722],"type":"Point"}
}