{
  "type": "Feature",
  "properties": {
    "gn:admin1_code":"02",
    "gn:asciiname":"Banjevici",
    "gn:country_code":"BA",
    "gn:dem":542,
    "gn:feature_class":"P",
    "gn:feature_code":"PPL",
    "gn:name":"Banjevi\u0107i",
    "gn:population":0,
    "gn:timezone":"Europe/Sarajevo",
    "iso:country":"BA",
    "name:und_x_variant":[
        "Banjevi\u0107",
        "Banjevi\u0107i"
    ],
    "wof:name":"Banjevici",
    "wof:placetype":"locality"
},
  "geometry": {"coordinates":[19.1824,44.24989],"type":"Point"}
}