{
  "type": "Feature",
  "properties": {
    "gn:admin1_code":"02",
    "gn:asciiname":"Banjevici",
    "gn:country_code":"BA",
    "gn:dem":542,
    "gn:feature_class":"P",
    "gn:feature_code":"PPL",
    "gn:name":"Banjevi\u0107i",
    "gn:population":0,
    "gn:timezone":"Europe/Sarajevo",
    "iso:country":"BA",
    "name:bos_x_preferred":[
        "Banjevi\u0107i"
    ],
    "name:bul_x_preferred":[
        "\u0411\u0430\u043d\u0435\u0432\u0438\u0447\u0438"
    ],
    "name:fra_x_preferred":[
        "Banjevi\u0107i"
    ],
    "name:hrv_x_preferred":[
        "Banjevi\u0107i"
    ],
    "name:rus_x_preferred":[
        "\u0411\u0430\u043d\u0435\u0432\u0438\u0447\u0438"
    ],
    "name:srp_x_preferred":[
        "\u0411\u0430\u045a\u0435\u0432\u0438\u045b\u0438"
    ],
    "name:und_x_variant":[
        "Banjevi\u0107"
    ],
    "wof:name":"Banjevici",
    "wof:placetype":"locality"
},
  "geometry": {"coordinates":[19.1824,44.24989],"type":"Point"}
}