{
  "type": "Feature",
  "properties": {
    "gn:admin1_code":"02",
    "gn:asciiname":"Hadzici",
    "gn:country_code":"BA",
    "gn:dem":161,
    "gn:feature_class":"P",
    "gn:feature_code":"PPL",
    "gn:name":"Had\u017ei\u0107i",
    "gn:population":0,
    "gn:timezone":"Europe/Sarajevo",
    "iso:country":"BA",
    "wof:name":"Hadzici",
    "wof:placetype":"locality"
},
  "geometry": {"coordinates":[16.86297,44.91967],"type":"Point"}
}