{
  "type": "Feature",
  "properties": {
    "gn:admin1_code":"01",
    "gn:asciiname":"Ravan",
    "gn:country_code":"BA",
    "gn:dem":374,
    "gn:feature_class":"P",
    "gn:feature_code":"PPL",
    "gn:name":"Ravan",
    "gn:population":0,
    "gn:timezone":"Europe/Sarajevo",
    "iso:country":"BA",
    "wof:name":"Ravan",
    "wof:placetype":"locality"
},
  "geometry": {"coordinates":[18.29247,44.43497],"type":"Point"}
}