{
  "type": "Feature",
  "properties": {
    "gn:admin1_code":"02",
    "gn:asciiname":"Jaksin Do",
    "gn:country_code":"BA",
    "gn:dem":923,
    "gn:feature_class":"P",
    "gn:feature_code":"PPL",
    "gn:name":"Jak\u0161in Do",
    "gn:population":0,
    "gn:timezone":"Europe/Sarajevo",
    "iso:country":"BA",
    "wof:name":"Jaksin Do",
    "wof:placetype":"locality"
},
  "geometry": {"coordinates":[18.80168,43.82387],"type":"Point"}
}