{
  "type": "Feature",
  "properties": {
    "gn:admin1_code":"02",
    "gn:asciiname":"Mladenovici",
    "gn:country_code":"BA",
    "gn:dem":807,
    "gn:feature_class":"P",
    "gn:feature_code":"PPL",
    "gn:name":"Mladenovi\u0107i",
    "gn:population":0,
    "gn:timezone":"Europe/Sarajevo",
    "iso:country":"BA",
    "wof:name":"Mladenovici",
    "wof:placetype":"locality"
},
  "geometry": {"coordinates":[17.30679,44.53753],"type":"Point"}
}