{
  "type": "Feature",
  "properties": {
    "gn:admin1_code":"01",
    "gn:asciiname":"Gornji Vukodol",
    "gn:country_code":"BA",
    "gn:dem":260,
    "gn:feature_class":"P",
    "gn:feature_code":"PPL",
    "gn:name":"Gornji Vukodol",
    "gn:population":0,
    "gn:timezone":"Europe/Sarajevo",
    "iso:country":"BA",
    "wof:name":"Gornji Vukodol",
    "wof:placetype":"locality"
},
  "geometry": {"coordinates":[17.79051,43.32549],"type":"Point"}
}