{
  "type": "Feature",
  "properties": {
    "gn:admin1_code":"01",
    "gn:asciiname":"Kurtici",
    "gn:country_code":"BA",
    "gn:dem":233,
    "gn:feature_class":"P",
    "gn:feature_code":"PPL",
    "gn:name":"Kurti\u0107i",
    "gn:population":0,
    "gn:timezone":"Europe/Sarajevo",
    "iso:country":"BA",
    "wof:name":"Kurtici",
    "wof:placetype":"locality"
},
  "geometry": {"coordinates":[15.92226,45.14796],"type":"Point"}
}