{
  "type": "Feature",
  "properties": {
    "gn:admin1_code":"02",
    "gn:asciiname":"Granica",
    "gn:country_code":"BA",
    "gn:dem":980,
    "gn:feature_class":"P",
    "gn:feature_code":"PPL",
    "gn:name":"Granica",
    "gn:population":0,
    "gn:timezone":"Europe/Sarajevo",
    "iso:country":"BA",
    "name:bos_x_preferred":[
        "Granica"
    ],
    "name:bul_x_preferred":[
        "\u0413\u0440\u0430\u043d\u0438\u0446\u0430"
    ],
    "name:ceb_x_preferred":[
        "Granica"
    ],
    "name:deu_x_preferred":[
        "Granica"
    ],
    "name:fra_x_preferred":[
        "Granica"
    ],
    "name:hrv_x_preferred":[
        "Granica"
    ],
    "name:mkd_x_preferred":[
        "\u0413\u0440\u0430\u043d\u0438\u0446\u0430"
    ],
    "name:pol_x_preferred":[
        "Granica"
    ],
    "name:rus_x_preferred":[
        "\u0413\u0440\u0430\u043d\u0438\u0446\u0430"
    ],
    "name:srp_x_preferred":[
        "\u0413\u0440\u0430\u043d\u0438\u0446\u0430"
    ],
    "name:swe_x_preferred":[
        "Granica"
    ],
    "name:ukr_x_preferred":[
        "\u0490\u0440\u0430\u043d\u0438\u0446\u044f"
    ],
    "wof:name":"Granica",
    "wof:placetype":"locality"
},
  "geometry": {"coordinates":[18.28598,42.97877],"type":"Point"}
}