{
  "type": "Feature",
  "properties": {
    "gn:admin1_code":"02",
    "gn:asciiname":"Mjesaji",
    "gn:country_code":"BA",
    "gn:dem":582,
    "gn:feature_class":"P",
    "gn:feature_code":"PPLL",
    "gn:name":"Mje\u0161aji",
    "gn:population":0,
    "gn:timezone":"Europe/Sarajevo",
    "iso:country":"BA",
    "name:und_x_variant":[
        "Mje\u0161aji"
    ],
    "wof:name":"Mjesaji",
    "wof:placetype":"locality"
},
  "geometry": {"coordinates":[18.75079,43.4367],"type":"Point"}
}