{
  "type": "Feature",
  "properties": {
    "gn:admin1_code":"01",
    "gn:asciiname":"Skenderovi",
    "gn:country_code":"BA",
    "gn:dem":1328,
    "gn:feature_class":"P",
    "gn:feature_code":"PPL",
    "gn:name":"Skenderovi",
    "gn:population":0,
    "gn:timezone":"Europe/Sarajevo",
    "iso:country":"BA",
    "wof:name":"Skenderovi",
    "wof:placetype":"locality"
},
  "geometry": {"coordinates":[17.42412,43.73634000000001],"type":"Point"}
}