{
  "type": "Feature",
  "properties": {
    "gn:admin1_code":"02",
    "gn:asciiname":"Munjize",
    "gn:country_code":"BA",
    "gn:dem":193,
    "gn:feature_class":"P",
    "gn:feature_code":"PPL",
    "gn:name":"Munjize",
    "gn:population":0,
    "gn:timezone":"Europe/Sarajevo",
    "iso:country":"BA",
    "wof:name":"Munjize",
    "wof:placetype":"locality"
},
  "geometry": {"coordinates":[16.71077,45.00924000000001],"type":"Point"}
}