{
  "type": "Feature",
  "properties": {
    "gn:admin1_code":"01",
    "gn:asciiname":"Dzemat",
    "gn:country_code":"BA",
    "gn:dem":401,
    "gn:feature_class":"P",
    "gn:feature_code":"PPLL",
    "gn:name":"D\u017eemat",
    "gn:population":0,
    "gn:timezone":"Europe/Sarajevo",
    "iso:country":"BA",
    "wof:name":"Dzemat",
    "wof:placetype":"locality"
},
  "geometry": {"coordinates":[18.94447000000001,44.57997],"type":"Point"}
}