{
  "type": "Feature",
  "properties": {
    "gn:admin1_code":"01",
    "gn:asciiname":"Erici",
    "gn:country_code":"BA",
    "gn:dem":286,
    "gn:feature_class":"P",
    "gn:feature_code":"PPL",
    "gn:name":"Eri\u0107i",
    "gn:population":0,
    "gn:timezone":"Europe/Sarajevo",
    "iso:country":"BA",
    "wof:name":"Erici",
    "wof:placetype":"locality"
},
  "geometry": {"coordinates":[17.95436,44.71409],"type":"Point"}
}