{
  "type": "Feature",
  "properties": {
    "gn:admin1_code":"01",
    "gn:asciiname":"Vaskovici",
    "gn:country_code":"BA",
    "gn:dem":1072,
    "gn:feature_class":"P",
    "gn:feature_code":"PPL",
    "gn:name":"Vaskovi\u0107i",
    "gn:population":0,
    "gn:timezone":"Europe/Sarajevo",
    "iso:country":"BA",
    "wof:name":"Vaskovici",
    "wof:placetype":"locality"
},
  "geometry": {"coordinates":[18.80879,44.15313],"type":"Point"}
}