{
  "type": "Feature",
  "properties": {
    "gn:admin1_code":"01",
    "gn:asciiname":"Pluzevine",
    "gn:country_code":"BA",
    "gn:dem":430,
    "gn:feature_class":"P",
    "gn:feature_code":"PPL",
    "gn:name":"Plu\u017eevine",
    "gn:population":0,
    "gn:timezone":"Europe/Sarajevo",
    "iso:country":"BA",
    "wof:name":"Pluzevine",
    "wof:placetype":"locality"
},
  "geometry": {"coordinates":[18.25037,44.4736],"type":"Point"}
}