{
  "type": "Feature",
  "properties": {
    "gn:admin1_code":"01",
    "gn:asciiname":"Strupnic",
    "gn:country_code":"BA",
    "gn:dem":780,
    "gn:feature_class":"P",
    "gn:feature_code":"PPL",
    "gn:name":"Strupni\u0107",
    "gn:population":0,
    "gn:timezone":"Europe/Sarajevo",
    "iso:country":"BA",
    "name:und_x_variant":[
        "Strupni\u0107"
    ],
    "wof:name":"Strupnic",
    "wof:placetype":"locality"
},
  "geometry": {"coordinates":[16.78972000000001,43.93333],"type":"Point"}
}