{
  "type": "Feature",
  "properties": {
    "gn:admin1_code":"02",
    "gn:asciiname":"Studenac",
    "gn:country_code":"BA",
    "gn:dem":767,
    "gn:feature_class":"P",
    "gn:feature_code":"PPL",
    "gn:name":"Studenac",
    "gn:population":0,
    "gn:timezone":"Europe/Sarajevo",
    "iso:country":"BA",
    "wof:name":"Studenac",
    "wof:placetype":"locality"
},
  "geometry": {"coordinates":[16.70028,44.44583],"type":"Point"}
}