{
  "type": "Feature",
  "properties": {
    "gn:admin1_code":"01",
    "gn:asciiname":"Zuje",
    "gn:country_code":"BA",
    "gn:dem":364,
    "gn:feature_class":"P",
    "gn:feature_code":"PPL",
    "gn:name":"\u017duje",
    "gn:population":0,
    "gn:timezone":"Europe/Sarajevo",
    "iso:country":"BA",
    "wof:name":"Zuje",
    "wof:placetype":"locality"
},
  "geometry": {"coordinates":[18.97077,44.51014],"type":"Point"}
}