{
  "type": "Feature",
  "properties": {
    "gn:admin1_code":"02",
    "gn:asciiname":"Pustara",
    "gn:country_code":"BA",
    "gn:dem":182,
    "gn:feature_class":"P",
    "gn:feature_code":"PPL",
    "gn:name":"Pustara",
    "gn:population":0,
    "gn:timezone":"Europe/Sarajevo",
    "iso:country":"BA",
    "wof:name":"Pustara",
    "wof:placetype":"locality"
},
  "geometry": {"coordinates":[17.71022,44.85296],"type":"Point"}
}