{
  "type": "Feature",
  "properties": {
    "gn:admin1_code":"02",
    "gn:asciiname":"Stojnici",
    "gn:country_code":"BA",
    "gn:dem":343,
    "gn:feature_class":"P",
    "gn:feature_code":"PPL",
    "gn:name":"Stojni\u0107i",
    "gn:population":0,
    "gn:timezone":"Europe/Sarajevo",
    "iso:country":"BA",
    "wof:name":"Stojnici",
    "wof:placetype":"locality"
},
  "geometry": {"coordinates":[17.01134,44.9306],"type":"Point"}
}