{
  "type": "Feature",
  "properties": {
    "gn:admin1_code":"02",
    "gn:asciiname":"Orasje",
    "gn:country_code":"BA",
    "gn:dem":796,
    "gn:feature_class":"P",
    "gn:feature_code":"PPL",
    "gn:name":"Ora\u0161je",
    "gn:population":0,
    "gn:timezone":"Europe/Sarajevo",
    "iso:country":"BA",
    "wof:name":"Orasje",
    "wof:placetype":"locality"
},
  "geometry": {"coordinates":[18.97049,43.32762],"type":"Point"}
}