{
  "type": "Feature",
  "properties": {
    "gn:admin1_code":"01",
    "gn:asciiname":"Smajici",
    "gn:country_code":"BA",
    "gn:dem":225,
    "gn:feature_class":"P",
    "gn:feature_code":"PPL",
    "gn:name":"Smaji\u0107i",
    "gn:population":0,
    "gn:timezone":"Europe/Sarajevo",
    "iso:country":"BA",
    "wof:name":"Smajici",
    "wof:placetype":"locality"
},
  "geometry": {"coordinates":[18.08053,44.61598],"type":"Point"}
}