{
  "type": "Feature",
  "properties": {
    "gn:admin1_code":"02",
    "gn:asciiname":"Jelah",
    "gn:country_code":"BA",
    "gn:dem":334,
    "gn:feature_class":"P",
    "gn:feature_code":"PPL",
    "gn:name":"Jelah",
    "gn:population":0,
    "gn:timezone":"Europe/Sarajevo",
    "iso:country":"BA",
    "name:bos_x_preferred":[
        "Jelah"
    ],
    "name:ceb_x_preferred":[
        "Jelah"
    ],
    "name:fra_x_preferred":[
        "Jelah"
    ],
    "name:hrv_x_preferred":[
        "Jelah"
    ],
    "name:srp_x_preferred":[
        "\u0408\u0435\u043b\u0430\u0445"
    ],
    "name:swe_x_preferred":[
        "Jelah"
    ],
    "wof:name":"Jelah",
    "wof:placetype":"locality"
},
  "geometry": {"coordinates":[19.12478,44.23396],"type":"Point"}
}