{
  "type": "Feature",
  "properties": {
    "gn:admin1_code":"02",
    "gn:asciiname":"Kukulje",
    "gn:country_code":"BA",
    "gn:dem":101,
    "gn:feature_class":"P",
    "gn:feature_code":"PPLL",
    "gn:name":"Kukulje",
    "gn:population":0,
    "gn:timezone":"Europe/Sarajevo",
    "iso:country":"BA",
    "wof:name":"Kukulje",
    "wof:placetype":"locality"
},
  "geometry": {"coordinates":[17.40706,44.99155],"type":"Point"}
}