{
  "type": "Feature",
  "properties": {
    "gn:admin1_code":"01",
    "gn:asciiname":"Lasici",
    "gn:country_code":"BA",
    "gn:dem":280,
    "gn:feature_class":"P",
    "gn:feature_code":"PPL",
    "gn:name":"Lasi\u0107i",
    "gn:population":0,
    "gn:timezone":"Europe/Sarajevo",
    "iso:country":"BA",
    "wof:name":"Lasici",
    "wof:placetype":"locality"
},
  "geometry": {"coordinates":[17.62937999999999,43.34964],"type":"Point"}
}