{
  "type": "Feature",
  "properties": {
    "gn:admin1_code":"01",
    "gn:asciiname":"Nukici",
    "gn:country_code":"BA",
    "gn:dem":312,
    "gn:feature_class":"P",
    "gn:feature_code":"PPL",
    "gn:name":"Nuki\u0107i",
    "gn:population":0,
    "gn:timezone":"Europe/Sarajevo",
    "iso:country":"BA",
    "wof:name":"Nukici",
    "wof:placetype":"locality"
},
  "geometry": {"coordinates":[18.43292000000001,44.63948],"type":"Point"}
}