{
  "type": "Feature",
  "properties": {
    "gn:admin1_code":"02",
    "gn:asciiname":"Kraje",
    "gn:country_code":"BA",
    "gn:dem":484,
    "gn:feature_class":"P",
    "gn:feature_code":"PPL",
    "gn:name":"Kraje",
    "gn:population":0,
    "gn:timezone":"Europe/Sarajevo",
    "iso:country":"BA",
    "wof:name":"Kraje",
    "wof:placetype":"locality"
},
  "geometry": {"coordinates":[18.89073,43.48097],"type":"Point"}
}