{
  "type": "Feature",
  "properties": {
    "gn:admin1_code":"01",
    "gn:asciiname":"Zagorje",
    "gn:country_code":"BA",
    "gn:dem":615,
    "gn:feature_class":"P",
    "gn:feature_code":"PPLL",
    "gn:name":"Zagorje",
    "gn:population":0,
    "gn:timezone":"Europe/Sarajevo",
    "iso:country":"BA",
    "wof:name":"Zagorje",
    "wof:placetype":"locality"
},
  "geometry": {"coordinates":[17.21947,43.54103],"type":"Point"}
}