{
  "type": "Feature",
  "properties": {
    "gn:admin1_code":"01",
    "gn:asciiname":"Kazijevici",
    "gn:country_code":"BA",
    "gn:dem":671,
    "gn:feature_class":"P",
    "gn:feature_code":"PPL",
    "gn:name":"Kazijevi\u0107i",
    "gn:population":0,
    "gn:timezone":"Europe/Sarajevo",
    "iso:country":"BA",
    "wof:name":"Kazijevici",
    "wof:placetype":"locality"
},
  "geometry": {"coordinates":[17.48635,43.82388],"type":"Point"}
}