{
  "type": "Feature",
  "properties": {
    "gn:admin1_code":"02",
    "gn:asciiname":"Buzuk",
    "gn:country_code":"BA",
    "gn:dem":330,
    "gn:feature_class":"P",
    "gn:feature_code":"PPL",
    "gn:name":"Buzuk",
    "gn:population":0,
    "gn:timezone":"Europe/Sarajevo",
    "iso:country":"BA",
    "name:sqi_x_preferred":[
        "Buzuku"
    ],
    "wof:name":"Buzuk",
    "wof:placetype":"locality"
},
  "geometry": {"coordinates":[16.4863,44.87759000000001],"type":"Point"}
}