{
  "type": "Feature",
  "properties": {
    "gn:admin1_code":"01",
    "gn:asciiname":"Krivokuce",
    "gn:country_code":"BA",
    "gn:dem":610,
    "gn:feature_class":"P",
    "gn:feature_code":"PPL",
    "gn:name":"Krivoku\u0107e",
    "gn:population":0,
    "gn:timezone":"Europe/Sarajevo",
    "iso:country":"BA",
    "wof:name":"Krivokuce",
    "wof:placetype":"locality"
},
  "geometry": {"coordinates":[16.2627,44.57393],"type":"Point"}
}