{
  "type": "Feature",
  "properties": {
    "gn:admin1_code":"01",
    "gn:asciiname":"Fakici",
    "gn:country_code":"BA",
    "gn:dem":651,
    "gn:feature_class":"P",
    "gn:feature_code":"PPL",
    "gn:name":"Faki\u0107i",
    "gn:population":0,
    "gn:timezone":"Europe/Sarajevo",
    "iso:country":"BA",
    "name:bos_x_preferred":[
        "Faki\u0107i"
    ],
    "name:fra_x_preferred":[
        "Faki\u0107i"
    ],
    "name:hrv_x_preferred":[
        "Faki\u0107i"
    ],
    "name:srp_x_preferred":[
        "\u0424\u0430\u043a\u0438\u045b\u0438"
    ],
    "name:urd_x_preferred":[
        "\u0641\u0627\u06a9\u06cc\u0633\u06cc"
    ],
    "wof:name":"Fakici",
    "wof:placetype":"locality"
},
  "geometry": {"coordinates":[17.40707,44.08562],"type":"Point"}
}