{
  "type": "Feature",
  "properties": {
    "gn:admin1_code":"01",
    "gn:asciiname":"Novakovici",
    "gn:country_code":"BA",
    "gn:dem":547,
    "gn:feature_class":"P",
    "gn:feature_code":"PPL",
    "gn:name":"Novakovi\u0107i",
    "gn:population":0,
    "gn:timezone":"Europe/Sarajevo",
    "iso:country":"BA",
    "wof:name":"Novakovici",
    "wof:placetype":"locality"
},
  "geometry": {"coordinates":[16.03185,44.56953],"type":"Point"}
}