{
  "type": "Feature",
  "properties": {
    "gn:admin1_code":"01",
    "gn:asciiname":"Duranovici",
    "gn:country_code":"BA",
    "gn:dem":693,
    "gn:feature_class":"P",
    "gn:feature_code":"PPL",
    "gn:name":"Duranovi\u0107i",
    "gn:population":0,
    "gn:timezone":"Europe/Sarajevo",
    "iso:country":"BA",
    "name:bos_x_preferred":[
        "Duranovi\u0107i"
    ],
    "name:ceb_x_preferred":[
        "Duranovi\u0107i"
    ],
    "name:fra_x_preferred":[
        "Duranovi\u0107i"
    ],
    "name:hrv_x_preferred":[
        "Duranovi\u0107i"
    ],
    "name:swe_x_preferred":[
        "Duranovi\u0107i"
    ],
    "wof:name":"Duranovici",
    "wof:placetype":"locality"
},
  "geometry": {"coordinates":[18.09082,43.77548],"type":"Point"}
}