{
  "type": "Feature",
  "properties": {
    "gn:admin1_code":"02",
    "gn:asciiname":"Skelani",
    "gn:country_code":"BA",
    "gn:dem":267,
    "gn:feature_class":"P",
    "gn:feature_code":"PPL",
    "gn:name":"Skelani",
    "gn:population":0,
    "gn:timezone":"Europe/Sarajevo",
    "iso:country":"BA",
    "name:bos_x_preferred":[
        "Skelani"
    ],
    "name:bul_x_preferred":[
        "\u0421\u043a\u0435\u043b\u0430\u043d\u0438"
    ],
    "name:ces_x_preferred":[
        "Skelani"
    ],
    "name:fra_x_preferred":[
        "Skelani"
    ],
    "name:hrv_x_preferred":[
        "Skelani"
    ],
    "name:jpn_x_preferred":[
        "\u30b9\u30b1\u30e9\u30cb"
    ],
    "name:rus_x_preferred":[
        "\u0421\u043a\u0435\u043b\u0430\u043d\u0438"
    ],
    "name:srp_x_preferred":[
        "\u0421\u043a\u0435\u043b\u0430\u043d\u0438"
    ],
    "wof:name":"Skelani",
    "wof:placetype":"locality"
},
  "geometry": {"coordinates":[19.53556,43.97528],"type":"Point"}
}