{
  "type": "Feature",
  "properties": {
    "gn:admin1_code":"01",
    "gn:asciiname":"Podbare",
    "gn:country_code":"BA",
    "gn:dem":594,
    "gn:feature_class":"P",
    "gn:feature_code":"PPL",
    "gn:name":"Podbare",
    "gn:population":0,
    "gn:timezone":"Europe/Sarajevo",
    "iso:country":"BA",
    "name:bos_x_preferred":[
        "Podbare"
    ],
    "name:ceb_x_preferred":[
        "Podbare"
    ],
    "name:fra_x_preferred":[
        "Podbare"
    ],
    "name:swe_x_preferred":[
        "Podbare"
    ],
    "wof:name":"Podbare",
    "wof:placetype":"locality"
},
  "geometry": {"coordinates":[17.96528,44.08167],"type":"Point"}
}