{
  "type": "Feature",
  "properties": {
    "gn:admin1_code":"02",
    "gn:asciiname":"Jezero",
    "gn:country_code":"BA",
    "gn:dem":140,
    "gn:feature_class":"P",
    "gn:feature_code":"PPL",
    "gn:name":"Jezero",
    "gn:population":0,
    "gn:timezone":"Europe/Sarajevo",
    "iso:country":"BA",
    "wof:name":"Jezero",
    "wof:placetype":"locality"
},
  "geometry": {"coordinates":[19.12862,44.538],"type":"Point"}
}