{
  "type": "Feature",
  "properties": {
    "gn:admin1_code":"02",
    "gn:asciiname":"Milekici",
    "gn:country_code":"BA",
    "gn:dem":513,
    "gn:feature_class":"P",
    "gn:feature_code":"PPLL",
    "gn:name":"Mileki\u0107i",
    "gn:population":0,
    "gn:timezone":"Europe/Sarajevo",
    "iso:country":"BA",
    "wof:name":"Milekici",
    "wof:placetype":"locality"
},
  "geometry": {"coordinates":[16.93037,44.36205],"type":"Point"}
}