{
  "type": "Feature",
  "properties": {
    "gn:admin1_code":"01",
    "gn:asciiname":"Bijeli Potok",
    "gn:country_code":"BA",
    "gn:dem":356,
    "gn:feature_class":"P",
    "gn:feature_code":"PPL",
    "gn:name":"Bijeli Potok",
    "gn:population":0,
    "gn:timezone":"Europe/Sarajevo",
    "iso:country":"BA",
    "wof:name":"Bijeli Potok",
    "wof:placetype":"locality"
},
  "geometry": {"coordinates":[18.20712,44.75747],"type":"Point"}
}