{
  "type": "Feature",
  "properties": {
    "gn:admin1_code":"02",
    "gn:asciiname":"Volujak",
    "gn:country_code":"BA",
    "gn:dem":296,
    "gn:feature_class":"P",
    "gn:feature_code":"PPL",
    "gn:name":"Volujak",
    "gn:population":0,
    "gn:timezone":"Europe/Sarajevo",
    "iso:country":"BA",
    "wof:name":"Volujak",
    "wof:placetype":"locality"
},
  "geometry": {"coordinates":[18.29706,44.63421],"type":"Point"}
}