{
  "type": "Feature",
  "properties": {
    "gn:admin1_code":"02",
    "gn:asciiname":"Volujak",
    "gn:country_code":"BA",
    "gn:dem":296,
    "gn:feature_class":"P",
    "gn:feature_code":"PPL",
    "gn:name":"Volujak",
    "gn:population":0,
    "gn:timezone":"Europe/Sarajevo",
    "iso:country":"BA",
    "name:bos_x_preferred":[
        "Volujak"
    ],
    "name:bul_x_preferred":[
        "\u0412\u043e\u043b\u0443\u044f\u043a"
    ],
    "name:ceb_x_preferred":[
        "Volujak"
    ],
    "name:fra_x_preferred":[
        "Volujak"
    ],
    "name:hrv_x_preferred":[
        "Volujak"
    ],
    "name:rus_x_preferred":[
        "\u0412\u043e\u043b\u0443\u044f\u043a"
    ],
    "name:swe_x_preferred":[
        "Volujak"
    ],
    "wof:name":"Volujak",
    "wof:placetype":"locality"
},
  "geometry": {"coordinates":[18.29706,44.63421],"type":"Point"}
}