{
  "type": "Feature",
  "properties": {
    "gn:admin1_code":"01",
    "gn:asciiname":"Muminovaca",
    "gn:country_code":"BA",
    "gn:dem":95,
    "gn:feature_class":"P",
    "gn:feature_code":"PPL",
    "gn:name":"Muminova\u010da",
    "gn:population":0,
    "gn:timezone":"Europe/Sarajevo",
    "iso:country":"BA",
    "wof:name":"Muminovaca",
    "wof:placetype":"locality"
},
  "geometry": {"coordinates":[17.74829,43.12213],"type":"Point"}
}