{
  "type": "Feature",
  "properties": {
    "gn:admin1_code":"01",
    "gn:asciiname":"Kolonija",
    "gn:country_code":"BA",
    "gn:dem":334,
    "gn:feature_class":"P",
    "gn:feature_code":"PPL",
    "gn:name":"Kolonija",
    "gn:population":0,
    "gn:timezone":"Europe/Sarajevo",
    "iso:country":"BA",
    "wof:name":"Kolonija",
    "wof:placetype":"locality"
},
  "geometry": {"coordinates":[17.29208,44.37761],"type":"Point"}
}