{
  "type": "Feature",
  "properties": {
    "gn:admin1_code":"02",
    "gn:asciiname":"Daidzici",
    "gn:country_code":"BA",
    "gn:dem":115,
    "gn:feature_class":"P",
    "gn:feature_code":"PPL",
    "gn:name":"Daid\u017ei\u010di",
    "gn:population":0,
    "gn:timezone":"Europe/Sarajevo",
    "iso:country":"BA",
    "wof:name":"Daidzici",
    "wof:placetype":"locality"
},
  "geometry": {"coordinates":[18.03232,45.03696],"type":"Point"}
}