{
  "type": "Feature",
  "properties": {
    "gn:admin1_code":"01",
    "gn:asciiname":"Godinja",
    "gn:country_code":"BA",
    "gn:dem":931,
    "gn:feature_class":"P",
    "gn:feature_code":"PPL",
    "gn:name":"Godinja",
    "gn:population":0,
    "gn:timezone":"Europe/Sarajevo",
    "iso:country":"BA",
    "name:bos_x_preferred":[
        "Godinja"
    ],
    "name:und_x_variant":[
        "Godinje",
        "Godinjaa"
    ],
    "wof:name":"Godinja",
    "wof:placetype":"locality"
},
  "geometry": {"coordinates":[18.39539,43.64874],"type":"Point"}
}