{
  "type": "Feature",
  "properties": {
    "gn:admin1_code":"01",
    "gn:asciiname":"Dedici",
    "gn:country_code":"BA",
    "gn:dem":238,
    "gn:feature_class":"P",
    "gn:feature_code":"PPL",
    "gn:name":"De\u0111i\u0107i",
    "gn:population":0,
    "gn:timezone":"Europe/Sarajevo",
    "iso:country":"BA",
    "wof:name":"Dedici",
    "wof:placetype":"locality"
},
  "geometry": {"coordinates":[18.52798,44.56357],"type":"Point"}
}