{
  "type": "Feature",
  "properties": {
    "gn:admin1_code":"02",
    "gn:asciiname":"Povelic",
    "gn:country_code":"BA",
    "gn:dem":93,
    "gn:feature_class":"P",
    "gn:feature_code":"PPLL",
    "gn:name":"Poveli\u0107",
    "gn:population":0,
    "gn:timezone":"Europe/Sarajevo",
    "iso:country":"BA",
    "wof:name":"Povelic",
    "wof:placetype":"locality"
},
  "geometry": {"coordinates":[17.50161,45.07396],"type":"Point"}
}