{
  "type": "Feature",
  "properties": {
    "gn:admin1_code":"02",
    "gn:asciiname":"Uremovci",
    "gn:country_code":"BA",
    "gn:dem":149,
    "gn:feature_class":"P",
    "gn:feature_code":"PPL",
    "gn:name":"Uremovci",
    "gn:population":0,
    "gn:timezone":"Europe/Sarajevo",
    "iso:country":"BA",
    "wof:name":"Uremovci",
    "wof:placetype":"locality"
},
  "geometry": {"coordinates":[16.75808,45.11355],"type":"Point"}
}