{
  "type": "Feature",
  "properties": {
    "gn:admin1_code":"02",
    "gn:asciiname":"Ruskici",
    "gn:country_code":"BA",
    "gn:dem":99,
    "gn:feature_class":"P",
    "gn:feature_code":"PPL",
    "gn:name":"Ru\u0161ki\u0107i",
    "gn:population":0,
    "gn:timezone":"Europe/Sarajevo",
    "iso:country":"BA",
    "wof:name":"Ruskici",
    "wof:placetype":"locality"
},
  "geometry": {"coordinates":[18.0747,45.0671],"type":"Point"}
}