{
  "type": "Feature",
  "properties": {
    "gn:admin1_code":"01",
    "gn:asciiname":"Martinovici",
    "gn:country_code":"BA",
    "gn:dem":420,
    "gn:feature_class":"P",
    "gn:feature_code":"PPL",
    "gn:name":"Martinovi\u0107i",
    "gn:population":0,
    "gn:timezone":"Europe/Sarajevo",
    "iso:country":"BA",
    "wof:name":"Martinovici",
    "wof:placetype":"locality"
},
  "geometry": {"coordinates":[18.69198,44.66519],"type":"Point"}
}