{
  "type": "Feature",
  "properties": {
    "gn:admin1_code":"02",
    "gn:asciiname":"Kokorina",
    "gn:country_code":"BA",
    "gn:dem":956,
    "gn:feature_class":"P",
    "gn:feature_code":"PPLL",
    "gn:name":"Kokorina",
    "gn:population":0,
    "gn:timezone":"Europe/Sarajevo",
    "iso:country":"BA",
    "name:bos_x_preferred":[
        "Kokorina"
    ],
    "name:ell_x_preferred":[
        "\u039a\u03bf\u03ba\u03cc\u03c1\u03b9\u03bd\u03b1"
    ],
    "name:fra_x_preferred":[
        "Kokorina"
    ],
    "name:hrv_x_preferred":[
        "Kokorina"
    ],
    "name:srp_x_preferred":[
        "\u041a\u043e\u043a\u043e\u0440\u0438\u043d\u0430"
    ],
    "wof:name":"Kokorina",
    "wof:placetype":"locality"
},
  "geometry": {"coordinates":[18.01935,43.27114],"type":"Point"}
}