{
  "type": "Feature",
  "properties": {
    "gn:admin1_code":"02",
    "gn:asciiname":"Srpsko Glinje",
    "gn:country_code":"BA",
    "gn:dem":278,
    "gn:feature_class":"P",
    "gn:feature_code":"PPL",
    "gn:name":"Srpsko Glinje",
    "gn:population":0,
    "gn:timezone":"Europe/Sarajevo",
    "iso:country":"BA",
    "wof:name":"Srpsko Glinje",
    "wof:placetype":"locality"
},
  "geometry": {"coordinates":[19.05307,44.62329],"type":"Point"}
}