{
  "type": "Feature",
  "properties": {
    "gn:admin1_code":"02",
    "gn:asciiname":"Crnca",
    "gn:country_code":"BA",
    "gn:dem":350,
    "gn:feature_class":"P",
    "gn:feature_code":"PPL",
    "gn:name":"Crn\u010da",
    "gn:population":0,
    "gn:timezone":"Europe/Sarajevo",
    "iso:country":"BA",
    "wof:name":"Crnca",
    "wof:placetype":"locality"
},
  "geometry": {"coordinates":[19.28528,43.79111],"type":"Point"}
}