{
  "type": "Feature",
  "properties": {
    "gn:admin1_code":"02",
    "gn:asciiname":"Stara Ovcara",
    "gn:country_code":"BA",
    "gn:dem":1156,
    "gn:feature_class":"P",
    "gn:feature_code":"PPL",
    "gn:name":"Stara Ov\u010dara",
    "gn:population":0,
    "gn:timezone":"Europe/Sarajevo",
    "iso:country":"BA",
    "wof:name":"Stara Ovcara",
    "wof:placetype":"locality"
},
  "geometry": {"coordinates":[16.80448,44.27357],"type":"Point"}
}