{
  "type": "Feature",
  "properties": {
    "gn:admin1_code":"01",
    "gn:asciiname":"Ljuti Dolac",
    "gn:country_code":"BA",
    "gn:dem":260,
    "gn:feature_class":"P",
    "gn:feature_code":"PPLL",
    "gn:name":"Ljuti Dolac",
    "gn:population":0,
    "gn:timezone":"Europe/Sarajevo",
    "iso:country":"BA",
    "name:bos_x_preferred":[
        "Ljuti Dolac"
    ],
    "name:ceb_x_preferred":[
        "Ljuti Dolac"
    ],
    "name:fra_x_preferred":[
        "Ljuti Dolac"
    ],
    "name:hrv_x_preferred":[
        "Ljuti Dolac"
    ],
    "name:srp_x_preferred":[
        "\u0409\u0443\u0442\u0438 \u0414\u043e\u043b\u0430\u0446"
    ],
    "name:swe_x_preferred":[
        "Ljuti Dolac"
    ],
    "wof:name":"Ljuti Dolac",
    "wof:placetype":"locality"
},
  "geometry": {"coordinates":[17.69917000000001,43.30841],"type":"Point"}
}