{
  "type": "Feature",
  "properties": {
    "gn:admin1_code":"01",
    "gn:asciiname":"Ljuti Dolac",
    "gn:country_code":"BA",
    "gn:dem":260,
    "gn:feature_class":"P",
    "gn:feature_code":"PPLL",
    "gn:name":"Ljuti Dolac",
    "gn:population":0,
    "gn:timezone":"Europe/Sarajevo",
    "iso:country":"BA",
    "wof:name":"Ljuti Dolac",
    "wof:placetype":"locality"
},
  "geometry": {"coordinates":[17.69917000000001,43.30841],"type":"Point"}
}