{
  "type": "Feature",
  "properties": {
    "gn:admin1_code":"01",
    "gn:asciiname":"Simici",
    "gn:country_code":"BA",
    "gn:dem":266,
    "gn:feature_class":"P",
    "gn:feature_code":"PPL",
    "gn:name":"\u0160imi\u0107i",
    "gn:population":0,
    "gn:timezone":"Europe/Sarajevo",
    "iso:country":"BA",
    "wof:name":"Simici",
    "wof:placetype":"locality"
},
  "geometry": {"coordinates":[17.33885,43.40058],"type":"Point"}
}