{
  "type": "Feature",
  "properties": {
    "gn:admin1_code":"01",
    "gn:asciiname":"Gornja Mahala",
    "gn:country_code":"BA",
    "gn:dem":912,
    "gn:feature_class":"P",
    "gn:feature_code":"PPL",
    "gn:name":"Gornja Mahala",
    "gn:population":0,
    "gn:timezone":"Europe/Sarajevo",
    "iso:country":"BA",
    "wof:name":"Gornja Mahala",
    "wof:placetype":"locality"
},
  "geometry": {"coordinates":[17.59269,43.71597],"type":"Point"}
}