{
  "type": "Feature",
  "properties": {
    "gn:admin1_code":"02",
    "gn:asciiname":"Srdici",
    "gn:country_code":"BA",
    "gn:dem":168,
    "gn:feature_class":"P",
    "gn:feature_code":"PPL",
    "gn:name":"Srdi\u0107i",
    "gn:population":0,
    "gn:timezone":"Europe/Sarajevo",
    "iso:country":"BA",
    "wof:name":"Srdici",
    "wof:placetype":"locality"
},
  "geometry": {"coordinates":[16.6604,44.83811],"type":"Point"}
}