{
  "type": "Feature",
  "properties": {
    "gn:admin1_code":"01",
    "gn:asciiname":"Mejrimici",
    "gn:country_code":"BA",
    "gn:dem":217,
    "gn:feature_class":"P",
    "gn:feature_code":"PPL",
    "gn:name":"Mejrimi\u0107i",
    "gn:population":0,
    "gn:timezone":"Europe/Sarajevo",
    "iso:country":"BA",
    "wof:name":"Mejrimici",
    "wof:placetype":"locality"
},
  "geometry": {"coordinates":[18.43183,44.86751],"type":"Point"}
}