{
  "type": "Feature",
  "properties": {
    "gn:admin1_code":"01",
    "gn:asciiname":"Kovacine",
    "gn:country_code":"BA",
    "gn:dem":1030,
    "gn:feature_class":"P",
    "gn:feature_code":"PPL",
    "gn:name":"Kova\u010dine",
    "gn:population":0,
    "gn:timezone":"Europe/Sarajevo",
    "iso:country":"BA",
    "wof:name":"Kovacine",
    "wof:placetype":"locality"
},
  "geometry": {"coordinates":[18.4429,44.07009],"type":"Point"}
}