{
  "type": "Feature",
  "properties": {
    "gn:admin1_code":"01",
    "gn:asciiname":"Odrace",
    "gn:country_code":"BA",
    "gn:dem":726,
    "gn:feature_class":"P",
    "gn:feature_code":"PPL",
    "gn:name":"Odra\u010de",
    "gn:population":0,
    "gn:timezone":"Europe/Sarajevo",
    "iso:country":"BA",
    "name:bos_x_preferred":[
        "Odra\u010de"
    ],
    "name:fra_x_preferred":[
        "Odra\u010de"
    ],
    "name:hrv_x_preferred":[
        "Odra\u010de"
    ],
    "name:und_x_variant":[
        "Odra\u010de"
    ],
    "wof:name":"Odrace",
    "wof:placetype":"locality"
},
  "geometry": {"coordinates":[18.02,44.03355],"type":"Point"}
}