{
  "type": "Feature",
  "properties": {
    "gn:admin1_code":"02",
    "gn:asciiname":"Surovi",
    "gn:country_code":"BA",
    "gn:dem":780,
    "gn:feature_class":"P",
    "gn:feature_code":"PPL",
    "gn:name":"Surovi",
    "gn:population":0,
    "gn:timezone":"Europe/Sarajevo",
    "iso:country":"BA",
    "name:bos_x_preferred":[
        "Surovi"
    ],
    "name:fra_x_preferred":[
        "Surovi"
    ],
    "name:srp_x_preferred":[
        "\u0421\u0443\u0440\u043e\u0432\u0438"
    ],
    "wof:name":"Surovi",
    "wof:placetype":"locality"
},
  "geometry": {"coordinates":[18.96672,43.77316],"type":"Point"}
}