{
  "type": "Feature",
  "properties": {
    "gn:admin1_code":"02",
    "gn:asciiname":"Porjecina",
    "gn:country_code":"BA",
    "gn:dem":225,
    "gn:feature_class":"P",
    "gn:feature_code":"PPL",
    "gn:name":"Porje\u010dina",
    "gn:population":0,
    "gn:timezone":"Europe/Sarajevo",
    "iso:country":"BA",
    "wof:name":"Porjecina",
    "wof:placetype":"locality"
},
  "geometry": {"coordinates":[18.39111,44.59639],"type":"Point"}
}