{
  "type": "Feature",
  "properties": {
    "gn:admin1_code":"02",
    "gn:asciiname":"Stupanj",
    "gn:country_code":"BA",
    "gn:dem":827,
    "gn:feature_class":"P",
    "gn:feature_code":"PPL",
    "gn:name":"Stupanj",
    "gn:population":0,
    "gn:timezone":"Europe/Sarajevo",
    "iso:country":"BA",
    "wof:name":"Stupanj",
    "wof:placetype":"locality"
},
  "geometry": {"coordinates":[18.71752,44.00607],"type":"Point"}
}