{
  "type": "Feature",
  "properties": {
    "gn:admin1_code":"01",
    "gn:asciiname":"Pjesevac Greda",
    "gn:country_code":"BA",
    "gn:dem":252,
    "gn:feature_class":"P",
    "gn:feature_code":"PPL",
    "gn:name":"Pje\u0161evac Greda",
    "gn:population":0,
    "gn:timezone":"Europe/Sarajevo",
    "iso:country":"BA",
    "wof:name":"Pjesevac Greda",
    "wof:placetype":"locality"
},
  "geometry": {"coordinates":[17.89399,43.12146],"type":"Point"}
}