{
  "type": "Feature",
  "properties": {
    "gn:admin1_code":"01",
    "gn:asciiname":"Skocblusicevhan",
    "gn:country_code":"BA",
    "gn:dem":898,
    "gn:feature_class":"P",
    "gn:feature_code":"PPL",
    "gn:name":"Sko\u010dblu\u0161i\u0107evhan",
    "gn:population":0,
    "gn:timezone":"Europe/Sarajevo",
    "iso:country":"BA",
    "wof:name":"Skocblusicevhan",
    "wof:placetype":"locality"
},
  "geometry": {"coordinates":[17.2775,43.5875],"type":"Point"}
}