{
  "type": "Feature",
  "properties": {
    "gn:admin1_code":"02",
    "gn:asciiname":"Kovacevici",
    "gn:country_code":"BA",
    "gn:dem":162,
    "gn:feature_class":"P",
    "gn:feature_code":"PPL",
    "gn:name":"Kova\u010devi\u0107i",
    "gn:population":0,
    "gn:timezone":"Europe/Sarajevo",
    "iso:country":"BA",
    "name:und_x_variant":[
        "Lu\u017eani",
        "Kova\u010devi\u0107i"
    ],
    "wof:name":"Kovacevici",
    "wof:placetype":"locality"
},
  "geometry": {"coordinates":[19.19864,44.28366],"type":"Point"}
}