{
  "type": "Feature",
  "properties": {
    "gn:admin1_code":"02",
    "gn:asciiname":"Vranovina",
    "gn:country_code":"BA",
    "gn:dem":1469,
    "gn:feature_class":"P",
    "gn:feature_code":"PPLL",
    "gn:name":"Vranovina",
    "gn:population":0,
    "gn:timezone":"Europe/Sarajevo",
    "iso:country":"BA",
    "name:bos_x_preferred":[
        "Vranovina"
    ],
    "name:fra_x_preferred":[
        "Vranovina"
    ],
    "name:hrv_x_preferred":[
        "Vranovina"
    ],
    "name:srp_x_preferred":[
        "\u0412\u0440\u0430\u043d\u043e\u0432\u0438\u043d\u0430"
    ],
    "wof:name":"Vranovina",
    "wof:placetype":"locality"
},
  "geometry": {"coordinates":[19.01332,43.26645],"type":"Point"}
}