{
  "type": "Feature",
  "properties": {
    "gn:admin1_code":"01",
    "gn:asciiname":"Calikovac",
    "gn:country_code":"BA",
    "gn:dem":556,
    "gn:feature_class":"P",
    "gn:feature_code":"PPL",
    "gn:name":"\u010calikovac",
    "gn:population":0,
    "gn:timezone":"Europe/Sarajevo",
    "iso:country":"BA",
    "wof:name":"Calikovac",
    "wof:placetype":"locality"
},
  "geometry": {"coordinates":[18.06806,43.99444],"type":"Point"}
}