{
  "type": "Feature",
  "properties": {
    "gn:admin1_code":"02",
    "gn:asciiname":"Mededa",
    "gn:country_code":"BA",
    "gn:dem":949,
    "gn:feature_class":"P",
    "gn:feature_code":"PPL",
    "gn:name":"Me\u0111e\u0111a",
    "gn:population":0,
    "gn:timezone":"Europe/Sarajevo",
    "iso:country":"BA",
    "wof:name":"Mededa",
    "wof:placetype":"locality"
},
  "geometry": {"coordinates":[18.75115,43.40765],"type":"Point"}
}