{
  "type": "Feature",
  "properties": {
    "gn:admin1_code":"02",
    "gn:asciiname":"Modran",
    "gn:country_code":"BA",
    "gn:dem":122,
    "gn:feature_class":"P",
    "gn:feature_code":"PPL",
    "gn:name":"Modran",
    "gn:population":0,
    "gn:timezone":"Europe/Sarajevo",
    "iso:country":"BA",
    "wof:name":"Modran",
    "wof:placetype":"locality"
},
  "geometry": {"coordinates":[19.17669,44.67224],"type":"Point"}
}