{
  "type": "Feature",
  "properties": {
    "gn:admin1_code":"02",
    "gn:asciiname":"Modran",
    "gn:country_code":"BA",
    "gn:dem":122,
    "gn:feature_class":"P",
    "gn:feature_code":"PPL",
    "gn:name":"Modran",
    "gn:population":0,
    "gn:timezone":"Europe/Sarajevo",
    "iso:country":"BA",
    "name:bos_x_preferred":[
        "Modran"
    ],
    "name:ceb_x_preferred":[
        "Modran"
    ],
    "name:fra_x_preferred":[
        "Modran"
    ],
    "name:hrv_x_preferred":[
        "Modran"
    ],
    "name:rus_x_preferred":[
        "\u041c\u043e\u0434\u0440\u0430\u043d"
    ],
    "name:slv_x_preferred":[
        "Modran"
    ],
    "name:srp_x_preferred":[
        "\u041c\u043e\u0434\u0440\u0430\u043d"
    ],
    "wof:name":"Modran",
    "wof:placetype":"locality"
},
  "geometry": {"coordinates":[19.17669,44.67224],"type":"Point"}
}