{
  "type": "Feature",
  "properties": {
    "gn:admin1_code":"01",
    "gn:asciiname":"Grm",
    "gn:country_code":"BA",
    "gn:dem":470,
    "gn:feature_class":"P",
    "gn:feature_code":"PPL",
    "gn:name":"Grm",
    "gn:population":0,
    "gn:timezone":"Europe/Sarajevo",
    "iso:country":"BA",
    "name:bos_x_preferred":[
        "Grm"
    ],
    "name:ceb_x_preferred":[
        "Grm"
    ],
    "name:hrv_x_preferred":[
        "Grm"
    ],
    "name:nld_x_preferred":[
        "Grm"
    ],
    "name:pol_x_preferred":[
        "Grm"
    ],
    "name:slv_x_preferred":[
        "Grm"
    ],
    "name:swe_x_preferred":[
        "Grm"
    ],
    "wof:name":"Grm",
    "wof:placetype":"locality"
},
  "geometry": {"coordinates":[18.15985,44.09222000000001],"type":"Point"}
}