{
  "type": "Feature",
  "properties": {
    "gn:admin1_code":"02",
    "gn:asciiname":"Zablece",
    "gn:country_code":"BA",
    "gn:dem":483,
    "gn:feature_class":"P",
    "gn:feature_code":"PPLL",
    "gn:name":"Zable\u0107e",
    "gn:population":0,
    "gn:timezone":"Europe/Sarajevo",
    "iso:country":"BA",
    "name:und_x_variant":[
        "Zabla\u0107e",
        "Zable\u0107e"
    ],
    "wof:name":"Zablece",
    "wof:placetype":"locality"
},
  "geometry": {"coordinates":[16.84234,44.49191],"type":"Point"}
}