{
  "type": "Feature",
  "properties": {
    "gn:admin1_code":"02",
    "gn:asciiname":"Zablece",
    "gn:country_code":"BA",
    "gn:dem":483,
    "gn:feature_class":"P",
    "gn:feature_code":"PPLL",
    "gn:name":"Zable\u0107e",
    "gn:population":0,
    "gn:timezone":"Europe/Sarajevo",
    "iso:country":"BA",
    "name:bos_x_preferred":[
        "Zable\u0107e"
    ],
    "name:ceb_x_preferred":[
        "Zable\u0107e"
    ],
    "name:fra_x_preferred":[
        "Zable\u0107e"
    ],
    "name:srp_x_preferred":[
        "\u0417\u0430\u0431\u043b\u0435\u045b\u0435"
    ],
    "name:swe_x_preferred":[
        "Zable\u0107e"
    ],
    "name:und_x_variant":[
        "Zabla\u0107e",
        "Zable\u0107e"
    ],
    "name:urd_x_preferred":[
        "\u0632\u0628\u0644\u06d2\u0686\u0627"
    ],
    "wof:name":"Zablece",
    "wof:placetype":"locality"
},
  "geometry": {"coordinates":[16.84234,44.49191],"type":"Point"}
}