{
  "type": "Feature",
  "properties": {
    "gn:admin1_code":"01",
    "gn:asciiname":"Potkraj",
    "gn:country_code":"BA",
    "gn:dem":921,
    "gn:feature_class":"P",
    "gn:feature_code":"PPL",
    "gn:name":"Potkraj",
    "gn:population":0,
    "gn:timezone":"Europe/Sarajevo",
    "iso:country":"BA",
    "name:und_x_variant":[
        "Podkraj",
        "Potkraj"
    ],
    "wof:name":"Potkraj",
    "wof:placetype":"locality"
},
  "geometry": {"coordinates":[16.90721,44.06989],"type":"Point"}
}