{
  "type": "Feature",
  "properties": {
    "gn:admin1_code":"01",
    "gn:asciiname":"Lugovi",
    "gn:country_code":"BA",
    "gn:dem":344,
    "gn:feature_class":"P",
    "gn:feature_code":"PPLL",
    "gn:name":"Lugovi",
    "gn:population":0,
    "gn:timezone":"Europe/Sarajevo",
    "iso:country":"BA",
    "name:bos_x_preferred":[
        "Lugovi"
    ],
    "name:fra_x_preferred":[
        "Lugovi"
    ],
    "name:hrv_x_preferred":[
        "Lugovi"
    ],
    "name:slv_x_preferred":[
        "Lugovi"
    ],
    "name:srp_x_preferred":[
        "\u041b\u0443\u0433\u043e\u0432\u0438"
    ],
    "wof:name":"Lugovi",
    "wof:placetype":"locality"
},
  "geometry": {"coordinates":[17.9773,44.51975],"type":"Point"}
}