{
  "type": "Feature",
  "properties": {
    "gn:admin1_code":"01",
    "gn:asciiname":"Oglavak",
    "gn:country_code":"BA",
    "gn:dem":294,
    "gn:feature_class":"P",
    "gn:feature_code":"PPL",
    "gn:name":"Oglavak",
    "gn:population":0,
    "gn:timezone":"Europe/Sarajevo",
    "iso:country":"BA",
    "wof:name":"Oglavak",
    "wof:placetype":"locality"
},
  "geometry": {"coordinates":[17.92389,44.34604],"type":"Point"}
}