{
  "type": "Feature",
  "properties": {
    "gn:admin1_code":"01",
    "gn:asciiname":"Njivice",
    "gn:country_code":"BA",
    "gn:dem":147,
    "gn:feature_class":"P",
    "gn:feature_code":"PPL",
    "gn:name":"Njivice",
    "gn:population":0,
    "gn:timezone":"Europe/Sarajevo",
    "iso:country":"BA",
    "wof:name":"Njivice",
    "wof:placetype":"locality"
},
  "geometry": {"coordinates":[17.9663,43.07061],"type":"Point"}
}