{
  "type": "Feature",
  "properties": {
    "gn:admin1_code":"01",
    "gn:asciiname":"Brezici",
    "gn:country_code":"BA",
    "gn:dem":284,
    "gn:feature_class":"P",
    "gn:feature_code":"PPL",
    "gn:name":"Brezi\u0107i",
    "gn:population":0,
    "gn:timezone":"Europe/Sarajevo",
    "iso:country":"BA",
    "name:bos_x_preferred":[
        "Brezici"
    ],
    "name:fra_x_preferred":[
        "Brezici"
    ],
    "name:hrv_x_preferred":[
        "Brezici"
    ],
    "name:srp_x_preferred":[
        "\u0411\u0440\u0435\u0437\u0438\u0446\u0438"
    ],
    "wof:name":"Brezici",
    "wof:placetype":"locality"
},
  "geometry": {"coordinates":[18.52305,44.58722],"type":"Point"}
}