{
  "type": "Feature",
  "properties": {
    "gn:admin1_code":"01",
    "gn:asciiname":"Kitosevici",
    "gn:country_code":"BA",
    "gn:dem":971,
    "gn:feature_class":"P",
    "gn:feature_code":"PPL",
    "gn:name":"Kito\u0161evi\u0107i",
    "gn:population":0,
    "gn:timezone":"Europe/Sarajevo",
    "iso:country":"BA",
    "wof:name":"Kitosevici",
    "wof:placetype":"locality"
},
  "geometry": {"coordinates":[18.465,44.01333],"type":"Point"}
}