{
  "type": "Feature",
  "properties": {
    "gn:admin1_code":"01",
    "gn:asciiname":"Marinkovci",
    "gn:country_code":"BA",
    "gn:dem":786,
    "gn:feature_class":"P",
    "gn:feature_code":"PPLL",
    "gn:name":"Marinkovci",
    "gn:population":0,
    "gn:timezone":"Europe/Sarajevo",
    "iso:country":"BA",
    "name:bos_x_preferred":[
        "Marinkovci"
    ],
    "name:fra_x_preferred":[
        "Marinkovci"
    ],
    "name:srp_x_preferred":[
        "\u041c\u0430\u0440\u0438\u043d\u043a\u043e\u0432\u0446\u0438"
    ],
    "wof:name":"Marinkovci",
    "wof:placetype":"locality"
},
  "geometry": {"coordinates":[16.45477,44.18145],"type":"Point"}
}