{
  "type": "Feature",
  "properties": {
    "gn:admin1_code":"01",
    "gn:asciiname":"Marinkovci",
    "gn:country_code":"BA",
    "gn:dem":786,
    "gn:feature_class":"P",
    "gn:feature_code":"PPLL",
    "gn:name":"Marinkovci",
    "gn:population":0,
    "gn:timezone":"Europe/Sarajevo",
    "iso:country":"BA",
    "wof:name":"Marinkovci",
    "wof:placetype":"locality"
},
  "geometry": {"coordinates":[16.45477,44.18145],"type":"Point"}
}