{
  "type": "Feature",
  "properties": {
    "gn:admin1_code":"02",
    "gn:asciiname":"Sredani",
    "gn:country_code":"BA",
    "gn:dem":904,
    "gn:feature_class":"P",
    "gn:feature_code":"PPLL",
    "gn:name":"Sre\u0111ani",
    "gn:population":0,
    "gn:timezone":"Europe/Sarajevo",
    "iso:country":"BA",
    "wof:name":"Sredani",
    "wof:placetype":"locality"
},
  "geometry": {"coordinates":[17.02762,44.33252],"type":"Point"}
}