{
  "type": "Feature",
  "properties": {
    "gn:admin1_code":"02",
    "gn:asciiname":"Andici",
    "gn:country_code":"BA",
    "gn:dem":490,
    "gn:feature_class":"P",
    "gn:feature_code":"PPL",
    "gn:name":"An\u0111i\u0107i",
    "gn:population":0,
    "gn:timezone":"Europe/Sarajevo",
    "iso:country":"BA",
    "wof:name":"Andici",
    "wof:placetype":"locality"
},
  "geometry": {"coordinates":[19.20399,44.2396],"type":"Point"}
}