{
  "type": "Feature",
  "properties": {
    "gn:admin1_code":"02",
    "gn:asciiname":"Donji Peci",
    "gn:country_code":"BA",
    "gn:dem":235,
    "gn:feature_class":"P",
    "gn:feature_code":"PPL",
    "gn:name":"Donji Pe\u0107i",
    "gn:population":0,
    "gn:timezone":"Europe/Sarajevo",
    "iso:country":"BA",
    "wof:name":"Donji Peci",
    "wof:placetype":"locality"
},
  "geometry": {"coordinates":[19.44639,43.96111],"type":"Point"}
}