{
  "type": "Feature",
  "properties": {
    "gn:admin1_code":"01",
    "gn:asciiname":"Zlib",
    "gn:country_code":"BA",
    "gn:dem":205,
    "gn:feature_class":"P",
    "gn:feature_code":"PPL",
    "gn:name":"\u017dlib",
    "gn:population":0,
    "gn:timezone":"Europe/Sarajevo",
    "iso:country":"BA",
    "name:ara_x_preferred":[
        "\u0632\u064a \u0644\u064a\u0628"
    ],
    "name:ces_x_preferred":[
        "Zlib"
    ],
    "name:deu_x_preferred":[
        "Zlib"
    ],
    "name:ell_x_preferred":[
        "Zlib"
    ],
    "name:fin_x_preferred":[
        "Zlib"
    ],
    "name:fra_x_preferred":[
        "Zlib"
    ],
    "name:jpn_x_preferred":[
        "Zlib"
    ],
    "name:kor_x_preferred":[
        "Zlib"
    ],
    "name:nor_x_preferred":[
        "Zlib"
    ],
    "name:pol_x_preferred":[
        "Zlib"
    ],
    "name:por_x_preferred":[
        "Zlib"
    ],
    "name:rus_x_preferred":[
        "Zlib"
    ],
    "name:spa_x_preferred":[
        "Zlib"
    ],
    "name:swe_x_preferred":[
        "Zlib"
    ],
    "name:ukr_x_preferred":[
        "Zlib"
    ],
    "name:zho_x_preferred":[
        "Zlib"
    ],
    "wof:name":"Zlib",
    "wof:placetype":"locality"
},
  "geometry": {"coordinates":[17.69111000000001,43.53177],"type":"Point"}
}