{
  "type": "Feature",
  "properties": {
    "gn:admin1_code":"01",
    "gn:asciiname":"Lukajici",
    "gn:country_code":"BA",
    "gn:dem":888,
    "gn:feature_class":"P",
    "gn:feature_code":"PPL",
    "gn:name":"Lukaji\u0107i",
    "gn:population":0,
    "gn:timezone":"Europe/Sarajevo",
    "iso:country":"BA",
    "wof:name":"Lukajici",
    "wof:placetype":"locality"
},
  "geometry": {"coordinates":[16.66807,44.20849000000001],"type":"Point"}
}