{
  "type": "Feature",
  "properties": {
    "gn:admin1_code":"01",
    "gn:asciiname":"Orasje",
    "gn:country_code":"BA",
    "gn:dem":434,
    "gn:feature_class":"P",
    "gn:feature_code":"PPL",
    "gn:name":"Ora\u0161je",
    "gn:population":0,
    "gn:timezone":"Europe/Sarajevo",
    "iso:country":"BA",
    "wof:name":"Orasje",
    "wof:placetype":"locality"
},
  "geometry": {"coordinates":[18.33434,44.34841],"type":"Point"}
}