{
  "type": "Feature",
  "properties": {
    "gn:admin1_code":"02",
    "gn:asciiname":"Radomile",
    "gn:country_code":"BA",
    "gn:dem":854,
    "gn:feature_class":"P",
    "gn:feature_code":"PPL",
    "gn:name":"Radomile",
    "gn:population":0,
    "gn:timezone":"Europe/Sarajevo",
    "iso:country":"BA",
    "wof:name":"Radomile",
    "wof:placetype":"locality"
},
  "geometry": {"coordinates":[16.92406,44.42767],"type":"Point"}
}