{
  "type": "Feature",
  "properties": {
    "gn:admin1_code":"02",
    "gn:asciiname":"Koprivno",
    "gn:country_code":"BA",
    "gn:dem":573,
    "gn:feature_class":"P",
    "gn:feature_code":"PPLL",
    "gn:name":"Koprivno",
    "gn:population":0,
    "gn:timezone":"Europe/Sarajevo",
    "iso:country":"BA",
    "wof:name":"Koprivno",
    "wof:placetype":"locality"
},
  "geometry": {"coordinates":[19.16277,44.14449000000001],"type":"Point"}
}