{
  "type": "Feature",
  "properties": {
    "gn:admin1_code":"02",
    "gn:asciiname":"Stevanovica Torine",
    "gn:country_code":"BA",
    "gn:dem":958,
    "gn:feature_class":"P",
    "gn:feature_code":"PPL",
    "gn:name":"Stevanovi\u0107a Torine",
    "gn:population":0,
    "gn:timezone":"Europe/Sarajevo",
    "iso:country":"BA",
    "wof:name":"Stevanovica Torine",
    "wof:placetype":"locality"
},
  "geometry": {"coordinates":[18.30956,43.09424],"type":"Point"}
}