{
  "type": "Feature",
  "properties": {
    "gn:admin1_code":"02",
    "gn:asciiname":"Dragaljici",
    "gn:country_code":"BA",
    "gn:dem":839,
    "gn:feature_class":"P",
    "gn:feature_code":"PPL",
    "gn:name":"Dragalji\u0107i",
    "gn:population":0,
    "gn:timezone":"Europe/Sarajevo",
    "iso:country":"BA",
    "wof:name":"Dragaljici",
    "wof:placetype":"locality"
},
  "geometry": {"coordinates":[18.62506,44.01517],"type":"Point"}
}