{
  "type": "Feature",
  "properties": {
    "gn:admin1_code":"01",
    "gn:asciiname":"Kozuli",
    "gn:country_code":"BA",
    "gn:dem":248,
    "gn:feature_class":"P",
    "gn:feature_code":"PPL",
    "gn:name":"Ko\u017euli",
    "gn:population":0,
    "gn:timezone":"Europe/Sarajevo",
    "iso:country":"BA",
    "wof:name":"Kozuli",
    "wof:placetype":"locality"
},
  "geometry": {"coordinates":[17.64472,43.34111],"type":"Point"}
}