{
  "type": "Feature",
  "properties": {
    "gn:admin1_code":"01",
    "gn:asciiname":"Vesici",
    "gn:country_code":"BA",
    "gn:dem":835,
    "gn:feature_class":"P",
    "gn:feature_code":"PPL",
    "gn:name":"Vesi\u0107i",
    "gn:population":0,
    "gn:timezone":"Europe/Sarajevo",
    "iso:country":"BA",
    "wof:name":"Vesici",
    "wof:placetype":"locality"
},
  "geometry": {"coordinates":[17.95738,44.23511],"type":"Point"}
}