{
  "type": "Feature",
  "properties": {
    "gn:admin1_code":"02",
    "gn:asciiname":"Bogdanici",
    "gn:country_code":"BA",
    "gn:dem":749,
    "gn:feature_class":"P",
    "gn:feature_code":"PPLL",
    "gn:name":"Bogdani\u0107i",
    "gn:population":0,
    "gn:timezone":"Europe/Sarajevo",
    "iso:country":"BA",
    "name:bos_x_preferred":[
        "Bogdani\u0107i"
    ],
    "name:fra_x_preferred":[
        "Bogdani\u0107i"
    ],
    "name:srp_x_preferred":[
        "\u0411\u043e\u0433\u0434\u0430\u043d\u0438\u045b\u0438"
    ],
    "name:und_x_variant":[
        "Bogdani\u0107i"
    ],
    "wof:name":"Bogdanici",
    "wof:placetype":"locality"
},
  "geometry": {"coordinates":[19.0069,43.70264],"type":"Point"}
}