{
  "type": "Feature",
  "properties": {
    "gn:admin1_code":"01",
    "gn:asciiname":"Hakalovici",
    "gn:country_code":"BA",
    "gn:dem":738,
    "gn:feature_class":"P",
    "gn:feature_code":"PPL",
    "gn:name":"Hakalovi\u0107i",
    "gn:population":0,
    "gn:timezone":"Europe/Sarajevo",
    "iso:country":"BA",
    "wof:name":"Hakalovici",
    "wof:placetype":"locality"
},
  "geometry": {"coordinates":[17.86639,43.75722],"type":"Point"}
}