{
  "type": "Feature",
  "properties": {
    "gn:admin1_code":"00",
    "gn:asciiname":"Gurbet",
    "gn:country_code":"BA",
    "gn:dem":159,
    "gn:feature_class":"P",
    "gn:feature_code":"PPL",
    "gn:name":"Gurbet",
    "gn:population":0,
    "gn:timezone":"Europe/Sarajevo",
    "iso:country":"BA",
    "wof:name":"Gurbet",
    "wof:placetype":"locality"
},
  "geometry": {"coordinates":[19.07306,44.69667000000001],"type":"Point"}
}