{
  "type": "Feature",
  "properties": {
    "gn:admin1_code":"01",
    "gn:asciiname":"Podovi",
    "gn:country_code":"BA",
    "gn:dem":770,
    "gn:feature_class":"P",
    "gn:feature_code":"PPL",
    "gn:name":"Podovi",
    "gn:population":0,
    "gn:timezone":"Europe/Sarajevo",
    "iso:country":"BA",
    "wof:name":"Podovi",
    "wof:placetype":"locality"
},
  "geometry": {"coordinates":[16.41667,44.36667],"type":"Point"}
}