{
  "type": "Feature",
  "properties": {
    "gn:admin1_code":"01",
    "gn:asciiname":"Bocinja Donja",
    "gn:country_code":"BA",
    "gn:dem":185,
    "gn:feature_class":"P",
    "gn:feature_code":"PPL",
    "gn:name":"Bo\u010dinja Donja",
    "gn:population":0,
    "gn:timezone":"Europe/Sarajevo",
    "iso:country":"BA",
    "name:und_x_variant":[
        "Bo\u010dinja",
        "Bo\u010dinje",
        "Bo\u010dina",
        "Bo\u010dinja Donja"
    ],
    "wof:name":"Bocinja Donja",
    "wof:placetype":"locality"
},
  "geometry": {"coordinates":[18.18096,44.5108],"type":"Point"}
}