{
  "type": "Feature",
  "properties": {
    "gn:admin1_code":"01",
    "gn:asciiname":"Podanovici",
    "gn:country_code":"BA",
    "gn:dem":232,
    "gn:feature_class":"P",
    "gn:feature_code":"PPL",
    "gn:name":"Podanovi\u0107i",
    "gn:population":0,
    "gn:timezone":"Europe/Sarajevo",
    "iso:country":"BA",
    "wof:name":"Podanovici",
    "wof:placetype":"locality"
},
  "geometry": {"coordinates":[18.51137,44.47731],"type":"Point"}
}