{
  "type": "Feature",
  "properties": {
    "gn:admin1_code":"01",
    "gn:asciiname":"Bilbije",
    "gn:country_code":"BA",
    "gn:dem":463,
    "gn:feature_class":"P",
    "gn:feature_code":"PPL",
    "gn:name":"Bilbije",
    "gn:population":0,
    "gn:timezone":"Europe/Sarajevo",
    "iso:country":"BA",
    "wof:name":"Bilbije",
    "wof:placetype":"locality"
},
  "geometry": {"coordinates":[16.45209,44.81073],"type":"Point"}
}