{
  "type": "Feature",
  "properties": {
    "gn:admin1_code":"01",
    "gn:asciiname":"Smionica",
    "gn:country_code":"BA",
    "gn:dem":606,
    "gn:feature_class":"P",
    "gn:feature_code":"PPL",
    "gn:name":"Smionica",
    "gn:population":0,
    "gn:timezone":"Europe/Sarajevo",
    "iso:country":"BA",
    "name:bos_x_preferred":[
        "Smionica"
    ],
    "name:ceb_x_preferred":[
        "Smionica"
    ],
    "name:fra_x_preferred":[
        "Smionica"
    ],
    "name:hrv_x_preferred":[
        "Smionica"
    ],
    "name:srp_x_preferred":[
        "\u0421\u043c\u0438\u043e\u043d\u0438\u0446\u0430"
    ],
    "name:swe_x_preferred":[
        "Smionica"
    ],
    "wof:name":"Smionica",
    "wof:placetype":"locality"
},
  "geometry": {"coordinates":[17.33046,44.39983],"type":"Point"}
}