{
  "type": "Feature",
  "properties": {
    "gn:admin1_code":"02",
    "gn:asciiname":"Klanac",
    "gn:country_code":"BA",
    "gn:dem":857,
    "gn:feature_class":"P",
    "gn:feature_code":"PPL",
    "gn:name":"Klanac",
    "gn:population":0,
    "gn:timezone":"Europe/Sarajevo",
    "iso:country":"BA",
    "name:bos_x_preferred":[
        "Klanac"
    ],
    "name:ceb_x_preferred":[
        "Klanac"
    ],
    "name:fra_x_preferred":[
        "Klanac"
    ],
    "name:hrv_x_preferred":[
        "Klanac"
    ],
    "name:hun_x_preferred":[
        "Klanac"
    ],
    "name:nld_x_preferred":[
        "Klanac"
    ],
    "name:slv_x_preferred":[
        "Klanac"
    ],
    "name:srp_x_preferred":[
        "\u041a\u043b\u0430\u043d\u0430\u0446"
    ],
    "name:swe_x_preferred":[
        "Klanac"
    ],
    "wof:name":"Klanac",
    "wof:placetype":"locality"
},
  "geometry": {"coordinates":[19.17363,43.58078],"type":"Point"}
}