{
  "type": "Feature",
  "properties": {
    "gn:admin1_code":"02",
    "gn:asciiname":"Mihailovici",
    "gn:country_code":"BA",
    "gn:dem":363,
    "gn:feature_class":"P",
    "gn:feature_code":"PPL",
    "gn:name":"Mihailovi\u0107i",
    "gn:population":0,
    "gn:timezone":"Europe/Sarajevo",
    "iso:country":"BA",
    "wof:name":"Mihailovici",
    "wof:placetype":"locality"
},
  "geometry": {"coordinates":[18.98159,44.44311],"type":"Point"}
}