{
  "type": "Feature",
  "properties": {
    "gn:admin1_code":"02",
    "gn:asciiname":"Kuzmani",
    "gn:country_code":"BA",
    "gn:dem":619,
    "gn:feature_class":"P",
    "gn:feature_code":"PPLL",
    "gn:name":"Kuzmani",
    "gn:population":0,
    "gn:timezone":"Europe/Sarajevo",
    "iso:country":"BA",
    "wof:name":"Kuzmani",
    "wof:placetype":"locality"
},
  "geometry": {"coordinates":[17.7712,44.53431],"type":"Point"}
}