{
  "type": "Feature",
  "properties": {
    "gn:admin1_code":"01",
    "gn:asciiname":"Vrkasic",
    "gn:country_code":"BA",
    "gn:dem":216,
    "gn:feature_class":"P",
    "gn:feature_code":"PPL",
    "gn:name":"Vrka\u0161i\u0107",
    "gn:population":0,
    "gn:timezone":"Europe/Sarajevo",
    "iso:country":"BA",
    "wof:name":"Vrkasic",
    "wof:placetype":"locality"
},
  "geometry": {"coordinates":[15.84389,44.83592],"type":"Point"}
}