{
  "type": "Feature",
  "properties": {
    "gn:admin1_code":"02",
    "gn:asciiname":"Sehovina",
    "gn:country_code":"BA",
    "gn:dem":970,
    "gn:feature_class":"P",
    "gn:feature_code":"PPL",
    "gn:name":"\u0160ehovina",
    "gn:population":0,
    "gn:timezone":"Europe/Sarajevo",
    "iso:country":"BA",
    "wof:name":"Sehovina",
    "wof:placetype":"locality"
},
  "geometry": {"coordinates":[18.50485,43.81271],"type":"Point"}
}