{
  "type": "Feature",
  "properties": {
    "gn:admin1_code":"01",
    "gn:asciiname":"Krekici",
    "gn:country_code":"BA",
    "gn:dem":904,
    "gn:feature_class":"P",
    "gn:feature_code":"PPL",
    "gn:name":"Kreki\u0107i",
    "gn:population":0,
    "gn:timezone":"Europe/Sarajevo",
    "iso:country":"BA",
    "wof:name":"Krekici",
    "wof:placetype":"locality"
},
  "geometry": {"coordinates":[17.35262,43.51912],"type":"Point"}
}