{
  "type": "Feature",
  "properties": {
    "gn:admin1_code":"01",
    "gn:asciiname":"Potok",
    "gn:country_code":"BA",
    "gn:dem":613,
    "gn:feature_class":"P",
    "gn:feature_code":"PPL",
    "gn:name":"Potok",
    "gn:population":0,
    "gn:timezone":"Europe/Sarajevo",
    "iso:country":"BA",
    "wof:name":"Potok",
    "wof:placetype":"locality"
},
  "geometry": {"coordinates":[17.60715,44.15417],"type":"Point"}
}