{
  "type": "Feature",
  "properties": {
    "gn:admin1_code":"02",
    "gn:asciiname":"Subin",
    "gn:country_code":"BA",
    "gn:dem":642,
    "gn:feature_class":"P",
    "gn:feature_code":"PPL",
    "gn:name":"\u0160ubin",
    "gn:population":0,
    "gn:timezone":"Europe/Sarajevo",
    "iso:country":"BA",
    "name:und_x_variant":[
        "\u0160ubin"
    ],
    "wof:name":"Subin",
    "wof:placetype":"locality"
},
  "geometry": {"coordinates":[19.3975,44.075],"type":"Point"}
}