{
  "type": "Feature",
  "properties": {
    "gn:admin1_code":"01",
    "gn:asciiname":"Sip",
    "gn:country_code":"BA",
    "gn:dem":568,
    "gn:feature_class":"P",
    "gn:feature_code":"PPL",
    "gn:name":"\u0160ip",
    "gn:population":0,
    "gn:timezone":"Europe/Sarajevo",
    "iso:country":"BA",
    "wof:name":"Sip",
    "wof:placetype":"locality"
},
  "geometry": {"coordinates":[18.39528,43.87972],"type":"Point"}
}