{
  "type": "Feature",
  "properties": {
    "gn:admin1_code":"01",
    "gn:asciiname":"Brda",
    "gn:country_code":"BA",
    "gn:dem":850,
    "gn:feature_class":"P",
    "gn:feature_code":"PPLL",
    "gn:name":"Brda",
    "gn:population":0,
    "gn:timezone":"Europe/Sarajevo",
    "iso:country":"BA",
    "wof:name":"Brda",
    "wof:placetype":"locality"
},
  "geometry": {"coordinates":[16.55667,44.28833],"type":"Point"}
}