{
  "type": "Feature",
  "properties": {
    "gn:admin1_code":"01",
    "gn:asciiname":"Maslina Strana",
    "gn:country_code":"BA",
    "gn:dem":954,
    "gn:feature_class":"P",
    "gn:feature_code":"PPL",
    "gn:name":"Maslina Strana",
    "gn:population":0,
    "gn:timezone":"Europe/Sarajevo",
    "iso:country":"BA",
    "wof:name":"Maslina Strana",
    "wof:placetype":"locality"
},
  "geometry": {"coordinates":[16.79028,44.19333],"type":"Point"}
}