{
  "type": "Feature",
  "properties": {
    "gn:admin1_code":"01",
    "gn:asciiname":"Maslina Strana",
    "gn:country_code":"BA",
    "gn:dem":954,
    "gn:feature_class":"P",
    "gn:feature_code":"PPL",
    "gn:name":"Maslina Strana",
    "gn:population":0,
    "gn:timezone":"Europe/Sarajevo",
    "iso:country":"BA",
    "name:bos_x_preferred":[
        "Maslina Strana"
    ],
    "name:fra_x_preferred":[
        "Maslina Strana"
    ],
    "name:srp_x_preferred":[
        "\u041c\u0430\u0441\u043b\u0438\u043d\u0430 \u0421\u0442\u0440\u0430\u043d\u0430"
    ],
    "wof:name":"Maslina Strana",
    "wof:placetype":"locality"
},
  "geometry": {"coordinates":[16.79028,44.19333],"type":"Point"}
}