{
  "type": "Feature",
  "properties": {
    "gn:admin1_code":"01",
    "gn:asciiname":"Karici",
    "gn:country_code":"BA",
    "gn:dem":534,
    "gn:feature_class":"P",
    "gn:feature_code":"PPL",
    "gn:name":"Kari\u0107i",
    "gn:population":0,
    "gn:timezone":"Europe/Sarajevo",
    "iso:country":"BA",
    "wof:name":"Karici",
    "wof:placetype":"locality"
},
  "geometry": {"coordinates":[17.97804,44.1499],"type":"Point"}
}