{
  "type": "Feature",
  "properties": {
    "gn:admin1_code":"01",
    "gn:asciiname":"Olovo",
    "gn:country_code":"BA",
    "gn:dem":1159,
    "gn:feature_class":"P",
    "gn:feature_code":"PPL",
    "gn:name":"Olovo",
    "gn:population":0,
    "gn:timezone":"Europe/Sarajevo",
    "iso:country":"BA",
    "wof:name":"Olovo",
    "wof:placetype":"locality"
},
  "geometry": {"coordinates":[17.26267,43.9947],"type":"Point"}
}