{
  "type": "Feature",
  "properties": {
    "gn:admin1_code":"01",
    "gn:asciiname":"Olovo",
    "gn:country_code":"BA",
    "gn:dem":1159,
    "gn:feature_class":"P",
    "gn:feature_code":"PPL",
    "gn:name":"Olovo",
    "gn:population":0,
    "gn:timezone":"Europe/Sarajevo",
    "iso:country":"BA",
    "name:bos_x_preferred":[
        "Olovo"
    ],
    "name:bul_x_preferred":[
        "\u041e\u043b\u043e\u0432\u043e"
    ],
    "name:ceb_x_preferred":[
        "Olovo"
    ],
    "name:deu_x_preferred":[
        "Olovo"
    ],
    "name:fra_x_preferred":[
        "Olovo"
    ],
    "name:hrv_x_preferred":[
        "Olovo"
    ],
    "name:ita_x_preferred":[
        "Olovo"
    ],
    "name:mkd_x_preferred":[
        "\u041e\u043b\u043e\u0432\u043e"
    ],
    "name:nld_x_preferred":[
        "Olovo"
    ],
    "name:pol_x_preferred":[
        "Olovo"
    ],
    "name:por_x_preferred":[
        "Olovo"
    ],
    "name:rus_x_preferred":[
        "\u041e\u043b\u043e\u0432\u043e"
    ],
    "name:spa_x_preferred":[
        "Olovo"
    ],
    "name:sqi_x_preferred":[
        "Ollovo"
    ],
    "name:srp_x_preferred":[
        "\u041e\u043b\u043e\u0432\u043e"
    ],
    "name:tur_x_preferred":[
        "Olovo"
    ],
    "name:urd_x_preferred":[
        "\u0627\u0648\u0644\u0648\u0648"
    ],
    "wof:name":"Olovo",
    "wof:placetype":"locality"
},
  "geometry": {"coordinates":[17.26267,43.9947],"type":"Point"}
}