{
  "type": "Feature",
  "properties": {
    "gn:admin1_code":"02",
    "gn:asciiname":"Otez",
    "gn:country_code":"BA",
    "gn:dem":989,
    "gn:feature_class":"P",
    "gn:feature_code":"PPL",
    "gn:name":"Otez",
    "gn:population":0,
    "gn:timezone":"Europe/Sarajevo",
    "iso:country":"BA",
    "wof:name":"Otez",
    "wof:placetype":"locality"
},
  "geometry": {"coordinates":[18.70398,43.70601],"type":"Point"}
}