{
  "type": "Feature",
  "properties": {
    "gn:admin1_code":"02",
    "gn:asciiname":"Canakcije",
    "gn:country_code":"BA",
    "gn:dem":303,
    "gn:feature_class":"P",
    "gn:feature_code":"PPL",
    "gn:name":"\u010canak\u010dije",
    "gn:population":0,
    "gn:timezone":"Europe/Sarajevo",
    "iso:country":"BA",
    "wof:name":"Canakcije",
    "wof:placetype":"locality"
},
  "geometry": {"coordinates":[18.97078,44.3927],"type":"Point"}
}