{
  "type": "Feature",
  "properties": {
    "gn:admin1_code":"02",
    "gn:asciiname":"Tomasi",
    "gn:country_code":"BA",
    "gn:dem":202,
    "gn:feature_class":"P",
    "gn:feature_code":"PPL",
    "gn:name":"Toma\u0161i",
    "gn:population":0,
    "gn:timezone":"Europe/Sarajevo",
    "iso:country":"BA",
    "name:cos_x_preferred":[
        "Tomasi"
    ],
    "wof:name":"Tomasi",
    "wof:placetype":"locality"
},
  "geometry": {"coordinates":[16.47728,44.90068],"type":"Point"}
}