{
  "type": "Feature",
  "properties": {
    "gn:admin1_code":"01",
    "gn:asciiname":"Hadzica Glavica",
    "gn:country_code":"BA",
    "gn:dem":358,
    "gn:feature_class":"P",
    "gn:feature_code":"PPL",
    "gn:name":"Had\u017ei\u0107a Glavica",
    "gn:population":0,
    "gn:timezone":"Europe/Sarajevo",
    "iso:country":"BA",
    "wof:name":"Hadzica Glavica",
    "wof:placetype":"locality"
},
  "geometry": {"coordinates":[16.06801,44.65414000000001],"type":"Point"}
}