{
  "type": "Feature",
  "properties": {
    "gn:admin1_code":"01",
    "gn:asciiname":"Velika",
    "gn:country_code":"BA",
    "gn:dem":1109,
    "gn:feature_class":"P",
    "gn:feature_code":"PPL",
    "gn:name":"Velika",
    "gn:population":0,
    "gn:timezone":"Europe/Sarajevo",
    "iso:country":"BA",
    "wof:name":"Velika",
    "wof:placetype":"locality"
},
  "geometry": {"coordinates":[17.995,43.75139],"type":"Point"}
}