{
  "type": "Feature",
  "properties": {
    "gn:admin1_code":"02",
    "gn:asciiname":"Raca",
    "gn:country_code":"BA",
    "gn:dem":607,
    "gn:feature_class":"P",
    "gn:feature_code":"PPLL",
    "gn:name":"Ra\u010da",
    "gn:population":0,
    "gn:timezone":"Europe/Sarajevo",
    "iso:country":"BA",
    "name:ceb_x_preferred":[
        "Raca"
    ],
    "name:deu_x_preferred":[
        "Raca"
    ],
    "name:hsb_x_preferred":[
        "Raca"
    ],
    "name:ita_x_preferred":[
        "Raca"
    ],
    "name:nld_x_preferred":[
        "Raca"
    ],
    "name:spa_x_preferred":[
        "Raca"
    ],
    "name:sqi_x_preferred":[
        "Ra\u00e7a"
    ],
    "name:swe_x_preferred":[
        "Raca"
    ],
    "wof:name":"Raca",
    "wof:placetype":"locality"
},
  "geometry": {"coordinates":[18.89858,44.19591],"type":"Point"}
}