{
  "type": "Feature",
  "properties": {
    "gn:admin1_code":"01",
    "gn:asciiname":"Draga",
    "gn:country_code":"BA",
    "gn:dem":647,
    "gn:feature_class":"P",
    "gn:feature_code":"PPL",
    "gn:name":"Draga",
    "gn:population":0,
    "gn:timezone":"Europe/Sarajevo",
    "iso:country":"BA",
    "wof:name":"Draga",
    "wof:placetype":"locality"
},
  "geometry": {"coordinates":[17.64322,43.40955],"type":"Point"}
}