{
  "type": "Feature",
  "properties": {
    "gn:admin1_code":"01",
    "gn:asciiname":"Bjelis",
    "gn:country_code":"BA",
    "gn:dem":596,
    "gn:feature_class":"P",
    "gn:feature_code":"PPL",
    "gn:name":"Bjeli\u0161",
    "gn:population":0,
    "gn:timezone":"Europe/Sarajevo",
    "iso:country":"BA",
    "wof:name":"Bjelis",
    "wof:placetype":"locality"
},
  "geometry": {"coordinates":[18.63401,44.1439],"type":"Point"}
}