{
  "type": "Feature",
  "properties": {
    "gn:admin1_code":"01",
    "gn:asciiname":"Ruzici",
    "gn:country_code":"BA",
    "gn:dem":353,
    "gn:feature_class":"P",
    "gn:feature_code":"PPLL",
    "gn:name":"Ru\u017ei\u0107i",
    "gn:population":0,
    "gn:timezone":"Europe/Sarajevo",
    "iso:country":"BA",
    "wof:name":"Ruzici",
    "wof:placetype":"locality"
},
  "geometry": {"coordinates":[17.38857999999999,43.35491],"type":"Point"}
}