{
  "type": "Feature",
  "properties": {
    "gn:admin1_code":"01",
    "gn:asciiname":"Leke",
    "gn:country_code":"BA",
    "gn:dem":284,
    "gn:feature_class":"P",
    "gn:feature_code":"PPL",
    "gn:name":"Leke",
    "gn:population":0,
    "gn:timezone":"Europe/Sarajevo",
    "iso:country":"BA",
    "name:bre_x_preferred":[
        "Leke"
    ],
    "name:ceb_x_preferred":[
        "Leke"
    ],
    "name:fas_x_preferred":[
        "\u0644\u06a9"
    ],
    "name:fra_x_preferred":[
        "Leke"
    ],
    "name:nld_x_preferred":[
        "Leke"
    ],
    "name:por_x_preferred":[
        "Leke"
    ],
    "name:swe_x_preferred":[
        "Leke"
    ],
    "name:vls_x_preferred":[
        "Leke"
    ],
    "wof:name":"Leke",
    "wof:placetype":"locality"
},
  "geometry": {"coordinates":[17.3741,43.33231],"type":"Point"}
}