{
  "type": "Feature",
  "properties": {
    "gn:admin1_code":"02",
    "gn:asciiname":"Zanjevo",
    "gn:country_code":"BA",
    "gn:dem":351,
    "gn:feature_class":"P",
    "gn:feature_code":"PPL",
    "gn:name":"\u017danjevo",
    "gn:population":0,
    "gn:timezone":"Europe/Sarajevo",
    "iso:country":"BA",
    "wof:name":"Zanjevo",
    "wof:placetype":"locality"
},
  "geometry": {"coordinates":[19.52666,44.06981],"type":"Point"}
}