{
  "type": "Feature",
  "properties": {
    "gn:admin1_code":"01",
    "gn:asciiname":"Majkic-Japra Gornja",
    "gn:country_code":"BA",
    "gn:dem":532,
    "gn:feature_class":"P",
    "gn:feature_code":"PPL",
    "gn:name":"Majki\u0107-Japra Gornja",
    "gn:population":0,
    "gn:timezone":"Europe/Sarajevo",
    "iso:country":"BA",
    "wof:name":"Majkic-Japra Gornja",
    "wof:placetype":"locality"
},
  "geometry": {"coordinates":[16.36445,44.76977],"type":"Point"}
}