{
  "type": "Feature",
  "properties": {
    "gn:admin1_code":"02",
    "gn:asciiname":"Hatelji",
    "gn:country_code":"BA",
    "gn:dem":495,
    "gn:feature_class":"P",
    "gn:feature_code":"PPLL",
    "gn:name":"Hatelji",
    "gn:population":0,
    "gn:timezone":"Europe/Sarajevo",
    "iso:country":"BA",
    "wof:name":"Hatelji",
    "wof:placetype":"locality"
},
  "geometry": {"coordinates":[18.19929,43.0905],"type":"Point"}
}