{
  "type": "Feature",
  "properties": {
    "gn:admin1_code":"01",
    "gn:asciiname":"Mustelji",
    "gn:country_code":"BA",
    "gn:dem":395,
    "gn:feature_class":"P",
    "gn:feature_code":"PPL",
    "gn:name":"Mustelji",
    "gn:population":0,
    "gn:timezone":"Europe/Sarajevo",
    "iso:country":"BA",
    "wof:name":"Mustelji",
    "wof:placetype":"locality"
},
  "geometry": {"coordinates":[16.19557,44.90863],"type":"Point"}
}