{
  "type": "Feature",
  "properties": {
    "gn:country":"BA",
    "gn:fcode":"PPL",
    "gn:population":4424,
    "iso:country":"BA",
    "qs:name":"Stupari",
    "qs:name_adm0":"Bosna i Hercegovina",
    "qs:name_adm1":"Federacija Bosne I Hercegovine",
    "qs:photos_9k":1,
    "qs:photos_9r":1,
    "qs:photos_all":1,
    "qs:photos_sr":0,
    "qs:placetype":"Town",
    "qs:pop_sr":"4",
    "wof:name":"Stupari",
    "wof:placetype":"locality",
    "wof:population":4424
},
  "geometry": {"coordinates":[18.68416,44.31382],"type":"Point"}
}