{
  "type": "Feature",
  "properties": {
    "gn:admin1_code":"02",
    "gn:asciiname":"Palez",
    "gn:country_code":"BA",
    "gn:dem":924,
    "gn:feature_class":"P",
    "gn:feature_code":"PPL",
    "gn:name":"Pale\u017e",
    "gn:population":0,
    "gn:timezone":"Europe/Sarajevo",
    "iso:country":"BA",
    "wof:name":"Palez",
    "wof:placetype":"locality"
},
  "geometry": {"coordinates":[19.12161,43.99588],"type":"Point"}
}