{
  "type": "Feature",
  "properties": {
    "gn:admin1_code":"01",
    "gn:asciiname":"Slipcevici",
    "gn:country_code":"BA",
    "gn:dem":984,
    "gn:feature_class":"P",
    "gn:feature_code":"PPL",
    "gn:name":"Slip\u010devi\u0107i",
    "gn:population":0,
    "gn:timezone":"Europe/Sarajevo",
    "iso:country":"BA",
    "wof:name":"Slipcevici",
    "wof:placetype":"locality"
},
  "geometry": {"coordinates":[17.4083,44.40046],"type":"Point"}
}