{
  "type": "Feature",
  "properties": {
    "gn:admin1_code":"02",
    "gn:asciiname":"Dragojevici",
    "gn:country_code":"BA",
    "gn:dem":655,
    "gn:feature_class":"P",
    "gn:feature_code":"PPLL",
    "gn:name":"Dragojevi\u0107i",
    "gn:population":0,
    "gn:timezone":"Europe/Sarajevo",
    "iso:country":"BA",
    "name:und_x_variant":[
        "Dragojevi\u0107i"
    ],
    "wof:name":"Dragojevici",
    "wof:placetype":"locality"
},
  "geometry": {"coordinates":[18.80263,43.53591],"type":"Point"}
}