{
  "type": "Feature",
  "properties": {
    "gn:admin1_code":"01",
    "gn:asciiname":"Alagovac",
    "gn:country_code":"BA",
    "gn:dem":305,
    "gn:feature_class":"P",
    "gn:feature_code":"PPL",
    "gn:name":"Alagovac",
    "gn:population":0,
    "gn:timezone":"Europe/Sarajevo",
    "iso:country":"BA",
    "wof:name":"Alagovac",
    "wof:placetype":"locality"
},
  "geometry": {"coordinates":[17.37774,43.37531],"type":"Point"}
}