{
  "type": "Feature",
  "properties": {
    "gn:admin1_code":"02",
    "gn:asciiname":"Tesevici",
    "gn:country_code":"BA",
    "gn:dem":574,
    "gn:feature_class":"P",
    "gn:feature_code":"PPL",
    "gn:name":"Te\u0161evi\u0107i",
    "gn:population":0,
    "gn:timezone":"Europe/Sarajevo",
    "iso:country":"BA",
    "wof:name":"Tesevici",
    "wof:placetype":"locality"
},
  "geometry": {"coordinates":[18.76439,43.56135],"type":"Point"}
}