{
  "type": "Feature",
  "properties": {
    "gn:admin1_code":"02",
    "gn:asciiname":"Grabicani",
    "gn:country_code":"BA",
    "gn:dem":246,
    "gn:feature_class":"P",
    "gn:feature_code":"PPL",
    "gn:name":"Grabi\u010dani",
    "gn:population":0,
    "gn:timezone":"Europe/Sarajevo",
    "iso:country":"BA",
    "wof:name":"Grabicani",
    "wof:placetype":"locality"
},
  "geometry": {"coordinates":[18.26018,44.89223],"type":"Point"}
}