{
  "type": "Feature",
  "properties": {
    "gn:admin1_code":"02",
    "gn:asciiname":"Bojanici",
    "gn:country_code":"BA",
    "gn:dem":662,
    "gn:feature_class":"P",
    "gn:feature_code":"PPL",
    "gn:name":"Bojani\u0107i",
    "gn:population":0,
    "gn:timezone":"Europe/Sarajevo",
    "iso:country":"BA",
    "wof:name":"Bojanici",
    "wof:placetype":"locality"
},
  "geometry": {"coordinates":[17.14132,44.48868],"type":"Point"}
}