{
  "type": "Feature",
  "properties": {
    "gn:admin1_code":"02",
    "gn:asciiname":"Kerici",
    "gn:country_code":"BA",
    "gn:dem":222,
    "gn:feature_class":"P",
    "gn:feature_code":"PPL",
    "gn:name":"Keri\u0107i",
    "gn:population":0,
    "gn:timezone":"Europe/Sarajevo",
    "iso:country":"BA",
    "wof:name":"Kerici",
    "wof:placetype":"locality"
},
  "geometry": {"coordinates":[16.60476,44.93389000000001],"type":"Point"}
}