{
  "type": "Feature",
  "properties": {
    "gn:admin1_code":"01",
    "gn:asciiname":"Vukadini",
    "gn:country_code":"BA",
    "gn:dem":712,
    "gn:feature_class":"P",
    "gn:feature_code":"PPL",
    "gn:name":"Vukadini",
    "gn:population":0,
    "gn:timezone":"Europe/Sarajevo",
    "iso:country":"BA",
    "wof:name":"Vukadini",
    "wof:placetype":"locality"
},
  "geometry": {"coordinates":[16.91414,43.80644],"type":"Point"}
}