{
  "type": "Feature",
  "properties": {
    "gn:admin1_code":"01",
    "gn:asciiname":"Stari Grad",
    "gn:country_code":"BA",
    "gn:dem":845,
    "gn:feature_class":"P",
    "gn:feature_code":"PPL",
    "gn:name":"Stari Grad",
    "gn:population":0,
    "gn:timezone":"Europe/Sarajevo",
    "iso:country":"BA",
    "name:bos_x_preferred":[
        "Stari Grad"
    ],
    "name:bul_x_preferred":[
        "\u0421\u0442\u0430\u0440\u0438 \u0433\u0440\u0430\u0434"
    ],
    "name:ceb_x_preferred":[
        "Op\u0107ina Stari Grad Sarajevo"
    ],
    "name:dan_x_preferred":[
        "Stari Grad"
    ],
    "name:deu_x_preferred":[
        "Sarajevo-Stari Grad"
    ],
    "name:ell_x_preferred":[
        "\u03a3\u03c4\u03ac\u03c1\u03b9 \u0393\u03ba\u03c1\u03b1\u03bd\u03c4"
    ],
    "name:fra_x_preferred":[
        "Stari Grad"
    ],
    "name:hrv_x_preferred":[
        "Stari Grad Sarajevo"
    ],
    "name:jpn_x_preferred":[
        "\u30b9\u30bf\u30ea\u30fb\u30b0\u30e9\u30fc\u30c9"
    ],
    "name:mkd_x_preferred":[
        "\u0421\u0442\u0430\u0440\u0438 \u0413\u0440\u0430\u0434"
    ],
    "name:nld_x_preferred":[
        "Stari Grad"
    ],
    "name:pol_x_preferred":[
        "Stare Miasto"
    ],
    "name:spa_x_preferred":[
        "Stari Grad"
    ],
    "name:sqi_x_preferred":[
        "Stari Grad"
    ],
    "name:srp_x_preferred":[
        "\u041e\u043f\u0448\u0442\u0438\u043d\u0430 \u0421\u0442\u0430\u0440\u0438 \u0433\u0440\u0430\u0434"
    ],
    "name:srp_x_variant":[
        "\u041e\u043f\u0448\u0442\u0438\u043d\u0430 \u0421\u0442\u0430\u0440\u0438 \u0413\u0440\u0430\u0434"
    ],
    "name:swe_x_preferred":[
        "Op\u0107ina Stari Grad Sarajevo"
    ],
    "name:tur_x_preferred":[
        "Stari Grad"
    ],
    "name:ukr_x_preferred":[
        "\u0421\u0442\u0430\u0440\u0456-\u0413\u0440\u0430\u0434"
    ],
    "name:urd_x_preferred":[
        "\u0633\u062a\u0627\u0631\u06cc \u06af\u0631\u0627\u062f"
    ],
    "wof:name":"Stari Grad",
    "wof:placetype":"locality"
},
  "geometry": {"coordinates":[18.01206,43.68599],"type":"Point"}
}