{
  "type": "Feature",
  "properties": {
    "gn:admin1_code":"01",
    "gn:asciiname":"Stari Grad",
    "gn:country_code":"BA",
    "gn:dem":845,
    "gn:feature_class":"P",
    "gn:feature_code":"PPL",
    "gn:name":"Stari Grad",
    "gn:population":0,
    "gn:timezone":"Europe/Sarajevo",
    "iso:country":"BA",
    "name:bul_x_preferred":[
        "\u0421\u0442\u0430\u0440\u0438 \u0433\u0440\u0430\u0434"
    ],
    "name:deu_x_preferred":[
        "Sarajevo-Stari Grad"
    ],
    "name:jpn_x_preferred":[
        "\u30b9\u30bf\u30ea\u30fb\u30b0\u30e9\u30fc\u30c9"
    ],
    "name:pol_x_preferred":[
        "Stare Miasto"
    ],
    "name:srp_x_preferred":[
        "\u041e\u043f\u0448\u0442\u0438\u043d\u0430 \u0421\u0442\u0430\u0440\u0438 \u0433\u0440\u0430\u0434"
    ],
    "name:ukr_x_preferred":[
        "\u0421\u0442\u0430\u0440\u0456-\u0413\u0440\u0430\u0434"
    ],
    "wof:name":"Stari Grad",
    "wof:placetype":"locality"
},
  "geometry": {"coordinates":[18.01206,43.68599],"type":"Point"}
}