{
  "type": "Feature",
  "properties": {
    "gn:admin1_code":"02",
    "gn:asciiname":"Sulice",
    "gn:country_code":"BA",
    "gn:dem":735,
    "gn:feature_class":"P",
    "gn:feature_code":"PPL",
    "gn:name":"Sulice",
    "gn:population":0,
    "gn:timezone":"Europe/Sarajevo",
    "iso:country":"BA",
    "name:fra_x_preferred":[
        "Sulice"
    ],
    "name:srp_x_preferred":[
        "\u0421\u0443\u043b\u0438\u0446\u0435"
    ],
    "wof:name":"Sulice",
    "wof:placetype":"locality"
},
  "geometry": {"coordinates":[19.42417,43.99111],"type":"Point"}
}