{
  "type": "Feature",
  "properties": {
    "gn:admin1_code":"01",
    "gn:asciiname":"Krivoglavci",
    "gn:country_code":"BA",
    "gn:dem":551,
    "gn:feature_class":"P",
    "gn:feature_code":"PPL",
    "gn:name":"Krivoglavci",
    "gn:population":0,
    "gn:timezone":"Europe/Sarajevo",
    "iso:country":"BA",
    "name:bos_x_preferred":[
        "Krivoglavci"
    ],
    "name:ceb_x_preferred":[
        "Krivoglavci"
    ],
    "name:fra_x_preferred":[
        "Krivoglavci"
    ],
    "name:swe_x_preferred":[
        "Krivoglavci"
    ],
    "wof:name":"Krivoglavci",
    "wof:placetype":"locality"
},
  "geometry": {"coordinates":[18.32199,43.90261],"type":"Point"}
}