{
  "type": "Feature",
  "properties": {
    "gn:admin1_code":"01",
    "gn:asciiname":"Bacverac",
    "gn:country_code":"BA",
    "gn:dem":969,
    "gn:feature_class":"P",
    "gn:feature_code":"PPL",
    "gn:name":"Ba\u010dverac",
    "gn:population":0,
    "gn:timezone":"Europe/Sarajevo",
    "iso:country":"BA",
    "wof:name":"Bacverac",
    "wof:placetype":"locality"
},
  "geometry": {"coordinates":[17.61122,43.44332],"type":"Point"}
}