{
  "type": "Feature",
  "properties": {
    "gn:admin1_code":"01",
    "gn:asciiname":"Servani",
    "gn:country_code":"BA",
    "gn:dem":732,
    "gn:feature_class":"P",
    "gn:feature_code":"PPL",
    "gn:name":"Servani",
    "gn:population":0,
    "gn:timezone":"Europe/Sarajevo",
    "iso:country":"BA",
    "name:bos_x_preferred":[
        "Servani"
    ],
    "name:fra_x_preferred":[
        "Servani"
    ],
    "name:srp_x_preferred":[
        "\u0421\u0435\u0440\u0432\u0430\u043d\u0438"
    ],
    "wof:name":"Servani",
    "wof:placetype":"locality"
},
  "geometry": {"coordinates":[17.4895,44.12823],"type":"Point"}
}