{
  "type": "Feature",
  "properties": {
    "gn:admin1_code":"02",
    "gn:asciiname":"Tuk",
    "gn:country_code":"BA",
    "gn:dem":491,
    "gn:feature_class":"P",
    "gn:feature_code":"PPL",
    "gn:name":"Tuk",
    "gn:population":0,
    "gn:timezone":"Europe/Sarajevo",
    "iso:country":"BA",
    "wof:name":"Tuk",
    "wof:placetype":"locality"
},
  "geometry": {"coordinates":[19.40722,44.10583],"type":"Point"}
}