{
  "type": "Feature",
  "properties": {
    "gn:admin1_code":"02",
    "gn:asciiname":"Dumanjici",
    "gn:country_code":"BA",
    "gn:dem":888,
    "gn:feature_class":"P",
    "gn:feature_code":"PPL",
    "gn:name":"Dumanji\u0107i",
    "gn:population":0,
    "gn:timezone":"Europe/Sarajevo",
    "iso:country":"BA",
    "name:und_x_variant":[
        "Dumani\u0107i",
        "Dumonji\u0107i",
        "Dumanji\u0107i"
    ],
    "wof:name":"Dumanjici",
    "wof:placetype":"locality"
},
  "geometry": {"coordinates":[19.03767,43.89864],"type":"Point"}
}