{
  "type": "Feature",
  "properties": {
    "gn:admin1_code":"BRC",
    "gn:asciiname":"Vuksic Gornji",
    "gn:country_code":"BA",
    "gn:dem":92,
    "gn:feature_class":"P",
    "gn:feature_code":"PPL",
    "gn:name":"Vuk\u0161i\u0107 Gornji",
    "gn:population":0,
    "gn:timezone":"Europe/Sarajevo",
    "iso:country":"BA",
    "name:bos_x_preferred":[
        "Vuk\u0161i\u0107 Gornji"
    ],
    "name:ceb_x_preferred":[
        "Vuk\u0161i\u0107 Gornji"
    ],
    "name:fra_x_preferred":[
        "Vuk\u0161i\u0107 Gornji"
    ],
    "name:hrv_x_preferred":[
        "Vuk\u0161i\u0107 Gornji"
    ],
    "name:srp_x_preferred":[
        "\u0412\u0443\u043a\u0448\u0438\u045b \u0413\u043e\u0440\u045a\u0438"
    ],
    "name:swe_x_preferred":[
        "Vuk\u0161i\u0107 Gornji"
    ],
    "name:und_x_variant":[
        "Gornji Vuk\u0161i\u0107",
        "Vuk\u0161i\u0107 Gornji"
    ],
    "wof:name":"Vuksic Gornji",
    "wof:placetype":"locality"
},
  "geometry": {"coordinates":[18.66401,44.88325],"type":"Point"}
}