{
  "type": "Feature",
  "properties": {
    "gn:admin1_code":"02",
    "gn:asciiname":"Kuvalji",
    "gn:country_code":"BA",
    "gn:dem":236,
    "gn:feature_class":"P",
    "gn:feature_code":"PPL",
    "gn:name":"Kuvalji",
    "gn:population":0,
    "gn:timezone":"Europe/Sarajevo",
    "iso:country":"BA",
    "wof:name":"Kuvalji",
    "wof:placetype":"locality"
},
  "geometry": {"coordinates":[16.89754,44.82663],"type":"Point"}
}