{
  "type": "Feature",
  "properties": {
    "gn:admin1_code":"02",
    "gn:asciiname":"Cadavica Donja",
    "gn:country_code":"BA",
    "gn:dem":246,
    "gn:feature_class":"P",
    "gn:feature_code":"PPL",
    "gn:name":"\u010ca\u0111avica Donja",
    "gn:population":0,
    "gn:timezone":"Europe/Sarajevo",
    "iso:country":"BA",
    "name:bos_x_preferred":[
        "\u010ca\u0111avica Donja"
    ],
    "name:ceb_x_preferred":[
        "\u010ca\u0111avica Donja"
    ],
    "name:fra_x_preferred":[
        "\u010ca\u0111avica Donja"
    ],
    "name:hrv_x_preferred":[
        "\u010ca\u0111avica Donja"
    ],
    "name:srp_x_preferred":[
        "\u0427\u0430\u0452\u0430\u0432\u0438\u0446\u0430 \u0414\u043e\u045a\u0430"
    ],
    "name:swe_x_preferred":[
        "\u010ca\u0111avica Donja"
    ],
    "name:und_x_variant":[
        "Donja \u010cadjavica",
        "\u010ca\u0111evica Donja",
        "\u010ca\u0111avica Donja"
    ],
    "wof:name":"Cadavica Donja",
    "wof:placetype":"locality"
},
  "geometry": {"coordinates":[16.32336,44.96578],"type":"Point"}
}