{
  "type": "Feature",
  "properties": {
    "gn:admin1_code":"01",
    "gn:asciiname":"Cemerno",
    "gn:country_code":"BA",
    "gn:dem":1260,
    "gn:feature_class":"P",
    "gn:feature_code":"PPLL",
    "gn:name":"\u010cemerno",
    "gn:population":0,
    "gn:timezone":"Europe/Sarajevo",
    "iso:country":"BA",
    "wof:name":"Cemerno",
    "wof:placetype":"locality"
},
  "geometry": {"coordinates":[18.3719,44.03583],"type":"Point"}
}