{
  "type": "Feature",
  "properties": {
    "gn:admin1_code":"01",
    "gn:asciiname":"Kula",
    "gn:country_code":"BA",
    "gn:dem":240,
    "gn:feature_class":"P",
    "gn:feature_code":"PPL",
    "gn:name":"Kula",
    "gn:population":0,
    "gn:timezone":"Europe/Sarajevo",
    "iso:country":"BA",
    "wof:name":"Kula",
    "wof:placetype":"locality"
},
  "geometry": {"coordinates":[15.92503,44.80337],"type":"Point"}
}