{
  "type": "Feature",
  "properties": {
    "gn:admin1_code":"01",
    "gn:asciiname":"Podglavica",
    "gn:country_code":"BA",
    "gn:dem":451,
    "gn:feature_class":"P",
    "gn:feature_code":"PPL",
    "gn:name":"Podglavica",
    "gn:population":0,
    "gn:timezone":"Europe/Sarajevo",
    "iso:country":"BA",
    "name:bos_x_preferred":[
        "Podglavica"
    ],
    "name:fra_x_preferred":[
        "Podglavica"
    ],
    "name:srp_x_preferred":[
        "\u041f\u043e\u0434\u0433\u043b\u0430\u0432\u0438\u0446\u0430"
    ],
    "wof:name":"Podglavica",
    "wof:placetype":"locality"
},
  "geometry": {"coordinates":[16.46651,44.78556],"type":"Point"}
}