{
  "type": "Feature",
  "properties": {
    "gn:admin1_code":"02",
    "gn:asciiname":"Plema",
    "gn:country_code":"BA",
    "gn:dem":541,
    "gn:feature_class":"P",
    "gn:feature_code":"PPLL",
    "gn:name":"Plema",
    "gn:population":0,
    "gn:timezone":"Europe/Sarajevo",
    "iso:country":"BA",
    "wof:name":"Plema",
    "wof:placetype":"locality"
},
  "geometry": {"coordinates":[19.48388,43.62119000000001],"type":"Point"}
}