{
  "type": "Feature",
  "properties": {
    "gn:admin1_code":"02",
    "gn:asciiname":"Prijakovci",
    "gn:country_code":"BA",
    "gn:dem":253,
    "gn:feature_class":"P",
    "gn:feature_code":"PPL",
    "gn:name":"Prijakovci",
    "gn:population":0,
    "gn:timezone":"Europe/Sarajevo",
    "iso:country":"BA",
    "wof:name":"Prijakovci",
    "wof:placetype":"locality"
},
  "geometry": {"coordinates":[17.15554,44.88253],"type":"Point"}
}