{
  "type": "Feature",
  "properties": {
    "gn:admin1_code":"02",
    "gn:asciiname":"Dzakici",
    "gn:country_code":"BA",
    "gn:dem":1005,
    "gn:feature_class":"P",
    "gn:feature_code":"PPL",
    "gn:name":"D\u017eaki\u0107i",
    "gn:population":0,
    "gn:timezone":"Europe/Sarajevo",
    "iso:country":"BA",
    "wof:name":"Dzakici",
    "wof:placetype":"locality"
},
  "geometry": {"coordinates":[17.12455,44.16189],"type":"Point"}
}