{
  "type": "Feature",
  "properties": {
    "gn:admin1_code":"02",
    "gn:asciiname":"Pavlovici",
    "gn:country_code":"BA",
    "gn:dem":434,
    "gn:feature_class":"P",
    "gn:feature_code":"PPL",
    "gn:name":"Pavlovi\u0107i",
    "gn:population":0,
    "gn:timezone":"Europe/Sarajevo",
    "iso:country":"BA",
    "wof:name":"Pavlovici",
    "wof:placetype":"locality"
},
  "geometry": {"coordinates":[18.21429,44.87300000000001],"type":"Point"}
}