{
  "type": "Feature",
  "properties": {
    "gn:admin1_code":"02",
    "gn:asciiname":"Kosa",
    "gn:country_code":"BA",
    "gn:dem":147,
    "gn:feature_class":"P",
    "gn:feature_code":"PPL",
    "gn:name":"Kosa",
    "gn:population":0,
    "gn:timezone":"Europe/Sarajevo",
    "iso:country":"BA",
    "wof:name":"Kosa",
    "wof:placetype":"locality"
},
  "geometry": {"coordinates":[18.91095,44.74834],"type":"Point"}
}