{
  "type": "Feature",
  "properties": {
    "gn:admin1_code":"01",
    "gn:asciiname":"Crnice",
    "gn:country_code":"BA",
    "gn:dem":623,
    "gn:feature_class":"P",
    "gn:feature_code":"PPL",
    "gn:name":"Crni\u010de",
    "gn:population":0,
    "gn:timezone":"Europe/Sarajevo",
    "iso:country":"BA",
    "name:bos_x_preferred":[
        "Crni\u010de"
    ],
    "name:ceb_x_preferred":[
        "Crni\u010de"
    ],
    "name:fra_x_preferred":[
        "Crni\u010de"
    ],
    "name:hrv_x_preferred":[
        "Crni\u010de"
    ],
    "name:srp_x_preferred":[
        "\u0426\u0440\u043d\u0438\u0447\u0435"
    ],
    "name:swe_x_preferred":[
        "Crni\u010de"
    ],
    "wof:name":"Crnice",
    "wof:placetype":"locality"
},
  "geometry": {"coordinates":[17.44862,44.03141],"type":"Point"}
}