{
  "type": "Feature",
  "properties": {
    "gn:admin1_code":"02",
    "gn:asciiname":"Cekrnje",
    "gn:country_code":"BA",
    "gn:dem":1013,
    "gn:feature_class":"P",
    "gn:feature_code":"PPL",
    "gn:name":"\u010cekrnje",
    "gn:population":0,
    "gn:timezone":"Europe/Sarajevo",
    "iso:country":"BA",
    "wof:name":"Cekrnje",
    "wof:placetype":"locality"
},
  "geometry": {"coordinates":[18.30595,43.25126],"type":"Point"}
}