{
  "type": "Feature",
  "properties": {
    "gn:admin1_code":"02",
    "gn:asciiname":"Lipovac",
    "gn:country_code":"BA",
    "gn:dem":657,
    "gn:feature_class":"P",
    "gn:feature_code":"PPL",
    "gn:name":"Lipovac",
    "gn:population":0,
    "gn:timezone":"Europe/Sarajevo",
    "iso:country":"BA",
    "name:bos_x_preferred":[
        "Lipovac"
    ],
    "name:ceb_x_preferred":[
        "Lipovac"
    ],
    "name:deu_x_preferred":[
        "Lipovac"
    ],
    "name:fra_x_preferred":[
        "Lipovac"
    ],
    "name:hrv_x_preferred":[
        "Lipovac"
    ],
    "name:hun_x_preferred":[
        "Lipovac"
    ],
    "name:nld_x_preferred":[
        "Lipovac"
    ],
    "name:slv_x_preferred":[
        "Lipovac"
    ],
    "name:spa_x_preferred":[
        "Lipovac"
    ],
    "name:srp_x_preferred":[
        "\u041b\u0438\u043f\u043e\u0432\u0430\u0446"
    ],
    "name:swe_x_preferred":[
        "Lipovac"
    ],
    "wof:name":"Lipovac",
    "wof:placetype":"locality"
},
  "geometry": {"coordinates":[19.2364,44.09195],"type":"Point"}
}