{
  "type": "Feature",
  "properties": {
    "gn:admin1_code":"02",
    "gn:asciiname":"Delici",
    "gn:country_code":"BA",
    "gn:dem":441,
    "gn:feature_class":"P",
    "gn:feature_code":"PPL",
    "gn:name":"Deli\u0107i",
    "gn:population":0,
    "gn:timezone":"Europe/Sarajevo",
    "iso:country":"BA",
    "wof:name":"Delici",
    "wof:placetype":"locality"
},
  "geometry": {"coordinates":[19.13651,44.2428],"type":"Point"}
}