{
  "type": "Feature",
  "properties": {
    "gn:admin1_code":"01",
    "gn:asciiname":"Izacic-Grad",
    "gn:country_code":"BA",
    "gn:dem":344,
    "gn:feature_class":"P",
    "gn:feature_code":"PPL",
    "gn:name":"Iza\u010di\u0107-Grad",
    "gn:population":0,
    "gn:timezone":"Europe/Sarajevo",
    "iso:country":"BA",
    "wof:name":"Izacic-Grad",
    "wof:placetype":"locality"
},
  "geometry": {"coordinates":[15.78266,44.88243],"type":"Point"}
}