{
  "type": "Feature",
  "properties": {
    "gn:admin1_code":"01",
    "gn:asciiname":"Crno Osoje",
    "gn:country_code":"BA",
    "gn:dem":790,
    "gn:feature_class":"P",
    "gn:feature_code":"PPL",
    "gn:name":"Crno Osoje",
    "gn:population":0,
    "gn:timezone":"Europe/Sarajevo",
    "iso:country":"BA",
    "wof:name":"Crno Osoje",
    "wof:placetype":"locality"
},
  "geometry": {"coordinates":[17.24874,43.55353],"type":"Point"}
}