{
  "type": "Feature",
  "properties": {
    "gn:admin1_code":"02",
    "gn:asciiname":"Nikolici",
    "gn:country_code":"BA",
    "gn:dem":453,
    "gn:feature_class":"P",
    "gn:feature_code":"PPL",
    "gn:name":"Nikoli\u0107i",
    "gn:population":0,
    "gn:timezone":"Europe/Sarajevo",
    "iso:country":"BA",
    "wof:name":"Nikolici",
    "wof:placetype":"locality"
},
  "geometry": {"coordinates":[17.1894,44.62161],"type":"Point"}
}