{
  "type": "Feature",
  "properties": {
    "gn:admin1_code":"02",
    "gn:asciiname":"Grbici",
    "gn:country_code":"BA",
    "gn:dem":219,
    "gn:feature_class":"P",
    "gn:feature_code":"PPL",
    "gn:name":"Grbi\u0107i",
    "gn:population":0,
    "gn:timezone":"Europe/Sarajevo",
    "iso:country":"BA",
    "wof:name":"Grbici",
    "wof:placetype":"locality"
},
  "geometry": {"coordinates":[16.40639,44.94639],"type":"Point"}
}