{
  "type": "Feature",
  "properties": {
    "gn:admin1_code":"02",
    "gn:asciiname":"Grujici",
    "gn:country_code":"BA",
    "gn:dem":479,
    "gn:feature_class":"P",
    "gn:feature_code":"PPL",
    "gn:name":"Gruji\u0107i",
    "gn:population":0,
    "gn:timezone":"Europe/Sarajevo",
    "iso:country":"BA",
    "wof:name":"Grujici",
    "wof:placetype":"locality"
},
  "geometry": {"coordinates":[19.54472,44.04361],"type":"Point"}
}