{
  "type": "Feature",
  "properties": {
    "gn:admin1_code":"01",
    "gn:asciiname":"Gornje Bare",
    "gn:country_code":"BA",
    "gn:dem":1038,
    "gn:feature_class":"P",
    "gn:feature_code":"PPL",
    "gn:name":"Gornje Bare",
    "gn:population":0,
    "gn:timezone":"Europe/Sarajevo",
    "iso:country":"BA",
    "name:ceb_x_preferred":[
        "Gornje Bare"
    ],
    "name:hrv_x_preferred":[
        "Gornje Bare"
    ],
    "name:srp_x_preferred":[
        "\u0413\u043e\u0440\u045a\u0435 \u0411\u0430\u0440\u0435"
    ],
    "name:swe_x_preferred":[
        "Gornje Bare"
    ],
    "wof:name":"Gornje Bare",
    "wof:placetype":"locality"
},
  "geometry": {"coordinates":[18.83176,43.72657],"type":"Point"}
}