{
  "type": "Feature",
  "properties": {
    "gn:admin1_code":"01",
    "gn:asciiname":"Mujakovici",
    "gn:country_code":"BA",
    "gn:dem":908,
    "gn:feature_class":"P",
    "gn:feature_code":"PPL",
    "gn:name":"Mujakovi\u0107i",
    "gn:population":0,
    "gn:timezone":"Europe/Sarajevo",
    "iso:country":"BA",
    "name:und_x_variant":[
        "Mujakovi\u0107",
        "Mujkovi\u010di",
        "Mujakovi\u0107i"
    ],
    "wof:name":"Mujakovici",
    "wof:placetype":"locality"
},
  "geometry": {"coordinates":[17.81862000000001,43.97174],"type":"Point"}
}