{
  "type": "Feature",
  "properties": {
    "gn:admin1_code":"02",
    "gn:asciiname":"Begovac",
    "gn:country_code":"BA",
    "gn:dem":371,
    "gn:feature_class":"P",
    "gn:feature_code":"PPL",
    "gn:name":"Begovac",
    "gn:population":0,
    "gn:timezone":"Europe/Sarajevo",
    "iso:country":"BA",
    "name:bos_x_preferred":[
        "Begovac"
    ],
    "name:hrv_x_preferred":[
        "Begovac"
    ],
    "name:hun_x_preferred":[
        "Begovac"
    ],
    "name:nld_x_preferred":[
        "Begovac"
    ],
    "name:slv_x_preferred":[
        "Begovac"
    ],
    "name:spa_x_preferred":[
        "Begovac"
    ],
    "name:srp_x_preferred":[
        "\u0411\u0435\u0433\u043e\u0432\u0430\u0446"
    ],
    "name:ukr_x_preferred":[
        "\u0411\u0435\u0433\u043e\u0432\u0430\u0446\u044c"
    ],
    "wof:name":"Begovac",
    "wof:placetype":"locality"
},
  "geometry": {"coordinates":[16.54104,45.07854],"type":"Point"}
}