{
  "type": "Feature",
  "properties": {
    "gn:admin1_code":"02",
    "gn:asciiname":"Panici",
    "gn:country_code":"BA",
    "gn:dem":188,
    "gn:feature_class":"P",
    "gn:feature_code":"PPL",
    "gn:name":"Pani\u0107i",
    "gn:population":0,
    "gn:timezone":"Europe/Sarajevo",
    "iso:country":"BA",
    "wof:name":"Panici",
    "wof:placetype":"locality"
},
  "geometry": {"coordinates":[17.80052000000001,44.73932],"type":"Point"}
}