{
  "type": "Feature",
  "properties": {
    "gn:admin1_code":"01",
    "gn:asciiname":"Bogusici",
    "gn:country_code":"BA",
    "gn:dem":486,
    "gn:feature_class":"P",
    "gn:feature_code":"PPL",
    "gn:name":"Bogu\u0161i\u0107i",
    "gn:population":0,
    "gn:timezone":"Europe/Sarajevo",
    "iso:country":"BA",
    "name:bos_x_preferred":[
        "Bogu\u0161i\u0107i"
    ],
    "name:fra_x_preferred":[
        "Bogu\u0161i\u0107i"
    ],
    "name:und_x_variant":[
        "Bogu\u0161i\u0107i"
    ],
    "wof:name":"Bogusici",
    "wof:placetype":"locality"
},
  "geometry": {"coordinates":[18.90966,43.64134],"type":"Point"}
}