{
  "type": "Feature",
  "properties": {
    "gn:admin1_code":"02",
    "gn:asciiname":"Ljutava",
    "gn:country_code":"BA",
    "gn:dem":104,
    "gn:feature_class":"P",
    "gn:feature_code":"PPL",
    "gn:name":"Ljutava",
    "gn:population":0,
    "gn:timezone":"Europe/Sarajevo",
    "iso:country":"BA",
    "wof:name":"Ljutava",
    "wof:placetype":"locality"
},
  "geometry": {"coordinates":[17.15256,45.11527],"type":"Point"}
}