{
  "type": "Feature",
  "properties": {
    "gn:admin1_code":"01",
    "gn:asciiname":"Sastavci",
    "gn:country_code":"BA",
    "gn:dem":610,
    "gn:feature_class":"P",
    "gn:feature_code":"PPL",
    "gn:name":"Sastavci",
    "gn:population":0,
    "gn:timezone":"Europe/Sarajevo",
    "iso:country":"BA",
    "wof:name":"Sastavci",
    "wof:placetype":"locality"
},
  "geometry": {"coordinates":[18.07986,43.82278],"type":"Point"}
}