{
  "type": "Feature",
  "properties": {
    "gn:admin1_code":"02",
    "gn:asciiname":"Krstici",
    "gn:country_code":"BA",
    "gn:dem":168,
    "gn:feature_class":"P",
    "gn:feature_code":"PPL",
    "gn:name":"Krsti\u0107i",
    "gn:population":0,
    "gn:timezone":"Europe/Sarajevo",
    "iso:country":"BA",
    "wof:name":"Krstici",
    "wof:placetype":"locality"
},
  "geometry": {"coordinates":[18.9257,44.71975],"type":"Point"}
}