{
  "type": "Feature",
  "properties": {
    "iso:country":"BA",
    "name:bos_x_preferred":[
        "Ustipra\u010da"
    ],
    "name:chi_x_preferred":[
        "\u65b0\u6208\u62c9\u65e5\u4ee3"
    ],
    "name:dut_x_preferred":[
        "Ustipra\u010da"
    ],
    "name:eng_x_preferred":[
        "Ustipra\u010da"
    ],
    "name:fre_x_preferred":[
        "Ustipra\u010da"
    ],
    "name:ger_x_preferred":[
        "Ustipra\u010da"
    ],
    "name:hrv_x_preferred":[
        "Ustipra\u010da"
    ],
    "name:ita_x_preferred":[
        "Ustipra\u010da"
    ],
    "name:jpn_x_preferred":[
        "\u30ce\u30f4\u30a9\u30fb\u30b4\u30e9\u30b8\u30e5\u30c7"
    ],
    "name:pol_x_preferred":[
        "Novo Gora\u017ede"
    ],
    "name:rus_x_preferred":[
        "\u0423\u0441\u0442\u0438\u043f\u0440\u0430\u0447\u0430"
    ],
    "name:spa_x_preferred":[
        "Novo Gora\u017ede"
    ],
    "name:srp_x_preferred":[
        "\u041d\u043e\u0432\u043e \u0413\u043e\u0440\u0430\u0436\u0434\u0435"
    ],
    "name:swe_x_preferred":[
        "Ustipra\u010da"
    ],
    "name:tat_x_preferred":[
        "\u0423\u0441\u0442\u0438\u043f\u0440\u0430\u0447\u0430"
    ],
    "name:urd_x_preferred":[
        "\u0646\u0648\u0648\u0648 \u06af\u0648\u0631\u0634\u062f\u06d2"
    ],
    "qs:name":"Ustipra\u010da",
    "qs:name_adm0":"Bosna i Hercegovina",
    "qs:name_adm1":"Republika Srpska",
    "qs:photos":10,
    "qs:photos_1k":2,
    "qs:photos_9k":1,
    "qs:photos_9r":1,
    "qs:photos_all":10,
    "qs:photos_sr":1,
    "qs:placetype":"Town",
    "qs:pop_sr":"0",
    "wof:name":"Ustipra\u010da",
    "wof:placetype":"locality"
},
  "geometry": {"coordinates":[19.085986,43.6910315],"type":"Point"}
}