{
  "type": "Feature",
  "properties": {
    "gn:admin1_code":"02",
    "gn:asciiname":"Miluni",
    "gn:country_code":"BA",
    "gn:dem":867,
    "gn:feature_class":"P",
    "gn:feature_code":"PPL",
    "gn:name":"Miluni",
    "gn:population":0,
    "gn:timezone":"Europe/Sarajevo",
    "iso:country":"BA",
    "wof:name":"Miluni",
    "wof:placetype":"locality"
},
  "geometry": {"coordinates":[16.89386,44.4626],"type":"Point"}
}