{
  "type": "Feature",
  "properties": {
    "gn:admin1_code":"02",
    "gn:asciiname":"Tvrdimici",
    "gn:country_code":"BA",
    "gn:dem":1033,
    "gn:feature_class":"P",
    "gn:feature_code":"PPL",
    "gn:name":"Tvrdimi\u0107i",
    "gn:population":0,
    "gn:timezone":"Europe/Sarajevo",
    "iso:country":"BA",
    "name:bos_x_preferred":[
        "Tvrdimi\u0107i"
    ],
    "name:fra_x_preferred":[
        "Tvrdimi\u0107i"
    ],
    "name:hrv_x_preferred":[
        "Tvrdimi\u0107i"
    ],
    "name:srp_x_preferred":[
        "\u0422\u0432\u0440\u0434\u0438\u043c\u0438\u045b\u0438"
    ],
    "name:und_x_variant":[
        "Tvrdini\u0107i"
    ],
    "wof:name":"Tvrdimici",
    "wof:placetype":"locality"
},
  "geometry": {"coordinates":[18.45187,43.77878],"type":"Point"}
}