{
  "type": "Feature",
  "properties": {
    "gn:admin1_code":"01",
    "gn:asciiname":"Krsno Polje",
    "gn:country_code":"BA",
    "gn:dem":198,
    "gn:feature_class":"P",
    "gn:feature_code":"PPLL",
    "gn:name":"Krsno Polje",
    "gn:population":0,
    "gn:timezone":"Europe/Sarajevo",
    "iso:country":"BA",
    "name:bos_x_preferred":[
        "Krsno Polje"
    ],
    "name:ceb_x_preferred":[
        "Krsno Polje"
    ],
    "name:fra_x_preferred":[
        "Krsno Polje"
    ],
    "name:hrv_x_preferred":[
        "Krsno Polje"
    ],
    "name:swe_x_preferred":[
        "Krsno Polje"
    ],
    "wof:name":"Krsno Polje",
    "wof:placetype":"locality"
},
  "geometry": {"coordinates":[18.14975,44.5224],"type":"Point"}
}