{
  "type": "Feature",
  "properties": {
    "gn:admin1_code":"01",
    "gn:asciiname":"Radakovici",
    "gn:country_code":"BA",
    "gn:dem":419,
    "gn:feature_class":"P",
    "gn:feature_code":"PPL",
    "gn:name":"Radakovi\u0107i",
    "gn:population":0,
    "gn:timezone":"Europe/Sarajevo",
    "iso:country":"BA",
    "wof:name":"Radakovici",
    "wof:placetype":"locality"
},
  "geometry": {"coordinates":[16.50029,44.84605],"type":"Point"}
}