{
  "type": "Feature",
  "properties": {
    "gn:admin1_code":"02",
    "gn:asciiname":"Cembici",
    "gn:country_code":"BA",
    "gn:dem":119,
    "gn:feature_class":"P",
    "gn:feature_code":"PPL",
    "gn:name":"\u010cembi\u0107i",
    "gn:population":0,
    "gn:timezone":"Europe/Sarajevo",
    "iso:country":"BA",
    "wof:name":"Cembici",
    "wof:placetype":"locality"
},
  "geometry": {"coordinates":[19.12616,44.76591],"type":"Point"}
}