{
  "type": "Feature",
  "properties": {
    "gn:admin1_code":"02",
    "gn:asciiname":"Kerle",
    "gn:country_code":"BA",
    "gn:dem":703,
    "gn:feature_class":"P",
    "gn:feature_code":"PPL",
    "gn:name":"Kerle",
    "gn:population":0,
    "gn:timezone":"Europe/Sarajevo",
    "iso:country":"BA",
    "wof:name":"Kerle",
    "wof:placetype":"locality"
},
  "geometry": {"coordinates":[17.59362999999999,44.47641],"type":"Point"}
}