{
  "type": "Feature",
  "properties": {
    "gn:admin1_code":"02",
    "gn:asciiname":"Srnetica",
    "gn:country_code":"BA",
    "gn:dem":1044,
    "gn:feature_class":"P",
    "gn:feature_code":"PPL",
    "gn:name":"Srnetica",
    "gn:population":0,
    "gn:timezone":"Europe/Sarajevo",
    "iso:country":"BA",
    "name:bos_x_preferred":[
        "Srnetica"
    ],
    "name:fra_x_preferred":[
        "Srnetica"
    ],
    "name:hrv_x_preferred":[
        "Srnetica"
    ],
    "name:srp_x_preferred":[
        "\u0421\u0440\u043d\u0435\u0442\u0438\u0446\u0430"
    ],
    "wof:name":"Srnetica",
    "wof:placetype":"locality"
},
  "geometry": {"coordinates":[16.59778,44.45306],"type":"Point"}
}