{
  "type": "Feature",
  "properties": {
    "gn:admin1_code":"02",
    "gn:asciiname":"Srnetica",
    "gn:country_code":"BA",
    "gn:dem":1044,
    "gn:feature_class":"P",
    "gn:feature_code":"PPL",
    "gn:name":"Srnetica",
    "gn:population":0,
    "gn:timezone":"Europe/Sarajevo",
    "iso:country":"BA",
    "wof:name":"Srnetica",
    "wof:placetype":"locality"
},
  "geometry": {"coordinates":[16.59778,44.45306],"type":"Point"}
}