{
  "type": "Feature",
  "properties": {
    "gn:admin1_code":"02",
    "gn:asciiname":"Kabanj",
    "gn:country_code":"BA",
    "gn:dem":362,
    "gn:feature_class":"P",
    "gn:feature_code":"PPL",
    "gn:name":"Kabanj",
    "gn:population":0,
    "gn:timezone":"Europe/Sarajevo",
    "iso:country":"BA",
    "wof:name":"Kabanj",
    "wof:placetype":"locality"
},
  "geometry": {"coordinates":[19.16431,44.20223],"type":"Point"}
}