{
  "type": "Feature",
  "properties": {
    "gn:admin1_code":"01",
    "gn:asciiname":"Cehajici",
    "gn:country_code":"BA",
    "gn:dem":187,
    "gn:feature_class":"P",
    "gn:feature_code":"PPL",
    "gn:name":"\u010cehaji\u0107i",
    "gn:population":0,
    "gn:timezone":"Europe/Sarajevo",
    "iso:country":"BA",
    "wof:name":"Cehajici",
    "wof:placetype":"locality"
},
  "geometry": {"coordinates":[18.0918,44.52612],"type":"Point"}
}