{
  "type": "Feature",
  "properties": {
    "gn:admin1_code":"01",
    "gn:asciiname":"Lipa",
    "gn:country_code":"BA",
    "gn:dem":720,
    "gn:feature_class":"P",
    "gn:feature_code":"PPLL",
    "gn:name":"Lipa",
    "gn:population":0,
    "gn:timezone":"Europe/Sarajevo",
    "iso:country":"BA",
    "wof:name":"Lipa",
    "wof:placetype":"locality"
},
  "geometry": {"coordinates":[16.07594,44.69521],"type":"Point"}
}