{
  "type": "Feature",
  "properties": {
    "gn:admin1_code":"01",
    "gn:asciiname":"Zlatici",
    "gn:country_code":"BA",
    "gn:dem":315,
    "gn:feature_class":"P",
    "gn:feature_code":"PPL",
    "gn:name":"Zlati\u0107i",
    "gn:population":0,
    "gn:timezone":"Europe/Sarajevo",
    "iso:country":"BA",
    "wof:name":"Zlatici",
    "wof:placetype":"locality"
},
  "geometry": {"coordinates":[18.03014,44.61703],"type":"Point"}
}