{
  "type": "Feature",
  "properties": {
    "gn:admin1_code":"01",
    "gn:asciiname":"Semin",
    "gn:country_code":"BA",
    "gn:dem":706,
    "gn:feature_class":"P",
    "gn:feature_code":"PPL",
    "gn:name":"Semin",
    "gn:population":0,
    "gn:timezone":"Europe/Sarajevo",
    "iso:country":"BA",
    "name:ceb_x_preferred":[
        "Semin"
    ],
    "name:deu_x_preferred":[
        "Semin"
    ],
    "name:ind_x_preferred":[
        "Semin"
    ],
    "name:nld_x_preferred":[
        "Semin"
    ],
    "name:swe_x_preferred":[
        "Semin"
    ],
    "wof:name":"Semin",
    "wof:placetype":"locality"
},
  "geometry": {"coordinates":[17.35996,44.15486],"type":"Point"}
}