{
  "type": "Feature",
  "properties": {
    "gn:admin1_code":"01",
    "gn:asciiname":"Grabac",
    "gn:country_code":"BA",
    "gn:dem":477,
    "gn:feature_class":"P",
    "gn:feature_code":"PPL",
    "gn:name":"Grabac",
    "gn:population":0,
    "gn:timezone":"Europe/Sarajevo",
    "iso:country":"BA",
    "wof:name":"Grabac",
    "wof:placetype":"locality"
},
  "geometry": {"coordinates":[17.94662000000001,44.26144],"type":"Point"}
}