{
  "type": "Feature",
  "properties": {
    "gn:admin1_code":"01",
    "gn:asciiname":"Lisicine",
    "gn:country_code":"BA",
    "gn:dem":375,
    "gn:feature_class":"P",
    "gn:feature_code":"PPL",
    "gn:name":"Lisi\u010dine",
    "gn:population":0,
    "gn:timezone":"Europe/Sarajevo",
    "iso:country":"BA",
    "wof:name":"Lisicine",
    "wof:placetype":"locality"
},
  "geometry": {"coordinates":[18.98779,44.61491],"type":"Point"}
}