{
  "type": "Feature",
  "properties": {
    "gn:admin1_code":"01",
    "gn:asciiname":"Hadrovci",
    "gn:country_code":"BA",
    "gn:dem":329,
    "gn:feature_class":"P",
    "gn:feature_code":"PPLL",
    "gn:name":"Hadrovci",
    "gn:population":0,
    "gn:timezone":"Europe/Sarajevo",
    "iso:country":"BA",
    "wof:name":"Hadrovci",
    "wof:placetype":"locality"
},
  "geometry": {"coordinates":[16.42376,44.85579],"type":"Point"}
}