{
  "type": "Feature",
  "properties": {
    "gn:admin1_code":"02",
    "gn:asciiname":"Travari",
    "gn:country_code":"BA",
    "gn:dem":750,
    "gn:feature_class":"P",
    "gn:feature_code":"PPL",
    "gn:name":"Travari",
    "gn:population":0,
    "gn:timezone":"Europe/Sarajevo",
    "iso:country":"BA",
    "wof:name":"Travari",
    "wof:placetype":"locality"
},
  "geometry": {"coordinates":[16.91267,44.48519],"type":"Point"}
}