{
  "type": "Feature",
  "properties": {
    "gn:admin1_code":"02",
    "gn:asciiname":"Ninici",
    "gn:country_code":"BA",
    "gn:dem":757,
    "gn:feature_class":"P",
    "gn:feature_code":"PPL",
    "gn:name":"Nini\u0107i",
    "gn:population":0,
    "gn:timezone":"Europe/Sarajevo",
    "iso:country":"BA",
    "wof:name":"Ninici",
    "wof:placetype":"locality"
},
  "geometry": {"coordinates":[17.11632,44.24712],"type":"Point"}
}