{
  "type": "Feature",
  "properties": {
    "gn:admin1_code":"01",
    "gn:asciiname":"Durusovina",
    "gn:country_code":"BA",
    "gn:dem":768,
    "gn:feature_class":"P",
    "gn:feature_code":"PPL",
    "gn:name":"Durusovina",
    "gn:population":0,
    "gn:timezone":"Europe/Sarajevo",
    "iso:country":"BA",
    "wof:name":"Durusovina",
    "wof:placetype":"locality"
},
  "geometry": {"coordinates":[17.95482,43.26203],"type":"Point"}
}