{
  "type": "Feature",
  "properties": {
    "gn:admin1_code":"02",
    "gn:asciiname":"Rastusa",
    "gn:country_code":"BA",
    "gn:dem":305,
    "gn:feature_class":"P",
    "gn:feature_code":"PPLL",
    "gn:name":"Rastu\u0161a",
    "gn:population":0,
    "gn:timezone":"Europe/Sarajevo",
    "iso:country":"BA",
    "wof:name":"Rastusa",
    "wof:placetype":"locality"
},
  "geometry": {"coordinates":[17.78592,44.70676],"type":"Point"}
}