{
  "type": "Feature",
  "properties": {
    "gn:admin1_code":"01",
    "gn:asciiname":"Budimiri",
    "gn:country_code":"BA",
    "gn:dem":621,
    "gn:feature_class":"P",
    "gn:feature_code":"PPL",
    "gn:name":"Budimiri",
    "gn:population":0,
    "gn:timezone":"Europe/Sarajevo",
    "iso:country":"BA",
    "wof:name":"Budimiri",
    "wof:placetype":"locality"
},
  "geometry": {"coordinates":[17.15265,43.52424],"type":"Point"}
}