{
  "type": "Feature",
  "properties": {
    "gn:admin1_code":"02",
    "gn:asciiname":"Cetojevici",
    "gn:country_code":"BA",
    "gn:dem":299,
    "gn:feature_class":"P",
    "gn:feature_code":"PPLL",
    "gn:name":"\u0106etojevi\u0107i",
    "gn:population":0,
    "gn:timezone":"Europe/Sarajevo",
    "iso:country":"BA",
    "wof:name":"Cetojevici",
    "wof:placetype":"locality"
},
  "geometry": {"coordinates":[17.38099,44.81685],"type":"Point"}
}