{
  "type": "Feature",
  "properties": {
    "gn:admin1_code":"01",
    "gn:asciiname":"Rudnik",
    "gn:country_code":"BA",
    "gn:dem":631,
    "gn:feature_class":"P",
    "gn:feature_code":"PPL",
    "gn:name":"Rudnik",
    "gn:population":0,
    "gn:timezone":"Europe/Sarajevo",
    "iso:country":"BA",
    "wof:name":"Rudnik",
    "wof:placetype":"locality"
},
  "geometry": {"coordinates":[18.18468,43.87223],"type":"Point"}
}