{
  "type": "Feature",
  "properties": {
    "gn:admin1_code":"01",
    "gn:asciiname":"Crnomarkovici",
    "gn:country_code":"BA",
    "gn:dem":728,
    "gn:feature_class":"P",
    "gn:feature_code":"PPL",
    "gn:name":"Crnomarkovi\u0107i",
    "gn:population":0,
    "gn:timezone":"Europe/Sarajevo",
    "iso:country":"BA",
    "wof:name":"Crnomarkovici",
    "wof:placetype":"locality"
},
  "geometry": {"coordinates":[16.62056,44.10417],"type":"Point"}
}