{
  "type": "Feature",
  "properties": {
    "gn:admin1_code":"02",
    "gn:asciiname":"Mandici",
    "gn:country_code":"BA",
    "gn:dem":443,
    "gn:feature_class":"P",
    "gn:feature_code":"PPL",
    "gn:name":"Mandi\u0107i",
    "gn:population":0,
    "gn:timezone":"Europe/Sarajevo",
    "iso:country":"BA",
    "wof:name":"Mandici",
    "wof:placetype":"locality"
},
  "geometry": {"coordinates":[17.83261,44.53301],"type":"Point"}
}