{
  "type": "Feature",
  "properties": {
    "gn:admin1_code":"01",
    "gn:asciiname":"Milesici",
    "gn:country_code":"BA",
    "gn:dem":236,
    "gn:feature_class":"P",
    "gn:feature_code":"PPLL",
    "gn:name":"Mile\u0161i\u0107i",
    "gn:population":0,
    "gn:timezone":"Europe/Sarajevo",
    "iso:country":"BA",
    "wof:name":"Milesici",
    "wof:placetype":"locality"
},
  "geometry": {"coordinates":[18.56888,44.56375],"type":"Point"}
}