{
  "type": "Feature",
  "properties": {
    "gn:admin1_code":"01",
    "gn:asciiname":"Kusesi",
    "gn:country_code":"BA",
    "gn:dem":818,
    "gn:feature_class":"P",
    "gn:feature_code":"PPL",
    "gn:name":"Ku\u0161e\u0161i",
    "gn:population":0,
    "gn:timezone":"Europe/Sarajevo",
    "iso:country":"BA",
    "name:bos_x_preferred":[
        "Ku\u0161e\u0161i"
    ],
    "name:fra_x_preferred":[
        "Ku\u0161e\u0161i"
    ],
    "wof:name":"Kusesi",
    "wof:placetype":"locality"
},
  "geometry": {"coordinates":[18.86121,43.65657],"type":"Point"}
}