{
  "type": "Feature",
  "properties": {
    "gn:admin1_code":"02",
    "gn:asciiname":"Drevusa",
    "gn:country_code":"BA",
    "gn:dem":552,
    "gn:feature_class":"P",
    "gn:feature_code":"PPL",
    "gn:name":"Drevu\u0161a",
    "gn:population":0,
    "gn:timezone":"Europe/Sarajevo",
    "iso:country":"BA",
    "name:und_x_variant":[
        "Dreu\u0161a",
        "Drevu\u0161a"
    ],
    "wof:name":"Drevusa",
    "wof:placetype":"locality"
},
  "geometry": {"coordinates":[17.17159,44.45991],"type":"Point"}
}