{
  "type": "Feature",
  "properties": {
    "gn:admin1_code":"01",
    "gn:asciiname":"Elezovici",
    "gn:country_code":"BA",
    "gn:dem":138,
    "gn:feature_class":"P",
    "gn:feature_code":"PPLL",
    "gn:name":"Elezovi\u0107i",
    "gn:population":0,
    "gn:timezone":"Europe/Sarajevo",
    "iso:country":"BA",
    "wof:name":"Elezovici",
    "wof:placetype":"locality"
},
  "geometry": {"coordinates":[15.93708,45.17814],"type":"Point"}
}