{
  "type": "Feature",
  "properties": {
    "gn:admin1_code":"01",
    "gn:asciiname":"Jasenova Ravan",
    "gn:country_code":"BA",
    "gn:dem":714,
    "gn:feature_class":"P",
    "gn:feature_code":"PPL",
    "gn:name":"Jasenova Ravan",
    "gn:population":0,
    "gn:timezone":"Europe/Sarajevo",
    "iso:country":"BA",
    "wof:name":"Jasenova Ravan",
    "wof:placetype":"locality"
},
  "geometry": {"coordinates":[18.39722,43.97778],"type":"Point"}
}