{
  "type": "Feature",
  "properties": {
    "gn:admin1_code":"02",
    "gn:asciiname":"Vulete",
    "gn:country_code":"BA",
    "gn:dem":887,
    "gn:feature_class":"P",
    "gn:feature_code":"PPL",
    "gn:name":"Vulete",
    "gn:population":0,
    "gn:timezone":"Europe/Sarajevo",
    "iso:country":"BA",
    "wof:name":"Vulete",
    "wof:placetype":"locality"
},
  "geometry": {"coordinates":[17.01741,44.33484],"type":"Point"}
}