{
  "type": "Feature",
  "properties": {
    "gn:admin1_code":"01",
    "gn:asciiname":"Zeljke",
    "gn:country_code":"BA",
    "gn:dem":918,
    "gn:feature_class":"P",
    "gn:feature_code":"PPL",
    "gn:name":"Zeljke",
    "gn:population":0,
    "gn:timezone":"Europe/Sarajevo",
    "iso:country":"BA",
    "wof:name":"Zeljke",
    "wof:placetype":"locality"
},
  "geometry": {"coordinates":[17.42892,44.17026],"type":"Point"}
}