{
  "type": "Feature",
  "properties": {
    "gn:admin1_code":"01",
    "gn:asciiname":"Vranjesi",
    "gn:country_code":"BA",
    "gn:dem":245,
    "gn:feature_class":"P",
    "gn:feature_code":"PPL",
    "gn:name":"Vranje\u0161i",
    "gn:population":0,
    "gn:timezone":"Europe/Sarajevo",
    "iso:country":"BA",
    "wof:name":"Vranjesi",
    "wof:placetype":"locality"
},
  "geometry": {"coordinates":[17.41957,43.33378],"type":"Point"}
}