{
  "type": "Feature",
  "properties": {
    "gn:admin1_code":"02",
    "gn:asciiname":"Ukrinica",
    "gn:country_code":"BA",
    "gn:dem":314,
    "gn:feature_class":"P",
    "gn:feature_code":"PPLL",
    "gn:name":"Ukrinica",
    "gn:population":0,
    "gn:timezone":"Europe/Sarajevo",
    "iso:country":"BA",
    "name:und_x_variant":[
        "Ukrnjica",
        "Ukrinica"
    ],
    "wof:name":"Ukrinica",
    "wof:placetype":"locality"
},
  "geometry": {"coordinates":[17.78662000000001,44.66343],"type":"Point"}
}