{
  "type": "Feature",
  "properties": {
    "gn:admin1_code":"01",
    "gn:asciiname":"Grahovici",
    "gn:country_code":"BA",
    "gn:dem":146,
    "gn:feature_class":"P",
    "gn:feature_code":"PPL",
    "gn:name":"Grahovi\u0107i",
    "gn:population":0,
    "gn:timezone":"Europe/Sarajevo",
    "iso:country":"BA",
    "name:und_x_variant":[
        "Grahovi\u0107",
        "Grahovi\u0107i"
    ],
    "wof:name":"Grahovici",
    "wof:placetype":"locality"
},
  "geometry": {"coordinates":[15.81462,45.16069],"type":"Point"}
}