{
  "type": "Feature",
  "properties": {
    "gn:admin1_code":"02",
    "gn:asciiname":"Petrovici",
    "gn:country_code":"BA",
    "gn:dem":240,
    "gn:feature_class":"P",
    "gn:feature_code":"PPL",
    "gn:name":"Petrovi\u0107i",
    "gn:population":0,
    "gn:timezone":"Europe/Sarajevo",
    "iso:country":"BA",
    "wof:name":"Petrovici",
    "wof:placetype":"locality"
},
  "geometry": {"coordinates":[18.17389,44.83889],"type":"Point"}
}