{
  "type": "Feature",
  "properties": {
    "gn:admin1_code":"02",
    "gn:asciiname":"Dubica",
    "gn:country_code":"BA",
    "gn:dem":845,
    "gn:feature_class":"P",
    "gn:feature_code":"PPLL",
    "gn:name":"Dubica",
    "gn:population":0,
    "gn:timezone":"Europe/Sarajevo",
    "iso:country":"BA",
    "name:bel_x_preferred":[
        "\u0414\u0443\u0431\u0456\u0446\u0430"
    ],
    "name:bos_x_preferred":[
        "Dubica"
    ],
    "name:ceb_x_preferred":[
        "Dubica"
    ],
    "name:fra_x_preferred":[
        "Dubica"
    ],
    "name:hrv_x_preferred":[
        "Dubica"
    ],
    "name:lit_x_preferred":[
        "Dubica"
    ],
    "name:pol_x_preferred":[
        "Dubica"
    ],
    "name:rus_x_preferred":[
        "\u0414\u0443\u0431\u0438\u0446\u0430"
    ],
    "name:srp_x_preferred":[
        "\u0414\u0443\u0431\u0438\u0446\u0430"
    ],
    "name:swe_x_preferred":[
        "Dubica"
    ],
    "wof:name":"Dubica",
    "wof:placetype":"locality"
},
  "geometry": {"coordinates":[16.98338,44.51668],"type":"Point"}
}