{
  "type": "Feature",
  "properties": {
    "gn:admin1_code":"02",
    "gn:asciiname":"Borovci",
    "gn:country_code":"BA",
    "gn:dem":275,
    "gn:feature_class":"P",
    "gn:feature_code":"PPLL",
    "gn:name":"Borovci",
    "gn:population":0,
    "gn:timezone":"Europe/Sarajevo",
    "iso:country":"BA",
    "wof:name":"Borovci",
    "wof:placetype":"locality"
},
  "geometry": {"coordinates":[17.01627,44.86001],"type":"Point"}
}