{
  "type": "Feature",
  "properties": {
    "gn:admin1_code":"02",
    "gn:asciiname":"Mrakici",
    "gn:country_code":"BA",
    "gn:dem":740,
    "gn:feature_class":"P",
    "gn:feature_code":"PPL",
    "gn:name":"Mraki\u0107i",
    "gn:population":0,
    "gn:timezone":"Europe/Sarajevo",
    "iso:country":"BA",
    "wof:name":"Mrakici",
    "wof:placetype":"locality"
},
  "geometry": {"coordinates":[18.82587,44.20501],"type":"Point"}
}