{
  "type": "Feature",
  "properties": {
    "gn:admin1_code":"01",
    "gn:asciiname":"Bajramovci",
    "gn:country_code":"BA",
    "gn:dem":1122,
    "gn:feature_class":"P",
    "gn:feature_code":"PPLL",
    "gn:name":"Bajramovci",
    "gn:population":0,
    "gn:timezone":"Europe/Sarajevo",
    "iso:country":"BA",
    "name:bul_x_preferred":[
        "\u0411\u0430\u0439\u0440\u0430\u043c\u043e\u0432\u0446\u0438"
    ],
    "name:fra_x_preferred":[
        "Bayramovtsi"
    ],
    "name:hun_x_preferred":[
        "Bajramovci"
    ],
    "name:mkd_x_preferred":[
        "\u0411\u0430\u0458\u0440\u0430\u043c\u043e\u0432\u0446\u0438"
    ],
    "name:sqi_x_preferred":[
        "Bajramoci"
    ],
    "name:srp_x_preferred":[
        "\u0411\u0430\u0458\u0440\u0430\u043c\u043e\u0432\u0446\u0438"
    ],
    "wof:name":"Bajramovci",
    "wof:placetype":"locality"
},
  "geometry": {"coordinates":[17.11119,44.05606],"type":"Point"}
}