{
  "type": "Feature",
  "properties": {
    "gn:admin1_code":"01",
    "gn:asciiname":"Hajdukovici",
    "gn:country_code":"BA",
    "gn:dem":709,
    "gn:feature_class":"P",
    "gn:feature_code":"PPL",
    "gn:name":"Hajdukovi\u0107i",
    "gn:population":0,
    "gn:timezone":"Europe/Sarajevo",
    "iso:country":"BA",
    "wof:name":"Hajdukovici",
    "wof:placetype":"locality"
},
  "geometry": {"coordinates":[16.95435,43.84107],"type":"Point"}
}