{
  "type": "Feature",
  "properties": {
    "gn:admin1_code":"01",
    "gn:asciiname":"Hasanovici",
    "gn:country_code":"BA",
    "gn:dem":823,
    "gn:feature_class":"P",
    "gn:feature_code":"PPL",
    "gn:name":"Hasanovi\u0107i",
    "gn:population":0,
    "gn:timezone":"Europe/Sarajevo",
    "iso:country":"BA",
    "name:und_x_variant":[
        "Hasanovi\u0107i"
    ],
    "wof:name":"Hasanovici",
    "wof:placetype":"locality"
},
  "geometry": {"coordinates":[17.94064,43.72876],"type":"Point"}
}