{
  "type": "Feature",
  "properties": {
    "gn:admin1_code":"02",
    "gn:asciiname":"Basarici",
    "gn:country_code":"BA",
    "gn:dem":792,
    "gn:feature_class":"P",
    "gn:feature_code":"PPLL",
    "gn:name":"Basari\u0107i",
    "gn:population":0,
    "gn:timezone":"Europe/Sarajevo",
    "iso:country":"BA",
    "wof:name":"Basarici",
    "wof:placetype":"locality"
},
  "geometry": {"coordinates":[18.67514,43.38269],"type":"Point"}
}