{
  "type": "Feature",
  "properties": {
    "gn:admin1_code":"01",
    "gn:asciiname":"Milaci",
    "gn:country_code":"BA",
    "gn:dem":866,
    "gn:feature_class":"P",
    "gn:feature_code":"PPL",
    "gn:name":"Mila\u0107i",
    "gn:population":0,
    "gn:timezone":"Europe/Sarajevo",
    "iso:country":"BA",
    "wof:name":"Milaci",
    "wof:placetype":"locality"
},
  "geometry": {"coordinates":[17.39278,44.17472],"type":"Point"}
}