{
  "type": "Feature",
  "properties": {
    "gn:admin1_code":"02",
    "gn:admin2_code":"3294894.0",
    "gn:asciiname":"Tutnjevici",
    "gn:country_code":"BA",
    "gn:dem":206,
    "gn:feature_class":"P",
    "gn:feature_code":"PPL",
    "gn:name":"Tutnjevici",
    "gn:population":0,
    "gn:timezone":"Europe/Sarajevo",
    "iso:country":"BA",
    "wof:name":"Tutnjevici",
    "wof:placetype":"locality"
},
  "geometry": {"coordinates":[17.83476,44.80363],"type":"Point"}
}