{
  "type": "Feature",
  "properties": {
    "gn:admin1_code":"02",
    "gn:asciiname":"Glavica",
    "gn:country_code":"BA",
    "gn:dem":896,
    "gn:feature_class":"P",
    "gn:feature_code":"PPL",
    "gn:name":"Glavica",
    "gn:population":0,
    "gn:timezone":"Europe/Sarajevo",
    "iso:country":"BA",
    "wof:name":"Glavica",
    "wof:placetype":"locality"
},
  "geometry": {"coordinates":[18.15864,43.2354],"type":"Point"}
}