{
  "type": "Feature",
  "properties": {
    "gn:admin1_code":"01",
    "gn:asciiname":"Bazine",
    "gn:country_code":"BA",
    "gn:dem":408,
    "gn:feature_class":"P",
    "gn:feature_code":"PPL",
    "gn:name":"Bazine",
    "gn:population":0,
    "gn:timezone":"Europe/Sarajevo",
    "iso:country":"BA",
    "wof:name":"Bazine",
    "wof:placetype":"locality"
},
  "geometry": {"coordinates":[17.47808,43.398],"type":"Point"}
}