{
  "type": "Feature",
  "properties": {
    "gn:admin1_code":"02",
    "gn:asciiname":"Banovici",
    "gn:country_code":"BA",
    "gn:dem":1070,
    "gn:feature_class":"P",
    "gn:feature_code":"PPL",
    "gn:name":"Banovi\u0107i",
    "gn:population":0,
    "gn:timezone":"Europe/Sarajevo",
    "iso:country":"BA",
    "wof:name":"Banovici",
    "wof:placetype":"locality"
},
  "geometry": {"coordinates":[17.4686,44.43558],"type":"Point"}
}