{
  "type": "Feature",
  "properties": {
    "gn:admin1_code":"01",
    "gn:asciiname":"Gornja Koprivnica",
    "gn:country_code":"BA",
    "gn:dem":522,
    "gn:feature_class":"P",
    "gn:feature_code":"PPL",
    "gn:name":"Gornja Koprivnica",
    "gn:population":0,
    "gn:timezone":"Europe/Sarajevo",
    "iso:country":"BA",
    "wof:name":"Gornja Koprivnica",
    "wof:placetype":"locality"
},
  "geometry": {"coordinates":[18.09247,44.1039],"type":"Point"}
}