{
  "type": "Feature",
  "properties": {
    "gn:admin1_code":"01",
    "gn:asciiname":"Cuklic",
    "gn:country_code":"BA",
    "gn:dem":737,
    "gn:feature_class":"P",
    "gn:feature_code":"PPL",
    "gn:name":"\u010cukli\u0107",
    "gn:population":0,
    "gn:timezone":"Europe/Sarajevo",
    "iso:country":"BA",
    "name:bos_x_preferred":[
        "\u010cukli\u0107"
    ],
    "name:ceb_x_preferred":[
        "\u010cukli\u0107"
    ],
    "name:fra_x_preferred":[
        "\u010cukli\u0107"
    ],
    "name:hrv_x_preferred":[
        "\u010cukli\u0107"
    ],
    "name:swe_x_preferred":[
        "\u010cukli\u0107"
    ],
    "name:und_x_variant":[
        "\u010cukli\u0107"
    ],
    "wof:name":"Cuklic",
    "wof:placetype":"locality"
},
  "geometry": {"coordinates":[16.88279,43.76134],"type":"Point"}
}