{
  "type": "Feature",
  "properties": {
    "gn:admin1_code":"01",
    "gn:asciiname":"Podvidaca",
    "gn:country_code":"BA",
    "gn:dem":437,
    "gn:feature_class":"P",
    "gn:feature_code":"PPLL",
    "gn:name":"Podvida\u010da",
    "gn:population":0,
    "gn:timezone":"Europe/Sarajevo",
    "iso:country":"BA",
    "wof:name":"Podvidaca",
    "wof:placetype":"locality"
},
  "geometry": {"coordinates":[16.51389,44.843],"type":"Point"}
}