{
  "type": "Feature",
  "properties": {
    "gn:admin1_code":"01",
    "gn:asciiname":"Ljubijankici",
    "gn:country_code":"BA",
    "gn:dem":312,
    "gn:feature_class":"P",
    "gn:feature_code":"PPL",
    "gn:name":"Ljubijanki\u0107i",
    "gn:population":0,
    "gn:timezone":"Europe/Sarajevo",
    "iso:country":"BA",
    "name:bos_x_preferred":[
        "Ljubijanki\u0107i"
    ],
    "name:ceb_x_preferred":[
        "Ljubijanki\u0107i"
    ],
    "name:fra_x_preferred":[
        "Ljubijanki\u0107i"
    ],
    "name:hrv_x_preferred":[
        "Ljubijanki\u0107i"
    ],
    "name:swe_x_preferred":[
        "Ljubijanki\u0107i"
    ],
    "name:und_x_variant":[
        "Ljubljanki\u0107i"
    ],
    "wof:name":"Ljubijankici",
    "wof:placetype":"locality"
},
  "geometry": {"coordinates":[15.97697,45.03137],"type":"Point"}
}