{
  "type": "Feature",
  "properties": {
    "gn:admin1_code":"01",
    "gn:asciiname":"Celine",
    "gn:country_code":"BA",
    "gn:dem":883,
    "gn:feature_class":"P",
    "gn:feature_code":"PPL",
    "gn:name":"\u010celine",
    "gn:population":0,
    "gn:timezone":"Europe/Sarajevo",
    "iso:country":"BA",
    "name:nld_x_preferred":[
        "Celine"
    ],
    "name:nno_x_preferred":[
        "Celine"
    ],
    "name:nor_x_preferred":[
        "Celine"
    ],
    "name:swe_x_preferred":[
        "Celine"
    ],
    "wof:name":"Celine",
    "wof:placetype":"locality"
},
  "geometry": {"coordinates":[17.31019,43.64672],"type":"Point"}
}