{
  "type": "Feature",
  "properties": {
    "gn:admin1_code":"02",
    "gn:asciiname":"Kukrike",
    "gn:country_code":"BA",
    "gn:dem":139,
    "gn:feature_class":"P",
    "gn:feature_code":"PPL",
    "gn:name":"Kukrike",
    "gn:population":0,
    "gn:timezone":"Europe/Sarajevo",
    "iso:country":"BA",
    "wof:name":"Kukrike",
    "wof:placetype":"locality"
},
  "geometry": {"coordinates":[16.51576,45.18106],"type":"Point"}
}