{
  "type": "Feature",
  "properties": {
    "gn:admin1_code":"01",
    "gn:asciiname":"Radalj Mahala",
    "gn:country_code":"BA",
    "gn:dem":108,
    "gn:feature_class":"P",
    "gn:feature_code":"PPL",
    "gn:name":"Radalj Mahala",
    "gn:population":0,
    "gn:timezone":"Europe/Sarajevo",
    "iso:country":"BA",
    "wof:name":"Radalj Mahala",
    "wof:placetype":"locality"
},
  "geometry": {"coordinates":[17.47361,43.1825],"type":"Point"}
}