{
  "type": "Feature",
  "properties": {
    "gn:admin1_code":"01",
    "gn:asciiname":"Sokolj",
    "gn:country_code":"BA",
    "gn:dem":607,
    "gn:feature_class":"P",
    "gn:feature_code":"PPL",
    "gn:name":"Sokolj",
    "gn:population":0,
    "gn:timezone":"Europe/Sarajevo",
    "iso:country":"BA",
    "wof:name":"Sokolj",
    "wof:placetype":"locality"
},
  "geometry": {"coordinates":[18.23815,44.01345],"type":"Point"}
}