{
  "type": "Feature",
  "properties": {
    "gn:admin1_code":"01",
    "gn:asciiname":"Masle",
    "gn:country_code":"BA",
    "gn:dem":270,
    "gn:feature_class":"P",
    "gn:feature_code":"PPL",
    "gn:name":"Masle",
    "gn:population":0,
    "gn:timezone":"Europe/Sarajevo",
    "iso:country":"BA",
    "wof:name":"Masle",
    "wof:placetype":"locality"
},
  "geometry": {"coordinates":[18.76983,44.4698],"type":"Point"}
}