{
  "type": "Feature",
  "properties": {
    "gn:asciiname":"Smrdan",
    "gn:country_code":"BA",
    "gn:dem":629,
    "gn:feature_class":"P",
    "gn:feature_code":"PPLL",
    "gn:name":"Smrdan",
    "gn:population":0,
    "gn:timezone":"Europe/Sarajevo",
    "iso:country":"BA",
    "name:ceb_x_preferred":[
        "Smrdan"
    ],
    "name:fra_x_preferred":[
        "Smrdan"
    ],
    "name:hrv_x_preferred":[
        "Smrdan"
    ],
    "name:slv_x_preferred":[
        "Smrdan"
    ],
    "name:srp_x_preferred":[
        "\u0421\u043c\u0440\u0434\u0430\u043d"
    ],
    "name:swe_x_preferred":[
        "Smrdan"
    ],
    "wof:name":"Smrdan",
    "wof:placetype":"locality"
},
  "geometry": {"coordinates":[16.6577,44.57569],"type":"Point"}
}