{
  "type": "Feature",
  "properties": {
    "gn:asciiname":"Smrdan",
    "gn:country_code":"BA",
    "gn:dem":629,
    "gn:feature_class":"P",
    "gn:feature_code":"PPLL",
    "gn:name":"Smrdan",
    "gn:population":0,
    "gn:timezone":"Europe/Sarajevo",
    "iso:country":"BA",
    "wof:name":"Smrdan",
    "wof:placetype":"locality"
},
  "geometry": {"coordinates":[16.6577,44.57569],"type":"Point"}
}