{
  "type": "Feature",
  "properties": {
    "gn:admin1_code":"01",
    "gn:asciiname":"Vracevici",
    "gn:country_code":"BA",
    "gn:dem":226,
    "gn:feature_class":"P",
    "gn:feature_code":"PPL",
    "gn:name":"Vra\u010devi\u0107i",
    "gn:population":0,
    "gn:timezone":"Europe/Sarajevo",
    "iso:country":"BA",
    "wof:name":"Vracevici",
    "wof:placetype":"locality"
},
  "geometry": {"coordinates":[18.40564,44.53248],"type":"Point"}
}