{
  "type": "Feature",
  "properties": {
    "gn:admin1_code":"02",
    "gn:asciiname":"Blagojevici",
    "gn:country_code":"BA",
    "gn:dem":341,
    "gn:feature_class":"P",
    "gn:feature_code":"PPL",
    "gn:name":"Blagojevi\u0107i",
    "gn:population":0,
    "gn:timezone":"Europe/Sarajevo",
    "iso:country":"BA",
    "wof:name":"Blagojevici",
    "wof:placetype":"locality"
},
  "geometry": {"coordinates":[16.925,44.7564],"type":"Point"}
}