{
  "type": "Feature",
  "properties": {
    "gn:admin1_code":"02",
    "gn:asciiname":"Vagan",
    "gn:country_code":"BA",
    "gn:dem":385,
    "gn:feature_class":"P",
    "gn:feature_code":"PPL",
    "gn:name":"Vagan",
    "gn:population":0,
    "gn:timezone":"Europe/Sarajevo",
    "iso:country":"BA",
    "wof:name":"Vagan",
    "wof:placetype":"locality"
},
  "geometry": {"coordinates":[19.42347,43.57518],"type":"Point"}
}