{
  "type": "Feature",
  "properties": {
    "gn:admin1_code":"01",
    "gn:asciiname":"Bejici",
    "gn:country_code":"BA",
    "gn:dem":236,
    "gn:feature_class":"P",
    "gn:feature_code":"PPL",
    "gn:name":"Beji\u0107i",
    "gn:population":0,
    "gn:timezone":"Europe/Sarajevo",
    "iso:country":"BA",
    "wof:name":"Bejici",
    "wof:placetype":"locality"
},
  "geometry": {"coordinates":[18.004,44.72139],"type":"Point"}
}