{
  "type": "Feature",
  "properties": {
    "gn:admin1_code":"02",
    "gn:asciiname":"Kuljani",
    "gn:country_code":"BA",
    "gn:dem":163,
    "gn:feature_class":"P",
    "gn:feature_code":"PPLL",
    "gn:name":"Kuljani",
    "gn:population":0,
    "gn:timezone":"Europe/Sarajevo",
    "iso:country":"BA",
    "name:bos_x_preferred":[
        "Kuljani"
    ],
    "name:ceb_x_preferred":[
        "Kuljani"
    ],
    "name:fra_x_preferred":[
        "Kuljani"
    ],
    "name:hrv_x_preferred":[
        "Kuljani"
    ],
    "name:rus_x_preferred":[
        "\u041a\u0443\u043b\u044f\u043d\u0438"
    ],
    "name:slv_x_preferred":[
        "Kuljani"
    ],
    "name:srp_x_preferred":[
        "\u041a\u0443\u0459\u0430\u043d\u0438"
    ],
    "name:swe_x_preferred":[
        "Kuljani"
    ],
    "wof:name":"Kuljani",
    "wof:placetype":"locality"
},
  "geometry": {"coordinates":[17.19974,44.84583],"type":"Point"}
}