{
  "type": "Feature",
  "properties": {
    "gn:admin1_code":"01",
    "gn:asciiname":"Dalasenovci",
    "gn:country_code":"BA",
    "gn:dem":441,
    "gn:feature_class":"P",
    "gn:feature_code":"PPL",
    "gn:name":"Dalasenovci",
    "gn:population":0,
    "gn:timezone":"Europe/Sarajevo",
    "iso:country":"BA",
    "wof:name":"Dalasenovci",
    "wof:placetype":"locality"
},
  "geometry": {"coordinates":[16.04705,44.61587],"type":"Point"}
}