{
  "type": "Feature",
  "properties": {
    "gn:admin1_code":"01",
    "gn:asciiname":"Podhranjen",
    "gn:country_code":"BA",
    "gn:dem":511,
    "gn:feature_class":"P",
    "gn:feature_code":"PPLL",
    "gn:name":"Podhranjen",
    "gn:population":0,
    "gn:timezone":"Europe/Sarajevo",
    "iso:country":"BA",
    "name:bos_x_preferred":[
        "Podhranjen"
    ],
    "name:fra_x_preferred":[
        "Podhranjen"
    ],
    "wof:name":"Podhranjen",
    "wof:placetype":"locality"
},
  "geometry": {"coordinates":[18.93029,43.69744],"type":"Point"}
}