{
  "type": "Feature",
  "properties": {
    "gn:admin1_code":"02",
    "gn:asciiname":"Crkvena",
    "gn:country_code":"BA",
    "gn:dem":244,
    "gn:feature_class":"P",
    "gn:feature_code":"PPLL",
    "gn:name":"Crkvena",
    "gn:population":0,
    "gn:timezone":"Europe/Sarajevo",
    "iso:country":"BA",
    "wof:name":"Crkvena",
    "wof:placetype":"locality"
},
  "geometry": {"coordinates":[17.50858,44.8366],"type":"Point"}
}