{
  "type": "Feature",
  "properties": {
    "gn:admin1_code":"01",
    "gn:asciiname":"Matina",
    "gn:country_code":"BA",
    "gn:dem":296,
    "gn:feature_class":"P",
    "gn:feature_code":"PPLL",
    "gn:name":"Matina",
    "gn:population":0,
    "gn:timezone":"Europe/Sarajevo",
    "iso:country":"BA",
    "wof:name":"Matina",
    "wof:placetype":"locality"
},
  "geometry": {"coordinates":[18.02378,44.48177],"type":"Point"}
}