{
  "type": "Feature",
  "properties": {
    "gn:admin1_code":"01",
    "gn:asciiname":"Matina",
    "gn:country_code":"BA",
    "gn:dem":296,
    "gn:feature_class":"P",
    "gn:feature_code":"PPLL",
    "gn:name":"Matina",
    "gn:population":0,
    "gn:timezone":"Europe/Sarajevo",
    "iso:country":"BA",
    "name:bpy_x_preferred":[
        "\u09ae\u09be\u099f\u09bf\u09a8\u09be"
    ],
    "name:epo_x_preferred":[
        "Matina"
    ],
    "name:eus_x_preferred":[
        "Matina"
    ],
    "name:fra_x_preferred":[
        "Matina"
    ],
    "name:hye_x_preferred":[
        "\u0544\u0561\u057f\u056b\u0576\u0561"
    ],
    "name:ita_x_preferred":[
        "Matina"
    ],
    "name:kat_x_preferred":[
        "\u10db\u10d0\u10e2\u10d8\u10dc\u10d0"
    ],
    "name:kaz_x_preferred":[
        "\u041c\u0430\u0442\u0438\u043d\u0430"
    ],
    "name:mlg_x_preferred":[
        "Matina"
    ],
    "name:nld_x_preferred":[
        "Matina"
    ],
    "name:nor_x_preferred":[
        "Matina"
    ],
    "name:pol_x_preferred":[
        "Matina"
    ],
    "name:por_x_preferred":[
        "Matina"
    ],
    "name:ron_x_preferred":[
        "Matina"
    ],
    "name:rus_x_preferred":[
        "\u041c\u0430\u0442\u0438\u043d\u0430"
    ],
    "name:vol_x_preferred":[
        "Matina"
    ],
    "name:war_x_preferred":[
        "Matina"
    ],
    "name:zho_x_preferred":[
        "\u9a6c\u8482\u7eb3"
    ],
    "wof:name":"Matina",
    "wof:placetype":"locality"
},
  "geometry": {"coordinates":[18.02378,44.48177],"type":"Point"}
}