{
  "type": "Feature",
  "properties": {
    "gn:admin1_code":"01",
    "gn:asciiname":"Kunosici",
    "gn:country_code":"BA",
    "gn:dem":1029,
    "gn:feature_class":"P",
    "gn:feature_code":"PPL",
    "gn:name":"Kunosi\u0107i",
    "gn:population":0,
    "gn:timezone":"Europe/Sarajevo",
    "iso:country":"BA",
    "name:bos_x_preferred":[
        "Kunosi\u0107i"
    ],
    "name:fra_x_preferred":[
        "Kunosi\u0107i"
    ],
    "name:hrv_x_preferred":[
        "Kunosi\u0107i"
    ],
    "name:pol_x_preferred":[
        "Kunosi\u0107i"
    ],
    "name:srp_x_preferred":[
        "\u041a\u0443\u043d\u043e\u0441\u0438\u045b\u0438"
    ],
    "wof:name":"Kunosici",
    "wof:placetype":"locality"
},
  "geometry": {"coordinates":[18.41505,44.06793],"type":"Point"}
}