{
  "type": "Feature",
  "properties": {
    "gn:admin1_code":"01",
    "gn:asciiname":"Jastrebica",
    "gn:country_code":"BA",
    "gn:dem":339,
    "gn:feature_class":"P",
    "gn:feature_code":"PPL",
    "gn:name":"Jastrebica",
    "gn:population":0,
    "gn:timezone":"Europe/Sarajevo",
    "iso:country":"BA",
    "wof:name":"Jastrebica",
    "wof:placetype":"locality"
},
  "geometry": {"coordinates":[18.51063,44.61343],"type":"Point"}
}