{
  "type": "Feature",
  "properties": {
    "gn:admin1_code":"02",
    "gn:asciiname":"Podnovlje",
    "gn:country_code":"BA",
    "gn:dem":126,
    "gn:feature_class":"P",
    "gn:feature_code":"PPLL",
    "gn:name":"Podnovlje",
    "gn:population":0,
    "gn:timezone":"Europe/Sarajevo",
    "iso:country":"BA",
    "name:bos_x_preferred":[
        "Podnovlje"
    ],
    "name:ceb_x_preferred":[
        "Podnovlje"
    ],
    "name:fra_x_preferred":[
        "Podnovlje"
    ],
    "name:hrv_x_preferred":[
        "Podnovlje"
    ],
    "name:srp_x_preferred":[
        "\u041f\u043e\u0434\u043d\u043e\u0432\u0459\u0435"
    ],
    "name:swe_x_preferred":[
        "Podnovlje"
    ],
    "wof:name":"Podnovlje",
    "wof:placetype":"locality"
},
  "geometry": {"coordinates":[18.11669,44.9483],"type":"Point"}
}