{
  "type": "Feature",
  "properties": {
    "gn:admin1_code":"01",
    "gn:asciiname":"Stanica Brdo",
    "gn:country_code":"BA",
    "gn:dem":575,
    "gn:feature_class":"P",
    "gn:feature_code":"PPL",
    "gn:name":"Stani\u0107a Brdo",
    "gn:population":0,
    "gn:timezone":"Europe/Sarajevo",
    "iso:country":"BA",
    "wof:name":"Stanica Brdo",
    "wof:placetype":"locality"
},
  "geometry": {"coordinates":[16.5567,44.6724],"type":"Point"}
}