{
  "type": "Feature",
  "properties": {
    "gn:admin1_code":"01",
    "gn:asciiname":"Spahovici",
    "gn:country_code":"BA",
    "gn:dem":891,
    "gn:feature_class":"P",
    "gn:feature_code":"PPL",
    "gn:name":"Spahovi\u0107i",
    "gn:population":0,
    "gn:timezone":"Europe/Sarajevo",
    "iso:country":"BA",
    "name:bos_x_preferred":[
        "Spahovi\u0107i"
    ],
    "name:fra_x_preferred":[
        "Spahovi\u0107i"
    ],
    "name:und_x_variant":[
        "Spahovi\u0107i"
    ],
    "wof:name":"Spahovici",
    "wof:placetype":"locality"
},
  "geometry": {"coordinates":[18.84411,43.67152],"type":"Point"}
}