{
  "type": "Feature",
  "properties": {
    "gn:admin1_code":"01",
    "gn:asciiname":"Krtova",
    "gn:country_code":"BA",
    "gn:dem":188,
    "gn:feature_class":"P",
    "gn:feature_code":"PPLL",
    "gn:name":"Krtova",
    "gn:population":0,
    "gn:timezone":"Europe/Sarajevo",
    "iso:country":"BA",
    "name:und_x_variant":[
        "Krtov",
        "Krtova"
    ],
    "wof:name":"Krtova",
    "wof:placetype":"locality"
},
  "geometry": {"coordinates":[18.41131,44.58143],"type":"Point"}
}