{
  "type": "Feature",
  "properties": {
    "gn:admin1_code":"02",
    "gn:asciiname":"Donja Kocela",
    "gn:country_code":"BA",
    "gn:dem":285,
    "gn:feature_class":"P",
    "gn:feature_code":"PPL",
    "gn:name":"Donja Ko\u010dela",
    "gn:population":0,
    "gn:timezone":"Europe/Sarajevo",
    "iso:country":"BA",
    "name:bos_x_preferred":[
        "Donja Ko\u010dela"
    ],
    "name:fra_x_preferred":[
        "Donja Ko\u010dela"
    ],
    "name:srp_x_preferred":[
        "\u0414\u043e\u045a\u0430 \u041a\u043e\u0447\u0435\u043b\u0430"
    ],
    "name:und_x_variant":[
        "Donja Ko\u010dela"
    ],
    "wof:name":"Donja Kocela",
    "wof:placetype":"locality"
},
  "geometry": {"coordinates":[18.24601,42.74414],"type":"Point"}
}