{
  "type": "Feature",
  "properties": {
    "gn:admin1_code":"02",
    "gn:asciiname":"Veljke",
    "gn:country_code":"BA",
    "gn:dem":1167,
    "gn:feature_class":"P",
    "gn:feature_code":"PPL",
    "gn:name":"Veljke",
    "gn:population":0,
    "gn:timezone":"Europe/Sarajevo",
    "iso:country":"BA",
    "wof:name":"Veljke",
    "wof:placetype":"locality"
},
  "geometry": {"coordinates":[17.1755,44.06406],"type":"Point"}
}