{
  "type": "Feature",
  "properties": {
    "gn:admin1_code":"01",
    "gn:asciiname":"Biske",
    "gn:country_code":"BA",
    "gn:dem":616,
    "gn:feature_class":"P",
    "gn:feature_code":"PPL",
    "gn:name":"Bi\u0161ke",
    "gn:population":0,
    "gn:timezone":"Europe/Sarajevo",
    "iso:country":"BA",
    "wof:name":"Biske",
    "wof:placetype":"locality"
},
  "geometry": {"coordinates":[17.29192999999999,43.4895],"type":"Point"}
}