{
  "type": "Feature",
  "properties": {
    "gn:admin1_code":"01",
    "gn:asciiname":"Mihovici",
    "gn:country_code":"BA",
    "gn:dem":508,
    "gn:feature_class":"P",
    "gn:feature_code":"PPL",
    "gn:name":"Mihovi\u0107i",
    "gn:population":0,
    "gn:timezone":"Europe/Sarajevo",
    "iso:country":"BA",
    "wof:name":"Mihovici",
    "wof:placetype":"locality"
},
  "geometry": {"coordinates":[18.84262,43.61608],"type":"Point"}
}