{
  "type": "Feature",
  "properties": {
    "gn:admin1_code":"02",
    "gn:asciiname":"Majstorovici",
    "gn:country_code":"BA",
    "gn:dem":176,
    "gn:feature_class":"P",
    "gn:feature_code":"PPL",
    "gn:name":"Majstorovi\u0107i",
    "gn:population":0,
    "gn:timezone":"Europe/Sarajevo",
    "iso:country":"BA",
    "name:und_x_variant":[
        "Mari\u0107ka",
        "Majstorovi\u0107i"
    ],
    "wof:name":"Majstorovici",
    "wof:placetype":"locality"
},
  "geometry": {"coordinates":[16.85126,44.85946],"type":"Point"}
}