{
  "type": "Feature",
  "properties": {
    "gn:admin1_code":"02",
    "gn:asciiname":"Jakes",
    "gn:country_code":"BA",
    "gn:dem":113,
    "gn:feature_class":"P",
    "gn:feature_code":"PPL",
    "gn:name":"Jake\u0161",
    "gn:population":0,
    "gn:timezone":"Europe/Sarajevo",
    "iso:country":"BA",
    "name:deu_x_preferred":[
        "Jakes"
    ],
    "name:fin_x_preferred":[
        "Jakes"
    ],
    "name:rus_x_preferred":[
        "\u0414\u0436\u0435\u0439\u043a\u0441"
    ],
    "wof:name":"Jakes",
    "wof:placetype":"locality"
},
  "geometry": {"coordinates":[18.28194,44.97972],"type":"Point"}
}