{
  "type": "Feature",
  "properties": {
    "gn:admin1_code":"01",
    "gn:asciiname":"Hamandzici",
    "gn:country_code":"BA",
    "gn:dem":1047,
    "gn:feature_class":"P",
    "gn:feature_code":"PPL",
    "gn:name":"Hamand\u017ei\u0107i",
    "gn:population":0,
    "gn:timezone":"Europe/Sarajevo",
    "iso:country":"BA",
    "name:und_x_variant":[
        "Hamamd\u017ei\u0107i",
        "Hamand\u017ei\u0107i"
    ],
    "wof:name":"Hamandzici",
    "wof:placetype":"locality"
},
  "geometry": {"coordinates":[17.46417000000001,44.27252],"type":"Point"}
}