{
  "type": "Feature",
  "properties": {
    "gn:admin1_code":"02",
    "gn:asciiname":"Sikmani",
    "gn:country_code":"BA",
    "gn:dem":696,
    "gn:feature_class":"P",
    "gn:feature_code":"PPL",
    "gn:name":"\u0160ikmani",
    "gn:population":0,
    "gn:timezone":"Europe/Sarajevo",
    "iso:country":"BA",
    "wof:name":"Sikmani",
    "wof:placetype":"locality"
},
  "geometry": {"coordinates":[17.23228,44.62162],"type":"Point"}
}