{
  "type": "Feature",
  "properties": {
    "gn:admin1_code":"01",
    "gn:asciiname":"Topalovici",
    "gn:country_code":"BA",
    "gn:dem":206,
    "gn:feature_class":"P",
    "gn:feature_code":"PPL",
    "gn:name":"Topalovi\u0107i",
    "gn:population":0,
    "gn:timezone":"Europe/Sarajevo",
    "iso:country":"BA",
    "wof:name":"Topalovici",
    "wof:placetype":"locality"
},
  "geometry": {"coordinates":[18.47337000000001,44.74782],"type":"Point"}
}