{
  "type": "Feature",
  "properties": {
    "gn:admin1_code":"01",
    "gn:asciiname":"Vehabovici",
    "gn:country_code":"BA",
    "gn:dem":288,
    "gn:feature_class":"P",
    "gn:feature_code":"PPL",
    "gn:name":"Vehabovi\u0107i",
    "gn:population":0,
    "gn:timezone":"Europe/Sarajevo",
    "iso:country":"BA",
    "wof:name":"Vehabovici",
    "wof:placetype":"locality"
},
  "geometry": {"coordinates":[18.07806,44.59043],"type":"Point"}
}