{
  "type": "Feature",
  "properties": {
    "gn:admin1_code":"01",
    "gn:asciiname":"Stojkovici",
    "gn:country_code":"BA",
    "gn:dem":698,
    "gn:feature_class":"P",
    "gn:feature_code":"PPL",
    "gn:name":"Stojkovi\u0107i",
    "gn:population":0,
    "gn:timezone":"Europe/Sarajevo",
    "iso:country":"BA",
    "name:bos_x_preferred":[
        "Stojkovi\u0107i"
    ],
    "name:fra_x_preferred":[
        "Stojkovi\u0107i"
    ],
    "name:hrv_x_preferred":[
        "Stojkovi\u0107i"
    ],
    "wof:name":"Stojkovici",
    "wof:placetype":"locality"
},
  "geometry": {"coordinates":[18.07972,43.98139000000001],"type":"Point"}
}