{
  "type": "Feature",
  "properties": {
    "gn:admin1_code":"01",
    "gn:asciiname":"Velika Dabrnja",
    "gn:country_code":"BA",
    "gn:dem":224,
    "gn:feature_class":"P",
    "gn:feature_code":"PPL",
    "gn:name":"Velika Dabrnja",
    "gn:population":0,
    "gn:timezone":"Europe/Sarajevo",
    "iso:country":"BA",
    "wof:name":"Velika Dabrnja",
    "wof:placetype":"locality"
},
  "geometry": {"coordinates":[16.20361,45.03056],"type":"Point"}
}