{
  "type": "Feature",
  "properties": {
    "gn:admin1_code":"01",
    "gn:asciiname":"Raska Gora",
    "gn:country_code":"BA",
    "gn:dem":459,
    "gn:feature_class":"P",
    "gn:feature_code":"PPL",
    "gn:name":"Ra\u0161ka Gora",
    "gn:population":0,
    "gn:timezone":"Europe/Sarajevo",
    "iso:country":"BA",
    "wof:name":"Raska Gora",
    "wof:placetype":"locality"
},
  "geometry": {"coordinates":[17.85,43.41667],"type":"Point"}
}