{
  "type": "Feature",
  "properties": {
    "gn:admin1_code":"02",
    "gn:asciiname":"Trnacko",
    "gn:country_code":"BA",
    "gn:dem":355,
    "gn:feature_class":"P",
    "gn:feature_code":"PPLL",
    "gn:name":"Trna\u010dko",
    "gn:population":0,
    "gn:timezone":"Europe/Sarajevo",
    "iso:country":"BA",
    "name:und_x_variant":[
        "Trna\u010dka",
        "Trna\u010dko"
    ],
    "wof:name":"Trnacko",
    "wof:placetype":"locality"
},
  "geometry": {"coordinates":[18.95028,44.65844],"type":"Point"}
}