{
  "type": "Feature",
  "properties": {
    "gn:admin1_code":"01",
    "gn:asciiname":"Jezerci",
    "gn:country_code":"BA",
    "gn:dem":1068,
    "gn:feature_class":"P",
    "gn:feature_code":"PPL",
    "gn:name":"Jezerci",
    "gn:population":0,
    "gn:timezone":"Europe/Sarajevo",
    "iso:country":"BA",
    "wof:name":"Jezerci",
    "wof:placetype":"locality"
},
  "geometry": {"coordinates":[17.69011,44.03658],"type":"Point"}
}