{
  "type": "Feature",
  "properties": {
    "gn:admin1_code":"01",
    "gn:asciiname":"Krcevine",
    "gn:country_code":"BA",
    "gn:dem":656,
    "gn:feature_class":"P",
    "gn:feature_code":"PPL",
    "gn:name":"Kr\u010devine",
    "gn:population":0,
    "gn:timezone":"Europe/Sarajevo",
    "iso:country":"BA",
    "wof:name":"Krcevine",
    "wof:placetype":"locality"
},
  "geometry": {"coordinates":[18.20522,43.97654],"type":"Point"}
}