{
  "type": "Feature",
  "properties": {
    "gn:admin1_code":"02",
    "gn:asciiname":"Vrapci",
    "gn:country_code":"BA",
    "gn:dem":836,
    "gn:feature_class":"P",
    "gn:feature_code":"PPLL",
    "gn:name":"Vrapci",
    "gn:population":0,
    "gn:timezone":"Europe/Sarajevo",
    "iso:country":"BA",
    "name:und_x_variant":[
        "Vrabci",
        "Vrapci"
    ],
    "wof:name":"Vrapci",
    "wof:placetype":"locality"
},
  "geometry": {"coordinates":[18.77516,44.0298],"type":"Point"}
}