{
  "type": "Feature",
  "properties": {
    "gn:admin1_code":"02",
    "gn:asciiname":"Kraljevici",
    "gn:country_code":"BA",
    "gn:dem":611,
    "gn:feature_class":"P",
    "gn:feature_code":"PPL",
    "gn:name":"Kraljevi\u0107i",
    "gn:population":0,
    "gn:timezone":"Europe/Sarajevo",
    "iso:country":"BA",
    "wof:name":"Kraljevici",
    "wof:placetype":"locality"
},
  "geometry": {"coordinates":[18.8205,44.24291],"type":"Point"}
}