{
  "type": "Feature",
  "properties": {
    "gn:admin1_code":"01",
    "gn:asciiname":"Budici",
    "gn:country_code":"BA",
    "gn:dem":492,
    "gn:feature_class":"P",
    "gn:feature_code":"PPL",
    "gn:name":"Budi\u0107i",
    "gn:population":0,
    "gn:timezone":"Europe/Sarajevo",
    "iso:country":"BA",
    "name:bos_x_preferred":[
        "Budi\u0107i"
    ],
    "name:ceb_x_preferred":[
        "Budi\u0107i"
    ],
    "name:fra_x_preferred":[
        "Budi\u0107i"
    ],
    "name:swe_x_preferred":[
        "Budi\u0107i"
    ],
    "wof:name":"Budici",
    "wof:placetype":"locality"
},
  "geometry": {"coordinates":[18.95661,43.65948],"type":"Point"}
}