{
  "type": "Feature",
  "properties": {
    "gn:admin1_code":"02",
    "gn:asciiname":"Stupine",
    "gn:country_code":"BA",
    "gn:dem":517,
    "gn:feature_class":"P",
    "gn:feature_code":"PPL",
    "gn:name":"Stupine",
    "gn:population":0,
    "gn:timezone":"Europe/Sarajevo",
    "iso:country":"BA",
    "wof:name":"Stupine",
    "wof:placetype":"locality"
},
  "geometry": {"coordinates":[19.28472,44.10472],"type":"Point"}
}