{
  "type": "Feature",
  "properties": {
    "gn:country":"BA",
    "gn:fcode":"PPL",
    "gn:population":0,
    "iso:country":"BA",
    "name:bos_x_preferred":[
        "Ostro\u017eac"
    ],
    "name:cat_x_preferred":[
        "Ostro\u017eac"
    ],
    "name:ceb_x_preferred":[
        "Ostro\u017eac"
    ],
    "name:ces_x_preferred":[
        "Ostro\u017eac"
    ],
    "name:dan_x_preferred":[
        "Ostro\u017eac"
    ],
    "name:deu_x_preferred":[
        "Ostro\u017eac"
    ],
    "name:eng_x_preferred":[
        "Ostro\u017eac"
    ],
    "name:eus_x_preferred":[
        "Ostro\u017eac"
    ],
    "name:fin_x_preferred":[
        "Ostro\u017eac"
    ],
    "name:fra_x_preferred":[
        "Ostro\u017eac"
    ],
    "name:hrv_x_preferred":[
        "Ostro\u017eac"
    ],
    "name:ind_x_preferred":[
        "Ostro\u017eac"
    ],
    "name:ita_x_preferred":[
        "Ostro\u017eac"
    ],
    "name:nld_x_preferred":[
        "Ostro\u017eac"
    ],
    "name:nno_x_preferred":[
        "Ostro\u017eac"
    ],
    "name:nob_x_preferred":[
        "Ostro\u017eac"
    ],
    "name:oci_x_preferred":[
        "Ostro\u017eac"
    ],
    "name:pol_x_preferred":[
        "Ostro\u017eac"
    ],
    "name:por_x_preferred":[
        "Ostro\u017eac"
    ],
    "name:ron_x_preferred":[
        "Ostro\u017eac"
    ],
    "name:slk_x_preferred":[
        "Ostro\u017eac"
    ],
    "name:slv_x_preferred":[
        "Ostro\u017eac"
    ],
    "name:spa_x_preferred":[
        "Ostro\u017eac"
    ],
    "name:srp_x_preferred":[
        "\u041e\u0441\u0442\u0440\u043e\u0436\u0430\u0446"
    ],
    "name:swe_x_preferred":[
        "Ostro\u017eac"
    ],
    "name:tgl_x_preferred":[
        "Ostro\u017eac"
    ],
    "name:tur_x_preferred":[
        "Ostro\u017eac"
    ],
    "name:war_x_preferred":[
        "Ostro\u017eac"
    ],
    "qs:name":"Ostro\u017eac",
    "qs:name_adm0":"Bosna i Hercegovina",
    "qs:name_adm1":"Federacija Bosne I Hercegovine",
    "qs:photos":105,
    "qs:photos_1k":21,
    "qs:photos_9k":1,
    "qs:photos_9r":3,
    "qs:photos_all":105,
    "qs:photos_sr":3,
    "qs:placetype":"Town",
    "qs:pop_sr":"0",
    "wof:name":"Ostro\u017eac",
    "wof:placetype":"locality",
    "wof:population":0
},
  "geometry": {"coordinates":[17.8265,43.68446],"type":"Point"}
}