{
  "type": "Feature",
  "properties": {
    "gn:admin1_code":"01",
    "gn:asciiname":"Karasnica",
    "gn:country_code":"BA",
    "gn:dem":398,
    "gn:feature_class":"P",
    "gn:feature_code":"PPL",
    "gn:name":"Kara\u0161nica",
    "gn:population":0,
    "gn:timezone":"Europe/Sarajevo",
    "iso:country":"BA",
    "wof:name":"Karasnica",
    "wof:placetype":"locality"
},
  "geometry": {"coordinates":[18.06632,44.54444],"type":"Point"}
}