{
  "type": "Feature",
  "properties": {
    "gn:admin1_code":"02",
    "gn:asciiname":"Diklici",
    "gn:country_code":"BA",
    "gn:dem":259,
    "gn:feature_class":"P",
    "gn:feature_code":"PPL",
    "gn:name":"Dikli\u0107i",
    "gn:population":0,
    "gn:timezone":"Europe/Sarajevo",
    "iso:country":"BA",
    "name:und_x_variant":[
        "Dikli\u0107i"
    ],
    "wof:name":"Diklici",
    "wof:placetype":"locality"
},
  "geometry": {"coordinates":[18.09529,42.78041],"type":"Point"}
}