{
  "type": "Feature",
  "properties": {
    "gn:admin1_code":"02",
    "gn:asciiname":"Gornja Lepenica",
    "gn:country_code":"BA",
    "gn:dem":184,
    "gn:feature_class":"P",
    "gn:feature_code":"PPLL",
    "gn:name":"Gornja Lepenica",
    "gn:population":0,
    "gn:timezone":"Europe/Sarajevo",
    "iso:country":"BA",
    "name:und_x_variant":[
        "Lepenica",
        "Gornja Lepenica"
    ],
    "wof:name":"Gornja Lepenica",
    "wof:placetype":"locality"
},
  "geometry": {"coordinates":[17.65979,45.03279000000001],"type":"Point"}
}