{
  "type": "Feature",
  "properties": {
    "gn:admin1_code":"01",
    "gn:asciiname":"Ulog",
    "gn:country_code":"BA",
    "gn:dem":97,
    "gn:feature_class":"P",
    "gn:feature_code":"PPL",
    "gn:name":"Ulog",
    "gn:population":0,
    "gn:timezone":"Europe/Sarajevo",
    "iso:country":"BA",
    "name:bos_x_preferred":[
        "Ulog"
    ],
    "name:fra_x_preferred":[
        "Ulog"
    ],
    "name:hrv_x_preferred":[
        "Ulog"
    ],
    "name:srp_x_preferred":[
        "\u0423\u043b\u043e\u0433"
    ],
    "wof:name":"Ulog",
    "wof:placetype":"locality"
},
  "geometry": {"coordinates":[17.78646,43.3075],"type":"Point"}
}