{
  "type": "Feature",
  "properties": {
    "gn:admin1_code":"01",
    "gn:asciiname":"Kaici",
    "gn:country_code":"BA",
    "gn:dem":622,
    "gn:feature_class":"P",
    "gn:feature_code":"PPL",
    "gn:name":"Kai\u0107i",
    "gn:population":0,
    "gn:timezone":"Europe/Sarajevo",
    "iso:country":"BA",
    "wof:name":"Kaici",
    "wof:placetype":"locality"
},
  "geometry": {"coordinates":[17.47317,44.05031],"type":"Point"}
}