{
  "type": "Feature",
  "properties": {
    "gn:admin1_code":"02",
    "gn:asciiname":"Slisci",
    "gn:country_code":"BA",
    "gn:dem":214,
    "gn:feature_class":"P",
    "gn:feature_code":"PPL",
    "gn:name":"Sli\u0161ci",
    "gn:population":0,
    "gn:timezone":"Europe/Sarajevo",
    "iso:country":"BA",
    "wof:name":"Slisci",
    "wof:placetype":"locality"
},
  "geometry": {"coordinates":[18.0135,44.90492],"type":"Point"}
}