{
  "type": "Feature",
  "properties": {
    "gn:admin1_code":"02",
    "gn:asciiname":"Skorlin",
    "gn:country_code":"BA",
    "gn:dem":1108,
    "gn:feature_class":"P",
    "gn:feature_code":"PPL",
    "gn:name":"Skorlin",
    "gn:population":0,
    "gn:timezone":"Europe/Sarajevo",
    "iso:country":"BA",
    "wof:name":"Skorlin",
    "wof:placetype":"locality"
},
  "geometry": {"coordinates":[18.80226,44.02817],"type":"Point"}
}