{
  "type": "Feature",
  "properties": {
    "gn:admin1_code":"02",
    "gn:asciiname":"Majkici",
    "gn:country_code":"BA",
    "gn:dem":210,
    "gn:feature_class":"P",
    "gn:feature_code":"PPL",
    "gn:name":"Majki\u0107i",
    "gn:population":0,
    "gn:timezone":"Europe/Sarajevo",
    "iso:country":"BA",
    "wof:name":"Majkici",
    "wof:placetype":"locality"
},
  "geometry": {"coordinates":[16.4693,44.98341],"type":"Point"}
}