{
  "type": "Feature",
  "properties": {
    "gn:admin1_code":"02",
    "gn:asciiname":"Dolovi",
    "gn:country_code":"BA",
    "gn:dem":760,
    "gn:feature_class":"P",
    "gn:feature_code":"PPL",
    "gn:name":"Dolovi",
    "gn:population":0,
    "gn:timezone":"Europe/Sarajevo",
    "iso:country":"BA",
    "wof:name":"Dolovi",
    "wof:placetype":"locality"
},
  "geometry": {"coordinates":[19.14851,43.74703],"type":"Point"}
}