{
  "type": "Feature",
  "properties": {
    "gn:admin1_code":"01",
    "gn:asciiname":"Kruscica",
    "gn:country_code":"BA",
    "gn:dem":459,
    "gn:feature_class":"P",
    "gn:feature_code":"PPL",
    "gn:name":"Kru\u0161\u010dica",
    "gn:population":0,
    "gn:timezone":"Europe/Sarajevo",
    "iso:country":"BA",
    "wof:name":"Kruscica",
    "wof:placetype":"locality"
},
  "geometry": {"coordinates":[17.78758,44.13527],"type":"Point"}
}