{
  "type": "Feature",
  "properties": {
    "gn:admin1_code":"01",
    "gn:asciiname":"Cuzici",
    "gn:country_code":"BA",
    "gn:dem":80,
    "gn:feature_class":"P",
    "gn:feature_code":"PPL",
    "gn:name":"Cu\u017ei\u0107i",
    "gn:population":0,
    "gn:timezone":"Europe/Sarajevo",
    "iso:country":"BA",
    "wof:name":"Cuzici",
    "wof:placetype":"locality"
},
  "geometry": {"coordinates":[17.57391,43.14371],"type":"Point"}
}