{
  "type": "Feature",
  "properties": {
    "gn:admin1_code":"02",
    "gn:asciiname":"Jelovci",
    "gn:country_code":"BA",
    "gn:dem":1024,
    "gn:feature_class":"P",
    "gn:feature_code":"PPL",
    "gn:name":"Jelovci",
    "gn:population":0,
    "gn:timezone":"Europe/Sarajevo",
    "iso:country":"BA",
    "wof:name":"Jelovci",
    "wof:placetype":"locality"
},
  "geometry": {"coordinates":[19.0255,44.03025],"type":"Point"}
}