{
  "type": "Feature",
  "properties": {
    "gn:admin1_code":"02",
    "gn:asciiname":"Nedici",
    "gn:country_code":"BA",
    "gn:dem":1072,
    "gn:feature_class":"P",
    "gn:feature_code":"PPL",
    "gn:name":"Nedi\u0107i",
    "gn:population":0,
    "gn:timezone":"Europe/Sarajevo",
    "iso:country":"BA",
    "wof:name":"Nedici",
    "wof:placetype":"locality"
},
  "geometry": {"coordinates":[17.43285,44.46427],"type":"Point"}
}