{
  "type": "Feature",
  "properties": {
    "gn:admin1_code":"01",
    "gn:asciiname":"Stubljaci",
    "gn:country_code":"BA",
    "gn:dem":779,
    "gn:feature_class":"P",
    "gn:feature_code":"PPL",
    "gn:name":"Stubljaci",
    "gn:population":0,
    "gn:timezone":"Europe/Sarajevo",
    "iso:country":"BA",
    "wof:name":"Stubljaci",
    "wof:placetype":"locality"
},
  "geometry": {"coordinates":[18.25335,43.48078],"type":"Point"}
}