{
  "type": "Feature",
  "properties": {
    "gn:admin1_code":"01",
    "gn:asciiname":"Brdo",
    "gn:country_code":"BA",
    "gn:dem":780,
    "gn:feature_class":"P",
    "gn:feature_code":"PPL",
    "gn:name":"Brdo",
    "gn:population":0,
    "gn:timezone":"Europe/Sarajevo",
    "iso:country":"BA",
    "name:bos_x_preferred":[
        "Brdo"
    ],
    "name:ceb_x_preferred":[
        "Brdo"
    ],
    "name:ces_x_preferred":[
        "Brdo"
    ],
    "name:deu_x_preferred":[
        "Brdo"
    ],
    "name:fra_x_preferred":[
        "Brdo"
    ],
    "name:hrv_x_preferred":[
        "Brdo"
    ],
    "name:hun_x_preferred":[
        "Brdo"
    ],
    "name:nld_x_preferred":[
        "Brdo"
    ],
    "name:pol_x_preferred":[
        "Brdo"
    ],
    "name:slv_x_preferred":[
        "Brdo"
    ],
    "name:srp_x_preferred":[
        "\u0411\u0440\u0434\u043e"
    ],
    "name:swe_x_preferred":[
        "Brdo"
    ],
    "name:ukr_x_preferred":[
        "\u0411\u0440\u0434\u043e"
    ],
    "wof:name":"Brdo",
    "wof:placetype":"locality"
},
  "geometry": {"coordinates":[18.13278,43.93639],"type":"Point"}
}