{
  "type": "Feature",
  "properties": {
    "gn:admin1_code":"02",
    "gn:asciiname":"Milecanica",
    "gn:country_code":"BA",
    "gn:dem":213,
    "gn:feature_class":"P",
    "gn:feature_code":"PPLL",
    "gn:name":"Mile\u010danica",
    "gn:population":0,
    "gn:timezone":"Europe/Sarajevo",
    "iso:country":"BA",
    "name:und_x_variant":[
        "Mlje\u010danica",
        "Mile\u010danica"
    ],
    "wof:name":"Milecanica",
    "wof:placetype":"locality"
},
  "geometry": {"coordinates":[16.75136,45.09044],"type":"Point"}
}