{
  "type": "Feature",
  "properties": {
    "gn:country":"BA",
    "gn:fcode":"PPL",
    "gn:pop":13551,
    "iso:country":"BA",
    "name:bos_x_preferred":[
        "Sanski Most"
    ],
    "name:bul_x_preferred":[
        "\u0421\u0430\u043d\u0441\u043a\u0438 \u043c\u043e\u0441\u0442"
    ],
    "name:cat_x_preferred":[
        "Sanski Most"
    ],
    "name:ces_x_preferred":[
        "Sanski Most"
    ],
    "name:dan_x_preferred":[
        "Sanski Most"
    ],
    "name:deu_x_preferred":[
        "Sanski Most"
    ],
    "name:eng_x_preferred":[
        "Sanski Most"
    ],
    "name:fao_x_preferred":[
        "Sanski Most"
    ],
    "name:fra_x_preferred":[
        "Sanski Most"
    ],
    "name:hbs_x_preferred":[
        "Sanski Most"
    ],
    "name:hrv_x_preferred":[
        "Sanski Most"
    ],
    "name:ile_x_preferred":[
        "Sanski Most"
    ],
    "name:ita_x_preferred":[
        "Sanski Most"
    ],
    "name:jav_x_preferred":[
        "Sanski Most"
    ],
    "name:jpn_x_preferred":[
        "\u30b5\u30f3\u30b9\u30ad\u30fb\u30e2\u30b9\u30c8"
    ],
    "name:kor_x_preferred":[
        "\uc0b0\uc2a4\ud0a4\ubaa8\uc2a4\ud2b8"
    ],
    "name:lit_x_preferred":[
        "Sanski Mostas"
    ],
    "name:mkd_x_preferred":[
        "\u0421\u0430\u043d\u0441\u043a\u0438 \u041c\u043e\u0441\u0442"
    ],
    "name:nld_x_preferred":[
        "Sanski Most"
    ],
    "name:pol_x_preferred":[
        "Sanski Most"
    ],
    "name:rus_x_preferred":[
        "\u0421\u0430\u043d\u0441\u043a\u0438-\u041c\u043e\u0441\u0442"
    ],
    "name:slv_x_preferred":[
        "Sanski Most"
    ],
    "name:spa_x_preferred":[
        "Sanski Most"
    ],
    "name:sqi_x_preferred":[
        "Sanski Most"
    ],
    "name:srp_x_preferred":[
        "\u0421\u0430\u043d\u0441\u043a\u0438 \u041c\u043e\u0441\u0442"
    ],
    "name:swe_x_preferred":[
        "Sanski Most"
    ],
    "name:tat_x_preferred":[
        "\u0421\u0430\u043d\u0441\u043a\u0438-\u041c\u043e\u0441\u0442"
    ],
    "name:tur_x_preferred":[
        "Sanski Most"
    ],
    "name:unk_x_variant":[
        "Sana"
    ],
    "name:urd_x_preferred":[
        "\u0633\u0627\u0646\u0633\u06a9\u06cc \u0645\u0648\u0633\u0679"
    ],
    "name:zho_x_preferred":[
        "\u6851\u65af\u57fa\u83ab\u65af\u7279"
    ],
    "qs:name":"Sanski Most",
    "qs:name_adm0":"Bosna i Hercegovina",
    "qs:name_adm1":"Federacija Bosne I Hercegovine",
    "qs:photos":88,
    "qs:photos_1k":18,
    "qs:photos_9k":1,
    "qs:photos_9r":3,
    "qs:photos_all":88,
    "qs:photos_sr":3,
    "qs:placetype":"Town",
    "qs:pop_sr":"6",
    "wd:wordcount":485,
    "wof:name":"Sanski Most",
    "wof:placetype":"locality",
    "wof:population":13551
},
  "geometry": {"coordinates":[16.667,44.7667],"type":"Point"}
}