{
  "type": "Feature",
  "properties": {
    "gn:admin1_code":"02",
    "gn:asciiname":"Gornji Ruzevic",
    "gn:country_code":"BA",
    "gn:dem":274,
    "gn:feature_class":"P",
    "gn:feature_code":"PPLL",
    "gn:name":"Gornji Ru\u017eevi\u0107",
    "gn:population":0,
    "gn:timezone":"Europe/Sarajevo",
    "iso:country":"BA",
    "name:und_x_variant":[
        "Ru\u017eevici Gornji",
        "Gornji Ru\u017eevi\u0107i",
        "Gornji Ru\u017eevi\u0107"
    ],
    "wof:name":"Gornji Ruzevic",
    "wof:placetype":"locality"
},
  "geometry": {"coordinates":[17.82176,44.6158],"type":"Point"}
}