{
  "type": "Feature",
  "properties": {
    "gn:admin1_code":"01",
    "gn:asciiname":"Popov Do",
    "gn:country_code":"BA",
    "gn:dem":406,
    "gn:feature_class":"P",
    "gn:feature_code":"PPL",
    "gn:name":"Popov Do",
    "gn:population":0,
    "gn:timezone":"Europe/Sarajevo",
    "iso:country":"BA",
    "name:fra_x_preferred":[
        "Popov Do"
    ],
    "name:ron_x_preferred":[
        "Popov Do"
    ],
    "name:slv_x_preferred":[
        "Popov Do"
    ],
    "name:srp_x_preferred":[
        "\u041f\u043e\u043f\u043e\u0432 \u0414\u043e"
    ],
    "wof:name":"Popov Do",
    "wof:placetype":"locality"
},
  "geometry": {"coordinates":[18.96862,43.67742],"type":"Point"}
}