{
  "type": "Feature",
  "properties": {
    "gn:admin1_code":"02",
    "gn:asciiname":"Cerovi Do",
    "gn:country_code":"BA",
    "gn:dem":901,
    "gn:feature_class":"P",
    "gn:feature_code":"PPL",
    "gn:name":"Cerovi Do",
    "gn:population":0,
    "gn:timezone":"Europe/Sarajevo",
    "iso:country":"BA",
    "wof:name":"Cerovi Do",
    "wof:placetype":"locality"
},
  "geometry": {"coordinates":[18.50388,42.65681],"type":"Point"}
}