{
  "type": "Feature",
  "properties": {
    "gn:admin1_code":"01",
    "gn:asciiname":"Ricina",
    "gn:country_code":"BA",
    "gn:dem":891,
    "gn:feature_class":"P",
    "gn:feature_code":"PPL",
    "gn:name":"Ri\u010dina",
    "gn:population":0,
    "gn:timezone":"Europe/Sarajevo",
    "iso:country":"BA",
    "wof:name":"Ricina",
    "wof:placetype":"locality"
},
  "geometry": {"coordinates":[17.46528,43.49417],"type":"Point"}
}