{
  "type": "Feature",
  "properties": {
    "gn:admin1_code":"02",
    "gn:asciiname":"Tulici",
    "gn:country_code":"BA",
    "gn:dem":213,
    "gn:feature_class":"P",
    "gn:feature_code":"PPL",
    "gn:name":"Tuli\u0107i",
    "gn:population":0,
    "gn:timezone":"Europe/Sarajevo",
    "iso:country":"BA",
    "wof:name":"Tulici",
    "wof:placetype":"locality"
},
  "geometry": {"coordinates":[19.08198,44.39899000000001],"type":"Point"}
}