{
  "type": "Feature",
  "properties": {
    "gn:admin1_code":"02",
    "gn:asciiname":"Moconji",
    "gn:country_code":"BA",
    "gn:dem":394,
    "gn:feature_class":"P",
    "gn:feature_code":"PPL",
    "gn:name":"Moconji",
    "gn:population":0,
    "gn:timezone":"Europe/Sarajevo",
    "iso:country":"BA",
    "wof:name":"Moconji",
    "wof:placetype":"locality"
},
  "geometry": {"coordinates":[17.105,44.74583],"type":"Point"}
}