{
  "type": "Feature",
  "properties": {
    "gn:admin1_code":"02",
    "gn:asciiname":"Alagici",
    "gn:country_code":"BA",
    "gn:dem":243,
    "gn:feature_class":"P",
    "gn:feature_code":"PPL",
    "gn:name":"Alagi\u0107i",
    "gn:population":0,
    "gn:timezone":"Europe/Sarajevo",
    "iso:country":"BA",
    "wof:name":"Alagici",
    "wof:placetype":"locality"
},
  "geometry": {"coordinates":[17.86932000000001,44.61145],"type":"Point"}
}