{
  "type": "Feature",
  "properties": {
    "gn:admin1_code":"02",
    "gn:asciiname":"Gornji Mackovac",
    "gn:country_code":"BA",
    "gn:dem":360,
    "gn:feature_class":"P",
    "gn:feature_code":"PPL",
    "gn:name":"Gornji Ma\u010dkovac",
    "gn:population":0,
    "gn:timezone":"Europe/Sarajevo",
    "iso:country":"BA",
    "wof:name":"Gornji Mackovac",
    "wof:placetype":"locality"
},
  "geometry": {"coordinates":[18.7931,44.66509],"type":"Point"}
}