{
  "type": "Feature",
  "properties": {
    "gn:admin1_code":"00",
    "gn:asciiname":"Jelisavci",
    "gn:country_code":"BA",
    "gn:dem":344,
    "gn:feature_class":"P",
    "gn:feature_code":"PPL",
    "gn:name":"Jelisavci",
    "gn:population":0,
    "gn:timezone":"Europe/Sarajevo",
    "iso:country":"BA",
    "wof:name":"Jelisavci",
    "wof:placetype":"locality"
},
  "geometry": {"coordinates":[16.413,44.86362],"type":"Point"}
}