{
  "type": "Feature",
  "properties": {
    "gn:admin1_code":"01",
    "gn:asciiname":"Rasavci",
    "gn:country_code":"BA",
    "gn:dem":977,
    "gn:feature_class":"P",
    "gn:feature_code":"PPLL",
    "gn:name":"Rasavci",
    "gn:population":0,
    "gn:timezone":"Europe/Sarajevo",
    "iso:country":"BA",
    "name:bos_x_preferred":[
        "Rasavci"
    ],
    "name:fra_x_preferred":[
        "Rasavci"
    ],
    "name:srp_x_preferred":[
        "\u0420\u0430\u0441\u0430\u0432\u0446\u0438"
    ],
    "wof:name":"Rasavci",
    "wof:placetype":"locality"
},
  "geometry": {"coordinates":[17.33152,44.16849000000001],"type":"Point"}
}