{
  "type": "Feature",
  "properties": {
    "gn:admin1_code":"02",
    "gn:asciiname":"Mirkovici",
    "gn:country_code":"BA",
    "gn:dem":367,
    "gn:feature_class":"P",
    "gn:feature_code":"PPL",
    "gn:name":"Mirkovi\u0107i",
    "gn:population":0,
    "gn:timezone":"Europe/Sarajevo",
    "iso:country":"BA",
    "wof:name":"Mirkovici",
    "wof:placetype":"locality"
},
  "geometry": {"coordinates":[18.96833,44.6425],"type":"Point"}
}