{
  "type": "Feature",
  "properties": {
    "gn:admin1_code":"02",
    "gn:asciiname":"Sokolovici",
    "gn:country_code":"BA",
    "gn:dem":1024,
    "gn:feature_class":"P",
    "gn:feature_code":"PPL",
    "gn:name":"Sokolovi\u0107i",
    "gn:population":0,
    "gn:timezone":"Europe/Sarajevo",
    "iso:country":"BA",
    "wof:name":"Sokolovici",
    "wof:placetype":"locality"
},
  "geometry": {"coordinates":[18.86236,44.03059],"type":"Point"}
}