{
  "type": "Feature",
  "properties": {
    "gn:admin1_code":"02",
    "gn:asciiname":"Siljkovo Brdo",
    "gn:country_code":"BA",
    "gn:dem":226,
    "gn:feature_class":"P",
    "gn:feature_code":"PPL",
    "gn:name":"\u0160iljkovo Brdo",
    "gn:population":0,
    "gn:timezone":"Europe/Sarajevo",
    "iso:country":"BA",
    "wof:name":"Siljkovo Brdo",
    "wof:placetype":"locality"
},
  "geometry": {"coordinates":[17.38485,44.75526],"type":"Point"}
}