{
  "type": "Feature",
  "properties": {
    "gn:admin1_code":"02",
    "gn:asciiname":"Potocari",
    "gn:country_code":"BA",
    "gn:dem":132,
    "gn:feature_class":"P",
    "gn:feature_code":"PPL",
    "gn:name":"Poto\u010dari",
    "gn:population":0,
    "gn:timezone":"Europe/Sarajevo",
    "iso:country":"BA",
    "wof:name":"Potocari",
    "wof:placetype":"locality"
},
  "geometry": {"coordinates":[18.55148,44.83918],"type":"Point"}
}