{
  "type": "Feature",
  "properties": {
    "gn:admin1_code":"02",
    "gn:asciiname":"Bodenik",
    "gn:country_code":"BA",
    "gn:dem":853,
    "gn:feature_class":"P",
    "gn:feature_code":"PPL",
    "gn:name":"Bodenik",
    "gn:population":0,
    "gn:timezone":"Europe/Sarajevo",
    "iso:country":"BA",
    "name:bos_x_preferred":[
        "Bodenik"
    ],
    "name:fra_x_preferred":[
        "Bodenik"
    ],
    "name:rus_x_preferred":[
        "\u0411\u043e\u0434\u0435\u043d\u0438\u043a"
    ],
    "name:slv_x_preferred":[
        "Bodenik"
    ],
    "name:srp_x_preferred":[
        "\u0411\u043e\u0434\u0435\u043d\u0438\u043a"
    ],
    "wof:name":"Bodenik",
    "wof:placetype":"locality"
},
  "geometry": {"coordinates":[18.35707,42.91108],"type":"Point"}
}