{
  "type": "Feature",
  "properties": {
    "gn:admin1_code":"BRC",
    "gn:asciiname":"Ribic",
    "gn:country_code":"BA",
    "gn:dem":210,
    "gn:feature_class":"P",
    "gn:feature_code":"PPL",
    "gn:name":"Ribi\u0107",
    "gn:population":0,
    "gn:timezone":"Europe/Sarajevo",
    "iso:country":"BA",
    "wof:name":"Ribic",
    "wof:placetype":"locality"
},
  "geometry": {"coordinates":[18.75866,44.77372],"type":"Point"}
}