{
  "type": "Feature",
  "properties": {
    "gn:admin1_code":"02",
    "gn:asciiname":"Golobrde",
    "gn:country_code":"BA",
    "gn:dem":971,
    "gn:feature_class":"P",
    "gn:feature_code":"PPL",
    "gn:name":"Golobr\u0111e",
    "gn:population":0,
    "gn:timezone":"Europe/Sarajevo",
    "iso:country":"BA",
    "name:bos_x_preferred":[
        "Golobr\u0111e"
    ],
    "name:fra_x_preferred":[
        "Golobr\u0111e"
    ],
    "name:rus_x_preferred":[
        "\u0413\u043e\u043b\u043e\u0431\u0440\u0434\u0436\u0435"
    ],
    "name:slv_x_preferred":[
        "Golobr\u0111e"
    ],
    "name:srp_x_preferred":[
        "\u0413\u043e\u043b\u043e\u0431\u0440\u0452\u0435"
    ],
    "name:und_x_variant":[
        "Golobrdje"
    ],
    "wof:name":"Golobrde",
    "wof:placetype":"locality"
},
  "geometry": {"coordinates":[18.47909,42.98617],"type":"Point"}
}