{
  "type": "Feature",
  "properties": {
    "gn:admin1_code":"02",
    "gn:asciiname":"Grlici",
    "gn:country_code":"BA",
    "gn:dem":227,
    "gn:feature_class":"P",
    "gn:feature_code":"PPL",
    "gn:name":"Grli\u0107i",
    "gn:population":0,
    "gn:timezone":"Europe/Sarajevo",
    "iso:country":"BA",
    "wof:name":"Grlici",
    "wof:placetype":"locality"
},
  "geometry": {"coordinates":[18.01395,44.85086],"type":"Point"}
}