{
  "type": "Feature",
  "properties": {
    "gn:admin1_code":"01",
    "gn:asciiname":"Colopeci",
    "gn:country_code":"BA",
    "gn:dem":648,
    "gn:feature_class":"P",
    "gn:feature_code":"PPL",
    "gn:name":"\u010colopeci",
    "gn:population":0,
    "gn:timezone":"Europe/Sarajevo",
    "iso:country":"BA",
    "wof:name":"Colopeci",
    "wof:placetype":"locality"
},
  "geometry": {"coordinates":[17.89108,43.71372],"type":"Point"}
}