{
  "type": "Feature",
  "properties": {
    "gn:admin1_code":"01",
    "gn:asciiname":"Sokolice",
    "gn:country_code":"BA",
    "gn:dem":792,
    "gn:feature_class":"P",
    "gn:feature_code":"PPL",
    "gn:name":"Sokolice",
    "gn:population":0,
    "gn:timezone":"Europe/Sarajevo",
    "iso:country":"BA",
    "wof:name":"Sokolice",
    "wof:placetype":"locality"
},
  "geometry": {"coordinates":[18.17607000000001,43.51193],"type":"Point"}
}