{
  "type": "Feature",
  "properties": {
    "gn:country":"BA",
    "gn:fcode":"PPL",
    "gn:pop":5062,
    "iso:country":"BA",
    "name:bos_x_preferred":[
        "Mahala"
    ],
    "name:bul_x_preferred":[
        "\u041c\u0430\u0445\u0430\u043b\u0430"
    ],
    "name:ces_x_preferred":[
        "Mahala"
    ],
    "name:eng_x_preferred":[
        "Mahala"
    ],
    "name:fas_x_preferred":[
        "\u0645\u062d\u0644\u0647"
    ],
    "name:mkd_x_preferred":[
        "\u043c\u0430\u0430\u043b\u043e"
    ],
    "name:rus_x_preferred":[
        "\u043c\u0430\u0445\u0430\u043b\u0430"
    ],
    "name:srp_x_preferred":[
        "\u041c\u0430\u0445\u0430\u043b\u0430"
    ],
    "qs:name":"Mahala",
    "qs:photos_9r":0,
    "qs:photos_sr":0,
    "qs:pop_sr":"5",
    "wd:wordcount":330,
    "wof:name":"Mahala",
    "wof:placetype":"locality",
    "wof:population":5062
},
  "geometry": {"coordinates":[18.25528,44.01194],"type":"Point"}
}