{
  "type": "Feature",
  "properties": {
    "gn:country":"BA",
    "gn:fcode":"PPL",
    "gn:population":5062,
    "iso:country":"BA",
    "name:ara_x_preferred":[
        "\u0645\u062d\u0644\u0629"
    ],
    "name:aze_x_preferred":[
        "M\u0259h\u0259ll\u0259"
    ],
    "name:bak_x_preferred":[
        "\u041c\u04d9\u0445\u04d9\u043b\u043b\u04d9"
    ],
    "name:bos_x_preferred":[
        "Mahala"
    ],
    "name:bul_x_preferred":[
        "\u041c\u0430\u0445\u0430\u043b\u0430"
    ],
    "name:cat_x_preferred":[
        "mahalle"
    ],
    "name:ces_x_preferred":[
        "Mahala"
    ],
    "name:dan_x_preferred":[
        "mahallah"
    ],
    "name:deu_x_preferred":[
        "Mahalla"
    ],
    "name:ell_x_preferred":[
        "\u03bc\u03b1\u03c7\u03b1\u03bb\u03ac\u03c2"
    ],
    "name:eng_x_preferred":[
        "Mahala"
    ],
    "name:eng_x_variant":[
        "mahallah"
    ],
    "name:fas_x_preferred":[
        "\u0645\u062d\u0644\u0647"
    ],
    "name:hrv_x_preferred":[
        "Mahala"
    ],
    "name:hsb_x_preferred":[
        "mahala"
    ],
    "name:hye_x_preferred":[
        "\u0544\u0561\u0570\u0561\u056c"
    ],
    "name:ita_x_preferred":[
        "mahallah"
    ],
    "name:jpn_x_preferred":[
        "\u30de\u30cf\u30c3\u30e9"
    ],
    "name:mal_x_preferred":[
        "\u0d2e\u0d39\u0d32\u0d4d\u0d32\u0d4d"
    ],
    "name:mkd_x_preferred":[
        "\u043c\u0430\u0430\u043b\u043e"
    ],
    "name:nob_x_preferred":[
        "mahallah"
    ],
    "name:pnb_x_preferred":[
        "\u0645\u062d\u0644\u06c1"
    ],
    "name:por_x_preferred":[
        "mahalla"
    ],
    "name:ron_x_preferred":[
        "Mahala"
    ],
    "name:rus_x_preferred":[
        "\u043c\u0430\u0445\u0430\u043b\u0430"
    ],
    "name:rus_x_variant":[
        "\u043c\u0430\u0445\u0430\u043b\u043b\u044f"
    ],
    "name:spa_x_preferred":[
        "mahalla"
    ],
    "name:sqi_x_preferred":[
        "M\u00ebhalla"
    ],
    "name:srp_x_preferred":[
        "\u041c\u0430\u0445\u0430\u043b\u0430"
    ],
    "name:srp_x_variant":[
        "\u043c\u0430\u0445\u0430\u043b\u0430"
    ],
    "name:tat_x_preferred":[
        "\u041c\u04d9\u0445\u04d9\u043b\u043b\u04d9"
    ],
    "name:tur_x_preferred":[
        "mahalle"
    ],
    "name:ukr_x_preferred":[
        "\u043c\u0430\u0445\u0430\u043b\u043b\u044f"
    ],
    "name:urd_x_preferred":[
        "\u0645\u062d\u0644\u06c1"
    ],
    "name:uzb_x_preferred":[
        "Mahalla"
    ],
    "qs:name":"Mahala",
    "qs:photos_9r":0,
    "qs:photos_sr":0,
    "qs:pop_sr":"5",
    "wd:wordcount":330,
    "wof:name":"Mahala",
    "wof:placetype":"locality",
    "wof:population":5062
},
  "geometry": {"coordinates":[18.25528,44.01194],"type":"Point"}
}