{
  "type": "Feature",
  "properties": {
    "gn:country":"BA",
    "gn:fcode":"PPL",
    "gn:pop":5062,
    "iso:country":"BA",
    "qs:name":"Mahala",
    "qs:photos_9r":0,
    "qs:photos_sr":0,
    "qs:pop_sr":"5",
    "wd:wordcount":330,
    "wof:name":"Mahala",
    "wof:placetype":"locality",
    "wof:population":5062
},
  "geometry": {"coordinates":[18.25528,44.01194],"type":"Point"}
}