{
  "type": "Feature",
  "properties": {
    "gn:admin1_code":"02",
    "gn:asciiname":"Grede",
    "gn:country_code":"BA",
    "gn:dem":84,
    "gn:feature_class":"P",
    "gn:feature_code":"PPL",
    "gn:name":"Grede",
    "gn:population":0,
    "gn:timezone":"Europe/Sarajevo",
    "iso:country":"BA",
    "wof:name":"Grede",
    "wof:placetype":"locality"
},
  "geometry": {"coordinates":[18.00097000000001,45.11903],"type":"Point"}
}