{
  "type": "Feature",
  "properties": {
    "gn:admin1_code":"02",
    "gn:asciiname":"Savkovica Do",
    "gn:country_code":"BA",
    "gn:dem":966,
    "gn:feature_class":"P",
    "gn:feature_code":"PPL",
    "gn:name":"Savkovi\u0107a Do",
    "gn:population":0,
    "gn:timezone":"Europe/Sarajevo",
    "iso:country":"BA",
    "wof:name":"Savkovica Do",
    "wof:placetype":"locality"
},
  "geometry": {"coordinates":[17.22061,44.13481],"type":"Point"}
}