{
  "type": "Feature",
  "properties": {
    "gn:admin1_code":"02",
    "gn:asciiname":"Kasindo",
    "gn:country_code":"BA",
    "gn:dem":586,
    "gn:feature_class":"P",
    "gn:feature_code":"PPLL",
    "gn:name":"Kasindo",
    "gn:population":0,
    "gn:timezone":"Europe/Sarajevo",
    "iso:country":"BA",
    "name:bos_x_preferred":[
        "Kasindo"
    ],
    "name:ceb_x_preferred":[
        "Kasindo"
    ],
    "name:fra_x_preferred":[
        "Kasindo"
    ],
    "name:hrv_x_preferred":[
        "Kasindo"
    ],
    "name:pol_x_preferred":[
        "Kasindo"
    ],
    "name:srp_x_preferred":[
        "\u041a\u0430\u0441\u0438\u043d\u0434\u043e"
    ],
    "name:swe_x_preferred":[
        "Kasindo"
    ],
    "name:und_x_variant":[
        "Kobiljdo-Kasindo"
    ],
    "wof:name":"Kasindo",
    "wof:placetype":"locality"
},
  "geometry": {"coordinates":[18.38847,43.79793],"type":"Point"}
}