{
  "type": "Feature",
  "properties": {
    "gn:admin1_code":"02",
    "gn:asciiname":"Kasindo",
    "gn:country_code":"BA",
    "gn:dem":586,
    "gn:feature_class":"P",
    "gn:feature_code":"PPLL",
    "gn:name":"Kasindo",
    "gn:population":0,
    "gn:timezone":"Europe/Sarajevo",
    "iso:country":"BA",
    "name:und_x_variant":[
        "Kobiljdo-Kasindo",
        "Kasindo"
    ],
    "wof:name":"Kasindo",
    "wof:placetype":"locality"
},
  "geometry": {"coordinates":[18.38847,43.79793],"type":"Point"}
}