{
  "type": "Feature",
  "properties": {
    "gn:admin1_code":"02",
    "gn:asciiname":"Kosa",
    "gn:country_code":"BA",
    "gn:dem":298,
    "gn:feature_class":"P",
    "gn:feature_code":"PPL",
    "gn:name":"Kosa",
    "gn:population":0,
    "gn:timezone":"Europe/Sarajevo",
    "iso:country":"BA",
    "name:swe_x_preferred":[
        "Kosa"
    ],
    "wof:name":"Kosa",
    "wof:placetype":"locality"
},
  "geometry": {"coordinates":[18.98023,44.63575],"type":"Point"}
}