{
  "type": "Feature",
  "properties": {
    "gn:admin1_code":"00",
    "gn:asciiname":"Mujanovici",
    "gn:country_code":"BA",
    "gn:dem":340,
    "gn:feature_class":"P",
    "gn:feature_code":"PPL",
    "gn:name":"Mujanovi\u0107i",
    "gn:population":0,
    "gn:timezone":"Europe/Sarajevo",
    "iso:country":"BA",
    "wof:name":"Mujanovici",
    "wof:placetype":"locality"
},
  "geometry": {"coordinates":[18.66669,44.36361],"type":"Point"}
}