{
  "type": "Feature",
  "properties": {
    "gn:admin1_code":"02",
    "gn:asciiname":"Donja Topola",
    "gn:country_code":"BA",
    "gn:dem":97,
    "gn:feature_class":"P",
    "gn:feature_code":"PPL",
    "gn:name":"Donja Topola",
    "gn:population":0,
    "gn:timezone":"Europe/Sarajevo",
    "iso:country":"BA",
    "wof:name":"Donja Topola",
    "wof:placetype":"locality"
},
  "geometry": {"coordinates":[17.3083,45.06513],"type":"Point"}
}