{
  "type": "Feature",
  "properties": {
    "gn:admin1_code":"01",
    "gn:asciiname":"Zupa",
    "gn:country_code":"BA",
    "gn:dem":649,
    "gn:feature_class":"P",
    "gn:feature_code":"PPLL",
    "gn:name":"\u017dupa",
    "gn:population":0,
    "gn:timezone":"Europe/Sarajevo",
    "iso:country":"BA",
    "wof:name":"Zupa",
    "wof:placetype":"locality"
},
  "geometry": {"coordinates":[16.54128,44.27749],"type":"Point"}
}