{
  "type": "Feature",
  "properties": {
    "gn:admin1_code":"01",
    "gn:asciiname":"Kajisi",
    "gn:country_code":"BA",
    "gn:dem":393,
    "gn:feature_class":"P",
    "gn:feature_code":"PPL",
    "gn:name":"Kaji\u0161i",
    "gn:population":0,
    "gn:timezone":"Europe/Sarajevo",
    "iso:country":"BA",
    "wof:name":"Kajisi",
    "wof:placetype":"locality"
},
  "geometry": {"coordinates":[16.82942,44.54962],"type":"Point"}
}