{
  "type": "Feature",
  "properties": {
    "gn:admin1_code":"02",
    "gn:asciiname":"Orah",
    "gn:country_code":"BA",
    "gn:dem":890,
    "gn:feature_class":"P",
    "gn:feature_code":"PPL",
    "gn:name":"Orah",
    "gn:population":0,
    "gn:timezone":"Europe/Sarajevo",
    "iso:country":"BA",
    "wof:name":"Orah",
    "wof:placetype":"locality"
},
  "geometry": {"coordinates":[19.34639,43.68278],"type":"Point"}
}