{
  "type": "Feature",
  "properties": {
    "gn:admin1_code":"01",
    "gn:asciiname":"Gecet",
    "gn:country_code":"BA",
    "gn:dem":309,
    "gn:feature_class":"P",
    "gn:feature_code":"PPL",
    "gn:name":"Ge\u010det",
    "gn:population":0,
    "gn:timezone":"Europe/Sarajevo",
    "iso:country":"BA",
    "wof:name":"Gecet",
    "wof:placetype":"locality"
},
  "geometry": {"coordinates":[16.10056,44.56667],"type":"Point"}
}