{
  "type": "Feature",
  "properties": {
    "gn:admin1_code":"02",
    "gn:asciiname":"Vasiljevici",
    "gn:country_code":"BA",
    "gn:dem":742,
    "gn:feature_class":"P",
    "gn:feature_code":"PPL",
    "gn:name":"Vasiljevi\u0107i",
    "gn:population":0,
    "gn:timezone":"Europe/Sarajevo",
    "iso:country":"BA",
    "wof:name":"Vasiljevici",
    "wof:placetype":"locality"
},
  "geometry": {"coordinates":[16.79389,44.43194],"type":"Point"}
}