{
  "type": "Feature",
  "properties": {
    "gn:admin1_code":"02",
    "gn:asciiname":"Orasje Povrs",
    "gn:country_code":"BA",
    "gn:dem":355,
    "gn:feature_class":"P",
    "gn:feature_code":"PPL",
    "gn:name":"Ora\u0161je Povr\u0161",
    "gn:population":0,
    "gn:timezone":"Europe/Sarajevo",
    "iso:country":"BA",
    "name:bos_x_preferred":[
        "Ora\u0161je Povr\u0161"
    ],
    "name:fra_x_preferred":[
        "Ora\u0161je Povr\u0161"
    ],
    "name:srp_x_preferred":[
        "\u041e\u0440\u0430\u0448\u0458\u0435 \u041f\u043e\u0432\u0440\u0448"
    ],
    "wof:name":"Orasje Povrs",
    "wof:placetype":"locality"
},
  "geometry": {"coordinates":[18.2675,42.67446],"type":"Point"}
}