{
  "type": "Feature",
  "properties": {
    "gn:admin1_code":"02",
    "gn:asciiname":"Orasje Povrs",
    "gn:country_code":"BA",
    "gn:dem":355,
    "gn:feature_class":"P",
    "gn:feature_code":"PPL",
    "gn:name":"Ora\u0161je Povr\u0161",
    "gn:population":0,
    "gn:timezone":"Europe/Sarajevo",
    "iso:country":"BA",
    "name:und_x_variant":[
        "Ora\u0161je Povr\u0161"
    ],
    "wof:name":"Orasje Povrs",
    "wof:placetype":"locality"
},
  "geometry": {"coordinates":[18.2675,42.67446],"type":"Point"}
}