{
  "type": "Feature",
  "properties": {
    "gn:admin1_code":"02",
    "gn:asciiname":"Bradici",
    "gn:country_code":"BA",
    "gn:dem":484,
    "gn:feature_class":"P",
    "gn:feature_code":"PPL",
    "gn:name":"Bradi\u0107i",
    "gn:population":0,
    "gn:timezone":"Europe/Sarajevo",
    "iso:country":"BA",
    "name:und_x_variant":[
        "Lazi\u0107i",
        "Bradi\u0107i"
    ],
    "wof:name":"Bradici",
    "wof:placetype":"locality"
},
  "geometry": {"coordinates":[19.53959,44.04416],"type":"Point"}
}