{
  "type": "Feature",
  "properties": {
    "gn:admin1_code":"02",
    "gn:asciiname":"Jokici",
    "gn:country_code":"BA",
    "gn:dem":130,
    "gn:feature_class":"P",
    "gn:feature_code":"PPLL",
    "gn:name":"Joki\u0107i",
    "gn:population":0,
    "gn:timezone":"Europe/Sarajevo",
    "iso:country":"BA",
    "name:und_x_variant":[
        "Joki\u0107",
        "Joki\u0107i"
    ],
    "wof:name":"Jokici",
    "wof:placetype":"locality"
},
  "geometry": {"coordinates":[19.06642,44.76964],"type":"Point"}
}