{
  "type": "Feature",
  "properties": {
    "gn:admin1_code":"02",
    "gn:asciiname":"Brkica Potok",
    "gn:country_code":"BA",
    "gn:dem":275,
    "gn:feature_class":"P",
    "gn:feature_code":"PPL",
    "gn:name":"Brki\u010da Potok",
    "gn:population":0,
    "gn:timezone":"Europe/Sarajevo",
    "iso:country":"BA",
    "wof:name":"Brkica Potok",
    "wof:placetype":"locality"
},
  "geometry": {"coordinates":[17.89189,44.57651],"type":"Point"}
}