{
  "type": "Feature",
  "properties": {
    "gn:admin1_code":"01",
    "gn:asciiname":"Orahovica",
    "gn:country_code":"BA",
    "gn:dem":286,
    "gn:feature_class":"P",
    "gn:feature_code":"PPL",
    "gn:name":"Orahovica",
    "gn:population":0,
    "gn:timezone":"Europe/Sarajevo",
    "iso:country":"BA",
    "wof:name":"Orahovica",
    "wof:placetype":"locality"
},
  "geometry": {"coordinates":[17.91568,43.67052],"type":"Point"}
}