{
  "type": "Feature",
  "properties": {
    "gn:admin1_code":"01",
    "gn:asciiname":"Orahovica",
    "gn:country_code":"BA",
    "gn:dem":286,
    "gn:feature_class":"P",
    "gn:feature_code":"PPL",
    "gn:name":"Orahovica",
    "gn:population":0,
    "gn:timezone":"Europe/Sarajevo",
    "iso:country":"BA",
    "name:bos_x_preferred":[
        "Orahovica"
    ],
    "name:ceb_x_preferred":[
        "Orahovica"
    ],
    "name:ces_x_preferred":[
        "Orahovica"
    ],
    "name:ckb_x_preferred":[
        "\u0626\u06c6\u0631\u0627\u062e\u06c6\u06a4\u06cc\u062a\u0633\u0627"
    ],
    "name:deu_x_preferred":[
        "Orahovica"
    ],
    "name:epo_x_preferred":[
        "Orahovica"
    ],
    "name:fas_x_preferred":[
        "\u0627\u0631\u0627\u062e\u0648\u06cc\u062a\u0633\u0627"
    ],
    "name:fra_x_preferred":[
        "Orahovica"
    ],
    "name:glg_x_preferred":[
        "Orahovica"
    ],
    "name:hrv_x_preferred":[
        "Orahovica"
    ],
    "name:hun_x_preferred":[
        "Raholca"
    ],
    "name:ita_x_preferred":[
        "Orahovica"
    ],
    "name:mkd_x_preferred":[
        "\u041e\u0440\u0430\u0445\u043e\u0432\u0438\u0446\u0430"
    ],
    "name:nld_x_preferred":[
        "Orahovica"
    ],
    "name:pol_x_preferred":[
        "Orahovica"
    ],
    "name:ron_x_preferred":[
        "Orahovica"
    ],
    "name:rus_x_preferred":[
        "\u041e\u0440\u0430\u0445\u043e\u0432\u0438\u0446\u0430"
    ],
    "name:slv_x_preferred":[
        "Orahovica"
    ],
    "name:spa_x_preferred":[
        "Orahovica"
    ],
    "name:sqi_x_preferred":[
        "Orahovica"
    ],
    "name:srp_x_preferred":[
        "\u041e\u0440\u0430\u0445\u043e\u0432\u0438\u0446\u0430"
    ],
    "name:swe_x_preferred":[
        "Orahovica"
    ],
    "name:tur_x_preferred":[
        "Rahovi\u00e7e"
    ],
    "name:ukr_x_preferred":[
        "\u041e\u0440\u0430\u0445\u043e\u0432\u0438\u0446\u044f"
    ],
    "name:war_x_preferred":[
        "Orahovica"
    ],
    "name:zho_x_preferred":[
        "\u5967\u62c9\u970d\u7dad\u5bdf"
    ],
    "wof:name":"Orahovica",
    "wof:placetype":"locality"
},
  "geometry": {"coordinates":[17.91568,43.67052],"type":"Point"}
}