{
  "type": "Feature",
  "properties": {
    "gn:admin1_code":"01",
    "gn:asciiname":"Babunovici",
    "gn:country_code":"BA",
    "gn:dem":230,
    "gn:feature_class":"P",
    "gn:feature_code":"PPL",
    "gn:name":"Babunovi\u0107i",
    "gn:population":0,
    "gn:timezone":"Europe/Sarajevo",
    "iso:country":"BA",
    "name:bos_x_preferred":[
        "Babunovi\u0107i"
    ],
    "name:ceb_x_preferred":[
        "Babunovi\u0107i"
    ],
    "name:fra_x_preferred":[
        "Babunovi\u0107i"
    ],
    "name:hrv_x_preferred":[
        "Babunovi\u0107i"
    ],
    "name:swe_x_preferred":[
        "Babunovi\u0107i"
    ],
    "name:und_x_variant":[
        "Babunovi\u0107i"
    ],
    "wof:name":"Babunovici",
    "wof:placetype":"locality"
},
  "geometry": {"coordinates":[18.47361,44.71167],"type":"Point"}
}