{
  "type": "Feature",
  "properties": {
    "gn:admin1_code":"01",
    "gn:asciiname":"Beljani",
    "gn:country_code":"BA",
    "gn:dem":866,
    "gn:feature_class":"P",
    "gn:feature_code":"PPL",
    "gn:name":"Beljani",
    "gn:population":0,
    "gn:timezone":"Europe/Sarajevo",
    "iso:country":"BA",
    "wof:name":"Beljani",
    "wof:placetype":"locality"
},
  "geometry": {"coordinates":[17.12432,43.64117],"type":"Point"}
}