{
  "type": "Feature",
  "properties": {
    "gn:admin1_code":"01",
    "gn:asciiname":"Tuk",
    "gn:country_code":"BA",
    "gn:dem":200,
    "gn:feature_class":"P",
    "gn:feature_code":"PPL",
    "gn:name":"Tuk",
    "gn:population":0,
    "gn:timezone":"Europe/Sarajevo",
    "iso:country":"BA",
    "wof:name":"Tuk",
    "wof:placetype":"locality"
},
  "geometry": {"coordinates":[15.80611,45.17361],"type":"Point"}
}