{
  "type": "Feature",
  "properties": {
    "gn:country":"BA",
    "gn:fcode":"PPL",
    "gn:pop":3987,
    "iso:country":"BA",
    "name:baq_x_preferred":[
        "Dobrinje"
    ],
    "name:bos_x_preferred":[
        "Dobrinje"
    ],
    "name:cat_x_preferred":[
        "Dobrinje"
    ],
    "name:cze_x_preferred":[
        "Dobrinje"
    ],
    "name:dan_x_preferred":[
        "Dobrinje"
    ],
    "name:dut_x_preferred":[
        "Dobrinje"
    ],
    "name:eng_x_preferred":[
        "Dobrinje"
    ],
    "name:fin_x_preferred":[
        "Dobrinje"
    ],
    "name:fre_x_preferred":[
        "Dobrinje"
    ],
    "name:ger_x_preferred":[
        "Dobrinje"
    ],
    "name:hrv_x_preferred":[
        "Dobrinje"
    ],
    "name:ind_x_preferred":[
        "Dobrinje"
    ],
    "name:ita_x_preferred":[
        "Dobrinje"
    ],
    "name:nno_x_preferred":[
        "Dobrinje"
    ],
    "name:nob_x_preferred":[
        "Dobrinje"
    ],
    "name:oci_x_preferred":[
        "Dobrinje"
    ],
    "name:pol_x_preferred":[
        "Dobrinje"
    ],
    "name:por_x_preferred":[
        "Dobrinje"
    ],
    "name:rum_x_preferred":[
        "Dobrinje"
    ],
    "name:slo_x_preferred":[
        "Dobrinje"
    ],
    "name:slv_x_preferred":[
        "Dobrinje"
    ],
    "name:spa_x_preferred":[
        "Dobrinje"
    ],
    "name:swe_x_preferred":[
        "Dobrinje"
    ],
    "name:tgl_x_preferred":[
        "Dobrinje"
    ],
    "name:tur_x_preferred":[
        "Dobrinje"
    ],
    "name:war_x_preferred":[
        "Dobrinje"
    ],
    "qs:name":"Dobrinje",
    "qs:name_adm0":"Bosna i Hercegovina",
    "qs:name_adm1":"Federacija Bosne I Hercegovine",
    "qs:photos_9k":1,
    "qs:photos_9r":1,
    "qs:photos_all":1,
    "qs:photos_sr":0,
    "qs:placetype":"Town",
    "qs:pop_sr":"4",
    "wd:wordcount":69,
    "wof:name":"Dobrinje",
    "wof:placetype":"locality",
    "wof:population":3987
},
  "geometry": {"coordinates":[18.11958,44.05008],"type":"Point"}
}