{
  "type": "Feature",
  "properties": {
    "gn:admin1_code":"02",
    "gn:asciiname":"Donji Tvrdosi",
    "gn:country_code":"BA",
    "gn:dem":317,
    "gn:feature_class":"P",
    "gn:feature_code":"PPL",
    "gn:name":"Donji Tvrdo\u0161i",
    "gn:population":0,
    "gn:timezone":"Europe/Sarajevo",
    "iso:country":"BA",
    "wof:name":"Donji Tvrdosi",
    "wof:placetype":"locality"
},
  "geometry": {"coordinates":[18.28248,42.72209],"type":"Point"}
}