{
  "type": "Feature",
  "properties": {
    "gn:admin1_code":"02",
    "gn:asciiname":"Bukrici",
    "gn:country_code":"BA",
    "gn:dem":639,
    "gn:feature_class":"P",
    "gn:feature_code":"PPL",
    "gn:name":"Bukri\u0107i",
    "gn:population":0,
    "gn:timezone":"Europe/Sarajevo",
    "iso:country":"BA",
    "wof:name":"Bukrici",
    "wof:placetype":"locality"
},
  "geometry": {"coordinates":[18.99192,43.83685],"type":"Point"}
}