{
  "type": "Feature",
  "properties": {
    "gn:admin1_code":"02",
    "gn:asciiname":"Radovici",
    "gn:country_code":"BA",
    "gn:dem":810,
    "gn:feature_class":"P",
    "gn:feature_code":"PPL",
    "gn:name":"Radovi\u0107i",
    "gn:population":0,
    "gn:timezone":"Europe/Sarajevo",
    "iso:country":"BA",
    "wof:name":"Radovici",
    "wof:placetype":"locality"
},
  "geometry": {"coordinates":[18.89361,43.78111],"type":"Point"}
}