{
  "type": "Feature",
  "properties": {
    "gn:admin1_code":"02",
    "gn:asciiname":"Gaj",
    "gn:country_code":"BA",
    "gn:dem":989,
    "gn:feature_class":"P",
    "gn:feature_code":"PPL",
    "gn:name":"Gaj",
    "gn:population":0,
    "gn:timezone":"Europe/Sarajevo",
    "iso:country":"BA",
    "wof:name":"Gaj",
    "wof:placetype":"locality"
},
  "geometry": {"coordinates":[18.93515,43.96339],"type":"Point"}
}