{
  "type": "Feature",
  "properties": {
    "gn:admin1_code":"02",
    "gn:asciiname":"Brainci",
    "gn:country_code":"BA",
    "gn:dem":887,
    "gn:feature_class":"P",
    "gn:feature_code":"PPLL",
    "gn:name":"Brainci",
    "gn:population":0,
    "gn:timezone":"Europe/Sarajevo",
    "iso:country":"BA",
    "wof:name":"Brainci",
    "wof:placetype":"locality"
},
  "geometry": {"coordinates":[18.86528,44.34222000000001],"type":"Point"}
}