{
  "type": "Feature",
  "properties": {
    "gn:asciiname":"Klajici",
    "gn:country_code":"BA",
    "gn:dem":263,
    "gn:feature_class":"P",
    "gn:feature_code":"PPL",
    "gn:name":"\u041a\u0459\u0430\u0458\u0438\u045b\u0438",
    "gn:population":0,
    "gn:timezone":"Europe/Sarajevo",
    "iso:country":"BA",
    "name:und_x_variant":[
        "Kljajici"
    ],
    "wof:name":"Klajici",
    "wof:placetype":"locality"
},
  "geometry": {"coordinates":[17.91952000000001,44.90916],"type":"Point"}
}