{
  "type": "Feature",
  "properties": {
    "gn:admin1_code":"01",
    "gn:asciiname":"Gradina",
    "gn:country_code":"BA",
    "gn:dem":664,
    "gn:feature_class":"P",
    "gn:feature_code":"PPL",
    "gn:name":"Gradina",
    "gn:population":0,
    "gn:timezone":"Europe/Sarajevo",
    "iso:country":"BA",
    "wof:name":"Gradina",
    "wof:placetype":"locality"
},
  "geometry": {"coordinates":[17.88517000000001,43.97112],"type":"Point"}
}