{
  "type": "Feature",
  "properties": {
    "gn:admin1_code":"01",
    "gn:asciiname":"Rekici",
    "gn:country_code":"BA",
    "gn:dem":318,
    "gn:feature_class":"P",
    "gn:feature_code":"PPL",
    "gn:name":"Reki\u0107i",
    "gn:population":0,
    "gn:timezone":"Europe/Sarajevo",
    "iso:country":"BA",
    "wof:name":"Rekici",
    "wof:placetype":"locality"
},
  "geometry": {"coordinates":[15.9653,45.03422],"type":"Point"}
}