{
  "type": "Feature",
  "properties": {
    "gn:admin1_code":"01",
    "gn:asciiname":"Orasac",
    "gn:country_code":"BA",
    "gn:dem":506,
    "gn:feature_class":"P",
    "gn:feature_code":"PPL",
    "gn:name":"Ora\u0161ac",
    "gn:population":0,
    "gn:timezone":"Europe/Sarajevo",
    "iso:country":"BA",
    "wof:name":"Orasac",
    "wof:placetype":"locality"
},
  "geometry": {"coordinates":[18.09637,44.00612],"type":"Point"}
}