{
  "type": "Feature",
  "properties": {
    "gn:admin1_code":"02",
    "gn:asciiname":"Bukale",
    "gn:country_code":"BA",
    "gn:dem":329,
    "gn:feature_class":"P",
    "gn:feature_code":"PPL",
    "gn:name":"Bukale",
    "gn:population":0,
    "gn:timezone":"Europe/Sarajevo",
    "iso:country":"BA",
    "wof:name":"Bukale",
    "wof:placetype":"locality"
},
  "geometry": {"coordinates":[16.69046,45.03157],"type":"Point"}
}