{
  "type": "Feature",
  "properties": {
    "gn:admin1_code":"01",
    "gn:asciiname":"Misite",
    "gn:country_code":"BA",
    "gn:dem":595,
    "gn:feature_class":"P",
    "gn:feature_code":"PPL",
    "gn:name":"Mi\u0161ite",
    "gn:population":0,
    "gn:timezone":"Europe/Sarajevo",
    "iso:country":"BA",
    "wof:name":"Misite",
    "wof:placetype":"locality"
},
  "geometry": {"coordinates":[18.05927,42.77716],"type":"Point"}
}