{
  "type": "Feature",
  "properties": {
    "gn:admin1_code":"01",
    "gn:asciiname":"Jazvenik",
    "gn:country_code":"BA",
    "gn:dem":1006,
    "gn:feature_class":"P",
    "gn:feature_code":"PPL",
    "gn:name":"Jazvenik",
    "gn:population":0,
    "gn:timezone":"Europe/Sarajevo",
    "iso:country":"BA",
    "name:bos_x_preferred":[
        "Jazvenik"
    ],
    "name:fra_x_preferred":[
        "Jazvenik"
    ],
    "name:hrv_x_preferred":[
        "Jazvenik"
    ],
    "name:srp_x_preferred":[
        "\u0408\u0430\u0437\u0432\u0435\u043d\u0438\u043a"
    ],
    "wof:name":"Jazvenik",
    "wof:placetype":"locality"
},
  "geometry": {"coordinates":[17.437,43.93812],"type":"Point"}
}