{
  "type": "Feature",
  "properties": {
    "gn:admin1_code":"01",
    "gn:asciiname":"Mosevici",
    "gn:country_code":"BA",
    "gn:dem":763,
    "gn:feature_class":"P",
    "gn:feature_code":"PPL",
    "gn:name":"Mo\u0161evi\u0107i",
    "gn:population":0,
    "gn:timezone":"Europe/Sarajevo",
    "iso:country":"BA",
    "name:bos_x_preferred":[
        "Mo\u0161evi\u0107i"
    ],
    "name:fra_x_preferred":[
        "Mo\u0161evi\u0107i"
    ],
    "name:hrv_x_preferred":[
        "Mo\u0161evi\u0107i"
    ],
    "name:pol_x_preferred":[
        "Mo\u0161evi\u0107i"
    ],
    "name:und_x_variant":[
        "Mo\u0161evi\u0107i"
    ],
    "wof:name":"Mosevici",
    "wof:placetype":"locality"
},
  "geometry": {"coordinates":[18.44393,44.03072],"type":"Point"}
}