{
  "type": "Feature",
  "properties": {
    "gn:admin1_code":"01",
    "gn:asciiname":"Biljevina",
    "gn:country_code":"BA",
    "gn:dem":847,
    "gn:feature_class":"P",
    "gn:feature_code":"PPL",
    "gn:name":"Biljevina",
    "gn:population":0,
    "gn:timezone":"Europe/Sarajevo",
    "iso:country":"BA",
    "wof:name":"Biljevina",
    "wof:placetype":"locality"
},
  "geometry": {"coordinates":[17.92556,44.38386],"type":"Point"}
}