{
  "type": "Feature",
  "properties": {
    "gn:admin1_code":"02",
    "gn:asciiname":"Luzani Korovski",
    "gn:country_code":"BA",
    "gn:dem":92,
    "gn:feature_class":"P",
    "gn:feature_code":"PPL",
    "gn:name":"Lu\u017eani Korovski",
    "gn:population":0,
    "gn:timezone":"Europe/Sarajevo",
    "iso:country":"BA",
    "wof:name":"Luzani Korovski",
    "wof:placetype":"locality"
},
  "geometry": {"coordinates":[17.77093,45.07517],"type":"Point"}
}