{
  "type": "Feature",
  "properties": {
    "gn:admin1_code":"01",
    "gn:asciiname":"Tujnica",
    "gn:country_code":"BA",
    "gn:dem":239,
    "gn:feature_class":"P",
    "gn:feature_code":"PPL",
    "gn:name":"Tujnica",
    "gn:population":0,
    "gn:timezone":"Europe/Sarajevo",
    "iso:country":"BA",
    "name:bos_x_preferred":[
        "Tujnica"
    ],
    "name:ceb_x_preferred":[
        "Tujnica"
    ],
    "name:fra_x_preferred":[
        "Tujnica"
    ],
    "name:hrv_x_preferred":[
        "Tujnica"
    ],
    "name:swe_x_preferred":[
        "Tujnica"
    ],
    "wof:name":"Tujnica",
    "wof:placetype":"locality"
},
  "geometry": {"coordinates":[18.0617,44.52168],"type":"Point"}
}