{
  "type": "Feature",
  "properties": {
    "gn:admin1_code":"02",
    "gn:asciiname":"Gustovara",
    "gn:country_code":"BA",
    "gn:dem":601,
    "gn:feature_class":"P",
    "gn:feature_code":"PPLL",
    "gn:name":"Gustovara",
    "gn:population":0,
    "gn:timezone":"Europe/Sarajevo",
    "iso:country":"BA",
    "wof:name":"Gustovara",
    "wof:placetype":"locality"
},
  "geometry": {"coordinates":[17.12238,44.44982],"type":"Point"}
}