{
  "type": "Feature",
  "properties": {
    "gn:admin1_code":"01",
    "gn:asciiname":"Huremi",
    "gn:country_code":"BA",
    "gn:dem":339,
    "gn:feature_class":"P",
    "gn:feature_code":"PPL",
    "gn:name":"Huremi",
    "gn:population":0,
    "gn:timezone":"Europe/Sarajevo",
    "iso:country":"BA",
    "wof:name":"Huremi",
    "wof:placetype":"locality"
},
  "geometry": {"coordinates":[18.13739,44.39892],"type":"Point"}
}