{
  "type": "Feature",
  "properties": {
    "gn:admin1_code":"01",
    "gn:asciiname":"Mlados",
    "gn:country_code":"BA",
    "gn:dem":839,
    "gn:feature_class":"P",
    "gn:feature_code":"PPL",
    "gn:name":"Mlado\u0161",
    "gn:population":0,
    "gn:timezone":"Europe/Sarajevo",
    "iso:country":"BA",
    "wof:name":"Mlados",
    "wof:placetype":"locality"
},
  "geometry": {"coordinates":[17.99973,44.07553],"type":"Point"}
}