{
  "type": "Feature",
  "properties": {
    "gn:admin1_code":"02",
    "gn:asciiname":"Rabar",
    "gn:country_code":"BA",
    "gn:dem":1059,
    "gn:feature_class":"P",
    "gn:feature_code":"PPL",
    "gn:name":"Rabar",
    "gn:population":0,
    "gn:timezone":"Europe/Sarajevo",
    "iso:country":"BA",
    "wof:name":"Rabar",
    "wof:placetype":"locality"
},
  "geometry": {"coordinates":[18.87459,43.85471],"type":"Point"}
}