{
  "type": "Feature",
  "properties": {
    "gn:admin1_code":"02",
    "gn:asciiname":"Vidici",
    "gn:country_code":"BA",
    "gn:dem":187,
    "gn:feature_class":"P",
    "gn:feature_code":"PPL",
    "gn:name":"Vidi\u0107i",
    "gn:population":0,
    "gn:timezone":"Europe/Sarajevo",
    "iso:country":"BA",
    "wof:name":"Vidici",
    "wof:placetype":"locality"
},
  "geometry": {"coordinates":[17.74592999999999,44.9364],"type":"Point"}
}