{
  "type": "Feature",
  "properties": {
    "gn:admin1_code":"01",
    "gn:asciiname":"Hrnjadi",
    "gn:country_code":"BA",
    "gn:dem":1001,
    "gn:feature_class":"P",
    "gn:feature_code":"PPL",
    "gn:name":"Hrnjadi",
    "gn:population":0,
    "gn:timezone":"Europe/Sarajevo",
    "iso:country":"BA",
    "wof:name":"Hrnjadi",
    "wof:placetype":"locality"
},
  "geometry": {"coordinates":[16.27311,44.41159],"type":"Point"}
}