{
  "type": "Feature",
  "properties": {
    "gn:admin1_code":"02",
    "gn:asciiname":"Marici",
    "gn:country_code":"BA",
    "gn:dem":193,
    "gn:feature_class":"P",
    "gn:feature_code":"PPL",
    "gn:name":"Mari\u0107i",
    "gn:population":0,
    "gn:timezone":"Europe/Sarajevo",
    "iso:country":"BA",
    "wof:name":"Marici",
    "wof:placetype":"locality"
},
  "geometry": {"coordinates":[17.82692,44.83629000000001],"type":"Point"}
}