{
  "type": "Feature",
  "properties": {
    "gn:admin1_code":"02",
    "gn:asciiname":"Keseri",
    "gn:country_code":"BA",
    "gn:dem":252,
    "gn:feature_class":"P",
    "gn:feature_code":"PPL",
    "gn:name":"Keseri",
    "gn:population":0,
    "gn:timezone":"Europe/Sarajevo",
    "iso:country":"BA",
    "wof:name":"Keseri",
    "wof:placetype":"locality"
},
  "geometry": {"coordinates":[17.90272000000001,44.72695],"type":"Point"}
}