{
  "type": "Feature",
  "properties": {
    "gn:admin1_code":"00",
    "gn:asciiname":"Denkovci",
    "gn:country_code":"BA",
    "gn:dem":517,
    "gn:feature_class":"P",
    "gn:feature_code":"PPL",
    "gn:name":"Denkovci",
    "gn:population":0,
    "gn:timezone":"Europe/Sarajevo",
    "iso:country":"BA",
    "name:und_x_variant":[
        "Denkovi\u0107i",
        "Denkovci"
    ],
    "wof:name":"Denkovci",
    "wof:placetype":"locality"
},
  "geometry": {"coordinates":[18.47957,44.39061],"type":"Point"}
}