{
  "type": "Feature",
  "properties": {
    "gn:admin1_code":"01",
    "gn:asciiname":"Garista",
    "gn:country_code":"BA",
    "gn:dem":556,
    "gn:feature_class":"P",
    "gn:feature_code":"PPL",
    "gn:name":"Gari\u0161ta",
    "gn:population":0,
    "gn:timezone":"Europe/Sarajevo",
    "iso:country":"BA",
    "wof:name":"Garista",
    "wof:placetype":"locality"
},
  "geometry": {"coordinates":[17.80712999999999,43.39906],"type":"Point"}
}