{
  "type": "Feature",
  "properties": {
    "gn:admin1_code":"01",
    "gn:asciiname":"Semetis",
    "gn:country_code":"BA",
    "gn:dem":746,
    "gn:feature_class":"P",
    "gn:feature_code":"PPL",
    "gn:name":"Semeti\u0161",
    "gn:population":0,
    "gn:timezone":"Europe/Sarajevo",
    "iso:country":"BA",
    "name:bos_x_preferred":[
        "Semeti\u0161"
    ],
    "name:ceb_x_preferred":[
        "Semeti\u0161"
    ],
    "name:fra_x_preferred":[
        "Semeti\u0161"
    ],
    "name:hrv_x_preferred":[
        "Semeti\u0161"
    ],
    "name:srp_x_preferred":[
        "\u0421\u0435\u043c\u0435\u0442\u0438\u0448"
    ],
    "name:swe_x_preferred":[
        "Semeti\u0161"
    ],
    "name:und_x_variant":[
        "Semeti\u0161"
    ],
    "wof:name":"Semetis",
    "wof:placetype":"locality"
},
  "geometry": {"coordinates":[18.15885,44.17537],"type":"Point"}
}