{
  "type": "Feature",
  "properties": {
    "gn:admin1_code":"02",
    "gn:asciiname":"Oteza",
    "gn:country_code":"BA",
    "gn:dem":128,
    "gn:feature_class":"P",
    "gn:feature_code":"PPL",
    "gn:name":"Ote\u017ea",
    "gn:population":0,
    "gn:timezone":"Europe/Sarajevo",
    "iso:country":"BA",
    "wof:name":"Oteza",
    "wof:placetype":"locality"
},
  "geometry": {"coordinates":[18.31236,44.92444],"type":"Point"}
}