{
  "type": "Feature",
  "properties": {
    "gn:admin1_code":"02",
    "gn:asciiname":"Buckovici",
    "gn:country_code":"BA",
    "gn:dem":622,
    "gn:feature_class":"P",
    "gn:feature_code":"PPL",
    "gn:name":"Bu\u010dkovi\u0107i",
    "gn:population":0,
    "gn:timezone":"Europe/Sarajevo",
    "iso:country":"BA",
    "wof:name":"Buckovici",
    "wof:placetype":"locality"
},
  "geometry": {"coordinates":[19.01824,43.59029],"type":"Point"}
}