{
  "type": "Feature",
  "properties": {
    "gn:admin1_code":"01",
    "gn:asciiname":"Redak",
    "gn:country_code":"BA",
    "gn:dem":386,
    "gn:feature_class":"P",
    "gn:feature_code":"PPL",
    "gn:name":"Redak",
    "gn:population":0,
    "gn:timezone":"Europe/Sarajevo",
    "iso:country":"BA",
    "wof:name":"Redak",
    "wof:placetype":"locality"
},
  "geometry": {"coordinates":[16.07806,45.04389000000001],"type":"Point"}
}