{
  "type": "Feature",
  "properties": {
    "gn:admin1_code":"02",
    "gn:asciiname":"Jurici",
    "gn:country_code":"BA",
    "gn:dem":639,
    "gn:feature_class":"P",
    "gn:feature_code":"PPL",
    "gn:name":"Juri\u0107i",
    "gn:population":0,
    "gn:timezone":"Europe/Sarajevo",
    "iso:country":"BA",
    "wof:name":"Jurici",
    "wof:placetype":"locality"
},
  "geometry": {"coordinates":[17.43592,44.54268],"type":"Point"}
}