{
  "type": "Feature",
  "properties": {
    "gn:admin1_code":"01",
    "gn:asciiname":"Vranjcici",
    "gn:country_code":"BA",
    "gn:dem":758,
    "gn:feature_class":"P",
    "gn:feature_code":"PPL",
    "gn:name":"Vranj\u010di\u0107i",
    "gn:population":0,
    "gn:timezone":"Europe/Sarajevo",
    "iso:country":"BA",
    "wof:name":"Vranjcici",
    "wof:placetype":"locality"
},
  "geometry": {"coordinates":[18.88485,43.63376],"type":"Point"}
}