{
  "type": "Feature",
  "properties": {
    "gn:admin1_code":"01",
    "gn:asciiname":"Loncanik",
    "gn:country_code":"BA",
    "gn:dem":183,
    "gn:feature_class":"P",
    "gn:feature_code":"PPL",
    "gn:name":"Lon\u010danik",
    "gn:population":0,
    "gn:timezone":"Europe/Sarajevo",
    "iso:country":"BA",
    "wof:name":"Loncanik",
    "wof:placetype":"locality"
},
  "geometry": {"coordinates":[16.01591,45.13845],"type":"Point"}
}