{
  "type": "Feature",
  "properties": {
    "gn:admin1_code":"01",
    "gn:asciiname":"Sadic Mahala",
    "gn:country_code":"BA",
    "gn:dem":171,
    "gn:feature_class":"P",
    "gn:feature_code":"PPL",
    "gn:name":"\u0160adi\u0107 Mahala",
    "gn:population":0,
    "gn:timezone":"Europe/Sarajevo",
    "iso:country":"BA",
    "wof:name":"Sadic Mahala",
    "wof:placetype":"locality"
},
  "geometry": {"coordinates":[18.81358,44.72124],"type":"Point"}
}