{
  "type": "Feature",
  "properties": {
    "gn:admin1_code":"02",
    "gn:asciiname":"Topalovici",
    "gn:country_code":"BA",
    "gn:dem":384,
    "gn:feature_class":"P",
    "gn:feature_code":"PPL",
    "gn:name":"Topalovi\u0107i",
    "gn:population":0,
    "gn:timezone":"Europe/Sarajevo",
    "iso:country":"BA",
    "wof:name":"Topalovici",
    "wof:placetype":"locality"
},
  "geometry": {"coordinates":[18.14143,44.68357],"type":"Point"}
}