{
  "type": "Feature",
  "properties": {
    "gn:admin1_code":"01",
    "gn:asciiname":"Proslap",
    "gn:country_code":"BA",
    "gn:dem":603,
    "gn:feature_class":"P",
    "gn:feature_code":"PPL",
    "gn:name":"Proslap",
    "gn:population":0,
    "gn:timezone":"Europe/Sarajevo",
    "iso:country":"BA",
    "wof:name":"Proslap",
    "wof:placetype":"locality"
},
  "geometry": {"coordinates":[17.51881,43.78554000000001],"type":"Point"}
}