{
  "type": "Feature",
  "properties": {
    "gn:admin1_code":"02",
    "gn:asciiname":"Gocici",
    "gn:country_code":"BA",
    "gn:dem":308,
    "gn:feature_class":"P",
    "gn:feature_code":"PPL",
    "gn:name":"Go\u010di\u0107i",
    "gn:population":0,
    "gn:timezone":"Europe/Sarajevo",
    "iso:country":"BA",
    "wof:name":"Gocici",
    "wof:placetype":"locality"
},
  "geometry": {"coordinates":[16.46305,44.90969000000001],"type":"Point"}
}