{
  "type": "Feature",
  "properties": {
    "gn:admin1_code":"01",
    "gn:asciiname":"Adze",
    "gn:country_code":"BA",
    "gn:dem":274,
    "gn:feature_class":"P",
    "gn:feature_code":"PPL",
    "gn:name":"Ad\u017ee",
    "gn:population":0,
    "gn:timezone":"Europe/Sarajevo",
    "iso:country":"BA",
    "name:ace_x_preferred":[
        "Beuli\u00f4ng"
    ],
    "name:ang_x_preferred":[
        "Adesa"
    ],
    "name:arg_x_preferred":[
        "Ixuela"
    ],
    "name:bar_x_preferred":[
        "Dexel"
    ],
    "name:ben_x_preferred":[
        "\u09ac\u09be\u099f\u09be\u09b2\u09bf"
    ],
    "name:bul_x_preferred":[
        "\u0422\u0435\u0441\u043b\u0430"
    ],
    "name:cat_x_preferred":[
        "Aixa"
    ],
    "name:ces_x_preferred":[
        "Teslice"
    ],
    "name:cym_x_preferred":[
        "Neddyf"
    ],
    "name:dan_x_preferred":[
        "Skar\u00f8kse"
    ],
    "name:deu_x_preferred":[
        "Dechsel"
    ],
    "name:epo_x_preferred":[
        "Adzo"
    ],
    "name:est_x_preferred":[
        "Tahumiskirves"
    ],
    "name:eus_x_preferred":[
        "Zeio"
    ],
    "name:fin_x_preferred":[
        "Talso"
    ],
    "name:fra_x_preferred":[
        "Herminette"
    ],
    "name:gle_x_preferred":[
        "T\u00e1l"
    ],
    "name:glg_x_preferred":[
        "Aixola"
    ],
    "name:hin_x_preferred":[
        "\u092c\u0938\u0942\u0932\u093e"
    ],
    "name:hun_x_preferred":[
        "Fejsze"
    ],
    "name:hye_x_preferred":[
        "\u0548\u0582\u0580\u0561\u0563"
    ],
    "name:ind_x_preferred":[
        "Beliung"
    ],
    "name:isl_x_preferred":[
        "Skar\u00f6xi"
    ],
    "name:ita_x_preferred":[
        "Ascia"
    ],
    "name:kom_x_preferred":[
        "\u041a\u0435\u0440\u0430\u043d"
    ],
    "name:lfn_x_preferred":[
        "Axia"
    ],
    "name:lit_x_preferred":[
        "Vedega"
    ],
    "name:mkd_x_preferred":[
        "\u0422\u0435\u0441\u043b\u0430"
    ],
    "name:msa_x_preferred":[
        "Beliung"
    ],
    "name:nld_x_preferred":[
        "Dissel"
    ],
    "name:pam_x_preferred":[
        "Daras"
    ],
    "name:pol_x_preferred":[
        "Ciesak"
    ],
    "name:por_x_preferred":[
        "Enx\u00f3"
    ],
    "name:ron_x_preferred":[
        "Tesl\u0103"
    ],
    "name:rus_x_preferred":[
        "\u0422\u0435\u0441\u043b\u043e"
    ],
    "name:spa_x_preferred":[
        "Azuela"
    ],
    "name:sqi_x_preferred":[
        "Sqepari"
    ],
    "name:srp_x_preferred":[
        "\u0422\u0435\u0441\u043b\u0430"
    ],
    "name:sun_x_preferred":[
        "Baliung"
    ],
    "name:swe_x_preferred":[
        "Skarvyxa"
    ],
    "name:tam_x_preferred":[
        "\u0bb5\u0bbe\u0b9a\u0bbf"
    ],
    "name:ukr_x_preferred":[
        "\u0422\u0435\u0441\u043b\u043e"
    ],
    "wof:name":"Adze",
    "wof:placetype":"locality"
},
  "geometry": {"coordinates":[18.00219,44.5062],"type":"Point"}
}