{
  "type": "Feature",
  "properties": {
    "gn:admin1_code":"01",
    "gn:asciiname":"Zavolje",
    "gn:country_code":"BA",
    "gn:dem":468,
    "gn:feature_class":"P",
    "gn:feature_code":"PPL",
    "gn:name":"Zavolje",
    "gn:population":0,
    "gn:timezone":"Europe/Sarajevo",
    "iso:country":"BA",
    "name:bos_x_preferred":[
        "Zavolje"
    ],
    "name:fra_x_preferred":[
        "Zavolje"
    ],
    "name:srp_x_preferred":[
        "\u0417\u0430\u0432\u043e\u0459\u0435"
    ],
    "name:und_x_variant":[
        "Sanica Zavolje",
        "Zavolje"
    ],
    "wof:name":"Zavolje",
    "wof:placetype":"locality"
},
  "geometry": {"coordinates":[16.60107,44.61802],"type":"Point"}
}