{
  "type": "Feature",
  "properties": {
    "gn:admin1_code":"01",
    "gn:asciiname":"Johe",
    "gn:country_code":"BA",
    "gn:dem":1187,
    "gn:feature_class":"P",
    "gn:feature_code":"PPL",
    "gn:name":"Johe",
    "gn:population":0,
    "gn:timezone":"Europe/Sarajevo",
    "iso:country":"BA",
    "wof:name":"Johe",
    "wof:placetype":"locality"
},
  "geometry": {"coordinates":[18.73165,43.6572],"type":"Point"}
}