{
  "type": "Feature",
  "properties": {
    "gn:admin1_code":"01",
    "gn:asciiname":"Puticevo",
    "gn:country_code":"BA",
    "gn:dem":511,
    "gn:feature_class":"P",
    "gn:feature_code":"PPLL",
    "gn:name":"Puti\u010devo",
    "gn:population":0,
    "gn:timezone":"Europe/Sarajevo",
    "iso:country":"BA",
    "wof:name":"Puticevo",
    "wof:placetype":"locality"
},
  "geometry": {"coordinates":[17.71104,44.21642],"type":"Point"}
}