{
  "type": "Feature",
  "properties": {
    "gn:admin1_code":"02",
    "gn:asciiname":"Radovci",
    "gn:country_code":"BA",
    "gn:dem":201,
    "gn:feature_class":"P",
    "gn:feature_code":"PPL",
    "gn:name":"Radovci",
    "gn:population":0,
    "gn:timezone":"Europe/Sarajevo",
    "iso:country":"BA",
    "wof:name":"Radovci",
    "wof:placetype":"locality"
},
  "geometry": {"coordinates":[17.3293,44.72896],"type":"Point"}
}