{
  "type": "Feature",
  "properties": {
    "gn:admin1_code":"01",
    "gn:asciiname":"Klek",
    "gn:country_code":"BA",
    "gn:dem":765,
    "gn:feature_class":"P",
    "gn:feature_code":"PPL",
    "gn:name":"Klek",
    "gn:population":0,
    "gn:timezone":"Europe/Sarajevo",
    "iso:country":"BA",
    "name:bos_x_preferred":[
        "Klek"
    ],
    "name:ceb_x_preferred":[
        "Klek"
    ],
    "name:deu_x_preferred":[
        "Klek"
    ],
    "name:fra_x_preferred":[
        "Klek"
    ],
    "name:hrv_x_preferred":[
        "Klek"
    ],
    "name:hun_x_preferred":[
        "Klek"
    ],
    "name:pol_x_preferred":[
        "Klek"
    ],
    "name:rus_x_preferred":[
        "\u041a\u043b\u0435\u043a"
    ],
    "name:slv_x_preferred":[
        "Klek"
    ],
    "name:srp_x_preferred":[
        "\u041a\u043b\u0435\u043a"
    ],
    "name:swe_x_preferred":[
        "Klek"
    ],
    "name:ukr_x_preferred":[
        "\u041a\u043b\u0435\u043a"
    ],
    "wof:name":"Klek",
    "wof:placetype":"locality"
},
  "geometry": {"coordinates":[17.702,43.76526],"type":"Point"}
}