{
  "type": "Feature",
  "properties": {
    "gn:admin1_code":"01",
    "gn:asciiname":"Klek",
    "gn:country_code":"BA",
    "gn:dem":765,
    "gn:feature_class":"P",
    "gn:feature_code":"PPL",
    "gn:name":"Klek",
    "gn:population":0,
    "gn:timezone":"Europe/Sarajevo",
    "iso:country":"BA",
    "wof:name":"Klek",
    "wof:placetype":"locality"
},
  "geometry": {"coordinates":[17.702,43.76526],"type":"Point"}
}