{
  "type": "Feature",
  "properties": {
    "gn:admin1_code":"01",
    "gn:asciiname":"Jagodar",
    "gn:country_code":"BA",
    "gn:dem":835,
    "gn:feature_class":"P",
    "gn:feature_code":"PPL",
    "gn:name":"Jagodar",
    "gn:population":0,
    "gn:timezone":"Europe/Sarajevo",
    "iso:country":"BA",
    "wof:name":"Jagodar",
    "wof:placetype":"locality"
},
  "geometry": {"coordinates":[18.3879,43.69911],"type":"Point"}
}