{
  "type": "Feature",
  "properties": {
    "gn:admin1_code":"02",
    "gn:asciiname":"Cerenkovici",
    "gn:country_code":"BA",
    "gn:dem":1146,
    "gn:feature_class":"P",
    "gn:feature_code":"PPL",
    "gn:name":"\u010cerenkovi\u0107i",
    "gn:population":0,
    "gn:timezone":"Europe/Sarajevo",
    "iso:country":"BA",
    "wof:name":"Cerenkovici",
    "wof:placetype":"locality"
},
  "geometry": {"coordinates":[18.435,43.53083],"type":"Point"}
}