{
  "type": "Feature",
  "properties": {
    "gn:admin1_code":"01",
    "gn:asciiname":"Pratnice",
    "gn:country_code":"BA",
    "gn:dem":554,
    "gn:feature_class":"P",
    "gn:feature_code":"PPL",
    "gn:name":"Pratnice",
    "gn:population":0,
    "gn:timezone":"Europe/Sarajevo",
    "iso:country":"BA",
    "wof:name":"Pratnice",
    "wof:placetype":"locality"
},
  "geometry": {"coordinates":[15.96926,44.70115],"type":"Point"}
}