{
  "type": "Feature",
  "properties": {
    "gn:admin1_code":"02",
    "gn:asciiname":"Zeljkovici",
    "gn:country_code":"BA",
    "gn:dem":301,
    "gn:feature_class":"P",
    "gn:feature_code":"PPL",
    "gn:name":"Zeljkovi\u0107i",
    "gn:population":0,
    "gn:timezone":"Europe/Sarajevo",
    "iso:country":"BA",
    "wof:name":"Zeljkovici",
    "wof:placetype":"locality"
},
  "geometry": {"coordinates":[16.95095,44.74849],"type":"Point"}
}