{
  "type": "Feature",
  "properties": {
    "gn:admin1_code":"02",
    "gn:asciiname":"Radosavska",
    "gn:country_code":"BA",
    "gn:dem":214,
    "gn:feature_class":"P",
    "gn:feature_code":"PPLL",
    "gn:name":"Radosavska",
    "gn:population":0,
    "gn:timezone":"Europe/Sarajevo",
    "iso:country":"BA",
    "wof:name":"Radosavska",
    "wof:placetype":"locality"
},
  "geometry": {"coordinates":[16.9494,44.8504],"type":"Point"}
}