{
  "type": "Feature",
  "properties": {
    "gn:admin1_code":"02",
    "gn:asciiname":"Radosavska",
    "gn:country_code":"BA",
    "gn:dem":214,
    "gn:feature_class":"P",
    "gn:feature_code":"PPLL",
    "gn:name":"Radosavska",
    "gn:population":0,
    "gn:timezone":"Europe/Sarajevo",
    "iso:country":"BA",
    "name:bos_x_preferred":[
        "Radosavska"
    ],
    "name:ceb_x_preferred":[
        "Radosavska"
    ],
    "name:fra_x_preferred":[
        "Radosavska"
    ],
    "name:hrv_x_preferred":[
        "Radosavska"
    ],
    "name:rus_x_preferred":[
        "\u0420\u0430\u0434\u043e\u0441\u0430\u0432\u0441\u043a\u0430"
    ],
    "name:slv_x_preferred":[
        "Radosavska"
    ],
    "name:srp_x_preferred":[
        "\u0420\u0430\u0434\u043e\u0441\u0430\u0432\u0441\u043a\u0430"
    ],
    "name:swe_x_preferred":[
        "Radosavska"
    ],
    "wof:name":"Radosavska",
    "wof:placetype":"locality"
},
  "geometry": {"coordinates":[16.9494,44.8504],"type":"Point"}
}