{
  "type": "Feature",
  "properties": {
    "gn:admin1_code":"01",
    "gn:asciiname":"Ramici",
    "gn:country_code":"BA",
    "gn:dem":442,
    "gn:feature_class":"P",
    "gn:feature_code":"PPL",
    "gn:name":"Rami\u0107i",
    "gn:population":0,
    "gn:timezone":"Europe/Sarajevo",
    "iso:country":"BA",
    "wof:name":"Ramici",
    "wof:placetype":"locality"
},
  "geometry": {"coordinates":[16.46674,44.79565],"type":"Point"}
}