{
  "type": "Feature",
  "properties": {
    "gn:admin1_code":"01",
    "gn:asciiname":"Pehari",
    "gn:country_code":"BA",
    "gn:dem":132,
    "gn:feature_class":"P",
    "gn:feature_code":"PPL",
    "gn:name":"Pehari",
    "gn:population":0,
    "gn:timezone":"Europe/Sarajevo",
    "iso:country":"BA",
    "wof:name":"Pehari",
    "wof:placetype":"locality"
},
  "geometry": {"coordinates":[17.62222000000001,43.14417],"type":"Point"}
}