{
  "type": "Feature",
  "properties": {
    "gn:admin1_code":"01",
    "gn:asciiname":"Ceruzici",
    "gn:country_code":"BA",
    "gn:dem":960,
    "gn:feature_class":"P",
    "gn:feature_code":"PPL",
    "gn:name":"\u010ceru\u017ei\u0107i",
    "gn:population":0,
    "gn:timezone":"Europe/Sarajevo",
    "iso:country":"BA",
    "name:bos_x_preferred":[
        "\u010ceru\u017ei\u0107i"
    ],
    "name:fra_x_preferred":[
        "\u010ceru\u017ei\u0107i"
    ],
    "wof:name":"Ceruzici",
    "wof:placetype":"locality"
},
  "geometry": {"coordinates":[18.40457,43.69831],"type":"Point"}
}