{
  "type": "Feature",
  "properties": {
    "gn:admin1_code":"01",
    "gn:asciiname":"Cipic",
    "gn:country_code":"BA",
    "gn:dem":639,
    "gn:feature_class":"P",
    "gn:feature_code":"PPL",
    "gn:name":"Cipi\u0107",
    "gn:population":0,
    "gn:timezone":"Europe/Sarajevo",
    "iso:country":"BA",
    "wof:name":"Cipic",
    "wof:placetype":"locality"
},
  "geometry": {"coordinates":[17.24201,44.28948],"type":"Point"}
}