{
  "type": "Feature",
  "properties": {
    "gn:admin1_code":"00",
    "gn:asciiname":"Rujici",
    "gn:country_code":"BA",
    "gn:dem":470,
    "gn:feature_class":"P",
    "gn:feature_code":"PPL",
    "gn:name":"Ruji\u0107i",
    "gn:population":0,
    "gn:timezone":"Europe/Sarajevo",
    "iso:country":"BA",
    "wof:name":"Rujici",
    "wof:placetype":"locality"
},
  "geometry": {"coordinates":[18.70874,44.30499],"type":"Point"}
}