{
  "type": "Feature",
  "properties": {
    "gn:admin1_code":"01",
    "gn:asciiname":"Podporim",
    "gn:country_code":"BA",
    "gn:dem":549,
    "gn:feature_class":"P",
    "gn:feature_code":"PPL",
    "gn:name":"Podporim",
    "gn:population":0,
    "gn:timezone":"Europe/Sarajevo",
    "iso:country":"BA",
    "wof:name":"Podporim",
    "wof:placetype":"locality"
},
  "geometry": {"coordinates":[17.92877,43.45231],"type":"Point"}
}