{
  "type": "Feature",
  "properties": {
    "gn:admin1_code":"01",
    "gn:asciiname":"Drvetine",
    "gn:country_code":"BA",
    "gn:dem":550,
    "gn:feature_class":"P",
    "gn:feature_code":"PPL",
    "gn:name":"Drvetine",
    "gn:population":0,
    "gn:timezone":"Europe/Sarajevo",
    "iso:country":"BA",
    "name:bos_x_preferred":[
        "Drvetine"
    ],
    "name:ceb_x_preferred":[
        "Drvetine"
    ],
    "name:fra_x_preferred":[
        "Drvetine"
    ],
    "name:hrv_x_preferred":[
        "Drvetine"
    ],
    "name:srp_x_preferred":[
        "\u0414\u0440\u0432\u0435\u0442\u0438\u043d\u0435"
    ],
    "name:swe_x_preferred":[
        "Drvetine"
    ],
    "wof:name":"Drvetine",
    "wof:placetype":"locality"
},
  "geometry": {"coordinates":[17.45028,44.1025],"type":"Point"}
}