{
  "type": "Feature",
  "properties": {
    "gn:admin1_code":"02",
    "gn:asciiname":"Jakovljevici",
    "gn:country_code":"BA",
    "gn:dem":251,
    "gn:feature_class":"P",
    "gn:feature_code":"PPL",
    "gn:name":"Jakovljevi\u0107i",
    "gn:population":0,
    "gn:timezone":"Europe/Sarajevo",
    "iso:country":"BA",
    "wof:name":"Jakovljevici",
    "wof:placetype":"locality"
},
  "geometry": {"coordinates":[16.94192,44.84121],"type":"Point"}
}