{
  "type": "Feature",
  "properties": {
    "gn:admin1_code":"01",
    "gn:asciiname":"Polje Ostruznica",
    "gn:country_code":"BA",
    "gn:dem":548,
    "gn:feature_class":"P",
    "gn:feature_code":"PPL",
    "gn:name":"Polje Ostru\u017enica",
    "gn:population":0,
    "gn:timezone":"Europe/Sarajevo",
    "iso:country":"BA",
    "name:und_x_variant":[
        "Polje Ostru\u017enica"
    ],
    "wof:name":"Polje Ostruznica",
    "wof:placetype":"locality"
},
  "geometry": {"coordinates":[17.94161,43.97077],"type":"Point"}
}