{
  "type": "Feature",
  "properties": {
    "gn:admin1_code":"01",
    "gn:asciiname":"Polje Ostruznica",
    "gn:country_code":"BA",
    "gn:dem":548,
    "gn:feature_class":"P",
    "gn:feature_code":"PPL",
    "gn:name":"Polje Ostru\u017enica",
    "gn:population":0,
    "gn:timezone":"Europe/Sarajevo",
    "iso:country":"BA",
    "name:bos_x_preferred":[
        "Polje Ostru\u017enica"
    ],
    "name:fra_x_preferred":[
        "Polje Ostru\u017enica"
    ],
    "name:hrv_x_preferred":[
        "Polje Ostru\u017enica"
    ],
    "name:srp_x_preferred":[
        "\u041f\u043e\u0459\u0435 \u041e\u0441\u0442\u0440\u0443\u0436\u043d\u0438\u0446\u0430"
    ],
    "wof:name":"Polje Ostruznica",
    "wof:placetype":"locality"
},
  "geometry": {"coordinates":[17.94161,43.97077],"type":"Point"}
}