{
  "type": "Feature",
  "properties": {
    "gn:admin1_code":"01",
    "gn:asciiname":"Dabovici",
    "gn:country_code":"BA",
    "gn:dem":889,
    "gn:feature_class":"P",
    "gn:feature_code":"PPL",
    "gn:name":"Dabovi\u0107i",
    "gn:population":0,
    "gn:timezone":"Europe/Sarajevo",
    "iso:country":"BA",
    "wof:name":"Dabovici",
    "wof:placetype":"locality"
},
  "geometry": {"coordinates":[18.58938,44.06473],"type":"Point"}
}