{
  "type": "Feature",
  "properties": {
    "gn:admin1_code":"01",
    "gn:asciiname":"Zorici",
    "gn:country_code":"BA",
    "gn:dem":275,
    "gn:feature_class":"P",
    "gn:feature_code":"PPL",
    "gn:name":"Zori\u0107i",
    "gn:population":0,
    "gn:timezone":"Europe/Sarajevo",
    "iso:country":"BA",
    "wof:name":"Zorici",
    "wof:placetype":"locality"
},
  "geometry": {"coordinates":[17.36299,43.39218],"type":"Point"}
}