{
  "type": "Feature",
  "properties": {
    "gn:admin1_code":"02",
    "gn:asciiname":"Biserina Kula",
    "gn:country_code":"BA",
    "gn:dem":833,
    "gn:feature_class":"P",
    "gn:feature_code":"PPL",
    "gn:name":"Biserina Kula",
    "gn:population":0,
    "gn:timezone":"Europe/Sarajevo",
    "iso:country":"BA",
    "name:und_x_variant":[
        "Beserina Kula",
        "Biserina Kula"
    ],
    "wof:name":"Biserina Kula",
    "wof:placetype":"locality"
},
  "geometry": {"coordinates":[18.55493,43.86865],"type":"Point"}
}