{
  "type": "Feature",
  "properties": {
    "gn:admin1_code":"02",
    "gn:asciiname":"Jerinici",
    "gn:country_code":"BA",
    "gn:dem":177,
    "gn:feature_class":"P",
    "gn:feature_code":"PPL",
    "gn:name":"Jerini\u0107i",
    "gn:population":0,
    "gn:timezone":"Europe/Sarajevo",
    "iso:country":"BA",
    "wof:name":"Jerinici",
    "wof:placetype":"locality"
},
  "geometry": {"coordinates":[17.85167000000001,44.91388],"type":"Point"}
}