{
  "type": "Feature",
  "properties": {
    "gn:admin1_code":"01",
    "gn:asciiname":"Krke",
    "gn:country_code":"BA",
    "gn:dem":253,
    "gn:feature_class":"P",
    "gn:feature_code":"PPL",
    "gn:name":"Krke",
    "gn:population":0,
    "gn:timezone":"Europe/Sarajevo",
    "iso:country":"BA",
    "wof:name":"Krke",
    "wof:placetype":"locality"
},
  "geometry": {"coordinates":[18.53018,44.505],"type":"Point"}
}