{
  "type": "Feature",
  "properties": {
    "gn:admin1_code":"01",
    "gn:asciiname":"Sainovac",
    "gn:country_code":"BA",
    "gn:dem":382,
    "gn:feature_class":"P",
    "gn:feature_code":"PPL",
    "gn:name":"\u0160ainovac",
    "gn:population":0,
    "gn:timezone":"Europe/Sarajevo",
    "iso:country":"BA",
    "wof:name":"Sainovac",
    "wof:placetype":"locality"
},
  "geometry": {"coordinates":[16.45533,44.72695],"type":"Point"}
}