{
  "type": "Feature",
  "properties": {
    "gn:admin1_code":"01",
    "gn:asciiname":"Krasulje",
    "gn:country_code":"BA",
    "gn:dem":433,
    "gn:feature_class":"P",
    "gn:feature_code":"PPLL",
    "gn:name":"Krasulje",
    "gn:population":0,
    "gn:timezone":"Europe/Sarajevo",
    "iso:country":"BA",
    "wof:name":"Krasulje",
    "wof:placetype":"locality"
},
  "geometry": {"coordinates":[16.74637,44.60583],"type":"Point"}
}