{
  "type": "Feature",
  "properties": {
    "gn:admin1_code":"01",
    "gn:asciiname":"Krasulje",
    "gn:country_code":"BA",
    "gn:dem":433,
    "gn:feature_class":"P",
    "gn:feature_code":"PPLL",
    "gn:name":"Krasulje",
    "gn:population":0,
    "gn:timezone":"Europe/Sarajevo",
    "iso:country":"BA",
    "name:bos_x_preferred":[
        "Krasulje"
    ],
    "name:ceb_x_preferred":[
        "Krasulje"
    ],
    "name:fra_x_preferred":[
        "Krasulje"
    ],
    "name:hrv_x_preferred":[
        "Krasulje"
    ],
    "name:srp_x_preferred":[
        "\u041a\u0440\u0430\u0441\u0443\u0459\u0435"
    ],
    "name:swe_x_preferred":[
        "Krasulje"
    ],
    "wof:name":"Krasulje",
    "wof:placetype":"locality"
},
  "geometry": {"coordinates":[16.74637,44.60583],"type":"Point"}
}