{
  "type": "Feature",
  "properties": {
    "gn:admin1_code":"01",
    "gn:asciiname":"Donja Kotlina",
    "gn:country_code":"BA",
    "gn:dem":694,
    "gn:feature_class":"P",
    "gn:feature_code":"PPL",
    "gn:name":"Donja Kotlina",
    "gn:population":0,
    "gn:timezone":"Europe/Sarajevo",
    "iso:country":"BA",
    "wof:name":"Donja Kotlina",
    "wof:placetype":"locality"
},
  "geometry": {"coordinates":[16.54498,44.31965],"type":"Point"}
}