{
  "type": "Feature",
  "properties": {
    "gn:admin1_code":"02",
    "gn:asciiname":"Bec",
    "gn:country_code":"BA",
    "gn:dem":172,
    "gn:feature_class":"P",
    "gn:feature_code":"PPL",
    "gn:name":"Be\u010d",
    "gn:population":0,
    "gn:timezone":"Europe/Sarajevo",
    "iso:country":"BA",
    "name:srp_x_preferred":[
        "\u0411\u0435\u0446"
    ],
    "wof:name":"Bec",
    "wof:placetype":"locality"
},
  "geometry": {"coordinates":[16.68455,45.0879],"type":"Point"}
}