{
  "type": "Feature",
  "properties": {
    "gn:admin1_code":"02",
    "gn:asciiname":"Cengic Do",
    "gn:country_code":"BA",
    "gn:dem":716,
    "gn:feature_class":"P",
    "gn:feature_code":"PPL",
    "gn:name":"\u010cengi\u0107 Do",
    "gn:population":0,
    "gn:timezone":"Europe/Sarajevo",
    "iso:country":"BA",
    "wof:name":"Cengic Do",
    "wof:placetype":"locality"
},
  "geometry": {"coordinates":[18.43398,42.98524000000001],"type":"Point"}
}