{
  "type": "Feature",
  "properties": {
    "gn:admin1_code":"02",
    "gn:asciiname":"Sopot",
    "gn:country_code":"BA",
    "gn:dem":992,
    "gn:feature_class":"P",
    "gn:feature_code":"PPL",
    "gn:name":"Sopot",
    "gn:population":0,
    "gn:timezone":"Europe/Sarajevo",
    "iso:country":"BA",
    "wof:name":"Sopot",
    "wof:placetype":"locality"
},
  "geometry": {"coordinates":[18.2495,43.24109],"type":"Point"}
}