{
  "type": "Feature",
  "properties": {
    "gn:admin1_code":"02",
    "gn:asciiname":"Okiljevici",
    "gn:country_code":"BA",
    "gn:dem":1141,
    "gn:feature_class":"P",
    "gn:feature_code":"PPL",
    "gn:name":"Okiljevi\u0107i",
    "gn:population":0,
    "gn:timezone":"Europe/Sarajevo",
    "iso:country":"BA",
    "wof:name":"Okiljevici",
    "wof:placetype":"locality"
},
  "geometry": {"coordinates":[18.611,43.16192],"type":"Point"}
}