{
  "type": "Feature",
  "properties": {
    "gn:admin1_code":"02",
    "gn:asciiname":"Kos",
    "gn:country_code":"BA",
    "gn:dem":656,
    "gn:feature_class":"P",
    "gn:feature_code":"PPL",
    "gn:name":"Kos",
    "gn:population":0,
    "gn:timezone":"Europe/Sarajevo",
    "iso:country":"BA",
    "wof:name":"Kos",
    "wof:placetype":"locality"
},
  "geometry": {"coordinates":[16.93192,45.00299],"type":"Point"}
}