{
  "type": "Feature",
  "properties": {
    "gn:admin1_code":"02",
    "gn:asciiname":"Kos",
    "gn:country_code":"BA",
    "gn:dem":656,
    "gn:feature_class":"P",
    "gn:feature_code":"PPL",
    "gn:name":"Kos",
    "gn:population":0,
    "gn:timezone":"Europe/Sarajevo",
    "iso:country":"BA",
    "name:ara_x_preferred":[
        "\u0643\u0648\u0633"
    ],
    "name:ast_x_preferred":[
        "Kos"
    ],
    "name:bos_x_preferred":[
        "Kos"
    ],
    "name:bre_x_preferred":[
        "Kos"
    ],
    "name:bul_x_preferred":[
        "\u041a\u043e\u0441"
    ],
    "name:cat_x_preferred":[
        "Kos"
    ],
    "name:cdo_x_preferred":[
        "G\u014f\u0324-s\u00ea\u0324\u1e73"
    ],
    "name:ceb_x_preferred":[
        "N\u00edsos Kos"
    ],
    "name:ces_x_preferred":[
        "K\u00f3s"
    ],
    "name:cym_x_preferred":[
        "Kos"
    ],
    "name:dan_x_preferred":[
        "Kos"
    ],
    "name:deu_x_preferred":[
        "Kos"
    ],
    "name:ell_x_preferred":[
        "\u039a\u03c9\u03c2"
    ],
    "name:epo_x_preferred":[
        "Kos"
    ],
    "name:est_x_preferred":[
        "Kos"
    ],
    "name:eus_x_preferred":[
        "Kos"
    ],
    "name:fao_x_preferred":[
        "Kos"
    ],
    "name:fas_x_preferred":[
        "\u062c\u0632\u06cc\u0631\u0647 \u06a9\u0633"
    ],
    "name:fin_x_preferred":[
        "Kos"
    ],
    "name:fra_x_preferred":[
        "Kos"
    ],
    "name:fry_x_preferred":[
        "Kos"
    ],
    "name:glg_x_preferred":[
        "Cos"
    ],
    "name:heb_x_preferred":[
        "\u05e7\u05d5\u05e1"
    ],
    "name:hrv_x_preferred":[
        "Kos"
    ],
    "name:hun_x_preferred":[
        "Kosz"
    ],
    "name:ile_x_preferred":[
        "Kos"
    ],
    "name:ind_x_preferred":[
        "Pulau Kos"
    ],
    "name:isl_x_preferred":[
        "Kos"
    ],
    "name:ita_x_preferred":[
        "Coo"
    ],
    "name:jpn_x_preferred":[
        "\u30b3\u30b9\u5cf6"
    ],
    "name:kor_x_preferred":[
        "\ucf54\uc2a4\uc12c"
    ],
    "name:lat_x_preferred":[
        "Cos"
    ],
    "name:lim_x_preferred":[
        "Kos"
    ],
    "name:lit_x_preferred":[
        "Kosas"
    ],
    "name:nld_x_preferred":[
        "Kos"
    ],
    "name:nno_x_preferred":[
        "Kos"
    ],
    "name:nor_x_preferred":[
        "Kos"
    ],
    "name:pol_x_preferred":[
        "Kos"
    ],
    "name:por_x_preferred":[
        "C\u00f3s"
    ],
    "name:ron_x_preferred":[
        "Kos"
    ],
    "name:rus_x_preferred":[
        "\u041a\u043e\u0441"
    ],
    "name:sco_x_preferred":[
        "Kos"
    ],
    "name:slk_x_preferred":[
        "Kos"
    ],
    "name:slv_x_preferred":[
        "Kos"
    ],
    "name:spa_x_preferred":[
        "Cos"
    ],
    "name:srp_x_preferred":[
        "\u041a\u043e\u0441"
    ],
    "name:swe_x_preferred":[
        "Kos"
    ],
    "name:tur_x_preferred":[
        "\u0130stank\u00f6y"
    ],
    "name:ukr_x_preferred":[
        "\u041a\u043e\u0441"
    ],
    "name:urd_x_preferred":[
        "\u06a9\u0648\u0633"
    ],
    "name:vie_x_preferred":[
        "Kos"
    ],
    "name:wuu_x_preferred":[
        "\u79d1\u65af\u5c9b"
    ],
    "name:zho_x_preferred":[
        "\u79d1\u65af\u5c9b"
    ],
    "wof:name":"Kos",
    "wof:placetype":"locality"
},
  "geometry": {"coordinates":[16.93192,45.00299],"type":"Point"}
}