{
  "type": "Feature",
  "properties": {
    "gn:admin1_code":"02",
    "gn:asciiname":"Volari",
    "gn:country_code":"BA",
    "gn:dem":476,
    "gn:feature_class":"P",
    "gn:feature_code":"PPLL",
    "gn:name":"Volari",
    "gn:population":0,
    "gn:timezone":"Europe/Sarajevo",
    "iso:country":"BA",
    "wof:name":"Volari",
    "wof:placetype":"locality"
},
  "geometry": {"coordinates":[17.1286,44.28608],"type":"Point"}
}