{
  "type": "Feature",
  "properties": {
    "gn:admin1_code":"02",
    "gn:asciiname":"Lokvenice",
    "gn:country_code":"BA",
    "gn:dem":977,
    "gn:feature_class":"P",
    "gn:feature_code":"PPL",
    "gn:name":"Lokvenice",
    "gn:population":0,
    "gn:timezone":"Europe/Sarajevo",
    "iso:country":"BA",
    "wof:name":"Lokvenice",
    "wof:placetype":"locality"
},
  "geometry": {"coordinates":[18.9312,43.94564],"type":"Point"}
}