{
  "type": "Feature",
  "properties": {
    "gn:admin1_code":"01",
    "gn:asciiname":"Plahovici",
    "gn:country_code":"BA",
    "gn:dem":705,
    "gn:feature_class":"P",
    "gn:feature_code":"PPL",
    "gn:name":"Plahovi\u0107i",
    "gn:population":0,
    "gn:timezone":"Europe/Sarajevo",
    "iso:country":"BA",
    "wof:name":"Plahovici",
    "wof:placetype":"locality"
},
  "geometry": {"coordinates":[17.93722,44.25256],"type":"Point"}
}