{
  "type": "Feature",
  "properties": {
    "gn:admin1_code":"02",
    "gn:asciiname":"Donjani",
    "gn:country_code":"BA",
    "gn:dem":223,
    "gn:feature_class":"P",
    "gn:feature_code":"PPL",
    "gn:name":"Donjani",
    "gn:population":0,
    "gn:timezone":"Europe/Sarajevo",
    "iso:country":"BA",
    "wof:name":"Donjani",
    "wof:placetype":"locality"
},
  "geometry": {"coordinates":[18.18211,44.93486],"type":"Point"}
}