{
  "type": "Feature",
  "properties": {
    "gn:admin1_code":"01",
    "gn:asciiname":"Borajna",
    "gn:country_code":"BA",
    "gn:dem":279,
    "gn:feature_class":"P",
    "gn:feature_code":"PPLL",
    "gn:name":"Borajna",
    "gn:population":0,
    "gn:timezone":"Europe/Sarajevo",
    "iso:country":"BA",
    "wof:name":"Borajna",
    "wof:placetype":"locality"
},
  "geometry": {"coordinates":[17.48361,43.29954],"type":"Point"}
}