{
  "type": "Feature",
  "properties": {
    "gn:admin1_code":"01",
    "gn:asciiname":"Borajna",
    "gn:country_code":"BA",
    "gn:dem":279,
    "gn:feature_class":"P",
    "gn:feature_code":"PPLL",
    "gn:name":"Borajna",
    "gn:population":0,
    "gn:timezone":"Europe/Sarajevo",
    "iso:country":"BA",
    "name:bos_x_preferred":[
        "Borajna"
    ],
    "name:ceb_x_preferred":[
        "Borajna"
    ],
    "name:ell_x_preferred":[
        "\u039c\u03c0\u03cc\u03c1\u03b1\u03ca\u03bd\u03b1"
    ],
    "name:fra_x_preferred":[
        "Borajna"
    ],
    "name:hrv_x_preferred":[
        "Borajna"
    ],
    "name:srp_x_preferred":[
        "\u0411\u043e\u0440\u0430\u0458\u043d\u0430"
    ],
    "name:swe_x_preferred":[
        "Borajna"
    ],
    "wof:name":"Borajna",
    "wof:placetype":"locality"
},
  "geometry": {"coordinates":[17.48361,43.29954],"type":"Point"}
}