{
  "type": "Feature",
  "properties": {
    "gn:admin1_code":"02",
    "gn:asciiname":"Budzak",
    "gn:country_code":"BA",
    "gn:dem":146,
    "gn:feature_class":"P",
    "gn:feature_code":"PPL",
    "gn:name":"Bud\u017eak",
    "gn:population":0,
    "gn:timezone":"Europe/Sarajevo",
    "iso:country":"BA",
    "wof:name":"Budzak",
    "wof:placetype":"locality"
},
  "geometry": {"coordinates":[17.21267000000001,44.80385],"type":"Point"}
}