{
  "type": "Feature",
  "properties": {
    "gn:admin1_code":"01",
    "gn:asciiname":"Sapine",
    "gn:country_code":"BA",
    "gn:dem":881,
    "gn:feature_class":"P",
    "gn:feature_code":"PPL",
    "gn:name":"\u0160apine",
    "gn:population":0,
    "gn:timezone":"Europe/Sarajevo",
    "iso:country":"BA",
    "wof:name":"Sapine",
    "wof:placetype":"locality"
},
  "geometry": {"coordinates":[17.12067,43.5873],"type":"Point"}
}