{
  "type": "Feature",
  "properties": {
    "gn:admin1_code":"02",
    "gn:asciiname":"Sikarici",
    "gn:country_code":"BA",
    "gn:dem":126,
    "gn:feature_class":"P",
    "gn:feature_code":"PPL",
    "gn:name":"\u0160ikari\u0107i",
    "gn:population":0,
    "gn:timezone":"Europe/Sarajevo",
    "iso:country":"BA",
    "wof:name":"Sikarici",
    "wof:placetype":"locality"
},
  "geometry": {"coordinates":[18.88697,44.77351],"type":"Point"}
}