{
  "type": "Feature",
  "properties": {
    "gn:admin1_code":"01",
    "gn:asciiname":"Bakovicka Citonja",
    "gn:country_code":"BA",
    "gn:dem":959,
    "gn:feature_class":"P",
    "gn:feature_code":"PPLL",
    "gn:name":"Bakovi\u0107ka Citonja",
    "gn:population":0,
    "gn:timezone":"Europe/Sarajevo",
    "iso:country":"BA",
    "name:bos_x_preferred":[
        "Bakovi\u0107ka Citonja"
    ],
    "name:fra_x_preferred":[
        "Bakovi\u0107ka Citonja"
    ],
    "name:hrv_x_preferred":[
        "Bakovi\u0107ka Citonja"
    ],
    "name:srp_x_preferred":[
        "\u0411\u0430\u043a\u043e\u0432\u0438\u045b\u043a\u0430 \u0426\u0438\u0442\u043e\u045a\u0430"
    ],
    "wof:name":"Bakovicka Citonja",
    "wof:placetype":"locality"
},
  "geometry": {"coordinates":[17.95453,43.94193],"type":"Point"}
}