{
  "type": "Feature",
  "properties": {
    "gn:admin1_code":"01",
    "gn:asciiname":"Bakovicka Citonja",
    "gn:country_code":"BA",
    "gn:dem":959,
    "gn:feature_class":"P",
    "gn:feature_code":"PPLL",
    "gn:name":"Bakovi\u0107ka Citonja",
    "gn:population":0,
    "gn:timezone":"Europe/Sarajevo",
    "iso:country":"BA",
    "name:und_x_variant":[
        "Bakovi\u0107ka Citonja"
    ],
    "wof:name":"Bakovicka Citonja",
    "wof:placetype":"locality"
},
  "geometry": {"coordinates":[17.95453,43.94193],"type":"Point"}
}