{
  "type": "Feature",
  "properties": {
    "gn:admin1_code":"02",
    "gn:asciiname":"Korita",
    "gn:country_code":"BA",
    "gn:dem":817,
    "gn:feature_class":"P",
    "gn:feature_code":"PPL",
    "gn:name":"Korita",
    "gn:population":0,
    "gn:timezone":"Europe/Sarajevo",
    "iso:country":"BA",
    "name:bos_x_preferred":[
        "Korita"
    ],
    "name:ceb_x_preferred":[
        "Korita"
    ],
    "name:fra_x_preferred":[
        "Korita"
    ],
    "name:hrv_x_preferred":[
        "Korita"
    ],
    "name:hun_x_preferred":[
        "Korita"
    ],
    "name:nld_x_preferred":[
        "Korita"
    ],
    "name:pol_x_preferred":[
        "Korita"
    ],
    "name:rus_x_preferred":[
        "\u041a\u043e\u0440\u0438\u0442\u0430"
    ],
    "name:slv_x_preferred":[
        "Korita"
    ],
    "name:sqi_x_preferred":[
        "Korita"
    ],
    "name:srp_x_preferred":[
        "\u041a\u043e\u0440\u0438\u0442\u0430"
    ],
    "name:swe_x_preferred":[
        "Korita"
    ],
    "name:ukr_x_preferred":[
        "\u041a\u043e\u0440\u0438\u0442\u0430"
    ],
    "wof:name":"Korita",
    "wof:placetype":"locality"
},
  "geometry": {"coordinates":[18.99881,44.27307],"type":"Point"}
}