{
  "type": "Feature",
  "properties": {
    "gn:admin1_code":"02",
    "gn:asciiname":"Korita",
    "gn:country_code":"BA",
    "gn:dem":817,
    "gn:feature_class":"P",
    "gn:feature_code":"PPL",
    "gn:name":"Korita",
    "gn:population":0,
    "gn:timezone":"Europe/Sarajevo",
    "iso:country":"BA",
    "wof:name":"Korita",
    "wof:placetype":"locality"
},
  "geometry": {"coordinates":[18.99881,44.27307],"type":"Point"}
}