{
  "type": "Feature",
  "properties": {
    "gn:admin1_code":"01",
    "gn:asciiname":"Modrave",
    "gn:country_code":"BA",
    "gn:dem":715,
    "gn:feature_class":"P",
    "gn:feature_code":"PPL",
    "gn:name":"Modrave",
    "gn:population":0,
    "gn:timezone":"Europe/Sarajevo",
    "iso:country":"BA",
    "wof:name":"Modrave",
    "wof:placetype":"locality"
},
  "geometry": {"coordinates":[17.72344,43.42343],"type":"Point"}
}