{
  "type": "Feature",
  "properties": {
    "gn:admin1_code":"02",
    "gn:asciiname":"Bjelas",
    "gn:country_code":"BA",
    "gn:dem":92,
    "gn:feature_class":"P",
    "gn:feature_code":"PPL",
    "gn:name":"Bjela\u0161",
    "gn:population":0,
    "gn:timezone":"Europe/Sarajevo",
    "iso:country":"BA",
    "wof:name":"Bjelas",
    "wof:placetype":"locality"
},
  "geometry": {"coordinates":[18.00151,45.04684],"type":"Point"}
}