{
  "type": "Feature",
  "properties": {
    "gn:admin1_code":"02",
    "gn:asciiname":"Palije",
    "gn:country_code":"BA",
    "gn:dem":285,
    "gn:feature_class":"P",
    "gn:feature_code":"PPL",
    "gn:name":"Palije",
    "gn:population":0,
    "gn:timezone":"Europe/Sarajevo",
    "iso:country":"BA",
    "wof:name":"Palije",
    "wof:placetype":"locality"
},
  "geometry": {"coordinates":[16.59372999999999,45.18923],"type":"Point"}
}