{
  "type": "Feature",
  "properties": {
    "gn:admin1_code":"01",
    "gn:asciiname":"Demirovica Mahala",
    "gn:country_code":"BA",
    "gn:dem":113,
    "gn:feature_class":"P",
    "gn:feature_code":"PPL",
    "gn:name":"Demirovi\u0107a Mahala",
    "gn:population":0,
    "gn:timezone":"Europe/Sarajevo",
    "iso:country":"BA",
    "wof:name":"Demirovica Mahala",
    "wof:placetype":"locality"
},
  "geometry": {"coordinates":[17.84717999999999,43.22444],"type":"Point"}
}