{
  "type": "Feature",
  "properties": {
    "gn:admin1_code":"01",
    "gn:asciiname":"Okolista",
    "gn:country_code":"BA",
    "gn:dem":510,
    "gn:feature_class":"P",
    "gn:feature_code":"PPL",
    "gn:name":"Okoli\u0161ta",
    "gn:population":0,
    "gn:timezone":"Europe/Sarajevo",
    "iso:country":"BA",
    "wof:name":"Okolista",
    "wof:placetype":"locality"
},
  "geometry": {"coordinates":[18.81074,43.63832],"type":"Point"}
}