{
  "type": "Feature",
  "properties": {
    "gn:admin1_code":"01",
    "gn:asciiname":"Dubravica",
    "gn:country_code":"BA",
    "gn:dem":140,
    "gn:feature_class":"P",
    "gn:feature_code":"PPL",
    "gn:name":"Dubravica",
    "gn:population":0,
    "gn:timezone":"Europe/Sarajevo",
    "iso:country":"BA",
    "wof:name":"Dubravica",
    "wof:placetype":"locality"
},
  "geometry": {"coordinates":[17.73777999999999,43.02694],"type":"Point"}
}