{
  "type": "Feature",
  "properties": {
    "gn:admin1_code":"01",
    "gn:asciiname":"Tomina Pojata",
    "gn:country_code":"BA",
    "gn:dem":1285,
    "gn:feature_class":"P",
    "gn:feature_code":"PPL",
    "gn:name":"Tomina Pojata",
    "gn:population":0,
    "gn:timezone":"Europe/Sarajevo",
    "iso:country":"BA",
    "wof:name":"Tomina Pojata",
    "wof:placetype":"locality"
},
  "geometry": {"coordinates":[17.00745,44.02708],"type":"Point"}
}