{
  "type": "Feature",
  "properties": {
    "gn:admin1_code":"02",
    "gn:asciiname":"Majevac",
    "gn:country_code":"BA",
    "gn:dem":523,
    "gn:feature_class":"P",
    "gn:feature_code":"PPLL",
    "gn:name":"Majevac",
    "gn:population":0,
    "gn:timezone":"Europe/Sarajevo",
    "iso:country":"BA",
    "wof:name":"Majevac",
    "wof:placetype":"locality"
},
  "geometry": {"coordinates":[17.0379,44.24153],"type":"Point"}
}