{
  "type": "Feature",
  "properties": {
    "gn:admin1_code":"01",
    "gn:asciiname":"Gornji Zegar",
    "gn:country_code":"BA",
    "gn:dem":152,
    "gn:feature_class":"P",
    "gn:feature_code":"PPL",
    "gn:name":"Gornji \u017degar",
    "gn:population":0,
    "gn:timezone":"Europe/Sarajevo",
    "iso:country":"BA",
    "wof:name":"Gornji Zegar",
    "wof:placetype":"locality"
},
  "geometry": {"coordinates":[16.18139,44.95611],"type":"Point"}
}