{
  "type": "Feature",
  "properties": {
    "gn:admin1_code":"02",
    "gn:asciiname":"Gornji Teslic",
    "gn:country_code":"BA",
    "gn:dem":277,
    "gn:feature_class":"P",
    "gn:feature_code":"PPL",
    "gn:name":"Gornji Tesli\u0107",
    "gn:population":0,
    "gn:timezone":"Europe/Sarajevo",
    "iso:country":"BA",
    "name:und_x_variant":[
        "Tesli\u0107 Gornji",
        "Tesli\u0107 Gusti",
        "Gornji Tesli\u0107"
    ],
    "wof:name":"Gornji Teslic",
    "wof:placetype":"locality"
},
  "geometry": {"coordinates":[17.79732000000001,44.58305],"type":"Point"}
}