{
  "type": "Feature",
  "properties": {
    "gn:country":"BA",
    "gn:fcode":"PPL",
    "gn:pop":332,
    "iso:country":"BA",
    "qs:name":"Medakova Glavica",
    "qs:photos_9r":0,
    "qs:photos_sr":0,
    "qs:pop_sr":"2",
    "wof:name":"Medakova Glavica",
    "wof:placetype":"locality",
    "wof:population":332
},
  "geometry": {"coordinates":[15.87497,44.93593],"type":"Point"}
}