{
  "type": "Feature",
  "properties": {
    "gn:admin1_code":"01",
    "gn:asciiname":"Vlake",
    "gn:country_code":"BA",
    "gn:dem":320,
    "gn:feature_class":"P",
    "gn:feature_code":"PPL",
    "gn:name":"Vlake",
    "gn:population":0,
    "gn:timezone":"Europe/Sarajevo",
    "iso:country":"BA",
    "name:fra_x_preferred":[
        "Vlake"
    ],
    "name:fry_x_preferred":[
        "Vlake"
    ],
    "name:nld_x_preferred":[
        "Vlake"
    ],
    "name:tam_x_preferred":[
        "\u0bb5\u0bc6\u0bb2\u0b95\u0bcd"
    ],
    "name:zea_x_preferred":[
        "Vlaeke"
    ],
    "wof:name":"Vlake",
    "wof:placetype":"locality"
},
  "geometry": {"coordinates":[17.80878,43.24561],"type":"Point"}
}