{
  "type": "Feature",
  "properties": {
    "gn:admin1_code":"02",
    "gn:asciiname":"Borje",
    "gn:country_code":"BA",
    "gn:dem":1008,
    "gn:feature_class":"P",
    "gn:feature_code":"PPL",
    "gn:name":"Borje",
    "gn:population":0,
    "gn:timezone":"Europe/Sarajevo",
    "iso:country":"BA",
    "name:bos_x_preferred":[
        "Borje"
    ],
    "name:ceb_x_preferred":[
        "Borje"
    ],
    "name:fra_x_preferred":[
        "Borje"
    ],
    "name:hrv_x_preferred":[
        "Borje"
    ],
    "name:rus_x_preferred":[
        "\u0411\u043e\u0440\u044c\u0435"
    ],
    "name:srp_x_preferred":[
        "\u0411\u043e\u0440\u0458\u0435"
    ],
    "name:swe_x_preferred":[
        "Borje"
    ],
    "wof:name":"Borje",
    "wof:placetype":"locality"
},
  "geometry": {"coordinates":[18.95812,43.38433],"type":"Point"}
}