{
  "type": "Feature",
  "properties": {
    "gn:admin1_code":"00",
    "gn:asciiname":"Delici",
    "gn:country_code":"BA",
    "gn:dem":367,
    "gn:feature_class":"P",
    "gn:feature_code":"PPL",
    "gn:name":"Deli\u0107i",
    "gn:population":0,
    "gn:timezone":"Europe/Sarajevo",
    "iso:country":"BA",
    "wof:name":"Delici",
    "wof:placetype":"locality"
},
  "geometry": {"coordinates":[18.36085,44.38671],"type":"Point"}
}