{
  "type": "Feature",
  "properties": {
    "gn:admin1_code":"02",
    "gn:asciiname":"Todorovici",
    "gn:country_code":"BA",
    "gn:dem":848,
    "gn:feature_class":"P",
    "gn:feature_code":"PPL",
    "gn:name":"Todorovi\u0107i",
    "gn:population":0,
    "gn:timezone":"Europe/Sarajevo",
    "iso:country":"BA",
    "name:und_x_variant":[
        "Todorovi\u0107i"
    ],
    "wof:name":"Todorovici",
    "wof:placetype":"locality"
},
  "geometry": {"coordinates":[19.22099,43.57979],"type":"Point"}
}