{
  "type": "Feature",
  "properties": {
    "gn:admin1_code":"01",
    "gn:asciiname":"Kijev Do",
    "gn:country_code":"BA",
    "gn:dem":583,
    "gn:feature_class":"P",
    "gn:feature_code":"PPL",
    "gn:name":"Kijev Do",
    "gn:population":0,
    "gn:timezone":"Europe/Sarajevo",
    "iso:country":"BA",
    "name:bos_x_preferred":[
        "Kijev Do"
    ],
    "name:fra_x_preferred":[
        "Kijev Do"
    ],
    "name:hrv_x_preferred":[
        "Kijev Do"
    ],
    "name:srp_x_preferred":[
        "\u041a\u0438\u0458\u0435\u0432 \u0414\u043e"
    ],
    "wof:name":"Kijev Do",
    "wof:placetype":"locality"
},
  "geometry": {"coordinates":[17.9942,42.80703],"type":"Point"}
}