{
  "type": "Feature",
  "properties": {
    "gn:admin1_code":"01",
    "gn:asciiname":"Kijev Do",
    "gn:country_code":"BA",
    "gn:dem":583,
    "gn:feature_class":"P",
    "gn:feature_code":"PPL",
    "gn:name":"Kijev Do",
    "gn:population":0,
    "gn:timezone":"Europe/Sarajevo",
    "iso:country":"BA",
    "wof:name":"Kijev Do",
    "wof:placetype":"locality"
},
  "geometry": {"coordinates":[17.9942,42.80703],"type":"Point"}
}