{
  "type": "Feature",
  "properties": {
    "gn:admin1_code":"02",
    "gn:asciiname":"Velika Johova",
    "gn:country_code":"BA",
    "gn:dem":129,
    "gn:feature_class":"P",
    "gn:feature_code":"PPL",
    "gn:name":"Velika Johova",
    "gn:population":0,
    "gn:timezone":"Europe/Sarajevo",
    "iso:country":"BA",
    "wof:name":"Velika Johova",
    "wof:placetype":"locality"
},
  "geometry": {"coordinates":[16.70135,45.18634],"type":"Point"}
}