{
  "type": "Feature",
  "properties": {
    "gn:admin1_code":"01",
    "gn:asciiname":"Spahici",
    "gn:country_code":"BA",
    "gn:dem":241,
    "gn:feature_class":"P",
    "gn:feature_code":"PPL",
    "gn:name":"Spahi\u0107i",
    "gn:population":0,
    "gn:timezone":"Europe/Sarajevo",
    "iso:country":"BA",
    "wof:name":"Spahici",
    "wof:placetype":"locality"
},
  "geometry": {"coordinates":[18.08887,44.61955],"type":"Point"}
}