{
  "type": "Feature",
  "properties": {
    "gn:admin1_code":"01",
    "gn:asciiname":"Zugolj",
    "gn:country_code":"BA",
    "gn:dem":530,
    "gn:feature_class":"P",
    "gn:feature_code":"PPL",
    "gn:name":"\u017dugolj",
    "gn:population":0,
    "gn:timezone":"Europe/Sarajevo",
    "iso:country":"BA",
    "wof:name":"Zugolj",
    "wof:placetype":"locality"
},
  "geometry": {"coordinates":[18.10862,44.15481],"type":"Point"}
}