{
  "type": "Feature",
  "properties": {
    "gn:admin1_code":"02",
    "gn:asciiname":"Solakovici",
    "gn:country_code":"BA",
    "gn:dem":792,
    "gn:feature_class":"P",
    "gn:feature_code":"PPLL",
    "gn:name":"Solakovi\u0107i",
    "gn:population":0,
    "gn:timezone":"Europe/Sarajevo",
    "iso:country":"BA",
    "wof:name":"Solakovici",
    "wof:placetype":"locality"
},
  "geometry": {"coordinates":[19.09591,43.73987],"type":"Point"}
}