{
  "type": "Feature",
  "properties": {
    "gn:admin1_code":"02",
    "gn:asciiname":"Pekija",
    "gn:country_code":"BA",
    "gn:dem":328,
    "gn:feature_class":"P",
    "gn:feature_code":"PPL",
    "gn:name":"Pekija",
    "gn:population":0,
    "gn:timezone":"Europe/Sarajevo",
    "iso:country":"BA",
    "wof:name":"Pekija",
    "wof:placetype":"locality"
},
  "geometry": {"coordinates":[16.65535,45.07927],"type":"Point"}
}