{
  "type": "Feature",
  "properties": {
    "gn:admin1_code":"BRC",
    "gn:asciiname":"Njiverice",
    "gn:country_code":"BA",
    "gn:dem":109,
    "gn:feature_class":"P",
    "gn:feature_code":"PPL",
    "gn:name":"Njiverice",
    "gn:population":0,
    "gn:timezone":"Europe/Sarajevo",
    "iso:country":"BA",
    "wof:name":"Njiverice",
    "wof:placetype":"locality"
},
  "geometry": {"coordinates":[18.77421,44.8126],"type":"Point"}
}