{
  "type": "Feature",
  "properties": {
    "gn:admin1_code":"02",
    "gn:asciiname":"Kelemani",
    "gn:country_code":"BA",
    "gn:dem":1108,
    "gn:feature_class":"P",
    "gn:feature_code":"PPL",
    "gn:name":"Kelemani",
    "gn:population":0,
    "gn:timezone":"Europe/Sarajevo",
    "iso:country":"BA",
    "wof:name":"Kelemani",
    "wof:placetype":"locality"
},
  "geometry": {"coordinates":[17.47197,44.40269],"type":"Point"}
}