{
  "type": "Feature",
  "properties": {
    "gn:admin1_code":"02",
    "gn:asciiname":"Mala Jelovaca",
    "gn:country_code":"BA",
    "gn:dem":291,
    "gn:feature_class":"P",
    "gn:feature_code":"PPL",
    "gn:name":"Mala Jelova\u010da",
    "gn:population":0,
    "gn:timezone":"Europe/Sarajevo",
    "iso:country":"BA",
    "wof:name":"Mala Jelovaca",
    "wof:placetype":"locality"
},
  "geometry": {"coordinates":[17.44333,44.74806],"type":"Point"}
}