{
  "type": "Feature",
  "properties": {
    "gn:admin1_code":"01",
    "gn:asciiname":"Cirkici",
    "gn:country_code":"BA",
    "gn:dem":381,
    "gn:feature_class":"P",
    "gn:feature_code":"PPL",
    "gn:name":"\u010cirki\u0107i",
    "gn:population":0,
    "gn:timezone":"Europe/Sarajevo",
    "iso:country":"BA",
    "wof:name":"Cirkici",
    "wof:placetype":"locality"
},
  "geometry": {"coordinates":[16.51111,44.82944000000001],"type":"Point"}
}