{
  "type": "Feature",
  "properties": {
    "gn:admin1_code":"01",
    "gn:asciiname":"Stojakovici",
    "gn:country_code":"BA",
    "gn:dem":380,
    "gn:feature_class":"P",
    "gn:feature_code":"PPL",
    "gn:name":"Stojakovi\u0107i",
    "gn:population":0,
    "gn:timezone":"Europe/Sarajevo",
    "iso:country":"BA",
    "wof:name":"Stojakovici",
    "wof:placetype":"locality"
},
  "geometry": {"coordinates":[16.13528,45.05556],"type":"Point"}
}