{
  "type": "Feature",
  "properties": {
    "gn:admin1_code":"02",
    "gn:asciiname":"Zilici",
    "gn:country_code":"BA",
    "gn:dem":509,
    "gn:feature_class":"P",
    "gn:feature_code":"PPL",
    "gn:name":"\u017dili\u0107i",
    "gn:population":0,
    "gn:timezone":"Europe/Sarajevo",
    "iso:country":"BA",
    "wof:name":"Zilici",
    "wof:placetype":"locality"
},
  "geometry": {"coordinates":[17.51666,44.59015],"type":"Point"}
}