{
  "type": "Feature",
  "properties": {
    "gn:admin1_code":"02",
    "gn:asciiname":"Milojevici",
    "gn:country_code":"BA",
    "gn:dem":397,
    "gn:feature_class":"P",
    "gn:feature_code":"PPL",
    "gn:name":"Milojevi\u0107i",
    "gn:population":0,
    "gn:timezone":"Europe/Sarajevo",
    "iso:country":"BA",
    "wof:name":"Milojevici",
    "wof:placetype":"locality"
},
  "geometry": {"coordinates":[17.00696,44.72145],"type":"Point"}
}