{
  "type": "Feature",
  "properties": {
    "gn:admin1_code":"02",
    "gn:asciiname":"Ljubomir",
    "gn:country_code":"BA",
    "gn:dem":554,
    "gn:feature_class":"P",
    "gn:feature_code":"PPL",
    "gn:name":"Ljubomir",
    "gn:population":0,
    "gn:timezone":"Europe/Sarajevo",
    "iso:country":"BA",
    "wof:name":"Ljubomir",
    "wof:placetype":"locality"
},
  "geometry": {"coordinates":[18.33638,42.79119],"type":"Point"}
}