{
  "type": "Feature",
  "properties": {
    "gn:admin1_code":"01",
    "gn:asciiname":"Tomina",
    "gn:country_code":"BA",
    "gn:dem":331,
    "gn:feature_class":"P",
    "gn:feature_code":"PPL",
    "gn:name":"Tomina",
    "gn:population":0,
    "gn:timezone":"Europe/Sarajevo",
    "iso:country":"BA",
    "wof:name":"Tomina",
    "wof:placetype":"locality"
},
  "geometry": {"coordinates":[16.7556,44.70948],"type":"Point"}
}