{
  "type": "Feature",
  "properties": {
    "gn:admin1_code":"01",
    "gn:asciiname":"Majstorovici",
    "gn:country_code":"BA",
    "gn:dem":771,
    "gn:feature_class":"P",
    "gn:feature_code":"PPL",
    "gn:name":"Majstorovi\u0107i",
    "gn:population":0,
    "gn:timezone":"Europe/Sarajevo",
    "iso:country":"BA",
    "wof:name":"Majstorovici",
    "wof:placetype":"locality"
},
  "geometry": {"coordinates":[16.55859,44.09216],"type":"Point"}
}