{
  "type": "Feature",
  "properties": {
    "gn:admin1_code":"01",
    "gn:asciiname":"Donji Polog",
    "gn:country_code":"BA",
    "gn:dem":421,
    "gn:feature_class":"P",
    "gn:feature_code":"PPLL",
    "gn:name":"Donji Polog",
    "gn:population":0,
    "gn:timezone":"Europe/Sarajevo",
    "iso:country":"BA",
    "wof:name":"Donji Polog",
    "wof:placetype":"locality"
},
  "geometry": {"coordinates":[17.71995,43.34665],"type":"Point"}
}