{
  "type": "Feature",
  "properties": {
    "gn:admin1_code":"02",
    "gn:asciiname":"Zagoni",
    "gn:country_code":"BA",
    "gn:dem":143,
    "gn:feature_class":"P",
    "gn:feature_code":"PPLL",
    "gn:name":"Zagoni",
    "gn:population":0,
    "gn:timezone":"Europe/Sarajevo",
    "iso:country":"BA",
    "wof:name":"Zagoni",
    "wof:placetype":"locality"
},
  "geometry": {"coordinates":[19.10101,44.72194],"type":"Point"}
}