{
  "type": "Feature",
  "properties": {
    "gn:admin1_code":"02",
    "gn:asciiname":"Telici",
    "gn:country_code":"BA",
    "gn:dem":292,
    "gn:feature_class":"P",
    "gn:feature_code":"PPL",
    "gn:name":"Teli\u0107i",
    "gn:population":0,
    "gn:timezone":"Europe/Sarajevo",
    "iso:country":"BA",
    "wof:name":"Telici",
    "wof:placetype":"locality"
},
  "geometry": {"coordinates":[17.05611,44.83111],"type":"Point"}
}