{
  "type": "Feature",
  "properties": {
    "gn:admin1_code":"01",
    "gn:asciiname":"Kudici",
    "gn:country_code":"BA",
    "gn:dem":444,
    "gn:feature_class":"P",
    "gn:feature_code":"PPLL",
    "gn:name":"Kudi\u0107i",
    "gn:population":0,
    "gn:timezone":"Europe/Sarajevo",
    "iso:country":"BA",
    "name:und_x_variant":[
        "Kudi\u0107 Selo",
        "Kudi\u0107i"
    ],
    "wof:name":"Kudici",
    "wof:placetype":"locality"
},
  "geometry": {"coordinates":[15.81559,45.08351],"type":"Point"}
}