{
  "type": "Feature",
  "properties": {
    "gn:admin1_code":"02",
    "gn:asciiname":"Tramosljani",
    "gn:country_code":"BA",
    "gn:dem":158,
    "gn:feature_class":"P",
    "gn:feature_code":"PPL",
    "gn:name":"Tramo\u0161ljani",
    "gn:population":0,
    "gn:timezone":"Europe/Sarajevo",
    "iso:country":"BA",
    "wof:name":"Tramosljani",
    "wof:placetype":"locality"
},
  "geometry": {"coordinates":[17.23177,44.94765],"type":"Point"}
}