{
  "type": "Feature",
  "properties": {
    "gn:admin1_code":"01",
    "gn:asciiname":"Okici",
    "gn:country_code":"BA",
    "gn:dem":183,
    "gn:feature_class":"P",
    "gn:feature_code":"PPL",
    "gn:name":"Oki\u0107i",
    "gn:population":0,
    "gn:timezone":"Europe/Sarajevo",
    "iso:country":"BA",
    "wof:name":"Okici",
    "wof:placetype":"locality"
},
  "geometry": {"coordinates":[18.41053,44.86506],"type":"Point"}
}