{
  "type": "Feature",
  "properties": {
    "gn:country":"BA",
    "gn:fcode":"PPL",
    "gn:pop":4508,
    "iso:country":"BA",
    "name:bos_x_preferred":[
        "Vlasenica"
    ],
    "name:deu_x_preferred":[
        "Vlasenica"
    ],
    "name:eng_x_preferred":[
        "Vlasenica"
    ],
    "name:fas_x_preferred":[
        "\u0648\u0644\u0627\u0633\u0646\u06cc\u062a\u0633\u0627"
    ],
    "name:fra_x_preferred":[
        "Vlasenica"
    ],
    "name:heb_x_preferred":[
        "\u05d5\u05dc\u05d0\u05e1\u05e0\u05d9\u05e6\u05d4"
    ],
    "name:hrv_x_preferred":[
        "Vlasenica"
    ],
    "name:hye_x_preferred":[
        "\u054e\u056c\u0561\u057d\u0565\u0576\u056b\u0581\u0561"
    ],
    "name:ita_x_preferred":[
        "Vlasenica"
    ],
    "name:jpn_x_preferred":[
        "\u30f4\u30e9\u30bb\u30cb\u30c4\u30a1"
    ],
    "name:kor_x_preferred":[
        "\ube14\ub77c\uc138\ub2c8\ucc28"
    ],
    "name:nld_x_preferred":[
        "Vlasenica"
    ],
    "name:nob_x_preferred":[
        "Vlasenica"
    ],
    "name:pol_x_preferred":[
        "Vlasenica"
    ],
    "name:rus_x_preferred":[
        "\u0412\u043b\u0430\u0441\u0435\u043d\u0438\u0446\u0430"
    ],
    "name:slv_x_preferred":[
        "Vlasenica"
    ],
    "name:spa_x_preferred":[
        "Vlasenica"
    ],
    "name:srp_x_preferred":[
        "\u0412\u043b\u0430\u0441\u0435\u043d\u0438\u0446\u0430"
    ],
    "name:swe_x_preferred":[
        "Vlasenica"
    ],
    "name:unk_x_variant":[
        "Vlasenice"
    ],
    "name:urd_x_preferred":[
        "\u0648\u0644\u0627\u0633\u06cc\u0646\u06cc\u062a\u0633\u0627"
    ],
    "name:zho_x_preferred":[
        "\u5f17\u62c9\u585e\u5c3c\u5bdf"
    ],
    "qs:name":"Vlasenica",
    "qs:photos_9r":0,
    "qs:photos_sr":0,
    "qs:pop_sr":"4",
    "wd:wordcount":252,
    "wof:name":"Vlasenica",
    "wof:placetype":"locality",
    "wof:population":4508
},
  "geometry": {"coordinates":[18.94096,44.18183],"type":"Point"}
}