{
  "type": "Feature",
  "properties": {
    "gn:admin1_code":"BRC",
    "gn:asciiname":"Petrici",
    "gn:country_code":"BA",
    "gn:dem":138,
    "gn:feature_class":"P",
    "gn:feature_code":"PPL",
    "gn:name":"Petri\u0107i",
    "gn:population":0,
    "gn:timezone":"Europe/Sarajevo",
    "iso:country":"BA",
    "wof:name":"Petrici",
    "wof:placetype":"locality"
},
  "geometry": {"coordinates":[18.83674,44.80817],"type":"Point"}
}