{
  "type": "Feature",
  "properties": {
    "gn:admin1_code":"02",
    "gn:asciiname":"Ravnice",
    "gn:country_code":"BA",
    "gn:dem":169,
    "gn:feature_class":"P",
    "gn:feature_code":"PPLL",
    "gn:name":"Ravnice",
    "gn:population":0,
    "gn:timezone":"Europe/Sarajevo",
    "iso:country":"BA",
    "name:und_x_variant":[
        "Donje Ravnice",
        "Ravnice"
    ],
    "wof:name":"Ravnice",
    "wof:placetype":"locality"
},
  "geometry": {"coordinates":[16.42005,45.10541],"type":"Point"}
}