{
  "type": "Feature",
  "properties": {
    "gn:admin1_code":"01",
    "gn:asciiname":"Sulici",
    "gn:country_code":"BA",
    "gn:dem":957,
    "gn:feature_class":"P",
    "gn:feature_code":"PPL",
    "gn:name":"Suli\u0107i",
    "gn:population":0,
    "gn:timezone":"Europe/Sarajevo",
    "iso:country":"BA",
    "wof:name":"Sulici",
    "wof:placetype":"locality"
},
  "geometry": {"coordinates":[17.2835,43.57082],"type":"Point"}
}