{
  "type": "Feature",
  "properties": {
    "gn:admin1_code":"02",
    "gn:asciiname":"Donje Selo",
    "gn:country_code":"BA",
    "gn:dem":1073,
    "gn:feature_class":"P",
    "gn:feature_code":"PPL",
    "gn:name":"Donje Selo",
    "gn:population":0,
    "gn:timezone":"Europe/Sarajevo",
    "iso:country":"BA",
    "name:bos_x_preferred":[
        "Donje Selo"
    ],
    "name:ceb_x_preferred":[
        "Donje Selo"
    ],
    "name:fra_x_preferred":[
        "Donje Selo"
    ],
    "name:hrv_x_preferred":[
        "Donje Selo"
    ],
    "name:hun_x_preferred":[
        "Donje Selo"
    ],
    "name:nld_x_preferred":[
        "Donje Selo"
    ],
    "name:slv_x_preferred":[
        "Donje Selo"
    ],
    "name:srp_x_preferred":[
        "\u0414\u043e\u045a\u0435 \u0421\u0435\u043b\u043e"
    ],
    "name:swe_x_preferred":[
        "Donje Selo"
    ],
    "wof:name":"Donje Selo",
    "wof:placetype":"locality"
},
  "geometry": {"coordinates":[18.34882,43.16411],"type":"Point"}
}