{
  "type": "Feature",
  "properties": {
    "gn:admin1_code":"01",
    "gn:asciiname":"Zaseok",
    "gn:country_code":"BA",
    "gn:dem":605,
    "gn:feature_class":"P",
    "gn:feature_code":"PPL",
    "gn:name":"Zaseok",
    "gn:population":0,
    "gn:timezone":"Europe/Sarajevo",
    "iso:country":"BA",
    "name:bos_x_preferred":[
        "Zaseok"
    ],
    "name:fra_x_preferred":[
        "Zaseok"
    ],
    "name:hrv_x_preferred":[
        "Zaseok"
    ],
    "name:srp_x_preferred":[
        "\u0417\u0430\u0441\u0435\u043e\u043a"
    ],
    "wof:name":"Zaseok",
    "wof:placetype":"locality"
},
  "geometry": {"coordinates":[16.25607999999999,44.19531],"type":"Point"}
}