{
  "type": "Feature",
  "properties": {
    "gn:admin1_code":"02",
    "gn:asciiname":"Banjsko Brdo",
    "gn:country_code":"BA",
    "gn:dem":121,
    "gn:feature_class":"P",
    "gn:feature_code":"PPL",
    "gn:name":"Banjsko Brdo",
    "gn:population":0,
    "gn:timezone":"Europe/Sarajevo",
    "iso:country":"BA",
    "wof:name":"Banjsko Brdo",
    "wof:placetype":"locality"
},
  "geometry": {"coordinates":[16.88089,45.19129],"type":"Point"}
}