{
  "type": "Feature",
  "properties": {
    "gn:admin1_code":"01",
    "gn:asciiname":"Zaselo",
    "gn:country_code":"BA",
    "gn:dem":887,
    "gn:feature_class":"P",
    "gn:feature_code":"PPL",
    "gn:name":"Zaselo",
    "gn:population":0,
    "gn:timezone":"Europe/Sarajevo",
    "iso:country":"BA",
    "wof:name":"Zaselo",
    "wof:placetype":"locality"
},
  "geometry": {"coordinates":[17.56657,44.20314000000001],"type":"Point"}
}