{
  "type": "Feature",
  "properties": {
    "gn:admin1_code":"01",
    "gn:asciiname":"Zaljesce",
    "gn:country_code":"BA",
    "gn:dem":1078,
    "gn:feature_class":"P",
    "gn:feature_code":"PPL",
    "gn:name":"Zalje\u0161\u0107e",
    "gn:population":0,
    "gn:timezone":"Europe/Sarajevo",
    "iso:country":"BA",
    "wof:name":"Zaljesce",
    "wof:placetype":"locality"
},
  "geometry": {"coordinates":[18.75776,43.70758],"type":"Point"}
}