{
  "type": "Feature",
  "properties": {
    "gn:admin1_code":"01",
    "gn:asciiname":"Kokorovic",
    "gn:country_code":"BA",
    "gn:dem":402,
    "gn:feature_class":"P",
    "gn:feature_code":"PPL",
    "gn:name":"Kokorovi\u0107",
    "gn:population":0,
    "gn:timezone":"Europe/Sarajevo",
    "iso:country":"BA",
    "wof:name":"Kokorovic",
    "wof:placetype":"locality"
},
  "geometry": {"coordinates":[18.43199,44.24753],"type":"Point"}
}