{
  "type": "Feature",
  "properties": {
    "gn:admin1_code":"01",
    "gn:asciiname":"Poljani",
    "gn:country_code":"BA",
    "gn:dem":644,
    "gn:feature_class":"P",
    "gn:feature_code":"PPL",
    "gn:name":"Poljani",
    "gn:population":0,
    "gn:timezone":"Europe/Sarajevo",
    "iso:country":"BA",
    "name:bos_x_preferred":[
        "Poljani"
    ],
    "name:fra_x_preferred":[
        "Poljani"
    ],
    "name:hrv_x_preferred":[
        "Poljani"
    ],
    "name:hun_x_preferred":[
        "Poljani"
    ],
    "name:nld_x_preferred":[
        "Poljani"
    ],
    "name:rus_x_preferred":[
        "\u041f\u043e\u043b\u044f\u043d\u0435"
    ],
    "name:slk_x_preferred":[
        "Po\u013eany"
    ],
    "name:slv_x_preferred":[
        "Poljani"
    ],
    "name:srp_x_preferred":[
        "\u041f\u043e\u0459\u0430\u043d\u0438"
    ],
    "wof:name":"Poljani",
    "wof:placetype":"locality"
},
  "geometry": {"coordinates":[18.08623,43.86574],"type":"Point"}
}