{
  "type": "Feature",
  "properties": {
    "gn:admin1_code":"01",
    "gn:asciiname":"Poljani",
    "gn:country_code":"BA",
    "gn:dem":644,
    "gn:feature_class":"P",
    "gn:feature_code":"PPL",
    "gn:name":"Poljani",
    "gn:population":0,
    "gn:timezone":"Europe/Sarajevo",
    "iso:country":"BA",
    "wof:name":"Poljani",
    "wof:placetype":"locality"
},
  "geometry": {"coordinates":[18.08623,43.86574],"type":"Point"}
}