{
  "type": "Feature",
  "properties": {
    "gn:admin1_code":"02",
    "gn:asciiname":"Gojici",
    "gn:country_code":"BA",
    "gn:dem":279,
    "gn:feature_class":"P",
    "gn:feature_code":"PPL",
    "gn:name":"Goji\u0107i",
    "gn:population":0,
    "gn:timezone":"Europe/Sarajevo",
    "iso:country":"BA",
    "wof:name":"Gojici",
    "wof:placetype":"locality"
},
  "geometry": {"coordinates":[17.84111,44.70167],"type":"Point"}
}