{
  "type": "Feature",
  "properties": {
    "gn:admin1_code":"02",
    "gn:asciiname":"Sivolji",
    "gn:country_code":"BA",
    "gn:dem":1169,
    "gn:feature_class":"P",
    "gn:feature_code":"PPLL",
    "gn:name":"Sivolji",
    "gn:population":0,
    "gn:timezone":"Europe/Sarajevo",
    "iso:country":"BA",
    "name:und_x_variant":[
        "\u0160ivolje",
        "Sivolji"
    ],
    "wof:name":"Sivolji",
    "wof:placetype":"locality"
},
  "geometry": {"coordinates":[18.5134,43.53175],"type":"Point"}
}