{
  "type": "Feature",
  "properties": {
    "gn:admin1_code":"02",
    "gn:asciiname":"Kumala",
    "gn:country_code":"BA",
    "gn:dem":606,
    "gn:feature_class":"P",
    "gn:feature_code":"PPL",
    "gn:name":"Kumala",
    "gn:population":0,
    "gn:timezone":"Europe/Sarajevo",
    "iso:country":"BA",
    "wof:name":"Kumala",
    "wof:placetype":"locality"
},
  "geometry": {"coordinates":[17.21937,44.72655],"type":"Point"}
}