{
  "type": "Feature",
  "properties": {
    "gn:admin1_code":"01",
    "gn:asciiname":"Sici",
    "gn:country_code":"BA",
    "gn:dem":219,
    "gn:feature_class":"P",
    "gn:feature_code":"PPL",
    "gn:name":"\u0160i\u0107i",
    "gn:population":0,
    "gn:timezone":"Europe/Sarajevo",
    "iso:country":"BA",
    "wof:name":"Sici",
    "wof:placetype":"locality"
},
  "geometry": {"coordinates":[18.57567,44.51944],"type":"Point"}
}