{
  "type": "Feature",
  "properties": {
    "gn:admin1_code":"01",
    "gn:asciiname":"Pavice",
    "gn:country_code":"BA",
    "gn:dem":850,
    "gn:feature_class":"P",
    "gn:feature_code":"PPL",
    "gn:name":"Pavice",
    "gn:population":0,
    "gn:timezone":"Europe/Sarajevo",
    "iso:country":"BA",
    "name:bos_x_preferred":[
        "Pavice"
    ],
    "name:ceb_x_preferred":[
        "Pavice"
    ],
    "name:fra_x_preferred":[
        "Pavice"
    ],
    "name:srp_x_preferred":[
        "\u041f\u0430\u0432\u0438\u0446\u0435"
    ],
    "name:swe_x_preferred":[
        "Pavice"
    ],
    "wof:name":"Pavice",
    "wof:placetype":"locality"
},
  "geometry": {"coordinates":[17.52887999999999,44.01656],"type":"Point"}
}