{
  "type": "Feature",
  "properties": {
    "gn:admin1_code":"02",
    "gn:asciiname":"Suvaja",
    "gn:country_code":"BA",
    "gn:dem":121,
    "gn:feature_class":"P",
    "gn:feature_code":"PPLL",
    "gn:name":"Suvaja",
    "gn:population":0,
    "gn:timezone":"Europe/Sarajevo",
    "iso:country":"BA",
    "name:bos_x_preferred":[
        "Suvaja"
    ],
    "name:bul_x_preferred":[
        "\u0421\u0443\u0432\u0430\u044f"
    ],
    "name:ceb_x_preferred":[
        "Suvaja"
    ],
    "name:fra_x_preferred":[
        "Suvaja"
    ],
    "name:hrv_x_preferred":[
        "Suvaja"
    ],
    "name:nld_x_preferred":[
        "Suvaja"
    ],
    "name:por_x_preferred":[
        "Suvaja"
    ],
    "name:slv_x_preferred":[
        "Suvaja"
    ],
    "name:srp_x_preferred":[
        "\u0421\u0443\u0432\u0430\u0458\u0430"
    ],
    "name:swe_x_preferred":[
        "Suvaja"
    ],
    "wof:name":"Suvaja",
    "wof:placetype":"locality"
},
  "geometry": {"coordinates":[16.72634,45.19613],"type":"Point"}
}