{
  "type": "Feature",
  "properties": {
    "gn:admin1_code":"01",
    "gn:asciiname":"Vrazalice",
    "gn:country_code":"BA",
    "gn:dem":943,
    "gn:feature_class":"P",
    "gn:feature_code":"PPLL",
    "gn:name":"Vra\u017ealice",
    "gn:population":0,
    "gn:timezone":"Europe/Sarajevo",
    "iso:country":"BA",
    "wof:name":"Vrazalice",
    "wof:placetype":"locality"
},
  "geometry": {"coordinates":[18.92027,43.74405],"type":"Point"}
}