{
  "type": "Feature",
  "properties": {
    "gn:admin1_code":"02",
    "gn:asciiname":"Kraljicani",
    "gn:country_code":"BA",
    "gn:dem":88,
    "gn:feature_class":"P",
    "gn:feature_code":"PPL",
    "gn:name":"Kralji\u010dani",
    "gn:population":0,
    "gn:timezone":"Europe/Sarajevo",
    "iso:country":"BA",
    "wof:name":"Kraljicani",
    "wof:placetype":"locality"
},
  "geometry": {"coordinates":[18.49736,44.96097],"type":"Point"}
}