{
  "type": "Feature",
  "properties": {
    "gn:admin1_code":"01",
    "gn:asciiname":"Popovici",
    "gn:country_code":"BA",
    "gn:dem":661,
    "gn:feature_class":"P",
    "gn:feature_code":"PPL",
    "gn:name":"Popovi\u0107i",
    "gn:population":0,
    "gn:timezone":"Europe/Sarajevo",
    "iso:country":"BA",
    "wof:name":"Popovici",
    "wof:placetype":"locality"
},
  "geometry": {"coordinates":[16.24285,44.36963],"type":"Point"}
}