{
  "type": "Feature",
  "properties": {
    "gn:admin1_code":"02",
    "gn:asciiname":"Smiljcici",
    "gn:country_code":"BA",
    "gn:dem":399,
    "gn:feature_class":"P",
    "gn:feature_code":"PPL",
    "gn:name":"Smilj\u010di\u0107i",
    "gn:population":0,
    "gn:timezone":"Europe/Sarajevo",
    "iso:country":"BA",
    "wof:name":"Smiljcici",
    "wof:placetype":"locality"
},
  "geometry": {"coordinates":[17.14166,44.93632],"type":"Point"}
}