{
  "type": "Feature",
  "properties": {
    "gn:admin1_code":"BRC",
    "gn:asciiname":"Baltici",
    "gn:country_code":"BA",
    "gn:dem":136,
    "gn:feature_class":"P",
    "gn:feature_code":"PPL",
    "gn:name":"Balti\u0107i",
    "gn:population":0,
    "gn:timezone":"Europe/Sarajevo",
    "iso:country":"BA",
    "wof:name":"Baltici",
    "wof:placetype":"locality"
},
  "geometry": {"coordinates":[18.87651,44.80255],"type":"Point"}
}