{
  "type": "Feature",
  "properties": {
    "gn:admin1_code":"01",
    "gn:asciiname":"Vrbanja",
    "gn:country_code":"BA",
    "gn:dem":717,
    "gn:feature_class":"P",
    "gn:feature_code":"PPL",
    "gn:name":"Vrbanja",
    "gn:population":0,
    "gn:timezone":"Europe/Sarajevo",
    "iso:country":"BA",
    "name:bos_x_preferred":[
        "Vrbanja"
    ],
    "name:fra_x_preferred":[
        "Vrbanja"
    ],
    "wof:name":"Vrbanja",
    "wof:placetype":"locality"
},
  "geometry": {"coordinates":[18.08167000000001,43.78417],"type":"Point"}
}