{
  "type": "Feature",
  "properties": {
    "gn:admin1_code":"02",
    "gn:asciiname":"Zelenka",
    "gn:country_code":"BA",
    "gn:dem":833,
    "gn:feature_class":"P",
    "gn:feature_code":"PPL",
    "gn:name":"Zelenka",
    "gn:population":0,
    "gn:timezone":"Europe/Sarajevo",
    "iso:country":"BA",
    "wof:name":"Zelenka",
    "wof:placetype":"locality"
},
  "geometry": {"coordinates":[18.86934,43.50992],"type":"Point"}
}