{
  "type": "Feature",
  "properties": {
    "gn:admin1_code":"02",
    "gn:asciiname":"Zarkovina",
    "gn:country_code":"BA",
    "gn:dem":213,
    "gn:feature_class":"P",
    "gn:feature_code":"PPL",
    "gn:name":"\u017darkovina",
    "gn:population":0,
    "gn:timezone":"Europe/Sarajevo",
    "iso:country":"BA",
    "name:bos_x_preferred":[
        "\u017darkovina"
    ],
    "name:ceb_x_preferred":[
        "\u017darkovina"
    ],
    "name:fra_x_preferred":[
        "\u017darkovina"
    ],
    "name:srp_x_preferred":[
        "\u0416\u0430\u0440\u043a\u043e\u0432\u0438\u043d\u0430"
    ],
    "name:swe_x_preferred":[
        "\u017darkovina"
    ],
    "wof:name":"Zarkovina",
    "wof:placetype":"locality"
},
  "geometry": {"coordinates":[17.84977,44.63231],"type":"Point"}
}