{
  "type": "Feature",
  "properties": {
    "gn:admin1_code":"02",
    "gn:asciiname":"Zarkovina",
    "gn:country_code":"BA",
    "gn:dem":213,
    "gn:feature_class":"P",
    "gn:feature_code":"PPL",
    "gn:name":"\u017darkovina",
    "gn:population":0,
    "gn:timezone":"Europe/Sarajevo",
    "iso:country":"BA",
    "name:und_x_variant":[
        "\u017darkovina"
    ],
    "wof:name":"Zarkovina",
    "wof:placetype":"locality"
},
  "geometry": {"coordinates":[17.84977,44.63231],"type":"Point"}
}