{
  "type": "Feature",
  "properties": {
    "gn:admin1_code":"02",
    "gn:asciiname":"Uksici",
    "gn:country_code":"BA",
    "gn:dem":533,
    "gn:feature_class":"P",
    "gn:feature_code":"PPL",
    "gn:name":"Uk\u0161i\u0107i",
    "gn:population":0,
    "gn:timezone":"Europe/Sarajevo",
    "iso:country":"BA",
    "name:und_x_variant":[
        "Uk\u0161i\u0107i"
    ],
    "wof:name":"Uksici",
    "wof:placetype":"locality"
},
  "geometry": {"coordinates":[18.32042,42.78804],"type":"Point"}
}