{
  "type": "Feature",
  "properties": {
    "gn:admin1_code":"01",
    "gn:asciiname":"Corici",
    "gn:country_code":"BA",
    "gn:dem":310,
    "gn:feature_class":"P",
    "gn:feature_code":"PPL",
    "gn:name":"Cori\u0107i",
    "gn:population":0,
    "gn:timezone":"Europe/Sarajevo",
    "iso:country":"BA",
    "wof:name":"Corici",
    "wof:placetype":"locality"
},
  "geometry": {"coordinates":[18.3365,44.72263],"type":"Point"}
}