{
  "type": "Feature",
  "properties": {
    "gn:admin1_code":"01",
    "gn:asciiname":"Sisti",
    "gn:country_code":"BA",
    "gn:dem":322,
    "gn:feature_class":"P",
    "gn:feature_code":"PPL",
    "gn:name":"\u0160i\u0161ti",
    "gn:population":0,
    "gn:timezone":"Europe/Sarajevo",
    "iso:country":"BA",
    "name:deu_x_preferred":[
        "Sisti"
    ],
    "name:ita_x_preferred":[
        "Sisti"
    ],
    "wof:name":"Sisti",
    "wof:placetype":"locality"
},
  "geometry": {"coordinates":[15.87639,45.00056],"type":"Point"}
}