{
  "type": "Feature",
  "properties": {
    "gn:admin1_code":"01",
    "gn:asciiname":"Catici",
    "gn:country_code":"BA",
    "gn:dem":1149,
    "gn:feature_class":"P",
    "gn:feature_code":"PPL",
    "gn:name":"\u0106ati\u0107i",
    "gn:population":0,
    "gn:timezone":"Europe/Sarajevo",
    "iso:country":"BA",
    "wof:name":"Catici",
    "wof:placetype":"locality"
},
  "geometry": {"coordinates":[17.58116,44.32575],"type":"Point"}
}