{
  "type": "Feature",
  "properties": {
    "gn:admin1_code":"00",
    "gn:asciiname":"Balici",
    "gn:country_code":"BA",
    "gn:dem":503,
    "gn:feature_class":"P",
    "gn:feature_code":"PPL",
    "gn:name":"Bali\u0107i",
    "gn:population":0,
    "gn:timezone":"Europe/Sarajevo",
    "iso:country":"BA",
    "wof:name":"Balici",
    "wof:placetype":"locality"
},
  "geometry": {"coordinates":[18.39726,44.38323],"type":"Point"}
}