{
  "type": "Feature",
  "properties": {
    "gn:admin1_code":"02",
    "gn:asciiname":"Logor",
    "gn:country_code":"BA",
    "gn:dem":470,
    "gn:feature_class":"P",
    "gn:feature_code":"PPL",
    "gn:name":"Logor",
    "gn:population":0,
    "gn:timezone":"Europe/Sarajevo",
    "iso:country":"BA",
    "wof:name":"Logor",
    "wof:placetype":"locality"
},
  "geometry": {"coordinates":[18.41194,42.8675],"type":"Point"}
}