{
  "type": "Feature",
  "properties": {
    "gn:admin1_code":"02",
    "gn:asciiname":"Lazovi",
    "gn:country_code":"BA",
    "gn:dem":1000,
    "gn:feature_class":"P",
    "gn:feature_code":"PPL",
    "gn:name":"Lazovi",
    "gn:population":0,
    "gn:timezone":"Europe/Sarajevo",
    "iso:country":"BA",
    "wof:name":"Lazovi",
    "wof:placetype":"locality"
},
  "geometry": {"coordinates":[19.08644,44.00842],"type":"Point"}
}