{
  "type": "Feature",
  "properties": {
    "gn:admin1_code":"01",
    "gn:asciiname":"Zelenika",
    "gn:country_code":"BA",
    "gn:dem":406,
    "gn:feature_class":"P",
    "gn:feature_code":"PPL",
    "gn:name":"Zelenika",
    "gn:population":0,
    "gn:timezone":"Europe/Sarajevo",
    "iso:country":"BA",
    "name:bul_x_preferred":[
        "\u0417\u0435\u043b\u0435\u043d\u0438\u043a\u0430"
    ],
    "name:fas_x_preferred":[
        "\u0632\u0644\u0646\u06cc\u06a9\u0627"
    ],
    "name:kaz_x_preferred":[
        "\u0417\u0435\u043b\u0435\u043d\u0438\u043a\u0430"
    ],
    "name:pol_x_preferred":[
        "Zelenika"
    ],
    "name:ron_x_preferred":[
        "Zelenika"
    ],
    "name:rus_x_preferred":[
        "\u0417\u0435\u043b\u0435\u043d\u0438\u043a\u0430"
    ],
    "name:ukr_x_preferred":[
        "\u0417\u0435\u043b\u0435\u043d\u0438\u043a\u0430"
    ],
    "wof:name":"Zelenika",
    "wof:placetype":"locality"
},
  "geometry": {"coordinates":[17.91164,43.45719],"type":"Point"}
}