{
  "type": "Feature",
  "properties": {
    "gn:admin1_code":"01",
    "gn:asciiname":"Zelenika",
    "gn:country_code":"BA",
    "gn:dem":406,
    "gn:feature_class":"P",
    "gn:feature_code":"PPL",
    "gn:name":"Zelenika",
    "gn:population":0,
    "gn:timezone":"Europe/Sarajevo",
    "iso:country":"BA",
    "wof:name":"Zelenika",
    "wof:placetype":"locality"
},
  "geometry": {"coordinates":[17.91164,43.45719],"type":"Point"}
}