{
  "type": "Feature",
  "properties": {
    "gn:admin1_code":"02",
    "gn:asciiname":"Miholjevine",
    "gn:cc2":"BA",
    "gn:country_code":"BA",
    "gn:dem":807,
    "gn:feature_class":"P",
    "gn:feature_code":"PPL",
    "gn:name":"Miholjevine",
    "gn:population":0,
    "gn:timezone":"Europe/Sarajevo",
    "iso:country":"BA",
    "name:bos_x_preferred":[
        "Miholjevine"
    ],
    "name:bul_x_preferred":[
        "\u041c\u0438\u0445\u043e\u043b\u0435\u0432\u0438\u043d\u0435"
    ],
    "name:fra_x_preferred":[
        "Miholjevine"
    ],
    "name:hrv_x_preferred":[
        "Miholjevine"
    ],
    "name:srp_x_preferred":[
        "\u041c\u0438\u0445\u043e\u0459\u0435\u0432\u0438\u043d\u0435"
    ],
    "name:und_x_variant":[
        "Mihovljevina"
    ],
    "wof:name":"Miholjevine",
    "wof:placetype":"locality"
},
  "geometry": {"coordinates":[19.44972000000001,44.05194],"type":"Point"}
}