{
  "type": "Feature",
  "properties": {
    "gn:admin1_code":"02",
    "gn:asciiname":"Kuvelji",
    "gn:country_code":"BA",
    "gn:dem":987,
    "gn:feature_class":"P",
    "gn:feature_code":"PPL",
    "gn:name":"Kuvelji",
    "gn:population":0,
    "gn:timezone":"Europe/Sarajevo",
    "iso:country":"BA",
    "wof:name":"Kuvelji",
    "wof:placetype":"locality"
},
  "geometry": {"coordinates":[18.95671,43.53692],"type":"Point"}
}