{
  "type": "Feature",
  "properties": {
    "gn:admin1_code":"01",
    "gn:asciiname":"Seline",
    "gn:country_code":"BA",
    "gn:dem":712,
    "gn:feature_class":"P",
    "gn:feature_code":"PPL",
    "gn:name":"Seline",
    "gn:population":0,
    "gn:timezone":"Europe/Sarajevo",
    "iso:country":"BA",
    "wof:name":"Seline",
    "wof:placetype":"locality"
},
  "geometry": {"coordinates":[16.70853,43.99403],"type":"Point"}
}