{
  "type": "Feature",
  "properties": {
    "gn:admin1_code":"01",
    "gn:asciiname":"Seline",
    "gn:country_code":"BA",
    "gn:dem":712,
    "gn:feature_class":"P",
    "gn:feature_code":"PPL",
    "gn:name":"Seline",
    "gn:population":0,
    "gn:timezone":"Europe/Sarajevo",
    "iso:country":"BA",
    "name:bos_x_preferred":[
        "Seline"
    ],
    "name:ces_x_preferred":[
        "Seline"
    ],
    "name:fra_x_preferred":[
        "Seline"
    ],
    "name:hrv_x_preferred":[
        "Seline"
    ],
    "name:hun_x_preferred":[
        "Seline"
    ],
    "name:slv_x_preferred":[
        "Seline"
    ],
    "name:srp_x_preferred":[
        "\u0421\u0435\u043b\u0438\u043d\u0435"
    ],
    "name:ukr_x_preferred":[
        "\u0421\u0435\u043b\u0438\u043d\u0435"
    ],
    "wof:name":"Seline",
    "wof:placetype":"locality"
},
  "geometry": {"coordinates":[16.70853,43.99403],"type":"Point"}
}