{
  "type": "Feature",
  "properties": {
    "gn:admin1_code":"02",
    "gn:asciiname":"Rosici",
    "gn:country_code":"BA",
    "gn:dem":153,
    "gn:feature_class":"P",
    "gn:feature_code":"PPL",
    "gn:name":"Rosi\u0107i",
    "gn:population":0,
    "gn:timezone":"Europe/Sarajevo",
    "iso:country":"BA",
    "wof:name":"Rosici",
    "wof:placetype":"locality"
},
  "geometry": {"coordinates":[16.87195,44.89345],"type":"Point"}
}