{
  "type": "Feature",
  "properties": {
    "gn:admin1_code":"02",
    "gn:asciiname":"Skenderovici",
    "gn:country_code":"BA",
    "gn:dem":824,
    "gn:feature_class":"P",
    "gn:feature_code":"PPL",
    "gn:name":"Skenderovi\u0107i",
    "gn:population":0,
    "gn:timezone":"Europe/Sarajevo",
    "iso:country":"BA",
    "name:bos_x_preferred":[
        "Skenderovi\u0107i"
    ],
    "name:bul_x_preferred":[
        "\u0421\u043a\u0435\u043d\u0434\u0435\u0440\u043e\u0432\u0438\u0447\u0438"
    ],
    "name:fra_x_preferred":[
        "Skenderovi\u0107i"
    ],
    "name:hrv_x_preferred":[
        "Skenderovi\u0107i"
    ],
    "name:srp_x_preferred":[
        "\u0421\u043a\u0435\u043d\u0434\u0435\u0440\u043e\u0432\u0438\u045b\u0438"
    ],
    "name:und_x_variant":[
        "Skenderovi\u0107"
    ],
    "wof:name":"Skenderovici",
    "wof:placetype":"locality"
},
  "geometry": {"coordinates":[19.35964,44.08447],"type":"Point"}
}