{
  "type": "Feature",
  "properties": {
    "gn:admin1_code":"02",
    "gn:asciiname":"Pavlovci",
    "gn:country_code":"BA",
    "gn:dem":1209,
    "gn:feature_class":"P",
    "gn:feature_code":"PPL",
    "gn:name":"Pavlovci",
    "gn:population":0,
    "gn:timezone":"Europe/Sarajevo",
    "iso:country":"BA",
    "wof:name":"Pavlovci",
    "wof:placetype":"locality"
},
  "geometry": {"coordinates":[18.49712,43.54514],"type":"Point"}
}