{
  "type": "Feature",
  "properties": {
    "gn:admin1_code":"02",
    "gn:asciiname":"Jasen",
    "gn:country_code":"BA",
    "gn:dem":557,
    "gn:feature_class":"P",
    "gn:feature_code":"PPL",
    "gn:name":"Jasen",
    "gn:population":0,
    "gn:timezone":"Europe/Sarajevo",
    "iso:country":"BA",
    "wof:name":"Jasen",
    "wof:placetype":"locality"
},
  "geometry": {"coordinates":[18.38861,42.73912],"type":"Point"}
}