{
  "type": "Feature",
  "properties": {
    "gn:admin1_code":"02",
    "gn:asciiname":"Kerlec",
    "gn:country_code":"BA",
    "gn:dem":908,
    "gn:feature_class":"P",
    "gn:feature_code":"PPL",
    "gn:name":"Kerlec",
    "gn:population":0,
    "gn:timezone":"Europe/Sarajevo",
    "iso:country":"BA",
    "wof:name":"Kerlec",
    "wof:placetype":"locality"
},
  "geometry": {"coordinates":[17.12923,44.16824],"type":"Point"}
}