{
  "type": "Feature",
  "properties": {
    "gn:admin1_code":"01",
    "gn:asciiname":"Babici",
    "gn:country_code":"BA",
    "gn:dem":673,
    "gn:feature_class":"P",
    "gn:feature_code":"PPL",
    "gn:name":"Babi\u0107i",
    "gn:population":0,
    "gn:timezone":"Europe/Sarajevo",
    "iso:country":"BA",
    "wof:name":"Babici",
    "wof:placetype":"locality"
},
  "geometry": {"coordinates":[16.23167,44.38833],"type":"Point"}
}