{
  "type": "Feature",
  "properties": {
    "gn:admin1_code":"01",
    "gn:asciiname":"Karijani",
    "gn:country_code":"BA",
    "gn:dem":748,
    "gn:feature_class":"P",
    "gn:feature_code":"PPL",
    "gn:name":"Karijani",
    "gn:population":0,
    "gn:timezone":"Europe/Sarajevo",
    "iso:country":"BA",
    "wof:name":"Karijani",
    "wof:placetype":"locality"
},
  "geometry": {"coordinates":[16.96459,43.79559],"type":"Point"}
}