{
  "type": "Feature",
  "properties": {
    "gn:admin1_code":"01",
    "gn:asciiname":"Marici",
    "gn:country_code":"BA",
    "gn:dem":1148,
    "gn:feature_class":"P",
    "gn:feature_code":"PPL",
    "gn:name":"Mari\u0107i",
    "gn:population":0,
    "gn:timezone":"Europe/Sarajevo",
    "iso:country":"BA",
    "wof:name":"Marici",
    "wof:placetype":"locality"
},
  "geometry": {"coordinates":[17.25892,43.89472],"type":"Point"}
}