{
  "type": "Feature",
  "properties": {
    "gn:admin1_code":"01",
    "gn:asciiname":"Prline",
    "gn:country_code":"BA",
    "gn:dem":343,
    "gn:feature_class":"P",
    "gn:feature_code":"PPL",
    "gn:name":"Prline",
    "gn:population":0,
    "gn:timezone":"Europe/Sarajevo",
    "iso:country":"BA",
    "wof:name":"Prline",
    "wof:placetype":"locality"
},
  "geometry": {"coordinates":[16.01664,44.94577],"type":"Point"}
}