{
  "type": "Feature",
  "properties": {
    "gn:admin1_code":"02",
    "gn:asciiname":"Bubnjevi",
    "gn:country_code":"BA",
    "gn:dem":821,
    "gn:feature_class":"P",
    "gn:feature_code":"PPL",
    "gn:name":"Bubnjevi",
    "gn:population":0,
    "gn:timezone":"Europe/Sarajevo",
    "iso:country":"BA",
    "wof:name":"Bubnjevi",
    "wof:placetype":"locality"
},
  "geometry": {"coordinates":[17.00292,44.3204],"type":"Point"}
}