{
  "type": "Feature",
  "properties": {
    "gn:admin1_code":"02",
    "gn:asciiname":"Gligorici",
    "gn:country_code":"BA",
    "gn:dem":132,
    "gn:feature_class":"P",
    "gn:feature_code":"PPL",
    "gn:name":"Gligori\u0107i",
    "gn:population":0,
    "gn:timezone":"Europe/Sarajevo",
    "iso:country":"BA",
    "wof:name":"Gligorici",
    "wof:placetype":"locality"
},
  "geometry": {"coordinates":[17.55303,44.96752],"type":"Point"}
}