{
  "type": "Feature",
  "properties": {
    "gn:admin1_code":"01",
    "gn:asciiname":"Laze",
    "gn:country_code":"BA",
    "gn:dem":1119,
    "gn:feature_class":"P",
    "gn:feature_code":"PPL",
    "gn:name":"Laze",
    "gn:population":0,
    "gn:timezone":"Europe/Sarajevo",
    "iso:country":"BA",
    "name:bos_x_preferred":[
        "Laze"
    ],
    "name:ceb_x_preferred":[
        "Laze"
    ],
    "name:fra_x_preferred":[
        "Laze"
    ],
    "name:hrv_x_preferred":[
        "Laze"
    ],
    "name:ita_x_preferred":[
        "Laze"
    ],
    "name:nld_x_preferred":[
        "Laze"
    ],
    "name:pol_x_preferred":[
        "Laze"
    ],
    "name:sco_x_preferred":[
        "Laze"
    ],
    "name:slv_x_preferred":[
        "Laze"
    ],
    "name:srp_x_preferred":[
        "\u041b\u0430\u0437\u0435"
    ],
    "name:swe_x_preferred":[
        "Laze"
    ],
    "wof:name":"Laze",
    "wof:placetype":"locality"
},
  "geometry": {"coordinates":[17.72614,44.01452000000001],"type":"Point"}
}