{
  "type": "Feature",
  "properties": {
    "gn:admin1_code":"01",
    "gn:asciiname":"Laze",
    "gn:country_code":"BA",
    "gn:dem":1119,
    "gn:feature_class":"P",
    "gn:feature_code":"PPL",
    "gn:name":"Laze",
    "gn:population":0,
    "gn:timezone":"Europe/Sarajevo",
    "iso:country":"BA",
    "wof:name":"Laze",
    "wof:placetype":"locality"
},
  "geometry": {"coordinates":[17.72614,44.01452000000001],"type":"Point"}
}