{
  "type": "Feature",
  "properties": {
    "gn:admin1_code":"02",
    "gn:asciiname":"Reljici",
    "gn:country_code":"BA",
    "gn:dem":746,
    "gn:feature_class":"P",
    "gn:feature_code":"PPL",
    "gn:name":"Relji\u0107i",
    "gn:population":0,
    "gn:timezone":"Europe/Sarajevo",
    "iso:country":"BA",
    "wof:name":"Reljici",
    "wof:placetype":"locality"
},
  "geometry": {"coordinates":[17.38017,44.50948],"type":"Point"}
}