{
  "type": "Feature",
  "properties": {
    "gn:admin1_code":"02",
    "gn:asciiname":"Sutilovici",
    "gn:country_code":"BA",
    "gn:dem":244,
    "gn:feature_class":"P",
    "gn:feature_code":"PPL",
    "gn:name":"\u0160utilovi\u0107i",
    "gn:population":0,
    "gn:timezone":"Europe/Sarajevo",
    "iso:country":"BA",
    "wof:name":"Sutilovici",
    "wof:placetype":"locality"
},
  "geometry": {"coordinates":[16.99705,44.90164],"type":"Point"}
}