{
  "type": "Feature",
  "properties": {
    "gn:admin1_code":"02",
    "gn:asciiname":"Bilanovici",
    "gn:country_code":"BA",
    "gn:dem":412,
    "gn:feature_class":"P",
    "gn:feature_code":"PPL",
    "gn:name":"Bilanovi\u0107i",
    "gn:population":0,
    "gn:timezone":"Europe/Sarajevo",
    "iso:country":"BA",
    "wof:name":"Bilanovici",
    "wof:placetype":"locality"
},
  "geometry": {"coordinates":[17.44754,44.61253],"type":"Point"}
}