{
  "type": "Feature",
  "properties": {
    "gn:admin1_code":"01",
    "gn:asciiname":"Curak",
    "gn:country_code":"BA",
    "gn:dem":737,
    "gn:feature_class":"P",
    "gn:feature_code":"PPL",
    "gn:name":"\u0106urak",
    "gn:population":0,
    "gn:timezone":"Europe/Sarajevo",
    "iso:country":"BA",
    "wof:name":"Curak",
    "wof:placetype":"locality"
},
  "geometry": {"coordinates":[16.79335,43.85744],"type":"Point"}
}