{
  "type": "Feature",
  "properties": {
    "gn:admin1_code":"01",
    "gn:asciiname":"Saletovici",
    "gn:country_code":"BA",
    "gn:dem":373,
    "gn:feature_class":"P",
    "gn:feature_code":"PPL",
    "gn:name":"Saletovi\u0107i",
    "gn:population":0,
    "gn:timezone":"Europe/Sarajevo",
    "iso:country":"BA",
    "wof:name":"Saletovici",
    "wof:placetype":"locality"
},
  "geometry": {"coordinates":[18.52512,44.43886],"type":"Point"}
}