{
  "type": "Feature",
  "properties": {
    "gn:admin1_code":"01",
    "gn:asciiname":"Tkanice",
    "gn:country_code":"BA",
    "gn:dem":166,
    "gn:feature_class":"P",
    "gn:feature_code":"PPL",
    "gn:name":"Tkanice",
    "gn:population":0,
    "gn:timezone":"Europe/Sarajevo",
    "iso:country":"BA",
    "wof:name":"Tkanice",
    "wof:placetype":"locality"
},
  "geometry": {"coordinates":[17.36044,43.3211],"type":"Point"}
}