{
  "type": "Feature",
  "properties": {
    "gn:admin1_code":"02",
    "gn:asciiname":"Jelici",
    "gn:country_code":"BA",
    "gn:dem":644,
    "gn:feature_class":"P",
    "gn:feature_code":"PPL",
    "gn:name":"Jeli\u0107i",
    "gn:population":0,
    "gn:timezone":"Europe/Sarajevo",
    "iso:country":"BA",
    "name:bos_x_preferred":[
        "Jeli\u0107i"
    ],
    "name:fra_x_preferred":[
        "Jeli\u0107i"
    ],
    "name:hrv_x_preferred":[
        "Jeli\u0107i"
    ],
    "name:rus_x_preferred":[
        "\u0415\u043b\u0438\u0447\u0438"
    ],
    "name:srp_x_preferred":[
        "\u0408\u0435\u043b\u0438\u045b\u0438"
    ],
    "wof:name":"Jelici",
    "wof:placetype":"locality"
},
  "geometry": {"coordinates":[19.1874,43.72277],"type":"Point"}
}