{
  "type": "Feature",
  "properties": {
    "gn:admin1_code":"01",
    "gn:asciiname":"Bratica Brdo",
    "gn:country_code":"BA",
    "gn:dem":321,
    "gn:feature_class":"P",
    "gn:feature_code":"PPL",
    "gn:name":"Brati\u0107a Brdo",
    "gn:population":0,
    "gn:timezone":"Europe/Sarajevo",
    "iso:country":"BA",
    "wof:name":"Bratica Brdo",
    "wof:placetype":"locality"
},
  "geometry": {"coordinates":[16.19528,44.97194],"type":"Point"}
}