{
  "type": "Feature",
  "properties": {
    "gn:admin1_code":"01",
    "gn:asciiname":"Rastovica",
    "gn:country_code":"BA",
    "gn:dem":632,
    "gn:feature_class":"P",
    "gn:feature_code":"PPL",
    "gn:name":"Rastovica",
    "gn:population":0,
    "gn:timezone":"Europe/Sarajevo",
    "iso:country":"BA",
    "wof:name":"Rastovica",
    "wof:placetype":"locality"
},
  "geometry": {"coordinates":[18.0161,43.88766],"type":"Point"}
}