{
  "type": "Feature",
  "properties": {
    "gn:admin1_code":"02",
    "gn:asciiname":"Poljasi",
    "gn:country_code":"BA",
    "gn:dem":96,
    "gn:feature_class":"P",
    "gn:feature_code":"PPL",
    "gn:name":"Polja\u0161i",
    "gn:population":0,
    "gn:timezone":"Europe/Sarajevo",
    "iso:country":"BA",
    "wof:name":"Poljasi",
    "wof:placetype":"locality"
},
  "geometry": {"coordinates":[17.28987,45.06777],"type":"Point"}
}