{
  "type": "Feature",
  "properties": {
    "gn:admin1_code":"01",
    "gn:asciiname":"Baraci",
    "gn:country_code":"BA",
    "gn:dem":174,
    "gn:feature_class":"P",
    "gn:feature_code":"PPL",
    "gn:name":"Bara\u0107i",
    "gn:population":0,
    "gn:timezone":"Europe/Sarajevo",
    "iso:country":"BA",
    "wof:name":"Baraci",
    "wof:placetype":"locality"
},
  "geometry": {"coordinates":[17.67217,43.19819],"type":"Point"}
}