{
  "type": "Feature",
  "properties": {
    "gn:admin1_code":"01",
    "gn:asciiname":"Poda",
    "gn:country_code":"BA",
    "gn:dem":816,
    "gn:feature_class":"P",
    "gn:feature_code":"PPL",
    "gn:name":"Poda",
    "gn:population":0,
    "gn:timezone":"Europe/Sarajevo",
    "iso:country":"BA",
    "name:bos_x_preferred":[
        "Poda"
    ],
    "name:bul_x_preferred":[
        "\u041f\u043e\u0434\u0430"
    ],
    "name:ceb_x_preferred":[
        "Poda"
    ],
    "name:deu_x_preferred":[
        "Poda"
    ],
    "name:est_x_preferred":[
        "Poda"
    ],
    "name:fra_x_preferred":[
        "Poda"
    ],
    "name:hrv_x_preferred":[
        "Poda"
    ],
    "name:nld_x_preferred":[
        "Poda"
    ],
    "name:por_x_preferred":[
        "Poda"
    ],
    "name:rus_x_preferred":[
        "\u041f\u043e\u0434\u0430"
    ],
    "name:slv_x_preferred":[
        "Poda"
    ],
    "name:srp_x_preferred":[
        "\u041f\u043e\u0434\u0430"
    ],
    "name:swe_x_preferred":[
        "Poda"
    ],
    "wof:name":"Poda",
    "wof:placetype":"locality"
},
  "geometry": {"coordinates":[17.67408,43.83184],"type":"Point"}
}