{
  "type": "Feature",
  "properties": {
    "gn:admin1_code":"02",
    "gn:asciiname":"Silovici",
    "gn:country_code":"BA",
    "gn:dem":686,
    "gn:feature_class":"P",
    "gn:feature_code":"PPL",
    "gn:name":"Silovi\u0107i",
    "gn:population":0,
    "gn:timezone":"Europe/Sarajevo",
    "iso:country":"BA",
    "wof:name":"Silovici",
    "wof:placetype":"locality"
},
  "geometry": {"coordinates":[18.89444,43.50861],"type":"Point"}
}