{
  "type": "Feature",
  "properties": {
    "gn:admin1_code":"01",
    "gn:asciiname":"Golo Brdo",
    "gn:country_code":"BA",
    "gn:dem":1059,
    "gn:feature_class":"P",
    "gn:feature_code":"PPL",
    "gn:name":"Golo Brdo",
    "gn:population":0,
    "gn:timezone":"Europe/Sarajevo",
    "iso:country":"BA",
    "wof:name":"Golo Brdo",
    "wof:placetype":"locality"
},
  "geometry": {"coordinates":[18.43722,44.12444],"type":"Point"}
}