{
  "type": "Feature",
  "properties": {
    "gn:admin1_code":"01",
    "gn:asciiname":"Golo Brdo",
    "gn:country_code":"BA",
    "gn:dem":1059,
    "gn:feature_class":"P",
    "gn:feature_code":"PPL",
    "gn:name":"Golo Brdo",
    "gn:population":0,
    "gn:timezone":"Europe/Sarajevo",
    "iso:country":"BA",
    "name:bos_x_preferred":[
        "Golo Brdo"
    ],
    "name:ceb_x_preferred":[
        "Golo Brdo"
    ],
    "name:fra_x_preferred":[
        "Golo Brdo"
    ],
    "name:hrv_x_preferred":[
        "Golo Brdo"
    ],
    "name:hun_x_preferred":[
        "Golo Brdo"
    ],
    "name:nld_x_preferred":[
        "Golo Brdo"
    ],
    "name:rus_x_preferred":[
        "\u0413\u043e\u043b\u043e-\u0411\u0440\u0434\u043e"
    ],
    "name:slv_x_preferred":[
        "Golo Brdo"
    ],
    "name:srp_x_preferred":[
        "\u0413\u043e\u043b\u043e \u0411\u0440\u0434\u043e"
    ],
    "name:swe_x_preferred":[
        "Golo Brdo"
    ],
    "wof:name":"Golo Brdo",
    "wof:placetype":"locality"
},
  "geometry": {"coordinates":[18.43722,44.12444],"type":"Point"}
}