{
  "type": "Feature",
  "properties": {
    "gn:admin1_code":"01",
    "gn:asciiname":"Sevici",
    "gn:country_code":"BA",
    "gn:dem":210,
    "gn:feature_class":"P",
    "gn:feature_code":"PPL",
    "gn:name":"\u0160evi\u0107i",
    "gn:population":0,
    "gn:timezone":"Europe/Sarajevo",
    "iso:country":"BA",
    "name:epo_x_preferred":[
        "SEVici"
    ],
    "wof:name":"Sevici",
    "wof:placetype":"locality"
},
  "geometry": {"coordinates":[16.01055,45.21164],"type":"Point"}
}