{
  "type": "Feature",
  "properties": {
    "gn:admin1_code":"02",
    "gn:asciiname":"Karin Put",
    "gn:country_code":"BA",
    "gn:dem":83,
    "gn:feature_class":"P",
    "gn:feature_code":"PPL",
    "gn:name":"Karin Put",
    "gn:population":0,
    "gn:timezone":"Europe/Sarajevo",
    "iso:country":"BA",
    "wof:name":"Karin Put",
    "wof:placetype":"locality"
},
  "geometry": {"coordinates":[19.27319,44.83999],"type":"Point"}
}