{
  "type": "Feature",
  "properties": {
    "gn:admin1_code":"01",
    "gn:asciiname":"Skahovica",
    "gn:country_code":"BA",
    "gn:dem":311,
    "gn:feature_class":"P",
    "gn:feature_code":"PPLL",
    "gn:name":"\u0160kahovica",
    "gn:population":0,
    "gn:timezone":"Europe/Sarajevo",
    "iso:country":"BA",
    "name:bos_x_preferred":[
        "\u0160kahovica"
    ],
    "name:ceb_x_preferred":[
        "\u0160kahovica"
    ],
    "name:fra_x_preferred":[
        "\u0160kahovica"
    ],
    "name:hrv_x_preferred":[
        "\u0160kahovica"
    ],
    "name:swe_x_preferred":[
        "\u0160kahovica"
    ],
    "wof:name":"Skahovica",
    "wof:placetype":"locality"
},
  "geometry": {"coordinates":[18.31213,44.7401],"type":"Point"}
}