{
  "type": "Feature",
  "properties": {
    "gn:admin1_code":"02",
    "gn:asciiname":"Gornji Mamici",
    "gn:country_code":"BA",
    "gn:dem":348,
    "gn:feature_class":"P",
    "gn:feature_code":"PPL",
    "gn:name":"Gornji Mami\u0107i",
    "gn:population":0,
    "gn:timezone":"Europe/Sarajevo",
    "iso:country":"BA",
    "name:und_x_variant":[
        "Gornji Mami\u0107i"
    ],
    "wof:name":"Gornji Mamici",
    "wof:placetype":"locality"
},
  "geometry": {"coordinates":[16.97109,44.94534],"type":"Point"}
}