{
  "type": "Feature",
  "properties": {
    "gn:admin1_code":"01",
    "gn:asciiname":"Grad",
    "gn:country_code":"BA",
    "gn:dem":322,
    "gn:feature_class":"P",
    "gn:feature_code":"PPL",
    "gn:name":"Grad",
    "gn:population":0,
    "gn:timezone":"Europe/Sarajevo",
    "iso:country":"BA",
    "name:aze_x_preferred":[
        "Qrad"
    ],
    "name:bos_x_preferred":[
        "Grad"
    ],
    "name:bul_x_preferred":[
        "\u0413\u0440\u0430\u0434"
    ],
    "name:ceb_x_preferred":[
        "Grad"
    ],
    "name:dan_x_preferred":[
        "Grad"
    ],
    "name:deu_x_preferred":[
        "Grad"
    ],
    "name:fin_x_preferred":[
        "Grad"
    ],
    "name:fra_x_preferred":[
        "Grad"
    ],
    "name:heb_x_preferred":[
        "\u05d2\u05e8\u05d0\u05d3"
    ],
    "name:hrv_x_preferred":[
        "Grad"
    ],
    "name:ita_x_preferred":[
        "Grad"
    ],
    "name:jpn_x_preferred":[
        "\u30b0\u30ec\u30fc\u30c9"
    ],
    "name:kor_x_preferred":[
        "\uadf8\ub77c\ub4dc"
    ],
    "name:ltz_x_preferred":[
        "Grad"
    ],
    "name:mkd_x_preferred":[
        "\u0413\u0440\u0430\u0434"
    ],
    "name:nld_x_preferred":[
        "Grad"
    ],
    "name:nno_x_preferred":[
        "Grad"
    ],
    "name:nor_x_preferred":[
        "Grad"
    ],
    "name:pfl_x_preferred":[
        "Grad"
    ],
    "name:pol_x_preferred":[
        "Grad"
    ],
    "name:por_x_preferred":[
        "Grad"
    ],
    "name:ron_x_preferred":[
        "Grad"
    ],
    "name:rus_x_preferred":[
        "\u0413\u0440\u0430\u0434"
    ],
    "name:slk_x_preferred":[
        "Grad"
    ],
    "name:slv_x_preferred":[
        "Grad"
    ],
    "name:srp_x_preferred":[
        "\u0413\u0440\u0430\u0434"
    ],
    "name:swe_x_preferred":[
        "Grad"
    ],
    "name:ukr_x_preferred":[
        "\u0413\u0440\u0430\u0434"
    ],
    "name:vie_x_preferred":[
        "Grad"
    ],
    "wof:name":"Grad",
    "wof:placetype":"locality"
},
  "geometry": {"coordinates":[15.89582,45.0589],"type":"Point"}
}