{
  "type": "Feature",
  "properties": {
    "gn:admin1_code":"01",
    "gn:asciiname":"Grad",
    "gn:country_code":"BA",
    "gn:dem":322,
    "gn:feature_class":"P",
    "gn:feature_code":"PPL",
    "gn:name":"Grad",
    "gn:population":0,
    "gn:timezone":"Europe/Sarajevo",
    "iso:country":"BA",
    "wof:name":"Grad",
    "wof:placetype":"locality"
},
  "geometry": {"coordinates":[15.89582,45.0589],"type":"Point"}
}