{
  "type": "Feature",
  "properties": {
    "gn:admin1_code":"02",
    "gn:asciiname":"Kutanja",
    "gn:country_code":"BA",
    "gn:dem":963,
    "gn:feature_class":"P",
    "gn:feature_code":"PPL",
    "gn:name":"Kutanja",
    "gn:population":0,
    "gn:timezone":"Europe/Sarajevo",
    "iso:country":"BA",
    "wof:name":"Kutanja",
    "wof:placetype":"locality"
},
  "geometry": {"coordinates":[17.22125,44.14586],"type":"Point"}
}