{
  "type": "Feature",
  "properties": {
    "gn:country":"BA",
    "gn:fcode":"PPLL",
    "gn:population":4600,
    "iso:country":"BA",
    "name:bos_x_preferred":[
        "Gornja Koprivna"
    ],
    "name:ceb_x_preferred":[
        "Gornja Koprivna"
    ],
    "name:eng_x_preferred":[
        "Gornja Koprivna"
    ],
    "name:fra_x_preferred":[
        "Gornja Koprivna"
    ],
    "name:hrv_x_preferred":[
        "Gornja Koprivna"
    ],
    "name:nld_x_preferred":[
        "Gornja Koprivna"
    ],
    "name:srp_x_preferred":[
        "\u0413\u043e\u0440\u045a\u0430 \u041a\u043e\u043f\u0440\u0438\u0432\u043d\u0430"
    ],
    "name:swe_x_preferred":[
        "Gornja Koprivna"
    ],
    "qs:name":"Gornja Koprivna",
    "qs:photos_9r":0,
    "qs:photos_sr":0,
    "qs:pop_sr":"4",
    "wd:wordcount":60,
    "wof:name":"Gornja Koprivna",
    "wof:placetype":"locality",
    "wof:population":4600
},
  "geometry": {"coordinates":[15.95487,45.01091],"type":"Point"}
}