{
  "type": "Feature",
  "properties": {
    "gn:admin1_code":"01",
    "gn:asciiname":"Begluk",
    "gn:country_code":"BA",
    "gn:dem":252,
    "gn:feature_class":"P",
    "gn:feature_code":"PPL",
    "gn:name":"Begluk",
    "gn:population":0,
    "gn:timezone":"Europe/Sarajevo",
    "iso:country":"BA",
    "wof:name":"Begluk",
    "wof:placetype":"locality"
},
  "geometry": {"coordinates":[15.80361,45.14167],"type":"Point"}
}