{
  "type": "Feature",
  "properties": {
    "gn:admin1_code":"01",
    "gn:asciiname":"Razboj",
    "gn:country_code":"BA",
    "gn:dem":801,
    "gn:feature_class":"P",
    "gn:feature_code":"PPLL",
    "gn:name":"Razboj",
    "gn:population":0,
    "gn:timezone":"Europe/Sarajevo",
    "iso:country":"BA",
    "wof:name":"Razboj",
    "wof:placetype":"locality"
},
  "geometry": {"coordinates":[16.28009,44.41713],"type":"Point"}
}