{
  "type": "Feature",
  "properties": {
    "gn:admin1_code":"02",
    "gn:asciiname":"Borkovici",
    "gn:country_code":"BA",
    "gn:dem":252,
    "gn:feature_class":"P",
    "gn:feature_code":"PPL",
    "gn:name":"Borkovi\u0107i",
    "gn:population":0,
    "gn:timezone":"Europe/Sarajevo",
    "iso:country":"BA",
    "wof:name":"Borkovici",
    "wof:placetype":"locality"
},
  "geometry": {"coordinates":[17.16019,44.98118],"type":"Point"}
}