{
  "type": "Feature",
  "properties": {
    "gn:admin1_code":"BRC",
    "gn:asciiname":"Antici",
    "gn:country_code":"BA",
    "gn:dem":142,
    "gn:feature_class":"P",
    "gn:feature_code":"PPL",
    "gn:name":"Anti\u0107i",
    "gn:population":0,
    "gn:timezone":"Europe/Sarajevo",
    "iso:country":"BA",
    "wof:name":"Antici",
    "wof:placetype":"locality"
},
  "geometry": {"coordinates":[18.85822000000001,44.78168],"type":"Point"}
}