{
  "type": "Feature",
  "properties": {
    "gn:admin1_code":"02",
    "gn:asciiname":"Kuzmanovici",
    "gn:country_code":"BA",
    "gn:dem":443,
    "gn:feature_class":"P",
    "gn:feature_code":"PPL",
    "gn:name":"Kuzmanovi\u0107i",
    "gn:population":0,
    "gn:timezone":"Europe/Sarajevo",
    "iso:country":"BA",
    "wof:name":"Kuzmanovici",
    "wof:placetype":"locality"
},
  "geometry": {"coordinates":[17.73706,44.48734],"type":"Point"}
}