{
  "type": "Feature",
  "properties": {
    "gn:admin1_code":"02",
    "gn:asciiname":"Rajkovici",
    "gn:country_code":"BA",
    "gn:dem":1190,
    "gn:feature_class":"P",
    "gn:feature_code":"PPL",
    "gn:name":"Rajkovi\u0107i",
    "gn:population":0,
    "gn:timezone":"Europe/Sarajevo",
    "iso:country":"BA",
    "wof:name":"Rajkovici",
    "wof:placetype":"locality"
},
  "geometry": {"coordinates":[19.01971,43.35355],"type":"Point"}
}