{
  "type": "Feature",
  "properties": {
    "gn:admin1_code":"02",
    "gn:asciiname":"Grabovaca",
    "gn:cc2":"BA",
    "gn:country_code":"BA",
    "gn:dem":394,
    "gn:feature_class":"P",
    "gn:feature_code":"PPL",
    "gn:name":"Grabova\u010da",
    "gn:population":0,
    "gn:timezone":"Europe/Sarajevo",
    "iso:country":"BA",
    "name:und_x_variant":[
        "Grabovi\u0107a",
        "Grabova\u010da"
    ],
    "wof:name":"Grabovaca",
    "wof:placetype":"locality"
},
  "geometry": {"coordinates":[17.51833,44.65361],"type":"Point"}
}