{
  "type": "Feature",
  "properties": {
    "gn:admin1_code":"02",
    "gn:asciiname":"Podrascici",
    "gn:country_code":"BA",
    "gn:dem":655,
    "gn:feature_class":"P",
    "gn:feature_code":"PPL",
    "gn:name":"Podra\u0161\u010di\u0107i",
    "gn:population":0,
    "gn:timezone":"Europe/Sarajevo",
    "iso:country":"BA",
    "wof:name":"Podrascici",
    "wof:placetype":"locality"
},
  "geometry": {"coordinates":[17.17012,44.38814],"type":"Point"}
}