{
  "type": "Feature",
  "properties": {
    "gn:admin1_code":"01",
    "gn:asciiname":"Grdovo",
    "gn:country_code":"BA",
    "gn:dem":1002,
    "gn:feature_class":"P",
    "gn:feature_code":"PPLL",
    "gn:name":"Grdovo",
    "gn:population":0,
    "gn:timezone":"Europe/Sarajevo",
    "iso:country":"BA",
    "wof:name":"Grdovo",
    "wof:placetype":"locality"
},
  "geometry": {"coordinates":[17.37595,44.26597],"type":"Point"}
}