{
  "type": "Feature",
  "properties": {
    "gn:admin1_code":"02",
    "gn:asciiname":"Lipici",
    "gn:country_code":"BA",
    "gn:dem":314,
    "gn:feature_class":"P",
    "gn:feature_code":"PPL",
    "gn:name":"Lipi\u0107i",
    "gn:population":0,
    "gn:timezone":"Europe/Sarajevo",
    "iso:country":"BA",
    "wof:name":"Lipici",
    "wof:placetype":"locality"
},
  "geometry": {"coordinates":[17.84451,44.66187],"type":"Point"}
}