{
  "type": "Feature",
  "properties": {
    "gn:admin1_code":"02",
    "gn:asciiname":"Prutine",
    "gn:country_code":"BA",
    "gn:dem":980,
    "gn:feature_class":"P",
    "gn:feature_code":"PPL",
    "gn:name":"Prutine",
    "gn:population":0,
    "gn:timezone":"Europe/Sarajevo",
    "iso:country":"BA",
    "name:bos_x_preferred":[
        "Prutine"
    ],
    "name:ceb_x_preferred":[
        "Prutine"
    ],
    "name:fra_x_preferred":[
        "Prutine"
    ],
    "name:srp_x_preferred":[
        "\u041f\u0440\u0443\u0442\u0438\u043d\u0435"
    ],
    "name:swe_x_preferred":[
        "Prutine"
    ],
    "wof:name":"Prutine",
    "wof:placetype":"locality"
},
  "geometry": {"coordinates":[18.61734,43.86486],"type":"Point"}
}