{
  "type": "Feature",
  "properties": {
    "gn:admin1_code":"01",
    "gn:asciiname":"Borovnica",
    "gn:country_code":"BA",
    "gn:dem":280,
    "gn:feature_class":"P",
    "gn:feature_code":"PPL",
    "gn:name":"Borovnica",
    "gn:population":0,
    "gn:timezone":"Europe/Sarajevo",
    "iso:country":"BA",
    "name:bos_x_preferred":[
        "Borovnica"
    ],
    "name:ceb_x_preferred":[
        "Borovnica"
    ],
    "name:hrv_x_preferred":[
        "Borovnica"
    ],
    "name:nld_x_preferred":[
        "Borovnica"
    ],
    "name:srp_x_preferred":[
        "\u0411\u043e\u0440\u043e\u0432\u043d\u0438\u0446\u0430"
    ],
    "name:swe_x_preferred":[
        "Borovnica"
    ],
    "wof:name":"Borovnica",
    "wof:placetype":"locality"
},
  "geometry": {"coordinates":[18.19005,44.3815],"type":"Point"}
}