{
  "type": "Feature",
  "properties": {
    "gn:admin1_code":"02",
    "gn:asciiname":"Causevici",
    "gn:country_code":"BA",
    "gn:dem":168,
    "gn:feature_class":"P",
    "gn:feature_code":"PPL",
    "gn:name":"\u010cau\u0161evi\u0107i",
    "gn:population":0,
    "gn:timezone":"Europe/Sarajevo",
    "iso:country":"BA",
    "wof:name":"Causevici",
    "wof:placetype":"locality"
},
  "geometry": {"coordinates":[16.81047,44.96854],"type":"Point"}
}