{
  "type": "Feature",
  "properties": {
    "gn:admin1_code":"02",
    "gn:asciiname":"Velebit",
    "gn:country_code":"BA",
    "gn:dem":383,
    "gn:feature_class":"P",
    "gn:feature_code":"PPL",
    "gn:name":"Velebit",
    "gn:population":0,
    "gn:timezone":"Europe/Sarajevo",
    "iso:country":"BA",
    "wof:name":"Velebit",
    "wof:placetype":"locality"
},
  "geometry": {"coordinates":[16.23702999999999,44.95452],"type":"Point"}
}