{
  "type": "Feature",
  "properties": {
    "gn:admin1_code":"02",
    "gn:asciiname":"Cerova",
    "gn:country_code":"BA",
    "gn:dem":173,
    "gn:feature_class":"P",
    "gn:feature_code":"PPL",
    "gn:name":"Cerova",
    "gn:population":0,
    "gn:timezone":"Europe/Sarajevo",
    "iso:country":"BA",
    "wof:name":"Cerova",
    "wof:placetype":"locality"
},
  "geometry": {"coordinates":[18.27702,44.9293],"type":"Point"}
}