{
  "type": "Feature",
  "properties": {
    "gn:admin1_code":"02",
    "gn:asciiname":"Raljici",
    "gn:country_code":"BA",
    "gn:dem":793,
    "gn:feature_class":"P",
    "gn:feature_code":"PPL",
    "gn:name":"Ralji\u0107i",
    "gn:population":0,
    "gn:timezone":"Europe/Sarajevo",
    "iso:country":"BA",
    "wof:name":"Raljici",
    "wof:placetype":"locality"
},
  "geometry": {"coordinates":[17.34584,44.48264],"type":"Point"}
}