{
  "type": "Feature",
  "properties": {
    "gn:admin1_code":"00",
    "gn:asciiname":"Pekara",
    "gn:country_code":"BA",
    "gn:dem":769,
    "gn:feature_class":"P",
    "gn:feature_code":"PPL",
    "gn:name":"Pekara",
    "gn:population":0,
    "gn:timezone":"Europe/Sarajevo",
    "iso:country":"BA",
    "wof:name":"Pekara",
    "wof:placetype":"locality"
},
  "geometry": {"coordinates":[18.57899,44.26103],"type":"Point"}
}