{
  "type": "Feature",
  "properties": {
    "gn:admin1_code":"02",
    "gn:asciiname":"Vile",
    "gn:country_code":"BA",
    "gn:dem":186,
    "gn:feature_class":"P",
    "gn:feature_code":"PPL",
    "gn:name":"Vile",
    "gn:population":0,
    "gn:timezone":"Europe/Sarajevo",
    "iso:country":"BA",
    "wof:name":"Vile",
    "wof:placetype":"locality"
},
  "geometry": {"coordinates":[16.70649,45.07352],"type":"Point"}
}