{
  "type": "Feature",
  "properties": {
    "gn:admin1_code":"02",
    "gn:asciiname":"Grabovaca",
    "gn:country_code":"BA",
    "gn:dem":319,
    "gn:feature_class":"P",
    "gn:feature_code":"PPL",
    "gn:name":"Grabova\u010da",
    "gn:population":0,
    "gn:timezone":"Europe/Sarajevo",
    "iso:country":"BA",
    "wof:name":"Grabovaca",
    "wof:placetype":"locality"
},
  "geometry": {"coordinates":[17.49751,44.70447],"type":"Point"}
}