{
  "type": "Feature",
  "properties": {
    "gn:admin1_code":"01",
    "gn:asciiname":"Orahovo",
    "gn:country_code":"BA",
    "gn:dem":988,
    "gn:feature_class":"P",
    "gn:feature_code":"PPL",
    "gn:name":"Orahovo",
    "gn:population":0,
    "gn:timezone":"Europe/Sarajevo",
    "iso:country":"BA",
    "wof:name":"Orahovo",
    "wof:placetype":"locality"
},
  "geometry": {"coordinates":[18.34481,44.04543],"type":"Point"}
}