{
  "type": "Feature",
  "properties": {
    "gn:admin1_code":"02",
    "gn:asciiname":"Pribjesci",
    "gn:country_code":"BA",
    "gn:dem":88,
    "gn:feature_class":"P",
    "gn:feature_code":"PPL",
    "gn:name":"Pribje\u0161ci",
    "gn:population":0,
    "gn:timezone":"Europe/Sarajevo",
    "iso:country":"BA",
    "wof:name":"Pribjesci",
    "wof:placetype":"locality"
},
  "geometry": {"coordinates":[17.43908,45.15672],"type":"Point"}
}