{
  "type": "Feature",
  "properties": {
    "gn:admin1_code":"01",
    "gn:asciiname":"Tolici",
    "gn:country_code":"BA",
    "gn:dem":659,
    "gn:feature_class":"P",
    "gn:feature_code":"PPL",
    "gn:name":"Toli\u0107i",
    "gn:population":0,
    "gn:timezone":"Europe/Sarajevo",
    "iso:country":"BA",
    "wof:name":"Tolici",
    "wof:placetype":"locality"
},
  "geometry": {"coordinates":[17.31316,43.45176],"type":"Point"}
}