{
  "type": "Feature",
  "properties": {
    "gn:admin1_code":"01",
    "gn:asciiname":"Ponjevici",
    "gn:country_code":"BA",
    "gn:dem":310,
    "gn:feature_class":"P",
    "gn:feature_code":"PPL",
    "gn:name":"Ponjevi\u0107i",
    "gn:population":0,
    "gn:timezone":"Europe/Sarajevo",
    "iso:country":"BA",
    "name:und_x_variant":[
        "Ponjevi\u0107i"
    ],
    "wof:name":"Ponjevici",
    "wof:placetype":"locality"
},
  "geometry": {"coordinates":[15.95833,45.04389000000001],"type":"Point"}
}