{
  "type": "Feature",
  "properties": {
    "gn:admin1_code":"02",
    "gn:asciiname":"Kutici",
    "gn:country_code":"BA",
    "gn:dem":463,
    "gn:feature_class":"P",
    "gn:feature_code":"PPL",
    "gn:name":"Kuti\u0107i",
    "gn:population":0,
    "gn:timezone":"Europe/Sarajevo",
    "iso:country":"BA",
    "wof:name":"Kutici",
    "wof:placetype":"locality"
},
  "geometry": {"coordinates":[17.19429,44.62035],"type":"Point"}
}