{
  "type": "Feature",
  "properties": {
    "gn:admin1_code":"02",
    "gn:asciiname":"Krekavice",
    "gn:country_code":"BA",
    "gn:dem":867,
    "gn:feature_class":"P",
    "gn:feature_code":"PPL",
    "gn:name":"Krekavice",
    "gn:population":0,
    "gn:timezone":"Europe/Sarajevo",
    "iso:country":"BA",
    "wof:name":"Krekavice",
    "wof:placetype":"locality"
},
  "geometry": {"coordinates":[18.24977,43.22039],"type":"Point"}
}