{
  "type": "Feature",
  "properties": {
    "gn:admin1_code":"02",
    "gn:asciiname":"Mocila Gornja",
    "gn:country_code":"BA",
    "gn:dem":85,
    "gn:feature_class":"P",
    "gn:feature_code":"PPL",
    "gn:name":"Mo\u010dila Gornja",
    "gn:population":0,
    "gn:timezone":"Europe/Sarajevo",
    "iso:country":"BA",
    "name:und_x_variant":[
        "Gornja Mo\u010dila",
        "Mo\u010dila Gornja"
    ],
    "wof:name":"Mocila Gornja",
    "wof:placetype":"locality"
},
  "geometry": {"coordinates":[17.96202000000001,45.10272],"type":"Point"}
}