{
  "type": "Feature",
  "properties": {
    "gn:admin1_code":"02",
    "gn:asciiname":"Slanac",
    "gn:country_code":"BA",
    "gn:dem":305,
    "gn:feature_class":"P",
    "gn:feature_code":"PPL",
    "gn:name":"Slanac",
    "gn:population":0,
    "gn:timezone":"Europe/Sarajevo",
    "iso:country":"BA",
    "wof:name":"Slanac",
    "wof:placetype":"locality"
},
  "geometry": {"coordinates":[17.38253,44.73517],"type":"Point"}
}