{
  "type": "Feature",
  "properties": {
    "gn:admin1_code":"02",
    "gn:asciiname":"Zgona",
    "gn:country_code":"BA",
    "gn:dem":1152,
    "gn:feature_class":"P",
    "gn:feature_code":"PPL",
    "gn:name":"Zgona",
    "gn:population":0,
    "gn:timezone":"Europe/Sarajevo",
    "iso:country":"BA",
    "name:und_x_variant":[
        "Mi\u0107i\u0107",
        "Zgona"
    ],
    "wof:name":"Zgona",
    "wof:placetype":"locality"
},
  "geometry": {"coordinates":[18.54498,43.98029],"type":"Point"}
}