{
  "type": "Feature",
  "properties": {
    "gn:admin1_code":"02",
    "gn:asciiname":"Luzani",
    "gn:country_code":"BA",
    "gn:dem":254,
    "gn:feature_class":"P",
    "gn:feature_code":"PPL",
    "gn:name":"Lu\u017eani",
    "gn:population":0,
    "gn:timezone":"Europe/Sarajevo",
    "iso:country":"BA",
    "wof:name":"Luzani",
    "wof:placetype":"locality"
},
  "geometry": {"coordinates":[18.3794,44.61507],"type":"Point"}
}