{
  "type": "Feature",
  "properties": {
    "gn:admin1_code":"01",
    "gn:asciiname":"Budak",
    "gn:country_code":"BA",
    "gn:dem":938,
    "gn:feature_class":"P",
    "gn:feature_code":"PPL",
    "gn:name":"Budak",
    "gn:population":0,
    "gn:timezone":"Europe/Sarajevo",
    "iso:country":"BA",
    "wof:name":"Budak",
    "wof:placetype":"locality"
},
  "geometry": {"coordinates":[16.69506,44.15666],"type":"Point"}
}