{
  "type": "Feature",
  "properties": {
    "gn:admin1_code":"02",
    "gn:asciiname":"Mostarici",
    "gn:country_code":"BA",
    "gn:dem":349,
    "gn:feature_class":"P",
    "gn:feature_code":"PPL",
    "gn:name":"Mostari\u0107i",
    "gn:population":0,
    "gn:timezone":"Europe/Sarajevo",
    "iso:country":"BA",
    "wof:name":"Mostarici",
    "wof:placetype":"locality"
},
  "geometry": {"coordinates":[19.1495,44.2777],"type":"Point"}
}