{
  "type": "Feature",
  "properties": {
    "gn:admin1_code":"02",
    "gn:asciiname":"Resetar",
    "gn:country_code":"BA",
    "gn:dem":94,
    "gn:feature_class":"P",
    "gn:feature_code":"PPL",
    "gn:name":"Re\u0161etar",
    "gn:population":0,
    "gn:timezone":"Europe/Sarajevo",
    "iso:country":"BA",
    "wof:name":"Resetar",
    "wof:placetype":"locality"
},
  "geometry": {"coordinates":[17.35244,45.04939],"type":"Point"}
}