{
  "type": "Feature",
  "properties": {
    "gn:admin1_code":"01",
    "gn:asciiname":"Vujatovici",
    "gn:country_code":"BA",
    "gn:dem":838,
    "gn:feature_class":"P",
    "gn:feature_code":"PPL",
    "gn:name":"Vujatovi\u0107i",
    "gn:population":0,
    "gn:timezone":"Europe/Sarajevo",
    "iso:country":"BA",
    "wof:name":"Vujatovici",
    "wof:placetype":"locality"
},
  "geometry": {"coordinates":[16.35056,44.18889],"type":"Point"}
}