{
  "type": "Feature",
  "properties": {
    "gn:admin1_code":"02",
    "gn:asciiname":"Saldumi",
    "gn:country_code":"BA",
    "gn:dem":177,
    "gn:feature_class":"P",
    "gn:feature_code":"PPL",
    "gn:name":"Saldumi",
    "gn:population":0,
    "gn:timezone":"Europe/Sarajevo",
    "iso:country":"BA",
    "wof:name":"Saldumi",
    "wof:placetype":"locality"
},
  "geometry": {"coordinates":[17.18638,44.99512],"type":"Point"}
}