{
  "type": "Feature",
  "properties": {
    "gn:admin1_code":"02",
    "gn:asciiname":"Sosici",
    "gn:country_code":"BA",
    "gn:dem":82,
    "gn:feature_class":"P",
    "gn:feature_code":"PPL",
    "gn:name":"\u0160o\u0161i\u0107i",
    "gn:population":0,
    "gn:timezone":"Europe/Sarajevo",
    "iso:country":"BA",
    "wof:name":"Sosici",
    "wof:placetype":"locality"
},
  "geometry": {"coordinates":[18.58118,45.00971],"type":"Point"}
}