{
  "type": "Feature",
  "properties": {
    "gn:admin1_code":"01",
    "gn:asciiname":"Luznica",
    "gn:country_code":"BA",
    "gn:dem":1229,
    "gn:feature_class":"P",
    "gn:feature_code":"PPL",
    "gn:name":"Lu\u017enica",
    "gn:population":0,
    "gn:timezone":"Europe/Sarajevo",
    "iso:country":"BA",
    "wof:name":"Luznica",
    "wof:placetype":"locality"
},
  "geometry": {"coordinates":[17.56724,44.30661],"type":"Point"}
}