{
  "type": "Feature",
  "properties": {
    "gn:admin1_code":"01",
    "gn:asciiname":"Gornja Dobosnica",
    "gn:country_code":"BA",
    "gn:dem":265,
    "gn:feature_class":"P",
    "gn:feature_code":"PPL",
    "gn:name":"Gornja Dobo\u0161nica",
    "gn:population":0,
    "gn:timezone":"Europe/Sarajevo",
    "iso:country":"BA",
    "wof:name":"Gornja Dobosnica",
    "wof:placetype":"locality"
},
  "geometry": {"coordinates":[18.47264,44.60276],"type":"Point"}
}