{
  "type": "Feature",
  "properties": {
    "gn:admin1_code":"02",
    "gn:asciiname":"Topreci",
    "gn:country_code":"BA",
    "gn:dem":302,
    "gn:feature_class":"P",
    "gn:feature_code":"PPL",
    "gn:name":"Topreci",
    "gn:population":0,
    "gn:timezone":"Europe/Sarajevo",
    "iso:country":"BA",
    "wof:name":"Topreci",
    "wof:placetype":"locality"
},
  "geometry": {"coordinates":[17.82338,44.66386],"type":"Point"}
}