{
  "type": "Feature",
  "properties": {
    "gn:admin1_code":"02",
    "gn:asciiname":"Gajici",
    "gn:country_code":"BA",
    "gn:dem":401,
    "gn:feature_class":"P",
    "gn:feature_code":"PPL",
    "gn:name":"Gaji\u0107i",
    "gn:population":0,
    "gn:timezone":"Europe/Sarajevo",
    "iso:country":"BA",
    "wof:name":"Gajici",
    "wof:placetype":"locality"
},
  "geometry": {"coordinates":[17.05529,44.73375],"type":"Point"}
}