{
  "type": "Feature",
  "properties": {
    "gn:admin1_code":"01",
    "gn:asciiname":"Ogrankovici",
    "gn:country_code":"BA",
    "gn:dem":383,
    "gn:feature_class":"P",
    "gn:feature_code":"PPL",
    "gn:name":"Ogrankovi\u0107i",
    "gn:population":0,
    "gn:timezone":"Europe/Sarajevo",
    "iso:country":"BA",
    "wof:name":"Ogrankovici",
    "wof:placetype":"locality"
},
  "geometry": {"coordinates":[16.01562,45.00031],"type":"Point"}
}