{
  "type": "Feature",
  "properties": {
    "gn:admin1_code":"01",
    "gn:asciiname":"Zlobrad",
    "gn:country_code":"BA",
    "gn:dem":396,
    "gn:feature_class":"P",
    "gn:feature_code":"PPL",
    "gn:name":"Zlobrad",
    "gn:population":0,
    "gn:timezone":"Europe/Sarajevo",
    "iso:country":"BA",
    "wof:name":"Zlobrad",
    "wof:placetype":"locality"
},
  "geometry": {"coordinates":[17.89282,43.19641],"type":"Point"}
}