{
  "type": "Feature",
  "properties": {
    "gn:admin1_code":"02",
    "gn:asciiname":"Jotanovici",
    "gn:country_code":"BA",
    "gn:dem":682,
    "gn:feature_class":"P",
    "gn:feature_code":"PPL",
    "gn:name":"Jotanovi\u0107i",
    "gn:population":0,
    "gn:timezone":"Europe/Sarajevo",
    "iso:country":"BA",
    "wof:name":"Jotanovici",
    "wof:placetype":"locality"
},
  "geometry": {"coordinates":[17.58936,44.60571],"type":"Point"}
}