{
  "type": "Feature",
  "properties": {
    "gn:admin1_code":"02",
    "gn:asciiname":"Rajeta",
    "gn:country_code":"BA",
    "gn:dem":164,
    "gn:feature_class":"P",
    "gn:feature_code":"PPLL",
    "gn:name":"Rajeta",
    "gn:population":0,
    "gn:timezone":"Europe/Sarajevo",
    "iso:country":"BA",
    "name:und_x_variant":[
        "Raje\u0161a",
        "Rajeta"
    ],
    "wof:name":"Rajeta",
    "wof:placetype":"locality"
},
  "geometry": {"coordinates":[19.14176,44.66142],"type":"Point"}
}