{
  "type": "Feature",
  "properties": {
    "gn:admin1_code":"01",
    "gn:asciiname":"Hrasno",
    "gn:country_code":"BA",
    "gn:dem":564,
    "gn:feature_class":"P",
    "gn:feature_code":"PPL",
    "gn:name":"Hrasno",
    "gn:population":0,
    "gn:timezone":"Europe/Sarajevo",
    "iso:country":"BA",
    "name:bos_x_preferred":[
        "Hrasno"
    ],
    "name:hrv_x_preferred":[
        "Hrasno"
    ],
    "name:srp_x_preferred":[
        "\u0425\u0440\u0430\u0441\u043d\u043e"
    ],
    "wof:name":"Hrasno",
    "wof:placetype":"locality"
},
  "geometry": {"coordinates":[18.38222,43.84389],"type":"Point"}
}