{
  "type": "Feature",
  "properties": {
    "gn:admin1_code":"02",
    "gn:asciiname":"Tanjevo",
    "gn:country_code":"BA",
    "gn:dem":879,
    "gn:feature_class":"P",
    "gn:feature_code":"PPL",
    "gn:name":"Tanjevo",
    "gn:population":0,
    "gn:timezone":"Europe/Sarajevo",
    "iso:country":"BA",
    "wof:name":"Tanjevo",
    "wof:placetype":"locality"
},
  "geometry": {"coordinates":[18.1337,43.20934000000001],"type":"Point"}
}