{
  "type": "Feature",
  "properties": {
    "gn:admin1_code":"02",
    "gn:asciiname":"Sibovi",
    "gn:country_code":"BA",
    "gn:dem":225,
    "gn:feature_class":"P",
    "gn:feature_code":"PPL",
    "gn:name":"\u0160ibovi",
    "gn:population":0,
    "gn:timezone":"Europe/Sarajevo",
    "iso:country":"BA",
    "wof:name":"Sibovi",
    "wof:placetype":"locality"
},
  "geometry": {"coordinates":[16.55548,44.94918],"type":"Point"}
}