{
  "type": "Feature",
  "properties": {
    "gn:admin1_code":"02",
    "gn:asciiname":"Donja Puharska",
    "gn:cc2":"BA",
    "gn:country_code":"BA",
    "gn:dem":141,
    "gn:feature_class":"P",
    "gn:feature_code":"PPL",
    "gn:name":"Donja Puharska",
    "gn:population":0,
    "gn:timezone":"Europe/Sarajevo",
    "iso:country":"BA",
    "name:und_x_variant":[
        "Puharska Donja",
        "Donja Puharska"
    ],
    "wof:name":"Donja Puharska",
    "wof:placetype":"locality"
},
  "geometry": {"coordinates":[16.71667,44.98333],"type":"Point"}
}