{
  "type": "Feature",
  "properties": {
    "gn:admin1_code":"01",
    "gn:asciiname":"Grbesi",
    "gn:country_code":"BA",
    "gn:dem":1068,
    "gn:feature_class":"P",
    "gn:feature_code":"PPL",
    "gn:name":"Grbe\u0161i",
    "gn:population":0,
    "gn:timezone":"Europe/Sarajevo",
    "iso:country":"BA",
    "wof:name":"Grbesi",
    "wof:placetype":"locality"
},
  "geometry": {"coordinates":[17.55499,43.77484000000001],"type":"Point"}
}