{
  "type": "Feature",
  "properties": {
    "gn:admin1_code":"02",
    "gn:asciiname":"Sedlici",
    "gn:country_code":"BA",
    "gn:dem":219,
    "gn:feature_class":"P",
    "gn:feature_code":"PPL",
    "gn:name":"Sedli\u0107i",
    "gn:population":0,
    "gn:timezone":"Europe/Sarajevo",
    "iso:country":"BA",
    "wof:name":"Sedlici",
    "wof:placetype":"locality"
},
  "geometry": {"coordinates":[17.88318,45.02088],"type":"Point"}
}