{
  "type": "Feature",
  "properties": {
    "gn:admin1_code":"01",
    "gn:asciiname":"Hrdala",
    "gn:country_code":"BA",
    "gn:dem":336,
    "gn:feature_class":"P",
    "gn:feature_code":"PPL",
    "gn:name":"Hrdala",
    "gn:population":0,
    "gn:timezone":"Europe/Sarajevo",
    "iso:country":"BA",
    "wof:name":"Hrdala",
    "wof:placetype":"locality"
},
  "geometry": {"coordinates":[15.93628,45.09022],"type":"Point"}
}