{
  "type": "Feature",
  "properties": {
    "gn:admin1_code":"01",
    "gn:asciiname":"Radinovici",
    "gn:country_code":"BA",
    "gn:dem":402,
    "gn:feature_class":"P",
    "gn:feature_code":"PPL",
    "gn:name":"Radinovi\u0107i",
    "gn:population":0,
    "gn:timezone":"Europe/Sarajevo",
    "iso:country":"BA",
    "wof:name":"Radinovici",
    "wof:placetype":"locality"
},
  "geometry": {"coordinates":[18.14026,44.03151],"type":"Point"}
}