{
  "type": "Feature",
  "properties": {
    "gn:admin1_code":"02",
    "gn:asciiname":"Gornja Palanka",
    "gn:country_code":"BA",
    "gn:dem":322,
    "gn:feature_class":"P",
    "gn:feature_code":"PPL",
    "gn:name":"Gornja Palanka",
    "gn:population":0,
    "gn:timezone":"Europe/Sarajevo",
    "iso:country":"BA",
    "wof:name":"Gornja Palanka",
    "wof:placetype":"locality"
},
  "geometry": {"coordinates":[17.80447000000001,44.70013],"type":"Point"}
}