{
  "type": "Feature",
  "properties": {
    "gn:admin1_code":"01",
    "gn:asciiname":"Maurovici",
    "gn:country_code":"BA",
    "gn:dem":458,
    "gn:feature_class":"P",
    "gn:feature_code":"PPL",
    "gn:name":"Maurovi\u0107i",
    "gn:population":0,
    "gn:timezone":"Europe/Sarajevo",
    "iso:country":"BA",
    "wof:name":"Maurovici",
    "wof:placetype":"locality"
},
  "geometry": {"coordinates":[18.08431,44.03179],"type":"Point"}
}