{
  "type": "Feature",
  "properties": {
    "gn:admin1_code":"02",
    "gn:asciiname":"Saric",
    "gn:country_code":"BA",
    "gn:dem":517,
    "gn:feature_class":"P",
    "gn:feature_code":"PPLL",
    "gn:name":"Sari\u0107",
    "gn:population":0,
    "gn:timezone":"Europe/Sarajevo",
    "iso:country":"BA",
    "name:und_x_variant":[
        "Sari\u0107i",
        "Sari\u0107"
    ],
    "wof:name":"Saric",
    "wof:placetype":"locality"
},
  "geometry": {"coordinates":[17.07938,44.27231],"type":"Point"}
}