{
  "type": "Feature",
  "properties": {
    "gn:admin1_code":"02",
    "gn:asciiname":"Bratanici",
    "gn:country_code":"BA",
    "gn:dem":213,
    "gn:feature_class":"P",
    "gn:feature_code":"PPL",
    "gn:name":"Bratani\u0107i",
    "gn:population":0,
    "gn:timezone":"Europe/Sarajevo",
    "iso:country":"BA",
    "wof:name":"Bratanici",
    "wof:placetype":"locality"
},
  "geometry": {"coordinates":[17.95925,44.82893],"type":"Point"}
}