{
  "type": "Feature",
  "properties": {
    "gn:admin1_code":"01",
    "gn:asciiname":"Hrastovi",
    "gn:country_code":"BA",
    "gn:dem":593,
    "gn:feature_class":"P",
    "gn:feature_code":"PPL",
    "gn:name":"Hrastovi",
    "gn:population":0,
    "gn:timezone":"Europe/Sarajevo",
    "iso:country":"BA",
    "wof:name":"Hrastovi",
    "wof:placetype":"locality"
},
  "geometry": {"coordinates":[18.0052,44.01549],"type":"Point"}
}