{
  "type": "Feature",
  "properties": {
    "gn:admin1_code":"01",
    "gn:asciiname":"Aladinici",
    "gn:country_code":"BA",
    "gn:dem":229,
    "gn:feature_class":"P",
    "gn:feature_code":"PPLL",
    "gn:name":"Aladini\u0107i",
    "gn:population":0,
    "gn:timezone":"Europe/Sarajevo",
    "iso:country":"BA",
    "wof:name":"Aladinici",
    "wof:placetype":"locality"
},
  "geometry": {"coordinates":[17.8517,43.12286],"type":"Point"}
}