{
  "type": "Feature",
  "properties": {
    "gn:country":"BA",
    "gn:fcode":"PPL",
    "gn:population":3909,
    "iso:country":"BA",
    "name:bos_x_preferred":[
        "\u010cajni\u010de"
    ],
    "name:bul_x_preferred":[
        "\u0427\u0430\u0439\u043d\u0438\u0447\u0435"
    ],
    "name:cat_x_preferred":[
        "\u010cajni\u010de"
    ],
    "name:ces_x_preferred":[
        "\u010cajni\u010de"
    ],
    "name:deu_x_preferred":[
        "\u010cajni\u010de"
    ],
    "name:ell_x_preferred":[
        "\u03a4\u03c3\u03ac\u03b9\u03bd\u03b9\u03c4\u03c3\u03b5"
    ],
    "name:eng_x_preferred":[
        "\u010cajni\u010de"
    ],
    "name:fas_x_preferred":[
        "\u0686\u0627\u06cc\u0646\u06cc\u0686\u0647"
    ],
    "name:fra_x_preferred":[
        "\u010cajni\u010de"
    ],
    "name:hrv_x_preferred":[
        "\u010cajni\u010de"
    ],
    "name:hsb_x_preferred":[
        "\u010cajni\u010de"
    ],
    "name:ita_x_preferred":[
        "\u010cajni\u010de"
    ],
    "name:jpn_x_preferred":[
        "\u30c1\u30e3\u30a4\u30cb\u30c1\u30a7"
    ],
    "name:nld_x_preferred":[
        "\u010cajni\u010de"
    ],
    "name:pol_x_preferred":[
        "\u010cajni\u010de"
    ],
    "name:rus_x_preferred":[
        "\u0427\u0430\u0439\u043d\u0438\u0447\u0435"
    ],
    "name:sco_x_preferred":[
        "\u010cajni\u010de"
    ],
    "name:spa_x_preferred":[
        "\u010cajni\u010de"
    ],
    "name:srp_x_preferred":[
        "\u0427\u0430\u0458\u043d\u0438\u0447\u0435"
    ],
    "name:swe_x_preferred":[
        "\u010cajni\u010de"
    ],
    "name:tat_x_preferred":[
        "\u0427\u0430\u0439\u043d\u0438\u0442\u0441\u0435"
    ],
    "name:tur_x_preferred":[
        "\u00c7ayni\u00e7e"
    ],
    "name:ukr_x_preferred":[
        "\u0427\u0430\u0439\u043d\u0438\u0447\u0435"
    ],
    "name:urd_x_preferred":[
        "\u0686\u0627\u06cc\u0646\u06cc\u0686\u06d2"
    ],
    "name:zho_x_preferred":[
        "\u67e5\u4f0a\u5c3c\u5207"
    ],
    "qs:name":"\u010cajni\u010de",
    "qs:name_adm0":"Bosna i Hercegovina",
    "qs:name_adm1":"Republika Srpska",
    "qs:photos_9k":1,
    "qs:photos_9r":1,
    "qs:photos_all":18,
    "qs:photos_sr":0,
    "qs:placetype":"Town",
    "qs:pop_sr":"4",
    "wd:wordcount":185,
    "wof:name":"\u010cajni\u010de",
    "wof:placetype":"locality",
    "wof:population":3909
},
  "geometry": {"coordinates":[19.07186,43.55712],"type":"Point"}
}