{
  "type": "Feature",
  "properties": {
    "gn:admin1_code":"02",
    "gn:asciiname":"Trnjani",
    "gn:country_code":"BA",
    "gn:dem":179,
    "gn:feature_class":"P",
    "gn:feature_code":"PPLL",
    "gn:name":"Trnjani",
    "gn:population":0,
    "gn:timezone":"Europe/Sarajevo",
    "iso:country":"BA",
    "name:bos_x_preferred":[
        "Trnjani"
    ],
    "name:ceb_x_preferred":[
        "Trnjani"
    ],
    "name:fra_x_preferred":[
        "Trnjani"
    ],
    "name:hrv_x_preferred":[
        "Trnjani"
    ],
    "name:slv_x_preferred":[
        "Trnjani"
    ],
    "name:srp_x_preferred":[
        "\u0422\u0440\u045a\u0430\u043d\u0438"
    ],
    "name:swe_x_preferred":[
        "Trnjani"
    ],
    "wof:name":"Trnjani",
    "wof:placetype":"locality"
},
  "geometry": {"coordinates":[18.07698,44.91512],"type":"Point"}
}