{
  "type": "Feature",
  "properties": {
    "gn:admin1_code":"02",
    "gn:asciiname":"Trnjani",
    "gn:country_code":"BA",
    "gn:dem":179,
    "gn:feature_class":"P",
    "gn:feature_code":"PPLL",
    "gn:name":"Trnjani",
    "gn:population":0,
    "gn:timezone":"Europe/Sarajevo",
    "iso:country":"BA",
    "wof:name":"Trnjani",
    "wof:placetype":"locality"
},
  "geometry": {"coordinates":[18.07698,44.91512],"type":"Point"}
}