{
  "type": "Feature",
  "properties": {
    "gn:admin1_code":"01",
    "gn:asciiname":"Renovica",
    "gn:country_code":"BA",
    "gn:dem":656,
    "gn:feature_class":"P",
    "gn:feature_code":"PPLL",
    "gn:name":"Renovica",
    "gn:population":0,
    "gn:timezone":"Europe/Sarajevo",
    "iso:country":"BA",
    "name:bos_x_preferred":[
        "Renovica"
    ],
    "name:fra_x_preferred":[
        "Renovica"
    ],
    "wof:name":"Renovica",
    "wof:placetype":"locality"
},
  "geometry": {"coordinates":[18.83278,43.76583],"type":"Point"}
}