{
  "type": "Feature",
  "properties": {
    "gn:admin1_code":"01",
    "gn:asciiname":"Kovacevac",
    "gn:country_code":"BA",
    "gn:dem":562,
    "gn:feature_class":"P",
    "gn:feature_code":"PPL",
    "gn:name":"Kova\u010devac",
    "gn:population":0,
    "gn:timezone":"Europe/Sarajevo",
    "iso:country":"BA",
    "wof:name":"Kovacevac",
    "wof:placetype":"locality"
},
  "geometry": {"coordinates":[18.24278,43.85889],"type":"Point"}
}