{
  "type": "Feature",
  "properties": {
    "gn:admin1_code":"01",
    "gn:asciiname":"Ljusina",
    "gn:country_code":"BA",
    "gn:dem":270,
    "gn:feature_class":"P",
    "gn:feature_code":"PPLL",
    "gn:name":"Ljusina",
    "gn:population":0,
    "gn:timezone":"Europe/Sarajevo",
    "iso:country":"BA",
    "wof:name":"Ljusina",
    "wof:placetype":"locality"
},
  "geometry": {"coordinates":[16.13199,44.94738],"type":"Point"}
}