{
  "type": "Feature",
  "properties": {
    "gn:admin1_code":"01",
    "gn:asciiname":"Ljusina",
    "gn:country_code":"BA",
    "gn:dem":270,
    "gn:feature_class":"P",
    "gn:feature_code":"PPLL",
    "gn:name":"Ljusina",
    "gn:population":0,
    "gn:timezone":"Europe/Sarajevo",
    "iso:country":"BA",
    "name:ara_x_preferred":[
        "\u0644\u064a\u0648\u0633\u064a\u0646\u0627"
    ],
    "name:bos_x_preferred":[
        "Ljusina"
    ],
    "name:fra_x_preferred":[
        "Ljusina"
    ],
    "name:hrv_x_preferred":[
        "Ljusina"
    ],
    "name:srp_x_preferred":[
        "\u0409\u0443\u0441\u0438\u043d\u0430"
    ],
    "wof:name":"Ljusina",
    "wof:placetype":"locality"
},
  "geometry": {"coordinates":[16.13199,44.94738],"type":"Point"}
}