{
  "type": "Feature",
  "properties": {
    "gn:admin1_code":"02",
    "gn:asciiname":"Gornji Srdevici",
    "gn:country_code":"BA",
    "gn:dem":162,
    "gn:feature_class":"P",
    "gn:feature_code":"PPLL",
    "gn:name":"Gornji Sr\u0111evi\u0107i",
    "gn:population":0,
    "gn:timezone":"Europe/Sarajevo",
    "iso:country":"BA",
    "wof:name":"Gornji Srdevici",
    "wof:placetype":"locality"
},
  "geometry": {"coordinates":[17.59197,44.97369000000001],"type":"Point"}
}