{
  "type": "Feature",
  "properties": {
    "gn:admin1_code":"02",
    "gn:asciiname":"Zuzelo",
    "gn:country_code":"BA",
    "gn:dem":509,
    "gn:feature_class":"P",
    "gn:feature_code":"PPL",
    "gn:name":"\u017du\u017eelo",
    "gn:population":0,
    "gn:timezone":"Europe/Sarajevo",
    "iso:country":"BA",
    "name:bos_x_preferred":[
        "\u017du\u017eelo"
    ],
    "name:fra_x_preferred":[
        "\u017du\u017eelo"
    ],
    "name:und_x_variant":[
        "\u017du\u017eelj"
    ],
    "wof:name":"Zuzelo",
    "wof:placetype":"locality"
},
  "geometry": {"coordinates":[19.01519,43.67082],"type":"Point"}
}