{
  "type": "Feature",
  "properties": {
    "gn:admin1_code":"01",
    "gn:asciiname":"Sovici",
    "gn:country_code":"BA",
    "gn:dem":856,
    "gn:feature_class":"P",
    "gn:feature_code":"PPLL",
    "gn:name":"Sovi\u0107i",
    "gn:population":0,
    "gn:timezone":"Europe/Sarajevo",
    "iso:country":"BA",
    "wof:name":"Sovici",
    "wof:placetype":"locality"
},
  "geometry": {"coordinates":[17.60086,43.70778],"type":"Point"}
}