{
  "type": "Feature",
  "properties": {
    "gn:admin1_code":"01",
    "gn:asciiname":"Smajilbasici",
    "gn:country_code":"BA",
    "gn:dem":166,
    "gn:feature_class":"P",
    "gn:feature_code":"PPL",
    "gn:name":"Smajilba\u0161i\u0107i",
    "gn:population":0,
    "gn:timezone":"Europe/Sarajevo",
    "iso:country":"BA",
    "wof:name":"Smajilbasici",
    "wof:placetype":"locality"
},
  "geometry": {"coordinates":[18.33829,44.66751],"type":"Point"}
}