{
  "type": "Feature",
  "properties": {
    "gn:admin1_code":"01",
    "gn:asciiname":"Bocinja Gornja",
    "gn:country_code":"BA",
    "gn:dem":395,
    "gn:feature_class":"P",
    "gn:feature_code":"PPLL",
    "gn:name":"Bo\u010dinja Gornja",
    "gn:population":0,
    "gn:timezone":"Europe/Sarajevo",
    "iso:country":"BA",
    "wof:name":"Bocinja Gornja",
    "wof:placetype":"locality"
},
  "geometry": {"coordinates":[18.20943,44.52562],"type":"Point"}
}