{
  "type": "Feature",
  "properties": {
    "gn:country":"BA",
    "gn:fcode":"PPL",
    "gn:population":3868,
    "iso:country":"BA",
    "name:bos_x_preferred":[
        "Dubravica"
    ],
    "name:ceb_x_preferred":[
        "Dubravica"
    ],
    "name:deu_x_preferred":[
        "Dubravica"
    ],
    "name:eng_x_preferred":[
        "Dubravica"
    ],
    "name:fra_x_preferred":[
        "Dubravica"
    ],
    "name:hrv_x_preferred":[
        "Dubravica"
    ],
    "name:hun_x_preferred":[
        "Dubravica"
    ],
    "name:nld_x_preferred":[
        "Dubravica"
    ],
    "name:ron_x_preferred":[
        "Dubravica"
    ],
    "name:srp_x_preferred":[
        "\u0414\u0443\u0431\u0440\u0430\u0432\u0438\u0446\u0430"
    ],
    "name:swe_x_preferred":[
        "Dubravica"
    ],
    "qs:name":"Dubravica",
    "qs:photos_9r":0,
    "qs:photos_sr":0,
    "qs:pop_sr":"4",
    "wd:wordcount":57,
    "wof:name":"Dubravica",
    "wof:placetype":"locality",
    "wof:population":3868
},
  "geometry": {"coordinates":[18.11882,44.44131],"type":"Point"}
}