{
  "type": "Feature",
  "properties": {
    "gn:country":"BA",
    "gn:fcode":"PPL",
    "gn:pop":3868,
    "iso:country":"BA",
    "qs:name":"Dubravica",
    "qs:photos_9r":0,
    "qs:photos_sr":0,
    "qs:pop_sr":"4",
    "wd:wordcount":57,
    "wof:name":"Dubravica",
    "wof:placetype":"locality",
    "wof:population":3868
},
  "geometry": {"coordinates":[18.11882,44.44131],"type":"Point"}
}