{
  "type": "Feature",
  "properties": {
    "gn:admin1_code":"02",
    "gn:asciiname":"Snijeznice",
    "gn:country_code":"BA",
    "gn:dem":1105,
    "gn:feature_class":"P",
    "gn:feature_code":"PPL",
    "gn:name":"Snije\u017enice",
    "gn:population":0,
    "gn:timezone":"Europe/Sarajevo",
    "iso:country":"BA",
    "wof:name":"Snijeznice",
    "wof:placetype":"locality"
},
  "geometry": {"coordinates":[18.41504,43.24704000000001],"type":"Point"}
}