{
  "type": "Feature",
  "properties": {
    "gn:admin1_code":"01",
    "gn:asciiname":"Luko",
    "gn:country_code":"BA",
    "gn:dem":793,
    "gn:feature_class":"P",
    "gn:feature_code":"PPLL",
    "gn:name":"Luko",
    "gn:population":0,
    "gn:timezone":"Europe/Sarajevo",
    "iso:country":"BA",
    "name:bos_x_preferred":[
        "Luko"
    ],
    "name:fra_x_preferred":[
        "Luko"
    ],
    "name:srp_x_preferred":[
        "\u041b\u0443\u043a\u043e"
    ],
    "wof:name":"Luko",
    "wof:placetype":"locality"
},
  "geometry": {"coordinates":[18.32675,43.48415],"type":"Point"}
}