{
  "type": "Feature",
  "properties": {
    "gn:admin1_code":"02",
    "gn:asciiname":"Poljari",
    "gn:country_code":"BA",
    "gn:dem":224,
    "gn:feature_class":"P",
    "gn:feature_code":"PPL",
    "gn:name":"Poljari",
    "gn:population":0,
    "gn:timezone":"Europe/Sarajevo",
    "iso:country":"BA",
    "name:bos_x_preferred":[
        "Poljari"
    ],
    "name:ell_x_preferred":[
        "\u03a0\u03cc\u03bb\u03b9\u03b1\u03c1\u03b9"
    ],
    "name:fra_x_preferred":[
        "Poljari"
    ],
    "name:hrv_x_preferred":[
        "Poljari"
    ],
    "name:rus_x_preferred":[
        "\u041f\u043e\u043b\u044f\u0440\u0438"
    ],
    "name:srp_x_preferred":[
        "\u041f\u043e\u0459\u0430\u0440\u0438"
    ],
    "wof:name":"Poljari",
    "wof:placetype":"locality"
},
  "geometry": {"coordinates":[16.89559,45.09361],"type":"Point"}
}