{
  "type": "Feature",
  "properties": {
    "gn:admin1_code":"02",
    "gn:asciiname":"Popici",
    "gn:country_code":"BA",
    "gn:dem":241,
    "gn:feature_class":"P",
    "gn:feature_code":"PPL",
    "gn:name":"Popi\u0107i",
    "gn:population":0,
    "gn:timezone":"Europe/Sarajevo",
    "iso:country":"BA",
    "wof:name":"Popici",
    "wof:placetype":"locality"
},
  "geometry": {"coordinates":[18.06238,44.95751],"type":"Point"}
}