{
  "type": "Feature",
  "properties": {
    "gn:admin1_code":"02",
    "gn:asciiname":"Radmanici",
    "gn:country_code":"BA",
    "gn:dem":510,
    "gn:feature_class":"P",
    "gn:feature_code":"PPL",
    "gn:name":"Radmani\u0107i",
    "gn:population":0,
    "gn:timezone":"Europe/Sarajevo",
    "iso:country":"BA",
    "name:und_x_variant":[
        "Radmani\u0107i"
    ],
    "wof:name":"Radmanici",
    "wof:placetype":"locality"
},
  "geometry": {"coordinates":[16.95444,44.70444000000001],"type":"Point"}
}