{
  "type": "Feature",
  "properties": {
    "gn:admin1_code":"02",
    "gn:asciiname":"Radmanici",
    "gn:country_code":"BA",
    "gn:dem":510,
    "gn:feature_class":"P",
    "gn:feature_code":"PPL",
    "gn:name":"Radmani\u0107i",
    "gn:population":0,
    "gn:timezone":"Europe/Sarajevo",
    "iso:country":"BA",
    "name:bos_x_preferred":[
        "Radmani\u0107i"
    ],
    "name:fra_x_preferred":[
        "Radmani\u0107i"
    ],
    "name:hrv_x_preferred":[
        "Radmani\u0107i"
    ],
    "name:rus_x_preferred":[
        "\u0420\u0430\u0434\u043c\u0430\u043d\u0438\u0447\u0438"
    ],
    "name:slv_x_preferred":[
        "Radmani\u0107i"
    ],
    "name:srp_x_preferred":[
        "\u0420\u0430\u0434\u043c\u0430\u043d\u0438\u045b\u0438"
    ],
    "name:und_x_variant":[
        "Radmani\u0107i"
    ],
    "wof:name":"Radmanici",
    "wof:placetype":"locality"
},
  "geometry": {"coordinates":[16.95444,44.70444000000001],"type":"Point"}
}