{
  "type": "Feature",
  "properties": {
    "gn:admin1_code":"02",
    "gn:asciiname":"Mindure",
    "gn:country_code":"BA",
    "gn:dem":996,
    "gn:feature_class":"P",
    "gn:feature_code":"PPL",
    "gn:name":"Min\u0111ure",
    "gn:population":0,
    "gn:timezone":"Europe/Sarajevo",
    "iso:country":"BA",
    "wof:name":"Mindure",
    "wof:placetype":"locality"
},
  "geometry": {"coordinates":[18.63229,43.82208],"type":"Point"}
}