{
  "type": "Feature",
  "properties": {
    "gn:admin1_code":"02",
    "gn:asciiname":"Brijeznica",
    "gn:country_code":"BA",
    "gn:dem":124,
    "gn:feature_class":"P",
    "gn:feature_code":"PPL",
    "gn:name":"Brije\u017enica",
    "gn:population":0,
    "gn:timezone":"Europe/Sarajevo",
    "iso:country":"BA",
    "name:und_x_variant":[
        "Donja Mionica",
        "Brije\u017enica"
    ],
    "wof:name":"Brijeznica",
    "wof:placetype":"locality"
},
  "geometry": {"coordinates":[18.52935,44.8659],"type":"Point"}
}