{
  "type": "Feature",
  "properties": {
    "gn:admin1_code":"01",
    "gn:asciiname":"Sopotnica",
    "gn:country_code":"BA",
    "gn:dem":521,
    "gn:feature_class":"P",
    "gn:feature_code":"PPL",
    "gn:name":"Sopotnica",
    "gn:population":0,
    "gn:timezone":"Europe/Sarajevo",
    "iso:country":"BA",
    "wof:name":"Sopotnica",
    "wof:placetype":"locality"
},
  "geometry": {"coordinates":[18.00062,44.11834],"type":"Point"}
}