{
  "type": "Feature",
  "properties": {
    "gn:admin1_code":"02",
    "gn:asciiname":"Baste",
    "gn:country_code":"BA",
    "gn:dem":557,
    "gn:feature_class":"P",
    "gn:feature_code":"PPL",
    "gn:name":"Baste",
    "gn:population":0,
    "gn:timezone":"Europe/Sarajevo",
    "iso:country":"BA",
    "wof:name":"Baste",
    "wof:placetype":"locality"
},
  "geometry": {"coordinates":[16.83564,44.75269],"type":"Point"}
}