{
  "type": "Feature",
  "properties": {
    "gn:admin1_code":"02",
    "gn:asciiname":"Vranjevac",
    "gn:country_code":"BA",
    "gn:dem":785,
    "gn:feature_class":"P",
    "gn:feature_code":"PPL",
    "gn:name":"Vranjevac",
    "gn:population":0,
    "gn:timezone":"Europe/Sarajevo",
    "iso:country":"BA",
    "wof:name":"Vranjevac",
    "wof:placetype":"locality"
},
  "geometry": {"coordinates":[18.98336,44.2676],"type":"Point"}
}