{
  "type": "Feature",
  "properties": {
    "gn:admin1_code":"02",
    "gn:asciiname":"Dodin Han",
    "gn:country_code":"BA",
    "gn:dem":845,
    "gn:feature_class":"P",
    "gn:feature_code":"PPL",
    "gn:name":"\u00d0o\u0111in Han",
    "gn:population":0,
    "gn:timezone":"Europe/Sarajevo",
    "iso:country":"BA",
    "wof:name":"Dodin Han",
    "wof:placetype":"locality"
},
  "geometry": {"coordinates":[18.69536,44.01425],"type":"Point"}
}