{
  "type": "Feature",
  "properties": {
    "gn:admin1_code":"01",
    "gn:asciiname":"Savije",
    "gn:country_code":"BA",
    "gn:dem":943,
    "gn:feature_class":"P",
    "gn:feature_code":"PPL",
    "gn:name":"\u0160avije",
    "gn:population":0,
    "gn:timezone":"Europe/Sarajevo",
    "iso:country":"BA",
    "wof:name":"Savije",
    "wof:placetype":"locality"
},
  "geometry": {"coordinates":[16.7592,44.16004],"type":"Point"}
}