{
  "type": "Feature",
  "properties": {
    "gn:admin1_code":"01",
    "gn:asciiname":"Celipici",
    "gn:country_code":"BA",
    "gn:dem":799,
    "gn:feature_class":"P",
    "gn:feature_code":"PPL",
    "gn:name":"\u010celipi\u0107i",
    "gn:population":0,
    "gn:timezone":"Europe/Sarajevo",
    "iso:country":"BA",
    "wof:name":"Celipici",
    "wof:placetype":"locality"
},
  "geometry": {"coordinates":[17.61496,44.1305],"type":"Point"}
}