{
  "type": "Feature",
  "properties": {
    "gn:admin1_code":"01",
    "gn:asciiname":"Grozdici",
    "gn:country_code":"BA",
    "gn:dem":239,
    "gn:feature_class":"P",
    "gn:feature_code":"PPL",
    "gn:name":"Grozdi\u0107i",
    "gn:population":0,
    "gn:timezone":"Europe/Sarajevo",
    "iso:country":"BA",
    "wof:name":"Grozdici",
    "wof:placetype":"locality"
},
  "geometry": {"coordinates":[18.10518,44.41413],"type":"Point"}
}