{
  "type": "Feature",
  "properties": {
    "gn:admin1_code":"02",
    "gn:asciiname":"Nadici",
    "gn:country_code":"BA",
    "gn:dem":895,
    "gn:feature_class":"P",
    "gn:feature_code":"PPL",
    "gn:name":"Nadi\u0107i",
    "gn:population":0,
    "gn:timezone":"Europe/Sarajevo",
    "iso:country":"BA",
    "wof:name":"Nadici",
    "wof:placetype":"locality"
},
  "geometry": {"coordinates":[18.81833,43.94778],"type":"Point"}
}