{
  "type": "Feature",
  "properties": {
    "gn:admin1_code":"02",
    "gn:asciiname":"Stanatovici",
    "gn:country_code":"BA",
    "gn:dem":552,
    "gn:feature_class":"P",
    "gn:feature_code":"PPLL",
    "gn:name":"Stanatovi\u0107i",
    "gn:population":0,
    "gn:timezone":"Europe/Sarajevo",
    "iso:country":"BA",
    "name:und_x_variant":[
        "Stanatovi\u0107i"
    ],
    "wof:name":"Stanatovici",
    "wof:placetype":"locality"
},
  "geometry": {"coordinates":[19.47173,44.08528],"type":"Point"}
}