{
  "type": "Feature",
  "properties": {
    "gn:admin1_code":"02",
    "gn:asciiname":"Stanatovici",
    "gn:country_code":"BA",
    "gn:dem":552,
    "gn:feature_class":"P",
    "gn:feature_code":"PPLL",
    "gn:name":"Stanatovi\u0107i",
    "gn:population":0,
    "gn:timezone":"Europe/Sarajevo",
    "iso:country":"BA",
    "name:bos_x_preferred":[
        "Stanatovi\u0107i"
    ],
    "name:bul_x_preferred":[
        "\u0421\u0442\u0430\u043d\u0430\u0442\u043e\u0432\u0438\u0447\u0438"
    ],
    "name:fra_x_preferred":[
        "Stanatovi\u0107i"
    ],
    "name:hrv_x_preferred":[
        "Stanatovi\u0107i"
    ],
    "name:rus_x_preferred":[
        "\u0421\u0442\u0430\u043d\u0430\u0442\u043e\u0432\u0438\u0447\u0438"
    ],
    "name:srp_x_preferred":[
        "\u0421\u0442\u0430\u043d\u0430\u0442\u043e\u0432\u0438\u045b\u0438"
    ],
    "wof:name":"Stanatovici",
    "wof:placetype":"locality"
},
  "geometry": {"coordinates":[19.47173,44.08528],"type":"Point"}
}