{
  "type": "Feature",
  "properties": {
    "gn:admin1_code":"01",
    "gn:asciiname":"Netaca",
    "gn:country_code":"BA",
    "gn:dem":226,
    "gn:feature_class":"P",
    "gn:feature_code":"PPLL",
    "gn:name":"Neta\u010da",
    "gn:population":0,
    "gn:timezone":"Europe/Sarajevo",
    "iso:country":"BA",
    "wof:name":"Netaca",
    "wof:placetype":"locality"
},
  "geometry": {"coordinates":[17.95736,44.68527],"type":"Point"}
}