{
  "type": "Feature",
  "properties": {
    "gn:admin1_code":"02",
    "gn:asciiname":"Katunista",
    "gn:country_code":"BA",
    "gn:dem":1137,
    "gn:feature_class":"P",
    "gn:feature_code":"PPL",
    "gn:name":"Katuni\u0161ta",
    "gn:population":0,
    "gn:timezone":"Europe/Sarajevo",
    "iso:country":"BA",
    "wof:name":"Katunista",
    "wof:placetype":"locality"
},
  "geometry": {"coordinates":[18.51521,43.57912],"type":"Point"}
}