{
  "type": "Feature",
  "properties": {
    "gn:admin1_code":"01",
    "gn:asciiname":"Stupari",
    "gn:country_code":"BA",
    "gn:dem":442,
    "gn:feature_class":"P",
    "gn:feature_code":"PPL",
    "gn:name":"Stupari",
    "gn:population":0,
    "gn:timezone":"Europe/Sarajevo",
    "iso:country":"BA",
    "wof:name":"Stupari",
    "wof:placetype":"locality"
},
  "geometry": {"coordinates":[16.69915,44.55077],"type":"Point"}
}