{
  "type": "Feature",
  "properties": {
    "gn:admin1_code":"02",
    "gn:asciiname":"Dedinjci",
    "gn:country_code":"BA",
    "gn:dem":218,
    "gn:feature_class":"P",
    "gn:feature_code":"PPLL",
    "gn:name":"\u00d0edinjci",
    "gn:population":0,
    "gn:timezone":"Europe/Sarajevo",
    "iso:country":"BA",
    "wof:name":"Dedinjci",
    "wof:placetype":"locality"
},
  "geometry": {"coordinates":[17.89856,44.78329],"type":"Point"}
}