{
  "type": "Feature",
  "properties": {
    "gn:admin1_code":"02",
    "gn:asciiname":"Lazukici",
    "gn:country_code":"BA",
    "gn:dem":902,
    "gn:feature_class":"P",
    "gn:feature_code":"PPL",
    "gn:name":"Lazuki\u0107i",
    "gn:population":0,
    "gn:timezone":"Europe/Sarajevo",
    "iso:country":"BA",
    "wof:name":"Lazukici",
    "wof:placetype":"locality"
},
  "geometry": {"coordinates":[17.13786,44.17204],"type":"Point"}
}