{
  "type": "Feature",
  "properties": {
    "gn:admin1_code":"01",
    "gn:asciiname":"Ratkovici",
    "gn:country_code":"BA",
    "gn:dem":443,
    "gn:feature_class":"P",
    "gn:feature_code":"PPL",
    "gn:name":"Ratkovi\u0107i",
    "gn:population":0,
    "gn:timezone":"Europe/Sarajevo",
    "iso:country":"BA",
    "name:bos_x_preferred":[
        "Ratkovi\u0107i"
    ],
    "name:ceb_x_preferred":[
        "Ratkovi\u0107i"
    ],
    "name:fra_x_preferred":[
        "Ratkovi\u0107i"
    ],
    "name:swe_x_preferred":[
        "Ratkovi\u0107i"
    ],
    "wof:name":"Ratkovici",
    "wof:placetype":"locality"
},
  "geometry": {"coordinates":[18.92099,43.63311],"type":"Point"}
}