{
  "type": "Feature",
  "properties": {
    "gn:country":"BA",
    "gn:fcode":"PPL",
    "gn:population":3489,
    "iso:country":"BA",
    "name:bos_x_preferred":[
        "Donja Dubica"
    ],
    "name:ceb_x_preferred":[
        "Donja Dubica"
    ],
    "name:eng_x_preferred":[
        "Donja Dubica"
    ],
    "name:fra_x_preferred":[
        "Donja Dubica"
    ],
    "name:hrv_x_preferred":[
        "Donja Dubica"
    ],
    "name:nld_x_preferred":[
        "Donja Dubica"
    ],
    "name:pol_x_preferred":[
        "Donja Dubica"
    ],
    "name:spa_x_preferred":[
        "Donja Dubica"
    ],
    "name:srp_x_preferred":[
        "\u0414\u043e\u045a\u0430 \u0414\u0443\u0431\u0438\u0446\u0430"
    ],
    "name:swe_x_preferred":[
        "Donja Dubica"
    ],
    "qs:name":"Donja Dubica",
    "qs:name_adm0":"Bosna i Hercegovina",
    "qs:name_adm1":"Federacija Bosne I Hercegovine",
    "qs:photos_9k":1,
    "qs:photos_9r":1,
    "qs:photos_all":1,
    "qs:photos_sr":0,
    "qs:placetype":"Town",
    "qs:pop_sr":"4",
    "wof:name":"Donja Dubica",
    "wof:placetype":"locality",
    "wof:population":3489
},
  "geometry": {"coordinates":[18.41023,45.07559],"type":"Point"}
}