{
  "type": "Feature",
  "properties": {
    "gn:admin1_code":"02",
    "gn:asciiname":"Smolici",
    "gn:country_code":"BA",
    "gn:dem":316,
    "gn:feature_class":"P",
    "gn:feature_code":"PPL",
    "gn:name":"Smoli\u0107i",
    "gn:population":0,
    "gn:timezone":"Europe/Sarajevo",
    "iso:country":"BA",
    "wof:name":"Smolici",
    "wof:placetype":"locality"
},
  "geometry": {"coordinates":[17.57125,44.77554],"type":"Point"}
}