{
  "type": "Feature",
  "properties": {
    "gn:admin1_code":"01",
    "gn:asciiname":"Sabanci",
    "gn:country_code":"BA",
    "gn:dem":972,
    "gn:feature_class":"P",
    "gn:feature_code":"PPL",
    "gn:name":"\u0160abanci",
    "gn:population":0,
    "gn:timezone":"Europe/Sarajevo",
    "iso:country":"BA",
    "name:und_x_variant":[
        "\u0160abanci"
    ],
    "wof:name":"Sabanci",
    "wof:placetype":"locality"
},
  "geometry": {"coordinates":[18.33648,43.69388],"type":"Point"}
}