{
  "type": "Feature",
  "properties": {
    "gn:admin1_code":"01",
    "gn:asciiname":"Pavlovici",
    "gn:country_code":"BA",
    "gn:dem":379,
    "gn:feature_class":"P",
    "gn:feature_code":"PPL",
    "gn:name":"Pavlovi\u0107i",
    "gn:population":0,
    "gn:timezone":"Europe/Sarajevo",
    "iso:country":"BA",
    "wof:name":"Pavlovici",
    "wof:placetype":"locality"
},
  "geometry": {"coordinates":[17.64832999999999,43.1275],"type":"Point"}
}