{
  "type": "Feature",
  "properties": {
    "gn:admin1_code":"01",
    "gn:asciiname":"Milasevci",
    "gn:country_code":"BA",
    "gn:dem":859,
    "gn:feature_class":"P",
    "gn:feature_code":"PPL",
    "gn:name":"Mila\u0161evci",
    "gn:population":0,
    "gn:timezone":"Europe/Sarajevo",
    "iso:country":"BA",
    "wof:name":"Milasevci",
    "wof:placetype":"locality"
},
  "geometry": {"coordinates":[17.36491,44.44534],"type":"Point"}
}