{
  "type": "Feature",
  "properties": {
    "gn:admin1_code":"02",
    "gn:asciiname":"Kusace",
    "gn:country_code":"BA",
    "gn:dem":925,
    "gn:feature_class":"P",
    "gn:feature_code":"PPLL",
    "gn:name":"Kusa\u010de",
    "gn:population":0,
    "gn:timezone":"Europe/Sarajevo",
    "iso:country":"BA",
    "name:bos_x_preferred":[
        "Kusa\u010de"
    ],
    "name:fra_x_preferred":[
        "Kusa\u010de"
    ],
    "name:srp_x_preferred":[
        "\u041a\u0443\u0441\u0430\u0447\u0435"
    ],
    "name:und_x_variant":[
        "Kusa\u010da",
        "Kusa\u010de"
    ],
    "wof:name":"Kusace",
    "wof:placetype":"locality"
},
  "geometry": {"coordinates":[18.85173,43.93185],"type":"Point"}
}