{
  "type": "Feature",
  "properties": {
    "gn:admin1_code":"02",
    "gn:asciiname":"Trebesnjica",
    "gn:country_code":"BA",
    "gn:dem":445,
    "gn:feature_class":"P",
    "gn:feature_code":"PPL",
    "gn:name":"Trebe\u0161njica",
    "gn:population":0,
    "gn:timezone":"Europe/Sarajevo",
    "iso:country":"BA",
    "wof:name":"Trebesnjica",
    "wof:placetype":"locality"
},
  "geometry": {"coordinates":[17.10926,44.28849],"type":"Point"}
}