{
  "type": "Feature",
  "properties": {
    "gn:admin1_code":"02",
    "gn:asciiname":"Stolice",
    "gn:country_code":"BA",
    "gn:dem":854,
    "gn:feature_class":"P",
    "gn:feature_code":"PPL",
    "gn:name":"Stolice",
    "gn:population":0,
    "gn:timezone":"Europe/Sarajevo",
    "iso:country":"BA",
    "wof:name":"Stolice",
    "wof:placetype":"locality"
},
  "geometry": {"coordinates":[18.34556,42.92628],"type":"Point"}
}