{
  "type": "Feature",
  "properties": {
    "gn:admin1_code":"01",
    "gn:asciiname":"Pelemis",
    "gn:country_code":"BA",
    "gn:dem":414,
    "gn:feature_class":"P",
    "gn:feature_code":"PPL",
    "gn:name":"Pelemis",
    "gn:population":0,
    "gn:timezone":"Europe/Sarajevo",
    "iso:country":"BA",
    "wof:name":"Pelemis",
    "wof:placetype":"locality"
},
  "geometry": {"coordinates":[18.78038,44.51664],"type":"Point"}
}