{
  "type": "Feature",
  "properties": {
    "gn:admin1_code":"02",
    "gn:asciiname":"Lisovici",
    "gn:country_code":"BA",
    "gn:dem":914,
    "gn:feature_class":"P",
    "gn:feature_code":"PPL",
    "gn:name":"Lisovi\u0107i",
    "gn:population":0,
    "gn:timezone":"Europe/Sarajevo",
    "iso:country":"BA",
    "wof:name":"Lisovici",
    "wof:placetype":"locality"
},
  "geometry": {"coordinates":[18.66634,43.70977],"type":"Point"}
}