{
  "type": "Feature",
  "properties": {
    "gn:admin1_code":"01",
    "gn:asciiname":"Osova",
    "gn:country_code":"BA",
    "gn:dem":336,
    "gn:feature_class":"P",
    "gn:feature_code":"PPL",
    "gn:name":"Osova",
    "gn:population":0,
    "gn:timezone":"Europe/Sarajevo",
    "iso:country":"BA",
    "wof:name":"Osova",
    "wof:placetype":"locality"
},
  "geometry": {"coordinates":[18.08347,44.44682],"type":"Point"}
}