{
  "type": "Feature",
  "properties": {
    "gn:country":"BA",
    "gn:fcode":"PPL",
    "gn:pop":4947,
    "iso:country":"BA",
    "name:bos_x_preferred":[
        "Rogatica"
    ],
    "name:bul_x_preferred":[
        "\u0420\u043e\u0433\u0430\u0442\u0438\u0446\u0430"
    ],
    "name:deu_x_preferred":[
        "Rogatica"
    ],
    "name:eng_x_preferred":[
        "Rogatica"
    ],
    "name:fin_x_preferred":[
        "Rogatica"
    ],
    "name:fra_x_preferred":[
        "Rogatica"
    ],
    "name:hrv_x_preferred":[
        "Rogatica"
    ],
    "name:ita_x_preferred":[
        "Rogatica"
    ],
    "name:jpn_x_preferred":[
        "\u30ed\u30ac\u30c6\u30a3\u30c4\u30a1"
    ],
    "name:lit_x_preferred":[
        "Rogatica"
    ],
    "name:nld_x_preferred":[
        "Rogatica"
    ],
    "name:pol_x_preferred":[
        "Rogatica"
    ],
    "name:rus_x_preferred":[
        "\u0420\u043e\u0433\u0430\u0442\u0438\u0446\u0430"
    ],
    "name:sco_x_preferred":[
        "Rogatica"
    ],
    "name:spa_x_preferred":[
        "Rogatica"
    ],
    "name:srp_x_preferred":[
        "\u0420\u043e\u0433\u0430\u0442\u0438\u0446\u0430"
    ],
    "name:swe_x_preferred":[
        "Rogatica"
    ],
    "name:tat_x_preferred":[
        "\u0420\u043e\u0433\u0430\u0442\u0438\u0442\u0441\u0430"
    ],
    "name:tur_x_preferred":[
        "Rogatica"
    ],
    "name:ukr_x_preferred":[
        "\u0420\u043e\u0433\u0430\u0442\u0438\u0446\u044f"
    ],
    "name:unk_x_variant":[
        "Jelengrad"
    ],
    "name:urd_x_preferred":[
        "\u0631\u0648\u06af\u0627\u062a\u06cc\u062a\u0633\u0627"
    ],
    "name:zho_x_preferred":[
        "\u7f57\u52a0\u8482\u5bdf"
    ],
    "qs:name":"Rogatica",
    "qs:name_adm0":"Bosna i Hercegovina",
    "qs:name_adm1":"Republika Srpska",
    "qs:photos_9k":1,
    "qs:photos_9r":1,
    "qs:photos_all":1,
    "qs:photos_sr":0,
    "qs:placetype":"Town",
    "qs:pop_sr":"4",
    "wd:wordcount":622,
    "wof:name":"Rogatica",
    "wof:placetype":"locality",
    "wof:population":4947
},
  "geometry": {"coordinates":[19.00363,43.79894],"type":"Point"}
}