{
  "type": "Feature",
  "properties": {
    "gn:country":"BA",
    "gn:fcode":"PPL",
    "gn:population":4947,
    "iso:country":"BA",
    "name:bos_x_preferred":[
        "Rogatica"
    ],
    "name:bul_x_preferred":[
        "\u0420\u043e\u0433\u0430\u0442\u0438\u0446\u0430"
    ],
    "name:cat_x_preferred":[
        "Rogatica"
    ],
    "name:ceb_x_preferred":[
        "Rogatica"
    ],
    "name:ces_x_preferred":[
        "Rogatica"
    ],
    "name:dan_x_preferred":[
        "Rogatica"
    ],
    "name:deu_x_preferred":[
        "Rogatica"
    ],
    "name:ell_x_preferred":[
        "\u03a1\u03bf\u03b3\u03ba\u03ac\u03c4\u03b9\u03c4\u03c3\u03b1"
    ],
    "name:eng_x_preferred":[
        "Rogatica"
    ],
    "name:eus_x_preferred":[
        "Rogatica"
    ],
    "name:fas_x_preferred":[
        "\u0631\u0648\u06af\u0627\u062a\u06cc\u062a\u0633\u0627"
    ],
    "name:fin_x_preferred":[
        "Rogatica"
    ],
    "name:fra_x_preferred":[
        "Rogatica"
    ],
    "name:heb_x_preferred":[
        "\u05e8\u05d5\u05d2\u05d0\u05d8\u05d9\u05e6\u05d4"
    ],
    "name:hrv_x_preferred":[
        "Rogatica"
    ],
    "name:hsb_x_preferred":[
        "Rogatica"
    ],
    "name:hye_x_preferred":[
        "\u054c\u0578\u0563\u0561\u057f\u056b\u0581\u0561"
    ],
    "name:ind_x_preferred":[
        "Rogatica"
    ],
    "name:ita_x_preferred":[
        "Rogatica"
    ],
    "name:jpn_x_preferred":[
        "\u30ed\u30ac\u30c6\u30a3\u30c4\u30a1"
    ],
    "name:lit_x_preferred":[
        "Rogatica"
    ],
    "name:nld_x_preferred":[
        "Rogatica"
    ],
    "name:nno_x_preferred":[
        "Rogatica"
    ],
    "name:nob_x_preferred":[
        "Rogatica"
    ],
    "name:oci_x_preferred":[
        "Rogatica"
    ],
    "name:pol_x_preferred":[
        "Rogatica"
    ],
    "name:por_x_preferred":[
        "Rogatica"
    ],
    "name:ron_x_preferred":[
        "Rogatica"
    ],
    "name:rus_x_preferred":[
        "\u0420\u043e\u0433\u0430\u0442\u0438\u0446\u0430"
    ],
    "name:sco_x_preferred":[
        "Rogatica"
    ],
    "name:slk_x_preferred":[
        "Rogatica"
    ],
    "name:slv_x_preferred":[
        "Rogatica"
    ],
    "name:spa_x_preferred":[
        "Rogatica"
    ],
    "name:sqi_x_preferred":[
        "Rogatica"
    ],
    "name:srp_x_preferred":[
        "\u0420\u043e\u0433\u0430\u0442\u0438\u0446\u0430"
    ],
    "name:swe_x_preferred":[
        "Rogatica"
    ],
    "name:szl_x_preferred":[
        "Rogatica"
    ],
    "name:tat_x_preferred":[
        "\u0420\u043e\u0433\u0430\u0442\u0438\u0442\u0441\u0430"
    ],
    "name:tgl_x_preferred":[
        "Rogatica"
    ],
    "name:tur_x_preferred":[
        "Rogatica"
    ],
    "name:ukr_x_preferred":[
        "\u0420\u043e\u0433\u0430\u0442\u0438\u0446\u044f"
    ],
    "name:und_x_variant":[
        "Jelengrad"
    ],
    "name:urd_x_preferred":[
        "\u0631\u0648\u06af\u0627\u062a\u06cc\u062a\u0633\u0627"
    ],
    "name:war_x_preferred":[
        "Rogatica"
    ],
    "name:zho_x_preferred":[
        "\u7f57\u52a0\u8482\u5bdf"
    ],
    "qs:name":"Rogatica",
    "qs:name_adm0":"Bosna i Hercegovina",
    "qs:name_adm1":"Republika Srpska",
    "qs:photos_9k":1,
    "qs:photos_9r":1,
    "qs:photos_all":1,
    "qs:photos_sr":0,
    "qs:placetype":"Town",
    "qs:pop_sr":"4",
    "wd:wordcount":622,
    "wof:name":"Rogatica",
    "wof:placetype":"locality",
    "wof:population":4947
},
  "geometry": {"coordinates":[19.00363,43.79894],"type":"Point"}
}