{
  "type": "Feature",
  "properties": {
    "gn:admin1_code":"01",
    "gn:asciiname":"Jezero",
    "gn:country_code":"BA",
    "gn:dem":649,
    "gn:feature_class":"P",
    "gn:feature_code":"PPL",
    "gn:name":"Jezero",
    "gn:population":0,
    "gn:timezone":"Europe/Sarajevo",
    "iso:country":"BA",
    "name:ara_x_preferred":[
        "\u062c\u064a\u0632\u064a\u0631\u0648"
    ],
    "name:bos_x_preferred":[
        "Jezero"
    ],
    "name:ceb_x_preferred":[
        "Jezero"
    ],
    "name:ces_x_preferred":[
        "Jezero"
    ],
    "name:deu_x_preferred":[
        "Jezero"
    ],
    "name:fra_x_preferred":[
        "Jezero"
    ],
    "name:hrv_x_preferred":[
        "Jezero"
    ],
    "name:nld_x_preferred":[
        "Jezero"
    ],
    "name:pol_x_preferred":[
        "Jezero"
    ],
    "name:rus_x_preferred":[
        "\u0415\u0437\u0435\u0440\u043e"
    ],
    "name:slv_x_preferred":[
        "Jezero"
    ],
    "name:srp_x_preferred":[
        "\u0408\u0435\u0437\u0435\u0440\u043e"
    ],
    "name:swe_x_preferred":[
        "Jezero"
    ],
    "name:ukr_x_preferred":[
        "\u0404\u0437\u0435\u0440\u043e"
    ],
    "wof:name":"Jezero",
    "wof:placetype":"locality"
},
  "geometry": {"coordinates":[17.83281000000001,44.22336],"type":"Point"}
}