{
  "type": "Feature",
  "properties": {
    "gn:admin1_code":"02",
    "gn:asciiname":"Citluk",
    "gn:country_code":"BA",
    "gn:dem":234,
    "gn:feature_class":"P",
    "gn:feature_code":"PPLL",
    "gn:name":"\u010citluk",
    "gn:population":0,
    "gn:timezone":"Europe/Sarajevo",
    "iso:country":"BA",
    "wof:name":"Citluk",
    "wof:placetype":"locality"
},
  "geometry": {"coordinates":[16.61964,45.14445],"type":"Point"}
}