{
  "type": "Feature",
  "properties": {
    "gn:admin1_code":"02",
    "gn:asciiname":"Bunar",
    "gn:country_code":"BA",
    "gn:dem":270,
    "gn:feature_class":"P",
    "gn:feature_code":"PPLL",
    "gn:name":"Bunar",
    "gn:population":0,
    "gn:timezone":"Europe/Sarajevo",
    "iso:country":"BA",
    "name:ceb_x_preferred":[
        "Bunar"
    ],
    "name:fra_x_preferred":[
        "Bunar"
    ],
    "name:msa_x_preferred":[
        "Bunar"
    ],
    "name:nld_x_preferred":[
        "Bunar"
    ],
    "name:por_x_preferred":[
        "Bunar"
    ],
    "name:slv_x_preferred":[
        "Bunar"
    ],
    "name:srp_x_preferred":[
        "\u0411\u0443\u043d\u0430\u0440"
    ],
    "wof:name":"Bunar",
    "wof:placetype":"locality"
},
  "geometry": {"coordinates":[18.00558,44.93262],"type":"Point"}
}