{
  "type": "Feature",
  "properties": {
    "gn:admin1_code":"02",
    "gn:asciiname":"Sokoliste",
    "gn:country_code":"BA",
    "gn:dem":242,
    "gn:feature_class":"P",
    "gn:feature_code":"PPL",
    "gn:name":"Sokoli\u0161te",
    "gn:population":0,
    "gn:timezone":"Europe/Sarajevo",
    "iso:country":"BA",
    "wof:name":"Sokoliste",
    "wof:placetype":"locality"
},
  "geometry": {"coordinates":[16.47111,45.00056],"type":"Point"}
}