{
  "type": "Feature",
  "properties": {
    "gn:admin1_code":"01",
    "gn:asciiname":"Busiste",
    "gn:country_code":"BA",
    "gn:dem":431,
    "gn:feature_class":"P",
    "gn:feature_code":"PPL",
    "gn:name":"Bu\u0161i\u0161te",
    "gn:population":0,
    "gn:timezone":"Europe/Sarajevo",
    "iso:country":"BA",
    "wof:name":"Busiste",
    "wof:placetype":"locality"
},
  "geometry": {"coordinates":[18.33535,44.75082],"type":"Point"}
}