{
  "type": "Feature",
  "properties": {
    "gn:admin1_code":"02",
    "gn:asciiname":"Vidovici",
    "gn:country_code":"BA",
    "gn:dem":427,
    "gn:feature_class":"P",
    "gn:feature_code":"PPLL",
    "gn:name":"Vidovi\u0107i",
    "gn:population":0,
    "gn:timezone":"Europe/Sarajevo",
    "iso:country":"BA",
    "wof:name":"Vidovici",
    "wof:placetype":"locality"
},
  "geometry": {"coordinates":[18.32428,44.82355],"type":"Point"}
}