{
  "type": "Feature",
  "properties": {
    "gn:admin1_code":"02",
    "gn:asciiname":"Gornje Kosjerovo",
    "gn:country_code":"BA",
    "gn:dem":108,
    "gn:feature_class":"P",
    "gn:feature_code":"PPL",
    "gn:name":"Gornje Kosjerovo",
    "gn:population":0,
    "gn:timezone":"Europe/Sarajevo",
    "iso:country":"BA",
    "wof:name":"Gornje Kosjerovo",
    "wof:placetype":"locality"
},
  "geometry": {"coordinates":[17.37878,44.96328],"type":"Point"}
}