{
  "type": "Feature",
  "properties": {
    "gn:admin1_code":"02",
    "gn:asciiname":"Donji Klokocevik",
    "gn:country_code":"BA",
    "gn:dem":1036,
    "gn:feature_class":"P",
    "gn:feature_code":"PPL",
    "gn:name":"Donji Kloko\u010devik",
    "gn:population":0,
    "gn:timezone":"Europe/Sarajevo",
    "iso:country":"BA",
    "name:und_x_variant":[
        "Kloko\u010devik",
        "Donji Kloko\u010devik"
    ],
    "wof:name":"Donji Klokocevik",
    "wof:placetype":"locality"
},
  "geometry": {"coordinates":[18.53221,43.84347],"type":"Point"}
}