{
  "type": "Feature",
  "properties": {
    "gn:admin1_code":"02",
    "gn:asciiname":"Oljace",
    "gn:country_code":"BA",
    "gn:dem":274,
    "gn:feature_class":"P",
    "gn:feature_code":"PPL",
    "gn:name":"Olja\u010de",
    "gn:population":0,
    "gn:timezone":"Europe/Sarajevo",
    "iso:country":"BA",
    "wof:name":"Oljace",
    "wof:placetype":"locality"
},
  "geometry": {"coordinates":[16.8611,44.68794000000001],"type":"Point"}
}