{
  "type": "Feature",
  "properties": {
    "gn:admin1_code":"01",
    "gn:asciiname":"Trninic-Brijeg",
    "gn:country_code":"BA",
    "gn:dem":556,
    "gn:feature_class":"P",
    "gn:feature_code":"PPL",
    "gn:name":"Trnini\u0107-Brijeg",
    "gn:population":0,
    "gn:timezone":"Europe/Sarajevo",
    "iso:country":"BA",
    "wof:name":"Trninic-Brijeg",
    "wof:placetype":"locality"
},
  "geometry": {"coordinates":[16.37153,44.35188],"type":"Point"}
}