{
  "type": "Feature",
  "properties": {
    "gn:admin1_code":"01",
    "gn:asciiname":"Kovcici",
    "gn:country_code":"BA",
    "gn:dem":278,
    "gn:feature_class":"P",
    "gn:feature_code":"PPL",
    "gn:name":"Kov\u010di\u0107i",
    "gn:population":0,
    "gn:timezone":"Europe/Sarajevo",
    "iso:country":"BA",
    "wof:name":"Kovcici",
    "wof:placetype":"locality"
},
  "geometry": {"coordinates":[17.93431,44.71644000000001],"type":"Point"}
}