{
  "type": "Feature",
  "properties": {
    "gn:admin1_code":"01",
    "gn:asciiname":"Kolunije",
    "gn:country_code":"BA",
    "gn:dem":803,
    "gn:feature_class":"P",
    "gn:feature_code":"PPL",
    "gn:name":"Kolunije",
    "gn:population":0,
    "gn:timezone":"Europe/Sarajevo",
    "iso:country":"BA",
    "wof:name":"Kolunije",
    "wof:placetype":"locality"
},
  "geometry": {"coordinates":[17.45309,44.19837],"type":"Point"}
}