{
  "type": "Feature",
  "properties": {
    "gn:admin1_code":"01",
    "gn:asciiname":"Svitava",
    "gn:country_code":"BA",
    "gn:dem":29,
    "gn:feature_class":"P",
    "gn:feature_code":"PPL",
    "gn:name":"Svitava",
    "gn:population":0,
    "gn:timezone":"Europe/Sarajevo",
    "iso:country":"BA",
    "wof:name":"Svitava",
    "wof:placetype":"locality"
},
  "geometry": {"coordinates":[17.81177000000001,43.01476],"type":"Point"}
}