{
  "type": "Feature",
  "properties": {
    "gn:admin1_code":"01",
    "gn:asciiname":"Luka",
    "gn:country_code":"BA",
    "gn:dem":633,
    "gn:feature_class":"P",
    "gn:feature_code":"PPL",
    "gn:name":"Luka",
    "gn:population":0,
    "gn:timezone":"Europe/Sarajevo",
    "iso:country":"BA",
    "wof:name":"Luka",
    "wof:placetype":"locality"
},
  "geometry": {"coordinates":[18.05179,44.20043],"type":"Point"}
}