{
  "type": "Feature",
  "properties": {
    "gn:admin1_code":"02",
    "gn:asciiname":"Zaublina",
    "gn:country_code":"BA",
    "gn:dem":787,
    "gn:feature_class":"P",
    "gn:feature_code":"PPL",
    "gn:name":"Zaublina",
    "gn:population":0,
    "gn:timezone":"Europe/Sarajevo",
    "iso:country":"BA",
    "name:und_x_variant":[
        "Zaublina Ja\u010di\u0161te",
        "Zaublina"
    ],
    "wof:name":"Zaublina",
    "wof:placetype":"locality"
},
  "geometry": {"coordinates":[18.33469,42.96052],"type":"Point"}
}