{
  "type": "Feature",
  "properties": {
    "gn:admin1_code":"01",
    "gn:asciiname":"Adzici",
    "gn:country_code":"BA",
    "gn:dem":407,
    "gn:feature_class":"P",
    "gn:feature_code":"PPL",
    "gn:name":"Ad\u017ei\u0107i",
    "gn:population":0,
    "gn:timezone":"Europe/Sarajevo",
    "iso:country":"BA",
    "wof:name":"Adzici",
    "wof:placetype":"locality"
},
  "geometry": {"coordinates":[17.51871,43.34381],"type":"Point"}
}