{
  "type": "Feature",
  "properties": {
    "gn:admin1_code":"02",
    "gn:asciiname":"Kragulji",
    "gn:country_code":"BA",
    "gn:dem":193,
    "gn:feature_class":"P",
    "gn:feature_code":"PPL",
    "gn:name":"Kragulji",
    "gn:population":0,
    "gn:timezone":"Europe/Sarajevo",
    "iso:country":"BA",
    "wof:name":"Kragulji",
    "wof:placetype":"locality"
},
  "geometry": {"coordinates":[16.56333,45.05556],"type":"Point"}
}