{
  "type": "Feature",
  "properties": {
    "gn:admin1_code":"01",
    "gn:asciiname":"Stojkovici",
    "gn:country_code":"BA",
    "gn:dem":495,
    "gn:feature_class":"P",
    "gn:feature_code":"PPLL",
    "gn:name":"Stojkovi\u0107i",
    "gn:population":0,
    "gn:timezone":"Europe/Sarajevo",
    "iso:country":"BA",
    "wof:name":"Stojkovici",
    "wof:placetype":"locality"
},
  "geometry": {"coordinates":[17.68204,44.19174],"type":"Point"}
}