{
  "type": "Feature",
  "properties": {
    "gn:admin1_code":"02",
    "gn:asciiname":"Krajcin",
    "gn:country_code":"BA",
    "gn:dem":254,
    "gn:feature_class":"P",
    "gn:feature_code":"PPL",
    "gn:name":"Kraj\u010din",
    "gn:population":0,
    "gn:timezone":"Europe/Sarajevo",
    "iso:country":"BA",
    "wof:name":"Krajcin",
    "wof:placetype":"locality"
},
  "geometry": {"coordinates":[16.64977,45.03073],"type":"Point"}
}