{
  "type": "Feature",
  "properties": {
    "gn:admin1_code":"02",
    "gn:asciiname":"Paratuse",
    "gn:country_code":"BA",
    "gn:dem":285,
    "gn:feature_class":"P",
    "gn:feature_code":"PPL",
    "gn:name":"Paratu\u0161e",
    "gn:population":0,
    "gn:timezone":"Europe/Sarajevo",
    "iso:country":"BA",
    "wof:name":"Paratuse",
    "wof:placetype":"locality"
},
  "geometry": {"coordinates":[16.68198,45.05379],"type":"Point"}
}