{
  "type": "Feature",
  "properties": {
    "gn:admin1_code":"02",
    "gn:asciiname":"Bacici",
    "gn:country_code":"BA",
    "gn:dem":209,
    "gn:feature_class":"P",
    "gn:feature_code":"PPL",
    "gn:name":"Ba\u010di\u0107i",
    "gn:population":0,
    "gn:timezone":"Europe/Sarajevo",
    "iso:country":"BA",
    "wof:name":"Bacici",
    "wof:placetype":"locality"
},
  "geometry": {"coordinates":[16.68222,44.915],"type":"Point"}
}