{
  "type": "Feature",
  "properties": {
    "gn:admin1_code":"01",
    "gn:asciiname":"Boboska",
    "gn:country_code":"BA",
    "gn:dem":263,
    "gn:feature_class":"P",
    "gn:feature_code":"PPL",
    "gn:name":"Bobo\u0161ka",
    "gn:population":0,
    "gn:timezone":"Europe/Sarajevo",
    "iso:country":"BA",
    "wof:name":"Boboska",
    "wof:placetype":"locality"
},
  "geometry": {"coordinates":[17.42098,43.36778],"type":"Point"}
}