{
  "type": "Feature",
  "properties": {
    "gn:admin1_code":"02",
    "gn:asciiname":"Radici",
    "gn:country_code":"BA",
    "gn:dem":305,
    "gn:feature_class":"P",
    "gn:feature_code":"PPL",
    "gn:name":"Radi\u0107i",
    "gn:population":0,
    "gn:timezone":"Europe/Sarajevo",
    "iso:country":"BA",
    "name:deu_x_preferred":[
        "Radici"
    ],
    "name:ita_x_preferred":[
        "Radici"
    ],
    "wof:name":"Radici",
    "wof:placetype":"locality"
},
  "geometry": {"coordinates":[18.11793,44.75314],"type":"Point"}
}