{
  "type": "Feature",
  "properties": {
    "gn:admin1_code":"02",
    "gn:asciiname":"Grobljani",
    "gn:country_code":"BA",
    "gn:dem":158,
    "gn:feature_class":"P",
    "gn:feature_code":"PPL",
    "gn:name":"Grobljani",
    "gn:population":0,
    "gn:timezone":"Europe/Sarajevo",
    "iso:country":"BA",
    "wof:name":"Grobljani",
    "wof:placetype":"locality"
},
  "geometry": {"coordinates":[17.37133,44.90847],"type":"Point"}
}