{
  "type": "Feature",
  "properties": {
    "gn:admin1_code":"02",
    "gn:asciiname":"Krupa na Vrbasu",
    "gn:country_code":"BA",
    "gn:dem":221,
    "gn:feature_class":"P",
    "gn:feature_code":"PPL",
    "gn:name":"Krupa na Vrbasu",
    "gn:population":1257,
    "gn:timezone":"Europe/Sarajevo",
    "iso:country":"BA",
    "name:bos_x_preferred":[
        "Krupa na Vrbasu"
    ],
    "name:ceb_x_preferred":[
        "Krupa na Vrbasu"
    ],
    "name:deu_x_preferred":[
        "Krupa na Vrbasu"
    ],
    "name:fra_x_preferred":[
        "Krupa na Vrbasu"
    ],
    "name:hrv_x_preferred":[
        "Krupa na Vrbasu"
    ],
    "name:lit_x_preferred":[
        "Krupa prie Vrbaso"
    ],
    "name:rus_x_preferred":[
        "\u041a\u0440\u0443\u043f\u0430-\u041d\u0430-\u0412\u0440\u0431\u0430\u0441\u0443"
    ],
    "name:rus_x_variant":[
        "\u041a\u0440\u0443\u043f\u0430-\u043d\u0430-\u0412\u0440\u0431\u0430\u0441\u0443"
    ],
    "name:slv_x_preferred":[
        "Krupa na Vrbasu"
    ],
    "name:srp_x_preferred":[
        "\u041a\u0440\u0443\u043f\u0430 \u043d\u0430 \u0412\u0440\u0431\u0430\u0441\u0443"
    ],
    "name:swe_x_preferred":[
        "Krupa na Vrbasu"
    ],
    "name:und_x_variant":[
        "Krupa",
        "Vrbas"
    ],
    "wof:name":"Krupa na Vrbasu",
    "wof:placetype":"locality",
    "wof:population":1257
},
  "geometry": {"coordinates":[17.14351,44.61875],"type":"Point"}
}