{
  "type": "Feature",
  "properties": {
    "gn:admin1_code":"01",
    "gn:asciiname":"Jandrica Selo",
    "gn:country_code":"BA",
    "gn:dem":1202,
    "gn:feature_class":"P",
    "gn:feature_code":"PPL",
    "gn:name":"Jandri\u0107a Selo",
    "gn:population":0,
    "gn:timezone":"Europe/Sarajevo",
    "iso:country":"BA",
    "wof:name":"Jandrica Selo",
    "wof:placetype":"locality"
},
  "geometry": {"coordinates":[17.29584,43.95769],"type":"Point"}
}