{
  "type": "Feature",
  "properties": {
    "gn:admin1_code":"02",
    "gn:asciiname":"Catici",
    "gn:country_code":"BA",
    "gn:dem":884,
    "gn:feature_class":"P",
    "gn:feature_code":"PPL",
    "gn:name":"\u010cati\u0107i",
    "gn:population":0,
    "gn:timezone":"Europe/Sarajevo",
    "iso:country":"BA",
    "wof:name":"Catici",
    "wof:placetype":"locality"
},
  "geometry": {"coordinates":[18.70803,44.04969000000001],"type":"Point"}
}