{
  "type": "Feature",
  "properties": {
    "gn:admin1_code":"01",
    "gn:asciiname":"Jasen",
    "gn:country_code":"BA",
    "gn:dem":618,
    "gn:feature_class":"P",
    "gn:feature_code":"PPL",
    "gn:name":"Jasen",
    "gn:population":0,
    "gn:timezone":"Europe/Sarajevo",
    "iso:country":"BA",
    "wof:name":"Jasen",
    "wof:placetype":"locality"
},
  "geometry": {"coordinates":[18.3521,43.76257],"type":"Point"}
}