{
  "type": "Feature",
  "properties": {
    "gn:admin1_code":"BRC",
    "gn:asciiname":"Spionica",
    "gn:country_code":"BA",
    "gn:dem":191,
    "gn:feature_class":"P",
    "gn:feature_code":"PPL",
    "gn:name":"\u0160pionica",
    "gn:population":0,
    "gn:timezone":"Europe/Sarajevo",
    "iso:country":"BA",
    "wof:name":"Spionica",
    "wof:placetype":"locality"
},
  "geometry": {"coordinates":[18.67222000000001,44.76139000000001],"type":"Point"}
}