{
  "type": "Feature",
  "properties": {
    "gn:admin1_code":"01",
    "gn:asciiname":"Topuzovo Polje",
    "gn:country_code":"BA",
    "gn:dem":414,
    "gn:feature_class":"P",
    "gn:feature_code":"PPL",
    "gn:name":"Topuzovo Polje",
    "gn:population":0,
    "gn:timezone":"Europe/Sarajevo",
    "iso:country":"BA",
    "name:und_x_variant":[
        "Tupozovo Polje",
        "Topuzovo Polje"
    ],
    "wof:name":"Topuzovo Polje",
    "wof:placetype":"locality"
},
  "geometry": {"coordinates":[18.16361,44.0068],"type":"Point"}
}