{
  "type": "Feature",
  "properties": {
    "gn:admin1_code":"01",
    "gn:asciiname":"Mala Sipovaca",
    "gn:country_code":"BA",
    "gn:dem":99,
    "gn:feature_class":"P",
    "gn:feature_code":"PPLL",
    "gn:name":"Mala \u0160ipova\u010da",
    "gn:population":0,
    "gn:timezone":"Europe/Sarajevo",
    "iso:country":"BA",
    "name:bos_x_preferred":[
        "\u0160ipova\u010da"
    ],
    "name:ceb_x_preferred":[
        "Mala \u0160ipova\u010da"
    ],
    "name:fra_x_preferred":[
        "\u0160ipova\u010da"
    ],
    "name:hrv_x_preferred":[
        "\u0160ipova\u010da"
    ],
    "name:srp_x_preferred":[
        "\u0428\u0438\u043f\u043e\u0432\u0430\u0447\u0430"
    ],
    "name:swe_x_preferred":[
        "Mala \u0160ipova\u010da"
    ],
    "name:und_x_variant":[
        "\u0160ipova\u010da",
        "Mala \u0160ipova\u010da"
    ],
    "wof:name":"Mala Sipovaca",
    "wof:placetype":"locality"
},
  "geometry": {"coordinates":[17.3918,43.25591],"type":"Point"}
}