{
  "type": "Feature",
  "properties": {
    "gn:admin1_code":"01",
    "gn:asciiname":"Strane",
    "gn:country_code":"BA",
    "gn:dem":442,
    "gn:feature_class":"P",
    "gn:feature_code":"PPL",
    "gn:name":"Strane",
    "gn:population":0,
    "gn:timezone":"Europe/Sarajevo",
    "iso:country":"BA",
    "name:bos_x_preferred":[
        "Strane"
    ],
    "name:hrv_x_preferred":[
        "Strane"
    ],
    "name:nld_x_preferred":[
        "Strane"
    ],
    "name:pol_x_preferred":[
        "Strane"
    ],
    "name:ron_x_preferred":[
        "Strane"
    ],
    "name:slv_x_preferred":[
        "Strane"
    ],
    "name:ukr_x_preferred":[
        "\u0421\u0442\u0440\u0430\u043d\u0435"
    ],
    "wof:name":"Strane",
    "wof:placetype":"locality"
},
  "geometry": {"coordinates":[17.89224,44.13053],"type":"Point"}
}