{
  "type": "Feature",
  "properties": {
    "gn:admin1_code":"01",
    "gn:asciiname":"Strane",
    "gn:country_code":"BA",
    "gn:dem":442,
    "gn:feature_class":"P",
    "gn:feature_code":"PPL",
    "gn:name":"Strane",
    "gn:population":0,
    "gn:timezone":"Europe/Sarajevo",
    "iso:country":"BA",
    "wof:name":"Strane",
    "wof:placetype":"locality"
},
  "geometry": {"coordinates":[17.89224,44.13053],"type":"Point"}
}