{
  "type": "Feature",
  "properties": {
    "gn:admin1_code":"02",
    "gn:asciiname":"Kalebace",
    "gn:country_code":"BA",
    "gn:dem":464,
    "gn:feature_class":"P",
    "gn:feature_code":"PPLL",
    "gn:name":"Kaleba\u010de",
    "gn:population":0,
    "gn:timezone":"Europe/Sarajevo",
    "iso:country":"BA",
    "name:und_x_variant":[
        "Kalaba\u010de",
        "Kaleba\u010de"
    ],
    "wof:name":"Kalebace",
    "wof:placetype":"locality"
},
  "geometry": {"coordinates":[18.96802000000001,44.31358],"type":"Point"}
}