{
  "type": "Feature",
  "properties": {
    "gn:admin1_code":"02",
    "gn:asciiname":"Grablje",
    "gn:country_code":"BA",
    "gn:dem":496,
    "gn:feature_class":"P",
    "gn:feature_code":"PPL",
    "gn:name":"Grablje",
    "gn:population":0,
    "gn:timezone":"Europe/Sarajevo",
    "iso:country":"BA",
    "wof:name":"Grablje",
    "wof:placetype":"locality"
},
  "geometry": {"coordinates":[18.137,42.92719],"type":"Point"}
}