{
  "type": "Feature",
  "properties": {
    "gn:admin1_code":"02",
    "gn:asciiname":"Paljustine",
    "gn:country_code":"BA",
    "gn:dem":107,
    "gn:feature_class":"P",
    "gn:feature_code":"PPL",
    "gn:name":"Palju\u0161tine",
    "gn:population":0,
    "gn:timezone":"Europe/Sarajevo",
    "iso:country":"BA",
    "wof:name":"Paljustine",
    "wof:placetype":"locality"
},
  "geometry": {"coordinates":[17.15159,45.06949],"type":"Point"}
}