{
  "type": "Feature",
  "properties": {
    "gn:admin1_code":"01",
    "gn:asciiname":"Husici",
    "gn:country_code":"BA",
    "gn:dem":453,
    "gn:feature_class":"P",
    "gn:feature_code":"PPL",
    "gn:name":"Husi\u0107i",
    "gn:population":0,
    "gn:timezone":"Europe/Sarajevo",
    "iso:country":"BA",
    "wof:name":"Husici",
    "wof:placetype":"locality"
},
  "geometry": {"coordinates":[16.73845,44.60276],"type":"Point"}
}