{
  "type": "Feature",
  "properties": {
    "gn:country":"BA",
    "gn:fcode":"PPL",
    "gn:pop":15950,
    "iso:country":"BA",
    "name:ara_x_preferred":[
        "\u0643\u0648\u0646\u064a\u064a\u062a\u0634"
    ],
    "name:bel_x_preferred":[
        "\u041a\u043e\u043d\u0456\u0446"
    ],
    "name:bos_x_preferred":[
        "Konjic"
    ],
    "name:bul_x_preferred":[
        "\u041a\u043e\u043d\u0438\u0446"
    ],
    "name:ces_x_preferred":[
        "Konjic"
    ],
    "name:dan_x_preferred":[
        "Konjic"
    ],
    "name:deu_x_preferred":[
        "Konjic"
    ],
    "name:ell_x_preferred":[
        "\u039a\u03cc\u03bd\u03b9\u03c4\u03c2"
    ],
    "name:eng_x_preferred":[
        "Konjic"
    ],
    "name:fas_x_preferred":[
        "\u06a9\u0648\u0646\u06cc\u06cc\u062a\u0633"
    ],
    "name:fra_x_preferred":[
        "Konjic"
    ],
    "name:hrv_x_preferred":[
        "Konjic"
    ],
    "name:ile_x_preferred":[
        "Konjic"
    ],
    "name:ita_x_preferred":[
        "Konjic"
    ],
    "name:jpn_x_preferred":[
        "\u30b3\u30cb\u30c4"
    ],
    "name:kor_x_preferred":[
        "\ucf54\ub2c8\uce20"
    ],
    "name:nld_x_preferred":[
        "Konjic"
    ],
    "name:pol_x_preferred":[
        "Konjic"
    ],
    "name:rus_x_preferred":[
        "\u041a\u043e\u043d\u044c\u0438\u0446"
    ],
    "name:slk_x_preferred":[
        "Konjic"
    ],
    "name:spa_x_preferred":[
        "Konjic"
    ],
    "name:sqi_x_preferred":[
        "Konjiqi"
    ],
    "name:srp_x_preferred":[
        "\u041a\u043e\u045a\u0438\u0446"
    ],
    "name:swe_x_preferred":[
        "Konjic"
    ],
    "name:tat_x_preferred":[
        "\u041a\u043e\u043d\u0438\u0442\u0441"
    ],
    "name:ukr_x_preferred":[
        "\u041a\u043e\u043d\u0456\u0446"
    ],
    "name:urd_x_preferred":[
        "\u06a9\u0648\u0646\u06cc\u0633"
    ],
    "name:zho_x_preferred":[
        "\u79d1\u5c3c\u8328"
    ],
    "qs:name":"Konjic",
    "qs:photos_9r":0,
    "qs:photos_sr":0,
    "qs:pop_sr":"6",
    "wd:wordcount":3313,
    "wof:name":"Konjic",
    "wof:placetype":"locality",
    "wof:population":15950
},
  "geometry": {"coordinates":[17.96082,43.65126],"type":"Point"}
}