{
  "type": "Feature",
  "properties": {
    "gn:admin1_code":"01",
    "gn:asciiname":"Vidovici",
    "gn:country_code":"BA",
    "gn:dem":178,
    "gn:feature_class":"P",
    "gn:feature_code":"PPL",
    "gn:name":"Vidovi\u0107i",
    "gn:population":0,
    "gn:timezone":"Europe/Sarajevo",
    "iso:country":"BA",
    "wof:name":"Vidovici",
    "wof:placetype":"locality"
},
  "geometry": {"coordinates":[16.71349,44.70741],"type":"Point"}
}