{
  "type": "Feature",
  "properties": {
    "gn:admin1_code":"02",
    "gn:asciiname":"Selacka",
    "gn:country_code":"BA",
    "gn:dem":925,
    "gn:feature_class":"P",
    "gn:feature_code":"PPLL",
    "gn:name":"Sela\u010dka",
    "gn:population":0,
    "gn:timezone":"Europe/Sarajevo",
    "iso:country":"BA",
    "wof:name":"Selacka",
    "wof:placetype":"locality"
},
  "geometry": {"coordinates":[17.60675,44.46432],"type":"Point"}
}