{
  "type": "Feature",
  "properties": {
    "gn:admin1_code":"01",
    "gn:asciiname":"Becirovici",
    "gn:country_code":"BA",
    "gn:dem":410,
    "gn:feature_class":"P",
    "gn:feature_code":"PPL",
    "gn:name":"Be\u0107irovi\u0107i",
    "gn:population":0,
    "gn:timezone":"Europe/Sarajevo",
    "iso:country":"BA",
    "wof:name":"Becirovici",
    "wof:placetype":"locality"
},
  "geometry": {"coordinates":[18.147,44.39694],"type":"Point"}
}