{
  "type": "Feature",
  "properties": {
    "gn:admin1_code":"02",
    "gn:asciiname":"Gornje Vodicevo",
    "gn:country_code":"BA",
    "gn:dem":241,
    "gn:feature_class":"P",
    "gn:feature_code":"PPLL",
    "gn:name":"Gornje Vodi\u010devo",
    "gn:population":0,
    "gn:timezone":"Europe/Sarajevo",
    "iso:country":"BA",
    "name:bos_x_preferred":[
        "Gornje Vodi\u010devo"
    ],
    "name:ceb_x_preferred":[
        "Gornje Vodi\u010devo"
    ],
    "name:fra_x_preferred":[
        "Gornje Vodi\u010devo"
    ],
    "name:hrv_x_preferred":[
        "Gornje Vodi\u010devo"
    ],
    "name:srp_x_preferred":[
        "\u0413\u043e\u0440\u045a\u0435 \u0412\u043e\u0434\u0438\u0447\u0435\u0432\u043e"
    ],
    "name:swe_x_preferred":[
        "Gornje Vodi\u010devo"
    ],
    "name:und_x_variant":[
        "Gornje Vodi\u010devo"
    ],
    "wof:name":"Gornje Vodicevo",
    "wof:placetype":"locality"
},
  "geometry": {"coordinates":[16.48157,45.13094],"type":"Point"}
}