{
  "type": "Feature",
  "properties": {
    "gn:admin1_code":"02",
    "gn:asciiname":"Gornje Vodicevo",
    "gn:country_code":"BA",
    "gn:dem":241,
    "gn:feature_class":"P",
    "gn:feature_code":"PPLL",
    "gn:name":"Gornje Vodi\u010devo",
    "gn:population":0,
    "gn:timezone":"Europe/Sarajevo",
    "iso:country":"BA",
    "name:und_x_variant":[
        "Gornje Vodi\u010devo"
    ],
    "wof:name":"Gornje Vodicevo",
    "wof:placetype":"locality"
},
  "geometry": {"coordinates":[16.48157,45.13094],"type":"Point"}
}