{
  "type": "Feature",
  "properties": {
    "gn:admin1_code":"02",
    "gn:asciiname":"Plavsici",
    "gn:country_code":"BA",
    "gn:dem":472,
    "gn:feature_class":"P",
    "gn:feature_code":"PPLL",
    "gn:name":"Plavsi\u0107i",
    "gn:population":0,
    "gn:timezone":"Europe/Sarajevo",
    "iso:country":"BA",
    "wof:name":"Plavsici",
    "wof:placetype":"locality"
},
  "geometry": {"coordinates":[17.07662,44.69834],"type":"Point"}
}