{
  "type": "Feature",
  "properties": {
    "gn:admin1_code":"02",
    "gn:asciiname":"Glozik",
    "gn:country_code":"BA",
    "gn:dem":103,
    "gn:feature_class":"P",
    "gn:feature_code":"PPL",
    "gn:name":"Glo\u017eik",
    "gn:population":0,
    "gn:timezone":"Europe/Sarajevo",
    "iso:country":"BA",
    "wof:name":"Glozik",
    "wof:placetype":"locality"
},
  "geometry": {"coordinates":[17.95011000000001,45.03659],"type":"Point"}
}