{
  "type": "Feature",
  "properties": {
    "gn:admin1_code":"01",
    "gn:asciiname":"Lijesce",
    "gn:country_code":"BA",
    "gn:dem":619,
    "gn:feature_class":"P",
    "gn:feature_code":"PPL",
    "gn:name":"Lije\u0161\u0107e",
    "gn:population":0,
    "gn:timezone":"Europe/Sarajevo",
    "iso:country":"BA",
    "wof:name":"Lijesce",
    "wof:placetype":"locality"
},
  "geometry": {"coordinates":[17.79417,43.7525],"type":"Point"}
}