{
  "type": "Feature",
  "properties": {
    "gn:admin1_code":"01",
    "gn:asciiname":"Visnjica",
    "gn:country_code":"BA",
    "gn:dem":532,
    "gn:feature_class":"P",
    "gn:feature_code":"PPL",
    "gn:name":"Vi\u0161njica",
    "gn:population":0,
    "gn:timezone":"Europe/Sarajevo",
    "iso:country":"BA",
    "name:bos_x_preferred":[
        "Vi\u0161njica"
    ],
    "name:ceb_x_preferred":[
        "Vi\u0161njica"
    ],
    "name:fra_x_preferred":[
        "Vi\u0161njica"
    ],
    "name:hrv_x_preferred":[
        "Vi\u0161njica"
    ],
    "name:swe_x_preferred":[
        "Vi\u0161njica"
    ],
    "wof:name":"Visnjica",
    "wof:placetype":"locality"
},
  "geometry": {"coordinates":[18.03862,43.94667000000001],"type":"Point"}
}