{
  "type": "Feature",
  "properties": {
    "gn:admin1_code":"01",
    "gn:asciiname":"Radici",
    "gn:country_code":"BA",
    "gn:dem":356,
    "gn:feature_class":"P",
    "gn:feature_code":"PPL",
    "gn:name":"Radi\u0107i",
    "gn:population":0,
    "gn:timezone":"Europe/Sarajevo",
    "iso:country":"BA",
    "name:deu_x_preferred":[
        "Radici"
    ],
    "name:ita_x_preferred":[
        "Radici"
    ],
    "wof:name":"Radici",
    "wof:placetype":"locality"
},
  "geometry": {"coordinates":[17.51588,43.31466],"type":"Point"}
}