{
  "type": "Feature",
  "properties": {
    "gn:admin1_code":"02",
    "gn:asciiname":"Berkovac",
    "gn:country_code":"BA",
    "gn:dem":99,
    "gn:feature_class":"P",
    "gn:feature_code":"PPL",
    "gn:name":"Berkovac",
    "gn:population":0,
    "gn:timezone":"Europe/Sarajevo",
    "iso:country":"BA",
    "name:ceb_x_preferred":[
        "Berkovac"
    ],
    "name:fas_x_preferred":[
        "\u0628\u0631\u06a9\u0648\u0648\u0627\u062a\u0633"
    ],
    "name:fra_x_preferred":[
        "Berkovac"
    ],
    "name:msa_x_preferred":[
        "Berkovac"
    ],
    "name:por_x_preferred":[
        "Berkovac"
    ],
    "name:slv_x_preferred":[
        "Berkovac"
    ],
    "name:srp_x_preferred":[
        "\u0411\u0435\u0440\u043a\u043e\u0432\u0430\u0446"
    ],
    "wof:name":"Berkovac",
    "wof:placetype":"locality"
},
  "geometry": {"coordinates":[17.75652000000001,45.08172],"type":"Point"}
}