{
  "type": "Feature",
  "properties": {
    "gn:admin1_code":"02",
    "gn:asciiname":"Berkovac",
    "gn:country_code":"BA",
    "gn:dem":99,
    "gn:feature_class":"P",
    "gn:feature_code":"PPL",
    "gn:name":"Berkovac",
    "gn:population":0,
    "gn:timezone":"Europe/Sarajevo",
    "iso:country":"BA",
    "wof:name":"Berkovac",
    "wof:placetype":"locality"
},
  "geometry": {"coordinates":[17.75652000000001,45.08172],"type":"Point"}
}