{
  "type": "Feature",
  "properties": {
    "gn:admin1_code":"02",
    "gn:asciiname":"Ribari",
    "gn:country_code":"BA",
    "gn:dem":425,
    "gn:feature_class":"P",
    "gn:feature_code":"PPL",
    "gn:name":"Ribari",
    "gn:population":0,
    "gn:timezone":"Europe/Sarajevo",
    "iso:country":"BA",
    "name:bos_x_preferred":[
        "Ribari"
    ],
    "name:fra_x_preferred":[
        "Ribari"
    ],
    "name:hrv_x_preferred":[
        "Ribari"
    ],
    "name:hun_x_preferred":[
        "Ribari"
    ],
    "name:nld_x_preferred":[
        "Ribari"
    ],
    "name:slv_x_preferred":[
        "Ribari"
    ],
    "name:srp_x_preferred":[
        "\u0420\u0438\u0431\u0430\u0440\u0438"
    ],
    "wof:name":"Ribari",
    "wof:placetype":"locality"
},
  "geometry": {"coordinates":[18.81214,43.56387],"type":"Point"}
}