{
  "type": "Feature",
  "properties": {
    "gn:admin1_code":"02",
    "gn:asciiname":"Kamare",
    "gn:country_code":"BA",
    "gn:dem":229,
    "gn:feature_class":"P",
    "gn:feature_code":"PPL",
    "gn:name":"Kamare",
    "gn:population":0,
    "gn:timezone":"Europe/Sarajevo",
    "iso:country":"BA",
    "name:ceb_x_preferred":[
        "Kamare"
    ],
    "name:swe_x_preferred":[
        "Kamare"
    ],
    "wof:name":"Kamare",
    "wof:placetype":"locality"
},
  "geometry": {"coordinates":[17.57269,44.84551],"type":"Point"}
}