{
  "type": "Feature",
  "properties": {
    "gn:admin1_code":"01",
    "gn:asciiname":"Bradve",
    "gn:country_code":"BA",
    "gn:dem":433,
    "gn:feature_class":"P",
    "gn:feature_code":"PPL",
    "gn:name":"Bradve",
    "gn:population":0,
    "gn:timezone":"Europe/Sarajevo",
    "iso:country":"BA",
    "wof:name":"Bradve",
    "wof:placetype":"locality"
},
  "geometry": {"coordinates":[18.12297,44.02428],"type":"Point"}
}