{
  "type": "Feature",
  "properties": {
    "gn:admin1_code":"01",
    "gn:asciiname":"Smricani",
    "gn:country_code":"BA",
    "gn:dem":744,
    "gn:feature_class":"P",
    "gn:feature_code":"PPLL",
    "gn:name":"Smri\u010dani",
    "gn:population":0,
    "gn:timezone":"Europe/Sarajevo",
    "iso:country":"BA",
    "name:bos_x_preferred":[
        "Smri\u010dani"
    ],
    "name:ceb_x_preferred":[
        "Smri\u010dani"
    ],
    "name:fra_x_preferred":[
        "Smri\u010dani"
    ],
    "name:hrv_x_preferred":[
        "Smri\u010dani"
    ],
    "name:swe_x_preferred":[
        "Smri\u010dani"
    ],
    "name:und_x_variant":[
        "Smri\u010dani"
    ],
    "wof:name":"Smricani",
    "wof:placetype":"locality"
},
  "geometry": {"coordinates":[17.00814,43.77055],"type":"Point"}
}