{
  "type": "Feature",
  "properties": {
    "gn:admin1_code":"01",
    "gn:asciiname":"Stanovi",
    "gn:country_code":"BA",
    "gn:dem":727,
    "gn:feature_class":"P",
    "gn:feature_code":"PPL",
    "gn:name":"Stanovi",
    "gn:population":0,
    "gn:timezone":"Europe/Sarajevo",
    "iso:country":"BA",
    "name:bos_x_preferred":[
        "Stanovi"
    ],
    "name:ceb_x_preferred":[
        "Stanovi"
    ],
    "name:fra_x_preferred":[
        "Stanovi"
    ],
    "name:hrv_x_preferred":[
        "Stanovi"
    ],
    "name:swe_x_preferred":[
        "Stanovi"
    ],
    "wof:name":"Stanovi",
    "wof:placetype":"locality"
},
  "geometry": {"coordinates":[16.65972,44.52556],"type":"Point"}
}