{
  "type": "Feature",
  "properties": {
    "gn:admin1_code":"02",
    "gn:asciiname":"Durkovine",
    "gn:country_code":"BA",
    "gn:dem":717,
    "gn:feature_class":"P",
    "gn:feature_code":"PPL",
    "gn:name":"\u00d0urkovine",
    "gn:population":0,
    "gn:timezone":"Europe/Sarajevo",
    "iso:country":"BA",
    "wof:name":"Durkovine",
    "wof:placetype":"locality"
},
  "geometry": {"coordinates":[18.84336,43.50668],"type":"Point"}
}