{
  "type": "Feature",
  "properties": {
    "gn:admin1_code":"02",
    "gn:asciiname":"Lukovice",
    "gn:country_code":"BA",
    "gn:dem":991,
    "gn:feature_class":"P",
    "gn:feature_code":"PPL",
    "gn:name":"Lukovice",
    "gn:population":0,
    "gn:timezone":"Europe/Sarajevo",
    "iso:country":"BA",
    "name:bos_x_preferred":[
        "Lukovice"
    ],
    "name:ceb_x_preferred":[
        "Lukovice"
    ],
    "name:fra_x_preferred":[
        "Lukovice"
    ],
    "name:srp_x_preferred":[
        "\u041b\u0443\u043a\u043e\u0432\u0438\u0446\u0435"
    ],
    "name:swe_x_preferred":[
        "Lukovice"
    ],
    "wof:name":"Lukovice",
    "wof:placetype":"locality"
},
  "geometry": {"coordinates":[18.4425,43.19222],"type":"Point"}
}