{
  "type": "Feature",
  "properties": {
    "gn:admin1_code":"02",
    "gn:asciiname":"Lukovice",
    "gn:country_code":"BA",
    "gn:dem":991,
    "gn:feature_class":"P",
    "gn:feature_code":"PPL",
    "gn:name":"Lukovice",
    "gn:population":0,
    "gn:timezone":"Europe/Sarajevo",
    "iso:country":"BA",
    "wof:name":"Lukovice",
    "wof:placetype":"locality"
},
  "geometry": {"coordinates":[18.4425,43.19222],"type":"Point"}
}