{
  "type": "Feature",
  "properties": {
    "gn:admin1_code":"02",
    "gn:asciiname":"Donji Baranci",
    "gn:country_code":"BA",
    "gn:dem":721,
    "gn:feature_class":"P",
    "gn:feature_code":"PPL",
    "gn:name":"Donji Baranci",
    "gn:population":0,
    "gn:timezone":"Europe/Sarajevo",
    "iso:country":"BA",
    "wof:name":"Donji Baranci",
    "wof:placetype":"locality"
},
  "geometry": {"coordinates":[19.37139,43.81111],"type":"Point"}
}