{
  "type": "Feature",
  "properties": {
    "gn:admin1_code":"01",
    "gn:asciiname":"Govedovici",
    "gn:country_code":"BA",
    "gn:dem":637,
    "gn:feature_class":"P",
    "gn:feature_code":"PPL",
    "gn:name":"Govedovi\u0107i",
    "gn:population":0,
    "gn:timezone":"Europe/Sarajevo",
    "iso:country":"BA",
    "name:bos_x_preferred":[
        "Govedovi\u0107i"
    ],
    "name:fra_x_preferred":[
        "Govedovi\u0107i"
    ],
    "name:hrv_x_preferred":[
        "Govedovi\u0107i"
    ],
    "name:srp_x_preferred":[
        "\u0413\u043e\u0432\u0435\u0434\u043e\u0432\u0438\u045b\u0438"
    ],
    "wof:name":"Govedovici",
    "wof:placetype":"locality"
},
  "geometry": {"coordinates":[18.15836,44.13052],"type":"Point"}
}