{
  "type": "Feature",
  "properties": {
    "gn:admin1_code":"02",
    "gn:asciiname":"Gojkovici",
    "gn:country_code":"BA",
    "gn:dem":198,
    "gn:feature_class":"P",
    "gn:feature_code":"PPL",
    "gn:name":"Gojkovi\u0107i",
    "gn:population":0,
    "gn:timezone":"Europe/Sarajevo",
    "iso:country":"BA",
    "wof:name":"Gojkovici",
    "wof:placetype":"locality"
},
  "geometry": {"coordinates":[17.04658,45.12279],"type":"Point"}
}