{
  "type": "Feature",
  "properties": {
    "gn:admin1_code":"01",
    "gn:asciiname":"Usanovici",
    "gn:country_code":"BA",
    "gn:dem":378,
    "gn:feature_class":"P",
    "gn:feature_code":"PPL",
    "gn:name":"Usanovi\u0107i",
    "gn:population":0,
    "gn:timezone":"Europe/Sarajevo",
    "iso:country":"BA",
    "wof:name":"Usanovici",
    "wof:placetype":"locality"
},
  "geometry": {"coordinates":[18.15794,44.38909],"type":"Point"}
}