{
  "type": "Feature",
  "properties": {
    "gn:admin1_code":"02",
    "gn:asciiname":"Draguljevici",
    "gn:country_code":"BA",
    "gn:dem":853,
    "gn:feature_class":"P",
    "gn:feature_code":"PPL",
    "gn:name":"Draguljevi\u0107i",
    "gn:population":0,
    "gn:timezone":"Europe/Sarajevo",
    "iso:country":"BA",
    "wof:name":"Draguljevici",
    "wof:placetype":"locality"
},
  "geometry": {"coordinates":[18.88625,43.81069],"type":"Point"}
}