{
  "type": "Feature",
  "properties": {
    "gn:admin1_code":"01",
    "gn:asciiname":"Bistricak",
    "gn:country_code":"BA",
    "gn:dem":426,
    "gn:feature_class":"P",
    "gn:feature_code":"PPL",
    "gn:name":"Bistri\u010dak",
    "gn:population":0,
    "gn:timezone":"Europe/Sarajevo",
    "iso:country":"BA",
    "wof:name":"Bistricak",
    "wof:placetype":"locality"
},
  "geometry": {"coordinates":[17.86397000000001,44.35448],"type":"Point"}
}