{
  "type": "Feature",
  "properties": {
    "gn:admin1_code":"01",
    "gn:asciiname":"Podjezero",
    "gn:country_code":"BA",
    "gn:dem":430,
    "gn:feature_class":"P",
    "gn:feature_code":"PPL",
    "gn:name":"Podjezero",
    "gn:population":0,
    "gn:timezone":"Europe/Sarajevo",
    "iso:country":"BA",
    "wof:name":"Podjezero",
    "wof:placetype":"locality"
},
  "geometry": {"coordinates":[17.8291,44.42363],"type":"Point"}
}