{
  "type": "Feature",
  "properties": {
    "gn:admin1_code":"02",
    "gn:asciiname":"Pribeljci",
    "gn:country_code":"BA",
    "gn:dem":927,
    "gn:feature_class":"P",
    "gn:feature_code":"PPLL",
    "gn:name":"Pribeljci",
    "gn:population":0,
    "gn:timezone":"Europe/Sarajevo",
    "iso:country":"BA",
    "wof:name":"Pribeljci",
    "wof:placetype":"locality"
},
  "geometry": {"coordinates":[17.2153,44.14301],"type":"Point"}
}