{
  "type": "Feature",
  "properties": {
    "gn:admin1_code":"02",
    "gn:asciiname":"Panici",
    "gn:country_code":"BA",
    "gn:dem":211,
    "gn:feature_class":"P",
    "gn:feature_code":"PPL",
    "gn:name":"Pani\u0107i",
    "gn:population":0,
    "gn:timezone":"Europe/Sarajevo",
    "iso:country":"BA",
    "wof:name":"Panici",
    "wof:placetype":"locality"
},
  "geometry": {"coordinates":[16.42546,44.89291],"type":"Point"}
}