{
  "type": "Feature",
  "properties": {
    "gn:admin1_code":"01",
    "gn:asciiname":"Mikici",
    "gn:country_code":"BA",
    "gn:dem":573,
    "gn:feature_class":"P",
    "gn:feature_code":"PPL",
    "gn:name":"Miki\u0107i",
    "gn:population":0,
    "gn:timezone":"Europe/Sarajevo",
    "iso:country":"BA",
    "wof:name":"Mikici",
    "wof:placetype":"locality"
},
  "geometry": {"coordinates":[16.22865,44.36007],"type":"Point"}
}