{
  "type": "Feature",
  "properties": {
    "gn:admin1_code":"02",
    "gn:asciiname":"Medni Do",
    "gn:country_code":"BA",
    "gn:dem":896,
    "gn:feature_class":"P",
    "gn:feature_code":"PPL",
    "gn:name":"Medni Do",
    "gn:population":0,
    "gn:timezone":"Europe/Sarajevo",
    "iso:country":"BA",
    "name:und_x_variant":[
        "Osoje",
        "Medni Do"
    ],
    "wof:name":"Medni Do",
    "wof:placetype":"locality"
},
  "geometry": {"coordinates":[18.69248,43.45211],"type":"Point"}
}