{
  "type": "Feature",
  "properties": {
    "gn:admin1_code":"01",
    "gn:asciiname":"Pelivan",
    "gn:country_code":"BA",
    "gn:dem":708,
    "gn:feature_class":"P",
    "gn:feature_code":"PPL",
    "gn:name":"Pelivan",
    "gn:population":0,
    "gn:timezone":"Europe/Sarajevo",
    "iso:country":"BA",
    "name:ita_x_preferred":[
        "Pelivan"
    ],
    "name:ron_x_preferred":[
        "Comuna Pelivan"
    ],
    "wof:name":"Pelivan",
    "wof:placetype":"locality"
},
  "geometry": {"coordinates":[16.84528,43.79833],"type":"Point"}
}