{
  "type": "Feature",
  "properties": {
    "gn:admin1_code":"01",
    "gn:asciiname":"Bucevaca",
    "gn:country_code":"BA",
    "gn:dem":1209,
    "gn:feature_class":"P",
    "gn:feature_code":"PPL",
    "gn:name":"Bu\u0107eva\u010da",
    "gn:population":0,
    "gn:timezone":"Europe/Sarajevo",
    "iso:country":"BA",
    "wof:name":"Bucevaca",
    "wof:placetype":"locality"
},
  "geometry": {"coordinates":[17.40521,43.89162],"type":"Point"}
}