{
  "type": "Feature",
  "properties": {
    "gn:admin1_code":"02",
    "gn:asciiname":"Mirnici",
    "gn:country_code":"BA",
    "gn:dem":329,
    "gn:feature_class":"P",
    "gn:feature_code":"PPL",
    "gn:name":"Mirni\u0107i",
    "gn:population":0,
    "gn:timezone":"Europe/Sarajevo",
    "iso:country":"BA",
    "wof:name":"Mirnici",
    "wof:placetype":"locality"
},
  "geometry": {"coordinates":[17.04294,44.77453],"type":"Point"}
}