{
  "type": "Feature",
  "properties": {
    "gn:admin1_code":"02",
    "gn:asciiname":"Iskovac",
    "gn:country_code":"BA",
    "gn:dem":168,
    "gn:feature_class":"P",
    "gn:feature_code":"PPL",
    "gn:name":"I\u0161kovac",
    "gn:population":0,
    "gn:timezone":"Europe/Sarajevo",
    "iso:country":"BA",
    "wof:name":"Iskovac",
    "wof:placetype":"locality"
},
  "geometry": {"coordinates":[16.63591,45.17634],"type":"Point"}
}