{
  "type": "Feature",
  "properties": {
    "gn:admin1_code":"02",
    "gn:asciiname":"Kendric",
    "gn:country_code":"BA",
    "gn:dem":654,
    "gn:feature_class":"P",
    "gn:feature_code":"PPL",
    "gn:name":"Kendri\u0107",
    "gn:population":0,
    "gn:timezone":"Europe/Sarajevo",
    "iso:country":"BA",
    "wof:name":"Kendric",
    "wof:placetype":"locality"
},
  "geometry": {"coordinates":[17.13808,44.20549000000001],"type":"Point"}
}