{
  "type": "Feature",
  "properties": {
    "gn:admin1_code":"02",
    "gn:asciiname":"Dracevo",
    "gn:country_code":"BA",
    "gn:dem":273,
    "gn:feature_class":"P",
    "gn:feature_code":"PPL",
    "gn:name":"Dra\u010devo",
    "gn:population":0,
    "gn:timezone":"Europe/Sarajevo",
    "iso:country":"BA",
    "name:und_x_variant":[
        "Dra\u010devo"
    ],
    "wof:name":"Dracevo",
    "wof:placetype":"locality"
},
  "geometry": {"coordinates":[18.06677,42.85775],"type":"Point"}
}