{
  "type": "Feature",
  "properties": {
    "gn:admin1_code":"01",
    "gn:asciiname":"Glavicno",
    "gn:country_code":"BA",
    "gn:dem":663,
    "gn:feature_class":"P",
    "gn:feature_code":"PPL",
    "gn:name":"Glavi\u010dno",
    "gn:population":0,
    "gn:timezone":"Europe/Sarajevo",
    "iso:country":"BA",
    "name:und_x_variant":[
        "Glavi\u010dina",
        "Glavi\u010dno"
    ],
    "wof:name":"Glavicno",
    "wof:placetype":"locality"
},
  "geometry": {"coordinates":[18.53305,44.17652],"type":"Point"}
}