{
  "type": "Feature",
  "properties": {
    "gn:admin1_code":"02",
    "gn:asciiname":"Canici",
    "gn:country_code":"BA",
    "gn:dem":639,
    "gn:feature_class":"P",
    "gn:feature_code":"PPL",
    "gn:name":"\u010cani\u0107i",
    "gn:population":0,
    "gn:timezone":"Europe/Sarajevo",
    "iso:country":"BA",
    "wof:name":"Canici",
    "wof:placetype":"locality"
},
  "geometry": {"coordinates":[18.83858,44.31657],"type":"Point"}
}