{
  "type": "Feature",
  "properties": {
    "gn:admin1_code":"01",
    "gn:asciiname":"Ponor",
    "gn:country_code":"BA",
    "gn:dem":1205,
    "gn:feature_class":"P",
    "gn:feature_code":"PPL",
    "gn:name":"Ponor",
    "gn:population":0,
    "gn:timezone":"Europe/Sarajevo",
    "iso:country":"BA",
    "wof:name":"Ponor",
    "wof:placetype":"locality"
},
  "geometry": {"coordinates":[17.563,43.67336],"type":"Point"}
}