{
  "type": "Feature",
  "properties": {
    "gn:admin1_code":"01",
    "gn:asciiname":"Jasenica",
    "gn:country_code":"BA",
    "gn:dem":423,
    "gn:feature_class":"P",
    "gn:feature_code":"PPLL",
    "gn:name":"Jasenica",
    "gn:population":0,
    "gn:timezone":"Europe/Sarajevo",
    "iso:country":"BA",
    "name:bos_x_preferred":[
        "Jasenica"
    ],
    "name:fra_x_preferred":[
        "Jasenica"
    ],
    "name:hrv_x_preferred":[
        "Jasenica"
    ],
    "name:srp_x_preferred":[
        "\u0408\u0430\u0441\u0435\u043d\u0438\u0446\u0430"
    ],
    "name:swe_x_preferred":[
        "Jasenica"
    ],
    "name:urd_x_preferred":[
        "\u062c\u0633\u0646\u06cc\u06a9\u0627"
    ],
    "wof:name":"Jasenica",
    "wof:placetype":"locality"
},
  "geometry": {"coordinates":[18.34401,44.84382],"type":"Point"}
}