{
  "type": "Feature",
  "properties": {
    "gn:admin1_code":"02",
    "gn:asciiname":"Korduni",
    "gn:country_code":"BA",
    "gn:dem":264,
    "gn:feature_class":"P",
    "gn:feature_code":"PPL",
    "gn:name":"Korduni",
    "gn:population":0,
    "gn:timezone":"Europe/Sarajevo",
    "iso:country":"BA",
    "wof:name":"Korduni",
    "wof:placetype":"locality"
},
  "geometry": {"coordinates":[19.05995,44.39609],"type":"Point"}
}