{
  "type": "Feature",
  "properties": {
    "gn:admin1_code":"01",
    "gn:asciiname":"Miskica Brdo",
    "gn:country_code":"BA",
    "gn:dem":679,
    "gn:feature_class":"P",
    "gn:feature_code":"PPL",
    "gn:name":"Mi\u0161ki\u0107a Brdo",
    "gn:population":0,
    "gn:timezone":"Europe/Sarajevo",
    "iso:country":"BA",
    "wof:name":"Miskica Brdo",
    "wof:placetype":"locality"
},
  "geometry": {"coordinates":[17.61579,44.22861],"type":"Point"}
}