{
  "type": "Feature",
  "properties": {
    "gn:admin1_code":"01",
    "gn:asciiname":"Begovici",
    "gn:country_code":"BA",
    "gn:dem":171,
    "gn:feature_class":"P",
    "gn:feature_code":"PPL",
    "gn:name":"Begovi\u0107i",
    "gn:population":0,
    "gn:timezone":"Europe/Sarajevo",
    "iso:country":"BA",
    "wof:name":"Begovici",
    "wof:placetype":"locality"
},
  "geometry": {"coordinates":[15.83972,45.14833],"type":"Point"}
}