{
  "type": "Feature",
  "properties": {
    "gn:admin1_code":"02",
    "gn:asciiname":"Ljuboje",
    "gn:country_code":"BA",
    "gn:dem":161,
    "gn:feature_class":"P",
    "gn:feature_code":"PPL",
    "gn:name":"Ljuboje",
    "gn:population":0,
    "gn:timezone":"Europe/Sarajevo",
    "iso:country":"BA",
    "wof:name":"Ljuboje",
    "wof:placetype":"locality"
},
  "geometry": {"coordinates":[16.67244,44.84974],"type":"Point"}
}