{
  "type": "Feature",
  "properties": {
    "gn:admin1_code":"01",
    "gn:asciiname":"Licani",
    "gn:country_code":"BA",
    "gn:dem":351,
    "gn:feature_class":"P",
    "gn:feature_code":"PPL",
    "gn:name":"Li\u010dani",
    "gn:population":0,
    "gn:timezone":"Europe/Sarajevo",
    "iso:country":"BA",
    "wof:name":"Licani",
    "wof:placetype":"locality"
},
  "geometry": {"coordinates":[16.13188,45.04012],"type":"Point"}
}