{
  "type": "Feature",
  "properties": {
    "gn:admin1_code":"01",
    "gn:asciiname":"Priluk",
    "gn:country_code":"BA",
    "gn:dem":223,
    "gn:feature_class":"P",
    "gn:feature_code":"PPLL",
    "gn:name":"Priluk",
    "gn:population":0,
    "gn:timezone":"Europe/Sarajevo",
    "iso:country":"BA",
    "wof:name":"Priluk",
    "wof:placetype":"locality"
},
  "geometry": {"coordinates":[18.53693,44.47055],"type":"Point"}
}