{
  "type": "Feature",
  "properties": {
    "gn:admin1_code":"02",
    "gn:asciiname":"Prgomet",
    "gn:country_code":"BA",
    "gn:dem":143,
    "gn:feature_class":"P",
    "gn:feature_code":"PPL",
    "gn:name":"Prgomet",
    "gn:population":0,
    "gn:timezone":"Europe/Sarajevo",
    "iso:country":"BA",
    "name:bos_x_preferred":[
        "Prgomet"
    ],
    "name:cat_x_preferred":[
        "Prgomet"
    ],
    "name:fra_x_preferred":[
        "Prgomet"
    ],
    "name:hrv_x_preferred":[
        "Prgomet"
    ],
    "name:hun_x_preferred":[
        "Prgomet"
    ],
    "name:ita_x_preferred":[
        "Prgomet"
    ],
    "name:nld_x_preferred":[
        "Prgomet"
    ],
    "name:pol_x_preferred":[
        "Gmina Prgomet"
    ],
    "name:ron_x_preferred":[
        "Comuna Prgomet"
    ],
    "name:slk_x_preferred":[
        "Prgomet"
    ],
    "name:slv_x_preferred":[
        "Prgomet"
    ],
    "name:srp_x_preferred":[
        "\u041f\u0440\u0433\u043e\u043c\u0435\u0442"
    ],
    "name:ukr_x_preferred":[
        "\u041f\u0440\u0433\u043e\u043c\u0435\u0442"
    ],
    "name:war_x_preferred":[
        "Prgomet"
    ],
    "wof:name":"Prgomet",
    "wof:placetype":"locality"
},
  "geometry": {"coordinates":[17.882,44.94028],"type":"Point"}
}