{
  "type": "Feature",
  "properties": {
    "gn:admin1_code":"02",
    "gn:asciiname":"Jurkici",
    "gn:country_code":"BA",
    "gn:dem":422,
    "gn:feature_class":"P",
    "gn:feature_code":"PPL",
    "gn:name":"Jurki\u0107i",
    "gn:population":0,
    "gn:timezone":"Europe/Sarajevo",
    "iso:country":"BA",
    "wof:name":"Jurkici",
    "wof:placetype":"locality"
},
  "geometry": {"coordinates":[17.1521,44.9369],"type":"Point"}
}