{
  "type": "Feature",
  "properties": {
    "gn:admin1_code":"02",
    "gn:asciiname":"Peulici",
    "gn:country_code":"BA",
    "gn:dem":264,
    "gn:feature_class":"P",
    "gn:feature_code":"PPL",
    "gn:name":"Peuli\u0107i",
    "gn:population":0,
    "gn:timezone":"Europe/Sarajevo",
    "iso:country":"BA",
    "wof:name":"Peulici",
    "wof:placetype":"locality"
},
  "geometry": {"coordinates":[17.6476,44.75458],"type":"Point"}
}