{
  "type": "Feature",
  "properties": {
    "gn:admin1_code":"02",
    "gn:asciiname":"Manojlovici",
    "gn:country_code":"BA",
    "gn:dem":413,
    "gn:feature_class":"P",
    "gn:feature_code":"PPL",
    "gn:name":"Manojlovi\u0107i",
    "gn:population":0,
    "gn:timezone":"Europe/Sarajevo",
    "iso:country":"BA",
    "wof:name":"Manojlovici",
    "wof:placetype":"locality"
},
  "geometry": {"coordinates":[19.0582,44.57736],"type":"Point"}
}