{
  "type": "Feature",
  "properties": {
    "gn:admin1_code":"01",
    "gn:asciiname":"Jaksici",
    "gn:country_code":"BA",
    "gn:dem":859,
    "gn:feature_class":"P",
    "gn:feature_code":"PPL",
    "gn:name":"Jak\u0161i\u0107i",
    "gn:population":0,
    "gn:timezone":"Europe/Sarajevo",
    "iso:country":"BA",
    "wof:name":"Jaksici",
    "wof:placetype":"locality"
},
  "geometry": {"coordinates":[16.53514,44.55599],"type":"Point"}
}