{
  "type": "Feature",
  "properties": {
    "gn:admin1_code":"02",
    "gn:asciiname":"Babaja",
    "gn:country_code":"BA",
    "gn:dem":274,
    "gn:feature_class":"P",
    "gn:feature_code":"PPL",
    "gn:name":"Babaja",
    "gn:population":0,
    "gn:timezone":"Europe/Sarajevo",
    "iso:country":"BA",
    "wof:name":"Babaja",
    "wof:placetype":"locality"
},
  "geometry": {"coordinates":[17.59432,44.84325],"type":"Point"}
}