{
  "type": "Feature",
  "properties": {
    "gn:admin1_code":"01",
    "gn:asciiname":"Curcici",
    "gn:country_code":"BA",
    "gn:dem":961,
    "gn:feature_class":"P",
    "gn:feature_code":"PPL",
    "gn:name":"Cur\u010di\u0107i",
    "gn:population":0,
    "gn:timezone":"Europe/Sarajevo",
    "iso:country":"BA",
    "wof:name":"Curcici",
    "wof:placetype":"locality"
},
  "geometry": {"coordinates":[17.20356,43.63357],"type":"Point"}
}