{
  "type": "Feature",
  "properties": {
    "gn:admin1_code":"01",
    "gn:asciiname":"Gornji Moranjci",
    "gn:country_code":"BA",
    "gn:dem":312,
    "gn:feature_class":"P",
    "gn:feature_code":"PPL",
    "gn:name":"Gornji Moranjci",
    "gn:population":0,
    "gn:timezone":"Europe/Sarajevo",
    "iso:country":"BA",
    "name:bos_x_preferred":[
        "Gornji Moranjci"
    ],
    "name:ceb_x_preferred":[
        "Gornji Moranjci"
    ],
    "name:fra_x_preferred":[
        "Gornji Moranjci"
    ],
    "name:hrv_x_preferred":[
        "Gornji Moranjci"
    ],
    "name:swe_x_preferred":[
        "Gornji Moranjci"
    ],
    "name:und_x_variant":[
        "Moranjci Gornji",
        "Gornji Moranjci"
    ],
    "wof:name":"Gornji Moranjci",
    "wof:placetype":"locality"
},
  "geometry": {"coordinates":[18.43126,44.67982],"type":"Point"}
}