{
  "type": "Feature",
  "properties": {
    "gn:admin1_code":"02",
    "gn:asciiname":"Tokovici",
    "gn:country_code":"BA",
    "gn:dem":1022,
    "gn:feature_class":"P",
    "gn:feature_code":"PPL",
    "gn:name":"Tokovi\u0107i",
    "gn:population":0,
    "gn:timezone":"Europe/Sarajevo",
    "iso:country":"BA",
    "wof:name":"Tokovici",
    "wof:placetype":"locality"
},
  "geometry": {"coordinates":[19.18041,43.60851],"type":"Point"}
}