{
  "type": "Feature",
  "properties": {
    "gn:admin1_code":"02",
    "gn:asciiname":"Duzi",
    "gn:country_code":"BA",
    "gn:dem":280,
    "gn:feature_class":"P",
    "gn:feature_code":"PPL",
    "gn:name":"Du\u017ei",
    "gn:population":0,
    "gn:timezone":"Europe/Sarajevo",
    "iso:country":"BA",
    "name:und_x_variant":[
        "Du\u017ei"
    ],
    "wof:name":"Duzi",
    "wof:placetype":"locality"
},
  "geometry": {"coordinates":[18.26546,42.70246],"type":"Point"}
}