{
  "type": "Feature",
  "properties": {
    "gn:admin1_code":"01",
    "gn:asciiname":"Ratanj",
    "gn:country_code":"BA",
    "gn:dem":788,
    "gn:feature_class":"P",
    "gn:feature_code":"PPL",
    "gn:name":"Ratanj",
    "gn:population":0,
    "gn:timezone":"Europe/Sarajevo",
    "iso:country":"BA",
    "name:bos_x_preferred":[
        "Ratanj"
    ],
    "name:fra_x_preferred":[
        "Ratanj"
    ],
    "name:hrv_x_preferred":[
        "Ratanj"
    ],
    "name:srp_x_preferred":[
        "\u0420\u0430\u0442\u0430\u045a"
    ],
    "name:und_x_variant":[
        "Rtanj",
        "Ratanj"
    ],
    "wof:name":"Ratanj",
    "wof:placetype":"locality"
},
  "geometry": {"coordinates":[18.21801,44.14453],"type":"Point"}
}