{
  "type": "Feature",
  "properties": {
    "gn:country":"BA",
    "gn:fcode":"PPL",
    "gn:population":4787,
    "iso:country":"BA",
    "name:bos_x_preferred":[
        "Pazari\u0107"
    ],
    "name:ceb_x_preferred":[
        "Pazari\u0107"
    ],
    "name:eng_x_preferred":[
        "Pazari\u0107"
    ],
    "name:fra_x_preferred":[
        "Pazari\u0107"
    ],
    "name:hrv_x_preferred":[
        "Pazari\u0107"
    ],
    "name:nld_x_preferred":[
        "Pazari\u0107"
    ],
    "name:swe_x_preferred":[
        "Pazari\u0107"
    ],
    "qs:name":"Pazari\u0107",
    "qs:name_adm0":"Bosna i Hercegovina",
    "qs:name_adm1":"Federacija Bosne I Hercegovine",
    "qs:photos_9k":1,
    "qs:photos_9r":1,
    "qs:photos_all":1,
    "qs:photos_sr":0,
    "qs:placetype":"Town",
    "qs:pop_sr":"4",
    "wd:wordcount":57,
    "wof:name":"Pazari\u0107",
    "wof:placetype":"locality",
    "wof:population":4787
},
  "geometry": {"coordinates":[18.16049,43.78882],"type":"Point"}
}