{
  "type": "Feature",
  "properties": {
    "gn:admin1_code":"02",
    "gn:asciiname":"Pranjkovac",
    "gn:country_code":"BA",
    "gn:dem":222,
    "gn:feature_class":"P",
    "gn:feature_code":"PPL",
    "gn:name":"Pranjkovac",
    "gn:population":0,
    "gn:timezone":"Europe/Sarajevo",
    "iso:country":"BA",
    "wof:name":"Pranjkovac",
    "wof:placetype":"locality"
},
  "geometry": {"coordinates":[18.08859,44.78118],"type":"Point"}
}