{
  "type": "Feature",
  "properties": {
    "gn:admin1_code":"01",
    "gn:asciiname":"Paretak",
    "gn:country_code":"BA",
    "gn:dem":574,
    "gn:feature_class":"P",
    "gn:feature_code":"PPLL",
    "gn:name":"Paretak",
    "gn:population":0,
    "gn:timezone":"Europe/Sarajevo",
    "iso:country":"BA",
    "name:bos_x_preferred":[
        "Paretak"
    ],
    "name:ceb_x_preferred":[
        "Paretak"
    ],
    "name:fra_x_preferred":[
        "Paretak"
    ],
    "name:hrv_x_preferred":[
        "Paretak"
    ],
    "name:swe_x_preferred":[
        "Paretak"
    ],
    "wof:name":"Paretak",
    "wof:placetype":"locality"
},
  "geometry": {"coordinates":[18.1372,43.91991],"type":"Point"}
}