{
  "type": "Feature",
  "properties": {
    "gn:admin1_code":"02",
    "gn:asciiname":"Gradina",
    "gn:country_code":"BA",
    "gn:dem":1011,
    "gn:feature_class":"P",
    "gn:feature_code":"PPL",
    "gn:name":"Gradina",
    "gn:population":0,
    "gn:timezone":"Europe/Sarajevo",
    "iso:country":"BA",
    "wof:name":"Gradina",
    "wof:placetype":"locality"
},
  "geometry": {"coordinates":[18.41618,43.20513],"type":"Point"}
}