{
  "type": "Feature",
  "properties": {
    "gn:admin1_code":"01",
    "gn:asciiname":"Ducci",
    "gn:country_code":"BA",
    "gn:dem":1251,
    "gn:feature_class":"P",
    "gn:feature_code":"PPL",
    "gn:name":"Du\u0107ci",
    "gn:population":0,
    "gn:timezone":"Europe/Sarajevo",
    "iso:country":"BA",
    "wof:name":"Ducci",
    "wof:placetype":"locality"
},
  "geometry": {"coordinates":[17.14288,43.98717],"type":"Point"}
}