{
  "type": "Feature",
  "properties": {
    "gn:admin1_code":"02",
    "gn:asciiname":"Kizici",
    "gn:country_code":"BA",
    "gn:dem":803,
    "gn:feature_class":"P",
    "gn:feature_code":"PPL",
    "gn:name":"Kizi\u0107i",
    "gn:population":0,
    "gn:timezone":"Europe/Sarajevo",
    "iso:country":"BA",
    "wof:name":"Kizici",
    "wof:placetype":"locality"
},
  "geometry": {"coordinates":[17.00475,44.3171],"type":"Point"}
}