{
  "type": "Feature",
  "properties": {
    "gn:admin1_code":"02",
    "gn:asciiname":"Imljani",
    "gn:country_code":"BA",
    "gn:dem":1117,
    "gn:feature_class":"P",
    "gn:feature_code":"PPLL",
    "gn:name":"Imljani",
    "gn:population":0,
    "gn:timezone":"Europe/Sarajevo",
    "iso:country":"BA",
    "name:bos_x_preferred":[
        "Imljani"
    ],
    "name:ceb_x_preferred":[
        "Imljani"
    ],
    "name:fra_x_preferred":[
        "Imljani"
    ],
    "name:hrv_x_preferred":[
        "Imljani"
    ],
    "name:srp_x_preferred":[
        "\u0418\u043c\u0459\u0430\u043d\u0438"
    ],
    "name:swe_x_preferred":[
        "Imljani"
    ],
    "wof:name":"Imljani",
    "wof:placetype":"locality"
},
  "geometry": {"coordinates":[17.4761,44.40183],"type":"Point"}
}