{
  "type": "Feature",
  "properties": {
    "gn:admin1_code":"02",
    "gn:asciiname":"Kubas",
    "gn:country_code":"BA",
    "gn:dem":850,
    "gn:feature_class":"P",
    "gn:feature_code":"PPL",
    "gn:name":"Kuba\u0161",
    "gn:population":0,
    "gn:timezone":"Europe/Sarajevo",
    "iso:country":"BA",
    "wof:name":"Kubas",
    "wof:placetype":"locality"
},
  "geometry": {"coordinates":[18.15336,43.06008],"type":"Point"}
}