{
  "type": "Feature",
  "properties": {
    "gn:admin1_code":"01",
    "gn:asciiname":"Podjelinak",
    "gn:country_code":"BA",
    "gn:dem":664,
    "gn:feature_class":"P",
    "gn:feature_code":"PPL",
    "gn:name":"Podjelinak",
    "gn:population":0,
    "gn:timezone":"Europe/Sarajevo",
    "iso:country":"BA",
    "wof:name":"Podjelinak",
    "wof:placetype":"locality"
},
  "geometry": {"coordinates":[17.23918,43.53025],"type":"Point"}
}