{
  "type": "Feature",
  "properties": {
    "gn:admin1_code":"01",
    "gn:asciiname":"Papratno",
    "gn:country_code":"BA",
    "gn:dem":1101,
    "gn:feature_class":"P",
    "gn:feature_code":"PPL",
    "gn:name":"Papratno",
    "gn:population":0,
    "gn:timezone":"Europe/Sarajevo",
    "iso:country":"BA",
    "wof:name":"Papratno",
    "wof:placetype":"locality"
},
  "geometry": {"coordinates":[18.40509,44.18569],"type":"Point"}
}