{
  "type": "Feature",
  "properties": {
    "gn:admin1_code":"01",
    "gn:asciiname":"Milino Selo",
    "gn:country_code":"BA",
    "gn:dem":275,
    "gn:feature_class":"P",
    "gn:feature_code":"PPL",
    "gn:name":"Milino Selo",
    "gn:population":0,
    "gn:timezone":"Europe/Sarajevo",
    "iso:country":"BA",
    "name:bos_x_preferred":[
        "Milino Selo"
    ],
    "name:ceb_x_preferred":[
        "Milino Selo"
    ],
    "name:fra_x_preferred":[
        "Milino Selo"
    ],
    "name:hrv_x_preferred":[
        "Milino Selo"
    ],
    "name:swe_x_preferred":[
        "Milino Selo"
    ],
    "wof:name":"Milino Selo",
    "wof:placetype":"locality"
},
  "geometry": {"coordinates":[18.41674,44.53779],"type":"Point"}
}