{
  "type": "Feature",
  "properties": {
    "gn:admin1_code":"01",
    "gn:asciiname":"Bilica Docic",
    "gn:country_code":"BA",
    "gn:dem":649,
    "gn:feature_class":"P",
    "gn:feature_code":"PPL",
    "gn:name":"Bili\u0107a Do\u010di\u0107",
    "gn:population":0,
    "gn:timezone":"Europe/Sarajevo",
    "iso:country":"BA",
    "wof:name":"Bilica Docic",
    "wof:placetype":"locality"
},
  "geometry": {"coordinates":[17.63739,44.23719000000001],"type":"Point"}
}