{
  "type": "Feature",
  "properties": {
    "gn:admin1_code":"02",
    "gn:asciiname":"Skocigrm",
    "gn:country_code":"BA",
    "gn:dem":397,
    "gn:feature_class":"P",
    "gn:feature_code":"PPL",
    "gn:name":"Sko\u010digrm",
    "gn:population":0,
    "gn:timezone":"Europe/Sarajevo",
    "iso:country":"BA",
    "name:bos_x_preferred":[
        "Sko\u010digrm"
    ],
    "name:fra_x_preferred":[
        "Sko\u010digrm"
    ],
    "name:srp_x_preferred":[
        "\u0421\u043a\u043e\u0447\u0438\u0433\u0440\u043c"
    ],
    "name:und_x_variant":[
        "Sko\u010dgrm",
        "Sko\u010digrm"
    ],
    "wof:name":"Skocigrm",
    "wof:placetype":"locality"
},
  "geometry": {"coordinates":[18.52121,42.68554],"type":"Point"}
}