{
  "type": "Feature",
  "properties": {
    "gn:admin1_code":"01",
    "gn:asciiname":"Perci",
    "gn:country_code":"BA",
    "gn:dem":906,
    "gn:feature_class":"P",
    "gn:feature_code":"PPL",
    "gn:name":"Perci",
    "gn:population":0,
    "gn:timezone":"Europe/Sarajevo",
    "iso:country":"BA",
    "name:bos_x_preferred":[
        "Perci"
    ],
    "name:fra_x_preferred":[
        "Perci"
    ],
    "name:hrv_x_preferred":[
        "Perci"
    ],
    "name:hun_x_preferred":[
        "Perci"
    ],
    "name:nld_x_preferred":[
        "Perci"
    ],
    "name:slv_x_preferred":[
        "Perci"
    ],
    "name:srp_x_preferred":[
        "\u041f\u0435\u0440\u0446\u0438"
    ],
    "name:ukr_x_preferred":[
        "\u041f\u0435\u0440\u0446\u0456"
    ],
    "wof:name":"Perci",
    "wof:placetype":"locality"
},
  "geometry": {"coordinates":[17.47452,43.50467],"type":"Point"}
}