{
  "type": "Feature",
  "properties": {
    "gn:admin1_code":"01",
    "gn:asciiname":"Perci",
    "gn:country_code":"BA",
    "gn:dem":906,
    "gn:feature_class":"P",
    "gn:feature_code":"PPL",
    "gn:name":"Perci",
    "gn:population":0,
    "gn:timezone":"Europe/Sarajevo",
    "iso:country":"BA",
    "wof:name":"Perci",
    "wof:placetype":"locality"
},
  "geometry": {"coordinates":[17.47452,43.50467],"type":"Point"}
}