{
  "type": "Feature",
  "properties": {
    "gn:admin1_code":"02",
    "gn:asciiname":"Knezovi",
    "gn:country_code":"BA",
    "gn:dem":548,
    "gn:feature_class":"P",
    "gn:feature_code":"PPL",
    "gn:name":"Knezovi",
    "gn:population":0,
    "gn:timezone":"Europe/Sarajevo",
    "iso:country":"BA",
    "wof:name":"Knezovi",
    "wof:placetype":"locality"
},
  "geometry": {"coordinates":[17.26738,44.62531],"type":"Point"}
}