{
  "type": "Feature",
  "properties": {
    "gn:admin1_code":"02",
    "gn:asciiname":"Berkovina",
    "gn:country_code":"BA",
    "gn:dem":1048,
    "gn:feature_class":"P",
    "gn:feature_code":"PPL",
    "gn:name":"Berkovina",
    "gn:population":0,
    "gn:timezone":"Europe/Sarajevo",
    "iso:country":"BA",
    "name:bos_x_preferred":[
        "Berkovina"
    ],
    "name:fra_x_preferred":[
        "Berkovina"
    ],
    "name:srp_x_preferred":[
        "\u0411\u0435\u0440\u043a\u043e\u0432\u0438\u043d\u0430"
    ],
    "wof:name":"Berkovina",
    "wof:placetype":"locality"
},
  "geometry": {"coordinates":[18.86965,44.08865],"type":"Point"}
}