{
  "type": "Feature",
  "properties": {
    "gn:admin1_code":"02",
    "gn:asciiname":"Davidovici",
    "gn:country_code":"BA",
    "gn:dem":383,
    "gn:feature_class":"P",
    "gn:feature_code":"PPL",
    "gn:name":"Davidovi\u0107i",
    "gn:population":0,
    "gn:timezone":"Europe/Sarajevo",
    "iso:country":"BA",
    "wof:name":"Davidovici",
    "wof:placetype":"locality"
},
  "geometry": {"coordinates":[16.37187,44.83884000000001],"type":"Point"}
}