{
  "type": "Feature",
  "properties": {
    "gn:admin1_code":"02",
    "gn:asciiname":"Petici",
    "gn:country_code":"BA",
    "gn:dem":214,
    "gn:feature_class":"P",
    "gn:feature_code":"PPL",
    "gn:name":"Peti\u0107i",
    "gn:population":0,
    "gn:timezone":"Europe/Sarajevo",
    "iso:country":"BA",
    "wof:name":"Petici",
    "wof:placetype":"locality"
},
  "geometry": {"coordinates":[16.40611,45.06583],"type":"Point"}
}