{
  "type": "Feature",
  "properties": {
    "gn:admin1_code":"01",
    "gn:asciiname":"Okoliste",
    "gn:country_code":"BA",
    "gn:dem":1196,
    "gn:feature_class":"P",
    "gn:feature_code":"PPL",
    "gn:name":"Okoli\u0161te",
    "gn:population":0,
    "gn:timezone":"Europe/Sarajevo",
    "iso:country":"BA",
    "wof:name":"Okoliste",
    "wof:placetype":"locality"
},
  "geometry": {"coordinates":[18.26833,44.21444],"type":"Point"}
}