{
  "type": "Feature",
  "properties": {
    "gn:admin1_code":"01",
    "gn:asciiname":"Bugar",
    "gn:country_code":"BA",
    "gn:dem":354,
    "gn:feature_class":"P",
    "gn:feature_code":"PPLL",
    "gn:name":"Bugar",
    "gn:population":0,
    "gn:timezone":"Europe/Sarajevo",
    "iso:country":"BA",
    "wof:name":"Bugar",
    "wof:placetype":"locality"
},
  "geometry": {"coordinates":[15.76966,44.93999],"type":"Point"}
}