{
  "type": "Feature",
  "properties": {
    "gn:admin1_code":"01",
    "gn:asciiname":"Bugar",
    "gn:country_code":"BA",
    "gn:dem":354,
    "gn:feature_class":"P",
    "gn:feature_code":"PPLL",
    "gn:name":"Bugar",
    "gn:population":0,
    "gn:timezone":"Europe/Sarajevo",
    "iso:country":"BA",
    "name:ara_x_preferred":[
        "\u0628\u0648\u063a\u0627\u0631"
    ],
    "name:bos_x_preferred":[
        "Bugar"
    ],
    "name:deu_x_preferred":[
        "Bugar"
    ],
    "name:ell_x_preferred":[
        "\u039c\u03c0\u03bf\u03cd\u03b3\u03ba\u03b1\u03c1"
    ],
    "name:fra_x_preferred":[
        "Bugar"
    ],
    "name:hrv_x_preferred":[
        "Bugar"
    ],
    "name:slv_x_preferred":[
        "Bugar"
    ],
    "name:srp_x_preferred":[
        "\u0411\u0443\u0433\u0430\u0440"
    ],
    "wof:name":"Bugar",
    "wof:placetype":"locality"
},
  "geometry": {"coordinates":[15.76966,44.93999],"type":"Point"}
}