{
  "type": "Feature",
  "properties": {
    "gn:admin1_code":"02",
    "gn:asciiname":"Vakuf",
    "gn:country_code":"BA",
    "gn:dem":907,
    "gn:feature_class":"P",
    "gn:feature_code":"PPL",
    "gn:name":"Vakuf",
    "gn:population":0,
    "gn:timezone":"Europe/Sarajevo",
    "iso:country":"BA",
    "name:bos_x_preferred":[
        "Vakuf"
    ],
    "name:fra_x_preferred":[
        "Vakuf"
    ],
    "name:hrv_x_preferred":[
        "Vakuf"
    ],
    "name:srp_x_preferred":[
        "\u0412\u0430\u043a\u0443\u0444"
    ],
    "wof:name":"Vakuf",
    "wof:placetype":"locality"
},
  "geometry": {"coordinates":[18.93429,43.40664],"type":"Point"}
}