{
  "type": "Feature",
  "properties": {
    "gn:admin1_code":"02",
    "gn:asciiname":"Vrhovine",
    "gn:country_code":"BA",
    "gn:dem":1095,
    "gn:feature_class":"P",
    "gn:feature_code":"PPL",
    "gn:name":"Vrhovine",
    "gn:population":0,
    "gn:timezone":"Europe/Sarajevo",
    "iso:country":"BA",
    "name:bos_x_preferred":[
        "Vrhovina"
    ],
    "name:fra_x_preferred":[
        "Vrhovina"
    ],
    "name:srp_x_preferred":[
        "\u0412\u0440\u0445\u043e\u0432\u0438\u043d\u0430"
    ],
    "name:und_x_variant":[
        "Vrhovine"
    ],
    "wof:name":"Vrhovine",
    "wof:placetype":"locality"
},
  "geometry": {"coordinates":[18.5543,43.96965],"type":"Point"}
}