{
  "type": "Feature",
  "properties": {
    "gn:admin1_code":"02",
    "gn:asciiname":"Kulina",
    "gn:country_code":"BA",
    "gn:dem":630,
    "gn:feature_class":"P",
    "gn:feature_code":"PPL",
    "gn:name":"Kulina",
    "gn:population":0,
    "gn:timezone":"Europe/Sarajevo",
    "iso:country":"BA",
    "name:bos_x_preferred":[
        "Kulina"
    ],
    "name:ceb_x_preferred":[
        "Kulina"
    ],
    "name:deu_x_preferred":[
        "Kulina"
    ],
    "name:fra_x_preferred":[
        "Kulina"
    ],
    "name:hrv_x_preferred":[
        "Kulina"
    ],
    "name:nld_x_preferred":[
        "Kulina"
    ],
    "name:rus_x_preferred":[
        "\u041a\u0443\u043b\u0438\u043d\u0430"
    ],
    "name:slv_x_preferred":[
        "Kulina"
    ],
    "name:srp_x_preferred":[
        "\u041a\u0443\u043b\u0438\u043d\u0430"
    ],
    "name:swe_x_preferred":[
        "Kulina"
    ],
    "wof:name":"Kulina",
    "wof:placetype":"locality"
},
  "geometry": {"coordinates":[18.387,42.94133],"type":"Point"}
}