{
  "type": "Feature",
  "properties": {
    "gn:admin1_code":"02",
    "gn:asciiname":"Kulina",
    "gn:country_code":"BA",
    "gn:dem":630,
    "gn:feature_class":"P",
    "gn:feature_code":"PPL",
    "gn:name":"Kulina",
    "gn:population":0,
    "gn:timezone":"Europe/Sarajevo",
    "iso:country":"BA",
    "wof:name":"Kulina",
    "wof:placetype":"locality"
},
  "geometry": {"coordinates":[18.387,42.94133],"type":"Point"}
}