{
  "type": "Feature",
  "properties": {
    "gn:admin1_code":"01",
    "gn:asciiname":"Vuletici",
    "gn:country_code":"BA",
    "gn:dem":242,
    "gn:feature_class":"P",
    "gn:feature_code":"PPL",
    "gn:name":"Vuleti\u0107i",
    "gn:population":0,
    "gn:timezone":"Europe/Sarajevo",
    "iso:country":"BA",
    "wof:name":"Vuletici",
    "wof:placetype":"locality"
},
  "geometry": {"coordinates":[17.49064,43.26261],"type":"Point"}
}