{
  "type": "Feature",
  "properties": {
    "gn:admin1_code":"01",
    "gn:asciiname":"Repovica",
    "gn:country_code":"BA",
    "gn:dem":310,
    "gn:feature_class":"P",
    "gn:feature_code":"PPL",
    "gn:name":"Repovica",
    "gn:population":0,
    "gn:timezone":"Europe/Sarajevo",
    "iso:country":"BA",
    "wof:name":"Repovica",
    "wof:placetype":"locality"
},
  "geometry": {"coordinates":[17.96157999999999,43.65827],"type":"Point"}
}