{
  "type": "Feature",
  "properties": {
    "gn:admin1_code":"01",
    "gn:asciiname":"Jablanica",
    "gn:country_code":"BA",
    "gn:dem":245,
    "gn:feature_class":"P",
    "gn:feature_code":"PPLL",
    "gn:name":"Jablanica",
    "gn:population":0,
    "gn:timezone":"Europe/Sarajevo",
    "iso:country":"BA",
    "name:bos_x_preferred":[
        "Jablanica"
    ],
    "name:bul_x_preferred":[
        "\u042f\u0431\u043b\u0430\u043d\u0438\u0446\u0430"
    ],
    "name:ceb_x_preferred":[
        "Jablanica"
    ],
    "name:deu_x_preferred":[
        "Jablanica"
    ],
    "name:fra_x_preferred":[
        "Jablanica"
    ],
    "name:hrv_x_preferred":[
        "Jablanica"
    ],
    "name:ita_x_preferred":[
        "Jablanica"
    ],
    "name:jpn_x_preferred":[
        "\u30e4\u30d6\u30e9\u30cb\u30c4\u30a1"
    ],
    "name:kor_x_preferred":[
        "\uc57c\ube14\ub77c\ub2c8\ucc28"
    ],
    "name:mkd_x_preferred":[
        "\u0408\u0430\u0431\u043b\u0430\u043d\u0438\u0446\u0430"
    ],
    "name:nld_x_preferred":[
        "Jablanica"
    ],
    "name:pol_x_preferred":[
        "Jablanica"
    ],
    "name:por_x_preferred":[
        "Jablanica"
    ],
    "name:rus_x_preferred":[
        "\u042f\u0431\u043b\u0430\u043d\u0438\u0446\u0430"
    ],
    "name:slv_x_preferred":[
        "Jablanica"
    ],
    "name:srp_x_preferred":[
        "\u0408\u0430\u0431\u043b\u0430\u043d\u0438\u0446\u0430"
    ],
    "name:swe_x_preferred":[
        "Jablanica"
    ],
    "name:ukr_x_preferred":[
        "\u042f\u0431\u043b\u0430\u043d\u0438\u0446\u044f"
    ],
    "wof:name":"Jablanica",
    "wof:placetype":"locality"
},
  "geometry": {"coordinates":[18.0221,44.58955],"type":"Point"}
}