{
  "type": "Feature",
  "properties": {
    "gn:admin1_code":"01",
    "gn:asciiname":"Jablanica",
    "gn:country_code":"BA",
    "gn:dem":245,
    "gn:feature_class":"P",
    "gn:feature_code":"PPLL",
    "gn:name":"Jablanica",
    "gn:population":0,
    "gn:timezone":"Europe/Sarajevo",
    "iso:country":"BA",
    "wof:name":"Jablanica",
    "wof:placetype":"locality"
},
  "geometry": {"coordinates":[18.0221,44.58955],"type":"Point"}
}