{
  "type": "Feature",
  "properties": {
    "gn:admin1_code":"01",
    "gn:asciiname":"Skutari",
    "gn:country_code":"BA",
    "gn:dem":836,
    "gn:feature_class":"P",
    "gn:feature_code":"PPL",
    "gn:name":"\u0160kutari",
    "gn:population":0,
    "gn:timezone":"Europe/Sarajevo",
    "iso:country":"BA",
    "name:fin_x_preferred":[
        "Skutari"
    ],
    "name:pol_x_preferred":[
        "Skutari"
    ],
    "name:swe_x_preferred":[
        "Skutari"
    ],
    "wof:name":"Skutari",
    "wof:placetype":"locality"
},
  "geometry": {"coordinates":[17.75191000000001,43.43729],"type":"Point"}
}