{
  "type": "Feature",
  "properties": {
    "gn:admin1_code":"02",
    "gn:asciiname":"Trgoviste",
    "gn:country_code":"BA",
    "gn:dem":531,
    "gn:feature_class":"P",
    "gn:feature_code":"PPL",
    "gn:name":"Trgovi\u0161te",
    "gn:population":0,
    "gn:timezone":"Europe/Sarajevo",
    "iso:country":"BA",
    "wof:name":"Trgoviste",
    "wof:placetype":"locality"
},
  "geometry": {"coordinates":[19.29,43.65778],"type":"Point"}
}