{
  "type": "Feature",
  "properties": {
    "gn:admin1_code":"01",
    "gn:asciiname":"Drenov Do",
    "gn:country_code":"BA",
    "gn:dem":417,
    "gn:feature_class":"P",
    "gn:feature_code":"PPL",
    "gn:name":"Drenov Do",
    "gn:population":0,
    "gn:timezone":"Europe/Sarajevo",
    "iso:country":"BA",
    "name:bos_x_preferred":[
        "Drenov Do"
    ],
    "name:fra_x_preferred":[
        "Drenov Do"
    ],
    "name:hrv_x_preferred":[
        "Drenov Do"
    ],
    "name:srp_x_preferred":[
        "\u0414\u0440\u0435\u043d\u043e\u0432 \u0414\u043e"
    ],
    "wof:name":"Drenov Do",
    "wof:placetype":"locality"
},
  "geometry": {"coordinates":[18.82037,44.52316],"type":"Point"}
}