{
  "type": "Feature",
  "properties": {
    "gn:admin1_code":"01",
    "gn:asciiname":"Hadzici",
    "gn:country_code":"BA",
    "gn:dem":1235,
    "gn:feature_class":"P",
    "gn:feature_code":"PPLL",
    "gn:name":"Had\u017ei\u0107i",
    "gn:population":0,
    "gn:timezone":"Europe/Sarajevo",
    "iso:country":"BA",
    "name:bos_x_preferred":[
        "Had\u017ei\u0107i"
    ],
    "name:fra_x_preferred":[
        "Had\u017ei\u0107i"
    ],
    "wof:name":"Hadzici",
    "wof:placetype":"locality"
},
  "geometry": {"coordinates":[18.86945,43.71303],"type":"Point"}
}