{
  "type": "Feature",
  "properties": {
    "gn:admin1_code":"02",
    "gn:asciiname":"Zec",
    "gn:country_code":"BA",
    "gn:dem":143,
    "gn:feature_class":"P",
    "gn:feature_code":"PPL",
    "gn:name":"Zec",
    "gn:population":0,
    "gn:timezone":"Europe/Sarajevo",
    "iso:country":"BA",
    "name:ceb_x_preferred":[
        "Zec"
    ],
    "name:deu_x_preferred":[
        "Zec"
    ],
    "name:hrv_x_preferred":[
        "Zec"
    ],
    "name:pol_x_preferred":[
        "Zec"
    ],
    "name:swe_x_preferred":[
        "Zec"
    ],
    "wof:name":"Zec",
    "wof:placetype":"locality"
},
  "geometry": {"coordinates":[17.77777,44.84673],"type":"Point"}
}