{
  "type": "Feature",
  "properties": {
    "gn:admin1_code":"01",
    "gn:asciiname":"Kosa",
    "gn:country_code":"BA",
    "gn:dem":314,
    "gn:feature_class":"P",
    "gn:feature_code":"PPL",
    "gn:name":"Kosa",
    "gn:population":0,
    "gn:timezone":"Europe/Sarajevo",
    "iso:country":"BA",
    "name:swe_x_preferred":[
        "Kosa"
    ],
    "wof:name":"Kosa",
    "wof:placetype":"locality"
},
  "geometry": {"coordinates":[18.98967,44.47861],"type":"Point"}
}