{
  "type": "Feature",
  "properties": {
    "gn:admin1_code":"02",
    "gn:asciiname":"Rajetkovici",
    "gn:country_code":"BA",
    "gn:dem":484,
    "gn:feature_class":"P",
    "gn:feature_code":"PPL",
    "gn:name":"Rajetkovi\u0107i",
    "gn:population":0,
    "gn:timezone":"Europe/Sarajevo",
    "iso:country":"BA",
    "wof:name":"Rajetkovici",
    "wof:placetype":"locality"
},
  "geometry": {"coordinates":[19.57028,44.02111],"type":"Point"}
}