{
  "type": "Feature",
  "properties": {
    "gn:admin1_code":"02",
    "gn:asciiname":"Lugonjici",
    "gn:country_code":"BA",
    "gn:dem":166,
    "gn:feature_class":"P",
    "gn:feature_code":"PPL",
    "gn:name":"Lugonji\u0107i",
    "gn:population":0,
    "gn:timezone":"Europe/Sarajevo",
    "iso:country":"BA",
    "wof:name":"Lugonjici",
    "wof:placetype":"locality"
},
  "geometry": {"coordinates":[18.83443,44.76953],"type":"Point"}
}