{
  "type": "Feature",
  "properties": {
    "gn:admin1_code":"01",
    "gn:asciiname":"Dolac",
    "gn:country_code":"BA",
    "gn:dem":292,
    "gn:feature_class":"P",
    "gn:feature_code":"PPL",
    "gn:name":"Dolac",
    "gn:population":0,
    "gn:timezone":"Europe/Sarajevo",
    "iso:country":"BA",
    "name:bos_x_preferred":[
        "Dolac"
    ],
    "name:ceb_x_preferred":[
        "Dolac"
    ],
    "name:fra_x_preferred":[
        "Dolac"
    ],
    "name:hrv_x_preferred":[
        "Dolac"
    ],
    "name:nld_x_preferred":[
        "Dolac"
    ],
    "name:por_x_preferred":[
        "Dolac"
    ],
    "name:slv_x_preferred":[
        "Dolac"
    ],
    "name:srp_x_preferred":[
        "\u0414\u043e\u043b\u0430\u0446"
    ],
    "name:swe_x_preferred":[
        "Dolac"
    ],
    "wof:name":"Dolac",
    "wof:placetype":"locality"
},
  "geometry": {"coordinates":[17.97164,44.59791],"type":"Point"}
}