{
  "type": "Feature",
  "properties": {
    "gn:admin1_code":"01",
    "gn:asciiname":"Lugarnica",
    "gn:country_code":"BA",
    "gn:dem":794,
    "gn:feature_class":"P",
    "gn:feature_code":"PPL",
    "gn:name":"Lugarnica",
    "gn:population":0,
    "gn:timezone":"Europe/Sarajevo",
    "iso:country":"BA",
    "wof:name":"Lugarnica",
    "wof:placetype":"locality"
},
  "geometry": {"coordinates":[16.39136,44.1585],"type":"Point"}
}