{
  "type": "Feature",
  "properties": {
    "gn:admin1_code":"01",
    "gn:asciiname":"Razici",
    "gn:country_code":"BA",
    "gn:dem":534,
    "gn:feature_class":"P",
    "gn:feature_code":"PPLL",
    "gn:name":"Razi\u0107i",
    "gn:population":0,
    "gn:timezone":"Europe/Sarajevo",
    "iso:country":"BA",
    "name:und_x_variant":[
        "Razi\u0107i"
    ],
    "wof:name":"Razici",
    "wof:placetype":"locality"
},
  "geometry": {"coordinates":[18.1095,43.51774],"type":"Point"}
}