{
  "type": "Feature",
  "properties": {
    "gn:admin1_code":"02",
    "gn:asciiname":"Vrbica",
    "gn:country_code":"BA",
    "gn:dem":1026,
    "gn:feature_class":"P",
    "gn:feature_code":"PPL",
    "gn:name":"Vrbica",
    "gn:population":0,
    "gn:timezone":"Europe/Sarajevo",
    "iso:country":"BA",
    "wof:name":"Vrbica",
    "wof:placetype":"locality"
},
  "geometry": {"coordinates":[18.93745,43.39504],"type":"Point"}
}