{
  "type": "Feature",
  "properties": {
    "gn:admin1_code":"02",
    "gn:asciiname":"Sejmenovici",
    "gn:country_code":"BA",
    "gn:dem":498,
    "gn:feature_class":"P",
    "gn:feature_code":"PPLL",
    "gn:name":"Sejmenovi\u0107i",
    "gn:population":0,
    "gn:timezone":"Europe/Sarajevo",
    "iso:country":"BA",
    "wof:name":"Sejmenovici",
    "wof:placetype":"locality"
},
  "geometry": {"coordinates":[19.06158,44.25766],"type":"Point"}
}