{
  "type": "Feature",
  "properties": {
    "gn:admin1_code":"02",
    "gn:asciiname":"Maletici",
    "gn:country_code":"BA",
    "gn:dem":206,
    "gn:feature_class":"P",
    "gn:feature_code":"PPL",
    "gn:name":"Maleti\u0107i",
    "gn:population":0,
    "gn:timezone":"Europe/Sarajevo",
    "iso:country":"BA",
    "wof:name":"Maletici",
    "wof:placetype":"locality"
},
  "geometry": {"coordinates":[17.78082999999999,44.80949],"type":"Point"}
}