{
  "type": "Feature",
  "properties": {
    "gn:admin1_code":"01",
    "gn:asciiname":"Sarica Dubrava",
    "gn:country_code":"BA",
    "gn:dem":347,
    "gn:feature_class":"P",
    "gn:feature_code":"PPL",
    "gn:name":"\u0160ari\u0107a Dubrava",
    "gn:population":0,
    "gn:timezone":"Europe/Sarajevo",
    "iso:country":"BA",
    "wof:name":"Sarica Dubrava",
    "wof:placetype":"locality"
},
  "geometry": {"coordinates":[17.52322,43.38585],"type":"Point"}
}