{
  "type": "Feature",
  "properties": {
    "gn:admin1_code":"02",
    "gn:asciiname":"Pribosijevici",
    "gn:country_code":"BA",
    "gn:dem":618,
    "gn:feature_class":"P",
    "gn:feature_code":"PPLL",
    "gn:name":"Pribo\u0161ijevi\u0107i",
    "gn:population":0,
    "gn:timezone":"Europe/Sarajevo",
    "iso:country":"BA",
    "wof:name":"Pribosijevici",
    "wof:placetype":"locality"
},
  "geometry": {"coordinates":[18.98166,43.787],"type":"Point"}
}