{
  "type": "Feature",
  "properties": {
    "gn:admin1_code":"01",
    "gn:asciiname":"Kudilji",
    "gn:country_code":"BA",
    "gn:dem":1209,
    "gn:feature_class":"P",
    "gn:feature_code":"PPL",
    "gn:name":"Kudilji",
    "gn:population":0,
    "gn:timezone":"Europe/Sarajevo",
    "iso:country":"BA",
    "wof:name":"Kudilji",
    "wof:placetype":"locality"
},
  "geometry": {"coordinates":[17.32512,43.91812],"type":"Point"}
}