{
  "type": "Feature",
  "properties": {
    "gn:admin1_code":"01",
    "gn:asciiname":"Vukmiri",
    "gn:country_code":"BA",
    "gn:dem":458,
    "gn:feature_class":"P",
    "gn:feature_code":"PPL",
    "gn:name":"Vukmiri",
    "gn:population":0,
    "gn:timezone":"Europe/Sarajevo",
    "iso:country":"BA",
    "name:und_x_variant":[
        "Vukmir",
        "Vukmiri"
    ],
    "wof:name":"Vukmiri",
    "wof:placetype":"locality"
},
  "geometry": {"coordinates":[18.93981,44.52252],"type":"Point"}
}