{
  "type": "Feature",
  "properties": {
    "gn:admin1_code":"01",
    "gn:asciiname":"Cukova Greda",
    "gn:cc2":"BA",
    "gn:country_code":"BA",
    "gn:dem":99,
    "gn:feature_class":"P",
    "gn:feature_code":"PPL",
    "gn:name":"\u010cukova Greda",
    "gn:population":0,
    "gn:timezone":"Europe/Sarajevo",
    "iso:country":"BA",
    "name:und_x_variant":[
        "\u010cukova Grad",
        "\u010cukova Greda"
    ],
    "wof:name":"Cukova Greda",
    "wof:placetype":"locality"
},
  "geometry": {"coordinates":[17.71667,42.95167],"type":"Point"}
}