{
  "type": "Feature",
  "properties": {
    "gn:admin1_code":"01",
    "gn:asciiname":"Humac",
    "gn:country_code":"BA",
    "gn:dem":258,
    "gn:feature_class":"P",
    "gn:feature_code":"PPL",
    "gn:name":"Humac",
    "gn:population":0,
    "gn:timezone":"Europe/Sarajevo",
    "iso:country":"BA",
    "name:bos_x_preferred":[
        "Humac"
    ],
    "name:ceb_x_preferred":[
        "Humac"
    ],
    "name:fra_x_preferred":[
        "Humac"
    ],
    "name:hrv_x_preferred":[
        "Humac"
    ],
    "name:hun_x_preferred":[
        "Humac"
    ],
    "name:srp_x_preferred":[
        "\u0425\u0443\u043c\u0430\u0446"
    ],
    "name:swe_x_preferred":[
        "Humac"
    ],
    "wof:name":"Humac",
    "wof:placetype":"locality"
},
  "geometry": {"coordinates":[17.85889,42.92222],"type":"Point"}
}