{
  "type": "Feature",
  "properties": {
    "gn:admin1_code":"01",
    "gn:asciiname":"Humac",
    "gn:country_code":"BA",
    "gn:dem":258,
    "gn:feature_class":"P",
    "gn:feature_code":"PPL",
    "gn:name":"Humac",
    "gn:population":0,
    "gn:timezone":"Europe/Sarajevo",
    "iso:country":"BA",
    "wof:name":"Humac",
    "wof:placetype":"locality"
},
  "geometry": {"coordinates":[17.85889,42.92222],"type":"Point"}
}