{
  "type": "Feature",
  "properties": {
    "gn:admin1_code":"02",
    "gn:asciiname":"Vranduk",
    "gn:country_code":"BA",
    "gn:dem":219,
    "gn:feature_class":"P",
    "gn:feature_code":"PPL",
    "gn:name":"Vranduk",
    "gn:population":0,
    "gn:timezone":"Europe/Sarajevo",
    "iso:country":"BA",
    "wof:name":"Vranduk",
    "wof:placetype":"locality"
},
  "geometry": {"coordinates":[18.03057,44.862],"type":"Point"}
}