{
  "type": "Feature",
  "properties": {
    "gn:admin1_code":"01",
    "gn:asciiname":"Gromilice",
    "gn:country_code":"BA",
    "gn:dem":369,
    "gn:feature_class":"P",
    "gn:feature_code":"PPL",
    "gn:name":"Gromilice",
    "gn:population":0,
    "gn:timezone":"Europe/Sarajevo",
    "iso:country":"BA",
    "wof:name":"Gromilice",
    "wof:placetype":"locality"
},
  "geometry": {"coordinates":[18.12139,44.47467],"type":"Point"}
}