{
  "type": "Feature",
  "properties": {
    "gn:admin1_code":"01",
    "gn:asciiname":"Basici",
    "gn:country_code":"BA",
    "gn:dem":192,
    "gn:feature_class":"P",
    "gn:feature_code":"PPL",
    "gn:name":"Basi\u0107i",
    "gn:population":0,
    "gn:timezone":"Europe/Sarajevo",
    "iso:country":"BA",
    "wof:name":"Basici",
    "wof:placetype":"locality"
},
  "geometry": {"coordinates":[18.3929,44.63938],"type":"Point"}
}