{
  "type": "Feature",
  "properties": {
    "gn:admin1_code":"01",
    "gn:asciiname":"Vaselici",
    "gn:country_code":"BA",
    "gn:dem":828,
    "gn:feature_class":"P",
    "gn:feature_code":"PPLL",
    "gn:name":"Va\u0161eli\u0107i",
    "gn:population":0,
    "gn:timezone":"Europe/Sarajevo",
    "iso:country":"BA",
    "wof:name":"Vaselici",
    "wof:placetype":"locality"
},
  "geometry": {"coordinates":[16.43152000000001,44.3623],"type":"Point"}
}