{
  "type": "Feature",
  "properties": {
    "gn:admin1_code":"01",
    "gn:asciiname":"Donje Ledenice",
    "gn:country_code":"BA",
    "gn:dem":97,
    "gn:feature_class":"P",
    "gn:feature_code":"PPLL",
    "gn:name":"Donje Ledenice",
    "gn:population":0,
    "gn:timezone":"Europe/Sarajevo",
    "iso:country":"BA",
    "name:bos_x_preferred":[
        "Donje Ledenice"
    ],
    "name:ceb_x_preferred":[
        "Donje Ledenice"
    ],
    "name:fra_x_preferred":[
        "Donje Ledenice"
    ],
    "name:hrv_x_preferred":[
        "Donje Ledenice"
    ],
    "name:swe_x_preferred":[
        "Donje Ledenice"
    ],
    "name:und_x_variant":[
        "Ledenice",
        "Donje Ledenice"
    ],
    "wof:name":"Donje Ledenice",
    "wof:placetype":"locality"
},
  "geometry": {"coordinates":[18.41913,44.91488],"type":"Point"}
}