{
  "type": "Feature",
  "properties": {
    "gn:admin1_code":"02",
    "gn:asciiname":"Brdani",
    "gn:country_code":"BA",
    "gn:dem":259,
    "gn:feature_class":"P",
    "gn:feature_code":"PPL",
    "gn:name":"Br\u0111ani",
    "gn:population":0,
    "gn:timezone":"Europe/Sarajevo",
    "iso:country":"BA",
    "name:und_x_variant":[
        "Br\u0111am",
        "Br\u0111ani"
    ],
    "wof:name":"Brdani",
    "wof:placetype":"locality"
},
  "geometry": {"coordinates":[19.10085,44.63402],"type":"Point"}
}