{
  "type": "Feature",
  "properties": {
    "gn:admin1_code":"01",
    "gn:asciiname":"Donji Jasenjani",
    "gn:country_code":"BA",
    "gn:dem":154,
    "gn:feature_class":"P",
    "gn:feature_code":"PPLL",
    "gn:name":"Donji Jasenjani",
    "gn:population":0,
    "gn:timezone":"Europe/Sarajevo",
    "iso:country":"BA",
    "wof:name":"Donji Jasenjani",
    "wof:placetype":"locality"
},
  "geometry": {"coordinates":[17.72696000000001,43.54786],"type":"Point"}
}