{
  "type": "Feature",
  "properties": {
    "gn:admin1_code":"01",
    "gn:asciiname":"Velesici",
    "gn:country_code":"BA",
    "gn:dem":616,
    "gn:feature_class":"P",
    "gn:feature_code":"PPL",
    "gn:name":"Vele\u0161i\u0107i",
    "gn:population":0,
    "gn:timezone":"Europe/Sarajevo",
    "iso:country":"BA",
    "wof:name":"Velesici",
    "wof:placetype":"locality"
},
  "geometry": {"coordinates":[18.3969,43.86832],"type":"Point"}
}