{
  "type": "Feature",
  "properties": {
    "gn:admin1_code":"01",
    "gn:asciiname":"Kaurinovici",
    "gn:country_code":"BA",
    "gn:dem":373,
    "gn:feature_class":"P",
    "gn:feature_code":"PPL",
    "gn:name":"Kaurinovi\u0107i",
    "gn:population":0,
    "gn:timezone":"Europe/Sarajevo",
    "iso:country":"BA",
    "wof:name":"Kaurinovici",
    "wof:placetype":"locality"
},
  "geometry": {"coordinates":[16.76608,44.77652],"type":"Point"}
}