{
  "type": "Feature",
  "properties": {
    "gn:admin1_code":"01",
    "gn:asciiname":"Celebic",
    "gn:country_code":"BA",
    "gn:dem":761,
    "gn:feature_class":"P",
    "gn:feature_code":"PPL",
    "gn:name":"\u010celebi\u0107",
    "gn:population":0,
    "gn:timezone":"Europe/Sarajevo",
    "iso:country":"BA",
    "wof:name":"Celebic",
    "wof:placetype":"locality"
},
  "geometry": {"coordinates":[16.75283,43.94829],"type":"Point"}
}