{
  "type": "Feature",
  "properties": {
    "gn:admin1_code":"02",
    "gn:asciiname":"Donje Mioce",
    "gn:country_code":"BA",
    "gn:dem":377,
    "gn:feature_class":"P",
    "gn:feature_code":"PPL",
    "gn:name":"Donje Mio\u010de",
    "gn:population":0,
    "gn:timezone":"Europe/Sarajevo",
    "iso:country":"BA",
    "wof:name":"Donje Mioce",
    "wof:placetype":"locality"
},
  "geometry": {"coordinates":[19.43255,43.5946],"type":"Point"}
}