{
  "type": "Feature",
  "properties": {
    "gn:admin1_code":"02",
    "gn:asciiname":"Brateljevici",
    "gn:country_code":"BA",
    "gn:dem":935,
    "gn:feature_class":"P",
    "gn:feature_code":"PPL",
    "gn:name":"Brateljevi\u0107i",
    "gn:population":0,
    "gn:timezone":"Europe/Sarajevo",
    "iso:country":"BA",
    "wof:name":"Brateljevici",
    "wof:placetype":"locality"
},
  "geometry": {"coordinates":[18.65015,43.71826],"type":"Point"}
}