{
  "type": "Feature",
  "properties": {
    "gn:admin1_code":"01",
    "gn:asciiname":"Miostrah",
    "gn:country_code":"BA",
    "gn:dem":357,
    "gn:feature_class":"P",
    "gn:feature_code":"PPLL",
    "gn:name":"Miostrah",
    "gn:population":0,
    "gn:timezone":"Europe/Sarajevo",
    "iso:country":"BA",
    "name:und_x_variant":[
        "Miostra",
        "Miostrah"
    ],
    "wof:name":"Miostrah",
    "wof:placetype":"locality"
},
  "geometry": {"coordinates":[16.00133,44.9095],"type":"Point"}
}