{
  "type": "Feature",
  "properties": {
    "gn:admin1_code":"01",
    "gn:asciiname":"Zelenika",
    "gn:country_code":"BA",
    "gn:dem":365,
    "gn:feature_class":"P",
    "gn:feature_code":"PPL",
    "gn:name":"Zelenika",
    "gn:population":0,
    "gn:timezone":"Europe/Sarajevo",
    "iso:country":"BA",
    "name:und_x_variant":[
        "Zloselo",
        "Zelenika"
    ],
    "wof:name":"Zelenika",
    "wof:placetype":"locality"
},
  "geometry": {"coordinates":[18.7466,44.38853],"type":"Point"}
}