{
  "type": "Feature",
  "properties": {
    "gn:admin1_code":"02",
    "gn:asciiname":"Prisocka",
    "gn:country_code":"BA",
    "gn:dem":849,
    "gn:feature_class":"P",
    "gn:feature_code":"PPLL",
    "gn:name":"Priso\u010dka",
    "gn:population":0,
    "gn:timezone":"Europe/Sarajevo",
    "iso:country":"BA",
    "wof:name":"Prisocka",
    "wof:placetype":"locality"
},
  "geometry": {"coordinates":[17.58306,44.4425],"type":"Point"}
}