{
  "type": "Feature",
  "properties": {
    "gn:admin1_code":"02",
    "gn:asciiname":"Sapci",
    "gn:country_code":"BA",
    "gn:dem":988,
    "gn:feature_class":"P",
    "gn:feature_code":"PPL",
    "gn:name":"\u0160apci",
    "gn:population":0,
    "gn:timezone":"Europe/Sarajevo",
    "iso:country":"BA",
    "wof:name":"Sapci",
    "wof:placetype":"locality"
},
  "geometry": {"coordinates":[18.66211,43.7949],"type":"Point"}
}