{
  "type": "Feature",
  "properties": {
    "gn:admin1_code":"01",
    "gn:asciiname":"Horozovo Brdo",
    "gn:country_code":"BA",
    "gn:dem":426,
    "gn:feature_class":"P",
    "gn:feature_code":"PPL",
    "gn:name":"Horozovo Brdo",
    "gn:population":0,
    "gn:timezone":"Europe/Sarajevo",
    "iso:country":"BA",
    "wof:name":"Horozovo Brdo",
    "wof:placetype":"locality"
},
  "geometry": {"coordinates":[15.96659,44.99152],"type":"Point"}
}