{
  "type": "Feature",
  "properties": {
    "gn:admin1_code":"02",
    "gn:asciiname":"Nevorici",
    "gn:country_code":"BA",
    "gn:dem":591,
    "gn:feature_class":"P",
    "gn:feature_code":"PPL",
    "gn:name":"Nevori\u0107i",
    "gn:population":0,
    "gn:timezone":"Europe/Sarajevo",
    "iso:country":"BA",
    "name:bos_x_preferred":[
        "Nevori\u0107i"
    ],
    "name:fra_x_preferred":[
        "Nevori\u0107i"
    ],
    "name:srp_x_preferred":[
        "\u041d\u0435\u0432\u043e\u0440\u0438\u045b\u0438"
    ],
    "name:und_x_variant":[
        "Nevori\u0107i"
    ],
    "wof:name":"Nevorici",
    "wof:placetype":"locality"
},
  "geometry": {"coordinates":[18.95513,43.59637],"type":"Point"}
}