{
  "type": "Feature",
  "properties": {
    "gn:admin1_code":"01",
    "gn:asciiname":"Podkozara Donja",
    "gn:country_code":"BA",
    "gn:dem":384,
    "gn:feature_class":"P",
    "gn:feature_code":"PPLL",
    "gn:name":"Podkozara Donja",
    "gn:population":0,
    "gn:timezone":"Europe/Sarajevo",
    "iso:country":"BA",
    "wof:name":"Podkozara Donja",
    "wof:placetype":"locality"
},
  "geometry": {"coordinates":[18.9857,43.63227],"type":"Point"}
}