{
  "type": "Feature",
  "properties": {
    "gn:admin1_code":"02",
    "gn:asciiname":"Okoliste",
    "gn:country_code":"BA",
    "gn:dem":840,
    "gn:feature_class":"P",
    "gn:feature_code":"PPL",
    "gn:name":"Okoli\u0161te",
    "gn:population":0,
    "gn:timezone":"Europe/Sarajevo",
    "iso:country":"BA",
    "wof:name":"Okoliste",
    "wof:placetype":"locality"
},
  "geometry": {"coordinates":[18.66843,44.01476],"type":"Point"}
}