{
  "type": "Feature",
  "properties": {
    "gn:admin1_code":"01",
    "gn:asciiname":"Zajezda",
    "gn:country_code":"BA",
    "gn:dem":547,
    "gn:feature_class":"P",
    "gn:feature_code":"PPL",
    "gn:name":"Zajezda",
    "gn:population":0,
    "gn:timezone":"Europe/Sarajevo",
    "iso:country":"BA",
    "name:bos_x_preferred":[
        "Zajezda"
    ],
    "name:ceb_x_preferred":[
        "Zajezda"
    ],
    "name:fra_x_preferred":[
        "Zajezda"
    ],
    "name:hrv_x_preferred":[
        "Zajezda"
    ],
    "name:hun_x_preferred":[
        "Zajezda"
    ],
    "name:nld_x_preferred":[
        "Zajezda"
    ],
    "name:slv_x_preferred":[
        "Zajezda"
    ],
    "name:spa_x_preferred":[
        "Zajezda"
    ],
    "name:srp_x_preferred":[
        "\u0417\u0430\u0458\u0435\u0437\u0434\u0430"
    ],
    "name:swe_x_preferred":[
        "Zajezda"
    ],
    "name:ukr_x_preferred":[
        "\u0417\u0430\u0454\u0437\u0434\u0430"
    ],
    "wof:name":"Zajezda",
    "wof:placetype":"locality"
},
  "geometry": {"coordinates":[18.16423,44.08453],"type":"Point"}
}