{
  "type": "Feature",
  "properties": {
    "gn:admin1_code":"02",
    "gn:asciiname":"Bukovica Gornja",
    "gn:country_code":"BA",
    "gn:dem":669,
    "gn:feature_class":"P",
    "gn:feature_code":"PPL",
    "gn:name":"Bukovica Gornja",
    "gn:population":0,
    "gn:timezone":"Europe/Sarajevo",
    "iso:country":"BA",
    "name:bos_x_preferred":[
        "Bukovica Gornja"
    ],
    "name:fra_x_preferred":[
        "Bukovica Gornja"
    ],
    "name:hrv_x_preferred":[
        "Bukovica Gornja"
    ],
    "name:rus_x_preferred":[
        "\u0411\u0443\u043a\u043e\u0432\u0438\u0446\u0430-\u0413\u043e\u0440\u043d\u044f"
    ],
    "name:slv_x_preferred":[
        "Bukovica Gornja"
    ],
    "name:srp_x_preferred":[
        "\u0411\u0443\u043a\u043e\u0432\u0438\u0446\u0430 \u0413\u043e\u0440\u045a\u0430"
    ],
    "name:urd_x_preferred":[
        "\u0628\u0648\u06a9\u0648\u0648\u06cc\u062a\u0633\u0627 \u06af\u0648\u0631\u0646\u06cc\u0627"
    ],
    "wof:name":"Bukovica Gornja",
    "wof:placetype":"locality"
},
  "geometry": {"coordinates":[19.18333,44.13333],"type":"Point"}
}