{
  "type": "Feature",
  "properties": {
    "gn:admin1_code":"02",
    "gn:asciiname":"Bukovica Gornja",
    "gn:country_code":"BA",
    "gn:dem":669,
    "gn:feature_class":"P",
    "gn:feature_code":"PPL",
    "gn:name":"Bukovica Gornja",
    "gn:population":0,
    "gn:timezone":"Europe/Sarajevo",
    "iso:country":"BA",
    "wof:name":"Bukovica Gornja",
    "wof:placetype":"locality"
},
  "geometry": {"coordinates":[19.18333,44.13333],"type":"Point"}
}