{
  "type": "Feature",
  "properties": {
    "gn:admin1_code":"02",
    "gn:asciiname":"Trpinje",
    "gn:country_code":"BA",
    "gn:dem":1039,
    "gn:feature_class":"P",
    "gn:feature_code":"PPL",
    "gn:name":"Trpinje",
    "gn:population":0,
    "gn:timezone":"Europe/Sarajevo",
    "iso:country":"BA",
    "name:bos_x_preferred":[
        "Trpinje"
    ],
    "name:fra_x_preferred":[
        "Trpinje"
    ],
    "name:rus_x_preferred":[
        "\u0422\u0440\u043f\u0438\u043d\u0435"
    ],
    "name:srp_x_preferred":[
        "\u0422\u0440\u043f\u0438\u045a\u0435"
    ],
    "wof:name":"Trpinje",
    "wof:placetype":"locality"
},
  "geometry": {"coordinates":[19.0407,43.54600000000001],"type":"Point"}
}