{
  "type": "Feature",
  "properties": {
    "gn:admin1_code":"BRC",
    "gn:asciiname":"Potocari",
    "gn:country_code":"BA",
    "gn:dem":123,
    "gn:feature_class":"P",
    "gn:feature_code":"PPLL",
    "gn:name":"Poto\u010dari",
    "gn:population":0,
    "gn:timezone":"Europe/Sarajevo",
    "iso:country":"BA",
    "wof:name":"Potocari",
    "wof:placetype":"locality"
},
  "geometry": {"coordinates":[18.81725,44.82629],"type":"Point"}
}