{
  "type": "Feature",
  "properties": {
    "gn:admin1_code":"01",
    "gn:asciiname":"Manjusci",
    "gn:country_code":"BA",
    "gn:dem":1139,
    "gn:feature_class":"P",
    "gn:feature_code":"PPL",
    "gn:name":"Manju\u0161ci",
    "gn:population":0,
    "gn:timezone":"Europe/Sarajevo",
    "iso:country":"BA",
    "wof:name":"Manjusci",
    "wof:placetype":"locality"
},
  "geometry": {"coordinates":[17.4451,43.80673],"type":"Point"}
}