{
  "type": "Feature",
  "properties": {
    "gn:admin1_code":"02",
    "gn:asciiname":"Zivoskup",
    "gn:country_code":"BA",
    "gn:dem":395,
    "gn:feature_class":"P",
    "gn:feature_code":"PPLL",
    "gn:name":"\u017divoskup",
    "gn:population":0,
    "gn:timezone":"Europe/Sarajevo",
    "iso:country":"BA",
    "wof:name":"Zivoskup",
    "wof:placetype":"locality"
},
  "geometry": {"coordinates":[16.35776,44.8562],"type":"Point"}
}