{
  "type": "Feature",
  "properties": {
    "gn:admin1_code":"02",
    "gn:asciiname":"Zivanovici",
    "gn:country_code":"BA",
    "gn:dem":1333,
    "gn:feature_class":"P",
    "gn:feature_code":"PPL",
    "gn:name":"\u017divanovi\u0107i",
    "gn:population":0,
    "gn:timezone":"Europe/Sarajevo",
    "iso:country":"BA",
    "name:und_x_variant":[
        "\u017divanovi\u0107",
        "\u017divanovi\u0107i"
    ],
    "wof:name":"Zivanovici",
    "wof:placetype":"locality"
},
  "geometry": {"coordinates":[19.00296,43.30708],"type":"Point"}
}