{
  "type": "Feature",
  "properties": {
    "gn:admin1_code":"01",
    "gn:asciiname":"Savici",
    "gn:country_code":"BA",
    "gn:dem":1020,
    "gn:feature_class":"P",
    "gn:feature_code":"PPL",
    "gn:name":"Savi\u0107i",
    "gn:population":0,
    "gn:timezone":"Europe/Sarajevo",
    "iso:country":"BA",
    "wof:name":"Savici",
    "wof:placetype":"locality"
},
  "geometry": {"coordinates":[16.61825,44.26725],"type":"Point"}
}