{
  "type": "Feature",
  "properties": {
    "gn:admin1_code":"01",
    "gn:asciiname":"Kojsina",
    "gn:country_code":"BA",
    "gn:dem":750,
    "gn:feature_class":"P",
    "gn:feature_code":"PPL",
    "gn:name":"Kojsina",
    "gn:population":0,
    "gn:timezone":"Europe/Sarajevo",
    "iso:country":"BA",
    "wof:name":"Kojsina",
    "wof:placetype":"locality"
},
  "geometry": {"coordinates":[18.01418,43.86483],"type":"Point"}
}