{
  "type": "Feature",
  "properties": {
    "gn:admin1_code":"02",
    "gn:asciiname":"Lazici",
    "gn:country_code":"BA",
    "gn:dem":536,
    "gn:feature_class":"P",
    "gn:feature_code":"PPL",
    "gn:name":"Lazi\u0107i",
    "gn:population":0,
    "gn:timezone":"Europe/Sarajevo",
    "iso:country":"BA",
    "wof:name":"Lazici",
    "wof:placetype":"locality"
},
  "geometry": {"coordinates":[17.13193,44.33698],"type":"Point"}
}