{
  "type": "Feature",
  "properties": {
    "gn:admin1_code":"01",
    "gn:asciiname":"Balinovac",
    "gn:country_code":"BA",
    "gn:dem":77,
    "gn:feature_class":"P",
    "gn:feature_code":"PPL",
    "gn:name":"Balinovac",
    "gn:population":0,
    "gn:timezone":"Europe/Sarajevo",
    "iso:country":"BA",
    "name:ceb_x_preferred":[
        "Balinovac"
    ],
    "name:fra_x_preferred":[
        "Balinovac"
    ],
    "name:msa_x_preferred":[
        "Balinovac"
    ],
    "name:por_x_preferred":[
        "Balinovac"
    ],
    "name:slv_x_preferred":[
        "Balinovac"
    ],
    "name:sqi_x_preferred":[
        "Balinoci"
    ],
    "name:srp_x_preferred":[
        "\u0411\u0430\u043b\u0438\u043d\u043e\u0432\u0430\u0446"
    ],
    "wof:name":"Balinovac",
    "wof:placetype":"locality"
},
  "geometry": {"coordinates":[17.79502,43.33791],"type":"Point"}
}