{
  "type": "Feature",
  "properties": {
    "gn:admin1_code":"02",
    "gn:asciiname":"Vrhovci",
    "gn:country_code":"BA",
    "gn:dem":189,
    "gn:feature_class":"P",
    "gn:feature_code":"PPL",
    "gn:name":"Vrhovci",
    "gn:population":0,
    "gn:timezone":"Europe/Sarajevo",
    "iso:country":"BA",
    "wof:name":"Vrhovci",
    "wof:placetype":"locality"
},
  "geometry": {"coordinates":[17.18486,44.99973],"type":"Point"}
}