{
  "type": "Feature",
  "properties": {
    "gn:admin1_code":"01",
    "gn:asciiname":"Doljani",
    "gn:country_code":"BA",
    "gn:dem":90,
    "gn:feature_class":"P",
    "gn:feature_code":"PPL",
    "gn:name":"Doljani",
    "gn:population":0,
    "gn:timezone":"Europe/Sarajevo",
    "iso:country":"BA",
    "wof:name":"Doljani",
    "wof:placetype":"locality"
},
  "geometry": {"coordinates":[18.34125,45.06076],"type":"Point"}
}