{
  "type": "Feature",
  "properties": {
    "gn:admin1_code":"01",
    "gn:asciiname":"Stekina Draga",
    "gn:country_code":"BA",
    "gn:dem":920,
    "gn:feature_class":"P",
    "gn:feature_code":"PPL",
    "gn:name":"\u0160tekina Draga",
    "gn:population":0,
    "gn:timezone":"Europe/Sarajevo",
    "iso:country":"BA",
    "wof:name":"Stekina Draga",
    "wof:placetype":"locality"
},
  "geometry": {"coordinates":[17.25333,43.61778],"type":"Point"}
}