{
  "type": "Feature",
  "properties": {
    "gn:country":"BA",
    "gn:fcode":"PPL",
    "gn:pop":1,
    "iso:country":"BA",
    "name:bos_x_preferred":[
        "Br\u0111ani"
    ],
    "name:ceb_x_preferred":[
        "Br\u0111ani"
    ],
    "name:eng_x_preferred":[
        "Br\u0111ani"
    ],
    "name:fra_x_preferred":[
        "Br\u0111ani"
    ],
    "name:hrv_x_preferred":[
        "Br\u0111ani"
    ],
    "name:nld_x_preferred":[
        "Br\u0111ani"
    ],
    "name:por_x_preferred":[
        "Br\u0111ani"
    ],
    "name:slv_x_preferred":[
        "Br\u0111ani"
    ],
    "name:srp_x_preferred":[
        "\u0411\u0440\u0452\u0430\u043d\u0438"
    ],
    "name:swe_x_preferred":[
        "Br\u0111ani"
    ],
    "name:ukr_x_preferred":[
        "\u0411\u0440\u0434\u0436\u0430\u043d\u0456"
    ],
    "qs:name":"Br\u0111ani",
    "qs:photos_9r":0,
    "qs:photos_sr":0,
    "qs:pop_sr":"1",
    "wd:wordcount":77,
    "wof:name":"Br\u0111ani",
    "wof:placetype":"locality",
    "wof:population":1
},
  "geometry": {"coordinates":[18.17859,44.68672],"type":"Point"}
}