{
  "type": "Feature",
  "properties": {
    "gn:country":"BA",
    "gn:fcode":"PPL",
    "gn:pop":1,
    "iso:country":"BA",
    "qs:name":"Br\u0111ani",
    "qs:photos_9r":0,
    "qs:photos_sr":0,
    "qs:pop_sr":"1",
    "wd:wordcount":77,
    "wof:name":"Br\u0111ani",
    "wof:placetype":"locality",
    "wof:population":1
},
  "geometry": {"coordinates":[18.17859,44.68672],"type":"Point"}
}