{
  "type": "Feature",
  "properties": {
    "gn:admin1_code":"02",
    "gn:asciiname":"Plazace",
    "gn:country_code":"BA",
    "gn:dem":527,
    "gn:feature_class":"P",
    "gn:feature_code":"PPL",
    "gn:name":"Plaza\u010de",
    "gn:population":0,
    "gn:timezone":"Europe/Sarajevo",
    "iso:country":"BA",
    "wof:name":"Plazace",
    "wof:placetype":"locality"
},
  "geometry": {"coordinates":[18.8368,44.25501],"type":"Point"}
}