{
  "type": "Feature",
  "properties": {
    "gn:admin1_code":"01",
    "gn:asciiname":"Bare",
    "gn:country_code":"BA",
    "gn:dem":454,
    "gn:feature_class":"P",
    "gn:feature_code":"PPL",
    "gn:name":"Bare",
    "gn:population":0,
    "gn:timezone":"Europe/Sarajevo",
    "iso:country":"BA",
    "wof:name":"Bare",
    "wof:placetype":"locality"
},
  "geometry": {"coordinates":[17.3115,44.35277],"type":"Point"}
}