{
  "type": "Feature",
  "properties": {
    "gn:admin1_code":"01",
    "gn:asciiname":"Liskovaca",
    "gn:country_code":"BA",
    "gn:dem":739,
    "gn:feature_class":"P",
    "gn:feature_code":"PPL",
    "gn:name":"Liskova\u010da",
    "gn:population":0,
    "gn:timezone":"Europe/Sarajevo",
    "iso:country":"BA",
    "name:und_x_variant":[
        "Liskova\u010da"
    ],
    "wof:name":"Liskovaca",
    "wof:placetype":"locality"
},
  "geometry": {"coordinates":[16.97975,43.6348],"type":"Point"}
}