{
  "type": "Feature",
  "properties": {
    "gn:admin1_code":"01",
    "gn:asciiname":"Liskovaca",
    "gn:country_code":"BA",
    "gn:dem":739,
    "gn:feature_class":"P",
    "gn:feature_code":"PPL",
    "gn:name":"Liskova\u010da",
    "gn:population":0,
    "gn:timezone":"Europe/Sarajevo",
    "iso:country":"BA",
    "name:bos_x_preferred":[
        "Liskova\u010da"
    ],
    "name:ceb_x_preferred":[
        "Liskova\u010da"
    ],
    "name:fra_x_preferred":[
        "Liskova\u010da"
    ],
    "name:hrv_x_preferred":[
        "Liskova\u010da"
    ],
    "name:srp_x_preferred":[
        "\u041b\u0438\u0441\u043a\u043e\u0432\u0430\u0447\u0430"
    ],
    "name:swe_x_preferred":[
        "Liskova\u010da"
    ],
    "name:und_x_variant":[
        "Liskova\u010da"
    ],
    "wof:name":"Liskovaca",
    "wof:placetype":"locality"
},
  "geometry": {"coordinates":[16.97975,43.6348],"type":"Point"}
}