{
  "type": "Feature",
  "properties": {
    "gn:admin1_code":"01",
    "gn:asciiname":"Budisnja Ravan",
    "gn:country_code":"BA",
    "gn:dem":867,
    "gn:feature_class":"P",
    "gn:feature_code":"PPLL",
    "gn:name":"Budi\u0161nja Ravan",
    "gn:population":0,
    "gn:timezone":"Europe/Sarajevo",
    "iso:country":"BA",
    "name:und_x_variant":[
        "Budisna Ravan",
        "Budi\u0161nja Ravan"
    ],
    "wof:name":"Budisnja Ravan",
    "wof:placetype":"locality"
},
  "geometry": {"coordinates":[17.87839,43.76659],"type":"Point"}
}