{
  "type": "Feature",
  "properties": {
    "gn:admin1_code":"01",
    "gn:asciiname":"Budisnja Ravan",
    "gn:country_code":"BA",
    "gn:dem":867,
    "gn:feature_class":"P",
    "gn:feature_code":"PPLL",
    "gn:name":"Budi\u0161nja Ravan",
    "gn:population":0,
    "gn:timezone":"Europe/Sarajevo",
    "iso:country":"BA",
    "name:ara_x_preferred":[
        "\u0628\u0648\u062f\u064a\u0634\u0646\u064a\u0627 \u0631\u0627\u0641\u0627\u0646"
    ],
    "name:bos_x_preferred":[
        "Budi\u0161nja Ravan"
    ],
    "name:fra_x_preferred":[
        "Budi\u0161nja Ravan"
    ],
    "name:hrv_x_preferred":[
        "Budi\u0161nja Ravan"
    ],
    "name:srp_x_preferred":[
        "\u0411\u0443\u0434\u0438\u0448\u045a\u0430 \u0420\u0430\u0432\u0430\u043d"
    ],
    "name:und_x_variant":[
        "Budisna Ravan"
    ],
    "wof:name":"Budisnja Ravan",
    "wof:placetype":"locality"
},
  "geometry": {"coordinates":[17.87839,43.76659],"type":"Point"}
}