{
  "type": "Feature",
  "properties": {
    "gn:admin1_code":"02",
    "gn:asciiname":"Durdev Do",
    "gn:country_code":"BA",
    "gn:dem":1146,
    "gn:feature_class":"P",
    "gn:feature_code":"PPL",
    "gn:name":"\u00d0ur\u0111ev Do",
    "gn:population":0,
    "gn:timezone":"Europe/Sarajevo",
    "iso:country":"BA",
    "name:und_x_variant":[
        "Milinkovi\u010di",
        "\u00d0ur\u0111ev Do"
    ],
    "wof:name":"Durdev Do",
    "wof:placetype":"locality"
},
  "geometry": {"coordinates":[18.6349,43.1336],"type":"Point"}
}