{
  "type": "Feature",
  "properties": {
    "gn:admin1_code":"01",
    "gn:asciiname":"Donje Zivinice",
    "gn:country_code":"BA",
    "gn:dem":236,
    "gn:feature_class":"P",
    "gn:feature_code":"PPLL",
    "gn:name":"Donje \u017divinice",
    "gn:population":0,
    "gn:timezone":"Europe/Sarajevo",
    "iso:country":"BA",
    "name:und_x_variant":[
        "\u017divince Donje",
        "Katoli\u010dke \u017divinice",
        "Donje \u017divinice"
    ],
    "wof:name":"Donje Zivinice",
    "wof:placetype":"locality"
},
  "geometry": {"coordinates":[18.61573,44.45105],"type":"Point"}
}