{
  "type": "Feature",
  "properties": {
    "gn:admin1_code":"02",
    "gn:asciiname":"Kalkani",
    "gn:country_code":"BA",
    "gn:dem":892,
    "gn:feature_class":"P",
    "gn:feature_code":"PPL",
    "gn:name":"Kalkani",
    "gn:population":0,
    "gn:timezone":"Europe/Sarajevo",
    "iso:country":"BA",
    "wof:name":"Kalkani",
    "wof:placetype":"locality"
},
  "geometry": {"coordinates":[16.9871,44.28632],"type":"Point"}
}