{
  "type": "Feature",
  "properties": {
    "gn:admin1_code":"02",
    "gn:asciiname":"Sivolinac",
    "gn:country_code":"BA",
    "gn:dem":98,
    "gn:feature_class":"P",
    "gn:feature_code":"PPL",
    "gn:name":"Sivolinac",
    "gn:population":0,
    "gn:timezone":"Europe/Sarajevo",
    "iso:country":"BA",
    "wof:name":"Sivolinac",
    "wof:placetype":"locality"
},
  "geometry": {"coordinates":[17.00363,45.19817000000001],"type":"Point"}
}