{
  "type": "Feature",
  "properties": {
    "gn:admin1_code":"02",
    "gn:asciiname":"Velici",
    "gn:country_code":"BA",
    "gn:dem":128,
    "gn:feature_class":"P",
    "gn:feature_code":"PPL",
    "gn:name":"Veli\u010di",
    "gn:population":0,
    "gn:timezone":"Europe/Sarajevo",
    "iso:country":"BA",
    "wof:name":"Velici",
    "wof:placetype":"locality"
},
  "geometry": {"coordinates":[16.4625,45.03667],"type":"Point"}
}