{
  "type": "Feature",
  "properties": {
    "gn:admin1_code":"01",
    "gn:asciiname":"Police",
    "gn:country_code":"BA",
    "gn:dem":415,
    "gn:feature_class":"P",
    "gn:feature_code":"PPLL",
    "gn:name":"Police",
    "gn:population":0,
    "gn:timezone":"Europe/Sarajevo",
    "iso:country":"BA",
    "wof:name":"Police",
    "wof:placetype":"locality"
},
  "geometry": {"coordinates":[17.38179,43.36492],"type":"Point"}
}