{
  "type": "Feature",
  "properties": {
    "gn:admin1_code":"01",
    "gn:asciiname":"Sehiti",
    "gn:country_code":"BA",
    "gn:dem":479,
    "gn:feature_class":"P",
    "gn:feature_code":"PPL",
    "gn:name":"\u0160ehiti",
    "gn:population":0,
    "gn:timezone":"Europe/Sarajevo",
    "iso:country":"BA",
    "wof:name":"Sehiti",
    "wof:placetype":"locality"
},
  "geometry": {"coordinates":[15.95917,45.02181],"type":"Point"}
}