{
  "type": "Feature",
  "properties": {
    "gn:admin1_code":"01",
    "gn:asciiname":"Medarevici",
    "gn:country_code":"BA",
    "gn:dem":560,
    "gn:feature_class":"P",
    "gn:feature_code":"PPL",
    "gn:name":"Medarevi\u0107i",
    "gn:population":0,
    "gn:timezone":"Europe/Sarajevo",
    "iso:country":"BA",
    "wof:name":"Medarevici",
    "wof:placetype":"locality"
},
  "geometry": {"coordinates":[16.45004,44.34809],"type":"Point"}
}