{
  "type": "Feature",
  "properties": {
    "gn:admin1_code":"02",
    "gn:asciiname":"Vrbica",
    "gn:country_code":"BA",
    "gn:dem":892,
    "gn:feature_class":"P",
    "gn:feature_code":"PPL",
    "gn:name":"Vrbica",
    "gn:population":0,
    "gn:timezone":"Europe/Sarajevo",
    "iso:country":"BA",
    "name:bos_x_preferred":[
        "Vrbica"
    ],
    "name:bul_x_preferred":[
        "\u0412\u044a\u0440\u0431\u0438\u0446\u0430"
    ],
    "name:ceb_x_preferred":[
        "Vrbica"
    ],
    "name:fra_x_preferred":[
        "Vrbica"
    ],
    "name:hrv_x_preferred":[
        "Vrbica"
    ],
    "name:hun_x_preferred":[
        "Vrbica"
    ],
    "name:nld_x_preferred":[
        "Vrbica"
    ],
    "name:pol_x_preferred":[
        "Wyrbica"
    ],
    "name:ron_x_preferred":[
        "V\u0103rbi\u021ba"
    ],
    "name:rus_x_preferred":[
        "\u0412\u044b\u0440\u0431\u0438\u0446\u0430"
    ],
    "name:slk_x_preferred":[
        "Vrbica"
    ],
    "name:slv_x_preferred":[
        "Vrbica"
    ],
    "name:srp_x_preferred":[
        "\u0412\u0440\u0431\u0438\u0446\u0430"
    ],
    "name:swe_x_preferred":[
        "Vrbica"
    ],
    "name:ukr_x_preferred":[
        "\u0412\u0438\u0440\u0431\u0438\u0446\u044f"
    ],
    "wof:name":"Vrbica",
    "wof:placetype":"locality"
},
  "geometry": {"coordinates":[18.44201,42.5657],"type":"Point"}
}