{
  "type": "Feature",
  "properties": {
    "gn:admin1_code":"01",
    "gn:asciiname":"Dukanovina",
    "gn:country_code":"BA",
    "gn:dem":331,
    "gn:feature_class":"P",
    "gn:feature_code":"PPL",
    "gn:name":"Dukanovina",
    "gn:population":0,
    "gn:timezone":"Europe/Sarajevo",
    "iso:country":"BA",
    "wof:name":"Dukanovina",
    "wof:placetype":"locality"
},
  "geometry": {"coordinates":[18.39455,44.47209],"type":"Point"}
}