{
  "type": "Feature",
  "properties": {
    "gn:admin1_code":"01",
    "gn:asciiname":"Ivetici",
    "gn:country_code":"BA",
    "gn:dem":735,
    "gn:feature_class":"P",
    "gn:feature_code":"PPL",
    "gn:name":"Iveti\u0107i",
    "gn:population":0,
    "gn:timezone":"Europe/Sarajevo",
    "iso:country":"BA",
    "wof:name":"Ivetici",
    "wof:placetype":"locality"
},
  "geometry": {"coordinates":[16.66708,44.06356],"type":"Point"}
}