{
  "type": "Feature",
  "properties": {
    "gn:admin1_code":"02",
    "gn:asciiname":"Gradac",
    "gn:country_code":"BA",
    "gn:dem":649,
    "gn:feature_class":"P",
    "gn:feature_code":"PPLL",
    "gn:name":"Gradac",
    "gn:population":0,
    "gn:timezone":"Europe/Sarajevo",
    "iso:country":"BA",
    "wof:name":"Gradac",
    "wof:placetype":"locality"
},
  "geometry": {"coordinates":[18.75798,43.50767000000001],"type":"Point"}
}