{
  "type": "Feature",
  "properties": {
    "gn:admin1_code":"00",
    "gn:asciiname":"Jelasje",
    "gn:country_code":"BA",
    "gn:dem":731,
    "gn:feature_class":"P",
    "gn:feature_code":"PPL",
    "gn:name":"Jela\u0161je",
    "gn:population":0,
    "gn:timezone":"Europe/Sarajevo",
    "iso:country":"BA",
    "wof:name":"Jelasje",
    "wof:placetype":"locality"
},
  "geometry": {"coordinates":[18.45444,44.25972],"type":"Point"}
}