{
  "type": "Feature",
  "properties": {
    "gn:admin1_code":"02",
    "gn:asciiname":"Brest",
    "gn:country_code":"BA",
    "gn:dem":743,
    "gn:feature_class":"P",
    "gn:feature_code":"PPL",
    "gn:name":"Brest",
    "gn:population":0,
    "gn:timezone":"Europe/Sarajevo",
    "iso:country":"BA",
    "wof:name":"Brest",
    "wof:placetype":"locality"
},
  "geometry": {"coordinates":[19.03763,43.65482],"type":"Point"}
}