{
  "type": "Feature",
  "properties": {
    "gn:admin1_code":"02",
    "gn:asciiname":"Eraci",
    "gn:country_code":"BA",
    "gn:dem":932,
    "gn:feature_class":"P",
    "gn:feature_code":"PPL",
    "gn:name":"Era\u0107i",
    "gn:population":0,
    "gn:timezone":"Europe/Sarajevo",
    "iso:country":"BA",
    "wof:name":"Eraci",
    "wof:placetype":"locality"
},
  "geometry": {"coordinates":[17.0237,44.33706],"type":"Point"}
}