{
  "type": "Feature",
  "properties": {
    "gn:admin1_code":"01",
    "gn:asciiname":"Novo Naselje",
    "gn:country_code":"BA",
    "gn:dem":494,
    "gn:feature_class":"P",
    "gn:feature_code":"PPL",
    "gn:name":"Novo Naselje",
    "gn:population":0,
    "gn:timezone":"Europe/Sarajevo",
    "iso:country":"BA",
    "wof:name":"Novo Naselje",
    "wof:placetype":"locality"
},
  "geometry": {"coordinates":[17.68329,44.2112],"type":"Point"}
}