{
  "type": "Feature",
  "properties": {
    "gn:admin1_code":"01",
    "gn:asciiname":"Cavnik",
    "gn:country_code":"BA",
    "gn:dem":355,
    "gn:feature_class":"P",
    "gn:feature_code":"PPLL",
    "gn:name":"\u010cavnik",
    "gn:population":0,
    "gn:timezone":"Europe/Sarajevo",
    "iso:country":"BA",
    "wof:name":"Cavnik",
    "wof:placetype":"locality"
},
  "geometry": {"coordinates":[15.7776,44.90806],"type":"Point"}
}