{
  "type": "Feature",
  "properties": {
    "gn:admin1_code":"01",
    "gn:asciiname":"Kovaci",
    "gn:country_code":"BA",
    "gn:dem":881,
    "gn:feature_class":"P",
    "gn:feature_code":"PPL",
    "gn:name":"Kova\u010di",
    "gn:population":0,
    "gn:timezone":"Europe/Sarajevo",
    "iso:country":"BA",
    "wof:name":"Kovaci",
    "wof:placetype":"locality"
},
  "geometry": {"coordinates":[17.20006,43.66764000000001],"type":"Point"}
}