{
  "type": "Feature",
  "properties": {
    "gn:admin1_code":"02",
    "gn:asciiname":"Bogdanovica Brdo",
    "gn:country_code":"BA",
    "gn:dem":375,
    "gn:feature_class":"P",
    "gn:feature_code":"PPL",
    "gn:name":"Bogdanovi\u0107a Brdo",
    "gn:population":0,
    "gn:timezone":"Europe/Sarajevo",
    "iso:country":"BA",
    "wof:name":"Bogdanovica Brdo",
    "wof:placetype":"locality"
},
  "geometry": {"coordinates":[16.34382,44.86628],"type":"Point"}
}