{
  "type": "Feature",
  "properties": {
    "gn:admin1_code":"01",
    "gn:asciiname":"Podic",
    "gn:country_code":"BA",
    "gn:dem":912,
    "gn:feature_class":"P",
    "gn:feature_code":"PPLL",
    "gn:name":"Podi\u0107",
    "gn:population":0,
    "gn:timezone":"Europe/Sarajevo",
    "iso:country":"BA",
    "name:und_x_variant":[
        "Podi\u0107"
    ],
    "wof:name":"Podic",
    "wof:placetype":"locality"
},
  "geometry": {"coordinates":[16.55188,44.25529],"type":"Point"}
}