{
  "type": "Feature",
  "properties": {
    "gn:admin1_code":"01",
    "gn:asciiname":"Jelace",
    "gn:country_code":"BA",
    "gn:dem":836,
    "gn:feature_class":"P",
    "gn:feature_code":"PPL",
    "gn:name":"Jela\u010de",
    "gn:population":0,
    "gn:timezone":"Europe/Sarajevo",
    "iso:country":"BA",
    "name:bos_x_preferred":[
        "Jela\u010de"
    ],
    "name:fra_x_preferred":[
        "Jela\u010de"
    ],
    "name:hrv_x_preferred":[
        "Jela\u010de"
    ],
    "name:srp_x_preferred":[
        "\u0408\u0435\u043b\u0430\u0447\u0435"
    ],
    "name:und_x_variant":[
        "Jela\u010de"
    ],
    "wof:name":"Jelace",
    "wof:placetype":"locality"
},
  "geometry": {"coordinates":[17.56889,43.91861],"type":"Point"}
}