{
  "type": "Feature",
  "properties": {
    "gn:admin1_code":"01",
    "gn:asciiname":"Lozje",
    "gn:country_code":"BA",
    "gn:dem":342,
    "gn:feature_class":"P",
    "gn:feature_code":"PPL",
    "gn:name":"Lozje",
    "gn:population":0,
    "gn:timezone":"Europe/Sarajevo",
    "iso:country":"BA",
    "wof:name":"Lozje",
    "wof:placetype":"locality"
},
  "geometry": {"coordinates":[18.98806,43.67806],"type":"Point"}
}