{
  "type": "Feature",
  "properties": {
    "gn:admin1_code":"02",
    "gn:asciiname":"Greda",
    "gn:country_code":"BA",
    "gn:dem":88,
    "gn:feature_class":"P",
    "gn:feature_code":"PPL",
    "gn:name":"Greda",
    "gn:population":0,
    "gn:timezone":"Europe/Sarajevo",
    "iso:country":"BA",
    "name:bos_x_preferred":[
        "Greda"
    ],
    "name:ceb_x_preferred":[
        "Greda"
    ],
    "name:fra_x_preferred":[
        "Greda"
    ],
    "name:hrv_x_preferred":[
        "Greda"
    ],
    "name:hun_x_preferred":[
        "Greda"
    ],
    "name:nld_x_preferred":[
        "Greda"
    ],
    "name:slv_x_preferred":[
        "Greda"
    ],
    "name:srp_x_preferred":[
        "\u0413\u0440\u0435\u0434\u0430"
    ],
    "name:swe_x_preferred":[
        "Greda"
    ],
    "wof:name":"Greda",
    "wof:placetype":"locality"
},
  "geometry": {"coordinates":[17.32899,45.13892],"type":"Point"}
}