{
  "type": "Feature",
  "properties": {
    "gn:admin1_code":"01",
    "gn:asciiname":"Repovac",
    "gn:country_code":"BA",
    "gn:dem":1131,
    "gn:feature_class":"P",
    "gn:feature_code":"PPL",
    "gn:name":"Repovac",
    "gn:population":0,
    "gn:timezone":"Europe/Sarajevo",
    "iso:country":"BA",
    "wof:name":"Repovac",
    "wof:placetype":"locality"
},
  "geometry": {"coordinates":[16.65144,44.32194000000001],"type":"Point"}
}