{
  "type": "Feature",
  "properties": {
    "gn:admin1_code":"01",
    "gn:asciiname":"Repovac",
    "gn:country_code":"BA",
    "gn:dem":1131,
    "gn:feature_class":"P",
    "gn:feature_code":"PPL",
    "gn:name":"Repovac",
    "gn:population":0,
    "gn:timezone":"Europe/Sarajevo",
    "iso:country":"BA",
    "name:bos_x_preferred":[
        "Repovac"
    ],
    "name:bul_x_preferred":[
        "\u0420\u0435\u043f\u043e\u0432\u0430\u0446"
    ],
    "name:ceb_x_preferred":[
        "Repovac"
    ],
    "name:fra_x_preferred":[
        "Repovac"
    ],
    "name:hrv_x_preferred":[
        "Repovac"
    ],
    "name:rus_x_preferred":[
        "\u0420\u0435\u043f\u043e\u0432\u0430\u0446"
    ],
    "name:srp_x_preferred":[
        "\u0420\u0435\u043f\u043e\u0432\u0430\u0446"
    ],
    "name:swe_x_preferred":[
        "Repovac"
    ],
    "wof:name":"Repovac",
    "wof:placetype":"locality"
},
  "geometry": {"coordinates":[16.65144,44.32194000000001],"type":"Point"}
}