{
  "type": "Feature",
  "properties": {
    "gn:admin1_code":"01",
    "gn:asciiname":"Gotici",
    "gn:country_code":"BA",
    "gn:dem":855,
    "gn:feature_class":"P",
    "gn:feature_code":"PPL",
    "gn:name":"Goti\u0107i",
    "gn:population":0,
    "gn:timezone":"Europe/Sarajevo",
    "iso:country":"BA",
    "wof:name":"Gotici",
    "wof:placetype":"locality"
},
  "geometry": {"coordinates":[17.47784,44.27224],"type":"Point"}
}