{
  "type": "Feature",
  "properties": {
    "gn:admin1_code":"01",
    "gn:asciiname":"Gornji Ticici",
    "gn:country_code":"BA",
    "gn:dem":494,
    "gn:feature_class":"P",
    "gn:feature_code":"PPL",
    "gn:name":"Gornji Ti\u010di\u0107i",
    "gn:population":0,
    "gn:timezone":"Europe/Sarajevo",
    "iso:country":"BA",
    "wof:name":"Gornji Ticici",
    "wof:placetype":"locality"
},
  "geometry": {"coordinates":[18.0611,44.13724000000001],"type":"Point"}
}