{
  "type": "Feature",
  "properties": {
    "gn:admin1_code":"02",
    "gn:asciiname":"Lug",
    "gn:country_code":"BA",
    "gn:dem":132,
    "gn:feature_class":"P",
    "gn:feature_code":"PPL",
    "gn:name":"Lug",
    "gn:population":0,
    "gn:timezone":"Europe/Sarajevo",
    "iso:country":"BA",
    "wof:name":"Lug",
    "wof:placetype":"locality"
},
  "geometry": {"coordinates":[16.45056,45.12917],"type":"Point"}
}