{
  "type": "Feature",
  "properties": {
    "gn:admin1_code":"02",
    "gn:asciiname":"Tokanovici",
    "gn:country_code":"BA",
    "gn:dem":711,
    "gn:feature_class":"P",
    "gn:feature_code":"PPL",
    "gn:name":"Tokanovi\u0107i",
    "gn:population":0,
    "gn:timezone":"Europe/Sarajevo",
    "iso:country":"BA",
    "wof:name":"Tokanovici",
    "wof:placetype":"locality"
},
  "geometry": {"coordinates":[18.88875,44.33547],"type":"Point"}
}