{
  "type": "Feature",
  "properties": {
    "gn:admin1_code":"02",
    "gn:asciiname":"Pozarevo",
    "gn:country_code":"BA",
    "gn:dem":595,
    "gn:feature_class":"P",
    "gn:feature_code":"PPL",
    "gn:name":"Po\u017earevo",
    "gn:population":0,
    "gn:timezone":"Europe/Sarajevo",
    "iso:country":"BA",
    "wof:name":"Pozarevo",
    "wof:placetype":"locality"
},
  "geometry": {"coordinates":[18.85081,43.4893],"type":"Point"}
}