{
  "type": "Feature",
  "properties": {
    "gn:admin1_code":"01",
    "gn:asciiname":"Bucine",
    "gn:country_code":"BA",
    "gn:dem":76,
    "gn:feature_class":"P",
    "gn:feature_code":"PPL",
    "gn:name":"Bu\u010dine",
    "gn:population":0,
    "gn:timezone":"Europe/Sarajevo",
    "iso:country":"BA",
    "wof:name":"Bucine",
    "wof:placetype":"locality"
},
  "geometry": {"coordinates":[17.54528,43.175],"type":"Point"}
}