{
  "type": "Feature",
  "properties": {
    "gn:admin1_code":"01",
    "gn:asciiname":"Bucine",
    "gn:country_code":"BA",
    "gn:dem":76,
    "gn:feature_class":"P",
    "gn:feature_code":"PPL",
    "gn:name":"Bu\u010dine",
    "gn:population":0,
    "gn:timezone":"Europe/Sarajevo",
    "iso:country":"BA",
    "name:azb_x_preferred":[
        "\u0628\u0648\u0686\u06cc\u0646\u0647"
    ],
    "name:bcl_x_preferred":[
        "Bucine"
    ],
    "name:bel_x_preferred":[
        "\u0411\u0443\u0447\u044b\u043d\u044d"
    ],
    "name:bul_x_preferred":[
        "\u0411\u0443\u0447\u0438\u043d\u0435"
    ],
    "name:cat_x_preferred":[
        "Bucine"
    ],
    "name:ceb_x_preferred":[
        "Bucine"
    ],
    "name:ces_x_preferred":[
        "Bucine"
    ],
    "name:deu_x_preferred":[
        "Bucine"
    ],
    "name:epo_x_preferred":[
        "Bucine"
    ],
    "name:eus_x_preferred":[
        "Bucine"
    ],
    "name:fas_x_preferred":[
        "\u0628\u0648\u0686\u06cc\u0646\u0647"
    ],
    "name:fra_x_preferred":[
        "Bucine"
    ],
    "name:hun_x_preferred":[
        "Bucine"
    ],
    "name:hye_x_preferred":[
        "\u0532\u0578\u0582\u0579\u056b\u0576\u0565"
    ],
    "name:ita_x_preferred":[
        "Bucine"
    ],
    "name:jpn_x_preferred":[
        "\u30d6\u30fc\u30c1\u30cd"
    ],
    "name:kaz_x_preferred":[
        "\u0411\u0443\u0447\u0438\u043d\u0435"
    ],
    "name:kor_x_preferred":[
        "\ubd80\uce58\ub124"
    ],
    "name:lat_x_preferred":[
        "Bucinum"
    ],
    "name:lmo_x_preferred":[
        "Bucine"
    ],
    "name:msa_x_preferred":[
        "Bucine"
    ],
    "name:nap_x_preferred":[
        "Bucine"
    ],
    "name:nld_x_preferred":[
        "Bucine"
    ],
    "name:nor_x_preferred":[
        "Bucine"
    ],
    "name:pms_x_preferred":[
        "Bucine"
    ],
    "name:pol_x_preferred":[
        "Bucine"
    ],
    "name:por_x_preferred":[
        "Bucine"
    ],
    "name:ron_x_preferred":[
        "Bucine"
    ],
    "name:rus_x_preferred":[
        "\u0411\u0443\u0447\u0438\u043d\u0435"
    ],
    "name:scn_x_preferred":[
        "Bucine"
    ],
    "name:spa_x_preferred":[
        "Bucine"
    ],
    "name:srp_x_preferred":[
        "\u0411\u0443\u0447\u0438\u043d\u0435"
    ],
    "name:tgl_x_preferred":[
        "Bucine"
    ],
    "name:tur_x_preferred":[
        "Bucine"
    ],
    "name:ukr_x_preferred":[
        "\u0411\u0443\u0447\u0438\u043d\u0435"
    ],
    "name:uzb_x_preferred":[
        "Bucine"
    ],
    "name:vec_x_preferred":[
        "Bucine"
    ],
    "name:vie_x_preferred":[
        "Bucine"
    ],
    "name:vol_x_preferred":[
        "Bucine"
    ],
    "name:war_x_preferred":[
        "Bucine"
    ],
    "name:zho_x_preferred":[
        "\u5e03\u5947\u5185"
    ],
    "wof:name":"Bucine",
    "wof:placetype":"locality"
},
  "geometry": {"coordinates":[17.54528,43.175],"type":"Point"}
}