{
  "type": "Feature",
  "properties": {
    "gn:admin1_code":"02",
    "gn:asciiname":"Kovacevici",
    "gn:country_code":"BA",
    "gn:dem":228,
    "gn:feature_class":"P",
    "gn:feature_code":"PPL",
    "gn:name":"Kova\u010devi\u0107i",
    "gn:population":0,
    "gn:timezone":"Europe/Sarajevo",
    "iso:country":"BA",
    "wof:name":"Kovacevici",
    "wof:placetype":"locality"
},
  "geometry": {"coordinates":[17.87518,44.90948],"type":"Point"}
}