{
  "type": "Feature",
  "properties": {
    "gn:admin1_code":"01",
    "gn:asciiname":"Mihaljevici",
    "gn:country_code":"BA",
    "gn:dem":978,
    "gn:feature_class":"P",
    "gn:feature_code":"PPL",
    "gn:name":"Mihaljevi\u0107i",
    "gn:population":0,
    "gn:timezone":"Europe/Sarajevo",
    "iso:country":"BA",
    "wof:name":"Mihaljevici",
    "wof:placetype":"locality"
},
  "geometry": {"coordinates":[17.105,43.78694],"type":"Point"}
}