{
  "type": "Feature",
  "properties": {
    "gn:admin1_code":"02",
    "gn:asciiname":"Begici",
    "gn:country_code":"BA",
    "gn:dem":592,
    "gn:feature_class":"P",
    "gn:feature_code":"PPL",
    "gn:name":"Begi\u0107i",
    "gn:population":0,
    "gn:timezone":"Europe/Sarajevo",
    "iso:country":"BA",
    "wof:name":"Begici",
    "wof:placetype":"locality"
},
  "geometry": {"coordinates":[18.95733,44.20143],"type":"Point"}
}