{
  "type": "Feature",
  "properties": {
    "gn:admin1_code":"02",
    "gn:asciiname":"Bogovici",
    "gn:country_code":"BA",
    "gn:dem":688,
    "gn:feature_class":"P",
    "gn:feature_code":"PPL",
    "gn:name":"Bogovi\u0107i",
    "gn:population":0,
    "gn:timezone":"Europe/Sarajevo",
    "iso:country":"BA",
    "wof:name":"Bogovici",
    "wof:placetype":"locality"
},
  "geometry": {"coordinates":[17.13552,44.5159],"type":"Point"}
}