{
  "type": "Feature",
  "properties": {
    "gn:admin1_code":"02",
    "gn:asciiname":"Javorac",
    "gn:country_code":"BA",
    "gn:dem":558,
    "gn:feature_class":"P",
    "gn:feature_code":"PPL",
    "gn:name":"Javorac",
    "gn:population":0,
    "gn:timezone":"Europe/Sarajevo",
    "iso:country":"BA",
    "wof:name":"Javorac",
    "wof:placetype":"locality"
},
  "geometry": {"coordinates":[17.06943,44.96825],"type":"Point"}
}