{
  "type": "Feature",
  "properties": {
    "gn:admin1_code":"01",
    "gn:asciiname":"Brajkovici",
    "gn:country_code":"BA",
    "gn:dem":15,
    "gn:feature_class":"P",
    "gn:feature_code":"PPL",
    "gn:name":"Brajkovi\u0107i",
    "gn:population":0,
    "gn:timezone":"Europe/Sarajevo",
    "iso:country":"BA",
    "wof:name":"Brajkovici",
    "wof:placetype":"locality"
},
  "geometry": {"coordinates":[17.69486000000001,43.10187],"type":"Point"}
}