{
  "type": "Feature",
  "properties": {
    "gn:admin1_code":"02",
    "gn:asciiname":"Grabovica",
    "gn:country_code":"BA",
    "gn:dem":201,
    "gn:feature_class":"P",
    "gn:feature_code":"PPL",
    "gn:name":"Grabovica",
    "gn:population":0,
    "gn:timezone":"Europe/Sarajevo",
    "iso:country":"BA",
    "wof:name":"Grabovica",
    "wof:placetype":"locality"
},
  "geometry": {"coordinates":[16.94278,44.91583],"type":"Point"}
}