{
  "type": "Feature",
  "properties": {
    "gn:admin1_code":"02",
    "gn:asciiname":"Mikici",
    "gn:country_code":"BA",
    "gn:dem":323,
    "gn:feature_class":"P",
    "gn:feature_code":"PPL",
    "gn:name":"Miki\u0107i",
    "gn:population":0,
    "gn:timezone":"Europe/Sarajevo",
    "iso:country":"BA",
    "wof:name":"Mikici",
    "wof:placetype":"locality"
},
  "geometry": {"coordinates":[17.24391,44.66396],"type":"Point"}
}