{
  "type": "Feature",
  "properties": {
    "gn:admin1_code":"02",
    "gn:asciiname":"Mali Kolari",
    "gn:country_code":"BA",
    "gn:dem":531,
    "gn:feature_class":"P",
    "gn:feature_code":"PPL",
    "gn:name":"Mali Kolari",
    "gn:population":0,
    "gn:timezone":"Europe/Sarajevo",
    "iso:country":"BA",
    "wof:name":"Mali Kolari",
    "wof:placetype":"locality"
},
  "geometry": {"coordinates":[19.50556,44.00556],"type":"Point"}
}