{
  "type": "Feature",
  "properties": {
    "gn:admin1_code":"01",
    "gn:asciiname":"Vukicevici",
    "gn:country_code":"BA",
    "gn:dem":139,
    "gn:feature_class":"P",
    "gn:feature_code":"PPL",
    "gn:name":"Vuki\u010devi\u0107i",
    "gn:population":0,
    "gn:timezone":"Europe/Sarajevo",
    "iso:country":"BA",
    "wof:name":"Vukicevici",
    "wof:placetype":"locality"
},
  "geometry": {"coordinates":[17.97967000000001,43.05079],"type":"Point"}
}