{
  "type": "Feature",
  "properties": {
    "gn:admin1_code":"02",
    "gn:asciiname":"Jusupovici",
    "gn:country_code":"BA",
    "gn:dem":963,
    "gn:feature_class":"P",
    "gn:feature_code":"PPL",
    "gn:name":"Jusupovi\u0107i",
    "gn:population":0,
    "gn:timezone":"Europe/Sarajevo",
    "iso:country":"BA",
    "wof:name":"Jusupovici",
    "wof:placetype":"locality"
},
  "geometry": {"coordinates":[19.05074,44.04576],"type":"Point"}
}