{
  "type": "Feature",
  "properties": {
    "gn:admin1_code":"02",
    "gn:asciiname":"Glusca",
    "gn:country_code":"BA",
    "gn:dem":1080,
    "gn:feature_class":"P",
    "gn:feature_code":"PPL",
    "gn:name":"Glu\u0161ca",
    "gn:population":0,
    "gn:timezone":"Europe/Sarajevo",
    "iso:country":"BA",
    "name:und_x_variant":[
        "Glu\u0161ca"
    ],
    "wof:name":"Glusca",
    "wof:placetype":"locality"
},
  "geometry": {"coordinates":[18.63046,43.59564],"type":"Point"}
}