{
  "type": "Feature",
  "properties": {
    "gn:admin1_code":"01",
    "gn:asciiname":"Vis",
    "gn:country_code":"BA",
    "gn:dem":476,
    "gn:feature_class":"P",
    "gn:feature_code":"PPL",
    "gn:name":"Vis",
    "gn:population":0,
    "gn:timezone":"Europe/Sarajevo",
    "iso:country":"BA",
    "name:bel_x_preferred":[
        "\u0412\u0456\u0441"
    ],
    "name:bos_x_preferred":[
        "Vis"
    ],
    "name:bul_x_preferred":[
        "\u0412\u0438\u0441"
    ],
    "name:ceb_x_preferred":[
        "Vis"
    ],
    "name:deu_x_preferred":[
        "Vis"
    ],
    "name:fin_x_preferred":[
        "Vis"
    ],
    "name:fra_x_preferred":[
        "Vis"
    ],
    "name:hun_x_preferred":[
        "Vis"
    ],
    "name:hye_x_preferred":[
        "\u054e\u056b\u057d"
    ],
    "name:nld_x_preferred":[
        "Vis"
    ],
    "name:pol_x_preferred":[
        "Vis"
    ],
    "name:ron_x_preferred":[
        "Vis"
    ],
    "name:rus_x_preferred":[
        "\u0412\u0438\u0441"
    ],
    "name:slk_x_preferred":[
        "Vis"
    ],
    "name:slv_x_preferred":[
        "Vis"
    ],
    "name:spa_x_preferred":[
        "Vis"
    ],
    "name:srp_x_preferred":[
        "\u0412\u0438\u0441"
    ],
    "name:swe_x_preferred":[
        "Vis"
    ],
    "name:ukr_x_preferred":[
        "\u0412\u0456\u0441"
    ],
    "wof:name":"Vis",
    "wof:placetype":"locality"
},
  "geometry": {"coordinates":[18.17465,44.53489],"type":"Point"}
}