{
  "type": "Feature",
  "properties": {
    "gn:admin1_code":"01",
    "gn:asciiname":"Vis",
    "gn:country_code":"BA",
    "gn:dem":476,
    "gn:feature_class":"P",
    "gn:feature_code":"PPL",
    "gn:name":"Vis",
    "gn:population":0,
    "gn:timezone":"Europe/Sarajevo",
    "iso:country":"BA",
    "wof:name":"Vis",
    "wof:placetype":"locality"
},
  "geometry": {"coordinates":[18.17465,44.53489],"type":"Point"}
}