{
  "type": "Feature",
  "properties": {
    "gn:admin1_code":"02",
    "gn:asciiname":"Poljanci",
    "gn:country_code":"BA",
    "gn:dem":637,
    "gn:feature_class":"P",
    "gn:feature_code":"PPL",
    "gn:name":"Poljanci",
    "gn:population":0,
    "gn:timezone":"Europe/Sarajevo",
    "iso:country":"BA",
    "wof:name":"Poljanci",
    "wof:placetype":"locality"
},
  "geometry": {"coordinates":[17.13664,44.50296],"type":"Point"}
}