{
  "type": "Feature",
  "properties": {
    "gn:admin1_code":"01",
    "gn:asciiname":"Nezirovici",
    "gn:country_code":"BA",
    "gn:dem":481,
    "gn:feature_class":"P",
    "gn:feature_code":"PPL",
    "gn:name":"Nezirovi\u0107i",
    "gn:population":0,
    "gn:timezone":"Europe/Sarajevo",
    "iso:country":"BA",
    "name:bos_x_preferred":[
        "Nezirovi\u0107i"
    ],
    "name:ceb_x_preferred":[
        "Nezirovi\u0107i"
    ],
    "name:fra_x_preferred":[
        "Nezirovi\u0107i"
    ],
    "name:hrv_x_preferred":[
        "Nezirovi\u0107i"
    ],
    "name:swe_x_preferred":[
        "Nezirovi\u0107i"
    ],
    "wof:name":"Nezirovici",
    "wof:placetype":"locality"
},
  "geometry": {"coordinates":[17.93604,44.07881],"type":"Point"}
}