{
  "type": "Feature",
  "properties": {
    "gn:admin1_code":"01",
    "gn:asciiname":"Kosica",
    "gn:country_code":"BA",
    "gn:dem":208,
    "gn:feature_class":"P",
    "gn:feature_code":"PPL",
    "gn:name":"Kosica",
    "gn:population":0,
    "gn:timezone":"Europe/Sarajevo",
    "iso:country":"BA",
    "wof:name":"Kosica",
    "wof:placetype":"locality"
},
  "geometry": {"coordinates":[18.46328,44.7397],"type":"Point"}
}