{
  "type": "Feature",
  "properties": {
    "gn:admin1_code":"01",
    "gn:asciiname":"Gornja Bukovica",
    "gn:country_code":"BA",
    "gn:dem":507,
    "gn:feature_class":"P",
    "gn:feature_code":"PPLL",
    "gn:name":"Gornja Bukovica",
    "gn:population":0,
    "gn:timezone":"Europe/Sarajevo",
    "iso:country":"BA",
    "name:bos_x_preferred":[
        "Gornja Bukovica"
    ],
    "name:fra_x_preferred":[
        "Gornja Bukovica"
    ],
    "name:und_x_variant":[
        "Bukovica Gornja",
        "Gornja Bukovica"
    ],
    "wof:name":"Gornja Bukovica",
    "wof:placetype":"locality"
},
  "geometry": {"coordinates":[18.23703,44.55181],"type":"Point"}
}