{
  "type": "Feature",
  "properties": {
    "gn:admin1_code":"02",
    "gn:asciiname":"Dulici",
    "gn:country_code":"BA",
    "gn:dem":372,
    "gn:feature_class":"P",
    "gn:feature_code":"PPLL",
    "gn:name":"\u00d0uli\u0107i",
    "gn:population":0,
    "gn:timezone":"Europe/Sarajevo",
    "iso:country":"BA",
    "wof:name":"Dulici",
    "wof:placetype":"locality"
},
  "geometry": {"coordinates":[17.47752,44.53364000000001],"type":"Point"}
}