{
  "type": "Feature",
  "properties": {
    "gn:admin1_code":"02",
    "gn:asciiname":"Kitanovici",
    "gn:country_code":"BA",
    "gn:dem":275,
    "gn:feature_class":"P",
    "gn:feature_code":"PPL",
    "gn:name":"Kitanovi\u0107i",
    "gn:population":0,
    "gn:timezone":"Europe/Sarajevo",
    "iso:country":"BA",
    "wof:name":"Kitanovici",
    "wof:placetype":"locality"
},
  "geometry": {"coordinates":[17.87472,44.54381],"type":"Point"}
}