{
  "type": "Feature",
  "properties": {
    "gn:admin1_code":"01",
    "gn:asciiname":"Donji Mamici",
    "gn:country_code":"BA",
    "gn:dem":388,
    "gn:feature_class":"P",
    "gn:feature_code":"PPLL",
    "gn:name":"Donji Mami\u0107i",
    "gn:population":0,
    "gn:timezone":"Europe/Sarajevo",
    "iso:country":"BA",
    "name:und_x_variant":[
        "Donji Mami\u0107i"
    ],
    "wof:name":"Donji Mamici",
    "wof:placetype":"locality"
},
  "geometry": {"coordinates":[17.47919,43.34695],"type":"Point"}
}