{
  "type": "Feature",
  "properties": {
    "gn:admin1_code":"01",
    "gn:asciiname":"Donji Mamici",
    "gn:country_code":"BA",
    "gn:dem":388,
    "gn:feature_class":"P",
    "gn:feature_code":"PPLL",
    "gn:name":"Donji Mami\u0107i",
    "gn:population":0,
    "gn:timezone":"Europe/Sarajevo",
    "iso:country":"BA",
    "name:bos_x_preferred":[
        "Donji Mami\u0107i"
    ],
    "name:ell_x_preferred":[
        "\u039d\u03c4\u03cc\u03bd\u03b9 \u039c\u03ac\u03bc\u03b9\u03c4\u03c3\u03b9"
    ],
    "name:fra_x_preferred":[
        "Donji Mami\u0107i"
    ],
    "name:hrv_x_preferred":[
        "Donji Mami\u0107i"
    ],
    "name:srp_x_preferred":[
        "\u0414\u043e\u045a\u0438 \u041c\u0430\u043c\u0438\u045b\u0438"
    ],
    "wof:name":"Donji Mamici",
    "wof:placetype":"locality"
},
  "geometry": {"coordinates":[17.47919,43.34695],"type":"Point"}
}