{
  "type": "Feature",
  "properties": {
    "gn:admin1_code":"02",
    "gn:asciiname":"Nistavci",
    "gn:country_code":"BA",
    "gn:dem":150,
    "gn:feature_class":"P",
    "gn:feature_code":"PPL",
    "gn:name":"Ni\u0161tavci",
    "gn:population":0,
    "gn:timezone":"Europe/Sarajevo",
    "iso:country":"BA",
    "name:und_x_variant":[
        "Ni\u0161tovci",
        "Ni\u0161tavci"
    ],
    "wof:name":"Nistavci",
    "wof:placetype":"locality"
},
  "geometry": {"coordinates":[16.71575,44.88089],"type":"Point"}
}