{
  "type": "Feature",
  "properties": {
    "gn:admin1_code":"02",
    "gn:asciiname":"Gornje Brdo",
    "gn:country_code":"BA",
    "gn:dem":233,
    "gn:feature_class":"P",
    "gn:feature_code":"PPL",
    "gn:name":"Gornje Brdo",
    "gn:population":0,
    "gn:timezone":"Europe/Sarajevo",
    "iso:country":"BA",
    "wof:name":"Gornje Brdo",
    "wof:placetype":"locality"
},
  "geometry": {"coordinates":[16.91675,45.08886],"type":"Point"}
}