{
  "type": "Feature",
  "properties": {
    "gn:admin1_code":"02",
    "gn:asciiname":"Podkorjen",
    "gn:country_code":"BA",
    "gn:dem":628,
    "gn:feature_class":"P",
    "gn:feature_code":"PPL",
    "gn:name":"Podkorjen",
    "gn:population":0,
    "gn:timezone":"Europe/Sarajevo",
    "iso:country":"BA",
    "wof:name":"Podkorjen",
    "wof:placetype":"locality"
},
  "geometry": {"coordinates":[19.42271,44.0633],"type":"Point"}
}