{
  "type": "Feature",
  "properties": {
    "gn:admin1_code":"02",
    "gn:asciiname":"Blace",
    "gn:country_code":"BA",
    "gn:dem":522,
    "gn:feature_class":"P",
    "gn:feature_code":"PPLL",
    "gn:name":"Blace",
    "gn:population":0,
    "gn:timezone":"Europe/Sarajevo",
    "iso:country":"BA",
    "name:ara_x_preferred":[
        "\u0628\u0644\u0627\u062a\u0633\u064a"
    ],
    "name:deu_x_preferred":[
        "Blace"
    ],
    "name:fra_x_preferred":[
        "Blace"
    ],
    "name:hrv_x_preferred":[
        "Blace"
    ],
    "name:ita_x_preferred":[
        "Blace"
    ],
    "name:msa_x_preferred":[
        "Blace"
    ],
    "name:nld_x_preferred":[
        "Blace"
    ],
    "name:pnb_x_preferred":[
        "\u0628\u0644\u0627\u0686\u06d2"
    ],
    "name:pol_x_preferred":[
        "Blace"
    ],
    "name:por_x_preferred":[
        "Blace"
    ],
    "name:rus_x_preferred":[
        "\u0411\u043b\u0430\u0446\u0435"
    ],
    "name:slv_x_preferred":[
        "Blace"
    ],
    "name:sqi_x_preferred":[
        "Bllaca"
    ],
    "name:srp_x_preferred":[
        "\u0411\u043b\u0430\u0446\u0435"
    ],
    "name:tur_x_preferred":[
        "Blace"
    ],
    "name:zho_x_preferred":[
        "\u5e03\u62c9\u91c7"
    ],
    "wof:name":"Blace",
    "wof:placetype":"locality"
},
  "geometry": {"coordinates":[19.22619,43.88441],"type":"Point"}
}