{
  "type": "Feature",
  "properties": {
    "gn:admin1_code":"02",
    "gn:asciiname":"Palackovici",
    "gn:country_code":"BA",
    "gn:dem":365,
    "gn:feature_class":"P",
    "gn:feature_code":"PPL",
    "gn:name":"Pala\u010dkovi\u0107i",
    "gn:population":0,
    "gn:timezone":"Europe/Sarajevo",
    "iso:country":"BA",
    "wof:name":"Palackovici",
    "wof:placetype":"locality"
},
  "geometry": {"coordinates":[16.98748,44.73813],"type":"Point"}
}