{
  "type": "Feature",
  "properties": {
    "gn:admin1_code":"02",
    "gn:asciiname":"Ribalj Teg",
    "gn:country_code":"BA",
    "gn:dem":1187,
    "gn:feature_class":"P",
    "gn:feature_code":"PPL",
    "gn:name":"Ribalj Teg",
    "gn:population":0,
    "gn:timezone":"Europe/Sarajevo",
    "iso:country":"BA",
    "wof:name":"Ribalj Teg",
    "wof:placetype":"locality"
},
  "geometry": {"coordinates":[18.30892,43.26567],"type":"Point"}
}