{
  "type": "Feature",
  "properties": {
    "gn:admin1_code":"02",
    "gn:asciiname":"Puskovac",
    "gn:country_code":"BA",
    "gn:dem":243,
    "gn:feature_class":"P",
    "gn:feature_code":"PPLL",
    "gn:name":"Pu\u0161kovac",
    "gn:population":0,
    "gn:timezone":"Europe/Sarajevo",
    "iso:country":"BA",
    "wof:name":"Puskovac",
    "wof:placetype":"locality"
},
  "geometry": {"coordinates":[18.90638,44.69278],"type":"Point"}
}