{
  "type": "Feature",
  "properties": {
    "gn:admin1_code":"02",
    "gn:asciiname":"Poljice",
    "gn:country_code":"BA",
    "gn:dem":227,
    "gn:feature_class":"P",
    "gn:feature_code":"PPL",
    "gn:name":"Poljice",
    "gn:population":0,
    "gn:timezone":"Europe/Sarajevo",
    "iso:country":"BA",
    "wof:name":"Poljice",
    "wof:placetype":"locality"
},
  "geometry": {"coordinates":[17.14898,44.67169000000001],"type":"Point"}
}