{
  "type": "Feature",
  "properties": {
    "gn:admin1_code":"02",
    "gn:asciiname":"Bodirogici",
    "gn:country_code":"BA",
    "gn:dem":340,
    "gn:feature_class":"P",
    "gn:feature_code":"PPL",
    "gn:name":"Bodirogi\u0107i",
    "gn:population":0,
    "gn:timezone":"Europe/Sarajevo",
    "iso:country":"BA",
    "wof:name":"Bodirogici",
    "wof:placetype":"locality"
},
  "geometry": {"coordinates":[18.87286,44.37625],"type":"Point"}
}