{
  "type": "Feature",
  "properties": {
    "gn:admin1_code":"02",
    "gn:asciiname":"Gornja Vranjkovina",
    "gn:country_code":"BA",
    "gn:dem":328,
    "gn:feature_class":"P",
    "gn:feature_code":"PPL",
    "gn:name":"Gornja Vranjkovina",
    "gn:population":0,
    "gn:timezone":"Europe/Sarajevo",
    "iso:country":"BA",
    "wof:name":"Gornja Vranjkovina",
    "wof:placetype":"locality"
},
  "geometry": {"coordinates":[19.59134,44.05926],"type":"Point"}
}