{
  "type": "Feature",
  "properties": {
    "gn:admin1_code":"01",
    "gn:asciiname":"Bukva",
    "gn:country_code":"BA",
    "gn:dem":686,
    "gn:feature_class":"P",
    "gn:feature_code":"PPL",
    "gn:name":"Bukva",
    "gn:population":0,
    "gn:timezone":"Europe/Sarajevo",
    "iso:country":"BA",
    "wof:name":"Bukva",
    "wof:placetype":"locality"
},
  "geometry": {"coordinates":[18.10216,43.90068],"type":"Point"}
}