{
  "type": "Feature",
  "properties": {
    "gn:admin1_code":"01",
    "gn:asciiname":"Stita",
    "gn:country_code":"BA",
    "gn:dem":807,
    "gn:feature_class":"P",
    "gn:feature_code":"PPL",
    "gn:name":"\u0160tita",
    "gn:population":0,
    "gn:timezone":"Europe/Sarajevo",
    "iso:country":"BA",
    "wof:name":"Stita",
    "wof:placetype":"locality"
},
  "geometry": {"coordinates":[18.88277,43.65022],"type":"Point"}
}