{
  "type": "Feature",
  "properties": {
    "gn:admin1_code":"01",
    "gn:asciiname":"Doline",
    "gn:country_code":"BA",
    "gn:dem":804,
    "gn:feature_class":"P",
    "gn:feature_code":"PPL",
    "gn:name":"Doline",
    "gn:population":0,
    "gn:timezone":"Europe/Sarajevo",
    "iso:country":"BA",
    "name:fra_x_preferred":[
        "Doline"
    ],
    "wof:name":"Doline",
    "wof:placetype":"locality"
},
  "geometry": {"coordinates":[16.15126,44.65324],"type":"Point"}
}