{
  "type": "Feature",
  "properties": {
    "gn:admin1_code":"01",
    "gn:asciiname":"Doline",
    "gn:country_code":"BA",
    "gn:dem":804,
    "gn:feature_class":"P",
    "gn:feature_code":"PPL",
    "gn:name":"Doline",
    "gn:population":0,
    "gn:timezone":"Europe/Sarajevo",
    "iso:country":"BA",
    "name:ara_x_preferred":[
        "\u062f\u0648\u0644\u064a\u0646"
    ],
    "name:ben_x_preferred":[
        "\u09a1\u09cb\u09b2\u09bf\u09a8"
    ],
    "name:ell_x_preferred":[
        "\u039d\u03c4\u03bf\u03bb\u03af\u03bd"
    ],
    "name:fra_x_preferred":[
        "Doline"
    ],
    "name:hin_x_preferred":[
        "\u0921\u094b\u0932\u0940\u0928"
    ],
    "name:hun_x_preferred":[
        "Doline"
    ],
    "name:ind_x_preferred":[
        "Doline"
    ],
    "name:ita_x_preferred":[
        "D\u00e9l\u0131\u0328n\u0119"
    ],
    "name:jpn_x_preferred":[
        "\u30c9\u30ea\u30f3"
    ],
    "name:kor_x_preferred":[
        "\ub3cc\ub9b0"
    ],
    "name:pol_x_preferred":[
        "Doline"
    ],
    "name:rus_x_preferred":[
        "\u0414\u0435\u0439\u043b\u0438\u043d\u0435"
    ],
    "name:tur_x_preferred":[
        "Doline"
    ],
    "name:urd_x_preferred":[
        "\u0688\u0648\u0644\u0627\u0626\u0646"
    ],
    "name:vie_x_preferred":[
        "Doline"
    ],
    "wof:name":"Doline",
    "wof:placetype":"locality"
},
  "geometry": {"coordinates":[16.15126,44.65324],"type":"Point"}
}