{
  "type": "Feature",
  "properties": {
    "gn:admin1_code":"01",
    "gn:asciiname":"Donji Azapovici",
    "gn:country_code":"BA",
    "gn:dem":576,
    "gn:feature_class":"P",
    "gn:feature_code":"PPL",
    "gn:name":"Donji Azapovi\u0107i",
    "gn:population":0,
    "gn:timezone":"Europe/Sarajevo",
    "iso:country":"BA",
    "wof:name":"Donji Azapovici",
    "wof:placetype":"locality"
},
  "geometry": {"coordinates":[18.16222,43.88417000000001],"type":"Point"}
}