{
  "type": "Feature",
  "properties": {
    "gn:admin1_code":"01",
    "gn:asciiname":"Podhum",
    "gn:country_code":"BA",
    "gn:dem":432,
    "gn:feature_class":"P",
    "gn:feature_code":"PPL",
    "gn:name":"Podhum",
    "gn:population":0,
    "gn:timezone":"Europe/Sarajevo",
    "iso:country":"BA",
    "wof:name":"Podhum",
    "wof:placetype":"locality"
},
  "geometry": {"coordinates":[17.81981,43.75182],"type":"Point"}
}