{
  "type": "Feature",
  "properties": {
    "gn:admin1_code":"01",
    "gn:asciiname":"Tasovcici",
    "gn:country_code":"BA",
    "gn:dem":17,
    "gn:feature_class":"P",
    "gn:feature_code":"PPL",
    "gn:name":"Tasov\u010di\u0107i",
    "gn:population":2007,
    "gn:timezone":"Europe/Sarajevo",
    "iso:country":"BA",
    "name:bos_x_preferred":[
        "Tasov\u010di\u0107i"
    ],
    "name:ceb_x_preferred":[
        "Tasov\u010di\u0107i"
    ],
    "name:fra_x_preferred":[
        "Tasov\u010di\u0107i"
    ],
    "name:hrv_x_preferred":[
        "Tasov\u010di\u0107i"
    ],
    "name:spa_x_preferred":[
        "Tasov\u010di\u0107i"
    ],
    "name:srp_x_preferred":[
        "\u0422\u0430\u0441\u043e\u0432\u0447\u0438\u045b\u0438"
    ],
    "name:swe_x_preferred":[
        "Tasov\u010di\u0107i"
    ],
    "name:und_x_variant":[
        "Tasov\u010di\u0107i"
    ],
    "wof:name":"Tasovcici",
    "wof:placetype":"locality",
    "wof:population":2007
},
  "geometry": {"coordinates":[17.72,43.11333],"type":"Point"}
}