{
  "type": "Feature",
  "properties": {
    "gn:admin1_code":"01",
    "gn:asciiname":"Gornji Lucani",
    "gn:country_code":"BA",
    "gn:dem":459,
    "gn:feature_class":"P",
    "gn:feature_code":"PPL",
    "gn:name":"Gornji Lu\u010dani",
    "gn:population":0,
    "gn:timezone":"Europe/Sarajevo",
    "iso:country":"BA",
    "name:bos_x_preferred":[
        "Gornji Lu\u010dani"
    ],
    "name:ceb_x_preferred":[
        "Gornji Lu\u010dani"
    ],
    "name:fra_x_preferred":[
        "Gornji Lu\u010dani"
    ],
    "name:hrv_x_preferred":[
        "Gornji Lu\u010dani"
    ],
    "name:srp_x_preferred":[
        "\u0413\u043e\u0440\u045a\u0438 \u041b\u0443\u0447\u0430\u043d\u0438"
    ],
    "name:swe_x_preferred":[
        "Gornji Lu\u010dani"
    ],
    "wof:name":"Gornji Lucani",
    "wof:placetype":"locality"
},
  "geometry": {"coordinates":[17.98837,44.13718],"type":"Point"}
}