{
  "type": "Feature",
  "properties": {
    "gn:admin1_code":"01",
    "gn:asciiname":"Gornji Lucani",
    "gn:country_code":"BA",
    "gn:dem":459,
    "gn:feature_class":"P",
    "gn:feature_code":"PPL",
    "gn:name":"Gornji Lu\u010dani",
    "gn:population":0,
    "gn:timezone":"Europe/Sarajevo",
    "iso:country":"BA",
    "name:und_x_variant":[
        "Gornji Lu\u010dani"
    ],
    "wof:name":"Gornji Lucani",
    "wof:placetype":"locality"
},
  "geometry": {"coordinates":[17.98837,44.13718],"type":"Point"}
}