{
  "type": "Feature",
  "properties": {
    "gn:admin1_code":"02",
    "gn:asciiname":"Sahmani",
    "gn:country_code":"BA",
    "gn:dem":169,
    "gn:feature_class":"P",
    "gn:feature_code":"PPL",
    "gn:name":"\u0160ahmani",
    "gn:population":0,
    "gn:timezone":"Europe/Sarajevo",
    "iso:country":"BA",
    "wof:name":"Sahmani",
    "wof:placetype":"locality"
},
  "geometry": {"coordinates":[19.1251,44.32122],"type":"Point"}
}