{
  "type": "Feature",
  "properties": {
    "gn:admin1_code":"02",
    "gn:asciiname":"Gudura",
    "gn:country_code":"BA",
    "gn:dem":233,
    "gn:feature_class":"P",
    "gn:feature_code":"PPL",
    "gn:name":"Gudura",
    "gn:population":0,
    "gn:timezone":"Europe/Sarajevo",
    "iso:country":"BA",
    "wof:name":"Gudura",
    "wof:placetype":"locality"
},
  "geometry": {"coordinates":[19.13127,44.57432],"type":"Point"}
}