{
  "type": "Feature",
  "properties": {
    "gn:admin1_code":"02",
    "gn:asciiname":"Zaovista",
    "gn:country_code":"BA",
    "gn:dem":848,
    "gn:feature_class":"P",
    "gn:feature_code":"PPL",
    "gn:name":"Zaovista",
    "gn:population":0,
    "gn:timezone":"Europe/Sarajevo",
    "iso:country":"BA",
    "wof:name":"Zaovista",
    "wof:placetype":"locality"
},
  "geometry": {"coordinates":[18.13398,43.07322],"type":"Point"}
}