{
  "type": "Feature",
  "properties": {
    "gn:admin1_code":"02",
    "gn:asciiname":"Sarani",
    "gn:country_code":"BA",
    "gn:dem":708,
    "gn:feature_class":"P",
    "gn:feature_code":"PPL",
    "gn:name":"\u0160arani",
    "gn:population":0,
    "gn:timezone":"Europe/Sarajevo",
    "iso:country":"BA",
    "wof:name":"Sarani",
    "wof:placetype":"locality"
},
  "geometry": {"coordinates":[18.24115,42.81296],"type":"Point"}
}