{
  "type": "Feature",
  "properties": {
    "gn:admin1_code":"01",
    "gn:asciiname":"Kostajnica",
    "gn:country_code":"BA",
    "gn:dem":341,
    "gn:feature_class":"P",
    "gn:feature_code":"PPL",
    "gn:name":"Kostajnica",
    "gn:population":0,
    "gn:timezone":"Europe/Sarajevo",
    "iso:country":"BA",
    "wof:name":"Kostajnica",
    "wof:placetype":"locality"
},
  "geometry": {"coordinates":[17.80907000000001,43.71664000000001],"type":"Point"}
}