{
  "type": "Feature",
  "properties": {
    "gn:admin1_code":"01",
    "gn:asciiname":"Kostajnica",
    "gn:country_code":"BA",
    "gn:dem":341,
    "gn:feature_class":"P",
    "gn:feature_code":"PPL",
    "gn:name":"Kostajnica",
    "gn:population":0,
    "gn:timezone":"Europe/Sarajevo",
    "iso:country":"BA",
    "name:bos_x_preferred":[
        "Kostajnica"
    ],
    "name:ceb_x_preferred":[
        "Kostajnica"
    ],
    "name:deu_x_preferred":[
        "Kostajnica"
    ],
    "name:fra_x_preferred":[
        "Kostajnica"
    ],
    "name:hrv_x_preferred":[
        "Kostajnica"
    ],
    "name:ita_x_preferred":[
        "Kostajnica"
    ],
    "name:nld_x_preferred":[
        "Kostajnica"
    ],
    "name:pol_x_preferred":[
        "Kostajnica"
    ],
    "name:ron_x_preferred":[
        "Kostajnica"
    ],
    "name:rus_x_preferred":[
        "\u041a\u043e\u0441\u0442\u0430\u0439\u043d\u0438\u0446\u0430"
    ],
    "name:srp_x_preferred":[
        "\u041a\u043e\u0441\u0442\u0430\u0458\u043d\u0438\u0446\u0430"
    ],
    "name:swe_x_preferred":[
        "Kostajnica"
    ],
    "wof:name":"Kostajnica",
    "wof:placetype":"locality"
},
  "geometry": {"coordinates":[17.80907000000001,43.71664000000001],"type":"Point"}
}