{
  "type": "Feature",
  "properties": {
    "gn:admin1_code":"02",
    "gn:asciiname":"Rajetici",
    "gn:country_code":"BA",
    "gn:dem":979,
    "gn:feature_class":"P",
    "gn:feature_code":"PPL",
    "gn:name":"Rajeti\u0107i",
    "gn:population":0,
    "gn:timezone":"Europe/Sarajevo",
    "iso:country":"BA",
    "wof:name":"Rajetici",
    "wof:placetype":"locality"
},
  "geometry": {"coordinates":[18.92054,43.43437],"type":"Point"}
}