{
  "type": "Feature",
  "properties": {
    "gn:admin1_code":"01",
    "gn:asciiname":"Zavade",
    "gn:country_code":"BA",
    "gn:dem":494,
    "gn:feature_class":"P",
    "gn:feature_code":"PPL",
    "gn:name":"Zava\u0111e",
    "gn:population":0,
    "gn:timezone":"Europe/Sarajevo",
    "iso:country":"BA",
    "wof:name":"Zavade",
    "wof:placetype":"locality"
},
  "geometry": {"coordinates":[16.41889,44.3525],"type":"Point"}
}