{
  "type": "Feature",
  "properties": {
    "gn:admin1_code":"01",
    "gn:asciiname":"Rainci Donji",
    "gn:country_code":"BA",
    "gn:dem":248,
    "gn:feature_class":"P",
    "gn:feature_code":"PPLL",
    "gn:name":"Rainci Donji",
    "gn:population":0,
    "gn:timezone":"Europe/Sarajevo",
    "iso:country":"BA",
    "name:bos_x_preferred":[
        "Rainci Donji"
    ],
    "name:ceb_x_preferred":[
        "Rainci Donji"
    ],
    "name:fra_x_preferred":[
        "Rainci Donji"
    ],
    "name:hrv_x_preferred":[
        "Rainci Donji"
    ],
    "name:srp_x_preferred":[
        "\u0420\u0430\u0438\u043d\u0446\u0438 \u0414\u043e\u045a\u0438"
    ],
    "name:swe_x_preferred":[
        "Rainci Donji"
    ],
    "name:und_x_variant":[
        "Rajinci",
        "Rainci Donji"
    ],
    "wof:name":"Rainci Donji",
    "wof:placetype":"locality"
},
  "geometry": {"coordinates":[18.8099,44.44204000000001],"type":"Point"}
}