{
  "type": "Feature",
  "properties": {
    "gn:admin1_code":"02",
    "gn:asciiname":"Marjanovici",
    "gn:country_code":"BA",
    "gn:dem":523,
    "gn:feature_class":"P",
    "gn:feature_code":"PPL",
    "gn:name":"Marjanovi\u0107i",
    "gn:population":0,
    "gn:timezone":"Europe/Sarajevo",
    "iso:country":"BA",
    "wof:name":"Marjanovici",
    "wof:placetype":"locality"
},
  "geometry": {"coordinates":[17.4526,44.56124000000001],"type":"Point"}
}