{
  "type": "Feature",
  "properties": {
    "gn:admin1_code":"01",
    "gn:asciiname":"Pejici",
    "gn:country_code":"BA",
    "gn:dem":363,
    "gn:feature_class":"P",
    "gn:feature_code":"PPL",
    "gn:name":"Peji\u0107i",
    "gn:population":0,
    "gn:timezone":"Europe/Sarajevo",
    "iso:country":"BA",
    "wof:name":"Pejici",
    "wof:placetype":"locality"
},
  "geometry": {"coordinates":[18.17942,44.38594000000001],"type":"Point"}
}