{
  "type": "Feature",
  "properties": {
    "gn:admin1_code":"01",
    "gn:asciiname":"Siprage",
    "gn:country_code":"BA",
    "gn:dem":405,
    "gn:feature_class":"P",
    "gn:feature_code":"PPL",
    "gn:name":"\u0160iprage",
    "gn:population":0,
    "gn:timezone":"Europe/Sarajevo",
    "iso:country":"BA",
    "wof:name":"Siprage",
    "wof:placetype":"locality"
},
  "geometry": {"coordinates":[16.45871,44.74031],"type":"Point"}
}