{
  "type": "Feature",
  "properties": {
    "gn:admin1_code":"01",
    "gn:asciiname":"Kostre",
    "gn:country_code":"BA",
    "gn:dem":568,
    "gn:feature_class":"P",
    "gn:feature_code":"PPL",
    "gn:name":"Ko\u0161tre",
    "gn:population":0,
    "gn:timezone":"Europe/Sarajevo",
    "iso:country":"BA",
    "wof:name":"Kostre",
    "wof:placetype":"locality"
},
  "geometry": {"coordinates":[17.22286,43.52266],"type":"Point"}
}