{
  "type": "Feature",
  "properties": {
    "gn:admin1_code":"01",
    "gn:asciiname":"Donja Prisika",
    "gn:country_code":"BA",
    "gn:dem":730,
    "gn:feature_class":"P",
    "gn:feature_code":"PPL",
    "gn:name":"Donja Prisika",
    "gn:population":0,
    "gn:timezone":"Europe/Sarajevo",
    "iso:country":"BA",
    "wof:name":"Donja Prisika",
    "wof:placetype":"locality"
},
  "geometry": {"coordinates":[16.98646,43.60612],"type":"Point"}
}