{
  "type": "Feature",
  "properties": {
    "gn:admin1_code":"01",
    "gn:asciiname":"Kopjenica",
    "gn:country_code":"BA",
    "gn:dem":442,
    "gn:feature_class":"P",
    "gn:feature_code":"PPLL",
    "gn:name":"Kopjenica",
    "gn:population":0,
    "gn:timezone":"Europe/Sarajevo",
    "iso:country":"BA",
    "name:bos_x_preferred":[
        "Kopjenica"
    ],
    "name:fra_x_preferred":[
        "Kopjenica"
    ],
    "name:srp_x_preferred":[
        "\u041a\u043e\u043f\u0458\u0435\u043d\u0438\u0446\u0430"
    ],
    "name:und_x_variant":[
        "Kopljenica"
    ],
    "wof:name":"Kopjenica",
    "wof:placetype":"locality"
},
  "geometry": {"coordinates":[16.69412,44.56048],"type":"Point"}
}