{
  "type": "Feature",
  "properties": {
    "gn:admin1_code":"00",
    "gn:asciiname":"Bukvici",
    "gn:country_code":"BA",
    "gn:dem":426,
    "gn:feature_class":"P",
    "gn:feature_code":"PPL",
    "gn:name":"Bukvi\u0107i",
    "gn:population":0,
    "gn:timezone":"Europe/Sarajevo",
    "iso:country":"BA",
    "wof:name":"Bukvici",
    "wof:placetype":"locality"
},
  "geometry": {"coordinates":[18.37618,44.39516],"type":"Point"}
}