{
  "type": "Feature",
  "properties": {
    "gn:admin1_code":"02",
    "gn:asciiname":"Basica Do",
    "gn:country_code":"BA",
    "gn:dem":948,
    "gn:feature_class":"P",
    "gn:feature_code":"PPL",
    "gn:name":"Ba\u0161i\u0107a Do",
    "gn:population":0,
    "gn:timezone":"Europe/Sarajevo",
    "iso:country":"BA",
    "wof:name":"Basica Do",
    "wof:placetype":"locality"
},
  "geometry": {"coordinates":[18.64952000000001,43.05599],"type":"Point"}
}