{
  "type": "Feature",
  "properties": {
    "gn:admin1_code":"02",
    "gn:asciiname":"Mala Daljegosta",
    "gn:country_code":"BA",
    "gn:dem":611,
    "gn:feature_class":"P",
    "gn:feature_code":"PPL",
    "gn:name":"Mala Daljego\u0161ta",
    "gn:population":0,
    "gn:timezone":"Europe/Sarajevo",
    "iso:country":"BA",
    "name:bos_x_preferred":[
        "Mala Daljego\u0161ta"
    ],
    "name:bul_x_preferred":[
        "\u041c\u0430\u043b\u0430 \u0414\u0430\u043b\u0435\u0433\u043e\u0449\u0430"
    ],
    "name:ceb_x_preferred":[
        "Mala Daljego\u0161ta"
    ],
    "name:fra_x_preferred":[
        "Mala Daljego\u0161ta"
    ],
    "name:hrv_x_preferred":[
        "Mala Daljego\u0161ta"
    ],
    "name:srp_x_preferred":[
        "\u041c\u0430\u043b\u0430 \u0414\u0430\u0459\u0435\u0433\u043e\u0448\u0442\u0430"
    ],
    "name:swe_x_preferred":[
        "Mala Daljego\u0161ta"
    ],
    "name:und_x_variant":[
        "Mala Delego\u0161ta",
        "Mala Daljego\u0161ta"
    ],
    "wof:name":"Mala Daljegosta",
    "wof:placetype":"locality"
},
  "geometry": {"coordinates":[19.54349,44.01264000000001],"type":"Point"}
}