{
  "type": "Feature",
  "properties": {
    "gn:admin1_code":"01",
    "gn:asciiname":"Klisa",
    "gn:country_code":"BA",
    "gn:dem":312,
    "gn:feature_class":"P",
    "gn:feature_code":"PPL",
    "gn:name":"Klisa",
    "gn:population":0,
    "gn:timezone":"Europe/Sarajevo",
    "iso:country":"BA",
    "name:bos_x_preferred":[
        "Klisa"
    ],
    "name:ceb_x_preferred":[
        "Klisa"
    ],
    "name:fra_x_preferred":[
        "Klisa"
    ],
    "name:hrv_x_preferred":[
        "Klisa"
    ],
    "name:hun_x_preferred":[
        "Klisa"
    ],
    "name:nld_x_preferred":[
        "Klisa"
    ],
    "name:slv_x_preferred":[
        "Klisa"
    ],
    "name:srp_x_preferred":[
        "\u041a\u043b\u0438\u0441\u0430"
    ],
    "name:swe_x_preferred":[
        "Klisa"
    ],
    "wof:name":"Klisa",
    "wof:placetype":"locality"
},
  "geometry": {"coordinates":[15.92446,44.96933],"type":"Point"}
}