{
  "type": "Feature",
  "properties": {
    "gn:admin1_code":"02",
    "gn:asciiname":"Obrovac",
    "gn:country_code":"BA",
    "gn:dem":246,
    "gn:feature_class":"P",
    "gn:feature_code":"PPLL",
    "gn:name":"Obrovac",
    "gn:population":0,
    "gn:timezone":"Europe/Sarajevo",
    "iso:country":"BA",
    "name:bos_x_preferred":[
        "Obrovac"
    ],
    "name:ceb_x_preferred":[
        "Obrovac"
    ],
    "name:deu_x_preferred":[
        "Obrovac"
    ],
    "name:fra_x_preferred":[
        "Obrovac"
    ],
    "name:hrv_x_preferred":[
        "Obrovac"
    ],
    "name:hun_x_preferred":[
        "Obrovac"
    ],
    "name:ita_x_preferred":[
        "Obrovac"
    ],
    "name:rus_x_preferred":[
        "\u041e\u0431\u0440\u043e\u0432\u0430\u0446"
    ],
    "name:slv_x_preferred":[
        "Obrovac"
    ],
    "name:srp_x_preferred":[
        "\u041e\u0431\u0440\u043e\u0432\u0430\u0446"
    ],
    "name:swe_x_preferred":[
        "Obrovac"
    ],
    "wof:name":"Obrovac",
    "wof:placetype":"locality"
},
  "geometry": {"coordinates":[16.89036,44.76843],"type":"Point"}
}