{
  "type": "Feature",
  "properties": {
    "gn:admin1_code":"02",
    "gn:asciiname":"Obrovac",
    "gn:country_code":"BA",
    "gn:dem":246,
    "gn:feature_class":"P",
    "gn:feature_code":"PPLL",
    "gn:name":"Obrovac",
    "gn:population":0,
    "gn:timezone":"Europe/Sarajevo",
    "iso:country":"BA",
    "wof:name":"Obrovac",
    "wof:placetype":"locality"
},
  "geometry": {"coordinates":[16.89036,44.76843],"type":"Point"}
}