{
  "type": "Feature",
  "properties": {
    "gn:admin1_code":"01",
    "gn:asciiname":"Seferi",
    "gn:country_code":"BA",
    "gn:dem":758,
    "gn:feature_class":"P",
    "gn:feature_code":"PPL",
    "gn:name":"Seferi",
    "gn:population":0,
    "gn:timezone":"Europe/Sarajevo",
    "iso:country":"BA",
    "name:rus_x_preferred":[
        "\u0421\u0435\u0444\u0435\u0440\u0438"
    ],
    "wof:name":"Seferi",
    "wof:placetype":"locality"
},
  "geometry": {"coordinates":[17.50919,44.26936],"type":"Point"}
}