{
  "type": "Feature",
  "properties": {
    "gn:admin1_code":"02",
    "gn:asciiname":"Ilisija",
    "gn:country_code":"BA",
    "gn:dem":945,
    "gn:feature_class":"P",
    "gn:feature_code":"PPL",
    "gn:name":"Ilisija",
    "gn:population":0,
    "gn:timezone":"Europe/Sarajevo",
    "iso:country":"BA",
    "wof:name":"Ilisija",
    "wof:placetype":"locality"
},
  "geometry": {"coordinates":[18.85167,43.51694000000001],"type":"Point"}
}