{
  "type": "Feature",
  "properties": {
    "gn:admin1_code":"02",
    "gn:asciiname":"Svjetlanovici",
    "gn:country_code":"BA",
    "gn:dem":890,
    "gn:feature_class":"P",
    "gn:feature_code":"PPL",
    "gn:name":"Svjetlanovi\u0107i",
    "gn:population":0,
    "gn:timezone":"Europe/Sarajevo",
    "iso:country":"BA",
    "wof:name":"Svjetlanovici",
    "wof:placetype":"locality"
},
  "geometry": {"coordinates":[17.40217,44.52864],"type":"Point"}
}