{
  "type": "Feature",
  "properties": {
    "gn:admin1_code":"01",
    "gn:asciiname":"Vinogradi",
    "gn:country_code":"BA",
    "gn:dem":804,
    "gn:feature_class":"P",
    "gn:feature_code":"PPL",
    "gn:name":"Vinogradi",
    "gn:population":0,
    "gn:timezone":"Europe/Sarajevo",
    "iso:country":"BA",
    "wof:name":"Vinogradi",
    "wof:placetype":"locality"
},
  "geometry": {"coordinates":[17.23707000000001,44.33317],"type":"Point"}
}