{
  "type": "Feature",
  "properties": {
    "gn:admin1_code":"01",
    "gn:asciiname":"Vinogradi",
    "gn:country_code":"BA",
    "gn:dem":804,
    "gn:feature_class":"P",
    "gn:feature_code":"PPL",
    "gn:name":"Vinogradi",
    "gn:population":0,
    "gn:timezone":"Europe/Sarajevo",
    "iso:country":"BA",
    "name:bul_x_preferred":[
        "\u0412\u0438\u043d\u043e\u0433\u0440\u0430\u0434\u0438"
    ],
    "name:fas_x_preferred":[
        "\u0648\u06cc\u0646\u0648\u06af\u0631\u0627\u062f\u06cc"
    ],
    "name:kaz_x_preferred":[
        "\u0412\u0438\u043d\u043e\u0433\u0440\u0430\u0434\u0438"
    ],
    "name:mkd_x_preferred":[
        "\u041c\u0430\u043d\u045f\u043e\u0432\u043e"
    ],
    "name:pol_x_preferred":[
        "Winogradi"
    ],
    "name:ron_x_preferred":[
        "Vinogradi"
    ],
    "name:rus_x_preferred":[
        "\u0412\u0438\u043d\u043e\u0433\u0440\u0430\u0434\u0438"
    ],
    "name:ukr_x_preferred":[
        "\u0412\u0438\u043d\u043e\u0433\u0440\u0430\u0434\u0438"
    ],
    "wof:name":"Vinogradi",
    "wof:placetype":"locality"
},
  "geometry": {"coordinates":[17.23707000000001,44.33317],"type":"Point"}
}