{
  "type": "Feature",
  "properties": {
    "gn:admin1_code":"02",
    "gn:asciiname":"Ivazovici",
    "gn:country_code":"BA",
    "gn:dem":1099,
    "gn:feature_class":"P",
    "gn:feature_code":"PPL",
    "gn:name":"Ivazovi\u0107i",
    "gn:population":0,
    "gn:timezone":"Europe/Sarajevo",
    "iso:country":"BA",
    "name:und_x_variant":[
        "P\u012bleh-ye Sorkh",
        "Pila-i-Su\u1e5fkh",
        "Ivazovi\u0107i"
    ],
    "wof:name":"Ivazovici",
    "wof:placetype":"locality"
},
  "geometry": {"coordinates":[18.78373,44.06168],"type":"Point"}
}