{
  "type": "Feature",
  "properties": {
    "gn:admin1_code":"02",
    "gn:asciiname":"Donja Mahala",
    "gn:country_code":"BA",
    "gn:dem":382,
    "gn:feature_class":"P",
    "gn:feature_code":"PPL",
    "gn:name":"Donja Mahala",
    "gn:population":0,
    "gn:timezone":"Europe/Sarajevo",
    "iso:country":"BA",
    "name:bos_x_preferred":[
        "Donja Mahala"
    ],
    "name:ceb_x_preferred":[
        "Donja Mahala"
    ],
    "name:fra_x_preferred":[
        "Donja Mahala"
    ],
    "name:hrv_x_preferred":[
        "Donja Mahala"
    ],
    "name:srp_x_preferred":[
        "\u0414\u043e\u045a\u0430 \u041c\u0430\u0445\u0430\u043b\u0430"
    ],
    "name:swe_x_preferred":[
        "Donja Mahala"
    ],
    "wof:name":"Donja Mahala",
    "wof:placetype":"locality"
},
  "geometry": {"coordinates":[19.08055,44.23153],"type":"Point"}
}