{
  "type": "Feature",
  "properties": {
    "gn:admin1_code":"01",
    "gn:asciiname":"Citluk",
    "gn:country_code":"BA",
    "gn:dem":603,
    "gn:feature_class":"P",
    "gn:feature_code":"PPLL",
    "gn:name":"\u010citluk",
    "gn:population":0,
    "gn:timezone":"Europe/Sarajevo",
    "iso:country":"BA",
    "name:bos_x_preferred":[
        "\u010citluk"
    ],
    "name:ceb_x_preferred":[
        "\u010citluk"
    ],
    "name:fra_x_preferred":[
        "\u010citluk"
    ],
    "wof:name":"Citluk",
    "wof:placetype":"locality"
},
  "geometry": {"coordinates":[18.88221,43.65675],"type":"Point"}
}