{
  "type": "Feature",
  "properties": {
    "gn:admin1_code":"02",
    "gn:asciiname":"Vucja Luka",
    "gn:country_code":"BA",
    "gn:dem":1305,
    "gn:feature_class":"P",
    "gn:feature_code":"PPLL",
    "gn:name":"Vu\u010dja Luka",
    "gn:population":0,
    "gn:timezone":"Europe/Sarajevo",
    "iso:country":"BA",
    "name:bos_x_preferred":[
        "Vu\u010dja Luka"
    ],
    "name:ceb_x_preferred":[
        "Han Vu\u010dja Luka"
    ],
    "name:fra_x_preferred":[
        "Vu\u010dja Luka"
    ],
    "name:srp_x_preferred":[
        "\u0412\u0443\u0447\u0438\u0458\u0430 \u041b\u0443\u043a\u0430"
    ],
    "name:swe_x_preferred":[
        "Han Vu\u010dja Luka"
    ],
    "wof:name":"Vucja Luka",
    "wof:placetype":"locality"
},
  "geometry": {"coordinates":[18.5154,43.92546],"type":"Point"}
}