{
  "type": "Feature",
  "properties": {
    "gn:admin1_code":"02",
    "gn:asciiname":"Brda",
    "gn:country_code":"BA",
    "gn:dem":330,
    "gn:feature_class":"P",
    "gn:feature_code":"PPL",
    "gn:name":"Brda",
    "gn:population":0,
    "gn:timezone":"Europe/Sarajevo",
    "iso:country":"BA",
    "wof:name":"Brda",
    "wof:placetype":"locality"
},
  "geometry": {"coordinates":[16.65667,45.07149],"type":"Point"}
}