{
  "type": "Feature",
  "properties": {
    "gn:admin1_code":"01",
    "gn:asciiname":"Strbci",
    "gn:country_code":"BA",
    "gn:dem":838,
    "gn:feature_class":"P",
    "gn:feature_code":"PPL",
    "gn:name":"\u0160trbci",
    "gn:population":0,
    "gn:timezone":"Europe/Sarajevo",
    "iso:country":"BA",
    "wof:name":"Strbci",
    "wof:placetype":"locality"
},
  "geometry": {"coordinates":[16.43372999999999,44.2171],"type":"Point"}
}