{
  "type": "Feature",
  "properties": {
    "gn:admin1_code":"01",
    "gn:asciiname":"Medudrazje",
    "gn:country_code":"BA",
    "gn:dem":439,
    "gn:feature_class":"P",
    "gn:feature_code":"PPL",
    "gn:name":"Me\u0111udra\u017eje",
    "gn:population":0,
    "gn:timezone":"Europe/Sarajevo",
    "iso:country":"BA",
    "name:und_x_variant":[
        "Me\u0111udra\u017eje"
    ],
    "wof:name":"Medudrazje",
    "wof:placetype":"locality"
},
  "geometry": {"coordinates":[15.84537,44.76578],"type":"Point"}
}