{
  "type": "Feature",
  "properties": {
    "gn:admin1_code":"01",
    "gn:asciiname":"Medudrazje",
    "gn:country_code":"BA",
    "gn:dem":439,
    "gn:feature_class":"P",
    "gn:feature_code":"PPL",
    "gn:name":"Me\u0111udra\u017eje",
    "gn:population":0,
    "gn:timezone":"Europe/Sarajevo",
    "iso:country":"BA",
    "name:ara_x_preferred":[
        "\u0645\u064a\u062f\u0648\u062f\u0631\u0627\u0632\u064a"
    ],
    "name:bos_x_preferred":[
        "Me\u0111udra\u017eje"
    ],
    "name:ell_x_preferred":[
        "\u039c\u03b5\u03c4\u03b6\u03bf\u03cd\u03bd\u03c4\u03c1\u03b1\u03b6\u03b9\u03b5"
    ],
    "name:fra_x_preferred":[
        "Me\u0111udra\u017eje"
    ],
    "name:hrv_x_preferred":[
        "Me\u0111udra\u017eje"
    ],
    "name:slv_x_preferred":[
        "Me\u0111udra\u017eje"
    ],
    "name:srp_x_preferred":[
        "\u041c\u0435\u0452\u0443\u0434\u0440\u0430\u0436\u0458\u0435"
    ],
    "wof:name":"Medudrazje",
    "wof:placetype":"locality"
},
  "geometry": {"coordinates":[15.84537,44.76578],"type":"Point"}
}