{
  "type": "Feature",
  "properties": {
    "gn:admin1_code":"02",
    "gn:asciiname":"Kostur",
    "gn:country_code":"BA",
    "gn:dem":749,
    "gn:feature_class":"P",
    "gn:feature_code":"PPL",
    "gn:name":"Ko\u0161tur",
    "gn:population":0,
    "gn:timezone":"Europe/Sarajevo",
    "iso:country":"BA",
    "wof:name":"Kostur",
    "wof:placetype":"locality"
},
  "geometry": {"coordinates":[19.23568,44.06031],"type":"Point"}
}