{
  "type": "Feature",
  "properties": {
    "gn:admin1_code":"02",
    "gn:asciiname":"Davidovici",
    "gn:country_code":"BA",
    "gn:dem":323,
    "gn:feature_class":"P",
    "gn:feature_code":"PPL",
    "gn:name":"Davidovi\u0107i",
    "gn:population":0,
    "gn:timezone":"Europe/Sarajevo",
    "iso:country":"BA",
    "name:fra_x_preferred":[
        "Davidovici"
    ],
    "name:ron_x_preferred":[
        "Davidovici"
    ],
    "wof:name":"Davidovici",
    "wof:placetype":"locality"
},
  "geometry": {"coordinates":[16.50365,44.89823],"type":"Point"}
}