{
  "type": "Feature",
  "properties": {
    "gn:admin1_code":"01",
    "gn:asciiname":"Halilovci",
    "gn:country_code":"BA",
    "gn:dem":898,
    "gn:feature_class":"P",
    "gn:feature_code":"PPL",
    "gn:name":"Halilovci",
    "gn:population":0,
    "gn:timezone":"Europe/Sarajevo",
    "iso:country":"BA",
    "wof:name":"Halilovci",
    "wof:placetype":"locality"
},
  "geometry": {"coordinates":[17.48324,44.249],"type":"Point"}
}