{
  "type": "Feature",
  "properties": {
    "gn:admin1_code":"01",
    "gn:asciiname":"Spahici",
    "gn:country_code":"BA",
    "gn:dem":365,
    "gn:feature_class":"P",
    "gn:feature_code":"PPL",
    "gn:name":"Spahi\u0107i",
    "gn:population":0,
    "gn:timezone":"Europe/Sarajevo",
    "iso:country":"BA",
    "name:ara_x_preferred":[
        "\u0633\u0628\u0627\u0647\u064a\u062a\u0634\u064a"
    ],
    "name:bos_x_preferred":[
        "Spahi\u0107i"
    ],
    "name:ell_x_preferred":[
        "\u03a3\u03c0\u03ac\u03c7\u03b9\u03c4\u03c3\u03b9"
    ],
    "name:fra_x_preferred":[
        "Spahi\u0107i"
    ],
    "name:hrv_x_preferred":[
        "Spahi\u0107i"
    ],
    "name:slv_x_preferred":[
        "Spahi\u0107i"
    ],
    "name:srp_x_preferred":[
        "\u0421\u043f\u0430\u0445\u0438\u045b\u0438"
    ],
    "name:und_x_variant":[
        "Spahi\u0107i"
    ],
    "wof:name":"Spahici",
    "wof:placetype":"locality"
},
  "geometry": {"coordinates":[15.90889,44.87861],"type":"Point"}
}