{
  "type": "Feature",
  "properties": {
    "gn:admin1_code":"01",
    "gn:asciiname":"Spahici",
    "gn:country_code":"BA",
    "gn:dem":365,
    "gn:feature_class":"P",
    "gn:feature_code":"PPL",
    "gn:name":"Spahi\u0107i",
    "gn:population":0,
    "gn:timezone":"Europe/Sarajevo",
    "iso:country":"BA",
    "name:und_x_variant":[
        "Spahi\u0107i"
    ],
    "wof:name":"Spahici",
    "wof:placetype":"locality"
},
  "geometry": {"coordinates":[15.90889,44.87861],"type":"Point"}
}