{
  "type": "Feature",
  "properties": {
    "gn:admin1_code":"02",
    "gn:asciiname":"Mrkajici",
    "gn:country_code":"BA",
    "gn:dem":552,
    "gn:feature_class":"P",
    "gn:feature_code":"PPL",
    "gn:name":"Mrkaji\u0107i",
    "gn:population":0,
    "gn:timezone":"Europe/Sarajevo",
    "iso:country":"BA",
    "wof:name":"Mrkajici",
    "wof:placetype":"locality"
},
  "geometry": {"coordinates":[18.86168,44.30557],"type":"Point"}
}