{
  "type": "Feature",
  "properties": {
    "gn:admin1_code":"01",
    "gn:asciiname":"Boboljusci",
    "gn:country_code":"BA",
    "gn:dem":712,
    "gn:feature_class":"P",
    "gn:feature_code":"PPLL",
    "gn:name":"Boboljusci",
    "gn:population":0,
    "gn:timezone":"Europe/Sarajevo",
    "iso:country":"BA",
    "wof:name":"Boboljusci",
    "wof:placetype":"locality"
},
  "geometry": {"coordinates":[16.25368,44.43731],"type":"Point"}
}