{
  "type": "Feature",
  "properties": {
    "gn:admin1_code":"01",
    "gn:asciiname":"Boboljusci",
    "gn:country_code":"BA",
    "gn:dem":712,
    "gn:feature_class":"P",
    "gn:feature_code":"PPLL",
    "gn:name":"Boboljusci",
    "gn:population":0,
    "gn:timezone":"Europe/Sarajevo",
    "iso:country":"BA",
    "name:ara_x_preferred":[
        "\u0628\u0648\u0628\u0648\u0644\u064a\u0648\u062a\u0633\u064a"
    ],
    "name:bos_x_preferred":[
        "Boboljusci"
    ],
    "name:ell_x_preferred":[
        "\u039c\u03c0\u03bf\u03bc\u03c0\u03cc\u03bb\u03b9\u03bf\u03c5\u03c3\u03c4\u03c3\u03b9"
    ],
    "name:fra_x_preferred":[
        "Boboljusci"
    ],
    "name:hrv_x_preferred":[
        "Boboljusci"
    ],
    "name:srp_x_preferred":[
        "\u0411\u043e\u0431\u043e\u0459\u0443\u0441\u0446\u0438"
    ],
    "wof:name":"Boboljusci",
    "wof:placetype":"locality"
},
  "geometry": {"coordinates":[16.25368,44.43731],"type":"Point"}
}