{
  "type": "Feature",
  "properties": {
    "gn:admin1_code":"02",
    "gn:asciiname":"Gavranovici",
    "gn:country_code":"BA",
    "gn:dem":173,
    "gn:feature_class":"P",
    "gn:feature_code":"PPL",
    "gn:name":"Gavranovi\u0107i",
    "gn:population":0,
    "gn:timezone":"Europe/Sarajevo",
    "iso:country":"BA",
    "wof:name":"Gavranovici",
    "wof:placetype":"locality"
},
  "geometry": {"coordinates":[16.5067,44.93328],"type":"Point"}
}