{
  "type": "Feature",
  "properties": {
    "gn:admin1_code":"02",
    "gn:asciiname":"Glogova",
    "gn:country_code":"BA",
    "gn:dem":453,
    "gn:feature_class":"P",
    "gn:feature_code":"PPL",
    "gn:name":"Glogova",
    "gn:population":0,
    "gn:timezone":"Europe/Sarajevo",
    "iso:country":"BA",
    "name:bos_x_preferred":[
        "Glogova"
    ],
    "name:ceb_x_preferred":[
        "Glogova"
    ],
    "name:fra_x_preferred":[
        "Glogova"
    ],
    "name:hrv_x_preferred":[
        "Glogova"
    ],
    "name:rus_x_preferred":[
        "\u0413\u043b\u043e\u0433\u043e\u0432\u0430"
    ],
    "name:srp_x_preferred":[
        "\u0413\u043b\u043e\u0433\u043e\u0432\u0430"
    ],
    "name:swe_x_preferred":[
        "Glogova"
    ],
    "wof:name":"Glogova",
    "wof:placetype":"locality"
},
  "geometry": {"coordinates":[19.31722,43.77778],"type":"Point"}
}