{
  "type": "Feature",
  "properties": {
    "gn:admin1_code":"01",
    "gn:asciiname":"Dopasci",
    "gn:country_code":"BA",
    "gn:dem":620,
    "gn:feature_class":"P",
    "gn:feature_code":"PPLL",
    "gn:name":"Dopasci",
    "gn:population":0,
    "gn:timezone":"Europe/Sarajevo",
    "iso:country":"BA",
    "wof:name":"Dopasci",
    "wof:placetype":"locality"
},
  "geometry": {"coordinates":[18.75879,44.25454000000001],"type":"Point"}
}