{
  "type": "Feature",
  "properties": {
    "gn:country":"BA",
    "gn:fcode":"PPL",
    "gn:pop":7014,
    "iso:country":"BA",
    "name:bos_x_preferred":[
        "Gornji Vakuf"
    ],
    "name:bre_x_preferred":[
        "Gornji Vakuf-Uskoplje"
    ],
    "name:ces_x_preferred":[
        "Gornji Vakuf"
    ],
    "name:deu_x_preferred":[
        "Gornji Vakuf-Uskoplje"
    ],
    "name:eng_x_preferred":[
        "Gornji Vakuf-Uskoplje"
    ],
    "name:fra_x_preferred":[
        "Gornji Vakuf-Uskoplje"
    ],
    "name:heb_x_preferred":[
        "\u05d2\u05d5\u05e8\u05e0\u05d9 \u05d5\u05d0\u05e7\u05d5\u05e3"
    ],
    "name:hrv_x_preferred":[
        "Uskoplje"
    ],
    "name:hye_x_preferred":[
        "\u0533\u0578\u057c\u0576\u056b \u054e\u0561\u056f\u0578\u0582\u0586 \u0548\u0582\u057d\u056f\u0578\u057a\u056c\u0565"
    ],
    "name:ita_x_preferred":[
        "Gornji Vakuf-Uskoplje"
    ],
    "name:jpn_x_preferred":[
        "\u30b4\u30eb\u30cb\u30fb\u30f4\u30a1\u30af\u30d5\uff1d\u30a6\u30b9\u30b3\u30d7\u30ea\u30a7"
    ],
    "name:lit_x_preferred":[
        "Gorni Vakufas-Uskopl\u0117"
    ],
    "name:nld_x_preferred":[
        "Gornji Vakuf-Uskoplje"
    ],
    "name:pol_x_preferred":[
        "Gornji Vakuf-Uskoplje"
    ],
    "name:spa_x_preferred":[
        "Gornji Vakuf-Uskoplje"
    ],
    "name:sqi_x_preferred":[
        "Gornji Vakuf-Uskoplje"
    ],
    "name:srp_x_preferred":[
        "\u0413\u043e\u0440\u045a\u0438 \u0412\u0430\u043a\u0443\u0444-\u0423\u0441\u043a\u043e\u043f\u0459\u0435"
    ],
    "name:swe_x_preferred":[
        "Gornji Vakuf"
    ],
    "name:tat_x_preferred":[
        "\u0413\u043e\u0440\u043d\u0438-\u0412\u0430\u043a\u0443\u0444-\u0423\u0441\u043a\u043e\u043f\u043b\u0435"
    ],
    "name:tur_x_preferred":[
        "Gornji Vakuf"
    ],
    "name:unk_x_variant":[
        "Vakuf Gornji"
    ],
    "name:urd_x_preferred":[
        "\u06af\u0648\u0631\u0646\u06cc \u0648\u0627\u06a9\u0648\u0641-\u0627\u0648\u0633\u06a9\u0648\u067e\u0644\u06cc\u06d2"
    ],
    "name:zho_x_preferred":[
        "\u683c\u62c9\u5167\u5947\u74e6\u5eab\u592b"
    ],
    "qs:name":"Gornji Vakuf",
    "qs:photos_9r":0,
    "qs:photos_sr":0,
    "qs:pop_sr":"5",
    "wof:name":"Gornji Vakuf",
    "wof:placetype":"locality",
    "wof:population":7014
},
  "geometry": {"coordinates":[17.58833,43.93806],"type":"Point"}
}