{
  "type": "Feature",
  "properties": {
    "gn:admin1_code":"01",
    "gn:asciiname":"Selakovici",
    "gn:country_code":"BA",
    "gn:dem":787,
    "gn:feature_class":"P",
    "gn:feature_code":"PPL",
    "gn:name":"Selakovi\u0107i",
    "gn:population":0,
    "gn:timezone":"Europe/Sarajevo",
    "iso:country":"BA",
    "name:bos_x_preferred":[
        "Selakovi\u0107i"
    ],
    "name:fra_x_preferred":[
        "Selakovi\u0107i"
    ],
    "name:hrv_x_preferred":[
        "Selakovi\u0107i"
    ],
    "name:srp_x_preferred":[
        "\u0421\u0435\u043b\u0430\u043a\u043e\u0432\u0438\u045b\u0438"
    ],
    "wof:name":"Selakovici",
    "wof:placetype":"locality"
},
  "geometry": {"coordinates":[17.89997,43.95436],"type":"Point"}
}