{
  "type": "Feature",
  "properties": {
    "gn:admin1_code":"01",
    "gn:asciiname":"Selakovici",
    "gn:country_code":"BA",
    "gn:dem":787,
    "gn:feature_class":"P",
    "gn:feature_code":"PPL",
    "gn:name":"Selakovi\u0107i",
    "gn:population":0,
    "gn:timezone":"Europe/Sarajevo",
    "iso:country":"BA",
    "name:und_x_variant":[
        "Selakovi\u0107i"
    ],
    "wof:name":"Selakovici",
    "wof:placetype":"locality"
},
  "geometry": {"coordinates":[17.89997,43.95436],"type":"Point"}
}