{
  "type": "Feature",
  "properties": {
    "gn:admin1_code":"01",
    "gn:asciiname":"Handanagici",
    "gn:country_code":"BA",
    "gn:dem":394,
    "gn:feature_class":"P",
    "gn:feature_code":"PPL",
    "gn:name":"Handanagi\u0107i",
    "gn:population":0,
    "gn:timezone":"Europe/Sarajevo",
    "iso:country":"BA",
    "wof:name":"Handanagici",
    "wof:placetype":"locality"
},
  "geometry": {"coordinates":[15.94879,44.91437],"type":"Point"}
}