{
  "type": "Feature",
  "properties": {
    "gn:admin1_code":"02",
    "gn:asciiname":"Becici",
    "gn:country_code":"BA",
    "gn:dem":1008,
    "gn:feature_class":"P",
    "gn:feature_code":"PPL",
    "gn:name":"Be\u010di\u0107i",
    "gn:population":0,
    "gn:timezone":"Europe/Sarajevo",
    "iso:country":"BA",
    "name:und_x_variant":[
        "Hanina",
        "Be\u010di\u0107i"
    ],
    "wof:name":"Becici",
    "wof:placetype":"locality"
},
  "geometry": {"coordinates":[18.74078,43.83695],"type":"Point"}
}