{
  "type": "Feature",
  "properties": {
    "gn:admin1_code":"02",
    "gn:asciiname":"Gradina",
    "gn:country_code":"BA",
    "gn:dem":449,
    "gn:feature_class":"P",
    "gn:feature_code":"PPL",
    "gn:name":"Gradina",
    "gn:population":0,
    "gn:timezone":"Europe/Sarajevo",
    "iso:country":"BA",
    "wof:name":"Gradina",
    "wof:placetype":"locality"
},
  "geometry": {"coordinates":[19.0704,44.15345],"type":"Point"}
}