{
  "type": "Feature",
  "properties": {
    "gn:admin1_code":"02",
    "gn:asciiname":"Sela",
    "gn:country_code":"BA",
    "gn:dem":930,
    "gn:feature_class":"P",
    "gn:feature_code":"PPLL",
    "gn:name":"Sela",
    "gn:population":0,
    "gn:timezone":"Europe/Sarajevo",
    "iso:country":"BA",
    "name:bos_x_preferred":[
        "Sela"
    ],
    "name:fra_x_preferred":[
        "Sela"
    ],
    "name:srp_x_preferred":[
        "\u0421\u0435\u043b\u0430"
    ],
    "wof:name":"Sela",
    "wof:placetype":"locality"
},
  "geometry": {"coordinates":[18.27504,43.428],"type":"Point"}
}