{
  "type": "Feature",
  "properties": {
    "gn:admin1_code":"BRC",
    "gn:asciiname":"Staro Brezovo Polje",
    "gn:country_code":"BA",
    "gn:dem":89,
    "gn:feature_class":"P",
    "gn:feature_code":"PPL",
    "gn:name":"Staro Brezovo Polje",
    "gn:population":0,
    "gn:timezone":"Europe/Sarajevo",
    "iso:country":"BA",
    "wof:name":"Staro Brezovo Polje",
    "wof:placetype":"locality"
},
  "geometry": {"coordinates":[18.95042,44.84732],"type":"Point"}
}