{
  "type": "Feature",
  "properties": {
    "gn:admin1_code":"02",
    "gn:asciiname":"Gornji Karajzovci",
    "gn:country_code":"BA",
    "gn:dem":98,
    "gn:feature_class":"P",
    "gn:feature_code":"PPLL",
    "gn:name":"Gornji Karajzovci",
    "gn:population":0,
    "gn:timezone":"Europe/Sarajevo",
    "iso:country":"BA",
    "wof:name":"Gornji Karajzovci",
    "wof:placetype":"locality"
},
  "geometry": {"coordinates":[17.36886,45.01827],"type":"Point"}
}