{
  "type": "Feature",
  "properties": {
    "gn:admin1_code":"02",
    "gn:asciiname":"Gornji Karajzovci",
    "gn:country_code":"BA",
    "gn:dem":98,
    "gn:feature_class":"P",
    "gn:feature_code":"PPLL",
    "gn:name":"Gornji Karajzovci",
    "gn:population":0,
    "gn:timezone":"Europe/Sarajevo",
    "iso:country":"BA",
    "name:bos_x_preferred":[
        "Gornji Karajzovci"
    ],
    "name:ceb_x_preferred":[
        "Gornji Karajzovci"
    ],
    "name:fra_x_preferred":[
        "Gornji Karajzovci"
    ],
    "name:hrv_x_preferred":[
        "Gornji Karajzovci"
    ],
    "name:slv_x_preferred":[
        "Gornji Karajzovci"
    ],
    "name:srp_x_preferred":[
        "\u0413\u043e\u0440\u045a\u0438 \u041a\u0430\u0440\u0430\u0458\u0437\u043e\u0432\u0446\u0438"
    ],
    "name:swe_x_preferred":[
        "Gornji Karajzovci"
    ],
    "wof:name":"Gornji Karajzovci",
    "wof:placetype":"locality"
},
  "geometry": {"coordinates":[17.36886,45.01827],"type":"Point"}
}