{
  "type": "Feature",
  "properties": {
    "gn:admin1_code":"01",
    "gn:asciiname":"Peci",
    "gn:country_code":"BA",
    "gn:dem":809,
    "gn:feature_class":"P",
    "gn:feature_code":"PPLL",
    "gn:name":"Pe\u0107i",
    "gn:population":0,
    "gn:timezone":"Europe/Sarajevo",
    "iso:country":"BA",
    "name:und_x_variant":[
        "Pe\u0107i"
    ],
    "wof:name":"Peci",
    "wof:placetype":"locality"
},
  "geometry": {"coordinates":[16.31122,44.23904],"type":"Point"}
}