{
  "type": "Feature",
  "properties": {
    "gn:admin1_code":"01",
    "gn:asciiname":"Puljkovac",
    "gn:country_code":"BA",
    "gn:dem":203,
    "gn:feature_class":"P",
    "gn:feature_code":"PPL",
    "gn:name":"Puljkovac",
    "gn:population":0,
    "gn:timezone":"Europe/Sarajevo",
    "iso:country":"BA",
    "wof:name":"Puljkovac",
    "wof:placetype":"locality"
},
  "geometry": {"coordinates":[18.14463,44.56586],"type":"Point"}
}