{
  "type": "Feature",
  "properties": {
    "gn:admin1_code":"01",
    "gn:asciiname":"Zdralovac",
    "gn:country_code":"BA",
    "gn:dem":924,
    "gn:feature_class":"P",
    "gn:feature_code":"PPL",
    "gn:name":"\u017ddralovac",
    "gn:population":0,
    "gn:timezone":"Europe/Sarajevo",
    "iso:country":"BA",
    "wof:name":"Zdralovac",
    "wof:placetype":"locality"
},
  "geometry": {"coordinates":[16.90032,43.91613],"type":"Point"}
}