{
  "type": "Feature",
  "properties": {
    "gn:admin1_code":"02",
    "gn:asciiname":"Bosanska Jagodina",
    "gn:country_code":"BA",
    "gn:dem":359,
    "gn:feature_class":"P",
    "gn:feature_code":"PPL",
    "gn:name":"Bosanska Jagodina",
    "gn:population":0,
    "gn:timezone":"Europe/Sarajevo",
    "iso:country":"BA",
    "wof:name":"Bosanska Jagodina",
    "wof:placetype":"locality"
},
  "geometry": {"coordinates":[19.35639,43.78361],"type":"Point"}
}