{
  "type": "Feature",
  "properties": {
    "gn:admin1_code":"02",
    "gn:asciiname":"Pecnik",
    "gn:country_code":"BA",
    "gn:dem":234,
    "gn:feature_class":"P",
    "gn:feature_code":"PPL",
    "gn:name":"Pe\u0107nik",
    "gn:population":0,
    "gn:timezone":"Europe/Sarajevo",
    "iso:country":"BA",
    "wof:name":"Pecnik",
    "wof:placetype":"locality"
},
  "geometry": {"coordinates":[18.2375,45.00036],"type":"Point"}
}