{
  "type": "Feature",
  "properties": {
    "gn:admin1_code":"02",
    "gn:asciiname":"Adzici",
    "gn:country_code":"BA",
    "gn:dem":211,
    "gn:feature_class":"P",
    "gn:feature_code":"PPL",
    "gn:name":"Ad\u017ei\u0107i",
    "gn:population":0,
    "gn:timezone":"Europe/Sarajevo",
    "iso:country":"BA",
    "name:bos_x_preferred":[
        "Ad\u017ei\u0107i"
    ],
    "name:ell_x_preferred":[
        "\u0386\u03bd\u03c4\u03b6\u03b9\u03c4\u03c3\u03b9"
    ],
    "name:fra_x_preferred":[
        "Ad\u017ei\u0107i"
    ],
    "name:hrv_x_preferred":[
        "Ad\u017ei\u0107i"
    ],
    "name:slv_x_preferred":[
        "Ad\u017ei\u0107i"
    ],
    "name:srp_x_preferred":[
        "\u0410\u045f\u0438\u045b\u0438"
    ],
    "wof:name":"Adzici",
    "wof:placetype":"locality"
},
  "geometry": {"coordinates":[17.12848,44.99806],"type":"Point"}
}