{
  "type": "Feature",
  "properties": {
    "gn:admin1_code":"01",
    "gn:asciiname":"Gradac",
    "gn:country_code":"BA",
    "gn:dem":143,
    "gn:feature_class":"P",
    "gn:feature_code":"PPLL",
    "gn:name":"Gradac",
    "gn:population":0,
    "gn:timezone":"Europe/Sarajevo",
    "iso:country":"BA",
    "name:bos_x_preferred":[
        "Gradac"
    ],
    "name:cat_x_preferred":[
        "Gradac"
    ],
    "name:ceb_x_preferred":[
        "Gradac"
    ],
    "name:deu_x_preferred":[
        "Gradac"
    ],
    "name:fra_x_preferred":[
        "Gradac"
    ],
    "name:hrv_x_preferred":[
        "Gradac"
    ],
    "name:hun_x_preferred":[
        "Gradac"
    ],
    "name:nld_x_preferred":[
        "Gradac"
    ],
    "name:pol_x_preferred":[
        "Gradac"
    ],
    "name:ron_x_preferred":[
        "Gradac"
    ],
    "name:rus_x_preferred":[
        "\u0413\u0440\u0430\u0434\u0430\u0446"
    ],
    "name:slv_x_preferred":[
        "Gradac"
    ],
    "name:srp_x_preferred":[
        "\u0413\u0440\u0430\u0434\u0430\u0446"
    ],
    "name:swe_x_preferred":[
        "Gradac"
    ],
    "wof:name":"Gradac",
    "wof:placetype":"locality"
},
  "geometry": {"coordinates":[17.73472000000001,42.94806],"type":"Point"}
}