{
  "type": "Feature",
  "properties": {
    "gn:admin1_code":"01",
    "gn:asciiname":"Gradac",
    "gn:country_code":"BA",
    "gn:dem":143,
    "gn:feature_class":"P",
    "gn:feature_code":"PPLL",
    "gn:name":"Gradac",
    "gn:population":0,
    "gn:timezone":"Europe/Sarajevo",
    "iso:country":"BA",
    "wof:name":"Gradac",
    "wof:placetype":"locality"
},
  "geometry": {"coordinates":[17.73472000000001,42.94806],"type":"Point"}
}