{
  "type": "Feature",
  "properties": {
    "gn:admin1_code":"01",
    "gn:asciiname":"Jelah",
    "gn:country_code":"BA",
    "gn:dem":661,
    "gn:feature_class":"P",
    "gn:feature_code":"PPL",
    "gn:name":"Jelah",
    "gn:population":0,
    "gn:timezone":"Europe/Sarajevo",
    "iso:country":"BA",
    "wof:name":"Jelah",
    "wof:placetype":"locality"
},
  "geometry": {"coordinates":[18.83375,43.76113],"type":"Point"}
}