{
  "type": "Feature",
  "properties": {
    "gn:admin1_code":"01",
    "gn:asciiname":"Ahovo",
    "gn:country_code":"BA",
    "gn:dem":201,
    "gn:feature_class":"P",
    "gn:feature_code":"PPL",
    "gn:name":"Ahovo",
    "gn:population":0,
    "gn:timezone":"Europe/Sarajevo",
    "iso:country":"BA",
    "name:und_x_variant":[
        "Aovot",
        "Ahovo"
    ],
    "wof:name":"Ahovo",
    "wof:placetype":"locality"
},
  "geometry": {"coordinates":[15.98887,45.17399],"type":"Point"}
}