{
  "type": "Feature",
  "properties": {
    "gn:admin1_code":"02",
    "gn:asciiname":"Rijeka",
    "gn:country_code":"BA",
    "gn:dem":203,
    "gn:feature_class":"P",
    "gn:feature_code":"PPLL",
    "gn:name":"Rijeka",
    "gn:population":0,
    "gn:timezone":"Europe/Sarajevo",
    "iso:country":"BA",
    "wof:name":"Rijeka",
    "wof:placetype":"locality"
},
  "geometry": {"coordinates":[17.51179,44.90356],"type":"Point"}
}