{
  "type": "Feature",
  "properties": {
    "gn:admin1_code":"01",
    "gn:asciiname":"Donji Odzak",
    "gn:country_code":"BA",
    "gn:dem":1194,
    "gn:feature_class":"P",
    "gn:feature_code":"PPL",
    "gn:name":"Donji Od\u017eak",
    "gn:population":0,
    "gn:timezone":"Europe/Sarajevo",
    "iso:country":"BA",
    "wof:name":"Donji Odzak",
    "wof:placetype":"locality"
},
  "geometry": {"coordinates":[17.28715,43.99347],"type":"Point"}
}