{
  "type": "Feature",
  "properties": {
    "gn:admin1_code":"01",
    "gn:asciiname":"Janjina",
    "gn:country_code":"BA",
    "gn:dem":536,
    "gn:feature_class":"P",
    "gn:feature_code":"PPL",
    "gn:name":"Janjina",
    "gn:population":0,
    "gn:timezone":"Europe/Sarajevo",
    "iso:country":"BA",
    "name:bos_x_preferred":[
        "Janjina"
    ],
    "name:bul_x_preferred":[
        "\u042f\u043d\u0438\u043d\u0430"
    ],
    "name:ces_x_preferred":[
        "Janjina"
    ],
    "name:deu_x_preferred":[
        "Janjina"
    ],
    "name:fra_x_preferred":[
        "Janjina"
    ],
    "name:hrv_x_preferred":[
        "Janjina"
    ],
    "name:hun_x_preferred":[
        "Janjina"
    ],
    "name:ita_x_preferred":[
        "Iagnina"
    ],
    "name:nld_x_preferred":[
        "Janjina"
    ],
    "name:pol_x_preferred":[
        "Gmina Janjina"
    ],
    "name:ron_x_preferred":[
        "Comuna Janjina"
    ],
    "name:rus_x_preferred":[
        "\u042f\u043d\u044c\u0438\u043d\u0430"
    ],
    "name:slk_x_preferred":[
        "Janjina"
    ],
    "name:slv_x_preferred":[
        "Janjina"
    ],
    "name:srp_x_preferred":[
        "\u0408\u0430\u045a\u0438\u043d\u0430"
    ],
    "name:ukr_x_preferred":[
        "\u042f\u043d\u0456\u043d\u0430"
    ],
    "name:urd_x_preferred":[
        "\u062c\u0646\u062c\u06cc\u0646\u0627"
    ],
    "name:war_x_preferred":[
        "Janjina"
    ],
    "wof:name":"Janjina",
    "wof:placetype":"locality"
},
  "geometry": {"coordinates":[18.16431,43.49341],"type":"Point"}
}