{
  "type": "Feature",
  "properties": {
    "gn:admin1_code":"01",
    "gn:asciiname":"Janjina",
    "gn:country_code":"BA",
    "gn:dem":536,
    "gn:feature_class":"P",
    "gn:feature_code":"PPL",
    "gn:name":"Janjina",
    "gn:population":0,
    "gn:timezone":"Europe/Sarajevo",
    "iso:country":"BA",
    "wof:name":"Janjina",
    "wof:placetype":"locality"
},
  "geometry": {"coordinates":[18.16431,43.49341],"type":"Point"}
}