{
  "type": "Feature",
  "properties": {
    "gn:admin1_code":"02",
    "gn:asciiname":"Grabovica",
    "gn:country_code":"BA",
    "gn:dem":954,
    "gn:feature_class":"P",
    "gn:feature_code":"PPL",
    "gn:name":"Grabovica",
    "gn:population":0,
    "gn:timezone":"Europe/Sarajevo",
    "iso:country":"BA",
    "name:bos_x_preferred":[
        "Grabovica"
    ],
    "name:ceb_x_preferred":[
        "Grabovica"
    ],
    "name:deu_x_preferred":[
        "Grabovica"
    ],
    "name:fra_x_preferred":[
        "Grabovica"
    ],
    "name:hrv_x_preferred":[
        "Grabovica"
    ],
    "name:hun_x_preferred":[
        "Grabovica"
    ],
    "name:nld_x_preferred":[
        "Grabovica"
    ],
    "name:slv_x_preferred":[
        "Grabovica"
    ],
    "name:srp_x_preferred":[
        "\u0413\u0440\u0430\u0431\u043e\u0432\u0438\u0446\u0430"
    ],
    "name:swe_x_preferred":[
        "Grabovica"
    ],
    "wof:name":"Grabovica",
    "wof:placetype":"locality"
},
  "geometry": {"coordinates":[18.6836,43.77787],"type":"Point"}
}