{
  "type": "Feature",
  "properties": {
    "gn:admin1_code":"02",
    "gn:asciiname":"Velika Ljubina",
    "gn:country_code":"BA",
    "gn:dem":1098,
    "gn:feature_class":"P",
    "gn:feature_code":"PPL",
    "gn:name":"Velika Ljubina",
    "gn:population":0,
    "gn:timezone":"Europe/Sarajevo",
    "iso:country":"BA",
    "name:und_x_variant":[
        "Ljubina",
        "Velika Ljubina"
    ],
    "wof:name":"Velika Ljubina",
    "wof:placetype":"locality"
},
  "geometry": {"coordinates":[18.66409,43.42269],"type":"Point"}
}