{
  "type": "Feature",
  "properties": {
    "gn:admin1_code":"02",
    "gn:asciiname":"Ljeskovik",
    "gn:country_code":"BA",
    "gn:dem":880,
    "gn:feature_class":"P",
    "gn:feature_code":"PPL",
    "gn:name":"Ljeskovik",
    "gn:population":0,
    "gn:timezone":"Europe/Sarajevo",
    "iso:country":"BA",
    "name:bos_x_preferred":[
        "Ljeskovik"
    ],
    "name:fra_x_preferred":[
        "Ljeskovik"
    ],
    "name:hrv_x_preferred":[
        "Ljeskovik"
    ],
    "name:srp_x_preferred":[
        "\u0409\u0435\u0441\u043a\u043e\u0432\u0438\u043a"
    ],
    "wof:name":"Ljeskovik",
    "wof:placetype":"locality"
},
  "geometry": {"coordinates":[18.97176,43.5938],"type":"Point"}
}