{
  "type": "Feature",
  "properties": {
    "gn:admin1_code":"01",
    "gn:asciiname":"Sivrino Selo",
    "gn:country_code":"BA",
    "gn:dem":504,
    "gn:feature_class":"P",
    "gn:feature_code":"PPL",
    "gn:name":"Sivrino Selo",
    "gn:population":0,
    "gn:timezone":"Europe/Sarajevo",
    "iso:country":"BA",
    "wof:name":"Sivrino Selo",
    "wof:placetype":"locality"
},
  "geometry": {"coordinates":[17.82689,44.15508],"type":"Point"}
}