{
  "type": "Feature",
  "properties": {
    "gn:admin1_code":"01",
    "gn:asciiname":"Piskavica",
    "gn:country_code":"BA",
    "gn:dem":300,
    "gn:feature_class":"P",
    "gn:feature_code":"PPLL",
    "gn:name":"Piskavica",
    "gn:population":0,
    "gn:timezone":"Europe/Sarajevo",
    "iso:country":"BA",
    "name:und_x_variant":[
        "Gornja Piskavica",
        "Donja Piskavica",
        "Piskavica"
    ],
    "wof:name":"Piskavica",
    "wof:placetype":"locality"
},
  "geometry": {"coordinates":[18.34202,44.73042],"type":"Point"}
}