{
  "type": "Feature",
  "properties": {
    "gn:admin1_code":"01",
    "gn:asciiname":"Ahinbasici",
    "gn:country_code":"BA",
    "gn:dem":290,
    "gn:feature_class":"P",
    "gn:feature_code":"PPL",
    "gn:name":"Ahinba\u0161i\u0107i",
    "gn:population":0,
    "gn:timezone":"Europe/Sarajevo",
    "iso:country":"BA",
    "wof:name":"Ahinbasici",
    "wof:placetype":"locality"
},
  "geometry": {"coordinates":[18.20124,44.73375],"type":"Point"}
}