{
  "type": "Feature",
  "properties": {
    "gn:admin1_code":"02",
    "gn:asciiname":"Rakovica",
    "gn:country_code":"BA",
    "gn:dem":113,
    "gn:feature_class":"P",
    "gn:feature_code":"PPL",
    "gn:name":"Rakovica",
    "gn:population":0,
    "gn:timezone":"Europe/Sarajevo",
    "iso:country":"BA",
    "wof:name":"Rakovica",
    "wof:placetype":"locality"
},
  "geometry": {"coordinates":[16.89869,45.18696],"type":"Point"}
}