{
  "type": "Feature",
  "properties": {
    "gn:admin1_code":"02",
    "gn:asciiname":"Rakovica",
    "gn:country_code":"BA",
    "gn:dem":113,
    "gn:feature_class":"P",
    "gn:feature_code":"PPL",
    "gn:name":"Rakovica",
    "gn:population":0,
    "gn:timezone":"Europe/Sarajevo",
    "iso:country":"BA",
    "name:bos_x_preferred":[
        "Rakovica"
    ],
    "name:bul_x_preferred":[
        "\u0420\u0430\u043a\u043e\u0432\u0438\u0446\u0430"
    ],
    "name:ceb_x_preferred":[
        "Rakovica"
    ],
    "name:deu_x_preferred":[
        "Rakovica"
    ],
    "name:fra_x_preferred":[
        "Rakovica"
    ],
    "name:hrv_x_preferred":[
        "Rakovica"
    ],
    "name:hun_x_preferred":[
        "Rakovica"
    ],
    "name:nld_x_preferred":[
        "Rakovica"
    ],
    "name:ron_x_preferred":[
        "Rakovica"
    ],
    "name:rus_x_preferred":[
        "\u0420\u0430\u043a\u043e\u0432\u0438\u0446\u0430"
    ],
    "name:sco_x_preferred":[
        "Rakovica"
    ],
    "name:slv_x_preferred":[
        "Rakovica"
    ],
    "name:srp_x_preferred":[
        "\u0420\u0430\u043a\u043e\u0432\u0438\u0446\u0430"
    ],
    "name:swe_x_preferred":[
        "Rakovica"
    ],
    "name:ukr_x_preferred":[
        "\u0420\u0430\u043a\u043e\u0432\u0456\u0446\u0430"
    ],
    "wof:name":"Rakovica",
    "wof:placetype":"locality"
},
  "geometry": {"coordinates":[16.89869,45.18696],"type":"Point"}
}