{
  "type": "Feature",
  "properties": {
    "gn:admin1_code":"01",
    "gn:asciiname":"Hafizovici",
    "gn:country_code":"BA",
    "gn:dem":293,
    "gn:feature_class":"P",
    "gn:feature_code":"PPL",
    "gn:name":"Hafizovi\u0107i",
    "gn:population":0,
    "gn:timezone":"Europe/Sarajevo",
    "iso:country":"BA",
    "wof:name":"Hafizovici",
    "wof:placetype":"locality"
},
  "geometry": {"coordinates":[16.10716,44.99342],"type":"Point"}
}