{
  "type": "Feature",
  "properties": {
    "gn:admin1_code":"02",
    "gn:asciiname":"Cekrk",
    "gn:country_code":"BA",
    "gn:dem":774,
    "gn:feature_class":"P",
    "gn:feature_code":"PPL",
    "gn:name":"\u010cekrk",
    "gn:population":0,
    "gn:timezone":"Europe/Sarajevo",
    "iso:country":"BA",
    "wof:name":"Cekrk",
    "wof:placetype":"locality"
},
  "geometry": {"coordinates":[19.15139,43.93583],"type":"Point"}
}