{
  "type": "Feature",
  "properties": {
    "gn:admin1_code":"01",
    "gn:asciiname":"Milosev Dolac",
    "gn:country_code":"BA",
    "gn:dem":496,
    "gn:feature_class":"P",
    "gn:feature_code":"PPL",
    "gn:name":"Milo\u0161ev Dolac",
    "gn:population":0,
    "gn:timezone":"Europe/Sarajevo",
    "iso:country":"BA",
    "wof:name":"Milosev Dolac",
    "wof:placetype":"locality"
},
  "geometry": {"coordinates":[17.41122,43.38616],"type":"Point"}
}