{
  "type": "Feature",
  "properties": {
    "gn:admin1_code":"01",
    "gn:asciiname":"Fazlici",
    "gn:country_code":"BA",
    "gn:dem":174,
    "gn:feature_class":"P",
    "gn:feature_code":"PPL",
    "gn:name":"Fazli\u0107i",
    "gn:population":0,
    "gn:timezone":"Europe/Sarajevo",
    "iso:country":"BA",
    "wof:name":"Fazlici",
    "wof:placetype":"locality"
},
  "geometry": {"coordinates":[18.45907,44.81291],"type":"Point"}
}