{
  "type": "Feature",
  "properties": {
    "gn:admin1_code":"01",
    "gn:asciiname":"Rujevac",
    "gn:country_code":"BA",
    "gn:dem":212,
    "gn:feature_class":"P",
    "gn:feature_code":"PPL",
    "gn:name":"Rujevac",
    "gn:population":0,
    "gn:timezone":"Europe/Sarajevo",
    "iso:country":"BA",
    "wof:name":"Rujevac",
    "wof:placetype":"locality"
},
  "geometry": {"coordinates":[17.77212,43.09054],"type":"Point"}
}