{
  "type": "Feature",
  "properties": {
    "gn:admin1_code":"01",
    "gn:asciiname":"Rujevac",
    "gn:country_code":"BA",
    "gn:dem":212,
    "gn:feature_class":"P",
    "gn:feature_code":"PPL",
    "gn:name":"Rujevac",
    "gn:population":0,
    "gn:timezone":"Europe/Sarajevo",
    "iso:country":"BA",
    "name:fas_x_preferred":[
        "\u0631\u0648\u06cc\u0648\u0627\u062a\u0633"
    ],
    "name:fra_x_preferred":[
        "Rujevac"
    ],
    "name:msa_x_preferred":[
        "Rujevac"
    ],
    "name:nld_x_preferred":[
        "Rujevac"
    ],
    "name:por_x_preferred":[
        "Rujevac"
    ],
    "name:slv_x_preferred":[
        "Rujevac"
    ],
    "name:srp_x_preferred":[
        "\u0420\u0443\u0458\u0435\u0432\u0430\u0446"
    ],
    "wof:name":"Rujevac",
    "wof:placetype":"locality"
},
  "geometry": {"coordinates":[17.77212,43.09054],"type":"Point"}
}