{
  "type": "Feature",
  "properties": {
    "gn:admin1_code":"02",
    "gn:asciiname":"Gornji Volar",
    "gn:country_code":"BA",
    "gn:dem":208,
    "gn:feature_class":"P",
    "gn:feature_code":"PPLL",
    "gn:name":"Gornji Volar",
    "gn:population":0,
    "gn:timezone":"Europe/Sarajevo",
    "iso:country":"BA",
    "name:und_x_variant":[
        "Volar Gornji",
        "Katoli\u010dki Volar",
        "Gornji Volar"
    ],
    "wof:name":"Gornji Volar",
    "wof:placetype":"locality"
},
  "geometry": {"coordinates":[16.56478,44.96294],"type":"Point"}
}