{
  "type": "Feature",
  "properties": {
    "gn:admin1_code":"01",
    "gn:asciiname":"Trninici",
    "gn:country_code":"BA",
    "gn:dem":1043,
    "gn:feature_class":"P",
    "gn:feature_code":"PPL",
    "gn:name":"Trnini\u0107i",
    "gn:population":0,
    "gn:timezone":"Europe/Sarajevo",
    "iso:country":"BA",
    "wof:name":"Trninici",
    "wof:placetype":"locality"
},
  "geometry": {"coordinates":[16.44167,44.41111],"type":"Point"}
}