{
  "type": "Feature",
  "properties": {
    "gn:admin1_code":"02",
    "gn:asciiname":"Zabari",
    "gn:country_code":"BA",
    "gn:dem":96,
    "gn:feature_class":"P",
    "gn:feature_code":"PPL",
    "gn:name":"\u017dabari",
    "gn:population":0,
    "gn:timezone":"Europe/Sarajevo",
    "iso:country":"BA",
    "wof:name":"Zabari",
    "wof:placetype":"locality"
},
  "geometry": {"coordinates":[17.25855,45.02969],"type":"Point"}
}