{
  "type": "Feature",
  "properties": {
    "gn:admin1_code":"02",
    "gn:asciiname":"Hrvacani",
    "gn:country_code":"BA",
    "gn:dem":461,
    "gn:feature_class":"P",
    "gn:feature_code":"PPL",
    "gn:name":"Hrva\u0107ani",
    "gn:population":0,
    "gn:timezone":"Europe/Sarajevo",
    "iso:country":"BA",
    "wof:name":"Hrvacani",
    "wof:placetype":"locality"
},
  "geometry": {"coordinates":[17.4627,44.60651],"type":"Point"}
}