{
  "type": "Feature",
  "properties": {
    "gn:admin1_code":"01",
    "gn:asciiname":"Doci",
    "gn:country_code":"BA",
    "gn:dem":303,
    "gn:feature_class":"P",
    "gn:feature_code":"PPL",
    "gn:name":"Doci",
    "gn:population":0,
    "gn:timezone":"Europe/Sarajevo",
    "iso:country":"BA",
    "wof:name":"Doci",
    "wof:placetype":"locality"
},
  "geometry": {"coordinates":[17.85187999999999,43.71512],"type":"Point"}
}