{
  "type": "Feature",
  "properties": {
    "gn:admin1_code":"01",
    "gn:asciiname":"Donja Veceriska",
    "gn:country_code":"BA",
    "gn:dem":476,
    "gn:feature_class":"P",
    "gn:feature_code":"PPL",
    "gn:name":"Donja Ve\u010deriska",
    "gn:population":0,
    "gn:timezone":"Europe/Sarajevo",
    "iso:country":"BA",
    "name:und_x_variant":[
        "Donja Ve\u010derska",
        "Donja Ve\u010deriska"
    ],
    "wof:name":"Donja Veceriska",
    "wof:placetype":"locality"
},
  "geometry": {"coordinates":[17.76243999999999,44.15666],"type":"Point"}
}