{
  "type": "Feature",
  "properties": {
    "gn:admin1_code":"01",
    "gn:asciiname":"Selmani",
    "gn:country_code":"BA",
    "gn:dem":871,
    "gn:feature_class":"P",
    "gn:feature_code":"PPL",
    "gn:name":"Selmani",
    "gn:population":0,
    "gn:timezone":"Europe/Sarajevo",
    "iso:country":"BA",
    "wof:name":"Selmani",
    "wof:placetype":"locality"
},
  "geometry": {"coordinates":[17.4954,44.1528],"type":"Point"}
}