{
  "type": "Feature",
  "properties": {
    "gn:admin1_code":"01",
    "gn:asciiname":"Zagone",
    "gn:country_code":"BA",
    "gn:dem":775,
    "gn:feature_class":"P",
    "gn:feature_code":"PPL",
    "gn:name":"Zagone",
    "gn:population":0,
    "gn:timezone":"Europe/Sarajevo",
    "iso:country":"BA",
    "wof:name":"Zagone",
    "wof:placetype":"locality"
},
  "geometry": {"coordinates":[18.04191,44.15475],"type":"Point"}
}