{
  "type": "Feature",
  "properties": {
    "gn:admin1_code":"01",
    "gn:asciiname":"Gornje Selo",
    "gn:country_code":"BA",
    "gn:dem":669,
    "gn:feature_class":"P",
    "gn:feature_code":"PPL",
    "gn:name":"Gornje Selo",
    "gn:population":0,
    "gn:timezone":"Europe/Sarajevo",
    "iso:country":"BA",
    "wof:name":"Gornje Selo",
    "wof:placetype":"locality"
},
  "geometry": {"coordinates":[17.48446,43.82024000000001],"type":"Point"}
}