{
  "type": "Feature",
  "properties": {
    "gn:admin1_code":"01",
    "gn:asciiname":"Lopatice",
    "gn:country_code":"BA",
    "gn:dem":733,
    "gn:feature_class":"P",
    "gn:feature_code":"PPL",
    "gn:name":"Lopatice",
    "gn:population":0,
    "gn:timezone":"Europe/Sarajevo",
    "iso:country":"BA",
    "wof:name":"Lopatice",
    "wof:placetype":"locality"
},
  "geometry": {"coordinates":[17.71132,44.27276],"type":"Point"}
}