{
  "type": "Feature",
  "properties": {
    "gn:admin1_code":"02",
    "gn:asciiname":"Tomasi",
    "gn:country_code":"BA",
    "gn:dem":135,
    "gn:feature_class":"P",
    "gn:feature_code":"PPL",
    "gn:name":"Toma\u0161i",
    "gn:population":0,
    "gn:timezone":"Europe/Sarajevo",
    "iso:country":"BA",
    "wof:name":"Tomasi",
    "wof:placetype":"locality"
},
  "geometry": {"coordinates":[17.77587,44.88048],"type":"Point"}
}