{
  "type": "Feature",
  "properties": {
    "gn:admin1_code":"01",
    "gn:asciiname":"Arambasici",
    "gn:country_code":"BA",
    "gn:dem":571,
    "gn:feature_class":"P",
    "gn:feature_code":"PPL",
    "gn:name":"Aramba\u0161i\u0107i",
    "gn:population":0,
    "gn:timezone":"Europe/Sarajevo",
    "iso:country":"BA",
    "wof:name":"Arambasici",
    "wof:placetype":"locality"
},
  "geometry": {"coordinates":[17.31444,43.33],"type":"Point"}
}