{
  "type": "Feature",
  "properties": {
    "gn:admin1_code":"02",
    "gn:asciiname":"Katavici",
    "gn:country_code":"BA",
    "gn:dem":197,
    "gn:feature_class":"P",
    "gn:feature_code":"PPL",
    "gn:name":"Katavi\u0107i",
    "gn:population":0,
    "gn:timezone":"Europe/Sarajevo",
    "iso:country":"BA",
    "wof:name":"Katavici",
    "wof:placetype":"locality"
},
  "geometry": {"coordinates":[18.05175,44.85259],"type":"Point"}
}