{
  "type": "Feature",
  "properties": {
    "gn:admin1_code":"01",
    "gn:asciiname":"Grabovina",
    "gn:country_code":"BA",
    "gn:dem":17,
    "gn:feature_class":"P",
    "gn:feature_code":"PPL",
    "gn:name":"Grabovina",
    "gn:population":0,
    "gn:timezone":"Europe/Sarajevo",
    "iso:country":"BA",
    "wof:name":"Grabovina",
    "wof:placetype":"locality"
},
  "geometry": {"coordinates":[17.68833,43.11167],"type":"Point"}
}