{
  "type": "Feature",
  "properties": {
    "gn:admin1_code":"01",
    "gn:asciiname":"Kopanje",
    "gn:country_code":"BA",
    "gn:dem":1201,
    "gn:feature_class":"P",
    "gn:feature_code":"PPL",
    "gn:name":"Kopanje",
    "gn:population":0,
    "gn:timezone":"Europe/Sarajevo",
    "iso:country":"BA",
    "wof:name":"Kopanje",
    "wof:placetype":"locality"
},
  "geometry": {"coordinates":[16.97121,44.13969],"type":"Point"}
}