{
  "type": "Feature",
  "properties": {
    "gn:admin1_code":"01",
    "gn:asciiname":"Sabanci",
    "gn:country_code":"BA",
    "gn:dem":1008,
    "gn:feature_class":"P",
    "gn:feature_code":"PPL",
    "gn:name":"\u0160abanci",
    "gn:population":0,
    "gn:timezone":"Europe/Sarajevo",
    "iso:country":"BA",
    "name:bos_x_preferred":[
        "\u0160abanci"
    ],
    "name:fra_x_preferred":[
        "\u0160abanci"
    ],
    "name:urd_x_preferred":[
        "\u0633\u0628\u0646\u06a9\u06cc"
    ],
    "wof:name":"Sabanci",
    "wof:placetype":"locality"
},
  "geometry": {"coordinates":[18.50901,44.05802],"type":"Point"}
}