{
  "type": "Feature",
  "properties": {
    "gn:admin1_code":"02",
    "gn:asciiname":"Plana",
    "gn:country_code":"BA",
    "gn:dem":596,
    "gn:feature_class":"P",
    "gn:feature_code":"PPLL",
    "gn:name":"Plana",
    "gn:population":0,
    "gn:timezone":"Europe/Sarajevo",
    "iso:country":"BA",
    "name:arg_x_preferred":[
        "Plana"
    ],
    "name:bos_x_preferred":[
        "Plana"
    ],
    "name:cat_x_preferred":[
        "Plana"
    ],
    "name:ceb_x_preferred":[
        "Plana"
    ],
    "name:deu_x_preferred":[
        "Plana"
    ],
    "name:fra_x_preferred":[
        "Plana"
    ],
    "name:hrv_x_preferred":[
        "Plana"
    ],
    "name:ita_x_preferred":[
        "Plana"
    ],
    "name:jpn_x_preferred":[
        "\u30d7\u30e9\u30ca"
    ],
    "name:lat_x_preferred":[
        "Plana"
    ],
    "name:nld_x_preferred":[
        "Plana"
    ],
    "name:por_x_preferred":[
        "Plana"
    ],
    "name:rus_x_preferred":[
        "\u041f\u043b\u0430\u043d\u0430"
    ],
    "name:slk_x_preferred":[
        "Plana"
    ],
    "name:slv_x_preferred":[
        "Plana"
    ],
    "name:srp_x_preferred":[
        "\u041f\u043b\u0430\u043d\u0430"
    ],
    "name:swe_x_preferred":[
        "Plana"
    ],
    "name:ukr_x_preferred":[
        "\u041f\u043b\u0430\u043d\u0430"
    ],
    "wof:name":"Plana",
    "wof:placetype":"locality"
},
  "geometry": {"coordinates":[18.39784,42.96744],"type":"Point"}
}