{
  "type": "Feature",
  "properties": {
    "gn:admin1_code":"01",
    "gn:asciiname":"Samograd",
    "gn:country_code":"BA",
    "gn:dem":1215,
    "gn:feature_class":"P",
    "gn:feature_code":"PPL",
    "gn:name":"Samograd",
    "gn:population":0,
    "gn:timezone":"Europe/Sarajevo",
    "iso:country":"BA",
    "wof:name":"Samograd",
    "wof:placetype":"locality"
},
  "geometry": {"coordinates":[16.80943,44.2579],"type":"Point"}
}