{
  "type": "Feature",
  "properties": {
    "gn:admin1_code":"01",
    "gn:asciiname":"Duzica",
    "gn:country_code":"BA",
    "gn:dem":295,
    "gn:feature_class":"P",
    "gn:feature_code":"PPL",
    "gn:name":"Du\u017ei\u010da",
    "gn:population":0,
    "gn:timezone":"Europe/Sarajevo",
    "iso:country":"BA",
    "wof:name":"Duzica",
    "wof:placetype":"locality"
},
  "geometry": {"coordinates":[17.86601,42.92175],"type":"Point"}
}