{
  "type": "Feature",
  "properties": {
    "gn:admin1_code":"01",
    "gn:asciiname":"Dzindici",
    "gn:country_code":"BA",
    "gn:dem":652,
    "gn:feature_class":"P",
    "gn:feature_code":"PPL",
    "gn:name":"D\u017eindi\u0107i",
    "gn:population":0,
    "gn:timezone":"Europe/Sarajevo",
    "iso:country":"BA",
    "wof:name":"Dzindici",
    "wof:placetype":"locality"
},
  "geometry": {"coordinates":[18.06038,44.06044],"type":"Point"}
}