{
  "type": "Feature",
  "properties": {
    "gn:admin1_code":"02",
    "gn:asciiname":"Vratlo",
    "gn:country_code":"BA",
    "gn:dem":1186,
    "gn:feature_class":"P",
    "gn:feature_code":"PPL",
    "gn:name":"Vratlo",
    "gn:population":0,
    "gn:timezone":"Europe/Sarajevo",
    "iso:country":"BA",
    "wof:name":"Vratlo",
    "wof:placetype":"locality"
},
  "geometry": {"coordinates":[18.55193,43.49225],"type":"Point"}
}