{
  "type": "Feature",
  "properties": {
    "gn:admin1_code":"01",
    "gn:asciiname":"Perici",
    "gn:country_code":"BA",
    "gn:dem":174,
    "gn:feature_class":"P",
    "gn:feature_code":"PPL",
    "gn:name":"Peri\u0107i",
    "gn:population":0,
    "gn:timezone":"Europe/Sarajevo",
    "iso:country":"BA",
    "name:und_x_variant":[
        "Perica Mah",
        "Peri\u0107i"
    ],
    "wof:name":"Perici",
    "wof:placetype":"locality"
},
  "geometry": {"coordinates":[17.37529,43.29874],"type":"Point"}
}