{
  "type": "Feature",
  "properties": {
    "gn:admin1_code":"01",
    "gn:asciiname":"Ljetovik",
    "gn:country_code":"BA",
    "gn:dem":469,
    "gn:feature_class":"P",
    "gn:feature_code":"PPL",
    "gn:name":"Ljetovik",
    "gn:population":0,
    "gn:timezone":"Europe/Sarajevo",
    "iso:country":"BA",
    "name:bos_x_preferred":[
        "Ljetovik"
    ],
    "name:ceb_x_preferred":[
        "Ljetovik"
    ],
    "name:fra_x_preferred":[
        "Ljetovik"
    ],
    "name:hrv_x_preferred":[
        "Ljetovik"
    ],
    "name:swe_x_preferred":[
        "Ljetovik"
    ],
    "wof:name":"Ljetovik",
    "wof:placetype":"locality"
},
  "geometry": {"coordinates":[18.17,43.98389],"type":"Point"}
}