{
  "type": "Feature",
  "properties": {
    "gn:admin1_code":"01",
    "gn:asciiname":"Here",
    "gn:country_code":"BA",
    "gn:dem":1130,
    "gn:feature_class":"P",
    "gn:feature_code":"PPL",
    "gn:name":"Here",
    "gn:population":0,
    "gn:timezone":"Europe/Sarajevo",
    "iso:country":"BA",
    "name:deu_x_preferred":[
        "Here"
    ],
    "name:fra_x_preferred":[
        "Here"
    ],
    "name:hun_x_preferred":[
        "Here"
    ],
    "name:ita_x_preferred":[
        "Here"
    ],
    "name:jpn_x_preferred":[
        "Here"
    ],
    "name:nld_x_preferred":[
        "Here"
    ],
    "name:rus_x_preferred":[
        "\u0417\u0434\u0435\u0441\u044c"
    ],
    "name:slk_x_preferred":[
        "Here"
    ],
    "name:war_x_preferred":[
        "Nganhi"
    ],
    "name:zho_x_preferred":[
        "Here"
    ],
    "wof:name":"Here",
    "wof:placetype":"locality"
},
  "geometry": {"coordinates":[17.80528,43.81],"type":"Point"}
}