{
  "type": "Feature",
  "properties": {
    "gn:admin1_code":"01",
    "gn:asciiname":"Hasici",
    "gn:country_code":"BA",
    "gn:dem":445,
    "gn:feature_class":"P",
    "gn:feature_code":"PPL",
    "gn:name":"Hasi\u0107i",
    "gn:population":0,
    "gn:timezone":"Europe/Sarajevo",
    "iso:country":"BA",
    "name:bos_x_preferred":[
        "Hasi\u0107i"
    ],
    "name:ceb_x_preferred":[
        "Hasi\u0107i"
    ],
    "name:fra_x_preferred":[
        "Hasi\u0107i"
    ],
    "name:srp_x_preferred":[
        "\u0425\u0430\u0441\u0438\u045b\u0438"
    ],
    "name:swe_x_preferred":[
        "Hasi\u0107i"
    ],
    "name:und_x_variant":[
        "Hasi\u0107i"
    ],
    "wof:name":"Hasici",
    "wof:placetype":"locality"
},
  "geometry": {"coordinates":[16.72917,44.53806],"type":"Point"}
}