{
  "type": "Feature",
  "properties": {
    "gn:admin1_code":"02",
    "gn:asciiname":"Gornje Polje",
    "gn:country_code":"BA",
    "gn:dem":368,
    "gn:feature_class":"P",
    "gn:feature_code":"PPL",
    "gn:name":"Gornje Polje",
    "gn:population":0,
    "gn:timezone":"Europe/Sarajevo",
    "iso:country":"BA",
    "wof:name":"Gornje Polje",
    "wof:placetype":"locality"
},
  "geometry": {"coordinates":[19.41278,43.59466],"type":"Point"}
}