{
  "type": "Feature",
  "properties": {
    "gn:admin1_code":"02",
    "gn:asciiname":"Tatici",
    "gn:country_code":"BA",
    "gn:dem":134,
    "gn:feature_class":"P",
    "gn:feature_code":"PPL",
    "gn:name":"Tati\u0107i",
    "gn:population":0,
    "gn:timezone":"Europe/Sarajevo",
    "iso:country":"BA",
    "wof:name":"Tatici",
    "wof:placetype":"locality"
},
  "geometry": {"coordinates":[17.26057999999999,44.87225],"type":"Point"}
}