{
  "type": "Feature",
  "properties": {
    "gn:admin1_code":"02",
    "gn:asciiname":"Peilovici",
    "gn:country_code":"BA",
    "gn:dem":292,
    "gn:feature_class":"P",
    "gn:feature_code":"PPL",
    "gn:name":"Peilovi\u0107i",
    "gn:population":0,
    "gn:timezone":"Europe/Sarajevo",
    "iso:country":"BA",
    "wof:name":"Peilovici",
    "wof:placetype":"locality"
},
  "geometry": {"coordinates":[16.57078,45.07824],"type":"Point"}
}