{
  "type": "Feature",
  "properties": {
    "gn:admin1_code":"02",
    "gn:asciiname":"Bjeletic",
    "gn:country_code":"BA",
    "gn:dem":899,
    "gn:feature_class":"P",
    "gn:feature_code":"PPL",
    "gn:name":"Bjeleti\u0107",
    "gn:population":0,
    "gn:timezone":"Europe/Sarajevo",
    "iso:country":"BA",
    "wof:name":"Bjeletic",
    "wof:placetype":"locality"
},
  "geometry": {"coordinates":[18.9275,43.90203],"type":"Point"}
}