{
  "type": "Feature",
  "properties": {
    "gn:admin1_code":"02",
    "gn:asciiname":"Navolici",
    "gn:country_code":"BA",
    "gn:dem":426,
    "gn:feature_class":"P",
    "gn:feature_code":"PPL",
    "gn:name":"Navoli\u0107i",
    "gn:population":0,
    "gn:timezone":"Europe/Sarajevo",
    "iso:country":"BA",
    "wof:name":"Navolici",
    "wof:placetype":"locality"
},
  "geometry": {"coordinates":[17.06712000000001,44.71865],"type":"Point"}
}