{
  "type": "Feature",
  "properties": {
    "gn:admin1_code":"02",
    "gn:asciiname":"Donje Vrbno",
    "gn:country_code":"BA",
    "gn:dem":509,
    "gn:feature_class":"P",
    "gn:feature_code":"PPL",
    "gn:name":"Donje Vrbno",
    "gn:population":0,
    "gn:timezone":"Europe/Sarajevo",
    "iso:country":"BA",
    "wof:name":"Donje Vrbno",
    "wof:placetype":"locality"
},
  "geometry": {"coordinates":[18.43393,42.72858],"type":"Point"}
}