{
  "type": "Feature",
  "properties": {
    "gn:admin1_code":"02",
    "gn:asciiname":"Samardzije",
    "gn:country_code":"BA",
    "gn:dem":238,
    "gn:feature_class":"P",
    "gn:feature_code":"PPLL",
    "gn:name":"Samard\u017eije",
    "gn:population":0,
    "gn:timezone":"Europe/Sarajevo",
    "iso:country":"BA",
    "name:und_x_variant":[
        "Samard\u017eije"
    ],
    "wof:name":"Samardzije",
    "wof:placetype":"locality"
},
  "geometry": {"coordinates":[17.12587000000001,45.01737],"type":"Point"}
}