{
  "type": "Feature",
  "properties": {
    "gn:admin1_code":"01",
    "gn:asciiname":"Karaula",
    "gn:country_code":"BA",
    "gn:dem":356,
    "gn:feature_class":"P",
    "gn:feature_code":"PPL",
    "gn:name":"Karaula",
    "gn:population":0,
    "gn:timezone":"Europe/Sarajevo",
    "iso:country":"BA",
    "wof:name":"Karaula",
    "wof:placetype":"locality"
},
  "geometry": {"coordinates":[18.04491,44.46192],"type":"Point"}
}