{
  "type": "Feature",
  "properties": {
    "gn:admin1_code":"01",
    "gn:asciiname":"Dogani",
    "gn:country_code":"BA",
    "gn:dem":968,
    "gn:feature_class":"P",
    "gn:feature_code":"PPL",
    "gn:name":"Dogani",
    "gn:population":0,
    "gn:timezone":"Europe/Sarajevo",
    "iso:country":"BA",
    "wof:name":"Dogani",
    "wof:placetype":"locality"
},
  "geometry": {"coordinates":[17.40014,44.28063],"type":"Point"}
}