{
  "type": "Feature",
  "properties": {
    "gn:admin1_code":"BRC",
    "gn:asciiname":"Radosevici",
    "gn:country_code":"BA",
    "gn:dem":110,
    "gn:feature_class":"P",
    "gn:feature_code":"PPL",
    "gn:name":"Rado\u0161evi\u0107i",
    "gn:population":0,
    "gn:timezone":"Europe/Sarajevo",
    "iso:country":"BA",
    "wof:name":"Radosevici",
    "wof:placetype":"locality"
},
  "geometry": {"coordinates":[18.7104,44.85318],"type":"Point"}
}