{
  "type": "Feature",
  "properties": {
    "gn:admin1_code":"02",
    "gn:asciiname":"Dordani",
    "gn:country_code":"BA",
    "gn:dem":284,
    "gn:feature_class":"P",
    "gn:feature_code":"PPL",
    "gn:name":"\u00d0ordani",
    "gn:population":0,
    "gn:timezone":"Europe/Sarajevo",
    "iso:country":"BA",
    "wof:name":"Dordani",
    "wof:placetype":"locality"
},
  "geometry": {"coordinates":[17.73497,44.59437],"type":"Point"}
}