{
  "type": "Feature",
  "properties": {
    "gn:admin1_code":"01",
    "gn:asciiname":"Vujinovici",
    "gn:country_code":"BA",
    "gn:dem":401,
    "gn:feature_class":"P",
    "gn:feature_code":"PPL",
    "gn:name":"Vujinovi\u0107i",
    "gn:population":0,
    "gn:timezone":"Europe/Sarajevo",
    "iso:country":"BA",
    "wof:name":"Vujinovici",
    "wof:placetype":"locality"
},
  "geometry": {"coordinates":[16.7585,44.69184],"type":"Point"}
}