{
  "type": "Feature",
  "properties": {
    "gn:admin1_code":"01",
    "gn:asciiname":"Dudovine",
    "gn:country_code":"BA",
    "gn:dem":290,
    "gn:feature_class":"P",
    "gn:feature_code":"PPL",
    "gn:name":"Dudovine",
    "gn:population":0,
    "gn:timezone":"Europe/Sarajevo",
    "iso:country":"BA",
    "wof:name":"Dudovine",
    "wof:placetype":"locality"
},
  "geometry": {"coordinates":[17.90867,43.14399],"type":"Point"}
}