{
  "type": "Feature",
  "properties": {
    "gn:admin1_code":"01",
    "gn:asciiname":"Ravna",
    "gn:country_code":"BA",
    "gn:dem":342,
    "gn:feature_class":"P",
    "gn:feature_code":"PPLL",
    "gn:name":"Ravna",
    "gn:population":0,
    "gn:timezone":"Europe/Sarajevo",
    "iso:country":"BA",
    "wof:name":"Ravna",
    "wof:placetype":"locality"
},
  "geometry": {"coordinates":[18.05695,44.5855],"type":"Point"}
}