{
  "type": "Feature",
  "properties": {
    "gn:admin1_code":"01",
    "gn:asciiname":"Ravna",
    "gn:country_code":"BA",
    "gn:dem":342,
    "gn:feature_class":"P",
    "gn:feature_code":"PPLL",
    "gn:name":"Ravna",
    "gn:population":0,
    "gn:timezone":"Europe/Sarajevo",
    "iso:country":"BA",
    "name:bos_x_preferred":[
        "Ravna"
    ],
    "name:bul_x_preferred":[
        "\u0420\u0430\u0432\u043d\u0430"
    ],
    "name:ceb_x_preferred":[
        "Ravna"
    ],
    "name:fra_x_preferred":[
        "Ravna"
    ],
    "name:hrv_x_preferred":[
        "Ravna"
    ],
    "name:ron_x_preferred":[
        "Ravna"
    ],
    "name:rus_x_preferred":[
        "\u0420\u0430\u0432\u043d\u0430"
    ],
    "name:slv_x_preferred":[
        "Ravna"
    ],
    "name:srp_x_preferred":[
        "\u0420\u0430\u0432\u043d\u0430"
    ],
    "name:swe_x_preferred":[
        "Ravna"
    ],
    "name:ukr_x_preferred":[
        "\u0420\u0430\u0432\u043d\u0430"
    ],
    "wof:name":"Ravna",
    "wof:placetype":"locality"
},
  "geometry": {"coordinates":[18.05695,44.5855],"type":"Point"}
}