{
  "type": "Feature",
  "properties": {
    "gn:admin1_code":"01",
    "gn:asciiname":"Sando",
    "gn:country_code":"BA",
    "gn:dem":958,
    "gn:feature_class":"P",
    "gn:feature_code":"PPL",
    "gn:name":"Sando",
    "gn:population":0,
    "gn:timezone":"Europe/Sarajevo",
    "iso:country":"BA",
    "name:ceb_x_preferred":[
        "Sando"
    ],
    "name:deu_x_preferred":[
        "Sando"
    ],
    "name:heb_x_preferred":[
        "\u05e1\u05e0\u05d3\u05d5"
    ],
    "name:ita_x_preferred":[
        "Sando"
    ],
    "name:spa_x_preferred":[
        "Sando"
    ],
    "name:swe_x_preferred":[
        "Sando"
    ],
    "wof:name":"Sando",
    "wof:placetype":"locality"
},
  "geometry": {"coordinates":[18.50917,44.07611],"type":"Point"}
}