{
  "type": "Feature",
  "properties": {
    "gn:admin1_code":"01",
    "gn:asciiname":"Pokrajci",
    "gn:country_code":"BA",
    "gn:dem":708,
    "gn:feature_class":"P",
    "gn:feature_code":"PPL",
    "gn:name":"Pokrajci",
    "gn:population":0,
    "gn:timezone":"Europe/Sarajevo",
    "iso:country":"BA",
    "wof:name":"Pokrajci",
    "wof:placetype":"locality"
},
  "geometry": {"coordinates":[16.59167,44.05313],"type":"Point"}
}