{
  "type": "Feature",
  "properties": {
    "gn:admin1_code":"02",
    "gn:asciiname":"Blagojevici",
    "gn:country_code":"BA",
    "gn:dem":389,
    "gn:feature_class":"P",
    "gn:feature_code":"PPL",
    "gn:name":"Blagojevi\u0107i",
    "gn:population":0,
    "gn:timezone":"Europe/Sarajevo",
    "iso:country":"BA",
    "name:und_x_variant":[
        "Blatnica",
        "Blagojevi\u0107i"
    ],
    "wof:name":"Blagojevici",
    "wof:placetype":"locality"
},
  "geometry": {"coordinates":[17.82593,44.45531],"type":"Point"}
}