{
  "type": "Feature",
  "properties": {
    "gn:admin1_code":"01",
    "gn:asciiname":"Kokosari",
    "gn:country_code":"BA",
    "gn:dem":668,
    "gn:feature_class":"P",
    "gn:feature_code":"PPL",
    "gn:name":"Koko\u0161ari",
    "gn:population":0,
    "gn:timezone":"Europe/Sarajevo",
    "iso:country":"BA",
    "wof:name":"Kokosari",
    "wof:placetype":"locality"
},
  "geometry": {"coordinates":[17.6228,44.22652],"type":"Point"}
}