{
  "type": "Feature",
  "properties": {
    "gn:admin1_code":"02",
    "gn:asciiname":"Slapovic",
    "gn:country_code":"BA",
    "gn:dem":606,
    "gn:feature_class":"P",
    "gn:feature_code":"PPL",
    "gn:name":"Slapovi\u0107",
    "gn:population":0,
    "gn:timezone":"Europe/Sarajevo",
    "iso:country":"BA",
    "wof:name":"Slapovic",
    "wof:placetype":"locality"
},
  "geometry": {"coordinates":[19.24918,44.08112],"type":"Point"}
}