{
  "type": "Feature",
  "properties": {
    "gn:admin1_code":"02",
    "gn:asciiname":"Lokanjsko Branjevo",
    "gn:country_code":"BA",
    "gn:dem":250,
    "gn:feature_class":"P",
    "gn:feature_code":"PPL",
    "gn:name":"Lokanjsko Branjevo",
    "gn:population":0,
    "gn:timezone":"Europe/Sarajevo",
    "iso:country":"BA",
    "wof:name":"Lokanjsko Branjevo",
    "wof:placetype":"locality"
},
  "geometry": {"coordinates":[19.14422,44.5663],"type":"Point"}
}