{
  "type": "Feature",
  "properties": {
    "gn:admin1_code":"02",
    "gn:asciiname":"Brestovac",
    "gn:country_code":"BA",
    "gn:dem":449,
    "gn:feature_class":"P",
    "gn:feature_code":"PPL",
    "gn:name":"Brestovac",
    "gn:population":0,
    "gn:timezone":"Europe/Sarajevo",
    "iso:country":"BA",
    "name:bos_x_preferred":[
        "Brestovac"
    ],
    "name:ceb_x_preferred":[
        "Brestovac"
    ],
    "name:deu_x_preferred":[
        "Brestovac"
    ],
    "name:fra_x_preferred":[
        "Brestovac"
    ],
    "name:hrv_x_preferred":[
        "Brestovac"
    ],
    "name:nld_x_preferred":[
        "Brestovac"
    ],
    "name:slv_x_preferred":[
        "Brestovac"
    ],
    "name:srp_x_preferred":[
        "\u0411\u0440\u0435\u0441\u0442\u043e\u0432\u0430\u0446"
    ],
    "name:swe_x_preferred":[
        "Brestovac"
    ],
    "wof:name":"Brestovac",
    "wof:placetype":"locality"
},
  "geometry": {"coordinates":[17.64722,44.62816],"type":"Point"}
}