{
  "type": "Feature",
  "properties": {
    "gn:admin1_code":"02",
    "gn:asciiname":"Brestovac",
    "gn:country_code":"BA",
    "gn:dem":449,
    "gn:feature_class":"P",
    "gn:feature_code":"PPL",
    "gn:name":"Brestovac",
    "gn:population":0,
    "gn:timezone":"Europe/Sarajevo",
    "iso:country":"BA",
    "wof:name":"Brestovac",
    "wof:placetype":"locality"
},
  "geometry": {"coordinates":[17.64722,44.62816],"type":"Point"}
}