{
  "type": "Feature",
  "properties": {
    "gn:admin1_code":"01",
    "gn:asciiname":"Oklaji",
    "gn:country_code":"BA",
    "gn:dem":316,
    "gn:feature_class":"P",
    "gn:feature_code":"PPL",
    "gn:name":"Oklaji",
    "gn:population":0,
    "gn:timezone":"Europe/Sarajevo",
    "iso:country":"BA",
    "name:bos_x_preferred":[
        "Oklaji"
    ],
    "name:ceb_x_preferred":[
        "Oklaji"
    ],
    "name:fra_x_preferred":[
        "Oklaji"
    ],
    "name:hrv_x_preferred":[
        "Oklaji"
    ],
    "name:srp_x_preferred":[
        "\u041e\u043a\u043b\u0430\u0458\u0438"
    ],
    "name:swe_x_preferred":[
        "Oklaji"
    ],
    "wof:name":"Oklaji",
    "wof:placetype":"locality"
},
  "geometry": {"coordinates":[17.57556,43.39389],"type":"Point"}
}