{
  "type": "Feature",
  "properties": {
    "gn:admin1_code":"01",
    "gn:asciiname":"Varos",
    "gn:country_code":"BA",
    "gn:dem":318,
    "gn:feature_class":"P",
    "gn:feature_code":"PPL",
    "gn:name":"Varo\u0161",
    "gn:population":0,
    "gn:timezone":"Europe/Sarajevo",
    "iso:country":"BA",
    "wof:name":"Varos",
    "wof:placetype":"locality"
},
  "geometry": {"coordinates":[16.6325,44.72694],"type":"Point"}
}