{
  "type": "Feature",
  "properties": {
    "gn:admin1_code":"02",
    "gn:asciiname":"Gojsovac",
    "gn:country_code":"BA",
    "gn:dem":87,
    "gn:feature_class":"P",
    "gn:feature_code":"PPL",
    "gn:name":"Gojsovac",
    "gn:population":0,
    "gn:timezone":"Europe/Sarajevo",
    "iso:country":"BA",
    "wof:name":"Gojsovac",
    "wof:placetype":"locality"
},
  "geometry": {"coordinates":[19.23213,44.79182],"type":"Point"}
}