{
  "type": "Feature",
  "properties": {
    "gn:admin1_code":"02",
    "gn:asciiname":"Gojsovac",
    "gn:country_code":"BA",
    "gn:dem":87,
    "gn:feature_class":"P",
    "gn:feature_code":"PPL",
    "gn:name":"Gojsovac",
    "gn:population":0,
    "gn:timezone":"Europe/Sarajevo",
    "iso:country":"BA",
    "name:bos_x_preferred":[
        "Gojsovac"
    ],
    "name:ceb_x_preferred":[
        "Gojsovac"
    ],
    "name:fra_x_preferred":[
        "Gojsovac"
    ],
    "name:hrv_x_preferred":[
        "Gojsovac"
    ],
    "name:rus_x_preferred":[
        "\u0413\u043e\u0439\u0441\u043e\u0432\u0430\u0446"
    ],
    "name:slv_x_preferred":[
        "Gojsovac"
    ],
    "name:srp_x_preferred":[
        "\u0413\u043e\u0458\u0441\u043e\u0432\u0430\u0446"
    ],
    "name:swe_x_preferred":[
        "Gojsovac"
    ],
    "wof:name":"Gojsovac",
    "wof:placetype":"locality"
},
  "geometry": {"coordinates":[19.23213,44.79182],"type":"Point"}
}