{
  "type": "Feature",
  "properties": {
    "gn:admin1_code":"02",
    "gn:asciiname":"Gajici",
    "gn:country_code":"BA",
    "gn:dem":320,
    "gn:feature_class":"P",
    "gn:feature_code":"PPL",
    "gn:name":"Gaji\u0107i",
    "gn:population":0,
    "gn:timezone":"Europe/Sarajevo",
    "iso:country":"BA",
    "name:und_x_variant":[
        "Reli\u0107i",
        "Gaji\u0107i"
    ],
    "wof:name":"Gajici",
    "wof:placetype":"locality"
},
  "geometry": {"coordinates":[19.07186,44.55644],"type":"Point"}
}