{
  "type": "Feature",
  "properties": {
    "gn:admin1_code":"02",
    "gn:asciiname":"Karavlasi",
    "gn:country_code":"BA",
    "gn:dem":220,
    "gn:feature_class":"P",
    "gn:feature_code":"PPL",
    "gn:name":"Karavlasi",
    "gn:population":0,
    "gn:timezone":"Europe/Sarajevo",
    "iso:country":"BA",
    "wof:name":"Karavlasi",
    "wof:placetype":"locality"
},
  "geometry": {"coordinates":[17.87092,44.74686],"type":"Point"}
}