{
  "type": "Feature",
  "properties": {
    "gn:admin1_code":"01",
    "gn:asciiname":"Velika Brijesnica",
    "gn:country_code":"BA",
    "gn:dem":230,
    "gn:feature_class":"P",
    "gn:feature_code":"PPLL",
    "gn:name":"Velika Brijesnica",
    "gn:population":0,
    "gn:timezone":"Europe/Sarajevo",
    "iso:country":"BA",
    "name:und_x_variant":[
        "Brijesnica Velika",
        "Brijesnica",
        "Velika Brijesnica"
    ],
    "wof:name":"Velika Brijesnica",
    "wof:placetype":"locality"
},
  "geometry": {"coordinates":[18.21078,44.72748],"type":"Point"}
}