{
  "type": "Feature",
  "properties": {
    "gn:admin1_code":"02",
    "gn:asciiname":"Radujkovici",
    "gn:country_code":"BA",
    "gn:dem":297,
    "gn:feature_class":"P",
    "gn:feature_code":"PPL",
    "gn:name":"Radujkovi\u0107i",
    "gn:population":0,
    "gn:timezone":"Europe/Sarajevo",
    "iso:country":"BA",
    "wof:name":"Radujkovici",
    "wof:placetype":"locality"
},
  "geometry": {"coordinates":[17.3634,44.7586],"type":"Point"}
}