{
  "type": "Feature",
  "properties": {
    "gn:admin1_code":"01",
    "gn:asciiname":"Skomlici",
    "gn:country_code":"BA",
    "gn:dem":630,
    "gn:feature_class":"P",
    "gn:feature_code":"PPL",
    "gn:name":"\u0160komli\u0107i",
    "gn:population":0,
    "gn:timezone":"Europe/Sarajevo",
    "iso:country":"BA",
    "wof:name":"Skomlici",
    "wof:placetype":"locality"
},
  "geometry": {"coordinates":[18.17726,44.12038],"type":"Point"}
}