{
  "type": "Feature",
  "properties": {
    "gn:admin1_code":"01",
    "gn:asciiname":"Kesten",
    "gn:country_code":"BA",
    "gn:dem":413,
    "gn:feature_class":"P",
    "gn:feature_code":"PPLL",
    "gn:name":"Kesten",
    "gn:population":0,
    "gn:timezone":"Europe/Sarajevo",
    "iso:country":"BA",
    "name:bos_x_preferred":[
        "Kesten"
    ],
    "name:bul_x_preferred":[
        "\u041a\u0435\u0441\u0442\u0435\u043d"
    ],
    "name:ceb_x_preferred":[
        "Kesten"
    ],
    "name:deu_x_preferred":[
        "Kesten"
    ],
    "name:hrv_x_preferred":[
        "Kesten"
    ],
    "name:ita_x_preferred":[
        "Kesten"
    ],
    "name:pol_x_preferred":[
        "Kesten"
    ],
    "name:swe_x_preferred":[
        "Kesten"
    ],
    "wof:name":"Kesten",
    "wof:placetype":"locality"
},
  "geometry": {"coordinates":[18.32436,44.44524000000001],"type":"Point"}
}