{
  "type": "Feature",
  "properties": {
    "gn:admin1_code":"01",
    "gn:asciiname":"Bacevici",
    "gn:country_code":"BA",
    "gn:dem":36,
    "gn:feature_class":"P",
    "gn:feature_code":"PPL",
    "gn:name":"Ba\u010devi\u0107i",
    "gn:population":0,
    "gn:timezone":"Europe/Sarajevo",
    "iso:country":"BA",
    "name:und_x_variant":[
        "Ba\u010devi\u0107",
        "Ba\u010devi\u0107i"
    ],
    "wof:name":"Bacevici",
    "wof:placetype":"locality"
},
  "geometry": {"coordinates":[17.82146000000001,43.2649],"type":"Point"}
}