{
  "type": "Feature",
  "properties": {
    "gn:admin1_code":"02",
    "gn:asciiname":"Jusici",
    "gn:country_code":"BA",
    "gn:dem":828,
    "gn:feature_class":"P",
    "gn:feature_code":"PPLL",
    "gn:name":"Jusi\u0107i",
    "gn:population":0,
    "gn:timezone":"Europe/Sarajevo",
    "iso:country":"BA",
    "wof:name":"Jusici",
    "wof:placetype":"locality"
},
  "geometry": {"coordinates":[17.0414,44.32633],"type":"Point"}
}