{
  "type": "Feature",
  "properties": {
    "gn:admin1_code":"02",
    "gn:asciiname":"Kuridze",
    "gn:country_code":"BA",
    "gn:dem":640,
    "gn:feature_class":"P",
    "gn:feature_code":"PPL",
    "gn:name":"Kurid\u017ee",
    "gn:population":0,
    "gn:timezone":"Europe/Sarajevo",
    "iso:country":"BA",
    "wof:name":"Kuridze",
    "wof:placetype":"locality"
},
  "geometry": {"coordinates":[16.91063,44.51679],"type":"Point"}
}