{
  "type": "Feature",
  "properties": {
    "gn:admin1_code":"01",
    "gn:asciiname":"Sadikovaca",
    "gn:country_code":"BA",
    "gn:dem":612,
    "gn:feature_class":"P",
    "gn:feature_code":"PPL",
    "gn:name":"Sadikova\u010da",
    "gn:population":0,
    "gn:timezone":"Europe/Sarajevo",
    "iso:country":"BA",
    "wof:name":"Sadikovaca",
    "wof:placetype":"locality"
},
  "geometry": {"coordinates":[16.27212,44.55853],"type":"Point"}
}