{
  "type": "Feature",
  "properties": {
    "gn:admin1_code":"02",
    "gn:asciiname":"Zalukovlje",
    "gn:country_code":"BA",
    "gn:dem":842,
    "gn:feature_class":"P",
    "gn:feature_code":"PPL",
    "gn:name":"Zalukovlje",
    "gn:population":0,
    "gn:timezone":"Europe/Sarajevo",
    "iso:country":"BA",
    "wof:name":"Zalukovlje",
    "wof:placetype":"locality"
},
  "geometry": {"coordinates":[18.92699,44.17551],"type":"Point"}
}