{
  "type": "Feature",
  "properties": {
    "gn:admin1_code":"01",
    "gn:asciiname":"Klupe",
    "gn:country_code":"BA",
    "gn:dem":215,
    "gn:feature_class":"P",
    "gn:feature_code":"PPL",
    "gn:name":"Klupe",
    "gn:population":0,
    "gn:timezone":"Europe/Sarajevo",
    "iso:country":"BA",
    "wof:name":"Klupe",
    "wof:placetype":"locality"
},
  "geometry": {"coordinates":[15.91605,45.17965],"type":"Point"}
}