{
  "type": "Feature",
  "properties": {
    "gn:admin1_code":"02",
    "gn:asciiname":"Ilijak",
    "gn:country_code":"BA",
    "gn:dem":956,
    "gn:feature_class":"P",
    "gn:feature_code":"PPL",
    "gn:name":"Ilijak",
    "gn:population":0,
    "gn:timezone":"Europe/Sarajevo",
    "iso:country":"BA",
    "wof:name":"Ilijak",
    "wof:placetype":"locality"
},
  "geometry": {"coordinates":[18.80478,43.79114000000001],"type":"Point"}
}