{
  "type": "Feature",
  "properties": {
    "gn:admin1_code":"02",
    "gn:asciiname":"Lukare",
    "gn:country_code":"BA",
    "gn:dem":760,
    "gn:feature_class":"P",
    "gn:feature_code":"PPL",
    "gn:name":"Lukare",
    "gn:population":0,
    "gn:timezone":"Europe/Sarajevo",
    "iso:country":"BA",
    "name:ceb_x_preferred":[
        "Lukare"
    ],
    "name:fra_x_preferred":[
        "Lukare"
    ],
    "name:hun_x_preferred":[
        "Lukare"
    ],
    "name:msa_x_preferred":[
        "Lukare"
    ],
    "name:nld_x_preferred":[
        "Lukare"
    ],
    "name:por_x_preferred":[
        "Lukare"
    ],
    "name:slv_x_preferred":[
        "Lukare"
    ],
    "name:srp_x_preferred":[
        "\u041b\u0443\u043a\u0430\u0440\u0435"
    ],
    "wof:name":"Lukare",
    "wof:placetype":"locality"
},
  "geometry": {"coordinates":[19.20662,43.55264],"type":"Point"}
}