{
  "type": "Feature",
  "properties": {
    "gn:admin1_code":"01",
    "gn:asciiname":"Mitrovici",
    "gn:country_code":"BA",
    "gn:dem":483,
    "gn:feature_class":"P",
    "gn:feature_code":"PPL",
    "gn:name":"Mitrovi\u0107i",
    "gn:population":0,
    "gn:timezone":"Europe/Sarajevo",
    "iso:country":"BA",
    "wof:name":"Mitrovici",
    "wof:placetype":"locality"
},
  "geometry": {"coordinates":[18.73351,44.57804],"type":"Point"}
}