{
  "type": "Feature",
  "properties": {
    "gn:admin1_code":"02",
    "gn:asciiname":"Brezani",
    "gn:country_code":"BA",
    "gn:dem":884,
    "gn:feature_class":"P",
    "gn:feature_code":"PPLL",
    "gn:name":"Bre\u017eani",
    "gn:population":0,
    "gn:timezone":"Europe/Sarajevo",
    "iso:country":"BA",
    "wof:name":"Brezani",
    "wof:placetype":"locality"
},
  "geometry": {"coordinates":[19.37053,44.05832],"type":"Point"}
}