{
  "type": "Feature",
  "properties": {
    "gn:admin1_code":"02",
    "gn:asciiname":"Dzakule",
    "gn:country_code":"BA",
    "gn:dem":104,
    "gn:feature_class":"P",
    "gn:feature_code":"PPL",
    "gn:name":"D\u017eakule",
    "gn:population":0,
    "gn:timezone":"Europe/Sarajevo",
    "iso:country":"BA",
    "name:und_x_variant":[
        "D\u017eakule"
    ],
    "wof:name":"Dzakule",
    "wof:placetype":"locality"
},
  "geometry": {"coordinates":[17.23032000000001,45.04745],"type":"Point"}
}