{
  "type": "Feature",
  "properties": {
    "gn:admin1_code":"02",
    "gn:asciiname":"Gornji Potocari",
    "gn:country_code":"BA",
    "gn:dem":399,
    "gn:feature_class":"P",
    "gn:feature_code":"PPL",
    "gn:name":"Gornji Poto\u010dari",
    "gn:population":0,
    "gn:timezone":"Europe/Sarajevo",
    "iso:country":"BA",
    "wof:name":"Gornji Potocari",
    "wof:placetype":"locality"
},
  "geometry": {"coordinates":[16.82387,45.01163],"type":"Point"}
}