{
  "type": "Feature",
  "properties": {
    "gn:admin1_code":"02",
    "gn:asciiname":"Gornji Jandrici",
    "gn:country_code":"BA",
    "gn:dem":1041,
    "gn:feature_class":"P",
    "gn:feature_code":"PPL",
    "gn:name":"Gornji Jandri\u0107i",
    "gn:population":0,
    "gn:timezone":"Europe/Sarajevo",
    "iso:country":"BA",
    "wof:name":"Gornji Jandrici",
    "wof:placetype":"locality"
},
  "geometry": {"coordinates":[17.18747,44.12654000000001],"type":"Point"}
}