{
  "type": "Feature",
  "properties": {
    "gn:admin1_code":"01",
    "gn:asciiname":"Novi Mustajbasici",
    "gn:country_code":"BA",
    "gn:dem":360,
    "gn:feature_class":"P",
    "gn:feature_code":"PPL",
    "gn:name":"Novi Mustajba\u0161i\u0107i",
    "gn:population":0,
    "gn:timezone":"Europe/Sarajevo",
    "iso:country":"BA",
    "wof:name":"Novi Mustajbasici",
    "wof:placetype":"locality"
},
  "geometry": {"coordinates":[18.21338,44.43332],"type":"Point"}
}