{
  "type": "Feature",
  "properties": {
    "gn:admin1_code":"01",
    "gn:asciiname":"Jadovicke Uvale",
    "gn:country_code":"BA",
    "gn:dem":878,
    "gn:feature_class":"P",
    "gn:feature_code":"PPL",
    "gn:name":"Jadovi\u010dke Uvale",
    "gn:population":0,
    "gn:timezone":"Europe/Sarajevo",
    "iso:country":"BA",
    "wof:name":"Jadovicke Uvale",
    "wof:placetype":"locality"
},
  "geometry": {"coordinates":[16.08906,44.74663],"type":"Point"}
}