{
  "type": "Feature",
  "properties": {
    "gn:admin1_code":"02",
    "gn:asciiname":"Boljeradina",
    "gn:country_code":"BA",
    "gn:dem":924,
    "gn:feature_class":"P",
    "gn:feature_code":"PPLL",
    "gn:name":"Boljeradina",
    "gn:population":0,
    "gn:timezone":"Europe/Sarajevo",
    "iso:country":"BA",
    "name:und_x_variant":[
        "Boljoradina",
        "Boljeradina"
    ],
    "wof:name":"Boljeradina",
    "wof:placetype":"locality"
},
  "geometry": {"coordinates":[18.84874,43.51785],"type":"Point"}
}