{
  "type": "Feature",
  "properties": {
    "gn:admin1_code":"01",
    "gn:asciiname":"Bajrici",
    "gn:country_code":"BA",
    "gn:dem":344,
    "gn:feature_class":"P",
    "gn:feature_code":"PPL",
    "gn:name":"Bajri\u0107i",
    "gn:population":0,
    "gn:timezone":"Europe/Sarajevo",
    "iso:country":"BA",
    "name:ara_x_preferred":[
        "\u0628\u0627\u064a\u0631\u064a\u062a\u0634\u064a"
    ],
    "name:bos_x_preferred":[
        "Bajri\u0107i"
    ],
    "name:ell_x_preferred":[
        "\u039c\u03c0\u03ac\u03b9\u03c1\u03b9\u03c4\u03c3\u03b9"
    ],
    "name:fra_x_preferred":[
        "Bajri\u0107i"
    ],
    "name:hrv_x_preferred":[
        "Bajri\u0107i"
    ],
    "name:slv_x_preferred":[
        "Bajri\u0107i"
    ],
    "name:srp_x_preferred":[
        "\u0411\u0430\u0458\u0440\u0438\u045b\u0438"
    ],
    "wof:name":"Bajrici",
    "wof:placetype":"locality"
},
  "geometry": {"coordinates":[16.04453,44.94219],"type":"Point"}
}