{
  "type": "Feature",
  "properties": {
    "gn:admin1_code":"02",
    "gn:asciiname":"Mitici",
    "gn:country_code":"BA",
    "gn:dem":172,
    "gn:feature_class":"P",
    "gn:feature_code":"PPL",
    "gn:name":"Miti\u0107i",
    "gn:population":0,
    "gn:timezone":"Europe/Sarajevo",
    "iso:country":"BA",
    "wof:name":"Mitici",
    "wof:placetype":"locality"
},
  "geometry": {"coordinates":[19.03821,44.72582],"type":"Point"}
}