{
  "type": "Feature",
  "properties": {
    "gn:admin1_code":"01",
    "gn:asciiname":"Porici",
    "gn:country_code":"BA",
    "gn:dem":329,
    "gn:feature_class":"P",
    "gn:feature_code":"PPL",
    "gn:name":"Pori\u0107i",
    "gn:population":0,
    "gn:timezone":"Europe/Sarajevo",
    "iso:country":"BA",
    "wof:name":"Porici",
    "wof:placetype":"locality"
},
  "geometry": {"coordinates":[16.0541,45.09722],"type":"Point"}
}