{
  "type": "Feature",
  "properties": {
    "gn:admin1_code":"01",
    "gn:asciiname":"Ninkovici",
    "gn:country_code":"BA",
    "gn:dem":937,
    "gn:feature_class":"P",
    "gn:feature_code":"PPL",
    "gn:name":"Ninkovi\u0107i",
    "gn:population":0,
    "gn:timezone":"Europe/Sarajevo",
    "iso:country":"BA",
    "wof:name":"Ninkovici",
    "wof:placetype":"locality"
},
  "geometry": {"coordinates":[16.82403,44.13899],"type":"Point"}
}