{
  "type": "Feature",
  "properties": {
    "gn:admin1_code":"01",
    "gn:asciiname":"Prgosevo",
    "gn:country_code":"BA",
    "gn:dem":793,
    "gn:feature_class":"P",
    "gn:feature_code":"PPL",
    "gn:name":"Prgo\u0161evo",
    "gn:population":0,
    "gn:timezone":"Europe/Sarajevo",
    "iso:country":"BA",
    "wof:name":"Prgosevo",
    "wof:placetype":"locality"
},
  "geometry": {"coordinates":[18.59527000000001,44.09661],"type":"Point"}
}