{
  "type": "Feature",
  "properties": {
    "gn:admin1_code":"01",
    "gn:asciiname":"Adzici",
    "gn:country_code":"BA",
    "gn:dem":389,
    "gn:feature_class":"P",
    "gn:feature_code":"PPL",
    "gn:name":"Ad\u017eici",
    "gn:population":0,
    "gn:timezone":"Europe/Sarajevo",
    "iso:country":"BA",
    "wof:name":"Adzici",
    "wof:placetype":"locality"
},
  "geometry": {"coordinates":[18.30585,44.39637000000001],"type":"Point"}
}