{
  "type": "Feature",
  "properties": {
    "gn:admin1_code":"01",
    "gn:asciiname":"Skegri",
    "gn:country_code":"BA",
    "gn:dem":386,
    "gn:feature_class":"P",
    "gn:feature_code":"PPL",
    "gn:name":"\u0160kegri",
    "gn:population":0,
    "gn:timezone":"Europe/Sarajevo",
    "iso:country":"BA",
    "wof:name":"Skegri",
    "wof:placetype":"locality"
},
  "geometry": {"coordinates":[17.56782999999999,43.32869],"type":"Point"}
}