{
  "type": "Feature",
  "properties": {
    "gn:admin1_code":"02",
    "gn:asciiname":"Kunduci",
    "gn:country_code":"BA",
    "gn:dem":747,
    "gn:feature_class":"P",
    "gn:feature_code":"PPLL",
    "gn:name":"Kunduci",
    "gn:population":0,
    "gn:timezone":"Europe/Sarajevo",
    "iso:country":"BA",
    "name:bos_x_preferred":[
        "Kunduci"
    ],
    "name:ceb_x_preferred":[
        "Kunduci"
    ],
    "name:fra_x_preferred":[
        "Kunduci"
    ],
    "name:hrv_x_preferred":[
        "Kunduci"
    ],
    "name:srp_x_preferred":[
        "\u041a\u0443\u043d\u0434\u0443\u0446\u0438"
    ],
    "name:swe_x_preferred":[
        "Kunduci"
    ],
    "name:und_x_variant":[
        "Kundaci"
    ],
    "wof:name":"Kunduci",
    "wof:placetype":"locality"
},
  "geometry": {"coordinates":[18.77604,43.42913],"type":"Point"}
}