{
  "type": "Feature",
  "properties": {
    "gn:admin1_code":"02",
    "gn:asciiname":"Kunduci",
    "gn:country_code":"BA",
    "gn:dem":747,
    "gn:feature_class":"P",
    "gn:feature_code":"PPLL",
    "gn:name":"Kunduci",
    "gn:population":0,
    "gn:timezone":"Europe/Sarajevo",
    "iso:country":"BA",
    "name:und_x_variant":[
        "Kundaci",
        "Kunduci"
    ],
    "wof:name":"Kunduci",
    "wof:placetype":"locality"
},
  "geometry": {"coordinates":[18.77604,43.42913],"type":"Point"}
}