{
  "type": "Feature",
  "properties": {
    "gn:admin1_code":"01",
    "gn:asciiname":"Gladovici",
    "gn:country_code":"BA",
    "gn:dem":656,
    "gn:feature_class":"P",
    "gn:feature_code":"PPL",
    "gn:name":"Gladovi\u0107i",
    "gn:population":0,
    "gn:timezone":"Europe/Sarajevo",
    "iso:country":"BA",
    "wof:name":"Gladovici",
    "wof:placetype":"locality"
},
  "geometry": {"coordinates":[17.93169,44.30024],"type":"Point"}
}