{
  "type": "Feature",
  "properties": {
    "gn:admin1_code":"01",
    "gn:asciiname":"Pecka",
    "gn:country_code":"BA",
    "gn:dem":293,
    "gn:feature_class":"P",
    "gn:feature_code":"PPL",
    "gn:name":"Pecka",
    "gn:population":0,
    "gn:timezone":"Europe/Sarajevo",
    "iso:country":"BA",
    "name:ceb_x_preferred":[
        "Pecka"
    ],
    "name:ces_x_preferred":[
        "Pecka"
    ],
    "name:deu_x_preferred":[
        "Pecka"
    ],
    "name:eus_x_preferred":[
        "Pecka"
    ],
    "name:fas_x_preferred":[
        "\u067e\u062a\u0633\u06a9\u0627"
    ],
    "name:hun_x_preferred":[
        "Pecka"
    ],
    "name:ita_x_preferred":[
        "Pecka"
    ],
    "name:msa_x_preferred":[
        "Pecka"
    ],
    "name:nld_x_preferred":[
        "Pecka"
    ],
    "name:pol_x_preferred":[
        "Pecka"
    ],
    "name:por_x_preferred":[
        "Pecka"
    ],
    "name:slk_x_preferred":[
        "Pecka"
    ],
    "name:srp_x_preferred":[
        "\u041f\u0435\u0446\u043a\u0430"
    ],
    "name:swe_x_preferred":[
        "Pecka"
    ],
    "name:vie_x_preferred":[
        "Pecka"
    ],
    "wof:name":"Pecka",
    "wof:placetype":"locality"
},
  "geometry": {"coordinates":[16.12418,44.97069000000001],"type":"Point"}
}