{
  "type": "Feature",
  "properties": {
    "gn:admin1_code":"02",
    "gn:asciiname":"Gornji Ribnik",
    "gn:country_code":"BA",
    "gn:dem":311,
    "gn:feature_class":"P",
    "gn:feature_code":"PPLA2",
    "gn:name":"Gornji Ribnik",
    "gn:population":0,
    "gn:timezone":"Europe/Sarajevo",
    "iso:country":"BA",
    "name:bos_x_preferred":[
        "Gornji Ribnik"
    ],
    "name:ceb_x_preferred":[
        "Gornji Ribnik"
    ],
    "name:fra_x_preferred":[
        "Gornji Ribnik"
    ],
    "name:hrv_x_preferred":[
        "Gornji Ribnik"
    ],
    "name:rus_x_preferred":[
        "\u0413\u043e\u0440\u043d\u0438-\u0420\u0438\u0431\u043d\u0438\u043a"
    ],
    "name:srp_x_preferred":[
        "\u0413\u043e\u0440\u045a\u0438 \u0420\u0438\u0431\u043d\u0438\u043a"
    ],
    "name:swe_x_preferred":[
        "Gornji Ribnik"
    ],
    "name:und_x_variant":[
        "Ribnik Gornji",
        "Gornji Ribnik"
    ],
    "wof:name":"Gornji Ribnik",
    "wof:placetype":"locality"
},
  "geometry": {"coordinates":[16.8169,44.41752],"type":"Point"}
}