{
  "type": "Feature",
  "properties": {
    "gn:admin1_code":"01",
    "gn:asciiname":"Krezluk",
    "gn:country_code":"BA",
    "gn:dem":668,
    "gn:feature_class":"P",
    "gn:feature_code":"PPL",
    "gn:name":"Krezluk",
    "gn:population":0,
    "gn:timezone":"Europe/Sarajevo",
    "iso:country":"BA",
    "name:bos_x_preferred":[
        "Krezluk"
    ],
    "name:fra_x_preferred":[
        "Krezluk"
    ],
    "name:hrv_x_preferred":[
        "Krezluk"
    ],
    "name:srp_x_preferred":[
        "\u041a\u0440\u0435\u0437\u043b\u0443\u043a"
    ],
    "wof:name":"Krezluk",
    "wof:placetype":"locality"
},
  "geometry": {"coordinates":[17.37911,44.28129000000001],"type":"Point"}
}