{
  "type": "Feature",
  "properties": {
    "gn:admin1_code":"01",
    "gn:asciiname":"Crkvenjak",
    "gn:country_code":"BA",
    "gn:dem":675,
    "gn:feature_class":"P",
    "gn:feature_code":"PPL",
    "gn:name":"Crkvenjak",
    "gn:population":0,
    "gn:timezone":"Europe/Sarajevo",
    "iso:country":"BA",
    "wof:name":"Crkvenjak",
    "wof:placetype":"locality"
},
  "geometry": {"coordinates":[18.07956,43.88695],"type":"Point"}
}