{
  "type": "Feature",
  "properties": {
    "gn:admin1_code":"02",
    "gn:asciiname":"Savici",
    "gn:country_code":"BA",
    "gn:dem":455,
    "gn:feature_class":"P",
    "gn:feature_code":"PPL",
    "gn:name":"Savi\u0107i",
    "gn:population":0,
    "gn:timezone":"Europe/Sarajevo",
    "iso:country":"BA",
    "wof:name":"Savici",
    "wof:placetype":"locality"
},
  "geometry": {"coordinates":[17.47682,44.60587],"type":"Point"}
}