{
  "type": "Feature",
  "properties": {
    "gn:admin1_code":"01",
    "gn:asciiname":"Jasike",
    "gn:country_code":"BA",
    "gn:dem":438,
    "gn:feature_class":"P",
    "gn:feature_code":"PPL",
    "gn:name":"Jasike",
    "gn:population":0,
    "gn:timezone":"Europe/Sarajevo",
    "iso:country":"BA",
    "wof:name":"Jasike",
    "wof:placetype":"locality"
},
  "geometry": {"coordinates":[18.33792,44.45536],"type":"Point"}
}