{
  "type": "Feature",
  "properties": {
    "gn:admin1_code":"02",
    "gn:asciiname":"Marjanovici",
    "gn:country_code":"BA",
    "gn:dem":322,
    "gn:feature_class":"P",
    "gn:feature_code":"PPL",
    "gn:name":"Marjanovi\u0107i",
    "gn:population":0,
    "gn:timezone":"Europe/Sarajevo",
    "iso:country":"BA",
    "wof:name":"Marjanovici",
    "wof:placetype":"locality"
},
  "geometry": {"coordinates":[16.62219,45.07811],"type":"Point"}
}