{
  "type": "Feature",
  "properties": {
    "gn:admin1_code":"01",
    "gn:asciiname":"Ferhatlije",
    "gn:country_code":"BA",
    "gn:dem":671,
    "gn:feature_class":"P",
    "gn:feature_code":"PPL",
    "gn:name":"Ferhatlije",
    "gn:population":0,
    "gn:timezone":"Europe/Sarajevo",
    "iso:country":"BA",
    "wof:name":"Ferhatlije",
    "wof:placetype":"locality"
},
  "geometry": {"coordinates":[18.15833,43.77917],"type":"Point"}
}