{
  "type": "Feature",
  "properties": {
    "gn:admin1_code":"01",
    "gn:asciiname":"Papurina",
    "gn:country_code":"BA",
    "gn:dem":785,
    "gn:feature_class":"P",
    "gn:feature_code":"PPL",
    "gn:name":"Papurina",
    "gn:population":0,
    "gn:timezone":"Europe/Sarajevo",
    "iso:country":"BA",
    "wof:name":"Papurina",
    "wof:placetype":"locality"
},
  "geometry": {"coordinates":[18.00789,44.19242],"type":"Point"}
}