{
  "type": "Feature",
  "properties": {
    "gn:admin1_code":"02",
    "gn:asciiname":"Kladari",
    "gn:country_code":"BA",
    "gn:dem":92,
    "gn:feature_class":"P",
    "gn:feature_code":"PPLL",
    "gn:name":"Kladari",
    "gn:population":0,
    "gn:timezone":"Europe/Sarajevo",
    "iso:country":"BA",
    "wof:name":"Kladari",
    "wof:placetype":"locality"
},
  "geometry": {"coordinates":[17.42409,45.06092],"type":"Point"}
}