{
  "type": "Feature",
  "properties": {
    "gn:admin1_code":"01",
    "gn:asciiname":"Jovanovici",
    "gn:country_code":"BA",
    "gn:dem":261,
    "gn:feature_class":"P",
    "gn:feature_code":"PPL",
    "gn:name":"Jovanovi\u0107i",
    "gn:population":0,
    "gn:timezone":"Europe/Sarajevo",
    "iso:country":"BA",
    "wof:name":"Jovanovici",
    "wof:placetype":"locality"
},
  "geometry": {"coordinates":[18.92817,44.41548],"type":"Point"}
}