{
  "type": "Feature",
  "properties": {
    "gn:admin1_code":"01",
    "gn:asciiname":"Senkovici",
    "gn:country_code":"BA",
    "gn:dem":798,
    "gn:feature_class":"P",
    "gn:feature_code":"PPL",
    "gn:name":"\u0160enkovi\u0107i",
    "gn:population":0,
    "gn:timezone":"Europe/Sarajevo",
    "iso:country":"BA",
    "wof:name":"Senkovici",
    "wof:placetype":"locality"
},
  "geometry": {"coordinates":[17.60904,44.1288],"type":"Point"}
}