{
  "type": "Feature",
  "properties": {
    "gn:admin1_code":"02",
    "gn:asciiname":"Buljukovina",
    "gn:country_code":"BA",
    "gn:dem":861,
    "gn:feature_class":"P",
    "gn:feature_code":"PPL",
    "gn:name":"Buljukovina",
    "gn:population":0,
    "gn:timezone":"Europe/Sarajevo",
    "iso:country":"BA",
    "wof:name":"Buljukovina",
    "wof:placetype":"locality"
},
  "geometry": {"coordinates":[18.8041,43.86751],"type":"Point"}
}