{
  "type": "Feature",
  "properties": {
    "gn:admin1_code":"00",
    "gn:asciiname":"Zadne",
    "gn:country_code":"BA",
    "gn:dem":999,
    "gn:feature_class":"P",
    "gn:feature_code":"PPL",
    "gn:name":"Zadne",
    "gn:population":0,
    "gn:timezone":"Europe/Sarajevo",
    "iso:country":"BA",
    "wof:name":"Zadne",
    "wof:placetype":"locality"
},
  "geometry": {"coordinates":[17.84861,44.2825],"type":"Point"}
}