{
  "type": "Feature",
  "properties": {
    "gn:admin1_code":"BRC",
    "gn:asciiname":"Brka",
    "gn:country_code":"BA",
    "gn:dem":102,
    "gn:feature_class":"P",
    "gn:feature_code":"PPL",
    "gn:name":"Brka",
    "gn:population":0,
    "gn:timezone":"Europe/Sarajevo",
    "iso:country":"BA",
    "name:bos_x_preferred":[
        "Brka"
    ],
    "name:ell_x_preferred":[
        "\u039c\u03c0\u03c1\u03ba\u03b1"
    ],
    "name:fra_x_preferred":[
        "Brka"
    ],
    "name:hrv_x_preferred":[
        "Brka"
    ],
    "name:srp_x_preferred":[
        "\u0411\u0440\u043a\u0430"
    ],
    "wof:name":"Brka",
    "wof:placetype":"locality"
},
  "geometry": {"coordinates":[18.75674,44.84279],"type":"Point"}
}