{
  "type": "Feature",
  "properties": {
    "gn:admin1_code":"01",
    "gn:asciiname":"Jelik",
    "gn:country_code":"BA",
    "gn:dem":1034,
    "gn:feature_class":"P",
    "gn:feature_code":"PPL",
    "gn:name":"Jelik",
    "gn:population":0,
    "gn:timezone":"Europe/Sarajevo",
    "iso:country":"BA",
    "wof:name":"Jelik",
    "wof:placetype":"locality"
},
  "geometry": {"coordinates":[18.48912,44.06448],"type":"Point"}
}