{
  "type": "Feature",
  "properties": {
    "gn:admin1_code":"01",
    "gn:asciiname":"Gornji Bucici",
    "gn:country_code":"BA",
    "gn:dem":289,
    "gn:feature_class":"P",
    "gn:feature_code":"PPL",
    "gn:name":"Gornji Bu\u010di\u0107i",
    "gn:population":0,
    "gn:timezone":"Europe/Sarajevo",
    "iso:country":"BA",
    "wof:name":"Gornji Bucici",
    "wof:placetype":"locality"
},
  "geometry": {"coordinates":[17.85025,43.42305],"type":"Point"}
}