{
  "type": "Feature",
  "properties": {
    "gn:admin1_code":"02",
    "gn:asciiname":"Bunovi",
    "gn:country_code":"BA",
    "gn:dem":808,
    "gn:feature_class":"P",
    "gn:feature_code":"PPLL",
    "gn:name":"Bunovi",
    "gn:population":0,
    "gn:timezone":"Europe/Sarajevo",
    "iso:country":"BA",
    "name:bos_x_preferred":[
        "Bunovi"
    ],
    "name:fra_x_preferred":[
        "Bunovi"
    ],
    "name:hrv_x_preferred":[
        "Bunovi"
    ],
    "name:srp_x_preferred":[
        "\u0411\u0443\u043d\u043e\u0432\u0438"
    ],
    "wof:name":"Bunovi",
    "wof:placetype":"locality"
},
  "geometry": {"coordinates":[18.76679,43.46851],"type":"Point"}
}