{
  "type": "Feature",
  "properties": {
    "gn:admin1_code":"02",
    "gn:asciiname":"Ilici",
    "gn:country_code":"BA",
    "gn:dem":274,
    "gn:feature_class":"P",
    "gn:feature_code":"PPL",
    "gn:name":"Ili\u0107i",
    "gn:population":0,
    "gn:timezone":"Europe/Sarajevo",
    "iso:country":"BA",
    "wof:name":"Ilici",
    "wof:placetype":"locality"
},
  "geometry": {"coordinates":[17.93304,44.90079],"type":"Point"}
}