{
  "type": "Feature",
  "properties": {
    "gn:admin1_code":"01",
    "gn:asciiname":"Polici",
    "gn:country_code":"BA",
    "gn:dem":821,
    "gn:feature_class":"P",
    "gn:feature_code":"PPL",
    "gn:name":"Poli\u0107i",
    "gn:population":0,
    "gn:timezone":"Europe/Sarajevo",
    "iso:country":"BA",
    "wof:name":"Polici",
    "wof:placetype":"locality"
},
  "geometry": {"coordinates":[17.41029,44.23255],"type":"Point"}
}