{
  "type": "Feature",
  "properties": {
    "gn:country":"BA",
    "gn:fcode":"PPL",
    "gn:pop":4384,
    "iso:country":"BA",
    "name:bos_x_preferred":[
        "Vitina"
    ],
    "name:dut_x_preferred":[
        "Vitina"
    ],
    "name:eng_x_preferred":[
        "Vitina"
    ],
    "name:fre_x_preferred":[
        "Vitina"
    ],
    "name:hrv_x_preferred":[
        "Vitina"
    ],
    "name:srp_x_preferred":[
        "\u0412\u0438\u0442\u0438\u043d\u0430"
    ],
    "name:swe_x_preferred":[
        "Vitina"
    ],
    "qs:name":"Vitina",
    "qs:name_adm0":"Bosna i Hercegovina",
    "qs:name_adm1":"Federacija Bosne I Hercegovine",
    "qs:photos_9k":1,
    "qs:photos_9r":1,
    "qs:photos_all":2,
    "qs:photos_sr":0,
    "qs:placetype":"Town",
    "qs:pop_sr":"4",
    "wd:wordcount":564,
    "wof:name":"Vitina",
    "wof:placetype":"locality",
    "wof:population":4384
},
  "geometry": {"coordinates":[17.48389,43.2375],"type":"Point"}
}