{
  "type": "Feature",
  "properties": {
    "gn:country":"BA",
    "gn:fcode":"PPL",
    "gn:population":4384,
    "iso:country":"BA",
    "name:ara_x_preferred":[
        "\u0641\u064a\u062a\u064a\u0646\u0627"
    ],
    "name:ben_x_preferred":[
        "\u09ad\u09bf\u099f\u09bf\u09a8\u09be"
    ],
    "name:bos_x_preferred":[
        "Vitina"
    ],
    "name:ceb_x_preferred":[
        "Vitina"
    ],
    "name:deu_x_preferred":[
        "Vitina"
    ],
    "name:ell_x_preferred":[
        "\u0392\u03b9\u03c4\u03af\u03bd\u03b1"
    ],
    "name:eng_x_preferred":[
        "Viti/Vitina"
    ],
    "name:eng_x_variant":[
        "Vitina"
    ],
    "name:fas_x_preferred":[
        "\u0648\u06cc\u062a\u06cc\u0646\u0627"
    ],
    "name:fra_x_preferred":[
        "Vitina"
    ],
    "name:heb_x_preferred":[
        "\u05d5\u05d9\u05d8\u05d9\u05e0\u05d4"
    ],
    "name:hin_x_preferred":[
        "\u0935\u093f\u091f\u093f\u0928\u093e"
    ],
    "name:hrv_x_preferred":[
        "Vitina"
    ],
    "name:hun_x_preferred":[
        "Vitina"
    ],
    "name:ind_x_preferred":[
        "Vitina"
    ],
    "name:ita_x_preferred":[
        "Vitina"
    ],
    "name:jpn_x_preferred":[
        "\u30d3\u30c6\u30a3\u30ca"
    ],
    "name:kor_x_preferred":[
        "\ube44\ud2f0\ub098"
    ],
    "name:nld_x_preferred":[
        "Vitina"
    ],
    "name:pol_x_preferred":[
        "Vitina"
    ],
    "name:por_x_preferred":[
        "Vitina"
    ],
    "name:rus_x_preferred":[
        "\u0412\u0438\u0442\u0438\u043d\u0430"
    ],
    "name:spa_x_preferred":[
        "Vitina"
    ],
    "name:srp_x_preferred":[
        "\u0412\u0438\u0442\u0438\u043d\u0430"
    ],
    "name:swe_x_preferred":[
        "Vitina"
    ],
    "name:tur_x_preferred":[
        "Vitina"
    ],
    "name:ukr_x_preferred":[
        "\u0412\u0456\u0442\u0456\u043d\u0430"
    ],
    "name:urd_x_preferred":[
        "\u0648\u0627\u0626\u06cc\u0679\u06cc\u0646\u0627"
    ],
    "name:vie_x_preferred":[
        "Vitina"
    ],
    "name:zho_cn_x_preferred":[
        "\u7ef4\u8482\u7eb3"
    ],
    "name:zho_tw_x_preferred":[
        "\u7dad\u5e1d\u90a3"
    ],
    "qs:name":"Vitina",
    "qs:name_adm0":"Bosna i Hercegovina",
    "qs:name_adm1":"Federacija Bosne I Hercegovine",
    "qs:photos_9k":1,
    "qs:photos_9r":1,
    "qs:photos_all":2,
    "qs:photos_sr":0,
    "qs:placetype":"Town",
    "qs:pop_sr":"4",
    "wd:wordcount":564,
    "wof:name":"Vitina",
    "wof:placetype":"locality",
    "wof:population":4384
},
  "geometry": {"coordinates":[17.48389,43.2375],"type":"Point"}
}