{
  "type": "Feature",
  "properties": {
    "gn:admin1_code":"01",
    "gn:asciiname":"Donja Brda",
    "gn:country_code":"BA",
    "gn:dem":566,
    "gn:feature_class":"P",
    "gn:feature_code":"PPL",
    "gn:name":"Donja Brda",
    "gn:population":0,
    "gn:timezone":"Europe/Sarajevo",
    "iso:country":"BA",
    "name:bos_x_preferred":[
        "Donja Brda"
    ],
    "name:fra_x_preferred":[
        "Donja Brda"
    ],
    "wof:name":"Donja Brda",
    "wof:placetype":"locality"
},
  "geometry": {"coordinates":[18.95327,43.64125],"type":"Point"}
}