{
  "type": "Feature",
  "properties": {
    "gn:admin1_code":"01",
    "gn:asciiname":"Breske",
    "gn:country_code":"BA",
    "gn:dem":461,
    "gn:feature_class":"P",
    "gn:feature_code":"PPLL",
    "gn:name":"Bre\u0161ke",
    "gn:population":0,
    "gn:timezone":"Europe/Sarajevo",
    "iso:country":"BA",
    "wof:name":"Breske",
    "wof:placetype":"locality"
},
  "geometry": {"coordinates":[18.66476,44.60849],"type":"Point"}
}