{
  "type": "Feature",
  "properties": {
    "gn:admin1_code":"01",
    "gn:asciiname":"Cehari",
    "gn:country_code":"BA",
    "gn:dem":237,
    "gn:feature_class":"P",
    "gn:feature_code":"PPL",
    "gn:name":"\u010cehari",
    "gn:population":0,
    "gn:timezone":"Europe/Sarajevo",
    "iso:country":"BA",
    "wof:name":"Cehari",
    "wof:placetype":"locality"
},
  "geometry": {"coordinates":[17.74056000000001,43.67222],"type":"Point"}
}