{
  "type": "Feature",
  "properties": {
    "gn:admin1_code":"01",
    "gn:asciiname":"Vucipolje",
    "gn:country_code":"BA",
    "gn:dem":988,
    "gn:feature_class":"P",
    "gn:feature_code":"PPLL",
    "gn:name":"Vu\u010dipolje",
    "gn:population":0,
    "gn:timezone":"Europe/Sarajevo",
    "iso:country":"BA",
    "wof:name":"Vucipolje",
    "wof:placetype":"locality"
},
  "geometry": {"coordinates":[17.30965,43.52912],"type":"Point"}
}