{
  "type": "Feature",
  "properties": {
    "gn:admin1_code":"01",
    "gn:asciiname":"Dukanovici",
    "gn:country_code":"BA",
    "gn:dem":474,
    "gn:feature_class":"P",
    "gn:feature_code":"PPL",
    "gn:name":"\u00d0ukanovi\u0107i",
    "gn:population":0,
    "gn:timezone":"Europe/Sarajevo",
    "iso:country":"BA",
    "wof:name":"Dukanovici",
    "wof:placetype":"locality"
},
  "geometry": {"coordinates":[16.37397,44.76542],"type":"Point"}
}