{
  "type": "Feature",
  "properties": {
    "gn:admin1_code":"02",
    "gn:asciiname":"Mitrovici",
    "gn:country_code":"BA",
    "gn:dem":845,
    "gn:feature_class":"P",
    "gn:feature_code":"PPL",
    "gn:name":"Mitrovi\u0107i",
    "gn:population":0,
    "gn:timezone":"Europe/Sarajevo",
    "iso:country":"BA",
    "wof:name":"Mitrovici",
    "wof:placetype":"locality"
},
  "geometry": {"coordinates":[17.3622,44.50345],"type":"Point"}
}