{
  "type": "Feature",
  "properties": {
    "gn:admin1_code":"01",
    "gn:asciiname":"Kiseljak",
    "gn:country_code":"BA",
    "gn:dem":355,
    "gn:feature_class":"P",
    "gn:feature_code":"PPL",
    "gn:name":"Kiseljak",
    "gn:population":0,
    "gn:timezone":"Europe/Sarajevo",
    "iso:country":"BA",
    "wof:name":"Kiseljak",
    "wof:placetype":"locality"
},
  "geometry": {"coordinates":[18.00321,44.57071],"type":"Point"}
}