{
  "type": "Feature",
  "properties": {
    "gn:admin1_code":"01",
    "gn:asciiname":"Kiseljak",
    "gn:country_code":"BA",
    "gn:dem":355,
    "gn:feature_class":"P",
    "gn:feature_code":"PPL",
    "gn:name":"Kiseljak",
    "gn:population":0,
    "gn:timezone":"Europe/Sarajevo",
    "iso:country":"BA",
    "name:bos_x_preferred":[
        "Kiseljak"
    ],
    "name:deu_x_preferred":[
        "Kiseljak"
    ],
    "name:fas_x_preferred":[
        "\u06a9\u06cc\u0633\u0647\u200c\u0644\u06cc\u0627\u06a9"
    ],
    "name:fra_x_preferred":[
        "Kiseljak"
    ],
    "name:hrv_x_preferred":[
        "Kiseljak"
    ],
    "name:ita_x_preferred":[
        "Kiseljak"
    ],
    "name:jpn_x_preferred":[
        "\u30ad\u30bb\u30ea\u30e3\u30af"
    ],
    "name:lit_x_preferred":[
        "Kiseliakas"
    ],
    "name:nld_x_preferred":[
        "Kiseljak"
    ],
    "name:pol_x_preferred":[
        "Kiseljak"
    ],
    "name:rus_x_preferred":[
        "\u041a\u0438\u0441\u0435\u043b\u044f\u043a"
    ],
    "name:spa_x_preferred":[
        "Kiseljak"
    ],
    "name:sqi_x_preferred":[
        "Kiselaku"
    ],
    "name:srp_x_preferred":[
        "\u041a\u0438\u0441\u0435\u0459\u0430\u043a"
    ],
    "name:swe_x_preferred":[
        "Kiseljak"
    ],
    "name:tur_x_preferred":[
        "Kiseljak"
    ],
    "name:ukr_x_preferred":[
        "\u041a\u0438\u0441\u0435\u043b\u044f\u043a"
    ],
    "name:urd_x_preferred":[
        "\u06a9\u06cc\u0633\u0626\u06cc\u0627\u06a9"
    ],
    "name:zho_x_preferred":[
        "\u57fa\u585e\u723e\u96c5\u514b"
    ],
    "wof:name":"Kiseljak",
    "wof:placetype":"locality"
},
  "geometry": {"coordinates":[18.00321,44.57071],"type":"Point"}
}