{
  "type": "Feature",
  "properties": {
    "gn:admin1_code":"01",
    "gn:asciiname":"Zagornica",
    "gn:country_code":"BA",
    "gn:dem":417,
    "gn:feature_class":"P",
    "gn:feature_code":"PPL",
    "gn:name":"Zagornica",
    "gn:population":0,
    "gn:timezone":"Europe/Sarajevo",
    "iso:country":"BA",
    "wof:name":"Zagornica",
    "wof:placetype":"locality"
},
  "geometry": {"coordinates":[18.15455,44.02453],"type":"Point"}
}