{
  "type": "Feature",
  "properties": {
    "gn:admin1_code":"02",
    "gn:asciiname":"Lusici",
    "gn:country_code":"BA",
    "gn:dem":757,
    "gn:feature_class":"P",
    "gn:feature_code":"PPL",
    "gn:name":"Lusi\u0107i",
    "gn:population":0,
    "gn:timezone":"Europe/Sarajevo",
    "iso:country":"BA",
    "name:bos_x_preferred":[
        "Lusi\u0107i"
    ],
    "name:ceb_x_preferred":[
        "Lusi\u0107i"
    ],
    "name:fra_x_preferred":[
        "Lusi\u0107i"
    ],
    "name:hrv_x_preferred":[
        "Lusi\u0107i"
    ],
    "name:rus_x_preferred":[
        "\u041b\u0443\u0441\u0438\u0447\u0438"
    ],
    "name:slv_x_preferred":[
        "Lusi\u0107i"
    ],
    "name:srp_x_preferred":[
        "\u041b\u0443\u0441\u0438\u045b\u0438"
    ],
    "name:swe_x_preferred":[
        "Lusi\u0107i"
    ],
    "wof:name":"Lusici",
    "wof:placetype":"locality"
},
  "geometry": {"coordinates":[17.02379,44.5914],"type":"Point"}
}