{
  "type": "Feature",
  "properties": {
    "gn:admin1_code":"01",
    "gn:asciiname":"Stojanovici",
    "gn:country_code":"BA",
    "gn:dem":776,
    "gn:feature_class":"P",
    "gn:feature_code":"PPL",
    "gn:name":"Stojanovi\u0107i",
    "gn:population":0,
    "gn:timezone":"Europe/Sarajevo",
    "iso:country":"BA",
    "wof:name":"Stojanovici",
    "wof:placetype":"locality"
},
  "geometry": {"coordinates":[16.43167,44.59806],"type":"Point"}
}