{
  "type": "Feature",
  "properties": {
    "gn:admin1_code":"01",
    "gn:asciiname":"Rakanovici",
    "gn:country_code":"BA",
    "gn:dem":436,
    "gn:feature_class":"P",
    "gn:feature_code":"PPL",
    "gn:name":"Rakanovi\u0107i",
    "gn:population":0,
    "gn:timezone":"Europe/Sarajevo",
    "iso:country":"BA",
    "wof:name":"Rakanovici",
    "wof:placetype":"locality"
},
  "geometry": {"coordinates":[18.23984,44.52144000000001],"type":"Point"}
}