{
  "type": "Feature",
  "properties": {
    "gn:admin1_code":"02",
    "gn:asciiname":"Dobrodoli",
    "gn:country_code":"BA",
    "gn:dem":984,
    "gn:feature_class":"P",
    "gn:feature_code":"PPL",
    "gn:name":"Dobrodoli",
    "gn:population":0,
    "gn:timezone":"Europe/Sarajevo",
    "iso:country":"BA",
    "wof:name":"Dobrodoli",
    "wof:placetype":"locality"
},
  "geometry": {"coordinates":[18.72758,43.96512],"type":"Point"}
}