{
  "type": "Feature",
  "properties": {
    "gn:admin1_code":"01",
    "gn:asciiname":"Obaduse",
    "gn:country_code":"BA",
    "gn:dem":786,
    "gn:feature_class":"P",
    "gn:feature_code":"PPL",
    "gn:name":"Obadu\u0161e",
    "gn:population":0,
    "gn:timezone":"Europe/Sarajevo",
    "iso:country":"BA",
    "wof:name":"Obaduse",
    "wof:placetype":"locality"
},
  "geometry": {"coordinates":[17.36645,44.28805],"type":"Point"}
}