{
  "type": "Feature",
  "properties": {
    "gn:admin1_code":"01",
    "gn:asciiname":"Surmanci",
    "gn:country_code":"BA",
    "gn:dem":157,
    "gn:feature_class":"P",
    "gn:feature_code":"PPLL",
    "gn:name":"\u0160urmanci",
    "gn:population":0,
    "gn:timezone":"Europe/Sarajevo",
    "iso:country":"BA",
    "wof:name":"Surmanci",
    "wof:placetype":"locality"
},
  "geometry": {"coordinates":[17.73244,43.1715],"type":"Point"}
}