{
  "type": "Feature",
  "properties": {
    "gn:admin1_code":"02",
    "gn:asciiname":"Spasojevici",
    "gn:country_code":"BA",
    "gn:dem":362,
    "gn:feature_class":"P",
    "gn:feature_code":"PPL",
    "gn:name":"Spasojevi\u0107i",
    "gn:population":0,
    "gn:timezone":"Europe/Sarajevo",
    "iso:country":"BA",
    "wof:name":"Spasojevici",
    "wof:placetype":"locality"
},
  "geometry": {"coordinates":[18.86716,44.66866],"type":"Point"}
}