{
  "type": "Feature",
  "properties": {
    "gn:admin1_code":"02",
    "gn:asciiname":"Gornja Josanica",
    "gn:country_code":"BA",
    "gn:dem":569,
    "gn:feature_class":"P",
    "gn:feature_code":"PPL",
    "gn:name":"Gornja Jo\u0161anica",
    "gn:population":0,
    "gn:timezone":"Europe/Sarajevo",
    "iso:country":"BA",
    "wof:name":"Gornja Josanica",
    "wof:placetype":"locality"
},
  "geometry": {"coordinates":[18.84381,43.54388],"type":"Point"}
}