{
  "type": "Feature",
  "properties": {
    "gn:admin1_code":"02",
    "gn:asciiname":"Gornje Urije",
    "gn:country_code":"BA",
    "gn:dem":234,
    "gn:feature_class":"P",
    "gn:feature_code":"PPL",
    "gn:name":"Gornje Urije",
    "gn:population":0,
    "gn:timezone":"Europe/Sarajevo",
    "iso:country":"BA",
    "wof:name":"Gornje Urije",
    "wof:placetype":"locality"
},
  "geometry": {"coordinates":[16.39111,45.03333],"type":"Point"}
}