{
  "type": "Feature",
  "properties": {
    "gn:admin1_code":"01",
    "gn:asciiname":"Gornja Sisava",
    "gn:country_code":"BA",
    "gn:dem":1261,
    "gn:feature_class":"P",
    "gn:feature_code":"PPL",
    "gn:name":"Gornja \u0160i\u0161ava",
    "gn:population":0,
    "gn:timezone":"Europe/Sarajevo",
    "iso:country":"BA",
    "wof:name":"Gornja Sisava",
    "wof:placetype":"locality"
},
  "geometry": {"coordinates":[17.57122,44.31143],"type":"Point"}
}