{
  "type": "Feature",
  "properties": {
    "gn:admin1_code":"02",
    "gn:asciiname":"Jasikovice",
    "gn:country_code":"BA",
    "gn:dem":730,
    "gn:feature_class":"P",
    "gn:feature_code":"PPL",
    "gn:name":"Jasikovice",
    "gn:population":0,
    "gn:timezone":"Europe/Sarajevo",
    "iso:country":"BA",
    "wof:name":"Jasikovice",
    "wof:placetype":"locality"
},
  "geometry": {"coordinates":[19.00399,44.26151],"type":"Point"}
}