{
  "type": "Feature",
  "properties": {
    "gn:admin1_code":"01",
    "gn:asciiname":"Salihovici",
    "gn:country_code":"BA",
    "gn:dem":389,
    "gn:feature_class":"P",
    "gn:feature_code":"PPL",
    "gn:name":"Salihovi\u0107i",
    "gn:population":0,
    "gn:timezone":"Europe/Sarajevo",
    "iso:country":"BA",
    "wof:name":"Salihovici",
    "wof:placetype":"locality"
},
  "geometry": {"coordinates":[15.97861,44.94417],"type":"Point"}
}