{
  "type": "Feature",
  "properties": {
    "gn:admin1_code":"02",
    "gn:asciiname":"Andelici",
    "gn:country_code":"BA",
    "gn:dem":845,
    "gn:feature_class":"P",
    "gn:feature_code":"PPL",
    "gn:name":"An\u0111eli\u0107i",
    "gn:population":0,
    "gn:timezone":"Europe/Sarajevo",
    "iso:country":"BA",
    "wof:name":"Andelici",
    "wof:placetype":"locality"
},
  "geometry": {"coordinates":[16.90226,44.25735],"type":"Point"}
}