{
  "type": "Feature",
  "properties": {
    "gn:admin1_code":"01",
    "gn:asciiname":"Ljuta",
    "gn:country_code":"BA",
    "gn:dem":415,
    "gn:feature_class":"P",
    "gn:feature_code":"PPL",
    "gn:name":"Ljuta",
    "gn:population":0,
    "gn:timezone":"Europe/Sarajevo",
    "iso:country":"BA",
    "wof:name":"Ljuta",
    "wof:placetype":"locality"
},
  "geometry": {"coordinates":[18.02323,43.64306],"type":"Point"}
}