{
  "type": "Feature",
  "properties": {
    "gn:admin1_code":"01",
    "gn:asciiname":"Mutnik",
    "gn:country_code":"BA",
    "gn:dem":292,
    "gn:feature_class":"P",
    "gn:feature_code":"PPLL",
    "gn:name":"Mutnik",
    "gn:population":0,
    "gn:timezone":"Europe/Sarajevo",
    "iso:country":"BA",
    "wof:name":"Mutnik",
    "wof:placetype":"locality"
},
  "geometry": {"coordinates":[15.86245,44.96514000000001],"type":"Point"}
}