{
  "type": "Feature",
  "properties": {
    "gn:admin1_code":"02",
    "gn:asciiname":"Ivanj Do",
    "gn:country_code":"BA",
    "gn:dem":880,
    "gn:feature_class":"P",
    "gn:feature_code":"PPL",
    "gn:name":"Ivanj Do",
    "gn:population":0,
    "gn:timezone":"Europe/Sarajevo",
    "iso:country":"BA",
    "wof:name":"Ivanj Do",
    "wof:placetype":"locality"
},
  "geometry": {"coordinates":[18.39955,43.03532],"type":"Point"}
}