{
  "type": "Feature",
  "properties": {
    "gn:admin1_code":"01",
    "gn:asciiname":"Basinovac",
    "gn:country_code":"BA",
    "gn:dem":175,
    "gn:feature_class":"P",
    "gn:feature_code":"PPL",
    "gn:name":"Ba\u0161inovac",
    "gn:population":0,
    "gn:timezone":"Europe/Sarajevo",
    "iso:country":"BA",
    "wof:name":"Basinovac",
    "wof:placetype":"locality"
},
  "geometry": {"coordinates":[15.9492,45.16224],"type":"Point"}
}