{
  "type": "Feature",
  "properties": {
    "gn:admin1_code":"02",
    "gn:asciiname":"Bujakovici",
    "gn:country_code":"BA",
    "gn:dem":384,
    "gn:feature_class":"P",
    "gn:feature_code":"PPLL",
    "gn:name":"Bujakovi\u0107i",
    "gn:population":0,
    "gn:timezone":"Europe/Sarajevo",
    "iso:country":"BA",
    "name:bos_x_preferred":[
        "Bujakovi\u0107i"
    ],
    "name:bul_x_preferred":[
        "\u0411\u0443\u044f\u043a\u043e\u0432\u0438\u0447\u0438"
    ],
    "name:ceb_x_preferred":[
        "Bujakovi\u0107i"
    ],
    "name:fra_x_preferred":[
        "Bujakovi\u0107i"
    ],
    "name:hrv_x_preferred":[
        "Bujakovi\u0107i"
    ],
    "name:srp_x_preferred":[
        "\u0411\u0443\u0458\u0430\u043a\u043e\u0432\u0438\u045b\u0438"
    ],
    "name:und_x_variant":[
        "Bujakovi\u0107"
    ],
    "wof:name":"Bujakovici",
    "wof:placetype":"locality"
},
  "geometry": {"coordinates":[19.55244,44.00096],"type":"Point"}
}