{
  "type": "Feature",
  "properties": {
    "gn:admin1_code":"01",
    "gn:asciiname":"Karlasi",
    "gn:country_code":"BA",
    "gn:dem":340,
    "gn:feature_class":"P",
    "gn:feature_code":"PPL",
    "gn:name":"Karla\u0161i",
    "gn:population":0,
    "gn:timezone":"Europe/Sarajevo",
    "iso:country":"BA",
    "wof:name":"Karlasi",
    "wof:placetype":"locality"
},
  "geometry": {"coordinates":[16.78111,44.6395],"type":"Point"}
}