{
  "type": "Feature",
  "properties": {
    "gn:admin1_code":"02",
    "gn:asciiname":"Boranovici",
    "gn:country_code":"BA",
    "gn:dem":562,
    "gn:feature_class":"P",
    "gn:feature_code":"PPL",
    "gn:name":"Boranovi\u0107i",
    "gn:population":0,
    "gn:timezone":"Europe/Sarajevo",
    "iso:country":"BA",
    "wof:name":"Boranovici",
    "wof:placetype":"locality"
},
  "geometry": {"coordinates":[19.42277,43.60956],"type":"Point"}
}