{
  "type": "Feature",
  "properties": {
    "gn:admin1_code":"01",
    "gn:asciiname":"Cavas",
    "gn:country_code":"BA",
    "gn:dem":260,
    "gn:feature_class":"P",
    "gn:feature_code":"PPL",
    "gn:name":"\u010cava\u0161",
    "gn:population":0,
    "gn:timezone":"Europe/Sarajevo",
    "iso:country":"BA",
    "name:und_x_variant":[
        "\u010cava\u0161"
    ],
    "wof:name":"Cavas",
    "wof:placetype":"locality"
},
  "geometry": {"coordinates":[17.95557,42.94],"type":"Point"}
}