{
  "type": "Feature",
  "properties": {
    "gn:admin1_code":"02",
    "gn:asciiname":"Durakovici",
    "gn:country_code":"BA",
    "gn:dem":699,
    "gn:feature_class":"P",
    "gn:feature_code":"PPL",
    "gn:name":"Durakovi\u0107i",
    "gn:population":0,
    "gn:timezone":"Europe/Sarajevo",
    "iso:country":"BA",
    "wof:name":"Durakovici",
    "wof:placetype":"locality"
},
  "geometry": {"coordinates":[17.59107,44.42703],"type":"Point"}
}