{
  "type": "Feature",
  "properties": {
    "gn:country":"BA",
    "gn:fcode":"PPL",
    "gn:pop":6457,
    "iso:country":"BA",
    "name:bos_x_preferred":[
        "Gromiljak"
    ],
    "name:ceb_x_preferred":[
        "Gromiljak"
    ],
    "name:eng_x_preferred":[
        "Gromiljak"
    ],
    "name:fra_x_preferred":[
        "Gromiljak"
    ],
    "name:hrv_x_preferred":[
        "Gromiljak"
    ],
    "name:nld_x_preferred":[
        "Gromiljak"
    ],
    "name:swe_x_preferred":[
        "Gromiljak"
    ],
    "qs:name":"Gromiljak",
    "qs:name_adm0":"Bosna i Hercegovina",
    "qs:name_adm1":"Federacija Bosne I Hercegovine",
    "qs:photos_9r":0,
    "qs:photos_sr":0,
    "qs:placetype":"Town",
    "qs:pop_sr":"5",
    "wd:wordcount":57,
    "wof:name":"Gromiljak",
    "wof:placetype":"locality",
    "wof:population":6457
},
  "geometry": {"coordinates":[18.05504,43.96668],"type":"Point"}
}