{
  "type": "Feature",
  "properties": {
    "gn:admin1_code":"02",
    "gn:asciiname":"Smajlovici",
    "gn:country_code":"BA",
    "gn:dem":788,
    "gn:feature_class":"P",
    "gn:feature_code":"PPL",
    "gn:name":"Smajlovi\u0107i",
    "gn:population":0,
    "gn:timezone":"Europe/Sarajevo",
    "iso:country":"BA",
    "wof:name":"Smajlovici",
    "wof:placetype":"locality"
},
  "geometry": {"coordinates":[19.0389,43.85917],"type":"Point"}
}