{
  "type": "Feature",
  "properties": {
    "gn:admin1_code":"01",
    "gn:asciiname":"Gornji Ivancici",
    "gn:country_code":"BA",
    "gn:dem":1004,
    "gn:feature_class":"P",
    "gn:feature_code":"PPL",
    "gn:name":"Gornji Ivan\u010di\u0107i",
    "gn:population":0,
    "gn:timezone":"Europe/Sarajevo",
    "iso:country":"BA",
    "name:bos_x_preferred":[
        "Ivan\u010di\u0107i"
    ],
    "name:ceb_x_preferred":[
        "Gornji Ivan\u010di\u0107i"
    ],
    "name:fra_x_preferred":[
        "Ivan\u010di\u0107i"
    ],
    "name:pol_x_preferred":[
        "Ivan\u010di\u0107i"
    ],
    "name:swe_x_preferred":[
        "Gornji Ivan\u010di\u0107i"
    ],
    "wof:name":"Gornji Ivancici",
    "wof:placetype":"locality"
},
  "geometry": {"coordinates":[18.47379,44.05128],"type":"Point"}
}