{
  "type": "Feature",
  "properties": {
    "gn:admin1_code":"01",
    "gn:asciiname":"Crna Gora",
    "gn:country_code":"BA",
    "gn:dem":382,
    "gn:feature_class":"P",
    "gn:feature_code":"PPL",
    "gn:name":"Crna Gora",
    "gn:population":0,
    "gn:timezone":"Europe/Sarajevo",
    "iso:country":"BA",
    "wof:name":"Crna Gora",
    "wof:placetype":"locality"
},
  "geometry": {"coordinates":[15.92663,45.05586],"type":"Point"}
}