{
  "type": "Feature",
  "properties": {
    "gn:admin1_code":"02",
    "gn:asciiname":"Krunic Mahala",
    "gn:country_code":"BA",
    "gn:dem":87,
    "gn:feature_class":"P",
    "gn:feature_code":"PPL",
    "gn:name":"Kruni\u0107 Mahala",
    "gn:population":0,
    "gn:timezone":"Europe/Sarajevo",
    "iso:country":"BA",
    "wof:name":"Krunic Mahala",
    "wof:placetype":"locality"
},
  "geometry": {"coordinates":[18.65897,44.93107],"type":"Point"}
}