{
  "type": "Feature",
  "properties": {
    "gn:admin1_code":"02",
    "gn:asciiname":"Bogicevici",
    "gn:country_code":"BA",
    "gn:dem":467,
    "gn:feature_class":"P",
    "gn:feature_code":"PPL",
    "gn:name":"Bogi\u0107evi\u0107i",
    "gn:population":0,
    "gn:timezone":"Europe/Sarajevo",
    "iso:country":"BA",
    "wof:name":"Bogicevici",
    "wof:placetype":"locality"
},
  "geometry": {"coordinates":[19.05916,44.1781],"type":"Point"}
}