{
  "type": "Feature",
  "properties": {
    "gn:admin1_code":"01",
    "gn:asciiname":"Soko",
    "gn:country_code":"BA",
    "gn:dem":368,
    "gn:feature_class":"P",
    "gn:feature_code":"PPL",
    "gn:name":"Soko",
    "gn:population":0,
    "gn:timezone":"Europe/Sarajevo",
    "iso:country":"BA",
    "name:bos_x_preferred":[
        "Soko"
    ],
    "name:ceb_x_preferred":[
        "Soko"
    ],
    "name:fra_x_preferred":[
        "Soko"
    ],
    "name:hrv_x_preferred":[
        "Soko"
    ],
    "name:und_x_variant":[
        "Sokol",
        "Soko"
    ],
    "wof:name":"Soko",
    "wof:placetype":"locality"
},
  "geometry": {"coordinates":[18.33944,44.744],"type":"Point"}
}