{
  "type": "Feature",
  "properties": {
    "gn:admin1_code":"01",
    "gn:asciiname":"Musici",
    "gn:country_code":"BA",
    "gn:dem":907,
    "gn:feature_class":"P",
    "gn:feature_code":"PPL",
    "gn:name":"Musi\u0107i",
    "gn:population":0,
    "gn:timezone":"Europe/Sarajevo",
    "iso:country":"BA",
    "wof:name":"Musici",
    "wof:placetype":"locality"
},
  "geometry": {"coordinates":[18.52244,44.11389000000001],"type":"Point"}
}