{
  "type": "Feature",
  "properties": {
    "gn:admin1_code":"BRC",
    "gn:asciiname":"Bijeli Potok",
    "gn:country_code":"BA",
    "gn:dem":263,
    "gn:feature_class":"P",
    "gn:feature_code":"PPL",
    "gn:name":"Bijeli Potok",
    "gn:population":0,
    "gn:timezone":"Europe/Sarajevo",
    "iso:country":"BA",
    "name:und_x_variant":[
        "Poto\u010dari",
        "Poto\u010dani",
        "Bijeli Potok"
    ],
    "wof:name":"Bijeli Potok",
    "wof:placetype":"locality"
},
  "geometry": {"coordinates":[18.54946,44.77784000000001],"type":"Point"}
}