{
  "type": "Feature",
  "properties": {
    "gn:admin1_code":"00",
    "gn:asciiname":"Goletici",
    "gn:country_code":"BA",
    "gn:dem":852,
    "gn:feature_class":"P",
    "gn:feature_code":"PPL",
    "gn:name":"Goleti\u0107i",
    "gn:population":0,
    "gn:timezone":"Europe/Sarajevo",
    "iso:country":"BA",
    "name:und_x_variant":[
        "Goleti\u0107",
        "Goleti\u0107i"
    ],
    "wof:name":"Goletici",
    "wof:placetype":"locality"
},
  "geometry": {"coordinates":[18.62803,44.27371],"type":"Point"}
}