{
  "type": "Feature",
  "properties": {
    "gn:admin1_code":"01",
    "gn:asciiname":"Donja Sibenica",
    "gn:country_code":"BA",
    "gn:dem":693,
    "gn:feature_class":"P",
    "gn:feature_code":"PPL",
    "gn:name":"Donja \u0160ibenica",
    "gn:population":0,
    "gn:timezone":"Europe/Sarajevo",
    "iso:country":"BA",
    "wof:name":"Donja Sibenica",
    "wof:placetype":"locality"
},
  "geometry": {"coordinates":[17.32716,44.32881],"type":"Point"}
}