{
  "type": "Feature",
  "properties": {
    "gn:admin1_code":"02",
    "gn:asciiname":"Cicina",
    "gn:country_code":"BA",
    "gn:dem":266,
    "gn:feature_class":"P",
    "gn:feature_code":"PPL",
    "gn:name":"Cicina",
    "gn:population":0,
    "gn:timezone":"Europe/Sarajevo",
    "iso:country":"BA",
    "wof:name":"Cicina",
    "wof:placetype":"locality"
},
  "geometry": {"coordinates":[18.19787,42.75088],"type":"Point"}
}