{
  "type": "Feature",
  "properties": {
    "gn:admin1_code":"02",
    "gn:asciiname":"Kosutica",
    "gn:country_code":"BA",
    "gn:dem":913,
    "gn:feature_class":"P",
    "gn:feature_code":"PPL",
    "gn:name":"Ko\u0161utica",
    "gn:population":0,
    "gn:timezone":"Europe/Sarajevo",
    "iso:country":"BA",
    "name:und_x_variant":[
        "Ko\u0161utica"
    ],
    "wof:name":"Kosutica",
    "wof:placetype":"locality"
},
  "geometry": {"coordinates":[18.84724,43.96986],"type":"Point"}
}