{
  "type": "Feature",
  "properties": {
    "gn:admin1_code":"02",
    "gn:asciiname":"Koprivice",
    "gn:country_code":"BA",
    "gn:dem":1212,
    "gn:feature_class":"P",
    "gn:feature_code":"PPL",
    "gn:name":"Koprivice",
    "gn:population":0,
    "gn:timezone":"Europe/Sarajevo",
    "iso:country":"BA",
    "wof:name":"Koprivice",
    "wof:placetype":"locality"
},
  "geometry": {"coordinates":[18.70829,43.90704],"type":"Point"}
}