{
  "type": "Feature",
  "properties": {
    "gn:admin1_code":"01",
    "gn:asciiname":"Ljevaci",
    "gn:country_code":"BA",
    "gn:dem":1109,
    "gn:feature_class":"P",
    "gn:feature_code":"PPL",
    "gn:name":"Ljevaci",
    "gn:population":0,
    "gn:timezone":"Europe/Sarajevo",
    "iso:country":"BA",
    "wof:name":"Ljevaci",
    "wof:placetype":"locality"
},
  "geometry": {"coordinates":[18.41459,44.13731],"type":"Point"}
}