{
  "type": "Feature",
  "properties": {
    "gn:admin1_code":"02",
    "gn:asciiname":"Culumi",
    "gn:country_code":"BA",
    "gn:dem":707,
    "gn:feature_class":"P",
    "gn:feature_code":"PPL",
    "gn:name":"\u0106ulumi",
    "gn:population":0,
    "gn:timezone":"Europe/Sarajevo",
    "iso:country":"BA",
    "wof:name":"Culumi",
    "wof:placetype":"locality"
},
  "geometry": {"coordinates":[16.96523,44.30557],"type":"Point"}
}