{
  "type": "Feature",
  "properties": {
    "gn:admin1_code":"02",
    "gn:asciiname":"Pridvorica",
    "gn:country_code":"BA",
    "gn:dem":949,
    "gn:feature_class":"P",
    "gn:feature_code":"PPL",
    "gn:name":"Pridvorica",
    "gn:population":0,
    "gn:timezone":"Europe/Sarajevo",
    "iso:country":"BA",
    "wof:name":"Pridvorica",
    "wof:placetype":"locality"
},
  "geometry": {"coordinates":[18.48262,43.3286],"type":"Point"}
}