{
  "type": "Feature",
  "properties": {
    "gn:admin1_code":"01",
    "gn:asciiname":"Bili Potok",
    "gn:country_code":"BA",
    "gn:dem":1166,
    "gn:feature_class":"P",
    "gn:feature_code":"PPL",
    "gn:name":"Bili Potok",
    "gn:population":0,
    "gn:timezone":"Europe/Sarajevo",
    "iso:country":"BA",
    "wof:name":"Bili Potok",
    "wof:placetype":"locality"
},
  "geometry": {"coordinates":[17.23207,44.00598],"type":"Point"}
}