{
  "type": "Feature",
  "properties": {
    "gn:admin1_code":"01",
    "gn:asciiname":"Bili Potok",
    "gn:country_code":"BA",
    "gn:dem":1166,
    "gn:feature_class":"P",
    "gn:feature_code":"PPL",
    "gn:name":"Bili Potok",
    "gn:population":0,
    "gn:timezone":"Europe/Sarajevo",
    "iso:country":"BA",
    "name:bos_x_preferred":[
        "Bili Potok"
    ],
    "name:fra_x_preferred":[
        "Bili Potok"
    ],
    "name:hrv_x_preferred":[
        "Bili Potok"
    ],
    "name:srp_x_preferred":[
        "\u0411\u0438\u043b\u0438 \u041f\u043e\u0442\u043e\u043a"
    ],
    "wof:name":"Bili Potok",
    "wof:placetype":"locality"
},
  "geometry": {"coordinates":[17.23207,44.00598],"type":"Point"}
}