{
  "type": "Feature",
  "properties": {
    "gn:admin1_code":"01",
    "gn:asciiname":"Dolac Kurtegic",
    "gn:country_code":"BA",
    "gn:dem":1453,
    "gn:feature_class":"P",
    "gn:feature_code":"PPL",
    "gn:name":"Dolac Kurtegi\u0107",
    "gn:population":0,
    "gn:timezone":"Europe/Sarajevo",
    "iso:country":"BA",
    "wof:name":"Dolac Kurtegic",
    "wof:placetype":"locality"
},
  "geometry": {"coordinates":[16.82527,43.75579000000001],"type":"Point"}
}