{
  "type": "Feature",
  "properties": {
    "gn:admin1_code":"02",
    "gn:asciiname":"Repusevici",
    "gn:country_code":"BA",
    "gn:dem":759,
    "gn:feature_class":"P",
    "gn:feature_code":"PPL",
    "gn:name":"Repu\u0161evi\u0107i",
    "gn:population":0,
    "gn:timezone":"Europe/Sarajevo",
    "iso:country":"BA",
    "name:bos_x_preferred":[
        "Repu\u0161evi\u0107i"
    ],
    "name:fra_x_preferred":[
        "Repu\u0161evi\u0107i"
    ],
    "name:hrv_x_preferred":[
        "Repu\u0161evi\u0107i"
    ],
    "name:rus_x_preferred":[
        "\u0420\u0435\u043f\u0443\u0448\u0435\u0432\u0438\u0447\u0438"
    ],
    "name:srp_x_preferred":[
        "\u0420\u0435\u043f\u0443\u0448\u0435\u0432\u0438\u045b\u0438"
    ],
    "name:und_x_variant":[
        "Repo\u0161evi\u0107i"
    ],
    "wof:name":"Repusevici",
    "wof:placetype":"locality"
},
  "geometry": {"coordinates":[19.35122,43.69744],"type":"Point"}
}