{
  "type": "Feature",
  "properties": {
    "gn:admin1_code":"01",
    "gn:asciiname":"Banjici",
    "gn:country_code":"BA",
    "gn:dem":265,
    "gn:feature_class":"P",
    "gn:feature_code":"PPL",
    "gn:name":"Banji\u0107i",
    "gn:population":0,
    "gn:timezone":"Europe/Sarajevo",
    "iso:country":"BA",
    "wof:name":"Banjici",
    "wof:placetype":"locality"
},
  "geometry": {"coordinates":[18.43701,44.55201],"type":"Point"}
}