{
  "type": "Feature",
  "properties": {
    "gn:admin1_code":"02",
    "gn:asciiname":"Caprek",
    "gn:country_code":"BA",
    "gn:dem":137,
    "gn:feature_class":"P",
    "gn:feature_code":"PPL",
    "gn:name":"Caprek",
    "gn:population":0,
    "gn:timezone":"Europe/Sarajevo",
    "iso:country":"BA",
    "wof:name":"Caprek",
    "wof:placetype":"locality"
},
  "geometry": {"coordinates":[16.64666,45.01268],"type":"Point"}
}