{
  "type": "Feature",
  "properties": {
    "gn:admin1_code":"01",
    "gn:asciiname":"Cohodari",
    "gn:country_code":"BA",
    "gn:dem":369,
    "gn:feature_class":"P",
    "gn:feature_code":"PPL",
    "gn:name":"\u010cohodari",
    "gn:population":0,
    "gn:timezone":"Europe/Sarajevo",
    "iso:country":"BA",
    "wof:name":"Cohodari",
    "wof:placetype":"locality"
},
  "geometry": {"coordinates":[15.9919,44.9325],"type":"Point"}
}