{
  "type": "Feature",
  "properties": {
    "gn:admin1_code":"02",
    "gn:asciiname":"Jusici",
    "gn:country_code":"BA",
    "gn:dem":266,
    "gn:feature_class":"P",
    "gn:feature_code":"PPL",
    "gn:name":"Ju\u0161i\u0107i",
    "gn:population":0,
    "gn:timezone":"Europe/Sarajevo",
    "iso:country":"BA",
    "name:bos_x_preferred":[
        "Ju\u0161i\u0107i"
    ],
    "name:fra_x_preferred":[
        "Ju\u0161i\u0107i"
    ],
    "name:hrv_x_preferred":[
        "Ju\u0161i\u0107i"
    ],
    "name:hun_x_preferred":[
        "Ju\u0161i\u0107i"
    ],
    "name:srp_x_preferred":[
        "\u0408\u0443\u0448\u0438\u045b\u0438"
    ],
    "name:und_x_variant":[
        "Ju\u0161i\u0107i"
    ],
    "wof:name":"Jusici",
    "wof:placetype":"locality"
},
  "geometry": {"coordinates":[18.22111,42.73333],"type":"Point"}
}