{
  "type": "Feature",
  "properties": {
    "gn:admin1_code":"02",
    "gn:asciiname":"Dangube",
    "gn:country_code":"BA",
    "gn:dem":79,
    "gn:feature_class":"P",
    "gn:feature_code":"PPL",
    "gn:name":"Dangube",
    "gn:population":0,
    "gn:timezone":"Europe/Sarajevo",
    "iso:country":"BA",
    "name:und_x_variant":[
        "Danguba",
        "Dangube"
    ],
    "wof:name":"Dangube",
    "wof:placetype":"locality"
},
  "geometry": {"coordinates":[19.23691,44.87076],"type":"Point"}
}