{
  "type": "Feature",
  "properties": {
    "gn:admin1_code":"02",
    "gn:asciiname":"Rudice",
    "gn:country_code":"BA",
    "gn:dem":124,
    "gn:feature_class":"P",
    "gn:feature_code":"PPL",
    "gn:name":"Rudice",
    "gn:population":0,
    "gn:timezone":"Europe/Sarajevo",
    "iso:country":"BA",
    "wof:name":"Rudice",
    "wof:placetype":"locality"
},
  "geometry": {"coordinates":[16.35861,45.00417],"type":"Point"}
}