{
  "type": "Feature",
  "properties": {
    "gn:admin1_code":"02",
    "gn:asciiname":"Lipovac",
    "gn:country_code":"BA",
    "gn:dem":197,
    "gn:feature_class":"P",
    "gn:feature_code":"PPL",
    "gn:name":"Lipovac",
    "gn:population":0,
    "gn:timezone":"Europe/Sarajevo",
    "iso:country":"BA",
    "wof:name":"Lipovac",
    "wof:placetype":"locality"
},
  "geometry": {"coordinates":[17.13184,44.89232],"type":"Point"}
}