{
  "type": "Feature",
  "properties": {
    "gn:admin1_code":"01",
    "gn:asciiname":"Dubrava",
    "gn:country_code":"BA",
    "gn:dem":76,
    "gn:feature_class":"P",
    "gn:feature_code":"PPL",
    "gn:name":"Dubrava",
    "gn:population":0,
    "gn:timezone":"Europe/Sarajevo",
    "iso:country":"BA",
    "wof:name":"Dubrava",
    "wof:placetype":"locality"
},
  "geometry": {"coordinates":[17.48371,43.20135],"type":"Point"}
}