{
  "type": "Feature",
  "properties": {
    "gn:admin1_code":"02",
    "gn:asciiname":"Durdevici",
    "gn:country_code":"BA",
    "gn:dem":304,
    "gn:feature_class":"P",
    "gn:feature_code":"PPL",
    "gn:name":"\u00d0urdevi\u0107i",
    "gn:population":0,
    "gn:timezone":"Europe/Sarajevo",
    "iso:country":"BA",
    "wof:name":"Durdevici",
    "wof:placetype":"locality"
},
  "geometry": {"coordinates":[19.07879,44.17979],"type":"Point"}
}