{
  "type": "Feature",
  "properties": {
    "gn:admin1_code":"01",
    "gn:asciiname":"Antonici",
    "gn:country_code":"BA",
    "gn:dem":354,
    "gn:feature_class":"P",
    "gn:feature_code":"PPL",
    "gn:name":"Antoni\u0107i",
    "gn:population":0,
    "gn:timezone":"Europe/Sarajevo",
    "iso:country":"BA",
    "wof:name":"Antonici",
    "wof:placetype":"locality"
},
  "geometry": {"coordinates":[16.41279,44.85188],"type":"Point"}
}