{
  "type": "Feature",
  "properties": {
    "gn:admin1_code":"02",
    "gn:asciiname":"Marjanci",
    "gn:country_code":"BA",
    "gn:dem":344,
    "gn:feature_class":"P",
    "gn:feature_code":"PPL",
    "gn:name":"Marjanci",
    "gn:population":0,
    "gn:timezone":"Europe/Sarajevo",
    "iso:country":"BA",
    "wof:name":"Marjanci",
    "wof:placetype":"locality"
},
  "geometry": {"coordinates":[17.07313,44.79148],"type":"Point"}
}