{
  "type": "Feature",
  "properties": {
    "gn:admin1_code":"02",
    "gn:asciiname":"Sajtovici",
    "gn:country_code":"BA",
    "gn:dem":324,
    "gn:feature_class":"P",
    "gn:feature_code":"PPL",
    "gn:name":"Sajtovi\u0107i",
    "gn:population":0,
    "gn:timezone":"Europe/Sarajevo",
    "iso:country":"BA",
    "name:bos_x_preferred":[
        "Sajtovi\u0107i"
    ],
    "name:ceb_x_preferred":[
        "Sajtovi\u0107i"
    ],
    "name:fra_x_preferred":[
        "Sajtovi\u0107i"
    ],
    "name:hrv_x_preferred":[
        "Sajtovi\u0107i"
    ],
    "name:srp_x_preferred":[
        "\u0421\u0430\u0458\u0442\u043e\u0432\u0438\u045b\u0438"
    ],
    "name:swe_x_preferred":[
        "Sajtovi\u0107i"
    ],
    "name:und_x_variant":[
        "Sajovi\u0107i",
        "Sajtovi\u0107i"
    ],
    "wof:name":"Sajtovici",
    "wof:placetype":"locality"
},
  "geometry": {"coordinates":[18.88993,44.37835],"type":"Point"}
}