{
  "type": "Feature",
  "properties": {
    "gn:admin1_code":"01",
    "gn:asciiname":"Bogosici",
    "gn:country_code":"BA",
    "gn:dem":563,
    "gn:feature_class":"P",
    "gn:feature_code":"PPL",
    "gn:name":"Bogo\u0161i\u0107i",
    "gn:population":0,
    "gn:timezone":"Europe/Sarajevo",
    "iso:country":"BA",
    "wof:name":"Bogosici",
    "wof:placetype":"locality"
},
  "geometry": {"coordinates":[18.19735,44.04598],"type":"Point"}
}