{
  "type": "Feature",
  "properties": {
    "gn:admin1_code":"02",
    "gn:asciiname":"Golo Brdo",
    "gn:country_code":"BA",
    "gn:dem":1098,
    "gn:feature_class":"P",
    "gn:feature_code":"PPL",
    "gn:name":"Golo Brdo",
    "gn:population":0,
    "gn:timezone":"Europe/Sarajevo",
    "iso:country":"BA",
    "wof:name":"Golo Brdo",
    "wof:placetype":"locality"
},
  "geometry": {"coordinates":[17.45301,44.48635],"type":"Point"}
}