{
  "type": "Feature",
  "properties": {
    "gn:admin1_code":"01",
    "gn:asciiname":"Runici",
    "gn:country_code":"BA",
    "gn:dem":718,
    "gn:feature_class":"P",
    "gn:feature_code":"PPL",
    "gn:name":"Runi\u0107i",
    "gn:population":0,
    "gn:timezone":"Europe/Sarajevo",
    "iso:country":"BA",
    "wof:name":"Runici",
    "wof:placetype":"locality"
},
  "geometry": {"coordinates":[16.37465,44.5046],"type":"Point"}
}