{
  "type": "Feature",
  "properties": {
    "gn:admin1_code":"01",
    "gn:asciiname":"Hodzici",
    "gn:country_code":"BA",
    "gn:dem":779,
    "gn:feature_class":"P",
    "gn:feature_code":"PPL",
    "gn:name":"Hod\u017ei\u0107i",
    "gn:population":0,
    "gn:timezone":"Europe/Sarajevo",
    "iso:country":"BA",
    "name:und_x_variant":[
        "Hod\u017ei\u0107i"
    ],
    "wof:name":"Hodzici",
    "wof:placetype":"locality"
},
  "geometry": {"coordinates":[18.09264,44.24914],"type":"Point"}
}