{
  "type": "Feature",
  "properties": {
    "gn:admin1_code":"02",
    "gn:asciiname":"Donji Bulozi",
    "gn:country_code":"BA",
    "gn:dem":776,
    "gn:feature_class":"P",
    "gn:feature_code":"PPL",
    "gn:name":"Donji Bulozi",
    "gn:population":0,
    "gn:timezone":"Europe/Sarajevo",
    "iso:country":"BA",
    "name:und_x_variant":[
        "Bulozi",
        "Donji Bulozi"
    ],
    "wof:name":"Donji Bulozi",
    "wof:placetype":"locality"
},
  "geometry": {"coordinates":[18.50486,43.84854],"type":"Point"}
}