{
  "type": "Feature",
  "properties": {
    "gn:admin1_code":"01",
    "gn:asciiname":"Lug",
    "gn:country_code":"BA",
    "gn:dem":895,
    "gn:feature_class":"P",
    "gn:feature_code":"PPL",
    "gn:name":"Lug",
    "gn:population":0,
    "gn:timezone":"Europe/Sarajevo",
    "iso:country":"BA",
    "wof:name":"Lug",
    "wof:placetype":"locality"
},
  "geometry": {"coordinates":[17.24165,43.75933],"type":"Point"}
}