{
  "type": "Feature",
  "properties": {
    "gn:admin1_code":"01",
    "gn:asciiname":"Lug",
    "gn:country_code":"BA",
    "gn:dem":895,
    "gn:feature_class":"P",
    "gn:feature_code":"PPL",
    "gn:name":"Lug",
    "gn:population":0,
    "gn:timezone":"Europe/Sarajevo",
    "iso:country":"BA",
    "name:bel_x_preferred":[
        "\u041b\u0443\u0433"
    ],
    "name:bos_x_preferred":[
        "Lug"
    ],
    "name:ceb_x_preferred":[
        "Lug"
    ],
    "name:deu_x_preferred":[
        "Lug"
    ],
    "name:est_x_preferred":[
        "Lug"
    ],
    "name:fra_x_preferred":[
        "Lug"
    ],
    "name:hrv_x_preferred":[
        "Lug"
    ],
    "name:hun_x_preferred":[
        "Lug"
    ],
    "name:hye_x_preferred":[
        "\u053c\u0578\u0582\u0563"
    ],
    "name:nld_x_preferred":[
        "Lug"
    ],
    "name:pol_x_preferred":[
        "Lug"
    ],
    "name:por_x_preferred":[
        "Lug"
    ],
    "name:ron_x_preferred":[
        "Lug"
    ],
    "name:rus_x_preferred":[
        "\u041b\u0443\u0433"
    ],
    "name:slv_x_preferred":[
        "Lug"
    ],
    "name:spa_x_preferred":[
        "Lug"
    ],
    "name:srp_x_preferred":[
        "\u041b\u0443\u0433"
    ],
    "name:swe_x_preferred":[
        "Lug"
    ],
    "name:ukr_x_preferred":[
        "\u041b\u0443\u0433"
    ],
    "wof:name":"Lug",
    "wof:placetype":"locality"
},
  "geometry": {"coordinates":[17.24165,43.75933],"type":"Point"}
}