{
  "type": "Feature",
  "properties": {
    "gn:admin1_code":"01",
    "gn:asciiname":"Domazeti",
    "gn:country_code":"BA",
    "gn:dem":258,
    "gn:feature_class":"P",
    "gn:feature_code":"PPL",
    "gn:name":"Domazeti",
    "gn:population":0,
    "gn:timezone":"Europe/Sarajevo",
    "iso:country":"BA",
    "wof:name":"Domazeti",
    "wof:placetype":"locality"
},
  "geometry": {"coordinates":[16.6977,44.5948],"type":"Point"}
}