{
  "type": "Feature",
  "properties": {
    "gn:admin1_code":"01",
    "gn:asciiname":"Karicuse",
    "gn:country_code":"BA",
    "gn:dem":805,
    "gn:feature_class":"P",
    "gn:feature_code":"PPL",
    "gn:name":"Kari\u0107u\u0161e",
    "gn:population":0,
    "gn:timezone":"Europe/Sarajevo",
    "iso:country":"BA",
    "wof:name":"Karicuse",
    "wof:placetype":"locality"
},
  "geometry": {"coordinates":[17.96737000000001,43.26232],"type":"Point"}
}