{
  "type": "Feature",
  "properties": {
    "gn:admin1_code":"02",
    "gn:asciiname":"Bljustevac",
    "gn:country_code":"BA",
    "gn:dem":962,
    "gn:feature_class":"P",
    "gn:feature_code":"PPL",
    "gn:name":"Blju\u0161tevac",
    "gn:population":0,
    "gn:timezone":"Europe/Sarajevo",
    "iso:country":"BA",
    "name:bos_x_preferred":[
        "Blju\u0161tevac"
    ],
    "name:ceb_x_preferred":[
        "Blju\u0161tevac"
    ],
    "name:fra_x_preferred":[
        "Blju\u0161tevac"
    ],
    "name:srp_x_preferred":[
        "\u0411\u0459\u0443\u0448\u0442\u0435\u0432\u0430\u0446"
    ],
    "name:swe_x_preferred":[
        "Blju\u0161tevac"
    ],
    "name:und_x_variant":[
        "Bljustavac"
    ],
    "wof:name":"Bljustevac",
    "wof:placetype":"locality"
},
  "geometry": {"coordinates":[18.60123,43.88614000000001],"type":"Point"}
}