{
  "type": "Feature",
  "properties": {
    "gn:admin1_code":"02",
    "gn:asciiname":"Bljustevac",
    "gn:country_code":"BA",
    "gn:dem":962,
    "gn:feature_class":"P",
    "gn:feature_code":"PPL",
    "gn:name":"Blju\u0161tevac",
    "gn:population":0,
    "gn:timezone":"Europe/Sarajevo",
    "iso:country":"BA",
    "name:und_x_variant":[
        "Bljustavac",
        "Blju\u0161tevac"
    ],
    "wof:name":"Bljustevac",
    "wof:placetype":"locality"
},
  "geometry": {"coordinates":[18.60123,43.88614000000001],"type":"Point"}
}