{
  "type": "Feature",
  "properties": {
    "gn:admin1_code":"02",
    "gn:asciiname":"Bakinci",
    "gn:country_code":"BA",
    "gn:dem":142,
    "gn:feature_class":"P",
    "gn:feature_code":"PPL",
    "gn:name":"Bakinci",
    "gn:population":0,
    "gn:timezone":"Europe/Sarajevo",
    "iso:country":"BA",
    "wof:name":"Bakinci",
    "wof:placetype":"locality"
},
  "geometry": {"coordinates":[17.25147999999999,44.9455],"type":"Point"}
}