{
  "type": "Feature",
  "properties": {
    "gn:admin1_code":"01",
    "gn:asciiname":"Bajici",
    "gn:country_code":"BA",
    "gn:dem":1218,
    "gn:feature_class":"P",
    "gn:feature_code":"PPL",
    "gn:name":"Baji\u0107i",
    "gn:population":0,
    "gn:timezone":"Europe/Sarajevo",
    "iso:country":"BA",
    "wof:name":"Bajici",
    "wof:placetype":"locality"
},
  "geometry": {"coordinates":[17.38657000000001,43.91078],"type":"Point"}
}