{
  "type": "Feature",
  "properties": {
    "gn:admin1_code":"02",
    "gn:asciiname":"Arsenici",
    "gn:country_code":"BA",
    "gn:dem":97,
    "gn:feature_class":"P",
    "gn:feature_code":"PPL",
    "gn:name":"Arseni\u0107i",
    "gn:population":0,
    "gn:timezone":"Europe/Sarajevo",
    "iso:country":"BA",
    "wof:name":"Arsenici",
    "wof:placetype":"locality"
},
  "geometry": {"coordinates":[18.97267,44.81733],"type":"Point"}
}