{
  "type": "Feature",
  "properties": {
    "gn:admin1_code":"01",
    "gn:asciiname":"Stjepanovici",
    "gn:country_code":"BA",
    "gn:dem":389,
    "gn:feature_class":"P",
    "gn:feature_code":"PPL",
    "gn:name":"Stjepanovi\u0107i",
    "gn:population":0,
    "gn:timezone":"Europe/Sarajevo",
    "iso:country":"BA",
    "wof:name":"Stjepanovici",
    "wof:placetype":"locality"
},
  "geometry": {"coordinates":[18.64039,44.59657],"type":"Point"}
}