{
  "type": "Feature",
  "properties": {
    "gn:admin1_code":"02",
    "gn:asciiname":"Cudojevici",
    "gn:country_code":"BA",
    "gn:dem":620,
    "gn:feature_class":"P",
    "gn:feature_code":"PPL",
    "gn:name":"\u010cudojevi\u0107i",
    "gn:population":0,
    "gn:timezone":"Europe/Sarajevo",
    "iso:country":"BA",
    "wof:name":"Cudojevici",
    "wof:placetype":"locality"
},
  "geometry": {"coordinates":[18.96049,43.58518],"type":"Point"}
}