{
  "type": "Feature",
  "properties": {
    "gn:admin1_code":"02",
    "gn:asciiname":"Stojkovici",
    "gn:country_code":"BA",
    "gn:dem":199,
    "gn:feature_class":"P",
    "gn:feature_code":"PPL",
    "gn:name":"Stojkovi\u0107i",
    "gn:population":0,
    "gn:timezone":"Europe/Sarajevo",
    "iso:country":"BA",
    "wof:name":"Stojkovici",
    "wof:placetype":"locality"
},
  "geometry": {"coordinates":[17.86771,44.64008],"type":"Point"}
}