{
  "type": "Feature",
  "properties": {
    "gn:admin1_code":"01",
    "gn:asciiname":"Kopcic",
    "gn:country_code":"BA",
    "gn:dem":541,
    "gn:feature_class":"P",
    "gn:feature_code":"PPL",
    "gn:name":"Kop\u010di\u0107",
    "gn:population":0,
    "gn:timezone":"Europe/Sarajevo",
    "iso:country":"BA",
    "name:und_x_variant":[
        "Kop\u010di\u0107"
    ],
    "wof:name":"Kopcic",
    "wof:placetype":"locality"
},
  "geometry": {"coordinates":[17.41861,44.10777],"type":"Point"}
}