{
  "type": "Feature",
  "properties": {
    "gn:admin1_code":"02",
    "gn:asciiname":"Grbaca",
    "gn:country_code":"BA",
    "gn:dem":90,
    "gn:feature_class":"P",
    "gn:feature_code":"PPL",
    "gn:name":"Grba\u010da",
    "gn:population":0,
    "gn:timezone":"Europe/Sarajevo",
    "iso:country":"BA",
    "wof:name":"Grbaca",
    "wof:placetype":"locality"
},
  "geometry": {"coordinates":[18.49926,44.97966],"type":"Point"}
}