{
  "type": "Feature",
  "properties": {
    "gn:admin1_code":"02",
    "gn:asciiname":"Donje Brdo",
    "gn:country_code":"BA",
    "gn:dem":207,
    "gn:feature_class":"P",
    "gn:feature_code":"PPL",
    "gn:name":"Donje Brdo",
    "gn:population":0,
    "gn:timezone":"Europe/Sarajevo",
    "iso:country":"BA",
    "wof:name":"Donje Brdo",
    "wof:placetype":"locality"
},
  "geometry": {"coordinates":[16.91656,45.09734],"type":"Point"}
}