{
  "type": "Feature",
  "properties": {
    "gn:admin1_code":"01",
    "gn:asciiname":"Donja Jasenica",
    "gn:country_code":"BA",
    "gn:dem":44,
    "gn:feature_class":"P",
    "gn:feature_code":"PPL",
    "gn:name":"Donja Jasenica",
    "gn:population":0,
    "gn:timezone":"Europe/Sarajevo",
    "iso:country":"BA",
    "wof:name":"Donja Jasenica",
    "wof:placetype":"locality"
},
  "geometry": {"coordinates":[17.80672999999999,43.27826],"type":"Point"}
}