{
  "type": "Feature",
  "properties": {
    "gn:admin1_code":"02",
    "gn:asciiname":"Simici",
    "gn:country_code":"BA",
    "gn:dem":186,
    "gn:feature_class":"P",
    "gn:feature_code":"PPL",
    "gn:name":"Simi\u0107i",
    "gn:population":0,
    "gn:timezone":"Europe/Sarajevo",
    "iso:country":"BA",
    "wof:name":"Simici",
    "wof:placetype":"locality"
},
  "geometry": {"coordinates":[17.82624,44.83124],"type":"Point"}
}