{
  "type": "Feature",
  "properties": {
    "gn:admin1_code":"01",
    "gn:asciiname":"Veliki Skocaj",
    "gn:country_code":"BA",
    "gn:dem":379,
    "gn:feature_class":"P",
    "gn:feature_code":"PPL",
    "gn:name":"Veliki Sko\u010daj",
    "gn:population":0,
    "gn:timezone":"Europe/Sarajevo",
    "iso:country":"BA",
    "name:und_x_variant":[
        "Veliki Sko\u010daj"
    ],
    "wof:name":"Veliki Skocaj",
    "wof:placetype":"locality"
},
  "geometry": {"coordinates":[15.87472,44.75639],"type":"Point"}
}