{
  "type": "Feature",
  "properties": {
    "gn:admin1_code":"02",
    "gn:asciiname":"Gornje Selo",
    "gn:country_code":"BA",
    "gn:dem":999,
    "gn:feature_class":"P",
    "gn:feature_code":"PPL",
    "gn:name":"Gornje Selo",
    "gn:population":0,
    "gn:timezone":"Europe/Sarajevo",
    "iso:country":"BA",
    "wof:name":"Gornje Selo",
    "wof:placetype":"locality"
},
  "geometry": {"coordinates":[18.59135,43.05549],"type":"Point"}
}