{
  "type": "Feature",
  "properties": {
    "gn:admin1_code":"01",
    "gn:asciiname":"Basici",
    "gn:country_code":"BA",
    "gn:dem":730,
    "gn:feature_class":"P",
    "gn:feature_code":"PPL",
    "gn:name":"Ba\u0161i\u0107i",
    "gn:population":0,
    "gn:timezone":"Europe/Sarajevo",
    "iso:country":"BA",
    "name:bos_x_preferred":[
        "Ba\u0161i\u0107i"
    ],
    "name:ceb_x_preferred":[
        "Ba\u0161i\u0107i"
    ],
    "name:fra_x_preferred":[
        "Ba\u0161i\u0107i"
    ],
    "name:hrv_x_preferred":[
        "Ba\u0161i\u0107i"
    ],
    "name:srp_x_preferred":[
        "\u0411\u0430\u0448\u0438\u045b\u0438"
    ],
    "name:swe_x_preferred":[
        "Ba\u0161i\u0107i"
    ],
    "name:und_x_variant":[
        "Ba\u0161i\u0107i"
    ],
    "wof:name":"Basici",
    "wof:placetype":"locality"
},
  "geometry": {"coordinates":[18.11176,44.23419000000001],"type":"Point"}
}