{
  "type": "Feature",
  "properties": {
    "gn:admin1_code":"01",
    "gn:asciiname":"Briza",
    "gn:country_code":"BA",
    "gn:dem":984,
    "gn:feature_class":"P",
    "gn:feature_code":"PPL",
    "gn:name":"Briza",
    "gn:population":0,
    "gn:timezone":"Europe/Sarajevo",
    "iso:country":"BA",
    "wof:name":"Briza",
    "wof:placetype":"locality"
},
  "geometry": {"coordinates":[18.01566,44.08591],"type":"Point"}
}