{
  "type": "Feature",
  "properties": {
    "gn:admin1_code":"02",
    "gn:asciiname":"Stanici",
    "gn:country_code":"BA",
    "gn:dem":256,
    "gn:feature_class":"P",
    "gn:feature_code":"PPL",
    "gn:name":"Stani\u0107i",
    "gn:population":0,
    "gn:timezone":"Europe/Sarajevo",
    "iso:country":"BA",
    "wof:name":"Stanici",
    "wof:placetype":"locality"
},
  "geometry": {"coordinates":[18.01167000000001,44.92944],"type":"Point"}
}