{
  "type": "Feature",
  "properties": {
    "gn:admin1_code":"01",
    "gn:asciiname":"Kuline",
    "gn:country_code":"BA",
    "gn:dem":19,
    "gn:feature_class":"P",
    "gn:feature_code":"PPL",
    "gn:name":"Kuline",
    "gn:population":0,
    "gn:timezone":"Europe/Sarajevo",
    "iso:country":"BA",
    "wof:name":"Kuline",
    "wof:placetype":"locality"
},
  "geometry": {"coordinates":[17.73944,43.08944],"type":"Point"}
}