{
  "type": "Feature",
  "properties": {
    "gn:admin1_code":"01",
    "gn:asciiname":"Delanovici",
    "gn:country_code":"BA",
    "gn:dem":239,
    "gn:feature_class":"P",
    "gn:feature_code":"PPL",
    "gn:name":"Delanovi\u0107i",
    "gn:population":0,
    "gn:timezone":"Europe/Sarajevo",
    "iso:country":"BA",
    "wof:name":"Delanovici",
    "wof:placetype":"locality"
},
  "geometry": {"coordinates":[15.8101,45.12256],"type":"Point"}
}