{
  "type": "Feature",
  "properties": {
    "gn:admin1_code":"01",
    "gn:asciiname":"Veliko Selo",
    "gn:country_code":"BA",
    "gn:dem":524,
    "gn:feature_class":"P",
    "gn:feature_code":"PPL",
    "gn:name":"Veliko Selo",
    "gn:population":0,
    "gn:timezone":"Europe/Sarajevo",
    "iso:country":"BA",
    "wof:name":"Veliko Selo",
    "wof:placetype":"locality"
},
  "geometry": {"coordinates":[19.03333,44.55],"type":"Point"}
}