{
  "type": "Feature",
  "properties": {
    "gn:admin1_code":"02",
    "gn:asciiname":"Verici",
    "gn:country_code":"BA",
    "gn:dem":271,
    "gn:feature_class":"P",
    "gn:feature_code":"PPLL",
    "gn:name":"Veri\u0107i",
    "gn:population":0,
    "gn:timezone":"Europe/Sarajevo",
    "iso:country":"BA",
    "name:und_x_variant":[
        "Veri\u0107i"
    ],
    "wof:name":"Verici",
    "wof:placetype":"locality"
},
  "geometry": {"coordinates":[17.00772000000001,44.92446],"type":"Point"}
}