{
  "type": "Feature",
  "properties": {
    "gn:admin1_code":"02",
    "gn:asciiname":"Verici",
    "gn:country_code":"BA",
    "gn:dem":271,
    "gn:feature_class":"P",
    "gn:feature_code":"PPLL",
    "gn:name":"Veri\u0107i",
    "gn:population":0,
    "gn:timezone":"Europe/Sarajevo",
    "iso:country":"BA",
    "name:bos_x_preferred":[
        "Veri\u0107i"
    ],
    "name:ceb_x_preferred":[
        "Veri\u0107i"
    ],
    "name:fas_x_preferred":[
        "\u0648\u0631\u06cc\u0686\u06cc"
    ],
    "name:fra_x_preferred":[
        "Veri\u0107i"
    ],
    "name:hrv_x_preferred":[
        "Veri\u0107i"
    ],
    "name:rus_x_preferred":[
        "\u0412\u0435\u0440\u0438\u0447\u0438"
    ],
    "name:slv_x_preferred":[
        "Veri\u0107i"
    ],
    "name:srp_x_preferred":[
        "\u0412\u0435\u0440\u0438\u045b\u0438"
    ],
    "wof:name":"Verici",
    "wof:placetype":"locality"
},
  "geometry": {"coordinates":[17.00772000000001,44.92446],"type":"Point"}
}