{
  "type": "Feature",
  "properties": {
    "gn:admin1_code":"01",
    "gn:asciiname":"Alicevici",
    "gn:country_code":"BA",
    "gn:dem":363,
    "gn:feature_class":"P",
    "gn:feature_code":"PPL",
    "gn:name":"Ali\u010devi\u0107i",
    "gn:population":0,
    "gn:timezone":"Europe/Sarajevo",
    "iso:country":"BA",
    "wof:name":"Alicevici",
    "wof:placetype":"locality"
},
  "geometry": {"coordinates":[16.06247,45.01911],"type":"Point"}
}