{
  "type": "Feature",
  "properties": {
    "gn:admin1_code":"02",
    "gn:asciiname":"Ozren",
    "gn:country_code":"BA",
    "gn:dem":294,
    "gn:feature_class":"P",
    "gn:feature_code":"PPL",
    "gn:name":"Ozren",
    "gn:population":0,
    "gn:timezone":"Europe/Sarajevo",
    "iso:country":"BA",
    "name:bos_x_preferred":[
        "Ozren"
    ],
    "name:ceb_x_preferred":[
        "Ozren"
    ],
    "name:deu_x_preferred":[
        "Ozren"
    ],
    "name:fra_x_preferred":[
        "Ozren"
    ],
    "name:hrv_x_preferred":[
        "Ozren"
    ],
    "name:pol_x_preferred":[
        "Ozren"
    ],
    "name:srp_x_preferred":[
        "\u041e\u0437\u0440\u0435\u043d"
    ],
    "name:swe_x_preferred":[
        "Ozren"
    ],
    "wof:name":"Ozren",
    "wof:placetype":"locality"
},
  "geometry": {"coordinates":[18.32992,44.59804000000001],"type":"Point"}
}