{
  "type": "Feature",
  "properties": {
    "gn:admin1_code":"02",
    "gn:asciiname":"Kazanci",
    "gn:country_code":"BA",
    "gn:dem":655,
    "gn:feature_class":"P",
    "gn:feature_code":"PPL",
    "gn:name":"Kazanci",
    "gn:population":0,
    "gn:timezone":"Europe/Sarajevo",
    "iso:country":"BA",
    "name:bos_x_preferred":[
        "Kazanci"
    ],
    "name:ceb_x_preferred":[
        "Kazanci"
    ],
    "name:fra_x_preferred":[
        "Kazanci"
    ],
    "name:ron_x_preferred":[
        "Kazanci"
    ],
    "name:slv_x_preferred":[
        "Kazanci"
    ],
    "name:srp_x_preferred":[
        "\u041a\u0430\u0437\u0430\u043d\u0446\u0438"
    ],
    "wof:name":"Kazanci",
    "wof:placetype":"locality"
},
  "geometry": {"coordinates":[19.21345,43.74858],"type":"Point"}
}