{
  "type": "Feature",
  "properties": {
    "gn:admin1_code":"01",
    "gn:asciiname":"Cicci",
    "gn:country_code":"BA",
    "gn:dem":258,
    "gn:feature_class":"P",
    "gn:feature_code":"PPL",
    "gn:name":"\u010ci\u010dci",
    "gn:population":0,
    "gn:timezone":"Europe/Sarajevo",
    "iso:country":"BA",
    "wof:name":"Cicci",
    "wof:placetype":"locality"
},
  "geometry": {"coordinates":[17.97671,44.69745],"type":"Point"}
}