{
  "type": "Feature",
  "properties": {
    "gn:admin1_code":"02",
    "gn:asciiname":"Milovanovici",
    "gn:country_code":"BA",
    "gn:dem":145,
    "gn:feature_class":"P",
    "gn:feature_code":"PPL",
    "gn:name":"Milovanovi\u0107i",
    "gn:population":0,
    "gn:timezone":"Europe/Sarajevo",
    "iso:country":"BA",
    "wof:name":"Milovanovici",
    "wof:placetype":"locality"
},
  "geometry": {"coordinates":[17.20176,45.05512],"type":"Point"}
}