{
  "type": "Feature",
  "properties": {
    "gn:admin1_code":"01",
    "gn:asciiname":"Manjica Han",
    "gn:country_code":"BA",
    "gn:dem":892,
    "gn:feature_class":"P",
    "gn:feature_code":"PPL",
    "gn:name":"Manji\u0107a Han",
    "gn:population":0,
    "gn:timezone":"Europe/Sarajevo",
    "iso:country":"BA",
    "wof:name":"Manjica Han",
    "wof:placetype":"locality"
},
  "geometry": {"coordinates":[17.23541,43.76236],"type":"Point"}
}