{
  "type": "Feature",
  "properties": {
    "gn:admin1_code":"01",
    "gn:asciiname":"Modra",
    "gn:country_code":"BA",
    "gn:dem":441,
    "gn:feature_class":"P",
    "gn:feature_code":"PPLL",
    "gn:name":"Modra",
    "gn:population":0,
    "gn:timezone":"Europe/Sarajevo",
    "iso:country":"BA",
    "name:ara_x_preferred":[
        "\u0645\u0648\u062f\u0631\u0627"
    ],
    "name:bel_x_preferred":[
        "\u041c\u043e\u0434\u0440\u0430"
    ],
    "name:ceb_x_preferred":[
        "Modra"
    ],
    "name:ces_x_preferred":[
        "Modra"
    ],
    "name:dan_x_preferred":[
        "Modra"
    ],
    "name:deu_x_preferred":[
        "Modra"
    ],
    "name:epo_x_preferred":[
        "Modra"
    ],
    "name:est_x_preferred":[
        "Modra"
    ],
    "name:eus_x_preferred":[
        "Modra"
    ],
    "name:fas_x_preferred":[
        "\u0645\u062f\u0631\u0627"
    ],
    "name:fra_x_preferred":[
        "Modra"
    ],
    "name:hrv_x_preferred":[
        "Modra"
    ],
    "name:hun_x_preferred":[
        "Modor"
    ],
    "name:hye_x_preferred":[
        "\u0544\u0578\u0564\u0580\u0561"
    ],
    "name:ind_x_preferred":[
        "Modra"
    ],
    "name:ita_x_preferred":[
        "Modra"
    ],
    "name:kor_x_preferred":[
        "\ubaa8\ub4dc\ub77c"
    ],
    "name:lav_x_preferred":[
        "Modra"
    ],
    "name:msa_x_preferred":[
        "Modra"
    ],
    "name:nld_x_preferred":[
        "Modra"
    ],
    "name:pol_x_preferred":[
        "Modra"
    ],
    "name:por_x_preferred":[
        "Modra"
    ],
    "name:ron_x_preferred":[
        "Modra"
    ],
    "name:rus_x_preferred":[
        "\u041c\u043e\u0434\u0440\u0430"
    ],
    "name:slk_x_preferred":[
        "Modra"
    ],
    "name:slv_x_preferred":[
        "Modra"
    ],
    "name:spa_x_preferred":[
        "Modra"
    ],
    "name:srp_x_preferred":[
        "\u041c\u043e\u0434\u0440\u0430"
    ],
    "name:swe_x_preferred":[
        "Modra"
    ],
    "name:tur_x_preferred":[
        "Modra"
    ],
    "name:ukr_x_preferred":[
        "\u041c\u043e\u0434\u0440\u0430"
    ],
    "name:urd_x_preferred":[
        "\u0645\u0648\u062f\u0631\u0627"
    ],
    "name:war_x_preferred":[
        "Modra"
    ],
    "name:zho_x_preferred":[
        "\u83ab\u5fb7\u62c9"
    ],
    "wof:name":"Modra",
    "wof:placetype":"locality"
},
  "geometry": {"coordinates":[16.47038,44.82598],"type":"Point"}
}