{
  "type": "Feature",
  "properties": {
    "gn:admin1_code":"01",
    "gn:asciiname":"Modra",
    "gn:country_code":"BA",
    "gn:dem":441,
    "gn:feature_class":"P",
    "gn:feature_code":"PPLL",
    "gn:name":"Modra",
    "gn:population":0,
    "gn:timezone":"Europe/Sarajevo",
    "iso:country":"BA",
    "wof:name":"Modra",
    "wof:placetype":"locality"
},
  "geometry": {"coordinates":[16.47038,44.82598],"type":"Point"}
}