{
  "type": "Feature",
  "properties": {
    "gn:admin1_code":"01",
    "gn:asciiname":"Zirovic",
    "gn:country_code":"BA",
    "gn:dem":749,
    "gn:feature_class":"P",
    "gn:feature_code":"PPL",
    "gn:name":"\u017dirovi\u0107",
    "gn:population":0,
    "gn:timezone":"Europe/Sarajevo",
    "iso:country":"BA",
    "name:und_x_variant":[
        "\u017dirovi\u0107"
    ],
    "wof:name":"Zirovic",
    "wof:placetype":"locality"
},
  "geometry": {"coordinates":[16.86793,43.8764],"type":"Point"}
}