{
  "type": "Feature",
  "properties": {
    "gn:admin1_code":"02",
    "gn:asciiname":"Gvozdeni",
    "gn:country_code":"BA",
    "gn:dem":182,
    "gn:feature_class":"P",
    "gn:feature_code":"PPL",
    "gn:name":"Gvozdeni",
    "gn:population":0,
    "gn:timezone":"Europe/Sarajevo",
    "iso:country":"BA",
    "wof:name":"Gvozdeni",
    "wof:placetype":"locality"
},
  "geometry": {"coordinates":[16.75995,44.91092],"type":"Point"}
}