{
  "type": "Feature",
  "properties": {
    "gn:admin1_code":"02",
    "gn:asciiname":"Gornja Uvala",
    "gn:country_code":"BA",
    "gn:dem":851,
    "gn:feature_class":"P",
    "gn:feature_code":"PPL",
    "gn:name":"Gornja Uvala",
    "gn:population":0,
    "gn:timezone":"Europe/Sarajevo",
    "iso:country":"BA",
    "name:und_x_variant":[
        "Uvala",
        "Uvalica",
        "Gornja Uvala"
    ],
    "wof:name":"Gornja Uvala",
    "wof:placetype":"locality"
},
  "geometry": {"coordinates":[16.64153,44.39073],"type":"Point"}
}