{
  "type": "Feature",
  "properties": {
    "gn:admin1_code":"01",
    "gn:asciiname":"Eminovo Selo",
    "gn:country_code":"BA",
    "gn:dem":906,
    "gn:feature_class":"P",
    "gn:feature_code":"PPLL",
    "gn:name":"Eminovo Selo",
    "gn:population":0,
    "gn:timezone":"Europe/Sarajevo",
    "iso:country":"BA",
    "name:bos_x_preferred":[
        "Eminovo Selo"
    ],
    "name:ceb_x_preferred":[
        "Eminovo Selo"
    ],
    "name:fra_x_preferred":[
        "Eminovo Selo"
    ],
    "name:hrv_x_preferred":[
        "Eminovo Selo"
    ],
    "name:srp_x_preferred":[
        "\u0415\u043c\u0438\u043d\u043e\u0432\u043e \u0421\u0435\u043b\u043e"
    ],
    "name:swe_x_preferred":[
        "Eminovo Selo"
    ],
    "wof:name":"Eminovo Selo",
    "wof:placetype":"locality"
},
  "geometry": {"coordinates":[17.20549,43.74636],"type":"Point"}
}