{
  "type": "Feature",
  "properties": {
    "gn:admin1_code":"02",
    "gn:asciiname":"Budograj",
    "gn:country_code":"BA",
    "gn:dem":543,
    "gn:feature_class":"P",
    "gn:feature_code":"PPL",
    "gn:name":"Budograj",
    "gn:population":0,
    "gn:timezone":"Europe/Sarajevo",
    "iso:country":"BA",
    "wof:name":"Budograj",
    "wof:placetype":"locality"
},
  "geometry": {"coordinates":[19.02093,44.26765],"type":"Point"}
}