{
  "type": "Feature",
  "properties": {
    "gn:admin1_code":"02",
    "gn:asciiname":"Bratici",
    "gn:country_code":"BA",
    "gn:dem":1028,
    "gn:feature_class":"P",
    "gn:feature_code":"PPL",
    "gn:name":"Brati\u0107i",
    "gn:population":0,
    "gn:timezone":"Europe/Sarajevo",
    "iso:country":"BA",
    "wof:name":"Bratici",
    "wof:placetype":"locality"
},
  "geometry": {"coordinates":[18.21917,43.12667],"type":"Point"}
}