{
  "type": "Feature",
  "properties": {
    "gn:admin1_code":"01",
    "gn:asciiname":"Mehurici",
    "gn:country_code":"BA",
    "gn:dem":643,
    "gn:feature_class":"P",
    "gn:feature_code":"PPL",
    "gn:name":"Mehuri\u0107i",
    "gn:population":0,
    "gn:timezone":"Europe/Sarajevo",
    "iso:country":"BA",
    "name:bos_x_preferred":[
        "Mehuri\u0107i"
    ],
    "name:deu_x_preferred":[
        "Mehuri\u0107i"
    ],
    "name:fra_x_preferred":[
        "Mehuri\u0107i"
    ],
    "name:und_x_variant":[
        "Mehuri\u0107i"
    ],
    "wof:name":"Mehurici",
    "wof:placetype":"locality"
},
  "geometry": {"coordinates":[17.93394,44.04744],"type":"Point"}
}