{
  "type": "Feature",
  "properties": {
    "gn:admin1_code":"01",
    "gn:asciiname":"Cvitanovici",
    "gn:country_code":"BA",
    "gn:dem":221,
    "gn:feature_class":"P",
    "gn:feature_code":"PPL",
    "gn:name":"Cvitanovi\u0107i",
    "gn:population":0,
    "gn:timezone":"Europe/Sarajevo",
    "iso:country":"BA",
    "wof:name":"Cvitanovici",
    "wof:placetype":"locality"
},
  "geometry": {"coordinates":[17.73133,43.20926],"type":"Point"}
}