{
  "type": "Feature",
  "properties": {
    "gn:country":"BA",
    "gn:fcode":"PPL",
    "gn:pop":3516,
    "iso:country":"BA",
    "name:ceb_x_preferred":[
        "Ko\u010derin"
    ],
    "name:eng_x_preferred":[
        "Ko\u010derin"
    ],
    "name:fra_x_preferred":[
        "Ko\u010derin"
    ],
    "name:hrv_x_preferred":[
        "Ko\u010derin"
    ],
    "name:nld_x_preferred":[
        "Ko\u010derin"
    ],
    "name:srp_x_preferred":[
        "\u041a\u043e\u0447\u0435\u0440\u0438\u043d"
    ],
    "name:swe_x_preferred":[
        "Ko\u010derin"
    ],
    "name:tur_x_preferred":[
        "Ko\u010derin"
    ],
    "qs:name":"Ko\u010derin",
    "qs:name_adm0":"Bosna i Hercegovina",
    "qs:name_adm1":"Federacija Bosne I Hercegovine",
    "qs:photos_9r":0,
    "qs:photos_sr":0,
    "qs:placetype":"Town",
    "qs:pop_sr":"4",
    "wd:wordcount":70,
    "wof:name":"Ko\u010derin",
    "wof:placetype":"locality",
    "wof:population":3516
},
  "geometry": {"coordinates":[17.48552,43.39005],"type":"Point"}
}