{
  "type": "Feature",
  "properties": {
    "gn:admin1_code":"02",
    "gn:asciiname":"Sarcevici",
    "gn:country_code":"BA",
    "gn:dem":224,
    "gn:feature_class":"P",
    "gn:feature_code":"PPL",
    "gn:name":"Sar\u010devi\u0107i",
    "gn:population":0,
    "gn:timezone":"Europe/Sarajevo",
    "iso:country":"BA",
    "wof:name":"Sarcevici",
    "wof:placetype":"locality"
},
  "geometry": {"coordinates":[18.2103,44.97418],"type":"Point"}
}