{
  "type": "Feature",
  "properties": {
    "gn:admin1_code":"02",
    "gn:asciiname":"Potkucnice",
    "gn:country_code":"BA",
    "gn:dem":272,
    "gn:feature_class":"P",
    "gn:feature_code":"PPL",
    "gn:name":"Potku\u0107nice",
    "gn:population":0,
    "gn:timezone":"Europe/Sarajevo",
    "iso:country":"BA",
    "wof:name":"Potkucnice",
    "wof:placetype":"locality"
},
  "geometry": {"coordinates":[17.12922,44.80607],"type":"Point"}
}