{
  "type": "Feature",
  "properties": {
    "gn:admin1_code":"02",
    "gn:asciiname":"Donji Jelovac",
    "gn:country_code":"BA",
    "gn:dem":173,
    "gn:feature_class":"P",
    "gn:feature_code":"PPLL",
    "gn:name":"Donji Jelovac",
    "gn:population":0,
    "gn:timezone":"Europe/Sarajevo",
    "iso:country":"BA",
    "name:bos_x_preferred":[
        "Donji Jelovac"
    ],
    "name:ceb_x_preferred":[
        "Donji Jelovac"
    ],
    "name:fra_x_preferred":[
        "Donji Jelovac"
    ],
    "name:hrv_x_preferred":[
        "Donji Jelovac"
    ],
    "name:slv_x_preferred":[
        "Donji Jelovac"
    ],
    "name:srp_x_preferred":[
        "\u0414\u043e\u045a\u0438 \u0408\u0435\u043b\u043e\u0432\u0430\u0446"
    ],
    "name:swe_x_preferred":[
        "Donji Jelovac"
    ],
    "wof:name":"Donji Jelovac",
    "wof:placetype":"locality"
},
  "geometry": {"coordinates":[16.69481,45.08966],"type":"Point"}
}