{
  "type": "Feature",
  "properties": {
    "gn:admin1_code":"01",
    "gn:asciiname":"Krivajevici",
    "gn:country_code":"BA",
    "gn:dem":1021,
    "gn:feature_class":"P",
    "gn:feature_code":"PPL",
    "gn:name":"Krivajevi\u0107i",
    "gn:population":0,
    "gn:timezone":"Europe/Sarajevo",
    "iso:country":"BA",
    "name:bos_x_preferred":[
        "Krivajevi\u0107i"
    ],
    "name:fra_x_preferred":[
        "Krivajevi\u0107i"
    ],
    "name:hrv_x_preferred":[
        "Krivajevi\u0107i"
    ],
    "name:pol_x_preferred":[
        "Krivajevi\u0107i"
    ],
    "name:srp_x_preferred":[
        "\u041a\u0440\u0438\u0432\u0430\u0458\u0435\u0432\u0438\u045b\u0438"
    ],
    "wof:name":"Krivajevici",
    "wof:placetype":"locality"
},
  "geometry": {"coordinates":[18.52281,44.08537000000001],"type":"Point"}
}