{
  "type": "Feature",
  "properties": {
    "gn:admin1_code":"00",
    "gn:asciiname":"Kamensko",
    "gn:country_code":"BA",
    "gn:dem":750,
    "gn:feature_class":"P",
    "gn:feature_code":"PPL",
    "gn:name":"Kamensko",
    "gn:population":0,
    "gn:timezone":"Europe/Sarajevo",
    "iso:country":"BA",
    "name:bul_x_preferred":[
        "\u041a\u0430\u043c\u0435\u043d\u0441\u043a\u043e"
    ],
    "name:fas_x_preferred":[
        "\u06a9\u0627\u0645\u0646\u0633\u06a9\u0648"
    ],
    "name:kaz_x_preferred":[
        "\u041a\u0430\u043c\u0435\u043d\u0441\u043a\u043e"
    ],
    "name:rus_x_preferred":[
        "\u041a\u0430\u043c\u0435\u043d\u0441\u043a\u043e"
    ],
    "name:ukr_x_preferred":[
        "\u041a\u0430\u043c\u0435\u043d\u0441\u044c\u043a\u043e"
    ],
    "wof:name":"Kamensko",
    "wof:placetype":"locality"
},
  "geometry": {"coordinates":[18.45702,44.25658],"type":"Point"}
}