{
  "type": "Feature",
  "properties": {
    "gn:admin1_code":"01",
    "gn:asciiname":"Sridice",
    "gn:country_code":"BA",
    "gn:dem":645,
    "gn:feature_class":"P",
    "gn:feature_code":"PPL",
    "gn:name":"Sridice",
    "gn:population":0,
    "gn:timezone":"Europe/Sarajevo",
    "iso:country":"BA",
    "wof:name":"Sridice",
    "wof:placetype":"locality"
},
  "geometry": {"coordinates":[18.17907,44.13083],"type":"Point"}
}