{
  "type": "Feature",
  "properties": {
    "gn:admin1_code":"01",
    "gn:asciiname":"Glogosnica",
    "gn:country_code":"BA",
    "gn:dem":184,
    "gn:feature_class":"P",
    "gn:feature_code":"PPL",
    "gn:name":"Glogo\u0161nica",
    "gn:population":0,
    "gn:timezone":"Europe/Sarajevo",
    "iso:country":"BA",
    "wof:name":"Glogosnica",
    "wof:placetype":"locality"
},
  "geometry": {"coordinates":[17.7639,43.61998],"type":"Point"}
}