{
  "type": "Feature",
  "properties": {
    "gn:admin1_code":"02",
    "gn:asciiname":"Jovac",
    "gn:country_code":"BA",
    "gn:dem":120,
    "gn:feature_class":"P",
    "gn:feature_code":"PPL",
    "gn:name":"Jovac",
    "gn:population":0,
    "gn:timezone":"Europe/Sarajevo",
    "iso:country":"BA",
    "name:fas_x_preferred":[
        "\u06cc\u0648\u0648\u0627\u062a\u0633"
    ],
    "name:fra_x_preferred":[
        "Jovac"
    ],
    "name:msa_x_preferred":[
        "Jovac"
    ],
    "name:por_x_preferred":[
        "Jovac"
    ],
    "name:slv_x_preferred":[
        "Jovac"
    ],
    "name:srp_x_preferred":[
        "\u0408\u043e\u0432\u0430\u0446"
    ],
    "wof:name":"Jovac",
    "wof:placetype":"locality"
},
  "geometry": {"coordinates":[17.10197,45.08951],"type":"Point"}
}