{
  "type": "Feature",
  "properties": {
    "gn:admin1_code":"02",
    "gn:asciiname":"Jovac",
    "gn:country_code":"BA",
    "gn:dem":120,
    "gn:feature_class":"P",
    "gn:feature_code":"PPL",
    "gn:name":"Jovac",
    "gn:population":0,
    "gn:timezone":"Europe/Sarajevo",
    "iso:country":"BA",
    "wof:name":"Jovac",
    "wof:placetype":"locality"
},
  "geometry": {"coordinates":[17.10197,45.08951],"type":"Point"}
}