{
  "type": "Feature",
  "properties": {
    "gn:admin1_code":"02",
    "gn:asciiname":"Jazovac",
    "gn:country_code":"BA",
    "gn:dem":126,
    "gn:feature_class":"P",
    "gn:feature_code":"PPLL",
    "gn:name":"Jazovac",
    "gn:population":0,
    "gn:timezone":"Europe/Sarajevo",
    "iso:country":"BA",
    "name:bos_x_preferred":[
        "Jazovac"
    ],
    "name:ceb_x_preferred":[
        "Jazovac"
    ],
    "name:fra_x_preferred":[
        "Jazovac"
    ],
    "name:hrv_x_preferred":[
        "Jazovac"
    ],
    "name:slv_x_preferred":[
        "Jazovac"
    ],
    "name:srp_x_preferred":[
        "\u0408\u0430\u0437\u043e\u0432\u0430\u0446"
    ],
    "name:swe_x_preferred":[
        "Jazovac"
    ],
    "wof:name":"Jazovac",
    "wof:placetype":"locality"
},
  "geometry": {"coordinates":[17.20876,45.01855],"type":"Point"}
}