{
  "type": "Feature",
  "properties": {
    "gn:admin1_code":"02",
    "gn:asciiname":"Konjovici",
    "gn:country_code":"BA",
    "gn:dem":531,
    "gn:feature_class":"P",
    "gn:feature_code":"PPL",
    "gn:name":"Konjovi\u0107i",
    "gn:population":0,
    "gn:timezone":"Europe/Sarajevo",
    "iso:country":"BA",
    "wof:name":"Konjovici",
    "wof:placetype":"locality"
},
  "geometry": {"coordinates":[17.19919,44.48463],"type":"Point"}
}