{
  "type": "Feature",
  "properties": {
    "gn:admin1_code":"02",
    "gn:asciiname":"Gniona",
    "gn:cc2":"BA",
    "gn:country_code":"BA",
    "gn:dem":519,
    "gn:feature_class":"P",
    "gn:feature_code":"PPL",
    "gn:name":"Gniona",
    "gn:population":0,
    "gn:timezone":"Europe/Sarajevo",
    "iso:country":"BA",
    "name:und_x_variant":[
        "Gnjone",
        "Gniona"
    ],
    "wof:name":"Gniona",
    "wof:placetype":"locality"
},
  "geometry": {"coordinates":[19.25444,44.13361],"type":"Point"}
}