{
  "type": "Feature",
  "properties": {
    "gn:admin1_code":"01",
    "gn:asciiname":"Grnecaski Prolog",
    "gn:country_code":"BA",
    "gn:dem":710,
    "gn:feature_class":"P",
    "gn:feature_code":"PPL",
    "gn:name":"Grne\u010da\u0161ki Prolog",
    "gn:population":0,
    "gn:timezone":"Europe/Sarajevo",
    "iso:country":"BA",
    "wof:name":"Grnecaski Prolog",
    "wof:placetype":"locality"
},
  "geometry": {"coordinates":[16.83442,43.79481],"type":"Point"}
}