{
  "type": "Feature",
  "properties": {
    "gn:admin1_code":"02",
    "gn:asciiname":"Goranina",
    "gn:country_code":"BA",
    "gn:dem":591,
    "gn:feature_class":"P",
    "gn:feature_code":"PPL",
    "gn:name":"Goranina",
    "gn:population":0,
    "gn:timezone":"Europe/Sarajevo",
    "iso:country":"BA",
    "wof:name":"Goranina",
    "wof:placetype":"locality"
},
  "geometry": {"coordinates":[18.39889,43.83833],"type":"Point"}
}