{
  "type": "Feature",
  "properties": {
    "gn:admin1_code":"02",
    "gn:asciiname":"Voljice",
    "gn:country_code":"BA",
    "gn:dem":870,
    "gn:feature_class":"P",
    "gn:feature_code":"PPLL",
    "gn:name":"Voljice",
    "gn:population":0,
    "gn:timezone":"Europe/Sarajevo",
    "iso:country":"BA",
    "name:bos_x_preferred":[
        "Voljice"
    ],
    "name:ceb_x_preferred":[
        "Voljice"
    ],
    "name:fra_x_preferred":[
        "Voljice"
    ],
    "name:hrv_x_preferred":[
        "Voljice"
    ],
    "name:srp_x_preferred":[
        "\u0412\u043e\u0459\u0438\u0446\u0435"
    ],
    "name:swe_x_preferred":[
        "Voljice"
    ],
    "wof:name":"Voljice",
    "wof:placetype":"locality"
},
  "geometry": {"coordinates":[18.47646,43.01409],"type":"Point"}
}