{
  "type": "Feature",
  "properties": {
    "gn:admin1_code":"02",
    "gn:asciiname":"Skaric",
    "gn:country_code":"BA",
    "gn:dem":86,
    "gn:feature_class":"P",
    "gn:feature_code":"PPL",
    "gn:name":"\u0160kari\u0107",
    "gn:population":0,
    "gn:timezone":"Europe/Sarajevo",
    "iso:country":"BA",
    "name:und_x_variant":[
        "\u0160kari\u0107"
    ],
    "wof:name":"Skaric",
    "wof:placetype":"locality"
},
  "geometry": {"coordinates":[18.4539,45.03262],"type":"Point"}
}