{
  "type": "Feature",
  "properties": {
    "gn:admin1_code":"02",
    "gn:asciiname":"Gorica",
    "gn:country_code":"BA",
    "gn:dem":300,
    "gn:feature_class":"P",
    "gn:feature_code":"PPL",
    "gn:name":"Gorica",
    "gn:population":0,
    "gn:timezone":"Europe/Sarajevo",
    "iso:country":"BA",
    "wof:name":"Gorica",
    "wof:placetype":"locality"
},
  "geometry": {"coordinates":[18.37117000000001,42.71967],"type":"Point"}
}