{
  "type": "Feature",
  "properties": {
    "gn:admin1_code":"02",
    "gn:asciiname":"Gorica",
    "gn:country_code":"BA",
    "gn:dem":300,
    "gn:feature_class":"P",
    "gn:feature_code":"PPL",
    "gn:name":"Gorica",
    "gn:population":0,
    "gn:timezone":"Europe/Sarajevo",
    "iso:country":"BA",
    "name:bos_x_preferred":[
        "Gorica"
    ],
    "name:ceb_x_preferred":[
        "Gorica"
    ],
    "name:fra_x_preferred":[
        "Gorica"
    ],
    "name:hrv_x_preferred":[
        "Gorica"
    ],
    "name:hun_x_preferred":[
        "Gorica"
    ],
    "name:ita_x_preferred":[
        "Gorica"
    ],
    "name:nld_x_preferred":[
        "Gorica"
    ],
    "name:sco_x_preferred":[
        "Gorica"
    ],
    "name:slv_x_preferred":[
        "Gorica"
    ],
    "name:spa_x_preferred":[
        "Gorica"
    ],
    "name:srp_x_preferred":[
        "\u0413\u043e\u0440\u0438\u0446\u0430"
    ],
    "name:swe_x_preferred":[
        "Gorica"
    ],
    "wof:name":"Gorica",
    "wof:placetype":"locality"
},
  "geometry": {"coordinates":[18.37117000000001,42.71967],"type":"Point"}
}