{
  "type": "Feature",
  "properties": {
    "gn:admin1_code":"01",
    "gn:asciiname":"Gladno Brdo",
    "gn:country_code":"BA",
    "gn:dem":378,
    "gn:feature_class":"P",
    "gn:feature_code":"PPL",
    "gn:name":"Gladno Brdo",
    "gn:population":0,
    "gn:timezone":"Europe/Sarajevo",
    "iso:country":"BA",
    "wof:name":"Gladno Brdo",
    "wof:placetype":"locality"
},
  "geometry": {"coordinates":[16.06889,44.95611],"type":"Point"}
}