{
  "type": "Feature",
  "properties": {
    "gn:admin1_code":"01",
    "gn:asciiname":"Mala Dabrnja",
    "gn:country_code":"BA",
    "gn:dem":251,
    "gn:feature_class":"P",
    "gn:feature_code":"PPL",
    "gn:name":"Mala Dabrnja",
    "gn:population":0,
    "gn:timezone":"Europe/Sarajevo",
    "iso:country":"BA",
    "wof:name":"Mala Dabrnja",
    "wof:placetype":"locality"
},
  "geometry": {"coordinates":[16.21556,45.02778],"type":"Point"}
}