{
  "type": "Feature",
  "properties": {
    "gn:admin1_code":"02",
    "gn:admin2_code":"3294874.0",
    "gn:asciiname":"Gajici",
    "gn:country_code":"BA",
    "gn:dem":236,
    "gn:feature_class":"P",
    "gn:feature_code":"PPL",
    "gn:name":"Gaji\u0107i",
    "gn:population":0,
    "gn:timezone":"Europe/Sarajevo",
    "iso:country":"BA",
    "wof:name":"Gajici",
    "wof:placetype":"locality"
},
  "geometry": {"coordinates":[19.03091,44.65119],"type":"Point"}
}