{
  "type": "Feature",
  "properties": {
    "gn:admin1_code":"02",
    "gn:asciiname":"Veliko Blasko",
    "gn:country_code":"BA",
    "gn:dem":182,
    "gn:feature_class":"P",
    "gn:feature_code":"PPLL",
    "gn:name":"Veliko Bla\u0161ko",
    "gn:population":0,
    "gn:timezone":"Europe/Sarajevo",
    "iso:country":"BA",
    "name:und_x_variant":[
        "Bla\u0161ko Veliko",
        "Veliko Bla\u0161ko"
    ],
    "wof:name":"Veliko Blasko",
    "wof:placetype":"locality"
},
  "geometry": {"coordinates":[17.2924,44.86277000000001],"type":"Point"}
}