{
  "type": "Feature",
  "properties": {
    "gn:admin1_code":"02",
    "gn:asciiname":"Tonkovac",
    "gn:country_code":"BA",
    "gn:dem":806,
    "gn:feature_class":"P",
    "gn:feature_code":"PPL",
    "gn:name":"Tonkovac",
    "gn:population":0,
    "gn:timezone":"Europe/Sarajevo",
    "iso:country":"BA",
    "wof:name":"Tonkovac",
    "wof:placetype":"locality"
},
  "geometry": {"coordinates":[17.12167,44.34194],"type":"Point"}
}