{
  "type": "Feature",
  "properties": {
    "gn:admin1_code":"02",
    "gn:asciiname":"Kitovnice",
    "gn:country_code":"BA",
    "gn:dem":303,
    "gn:feature_class":"P",
    "gn:feature_code":"PPLL",
    "gn:name":"Kitovnice",
    "gn:population":0,
    "gn:timezone":"Europe/Sarajevo",
    "iso:country":"BA",
    "name:und_x_variant":[
        "Kitovnica",
        "Kitovnice"
    ],
    "wof:name":"Kitovnice",
    "wof:placetype":"locality"
},
  "geometry": {"coordinates":[19.04528,44.45081],"type":"Point"}
}