{
  "type": "Feature",
  "properties": {
    "gn:admin1_code":"02",
    "gn:asciiname":"Vrbaska",
    "gn:country_code":"BA",
    "gn:dem":105,
    "gn:feature_class":"P",
    "gn:feature_code":"PPLL",
    "gn:name":"Vrba\u0161ka",
    "gn:population":0,
    "gn:timezone":"Europe/Sarajevo",
    "iso:country":"BA",
    "name:und_x_variant":[
        "Vrba\u0161ka"
    ],
    "wof:name":"Vrbaska",
    "wof:placetype":"locality"
},
  "geometry": {"coordinates":[17.15679,45.10165],"type":"Point"}
}