{
  "type": "Feature",
  "properties": {
    "gn:admin1_code":"02",
    "gn:asciiname":"Bijelo Brdo",
    "gn:country_code":"BA",
    "gn:dem":142,
    "gn:feature_class":"P",
    "gn:feature_code":"PPLL",
    "gn:name":"Bijelo Brdo",
    "gn:population":0,
    "gn:timezone":"Europe/Sarajevo",
    "iso:country":"BA",
    "name:und_x_variant":[
        "Bjelo Brdo",
        "Bijelo Brdo"
    ],
    "wof:name":"Bijelo Brdo",
    "wof:placetype":"locality"
},
  "geometry": {"coordinates":[17.90679,45.02369],"type":"Point"}
}