{
  "type": "Feature",
  "properties": {
    "gn:admin1_code":"02",
    "gn:asciiname":"Bijelo Brdo",
    "gn:country_code":"BA",
    "gn:dem":142,
    "gn:feature_class":"P",
    "gn:feature_code":"PPLL",
    "gn:name":"Bijelo Brdo",
    "gn:population":0,
    "gn:timezone":"Europe/Sarajevo",
    "iso:country":"BA",
    "name:bos_x_preferred":[
        "Bijelo Brdo"
    ],
    "name:ceb_x_preferred":[
        "Bijelo Brdo"
    ],
    "name:fra_x_preferred":[
        "Bijelo Brdo"
    ],
    "name:hrv_x_preferred":[
        "Bijelo Brdo"
    ],
    "name:slv_x_preferred":[
        "Bijelo Brdo"
    ],
    "name:srp_x_preferred":[
        "\u0411\u0438\u0458\u0435\u043b\u043e \u0411\u0440\u0434\u043e"
    ],
    "name:swe_x_preferred":[
        "Bijelo Brdo"
    ],
    "name:und_x_variant":[
        "Bjelo Brdo"
    ],
    "wof:name":"Bijelo Brdo",
    "wof:placetype":"locality"
},
  "geometry": {"coordinates":[17.90679,45.02369],"type":"Point"}
}