{
  "type": "Feature",
  "properties": {
    "gn:admin1_code":"02",
    "gn:asciiname":"Dukarici",
    "gn:country_code":"BA",
    "gn:dem":555,
    "gn:feature_class":"P",
    "gn:feature_code":"PPL",
    "gn:name":"\u00d0ukari\u0107i",
    "gn:population":0,
    "gn:timezone":"Europe/Sarajevo",
    "iso:country":"BA",
    "wof:name":"Dukarici",
    "wof:placetype":"locality"
},
  "geometry": {"coordinates":[17.67124,44.52763],"type":"Point"}
}