{
  "type": "Feature",
  "properties": {
    "gn:admin1_code":"02",
    "gn:asciiname":"Stolici",
    "gn:country_code":"BA",
    "gn:dem":164,
    "gn:feature_class":"P",
    "gn:feature_code":"PPL",
    "gn:name":"Stoli\u0107i",
    "gn:population":0,
    "gn:timezone":"Europe/Sarajevo",
    "iso:country":"BA",
    "wof:name":"Stolici",
    "wof:placetype":"locality"
},
  "geometry": {"coordinates":[16.77778,45.14778],"type":"Point"}
}