{
  "type": "Feature",
  "properties": {
    "gn:admin1_code":"02",
    "gn:asciiname":"Potok",
    "gn:country_code":"BA",
    "gn:dem":967,
    "gn:feature_class":"P",
    "gn:feature_code":"PPL",
    "gn:name":"Potok",
    "gn:population":0,
    "gn:timezone":"Europe/Sarajevo",
    "iso:country":"BA",
    "wof:name":"Potok",
    "wof:placetype":"locality"
},
  "geometry": {"coordinates":[17.6137,44.39925],"type":"Point"}
}