{
  "type": "Feature",
  "properties": {
    "gn:admin1_code":"02",
    "gn:asciiname":"Donji Zalukovik",
    "gn:country_code":"BA",
    "gn:dem":340,
    "gn:feature_class":"P",
    "gn:feature_code":"PPLL",
    "gn:name":"Donji Zalukovik",
    "gn:population":0,
    "gn:timezone":"Europe/Sarajevo",
    "iso:country":"BA",
    "wof:name":"Donji Zalukovik",
    "wof:placetype":"locality"
},
  "geometry": {"coordinates":[19.00452,44.20569],"type":"Point"}
}