{
  "type": "Feature",
  "properties": {
    "gn:admin1_code":"02",
    "gn:asciiname":"Capnjak",
    "gn:country_code":"BA",
    "gn:dem":177,
    "gn:feature_class":"P",
    "gn:feature_code":"PPL",
    "gn:name":"\u010capnjak",
    "gn:population":0,
    "gn:timezone":"Europe/Sarajevo",
    "iso:country":"BA",
    "wof:name":"Capnjak",
    "wof:placetype":"locality"
},
  "geometry": {"coordinates":[16.9013,45.08842],"type":"Point"}
}