{
  "type": "Feature",
  "properties": {
    "gn:admin1_code":"02",
    "gn:asciiname":"Stojcici",
    "gn:country_code":"BA",
    "gn:dem":799,
    "gn:feature_class":"P",
    "gn:feature_code":"PPL",
    "gn:name":"Stoj\u010di\u0107i",
    "gn:population":0,
    "gn:timezone":"Europe/Sarajevo",
    "iso:country":"BA",
    "wof:name":"Stojcici",
    "wof:placetype":"locality"
},
  "geometry": {"coordinates":[17.01439,44.31272],"type":"Point"}
}