{
  "type": "Feature",
  "properties": {
    "gn:admin1_code":"02",
    "gn:asciiname":"Miletine",
    "gn:country_code":"BA",
    "gn:dem":889,
    "gn:feature_class":"P",
    "gn:feature_code":"PPL",
    "gn:name":"Miletine",
    "gn:population":0,
    "gn:timezone":"Europe/Sarajevo",
    "iso:country":"BA",
    "wof:name":"Miletine",
    "wof:placetype":"locality"
},
  "geometry": {"coordinates":[18.70272000000001,44.0102],"type":"Point"}
}