{
  "type": "Feature",
  "properties": {
    "gn:admin1_code":"02",
    "gn:asciiname":"Miletine",
    "gn:country_code":"BA",
    "gn:dem":889,
    "gn:feature_class":"P",
    "gn:feature_code":"PPL",
    "gn:name":"Miletine",
    "gn:population":0,
    "gn:timezone":"Europe/Sarajevo",
    "iso:country":"BA",
    "name:bos_x_preferred":[
        "Miletine"
    ],
    "name:fra_x_preferred":[
        "Miletine"
    ],
    "name:srp_x_preferred":[
        "\u041c\u0438\u043b\u0435\u0442\u0438\u043d\u0435"
    ],
    "wof:name":"Miletine",
    "wof:placetype":"locality"
},
  "geometry": {"coordinates":[18.70272000000001,44.0102],"type":"Point"}
}