{
  "type": "Feature",
  "properties": {
    "gn:admin1_code":"02",
    "gn:asciiname":"Maljnjak",
    "gn:country_code":"BA",
    "gn:dem":263,
    "gn:feature_class":"P",
    "gn:feature_code":"PPL",
    "gn:name":"Maljnjak",
    "gn:population":0,
    "gn:timezone":"Europe/Sarajevo",
    "iso:country":"BA",
    "wof:name":"Maljnjak",
    "wof:placetype":"locality"
},
  "geometry": {"coordinates":[16.44778,45.05028],"type":"Point"}
}