{
  "type": "Feature",
  "properties": {
    "gn:admin1_code":"01",
    "gn:asciiname":"Savicici",
    "gn:country_code":"BA",
    "gn:dem":617,
    "gn:feature_class":"P",
    "gn:feature_code":"PPL",
    "gn:name":"Savi\u010di\u0107i",
    "gn:population":0,
    "gn:timezone":"Europe/Sarajevo",
    "iso:country":"BA",
    "wof:name":"Savicici",
    "wof:placetype":"locality"
},
  "geometry": {"coordinates":[16.17284,44.4376],"type":"Point"}
}