{
  "type": "Feature",
  "properties": {
    "gn:admin1_code":"02",
    "gn:asciiname":"Sredici",
    "gn:country_code":"BA",
    "gn:dem":246,
    "gn:feature_class":"P",
    "gn:feature_code":"PPL",
    "gn:name":"Sredi\u0107i",
    "gn:population":0,
    "gn:timezone":"Europe/Sarajevo",
    "iso:country":"BA",
    "wof:name":"Sredici",
    "wof:placetype":"locality"
},
  "geometry": {"coordinates":[16.51009,44.94524000000001],"type":"Point"}
}