{
  "type": "Feature",
  "properties": {
    "gn:admin1_code":"01",
    "gn:asciiname":"Pope",
    "gn:country_code":"BA",
    "gn:dem":418,
    "gn:feature_class":"P",
    "gn:feature_code":"PPL",
    "gn:name":"Pope",
    "gn:population":0,
    "gn:timezone":"Europe/Sarajevo",
    "iso:country":"BA",
    "name:und_x_variant":[
        "Popi",
        "Pope"
    ],
    "wof:name":"Pope",
    "wof:placetype":"locality"
},
  "geometry": {"coordinates":[18.11504,44.1365],"type":"Point"}
}