{
  "type": "Feature",
  "properties": {
    "gn:admin1_code":"01",
    "gn:asciiname":"Otoka",
    "gn:country_code":"BA",
    "gn:dem":625,
    "gn:feature_class":"P",
    "gn:feature_code":"PPL",
    "gn:name":"Otoka",
    "gn:population":0,
    "gn:timezone":"Europe/Sarajevo",
    "iso:country":"BA",
    "name:bos_x_preferred":[
        "Otoka"
    ],
    "name:ceb_x_preferred":[
        "Otoka"
    ],
    "name:fra_x_preferred":[
        "Otoka"
    ],
    "name:hrv_x_preferred":[
        "Otoka"
    ],
    "name:rus_x_preferred":[
        "\u041e\u0442\u043e\u043a\u0430"
    ],
    "name:slv_x_preferred":[
        "Otoka"
    ],
    "name:srp_x_preferred":[
        "\u041e\u0442\u043e\u043a\u0430"
    ],
    "name:swe_x_preferred":[
        "Otoka"
    ],
    "wof:name":"Otoka",
    "wof:placetype":"locality"
},
  "geometry": {"coordinates":[18.06012,44.19841],"type":"Point"}
}