{
  "type": "Feature",
  "properties": {
    "gn:admin1_code":"02",
    "gn:asciiname":"Konjevici",
    "gn:country_code":"BA",
    "gn:dem":151,
    "gn:feature_class":"P",
    "gn:feature_code":"PPL",
    "gn:name":"Konjevi\u0107i",
    "gn:population":0,
    "gn:timezone":"Europe/Sarajevo",
    "iso:country":"BA",
    "wof:name":"Konjevici",
    "wof:placetype":"locality"
},
  "geometry": {"coordinates":[16.88184,44.88148],"type":"Point"}
}