{
  "type": "Feature",
  "properties": {
    "gn:admin1_code":"02",
    "gn:asciiname":"Bausovac",
    "gn:country_code":"BA",
    "gn:dem":140,
    "gn:feature_class":"P",
    "gn:feature_code":"PPL",
    "gn:name":"Bausovac",
    "gn:population":0,
    "gn:timezone":"Europe/Sarajevo",
    "iso:country":"BA",
    "wof:name":"Bausovac",
    "wof:placetype":"locality"
},
  "geometry": {"coordinates":[16.44,45.11639],"type":"Point"}
}