{
  "type": "Feature",
  "properties": {
    "gn:admin1_code":"01",
    "gn:asciiname":"Gutani",
    "gn:country_code":"BA",
    "gn:dem":411,
    "gn:feature_class":"P",
    "gn:feature_code":"PPL",
    "gn:name":"Gutani",
    "gn:population":0,
    "gn:timezone":"Europe/Sarajevo",
    "iso:country":"BA",
    "wof:name":"Gutani",
    "wof:placetype":"locality"
},
  "geometry": {"coordinates":[18.67832000000001,44.60917],"type":"Point"}
}