{
  "type": "Feature",
  "properties": {
    "gn:country":"BA",
    "gn:fcode":"PPL",
    "gn:pop":967,
    "iso:country":"BA",
    "name:bar_x_preferred":[
        "Brodac Gornji"
    ],
    "name:bos_x_preferred":[
        "Brodac Gornji"
    ],
    "name:bre_x_preferred":[
        "Brodac Gornji"
    ],
    "name:cat_x_preferred":[
        "Brodac Gornji"
    ],
    "name:cos_x_preferred":[
        "Brodac Gornji"
    ],
    "name:dan_x_preferred":[
        "Brodac Gornji"
    ],
    "name:deu_x_preferred":[
        "Brodac Gornji"
    ],
    "name:eng_x_preferred":[
        "Brodac Gornji"
    ],
    "name:fra_x_preferred":[
        "Brodac Gornji"
    ],
    "name:hrv_x_preferred":[
        "Brodac Gornji"
    ],
    "name:ind_x_preferred":[
        "Brodac Gornji"
    ],
    "name:ita_x_preferred":[
        "Brodac Gornji"
    ],
    "name:nds_x_preferred":[
        "Brodac Gornji"
    ],
    "name:nld_x_preferred":[
        "Brodac Gornji"
    ],
    "name:pol_x_preferred":[
        "Brodac Gornji"
    ],
    "name:por_x_preferred":[
        "Brodac Gornji"
    ],
    "name:ron_x_preferred":[
        "Brodac Gornji"
    ],
    "name:rus_x_preferred":[
        "\u0411\u0440\u043e\u0434\u0430\u0446-\u0413\u043e\u0440\u043d\u0438"
    ],
    "name:slv_x_preferred":[
        "Brodac Gornji"
    ],
    "name:spa_x_preferred":[
        "Brodac Gornji"
    ],
    "name:srp_x_preferred":[
        "\u0411\u0440\u043e\u0434\u0430\u0446 \u0413\u043e\u0440\u045a\u0438"
    ],
    "name:swe_x_preferred":[
        "Brodac Gornji"
    ],
    "name:tah_x_preferred":[
        "Brodac Gornji"
    ],
    "qs:name":"Brodac-Gornji",
    "qs:photos_9r":0,
    "qs:photos_sr":0,
    "qs:pop_sr":"2",
    "wd:wordcount":27,
    "wof:name":"Brodac-Gornji",
    "wof:placetype":"locality",
    "wof:population":967
},
  "geometry": {"coordinates":[19.26363,44.86373],"type":"Point"}
}