{
  "type": "Feature",
  "properties": {
    "gn:admin1_code":"01",
    "gn:asciiname":"Paraun",
    "gn:country_code":"BA",
    "gn:dem":629,
    "gn:feature_class":"P",
    "gn:feature_code":"PPL",
    "gn:name":"Paraun",
    "gn:population":0,
    "gn:timezone":"Europe/Sarajevo",
    "iso:country":"BA",
    "name:bos_x_preferred":[
        "Paraun"
    ],
    "name:fra_x_preferred":[
        "Paraun"
    ],
    "wof:name":"Paraun",
    "wof:placetype":"locality"
},
  "geometry": {"coordinates":[18.89712,43.62914],"type":"Point"}
}