{
  "type": "Feature",
  "properties": {
    "gn:admin1_code":"02",
    "gn:asciiname":"Bijakovac",
    "gn:country_code":"BA",
    "gn:dem":208,
    "gn:feature_class":"P",
    "gn:feature_code":"PPLL",
    "gn:name":"Bijakovac",
    "gn:population":0,
    "gn:timezone":"Europe/Sarajevo",
    "iso:country":"BA",
    "name:bos_x_preferred":[
        "Bijakovac"
    ],
    "name:ceb_x_preferred":[
        "Bijakovac"
    ],
    "name:fra_x_preferred":[
        "Bijakovac"
    ],
    "name:hrv_x_preferred":[
        "Bijakovac"
    ],
    "name:slv_x_preferred":[
        "Bijakovac"
    ],
    "name:srp_x_preferred":[
        "\u0411\u0438\u0458\u0430\u043a\u043e\u0432\u0430\u0446"
    ],
    "name:swe_x_preferred":[
        "Bijakovac"
    ],
    "wof:name":"Bijakovac",
    "wof:placetype":"locality"
},
  "geometry": {"coordinates":[16.95658,45.13249],"type":"Point"}
}