{
  "type": "Feature",
  "properties": {
    "gn:admin1_code":"01",
    "gn:asciiname":"Brijesnica Donja",
    "gn:country_code":"BA",
    "gn:dem":361,
    "gn:feature_class":"P",
    "gn:feature_code":"PPLL",
    "gn:name":"Brijesnica Donja",
    "gn:population":0,
    "gn:timezone":"Europe/Sarajevo",
    "iso:country":"BA",
    "name:bos_x_preferred":[
        "Brijesnica Donja"
    ],
    "name:fra_x_preferred":[
        "Brijesnica Donja"
    ],
    "name:hrv_x_preferred":[
        "Brijesnica Donja"
    ],
    "name:und_x_variant":[
        "Donja Brijesnica",
        "Brijesnica Donja"
    ],
    "wof:name":"Brijesnica Donja",
    "wof:placetype":"locality"
},
  "geometry": {"coordinates":[18.37901,44.51052],"type":"Point"}
}