{
  "type": "Feature",
  "properties": {
    "gn:admin1_code":"02",
    "gn:asciiname":"Osoja",
    "gn:country_code":"BA",
    "gn:dem":956,
    "gn:feature_class":"P",
    "gn:feature_code":"PPL",
    "gn:name":"Osoja",
    "gn:population":0,
    "gn:timezone":"Europe/Sarajevo",
    "iso:country":"BA",
    "name:bos_x_preferred":[
        "Osija"
    ],
    "name:fra_x_preferred":[
        "Osija"
    ],
    "name:srp_x_preferred":[
        "\u041e\u0441\u0438\u0458\u0430"
    ],
    "name:und_x_variant":[
        "Osija",
        "Osoja"
    ],
    "wof:name":"Osoja",
    "wof:placetype":"locality"
},
  "geometry": {"coordinates":[18.57401,43.58119],"type":"Point"}
}