{
  "type": "Feature",
  "properties": {
    "gn:admin1_code":"01",
    "gn:asciiname":"Grab",
    "gn:country_code":"BA",
    "gn:dem":74,
    "gn:feature_class":"P",
    "gn:feature_code":"PPLL",
    "gn:name":"Grab",
    "gn:population":0,
    "gn:timezone":"Europe/Sarajevo",
    "iso:country":"BA",
    "wof:name":"Grab",
    "wof:placetype":"locality"
},
  "geometry": {"coordinates":[17.45111,43.21694],"type":"Point"}
}