{
  "type": "Feature",
  "properties": {
    "gn:admin1_code":"02",
    "gn:asciiname":"Donje Krusevo",
    "gn:country_code":"BA",
    "gn:dem":530,
    "gn:feature_class":"P",
    "gn:feature_code":"PPL",
    "gn:name":"Donje Kru\u0161evo",
    "gn:population":0,
    "gn:timezone":"Europe/Sarajevo",
    "iso:country":"BA",
    "wof:name":"Donje Krusevo",
    "wof:placetype":"locality"
},
  "geometry": {"coordinates":[18.84583,43.33694000000001],"type":"Point"}
}