{
  "type": "Feature",
  "properties": {
    "gn:admin1_code":"02",
    "gn:asciiname":"Vulici",
    "gn:country_code":"BA",
    "gn:dem":351,
    "gn:feature_class":"P",
    "gn:feature_code":"PPL",
    "gn:name":"Vuli\u0107i",
    "gn:population":0,
    "gn:timezone":"Europe/Sarajevo",
    "iso:country":"BA",
    "wof:name":"Vulici",
    "wof:placetype":"locality"
},
  "geometry": {"coordinates":[16.84506,44.80157],"type":"Point"}
}