{
  "type": "Feature",
  "properties": {
    "gn:admin1_code":"02",
    "gn:asciiname":"Babin Do",
    "gn:country_code":"BA",
    "gn:dem":759,
    "gn:feature_class":"P",
    "gn:feature_code":"PPL",
    "gn:name":"Babin Do",
    "gn:population":0,
    "gn:timezone":"Europe/Sarajevo",
    "iso:country":"BA",
    "wof:name":"Babin Do",
    "wof:placetype":"locality"
},
  "geometry": {"coordinates":[18.0282,43.1236],"type":"Point"}
}