{
  "type": "Feature",
  "properties": {
    "gn:admin1_code":"01",
    "gn:asciiname":"Tolovina",
    "gn:country_code":"BA",
    "gn:dem":303,
    "gn:feature_class":"P",
    "gn:feature_code":"PPL",
    "gn:name":"Tolovina",
    "gn:population":0,
    "gn:timezone":"Europe/Sarajevo",
    "iso:country":"BA",
    "wof:name":"Tolovina",
    "wof:placetype":"locality"
},
  "geometry": {"coordinates":[17.84041000000001,43.20943],"type":"Point"}
}