{
  "type": "Feature",
  "properties": {
    "gn:admin1_code":"01",
    "gn:asciiname":"Panduri",
    "gn:country_code":"BA",
    "gn:dem":672,
    "gn:feature_class":"P",
    "gn:feature_code":"PPL",
    "gn:name":"Panduri",
    "gn:population":0,
    "gn:timezone":"Europe/Sarajevo",
    "iso:country":"BA",
    "name:deu_x_preferred":[
        "Panduri"
    ],
    "name:epo_x_preferred":[
        "Pandurio"
    ],
    "name:fra_x_preferred":[
        "Pandouri"
    ],
    "name:ita_x_preferred":[
        "Panduri"
    ],
    "name:kat_x_preferred":[
        "\u10e4\u10d0\u10dc\u10d3\u10e3\u10e0\u10d8"
    ],
    "name:rus_x_preferred":[
        "\u041f\u0430\u043d\u0434\u0443\u0440\u0438"
    ],
    "name:tur_x_preferred":[
        "Panduri"
    ],
    "name:ukr_x_preferred":[
        "\u041f\u0430\u043d\u0434\u0443\u0440\u0456"
    ],
    "wof:name":"Panduri",
    "wof:placetype":"locality"
},
  "geometry": {"coordinates":[17.86111,43.80167],"type":"Point"}
}