{
  "type": "Feature",
  "properties": {
    "gn:admin1_code":"02",
    "gn:asciiname":"Popovici",
    "gn:country_code":"BA",
    "gn:dem":346,
    "gn:feature_class":"P",
    "gn:feature_code":"PPL",
    "gn:name":"Popovi\u0107i",
    "gn:population":0,
    "gn:timezone":"Europe/Sarajevo",
    "iso:country":"BA",
    "name:heb_x_preferred":[
        "\u05e4\u05d5\u05e4\u05d5\u05d1\u05d9\u05e5'"
    ],
    "wof:name":"Popovici",
    "wof:placetype":"locality"
},
  "geometry": {"coordinates":[17.0697,44.81685],"type":"Point"}
}