{
  "type": "Feature",
  "properties": {
    "gn:admin1_code":"01",
    "gn:asciiname":"Grahovik",
    "gn:country_code":"BA",
    "gn:dem":520,
    "gn:feature_class":"P",
    "gn:feature_code":"PPLL",
    "gn:name":"Grahovik",
    "gn:population":0,
    "gn:timezone":"Europe/Sarajevo",
    "iso:country":"BA",
    "wof:name":"Grahovik",
    "wof:placetype":"locality"
},
  "geometry": {"coordinates":[17.67817999999999,44.21155],"type":"Point"}
}