{
  "type": "Feature",
  "properties": {
    "gn:admin1_code":"02",
    "gn:asciiname":"Ljubasi",
    "gn:country_code":"BA",
    "gn:dem":177,
    "gn:feature_class":"P",
    "gn:feature_code":"PPL",
    "gn:name":"Ljubasi",
    "gn:population":0,
    "gn:timezone":"Europe/Sarajevo",
    "iso:country":"BA",
    "wof:name":"Ljubasi",
    "wof:placetype":"locality"
},
  "geometry": {"coordinates":[17.88152999999999,44.94775],"type":"Point"}
}