{
  "type": "Feature",
  "properties": {
    "gn:admin1_code":"01",
    "gn:asciiname":"Tomina",
    "gn:country_code":"BA",
    "gn:dem":184,
    "gn:feature_class":"P",
    "gn:feature_code":"PPL",
    "gn:name":"Tomina",
    "gn:population":0,
    "gn:timezone":"Europe/Sarajevo",
    "iso:country":"BA",
    "name:ceb_x_preferred":[
        "Tomina"
    ],
    "name:deu_x_preferred":[
        "Tomina"
    ],
    "wof:name":"Tomina",
    "wof:placetype":"locality"
},
  "geometry": {"coordinates":[16.71749,44.70771],"type":"Point"}
}