{
  "type": "Feature",
  "properties": {
    "gn:admin1_code":"02",
    "gn:asciiname":"Baltici",
    "gn:country_code":"BA",
    "gn:dem":146,
    "gn:feature_class":"P",
    "gn:feature_code":"PPL",
    "gn:name":"Balti\u0107i",
    "gn:population":0,
    "gn:timezone":"Europe/Sarajevo",
    "iso:country":"BA",
    "wof:name":"Baltici",
    "wof:placetype":"locality"
},
  "geometry": {"coordinates":[16.81919,44.91497],"type":"Point"}
}