{
  "type": "Feature",
  "properties": {
    "gn:admin1_code":"02",
    "gn:asciiname":"Crni Vrh",
    "gn:country_code":"BA",
    "gn:dem":855,
    "gn:feature_class":"P",
    "gn:feature_code":"PPL",
    "gn:name":"Crni Vrh",
    "gn:population":0,
    "gn:timezone":"Europe/Sarajevo",
    "iso:country":"BA",
    "name:bos_x_preferred":[
        "Crni vrh"
    ],
    "name:ceb_x_preferred":[
        "Crni Vrh"
    ],
    "name:deu_x_preferred":[
        "Crni Vrh"
    ],
    "name:fra_x_preferred":[
        "Crni Vrh"
    ],
    "name:hrv_x_preferred":[
        "Crni Vrh"
    ],
    "name:slv_x_preferred":[
        "Crni Vrh"
    ],
    "name:srp_x_preferred":[
        "\u0426\u0440\u043d\u0438 \u0412\u0440\u0445"
    ],
    "name:swe_x_preferred":[
        "Crni Vrh"
    ],
    "wof:name":"Crni Vrh",
    "wof:placetype":"locality"
},
  "geometry": {"coordinates":[18.78354,43.4845],"type":"Point"}
}