{
  "type": "Feature",
  "properties": {
    "gn:admin1_code":"02",
    "gn:asciiname":"Blizanci",
    "gn:country_code":"BA",
    "gn:dem":1160,
    "gn:feature_class":"P",
    "gn:feature_code":"PPL",
    "gn:name":"Blizanci",
    "gn:population":0,
    "gn:timezone":"Europe/Sarajevo",
    "iso:country":"BA",
    "wof:name":"Blizanci",
    "wof:placetype":"locality"
},
  "geometry": {"coordinates":[18.44624,43.81643],"type":"Point"}
}