{
  "type": "Feature",
  "properties": {
    "gn:admin1_code":"02",
    "gn:asciiname":"Pobude",
    "gn:country_code":"BA",
    "gn:dem":396,
    "gn:feature_class":"P",
    "gn:feature_code":"PPLL",
    "gn:name":"Pobu\u0111e",
    "gn:population":0,
    "gn:timezone":"Europe/Sarajevo",
    "iso:country":"BA",
    "name:bos_x_preferred":[
        "Pobu\u0111e"
    ],
    "name:bul_x_preferred":[
        "\u041f\u043e\u0431\u0443\u0434\u0436\u0435"
    ],
    "name:ceb_x_preferred":[
        "Pobu\u0111e"
    ],
    "name:fra_x_preferred":[
        "Pobu\u0111e"
    ],
    "name:hrv_x_preferred":[
        "Pobu\u0111e"
    ],
    "name:rus_x_preferred":[
        "\u041f\u043e\u0431\u0443\u0434\u0436\u0435"
    ],
    "name:srp_x_preferred":[
        "\u041f\u043e\u0431\u0443\u0452\u0435"
    ],
    "name:swe_x_preferred":[
        "Pobu\u0111e"
    ],
    "name:und_x_variant":[
        "Pobu\u0111e"
    ],
    "wof:name":"Pobude",
    "wof:placetype":"locality"
},
  "geometry": {"coordinates":[19.13093,44.22314],"type":"Point"}
}