{
  "type": "Feature",
  "properties": {
    "gn:admin1_code":"02",
    "gn:asciiname":"Lucari",
    "gn:country_code":"BA",
    "gn:dem":542,
    "gn:feature_class":"P",
    "gn:feature_code":"PPL",
    "gn:name":"Lu\u010dari",
    "gn:population":0,
    "gn:timezone":"Europe/Sarajevo",
    "iso:country":"BA",
    "wof:name":"Lucari",
    "wof:placetype":"locality"
},
  "geometry": {"coordinates":[16.86416,44.39896],"type":"Point"}
}