{
  "type": "Feature",
  "properties": {
    "gn:admin1_code":"02",
    "gn:asciiname":"Osredak",
    "gn:country_code":"BA",
    "gn:dem":1162,
    "gn:feature_class":"P",
    "gn:feature_code":"PPL",
    "gn:name":"Osredak",
    "gn:population":0,
    "gn:timezone":"Europe/Sarajevo",
    "iso:country":"BA",
    "wof:name":"Osredak",
    "wof:placetype":"locality"
},
  "geometry": {"coordinates":[17.50279,44.40175],"type":"Point"}
}