{
  "type": "Feature",
  "properties": {
    "gn:admin1_code":"01",
    "gn:asciiname":"Sabici",
    "gn:country_code":"BA",
    "gn:dem":324,
    "gn:feature_class":"P",
    "gn:feature_code":"PPL",
    "gn:name":"\u0160abi\u0107i",
    "gn:population":0,
    "gn:timezone":"Europe/Sarajevo",
    "iso:country":"BA",
    "wof:name":"Sabici",
    "wof:placetype":"locality"
},
  "geometry": {"coordinates":[15.85634,44.96107],"type":"Point"}
}