{
  "type": "Feature",
  "properties": {
    "gn:admin1_code":"BRC",
    "gn:asciiname":"Kojici",
    "gn:country_code":"BA",
    "gn:dem":122,
    "gn:feature_class":"P",
    "gn:feature_code":"PPL",
    "gn:name":"Koji\u0107i",
    "gn:population":0,
    "gn:timezone":"Europe/Sarajevo",
    "iso:country":"BA",
    "wof:name":"Kojici",
    "wof:placetype":"locality"
},
  "geometry": {"coordinates":[18.83935,44.83543],"type":"Point"}
}