{
  "type": "Feature",
  "properties": {
    "gn:admin1_code":"01",
    "gn:asciiname":"Smoluca Donja",
    "gn:country_code":"BA",
    "gn:dem":324,
    "gn:feature_class":"P",
    "gn:feature_code":"PPLL",
    "gn:name":"Smolu\u0107a Donja",
    "gn:population":0,
    "gn:timezone":"Europe/Sarajevo",
    "iso:country":"BA",
    "name:und_x_variant":[
        "Smolu\u0107a",
        "Smolu\u0107a Donja"
    ],
    "wof:name":"Smoluca Donja",
    "wof:placetype":"locality"
},
  "geometry": {"coordinates":[18.51167,44.59808],"type":"Point"}
}