{
  "type": "Feature",
  "properties": {
    "gn:admin1_code":"01",
    "gn:asciiname":"Smoluca Donja",
    "gn:country_code":"BA",
    "gn:dem":324,
    "gn:feature_class":"P",
    "gn:feature_code":"PPLL",
    "gn:name":"Smolu\u0107a Donja",
    "gn:population":0,
    "gn:timezone":"Europe/Sarajevo",
    "iso:country":"BA",
    "name:bos_x_preferred":[
        "Smolu\u0107a Donja"
    ],
    "name:fra_x_preferred":[
        "Smolu\u0107a Donja"
    ],
    "name:hrv_x_preferred":[
        "Smolu\u0107a Donja"
    ],
    "name:srp_x_preferred":[
        "\u0421\u043c\u043e\u043b\u0443\u045b\u0430 \u0414\u043e\u045a\u0430"
    ],
    "name:und_x_variant":[
        "Smolu\u0107a",
        "Smolu\u0107a Donja"
    ],
    "wof:name":"Smoluca Donja",
    "wof:placetype":"locality"
},
  "geometry": {"coordinates":[18.51167,44.59808],"type":"Point"}
}