{
  "type": "Feature",
  "properties": {
    "gn:admin1_code":"02",
    "gn:asciiname":"Bojkici",
    "gn:country_code":"BA",
    "gn:dem":334,
    "gn:feature_class":"P",
    "gn:feature_code":"PPL",
    "gn:name":"Bojki\u0107i",
    "gn:population":0,
    "gn:timezone":"Europe/Sarajevo",
    "iso:country":"BA",
    "wof:name":"Bojkici",
    "wof:placetype":"locality"
},
  "geometry": {"coordinates":[18.77358,44.63517],"type":"Point"}
}