{
  "type": "Feature",
  "properties": {
    "gn:admin1_code":"01",
    "gn:asciiname":"Globarica",
    "gn:country_code":"BA",
    "gn:dem":351,
    "gn:feature_class":"P",
    "gn:feature_code":"PPLL",
    "gn:name":"Globarica",
    "gn:population":0,
    "gn:timezone":"Europe/Sarajevo",
    "iso:country":"BA",
    "name:bos_x_preferred":[
        "Globarica"
    ],
    "name:ceb_x_preferred":[
        "Globarica"
    ],
    "name:fra_x_preferred":[
        "Globarica"
    ],
    "name:hrv_x_preferred":[
        "Globarica"
    ],
    "name:swe_x_preferred":[
        "Globarica"
    ],
    "wof:name":"Globarica",
    "wof:placetype":"locality"
},
  "geometry": {"coordinates":[18.1351,44.48711],"type":"Point"}
}