{
  "type": "Feature",
  "properties": {
    "gn:admin1_code":"01",
    "gn:asciiname":"Kapici",
    "gn:country_code":"BA",
    "gn:dem":217,
    "gn:feature_class":"P",
    "gn:feature_code":"PPL",
    "gn:name":"Kapi\u0107i",
    "gn:population":0,
    "gn:timezone":"Europe/Sarajevo",
    "iso:country":"BA",
    "wof:name":"Kapici",
    "wof:placetype":"locality"
},
  "geometry": {"coordinates":[15.90338,45.17939000000001],"type":"Point"}
}