{
  "type": "Feature",
  "properties": {
    "gn:admin1_code":"01",
    "gn:asciiname":"Han-Bila",
    "gn:country_code":"BA",
    "gn:dem":513,
    "gn:feature_class":"P",
    "gn:feature_code":"PPL",
    "gn:name":"Han-Bila",
    "gn:population":0,
    "gn:timezone":"Europe/Sarajevo",
    "iso:country":"BA",
    "wof:name":"Han-Bila",
    "wof:placetype":"locality"
},
  "geometry": {"coordinates":[17.75928,44.23716],"type":"Point"}
}