{
  "type": "Feature",
  "properties": {
    "gn:admin1_code":"01",
    "gn:asciiname":"Hodzic",
    "gn:country_code":"BA",
    "gn:dem":1076,
    "gn:feature_class":"P",
    "gn:feature_code":"PPL",
    "gn:name":"Hod\u017ei\u0107",
    "gn:population":0,
    "gn:timezone":"Europe/Sarajevo",
    "iso:country":"BA",
    "wof:name":"Hodzic",
    "wof:placetype":"locality"
},
  "geometry": {"coordinates":[17.49174,43.78492],"type":"Point"}
}