{
  "type": "Feature",
  "properties": {
    "gn:admin1_code":"01",
    "gn:asciiname":"Cevani",
    "gn:country_code":"BA",
    "gn:dem":167,
    "gn:feature_class":"P",
    "gn:feature_code":"PPL",
    "gn:name":"\u0106evani",
    "gn:population":0,
    "gn:timezone":"Europe/Sarajevo",
    "iso:country":"BA",
    "wof:name":"Cevani",
    "wof:placetype":"locality"
},
  "geometry": {"coordinates":[15.83147,45.15029000000001],"type":"Point"}
}