{
  "type": "Feature",
  "properties": {
    "gn:admin1_code":"02",
    "gn:asciiname":"Grabik",
    "gn:country_code":"BA",
    "gn:dem":448,
    "gn:feature_class":"P",
    "gn:feature_code":"PPL",
    "gn:name":"Grabik",
    "gn:population":0,
    "gn:timezone":"Europe/Sarajevo",
    "iso:country":"BA",
    "wof:name":"Grabik",
    "wof:placetype":"locality"
},
  "geometry": {"coordinates":[17.50374,44.58577],"type":"Point"}
}