{
  "type": "Feature",
  "properties": {
    "gn:admin1_code":"02",
    "gn:asciiname":"Grabik",
    "gn:country_code":"BA",
    "gn:dem":448,
    "gn:feature_class":"P",
    "gn:feature_code":"PPL",
    "gn:name":"Grabik",
    "gn:population":0,
    "gn:timezone":"Europe/Sarajevo",
    "iso:country":"BA",
    "name:bos_x_preferred":[
        "Grabik"
    ],
    "name:ceb_x_preferred":[
        "Grabik"
    ],
    "name:fra_x_preferred":[
        "Grabik"
    ],
    "name:hrv_x_preferred":[
        "Grabik"
    ],
    "name:pol_x_preferred":[
        "Grabik"
    ],
    "name:slv_x_preferred":[
        "Grabik"
    ],
    "name:swe_x_preferred":[
        "Grabik"
    ],
    "name:ukr_x_preferred":[
        "\u0490\u0440\u0430\u0431\u0438\u043a"
    ],
    "wof:name":"Grabik",
    "wof:placetype":"locality"
},
  "geometry": {"coordinates":[17.50374,44.58577],"type":"Point"}
}