{
  "type": "Feature",
  "properties": {
    "gn:admin1_code":"01",
    "gn:asciiname":"Donji Cazanj",
    "gn:country_code":"BA",
    "gn:dem":696,
    "gn:feature_class":"P",
    "gn:feature_code":"PPL",
    "gn:name":"Donji \u010ca\u017eanj",
    "gn:population":0,
    "gn:timezone":"Europe/Sarajevo",
    "iso:country":"BA",
    "name:ara_x_preferred":[
        "\u062f\u0648\u0646\u064a\u064a \u0634\u0627\u0632\u0627\u0646\u064a"
    ],
    "name:bos_x_preferred":[
        "Donji \u010ca\u017eanj"
    ],
    "name:fra_x_preferred":[
        "Donji \u010ca\u017eanj"
    ],
    "name:hrv_x_preferred":[
        "Donji \u010ca\u017eanj"
    ],
    "name:srp_x_preferred":[
        "\u0414\u043e\u045a\u0438 \u0427\u0430\u0436\u0430\u045a"
    ],
    "name:und_x_variant":[
        "Donji \u010ca\u017eanj"
    ],
    "wof:name":"Donji Cazanj",
    "wof:placetype":"locality"
},
  "geometry": {"coordinates":[17.83805,43.80524000000001],"type":"Point"}
}