{
  "type": "Feature",
  "properties": {
    "gn:admin1_code":"01",
    "gn:asciiname":"Donji Cazanj",
    "gn:country_code":"BA",
    "gn:dem":696,
    "gn:feature_class":"P",
    "gn:feature_code":"PPL",
    "gn:name":"Donji \u010ca\u017eanj",
    "gn:population":0,
    "gn:timezone":"Europe/Sarajevo",
    "iso:country":"BA",
    "name:und_x_variant":[
        "Donji \u010ca\u017eanj"
    ],
    "wof:name":"Donji Cazanj",
    "wof:placetype":"locality"
},
  "geometry": {"coordinates":[17.83805,43.80524000000001],"type":"Point"}
}