{
  "type": "Feature",
  "properties": {
    "gn:admin1_code":"01",
    "gn:asciiname":"Donji Orasac",
    "gn:country_code":"BA",
    "gn:dem":605,
    "gn:feature_class":"P",
    "gn:feature_code":"PPL",
    "gn:name":"Donji Ora\u0161ac",
    "gn:population":0,
    "gn:timezone":"Europe/Sarajevo",
    "iso:country":"BA",
    "wof:name":"Donji Orasac",
    "wof:placetype":"locality"
},
  "geometry": {"coordinates":[17.41597,44.41621],"type":"Point"}
}