{
  "type": "Feature",
  "properties": {
    "gn:admin1_code":"01",
    "gn:asciiname":"Ivankovici",
    "gn:country_code":"BA",
    "gn:dem":94,
    "gn:feature_class":"P",
    "gn:feature_code":"PPL",
    "gn:name":"Ivankovi\u0107i",
    "gn:population":0,
    "gn:timezone":"Europe/Sarajevo",
    "iso:country":"BA",
    "wof:name":"Ivankovici",
    "wof:placetype":"locality"
},
  "geometry": {"coordinates":[18.34865,45.02159],"type":"Point"}
}