{
  "type": "Feature",
  "properties": {
    "gn:admin1_code":"02",
    "gn:asciiname":"Panincici",
    "gn:country_code":"BA",
    "gn:dem":911,
    "gn:feature_class":"P",
    "gn:feature_code":"PPL",
    "gn:name":"Panin\u010di\u0107i",
    "gn:population":0,
    "gn:timezone":"Europe/Sarajevo",
    "iso:country":"BA",
    "wof:name":"Panincici",
    "wof:placetype":"locality"
},
  "geometry": {"coordinates":[16.99087,44.36535],"type":"Point"}
}