{
  "type": "Feature",
  "properties": {
    "gn:admin1_code":"02",
    "gn:asciiname":"Vucenovici",
    "gn:country_code":"BA",
    "gn:dem":197,
    "gn:feature_class":"P",
    "gn:feature_code":"PPL",
    "gn:name":"Vu\u010denovi\u0107i",
    "gn:population":0,
    "gn:timezone":"Europe/Sarajevo",
    "iso:country":"BA",
    "wof:name":"Vucenovici",
    "wof:placetype":"locality"
},
  "geometry": {"coordinates":[16.73513,44.90598],"type":"Point"}
}