{
  "type": "Feature",
  "properties": {
    "gn:admin1_code":"01",
    "gn:asciiname":"Cape",
    "gn:country_code":"BA",
    "gn:dem":413,
    "gn:feature_class":"P",
    "gn:feature_code":"PPL",
    "gn:name":"Cape",
    "gn:population":0,
    "gn:timezone":"Europe/Sarajevo",
    "iso:country":"BA",
    "name:ara_x_preferred":[
        "\u0642\u0628\u0627\u0621"
    ],
    "name:cat_x_preferred":[
        "Capa"
    ],
    "name:dan_x_preferred":[
        "Kappe"
    ],
    "name:deu_x_preferred":[
        "Capa"
    ],
    "name:fas_x_preferred":[
        "\u0634\u0646\u0644"
    ],
    "name:fin_x_preferred":[
        "Keeppi"
    ],
    "name:ita_x_preferred":[
        "Cappa"
    ],
    "name:jpn_x_preferred":[
        "\u30b1\u30fc\u30d7"
    ],
    "name:scn_x_preferred":[
        "Cappa"
    ],
    "name:sot_x_preferred":[
        "Kapa"
    ],
    "name:spa_x_preferred":[
        "Capa"
    ],
    "name:swe_x_preferred":[
        "Cape"
    ],
    "wof:name":"Cape",
    "wof:placetype":"locality"
},
  "geometry": {"coordinates":[18.77777,43.57004000000001],"type":"Point"}
}