{
  "type": "Feature",
  "properties": {
    "gn:admin1_code":"01",
    "gn:asciiname":"Obrenovac",
    "gn:country_code":"BA",
    "gn:dem":567,
    "gn:feature_class":"P",
    "gn:feature_code":"PPL",
    "gn:name":"Obrenovac",
    "gn:population":0,
    "gn:timezone":"Europe/Sarajevo",
    "iso:country":"BA",
    "name:aze_x_preferred":[
        "Obrenova\u00e7"
    ],
    "name:bos_x_preferred":[
        "Obrenovac"
    ],
    "name:bul_x_preferred":[
        "\u041e\u0431\u0440\u0435\u043d\u043e\u0432\u0430\u0446"
    ],
    "name:ceb_x_preferred":[
        "Obrenovac"
    ],
    "name:ces_x_preferred":[
        "Obrenovac"
    ],
    "name:ckb_x_preferred":[
        "\u0626\u06c6\u0628\u0631\u06ce\u0646\u06c6\u06a4\u0627\u062a\u0633"
    ],
    "name:deu_x_preferred":[
        "Obrenovac"
    ],
    "name:ell_x_preferred":[
        "\u039f\u03bc\u03c0\u03c1\u03ad\u03bd\u03bf\u03b2\u03b1\u03c4\u03c2"
    ],
    "name:fas_x_preferred":[
        "\u0627\u0648\u0628\u0631\u0646\u0648\u0648\u0627\u062a\u0633"
    ],
    "name:fra_x_preferred":[
        "Obrenovac"
    ],
    "name:hrv_x_preferred":[
        "Obrenovac"
    ],
    "name:ind_x_preferred":[
        "Obrenovac"
    ],
    "name:ita_x_preferred":[
        "Obrenovac"
    ],
    "name:kor_x_preferred":[
        "\uc624\ube0c\ub808\ub178\ubc14\uce20"
    ],
    "name:lit_x_preferred":[
        "Obrenovacas"
    ],
    "name:msa_x_preferred":[
        "Obrenovac"
    ],
    "name:nld_x_preferred":[
        "Obrenovac"
    ],
    "name:nor_x_preferred":[
        "Obrenovac"
    ],
    "name:pol_x_preferred":[
        "Obrenovac"
    ],
    "name:por_x_preferred":[
        "Obrenovac"
    ],
    "name:slv_x_preferred":[
        "Obrenovac"
    ],
    "name:spa_x_preferred":[
        "Obrenovac"
    ],
    "name:srp_x_preferred":[
        "\u041e\u0431\u0440\u0435\u043d\u043e\u0432\u0430\u0446"
    ],
    "name:swe_x_preferred":[
        "Obrenovac"
    ],
    "name:tur_x_preferred":[
        "Obrenovac"
    ],
    "name:urd_x_preferred":[
        "\u0627\u0648\u0628\u0631\u06cc\u0646\u0648\u0648\u0627\u0633"
    ],
    "name:vie_x_preferred":[
        "Obrenovac"
    ],
    "name:zho_x_preferred":[
        "\u5967\u5e03\u96f7\u8afe\u74e6\u8328"
    ],
    "wof:name":"Obrenovac",
    "wof:placetype":"locality"
},
  "geometry": {"coordinates":[17.84395,43.75133],"type":"Point"}
}