{
  "type": "Feature",
  "properties": {
    "gn:admin1_code":"01",
    "gn:asciiname":"Starcevici",
    "gn:country_code":"BA",
    "gn:dem":238,
    "gn:feature_class":"P",
    "gn:feature_code":"PPL",
    "gn:name":"Star\u010devi\u0107i",
    "gn:population":0,
    "gn:timezone":"Europe/Sarajevo",
    "iso:country":"BA",
    "wof:name":"Starcevici",
    "wof:placetype":"locality"
},
  "geometry": {"coordinates":[16.66278,44.71614],"type":"Point"}
}