{
  "type": "Feature",
  "properties": {
    "gn:admin1_code":"01",
    "gn:asciiname":"Naselje Hajinici",
    "gn:country_code":"BA",
    "gn:dem":448,
    "gn:feature_class":"P",
    "gn:feature_code":"PPL",
    "gn:name":"Naselje Hajini\u0107i",
    "gn:population":0,
    "gn:timezone":"Europe/Sarajevo",
    "iso:country":"BA",
    "wof:name":"Naselje Hajinici",
    "wof:placetype":"locality"
},
  "geometry": {"coordinates":[18.17699,44.10233],"type":"Point"}
}