{
  "type": "Feature",
  "properties": {
    "gn:admin1_code":"02",
    "gn:asciiname":"Ranikuce",
    "gn:country_code":"BA",
    "gn:dem":862,
    "gn:feature_class":"P",
    "gn:feature_code":"PPL",
    "gn:name":"Raniku\u0107e",
    "gn:population":0,
    "gn:timezone":"Europe/Sarajevo",
    "iso:country":"BA",
    "wof:name":"Ranikuce",
    "wof:placetype":"locality"
},
  "geometry": {"coordinates":[18.20971,43.17142],"type":"Point"}
}