{
  "type": "Feature",
  "properties": {
    "gn:admin1_code":"01",
    "gn:asciiname":"Kevilji",
    "gn:country_code":"BA",
    "gn:dem":595,
    "gn:feature_class":"P",
    "gn:feature_code":"PPL",
    "gn:name":"Kevilji",
    "gn:population":0,
    "gn:timezone":"Europe/Sarajevo",
    "iso:country":"BA",
    "wof:name":"Kevilji",
    "wof:placetype":"locality"
},
  "geometry": {"coordinates":[18.17957,44.1127],"type":"Point"}
}