{
  "type": "Feature",
  "properties": {
    "gn:admin1_code":"01",
    "gn:asciiname":"Subasici",
    "gn:country_code":"BA",
    "gn:dem":624,
    "gn:feature_class":"P",
    "gn:feature_code":"PPL",
    "gn:name":"Suba\u0161i\u0107i",
    "gn:population":0,
    "gn:timezone":"Europe/Sarajevo",
    "iso:country":"BA",
    "wof:name":"Subasici",
    "wof:placetype":"locality"
},
  "geometry": {"coordinates":[18.1296,44.18343],"type":"Point"}
}