{
  "type": "Feature",
  "properties": {
    "gn:admin1_code":"01",
    "gn:asciiname":"Busevo",
    "gn:country_code":"BA",
    "gn:dem":721,
    "gn:feature_class":"P",
    "gn:feature_code":"PPL",
    "gn:name":"Bu\u0161evo",
    "gn:population":0,
    "gn:timezone":"Europe/Sarajevo",
    "iso:country":"BA",
    "name:bos_x_preferred":[
        "Bu\u0161evo"
    ],
    "name:ceb_x_preferred":[
        "Bu\u0161evo"
    ],
    "name:fra_x_preferred":[
        "Bu\u0161evo"
    ],
    "name:swe_x_preferred":[
        "Bu\u0161evo"
    ],
    "wof:name":"Busevo",
    "wof:placetype":"locality"
},
  "geometry": {"coordinates":[18.68163,44.23324],"type":"Point"}
}