{
  "type": "Feature",
  "properties": {
    "gn:admin1_code":"01",
    "gn:asciiname":"Zabrdo",
    "gn:country_code":"BA",
    "gn:dem":520,
    "gn:feature_class":"P",
    "gn:feature_code":"PPL",
    "gn:name":"Zabrdo",
    "gn:population":0,
    "gn:timezone":"Europe/Sarajevo",
    "iso:country":"BA",
    "name:bos_x_preferred":[
        "Zabrdo"
    ],
    "name:hrv_x_preferred":[
        "Zabrdo"
    ],
    "name:nld_x_preferred":[
        "Zabrdo"
    ],
    "name:pol_x_preferred":[
        "Zabrdo"
    ],
    "name:ron_x_preferred":[
        "Zabrdo"
    ],
    "name:slv_x_preferred":[
        "Zabrdo"
    ],
    "name:ukr_x_preferred":[
        "\u0417\u0430\u0431\u0440\u0434\u043e"
    ],
    "name:urd_x_preferred":[
        "\u0632\u0628\u0631\u062f\u0648"
    ],
    "wof:name":"Zabrdo",
    "wof:placetype":"locality"
},
  "geometry": {"coordinates":[17.26347,44.39663],"type":"Point"}
}