{
  "type": "Feature",
  "properties": {
    "gn:admin1_code":"01",
    "gn:asciiname":"Zabrdo",
    "gn:country_code":"BA",
    "gn:dem":520,
    "gn:feature_class":"P",
    "gn:feature_code":"PPL",
    "gn:name":"Zabrdo",
    "gn:population":0,
    "gn:timezone":"Europe/Sarajevo",
    "iso:country":"BA",
    "wof:name":"Zabrdo",
    "wof:placetype":"locality"
},
  "geometry": {"coordinates":[17.26347,44.39663],"type":"Point"}
}