{
  "type": "Feature",
  "properties": {
    "gn:admin1_code":"01",
    "gn:asciiname":"Klupe",
    "gn:country_code":"BA",
    "gn:dem":224,
    "gn:feature_class":"P",
    "gn:feature_code":"PPLL",
    "gn:name":"Klupe",
    "gn:population":0,
    "gn:timezone":"Europe/Sarajevo",
    "iso:country":"BA",
    "wof:name":"Klupe",
    "wof:placetype":"locality"
},
  "geometry": {"coordinates":[15.8624,45.19395],"type":"Point"}
}