{
  "type": "Feature",
  "properties": {
    "gn:admin1_code":"01",
    "gn:asciiname":"Pauc",
    "gn:country_code":"BA",
    "gn:dem":856,
    "gn:feature_class":"P",
    "gn:feature_code":"PPL",
    "gn:name":"Pau\u010d",
    "gn:population":0,
    "gn:timezone":"Europe/Sarajevo",
    "iso:country":"BA",
    "name:und_x_variant":[
        "Podpau\u010d",
        "Pau\u010d"
    ],
    "wof:name":"Pauc",
    "wof:placetype":"locality"
},
  "geometry": {"coordinates":[18.6249,44.2469],"type":"Point"}
}