{
  "type": "Feature",
  "properties": {
    "gn:admin1_code":"02",
    "gn:asciiname":"Muse",
    "gn:country_code":"BA",
    "gn:dem":142,
    "gn:feature_class":"P",
    "gn:feature_code":"PPLL",
    "gn:name":"Muse",
    "gn:population":0,
    "gn:timezone":"Europe/Sarajevo",
    "iso:country":"BA",
    "wof:name":"Muse",
    "wof:placetype":"locality"
},
  "geometry": {"coordinates":[17.77769,44.84447],"type":"Point"}
}