{
  "type": "Feature",
  "properties": {
    "gn:admin1_code":"01",
    "gn:asciiname":"Struzic",
    "gn:country_code":"BA",
    "gn:dem":1397,
    "gn:feature_class":"P",
    "gn:feature_code":"PPL",
    "gn:name":"Stru\u017eic",
    "gn:population":0,
    "gn:timezone":"Europe/Sarajevo",
    "iso:country":"BA",
    "wof:name":"Struzic",
    "wof:placetype":"locality"
},
  "geometry": {"coordinates":[17.56583,44.33556],"type":"Point"}
}