{
  "type": "Feature",
  "properties": {
    "gn:admin1_code":"02",
    "gn:asciiname":"Botici",
    "gn:country_code":"BA",
    "gn:dem":476,
    "gn:feature_class":"P",
    "gn:feature_code":"PPL",
    "gn:name":"Boti\u0107i",
    "gn:population":0,
    "gn:timezone":"Europe/Sarajevo",
    "iso:country":"BA",
    "wof:name":"Botici",
    "wof:placetype":"locality"
},
  "geometry": {"coordinates":[17.19778,44.61868],"type":"Point"}
}