{
  "type": "Feature",
  "properties": {
    "gn:admin1_code":"01",
    "gn:asciiname":"Pusine",
    "gn:country_code":"BA",
    "gn:dem":744,
    "gn:feature_class":"P",
    "gn:feature_code":"PPL",
    "gn:name":"Pu\u0161ine",
    "gn:population":0,
    "gn:timezone":"Europe/Sarajevo",
    "iso:country":"BA",
    "wof:name":"Pusine",
    "wof:placetype":"locality"
},
  "geometry": {"coordinates":[18.78837,43.63104000000001],"type":"Point"}
}