{
  "type": "Feature",
  "properties": {
    "gn:admin1_code":"02",
    "gn:asciiname":"Rapti Zupci",
    "gn:country_code":"BA",
    "gn:dem":519,
    "gn:feature_class":"P",
    "gn:feature_code":"PPL",
    "gn:name":"Rapti Zupci",
    "gn:population":0,
    "gn:timezone":"Europe/Sarajevo",
    "iso:country":"BA",
    "name:und_x_variant":[
        "Rapti",
        "Rapti Zubci",
        "Rapti Zupci"
    ],
    "wof:name":"Rapti Zupci",
    "wof:placetype":"locality"
},
  "geometry": {"coordinates":[18.36435,42.6865],"type":"Point"}
}