{
  "type": "Feature",
  "properties": {
    "gn:admin1_code":"02",
    "gn:asciiname":"Sedar",
    "gn:country_code":"BA",
    "gn:dem":1109,
    "gn:feature_class":"P",
    "gn:feature_code":"PPL",
    "gn:name":"Sedar",
    "gn:population":0,
    "gn:timezone":"Europe/Sarajevo",
    "iso:country":"BA",
    "wof:name":"Sedar",
    "wof:placetype":"locality"
},
  "geometry": {"coordinates":[18.63556,43.93083],"type":"Point"}
}