{
  "type": "Feature",
  "properties": {
    "gn:admin1_code":"01",
    "gn:asciiname":"Drenovo Tijesno",
    "gn:country_code":"BA",
    "gn:dem":455,
    "gn:feature_class":"P",
    "gn:feature_code":"PPL",
    "gn:name":"Drenovo Tijesno",
    "gn:population":0,
    "gn:timezone":"Europe/Sarajevo",
    "iso:country":"BA",
    "name:und_x_variant":[
        "Drenovo Tjesno",
        "Drenovo Tijesno"
    ],
    "wof:name":"Drenovo Tijesno",
    "wof:placetype":"locality"
},
  "geometry": {"coordinates":[15.98852,44.83381],"type":"Point"}
}