{
  "type": "Feature",
  "properties": {
    "gn:admin1_code":"01",
    "gn:asciiname":"Scipe",
    "gn:country_code":"BA",
    "gn:dem":1181,
    "gn:feature_class":"P",
    "gn:feature_code":"PPL",
    "gn:name":"\u0160\u0107ipe",
    "gn:population":0,
    "gn:timezone":"Europe/Sarajevo",
    "iso:country":"BA",
    "wof:name":"Scipe",
    "wof:placetype":"locality"
},
  "geometry": {"coordinates":[17.74722000000001,43.82944000000001],"type":"Point"}
}