{
  "type": "Feature",
  "properties": {
    "gn:admin1_code":"01",
    "gn:asciiname":"Vodenica",
    "gn:country_code":"BA",
    "gn:dem":678,
    "gn:feature_class":"P",
    "gn:feature_code":"PPL",
    "gn:name":"Vo\u0111enica",
    "gn:population":0,
    "gn:timezone":"Europe/Sarajevo",
    "iso:country":"BA",
    "name:und_x_variant":[
        "Vodjenica",
        "Vodenica",
        "Vo\u0107enica",
        "Vo\u0111enica"
    ],
    "wof:name":"Vodenica",
    "wof:placetype":"locality"
},
  "geometry": {"coordinates":[16.27265,44.63513],"type":"Point"}
}