{
  "type": "Feature",
  "properties": {
    "gn:admin1_code":"01",
    "gn:asciiname":"Vodenica",
    "gn:country_code":"BA",
    "gn:dem":678,
    "gn:feature_class":"P",
    "gn:feature_code":"PPL",
    "gn:name":"Vo\u0111enica",
    "gn:population":0,
    "gn:timezone":"Europe/Sarajevo",
    "iso:country":"BA",
    "name:bos_x_preferred":[
        "Vo\u0111enica"
    ],
    "name:ceb_x_preferred":[
        "Vo\u0111enica"
    ],
    "name:fra_x_preferred":[
        "Vo\u0111enica"
    ],
    "name:hrv_x_preferred":[
        "Vo\u0111enica"
    ],
    "name:srp_x_preferred":[
        "\u0412\u043e\u0452\u0435\u043d\u0438\u0446\u0430"
    ],
    "name:swe_x_preferred":[
        "Vo\u0111enica"
    ],
    "name:und_x_variant":[
        "Vodjenica",
        "Vodenica",
        "Vo\u0107enica",
        "Vo\u0111enica"
    ],
    "wof:name":"Vodenica",
    "wof:placetype":"locality"
},
  "geometry": {"coordinates":[16.27265,44.63513],"type":"Point"}
}