{
  "type": "Feature",
  "properties": {
    "gn:admin1_code":"02",
    "gn:asciiname":"Dzelilovici",
    "gn:country_code":"BA",
    "gn:dem":504,
    "gn:feature_class":"P",
    "gn:feature_code":"PPL",
    "gn:name":"D\u017eelilovi\u0107i",
    "gn:population":0,
    "gn:timezone":"Europe/Sarajevo",
    "iso:country":"BA",
    "wof:name":"Dzelilovici",
    "wof:placetype":"locality"
},
  "geometry": {"coordinates":[19.05533,44.24263],"type":"Point"}
}