{
  "type": "Feature",
  "properties": {
    "gn:country":"BA",
    "gn:fcode":"PPL",
    "gn:pop":6405,
    "iso:country":"BA",
    "name:ara_x_preferred":[
        "\u062a\u0633\u0644\u064a\u062a\u0634"
    ],
    "name:bos_x_preferred":[
        "Tesli\u0107"
    ],
    "name:bul_x_preferred":[
        "\u0422\u0435\u0441\u043b\u0438\u0447"
    ],
    "name:cat_x_preferred":[
        "Tesli\u0107"
    ],
    "name:ceb_x_preferred":[
        "Tesli\u0107"
    ],
    "name:ces_x_preferred":[
        "Tesli\u0107"
    ],
    "name:deu_x_preferred":[
        "Tesli\u0107"
    ],
    "name:ell_x_preferred":[
        "\u03a4\u03ad\u03c3\u03bb\u03b9\u03c4\u03c2"
    ],
    "name:eng_x_preferred":[
        "Tesli\u0107"
    ],
    "name:epo_x_preferred":[
        "Tesli\u0109"
    ],
    "name:fra_x_preferred":[
        "Tesli\u0107"
    ],
    "name:hrv_x_preferred":[
        "Tesli\u0107"
    ],
    "name:ita_x_preferred":[
        "Tesli\u0107"
    ],
    "name:jpn_x_preferred":[
        "\u30c6\u30b9\u30ea\u30c1"
    ],
    "name:lit_x_preferred":[
        "Tesli\u010dius"
    ],
    "name:mkd_x_preferred":[
        "\u0422\u0435\u0441\u043b\u0438\u045c"
    ],
    "name:nld_x_preferred":[
        "Tesli\u0107"
    ],
    "name:pol_x_preferred":[
        "Tesli\u0107"
    ],
    "name:rus_x_preferred":[
        "\u0422\u0435\u0441\u043b\u0438\u0447"
    ],
    "name:spa_x_preferred":[
        "Tesli\u0107"
    ],
    "name:sqi_x_preferred":[
        "Tesliqi"
    ],
    "name:srp_x_preferred":[
        "\u0422\u0435\u0441\u043b\u0438\u045b"
    ],
    "name:swe_x_preferred":[
        "Tesli\u0107"
    ],
    "name:tat_x_preferred":[
        "\u0422\u0435\u0441\u043b\u0438\u0447"
    ],
    "name:tur_x_preferred":[
        "Tesli\u0107"
    ],
    "name:ukr_x_preferred":[
        "\u0422\u0435\u0441\u043b\u0438\u0447"
    ],
    "name:urd_x_preferred":[
        "\u062a\u06cc\u0633\u0644\u0686"
    ],
    "name:zho_x_preferred":[
        "\u6cf0\u65af\u5229\u5947"
    ],
    "qs:name":"Tesli\u0107",
    "qs:name_adm0":"Bosna i Hercegovina",
    "qs:name_adm1":"Republika Srpska",
    "qs:photos":43,
    "qs:photos_1k":9,
    "qs:photos_9k":1,
    "qs:photos_9r":2,
    "qs:photos_all":43,
    "qs:photos_sr":2,
    "qs:placetype":"Town",
    "qs:pop_sr":"5",
    "wd:wordcount":739,
    "wof:name":"Tesli\u0107",
    "wof:placetype":"locality",
    "wof:population":6405
},
  "geometry": {"coordinates":[17.85972,44.60639],"type":"Point"}
}