{
  "type": "Feature",
  "properties": {
    "gn:admin1_code":"01",
    "gn:asciiname":"Obarak",
    "gn:country_code":"BA",
    "gn:dem":346,
    "gn:feature_class":"P",
    "gn:feature_code":"PPL",
    "gn:name":"Obarak",
    "gn:population":0,
    "gn:timezone":"Europe/Sarajevo",
    "iso:country":"BA",
    "wof:name":"Obarak",
    "wof:placetype":"locality"
},
  "geometry": {"coordinates":[18.98556,43.67583],"type":"Point"}
}