{
  "type": "Feature",
  "properties": {
    "gn:admin1_code":"02",
    "gn:asciiname":"Petkovici",
    "gn:country_code":"BA",
    "gn:dem":126,
    "gn:feature_class":"P",
    "gn:feature_code":"PPL",
    "gn:name":"Petkovi\u0107i",
    "gn:population":0,
    "gn:timezone":"Europe/Sarajevo",
    "iso:country":"BA",
    "wof:name":"Petkovici",
    "wof:placetype":"locality"
},
  "geometry": {"coordinates":[16.84317,45.15837],"type":"Point"}
}