{
  "type": "Feature",
  "properties": {
    "gn:admin1_code":"01",
    "gn:asciiname":"Porcici",
    "gn:country_code":"BA",
    "gn:dem":313,
    "gn:feature_class":"P",
    "gn:feature_code":"PPL",
    "gn:name":"Por\u010di\u0107i",
    "gn:population":0,
    "gn:timezone":"Europe/Sarajevo",
    "iso:country":"BA",
    "wof:name":"Porcici",
    "wof:placetype":"locality"
},
  "geometry": {"coordinates":[15.8375,45.02694],"type":"Point"}
}