{
  "type": "Feature",
  "properties": {
    "gn:admin1_code":"01",
    "gn:asciiname":"Zovke",
    "gn:country_code":"BA",
    "gn:dem":309,
    "gn:feature_class":"P",
    "gn:feature_code":"PPL",
    "gn:name":"Zovke",
    "gn:population":0,
    "gn:timezone":"Europe/Sarajevo",
    "iso:country":"BA",
    "wof:name":"Zovke",
    "wof:placetype":"locality"
},
  "geometry": {"coordinates":[17.70008,43.35407],"type":"Point"}
}