{
  "type": "Feature",
  "properties": {
    "gn:admin1_code":"01",
    "gn:asciiname":"Doke",
    "gn:country_code":"BA",
    "gn:dem":310,
    "gn:feature_class":"P",
    "gn:feature_code":"PPL",
    "gn:name":"Doke",
    "gn:population":0,
    "gn:timezone":"Europe/Sarajevo",
    "iso:country":"BA",
    "wof:name":"Doke",
    "wof:placetype":"locality"
},
  "geometry": {"coordinates":[17.75094,43.22687],"type":"Point"}
}