{
  "type": "Feature",
  "properties": {
    "gn:admin1_code":"01",
    "gn:asciiname":"Pire",
    "gn:country_code":"BA",
    "gn:dem":306,
    "gn:feature_class":"P",
    "gn:feature_code":"PPL",
    "gn:name":"Pire",
    "gn:population":0,
    "gn:timezone":"Europe/Sarajevo",
    "iso:country":"BA",
    "wof:name":"Pire",
    "wof:placetype":"locality"
},
  "geometry": {"coordinates":[18.017,44.49634],"type":"Point"}
}