{
  "type": "Feature",
  "properties": {
    "gn:admin1_code":"02",
    "gn:asciiname":"Turudije",
    "gn:country_code":"BA",
    "gn:dem":356,
    "gn:feature_class":"P",
    "gn:feature_code":"PPL",
    "gn:name":"Turudije",
    "gn:population":0,
    "gn:timezone":"Europe/Sarajevo",
    "iso:country":"BA",
    "wof:name":"Turudije",
    "wof:placetype":"locality"
},
  "geometry": {"coordinates":[16.79109,45.0225],"type":"Point"}
}