{
  "type": "Feature",
  "properties": {
    "gn:admin1_code":"02",
    "gn:asciiname":"Jorgici",
    "gn:country_code":"BA",
    "gn:dem":202,
    "gn:feature_class":"P",
    "gn:feature_code":"PPL",
    "gn:name":"Jorgi\u0107i",
    "gn:population":0,
    "gn:timezone":"Europe/Sarajevo",
    "iso:country":"BA",
    "wof:name":"Jorgici",
    "wof:placetype":"locality"
},
  "geometry": {"coordinates":[17.88665,44.64284],"type":"Point"}
}