{
  "type": "Feature",
  "properties": {
    "gn:admin1_code":"01",
    "gn:asciiname":"Husidici",
    "gn:country_code":"BA",
    "gn:dem":245,
    "gn:feature_class":"P",
    "gn:feature_code":"PPL",
    "gn:name":"Hu\u0161idi\u0107i",
    "gn:population":0,
    "gn:timezone":"Europe/Sarajevo",
    "iso:country":"BA",
    "wof:name":"Husidici",
    "wof:placetype":"locality"
},
  "geometry": {"coordinates":[15.89818,45.16535],"type":"Point"}
}