{
  "type": "Feature",
  "properties": {
    "gn:admin1_code":"01",
    "gn:asciiname":"Bilisici",
    "gn:country_code":"BA",
    "gn:dem":253,
    "gn:feature_class":"P",
    "gn:feature_code":"PPL",
    "gn:name":"Bili\u0161i\u0107i",
    "gn:population":0,
    "gn:timezone":"Europe/Sarajevo",
    "iso:country":"BA",
    "wof:name":"Bilisici",
    "wof:placetype":"locality"
},
  "geometry": {"coordinates":[17.7316,43.29557],"type":"Point"}
}