{
  "type": "Feature",
  "properties": {
    "gn:admin1_code":"01",
    "gn:asciiname":"Tadici",
    "gn:country_code":"BA",
    "gn:dem":471,
    "gn:feature_class":"P",
    "gn:feature_code":"PPL",
    "gn:name":"Tadi\u0107i",
    "gn:population":0,
    "gn:timezone":"Europe/Sarajevo",
    "iso:country":"BA",
    "wof:name":"Tadici",
    "wof:placetype":"locality"
},
  "geometry": {"coordinates":[16.4059,44.76303],"type":"Point"}
}