{
  "type": "Feature",
  "properties": {
    "gn:admin1_code":"02",
    "gn:asciiname":"Donji Lukavac",
    "gn:country_code":"BA",
    "gn:dem":883,
    "gn:feature_class":"P",
    "gn:feature_code":"PPL",
    "gn:name":"Donji Lukavac",
    "gn:population":0,
    "gn:timezone":"Europe/Sarajevo",
    "iso:country":"BA",
    "name:bos_x_preferred":[
        "Donji Lukavac"
    ],
    "name:fra_x_preferred":[
        "Donji Lukavac"
    ],
    "name:hrv_x_preferred":[
        "Donji Lukavac"
    ],
    "name:srp_x_preferred":[
        "\u0414\u043e\u045a\u0438 \u041b\u0443\u043a\u0430\u0432\u0430\u0446"
    ],
    "name:und_x_variant":[
        "Lukavac Donji"
    ],
    "wof:name":"Donji Lukavac",
    "wof:placetype":"locality"
},
  "geometry": {"coordinates":[18.29806,43.11194],"type":"Point"}
}