{
  "type": "Feature",
  "properties": {
    "gn:admin1_code":"02",
    "gn:asciiname":"Donji Lukavac",
    "gn:country_code":"BA",
    "gn:dem":883,
    "gn:feature_class":"P",
    "gn:feature_code":"PPL",
    "gn:name":"Donji Lukavac",
    "gn:population":0,
    "gn:timezone":"Europe/Sarajevo",
    "iso:country":"BA",
    "wof:name":"Donji Lukavac",
    "wof:placetype":"locality"
},
  "geometry": {"coordinates":[18.29806,43.11194],"type":"Point"}
}