{
  "type": "Feature",
  "properties": {
    "gn:admin1_code":"02",
    "gn:asciiname":"Dakovici",
    "gn:country_code":"BA",
    "gn:dem":538,
    "gn:feature_class":"P",
    "gn:feature_code":"PPL",
    "gn:name":"\u00d0akovi\u0107i",
    "gn:population":0,
    "gn:timezone":"Europe/Sarajevo",
    "iso:country":"BA",
    "wof:name":"Dakovici",
    "wof:placetype":"locality"
},
  "geometry": {"coordinates":[16.86427,44.37666],"type":"Point"}
}