{
  "type": "Feature",
  "properties": {
    "gn:admin1_code":"02",
    "gn:asciiname":"Kazmerici",
    "gn:country_code":"BA",
    "gn:dem":759,
    "gn:feature_class":"P",
    "gn:feature_code":"PPL",
    "gn:name":"Kazmeri\u0107i",
    "gn:population":0,
    "gn:timezone":"Europe/Sarajevo",
    "iso:country":"BA",
    "name:bos_x_preferred":[
        "Kazmeri\u0107i"
    ],
    "name:fra_x_preferred":[
        "Kazmeri\u0107i"
    ],
    "name:srp_x_preferred":[
        "\u041a\u0430\u0437\u043c\u0435\u0440\u0438\u045b\u0438"
    ],
    "name:und_x_variant":[
        "Kazmeri\u0107i"
    ],
    "wof:name":"Kazmerici",
    "wof:placetype":"locality"
},
  "geometry": {"coordinates":[18.72239,44.01065],"type":"Point"}
}