{
  "type": "Feature",
  "properties": {
    "gn:admin1_code":"01",
    "gn:asciiname":"Crnaja",
    "gn:country_code":"BA",
    "gn:dem":313,
    "gn:feature_class":"P",
    "gn:feature_code":"PPL",
    "gn:name":"Crnaja",
    "gn:population":0,
    "gn:timezone":"Europe/Sarajevo",
    "iso:country":"BA",
    "wof:name":"Crnaja",
    "wof:placetype":"locality"
},
  "geometry": {"coordinates":[15.80677,45.03927],"type":"Point"}
}