{
  "type": "Feature",
  "properties": {
    "gn:admin1_code":"01",
    "gn:asciiname":"Masinove Doline",
    "gn:country_code":"BA",
    "gn:dem":908,
    "gn:feature_class":"P",
    "gn:feature_code":"PPL",
    "gn:name":"Ma\u0161inove Doline",
    "gn:population":0,
    "gn:timezone":"Europe/Sarajevo",
    "iso:country":"BA",
    "wof:name":"Masinove Doline",
    "wof:placetype":"locality"
},
  "geometry": {"coordinates":[16.06603,44.75197],"type":"Point"}
}