{
  "type": "Feature",
  "properties": {
    "gn:country":"BA",
    "gn:fcode":"PPL",
    "gn:pop":4899,
    "iso:country":"BA",
    "name:bel_x_preferred":[
        "\u041c\u0430\u0441\u043b\u0430\u0432\u0430\u0440\u044d"
    ],
    "name:bos_x_preferred":[
        "Maslovare"
    ],
    "name:bul_x_preferred":[
        "\u041c\u0430\u0441\u043b\u043e\u0432\u0430\u0440\u0435"
    ],
    "name:ceb_x_preferred":[
        "Maslovare"
    ],
    "name:eng_x_preferred":[
        "Maslovare"
    ],
    "name:fra_x_preferred":[
        "Maslovare"
    ],
    "name:hrv_x_preferred":[
        "Maslovare"
    ],
    "name:hye_x_preferred":[
        "\u0544\u0561\u057d\u056c\u0578\u057e\u0561\u0580\u0565"
    ],
    "name:nld_x_preferred":[
        "Maslovare"
    ],
    "name:rus_x_preferred":[
        "\u041c\u0430\u0441\u043b\u043e\u0432\u0430\u0440\u0435"
    ],
    "name:srp_x_preferred":[
        "\u041c\u0430\u0441\u043b\u043e\u0432\u0430\u0440\u0435"
    ],
    "name:swe_x_preferred":[
        "Maslovare"
    ],
    "name:unk_x_variant":[
        "Mastovare"
    ],
    "qs:name":"Maslovare",
    "qs:name_adm0":"Bosna i Hercegovina",
    "qs:name_adm1":"Republika Srpska",
    "qs:photos_9r":0,
    "qs:photos_sr":0,
    "qs:placetype":"Town",
    "qs:pop_sr":"4",
    "wd:wordcount":393,
    "wof:name":"Maslovare",
    "wof:placetype":"locality",
    "wof:population":4899
},
  "geometry": {"coordinates":[17.53216,44.56594],"type":"Point"}
}