{
  "type": "Feature",
  "properties": {
    "gn:admin1_code":"02",
    "gn:asciiname":"Oglavak",
    "gn:country_code":"BA",
    "gn:dem":995,
    "gn:feature_class":"P",
    "gn:feature_code":"PPL",
    "gn:name":"Oglavak",
    "gn:population":0,
    "gn:timezone":"Europe/Sarajevo",
    "iso:country":"BA",
    "name:bos_x_preferred":[
        "Oglavak"
    ],
    "name:fra_x_preferred":[
        "Oglavak"
    ],
    "name:hrv_x_preferred":[
        "Oglavak"
    ],
    "name:srp_x_preferred":[
        "\u041e\u0433\u043b\u0430\u0432\u0430\u043a"
    ],
    "wof:name":"Oglavak",
    "wof:placetype":"locality"
},
  "geometry": {"coordinates":[18.63217,43.72145],"type":"Point"}
}