{
  "type": "Feature",
  "properties": {
    "gn:admin1_code":"02",
    "gn:asciiname":"Rusanj",
    "gn:country_code":"BA",
    "gn:dem":660,
    "gn:feature_class":"P",
    "gn:feature_code":"PPL",
    "gn:name":"Rusanj",
    "gn:population":0,
    "gn:timezone":"Europe/Sarajevo",
    "iso:country":"BA",
    "wof:name":"Rusanj",
    "wof:placetype":"locality"
},
  "geometry": {"coordinates":[19.0233,43.62745],"type":"Point"}
}