{
  "type": "Feature",
  "properties": {
    "gn:admin1_code":"02",
    "gn:asciiname":"Samac",
    "gn:country_code":"BA",
    "gn:dem":170,
    "gn:feature_class":"P",
    "gn:feature_code":"PPL",
    "gn:name":"\u0160amac",
    "gn:population":0,
    "gn:timezone":"Europe/Sarajevo",
    "iso:country":"BA",
    "wof:name":"Samac",
    "wof:placetype":"locality"
},
  "geometry": {"coordinates":[17.44506,44.84835],"type":"Point"}
}