{
  "type": "Feature",
  "properties": {
    "gn:admin1_code":"02",
    "gn:asciiname":"Pajici",
    "gn:country_code":"BA",
    "gn:dem":240,
    "gn:feature_class":"P",
    "gn:feature_code":"PPL",
    "gn:name":"Paji\u0107i",
    "gn:population":0,
    "gn:timezone":"Europe/Sarajevo",
    "iso:country":"BA",
    "wof:name":"Pajici",
    "wof:placetype":"locality"
},
  "geometry": {"coordinates":[19.28277000000001,44.1974],"type":"Point"}
}