{
  "type": "Feature",
  "properties": {
    "gn:admin1_code":"01",
    "gn:asciiname":"Rajici",
    "gn:country_code":"BA",
    "gn:dem":350,
    "gn:feature_class":"P",
    "gn:feature_code":"PPL",
    "gn:name":"Raji\u0107i",
    "gn:population":0,
    "gn:timezone":"Europe/Sarajevo",
    "iso:country":"BA",
    "wof:name":"Rajici",
    "wof:placetype":"locality"
},
  "geometry": {"coordinates":[17.86349,43.71417],"type":"Point"}
}