{
  "type": "Feature",
  "properties": {
    "gn:admin1_code":"02",
    "gn:asciiname":"Lujici",
    "gn:country_code":"BA",
    "gn:dem":429,
    "gn:feature_class":"P",
    "gn:feature_code":"PPL",
    "gn:name":"Luji\u0107i",
    "gn:population":0,
    "gn:timezone":"Europe/Sarajevo",
    "iso:country":"BA",
    "wof:name":"Lujici",
    "wof:placetype":"locality"
},
  "geometry": {"coordinates":[17.49829,44.51864000000001],"type":"Point"}
}