{
  "type": "Feature",
  "properties": {
    "gn:admin1_code":"01",
    "gn:asciiname":"Zlibina",
    "gn:country_code":"BA",
    "gn:dem":281,
    "gn:feature_class":"P",
    "gn:feature_code":"PPL",
    "gn:name":"\u017dlibina",
    "gn:population":0,
    "gn:timezone":"Europe/Sarajevo",
    "iso:country":"BA",
    "wof:name":"Zlibina",
    "wof:placetype":"locality"
},
  "geometry": {"coordinates":[17.40392,43.34743],"type":"Point"}
}