{
  "type": "Feature",
  "properties": {
    "gn:admin1_code":"01",
    "gn:asciiname":"Glibe",
    "gn:country_code":"BA",
    "gn:dem":669,
    "gn:feature_class":"P",
    "gn:feature_code":"PPL",
    "gn:name":"Glibe",
    "gn:population":0,
    "gn:timezone":"Europe/Sarajevo",
    "iso:country":"BA",
    "wof:name":"Glibe",
    "wof:placetype":"locality"
},
  "geometry": {"coordinates":[17.69252000000001,43.78744],"type":"Point"}
}