{
  "type": "Feature",
  "properties": {
    "gn:admin1_code":"01",
    "gn:asciiname":"Donji Kotorac",
    "gn:country_code":"BA",
    "gn:dem":520,
    "gn:feature_class":"P",
    "gn:feature_code":"PPL",
    "gn:name":"Donji Kotorac",
    "gn:population":0,
    "gn:timezone":"Europe/Sarajevo",
    "iso:country":"BA",
    "wof:name":"Donji Kotorac",
    "wof:placetype":"locality"
},
  "geometry": {"coordinates":[18.34513,43.81576],"type":"Point"}
}