{
  "type": "Feature",
  "properties": {
    "gn:admin1_code":"01",
    "gn:asciiname":"Blazuj",
    "gn:country_code":"BA",
    "gn:dem":943,
    "gn:feature_class":"P",
    "gn:feature_code":"PPL",
    "gn:name":"Bla\u017euj",
    "gn:population":0,
    "gn:timezone":"Europe/Sarajevo",
    "iso:country":"BA",
    "name:bos_x_preferred":[
        "Bla\u017euj"
    ],
    "name:ceb_x_preferred":[
        "Bla\u017euj"
    ],
    "name:fra_x_preferred":[
        "Bla\u017euj"
    ],
    "name:hrv_x_preferred":[
        "Bla\u017euj"
    ],
    "name:srp_x_preferred":[
        "\u0411\u043b\u0430\u0436\u0443\u0458"
    ],
    "name:swe_x_preferred":[
        "Bla\u017euj"
    ],
    "name:und_x_variant":[
        "Bla\u017eij"
    ],
    "wof:name":"Blazuj",
    "wof:placetype":"locality"
},
  "geometry": {"coordinates":[17.22009,43.73154],"type":"Point"}
}