{
  "type": "Feature",
  "properties": {
    "gn:admin1_code":"01",
    "gn:asciiname":"Blazuj",
    "gn:country_code":"BA",
    "gn:dem":943,
    "gn:feature_class":"P",
    "gn:feature_code":"PPL",
    "gn:name":"Bla\u017euj",
    "gn:population":0,
    "gn:timezone":"Europe/Sarajevo",
    "iso:country":"BA",
    "name:und_x_variant":[
        "Bla\u017eij",
        "Bla\u017euj"
    ],
    "wof:name":"Blazuj",
    "wof:placetype":"locality"
},
  "geometry": {"coordinates":[17.22009,43.73154],"type":"Point"}
}