{
  "type": "Feature",
  "properties": {
    "gn:admin1_code":"02",
    "gn:asciiname":"Ulinje",
    "gn:country_code":"BA",
    "gn:dem":747,
    "gn:feature_class":"P",
    "gn:feature_code":"PPL",
    "gn:name":"Ulinje",
    "gn:population":0,
    "gn:timezone":"Europe/Sarajevo",
    "iso:country":"BA",
    "name:bos_x_preferred":[
        "Ulinje"
    ],
    "name:fra_x_preferred":[
        "Ulinje"
    ],
    "name:hrv_x_preferred":[
        "Ulinje"
    ],
    "name:srp_x_preferred":[
        "\u0423\u043b\u0438\u045a\u0435"
    ],
    "wof:name":"Ulinje",
    "wof:placetype":"locality"
},
  "geometry": {"coordinates":[18.74556,43.5725],"type":"Point"}
}