{
  "type": "Feature",
  "properties": {
    "gn:admin1_code":"01",
    "gn:asciiname":"Haluge",
    "gn:country_code":"BA",
    "gn:dem":574,
    "gn:feature_class":"P",
    "gn:feature_code":"PPL",
    "gn:name":"Haluge",
    "gn:population":0,
    "gn:timezone":"Europe/Sarajevo",
    "iso:country":"BA",
    "name:bos_x_preferred":[
        "Haluge"
    ],
    "name:fra_x_preferred":[
        "Haluge"
    ],
    "name:hrv_x_preferred":[
        "Haluge"
    ],
    "name:srp_x_preferred":[
        "\u0425\u0430\u043b\u0443\u0433\u0435"
    ],
    "wof:name":"Haluge",
    "wof:placetype":"locality"
},
  "geometry": {"coordinates":[18.62859,44.13094],"type":"Point"}
}