{
  "type": "Feature",
  "properties": {
    "gn:admin1_code":"02",
    "gn:asciiname":"Turklje",
    "gn:country_code":"BA",
    "gn:dem":852,
    "gn:feature_class":"P",
    "gn:feature_code":"PPL",
    "gn:name":"Turklje",
    "gn:population":0,
    "gn:timezone":"Europe/Sarajevo",
    "iso:country":"BA",
    "wof:name":"Turklje",
    "wof:placetype":"locality"
},
  "geometry": {"coordinates":[17.1556,44.26204],"type":"Point"}
}