{
  "type": "Feature",
  "properties": {
    "gn:admin1_code":"01",
    "gn:asciiname":"Orescani",
    "gn:country_code":"BA",
    "gn:dem":381,
    "gn:feature_class":"P",
    "gn:feature_code":"PPL",
    "gn:name":"Ore\u0161\u010dani",
    "gn:population":0,
    "gn:timezone":"Europe/Sarajevo",
    "iso:country":"BA",
    "wof:name":"Orescani",
    "wof:placetype":"locality"
},
  "geometry": {"coordinates":[16.07295,44.956],"type":"Point"}
}