{
  "type": "Feature",
  "properties": {
    "gn:admin1_code":"02",
    "gn:asciiname":"Zulja",
    "gn:country_code":"BA",
    "gn:dem":316,
    "gn:feature_class":"P",
    "gn:feature_code":"PPL",
    "gn:name":"\u017dulja",
    "gn:population":0,
    "gn:timezone":"Europe/Sarajevo",
    "iso:country":"BA",
    "wof:name":"Zulja",
    "wof:placetype":"locality"
},
  "geometry": {"coordinates":[18.20648,42.78131],"type":"Point"}
}