{
  "type": "Feature",
  "properties": {
    "gn:admin1_code":"02",
    "gn:asciiname":"Saskinovci",
    "gn:country_code":"BA",
    "gn:dem":187,
    "gn:feature_class":"P",
    "gn:feature_code":"PPL",
    "gn:name":"\u0160a\u0161kinovci",
    "gn:population":0,
    "gn:timezone":"Europe/Sarajevo",
    "iso:country":"BA",
    "name:bos_x_preferred":[
        "\u0160a\u0161kinovci"
    ],
    "name:fra_x_preferred":[
        "\u0160a\u0161kinovci"
    ],
    "name:hrv_x_preferred":[
        "\u0160a\u0161kinovci"
    ],
    "name:srp_x_preferred":[
        "\u0428\u0430\u0448\u043a\u0438\u043d\u043e\u0432\u0446\u0438"
    ],
    "name:und_x_variant":[
        "\u0160a\u0161kinovci"
    ],
    "wof:name":"Saskinovci",
    "wof:placetype":"locality"
},
  "geometry": {"coordinates":[17.17423,44.97021],"type":"Point"}
}