{
  "type": "Feature",
  "properties": {
    "gn:admin1_code":"01",
    "gn:asciiname":"Budim",
    "gn:country_code":"BA",
    "gn:dem":531,
    "gn:feature_class":"P",
    "gn:feature_code":"PPL",
    "gn:name":"Budim",
    "gn:population":0,
    "gn:timezone":"Europe/Sarajevo",
    "iso:country":"BA",
    "wof:name":"Budim",
    "wof:placetype":"locality"
},
  "geometry": {"coordinates":[17.4631,43.40006],"type":"Point"}
}