{
  "type": "Feature",
  "properties": {
    "gn:admin1_code":"01",
    "gn:asciiname":"Jaklici",
    "gn:country_code":"BA",
    "gn:dem":571,
    "gn:feature_class":"P",
    "gn:feature_code":"PPL",
    "gn:name":"Jakli\u0107i",
    "gn:population":0,
    "gn:timezone":"Europe/Sarajevo",
    "iso:country":"BA",
    "wof:name":"Jaklici",
    "wof:placetype":"locality"
},
  "geometry": {"coordinates":[17.45029,44.04822],"type":"Point"}
}