{
  "type": "Feature",
  "properties": {
    "gn:admin1_code":"01",
    "gn:asciiname":"Humovaca",
    "gn:country_code":"BA",
    "gn:dem":196,
    "gn:feature_class":"P",
    "gn:feature_code":"PPL",
    "gn:name":"Humova\u010da",
    "gn:population":0,
    "gn:timezone":"Europe/Sarajevo",
    "iso:country":"BA",
    "wof:name":"Humovaca",
    "wof:placetype":"locality"
},
  "geometry": {"coordinates":[17.56002,43.22426],"type":"Point"}
}