{
  "type": "Feature",
  "properties": {
    "gn:admin1_code":"01",
    "gn:asciiname":"Bale",
    "gn:country_code":"BA",
    "gn:dem":866,
    "gn:feature_class":"P",
    "gn:feature_code":"PPL",
    "gn:name":"Bale",
    "gn:population":0,
    "gn:timezone":"Europe/Sarajevo",
    "iso:country":"BA",
    "name:ara_x_preferred":[
        "\u0628\u0627\u0644\u064a"
    ],
    "name:bos_x_preferred":[
        "Bale"
    ],
    "name:fra_x_preferred":[
        "Bale"
    ],
    "name:hrv_x_preferred":[
        "Bale"
    ],
    "name:srp_x_preferred":[
        "\u0411\u0430\u043b\u0435"
    ],
    "wof:name":"Bale",
    "wof:placetype":"locality"
},
  "geometry": {"coordinates":[17.9751,43.72944],"type":"Point"}
}