{
  "type": "Feature",
  "properties": {
    "gn:admin1_code":"02",
    "gn:asciiname":"Bojici",
    "gn:country_code":"BA",
    "gn:dem":1035,
    "gn:feature_class":"P",
    "gn:feature_code":"PPL",
    "gn:name":"Boji\u0107i",
    "gn:population":0,
    "gn:timezone":"Europe/Sarajevo",
    "iso:country":"BA",
    "name:bos_x_preferred":[
        "Boji\u0107i"
    ],
    "name:fra_x_preferred":[
        "Boji\u0107i"
    ],
    "name:hrv_x_preferred":[
        "Boji\u0107i"
    ],
    "name:srp_x_preferred":[
        "\u0411\u043e\u0458\u0438\u045b\u0438"
    ],
    "name:und_x_variant":[
        "Boji\u0107i"
    ],
    "wof:name":"Bojici",
    "wof:placetype":"locality"
},
  "geometry": {"coordinates":[18.35407,43.51092],"type":"Point"}
}