{
  "type": "Feature",
  "properties": {
    "gn:admin1_code":"BRC",
    "gn:asciiname":"Vuksic Donji",
    "gn:country_code":"BA",
    "gn:dem":87,
    "gn:feature_class":"P",
    "gn:feature_code":"PPLL",
    "gn:name":"Vuk\u0161i\u0107 Donji",
    "gn:population":0,
    "gn:timezone":"Europe/Sarajevo",
    "iso:country":"BA",
    "name:bos_x_preferred":[
        "Vuk\u0161i\u0107 Donji"
    ],
    "name:ceb_x_preferred":[
        "Vuk\u0161i\u0107 Donji"
    ],
    "name:fra_x_preferred":[
        "Vuk\u0161i\u0107 Donji"
    ],
    "name:hrv_x_preferred":[
        "Vuk\u0161i\u0107 Donji"
    ],
    "name:srp_x_preferred":[
        "\u0412\u0443\u043a\u0448\u0438\u045b \u0414\u043e\u045a\u0438"
    ],
    "name:swe_x_preferred":[
        "Vuk\u0161i\u0107 Donji"
    ],
    "name:und_x_variant":[
        "Donji Vuk\u0161i\u0107"
    ],
    "wof:name":"Vuksic Donji",
    "wof:placetype":"locality"
},
  "geometry": {"coordinates":[18.69656,44.90151],"type":"Point"}
}