{
  "type": "Feature",
  "properties": {
    "gn:admin1_code":"02",
    "gn:asciiname":"Jabuka",
    "gn:country_code":"BA",
    "gn:dem":1020,
    "gn:feature_class":"P",
    "gn:feature_code":"PPL",
    "gn:name":"Jabuka",
    "gn:population":0,
    "gn:timezone":"Europe/Sarajevo",
    "iso:country":"BA",
    "wof:name":"Jabuka",
    "wof:placetype":"locality"
},
  "geometry": {"coordinates":[18.58249,43.30707],"type":"Point"}
}