{
  "type": "Feature",
  "properties": {
    "gn:admin1_code":"02",
    "gn:asciiname":"Jabuka",
    "gn:country_code":"BA",
    "gn:dem":1020,
    "gn:feature_class":"P",
    "gn:feature_code":"PPL",
    "gn:name":"Jabuka",
    "gn:population":0,
    "gn:timezone":"Europe/Sarajevo",
    "iso:country":"BA",
    "name:bul_x_preferred":[
        "\u042f\u0431\u0443\u043a\u0430"
    ],
    "name:deu_x_preferred":[
        "Jabuka"
    ],
    "name:epo_x_preferred":[
        "Jabuka"
    ],
    "name:fra_x_preferred":[
        "Jabuka"
    ],
    "name:heb_x_preferred":[
        "\u05d9\u05d0\u05d1\u05d5\u05e7\u05d4"
    ],
    "name:hrv_x_preferred":[
        "Jabuka"
    ],
    "name:hun_x_preferred":[
        "Toront\u00e1lalm\u00e1s"
    ],
    "name:mkd_x_preferred":[
        "\u0408\u0430\u0431\u0443\u043a\u0430"
    ],
    "name:msa_x_preferred":[
        "Jabuka"
    ],
    "name:slv_x_preferred":[
        "Jabuka"
    ],
    "name:srp_x_preferred":[
        "\u0408\u0430\u0431\u0443\u043a\u0430"
    ],
    "name:urd_x_preferred":[
        "\u062c\u0628\u06a9\u06c1"
    ],
    "wof:name":"Jabuka",
    "wof:placetype":"locality"
},
  "geometry": {"coordinates":[18.58249,43.30707],"type":"Point"}
}