{
  "type": "Feature",
  "properties": {
    "gn:admin1_code":"02",
    "gn:asciiname":"Poljanice",
    "gn:country_code":"BA",
    "gn:dem":843,
    "gn:feature_class":"P",
    "gn:feature_code":"PPL",
    "gn:name":"Poljanice",
    "gn:population":0,
    "gn:timezone":"Europe/Sarajevo",
    "iso:country":"BA",
    "name:bos_x_preferred":[
        "Poljanice"
    ],
    "name:fra_x_preferred":[
        "Poljanice"
    ],
    "name:hrv_x_preferred":[
        "Poljanice"
    ],
    "name:rus_x_preferred":[
        "\u041f\u043e\u043b\u044f\u043d\u0438\u0446\u0435"
    ],
    "name:srp_x_preferred":[
        "\u041f\u043e\u0459\u0430\u043d\u0438\u0446\u0435"
    ],
    "name:und_x_variant":[
        "Poljani\u0107i"
    ],
    "wof:name":"Poljanice",
    "wof:placetype":"locality"
},
  "geometry": {"coordinates":[19.36533,43.70798],"type":"Point"}
}