{
  "type": "Feature",
  "properties": {
    "gn:admin1_code":"02",
    "gn:asciiname":"Prisoje",
    "gn:country_code":"BA",
    "gn:dem":521,
    "gn:feature_class":"P",
    "gn:feature_code":"PPL",
    "gn:name":"Prisoje",
    "gn:population":0,
    "gn:timezone":"Europe/Sarajevo",
    "iso:country":"BA",
    "wof:name":"Prisoje",
    "wof:placetype":"locality"
},
  "geometry": {"coordinates":[18.26896,43.04208],"type":"Point"}
}