{
  "type": "Feature",
  "properties": {
    "gn:admin1_code":"02",
    "gn:asciiname":"Dvorina",
    "gn:country_code":"BA",
    "gn:dem":217,
    "gn:feature_class":"P",
    "gn:feature_code":"PPL",
    "gn:name":"Dvorina",
    "gn:population":0,
    "gn:timezone":"Europe/Sarajevo",
    "iso:country":"BA",
    "wof:name":"Dvorina",
    "wof:placetype":"locality"
},
  "geometry": {"coordinates":[16.4718,44.99895],"type":"Point"}
}