{
  "type": "Feature",
  "properties": {
    "gn:admin1_code":"02",
    "gn:asciiname":"Perinje",
    "gn:country_code":"BA",
    "gn:dem":329,
    "gn:feature_class":"P",
    "gn:feature_code":"PPL",
    "gn:name":"Perinje",
    "gn:population":0,
    "gn:timezone":"Europe/Sarajevo",
    "iso:country":"BA",
    "wof:name":"Perinje",
    "wof:placetype":"locality"
},
  "geometry": {"coordinates":[18.96994,44.3096],"type":"Point"}
}