{
  "type": "Feature",
  "properties": {
    "gn:admin1_code":"01",
    "gn:asciiname":"Sabancici",
    "gn:country_code":"BA",
    "gn:dem":471,
    "gn:feature_class":"P",
    "gn:feature_code":"PPL",
    "gn:name":"\u0160aban\u010di\u0107i",
    "gn:population":0,
    "gn:timezone":"Europe/Sarajevo",
    "iso:country":"BA",
    "wof:name":"Sabancici",
    "wof:placetype":"locality"
},
  "geometry": {"coordinates":[17.76472,43.70132],"type":"Point"}
}