{
  "type": "Feature",
  "properties": {
    "gn:admin1_code":"02",
    "gn:asciiname":"Usora",
    "gn:country_code":"BA",
    "gn:dem":315,
    "gn:feature_class":"P",
    "gn:feature_code":"PPL",
    "gn:name":"Usora",
    "gn:population":0,
    "gn:timezone":"Europe/Sarajevo",
    "iso:country":"BA",
    "wof:name":"Usora",
    "wof:placetype":"locality"
},
  "geometry": {"coordinates":[17.71063,44.60632],"type":"Point"}
}