{
  "type": "Feature",
  "properties": {
    "gn:admin1_code":"02",
    "gn:asciiname":"Usora",
    "gn:country_code":"BA",
    "gn:dem":315,
    "gn:feature_class":"P",
    "gn:feature_code":"PPL",
    "gn:name":"Usora",
    "gn:population":0,
    "gn:timezone":"Europe/Sarajevo",
    "iso:country":"BA",
    "name:bos_x_preferred":[
        "Usora"
    ],
    "name:ceb_x_preferred":[
        "Usora"
    ],
    "name:deu_x_preferred":[
        "Usora"
    ],
    "name:fra_x_preferred":[
        "Usora"
    ],
    "name:hrv_x_preferred":[
        "Usora"
    ],
    "name:rus_x_preferred":[
        "\u0423\u0441\u043e\u0440\u0430"
    ],
    "name:spa_x_preferred":[
        "Usora"
    ],
    "name:srp_x_preferred":[
        "\u0423\u0441\u043e\u0440\u0430"
    ],
    "name:swe_x_preferred":[
        "Usora"
    ],
    "wof:name":"Usora",
    "wof:placetype":"locality"
},
  "geometry": {"coordinates":[17.71063,44.60632],"type":"Point"}
}