{
  "type": "Feature",
  "properties": {
    "gn:admin1_code":"01",
    "gn:asciiname":"Copi",
    "gn:country_code":"BA",
    "gn:dem":144,
    "gn:feature_class":"P",
    "gn:feature_code":"PPL",
    "gn:name":"\u010copi",
    "gn:population":0,
    "gn:timezone":"Europe/Sarajevo",
    "iso:country":"BA",
    "wof:name":"Copi",
    "wof:placetype":"locality"
},
  "geometry": {"coordinates":[17.72806,43.54274],"type":"Point"}
}