{
  "type": "Feature",
  "properties": {
    "gn:admin1_code":"02",
    "gn:asciiname":"Krusev Do",
    "gn:country_code":"BA",
    "gn:dem":826,
    "gn:feature_class":"P",
    "gn:feature_code":"PPLL",
    "gn:name":"Kru\u0161ev Do",
    "gn:population":0,
    "gn:timezone":"Europe/Sarajevo",
    "iso:country":"BA",
    "name:bos_x_preferred":[
        "Kru\u0161ev Do"
    ],
    "name:bul_x_preferred":[
        "\u041a\u0440\u0443\u0448\u0435\u0432 \u0414\u043e"
    ],
    "name:fra_x_preferred":[
        "Kru\u0161ev Do"
    ],
    "name:hrv_x_preferred":[
        "Kru\u0161ev Do"
    ],
    "name:srp_x_preferred":[
        "\u041a\u0440\u0443\u0448\u0435\u0432 \u0414\u043e"
    ],
    "name:und_x_variant":[
        "Kru\u0161ev Do"
    ],
    "wof:name":"Krusev Do",
    "wof:placetype":"locality"
},
  "geometry": {"coordinates":[19.20737,43.96554],"type":"Point"}
}