{
  "type": "Feature",
  "properties": {
    "gn:admin1_code":"02",
    "gn:asciiname":"Jezera",
    "gn:country_code":"BA",
    "gn:dem":813,
    "gn:feature_class":"P",
    "gn:feature_code":"PPL",
    "gn:name":"Jezera",
    "gn:population":0,
    "gn:timezone":"Europe/Sarajevo",
    "iso:country":"BA",
    "name:bos_x_preferred":[
        "Jezera"
    ],
    "name:ceb_x_preferred":[
        "Jezera"
    ],
    "name:fra_x_preferred":[
        "Jezera"
    ],
    "name:hrv_x_preferred":[
        "Jezera"
    ],
    "name:srp_x_preferred":[
        "\u0408\u0435\u0437\u0435\u0440\u0430"
    ],
    "name:swe_x_preferred":[
        "Jezera"
    ],
    "wof:name":"Jezera",
    "wof:placetype":"locality"
},
  "geometry": {"coordinates":[19.36971,43.73171],"type":"Point"}
}