{
  "type": "Feature",
  "properties": {
    "gn:admin1_code":"02",
    "gn:asciiname":"Bjelusine",
    "gn:country_code":"BA",
    "gn:dem":668,
    "gn:feature_class":"P",
    "gn:feature_code":"PPLL",
    "gn:name":"Bjelu\u0161ine",
    "gn:population":0,
    "gn:timezone":"Europe/Sarajevo",
    "iso:country":"BA",
    "wof:name":"Bjelusine",
    "wof:placetype":"locality"
},
  "geometry": {"coordinates":[19.47072,43.63221],"type":"Point"}
}