{
  "type": "Feature",
  "properties": {
    "gn:admin1_code":"01",
    "gn:asciiname":"Rovine",
    "gn:country_code":"BA",
    "gn:dem":721,
    "gn:feature_class":"P",
    "gn:feature_code":"PPL",
    "gn:name":"Rovine",
    "gn:population":0,
    "gn:timezone":"Europe/Sarajevo",
    "iso:country":"BA",
    "name:bos_x_preferred":[
        "Rovine"
    ],
    "name:ceb_x_preferred":[
        "Rovine"
    ],
    "name:fra_x_preferred":[
        "Rovine"
    ],
    "name:ita_x_preferred":[
        "Rovine"
    ],
    "name:slv_x_preferred":[
        "Rovine"
    ],
    "name:srp_x_preferred":[
        "\u0420\u043e\u0432\u0438\u043d\u0435"
    ],
    "name:swe_x_preferred":[
        "Rovine"
    ],
    "wof:name":"Rovine",
    "wof:placetype":"locality"
},
  "geometry": {"coordinates":[18.62646,44.15263],"type":"Point"}
}