{
  "type": "Feature",
  "properties": {
    "gn:admin1_code":"02",
    "gn:asciiname":"Grgici",
    "gn:country_code":"BA",
    "gn:dem":254,
    "gn:feature_class":"P",
    "gn:feature_code":"PPL",
    "gn:name":"Grgi\u0107i",
    "gn:population":0,
    "gn:timezone":"Europe/Sarajevo",
    "iso:country":"BA",
    "wof:name":"Grgici",
    "wof:placetype":"locality"
},
  "geometry": {"coordinates":[17.76424,44.64821],"type":"Point"}
}