{
  "type": "Feature",
  "properties": {
    "gn:admin1_code":"01",
    "gn:asciiname":"Rakitnica",
    "gn:country_code":"BA",
    "gn:dem":1168,
    "gn:feature_class":"P",
    "gn:feature_code":"PPL",
    "gn:name":"Rakitnica",
    "gn:population":0,
    "gn:timezone":"Europe/Sarajevo",
    "iso:country":"BA",
    "name:bos_x_preferred":[
        "Rakitnica"
    ],
    "wof:name":"Rakitnica",
    "wof:placetype":"locality"
},
  "geometry": {"coordinates":[18.27759,43.65726],"type":"Point"}
}