{
  "type": "Feature",
  "properties": {
    "gn:admin1_code":"01",
    "gn:asciiname":"Zagradinje",
    "gn:country_code":"BA",
    "gn:dem":432,
    "gn:feature_class":"P",
    "gn:feature_code":"PPL",
    "gn:name":"Zagradinje",
    "gn:population":0,
    "gn:timezone":"Europe/Sarajevo",
    "iso:country":"BA",
    "name:bos_x_preferred":[
        "Zagradinje"
    ],
    "name:fra_x_preferred":[
        "Zagradinje"
    ],
    "name:hrv_x_preferred":[
        "Zagradinje"
    ],
    "name:ita_x_preferred":[
        "Zagradinje"
    ],
    "name:srp_x_preferred":[
        "\u0417\u0430\u0433\u0440\u0430\u0434\u0438\u045a\u0435"
    ],
    "name:urd_x_preferred":[
        "\u0632\u06af\u0631\u0627\u062f\u0646\u062c\u06d2"
    ],
    "wof:name":"Zagradinje",
    "wof:placetype":"locality"
},
  "geometry": {"coordinates":[18.24056,42.6411],"type":"Point"}
}