{
  "type": "Feature",
  "properties": {
    "gn:admin1_code":"01",
    "gn:asciiname":"Zagradinje",
    "gn:country_code":"BA",
    "gn:dem":432,
    "gn:feature_class":"P",
    "gn:feature_code":"PPL",
    "gn:name":"Zagradinje",
    "gn:population":0,
    "gn:timezone":"Europe/Sarajevo",
    "iso:country":"BA",
    "wof:name":"Zagradinje",
    "wof:placetype":"locality"
},
  "geometry": {"coordinates":[18.24056,42.6411],"type":"Point"}
}