{
  "type": "Feature",
  "properties": {
    "gn:admin1_code":"02",
    "gn:asciiname":"Dolovi",
    "gn:country_code":"BA",
    "gn:dem":904,
    "gn:feature_class":"P",
    "gn:feature_code":"PPL",
    "gn:name":"Dolovi",
    "gn:population":0,
    "gn:timezone":"Europe/Sarajevo",
    "iso:country":"BA",
    "name:bos_x_preferred":[
        "Dolovi"
    ],
    "name:ceb_x_preferred":[
        "Dolovi"
    ],
    "name:fra_x_preferred":[
        "Dolovi"
    ],
    "name:hrv_x_preferred":[
        "Dolovi"
    ],
    "name:slv_x_preferred":[
        "Dolovi"
    ],
    "name:srp_x_preferred":[
        "\u0414\u043e\u043b\u043e\u0432\u0438"
    ],
    "name:swe_x_preferred":[
        "Dolovi"
    ],
    "wof:name":"Dolovi",
    "wof:placetype":"locality"
},
  "geometry": {"coordinates":[18.79851,44.02023],"type":"Point"}
}