{
  "type": "Feature",
  "properties": {
    "gn:admin1_code":"01",
    "gn:asciiname":"Miskici",
    "gn:country_code":"BA",
    "gn:dem":405,
    "gn:feature_class":"P",
    "gn:feature_code":"PPL",
    "gn:name":"Mi\u0161ki\u0107i",
    "gn:population":0,
    "gn:timezone":"Europe/Sarajevo",
    "iso:country":"BA",
    "name:und_x_variant":[
        "Mi\u0161ki\u0107a Selo",
        "Mi\u0161ki\u0107i"
    ],
    "wof:name":"Miskici",
    "wof:placetype":"locality"
},
  "geometry": {"coordinates":[15.83243,45.05726],"type":"Point"}
}