{
  "type": "Feature",
  "properties": {
    "gn:admin1_code":"02",
    "gn:asciiname":"Karalici",
    "gn:country_code":"BA",
    "gn:dem":374,
    "gn:feature_class":"P",
    "gn:feature_code":"PPLL",
    "gn:name":"Karali\u0107i",
    "gn:population":0,
    "gn:timezone":"Europe/Sarajevo",
    "iso:country":"BA",
    "wof:name":"Karalici",
    "wof:placetype":"locality"
},
  "geometry": {"coordinates":[17.03374,44.93271],"type":"Point"}
}