{
  "type": "Feature",
  "properties": {
    "gn:admin1_code":"02",
    "gn:asciiname":"Zapotocje",
    "gn:country_code":"BA",
    "gn:dem":901,
    "gn:feature_class":"P",
    "gn:feature_code":"PPL",
    "gn:name":"Zapoto\u010dje",
    "gn:population":0,
    "gn:timezone":"Europe/Sarajevo",
    "iso:country":"BA",
    "wof:name":"Zapotocje",
    "wof:placetype":"locality"
},
  "geometry": {"coordinates":[18.7998,43.40454],"type":"Point"}
}