{
  "type": "Feature",
  "properties": {
    "gn:admin1_code":"02",
    "gn:asciiname":"Scenica Ljubomir",
    "gn:country_code":"BA",
    "gn:dem":850,
    "gn:feature_class":"P",
    "gn:feature_code":"PPL",
    "gn:name":"\u0160\u0107enica Ljubomir",
    "gn:population":0,
    "gn:timezone":"Europe/Sarajevo",
    "iso:country":"BA",
    "name:bos_x_preferred":[
        "\u0160\u0107enica Ljubomir"
    ],
    "name:fra_x_preferred":[
        "\u0160\u0107enica Ljubomir"
    ],
    "name:srp_x_preferred":[
        "\u0428\u045b\u0435\u043d\u0438\u0446\u0430 \u0409\u0443\u0431\u043e\u043c\u0438\u0440"
    ],
    "name:und_x_variant":[
        "\u0160\u0107enica"
    ],
    "wof:name":"Scenica Ljubomir",
    "wof:placetype":"locality"
},
  "geometry": {"coordinates":[18.31742,42.83542],"type":"Point"}
}