{
  "type": "Feature",
  "properties": {
    "gn:admin1_code":"01",
    "gn:asciiname":"Gornji Rujani",
    "gn:country_code":"BA",
    "gn:dem":725,
    "gn:feature_class":"P",
    "gn:feature_code":"PPL",
    "gn:name":"Gornji Rujani",
    "gn:population":0,
    "gn:timezone":"Europe/Sarajevo",
    "iso:country":"BA",
    "name:bos_x_preferred":[
        "Gornji Rujani"
    ],
    "name:ceb_x_preferred":[
        "Gornji Rujani"
    ],
    "name:fra_x_preferred":[
        "Gornji Rujani"
    ],
    "name:swe_x_preferred":[
        "Gornji Rujani"
    ],
    "wof:name":"Gornji Rujani",
    "wof:placetype":"locality"
},
  "geometry": {"coordinates":[16.75423,43.88556],"type":"Point"}
}