{
  "type": "Feature",
  "properties": {
    "gn:admin1_code":"02",
    "gn:asciiname":"Gornji Bozinci",
    "gn:country_code":"BA",
    "gn:dem":257,
    "gn:feature_class":"P",
    "gn:feature_code":"PPL",
    "gn:name":"Gornji Bozinci",
    "gn:population":0,
    "gn:timezone":"Europe/Sarajevo",
    "iso:country":"BA",
    "name:und_x_variant":[
        "Katoli\u010dki Bo\u017einci",
        "Gornji Bozinci"
    ],
    "wof:name":"Gornji Bozinci",
    "wof:placetype":"locality"
},
  "geometry": {"coordinates":[18.05495,44.94841],"type":"Point"}
}