{
  "type": "Feature",
  "properties": {
    "gn:admin1_code":"02",
    "gn:asciiname":"Gornji Bozinci",
    "gn:country_code":"BA",
    "gn:dem":257,
    "gn:feature_class":"P",
    "gn:feature_code":"PPL",
    "gn:name":"Gornji Bozinci",
    "gn:population":0,
    "gn:timezone":"Europe/Sarajevo",
    "iso:country":"BA",
    "name:bos_x_preferred":[
        "Gornji Bo\u017einci"
    ],
    "name:ceb_x_preferred":[
        "Gornji Bozinci"
    ],
    "name:ell_x_preferred":[
        "\u0393\u03ba\u03cc\u03c1\u03bd\u03b9 \u039c\u03c0\u03cc\u03b6\u03b9\u03bd\u03c4\u03c3\u03b9"
    ],
    "name:fra_x_preferred":[
        "Gornji Bo\u017einci"
    ],
    "name:hrv_x_preferred":[
        "Gornji Bo\u017einci"
    ],
    "name:rus_x_preferred":[
        "\u0413\u043e\u0440\u043d\u0438-\u0411\u043e\u0436\u0438\u043d\u0446\u0438"
    ],
    "name:srp_x_preferred":[
        "\u0413\u043e\u0440\u045a\u0438 \u0411\u043e\u0436\u0438\u043d\u0446\u0438"
    ],
    "name:swe_x_preferred":[
        "Gornji Bozinci"
    ],
    "name:und_x_variant":[
        "Katoli\u010dki Bo\u017einci"
    ],
    "wof:name":"Gornji Bozinci",
    "wof:placetype":"locality"
},
  "geometry": {"coordinates":[18.05495,44.94841],"type":"Point"}
}