{
  "type": "Feature",
  "properties": {
    "gn:admin1_code":"01",
    "gn:asciiname":"Kriz",
    "gn:country_code":"BA",
    "gn:dem":239,
    "gn:feature_class":"P",
    "gn:feature_code":"PPL",
    "gn:name":"Kri\u017e",
    "gn:population":0,
    "gn:timezone":"Europe/Sarajevo",
    "iso:country":"BA",
    "name:ceb_x_preferred":[
        "Kriz"
    ],
    "name:deu_x_preferred":[
        "Kriz"
    ],
    "name:nds_x_preferred":[
        "Kriz"
    ],
    "name:slk_x_preferred":[
        "Kr\u00ed\u017e"
    ],
    "name:swe_x_preferred":[
        "Kriz"
    ],
    "wof:name":"Kriz",
    "wof:placetype":"locality"
},
  "geometry": {"coordinates":[15.8567,44.80358],"type":"Point"}
}