{
  "type": "Feature",
  "properties": {
    "gn:admin1_code":"02",
    "gn:asciiname":"Falovici",
    "gn:country_code":"BA",
    "gn:dem":532,
    "gn:feature_class":"P",
    "gn:feature_code":"PPL",
    "gn:name":"Falovi\u0107i",
    "gn:population":0,
    "gn:timezone":"Europe/Sarajevo",
    "iso:country":"BA",
    "wof:name":"Falovici",
    "wof:placetype":"locality"
},
  "geometry": {"coordinates":[18.88542,43.48362],"type":"Point"}
}