{
  "type": "Feature",
  "properties": {
    "gn:admin1_code":"02",
    "gn:asciiname":"Baljvine",
    "gn:country_code":"BA",
    "gn:dem":565,
    "gn:feature_class":"P",
    "gn:feature_code":"PPLL",
    "gn:name":"Baljvine",
    "gn:population":0,
    "gn:timezone":"Europe/Sarajevo",
    "iso:country":"BA",
    "name:bos_x_preferred":[
        "Baljvine"
    ],
    "name:fra_x_preferred":[
        "Baljvine"
    ],
    "name:hrv_x_preferred":[
        "Baljvine"
    ],
    "name:srp_x_preferred":[
        "\u0411\u0430\u0459\u0432\u0438\u043d\u0435"
    ],
    "name:swe_x_preferred":[
        "Baljvine"
    ],
    "wof:name":"Baljvine",
    "wof:placetype":"locality"
},
  "geometry": {"coordinates":[17.20373,44.47951],"type":"Point"}
}