{
  "type": "Feature",
  "properties": {
    "gn:admin1_code":"02",
    "gn:asciiname":"Baljvine",
    "gn:country_code":"BA",
    "gn:dem":565,
    "gn:feature_class":"P",
    "gn:feature_code":"PPLL",
    "gn:name":"Baljvine",
    "gn:population":0,
    "gn:timezone":"Europe/Sarajevo",
    "iso:country":"BA",
    "wof:name":"Baljvine",
    "wof:placetype":"locality"
},
  "geometry": {"coordinates":[17.20373,44.47951],"type":"Point"}
}