{
  "type": "Feature",
  "properties": {
    "gn:admin1_code":"02",
    "gn:asciiname":"Podkamen",
    "gn:country_code":"BA",
    "gn:dem":874,
    "gn:feature_class":"P",
    "gn:feature_code":"PPL",
    "gn:name":"Podkamen",
    "gn:population":0,
    "gn:timezone":"Europe/Sarajevo",
    "iso:country":"BA",
    "wof:name":"Podkamen",
    "wof:placetype":"locality"
},
  "geometry": {"coordinates":[19.07792,43.56797],"type":"Point"}
}