{
  "type": "Feature",
  "properties": {
    "gn:admin1_code":"02",
    "gn:asciiname":"Veoca",
    "gn:country_code":"BA",
    "gn:dem":308,
    "gn:feature_class":"P",
    "gn:feature_code":"PPL",
    "gn:name":"Veo\u010da",
    "gn:population":0,
    "gn:timezone":"Europe/Sarajevo",
    "iso:country":"BA",
    "wof:name":"Veoca",
    "wof:placetype":"locality"
},
  "geometry": {"coordinates":[19.08695,44.31781],"type":"Point"}
}