{
  "type": "Feature",
  "properties": {
    "gn:admin1_code":"01",
    "gn:asciiname":"Grabovice",
    "gn:country_code":"BA",
    "gn:dem":427,
    "gn:feature_class":"P",
    "gn:feature_code":"PPL",
    "gn:name":"Grabovice",
    "gn:population":0,
    "gn:timezone":"Europe/Sarajevo",
    "iso:country":"BA",
    "name:und_x_variant":[
        "Grabovica",
        "Grabovice"
    ],
    "wof:name":"Grabovice",
    "wof:placetype":"locality"
},
  "geometry": {"coordinates":[18.96044,44.48367],"type":"Point"}
}