{
  "type": "Feature",
  "properties": {
    "gn:admin1_code":"02",
    "gn:asciiname":"Vranic",
    "gn:country_code":"BA",
    "gn:dem":1119,
    "gn:feature_class":"P",
    "gn:feature_code":"PPL",
    "gn:name":"Vrani\u0107",
    "gn:population":0,
    "gn:timezone":"Europe/Sarajevo",
    "iso:country":"BA",
    "wof:name":"Vranic",
    "wof:placetype":"locality"
},
  "geometry": {"coordinates":[18.87417,43.42556],"type":"Point"}
}