{
  "type": "Feature",
  "properties": {
    "gn:admin1_code":"01",
    "gn:asciiname":"Skucani Vakuf",
    "gn:country_code":"BA",
    "gn:dem":398,
    "gn:feature_class":"P",
    "gn:feature_code":"PPLL",
    "gn:name":"Skucani Vakuf",
    "gn:population":0,
    "gn:timezone":"Europe/Sarajevo",
    "iso:country":"BA",
    "wof:name":"Skucani Vakuf",
    "wof:placetype":"locality"
},
  "geometry": {"coordinates":[16.45999,44.78395],"type":"Point"}
}