{
  "type": "Feature",
  "properties": {
    "gn:admin1_code":"02",
    "gn:asciiname":"Lug Gumjera",
    "gn:country_code":"BA",
    "gn:dem":119,
    "gn:feature_class":"P",
    "gn:feature_code":"PPL",
    "gn:name":"Lug Gumjera",
    "gn:population":0,
    "gn:timezone":"Europe/Sarajevo",
    "iso:country":"BA",
    "wof:name":"Lug Gumjera",
    "wof:placetype":"locality"
},
  "geometry": {"coordinates":[17.3905,44.92434],"type":"Point"}
}