{
  "type": "Feature",
  "properties": {
    "gn:admin1_code":"02",
    "gn:asciiname":"Vojnoge",
    "gn:country_code":"BA",
    "gn:dem":415,
    "gn:feature_class":"P",
    "gn:feature_code":"PPL",
    "gn:name":"Vojnoge",
    "gn:population":0,
    "gn:timezone":"Europe/Sarajevo",
    "iso:country":"BA",
    "wof:name":"Vojnoge",
    "wof:placetype":"locality"
},
  "geometry": {"coordinates":[18.7954,43.49822],"type":"Point"}
}