{
  "type": "Feature",
  "properties": {
    "gn:admin1_code":"01",
    "gn:asciiname":"Gunjace",
    "gn:country_code":"BA",
    "gn:dem":474,
    "gn:feature_class":"P",
    "gn:feature_code":"PPL",
    "gn:name":"Gunja\u010de",
    "gn:population":0,
    "gn:timezone":"Europe/Sarajevo",
    "iso:country":"BA",
    "wof:name":"Gunjace",
    "wof:placetype":"locality"
},
  "geometry": {"coordinates":[18.09612000000001,44.03356],"type":"Point"}
}