{
  "type": "Feature",
  "properties": {
    "gn:admin1_code":"01",
    "gn:asciiname":"Ravnice",
    "gn:country_code":"BA",
    "gn:dem":290,
    "gn:feature_class":"P",
    "gn:feature_code":"PPLL",
    "gn:name":"Ravnice",
    "gn:population":0,
    "gn:timezone":"Europe/Sarajevo",
    "iso:country":"BA",
    "wof:name":"Ravnice",
    "wof:placetype":"locality"
},
  "geometry": {"coordinates":[16.09204,45.09637],"type":"Point"}
}