{
  "type": "Feature",
  "properties": {
    "gn:admin1_code":"01",
    "gn:asciiname":"Ravnice",
    "gn:country_code":"BA",
    "gn:dem":290,
    "gn:feature_class":"P",
    "gn:feature_code":"PPLL",
    "gn:name":"Ravnice",
    "gn:population":0,
    "gn:timezone":"Europe/Sarajevo",
    "iso:country":"BA",
    "name:bos_x_preferred":[
        "Ravnice"
    ],
    "name:ceb_x_preferred":[
        "Ravnice"
    ],
    "name:fra_x_preferred":[
        "Ravnice"
    ],
    "name:hrv_x_preferred":[
        "Ravnice"
    ],
    "name:hun_x_preferred":[
        "Ravnice"
    ],
    "name:nld_x_preferred":[
        "Ravnice"
    ],
    "name:slv_x_preferred":[
        "Ravnice"
    ],
    "name:swe_x_preferred":[
        "Ravnice"
    ],
    "wof:name":"Ravnice",
    "wof:placetype":"locality"
},
  "geometry": {"coordinates":[16.09204,45.09637],"type":"Point"}
}