{
  "type": "Feature",
  "properties": {
    "gn:admin1_code":"02",
    "gn:asciiname":"Lukici",
    "gn:country_code":"BA",
    "gn:dem":102,
    "gn:feature_class":"P",
    "gn:feature_code":"PPL",
    "gn:name":"Luki\u0107i",
    "gn:population":0,
    "gn:timezone":"Europe/Sarajevo",
    "iso:country":"BA",
    "wof:name":"Lukici",
    "wof:placetype":"locality"
},
  "geometry": {"coordinates":[17.24562,45.04436],"type":"Point"}
}