{
  "type": "Feature",
  "properties": {
    "gn:admin1_code":"01",
    "gn:asciiname":"Svinjasnica",
    "gn:country_code":"BA",
    "gn:dem":427,
    "gn:feature_class":"P",
    "gn:feature_code":"PPLL",
    "gn:name":"Svinja\u0161nica",
    "gn:population":0,
    "gn:timezone":"Europe/Sarajevo",
    "iso:country":"BA",
    "wof:name":"Svinjasnica",
    "wof:placetype":"locality"
},
  "geometry": {"coordinates":[18.29476,44.44703],"type":"Point"}
}