{
  "type": "Feature",
  "properties": {
    "gn:admin1_code":"01",
    "gn:asciiname":"Dizdarevici",
    "gn:country_code":"BA",
    "gn:dem":221,
    "gn:feature_class":"P",
    "gn:feature_code":"PPL",
    "gn:name":"Dizdarevi\u0107i",
    "gn:population":0,
    "gn:timezone":"Europe/Sarajevo",
    "iso:country":"BA",
    "name:und_x_variant":[
        "Dizdarevica",
        "Dizdarevi\u0107i"
    ],
    "wof:name":"Dizdarevici",
    "wof:placetype":"locality"
},
  "geometry": {"coordinates":[15.91455,45.14403],"type":"Point"}
}