{
  "type": "Feature",
  "properties": {
    "gn:admin1_code":"01",
    "gn:asciiname":"Castovici",
    "gn:country_code":"BA",
    "gn:dem":509,
    "gn:feature_class":"P",
    "gn:feature_code":"PPL",
    "gn:name":"\u010castovi\u0107i",
    "gn:population":0,
    "gn:timezone":"Europe/Sarajevo",
    "iso:country":"BA",
    "wof:name":"Castovici",
    "wof:placetype":"locality"
},
  "geometry": {"coordinates":[16.73871,44.52989],"type":"Point"}
}