{
  "type": "Feature",
  "properties": {
    "gn:country":"BA",
    "gn:fcode":"PPLL",
    "gn:population":8210,
    "iso:country":"BA",
    "name:bos_x_preferred":[
        "Mili\u0107i"
    ],
    "name:ceb_x_preferred":[
        "Mili\u0107i"
    ],
    "name:eng_x_preferred":[
        "Mili\u0107i"
    ],
    "name:fra_x_preferred":[
        "Mili\u0107i"
    ],
    "name:nld_x_preferred":[
        "Mili\u0107i"
    ],
    "name:pol_x_preferred":[
        "Mili\u0107i"
    ],
    "name:slv_x_preferred":[
        "Mili\u0107i"
    ],
    "name:srp_x_preferred":[
        "\u041c\u0438\u043b\u0438\u045b\u0438"
    ],
    "name:swe_x_preferred":[
        "Mili\u0107i"
    ],
    "name:ukr_x_preferred":[
        "\u041c\u0438\u043b\u0438\u0447\u0456"
    ],
    "qs:name":"Mili\u0107i",
    "qs:photos_9r":0,
    "qs:photos_sr":0,
    "qs:pop_sr":"5",
    "wd:wordcount":36,
    "wof:name":"Mili\u0107i",
    "wof:placetype":"locality",
    "wof:population":8210
},
  "geometry": {"coordinates":[19.09195,44.17016],"type":"Point"}
}