{
  "type": "Feature",
  "properties": {
    "gn:country":"BA",
    "gn:fcode":"PPLL",
    "gn:pop":8210,
    "iso:country":"BA",
    "qs:name":"Mili\u0107i",
    "qs:photos_9r":0,
    "qs:photos_sr":0,
    "qs:pop_sr":"5",
    "wd:wordcount":36,
    "wof:name":"Mili\u0107i",
    "wof:placetype":"locality",
    "wof:population":8210
},
  "geometry": {"coordinates":[19.09195,44.17016],"type":"Point"}
}