{
  "type": "Feature",
  "properties": {
    "gn:admin1_code":"02",
    "gn:asciiname":"Mostanica",
    "gn:country_code":"BA",
    "gn:dem":193,
    "gn:feature_class":"P",
    "gn:feature_code":"PPL",
    "gn:name":"Mo\u0161tanica",
    "gn:population":0,
    "gn:timezone":"Europe/Sarajevo",
    "iso:country":"BA",
    "name:rus_x_preferred":[
        "\u041c\u043e\u0448\u0442\u0430\u043d\u0438\u0446\u0430"
    ],
    "name:srp_x_preferred":[
        "\u041c\u043e\u0448\u0442\u0430\u043d\u0438\u0446\u0430"
    ],
    "name:und_x_variant":[
        "Mo\u0161tanica"
    ],
    "wof:name":"Mostanica",
    "wof:placetype":"locality"
},
  "geometry": {"coordinates":[16.85724,45.0898],"type":"Point"}
}