{
  "type": "Feature",
  "properties": {
    "gn:admin1_code":"02",
    "gn:asciiname":"Sastavci",
    "gn:country_code":"BA",
    "gn:dem":404,
    "gn:feature_class":"P",
    "gn:feature_code":"PPL",
    "gn:name":"Sastavci",
    "gn:population":0,
    "gn:timezone":"Europe/Sarajevo",
    "iso:country":"BA",
    "name:ceb_x_preferred":[
        "Sastavci"
    ],
    "name:ces_x_preferred":[
        "Sastavci"
    ],
    "name:deu_x_preferred":[
        "Sastavci"
    ],
    "name:fra_x_preferred":[
        "Sastavci"
    ],
    "name:ita_x_preferred":[
        "Sastavci"
    ],
    "name:pol_x_preferred":[
        "Sastavci"
    ],
    "name:slk_x_preferred":[
        "Sastavci"
    ],
    "name:srp_x_preferred":[
        "\u0421\u0430\u0441\u0442\u0430\u0432\u0446\u0438"
    ],
    "name:swe_x_preferred":[
        "Sastavci"
    ],
    "wof:name":"Sastavci",
    "wof:placetype":"locality"
},
  "geometry": {"coordinates":[19.42639,43.55722],"type":"Point"}
}