{
  "type": "Feature",
  "properties": {
    "gn:admin1_code":"00",
    "gn:asciiname":"Banovici Selo",
    "gn:country_code":"BA",
    "gn:dem":450,
    "gn:feature_class":"P",
    "gn:feature_code":"PPL",
    "gn:name":"Banovi\u0107i Selo",
    "gn:population":0,
    "gn:timezone":"Europe/Sarajevo",
    "iso:country":"BA",
    "name:und_x_variant":[
        "Banovi\u0107i",
        "Banovi\u0107i Selo"
    ],
    "wof:name":"Banovici Selo",
    "wof:placetype":"locality"
},
  "geometry": {"coordinates":[18.44176,44.40277],"type":"Point"}
}