{
  "type": "Feature",
  "properties": {
    "gn:admin1_code":"00",
    "gn:asciiname":"Banovici Selo",
    "gn:country_code":"BA",
    "gn:dem":450,
    "gn:feature_class":"P",
    "gn:feature_code":"PPL",
    "gn:name":"Banovi\u0107i Selo",
    "gn:population":0,
    "gn:timezone":"Europe/Sarajevo",
    "iso:country":"BA",
    "name:ara_x_preferred":[
        "\u0628\u0627\u0646\u0648\u0641\u064a\u062a\u0634\u064a \u0633\u064a\u0644\u0648"
    ],
    "name:bos_x_preferred":[
        "Banovi\u0107i Selo"
    ],
    "name:ceb_x_preferred":[
        "Banovi\u0107i Selo"
    ],
    "name:fra_x_preferred":[
        "Banovi\u0107i Selo"
    ],
    "name:hrv_x_preferred":[
        "Banovi\u0107i"
    ],
    "name:slv_x_preferred":[
        "Banovi\u0107i Selo"
    ],
    "name:srp_x_preferred":[
        "\u0411\u0430\u043d\u043e\u0432\u0438\u045b\u0438"
    ],
    "name:swe_x_preferred":[
        "Banovi\u0107i Selo"
    ],
    "name:und_x_variant":[
        "Banovi\u0107i",
        "Banovi\u0107i Selo"
    ],
    "name:urd_x_preferred":[
        "\u0628\u0627\u0646\u0648\u0648\u06cc\u0686\u06cc"
    ],
    "wof:name":"Banovici Selo",
    "wof:placetype":"locality"
},
  "geometry": {"coordinates":[18.44176,44.40277],"type":"Point"}
}