{
  "type": "Feature",
  "properties": {
    "gn:admin1_code":"02",
    "gn:asciiname":"Suzici",
    "gn:country_code":"BA",
    "gn:dem":344,
    "gn:feature_class":"P",
    "gn:feature_code":"PPL",
    "gn:name":"Suzi\u0107i",
    "gn:population":0,
    "gn:timezone":"Europe/Sarajevo",
    "iso:country":"BA",
    "wof:name":"Suzici",
    "wof:placetype":"locality"
},
  "geometry": {"coordinates":[16.54519,45.07699],"type":"Point"}
}