{
  "type": "Feature",
  "properties": {
    "gn:admin1_code":"02",
    "gn:asciiname":"Jankovici",
    "gn:country_code":"BA",
    "gn:dem":386,
    "gn:feature_class":"P",
    "gn:feature_code":"PPL",
    "gn:name":"Jankovi\u0107i",
    "gn:population":0,
    "gn:timezone":"Europe/Sarajevo",
    "iso:country":"BA",
    "wof:name":"Jankovici",
    "wof:placetype":"locality"
},
  "geometry": {"coordinates":[19.10511,44.57787],"type":"Point"}
}