{
  "type": "Feature",
  "properties": {
    "gn:admin1_code":"02",
    "gn:asciiname":"Zabrezje",
    "gn:country_code":"BA",
    "gn:dem":1163,
    "gn:feature_class":"P",
    "gn:feature_code":"PPL",
    "gn:name":"Zabre\u017eje",
    "gn:population":0,
    "gn:timezone":"Europe/Sarajevo",
    "iso:country":"BA",
    "wof:name":"Zabrezje",
    "wof:placetype":"locality"
},
  "geometry": {"coordinates":[19.03347,43.94798],"type":"Point"}
}