{
  "type": "Feature",
  "properties": {
    "gn:admin1_code":"01",
    "gn:asciiname":"Rodici",
    "gn:country_code":"BA",
    "gn:dem":381,
    "gn:feature_class":"P",
    "gn:feature_code":"PPL",
    "gn:name":"Rodi\u0107i",
    "gn:population":0,
    "gn:timezone":"Europe/Sarajevo",
    "iso:country":"BA",
    "wof:name":"Rodici",
    "wof:placetype":"locality"
},
  "geometry": {"coordinates":[16.48914,44.78694],"type":"Point"}
}