{
  "type": "Feature",
  "properties": {
    "gn:admin1_code":"02",
    "gn:asciiname":"Krusevo Brdo",
    "gn:country_code":"BA",
    "gn:dem":925,
    "gn:feature_class":"P",
    "gn:feature_code":"PPLL",
    "gn:name":"Kru\u0161evo Brdo",
    "gn:population":0,
    "gn:timezone":"Europe/Sarajevo",
    "iso:country":"BA",
    "wof:name":"Krusevo Brdo",
    "wof:placetype":"locality"
},
  "geometry": {"coordinates":[17.63045,44.41135],"type":"Point"}
}