{
  "type": "Feature",
  "properties": {
    "gn:admin1_code":"02",
    "gn:asciiname":"Pilipovici",
    "gn:country_code":"BA",
    "gn:dem":311,
    "gn:feature_class":"P",
    "gn:feature_code":"PPL",
    "gn:name":"Pilipovi\u0107i",
    "gn:population":0,
    "gn:timezone":"Europe/Sarajevo",
    "iso:country":"BA",
    "wof:name":"Pilipovici",
    "wof:placetype":"locality"
},
  "geometry": {"coordinates":[16.64,45.05056],"type":"Point"}
}