{
  "type": "Feature",
  "properties": {
    "gn:admin1_code":"02",
    "gn:asciiname":"Konopljista",
    "gn:country_code":"BA",
    "gn:dem":495,
    "gn:feature_class":"P",
    "gn:feature_code":"PPLL",
    "gn:name":"Konoplji\u0161ta",
    "gn:population":0,
    "gn:timezone":"Europe/Sarajevo",
    "iso:country":"BA",
    "name:und_x_variant":[
        "Donje Konopljiste",
        "Konopljiste",
        "Gornje Konopljiste",
        "Konoplji\u0161ta"
    ],
    "wof:name":"Konopljista",
    "wof:placetype":"locality"
},
  "geometry": {"coordinates":[18.17982,44.64748],"type":"Point"}
}