{
  "type": "Feature",
  "properties": {
    "gn:admin1_code":"02",
    "gn:asciiname":"Kozja Luka",
    "gn:country_code":"BA",
    "gn:dem":507,
    "gn:feature_class":"P",
    "gn:feature_code":"PPLL",
    "gn:name":"Kozja Luka",
    "gn:population":0,
    "gn:timezone":"Europe/Sarajevo",
    "iso:country":"BA",
    "wof:name":"Kozja Luka",
    "wof:placetype":"locality"
},
  "geometry": {"coordinates":[18.69905,43.54584000000001],"type":"Point"}
}