{
  "type": "Feature",
  "properties": {
    "gn:admin1_code":"02",
    "gn:asciiname":"Rapta",
    "gn:country_code":"BA",
    "gn:dem":707,
    "gn:feature_class":"P",
    "gn:feature_code":"PPL",
    "gn:name":"Rapta",
    "gn:population":0,
    "gn:timezone":"Europe/Sarajevo",
    "iso:country":"BA",
    "wof:name":"Rapta",
    "wof:placetype":"locality"
},
  "geometry": {"coordinates":[17.2687,44.54695],"type":"Point"}
}