{
  "type": "Feature",
  "properties": {
    "gn:admin1_code":"01",
    "gn:asciiname":"Kosova",
    "gn:country_code":"BA",
    "gn:dem":316,
    "gn:feature_class":"P",
    "gn:feature_code":"PPLL",
    "gn:name":"Kosova",
    "gn:population":0,
    "gn:timezone":"Europe/Sarajevo",
    "iso:country":"BA",
    "wof:name":"Kosova",
    "wof:placetype":"locality"
},
  "geometry": {"coordinates":[18.0774,44.61993],"type":"Point"}
}