{
  "type": "Feature",
  "properties": {
    "gn:admin1_code":"01",
    "gn:asciiname":"Goles",
    "gn:country_code":"BA",
    "gn:dem":759,
    "gn:feature_class":"P",
    "gn:feature_code":"PPL",
    "gn:name":"Gole\u0161",
    "gn:population":0,
    "gn:timezone":"Europe/Sarajevo",
    "iso:country":"BA",
    "wof:name":"Goles",
    "wof:placetype":"locality"
},
  "geometry": {"coordinates":[17.5312,44.19335],"type":"Point"}
}