{
  "type": "Feature",
  "properties": {
    "gn:admin1_code":"02",
    "gn:asciiname":"Kolari",
    "gn:country_code":"BA",
    "gn:dem":626,
    "gn:feature_class":"P",
    "gn:feature_code":"PPL",
    "gn:name":"Kolari",
    "gn:population":0,
    "gn:timezone":"Europe/Sarajevo",
    "iso:country":"BA",
    "wof:name":"Kolari",
    "wof:placetype":"locality"
},
  "geometry": {"coordinates":[18.41111,43.74806],"type":"Point"}
}