{
  "type": "Feature",
  "properties": {
    "gn:admin1_code":"01",
    "gn:asciiname":"Gnjilista",
    "gn:country_code":"BA",
    "gn:dem":4,
    "gn:feature_class":"P",
    "gn:feature_code":"PPL",
    "gn:name":"Gnjili\u0161ta",
    "gn:population":0,
    "gn:timezone":"Europe/Sarajevo",
    "iso:country":"BA",
    "name:bos_x_preferred":[
        "Gnjili\u0161ta"
    ],
    "name:ceb_x_preferred":[
        "Gnjili\u0161ta"
    ],
    "name:fra_x_preferred":[
        "Gnjili\u0161ta"
    ],
    "name:hrv_x_preferred":[
        "Gnjili\u0161ta"
    ],
    "name:srp_x_preferred":[
        "\u0413\u045a\u0438\u043b\u0438\u0448\u0442\u0430"
    ],
    "name:swe_x_preferred":[
        "Gnjili\u0161ta"
    ],
    "name:und_x_variant":[
        "Gnjili\u0161ta"
    ],
    "wof:name":"Gnjilista",
    "wof:placetype":"locality"
},
  "geometry": {"coordinates":[17.73333,43.07694],"type":"Point"}
}