{
  "type": "Feature",
  "properties": {
    "gn:admin1_code":"02",
    "gn:asciiname":"Bozici",
    "gn:country_code":"BA",
    "gn:dem":656,
    "gn:feature_class":"P",
    "gn:feature_code":"PPL",
    "gn:name":"Bo\u017ei\u0107i",
    "gn:population":0,
    "gn:timezone":"Europe/Sarajevo",
    "iso:country":"BA",
    "wof:name":"Bozici",
    "wof:placetype":"locality"
},
  "geometry": {"coordinates":[17.19400000000001,44.3822],"type":"Point"}
}