{
  "type": "Feature",
  "properties": {
    "gn:admin1_code":"01",
    "gn:asciiname":"Gornji Vrljaj",
    "gn:country_code":"BA",
    "gn:dem":1033,
    "gn:feature_class":"P",
    "gn:feature_code":"PPL",
    "gn:name":"Gornji Vrljaj",
    "gn:population":0,
    "gn:timezone":"Europe/Sarajevo",
    "iso:country":"BA",
    "wof:name":"Gornji Vrljaj",
    "wof:placetype":"locality"
},
  "geometry": {"coordinates":[17.4621,44.22629000000001],"type":"Point"}
}