{
  "type": "Feature",
  "properties": {
    "gn:admin1_code":"02",
    "gn:asciiname":"Podjezero",
    "gn:country_code":"BA",
    "gn:dem":622,
    "gn:feature_class":"P",
    "gn:feature_code":"PPL",
    "gn:name":"Podjezero",
    "gn:population":0,
    "gn:timezone":"Europe/Sarajevo",
    "iso:country":"BA",
    "wof:name":"Podjezero",
    "wof:placetype":"locality"
},
  "geometry": {"coordinates":[19.44944,43.99917],"type":"Point"}
}