{
  "type": "Feature",
  "properties": {
    "gn:admin1_code":"02",
    "gn:asciiname":"Ljeskovac",
    "gn:country_code":"BA",
    "gn:dem":1016,
    "gn:feature_class":"P",
    "gn:feature_code":"PPL",
    "gn:name":"Ljeskovac",
    "gn:population":0,
    "gn:timezone":"Europe/Sarajevo",
    "iso:country":"BA",
    "name:bos_x_preferred":[
        "Ljeskovac"
    ],
    "name:ceb_x_preferred":[
        "Ljeskovac"
    ],
    "name:fra_x_preferred":[
        "Ljeskovac"
    ],
    "name:hrv_x_preferred":[
        "Ljeskovac"
    ],
    "name:rus_x_preferred":[
        "\u041b\u0435\u0441\u043a\u043e\u0432\u0430\u0446"
    ],
    "name:slv_x_preferred":[
        "Ljeskovac"
    ],
    "name:srp_x_preferred":[
        "\u0409\u0435\u0441\u043a\u043e\u0432\u0430\u0446"
    ],
    "name:swe_x_preferred":[
        "Ljeskovac"
    ],
    "wof:name":"Ljeskovac",
    "wof:placetype":"locality"
},
  "geometry": {"coordinates":[18.97393,44.06774],"type":"Point"}
}