{
  "type": "Feature",
  "properties": {
    "gn:admin1_code":"01",
    "gn:asciiname":"Bukovica",
    "gn:country_code":"BA",
    "gn:dem":949,
    "gn:feature_class":"P",
    "gn:feature_code":"PPL",
    "gn:name":"Bukovica",
    "gn:population":0,
    "gn:timezone":"Europe/Sarajevo",
    "iso:country":"BA",
    "wof:name":"Bukovica",
    "wof:placetype":"locality"
},
  "geometry": {"coordinates":[17.54417,43.78361],"type":"Point"}
}