{
  "type": "Feature",
  "properties": {
    "gn:admin1_code":"02",
    "gn:asciiname":"Jazbine",
    "gn:country_code":"BA",
    "gn:dem":362,
    "gn:feature_class":"P",
    "gn:feature_code":"PPL",
    "gn:name":"Jazbine",
    "gn:population":0,
    "gn:timezone":"Europe/Sarajevo",
    "iso:country":"BA",
    "wof:name":"Jazbine",
    "wof:placetype":"locality"
},
  "geometry": {"coordinates":[19.22103,44.19884],"type":"Point"}
}