{
  "type": "Feature",
  "properties": {
    "gn:admin1_code":"02",
    "gn:asciiname":"Miljanici",
    "gn:country_code":"BA",
    "gn:dem":659,
    "gn:feature_class":"P",
    "gn:feature_code":"PPL",
    "gn:name":"Miljani\u0107i",
    "gn:population":0,
    "gn:timezone":"Europe/Sarajevo",
    "iso:country":"BA",
    "wof:name":"Miljanici",
    "wof:placetype":"locality"
},
  "geometry": {"coordinates":[18.90333,44.18161],"type":"Point"}
}