{
  "type": "Feature",
  "properties": {
    "gn:admin1_code":"02",
    "gn:asciiname":"Cadavica Gornja",
    "gn:country_code":"BA",
    "gn:dem":167,
    "gn:feature_class":"P",
    "gn:feature_code":"PPL",
    "gn:name":"\u010ca\u0111avica Gornja",
    "gn:population":0,
    "gn:timezone":"Europe/Sarajevo",
    "iso:country":"BA",
    "name:bos_x_preferred":[
        "\u010ca\u0111avica Gornja"
    ],
    "name:ceb_x_preferred":[
        "\u010ca\u0111avica Gornja"
    ],
    "name:fra_x_preferred":[
        "\u010ca\u0111avica Gornja"
    ],
    "name:hrv_x_preferred":[
        "\u010ca\u0111avica Gornja"
    ],
    "name:srp_x_preferred":[
        "\u0427\u0430\u0452\u0430\u0432\u0438\u0446\u0430 \u0413\u043e\u0440\u045a\u0430"
    ],
    "name:swe_x_preferred":[
        "\u010ca\u0111avica Gornja"
    ],
    "name:und_x_variant":[
        "Gornja \u010cadjavica",
        "\u010ca\u0111evica Gornja",
        "\u010ca\u0111avica Gornja"
    ],
    "wof:name":"Cadavica Gornja",
    "wof:placetype":"locality"
},
  "geometry": {"coordinates":[16.37059,44.96257],"type":"Point"}
}