{
  "type": "Feature",
  "properties": {
    "gn:admin1_code":"02",
    "gn:asciiname":"Cadavica Gornja",
    "gn:country_code":"BA",
    "gn:dem":167,
    "gn:feature_class":"P",
    "gn:feature_code":"PPL",
    "gn:name":"\u010ca\u0111avica Gornja",
    "gn:population":0,
    "gn:timezone":"Europe/Sarajevo",
    "iso:country":"BA",
    "name:und_x_variant":[
        "Gornja \u010cadjavica",
        "\u010ca\u0111evica Gornja",
        "\u010ca\u0111avica Gornja"
    ],
    "wof:name":"Cadavica Gornja",
    "wof:placetype":"locality"
},
  "geometry": {"coordinates":[16.37059,44.96257],"type":"Point"}
}