{
  "type": "Feature",
  "properties": {
    "gn:admin1_code":"02",
    "gn:asciiname":"Zausje",
    "gn:country_code":"BA",
    "gn:dem":646,
    "gn:feature_class":"P",
    "gn:feature_code":"PPLL",
    "gn:name":"Zau\u0161je",
    "gn:population":0,
    "gn:timezone":"Europe/Sarajevo",
    "iso:country":"BA",
    "wof:name":"Zausje",
    "wof:placetype":"locality"
},
  "geometry": {"coordinates":[18.39553,42.91663],"type":"Point"}
}