{
  "type": "Feature",
  "properties": {
    "gn:admin1_code":"00",
    "gn:asciiname":"Gledinovac",
    "gn:country_code":"BA",
    "gn:dem":976,
    "gn:feature_class":"P",
    "gn:feature_code":"PPL",
    "gn:name":"Gledinovac",
    "gn:population":0,
    "gn:timezone":"Europe/Sarajevo",
    "iso:country":"BA",
    "wof:name":"Gledinovac",
    "wof:placetype":"locality"
},
  "geometry": {"coordinates":[18.54056,43.82417],"type":"Point"}
}