{
  "type": "Feature",
  "properties": {
    "gn:admin1_code":"01",
    "gn:asciiname":"Grljevici",
    "gn:country_code":"BA",
    "gn:dem":267,
    "gn:feature_class":"P",
    "gn:feature_code":"PPLL",
    "gn:name":"Grljevi\u0107i",
    "gn:population":0,
    "gn:timezone":"Europe/Sarajevo",
    "iso:country":"BA",
    "name:und_x_variant":[
        "Grlevi\u0107i",
        "Grljevi\u0107i"
    ],
    "wof:name":"Grljevici",
    "wof:placetype":"locality"
},
  "geometry": {"coordinates":[17.5105,43.27823],"type":"Point"}
}