{
  "type": "Feature",
  "properties": {
    "gn:admin1_code":"01",
    "gn:asciiname":"Nestici",
    "gn:country_code":"BA",
    "gn:dem":861,
    "gn:feature_class":"P",
    "gn:feature_code":"PPL",
    "gn:name":"Nesti\u0107i",
    "gn:population":0,
    "gn:timezone":"Europe/Sarajevo",
    "iso:country":"BA",
    "wof:name":"Nestici",
    "wof:placetype":"locality"
},
  "geometry": {"coordinates":[18.80879,43.6051],"type":"Point"}
}