{
  "type": "Feature",
  "properties": {
    "gn:admin1_code":"01",
    "gn:asciiname":"Donja Mionica",
    "gn:country_code":"BA",
    "gn:dem":150,
    "gn:feature_class":"P",
    "gn:feature_code":"PPLL",
    "gn:name":"Donja Mionica",
    "gn:population":0,
    "gn:timezone":"Europe/Sarajevo",
    "iso:country":"BA",
    "wof:name":"Donja Mionica",
    "wof:placetype":"locality"
},
  "geometry": {"coordinates":[18.50367,44.85025],"type":"Point"}
}