{
  "type": "Feature",
  "properties": {
    "gn:admin1_code":"02",
    "gn:asciiname":"Markovici",
    "gn:country_code":"BA",
    "gn:dem":723,
    "gn:feature_class":"P",
    "gn:feature_code":"PPL",
    "gn:name":"Markovi\u0107i",
    "gn:population":0,
    "gn:timezone":"Europe/Sarajevo",
    "iso:country":"BA",
    "wof:name":"Markovici",
    "wof:placetype":"locality"
},
  "geometry": {"coordinates":[17.64056,44.52464000000001],"type":"Point"}
}