{
  "type": "Feature",
  "properties": {
    "gn:admin1_code":"02",
    "gn:asciiname":"Stedra",
    "gn:country_code":"BA",
    "gn:dem":478,
    "gn:feature_class":"P",
    "gn:feature_code":"PPL",
    "gn:name":"\u0160tedra",
    "gn:population":0,
    "gn:timezone":"Europe/Sarajevo",
    "iso:country":"BA",
    "wof:name":"Stedra",
    "wof:placetype":"locality"
},
  "geometry": {"coordinates":[19.1401,44.09307],"type":"Point"}
}