{
  "type": "Feature",
  "properties": {
    "gn:admin1_code":"02",
    "gn:asciiname":"Knezici",
    "gn:country_code":"BA",
    "gn:dem":1252,
    "gn:feature_class":"P",
    "gn:feature_code":"PPL",
    "gn:name":"Kne\u017ei\u0107i",
    "gn:population":0,
    "gn:timezone":"Europe/Sarajevo",
    "iso:country":"BA",
    "wof:name":"Knezici",
    "wof:placetype":"locality"
},
  "geometry": {"coordinates":[17.11572,44.105],"type":"Point"}
}