{
  "type": "Feature",
  "properties": {
    "gn:admin1_code":"01",
    "gn:asciiname":"Lepirice",
    "gn:country_code":"BA",
    "gn:dem":259,
    "gn:feature_class":"P",
    "gn:feature_code":"PPL",
    "gn:name":"Lepirice",
    "gn:population":0,
    "gn:timezone":"Europe/Sarajevo",
    "iso:country":"BA",
    "wof:name":"Lepirice",
    "wof:placetype":"locality"
},
  "geometry": {"coordinates":[16.82137,44.50991],"type":"Point"}
}