{
  "type": "Feature",
  "properties": {
    "gn:admin1_code":"01",
    "gn:asciiname":"Zapoljak",
    "gn:country_code":"BA",
    "gn:dem":484,
    "gn:feature_class":"P",
    "gn:feature_code":"PPL",
    "gn:name":"Zapoljak",
    "gn:population":0,
    "gn:timezone":"Europe/Sarajevo",
    "iso:country":"BA",
    "name:bos_x_preferred":[
        "Zapoljak"
    ],
    "name:hrv_x_preferred":[
        "Zapoljak"
    ],
    "name:hun_x_preferred":[
        "Zapoljak"
    ],
    "name:nld_x_preferred":[
        "Zapoljak"
    ],
    "name:slv_x_preferred":[
        "Zapoljak"
    ],
    "name:spa_x_preferred":[
        "Zapoljak"
    ],
    "name:srp_x_preferred":[
        "\u0417\u0430\u043f\u043e\u0459\u0430\u043a"
    ],
    "name:ukr_x_preferred":[
        "\u0417\u0430\u043f\u043e\u043b\u044f\u043a"
    ],
    "wof:name":"Zapoljak",
    "wof:placetype":"locality"
},
  "geometry": {"coordinates":[15.96913,44.77784000000001],"type":"Point"}
}