{
  "type": "Feature",
  "properties": {
    "gn:admin1_code":"01",
    "gn:asciiname":"Zapoljak",
    "gn:country_code":"BA",
    "gn:dem":484,
    "gn:feature_class":"P",
    "gn:feature_code":"PPL",
    "gn:name":"Zapoljak",
    "gn:population":0,
    "gn:timezone":"Europe/Sarajevo",
    "iso:country":"BA",
    "wof:name":"Zapoljak",
    "wof:placetype":"locality"
},
  "geometry": {"coordinates":[15.96913,44.77784000000001],"type":"Point"}
}