{
  "type": "Feature",
  "properties": {
    "gn:admin1_code":"01",
    "gn:asciiname":"Cerov Dolac",
    "gn:country_code":"BA",
    "gn:dem":250,
    "gn:feature_class":"P",
    "gn:feature_code":"PPL",
    "gn:name":"Cerov Dolac",
    "gn:population":0,
    "gn:timezone":"Europe/Sarajevo",
    "iso:country":"BA",
    "wof:name":"Cerov Dolac",
    "wof:placetype":"locality"
},
  "geometry": {"coordinates":[17.44182,43.32143],"type":"Point"}
}