{
  "type": "Feature",
  "properties": {
    "gn:admin1_code":"01",
    "gn:asciiname":"Drugavci",
    "gn:country_code":"BA",
    "gn:dem":556,
    "gn:feature_class":"P",
    "gn:feature_code":"PPL",
    "gn:name":"Drugavci",
    "gn:population":0,
    "gn:timezone":"Europe/Sarajevo",
    "iso:country":"BA",
    "name:bos_x_preferred":[
        "Drugavci"
    ],
    "name:fra_x_preferred":[
        "Drugavci"
    ],
    "name:hrv_x_preferred":[
        "Drugavci"
    ],
    "wof:name":"Drugavci",
    "wof:placetype":"locality"
},
  "geometry": {"coordinates":[18.00679,44.23857],"type":"Point"}
}