{
  "type": "Feature",
  "properties": {
    "gn:admin1_code":"01",
    "gn:asciiname":"Donja Mravljaca",
    "gn:country_code":"BA",
    "gn:dem":808,
    "gn:feature_class":"P",
    "gn:feature_code":"PPL",
    "gn:name":"Donja Mravlja\u010da",
    "gn:population":0,
    "gn:timezone":"Europe/Sarajevo",
    "iso:country":"BA",
    "wof:name":"Donja Mravljaca",
    "wof:placetype":"locality"
},
  "geometry": {"coordinates":[18.77221,43.61106],"type":"Point"}
}