{
  "type": "Feature",
  "properties": {
    "gn:admin1_code":"02",
    "gn:asciiname":"Grubori",
    "gn:country_code":"BA",
    "gn:dem":202,
    "gn:feature_class":"P",
    "gn:feature_code":"PPL",
    "gn:name":"Grubori",
    "gn:population":0,
    "gn:timezone":"Europe/Sarajevo",
    "iso:country":"BA",
    "wof:name":"Grubori",
    "wof:placetype":"locality"
},
  "geometry": {"coordinates":[16.44379,45.1021],"type":"Point"}
}