{
  "type": "Feature",
  "properties": {
    "gn:admin1_code":"01",
    "gn:asciiname":"Butila",
    "gn:country_code":"BA",
    "gn:dem":534,
    "gn:feature_class":"P",
    "gn:feature_code":"PPL",
    "gn:name":"Butila",
    "gn:population":0,
    "gn:timezone":"Europe/Sarajevo",
    "iso:country":"BA",
    "wof:name":"Butila",
    "wof:placetype":"locality"
},
  "geometry": {"coordinates":[18.27472,43.87139000000001],"type":"Point"}
}