{
  "type": "Feature",
  "properties": {
    "gn:admin1_code":"02",
    "gn:asciiname":"Milici",
    "gn:country_code":"BA",
    "gn:dem":920,
    "gn:feature_class":"P",
    "gn:feature_code":"PPL",
    "gn:name":"Mili\u0107i",
    "gn:population":0,
    "gn:timezone":"Europe/Sarajevo",
    "iso:country":"BA",
    "name:und_x_variant":[
        "Ljeskovci",
        "Mili\u0107i"
    ],
    "wof:name":"Milici",
    "wof:placetype":"locality"
},
  "geometry": {"coordinates":[18.31028,42.84874],"type":"Point"}
}