{
  "type": "Feature",
  "properties": {
    "gn:admin1_code":"02",
    "gn:asciiname":"Vukovici",
    "gn:country_code":"BA",
    "gn:dem":986,
    "gn:feature_class":"P",
    "gn:feature_code":"PPL",
    "gn:name":"Vukovi\u0107i",
    "gn:population":0,
    "gn:timezone":"Europe/Sarajevo",
    "iso:country":"BA",
    "wof:name":"Vukovici",
    "wof:placetype":"locality"
},
  "geometry": {"coordinates":[17.29246,44.45823],"type":"Point"}
}