{
  "type": "Feature",
  "properties": {
    "gn:admin1_code":"01",
    "gn:asciiname":"Mandino Selo",
    "gn:country_code":"BA",
    "gn:dem":873,
    "gn:feature_class":"P",
    "gn:feature_code":"PPL",
    "gn:name":"Mandino Selo",
    "gn:population":0,
    "gn:timezone":"Europe/Sarajevo",
    "iso:country":"BA",
    "wof:name":"Mandino Selo",
    "wof:placetype":"locality"
},
  "geometry": {"coordinates":[17.30972,43.6825],"type":"Point"}
}