{
  "type": "Feature",
  "properties": {
    "gn:admin1_code":"01",
    "gn:asciiname":"Mandino Selo",
    "gn:country_code":"BA",
    "gn:dem":873,
    "gn:feature_class":"P",
    "gn:feature_code":"PPL",
    "gn:name":"Mandino Selo",
    "gn:population":0,
    "gn:timezone":"Europe/Sarajevo",
    "iso:country":"BA",
    "name:bos_x_preferred":[
        "Mandino Selo"
    ],
    "name:ceb_x_preferred":[
        "Mandino Selo"
    ],
    "name:fra_x_preferred":[
        "Mandino Selo"
    ],
    "name:hrv_x_preferred":[
        "Mandino Selo"
    ],
    "name:srp_x_preferred":[
        "\u041c\u0430\u043d\u0434\u0438\u043d\u043e \u0421\u0435\u043b\u043e"
    ],
    "name:swe_x_preferred":[
        "Mandino Selo"
    ],
    "wof:name":"Mandino Selo",
    "wof:placetype":"locality"
},
  "geometry": {"coordinates":[17.30972,43.6825],"type":"Point"}
}