{
  "type": "Feature",
  "properties": {
    "gn:admin1_code":"02",
    "gn:asciiname":"Krna Jela",
    "gn:country_code":"BA",
    "gn:dem":1123,
    "gn:feature_class":"P",
    "gn:feature_code":"PPL",
    "gn:name":"Krna Jela",
    "gn:population":0,
    "gn:timezone":"Europe/Sarajevo",
    "iso:country":"BA",
    "name:bos_x_preferred":[
        "Krna Jela"
    ],
    "name:fra_x_preferred":[
        "Krna Jela"
    ],
    "name:hrv_x_preferred":[
        "Krna Jela"
    ],
    "name:srp_x_preferred":[
        "\u041a\u0440\u043d\u0430 \u0408\u0435\u043b\u0430"
    ],
    "wof:name":"Krna Jela",
    "wof:placetype":"locality"
},
  "geometry": {"coordinates":[18.60391,43.28579000000001],"type":"Point"}
}