{
  "type": "Feature",
  "properties": {
    "gn:admin1_code":"02",
    "gn:asciiname":"Velije",
    "gn:country_code":"BA",
    "gn:dem":444,
    "gn:feature_class":"P",
    "gn:feature_code":"PPLL",
    "gn:name":"Velije",
    "gn:population":0,
    "gn:timezone":"Europe/Sarajevo",
    "iso:country":"BA",
    "wof:name":"Velije",
    "wof:placetype":"locality"
},
  "geometry": {"coordinates":[16.84339,44.43443],"type":"Point"}
}