{
  "type": "Feature",
  "properties": {
    "gn:admin1_code":"02",
    "gn:asciiname":"Velije",
    "gn:country_code":"BA",
    "gn:dem":444,
    "gn:feature_class":"P",
    "gn:feature_code":"PPLL",
    "gn:name":"Velije",
    "gn:population":0,
    "gn:timezone":"Europe/Sarajevo",
    "iso:country":"BA",
    "name:bos_x_preferred":[
        "Velije"
    ],
    "name:ceb_x_preferred":[
        "Velije"
    ],
    "name:fas_x_preferred":[
        "\u0648\u0644\u06cc\u062c"
    ],
    "name:fra_x_preferred":[
        "Velije"
    ],
    "name:srp_x_preferred":[
        "\u0412\u0435\u043b\u0438\u0458\u0435"
    ],
    "name:swe_x_preferred":[
        "Velije"
    ],
    "wof:name":"Velije",
    "wof:placetype":"locality"
},
  "geometry": {"coordinates":[16.84339,44.43443],"type":"Point"}
}