{
  "type": "Feature",
  "properties": {
    "gn:admin1_code":"01",
    "gn:asciiname":"Kozarci",
    "gn:country_code":"BA",
    "gn:dem":453,
    "gn:feature_class":"P",
    "gn:feature_code":"PPL",
    "gn:name":"Kozarci",
    "gn:population":0,
    "gn:timezone":"Europe/Sarajevo",
    "iso:country":"BA",
    "wof:name":"Kozarci",
    "wof:placetype":"locality"
},
  "geometry": {"coordinates":[16.77004,44.59474],"type":"Point"}
}