{
  "type": "Feature",
  "properties": {
    "gn:admin1_code":"02",
    "gn:asciiname":"Trnovica",
    "gn:country_code":"BA",
    "gn:dem":628,
    "gn:feature_class":"P",
    "gn:feature_code":"PPLL",
    "gn:name":"Trnovica",
    "gn:population":0,
    "gn:timezone":"Europe/Sarajevo",
    "iso:country":"BA",
    "name:bos_x_preferred":[
        "Trnovica"
    ],
    "name:ceb_x_preferred":[
        "Trnovica"
    ],
    "name:fra_x_preferred":[
        "Trnovica"
    ],
    "name:hrv_x_preferred":[
        "Trnovica"
    ],
    "name:hun_x_preferred":[
        "Trnovica"
    ],
    "name:nld_x_preferred":[
        "Trnovica"
    ],
    "name:rus_x_preferred":[
        "\u0422\u0440\u043d\u043e\u0432\u0438\u0446\u0430"
    ],
    "name:slv_x_preferred":[
        "Trnovica"
    ],
    "name:srp_x_preferred":[
        "\u0422\u0440\u043d\u043e\u0432\u0438\u0446\u0430"
    ],
    "name:swe_x_preferred":[
        "Trnovica"
    ],
    "name:ukr_x_preferred":[
        "\u0422\u0440\u043d\u043e\u0432\u0438\u0446\u044f"
    ],
    "name:und_x_variant":[
        "Trnavica"
    ],
    "wof:name":"Trnovica",
    "wof:placetype":"locality"
},
  "geometry": {"coordinates":[18.44764,42.95199],"type":"Point"}
}