{
  "type": "Feature",
  "properties": {
    "gn:admin1_code":"01",
    "gn:asciiname":"Pecukici",
    "gn:country_code":"BA",
    "gn:dem":897,
    "gn:feature_class":"P",
    "gn:feature_code":"PPL",
    "gn:name":"Pe\u0107uki\u0107i",
    "gn:population":0,
    "gn:timezone":"Europe/Sarajevo",
    "iso:country":"BA",
    "wof:name":"Pecukici",
    "wof:placetype":"locality"
},
  "geometry": {"coordinates":[17.28694,43.58528],"type":"Point"}
}