{
  "type": "Feature",
  "properties": {
    "gn:admin1_code":"01",
    "gn:asciiname":"Orasi",
    "gn:country_code":"BA",
    "gn:dem":465,
    "gn:feature_class":"P",
    "gn:feature_code":"PPL",
    "gn:name":"Orasi",
    "gn:population":0,
    "gn:timezone":"Europe/Sarajevo",
    "iso:country":"BA",
    "wof:name":"Orasi",
    "wof:placetype":"locality"
},
  "geometry": {"coordinates":[18.11508,44.14203],"type":"Point"}
}