{
  "type": "Feature",
  "properties": {
    "gn:admin1_code":"01",
    "gn:asciiname":"Bjelcevic",
    "gn:country_code":"BA",
    "gn:dem":527,
    "gn:feature_class":"P",
    "gn:feature_code":"PPL",
    "gn:name":"Bjel\u010devi\u0107",
    "gn:population":0,
    "gn:timezone":"Europe/Sarajevo",
    "iso:country":"BA",
    "wof:name":"Bjelcevic",
    "wof:placetype":"locality"
},
  "geometry": {"coordinates":[18.02111,44.55641],"type":"Point"}
}