{
  "type": "Feature",
  "properties": {
    "gn:admin1_code":"01",
    "gn:asciiname":"Susnjice",
    "gn:country_code":"BA",
    "gn:dem":993,
    "gn:feature_class":"P",
    "gn:feature_code":"PPL",
    "gn:name":"\u0160u\u0161njice",
    "gn:population":0,
    "gn:timezone":"Europe/Sarajevo",
    "iso:country":"BA",
    "wof:name":"Susnjice",
    "wof:placetype":"locality"
},
  "geometry": {"coordinates":[16.28272999999999,44.21543],"type":"Point"}
}