{
  "type": "Feature",
  "properties": {
    "gn:admin1_code":"02",
    "gn:asciiname":"Marinka",
    "gn:country_code":"BA",
    "gn:dem":314,
    "gn:feature_class":"P",
    "gn:feature_code":"PPL",
    "gn:name":"Marinka",
    "gn:population":0,
    "gn:timezone":"Europe/Sarajevo",
    "iso:country":"BA",
    "name:ceb_x_preferred":[
        "Marinka"
    ],
    "name:lit_x_preferred":[
        "Marinka"
    ],
    "name:nld_x_preferred":[
        "Marinka"
    ],
    "name:rus_x_preferred":[
        "\u041c\u0430\u0440\u0438\u043d\u043a\u0430"
    ],
    "name:swe_x_preferred":[
        "Marinka"
    ],
    "wof:name":"Marinka",
    "wof:placetype":"locality"
},
  "geometry": {"coordinates":[17.52246,44.84663],"type":"Point"}
}