{
  "type": "Feature",
  "properties": {
    "gn:admin1_code":"02",
    "gn:asciiname":"Podrid",
    "gn:country_code":"BA",
    "gn:dem":897,
    "gn:feature_class":"P",
    "gn:feature_code":"PPL",
    "gn:name":"Podrid",
    "gn:population":0,
    "gn:timezone":"Europe/Sarajevo",
    "iso:country":"BA",
    "name:und_x_variant":[
        "Podhrid",
        "Podrid"
    ],
    "wof:name":"Podrid",
    "wof:placetype":"locality"
},
  "geometry": {"coordinates":[19.20157,43.5711],"type":"Point"}
}