{
  "type": "Feature",
  "properties": {
    "gn:admin1_code":"01",
    "gn:asciiname":"Piralici",
    "gn:country_code":"BA",
    "gn:dem":454,
    "gn:feature_class":"P",
    "gn:feature_code":"PPL",
    "gn:name":"Pirali\u0107i",
    "gn:population":0,
    "gn:timezone":"Europe/Sarajevo",
    "iso:country":"BA",
    "wof:name":"Piralici",
    "wof:placetype":"locality"
},
  "geometry": {"coordinates":[18.46578,44.43339],"type":"Point"}
}