{
  "type": "Feature",
  "properties": {
    "gn:admin1_code":"02",
    "gn:asciiname":"Ivojevici",
    "gn:country_code":"BA",
    "gn:dem":995,
    "gn:feature_class":"P",
    "gn:feature_code":"PPL",
    "gn:name":"Ivojevi\u0107i",
    "gn:population":0,
    "gn:timezone":"Europe/Sarajevo",
    "iso:country":"BA",
    "wof:name":"Ivojevici",
    "wof:placetype":"locality"
},
  "geometry": {"coordinates":[18.75442,44.06836],"type":"Point"}
}