{
  "type": "Feature",
  "properties": {
    "gn:admin1_code":"01",
    "gn:asciiname":"Plavlje",
    "gn:country_code":"BA",
    "gn:dem":690,
    "gn:feature_class":"P",
    "gn:feature_code":"PPL",
    "gn:name":"Plavlje",
    "gn:population":0,
    "gn:timezone":"Europe/Sarajevo",
    "iso:country":"BA",
    "wof:name":"Plavlje",
    "wof:placetype":"locality"
},
  "geometry": {"coordinates":[18.14889,43.92083],"type":"Point"}
}