{
  "type": "Feature",
  "properties": {
    "gn:admin1_code":"02",
    "gn:asciiname":"Cuke",
    "gn:country_code":"BA",
    "gn:dem":914,
    "gn:feature_class":"P",
    "gn:feature_code":"PPL",
    "gn:name":"\u010cuke",
    "gn:population":0,
    "gn:timezone":"Europe/Sarajevo",
    "iso:country":"BA",
    "wof:name":"Cuke",
    "wof:placetype":"locality"
},
  "geometry": {"coordinates":[18.94417,43.39778],"type":"Point"}
}