{
  "type": "Feature",
  "properties": {
    "gn:asciiname":"Vlaka",
    "gn:country_code":"BA",
    "gn:dem":808,
    "gn:feature_class":"P",
    "gn:feature_code":"PPL",
    "gn:name":"Vlaka",
    "gn:population":0,
    "gn:timezone":"Europe/Sarajevo",
    "iso:country":"BA",
    "name:bos_x_preferred":[
        "Vlaka"
    ],
    "name:ceb_x_preferred":[
        "Vlaka"
    ],
    "name:fra_x_preferred":[
        "Vlaka"
    ],
    "name:hrv_x_preferred":[
        "Vlaka"
    ],
    "name:hun_x_preferred":[
        "Vlaka"
    ],
    "name:nld_x_preferred":[
        "Vlaka"
    ],
    "name:slv_x_preferred":[
        "Vlaka"
    ],
    "name:srp_x_preferred":[
        "\u0412\u043b\u0430\u043a\u0430"
    ],
    "name:swe_x_preferred":[
        "Vlaka"
    ],
    "name:ukr_x_preferred":[
        "\u0412\u043b\u0430\u043a\u0430"
    ],
    "wof:name":"Vlaka",
    "wof:placetype":"locality"
},
  "geometry": {"coordinates":[17.02885,43.60703],"type":"Point"}
}