{
  "type": "Feature",
  "properties": {
    "gn:admin1_code":"01",
    "gn:asciiname":"Tuhobici",
    "gn:country_code":"BA",
    "gn:dem":981,
    "gn:feature_class":"P",
    "gn:feature_code":"PPL",
    "gn:name":"Tuhobi\u0107i",
    "gn:population":0,
    "gn:timezone":"Europe/Sarajevo",
    "iso:country":"BA",
    "name:ara_x_preferred":[
        "\u062a\u0648\u0647\u0648\u0628\u064a\u062a\u0634\u064a"
    ],
    "name:bos_x_preferred":[
        "Tuhobi\u0107i"
    ],
    "name:fra_x_preferred":[
        "Tuhobi\u0107i"
    ],
    "name:hrv_x_preferred":[
        "Tuhobi\u0107i"
    ],
    "name:srp_x_preferred":[
        "\u0422\u0443\u0445\u043e\u0431\u0438\u045b\u0438"
    ],
    "name:und_x_variant":[
        "Tuhobi\u0107"
    ],
    "wof:name":"Tuhobici",
    "wof:placetype":"locality"
},
  "geometry": {"coordinates":[17.95317,43.75857],"type":"Point"}
}