{
  "type": "Feature",
  "properties": {
    "gn:admin1_code":"02",
    "gn:asciiname":"Grmuse",
    "gn:country_code":"BA",
    "gn:dem":348,
    "gn:feature_class":"P",
    "gn:feature_code":"PPL",
    "gn:name":"Grmu\u0161e",
    "gn:population":0,
    "gn:timezone":"Europe/Sarajevo",
    "iso:country":"BA",
    "wof:name":"Grmuse",
    "wof:placetype":"locality"
},
  "geometry": {"coordinates":[17.06806,44.75608],"type":"Point"}
}