{
  "type": "Feature",
  "properties": {
    "gn:admin1_code":"00",
    "gn:asciiname":"Katani",
    "gn:country_code":"BA",
    "gn:dem":460,
    "gn:feature_class":"P",
    "gn:feature_code":"PPL",
    "gn:name":"Katani",
    "gn:population":0,
    "gn:timezone":"Europe/Sarajevo",
    "iso:country":"BA",
    "wof:name":"Katani",
    "wof:placetype":"locality"
},
  "geometry": {"coordinates":[18.70093,44.36746],"type":"Point"}
}