{
  "type": "Feature",
  "properties": {
    "gn:admin1_code":"02",
    "gn:asciiname":"Kukrik",
    "gn:country_code":"BA",
    "gn:dem":547,
    "gn:feature_class":"P",
    "gn:feature_code":"PPL",
    "gn:name":"Kukrik",
    "gn:population":0,
    "gn:timezone":"Europe/Sarajevo",
    "iso:country":"BA",
    "wof:name":"Kukrik",
    "wof:placetype":"locality"
},
  "geometry": {"coordinates":[17.1652,44.57064],"type":"Point"}
}