{
  "type": "Feature",
  "properties": {
    "gn:admin1_code":"02",
    "gn:asciiname":"Dzemat",
    "gn:country_code":"BA",
    "gn:dem":183,
    "gn:feature_class":"P",
    "gn:feature_code":"PPL",
    "gn:name":"D\u017eemat",
    "gn:population":0,
    "gn:timezone":"Europe/Sarajevo",
    "iso:country":"BA",
    "wof:name":"Dzemat",
    "wof:placetype":"locality"
},
  "geometry": {"coordinates":[16.67672,45.12537],"type":"Point"}
}