{
  "type": "Feature",
  "properties": {
    "gn:admin1_code":"01",
    "gn:asciiname":"Ravno Brdo",
    "gn:country_code":"BA",
    "gn:dem":1202,
    "gn:feature_class":"P",
    "gn:feature_code":"PPL",
    "gn:name":"Ravno Brdo",
    "gn:population":0,
    "gn:timezone":"Europe/Sarajevo",
    "iso:country":"BA",
    "wof:name":"Ravno Brdo",
    "wof:placetype":"locality"
},
  "geometry": {"coordinates":[18.78111,43.6575],"type":"Point"}
}