{
  "type": "Feature",
  "properties": {
    "gn:admin1_code":"01",
    "gn:asciiname":"Ravno Brdo",
    "gn:country_code":"BA",
    "gn:dem":1202,
    "gn:feature_class":"P",
    "gn:feature_code":"PPL",
    "gn:name":"Ravno Brdo",
    "gn:population":0,
    "gn:timezone":"Europe/Sarajevo",
    "iso:country":"BA",
    "name:bos_x_preferred":[
        "Ravno Brdo"
    ],
    "name:bul_x_preferred":[
        "\u0420\u0430\u0432\u043d\u043e \u0411\u044a\u0440\u0434\u043e"
    ],
    "name:nld_x_preferred":[
        "Ravno Brdo"
    ],
    "name:pol_x_preferred":[
        "Ravno Brdo"
    ],
    "name:ron_x_preferred":[
        "Ravno Brdo"
    ],
    "name:slv_x_preferred":[
        "Ravno Brdo"
    ],
    "name:ukr_x_preferred":[
        "\u0420\u0430\u0432\u043d\u043e \u0411\u0440\u0434\u043e"
    ],
    "wof:name":"Ravno Brdo",
    "wof:placetype":"locality"
},
  "geometry": {"coordinates":[18.78111,43.6575],"type":"Point"}
}