{
  "type": "Feature",
  "properties": {
    "gn:admin1_code":"02",
    "gn:asciiname":"Crkvena",
    "gn:country_code":"BA",
    "gn:dem":468,
    "gn:feature_class":"P",
    "gn:feature_code":"PPL",
    "gn:name":"Crkvena",
    "gn:population":0,
    "gn:timezone":"Europe/Sarajevo",
    "iso:country":"BA",
    "wof:name":"Crkvena",
    "wof:placetype":"locality"
},
  "geometry": {"coordinates":[17.69683,44.51317],"type":"Point"}
}