{
  "type": "Feature",
  "properties": {
    "gn:admin1_code":"01",
    "gn:asciiname":"Mudrike",
    "gn:country_code":"BA",
    "gn:dem":1046,
    "gn:feature_class":"P",
    "gn:feature_code":"PPLL",
    "gn:name":"Mudrike",
    "gn:population":0,
    "gn:timezone":"Europe/Sarajevo",
    "iso:country":"BA",
    "name:ara_x_preferred":[
        "\u0645\u0648\u062f\u0631\u064a\u0643"
    ],
    "name:bos_x_preferred":[
        "Mudrike"
    ],
    "name:fra_x_preferred":[
        "Mudrike"
    ],
    "name:srp_x_preferred":[
        "\u041c\u0443\u0434\u0440\u0438\u043a\u0435"
    ],
    "wof:name":"Mudrike",
    "wof:placetype":"locality"
},
  "geometry": {"coordinates":[17.53533,44.30765],"type":"Point"}
}