{
  "type": "Feature",
  "properties": {
    "gn:admin1_code":"01",
    "gn:asciiname":"Mudrike",
    "gn:country_code":"BA",
    "gn:dem":1046,
    "gn:feature_class":"P",
    "gn:feature_code":"PPLL",
    "gn:name":"Mudrike",
    "gn:population":0,
    "gn:timezone":"Europe/Sarajevo",
    "iso:country":"BA",
    "wof:name":"Mudrike",
    "wof:placetype":"locality"
},
  "geometry": {"coordinates":[17.53533,44.30765],"type":"Point"}
}