{
  "type": "Feature",
  "properties": {
    "gn:admin1_code":"02",
    "gn:asciiname":"Drugovici",
    "gn:country_code":"BA",
    "gn:dem":185,
    "gn:feature_class":"P",
    "gn:feature_code":"PPLL",
    "gn:name":"Drugovi\u0107i",
    "gn:population":0,
    "gn:timezone":"Europe/Sarajevo",
    "iso:country":"BA",
    "name:und_x_variant":[
        "Dragovi\u0107i",
        "Drugovi\u0107i"
    ],
    "wof:name":"Drugovici",
    "wof:placetype":"locality"
},
  "geometry": {"coordinates":[17.41931,44.8818],"type":"Point"}
}