{
  "type": "Feature",
  "properties": {
    "gn:admin1_code":"02",
    "gn:asciiname":"Serdari",
    "gn:country_code":"BA",
    "gn:dem":360,
    "gn:feature_class":"P",
    "gn:feature_code":"PPL",
    "gn:name":"Serdari",
    "gn:population":0,
    "gn:timezone":"Europe/Sarajevo",
    "iso:country":"BA",
    "wof:name":"Serdari",
    "wof:placetype":"locality"
},
  "geometry": {"coordinates":[17.44218,44.603],"type":"Point"}
}