{
  "type": "Feature",
  "properties": {
    "gn:admin1_code":"02",
    "gn:asciiname":"Podjele",
    "gn:country_code":"BA",
    "gn:dem":945,
    "gn:feature_class":"P",
    "gn:feature_code":"PPL",
    "gn:name":"Podjele",
    "gn:population":0,
    "gn:timezone":"Europe/Sarajevo",
    "iso:country":"BA",
    "wof:name":"Podjele",
    "wof:placetype":"locality"
},
  "geometry": {"coordinates":[18.75972,43.95944],"type":"Point"}
}