{
  "type": "Feature",
  "properties": {
    "gn:admin1_code":"02",
    "gn:asciiname":"Ritani",
    "gn:country_code":"BA",
    "gn:dem":187,
    "gn:feature_class":"P",
    "gn:feature_code":"PPL",
    "gn:name":"Ritani",
    "gn:population":0,
    "gn:timezone":"Europe/Sarajevo",
    "iso:country":"BA",
    "wof:name":"Ritani",
    "wof:placetype":"locality"
},
  "geometry": {"coordinates":[16.94932,44.8053],"type":"Point"}
}