{
  "type": "Feature",
  "properties": {
    "gn:admin1_code":"02",
    "gn:asciiname":"Muslimanska Zabokvica",
    "gn:cc2":"BA",
    "gn:country_code":"BA",
    "gn:dem":248,
    "gn:feature_class":"P",
    "gn:feature_code":"PPLL",
    "gn:name":"Muslimanska \u017dabokvica",
    "gn:population":0,
    "gn:timezone":"Europe/Sarajevo",
    "iso:country":"BA",
    "name:und_x_variant":[
        "Muslimanska"
    ],
    "wof:name":"Muslimanska Zabokvica",
    "wof:placetype":"locality"
},
  "geometry": {"coordinates":[19.52778,43.96889],"type":"Point"}
}