{
  "type": "Feature",
  "properties": {
    "gn:admin1_code":"01",
    "gn:asciiname":"Kesine",
    "gn:country_code":"BA",
    "gn:dem":718,
    "gn:feature_class":"P",
    "gn:feature_code":"PPL",
    "gn:name":"Ke\u0161ine",
    "gn:population":0,
    "gn:timezone":"Europe/Sarajevo",
    "iso:country":"BA",
    "wof:name":"Kesine",
    "wof:placetype":"locality"
},
  "geometry": {"coordinates":[16.58649,44.07951],"type":"Point"}
}