{
  "type": "Feature",
  "properties": {
    "gn:admin1_code":"02",
    "gn:asciiname":"Gornje Cikote",
    "gn:country_code":"BA",
    "gn:dem":683,
    "gn:feature_class":"P",
    "gn:feature_code":"PPL",
    "gn:name":"Gornje Cikote",
    "gn:population":0,
    "gn:timezone":"Europe/Sarajevo",
    "iso:country":"BA",
    "wof:name":"Gornje Cikote",
    "wof:placetype":"locality"
},
  "geometry": {"coordinates":[19.40181,43.61203],"type":"Point"}
}