{
  "type": "Feature",
  "properties": {
    "gn:admin1_code":"01",
    "gn:asciiname":"Grabovi Do",
    "gn:country_code":"BA",
    "gn:dem":576,
    "gn:feature_class":"P",
    "gn:feature_code":"PPL",
    "gn:name":"Grabovi Do",
    "gn:population":0,
    "gn:timezone":"Europe/Sarajevo",
    "iso:country":"BA",
    "wof:name":"Grabovi Do",
    "wof:placetype":"locality"
},
  "geometry": {"coordinates":[17.90885,42.84377],"type":"Point"}
}