{
  "type": "Feature",
  "properties": {
    "gn:admin1_code":"02",
    "gn:asciiname":"Solila",
    "gn:country_code":"BA",
    "gn:dem":1102,
    "gn:feature_class":"P",
    "gn:feature_code":"PPL",
    "gn:name":"Solila",
    "gn:population":0,
    "gn:timezone":"Europe/Sarajevo",
    "iso:country":"BA",
    "name:fra_x_preferred":[
        "Solila"
    ],
    "name:ita_x_preferred":[
        "Solila"
    ],
    "name:mlg_x_preferred":[
        "Solila"
    ],
    "name:nld_x_preferred":[
        "Solila"
    ],
    "wof:name":"Solila",
    "wof:placetype":"locality"
},
  "geometry": {"coordinates":[19.06615,44.05178],"type":"Point"}
}