{
  "type": "Feature",
  "properties": {
    "gn:admin1_code":"02",
    "gn:asciiname":"Vrela",
    "gn:country_code":"BA",
    "gn:dem":882,
    "gn:feature_class":"P",
    "gn:feature_code":"PPL",
    "gn:name":"Vrela",
    "gn:population":0,
    "gn:timezone":"Europe/Sarajevo",
    "iso:country":"BA",
    "wof:name":"Vrela",
    "wof:placetype":"locality"
},
  "geometry": {"coordinates":[18.86833,43.47639],"type":"Point"}
}