{
  "type": "Feature",
  "properties": {
    "gn:admin1_code":"02",
    "gn:asciiname":"Vrhovci",
    "gn:country_code":"BA",
    "gn:dem":306,
    "gn:feature_class":"P",
    "gn:feature_code":"PPL",
    "gn:name":"Vrhovci",
    "gn:population":0,
    "gn:timezone":"Europe/Sarajevo",
    "iso:country":"BA",
    "name:bos_x_preferred":[
        "Vrhovci"
    ],
    "name:fra_x_preferred":[
        "Vrhovci"
    ],
    "name:hrv_x_preferred":[
        "Vrhovci"
    ],
    "name:hun_x_preferred":[
        "Vrhovci"
    ],
    "name:nld_x_preferred":[
        "Vrhovci"
    ],
    "name:slv_x_preferred":[
        "Vrhovci"
    ],
    "name:srp_x_preferred":[
        "\u0412\u0440\u0445\u043e\u0432\u0446\u0438"
    ],
    "wof:name":"Vrhovci",
    "wof:placetype":"locality"
},
  "geometry": {"coordinates":[17.49186,44.8121],"type":"Point"}
}