{
  "type": "Feature",
  "properties": {
    "gn:admin1_code":"02",
    "gn:asciiname":"Sincici",
    "gn:country_code":"BA",
    "gn:dem":372,
    "gn:feature_class":"P",
    "gn:feature_code":"PPL",
    "gn:name":"Sin\u0107i\u0107i",
    "gn:population":0,
    "gn:timezone":"Europe/Sarajevo",
    "iso:country":"BA",
    "wof:name":"Sincici",
    "wof:placetype":"locality"
},
  "geometry": {"coordinates":[19.61139,44.0275],"type":"Point"}
}