{
  "type": "Feature",
  "properties": {
    "gn:admin1_code":"02",
    "gn:asciiname":"Todorovici",
    "gn:country_code":"BA",
    "gn:dem":773,
    "gn:feature_class":"P",
    "gn:feature_code":"PPL",
    "gn:name":"Todorovi\u0107i",
    "gn:population":0,
    "gn:timezone":"Europe/Sarajevo",
    "iso:country":"BA",
    "wof:name":"Todorovici",
    "wof:placetype":"locality"
},
  "geometry": {"coordinates":[16.70722,44.46778],"type":"Point"}
}