{
  "type": "Feature",
  "properties": {
    "gn:admin1_code":"01",
    "gn:asciiname":"Gornje Ledenice",
    "gn:country_code":"BA",
    "gn:dem":94,
    "gn:feature_class":"P",
    "gn:feature_code":"PPLL",
    "gn:name":"Gornje Ledenice",
    "gn:population":0,
    "gn:timezone":"Europe/Sarajevo",
    "iso:country":"BA",
    "name:und_x_variant":[
        "Ledenice Gornje",
        "Muslimanski Ledenice",
        "Gornje Ledenice"
    ],
    "wof:name":"Gornje Ledenice",
    "wof:placetype":"locality"
},
  "geometry": {"coordinates":[18.45398,44.91678],"type":"Point"}
}