{
  "type": "Feature",
  "properties": {
    "gn:admin1_code":"01",
    "gn:asciiname":"Jukici",
    "gn:country_code":"BA",
    "gn:dem":316,
    "gn:feature_class":"P",
    "gn:feature_code":"PPL",
    "gn:name":"Juki\u0107i",
    "gn:population":0,
    "gn:timezone":"Europe/Sarajevo",
    "iso:country":"BA",
    "wof:name":"Jukici",
    "wof:placetype":"locality"
},
  "geometry": {"coordinates":[18.1028,44.48453],"type":"Point"}
}