{
  "type": "Feature",
  "properties": {
    "gn:admin1_code":"01",
    "gn:asciiname":"Prnjavor",
    "gn:country_code":"BA",
    "gn:dem":259,
    "gn:feature_class":"P",
    "gn:feature_code":"PPL",
    "gn:name":"Prnjavor",
    "gn:population":0,
    "gn:timezone":"Europe/Sarajevo",
    "iso:country":"BA",
    "name:ara_x_preferred":[
        "\u0628\u0631\u0646\u062c\u0627\u0641\u0648\u0631"
    ],
    "name:bos_x_preferred":[
        "Prnjavor"
    ],
    "name:ceb_x_preferred":[
        "Prnjavor"
    ],
    "name:deu_x_preferred":[
        "Prnjavor"
    ],
    "name:fra_x_preferred":[
        "Prnjavor"
    ],
    "name:hrv_x_preferred":[
        "Prnjavor"
    ],
    "name:hun_x_preferred":[
        "Prnjavor"
    ],
    "name:nld_x_preferred":[
        "Prnjavor"
    ],
    "name:slv_x_preferred":[
        "Prnjavor"
    ],
    "name:srp_x_preferred":[
        "\u041f\u0440\u045a\u0430\u0432\u043e\u0440"
    ],
    "name:swe_x_preferred":[
        "Prnjavor"
    ],
    "name:ukr_x_preferred":[
        "\u041f\u0440\u043d\u044f\u0432\u043e\u0440"
    ],
    "wof:name":"Prnjavor",
    "wof:placetype":"locality"
},
  "geometry": {"coordinates":[18.86634,44.44726],"type":"Point"}
}