{
  "type": "Feature",
  "properties": {
    "gn:admin1_code":"02",
    "gn:asciiname":"Novarlici",
    "gn:country_code":"BA",
    "gn:dem":223,
    "gn:feature_class":"P",
    "gn:feature_code":"PPL",
    "gn:name":"Novarli\u0107i",
    "gn:population":0,
    "gn:timezone":"Europe/Sarajevo",
    "iso:country":"BA",
    "wof:name":"Novarlici",
    "wof:placetype":"locality"
},
  "geometry": {"coordinates":[17.63048999999999,44.94768],"type":"Point"}
}