{
  "type": "Feature",
  "properties": {
    "gn:admin1_code":"01",
    "gn:asciiname":"Vitaljina",
    "gn:country_code":"BA",
    "gn:dem":73,
    "gn:feature_class":"P",
    "gn:feature_code":"PPLL",
    "gn:name":"Vitaljina",
    "gn:population":0,
    "gn:timezone":"Europe/Sarajevo",
    "iso:country":"BA",
    "name:bos_x_preferred":[
        "Vitaljina"
    ],
    "name:ces_x_preferred":[
        "Vitaljina"
    ],
    "name:hrv_x_preferred":[
        "Vitaljina"
    ],
    "name:hun_x_preferred":[
        "Vitaljina"
    ],
    "name:ita_x_preferred":[
        "Vitaljina"
    ],
    "name:slv_x_preferred":[
        "Vitaljina"
    ],
    "name:srp_x_preferred":[
        "\u0412\u0438\u0442\u0430\u0459\u0438\u043d\u0430"
    ],
    "name:ukr_x_preferred":[
        "\u0412\u0456\u0442\u0430\u043b\u0456\u043d\u0430"
    ],
    "wof:name":"Vitaljina",
    "wof:placetype":"locality"
},
  "geometry": {"coordinates":[17.56222,43.16944],"type":"Point"}
}