{
  "type": "Feature",
  "properties": {
    "gn:admin1_code":"01",
    "gn:asciiname":"Vitaljina",
    "gn:country_code":"BA",
    "gn:dem":73,
    "gn:feature_class":"P",
    "gn:feature_code":"PPLL",
    "gn:name":"Vitaljina",
    "gn:population":0,
    "gn:timezone":"Europe/Sarajevo",
    "iso:country":"BA",
    "wof:name":"Vitaljina",
    "wof:placetype":"locality"
},
  "geometry": {"coordinates":[17.56222,43.16944],"type":"Point"}
}