{
  "type": "Feature",
  "properties": {
    "gn:admin1_code":"02",
    "gn:asciiname":"Dugi Do",
    "gn:country_code":"BA",
    "gn:dem":844,
    "gn:feature_class":"P",
    "gn:feature_code":"PPL",
    "gn:name":"Dugi Do",
    "gn:population":0,
    "gn:timezone":"Europe/Sarajevo",
    "iso:country":"BA",
    "wof:name":"Dugi Do",
    "wof:placetype":"locality"
},
  "geometry": {"coordinates":[18.10382,43.18832],"type":"Point"}
}