{
  "type": "Feature",
  "properties": {
    "gn:admin1_code":"02",
    "gn:asciiname":"Kauri",
    "gn:country_code":"BA",
    "gn:dem":498,
    "gn:feature_class":"P",
    "gn:feature_code":"PPL",
    "gn:name":"Kauri",
    "gn:population":0,
    "gn:timezone":"Europe/Sarajevo",
    "iso:country":"BA",
    "wof:name":"Kauri",
    "wof:placetype":"locality"
},
  "geometry": {"coordinates":[17.12741,44.44151],"type":"Point"}
}