{
  "type": "Feature",
  "properties": {
    "gn:admin1_code":"01",
    "gn:asciiname":"Doljani",
    "gn:country_code":"BA",
    "gn:dem":83,
    "gn:feature_class":"P",
    "gn:feature_code":"PPL",
    "gn:name":"Doljani",
    "gn:population":0,
    "gn:timezone":"Europe/Sarajevo",
    "iso:country":"BA",
    "wof:name":"Doljani",
    "wof:placetype":"locality"
},
  "geometry": {"coordinates":[18.56894,45.02354],"type":"Point"}
}