{
  "type": "Feature",
  "properties": {
    "gn:admin1_code":"01",
    "gn:asciiname":"Podonis",
    "gn:country_code":"BA",
    "gn:dem":823,
    "gn:feature_class":"P",
    "gn:feature_code":"PPL",
    "gn:name":"Podoni\u0161",
    "gn:population":0,
    "gn:timezone":"Europe/Sarajevo",
    "iso:country":"BA",
    "wof:name":"Podonis",
    "wof:placetype":"locality"
},
  "geometry": {"coordinates":[17.53083,43.78111],"type":"Point"}
}