{
  "type": "Feature",
  "properties": {
    "gn:admin1_code":"02",
    "gn:asciiname":"Vodevica Do",
    "gn:country_code":"BA",
    "gn:dem":420,
    "gn:feature_class":"P",
    "gn:feature_code":"PPL",
    "gn:name":"Vodevica Do",
    "gn:population":0,
    "gn:timezone":"Europe/Sarajevo",
    "iso:country":"BA",
    "wof:name":"Vodevica Do",
    "wof:placetype":"locality"
},
  "geometry": {"coordinates":[17.14879,44.42512],"type":"Point"}
}