{
  "type": "Feature",
  "properties": {
    "gn:admin1_code":"02",
    "gn:asciiname":"Kuzmici",
    "gn:country_code":"BA",
    "gn:dem":880,
    "gn:feature_class":"P",
    "gn:feature_code":"PPL",
    "gn:name":"Kuzmi\u0107i",
    "gn:population":0,
    "gn:timezone":"Europe/Sarajevo",
    "iso:country":"BA",
    "wof:name":"Kuzmici",
    "wof:placetype":"locality"
},
  "geometry": {"coordinates":[17.47137,44.51207],"type":"Point"}
}