{
  "type": "Feature",
  "properties": {
    "gn:admin1_code":"02",
    "gn:asciiname":"Dunjaci",
    "gn:country_code":"BA",
    "gn:dem":311,
    "gn:feature_class":"P",
    "gn:feature_code":"PPL",
    "gn:name":"Dunjaci",
    "gn:population":0,
    "gn:timezone":"Europe/Sarajevo",
    "iso:country":"BA",
    "wof:name":"Dunjaci",
    "wof:placetype":"locality"
},
  "geometry": {"coordinates":[17.87836,44.66944],"type":"Point"}
}