{
  "type": "Feature",
  "properties": {
    "gn:admin1_code":"02",
    "gn:asciiname":"Podgrab",
    "gn:country_code":"BA",
    "gn:dem":735,
    "gn:feature_class":"P",
    "gn:feature_code":"PPLL",
    "gn:name":"Podgrab",
    "gn:population":0,
    "gn:timezone":"Europe/Sarajevo",
    "iso:country":"BA",
    "name:bos_x_preferred":[
        "Podgrab"
    ],
    "name:ceb_x_preferred":[
        "Podgrab"
    ],
    "name:fra_x_preferred":[
        "Podgrab"
    ],
    "name:hrv_x_preferred":[
        "Podgrab"
    ],
    "name:srp_x_preferred":[
        "\u041f\u043e\u0434\u0433\u0440\u0430\u0431"
    ],
    "name:swe_x_preferred":[
        "Podgrab"
    ],
    "wof:name":"Podgrab",
    "wof:placetype":"locality"
},
  "geometry": {"coordinates":[18.70369,43.76581],"type":"Point"}
}