{
  "type": "Feature",
  "properties": {
    "gn:admin1_code":"02",
    "gn:asciiname":"Podgrab",
    "gn:country_code":"BA",
    "gn:dem":735,
    "gn:feature_class":"P",
    "gn:feature_code":"PPLL",
    "gn:name":"Podgrab",
    "gn:population":0,
    "gn:timezone":"Europe/Sarajevo",
    "iso:country":"BA",
    "wof:name":"Podgrab",
    "wof:placetype":"locality"
},
  "geometry": {"coordinates":[18.70369,43.76581],"type":"Point"}
}