{
  "type": "Feature",
  "properties": {
    "gn:admin1_code":"02",
    "gn:asciiname":"Brezovica",
    "gn:country_code":"BA",
    "gn:dem":156,
    "gn:feature_class":"P",
    "gn:feature_code":"PPL",
    "gn:name":"Brezovica",
    "gn:population":0,
    "gn:timezone":"Europe/Sarajevo",
    "iso:country":"BA",
    "wof:name":"Brezovica",
    "wof:placetype":"locality"
},
  "geometry": {"coordinates":[19.16121,44.62186],"type":"Point"}
}