{
  "type": "Feature",
  "properties": {
    "gn:admin1_code":"02",
    "gn:asciiname":"Brezovica",
    "gn:country_code":"BA",
    "gn:dem":156,
    "gn:feature_class":"P",
    "gn:feature_code":"PPL",
    "gn:name":"Brezovica",
    "gn:population":0,
    "gn:timezone":"Europe/Sarajevo",
    "iso:country":"BA",
    "name:bos_x_preferred":[
        "Brezovica"
    ],
    "name:ceb_x_preferred":[
        "Brezovica"
    ],
    "name:ces_x_preferred":[
        "Brezovica"
    ],
    "name:deu_x_preferred":[
        "Brezovica"
    ],
    "name:epo_x_preferred":[
        "Brezovica"
    ],
    "name:fra_x_preferred":[
        "Brezovica"
    ],
    "name:heb_x_preferred":[
        "\u05d1\u05e8\u05d6\u05d5\u05d1\u05d9\u05e6\u05d4"
    ],
    "name:hrv_x_preferred":[
        "Brezovica"
    ],
    "name:hun_x_preferred":[
        "Brezovica"
    ],
    "name:ita_x_preferred":[
        "Brezovica"
    ],
    "name:nld_x_preferred":[
        "Brezovica"
    ],
    "name:pol_x_preferred":[
        "Brezovica"
    ],
    "name:ron_x_preferred":[
        "Brezovica"
    ],
    "name:slk_x_preferred":[
        "Brezovica"
    ],
    "name:slv_x_preferred":[
        "Brezovica"
    ],
    "name:spa_x_preferred":[
        "Brezovica"
    ],
    "name:srp_x_preferred":[
        "\u0411\u0440\u0435\u0437\u043e\u0432\u0438\u0446\u0430"
    ],
    "name:swe_x_preferred":[
        "Brezovica"
    ],
    "name:vie_x_preferred":[
        "Brezovica"
    ],
    "wof:name":"Brezovica",
    "wof:placetype":"locality"
},
  "geometry": {"coordinates":[19.16121,44.62186],"type":"Point"}
}