{
  "type": "Feature",
  "properties": {
    "gn:admin1_code":"02",
    "gn:asciiname":"Marinkovici",
    "gn:country_code":"BA",
    "gn:dem":186,
    "gn:feature_class":"P",
    "gn:feature_code":"PPL",
    "gn:name":"Marinkovi\u0107i",
    "gn:population":0,
    "gn:timezone":"Europe/Sarajevo",
    "iso:country":"BA",
    "wof:name":"Marinkovici",
    "wof:placetype":"locality"
},
  "geometry": {"coordinates":[17.41706,44.81917],"type":"Point"}
}