{
  "type": "Feature",
  "properties": {
    "gn:admin1_code":"01",
    "gn:asciiname":"Kulinari",
    "gn:country_code":"BA",
    "gn:dem":296,
    "gn:feature_class":"P",
    "gn:feature_code":"PPL",
    "gn:name":"Kulinari",
    "gn:population":0,
    "gn:timezone":"Europe/Sarajevo",
    "iso:country":"BA",
    "wof:name":"Kulinari",
    "wof:placetype":"locality"
},
  "geometry": {"coordinates":[17.68531,43.36381],"type":"Point"}
}