{
  "type": "Feature",
  "properties": {
    "gn:admin1_code":"02",
    "gn:asciiname":"Rodusa",
    "gn:country_code":"BA",
    "gn:dem":1061,
    "gn:feature_class":"P",
    "gn:feature_code":"PPL",
    "gn:name":"Rodu\u0161a",
    "gn:population":0,
    "gn:timezone":"Europe/Sarajevo",
    "iso:country":"BA",
    "wof:name":"Rodusa",
    "wof:placetype":"locality"
},
  "geometry": {"coordinates":[17.06047,44.19131],"type":"Point"}
}