{
  "type": "Feature",
  "properties": {
    "gn:admin1_code":"02",
    "gn:asciiname":"Duganovici",
    "gn:country_code":"BA",
    "gn:dem":846,
    "gn:feature_class":"P",
    "gn:feature_code":"PPL",
    "gn:name":"Duganovi\u0107i",
    "gn:population":0,
    "gn:timezone":"Europe/Sarajevo",
    "iso:country":"BA",
    "wof:name":"Duganovici",
    "wof:placetype":"locality"
},
  "geometry": {"coordinates":[18.78337,44.02782],"type":"Point"}
}