{
  "type": "Feature",
  "properties": {
    "gn:admin1_code":"02",
    "gn:asciiname":"Cipirovine",
    "gn:country_code":"BA",
    "gn:dem":97,
    "gn:feature_class":"P",
    "gn:feature_code":"PPL",
    "gn:name":"\u0106ipirovine",
    "gn:population":0,
    "gn:timezone":"Europe/Sarajevo",
    "iso:country":"BA",
    "name:bos_x_preferred":[
        "\u0106ipirovine"
    ],
    "name:ceb_x_preferred":[
        "\u0106ipirovine"
    ],
    "name:fra_x_preferred":[
        "\u0106ipirovine"
    ],
    "name:hrv_x_preferred":[
        "\u0106ipirovine"
    ],
    "name:rus_x_preferred":[
        "\u0427\u0438\u043f\u0438\u0440\u043e\u0432\u0438\u043d\u0435"
    ],
    "name:slv_x_preferred":[
        "\u0106ipirovine"
    ],
    "name:srp_x_preferred":[
        "\u040b\u0438\u043f\u0438\u0440\u043e\u0432\u0438\u043d\u0435"
    ],
    "name:swe_x_preferred":[
        "\u0106ipirovine"
    ],
    "name:und_x_variant":[
        "\u0106iperovine",
        "\u0106ipirovine"
    ],
    "wof:name":"Cipirovine",
    "wof:placetype":"locality"
},
  "geometry": {"coordinates":[19.23537,44.72087],"type":"Point"}
}