{
  "type": "Feature",
  "properties": {
    "gn:admin1_code":"01",
    "gn:asciiname":"Savanovici",
    "gn:country_code":"BA",
    "gn:dem":965,
    "gn:feature_class":"P",
    "gn:feature_code":"PPL",
    "gn:name":"Savanovi\u0107i",
    "gn:population":0,
    "gn:timezone":"Europe/Sarajevo",
    "iso:country":"BA",
    "wof:name":"Savanovici",
    "wof:placetype":"locality"
},
  "geometry": {"coordinates":[17.48627,44.1935],"type":"Point"}
}