{
  "type": "Feature",
  "properties": {
    "gn:admin1_code":"01",
    "gn:asciiname":"Vrdi",
    "gn:country_code":"BA",
    "gn:dem":483,
    "gn:feature_class":"P",
    "gn:feature_code":"PPL",
    "gn:name":"Vrdi",
    "gn:population":0,
    "gn:timezone":"Europe/Sarajevo",
    "iso:country":"BA",
    "wof:name":"Vrdi",
    "wof:placetype":"locality"
},
  "geometry": {"coordinates":[17.74669,43.50143],"type":"Point"}
}