{
  "type": "Feature",
  "properties": {
    "gn:admin1_code":"01",
    "gn:asciiname":"Lazine",
    "gn:country_code":"BA",
    "gn:dem":1407,
    "gn:feature_class":"P",
    "gn:feature_code":"PPL",
    "gn:name":"Lazine",
    "gn:population":0,
    "gn:timezone":"Europe/Sarajevo",
    "iso:country":"BA",
    "wof:name":"Lazine",
    "wof:placetype":"locality"
},
  "geometry": {"coordinates":[17.77547999999999,43.88497],"type":"Point"}
}