{
  "type": "Feature",
  "properties": {
    "gn:admin1_code":"01",
    "gn:asciiname":"Bajovci",
    "gn:country_code":"BA",
    "gn:dem":13,
    "gn:feature_class":"P",
    "gn:feature_code":"PPL",
    "gn:name":"Bajovci",
    "gn:population":0,
    "gn:timezone":"Europe/Sarajevo",
    "iso:country":"BA",
    "wof:name":"Bajovci",
    "wof:placetype":"locality"
},
  "geometry": {"coordinates":[17.76419,43.02069],"type":"Point"}
}