{
  "type": "Feature",
  "properties": {
    "gn:admin1_code":"01",
    "gn:asciiname":"Lebe",
    "gn:country_code":"BA",
    "gn:dem":933,
    "gn:feature_class":"P",
    "gn:feature_code":"PPL",
    "gn:name":"Lebe",
    "gn:population":0,
    "gn:timezone":"Europe/Sarajevo",
    "iso:country":"BA",
    "wof:name":"Lebe",
    "wof:placetype":"locality"
},
  "geometry": {"coordinates":[17.38216,43.47182],"type":"Point"}
}