{
  "type": "Feature",
  "properties": {
    "gn:admin1_code":"02",
    "gn:asciiname":"Stepanovici",
    "gn:country_code":"BA",
    "gn:dem":445,
    "gn:feature_class":"P",
    "gn:feature_code":"PPL",
    "gn:name":"Stepanovi\u0107i",
    "gn:population":0,
    "gn:timezone":"Europe/Sarajevo",
    "iso:country":"BA",
    "wof:name":"Stepanovici",
    "wof:placetype":"locality"
},
  "geometry": {"coordinates":[19.04707,44.19736],"type":"Point"}
}