{
  "type": "Feature",
  "properties": {
    "gn:country":"BA",
    "gn:fcode":"PPL",
    "gn:pop":4,
    "iso:country":"BA",
    "name:bul_x_preferred":[
        "\u0411\u043e\u0441\u0430\u043d\u0441\u043a\u0438 \u041f\u0435\u0442\u0440\u043e\u0432\u0430\u0446"
    ],
    "name:hye_x_preferred":[
        "\u0532\u0578\u057d\u0561\u0576\u057d\u056f\u056b \u054a\u0565\u057f\u0580\u0578\u057e\u0561\u0581"
    ],
    "name:jpn_x_preferred":[
        "\u30dc\u30b5\u30f3\u30b9\u30ad\u30fb\u30da\u30c8\u30ed\u30f4\u30a1\u30c4"
    ],
    "name:srp_x_preferred":[
        "\u0411\u043e\u0441\u0430\u043d\u0441\u043a\u0438 \u041f\u0435\u0442\u0440\u043e\u0432\u0430\u0446"
    ],
    "name:unk_x_variant":[
        "Petrovac"
    ],
    "name:zho_x_preferred":[
        "\u6ce2\u65af\u5c3c\u4e9e\u5f7c\u5f97\u7f85\u74e6\u8328"
    ],
    "qs:name":"Bosanski Petrovac",
    "qs:name_adm0":"Bosna i Hercegovina",
    "qs:name_adm1":"Federacija Bosne I Hercegovine",
    "qs:photos_9r":0,
    "qs:photos_sr":0,
    "qs:placetype":"Town",
    "qs:pop_sr":"1",
    "wd:wordcount":385,
    "wof:name":"Bosanski Petrovac",
    "wof:placetype":"locality",
    "wof:population":4
},
  "geometry": {"coordinates":[16.36897,44.55537],"type":"Point"}
}