{
  "type": "Feature",
  "properties": {
    "gn:country":"BA",
    "gn:fcode":"PPL",
    "gn:population":4,
    "iso:country":"BA",
    "name:ara_x_preferred":[
        "\u0628\u0648\u0633\u0627\u0646\u0633\u0643\u064a \u0628\u062a\u0631\u0648\u0641\u0627\u062a\u0633"
    ],
    "name:bos_x_preferred":[
        "Bosanski Petrovac"
    ],
    "name:bul_x_preferred":[
        "\u0411\u043e\u0441\u0430\u043d\u0441\u043a\u0438 \u041f\u0435\u0442\u0440\u043e\u0432\u0430\u0446"
    ],
    "name:cat_x_preferred":[
        "Bosanski Petrovac"
    ],
    "name:ces_x_preferred":[
        "Bosanski Petrovac"
    ],
    "name:deu_x_preferred":[
        "Bosanski Petrovac"
    ],
    "name:eng_x_preferred":[
        "Bosanski Petrovac"
    ],
    "name:eus_x_preferred":[
        "Bosanski Petrovac"
    ],
    "name:fas_x_preferred":[
        "\u0628\u0648\u0633\u0627\u0646\u0633\u06a9\u06cc \u067e\u062a\u0631\u0648\u0627\u062a\u0633"
    ],
    "name:fra_x_preferred":[
        "Bosanski Petrovac"
    ],
    "name:hrv_x_preferred":[
        "Bosanski Petrovac"
    ],
    "name:hsb_x_preferred":[
        "Bosanski Petrovac"
    ],
    "name:hye_x_preferred":[
        "\u0532\u0578\u057d\u0561\u0576\u057d\u056f\u056b \u054a\u0565\u057f\u0580\u0578\u057e\u0561\u0581"
    ],
    "name:ita_x_preferred":[
        "Bosanski Petrovac"
    ],
    "name:jpn_x_preferred":[
        "\u30dc\u30b5\u30f3\u30b9\u30ad\u30fb\u30da\u30c8\u30ed\u30f4\u30a1\u30c4"
    ],
    "name:kor_x_preferred":[
        "\ubcf4\uc0b0\uc2a4\ud0a4\ud398\ud2b8\ub85c\ubc14\uce20"
    ],
    "name:lit_x_preferred":[
        "Bosanski Petrovacas"
    ],
    "name:mkd_x_preferred":[
        "\u0411\u043e\u0441\u0430\u043d\u0441\u043a\u0438 \u041f\u0435\u0442\u0440\u043e\u0432\u0430\u0446"
    ],
    "name:nld_x_preferred":[
        "Bosanski Petrovac"
    ],
    "name:pol_x_preferred":[
        "Bosanski Petrovac"
    ],
    "name:rus_x_preferred":[
        "\u0411\u043e\u0441\u0430\u043d\u0441\u043a\u0438-\u041f\u0435\u0442\u0440\u043e\u0432\u0430\u0446"
    ],
    "name:slv_x_preferred":[
        "Bosanski Petrovac"
    ],
    "name:spa_x_preferred":[
        "Bosanski Petrovac"
    ],
    "name:sqi_x_preferred":[
        "Bosanski Petrovac"
    ],
    "name:srp_x_preferred":[
        "\u0411\u043e\u0441\u0430\u043d\u0441\u043a\u0438 \u041f\u0435\u0442\u0440\u043e\u0432\u0430\u0446"
    ],
    "name:swe_x_preferred":[
        "Bosanski Petrovac"
    ],
    "name:szl_x_preferred":[
        "Bosanski Petrovac"
    ],
    "name:tat_x_preferred":[
        "\u0411\u043e\u0441\u0430\u043d\u0441\u043a\u0438-\u041f\u0435\u0442\u0440\u043e\u0432\u0430\u0442\u0441"
    ],
    "name:tur_x_preferred":[
        "Bosanski Petrovac"
    ],
    "name:und_x_variant":[
        "Petrovac"
    ],
    "name:urd_x_preferred":[
        "\u0628\u0648\u0633\u0627\u0646\u0633\u06a9\u06cc \u067e\u06cc\u062a\u0631\u0648\u0648\u0627\u062a\u0633"
    ],
    "name:zho_x_preferred":[
        "\u6ce2\u65af\u5c3c\u4e9e\u5f7c\u5f97\u7f85\u74e6\u8328"
    ],
    "qs:name":"Bosanski Petrovac",
    "qs:name_adm0":"Bosna i Hercegovina",
    "qs:name_adm1":"Federacija Bosne I Hercegovine",
    "qs:photos_9r":0,
    "qs:photos_sr":0,
    "qs:placetype":"Town",
    "qs:pop_sr":"1",
    "wd:wordcount":385,
    "wof:name":"Bosanski Petrovac",
    "wof:placetype":"locality",
    "wof:population":4
},
  "geometry": {"coordinates":[16.36897,44.55537],"type":"Point"}
}