{
  "type": "Feature",
  "properties": {
    "gn:admin1_code":"02",
    "gn:asciiname":"Bujde",
    "gn:country_code":"BA",
    "gn:dem":244,
    "gn:feature_class":"P",
    "gn:feature_code":"PPL",
    "gn:name":"Bujde",
    "gn:population":0,
    "gn:timezone":"Europe/Sarajevo",
    "iso:country":"BA",
    "wof:name":"Bujde",
    "wof:placetype":"locality"
},
  "geometry": {"coordinates":[17.34251,44.66721],"type":"Point"}
}