{
  "type": "Feature",
  "properties": {
    "gn:admin1_code":"02",
    "gn:asciiname":"Makarici",
    "gn:country_code":"BA",
    "gn:dem":1076,
    "gn:feature_class":"P",
    "gn:feature_code":"PPL",
    "gn:name":"Makari\u0107i",
    "gn:population":0,
    "gn:timezone":"Europe/Sarajevo",
    "iso:country":"BA",
    "wof:name":"Makarici",
    "wof:placetype":"locality"
},
  "geometry": {"coordinates":[17.46357,44.40725],"type":"Point"}
}