{
  "type": "Feature",
  "properties": {
    "gn:admin1_code":"02",
    "gn:asciiname":"Lipac",
    "gn:country_code":"BA",
    "gn:dem":215,
    "gn:feature_class":"P",
    "gn:feature_code":"PPLL",
    "gn:name":"Lipac",
    "gn:population":0,
    "gn:timezone":"Europe/Sarajevo",
    "iso:country":"BA",
    "name:bos_x_preferred":[
        "Lipac"
    ],
    "name:ceb_x_preferred":[
        "Lipac"
    ],
    "name:fra_x_preferred":[
        "Lipac"
    ],
    "name:hrv_x_preferred":[
        "Lipac"
    ],
    "name:srp_x_preferred":[
        "\u041b\u0438\u043f\u0430\u0446"
    ],
    "name:swe_x_preferred":[
        "Lipac"
    ],
    "wof:name":"Lipac",
    "wof:placetype":"locality"
},
  "geometry": {"coordinates":[18.11193,44.71882],"type":"Point"}
}