{
  "type": "Feature",
  "properties": {
    "gn:admin1_code":"02",
    "gn:asciiname":"Prosic Jarak",
    "gn:country_code":"BA",
    "gn:dem":135,
    "gn:feature_class":"P",
    "gn:feature_code":"PPL",
    "gn:name":"Pro\u0161i\u0107 Jarak",
    "gn:population":0,
    "gn:timezone":"Europe/Sarajevo",
    "iso:country":"BA",
    "wof:name":"Prosic Jarak",
    "wof:placetype":"locality"
},
  "geometry": {"coordinates":[16.48167,45.16444],"type":"Point"}
}