{
  "type": "Feature",
  "properties": {
    "gn:admin1_code":"01",
    "gn:asciiname":"Poljari",
    "gn:country_code":"BA",
    "gn:dem":778,
    "gn:feature_class":"P",
    "gn:feature_code":"PPL",
    "gn:name":"Poljari",
    "gn:population":0,
    "gn:timezone":"Europe/Sarajevo",
    "iso:country":"BA",
    "wof:name":"Poljari",
    "wof:placetype":"locality"
},
  "geometry": {"coordinates":[16.2946,44.28588],"type":"Point"}
}