{
  "type": "Feature",
  "properties": {
    "gn:admin1_code":"02",
    "gn:asciiname":"Izgori",
    "gn:country_code":"BA",
    "gn:dem":946,
    "gn:feature_class":"P",
    "gn:feature_code":"PPLL",
    "gn:name":"Izgori",
    "gn:population":0,
    "gn:timezone":"Europe/Sarajevo",
    "iso:country":"BA",
    "name:bos_x_preferred":[
        "Izgori"
    ],
    "name:fra_x_preferred":[
        "Izgori"
    ],
    "name:hrv_x_preferred":[
        "Izgori"
    ],
    "name:srp_x_preferred":[
        "\u0418\u0437\u0433\u043e\u0440\u0438"
    ],
    "wof:name":"Izgori",
    "wof:placetype":"locality"
},
  "geometry": {"coordinates":[18.62497,43.28294],"type":"Point"}
}