{
  "type": "Feature",
  "properties": {
    "gn:admin1_code":"01",
    "gn:asciiname":"Gornji Lukomir",
    "gn:cc2":"BA",
    "gn:country_code":"BA",
    "gn:dem":1459,
    "gn:feature_class":"P",
    "gn:feature_code":"PPL",
    "gn:name":"Gornji Lukomir",
    "gn:population":0,
    "gn:timezone":"Europe/Sarajevo",
    "iso:country":"BA",
    "name:ara_x_preferred":[
        "\u0644\u0648\u0643\u0648\u0645\u064a\u0631"
    ],
    "name:bos_x_preferred":[
        "Lukomir"
    ],
    "name:deu_x_preferred":[
        "Lukomir"
    ],
    "name:fas_x_preferred":[
        "\u0644\u0648\u06a9\u0648\u0645\u06cc\u0631"
    ],
    "name:fra_x_preferred":[
        "Lukomir"
    ],
    "name:hrv_x_preferred":[
        "Lukomir"
    ],
    "name:srp_x_preferred":[
        "\u041b\u0443\u043a\u043e\u043c\u0438\u0440"
    ],
    "name:und_x_variant":[
        "Lukomir",
        "Gornji Lukomir"
    ],
    "wof:name":"Gornji Lukomir",
    "wof:placetype":"locality"
},
  "geometry": {"coordinates":[18.18333,43.63722],"type":"Point"}
}