{
  "type": "Feature",
  "properties": {
    "gn:admin1_code":"01",
    "gn:asciiname":"Gornji Lukomir",
    "gn:cc2":"BA",
    "gn:country_code":"BA",
    "gn:dem":1459,
    "gn:feature_class":"P",
    "gn:feature_code":"PPL",
    "gn:name":"Gornji Lukomir",
    "gn:population":0,
    "gn:timezone":"Europe/Sarajevo",
    "iso:country":"BA",
    "name:und_x_variant":[
        "Lukomir",
        "Gornji Lukomir"
    ],
    "wof:name":"Gornji Lukomir",
    "wof:placetype":"locality"
},
  "geometry": {"coordinates":[18.18333,43.63722],"type":"Point"}
}