{
  "type": "Feature",
  "properties": {
    "gn:admin1_code":"01",
    "gn:asciiname":"Skrobe",
    "gn:country_code":"BA",
    "gn:dem":981,
    "gn:feature_class":"P",
    "gn:feature_code":"PPL",
    "gn:name":"Skrobe",
    "gn:population":0,
    "gn:timezone":"Europe/Sarajevo",
    "iso:country":"BA",
    "wof:name":"Skrobe",
    "wof:placetype":"locality"
},
  "geometry": {"coordinates":[17.46,44.23733],"type":"Point"}
}