{
  "type": "Feature",
  "properties": {
    "gn:admin1_code":"01",
    "gn:asciiname":"Krcko Brdo",
    "gn:country_code":"BA",
    "gn:dem":568,
    "gn:feature_class":"P",
    "gn:feature_code":"PPL",
    "gn:name":"Kr\u010dko Brdo",
    "gn:population":0,
    "gn:timezone":"Europe/Sarajevo",
    "iso:country":"BA",
    "wof:name":"Krcko Brdo",
    "wof:placetype":"locality"
},
  "geometry": {"coordinates":[16.1524,44.4052],"type":"Point"}
}