{
  "type": "Feature",
  "properties": {
    "gn:admin1_code":"01",
    "gn:asciiname":"Vela",
    "gn:country_code":"BA",
    "gn:dem":856,
    "gn:feature_class":"P",
    "gn:feature_code":"PPL",
    "gn:name":"Vela",
    "gn:population":0,
    "gn:timezone":"Europe/Sarajevo",
    "iso:country":"BA",
    "name:bos_x_preferred":[
        "Vela"
    ],
    "name:fas_x_preferred":[
        "\u0648\u06cc\u0644\u0627"
    ],
    "name:fra_x_preferred":[
        "Vela"
    ],
    "wof:name":"Vela",
    "wof:placetype":"locality"
},
  "geometry": {"coordinates":[18.18411,43.90982],"type":"Point"}
}