{
  "type": "Feature",
  "properties": {
    "gn:admin1_code":"01",
    "gn:asciiname":"Pajtovici",
    "gn:country_code":"BA",
    "gn:dem":1005,
    "gn:feature_class":"P",
    "gn:feature_code":"PPL",
    "gn:name":"Pajtovi\u0107i",
    "gn:population":0,
    "gn:timezone":"Europe/Sarajevo",
    "iso:country":"BA",
    "name:und_x_variant":[
        "Pajlovi\u0107i",
        "Pajtovi\u0107i"
    ],
    "wof:name":"Pajtovici",
    "wof:placetype":"locality"
},
  "geometry": {"coordinates":[18.39646,44.10177],"type":"Point"}
}