{
  "type": "Feature",
  "properties": {
    "gn:admin1_code":"02",
    "gn:asciiname":"Ivanovici",
    "gn:country_code":"BA",
    "gn:dem":399,
    "gn:feature_class":"P",
    "gn:feature_code":"PPL",
    "gn:name":"Ivanovi\u0107i",
    "gn:population":0,
    "gn:timezone":"Europe/Sarajevo",
    "iso:country":"BA",
    "wof:name":"Ivanovici",
    "wof:placetype":"locality"
},
  "geometry": {"coordinates":[18.12474,44.67749],"type":"Point"}
}