{
  "type": "Feature",
  "properties": {
    "gn:admin1_code":"02",
    "gn:asciiname":"Gornji Obodnik",
    "gn:country_code":"BA",
    "gn:dem":386,
    "gn:feature_class":"P",
    "gn:feature_code":"PPL",
    "gn:name":"Gornji Obodnik",
    "gn:population":0,
    "gn:timezone":"Europe/Sarajevo",
    "iso:country":"BA",
    "wof:name":"Gornji Obodnik",
    "wof:placetype":"locality"
},
  "geometry": {"coordinates":[17.48426,44.57339],"type":"Point"}
}