{
  "type": "Feature",
  "properties": {
    "gn:admin1_code":"01",
    "gn:asciiname":"Bunari",
    "gn:country_code":"BA",
    "gn:dem":1024,
    "gn:feature_class":"P",
    "gn:feature_code":"PPLL",
    "gn:name":"Bunari",
    "gn:population":0,
    "gn:timezone":"Europe/Sarajevo",
    "iso:country":"BA",
    "wof:name":"Bunari",
    "wof:placetype":"locality"
},
  "geometry": {"coordinates":[17.86139,43.66028],"type":"Point"}
}