{
  "type": "Feature",
  "properties": {
    "gn:admin1_code":"01",
    "gn:asciiname":"Orah",
    "gn:country_code":"BA",
    "gn:dem":278,
    "gn:feature_class":"P",
    "gn:feature_code":"PPL",
    "gn:name":"Orah",
    "gn:population":0,
    "gn:timezone":"Europe/Sarajevo",
    "iso:country":"BA",
    "name:bos_x_preferred":[
        "Orah"
    ],
    "name:ceb_x_preferred":[
        "Orah"
    ],
    "name:fra_x_preferred":[
        "Orah"
    ],
    "name:hrv_x_preferred":[
        "Orah"
    ],
    "name:hun_x_preferred":[
        "Orah"
    ],
    "name:rus_x_preferred":[
        "\u041e\u0440\u0430\u0445"
    ],
    "name:slv_x_preferred":[
        "Orah"
    ],
    "name:srp_x_preferred":[
        "\u041e\u0440\u0430\u0445"
    ],
    "name:swe_x_preferred":[
        "Orah"
    ],
    "wof:name":"Orah",
    "wof:placetype":"locality"
},
  "geometry": {"coordinates":[18.18197,42.70002],"type":"Point"}
}