{
  "type": "Feature",
  "properties": {
    "gn:admin1_code":"01",
    "gn:asciiname":"Smrdan",
    "gn:country_code":"BA",
    "gn:dem":165,
    "gn:feature_class":"P",
    "gn:feature_code":"PPL",
    "gn:name":"Smrdan",
    "gn:population":0,
    "gn:timezone":"Europe/Sarajevo",
    "iso:country":"BA",
    "wof:name":"Smrdan",
    "wof:placetype":"locality"
},
  "geometry": {"coordinates":[16.17586,44.97837],"type":"Point"}
}