{
  "type": "Feature",
  "properties": {
    "gn:admin1_code":"01",
    "gn:asciiname":"Bosna",
    "gn:country_code":"BA",
    "gn:dem":418,
    "gn:feature_class":"P",
    "gn:feature_code":"PPL",
    "gn:name":"Bosna",
    "gn:population":0,
    "gn:timezone":"Europe/Sarajevo",
    "iso:country":"BA",
    "wof:name":"Bosna",
    "wof:placetype":"locality"
},
  "geometry": {"coordinates":[18.03444,44.13111],"type":"Point"}
}