{
  "type": "Feature",
  "properties": {
    "gn:admin1_code":"01",
    "gn:asciiname":"Bosna",
    "gn:country_code":"BA",
    "gn:dem":418,
    "gn:feature_class":"P",
    "gn:feature_code":"PPL",
    "gn:name":"Bosna",
    "gn:population":0,
    "gn:timezone":"Europe/Sarajevo",
    "iso:country":"BA",
    "name:bos_x_preferred":[
        "Bosna"
    ],
    "name:bul_x_preferred":[
        "\u0411\u043e\u0441\u043d\u0430"
    ],
    "name:ceb_x_preferred":[
        "Bosna"
    ],
    "name:ces_x_preferred":[
        "Bosna"
    ],
    "name:deu_x_preferred":[
        "Bosna"
    ],
    "name:fra_x_preferred":[
        "Bosna"
    ],
    "name:hrv_x_preferred":[
        "Bosna"
    ],
    "name:hun_x_preferred":[
        "Bosna"
    ],
    "name:ind_x_preferred":[
        "Bosna"
    ],
    "name:jav_x_preferred":[
        "Bosna"
    ],
    "name:mkd_x_preferred":[
        "\u0411\u043e\u0441\u043d\u0430"
    ],
    "name:pol_x_preferred":[
        "Bosna"
    ],
    "name:rus_x_preferred":[
        "\u0411\u043e\u0441\u043d\u0430"
    ],
    "name:slk_x_preferred":[
        "Bosna"
    ],
    "name:slv_x_preferred":[
        "Bosna"
    ],
    "name:srp_x_preferred":[
        "\u0411\u043e\u0441\u043d\u0430"
    ],
    "name:swe_x_preferred":[
        "Bosna"
    ],
    "name:ukr_x_preferred":[
        "\u0411\u043e\u0441\u043d\u0430"
    ],
    "wof:name":"Bosna",
    "wof:placetype":"locality"
},
  "geometry": {"coordinates":[18.03444,44.13111],"type":"Point"}
}