{
  "type": "Feature",
  "properties": {
    "gn:admin1_code":"02",
    "gn:asciiname":"Klek",
    "gn:country_code":"BA",
    "gn:dem":675,
    "gn:feature_class":"P",
    "gn:feature_code":"PPLL",
    "gn:name":"Klek",
    "gn:population":0,
    "gn:timezone":"Europe/Sarajevo",
    "iso:country":"BA",
    "wof:name":"Klek",
    "wof:placetype":"locality"
},
  "geometry": {"coordinates":[18.42054,43.79686],"type":"Point"}
}