{
  "type": "Feature",
  "properties": {
    "gn:admin1_code":"02",
    "gn:asciiname":"Vedovica",
    "gn:country_code":"BA",
    "gn:dem":280,
    "gn:feature_class":"P",
    "gn:feature_code":"PPL",
    "gn:name":"Vedovica",
    "gn:population":0,
    "gn:timezone":"Europe/Sarajevo",
    "iso:country":"BA",
    "name:bos_x_preferred":[
        "Vedovica"
    ],
    "name:fas_x_preferred":[
        "\u0648\u062f\u0648\u06cc\u06a9\u0627"
    ],
    "name:fra_x_preferred":[
        "Vedovica"
    ],
    "name:hrv_x_preferred":[
        "Vedovica"
    ],
    "name:srp_x_preferred":[
        "\u0412\u0435\u0434\u043e\u0432\u0438\u0446\u0430"
    ],
    "wof:name":"Vedovica",
    "wof:placetype":"locality"
},
  "geometry": {"coordinates":[16.38828,44.94813],"type":"Point"}
}