{
  "type": "Feature",
  "properties": {
    "gn:admin1_code":"02",
    "gn:asciiname":"Vedovica",
    "gn:country_code":"BA",
    "gn:dem":280,
    "gn:feature_class":"P",
    "gn:feature_code":"PPL",
    "gn:name":"Vedovica",
    "gn:population":0,
    "gn:timezone":"Europe/Sarajevo",
    "iso:country":"BA",
    "wof:name":"Vedovica",
    "wof:placetype":"locality"
},
  "geometry": {"coordinates":[16.38828,44.94813],"type":"Point"}
}