{
  "type": "Feature",
  "properties": {
    "gn:admin1_code":"02",
    "gn:asciiname":"Ljesljani",
    "gn:country_code":"BA",
    "gn:dem":239,
    "gn:feature_class":"P",
    "gn:feature_code":"PPL",
    "gn:name":"Lje\u0161ljani",
    "gn:population":0,
    "gn:timezone":"Europe/Sarajevo",
    "iso:country":"BA",
    "name:bos_x_preferred":[
        "Lje\u0161ljani"
    ],
    "name:deu_x_preferred":[
        "Lje\u0161ljani"
    ],
    "name:fra_x_preferred":[
        "Lje\u0161ljani"
    ],
    "name:hrv_x_preferred":[
        "Lje\u0161ljani"
    ],
    "name:srp_x_preferred":[
        "\u0409\u0435\u0448\u0459\u0430\u043d\u0438"
    ],
    "wof:name":"Ljesljani",
    "wof:placetype":"locality"
},
  "geometry": {"coordinates":[16.48,45.09278],"type":"Point"}
}