{
  "type": "Feature",
  "properties": {
    "gn:admin1_code":"02",
    "gn:asciiname":"Ljesljani",
    "gn:country_code":"BA",
    "gn:dem":239,
    "gn:feature_class":"P",
    "gn:feature_code":"PPL",
    "gn:name":"Lje\u0161ljani",
    "gn:population":0,
    "gn:timezone":"Europe/Sarajevo",
    "iso:country":"BA",
    "name:und_x_variant":[
        "Lje\u0161ljani"
    ],
    "wof:name":"Ljesljani",
    "wof:placetype":"locality"
},
  "geometry": {"coordinates":[16.48,45.09278],"type":"Point"}
}