{
  "type": "Feature",
  "properties": {
    "gn:admin1_code":"02",
    "gn:asciiname":"Kovacevici",
    "gn:country_code":"BA",
    "gn:dem":90,
    "gn:feature_class":"P",
    "gn:feature_code":"PPL",
    "gn:name":"Kova\u010devi\u0107i",
    "gn:population":0,
    "gn:timezone":"Europe/Sarajevo",
    "iso:country":"BA",
    "wof:name":"Kovacevici",
    "wof:placetype":"locality"
},
  "geometry": {"coordinates":[17.95732000000001,45.06506],"type":"Point"}
}