{
  "type": "Feature",
  "properties": {
    "gn:admin1_code":"02",
    "gn:asciiname":"Mustanica",
    "gn:country_code":"BA",
    "gn:dem":264,
    "gn:feature_class":"P",
    "gn:feature_code":"PPL",
    "gn:name":"Mu\u0161tanica",
    "gn:population":0,
    "gn:timezone":"Europe/Sarajevo",
    "iso:country":"BA",
    "wof:name":"Mustanica",
    "wof:placetype":"locality"
},
  "geometry": {"coordinates":[16.61571,44.8692],"type":"Point"}
}