{
  "type": "Feature",
  "properties": {
    "gn:admin1_code":"02",
    "gn:asciiname":"Imamovici",
    "gn:country_code":"BA",
    "gn:dem":869,
    "gn:feature_class":"P",
    "gn:feature_code":"PPLL",
    "gn:name":"Imamovi\u0107i",
    "gn:population":0,
    "gn:timezone":"Europe/Sarajevo",
    "iso:country":"BA",
    "name:bos_x_preferred":[
        "Imamovi\u0107i"
    ],
    "name:fra_x_preferred":[
        "Imamovi\u0107i"
    ],
    "name:srp_x_preferred":[
        "\u0418\u043c\u0430\u043c\u043e\u0432\u0438\u045b\u0438"
    ],
    "name:und_x_variant":[
        "Imamovi\u0107i"
    ],
    "wof:name":"Imamovici",
    "wof:placetype":"locality"
},
  "geometry": {"coordinates":[18.61998,44.00661],"type":"Point"}
}