{
  "type": "Feature",
  "properties": {
    "gn:admin1_code":"01",
    "gn:asciiname":"Mejremici",
    "gn:country_code":"BA",
    "gn:dem":287,
    "gn:feature_class":"P",
    "gn:feature_code":"PPL",
    "gn:name":"Mejremi\u0107i",
    "gn:population":0,
    "gn:timezone":"Europe/Sarajevo",
    "iso:country":"BA",
    "wof:name":"Mejremici",
    "wof:placetype":"locality"
},
  "geometry": {"coordinates":[18.26215,44.72199000000001],"type":"Point"}
}