{
  "type": "Feature",
  "properties": {
    "gn:admin1_code":"01",
    "gn:asciiname":"Kostel",
    "gn:country_code":"BA",
    "gn:dem":218,
    "gn:feature_class":"P",
    "gn:feature_code":"PPL",
    "gn:name":"Kostel",
    "gn:population":0,
    "gn:timezone":"Europe/Sarajevo",
    "iso:country":"BA",
    "name:bos_x_preferred":[
        "Kostel"
    ],
    "name:ces_x_preferred":[
        "Kostel"
    ],
    "name:deu_x_preferred":[
        "Kostel"
    ],
    "name:fra_x_preferred":[
        "Kostel"
    ],
    "name:hun_x_preferred":[
        "Kostel"
    ],
    "name:nld_x_preferred":[
        "Kostel"
    ],
    "name:ron_x_preferred":[
        "Kostel"
    ],
    "name:sco_x_preferred":[
        "Kostel"
    ],
    "name:slv_x_preferred":[
        "Kostel"
    ],
    "name:spa_x_preferred":[
        "Kostel"
    ],
    "name:srp_x_preferred":[
        "\u041a\u043e\u0441\u0442\u0435\u043b"
    ],
    "wof:name":"Kostel",
    "wof:placetype":"locality"
},
  "geometry": {"coordinates":[15.90227,44.88291],"type":"Point"}
}