{
  "type": "Feature",
  "properties": {
    "gn:admin1_code":"01",
    "gn:asciiname":"Lucina",
    "gn:country_code":"BA",
    "gn:dem":657,
    "gn:feature_class":"P",
    "gn:feature_code":"PPL",
    "gn:name":"Lu\u010dina",
    "gn:population":0,
    "gn:timezone":"Europe/Sarajevo",
    "iso:country":"BA",
    "name:ceb_x_preferred":[
        "Lucina"
    ],
    "name:ces_x_preferred":[
        "Lucina"
    ],
    "name:deu_x_preferred":[
        "Lucina"
    ],
    "name:fra_x_preferred":[
        "Lucina"
    ],
    "name:hun_x_preferred":[
        "Lucina"
    ],
    "name:ita_x_preferred":[
        "Lucina"
    ],
    "name:nds_x_preferred":[
        "Lucina"
    ],
    "name:nor_x_preferred":[
        "Lucina"
    ],
    "name:ron_x_preferred":[
        "Lucina"
    ],
    "name:swe_x_preferred":[
        "Lucina"
    ],
    "wof:name":"Lucina",
    "wof:placetype":"locality"
},
  "geometry": {"coordinates":[17.1098,43.53086],"type":"Point"}
}