{
  "type": "Feature",
  "properties": {
    "gn:admin1_code":"02",
    "gn:asciiname":"Vrelo",
    "gn:country_code":"BA",
    "gn:dem":611,
    "gn:feature_class":"P",
    "gn:feature_code":"PPL",
    "gn:name":"Vrelo",
    "gn:population":0,
    "gn:timezone":"Europe/Sarajevo",
    "iso:country":"BA",
    "wof:name":"Vrelo",
    "wof:placetype":"locality"
},
  "geometry": {"coordinates":[18.88863,44.2677],"type":"Point"}
}