{
  "type": "Feature",
  "properties": {
    "gn:admin1_code":"02",
    "gn:asciiname":"Vrelo",
    "gn:country_code":"BA",
    "gn:dem":611,
    "gn:feature_class":"P",
    "gn:feature_code":"PPL",
    "gn:name":"Vrelo",
    "gn:population":0,
    "gn:timezone":"Europe/Sarajevo",
    "iso:country":"BA",
    "name:bos_x_preferred":[
        "Vrelo"
    ],
    "name:bul_x_preferred":[
        "\u0412\u0440\u0435\u043b\u043e"
    ],
    "name:ceb_x_preferred":[
        "Vrelo"
    ],
    "name:fra_x_preferred":[
        "Vrelo"
    ],
    "name:hrv_x_preferred":[
        "Vrelo"
    ],
    "name:mkd_x_preferred":[
        "\u0412\u0440\u0435\u043b\u043e"
    ],
    "name:slv_x_preferred":[
        "Vrelo"
    ],
    "name:srp_x_preferred":[
        "\u0412\u0440\u0435\u043b\u043e"
    ],
    "name:swe_x_preferred":[
        "Vrelo"
    ],
    "wof:name":"Vrelo",
    "wof:placetype":"locality"
},
  "geometry": {"coordinates":[18.88863,44.2677],"type":"Point"}
}