{
  "type": "Feature",
  "properties": {
    "gn:admin1_code":"02",
    "gn:asciiname":"Pucari",
    "gn:country_code":"BA",
    "gn:dem":292,
    "gn:feature_class":"P",
    "gn:feature_code":"PPL",
    "gn:name":"Pucari",
    "gn:population":0,
    "gn:timezone":"Europe/Sarajevo",
    "iso:country":"BA",
    "wof:name":"Pucari",
    "wof:placetype":"locality"
},
  "geometry": {"coordinates":[18.87794,44.39636],"type":"Point"}
}