{
  "type": "Feature",
  "properties": {
    "gn:admin1_code":"01",
    "gn:asciiname":"Brzice",
    "gn:country_code":"BA",
    "gn:dem":283,
    "gn:feature_class":"P",
    "gn:feature_code":"PPL",
    "gn:name":"Brzice",
    "gn:population":0,
    "gn:timezone":"Europe/Sarajevo",
    "iso:country":"BA",
    "name:azb_x_preferred":[
        "\u0628\u0631\u0632\u06cc\u062a\u0633\u0647"
    ],
    "name:ceb_x_preferred":[
        "Brzice"
    ],
    "name:ces_x_preferred":[
        "Brzice"
    ],
    "name:deu_x_preferred":[
        "Brzice"
    ],
    "name:eus_x_preferred":[
        "Brzice"
    ],
    "name:fas_x_preferred":[
        "\u0628\u0631\u0632\u06cc\u062a\u0633\u0647"
    ],
    "name:fra_x_preferred":[
        "Brzice"
    ],
    "name:hun_x_preferred":[
        "Brzice"
    ],
    "name:ita_x_preferred":[
        "Brzice"
    ],
    "name:msa_x_preferred":[
        "Brzice"
    ],
    "name:nld_x_preferred":[
        "Brzice"
    ],
    "name:pol_x_preferred":[
        "Brzice"
    ],
    "name:por_x_preferred":[
        "Brzice"
    ],
    "name:slk_x_preferred":[
        "Brzice"
    ],
    "name:spa_x_preferred":[
        "Brzice"
    ],
    "name:srp_x_preferred":[
        "\u0411\u0440\u0437\u0438\u0446\u0435"
    ],
    "name:swe_x_preferred":[
        "Brzice"
    ],
    "name:urd_x_preferred":[
        "\u0628\u0631\u0632\u06a9\u06d2"
    ],
    "name:vie_x_preferred":[
        "Brzice"
    ],
    "wof:name":"Brzice",
    "wof:placetype":"locality"
},
  "geometry": {"coordinates":[17.44784,43.33852],"type":"Point"}
}