{
  "type": "Feature",
  "properties": {
    "gn:admin1_code":"01",
    "gn:asciiname":"Brzice",
    "gn:country_code":"BA",
    "gn:dem":283,
    "gn:feature_class":"P",
    "gn:feature_code":"PPL",
    "gn:name":"Brzice",
    "gn:population":0,
    "gn:timezone":"Europe/Sarajevo",
    "iso:country":"BA",
    "wof:name":"Brzice",
    "wof:placetype":"locality"
},
  "geometry": {"coordinates":[17.44784,43.33852],"type":"Point"}
}