{
  "type": "Feature",
  "properties": {
    "gn:admin1_code":"02",
    "gn:asciiname":"Licani",
    "gn:country_code":"BA",
    "gn:dem":282,
    "gn:feature_class":"P",
    "gn:feature_code":"PPL",
    "gn:name":"Li\u010dani",
    "gn:population":0,
    "gn:timezone":"Europe/Sarajevo",
    "iso:country":"BA",
    "wof:name":"Licani",
    "wof:placetype":"locality"
},
  "geometry": {"coordinates":[16.75133,45.03587],"type":"Point"}
}