{
  "type": "Feature",
  "properties": {
    "gn:admin1_code":"02",
    "gn:asciiname":"Hotocina",
    "gn:country_code":"BA",
    "gn:dem":985,
    "gn:feature_class":"P",
    "gn:feature_code":"PPLL",
    "gn:name":"Hoto\u010dina",
    "gn:population":0,
    "gn:timezone":"Europe/Sarajevo",
    "iso:country":"BA",
    "name:bos_x_preferred":[
        "Hoto\u010dina"
    ],
    "name:ceb_x_preferred":[
        "Hoto\u010dina"
    ],
    "name:fra_x_preferred":[
        "Hoto\u010dina"
    ],
    "name:srp_x_preferred":[
        "\u0425\u043e\u0442\u043e\u0447\u0438\u043d\u0430"
    ],
    "name:swe_x_preferred":[
        "Hoto\u010dina"
    ],
    "name:und_x_variant":[
        "Hoti\u010dina"
    ],
    "wof:name":"Hotocina",
    "wof:placetype":"locality"
},
  "geometry": {"coordinates":[18.66531,43.82463],"type":"Point"}
}