{
  "type": "Feature",
  "properties": {
    "gn:admin1_code":"02",
    "gn:asciiname":"Boljanovici",
    "gn:country_code":"BA",
    "gn:dem":1032,
    "gn:feature_class":"P",
    "gn:feature_code":"PPL",
    "gn:name":"Boljanovi\u0107i",
    "gn:population":0,
    "gn:timezone":"Europe/Sarajevo",
    "iso:country":"BA",
    "wof:name":"Boljanovici",
    "wof:placetype":"locality"
},
  "geometry": {"coordinates":[18.46821,43.60272],"type":"Point"}
}