{
  "type": "Feature",
  "properties": {
    "gn:admin1_code":"02",
    "gn:asciiname":"Zabrda",
    "gn:country_code":"BA",
    "gn:dem":833,
    "gn:feature_class":"P",
    "gn:feature_code":"PPL",
    "gn:name":"Zabrda",
    "gn:population":0,
    "gn:timezone":"Europe/Sarajevo",
    "iso:country":"BA",
    "wof:name":"Zabrda",
    "wof:placetype":"locality"
},
  "geometry": {"coordinates":[18.69067,44.05479],"type":"Point"}
}