{
  "type": "Feature",
  "properties": {
    "gn:admin1_code":"02",
    "gn:asciiname":"Bosanska Raca",
    "gn:country_code":"BA",
    "gn:dem":81,
    "gn:feature_class":"P",
    "gn:feature_code":"PPL",
    "gn:name":"Bosanska Ra\u010da",
    "gn:population":0,
    "gn:timezone":"Europe/Sarajevo",
    "iso:country":"BA",
    "wof:name":"Bosanska Raca",
    "wof:placetype":"locality"
},
  "geometry": {"coordinates":[19.33356,44.89399],"type":"Point"}
}