{
  "type": "Feature",
  "properties": {
    "gn:admin1_code":"01",
    "gn:asciiname":"Doljani",
    "gn:country_code":"BA",
    "gn:dem":578,
    "gn:feature_class":"P",
    "gn:feature_code":"PPLL",
    "gn:name":"Doljani",
    "gn:population":0,
    "gn:timezone":"Europe/Sarajevo",
    "iso:country":"BA",
    "name:ara_x_preferred":[
        "\u062f\u0648\u0644\u064a\u0627\u0646\u064a"
    ],
    "name:bos_x_preferred":[
        "Doljani"
    ],
    "name:fra_x_preferred":[
        "Doljani"
    ],
    "name:hrv_x_preferred":[
        "Doljani"
    ],
    "name:hun_x_preferred":[
        "Doljani"
    ],
    "name:nld_x_preferred":[
        "Doljani"
    ],
    "name:slv_x_preferred":[
        "Doljani"
    ],
    "name:spa_x_preferred":[
        "Doljani"
    ],
    "name:srp_x_preferred":[
        "\u0414\u043e\u0459\u0430\u043d\u0438"
    ],
    "wof:name":"Doljani",
    "wof:placetype":"locality"
},
  "geometry": {"coordinates":[17.66362,43.69323],"type":"Point"}
}