{
  "type": "Feature",
  "properties": {
    "gn:admin1_code":"01",
    "gn:asciiname":"Doljani",
    "gn:country_code":"BA",
    "gn:dem":578,
    "gn:feature_class":"P",
    "gn:feature_code":"PPLL",
    "gn:name":"Doljani",
    "gn:population":0,
    "gn:timezone":"Europe/Sarajevo",
    "iso:country":"BA",
    "wof:name":"Doljani",
    "wof:placetype":"locality"
},
  "geometry": {"coordinates":[17.66362,43.69323],"type":"Point"}
}