{
  "type": "Feature",
  "properties": {
    "gn:admin1_code":"01",
    "gn:asciiname":"Hotkovci",
    "gn:country_code":"BA",
    "gn:dem":936,
    "gn:feature_class":"P",
    "gn:feature_code":"PPLL",
    "gn:name":"Hotkovci",
    "gn:population":0,
    "gn:timezone":"Europe/Sarajevo",
    "iso:country":"BA",
    "name:bos_x_preferred":[
        "Hotkovci"
    ],
    "name:fra_x_preferred":[
        "Hotkovci"
    ],
    "name:hrv_x_preferred":[
        "Hotkovci"
    ],
    "name:srp_x_preferred":[
        "\u0425\u043e\u0442\u043a\u043e\u0432\u0446\u0438"
    ],
    "name:und_x_variant":[
        "Potkovci"
    ],
    "wof:name":"Hotkovci",
    "wof:placetype":"locality"
},
  "geometry": {"coordinates":[16.77457,44.20738],"type":"Point"}
}