{
  "type": "Feature",
  "properties": {
    "gn:admin1_code":"02",
    "gn:asciiname":"Gornja Ljubogosta",
    "gn:country_code":"BA",
    "gn:dem":947,
    "gn:feature_class":"P",
    "gn:feature_code":"PPL",
    "gn:name":"Gornja Ljubogo\u0161ta",
    "gn:population":0,
    "gn:timezone":"Europe/Sarajevo",
    "iso:country":"BA",
    "name:und_x_variant":[
        "Karaula",
        "Gornja Ljubogo\u0161ta"
    ],
    "wof:name":"Gornja Ljubogosta",
    "wof:placetype":"locality"
},
  "geometry": {"coordinates":[18.57449,43.86126],"type":"Point"}
}