{
  "type": "Feature",
  "properties": {
    "gn:admin1_code":"02",
    "gn:asciiname":"Slatkodo",
    "gn:country_code":"BA",
    "gn:dem":835,
    "gn:feature_class":"P",
    "gn:feature_code":"PPL",
    "gn:name":"Slatkodo",
    "gn:population":0,
    "gn:timezone":"Europe/Sarajevo",
    "iso:country":"BA",
    "wof:name":"Slatkodo",
    "wof:placetype":"locality"
},
  "geometry": {"coordinates":[18.08318,43.0844],"type":"Point"}
}