{
  "type": "Feature",
  "properties": {
    "gn:admin1_code":"01",
    "gn:asciiname":"Zabljak",
    "gn:country_code":"BA",
    "gn:dem":715,
    "gn:feature_class":"P",
    "gn:feature_code":"PPL",
    "gn:name":"\u017dabljak",
    "gn:population":0,
    "gn:timezone":"Europe/Sarajevo",
    "iso:country":"BA",
    "name:und_x_variant":[
        "Donji \u017dabljak",
        "\u017dabljak"
    ],
    "wof:name":"Zabljak",
    "wof:placetype":"locality"
},
  "geometry": {"coordinates":[16.99669,43.80978],"type":"Point"}
}