{
  "type": "Feature",
  "properties": {
    "gn:admin1_code":"01",
    "gn:asciiname":"Zabljak",
    "gn:country_code":"BA",
    "gn:dem":715,
    "gn:feature_class":"P",
    "gn:feature_code":"PPL",
    "gn:name":"\u017dabljak",
    "gn:population":0,
    "gn:timezone":"Europe/Sarajevo",
    "iso:country":"BA",
    "name:bos_x_preferred":[
        "\u017dabljak"
    ],
    "name:ceb_x_preferred":[
        "\u017dabljak"
    ],
    "name:fra_x_preferred":[
        "\u017dabljak"
    ],
    "name:hrv_x_preferred":[
        "\u017dabljak"
    ],
    "name:swe_x_preferred":[
        "\u017dabljak"
    ],
    "name:und_x_variant":[
        "Donji \u017dabljak",
        "\u017dabljak"
    ],
    "name:urd_x_preferred":[
        "\u0632\u0627\u0628\u0644\u062c\u06a9"
    ],
    "wof:name":"Zabljak",
    "wof:placetype":"locality"
},
  "geometry": {"coordinates":[16.99669,43.80978],"type":"Point"}
}