{
  "type": "Feature",
  "properties": {
    "gn:admin1_code":"01",
    "gn:asciiname":"Zascenje",
    "gn:country_code":"BA",
    "gn:dem":981,
    "gn:feature_class":"P",
    "gn:feature_code":"PPL",
    "gn:name":"Zas\u0107enje",
    "gn:population":0,
    "gn:timezone":"Europe/Sarajevo",
    "iso:country":"BA",
    "wof:name":"Zascenje",
    "wof:placetype":"locality"
},
  "geometry": {"coordinates":[18.17111,43.52139],"type":"Point"}
}