{
  "type": "Feature",
  "properties": {
    "gn:admin1_code":"02",
    "gn:asciiname":"Pavicici",
    "gn:country_code":"BA",
    "gn:dem":869,
    "gn:feature_class":"P",
    "gn:feature_code":"PPL",
    "gn:name":"Pavi\u010di\u0107i",
    "gn:population":0,
    "gn:timezone":"Europe/Sarajevo",
    "iso:country":"BA",
    "name:bos_x_preferred":[
        "Pavi\u010di\u0107i"
    ],
    "name:fra_x_preferred":[
        "Pavi\u010di\u0107i"
    ],
    "name:srp_x_preferred":[
        "\u041f\u0430\u0432\u0438\u0447\u0438\u045b\u0438"
    ],
    "wof:name":"Pavicici",
    "wof:placetype":"locality"
},
  "geometry": {"coordinates":[18.79843,43.86524],"type":"Point"}
}