{
  "type": "Feature",
  "properties": {
    "gn:admin1_code":"01",
    "gn:asciiname":"Gola Kosa",
    "gn:country_code":"BA",
    "gn:dem":649,
    "gn:feature_class":"P",
    "gn:feature_code":"PPL",
    "gn:name":"Gola Kosa",
    "gn:population":0,
    "gn:timezone":"Europe/Sarajevo",
    "iso:country":"BA",
    "wof:name":"Gola Kosa",
    "wof:placetype":"locality"
},
  "geometry": {"coordinates":[17.86326,44.16199],"type":"Point"}
}