{
  "type": "Feature",
  "properties": {
    "gn:admin1_code":"02",
    "gn:asciiname":"Lakici",
    "gn:country_code":"BA",
    "gn:dem":829,
    "gn:feature_class":"P",
    "gn:feature_code":"PPL",
    "gn:name":"Laki\u0107i",
    "gn:population":0,
    "gn:timezone":"Europe/Sarajevo",
    "iso:country":"BA",
    "wof:name":"Lakici",
    "wof:placetype":"locality"
},
  "geometry": {"coordinates":[17.01408,44.41977],"type":"Point"}
}