{
  "type": "Feature",
  "properties": {
    "gn:admin1_code":"02",
    "gn:asciiname":"Glavici",
    "gn:country_code":"BA",
    "gn:dem":473,
    "gn:feature_class":"P",
    "gn:feature_code":"PPL",
    "gn:name":"Glavi\u0107i",
    "gn:population":0,
    "gn:timezone":"Europe/Sarajevo",
    "iso:country":"BA",
    "wof:name":"Glavici",
    "wof:placetype":"locality"
},
  "geometry": {"coordinates":[17.19734,44.65884000000001],"type":"Point"}
}