{
  "type": "Feature",
  "properties": {
    "gn:admin1_code":"02",
    "gn:asciiname":"Donji Drinici",
    "gn:country_code":"BA",
    "gn:dem":301,
    "gn:feature_class":"P",
    "gn:feature_code":"PPL",
    "gn:name":"Donji Drini\u0107i",
    "gn:population":0,
    "gn:timezone":"Europe/Sarajevo",
    "iso:country":"BA",
    "wof:name":"Donji Drinici",
    "wof:placetype":"locality"
},
  "geometry": {"coordinates":[16.87524,44.70262],"type":"Point"}
}