{
  "type": "Feature",
  "properties": {
    "gn:admin1_code":"02",
    "gn:asciiname":"Lopatici",
    "gn:country_code":"BA",
    "gn:dem":1238,
    "gn:feature_class":"P",
    "gn:feature_code":"PPL",
    "gn:name":"Lopati\u0107i",
    "gn:population":0,
    "gn:timezone":"Europe/Sarajevo",
    "iso:country":"BA",
    "wof:name":"Lopatici",
    "wof:placetype":"locality"
},
  "geometry": {"coordinates":[18.68161,43.91862],"type":"Point"}
}