{
  "type": "Feature",
  "properties": {
    "gn:admin1_code":"01",
    "gn:asciiname":"Glamoc",
    "gn:country_code":"BA",
    "gn:dem":431,
    "gn:feature_class":"P",
    "gn:feature_code":"PPLL",
    "gn:name":"Glamo\u010d",
    "gn:population":0,
    "gn:timezone":"Europe/Sarajevo",
    "iso:country":"BA",
    "name:bos_x_preferred":[
        "Glamo\u010d"
    ],
    "name:ceb_x_preferred":[
        "Glamo\u010d"
    ],
    "name:fra_x_preferred":[
        "Glamo\u010d"
    ],
    "name:swe_x_preferred":[
        "Glamo\u010d"
    ],
    "name:und_x_variant":[
        "Glamo\u010d"
    ],
    "wof:name":"Glamoc",
    "wof:placetype":"locality"
},
  "geometry": {"coordinates":[18.94385,43.67066],"type":"Point"}
}