{
  "type": "Feature",
  "properties": {
    "gn:admin1_code":"02",
    "gn:asciiname":"Donja Lepenica",
    "gn:country_code":"BA",
    "gn:dem":235,
    "gn:feature_class":"P",
    "gn:feature_code":"PPLL",
    "gn:name":"Donja Lepenica",
    "gn:population":0,
    "gn:timezone":"Europe/Sarajevo",
    "iso:country":"BA",
    "wof:name":"Donja Lepenica",
    "wof:placetype":"locality"
},
  "geometry": {"coordinates":[17.62165,45.04264000000001],"type":"Point"}
}