{
  "type": "Feature",
  "properties": {
    "gn:admin1_code":"02",
    "gn:asciiname":"Sipovici",
    "gn:country_code":"BA",
    "gn:dem":498,
    "gn:feature_class":"P",
    "gn:feature_code":"PPL",
    "gn:name":"\u0160ipovi\u0107i",
    "gn:population":0,
    "gn:timezone":"Europe/Sarajevo",
    "iso:country":"BA",
    "wof:name":"Sipovici",
    "wof:placetype":"locality"
},
  "geometry": {"coordinates":[19.30556,43.79972],"type":"Point"}
}