{
  "type": "Feature",
  "properties": {
    "gn:admin1_code":"01",
    "gn:asciiname":"Privorac",
    "gn:country_code":"BA",
    "gn:dem":85,
    "gn:feature_class":"P",
    "gn:feature_code":"PPL",
    "gn:name":"Privorac",
    "gn:population":0,
    "gn:timezone":"Europe/Sarajevo",
    "iso:country":"BA",
    "wof:name":"Privorac",
    "wof:placetype":"locality"
},
  "geometry": {"coordinates":[17.80172,43.31779],"type":"Point"}
}