{
  "type": "Feature",
  "properties": {
    "gn:admin1_code":"01",
    "gn:asciiname":"Strijezevo",
    "gn:country_code":"BA",
    "gn:dem":948,
    "gn:feature_class":"P",
    "gn:feature_code":"PPL",
    "gn:name":"Strije\u017eevo",
    "gn:population":0,
    "gn:timezone":"Europe/Sarajevo",
    "iso:country":"BA",
    "name:und_x_variant":[
        "Stri\u017eero",
        "Stri\u017eevo",
        "Strije\u017eevo"
    ],
    "wof:name":"Strijezevo",
    "wof:placetype":"locality"
},
  "geometry": {"coordinates":[18.28966,44.09522],"type":"Point"}
}