{
  "type": "Feature",
  "properties": {
    "gn:admin1_code":"01",
    "gn:asciiname":"Miladinovici",
    "gn:country_code":"BA",
    "gn:dem":242,
    "gn:feature_class":"P",
    "gn:feature_code":"PPL",
    "gn:name":"Miladinovi\u0107i",
    "gn:population":0,
    "gn:timezone":"Europe/Sarajevo",
    "iso:country":"BA",
    "wof:name":"Miladinovici",
    "wof:placetype":"locality"
},
  "geometry": {"coordinates":[16.58427,44.80117],"type":"Point"}
}