{
  "type": "Feature",
  "properties": {
    "gn:admin1_code":"01",
    "gn:asciiname":"Cerovi Doci",
    "gn:country_code":"BA",
    "gn:dem":960,
    "gn:feature_class":"P",
    "gn:feature_code":"PPLL",
    "gn:name":"Cerovi Doci",
    "gn:population":0,
    "gn:timezone":"Europe/Sarajevo",
    "iso:country":"BA",
    "wof:name":"Cerovi Doci",
    "wof:placetype":"locality"
},
  "geometry": {"coordinates":[17.41054,43.47556],"type":"Point"}
}