{
  "type": "Feature",
  "properties": {
    "gn:admin1_code":"02",
    "gn:asciiname":"Borija",
    "gn:country_code":"BA",
    "gn:dem":1108,
    "gn:feature_class":"P",
    "gn:feature_code":"PPL",
    "gn:name":"Borija",
    "gn:population":0,
    "gn:timezone":"Europe/Sarajevo",
    "iso:country":"BA",
    "name:und_x_variant":[
        "Borja",
        "Borija"
    ],
    "wof:name":"Borija",
    "wof:placetype":"locality"
},
  "geometry": {"coordinates":[18.5282,43.50301],"type":"Point"}
}