{
  "type": "Feature",
  "properties": {
    "gn:admin1_code":"02",
    "gn:asciiname":"Prodanovici",
    "gn:country_code":"BA",
    "gn:dem":203,
    "gn:feature_class":"P",
    "gn:feature_code":"PPL",
    "gn:name":"Prodanovi\u0107i",
    "gn:population":0,
    "gn:timezone":"Europe/Sarajevo",
    "iso:country":"BA",
    "wof:name":"Prodanovici",
    "wof:placetype":"locality"
},
  "geometry": {"coordinates":[17.75171,44.83538],"type":"Point"}
}