{
  "type": "Feature",
  "properties": {
    "gn:admin1_code":"02",
    "gn:asciiname":"Blanusa",
    "gn:country_code":"BA",
    "gn:dem":274,
    "gn:feature_class":"P",
    "gn:feature_code":"PPL",
    "gn:name":"Blanu\u0161a",
    "gn:population":0,
    "gn:timezone":"Europe/Sarajevo",
    "iso:country":"BA",
    "wof:name":"Blanusa",
    "wof:placetype":"locality"
},
  "geometry": {"coordinates":[16.38552,44.87428],"type":"Point"}
}