{
  "type": "Feature",
  "properties": {
    "gn:admin1_code":"02",
    "gn:asciiname":"Arambasici",
    "gn:country_code":"BA",
    "gn:dem":201,
    "gn:feature_class":"P",
    "gn:feature_code":"PPL",
    "gn:name":"Aramba\u0161i\u0107i",
    "gn:population":0,
    "gn:timezone":"Europe/Sarajevo",
    "iso:country":"BA",
    "wof:name":"Arambasici",
    "wof:placetype":"locality"
},
  "geometry": {"coordinates":[17.95612999999999,44.95424000000001],"type":"Point"}
}