{
  "type": "Feature",
  "properties": {
    "gn:admin1_code":"02",
    "gn:asciiname":"Mrcevci",
    "gn:country_code":"BA",
    "gn:dem":107,
    "gn:feature_class":"P",
    "gn:feature_code":"PPLL",
    "gn:name":"Mr\u010devci",
    "gn:population":0,
    "gn:timezone":"Europe/Sarajevo",
    "iso:country":"BA",
    "wof:name":"Mrcevci",
    "wof:placetype":"locality"
},
  "geometry": {"coordinates":[17.35082,44.97546],"type":"Point"}
}