{
  "type": "Feature",
  "properties": {
    "gn:admin1_code":"02",
    "gn:asciiname":"Berkovici",
    "gn:country_code":"BA",
    "gn:dem":882,
    "gn:feature_class":"P",
    "gn:feature_code":"PPLL",
    "gn:name":"Berkovi\u0107i",
    "gn:population":0,
    "gn:timezone":"Europe/Sarajevo",
    "iso:country":"BA",
    "name:bos_x_preferred":[
        "Berkovi\u0107i"
    ],
    "name:fra_x_preferred":[
        "Berkovi\u0107i"
    ],
    "name:srp_x_preferred":[
        "\u0411\u0435\u0440\u043a\u043e\u0432\u0438\u045b\u0438"
    ],
    "name:und_x_variant":[
        "Berkovi\u0107i"
    ],
    "wof:name":"Berkovici",
    "wof:placetype":"locality"
},
  "geometry": {"coordinates":[19.02097,43.89782],"type":"Point"}
}