{
  "type": "Feature",
  "properties": {
    "gn:admin1_code":"02",
    "gn:asciiname":"Vakuf",
    "gn:country_code":"BA",
    "gn:dem":104,
    "gn:feature_class":"P",
    "gn:feature_code":"PPL",
    "gn:name":"Vakuf",
    "gn:population":0,
    "gn:timezone":"Europe/Sarajevo",
    "iso:country":"BA",
    "wof:name":"Vakuf",
    "wof:placetype":"locality"
},
  "geometry": {"coordinates":[17.35665,44.99219],"type":"Point"}
}