{
  "type": "Feature",
  "properties": {
    "gn:admin1_code":"01",
    "gn:asciiname":"Devetine",
    "gn:country_code":"BA",
    "gn:dem":204,
    "gn:feature_class":"P",
    "gn:feature_code":"PPL",
    "gn:name":"Devetine",
    "gn:population":0,
    "gn:timezone":"Europe/Sarajevo",
    "iso:country":"BA",
    "wof:name":"Devetine",
    "wof:placetype":"locality"
},
  "geometry": {"coordinates":[18.15549,44.4905],"type":"Point"}
}