{
  "type": "Feature",
  "properties": {
    "gn:admin1_code":"01",
    "gn:asciiname":"Ribarici",
    "gn:country_code":"BA",
    "gn:dem":498,
    "gn:feature_class":"P",
    "gn:feature_code":"PPL",
    "gn:name":"Ribari\u0107i",
    "gn:population":0,
    "gn:timezone":"Europe/Sarajevo",
    "iso:country":"BA",
    "name:bos_x_preferred":[
        "Ribari\u0107i"
    ],
    "name:fra_x_preferred":[
        "Ribari\u0107i"
    ],
    "name:pol_x_preferred":[
        "Ribari\u0107i"
    ],
    "wof:name":"Ribarici",
    "wof:placetype":"locality"
},
  "geometry": {"coordinates":[18.27629,43.93372],"type":"Point"}
}