{
  "type": "Feature",
  "properties": {
    "gn:admin1_code":"01",
    "gn:asciiname":"Strazbenica",
    "gn:country_code":"BA",
    "gn:dem":1135,
    "gn:feature_class":"P",
    "gn:feature_code":"PPL",
    "gn:name":"Stra\u017ebenica",
    "gn:population":0,
    "gn:timezone":"Europe/Sarajevo",
    "iso:country":"BA",
    "wof:name":"Strazbenica",
    "wof:placetype":"locality"
},
  "geometry": {"coordinates":[17.1879,44.00976],"type":"Point"}
}