{
  "type": "Feature",
  "properties": {
    "gn:admin1_code":"01",
    "gn:asciiname":"Hrasno Gornje",
    "gn:country_code":"BA",
    "gn:dem":513,
    "gn:feature_class":"P",
    "gn:feature_code":"PPL",
    "gn:name":"Hrasno Gornje",
    "gn:population":0,
    "gn:timezone":"Europe/Sarajevo",
    "iso:country":"BA",
    "name:und_x_variant":[
        "Hrasno",
        "Hrasno Gornje"
    ],
    "wof:name":"Hrasno Gornje",
    "wof:placetype":"locality"
},
  "geometry": {"coordinates":[18.85488,44.50283],"type":"Point"}
}