{
  "type": "Feature",
  "properties": {
    "gn:admin1_code":"01",
    "gn:asciiname":"Potkraj",
    "gn:country_code":"BA",
    "gn:dem":1181,
    "gn:feature_class":"P",
    "gn:feature_code":"PPL",
    "gn:name":"Potkraj",
    "gn:population":0,
    "gn:timezone":"Europe/Sarajevo",
    "iso:country":"BA",
    "wof:name":"Potkraj",
    "wof:placetype":"locality"
},
  "geometry": {"coordinates":[17.69581,44.05441],"type":"Point"}
}