{
  "type": "Feature",
  "properties": {
    "gn:admin1_code":"02",
    "gn:asciiname":"Seslija",
    "gn:country_code":"BA",
    "gn:dem":127,
    "gn:feature_class":"P",
    "gn:feature_code":"PPL",
    "gn:name":"\u0160e\u0161lija",
    "gn:population":0,
    "gn:timezone":"Europe/Sarajevo",
    "iso:country":"BA",
    "wof:name":"Seslija",
    "wof:placetype":"locality"
},
  "geometry": {"coordinates":[18.06092,44.85536],"type":"Point"}
}