{
  "type": "Feature",
  "properties": {
    "gn:admin1_code":"01",
    "gn:asciiname":"Latinovici",
    "gn:country_code":"BA",
    "gn:dem":761,
    "gn:feature_class":"P",
    "gn:feature_code":"PPL",
    "gn:name":"Latinovi\u0107i",
    "gn:population":0,
    "gn:timezone":"Europe/Sarajevo",
    "iso:country":"BA",
    "wof:name":"Latinovici",
    "wof:placetype":"locality"
},
  "geometry": {"coordinates":[16.43802,44.57093],"type":"Point"}
}