{
  "type": "Feature",
  "properties": {
    "gn:admin1_code":"01",
    "gn:asciiname":"Zvizde",
    "gn:country_code":"BA",
    "gn:dem":702,
    "gn:feature_class":"P",
    "gn:feature_code":"PPL",
    "gn:name":"Zvizde",
    "gn:population":0,
    "gn:timezone":"Europe/Sarajevo",
    "iso:country":"BA",
    "wof:name":"Zvizde",
    "wof:placetype":"locality"
},
  "geometry": {"coordinates":[17.58866,43.94285],"type":"Point"}
}