{
  "type": "Feature",
  "properties": {
    "gn:admin1_code":"02",
    "gn:asciiname":"Nova Ovcara",
    "gn:country_code":"BA",
    "gn:dem":1175,
    "gn:feature_class":"P",
    "gn:feature_code":"PPL",
    "gn:name":"Nova Ov\u010dara",
    "gn:population":0,
    "gn:timezone":"Europe/Sarajevo",
    "iso:country":"BA",
    "wof:name":"Nova Ovcara",
    "wof:placetype":"locality"
},
  "geometry": {"coordinates":[16.78565,44.29006],"type":"Point"}
}