{
  "type": "Feature",
  "properties": {
    "gn:admin1_code":"02",
    "gn:asciiname":"Berusica",
    "gn:country_code":"BA",
    "gn:dem":1319,
    "gn:feature_class":"P",
    "gn:feature_code":"PPL",
    "gn:name":"Beru\u0161ica",
    "gn:population":0,
    "gn:timezone":"Europe/Sarajevo",
    "iso:country":"BA",
    "name:und_x_variant":[
        "Beru\u0161ica"
    ],
    "wof:name":"Berusica",
    "wof:placetype":"locality"
},
  "geometry": {"coordinates":[18.64307,43.16217],"type":"Point"}
}