{
  "type": "Feature",
  "properties": {
    "gn:admin1_code":"02",
    "gn:asciiname":"Colici",
    "gn:country_code":"BA",
    "gn:dem":174,
    "gn:feature_class":"P",
    "gn:feature_code":"PPL",
    "gn:name":"\u010coli\u0107i",
    "gn:population":0,
    "gn:timezone":"Europe/Sarajevo",
    "iso:country":"BA",
    "wof:name":"Colici",
    "wof:placetype":"locality"
},
  "geometry": {"coordinates":[17.83996,44.82219],"type":"Point"}
}