{
  "type": "Feature",
  "properties": {
    "gn:admin1_code":"01",
    "gn:asciiname":"Dokanj",
    "gn:country_code":"BA",
    "gn:dem":326,
    "gn:feature_class":"P",
    "gn:feature_code":"PPL",
    "gn:name":"Dokanj",
    "gn:population":0,
    "gn:timezone":"Europe/Sarajevo",
    "iso:country":"BA",
    "wof:name":"Dokanj",
    "wof:placetype":"locality"
},
  "geometry": {"coordinates":[18.68271,44.59218],"type":"Point"}
}