{
  "type": "Feature",
  "properties": {
    "gn:admin1_code":"01",
    "gn:asciiname":"Gunjakovici",
    "gn:country_code":"BA",
    "gn:dem":916,
    "gn:feature_class":"P",
    "gn:feature_code":"PPL",
    "gn:name":"Gunjakovi\u0107i",
    "gn:population":0,
    "gn:timezone":"Europe/Sarajevo",
    "iso:country":"BA",
    "wof:name":"Gunjakovici",
    "wof:placetype":"locality"
},
  "geometry": {"coordinates":[17.61438,44.19198],"type":"Point"}
}