{
  "type": "Feature",
  "properties": {
    "gn:admin1_code":"01",
    "gn:asciiname":"Osojnica",
    "gn:country_code":"BA",
    "gn:dem":616,
    "gn:feature_class":"P",
    "gn:feature_code":"PPL",
    "gn:name":"Osojnica",
    "gn:population":0,
    "gn:timezone":"Europe/Sarajevo",
    "iso:country":"BA",
    "name:bos_x_preferred":[
        "Osojnica"
    ],
    "name:bul_x_preferred":[
        "\u041e\u0441\u043e\u0439\u043d\u0438\u0446\u0430"
    ],
    "name:hrv_x_preferred":[
        "Osojnica"
    ],
    "name:nld_x_preferred":[
        "Osojnica"
    ],
    "name:pol_x_preferred":[
        "Osojnica"
    ],
    "name:ron_x_preferred":[
        "Osojnica"
    ],
    "name:slv_x_preferred":[
        "Osojnica"
    ],
    "name:ukr_x_preferred":[
        "\u041e\u0441\u043e\u0439\u043d\u0438\u0446\u044f"
    ],
    "wof:name":"Osojnica",
    "wof:placetype":"locality"
},
  "geometry": {"coordinates":[18.04328,43.89822],"type":"Point"}
}