{
  "type": "Feature",
  "properties": {
    "gn:admin1_code":"01",
    "gn:asciiname":"Osojnica",
    "gn:country_code":"BA",
    "gn:dem":616,
    "gn:feature_class":"P",
    "gn:feature_code":"PPL",
    "gn:name":"Osojnica",
    "gn:population":0,
    "gn:timezone":"Europe/Sarajevo",
    "iso:country":"BA",
    "wof:name":"Osojnica",
    "wof:placetype":"locality"
},
  "geometry": {"coordinates":[18.04328,43.89822],"type":"Point"}
}