{
  "type": "Feature",
  "properties": {
    "gn:admin1_code":"02",
    "gn:asciiname":"Miosici",
    "gn:country_code":"BA",
    "gn:dem":1012,
    "gn:feature_class":"P",
    "gn:feature_code":"PPLL",
    "gn:name":"Mio\u0161i\u0107i",
    "gn:population":0,
    "gn:timezone":"Europe/Sarajevo",
    "iso:country":"BA",
    "name:und_x_variant":[
        "Mio\u0161i\u0107i"
    ],
    "wof:name":"Miosici",
    "wof:placetype":"locality"
},
  "geometry": {"coordinates":[18.77116,43.82956],"type":"Point"}
}