{
  "type": "Feature",
  "properties": {
    "gn:admin1_code":"02",
    "gn:asciiname":"Miosici",
    "gn:country_code":"BA",
    "gn:dem":1012,
    "gn:feature_class":"P",
    "gn:feature_code":"PPLL",
    "gn:name":"Mio\u0161i\u0107i",
    "gn:population":0,
    "gn:timezone":"Europe/Sarajevo",
    "iso:country":"BA",
    "name:bos_x_preferred":[
        "Mio\u0161i\u0107i"
    ],
    "name:fra_x_preferred":[
        "Mio\u0161i\u0107i"
    ],
    "name:srp_x_preferred":[
        "\u041c\u0438\u043e\u0448\u0438\u045b\u0438"
    ],
    "wof:name":"Miosici",
    "wof:placetype":"locality"
},
  "geometry": {"coordinates":[18.77116,43.82956],"type":"Point"}
}