{
  "type": "Feature",
  "properties": {
    "gn:admin1_code":"01",
    "gn:asciiname":"Borovac",
    "gn:country_code":"BA",
    "gn:dem":407,
    "gn:feature_class":"P",
    "gn:feature_code":"PPLL",
    "gn:name":"Borovac",
    "gn:population":0,
    "gn:timezone":"Europe/Sarajevo",
    "iso:country":"BA",
    "name:bos_x_preferred":[
        "Borovac"
    ],
    "name:bul_x_preferred":[
        "\u0411\u043e\u0440\u043e\u0432\u0430\u0446"
    ],
    "name:ceb_x_preferred":[
        "Borovac"
    ],
    "name:deu_x_preferred":[
        "Borovac"
    ],
    "name:fra_x_preferred":[
        "Borovac"
    ],
    "name:hrv_x_preferred":[
        "Borovac"
    ],
    "name:hun_x_preferred":[
        "Borovac"
    ],
    "name:nld_x_preferred":[
        "Borovac"
    ],
    "name:slv_x_preferred":[
        "Borovac"
    ],
    "name:srp_x_preferred":[
        "\u0411\u043e\u0440\u043e\u0432\u0430\u0446"
    ],
    "name:swe_x_preferred":[
        "Borovac"
    ],
    "name:und_x_variant":[
        "Borovci",
        "Borovac"
    ],
    "wof:name":"Borovac",
    "wof:placetype":"locality"
},
  "geometry": {"coordinates":[18.33972,44.45678],"type":"Point"}
}