{
  "type": "Feature",
  "properties": {
    "gn:admin1_code":"01",
    "gn:asciiname":"Hadrovici",
    "gn:country_code":"BA",
    "gn:dem":350,
    "gn:feature_class":"P",
    "gn:feature_code":"PPLL",
    "gn:name":"Hadrovi\u0107i",
    "gn:population":0,
    "gn:timezone":"Europe/Sarajevo",
    "iso:country":"BA",
    "wof:name":"Hadrovici",
    "wof:placetype":"locality"
},
  "geometry": {"coordinates":[18.20529,44.48036],"type":"Point"}
}