{
  "type": "Feature",
  "properties": {
    "gn:admin1_code":"01",
    "gn:asciiname":"Mlive",
    "gn:country_code":"BA",
    "gn:dem":883,
    "gn:feature_class":"P",
    "gn:feature_code":"PPL",
    "gn:name":"Mlive",
    "gn:population":0,
    "gn:timezone":"Europe/Sarajevo",
    "iso:country":"BA",
    "wof:name":"Mlive",
    "wof:placetype":"locality"
},
  "geometry": {"coordinates":[17.51606,44.08502],"type":"Point"}
}