{
  "type": "Feature",
  "properties": {
    "gn:admin1_code":"01",
    "gn:asciiname":"Markanovina",
    "gn:country_code":"BA",
    "gn:dem":441,
    "gn:feature_class":"P",
    "gn:feature_code":"PPL",
    "gn:name":"Markanovina",
    "gn:population":0,
    "gn:timezone":"Europe/Sarajevo",
    "iso:country":"BA",
    "wof:name":"Markanovina",
    "wof:placetype":"locality"
},
  "geometry": {"coordinates":[17.83592,43.4699],"type":"Point"}
}