{
  "type": "Feature",
  "properties": {
    "gn:admin1_code":"00",
    "gn:asciiname":"Vracevac",
    "gn:country_code":"BA",
    "gn:dem":394,
    "gn:feature_class":"P",
    "gn:feature_code":"PPL",
    "gn:name":"Vra\u010devac",
    "gn:population":0,
    "gn:timezone":"Europe/Sarajevo",
    "iso:country":"BA",
    "wof:name":"Vracevac",
    "wof:placetype":"locality"
},
  "geometry": {"coordinates":[18.42313,44.35018],"type":"Point"}
}