{
  "type": "Feature",
  "properties": {
    "gn:admin1_code":"02",
    "gn:asciiname":"Bok",
    "gn:country_code":"BA",
    "gn:dem":88,
    "gn:feature_class":"P",
    "gn:feature_code":"PPL",
    "gn:name":"Bok",
    "gn:population":0,
    "gn:timezone":"Europe/Sarajevo",
    "iso:country":"BA",
    "name:afr_x_preferred":[
        "Bok"
    ],
    "name:bos_x_preferred":[
        "Bok"
    ],
    "name:ceb_x_preferred":[
        "Bok"
    ],
    "name:ces_x_preferred":[
        "Bok"
    ],
    "name:deu_x_preferred":[
        "Bok"
    ],
    "name:fry_x_preferred":[
        "Bok"
    ],
    "name:nld_x_preferred":[
        "Bok"
    ],
    "name:nor_x_preferred":[
        "Bok"
    ],
    "name:pol_x_preferred":[
        "Bok"
    ],
    "name:por_x_preferred":[
        "Bok"
    ],
    "name:slv_x_preferred":[
        "Bok"
    ],
    "name:swe_x_preferred":[
        "Bok"
    ],
    "name:wln_x_preferred":[
        "Bok"
    ],
    "wof:name":"Bok",
    "wof:placetype":"locality"
},
  "geometry": {"coordinates":[17.36365,45.11837],"type":"Point"}
}