{
  "type": "Feature",
  "properties": {
    "gn:admin1_code":"01",
    "gn:asciiname":"Zabrig",
    "gn:country_code":"BA",
    "gn:dem":960,
    "gn:feature_class":"P",
    "gn:feature_code":"PPL",
    "gn:name":"Zabrig",
    "gn:population":0,
    "gn:timezone":"Europe/Sarajevo",
    "iso:country":"BA",
    "wof:name":"Zabrig",
    "wof:placetype":"locality"
},
  "geometry": {"coordinates":[17.27201,43.57235],"type":"Point"}
}