{
  "type": "Feature",
  "properties": {
    "gn:admin1_code":"02",
    "gn:asciiname":"Mijatovici",
    "gn:country_code":"BA",
    "gn:dem":261,
    "gn:feature_class":"P",
    "gn:feature_code":"PPL",
    "gn:name":"Mijatovi\u0107i",
    "gn:population":0,
    "gn:timezone":"Europe/Sarajevo",
    "iso:country":"BA",
    "wof:name":"Mijatovici",
    "wof:placetype":"locality"
},
  "geometry": {"coordinates":[17.01736,44.83884000000001],"type":"Point"}
}