{
  "type": "Feature",
  "properties": {
    "gn:admin1_code":"02",
    "gn:asciiname":"Rudin Do",
    "gn:country_code":"BA",
    "gn:dem":1024,
    "gn:feature_class":"P",
    "gn:feature_code":"PPL",
    "gn:name":"Rudin Do",
    "gn:population":0,
    "gn:timezone":"Europe/Sarajevo",
    "iso:country":"BA",
    "wof:name":"Rudin Do",
    "wof:placetype":"locality"
},
  "geometry": {"coordinates":[18.48028,42.91556],"type":"Point"}
}