{
  "type": "Feature",
  "properties": {
    "gn:admin1_code":"02",
    "gn:asciiname":"Pluznice",
    "gn:country_code":"BA",
    "gn:dem":1207,
    "gn:feature_class":"P",
    "gn:feature_code":"PPL",
    "gn:name":"Plu\u017enice",
    "gn:population":0,
    "gn:timezone":"Europe/Sarajevo",
    "iso:country":"BA",
    "name:und_x_variant":[
        "Rasadni\u0107",
        "Plu\u017enice"
    ],
    "wof:name":"Pluznice",
    "wof:placetype":"locality"
},
  "geometry": {"coordinates":[18.63399,43.96189],"type":"Point"}
}