{
  "type": "Feature",
  "properties": {
    "gn:admin1_code":"01",
    "gn:asciiname":"Vujaklije",
    "gn:country_code":"BA",
    "gn:dem":223,
    "gn:feature_class":"P",
    "gn:feature_code":"PPL",
    "gn:name":"Vujaklije",
    "gn:population":0,
    "gn:timezone":"Europe/Sarajevo",
    "iso:country":"BA",
    "wof:name":"Vujaklije",
    "wof:placetype":"locality"
},
  "geometry": {"coordinates":[16.00832999999999,45.2181],"type":"Point"}
}