{
  "type": "Feature",
  "properties": {
    "gn:admin1_code":"01",
    "gn:asciiname":"Visnjici",
    "gn:country_code":"BA",
    "gn:dem":1097,
    "gn:feature_class":"P",
    "gn:feature_code":"PPL",
    "gn:name":"Vi\u0161nji\u0107i",
    "gn:population":0,
    "gn:timezone":"Europe/Sarajevo",
    "iso:country":"BA",
    "wof:name":"Visnjici",
    "wof:placetype":"locality"
},
  "geometry": {"coordinates":[18.36902000000001,44.13659000000001],"type":"Point"}
}