{
  "type": "Feature",
  "properties": {
    "gn:admin1_code":"02",
    "gn:asciiname":"Zvijerina",
    "gn:country_code":"BA",
    "gn:dem":879,
    "gn:feature_class":"P",
    "gn:feature_code":"PPL",
    "gn:name":"Zvijerina",
    "gn:population":0,
    "gn:timezone":"Europe/Sarajevo",
    "iso:country":"BA",
    "name:bos_x_preferred":[
        "Zvijerina"
    ],
    "name:fra_x_preferred":[
        "Zvijerina"
    ],
    "name:rus_x_preferred":[
        "\u0417\u0432\u0438\u0435\u0440\u0438\u043d\u0430"
    ],
    "name:slv_x_preferred":[
        "Zvijerina"
    ],
    "name:srp_x_preferred":[
        "\u0417\u0432\u0438\u0458\u0435\u0440\u0438\u043d\u0430"
    ],
    "wof:name":"Zvijerina",
    "wof:placetype":"locality"
},
  "geometry": {"coordinates":[18.27479,42.94385],"type":"Point"}
}