{
  "type": "Feature",
  "properties": {
    "gn:admin1_code":"02",
    "gn:asciiname":"Simatovici",
    "gn:country_code":"BA",
    "gn:dem":207,
    "gn:feature_class":"P",
    "gn:feature_code":"PPL",
    "gn:name":"Simatovi\u0107i",
    "gn:population":0,
    "gn:timezone":"Europe/Sarajevo",
    "iso:country":"BA",
    "wof:name":"Simatovici",
    "wof:placetype":"locality"
},
  "geometry": {"coordinates":[16.74596,45.0103],"type":"Point"}
}