{
  "type": "Feature",
  "properties": {
    "gn:admin1_code":"01",
    "gn:asciiname":"Kolimer",
    "gn:country_code":"BA",
    "gn:dem":506,
    "gn:feature_class":"P",
    "gn:feature_code":"PPLL",
    "gn:name":"Kolimer",
    "gn:population":0,
    "gn:timezone":"Europe/Sarajevo",
    "iso:country":"BA",
    "wof:name":"Kolimer",
    "wof:placetype":"locality"
},
  "geometry": {"coordinates":[18.82744,44.5426],"type":"Point"}
}