{
  "type": "Feature",
  "properties": {
    "gn:admin1_code":"01",
    "gn:asciiname":"Bakaluse",
    "gn:country_code":"BA",
    "gn:dem":405,
    "gn:feature_class":"P",
    "gn:feature_code":"PPL",
    "gn:name":"Bakalu\u0161e",
    "gn:population":0,
    "gn:timezone":"Europe/Sarajevo",
    "iso:country":"BA",
    "wof:name":"Bakaluse",
    "wof:placetype":"locality"
},
  "geometry": {"coordinates":[18.65728,44.59542],"type":"Point"}
}