{
  "type": "Feature",
  "properties": {
    "gn:admin1_code":"02",
    "gn:asciiname":"Medas",
    "gn:country_code":"BA",
    "gn:dem":209,
    "gn:feature_class":"P",
    "gn:feature_code":"PPL",
    "gn:name":"Me\u0111a\u0161",
    "gn:population":0,
    "gn:timezone":"Europe/Sarajevo",
    "iso:country":"BA",
    "wof:name":"Medas",
    "wof:placetype":"locality"
},
  "geometry": {"coordinates":[18.31273,44.65986],"type":"Point"}
}