{
  "type": "Feature",
  "properties": {
    "gn:admin1_code":"01",
    "gn:asciiname":"Burzici",
    "gn:country_code":"BA",
    "gn:dem":350,
    "gn:feature_class":"P",
    "gn:feature_code":"PPL",
    "gn:name":"Burzi\u0107i",
    "gn:population":0,
    "gn:timezone":"Europe/Sarajevo",
    "iso:country":"BA",
    "wof:name":"Burzici",
    "wof:placetype":"locality"
},
  "geometry": {"coordinates":[16.05766,45.08691],"type":"Point"}
}