{
  "type": "Feature",
  "properties": {
    "gn:admin1_code":"01",
    "gn:asciiname":"Tomas",
    "gn:country_code":"BA",
    "gn:dem":262,
    "gn:feature_class":"P",
    "gn:feature_code":"PPL",
    "gn:name":"Tomas",
    "gn:population":0,
    "gn:timezone":"Europe/Sarajevo",
    "iso:country":"BA",
    "wof:name":"Tomas",
    "wof:placetype":"locality"
},
  "geometry": {"coordinates":[17.31278,43.34306],"type":"Point"}
}