{
  "type": "Feature",
  "properties": {
    "gn:admin1_code":"01",
    "gn:asciiname":"Tomas",
    "gn:country_code":"BA",
    "gn:dem":262,
    "gn:feature_class":"P",
    "gn:feature_code":"PPL",
    "gn:name":"Tomas",
    "gn:population":0,
    "gn:timezone":"Europe/Sarajevo",
    "iso:country":"BA",
    "name:bel_x_preferred":[
        "\u0422\u043e\u043c\u0430\u0441"
    ],
    "name:bul_x_preferred":[
        "\u0422\u043e\u043c\u0430\u0441"
    ],
    "name:ceb_x_preferred":[
        "Tomas"
    ],
    "name:fra_x_preferred":[
        "Tomas"
    ],
    "name:ita_x_preferred":[
        "Tomas"
    ],
    "name:nld_x_preferred":[
        "Tomas"
    ],
    "name:rus_x_preferred":[
        "\u0422\u043e\u043c\u0430\u0441"
    ],
    "name:slk_x_preferred":[
        "Tomas"
    ],
    "name:srp_x_preferred":[
        "\u0422\u043e\u043c\u0430\u0441"
    ],
    "name:swe_x_preferred":[
        "Tomas"
    ],
    "wof:name":"Tomas",
    "wof:placetype":"locality"
},
  "geometry": {"coordinates":[17.31278,43.34306],"type":"Point"}
}