{
  "type": "Feature",
  "properties": {
    "gn:admin1_code":"01",
    "gn:asciiname":"Gornji Azapovici",
    "gn:country_code":"BA",
    "gn:dem":635,
    "gn:feature_class":"P",
    "gn:feature_code":"PPL",
    "gn:name":"Gornji Azapovi\u0107i",
    "gn:population":0,
    "gn:timezone":"Europe/Sarajevo",
    "iso:country":"BA",
    "wof:name":"Gornji Azapovici",
    "wof:placetype":"locality"
},
  "geometry": {"coordinates":[18.17453,43.87841],"type":"Point"}
}