{
  "type": "Feature",
  "properties": {
    "gn:admin1_code":"02",
    "gn:asciiname":"Cikule",
    "gn:country_code":"BA",
    "gn:dem":93,
    "gn:feature_class":"P",
    "gn:feature_code":"PPL",
    "gn:name":"\u010cikule",
    "gn:population":0,
    "gn:timezone":"Europe/Sarajevo",
    "iso:country":"BA",
    "name:und_x_variant":[
        "\u010cikule"
    ],
    "wof:name":"Cikule",
    "wof:placetype":"locality"
},
  "geometry": {"coordinates":[17.26132,45.098],"type":"Point"}
}