{
  "type": "Feature",
  "properties": {
    "gn:admin1_code":"02",
    "gn:asciiname":"Cikule",
    "gn:country_code":"BA",
    "gn:dem":93,
    "gn:feature_class":"P",
    "gn:feature_code":"PPL",
    "gn:name":"\u010cikule",
    "gn:population":0,
    "gn:timezone":"Europe/Sarajevo",
    "iso:country":"BA",
    "name:bos_x_preferred":[
        "\u010cikule"
    ],
    "name:ceb_x_preferred":[
        "\u010cikule"
    ],
    "name:fra_x_preferred":[
        "\u010cikule"
    ],
    "name:hrv_x_preferred":[
        "\u010cikule"
    ],
    "name:slv_x_preferred":[
        "\u010cikule"
    ],
    "name:srp_x_preferred":[
        "\u0427\u0438\u043a\u0443\u043b\u0435"
    ],
    "name:swe_x_preferred":[
        "\u010cikule"
    ],
    "wof:name":"Cikule",
    "wof:placetype":"locality"
},
  "geometry": {"coordinates":[17.26132,45.098],"type":"Point"}
}