{
  "type": "Feature",
  "properties": {
    "gn:admin1_code":"01",
    "gn:asciiname":"Kondze",
    "gn:country_code":"BA",
    "gn:dem":170,
    "gn:feature_class":"P",
    "gn:feature_code":"PPL",
    "gn:name":"Kond\u017ee",
    "gn:population":0,
    "gn:timezone":"Europe/Sarajevo",
    "iso:country":"BA",
    "wof:name":"Kondze",
    "wof:placetype":"locality"
},
  "geometry": {"coordinates":[17.95332999999999,44.65944],"type":"Point"}
}