{
  "type": "Feature",
  "properties": {
    "gn:admin1_code":"02",
    "gn:asciiname":"Podada",
    "gn:country_code":"BA",
    "gn:dem":95,
    "gn:feature_class":"P",
    "gn:feature_code":"PPL",
    "gn:name":"Podada",
    "gn:population":0,
    "gn:timezone":"Europe/Sarajevo",
    "iso:country":"BA",
    "wof:name":"Podada",
    "wof:placetype":"locality"
},
  "geometry": {"coordinates":[18.40268,44.95911],"type":"Point"}
}