{
  "type": "Feature",
  "properties": {
    "gn:admin1_code":"02",
    "gn:asciiname":"Strike",
    "gn:country_code":"BA",
    "gn:dem":271,
    "gn:feature_class":"P",
    "gn:feature_code":"PPL",
    "gn:name":"Strike",
    "gn:population":0,
    "gn:timezone":"Europe/Sarajevo",
    "iso:country":"BA",
    "name:aze_x_preferred":[
        "Uzanma"
    ],
    "name:dan_x_preferred":[
        "Strike"
    ],
    "name:deu_x_preferred":[
        "Strike"
    ],
    "name:fra_x_preferred":[
        "Strike"
    ],
    "name:heb_x_preferred":[
        "\u05e9\u05d1\u05d9\u05ea\u05d4"
    ],
    "name:ita_x_preferred":[
        "Strike"
    ],
    "name:jpn_x_preferred":[
        "\u30b9\u30c8\u30e9\u30a4\u30af"
    ],
    "name:kor_x_preferred":[
        "\uc2a4\ud2b8\ub77c\uc774\ud06c"
    ],
    "name:nld_x_preferred":[
        "Strike"
    ],
    "name:por_x_preferred":[
        "Strike"
    ],
    "name:rus_x_preferred":[
        "\u0421\u0442\u0440\u0430\u0439\u043a"
    ],
    "name:spa_x_preferred":[
        "Strike"
    ],
    "name:swe_x_preferred":[
        "Strike"
    ],
    "name:tel_x_preferred":[
        "\u0c38\u0c2e\u0c4d\u0c2e\u0c46"
    ],
    "wof:name":"Strike",
    "wof:placetype":"locality"
},
  "geometry": {"coordinates":[17.10859,44.62216],"type":"Point"}
}