{
  "type": "Feature",
  "properties": {
    "gn:admin1_code":"02",
    "gn:asciiname":"Strike",
    "gn:country_code":"BA",
    "gn:dem":271,
    "gn:feature_class":"P",
    "gn:feature_code":"PPL",
    "gn:name":"Strike",
    "gn:population":0,
    "gn:timezone":"Europe/Sarajevo",
    "iso:country":"BA",
    "wof:name":"Strike",
    "wof:placetype":"locality"
},
  "geometry": {"coordinates":[17.10859,44.62216],"type":"Point"}
}