{
  "type": "Feature",
  "properties": {
    "gn:admin1_code":"01",
    "gn:asciiname":"Perivoje",
    "gn:country_code":"BA",
    "gn:dem":646,
    "gn:feature_class":"P",
    "gn:feature_code":"PPL",
    "gn:name":"Perivoje",
    "gn:population":0,
    "gn:timezone":"Europe/Sarajevo",
    "iso:country":"BA",
    "wof:name":"Perivoje",
    "wof:placetype":"locality"
},
  "geometry": {"coordinates":[18.33659,43.88246],"type":"Point"}
}