{
  "type": "Feature",
  "properties": {
    "gn:admin1_code":"02",
    "gn:asciiname":"Ruzica",
    "gn:country_code":"BA",
    "gn:dem":985,
    "gn:feature_class":"P",
    "gn:feature_code":"PPL",
    "gn:name":"Ru\u017eica",
    "gn:population":0,
    "gn:timezone":"Europe/Sarajevo",
    "iso:country":"BA",
    "wof:name":"Ruzica",
    "wof:placetype":"locality"
},
  "geometry": {"coordinates":[18.62405,43.88399],"type":"Point"}
}