{
  "type": "Feature",
  "properties": {
    "gn:admin1_code":"01",
    "gn:asciiname":"Kula Banjer",
    "gn:country_code":"BA",
    "gn:dem":420,
    "gn:feature_class":"P",
    "gn:feature_code":"PPL",
    "gn:name":"Kula Banjer",
    "gn:population":0,
    "gn:timezone":"Europe/Sarajevo",
    "iso:country":"BA",
    "wof:name":"Kula Banjer",
    "wof:placetype":"locality"
},
  "geometry": {"coordinates":[18.1996,43.99165],"type":"Point"}
}