{
  "type": "Feature",
  "properties": {
    "gn:admin1_code":"02",
    "gn:asciiname":"Gornji Vrbljani",
    "gn:country_code":"BA",
    "gn:dem":675,
    "gn:feature_class":"P",
    "gn:feature_code":"PPLL",
    "gn:name":"Gornji Vrbljani",
    "gn:population":0,
    "gn:timezone":"Europe/Sarajevo",
    "iso:country":"BA",
    "name:bos_x_preferred":[
        "Gornji Vrbljani"
    ],
    "name:ceb_x_preferred":[
        "Gornji Vrbljani"
    ],
    "name:fra_x_preferred":[
        "Gornji Vrbljani"
    ],
    "name:hrv_x_preferred":[
        "Gornji Vrbljani"
    ],
    "name:srp_x_preferred":[
        "\u0413\u043e\u0440\u045a\u0438 \u0412\u0440\u0431\u0459\u0430\u043d\u0438"
    ],
    "name:swe_x_preferred":[
        "Gornji Vrbljani"
    ],
    "wof:name":"Gornji Vrbljani",
    "wof:placetype":"locality"
},
  "geometry": {"coordinates":[16.79486,44.34184000000001],"type":"Point"}
}