{
  "type": "Feature",
  "properties": {
    "gn:admin1_code":"02",
    "gn:asciiname":"Hum Selo",
    "gn:country_code":"BA",
    "gn:dem":311,
    "gn:feature_class":"P",
    "gn:feature_code":"PPL",
    "gn:name":"Hum Selo",
    "gn:population":0,
    "gn:timezone":"Europe/Sarajevo",
    "iso:country":"BA",
    "name:und_x_variant":[
        "Hum",
        "Hum Selo"
    ],
    "wof:name":"Hum Selo",
    "wof:placetype":"locality"
},
  "geometry": {"coordinates":[18.19317,42.74213],"type":"Point"}
}