{
  "type": "Feature",
  "properties": {
    "gn:admin1_code":"02",
    "gn:asciiname":"Podomar",
    "gn:country_code":"BA",
    "gn:dem":779,
    "gn:feature_class":"P",
    "gn:feature_code":"PPL",
    "gn:name":"Podomar",
    "gn:population":0,
    "gn:timezone":"Europe/Sarajevo",
    "iso:country":"BA",
    "wof:name":"Podomar",
    "wof:placetype":"locality"
},
  "geometry": {"coordinates":[18.75224,44.03494],"type":"Point"}
}