{
  "type": "Feature",
  "properties": {
    "gn:admin1_code":"BRC",
    "gn:asciiname":"Kurjakovici",
    "gn:country_code":"BA",
    "gn:dem":93,
    "gn:feature_class":"P",
    "gn:feature_code":"PPL",
    "gn:name":"Kurjakovi\u0107i",
    "gn:population":0,
    "gn:timezone":"Europe/Sarajevo",
    "iso:country":"BA",
    "wof:name":"Kurjakovici",
    "wof:placetype":"locality"
},
  "geometry": {"coordinates":[18.98825,44.83333],"type":"Point"}
}