{
  "type": "Feature",
  "properties": {
    "gn:admin1_code":"02",
    "gn:asciiname":"Krtinje",
    "gn:country_code":"BA",
    "gn:dem":843,
    "gn:feature_class":"P",
    "gn:feature_code":"PPLL",
    "gn:name":"Krtinje",
    "gn:population":0,
    "gn:timezone":"Europe/Sarajevo",
    "iso:country":"BA",
    "wof:name":"Krtinje",
    "wof:placetype":"locality"
},
  "geometry": {"coordinates":[18.23406,42.89694],"type":"Point"}
}