{
  "type": "Feature",
  "properties": {
    "gn:admin1_code":"01",
    "gn:asciiname":"Prespica",
    "gn:country_code":"BA",
    "gn:dem":821,
    "gn:feature_class":"P",
    "gn:feature_code":"PPL",
    "gn:name":"Pre\u0161pica",
    "gn:population":0,
    "gn:timezone":"Europe/Sarajevo",
    "iso:country":"BA",
    "wof:name":"Prespica",
    "wof:placetype":"locality"
},
  "geometry": {"coordinates":[18.80626,43.76109],"type":"Point"}
}