{
  "type": "Feature",
  "properties": {
    "gn:admin1_code":"02",
    "gn:asciiname":"Rastovac",
    "gn:country_code":"BA",
    "gn:dem":898,
    "gn:feature_class":"P",
    "gn:feature_code":"PPL",
    "gn:name":"Rastovac",
    "gn:population":0,
    "gn:timezone":"Europe/Sarajevo",
    "iso:country":"BA",
    "name:bos_x_preferred":[
        "Rastovac"
    ],
    "name:ceb_x_preferred":[
        "Rastovac"
    ],
    "name:fra_x_preferred":[
        "Rastovac"
    ],
    "name:hrv_x_preferred":[
        "Rastovac"
    ],
    "name:hun_x_preferred":[
        "Rastovac"
    ],
    "name:nld_x_preferred":[
        "Rastovac"
    ],
    "name:slv_x_preferred":[
        "Rastovac"
    ],
    "name:srp_x_preferred":[
        "\u0420\u0430\u0441\u0442\u043e\u0432\u0430\u0446"
    ],
    "name:swe_x_preferred":[
        "Rastovac"
    ],
    "wof:name":"Rastovac",
    "wof:placetype":"locality"
},
  "geometry": {"coordinates":[18.65681,43.73332],"type":"Point"}
}