{
  "type": "Feature",
  "properties": {
    "gn:admin1_code":"02",
    "gn:asciiname":"Rastovac",
    "gn:country_code":"BA",
    "gn:dem":898,
    "gn:feature_class":"P",
    "gn:feature_code":"PPL",
    "gn:name":"Rastovac",
    "gn:population":0,
    "gn:timezone":"Europe/Sarajevo",
    "iso:country":"BA",
    "wof:name":"Rastovac",
    "wof:placetype":"locality"
},
  "geometry": {"coordinates":[18.65681,43.73332],"type":"Point"}
}