{
  "type": "Feature",
  "properties": {
    "gn:admin1_code":"01",
    "gn:asciiname":"Brnj",
    "gn:country_code":"BA",
    "gn:dem":523,
    "gn:feature_class":"P",
    "gn:feature_code":"PPL",
    "gn:name":"Brnj",
    "gn:population":0,
    "gn:timezone":"Europe/Sarajevo",
    "iso:country":"BA",
    "wof:name":"Brnj",
    "wof:placetype":"locality"
},
  "geometry": {"coordinates":[18.1151,44.15645],"type":"Point"}
}