{
  "type": "Feature",
  "properties": {
    "gn:admin1_code":"01",
    "gn:asciiname":"Brnj",
    "gn:country_code":"BA",
    "gn:dem":523,
    "gn:feature_class":"P",
    "gn:feature_code":"PPL",
    "gn:name":"Brnj",
    "gn:population":0,
    "gn:timezone":"Europe/Sarajevo",
    "iso:country":"BA",
    "name:bos_x_preferred":[
        "Brnj"
    ],
    "name:ceb_x_preferred":[
        "Brnj"
    ],
    "name:fra_x_preferred":[
        "Brnj"
    ],
    "name:hrv_x_preferred":[
        "Brnj"
    ],
    "name:srp_x_preferred":[
        "\u0411\u0440\u045a"
    ],
    "name:swe_x_preferred":[
        "Brnj"
    ],
    "wof:name":"Brnj",
    "wof:placetype":"locality"
},
  "geometry": {"coordinates":[18.1151,44.15645],"type":"Point"}
}