{
  "type": "Feature",
  "properties": {
    "gn:admin1_code":"01",
    "gn:asciiname":"Kutnja",
    "gn:country_code":"BA",
    "gn:dem":761,
    "gn:feature_class":"P",
    "gn:feature_code":"PPL",
    "gn:name":"Kutnja",
    "gn:population":0,
    "gn:timezone":"Europe/Sarajevo",
    "iso:country":"BA",
    "wof:name":"Kutnja",
    "wof:placetype":"locality"
},
  "geometry": {"coordinates":[18.22083,43.90972],"type":"Point"}
}