{
  "type": "Feature",
  "properties": {
    "gn:admin1_code":"01",
    "gn:asciiname":"Kisak",
    "gn:country_code":"BA",
    "gn:dem":325,
    "gn:feature_class":"P",
    "gn:feature_code":"PPL",
    "gn:name":"Kisak",
    "gn:population":0,
    "gn:timezone":"Europe/Sarajevo",
    "iso:country":"BA",
    "wof:name":"Kisak",
    "wof:placetype":"locality"
},
  "geometry": {"coordinates":[16.53177,44.79264000000001],"type":"Point"}
}