{
  "type": "Feature",
  "properties": {
    "gn:admin1_code":"02",
    "gn:asciiname":"Krizine",
    "gn:country_code":"BA",
    "gn:dem":382,
    "gn:feature_class":"P",
    "gn:feature_code":"PPL",
    "gn:name":"Kri\u017eine",
    "gn:population":0,
    "gn:timezone":"Europe/Sarajevo",
    "iso:country":"BA",
    "wof:name":"Krizine",
    "wof:placetype":"locality"
},
  "geometry": {"coordinates":[19.27281,44.25855],"type":"Point"}
}