{
  "type": "Feature",
  "properties": {
    "gn:admin1_code":"02",
    "gn:asciiname":"Grabovica",
    "gn:country_code":"BA",
    "gn:dem":484,
    "gn:feature_class":"P",
    "gn:feature_code":"PPLL",
    "gn:name":"Grabovica",
    "gn:population":0,
    "gn:timezone":"Europe/Sarajevo",
    "iso:country":"BA",
    "wof:name":"Grabovica",
    "wof:placetype":"locality"
},
  "geometry": {"coordinates":[17.50372999999999,44.49192],"type":"Point"}
}