{
  "type": "Feature",
  "properties": {
    "gn:admin1_code":"02",
    "gn:asciiname":"Sljivine",
    "gn:country_code":"BA",
    "gn:dem":583,
    "gn:feature_class":"P",
    "gn:feature_code":"PPL",
    "gn:name":"\u0160ljivine",
    "gn:population":0,
    "gn:timezone":"Europe/Sarajevo",
    "iso:country":"BA",
    "wof:name":"Sljivine",
    "wof:placetype":"locality"
},
  "geometry": {"coordinates":[18.33629,42.9862],"type":"Point"}
}