{
  "type": "Feature",
  "properties": {
    "gn:admin1_code":"02",
    "gn:asciiname":"Budisavlje",
    "gn:country_code":"BA",
    "gn:dem":874,
    "gn:feature_class":"P",
    "gn:feature_code":"PPL",
    "gn:name":"Budisavlje",
    "gn:population":0,
    "gn:timezone":"Europe/Sarajevo",
    "iso:country":"BA",
    "wof:name":"Budisavlje",
    "wof:placetype":"locality"
},
  "geometry": {"coordinates":[18.24762,43.22344],"type":"Point"}
}