{
  "type": "Feature",
  "properties": {
    "gn:admin1_code":"02",
    "gn:asciiname":"Budisavlje",
    "gn:country_code":"BA",
    "gn:dem":874,
    "gn:feature_class":"P",
    "gn:feature_code":"PPL",
    "gn:name":"Budisavlje",
    "gn:population":0,
    "gn:timezone":"Europe/Sarajevo",
    "iso:country":"BA",
    "name:bos_x_preferred":[
        "Budisavlje"
    ],
    "name:ceb_x_preferred":[
        "Budisavlje"
    ],
    "name:fra_x_preferred":[
        "Budisavlje"
    ],
    "name:hrv_x_preferred":[
        "Budisavlje"
    ],
    "name:srp_x_preferred":[
        "\u0411\u0443\u0434\u0438\u0441\u0430\u0432\u0459\u0435"
    ],
    "name:swe_x_preferred":[
        "Budisavlje"
    ],
    "wof:name":"Budisavlje",
    "wof:placetype":"locality"
},
  "geometry": {"coordinates":[18.24762,43.22344],"type":"Point"}
}