{
  "type": "Feature",
  "properties": {
    "gn:admin1_code":"01",
    "gn:asciiname":"Vrtace",
    "gn:country_code":"BA",
    "gn:dem":587,
    "gn:feature_class":"P",
    "gn:feature_code":"PPL",
    "gn:name":"Vrta\u010de",
    "gn:population":0,
    "gn:timezone":"Europe/Sarajevo",
    "iso:country":"BA",
    "wof:name":"Vrtace",
    "wof:placetype":"locality"
},
  "geometry": {"coordinates":[17.93348,44.29843],"type":"Point"}
}