{
  "type": "Feature",
  "properties": {
    "gn:admin1_code":"01",
    "gn:asciiname":"Vilici",
    "gn:country_code":"BA",
    "gn:dem":328,
    "gn:feature_class":"P",
    "gn:feature_code":"PPL",
    "gn:name":"Vili\u0107i",
    "gn:population":0,
    "gn:timezone":"Europe/Sarajevo",
    "iso:country":"BA",
    "wof:name":"Vilici",
    "wof:placetype":"locality"
},
  "geometry": {"coordinates":[15.85222,44.96949],"type":"Point"}
}