{
  "type": "Feature",
  "properties": {
    "gn:admin1_code":"01",
    "gn:asciiname":"Gracanica",
    "gn:country_code":"BA",
    "gn:dem":491,
    "gn:feature_class":"P",
    "gn:feature_code":"PPL",
    "gn:name":"Gra\u010danica",
    "gn:population":0,
    "gn:timezone":"Europe/Sarajevo",
    "iso:country":"BA",
    "wof:name":"Gracanica",
    "wof:placetype":"locality"
},
  "geometry": {"coordinates":[16.82118,44.67745],"type":"Point"}
}