{
  "type": "Feature",
  "properties": {
    "gn:admin1_code":"01",
    "gn:asciiname":"Do",
    "gn:country_code":"BA",
    "gn:dem":259,
    "gn:feature_class":"P",
    "gn:feature_code":"PPL",
    "gn:name":"Do",
    "gn:population":0,
    "gn:timezone":"Europe/Sarajevo",
    "iso:country":"BA",
    "wof:name":"Do",
    "wof:placetype":"locality"
},
  "geometry": {"coordinates":[17.82222,42.94278],"type":"Point"}
}