{
  "type": "Feature",
  "properties": {
    "gn:admin1_code":"01",
    "gn:asciiname":"Kijevo",
    "gn:country_code":"BA",
    "gn:dem":220,
    "gn:feature_class":"P",
    "gn:feature_code":"PPLL",
    "gn:name":"Kijevo",
    "gn:population":0,
    "gn:timezone":"Europe/Sarajevo",
    "iso:country":"BA",
    "name:bos_x_preferred":[
        "Kijevo"
    ],
    "name:fra_x_preferred":[
        "Kijevo"
    ],
    "name:hrv_x_preferred":[
        "Kijevo"
    ],
    "name:hun_x_preferred":[
        "Kijevo"
    ],
    "name:jpn_x_preferred":[
        "\u30ad\u30a4\u30a7\u30f4\u30a9"
    ],
    "name:nld_x_preferred":[
        "Kijevo"
    ],
    "name:slv_x_preferred":[
        "Kijevo"
    ],
    "name:srp_x_preferred":[
        "\u041a\u0438\u0458\u0435\u0432\u043e"
    ],
    "name:swe_x_preferred":[
        "Kijevo"
    ],
    "name:ukr_x_preferred":[
        "\u041a\u0438\u0454\u0432\u043e"
    ],
    "wof:name":"Kijevo",
    "wof:placetype":"locality"
},
  "geometry": {"coordinates":[16.73267,44.73609],"type":"Point"}
}