{
  "type": "Feature",
  "properties": {
    "gn:admin1_code":"01",
    "gn:asciiname":"Kijevo",
    "gn:country_code":"BA",
    "gn:dem":220,
    "gn:feature_class":"P",
    "gn:feature_code":"PPLL",
    "gn:name":"Kijevo",
    "gn:population":0,
    "gn:timezone":"Europe/Sarajevo",
    "iso:country":"BA",
    "wof:name":"Kijevo",
    "wof:placetype":"locality"
},
  "geometry": {"coordinates":[16.73267,44.73609],"type":"Point"}
}