{
  "type": "Feature",
  "properties": {
    "gn:admin1_code":"02",
    "gn:asciiname":"Malesevici",
    "gn:country_code":"BA",
    "gn:dem":766,
    "gn:feature_class":"P",
    "gn:feature_code":"PPL",
    "gn:name":"Male\u0161evi\u0107i",
    "gn:population":0,
    "gn:timezone":"Europe/Sarajevo",
    "iso:country":"BA",
    "wof:name":"Malesevici",
    "wof:placetype":"locality"
},
  "geometry": {"coordinates":[16.94128,44.50172],"type":"Point"}
}