{
  "type": "Feature",
  "properties": {
    "gn:admin1_code":"02",
    "gn:asciiname":"Sakotici",
    "gn:country_code":"BA",
    "gn:dem":298,
    "gn:feature_class":"P",
    "gn:feature_code":"PPL",
    "gn:name":"\u0160akoti\u0107i",
    "gn:population":0,
    "gn:timezone":"Europe/Sarajevo",
    "iso:country":"BA",
    "wof:name":"Sakotici",
    "wof:placetype":"locality"
},
  "geometry": {"coordinates":[19.06025,44.49499],"type":"Point"}
}