{
  "type": "Feature",
  "properties": {
    "gn:admin1_code":"01",
    "gn:asciiname":"Tresnjeva Glava",
    "gn:country_code":"BA",
    "gn:dem":761,
    "gn:feature_class":"P",
    "gn:feature_code":"PPL",
    "gn:name":"Tre\u0161njeva Glava",
    "gn:population":0,
    "gn:timezone":"Europe/Sarajevo",
    "iso:country":"BA",
    "wof:name":"Tresnjeva Glava",
    "wof:placetype":"locality"
},
  "geometry": {"coordinates":[18.02504,44.25755],"type":"Point"}
}