{
  "type": "Feature",
  "properties": {
    "gn:admin1_code":"02",
    "gn:asciiname":"Cokori",
    "gn:country_code":"BA",
    "gn:dem":367,
    "gn:feature_class":"P",
    "gn:feature_code":"PPLL",
    "gn:name":"\u010cokori",
    "gn:population":0,
    "gn:timezone":"Europe/Sarajevo",
    "iso:country":"BA",
    "name:bos_x_preferred":[
        "\u010cokori"
    ],
    "name:ceb_x_preferred":[
        "\u010cokori"
    ],
    "name:fra_x_preferred":[
        "\u010cokori"
    ],
    "name:hrv_x_preferred":[
        "\u010cokori"
    ],
    "name:rus_x_preferred":[
        "\u0427\u043e\u043a\u043e\u0440\u0438"
    ],
    "name:slv_x_preferred":[
        "\u010cokori"
    ],
    "name:srp_x_preferred":[
        "\u0427\u043e\u043a\u043e\u0440\u0438"
    ],
    "name:swe_x_preferred":[
        "\u010cokori"
    ],
    "name:und_x_variant":[
        "\u010cokori"
    ],
    "wof:name":"Cokori",
    "wof:placetype":"locality"
},
  "geometry": {"coordinates":[17.10304,44.78378],"type":"Point"}
}