{
  "type": "Feature",
  "properties": {
    "gn:admin1_code":"02",
    "gn:asciiname":"Cokori",
    "gn:country_code":"BA",
    "gn:dem":367,
    "gn:feature_class":"P",
    "gn:feature_code":"PPLL",
    "gn:name":"\u010cokori",
    "gn:population":0,
    "gn:timezone":"Europe/Sarajevo",
    "iso:country":"BA",
    "name:und_x_variant":[
        "\u010cokori"
    ],
    "wof:name":"Cokori",
    "wof:placetype":"locality"
},
  "geometry": {"coordinates":[17.10304,44.78378],"type":"Point"}
}