{
  "type": "Feature",
  "properties": {
    "gn:country":"BA",
    "gn:fcode":"PPLL",
    "gn:pop":4,
    "iso:country":"BA",
    "name:bos_x_preferred":[
        "Toj\u0161i\u0107i"
    ],
    "name:eng_x_preferred":[
        "Toj\u0161i\u0107i"
    ],
    "name:fra_x_preferred":[
        "Toj\u0161i\u0107i"
    ],
    "name:hrv_x_preferred":[
        "Toj\u0161i\u0107i"
    ],
    "name:nld_x_preferred":[
        "Toj\u0161i\u0107i"
    ],
    "name:swe_x_preferred":[
        "Toj\u0161i\u0107i"
    ],
    "qs:name":"Toj\u0161i\u0107i",
    "qs:photos_9r":0,
    "qs:photos_sr":0,
    "qs:pop_sr":"1",
    "wd:wordcount":57,
    "wof:name":"Toj\u0161i\u0107i",
    "wof:placetype":"locality",
    "wof:population":4
},
  "geometry": {"coordinates":[18.78686,44.48185],"type":"Point"}
}