{
  "type": "Feature",
  "properties": {
    "gn:admin1_code":"01",
    "gn:asciiname":"Ivankovica Dolac",
    "gn:country_code":"BA",
    "gn:dem":498,
    "gn:feature_class":"P",
    "gn:feature_code":"PPL",
    "gn:name":"Ivankovi\u0107a Dolac",
    "gn:population":0,
    "gn:timezone":"Europe/Sarajevo",
    "iso:country":"BA",
    "wof:name":"Ivankovica Dolac",
    "wof:placetype":"locality"
},
  "geometry": {"coordinates":[17.44507999999999,43.39083],"type":"Point"}
}