{
  "type": "Feature",
  "properties": {
    "gn:admin1_code":"01",
    "gn:asciiname":"Kovaci",
    "gn:country_code":"BA",
    "gn:dem":516,
    "gn:feature_class":"P",
    "gn:feature_code":"PPLL",
    "gn:name":"Kova\u010di",
    "gn:population":0,
    "gn:timezone":"Europe/Sarajevo",
    "iso:country":"BA",
    "name:bos_x_preferred":[
        "Kova\u010di"
    ],
    "name:ceb_x_preferred":[
        "Kova\u010di"
    ],
    "name:fra_x_preferred":[
        "Kova\u010di"
    ],
    "name:hrv_x_preferred":[
        "Kova\u010di"
    ],
    "name:swe_x_preferred":[
        "Kova\u010di"
    ],
    "name:und_x_variant":[
        "Kova\u010di"
    ],
    "wof:name":"Kovaci",
    "wof:placetype":"locality"
},
  "geometry": {"coordinates":[18.14505,43.8963],"type":"Point"}
}