{
  "type": "Feature",
  "properties": {
    "gn:admin1_code":"01",
    "gn:asciiname":"Lusca",
    "gn:country_code":"BA",
    "gn:dem":250,
    "gn:feature_class":"P",
    "gn:feature_code":"PPL",
    "gn:name":"Lu\u0161ca",
    "gn:population":0,
    "gn:timezone":"Europe/Sarajevo",
    "iso:country":"BA",
    "name:fra_x_preferred":[
        "Lusca"
    ],
    "name:ita_x_preferred":[
        "Lusca"
    ],
    "name:mkd_x_preferred":[
        "\u041b\u0443\u0441\u043a\u0430"
    ],
    "name:por_x_preferred":[
        "Lusca"
    ],
    "name:srp_x_preferred":[
        "\u041b\u0443\u0441\u043a\u0430"
    ],
    "wof:name":"Lusca",
    "wof:placetype":"locality"
},
  "geometry": {"coordinates":[17.82291,43.19181],"type":"Point"}
}