{
  "type": "Feature",
  "properties": {
    "gn:admin1_code":"01",
    "gn:asciiname":"Toholji",
    "gn:country_code":"BA",
    "gn:dem":557,
    "gn:feature_class":"P",
    "gn:feature_code":"PPL",
    "gn:name":"Toholji",
    "gn:population":0,
    "gn:timezone":"Europe/Sarajevo",
    "iso:country":"BA",
    "wof:name":"Toholji",
    "wof:placetype":"locality"
},
  "geometry": {"coordinates":[18.90306,43.66258],"type":"Point"}
}