{
  "type": "Feature",
  "properties": {
    "gn:admin1_code":"01",
    "gn:asciiname":"Rotilj",
    "gn:country_code":"BA",
    "gn:dem":551,
    "gn:feature_class":"P",
    "gn:feature_code":"PPL",
    "gn:name":"Rotilj",
    "gn:population":0,
    "gn:timezone":"Europe/Sarajevo",
    "iso:country":"BA",
    "wof:name":"Rotilj",
    "wof:placetype":"locality"
},
  "geometry": {"coordinates":[18.05216,43.93685],"type":"Point"}
}