{
  "type": "Feature",
  "properties": {
    "gn:admin1_code":"01",
    "gn:asciiname":"Tinja Donja",
    "gn:country_code":"BA",
    "gn:dem":285,
    "gn:feature_class":"P",
    "gn:feature_code":"PPL",
    "gn:name":"Tinja Donja",
    "gn:population":0,
    "gn:timezone":"Europe/Sarajevo",
    "iso:country":"BA",
    "name:bos_x_preferred":[
        "Tinja Donja"
    ],
    "name:ceb_x_preferred":[
        "Tinja Donja"
    ],
    "name:deu_x_preferred":[
        "Tinja Donja"
    ],
    "name:fra_x_preferred":[
        "Tinja Donja"
    ],
    "name:hrv_x_preferred":[
        "Tinja Donja"
    ],
    "name:swe_x_preferred":[
        "Tinja Donja"
    ],
    "name:und_x_variant":[
        "Pravoslavna Tinja"
    ],
    "wof:name":"Tinja Donja",
    "wof:placetype":"locality"
},
  "geometry": {"coordinates":[18.5605,44.63135],"type":"Point"}
}