{
  "type": "Feature",
  "properties": {
    "gn:admin1_code":"02",
    "gn:asciiname":"Varjace",
    "gn:country_code":"BA",
    "gn:dem":681,
    "gn:feature_class":"P",
    "gn:feature_code":"PPL",
    "gn:name":"Varja\u010de",
    "gn:population":0,
    "gn:timezone":"Europe/Sarajevo",
    "iso:country":"BA",
    "wof:name":"Varjace",
    "wof:placetype":"locality"
},
  "geometry": {"coordinates":[17.30169,44.57101],"type":"Point"}
}