{
  "type": "Feature",
  "properties": {
    "gn:admin1_code":"01",
    "gn:asciiname":"Bosnjakovo Brdo",
    "gn:country_code":"BA",
    "gn:dem":458,
    "gn:feature_class":"P",
    "gn:feature_code":"PPL",
    "gn:name":"Bo\u0161njakovo Brdo",
    "gn:population":0,
    "gn:timezone":"Europe/Sarajevo",
    "iso:country":"BA",
    "wof:name":"Bosnjakovo Brdo",
    "wof:placetype":"locality"
},
  "geometry": {"coordinates":[17.60284,43.39026],"type":"Point"}
}