{
  "type": "Feature",
  "properties": {
    "gn:admin1_code":"01",
    "gn:asciiname":"Barusici",
    "gn:country_code":"BA",
    "gn:dem":893,
    "gn:feature_class":"P",
    "gn:feature_code":"PPL",
    "gn:name":"Baru\u0161i\u0107i",
    "gn:population":0,
    "gn:timezone":"Europe/Sarajevo",
    "iso:country":"BA",
    "wof:name":"Barusici",
    "wof:placetype":"locality"
},
  "geometry": {"coordinates":[18.12667,43.81944],"type":"Point"}
}