{
  "type": "Feature",
  "properties": {
    "gn:admin1_code":"02",
    "gn:asciiname":"Capaja",
    "gn:country_code":"BA",
    "gn:dem":154,
    "gn:feature_class":"P",
    "gn:feature_code":"PPL",
    "gn:name":"\u010capaja",
    "gn:population":0,
    "gn:timezone":"Europe/Sarajevo",
    "iso:country":"BA",
    "wof:name":"Capaja",
    "wof:placetype":"locality"
},
  "geometry": {"coordinates":[16.63822,45.1824],"type":"Point"}
}