{
  "type": "Feature",
  "properties": {
    "gn:admin1_code":"02",
    "gn:asciiname":"Rajlovac",
    "gn:country_code":"BA",
    "gn:dem":191,
    "gn:feature_class":"P",
    "gn:feature_code":"PPL",
    "gn:name":"Rajlovac",
    "gn:population":0,
    "gn:timezone":"Europe/Sarajevo",
    "iso:country":"BA",
    "wof:name":"Rajlovac",
    "wof:placetype":"locality"
},
  "geometry": {"coordinates":[18.2642,45.01307],"type":"Point"}
}