{
  "type": "Feature",
  "properties": {
    "gn:admin1_code":"02",
    "gn:asciiname":"Kajkute",
    "gn:country_code":"BA",
    "gn:dem":232,
    "gn:feature_class":"P",
    "gn:feature_code":"PPL",
    "gn:name":"Kajkute",
    "gn:population":0,
    "gn:timezone":"Europe/Sarajevo",
    "iso:country":"BA",
    "wof:name":"Kajkute",
    "wof:placetype":"locality"
},
  "geometry": {"coordinates":[17.01181,44.84902],"type":"Point"}
}