{
  "type": "Feature",
  "properties": {
    "gn:admin1_code":"01",
    "gn:asciiname":"Vrhpolje",
    "gn:country_code":"BA",
    "gn:dem":618,
    "gn:feature_class":"P",
    "gn:feature_code":"PPL",
    "gn:name":"Vrhpolje",
    "gn:population":0,
    "gn:timezone":"Europe/Sarajevo",
    "iso:country":"BA",
    "name:bos_x_preferred":[
        "Vrhpolje"
    ],
    "name:ceb_x_preferred":[
        "Vrhpolje"
    ],
    "name:deu_x_preferred":[
        "Vrhpolje"
    ],
    "name:fra_x_preferred":[
        "Vrhpolje"
    ],
    "name:hrv_x_preferred":[
        "Vrhpolje"
    ],
    "name:ita_x_preferred":[
        "Vrhpolje"
    ],
    "name:nld_x_preferred":[
        "Vrhpolje"
    ],
    "name:slv_x_preferred":[
        "Vrhpolje"
    ],
    "wof:name":"Vrhpolje",
    "wof:placetype":"locality"
},
  "geometry": {"coordinates":[18.04488,44.23451],"type":"Point"}
}