{
  "type": "Feature",
  "properties": {
    "gn:admin1_code":"01",
    "gn:asciiname":"Poprzeni",
    "gn:country_code":"BA",
    "gn:dem":493,
    "gn:feature_class":"P",
    "gn:feature_code":"PPL",
    "gn:name":"Popr\u017eeni",
    "gn:population":0,
    "gn:timezone":"Europe/Sarajevo",
    "iso:country":"BA",
    "wof:name":"Poprzeni",
    "wof:placetype":"locality"
},
  "geometry": {"coordinates":[17.22522,44.3146],"type":"Point"}
}