{
  "type": "Feature",
  "properties": {
    "gn:admin1_code":"02",
    "gn:asciiname":"Rakici",
    "gn:country_code":"BA",
    "gn:dem":832,
    "gn:feature_class":"P",
    "gn:feature_code":"PPL",
    "gn:name":"Raki\u0107i",
    "gn:population":0,
    "gn:timezone":"Europe/Sarajevo",
    "iso:country":"BA",
    "wof:name":"Rakici",
    "wof:placetype":"locality"
},
  "geometry": {"coordinates":[19.41844,43.73743],"type":"Point"}
}