{
  "type": "Feature",
  "properties": {
    "gn:admin1_code":"01",
    "gn:asciiname":"Vukasovici",
    "gn:country_code":"BA",
    "gn:dem":1029,
    "gn:feature_class":"P",
    "gn:feature_code":"PPL",
    "gn:name":"Vukasovi\u0107i",
    "gn:population":0,
    "gn:timezone":"Europe/Sarajevo",
    "iso:country":"BA",
    "name:und_x_variant":[
        "Vukasovi\u0107i"
    ],
    "wof:name":"Vukasovici",
    "wof:placetype":"locality"
},
  "geometry": {"coordinates":[18.50576,44.01783],"type":"Point"}
}