{
  "type": "Feature",
  "properties": {
    "gn:admin1_code":"01",
    "gn:asciiname":"Hemici",
    "gn:country_code":"BA",
    "gn:dem":703,
    "gn:feature_class":"P",
    "gn:feature_code":"PPL",
    "gn:name":"Hemi\u0107i",
    "gn:population":0,
    "gn:timezone":"Europe/Sarajevo",
    "iso:country":"BA",
    "name:und_x_variant":[
        "Hemi\u0107i"
    ],
    "wof:name":"Hemici",
    "wof:placetype":"locality"
},
  "geometry": {"coordinates":[17.41427,44.22358],"type":"Point"}
}